{
  "type": "Feature",
  "properties": {
    "addr:full":"140 Hillsboro Pl Nashville TN 37215",
    "addr:housenumber":"140",
    "addr:postcode":"37215",
    "addr:street":"Hillsboro Pl",
    "iso:country":"US",
    "sg:address":"140 Hillsboro Pl",
    "sg:city":"Nashville",
    "sg:classifiers":[
        {
            "category":"Professional",
            "subcategory":"Lawyer & Legal Services",
            "type":"Services"
        }
    ],
    "sg:phone":"+1 615 279 0516",
    "sg:postcode":"37215",
    "sg:province":"TN",
    "sg:tags":[
        "research"
    ],
    "wof:name":"Lexis-Nexis",
    "wof:placetype":"venue"
},
  "geometry": {"coordinates":[-86.80641,36.120776],"type":"Point"}
}