{
  "type": "Feature",
  "properties": {
    "addr:full":"405 S Cumberland St Lebanon TN 37087",
    "addr:housenumber":"405",
    "addr:postcode":"37087",
    "addr:street":"S Cumberland St",
    "iso:country":"US",
    "sg:address":"405 S Cumberland St",
    "sg:city":"Lebanon",
    "sg:classifiers":[
        {
            "category":"Restaurant",
            "type":"Food & Drink"
        }
    ],
    "sg:menulink":"http://www.allmenus.com/tn/lebanon/105345-ryans/menu/",
    "sg:phone":"+1 615 453 6184",
    "sg:postcode":"37087",
    "sg:province":"TN",
    "sg:tags":[
        "american"
    ],
    "wof:name":"Ryan's",
    "wof:placetype":"venue"
},
  "geometry": {"coordinates":[-86.291657,36.199441],"type":"Point"}
}