{
  "type": "Feature",
  "properties": {
    "iso:country":"US",
    "sg:address":"15530 Birdsong Rd",
    "sg:city":"Holladay",
    "sg:classifiers":[
        {
            "category":"Real Estate",
            "subcategory":"Developer",
            "type":"Services"
        }
    ],
    "sg:phone":"+1 731 584 6948",
    "sg:postcode":"38341",
    "sg:province":"TN",
    "sg:tags":[
        "house",
        "construction"
    ],
    "wof:name":"Land Liquidation",
    "wof:placetype":"venue"
},
  "geometry": {"coordinates":[-87.97402,35.865924],"type":"Point"}
}