{
  "type": "Feature",
  "properties": {
    "addr:full":"1428 Lischey Ave Nashville TN 37207",
    "addr:housenumber":"1428",
    "addr:postcode":"37207",
    "addr:street":"Lischey Ave",
    "iso:country":"US",
    "sg:address":"1428 Lischey Ave",
    "sg:city":"Nashville",
    "sg:classifiers":[
        {
            "category":"Social Services",
            "subcategory":"Child Care",
            "type":"Services"
        }
    ],
    "sg:phone":"+1 615 226 5003",
    "sg:postcode":"37207",
    "sg:province":"TN",
    "wof:name":"Childrens Playhouse Childcare",
    "wof:placetype":"venue"
},
  "geometry": {"coordinates":[-86.762514,36.198472],"type":"Point"}
}