{
  "type": "Feature",
  "properties": {
    "iso:country":"US",
    "sg:address":"3864 Macon Rd",
    "sg:city":"Memphis",
    "sg:classifiers":[
        {
            "category":"Personal",
            "subcategory":"Beauty Salon",
            "type":"Services"
        }
    ],
    "sg:phone":"+1 901 323 2559",
    "sg:postcode":"38122",
    "sg:province":"TN",
    "sg:tags":[
        "shop"
    ],
    "wof:name":"Macon Road Beauty Salon",
    "wof:placetype":"venue"
},
  "geometry": {"coordinates":[-89.93203699999999,35.162438],"type":"Point"}
}