{
  "type": "Feature",
  "properties": {
    "iso:country":"US",
    "sg:address":"2580 Ottway Rd",
    "sg:city":"Greeneville",
    "sg:classifiers":[
        {
            "category":"Retail",
            "subcategory":"Repair Shop",
            "type":"Services"
        }
    ],
    "sg:phone":"+1 423 234 3051",
    "sg:postcode":"37745",
    "sg:province":"TN",
    "wof:name":"Fullens Repair Shop",
    "wof:placetype":"venue"
},
  "geometry": {"coordinates":[-82.86615500000001,36.26741],"type":"Point"}
}