{
  "type": "Feature",
  "properties": {
    "addr:full":"1946 Summertown Hwy Hohenwald TN 38462",
    "addr:housenumber":"1946",
    "addr:postcode":"38462",
    "addr:street":"Summertown Hwy",
    "iso:country":"US",
    "sg:address":"1946 Summertown Hwy",
    "sg:city":"Hohenwald",
    "sg:classifiers":[
        {
            "category":"Shopping",
            "subcategory":"Used Merchandise",
            "type":"Retail Goods"
        }
    ],
    "sg:phone":"+1 931 796 0662",
    "sg:postcode":"38462",
    "sg:province":"TN",
    "sg:tags":[
        "antique"
    ],
    "wof:name":"Millie's",
    "wof:placetype":"venue"
},
  "geometry": {"coordinates":[-87.48577,35.523908],"type":"Point"}
}