{
  "type": "Feature",
  "properties": {
    "iso:country":"US",
    "sg:address":"269 Bonita Pkwy",
    "sg:city":"Hendersonville",
    "sg:classifiers":[
        {
            "category":"Recreation",
            "type":"Entertainment"
        }
    ],
    "sg:phone":"+1 615 824 9997",
    "sg:postcode":"37075",
    "sg:province":"TN",
    "sg:tags":[
        "pool",
        "swimming"
    ],
    "wof:name":"Maples Pool",
    "wof:placetype":"venue"
},
  "geometry": {"coordinates":[-86.583246,36.302291],"type":"Point"}
}