{
  "type": "Feature",
  "properties": {
    "iso:country":"US",
    "sg:address":"319 Salvation Rd",
    "sg:city":"Kingsport",
    "sg:classifiers":[
        {
            "category":"Organizations",
            "subcategory":"Religious Organization",
            "type":"Services"
        }
    ],
    "sg:phone":"+1 423 246 2581",
    "sg:postcode":"37660",
    "sg:province":"TN",
    "sg:tags":[
        "church"
    ],
    "wof:name":"Way Of Life Baptist Church",
    "wof:placetype":"venue"
},
  "geometry": {"coordinates":[-82.543612,36.581699],"type":"Point"}
}