{
  "type": "Feature",
  "properties": {
    "iso:country":"US",
    "sg:address":"19 Gregson Pl",
    "sg:city":"Waverly",
    "sg:classifiers":[
        {
            "category":"Professional",
            "subcategory":"Engineering",
            "type":"Services"
        }
    ],
    "sg:phone":"+1 931 296 2646",
    "sg:postcode":"37185",
    "sg:province":"TN",
    "wof:name":"Con E Tech",
    "wof:placetype":"venue"
},
  "geometry": {"coordinates":[-87.724892,36.086995],"type":"Point"}
}