{
  "type": "Feature",
  "properties": {
    "iso:country":"US",
    "sg:address":"918 Buchanan St",
    "sg:city":"Nashville",
    "sg:classifiers":[
        {
            "category":"Government",
            "subcategory":"Post Office",
            "type":"Public Place"
        }
    ],
    "sg:phone":"+1 615 254 4215",
    "sg:postcode":"37208",
    "sg:province":"TN",
    "wof:name":"North Finance Station",
    "wof:placetype":"venue"
},
  "geometry": {"coordinates":[-86.802915,36.180534],"type":"Point"}
}