{
  "type": "Feature",
  "properties": {
    "iso:country":"US",
    "sg:address":"520 Amalie Ct",
    "sg:city":"Nashville",
    "sg:classifiers":[
        {
            "category":"Professional",
            "subcategory":"Management & Consulting",
            "type":"Services"
        }
    ],
    "sg:phone":"+1 615 331 1984",
    "sg:postcode":"37211",
    "sg:province":"TN",
    "sg:tags":[
        "consultant",
        "training"
    ],
    "wof:name":"Pamela White",
    "wof:placetype":"venue"
},
  "geometry": {"coordinates":[-86.722854,36.051519],"type":"Point"}
}