{
  "type": "Feature",
  "properties": {
    "iso:country":"US",
    "sg:address":"950 E Brooks Rd",
    "sg:city":"Memphis",
    "sg:classifiers":[
        {
            "category":"Autos & Motor Vehicles",
            "subcategory":"Auto Supplies",
            "type":"Retail Goods"
        }
    ],
    "sg:phone":"+1 901 332 3899",
    "sg:postcode":"38109",
    "sg:province":"TN",
    "sg:tags":[
        "automotive",
        "parts"
    ],
    "wof:name":"Four Wheel Parts Wholesalers",
    "wof:placetype":"venue"
},
  "geometry": {"coordinates":[-90.031355,35.06179],"type":"Point"}
}