{
  "type": "Feature",
  "properties": {
    "iso:country":"US",
    "sg:address":"3301 Rock Springs Rd",
    "sg:city":"Smyrna",
    "sg:classifiers":[
        {
            "category":"Education",
            "subcategory":"School",
            "type":"Public Place"
        }
    ],
    "sg:phone":"+1 615 904 3825",
    "sg:postcode":"37167",
    "sg:province":"TN",
    "wof:name":"Rock Springs Middle School",
    "wof:placetype":"venue"
},
  "geometry": {"coordinates":[-86.57480200000001,35.961582],"type":"Point"}
}