{
  "type": "Feature",
  "properties": {
    "addr:full":"101 Midway Ln Oak Ridge TN 37830",
    "addr:housenumber":"101",
    "addr:postcode":"37830",
    "addr:street":"Midway Ln",
    "iso:country":"US",
    "sg:address":"101 Midway Ln",
    "sg:city":"Oak Ridge",
    "sg:classifiers":[
        {
            "category":"Government",
            "subcategory":"Office",
            "type":"Public Place"
        }
    ],
    "sg:phone":"+1 865 482 7122",
    "sg:postcode":"37830",
    "sg:province":"TN",
    "wof:name":"Federal Bureau Investigations",
    "wof:placetype":"venue"
},
  "geometry": {"coordinates":[-84.24072,36.003145],"type":"Point"}
}