{
  "type": "Feature",
  "properties": {
    "addr:full":"810 Kirkwood Ave Nashville TN 37204",
    "addr:housenumber":"810",
    "addr:postcode":"37204",
    "addr:street":"Kirkwood Ave",
    "iso:country":"US",
    "sg:address":"810 Kirkwood Ave",
    "sg:city":"Nashville",
    "sg:classifiers":[
        {
            "category":"Shopping",
            "subcategory":"Used Merchandise",
            "type":"Retail Goods"
        }
    ],
    "sg:phone":"+1 615 414 5646",
    "sg:postcode":"37204",
    "sg:province":"TN",
    "sg:tags":[
        "shop",
        "consignment"
    ],
    "wof:name":"My Favorite Thing",
    "wof:placetype":"venue"
},
  "geometry": {"coordinates":[-86.77813500000001,36.121078],"type":"Point"}
}