{
  "type": "Feature",
  "properties": {
    "iso:country":"US",
    "sg:address":"279 Exchange Ave",
    "sg:city":"Memphis",
    "sg:classifiers":[
        {
            "category":"Professional",
            "subcategory":"Business Services",
            "type":"Services"
        }
    ],
    "sg:phone":"+1 901 528 1776",
    "sg:postcode":"38105",
    "sg:province":"TN",
    "sg:website":"www.memphisbonding.com",
    "wof:name":"Memphis Bonding Co",
    "wof:placetype":"venue"
},
  "geometry": {"coordinates":[-90.043571,35.149244],"type":"Point"}
}