{
  "type": "Feature",
  "properties": {
    "iso:country":"US",
    "sg:address":"2608 McCammon Rd",
    "sg:city":"Knoxville",
    "sg:classifiers":[
        {
            "category":"Food & Beverages",
            "subcategory":"Specialty",
            "type":"Retail Goods"
        }
    ],
    "sg:phone":"+1 865 577 3387",
    "sg:postcode":"37920",
    "sg:province":"TN",
    "wof:name":"Better Living Enterprises",
    "wof:placetype":"venue"
},
  "geometry": {"coordinates":[-83.884619,35.858219],"type":"Point"}
}