{
  "type": "Feature",
  "properties": {
    "addr:full":"2915 Southaire Dr Memphis TN 38118",
    "addr:housenumber":"2915",
    "addr:postcode":"38118",
    "addr:street":"Southaire Dr",
    "iso:country":"US",
    "sg:address":"2915 Southaire Dr",
    "sg:city":"Memphis",
    "sg:classifiers":[
        {
            "category":"Airline",
            "type":"Transportation"
        }
    ],
    "sg:phone":"+1 901 369 3303",
    "sg:postcode":"38118",
    "sg:province":"TN",
    "sg:tags":[
        "air",
        "carrier",
        "ground"
    ],
    "wof:name":"Fedex",
    "wof:placetype":"venue"
},
  "geometry": {"coordinates":[-89.96880299999999,35.06646],"type":"Point"}
}