{
  "type": "Feature",
  "properties": {
    "iso:country":"US",
    "sg:address":"3541 Neal Dr",
    "sg:city":"Knoxville",
    "sg:classifiers":[
        {
            "category":"Wholesale",
            "subcategory":"Durable Goods & Equipment",
            "type":"Manufacturing & Wholesale Goods"
        }
    ],
    "sg:phone":"+1 865 922 9916",
    "sg:postcode":"37918",
    "sg:province":"TN",
    "sg:tags":[
        "importer"
    ],
    "wof:name":"Avanti Savoia Imports LLC",
    "wof:placetype":"venue"
},
  "geometry": {"coordinates":[-83.927572,36.071504],"type":"Point"}
}