{
  "type": "Feature",
  "properties": {
    "iso:country":"US",
    "sg:address":"677 Phelan Ave",
    "sg:city":"Memphis",
    "sg:classifiers":[
        {
            "category":"Wholesale",
            "subcategory":"Machinery & Supplies",
            "type":"Manufacturing & Wholesale Goods"
        },
        {
            "category":"Wholesale",
            "subcategory":"Non-durable Goods",
            "type":"Manufacturing & Wholesale Goods"
        }
    ],
    "sg:phone":"+1 901 774 0400",
    "sg:postcode":"38126",
    "sg:province":"TN",
    "sg:tags":[
        "rubber",
        "leather",
        "shoe",
        "findings"
    ],
    "sg:website":"www.southernleathercompany.com",
    "wof:name":"Southern Leather Company La",
    "wof:placetype":"venue"
},
  "geometry": {"coordinates":[-90.042193,35.127306],"type":"Point"}
}