{
  "type": "Feature",
  "properties": {
    "iso:country":"US",
    "sg:address":"13833 Lillard Rd",
    "sg:city":"Soddy Daisy",
    "sg:classifiers":[
        {
            "category":"Professional",
            "type":"Services"
        }
    ],
    "sg:phone":"+1 423 332 1066",
    "sg:postcode":"37379",
    "sg:province":"TN",
    "wof:name":"ABC Elec Service",
    "wof:placetype":"venue"
},
  "geometry": {"coordinates":[-85.08739,35.326068],"type":"Point"}
}