{
  "type": "Feature",
  "properties": {
    "iso:country":"US",
    "sg:address":"1925 State Hwy 18",
    "sg:city":"Medon",
    "sg:classifiers":[
        {
            "category":"Organizations",
            "subcategory":"Religious Organization",
            "type":"Services"
        }
    ],
    "sg:phone":"+1 731 424 9019",
    "sg:postcode":"38356",
    "sg:province":"TN",
    "sg:tags":[
        "church"
    ],
    "wof:name":"Faith Tabernacle New Testment",
    "wof:placetype":"venue"
},
  "geometry": {"coordinates":[-88.86474800000001,35.465378],"type":"Point"}
}