{
  "type": "Feature",
  "properties": {
    "iso:country":"US",
    "sg:address":"225 Co Hwy 385",
    "sg:city":"Franklin",
    "sg:classifiers":[
        {
            "category":"Professional",
            "subcategory":"Accounting & Tax Preparation",
            "type":"Services"
        }
    ],
    "sg:phone":"+1 615 591 1381",
    "sg:postcode":"37055",
    "sg:province":"TN",
    "wof:name":"CPA Services Inc",
    "wof:placetype":"venue"
},
  "geometry": {"coordinates":[-87.401601,36.087188],"type":"Point"}
}