{
  "type": "Feature",
  "properties": {
    "iso:country":"US",
    "sg:address":"1502 W College St",
    "sg:city":"Murfreesboro",
    "sg:classifiers":[
        {
            "category":"Retail",
            "subcategory":"Auto Repair",
            "type":"Services"
        }
    ],
    "sg:phone":"+1 615 895 9392",
    "sg:postcode":"37129",
    "sg:province":"TN",
    "sg:tags":[
        "general"
    ],
    "wof:name":"Radfords",
    "wof:placetype":"venue"
},
  "geometry": {"coordinates":[-86.41247199999999,35.862171],"type":"Point"}
}