{
  "type": "Feature",
  "properties": {
    "iso:country":"US",
    "sg:address":"131 Ridgeview Trl",
    "sg:city":"Crossville",
    "sg:classifiers":[
        {
            "category":"Wholesale",
            "subcategory":"Durable Goods & Equipment",
            "type":"Manufacturing & Wholesale Goods"
        }
    ],
    "sg:phone":"+1 931 484 0174",
    "sg:postcode":"38571",
    "sg:province":"TN",
    "sg:tags":[
        "representative",
        "manufacturer"
    ],
    "wof:name":"Nolan Industries",
    "wof:placetype":"venue"
},
  "geometry": {"coordinates":[-85.140174,36.007916],"type":"Point"}
}