{
  "type": "Feature",
  "properties": {
    "iso:country":"US",
    "sg:address":"417 Bohannon Ave",
    "sg:city":"Greeneville",
    "sg:classifiers":[
        {
            "category":"Freight",
            "type":"Transportation"
        }
    ],
    "sg:phone":"+1 423 638 1187",
    "sg:postcode":"37745",
    "sg:province":"TN",
    "sg:tags":[
        "warehouse",
        "self",
        "storage"
    ],
    "wof:name":"Bewley Warehouses",
    "wof:placetype":"venue"
},
  "geometry": {"coordinates":[-82.816266,36.175526],"type":"Point"}
}