{
  "type": "Feature",
  "properties": {
    "addr:full":"11175 Fourwinds Dr Eads TN 38028",
    "addr:housenumber":"11175",
    "addr:postcode":"38028",
    "addr:street":"Fourwinds Dr",
    "iso:country":"US",
    "sg:address":"11175 Fourwinds Dr",
    "sg:city":"Eads",
    "sg:classifiers":[
        {
            "category":"Personal",
            "type":"Services"
        },
        {
            "category":"Professional",
            "subcategory":"Management & Consulting",
            "type":"Services"
        }
    ],
    "sg:phone":"+1 901 867 9560",
    "sg:postcode":"38028",
    "sg:province":"TN",
    "sg:tags":[
        "party",
        "planning"
    ],
    "wof:name":"Pop Goes The Party LLC",
    "wof:placetype":"venue"
},
  "geometry": {"coordinates":[-89.688635,35.190404],"type":"Point"}
}