{
  "type": "Feature",
  "properties": {
    "iso:country":"US",
    "sg:address":"298 Alp Green Rd",
    "sg:city":"Dayton",
    "sg:classifiers":[
        {
            "category":"Real Estate",
            "subcategory":"Real Estate Operator",
            "type":"Services"
        }
    ],
    "sg:phone":"+1 423 775 2524",
    "sg:postcode":"37321",
    "sg:province":"TN",
    "sg:tags":[
        "property",
        "lessor"
    ],
    "wof:name":"Green Rental Properties",
    "wof:placetype":"venue"
},
  "geometry": {"coordinates":[-85.04963600000001,35.46599],"type":"Point"}
}