{
  "type": "Feature",
  "properties": {
    "iso:country":"US",
    "sg:address":"5 Fernlawn St",
    "sg:city":"Jackson",
    "sg:classifiers":[
        {
            "category":"Building & Trades",
            "subcategory":"Construction",
            "type":"Services"
        }
    ],
    "sg:phone":"+1 731 431 2380",
    "sg:postcode":"38301",
    "sg:province":"TN",
    "sg:tags":[
        "roofing",
        "contractor"
    ],
    "wof:name":"Marco's Roofing",
    "wof:placetype":"venue"
},
  "geometry": {"coordinates":[-88.820803,35.639161],"type":"Point"}
}