{
  "type": "Feature",
  "properties": {
    "addr:full":"225 E Market St Kingsport TN 37660",
    "addr:housenumber":"225",
    "addr:postcode":"37660",
    "addr:street":"E Market St",
    "iso:country":"US",
    "sg:address":"225 E Market St",
    "sg:city":"Kingsport",
    "sg:classifiers":[
        {
            "category":"Wholesale",
            "subcategory":"Groceries",
            "type":"Manufacturing & Wholesale Goods"
        }
    ],
    "sg:phone":"+1 423 245 0771",
    "sg:postcode":"37660",
    "sg:province":"TN",
    "sg:tags":[
        "confectionery",
        "candy"
    ],
    "wof:name":"Gazebo Party Shop",
    "wof:placetype":"venue"
},
  "geometry": {"coordinates":[-82.559645,36.545668],"type":"Point"}
}