{
  "type": "Feature",
  "properties": {
    "iso:country":"US",
    "sg:address":"9306 Hidden Green Ln",
    "sg:city":"Knoxville",
    "sg:classifiers":[
        {
            "category":"Professional",
            "subcategory":"Management & Consulting",
            "type":"Services"
        }
    ],
    "sg:phone":"+1 865 531 7080",
    "sg:postcode":"37922",
    "sg:province":"TN",
    "wof:name":"Pegasus Sports Marketing",
    "wof:placetype":"venue"
},
  "geometry": {"coordinates":[-84.084844,35.892291],"type":"Point"}
}