{
  "type": "Feature",
  "properties": {
    "iso:country":"US",
    "sg:address":"5250 Virginia Way",
    "sg:city":"Brentwood",
    "sg:classifiers":[
        {
            "category":"Wholesale",
            "subcategory":"Durable Goods & Equipment",
            "type":"Manufacturing & Wholesale Goods"
        }
    ],
    "sg:phone":"+1 615 269 8005",
    "sg:postcode":"37027",
    "sg:province":"TN",
    "wof:name":"Total Benefits Communication",
    "wof:placetype":"venue"
},
  "geometry": {"coordinates":[-86.808081,36.032446],"type":"Point"}
}