{
  "type": "Feature",
  "properties": {
    "addr:full":"117 W Smith St Gallatin TN 37066",
    "addr:housenumber":"117",
    "addr:postcode":"37066",
    "addr:street":"W Smith St",
    "iso:country":"US",
    "sg:address":"117 W Smith St",
    "sg:city":"Gallatin",
    "sg:classifiers":[
        {
            "category":"Government",
            "subcategory":"Office",
            "type":"Public Place"
        }
    ],
    "sg:phone":"+1 615 452 4310",
    "sg:postcode":"37066",
    "sg:province":"TN",
    "wof:name":"Sumner County General Sessions",
    "wof:placetype":"venue"
},
  "geometry": {"coordinates":[-86.446744,36.386993],"type":"Point"}
}