{
  "type": "Feature",
  "properties": {
    "iso:country":"US",
    "sg:address":"1879 Franklin Pike",
    "sg:city":"Lewisburg",
    "sg:classifiers":[
        {
            "category":"Airline",
            "type":"Transportation"
        }
    ],
    "sg:phone":"+1 931 359 2731",
    "sg:postcode":"37091",
    "sg:province":"TN",
    "sg:tags":[
        "nonscheduled",
        "air"
    ],
    "sg:website":"www.lifeteam.net",
    "wof:name":"Air Evac Inc",
    "wof:placetype":"venue"
},
  "geometry": {"coordinates":[-86.806558,35.497319],"type":"Point"}
}