{
  "type": "Feature",
  "properties": {
    "addr:full":"104 Regency Dr Rogersville TN 37857",
    "addr:housenumber":"104",
    "addr:postcode":"37857",
    "addr:street":"Regency Dr",
    "iso:country":"US",
    "sg:address":"104 Regency Dr",
    "sg:city":"Rogersville",
    "sg:classifiers":[
        {
            "category":"Organizations",
            "subcategory":"Religious Organization",
            "type":"Services"
        }
    ],
    "sg:phone":"+1 423 345 0007",
    "sg:postcode":"37857",
    "sg:province":"TN",
    "sg:tags":[
        "church"
    ],
    "wof:name":"Kingdom Hall Of Jehovah's",
    "wof:placetype":"venue"
},
  "geometry": {"coordinates":[-82.891159,36.462696],"type":"Point"}
}