{
  "type": "Feature",
  "properties": {
    "iso:country":"US",
    "sg:address":"8781 Chaffee Rd",
    "sg:city":"Arlington",
    "sg:classifiers":[
        {
            "category":"Wholesale",
            "subcategory":"Machinery & Supplies",
            "type":"Manufacturing & Wholesale Goods"
        }
    ],
    "sg:phone":"+1 901 387 2026",
    "sg:postcode":"38002",
    "sg:province":"TN",
    "sg:tags":[
        "equipment",
        "conveyor",
        "conveying"
    ],
    "wof:name":"Lecorp",
    "wof:placetype":"venue"
},
  "geometry": {"coordinates":[-89.769454,35.267175],"type":"Point"}
}