{
  "type": "Feature",
  "properties": {
    "iso:country":"US",
    "sg:address":"5 Quail Ridge",
    "sg:city":"Trenton",
    "sg:classifiers":[
        {
            "category":"Wholesale",
            "subcategory":"Apparel",
            "type":"Manufacturing & Wholesale Goods"
        }
    ],
    "sg:phone":"+1 731 855 4523",
    "sg:postcode":"38382",
    "sg:province":"TN",
    "sg:tags":[
        "athletic",
        "child",
        "clothing",
        "mfg"
    ],
    "wof:name":"Nick Nack Pattywack",
    "wof:placetype":"venue"
},
  "geometry": {"coordinates":[-88.931169,35.999035],"type":"Point"}
}