{
  "type": "Feature",
  "properties": {
    "addr:full":"601 S Pkwy E Memphis TN 38106",
    "addr:housenumber":"601",
    "addr:postcode":"38106",
    "addr:street":"S Pkwy E",
    "iso:country":"US",
    "sg:address":"601 S Pkwy E",
    "sg:city":"Memphis",
    "sg:classifiers":[
        {
            "category":"Restaurant",
            "type":"Food & Drink"
        }
    ],
    "sg:phone":"+1 901 942 4888",
    "sg:postcode":"38106",
    "sg:province":"TN",
    "wof:name":"Ellen's Soul Food Restaurant",
    "wof:placetype":"venue"
},
  "geometry": {"coordinates":[-90.04194099999999,35.107251],"type":"Point"}
}