{
  "type": "Feature",
  "properties": {
    "iso:country":"US",
    "sg:address":"9724 Kingston Pike",
    "sg:city":"Knoxville",
    "sg:classifiers":[
        {
            "category":"Professional",
            "subcategory":"Lawyer & Legal Services",
            "type":"Services"
        }
    ],
    "sg:phone":"+1 865 357 9800",
    "sg:postcode":"37922",
    "sg:province":"TN",
    "sg:tags":[
        "attorney",
        "law",
        "bankruptcy"
    ],
    "sg:website":"http://www.menefeebrown.com",
    "wof:name":"Menefee & Brown LLP",
    "wof:placetype":"venue"
},
  "geometry": {"coordinates":[-84.110185,35.90595],"type":"Point"}
}