{
  "type": "Feature",
  "properties": {
    "addr:full":"2800 Whitten Rd Memphis TN 38133",
    "addr:postcode":"2800;38133",
    "addr:street":"Whitten Rd",
    "iso:country":"US",
    "sg:address":"2800 Whitten Rd",
    "sg:city":"Memphis",
    "sg:classifiers":[
        {
            "category":"Organizations",
            "subcategory":"Religious Organization",
            "type":"Services"
        }
    ],
    "sg:phone":"+1 901 328 9515",
    "sg:postcode":"38133",
    "sg:province":"TN",
    "sg:tags":[
        "church"
    ],
    "wof:name":"Christ Evangelical Church",
    "wof:placetype":"venue"
},
  "geometry": {"coordinates":[-89.83649800000001,35.199595],"type":"Point"}
}