{
  "type": "Feature",
  "properties": {
    "addr:full":"2505 Nolensville Pike Nashville TN 37211",
    "addr:housenumber":"2505",
    "addr:postcode":"37211",
    "addr:street":"Nolensville Pike",
    "iso:country":"US",
    "sg:address":"2505 Nolensville Pike",
    "sg:city":"Nashville",
    "sg:classifiers":[
        {
            "category":"Professional",
            "subcategory":"Lawyer & Legal Services",
            "type":"Services"
        }
    ],
    "sg:phone":"+1 615 256 7707",
    "sg:postcode":"37211",
    "sg:province":"TN",
    "sg:tags":[
        "attorney"
    ],
    "wof:name":"Fred Ramos",
    "wof:placetype":"venue"
},
  "geometry": {"coordinates":[-86.74890499999999,36.118065],"type":"Point"}
}