{
  "type": "Feature",
  "properties": {
    "addr:full":"52 Alton Hill Rd Lafayette TN 37083",
    "addr:housenumber":"52",
    "addr:postcode":"37083",
    "addr:street":"Alton Hill Rd",
    "iso:country":"US",
    "sg:address":"52 Alton Hill Rd",
    "sg:city":"Lafayette",
    "sg:classifiers":[
        {
            "category":"Organizations",
            "subcategory":"Religious Organization",
            "type":"Services"
        }
    ],
    "sg:phone":"+1 615 666 7351",
    "sg:postcode":"37083",
    "sg:province":"TN",
    "sg:tags":[
        "church"
    ],
    "wof:name":"Oasis Church",
    "wof:placetype":"venue"
},
  "geometry": {"coordinates":[-86.104422,36.528972],"type":"Point"}
}