{
  "type": "Feature",
  "properties": {
    "iso:country":"US",
    "sg:address":"1023 Park St",
    "sg:city":"Westmoreland",
    "sg:classifiers":[
        {
            "category":"Shopping",
            "subcategory":"Florist",
            "type":"Retail Goods"
        }
    ],
    "sg:phone":"+1 615 644 2203",
    "sg:postcode":"37186",
    "sg:province":"TN",
    "wof:name":"Westmoreland Florists",
    "wof:placetype":"venue"
},
  "geometry": {"coordinates":[-86.247619,36.561632],"type":"Point"}
}