{
  "type": "Feature",
  "properties": {
    "addr:full":"1226 Mattox Town Rd Lawrenceburg TN 38464",
    "addr:housenumber":"1226",
    "addr:postcode":"38464",
    "addr:street":"Mattox Town Rd",
    "iso:country":"US",
    "sg:address":"1226 Mattox Town Rd",
    "sg:city":"Lawrenceburg",
    "sg:classifiers":[
        {
            "category":"Autos & Motor Vehicles",
            "subcategory":"Automobile Sales",
            "type":"Retail Goods"
        },
        {
            "category":"Wholesale",
            "subcategory":"Auto Parts",
            "type":"Manufacturing & Wholesale Goods"
        }
    ],
    "sg:phone":"+1 931 829 3126",
    "sg:postcode":"38464",
    "sg:province":"TN",
    "sg:tags":[
        "car",
        "used",
        "dealer"
    ],
    "wof:name":"Clarks Auto Garage and Sales",
    "wof:placetype":"venue"
},
  "geometry": {"coordinates":[-87.28278899999999,35.296337],"type":"Point"}
}