{
  "type": "Feature",
  "properties": {
    "iso:country":"US",
    "sg:address":"1800 Fire Tower Rd",
    "sg:city":"Martin",
    "sg:classifiers":[
        {
            "category":"Banks & Credit Unions",
            "subcategory":"Bank",
            "type":"Services"
        }
    ],
    "sg:phone":"+1 731 364 5958",
    "sg:postcode":"38237",
    "sg:province":"TN",
    "wof:name":"New South Federal Bank",
    "wof:placetype":"venue"
},
  "geometry": {"coordinates":[-88.757842,36.349599],"type":"Point"}
}