{
  "type": "Feature",
  "properties": {
    "iso:country":"US",
    "sg:address":"221 Druid Hills Dr",
    "sg:city":"Dickson",
    "sg:classifiers":[
        {
            "category":"Freight",
            "type":"Transportation"
        }
    ],
    "sg:phone":"+1 615 446 7109",
    "sg:postcode":"37055",
    "sg:province":"TN",
    "sg:tags":[
        "trucking"
    ],
    "wof:name":"Gill Trucking Inc",
    "wof:placetype":"venue"
},
  "geometry": {"coordinates":[-87.39342600000001,36.101038],"type":"Point"}
}