{
  "type": "Feature",
  "properties": {
    "iso:country":"US",
    "sg:address":"303 Burning Tree Dr",
    "sg:city":"Hermitage",
    "sg:classifiers":[
        {
            "category":"Building & Trades",
            "subcategory":"Cleaning & Sanitation",
            "type":"Services"
        }
    ],
    "sg:phone":"+1 615 415 5004",
    "sg:postcode":"37076",
    "sg:province":"TN",
    "sg:tags":[
        "maintenance"
    ],
    "wof:name":"Lawrence Mary Janitorial Svc",
    "wof:placetype":"venue"
},
  "geometry": {"coordinates":[-86.599146,36.174024],"type":"Point"}
}