{
  "type": "Feature",
  "properties": {
    "iso:country":"US",
    "sg:address":"2826 Dogwood Pl",
    "sg:city":"Nashville",
    "sg:classifiers":[
        {
            "category":"Farming",
            "subcategory":"Fish & Marine Products",
            "type":"Manufacturing & Wholesale Goods"
        }
    ],
    "sg:phone":"+1 615 299 9938",
    "sg:postcode":"37204",
    "sg:province":"TN",
    "sg:tags":[
        "wildlife",
        "conservation"
    ],
    "wof:name":"Walden's Puddle Wildlife Rehab",
    "wof:placetype":"venue"
},
  "geometry": {"coordinates":[-86.764629,36.113692],"type":"Point"}
}