{
  "type": "Feature",
  "properties": {
    "iso:country":"US",
    "sg:address":"8060 Dayton Blvd",
    "sg:city":"Hixson",
    "sg:classifiers":[
        {
            "category":"Wholesale",
            "subcategory":"Metals & Minerals",
            "type":"Manufacturing & Wholesale Goods"
        }
    ],
    "sg:phone":"+1 423 842 7000",
    "sg:postcode":"37343",
    "sg:province":"TN",
    "sg:tags":[
        "steel",
        "building",
        "component",
        "structural"
    ],
    "wof:name":"Mc Gill Supply Unlimited Inc",
    "wof:placetype":"venue"
},
  "geometry": {"coordinates":[-85.23248700000001,35.209017],"type":"Point"}
}