{
  "type": "Feature",
  "properties": {
    "iso:country":"US",
    "sg:address":"321 Becton William Rd",
    "sg:city":"Ripley",
    "sg:phone":"+1 731 635 4081",
    "sg:postcode":"38063",
    "sg:province":"TN",
    "sg:tags":[
        "farm",
        "corn",
        "soybean",
        "cotton"
    ],
    "wof:name":"Olds Larry Farm",
    "wof:placetype":"venue"
},
  "geometry": {"coordinates":[-89.635206,35.76523],"type":"Point"}
}