{
  "type": "Feature",
  "properties": {
    "iso:country":"US",
    "sg:address":"17 E Circle Dr",
    "sg:city":"Monteagle",
    "sg:classifiers":[
        {
            "category":"Manufacturing",
            "subcategory":"Retail Goods",
            "type":"Manufacturing & Wholesale Goods"
        }
    ],
    "sg:phone":"+1 931 924 2422",
    "sg:postcode":"37356",
    "sg:province":"TN",
    "sg:tags":[
        "assembly",
        "fabricating"
    ],
    "wof:name":"Monteagle Assembly Managers Rs",
    "wof:placetype":"venue"
},
  "geometry": {"coordinates":[-85.83767,35.24162],"type":"Point"}
}