{
  "type": "Feature",
  "properties": {
    "addr:full":"2830 N Germantown Pkwy Memphis TN 38133",
    "addr:housenumber":"2830",
    "addr:postcode":"38133",
    "addr:street":"N Germantown Pkwy",
    "iso:country":"US",
    "sg:address":"2830 N Germantown Pkwy",
    "sg:city":"Memphis",
    "sg:classifiers":[
        {
            "category":"Restaurant",
            "type":"Food & Drink"
        }
    ],
    "sg:menulink":"http://www.allmenus.com/tn/memphis/29089-bahama-breeze/menu/",
    "sg:phone":"+1 901 385 8744",
    "sg:postcode":"38133",
    "sg:province":"TN",
    "sg:tags":[
        "jamaican"
    ],
    "wof:name":"Bahama Breeze",
    "wof:placetype":"venue"
},
  "geometry": {"coordinates":[-89.79200899999999,35.202327],"type":"Point"}
}