{
  "type": "Feature",
  "properties": {
    "iso:country":"US",
    "sg:address":"255 Dover Rd",
    "sg:city":"Clarksville",
    "sg:classifiers":[
        {
            "category":"Health Services",
            "subcategory":"Chiropractor",
            "type":"Services"
        }
    ],
    "sg:phone":"+1 931 906 2055",
    "sg:postcode":"37042",
    "sg:province":"TN",
    "wof:name":"Crow Chiropractic",
    "wof:placetype":"venue"
},
  "geometry": {"coordinates":[-87.400617,36.550591],"type":"Point"}
}