{
  "type": "Feature",
  "properties": {
    "iso:country":"US",
    "sg:address":"756 E Brookhaven Cir",
    "sg:city":"Memphis",
    "sg:classifiers":[
        {
            "category":"Professional",
            "subcategory":"Lawyer & Legal Services",
            "type":"Services"
        }
    ],
    "sg:phone":"+1 901 683 0025",
    "sg:postcode":"38117",
    "sg:province":"TN",
    "wof:name":"Parker James O Attorney At Law",
    "wof:placetype":"venue"
},
  "geometry": {"coordinates":[-89.889489,35.111739],"type":"Point"}
}