{
  "type": "Feature",
  "properties": {
    "iso:country":"US",
    "sg:address":"1005 N Tennessee Blvd",
    "sg:city":"Murfreesboro",
    "sg:classifiers":[
        {
            "category":"Health Services",
            "subcategory":"Doctor",
            "type":"Services"
        }
    ],
    "sg:phone":"+1 615 893 1615",
    "sg:postcode":"37130",
    "sg:province":"TN",
    "sg:tags":[
        "medical"
    ],
    "wof:name":"Stephen G Odom MD",
    "wof:placetype":"venue"
},
  "geometry": {"coordinates":[-86.37026400000001,35.856054],"type":"Point"}
}