{
  "type": "Feature",
  "properties": {
    "addr:full":"1012 Kevin Rd Knoxville TN 37923",
    "addr:housenumber":"1012",
    "addr:postcode":"37923",
    "addr:street":"Kevin Rd",
    "iso:country":"US",
    "sg:address":"1012 Kevin Rd",
    "sg:city":"Knoxville",
    "sg:classifiers":[
        {
            "category":"Professional",
            "subcategory":"Business Services",
            "type":"Services"
        }
    ],
    "sg:phone":"+1 865 690 5067",
    "sg:postcode":"37923",
    "sg:province":"TN",
    "wof:name":"Stb Designs",
    "wof:placetype":"venue"
},
  "geometry": {"coordinates":[-84.070595,35.938913],"type":"Point"}
}