{
  "type": "Feature",
  "properties": {
    "iso:country":"US",
    "sg:address":"133 Cherry Ln",
    "sg:city":"Murfreesboro",
    "sg:classifiers":[
        {
            "category":"Professional",
            "subcategory":"Management & Consulting",
            "type":"Services"
        }
    ],
    "sg:phone":"+1 615 890 5030",
    "sg:postcode":"37130",
    "sg:province":"TN",
    "sg:tags":[
        "educational"
    ],
    "wof:name":"Robert Eaker",
    "wof:placetype":"venue"
},
  "geometry": {"coordinates":[-86.375005,35.845368],"type":"Point"}
}