{
  "type": "Feature",
  "properties": {
    "iso:country":"US",
    "sg:address":"234 Mountain Rd",
    "sg:city":"Elora",
    "sg:classifiers":[
        {
            "category":"Farming",
            "subcategory":"Livestock Farm",
            "type":"Manufacturing & Wholesale Goods"
        }
    ],
    "sg:phone":"+1 931 937 8042",
    "sg:postcode":"37328",
    "sg:province":"AL",
    "sg:tags":[
        "cattle",
        "beef",
        "feedlot",
        "cotton"
    ],
    "wof:name":"Jerry Moorehead",
    "wof:placetype":"venue"
},
  "geometry": {"coordinates":[-86.33704,35.007159],"type":"Point"}
}