{
  "type": "Feature",
  "properties": {
    "iso:country":"US",
    "sg:address":"2201 Wilma Rudolph Blvd",
    "sg:city":"Clarksville",
    "sg:classifiers":[
        {
            "category":"Autos & Motor Vehicles",
            "subcategory":"Fuel & Gas Station",
            "type":"Retail Goods"
        }
    ],
    "sg:phone":"+1 931 906 1060",
    "sg:postcode":"37040",
    "sg:province":"TN",
    "sg:tags":[
        "oil"
    ],
    "wof:name":"Wayne's St Bethlehem Towing",
    "wof:placetype":"venue"
},
  "geometry": {"coordinates":[-87.307508,36.566665],"type":"Point"}
}