{
  "type": "Feature",
  "properties": {
    "addr:full":"42 Currie Rd Dyer TN 38330",
    "addr:housenumber":"42",
    "addr:postcode":"38330",
    "addr:street":"Currie Rd",
    "iso:country":"US",
    "sg:address":"42 Currie Rd",
    "sg:city":"Dyer",
    "sg:classifiers":[
        {
            "category":"Manufacturing",
            "subcategory":"Metals",
            "type":"Manufacturing & Wholesale Goods"
        }
    ],
    "sg:phone":"+1 731 692 2388",
    "sg:postcode":"38330",
    "sg:province":"TN",
    "sg:tags":[
        "steel",
        "fabrication",
        "structural"
    ],
    "wof:name":"Sullivan Fabricating Co",
    "wof:placetype":"venue"
},
  "geometry": {"coordinates":[-89.01112000000001,36.062076],"type":"Point"}
}