{
  "type": "Feature",
  "properties": {
    "iso:country":"US",
    "sg:address":"410 Basswood Ave",
    "sg:city":"Nashville",
    "sg:classifiers":[
        {
            "category":"Building & Trades",
            "subcategory":"Construction",
            "type":"Services"
        }
    ],
    "sg:phone":"+1 615 352 8008",
    "sg:postcode":"37209",
    "sg:province":"TN",
    "sg:tags":[
        "general",
        "contractor"
    ],
    "wof:name":"Mickey Palmer & Assoc",
    "wof:placetype":"venue"
},
  "geometry": {"coordinates":[-86.885092,36.151713],"type":"Point"}
}