{
  "type": "Feature",
  "properties": {
    "addr:full":"825 E Main St Gallatin TN 37066",
    "addr:housenumber":"825",
    "addr:postcode":"37066",
    "addr:street":"E Main St",
    "iso:country":"US",
    "sg:address":"825 E Main St",
    "sg:city":"Gallatin",
    "sg:classifiers":[
        {
            "category":"Shopping",
            "subcategory":"Department Store",
            "type":"Retail Goods"
        }
    ],
    "sg:phone":"+1 615 452 1500",
    "sg:postcode":"37066",
    "sg:province":"TN",
    "wof:name":"Kmart",
    "wof:placetype":"venue"
},
  "geometry": {"coordinates":[-86.428466,36.397784],"type":"Point"}
}