{
  "type": "Feature",
  "properties": {
    "addr:full":"2126 21st Ave S Nashville TN 37212",
    "addr:housenumber":"2126",
    "addr:postcode":"37212",
    "addr:street":"21St Ave S",
    "iso:country":"US",
    "sg:address":"2126 21st Ave S",
    "sg:city":"Nashville",
    "sg:classifiers":[
        {
            "category":"Wholesale",
            "subcategory":"Medical Equipment & Supplies",
            "type":"Manufacturing & Wholesale Goods"
        }
    ],
    "sg:phone":"+1 615 269 8874",
    "sg:postcode":"37212",
    "sg:province":"TN",
    "wof:name":"Surgical Support System",
    "wof:placetype":"venue"
},
  "geometry": {"coordinates":[-86.801844,36.130531],"type":"Point"}
}