{
  "type": "Feature",
  "properties": {
    "iso:country":"US",
    "sg:address":"113 W Court Sq",
    "sg:city":"Covington",
    "sg:classifiers":[
        {
            "category":"Shopping",
            "subcategory":"Clothing, Apparel, & Fashions",
            "type":"Retail Goods"
        }
    ],
    "sg:phone":"+1 901 476 9595",
    "sg:postcode":"38019",
    "sg:province":"TN",
    "sg:tags":[
        "shop",
        "bridal"
    ],
    "wof:name":"Glass Slipper Bridal Formal Wr",
    "wof:placetype":"venue"
},
  "geometry": {"coordinates":[-89.646597,35.564544],"type":"Point"}
}