{
  "type": "Feature",
  "properties": {
    "iso:country":"US",
    "sg:address":"1110 Gray Fox Ln",
    "sg:city":"Franklin",
    "sg:classifiers":[
        {
            "category":"Building & Trades",
            "subcategory":"Construction",
            "type":"Services"
        }
    ],
    "sg:phone":"+1 615 790 1116",
    "sg:postcode":"37069",
    "sg:province":"TN",
    "sg:tags":[
        "industrial"
    ],
    "wof:name":"Bgm Assoc Inc",
    "wof:placetype":"venue"
},
  "geometry": {"coordinates":[-86.86199999999999,35.949111],"type":"Point"}
}