{
  "type": "Feature",
  "properties": {
    "iso:country":"US",
    "sg:address":"1742 Edgemont Ave Unit 2",
    "sg:city":"Bristol",
    "sg:classifiers":[
        {
            "category":"Personal",
            "subcategory":"Beauty Salon",
            "type":"Services"
        }
    ],
    "sg:phone":"+1 423 968 3617",
    "sg:postcode":"37620",
    "sg:province":"TN",
    "sg:tags":[
        "hair",
        "stylist"
    ],
    "wof:name":"Fraser's Family Haircare",
    "wof:placetype":"venue"
},
  "geometry": {"coordinates":[-82.18602,36.574528],"type":"Point"}
}