{
  "type": "Feature",
  "properties": {
    "iso:country":"US",
    "sg:address":"645 S Main St",
    "sg:city":"Memphis",
    "sg:classifiers":[
        {
            "category":"Professional",
            "subcategory":"Management & Consulting",
            "type":"Services"
        }
    ],
    "sg:phone":"+1 901 522 1551",
    "sg:postcode":"38103",
    "sg:province":"TN",
    "sg:tags":[
        "marketing",
        "business"
    ],
    "wof:name":"Sdi",
    "wof:placetype":"venue"
},
  "geometry": {"coordinates":[-90.05915299999999,35.129935],"type":"Point"}
}