{
  "type": "Feature",
  "properties": {
    "addr:full":"47 Jones Cir Old Hickory TN 37138",
    "addr:housenumber":"47",
    "addr:postcode":"37138",
    "addr:street":"Jones Cir",
    "iso:country":"US",
    "sg:address":"47 Jones Cir",
    "sg:city":"Old Hickory",
    "sg:classifiers":[
        {
            "category":"Arts & Performance",
            "subcategory":"Theater",
            "type":"Entertainment"
        }
    ],
    "sg:phone":"+1 615 847 5811",
    "sg:postcode":"37138",
    "sg:province":"TN",
    "sg:tags":[
        "agency",
        "talent"
    ],
    "wof:name":"Mc Fadden and Associates Inc",
    "wof:placetype":"venue"
},
  "geometry": {"coordinates":[-86.64452300000001,36.269396],"type":"Point"}
}