{
  "type": "Feature",
  "properties": {
    "iso:country":"US",
    "sg:address":"6670 Lenox-Nauvoo Rd",
    "sg:city":"Dyersburg",
    "sg:classifiers":[
        {
            "category":"Building & Trades",
            "subcategory":"Plumbing",
            "type":"Services"
        }
    ],
    "sg:phone":"+1 731 285 7715",
    "sg:postcode":"38024",
    "sg:province":"TN",
    "sg:tags":[
        "contractor"
    ],
    "wof:name":"Hh Heating & Plumbing",
    "wof:placetype":"venue"
},
  "geometry": {"coordinates":[-89.457605,36.097849],"type":"Point"}
}