{
  "type": "Feature",
  "properties": {
    "iso:country":"US",
    "sg:address":"112 Hwy 52 W",
    "sg:city":"Lafayette",
    "sg:classifiers":[
        {
            "category":"Autos & Motor Vehicles",
            "subcategory":"Automobile Sales",
            "type":"Retail Goods"
        }
    ],
    "sg:phone":"+1 615 666 2205",
    "sg:postcode":"37083",
    "sg:province":"TN",
    "sg:tags":[
        "car",
        "dealer"
    ],
    "wof:name":"Smith's Motor Sales",
    "wof:placetype":"venue"
},
  "geometry": {"coordinates":[-86.027044,36.51766],"type":"Point"}
}