{
  "type": "Feature",
  "properties": {
    "addr:full":"701 US Hwy 45 Corinth TN 38834",
    "addr:housenumber":"701",
    "addr:postcode":"38834",
    "addr:street":"Us Hwy 45",
    "iso:country":"US",
    "sg:address":"701 US Hwy 45",
    "sg:city":"Corinth",
    "sg:classifiers":[
        {
            "category":"Organizations",
            "subcategory":"Religious Organization",
            "type":"Services"
        }
    ],
    "sg:phone":"+1 662 287 9160",
    "sg:postcode":"38834",
    "sg:province":"TN",
    "sg:tags":[
        "church"
    ],
    "wof:name":"Biggerville Pentecostal Church",
    "wof:placetype":"venue"
},
  "geometry": {"coordinates":[-88.559128,34.850883],"type":"Point"}
}