{
  "type": "Feature",
  "properties": {
    "iso:country":"US",
    "sg:address":"8307 Old Lee Hwy",
    "sg:city":"Ooltewah",
    "sg:classifiers":[
        {
            "category":"Restaurant",
            "type":"Food & Drink"
        }
    ],
    "sg:phone":"+1 423 238 4801",
    "sg:postcode":"37363",
    "sg:province":"TN",
    "wof:name":"Couch Barbecue",
    "wof:placetype":"venue"
},
  "geometry": {"coordinates":[-85.094026,35.073344],"type":"Point"}
}