{
  "type": "Feature",
  "properties": {
    "addr:full":"285 Church St NE Cleveland TN 37311",
    "addr:housenumber":"285",
    "addr:postcode":"37311",
    "addr:street":"Church St Ne",
    "iso:country":"US",
    "sg:address":"285 Church St NE",
    "sg:city":"Cleveland",
    "sg:classifiers":[
        {
            "category":"Government",
            "subcategory":"Office",
            "type":"Public Place"
        }
    ],
    "sg:phone":"+1 423 479 8144",
    "sg:postcode":"37311",
    "sg:province":"TN",
    "sg:tags":[
        "county",
        "resource"
    ],
    "wof:name":"Bradley County Child Support",
    "wof:placetype":"venue"
},
  "geometry": {"coordinates":[-84.873606,35.161199],"type":"Point"}
}