{
  "type": "Feature",
  "properties": {
    "addr:full":"282 N Cleveland St Memphis TN 38104",
    "addr:housenumber":"282",
    "addr:postcode":"38104",
    "addr:street":"N Cleveland St",
    "iso:country":"US",
    "sg:address":"282 N Cleveland St",
    "sg:city":"Memphis",
    "sg:classifiers":[
        {
            "category":"Restaurant",
            "type":"Food & Drink"
        }
    ],
    "sg:phone":"+1 901 726 9004",
    "sg:postcode":"38104",
    "sg:province":"TN",
    "sg:website":"http://www.zipweb.com/?businessName=Rudabagas/",
    "wof:name":"Rudabagas",
    "wof:placetype":"venue"
},
  "geometry": {"coordinates":[-90.014867,35.146284],"type":"Point"}
}