{
  "type": "Feature",
  "properties": {
    "addr:full":"1513 Dr D B Todd Jr Blvd Nashville TN 37208",
    "addr:housenumber":"1513",
    "addr:postcode":"37208",
    "addr:street":"Dr D;Jr Blvd",
    "iso:country":"US",
    "sg:address":"1513 Dr D B Todd Jr Blvd",
    "sg:city":"Nashville",
    "sg:classifiers":[
        {
            "category":"Organizations",
            "subcategory":"Community Association",
            "type":"Services"
        }
    ],
    "sg:phone":"+1 615 321 4767",
    "sg:postcode":"37208",
    "sg:province":"TN",
    "sg:tags":[
        "fraternal"
    ],
    "wof:name":"Masonic Lodge",
    "wof:placetype":"venue"
},
  "geometry": {"coordinates":[-86.808363,36.173628],"type":"Point"}
}