{
  "type": "Feature",
  "properties": {
    "iso:country":"US",
    "sg:address":"901 Woods Lake Dr",
    "sg:city":"Madison",
    "sg:classifiers":[
        {
            "category":"Professional",
            "type":"Services"
        }
    ],
    "sg:phone":"+1 615 868 3108",
    "sg:postcode":"37115",
    "sg:province":"TN",
    "wof:name":"McCracken Music",
    "wof:placetype":"venue"
},
  "geometry": {"coordinates":[-86.725646,36.280568],"type":"Point"}
}