{
  "type": "Feature",
  "properties": {
    "addr:full":"26 6th St Bristol TN 37620",
    "addr:housenumber":"26",
    "addr:postcode":"37620",
    "addr:street":"6Th St",
    "iso:country":"US",
    "sg:address":"26 6th St",
    "sg:city":"Bristol",
    "sg:classifiers":[
        {
            "category":"Personal",
            "subcategory":"Beauty Salon",
            "type":"Services"
        }
    ],
    "sg:phone":"+1 423 968 2633",
    "sg:postcode":"37620",
    "sg:province":"TN",
    "sg:tags":[
        "shop"
    ],
    "wof:name":"Beauty Garden",
    "wof:placetype":"venue"
},
  "geometry": {"coordinates":[-82.183423,36.594697],"type":"Point"}
}