{
  "type": "Feature",
  "properties": {
    "iso:country":"US",
    "sg:address":"2376 Twain Ave",
    "sg:city":"Memphis",
    "sg:classifiers":[
        {
            "category":"Professional",
            "subcategory":"Advertising",
            "type":"Services"
        }
    ],
    "sg:phone":"+1 901 743 0560",
    "sg:postcode":"38114",
    "sg:province":"TN",
    "wof:name":"JJVACATION.COM",
    "wof:placetype":"venue"
},
  "geometry": {"coordinates":[-89.981553,35.096374],"type":"Point"}
}