{
  "type": "Feature",
  "properties": {
    "iso:country":"US",
    "sg:address":"330 Broad St",
    "sg:city":"Kingsport",
    "sg:classifiers":[
        {
            "category":"Professional",
            "subcategory":"Business Services",
            "type":"Services"
        }
    ],
    "sg:phone":"+1 423 378 4609",
    "sg:postcode":"37660",
    "sg:province":"TN",
    "sg:tags":[
        "interior",
        "consultant",
        "designer",
        "design",
        "decorator"
    ],
    "wof:name":"Mc Clellan Interiors Inc",
    "wof:placetype":"venue"
},
  "geometry": {"coordinates":[-82.559421,36.547937],"type":"Point"}
}