{
  "type": "Feature",
  "properties": {
    "addr:full":"2303 Fort Henry Dr Kingsport TN 37664",
    "addr:housenumber":"2303",
    "addr:postcode":"37664",
    "addr:street":"Fort Henry Dr",
    "iso:country":"US",
    "sg:address":"2303 Fort Henry Dr",
    "sg:city":"Kingsport",
    "sg:classifiers":[
        {
            "category":"Retail",
            "subcategory":"Auto Repair",
            "type":"Services"
        }
    ],
    "sg:phone":"+1 423 246 5777",
    "sg:postcode":"37664",
    "sg:province":"TN",
    "sg:tags":[
        "automotive"
    ],
    "wof:name":"Kustom Kar",
    "wof:placetype":"venue"
},
  "geometry": {"coordinates":[-82.519812,36.525023],"type":"Point"}
}