{
  "type": "Feature",
  "properties": {
    "iso:country":"US",
    "sg:address":"8901 Rosemark Rd",
    "sg:city":"Millington",
    "sg:classifiers":[
        {
            "category":"Farming",
            "subcategory":"Livestock Farm",
            "type":"Manufacturing & Wholesale Goods"
        }
    ],
    "sg:phone":"+1 901 829 4646",
    "sg:postcode":"38053",
    "sg:province":"TN",
    "sg:tags":[
        "beef",
        "feedlot",
        "cattle"
    ],
    "wof:name":"Triple Lll Angus Farm",
    "wof:placetype":"venue"
},
  "geometry": {"coordinates":[-89.771416,35.369397],"type":"Point"}
}