{
  "type": "Feature",
  "properties": {
    "iso:country":"US",
    "sg:address":"119 Oak St",
    "sg:city":"Blountville",
    "sg:classifiers":[
        {
            "category":"Personal",
            "subcategory":"Beauty Salon",
            "type":"Services"
        }
    ],
    "sg:phone":"+1 423 323 5025",
    "sg:postcode":"37617",
    "sg:province":"TN",
    "sg:tags":[
        "shop"
    ],
    "wof:name":"Rachel's Beauty Shop",
    "wof:placetype":"venue"
},
  "geometry": {"coordinates":[-82.313087,36.537224],"type":"Point"}
}