{
  "type": "Feature",
  "properties": {
    "addr:full":"4853 Seedtick Rd Arlington TN 38002",
    "addr:housenumber":"4853",
    "addr:postcode":"38002",
    "addr:street":"Seedtick Rd",
    "iso:country":"US",
    "sg:address":"4853 Seedtick Rd",
    "sg:city":"Arlington",
    "sg:classifiers":[
        {
            "category":"Organizations",
            "subcategory":"Religious Organization",
            "type":"Services"
        }
    ],
    "sg:phone":"+1 901 867 8589",
    "sg:postcode":"38002",
    "sg:province":"TN",
    "sg:tags":[
        "church"
    ],
    "wof:name":"Twin Oaks Church Of Christ",
    "wof:placetype":"venue"
},
  "geometry": {"coordinates":[-89.734472,35.259667],"type":"Point"}
}