{
  "type": "Feature",
  "properties": {
    "iso:country":"US",
    "sg:address":"3675 Southwind Park Cove",
    "sg:city":"Memphis",
    "sg:classifiers":[
        {
            "category":"Retail",
            "subcategory":"Laundry & Dry Cleaning",
            "type":"Services"
        }
    ],
    "sg:phone":"+1 901 751 1966",
    "sg:postcode":"38125",
    "sg:province":"TN",
    "sg:tags":[
        "cleaners"
    ],
    "wof:name":"Your Cleaners",
    "wof:placetype":"venue"
},
  "geometry": {"coordinates":[-89.763814,35.048673],"type":"Point"}
}