{
  "type": "Feature",
  "properties": {
    "addr:full":"816 Andover Blvd Knoxville TN 37934",
    "addr:housenumber":"816",
    "addr:postcode":"37934",
    "addr:street":"Andover Blvd",
    "iso:country":"US",
    "sg:address":"816 Andover Blvd",
    "sg:city":"Knoxville",
    "sg:classifiers":[
        {
            "category":"Home & Garden",
            "subcategory":"Household Appliances",
            "type":"Retail Goods"
        }
    ],
    "sg:phone":"+1 865 675 3883",
    "sg:postcode":"37934",
    "sg:province":"TN",
    "wof:name":"Designs By Jenese",
    "wof:placetype":"venue"
},
  "geometry": {"coordinates":[-84.201065,35.882481],"type":"Point"}
}