{
  "type": "Feature",
  "properties": {
    "iso:country":"US",
    "sg:address":"2240 NW Broad St",
    "sg:city":"Murfreesboro",
    "sg:classifiers":[
        {
            "category":"Autos & Motor Vehicles",
            "subcategory":"Automobile Sales",
            "type":"Retail Goods"
        }
    ],
    "sg:phone":"+1 615 893 1333",
    "sg:postcode":"37129",
    "sg:province":"TN",
    "sg:tags":[
        "car",
        "dealer"
    ],
    "sg:website":"www.neilsandler.com",
    "wof:name":"Neill-Sandler Buick-Pontiac",
    "wof:placetype":"venue"
},
  "geometry": {"coordinates":[-86.40843,35.862689],"type":"Point"}
}