{
  "type": "Feature",
  "properties": {
    "iso:country":"US",
    "sg:address":"246 E Center St",
    "sg:city":"Kingsport",
    "sg:classifiers":[
        {
            "category":"Banks & Credit Unions",
            "subcategory":"Bank",
            "type":"Services"
        }
    ],
    "sg:phone":"+1 423 247 1191",
    "sg:postcode":"37664",
    "sg:province":"TN",
    "sg:tags":[
        "loan"
    ],
    "sg:website":"www.southernfinance.com",
    "wof:name":"Southern Finance & Thrift Corp",
    "wof:placetype":"venue"
},
  "geometry": {"coordinates":[-82.55824699999999,36.546592],"type":"Point"}
}