{
  "type": "Feature",
  "properties": {
    "iso:country":"US",
    "sg:address":"1961 Old Chilhowee Rd",
    "sg:city":"Seymour",
    "sg:classifiers":[
        {
            "category":"Manufacturing",
            "subcategory":"Apparel",
            "type":"Manufacturing & Wholesale Goods"
        }
    ],
    "sg:phone":"+1 865 982 4118",
    "sg:postcode":"37865",
    "sg:province":"TN",
    "wof:name":"Artistic Stitches",
    "wof:placetype":"venue"
},
  "geometry": {"coordinates":[-83.770054,35.781632],"type":"Point"}
}