{
  "type": "Feature",
  "properties": {
    "addr:full":"3777 Wilcox Blvd Chattanooga TN 37411",
    "addr:housenumber":"3777",
    "addr:postcode":"37411",
    "addr:street":"Wilcox Blvd",
    "iso:country":"US",
    "sg:address":"3777 Wilcox Blvd",
    "sg:city":"Chattanooga",
    "sg:classifiers":[
        {
            "category":"Organizations",
            "subcategory":"Religious Organization",
            "type":"Services"
        }
    ],
    "sg:phone":"+1 423 698 5900",
    "sg:postcode":"37411",
    "sg:province":"TN",
    "wof:name":"New Hope Mssnary Baptst Church",
    "wof:placetype":"venue"
},
  "geometry": {"coordinates":[-85.232997,35.045895],"type":"Point"}
}