{
  "type": "Feature",
  "properties": {
    "iso:country":"US",
    "sg:address":"7106 Moores Ln",
    "sg:city":"Brentwood",
    "sg:classifiers":[
        {
            "category":"Health Services",
            "subcategory":"Doctor",
            "type":"Services"
        }
    ],
    "sg:phone":"+1 615 221 9951",
    "sg:postcode":"37027",
    "sg:province":"TN",
    "sg:tags":[
        "medical"
    ],
    "wof:name":"Cool Springs Family Care Ctr",
    "wof:placetype":"venue"
},
  "geometry": {"coordinates":[-86.815442,35.967491],"type":"Point"}
}