{
  "type": "Feature",
  "properties": {
    "addr:full":"130 W Meeting St Dandridge TN 37725",
    "addr:housenumber":"130",
    "addr:postcode":"37725",
    "addr:street":"W Meeting St",
    "iso:country":"US",
    "sg:address":"130 W Meeting St",
    "sg:city":"Dandridge",
    "sg:classifiers":[
        {
            "category":"Social Services",
            "type":"Services"
        }
    ],
    "sg:phone":"+1 865 397 4693",
    "sg:postcode":"37725",
    "sg:province":"TN",
    "sg:tags":[
        "organization",
        "welfare"
    ],
    "wof:name":"Citizens For Job Equality & FA",
    "wof:placetype":"venue"
},
  "geometry": {"coordinates":[-83.418207,36.016017],"type":"Point"}
}