{
  "type": "Feature",
  "properties": {
    "iso:country":"US",
    "sg:address":"680 Industrial Rd",
    "sg:city":"Savannah",
    "sg:classifiers":[
        {
            "category":"Manufacturing",
            "subcategory":"Tools & Machinery",
            "type":"Manufacturing & Wholesale Goods"
        }
    ],
    "sg:phone":"+1 731 925 6617",
    "sg:postcode":"38372",
    "sg:province":"TN",
    "sg:tags":[
        "industry"
    ],
    "wof:name":"Cetec",
    "wof:placetype":"venue"
},
  "geometry": {"coordinates":[-88.23004299999999,35.164249],"type":"Point"}
}