{
  "type": "Feature",
  "properties": {
    "iso:country":"US",
    "sg:address":"3126 Alton Park Blvd",
    "sg:city":"Chattanooga",
    "sg:classifiers":[
        {
            "category":"Wholesale",
            "subcategory":"Machinery & Supplies",
            "type":"Manufacturing & Wholesale Goods"
        }
    ],
    "sg:phone":"+1 423 267 1203",
    "sg:postcode":"37410",
    "sg:province":"TN",
    "sg:tags":[
        "truck"
    ],
    "sg:website":"www.kencogroup.com",
    "wof:name":"Kenco Toyota-Lift",
    "wof:placetype":"venue"
},
  "geometry": {"coordinates":[-85.313292,35.016678],"type":"Point"}
}