{
  "type": "Feature",
  "properties": {
    "addr:full":"622 Hwy 52 E Lafayette TN 37083",
    "addr:housenumber":"622",
    "addr:postcode":"37083",
    "addr:street":"Hwy 52 E",
    "iso:country":"US",
    "sg:address":"622 Hwy 52 E",
    "sg:city":"Lafayette",
    "sg:classifiers":[
        {
            "category":"Insurance",
            "subcategory":"Insurance Agent",
            "type":"Services"
        }
    ],
    "sg:phone":"+1 615 666 4790",
    "sg:postcode":"37083",
    "sg:province":"TN",
    "wof:name":"Smith Insurance",
    "wof:placetype":"venue"
},
  "geometry": {"coordinates":[-86.0127,36.515832],"type":"Point"}
}