{
  "type": "Feature",
  "properties": {
    "iso:country":"US",
    "sg:address":"333 W Main St",
    "sg:city":"Brownsville",
    "sg:classifiers":[
        {
            "category":"Home & Garden",
            "subcategory":"Furniture",
            "type":"Retail Goods"
        }
    ],
    "sg:phone":"+1 731 772 0737",
    "sg:postcode":"38012",
    "sg:province":"TN",
    "wof:name":"Austin's Furniture & Appliance",
    "wof:placetype":"venue"
},
  "geometry": {"coordinates":[-89.26559,35.593944],"type":"Point"}
}