{
  "type": "Feature",
  "properties": {
    "addr:full":"506 N Farnum St Friendsville TN 37737",
    "addr:housenumber":"506",
    "addr:postcode":"37737",
    "addr:street":"N Farnum St",
    "iso:country":"US",
    "sg:address":"506 N Farnum St",
    "sg:city":"Friendsville",
    "sg:classifiers":[
        {
            "category":"Building & Trades",
            "subcategory":"Construction",
            "type":"Services"
        }
    ],
    "sg:phone":"+1 865 995 0703",
    "sg:postcode":"37737",
    "sg:province":"TN",
    "sg:tags":[
        "house"
    ],
    "wof:name":"Russells Building & Remodeling",
    "wof:placetype":"venue"
},
  "geometry": {"coordinates":[-84.126217,35.764077],"type":"Point"}
}