{
  "type": "Feature",
  "properties": {
    "addr:full":"1900 Patterson St Nashville TN 37203",
    "addr:housenumber":"1900",
    "addr:postcode":"37203",
    "addr:street":"Patterson St",
    "iso:country":"US",
    "sg:address":"1900 Patterson St",
    "sg:city":"Nashville",
    "sg:classifiers":[
        {
            "category":"Shopping",
            "subcategory":"Pharmacy",
            "type":"Retail Goods"
        }
    ],
    "sg:phone":"+1 615 327 1350",
    "sg:postcode":"37203",
    "sg:province":"TN",
    "wof:name":"Pardue's Pharmacy",
    "wof:placetype":"venue"
},
  "geometry": {"coordinates":[-86.80225900000001,36.155304],"type":"Point"}
}