{
  "type": "Feature",
  "properties": {
    "iso:country":"US",
    "sg:address":"4704 Millbranch Rd",
    "sg:city":"Memphis",
    "sg:classifiers":[
        {
            "category":"Wholesale",
            "subcategory":"Machinery & Supplies",
            "type":"Manufacturing & Wholesale Goods"
        }
    ],
    "sg:phone":"+1 901 345 6526",
    "sg:postcode":"38116",
    "sg:province":"TN",
    "sg:tags":[
        "equipment",
        "establishment"
    ],
    "wof:name":"Angel Beauty Supply",
    "wof:placetype":"venue"
},
  "geometry": {"coordinates":[-90.00753,35.020447],"type":"Point"}
}