{
  "type": "Feature",
  "properties": {
    "iso:country":"US",
    "sg:address":"340 Faithful Rd",
    "sg:city":"Parrottsville",
    "sg:phone":"+1 423 623 8145",
    "sg:postcode":"37843",
    "sg:province":"TN",
    "sg:tags":[
        "farm",
        "tobacco"
    ],
    "wof:name":"Howard Lafollette",
    "wof:placetype":"venue"
},
  "geometry": {"coordinates":[-83.087727,35.995089],"type":"Point"}
}