{
  "type": "Feature",
  "properties": {
    "iso:country":"US",
    "sg:address":"5760 Old Hickory Blvd",
    "sg:city":"Hermitage",
    "sg:classifiers":[
        {
            "category":"Shopping",
            "subcategory":"Computers & Home Electronics",
            "type":"Retail Goods"
        }
    ],
    "sg:phone":"+1 615 232 2994",
    "sg:postcode":"37076",
    "sg:province":"TN",
    "sg:tags":[
        "repair",
        "leasing",
        "sales"
    ],
    "wof:name":"Pcs 2 U Computer Sales & Lsg",
    "wof:placetype":"venue"
},
  "geometry": {"coordinates":[-86.601595,36.17133],"type":"Point"}
}