{
  "type": "Feature",
  "properties": {
    "iso:country":"US",
    "sg:address":"313 McDonald Dr",
    "sg:city":"Huntingdon",
    "sg:classifiers":[
        {
            "category":"Professional",
            "subcategory":"Business Services",
            "type":"Services"
        }
    ],
    "sg:phone":"+1 731 986 5915",
    "sg:postcode":"38344",
    "sg:province":"TN",
    "sg:tags":[
        "drafting"
    ],
    "wof:name":"Grant's Drafting Svc",
    "wof:placetype":"venue"
},
  "geometry": {"coordinates":[-88.42272199999999,36.012037],"type":"Point"}
}