{
  "type": "Feature",
  "properties": {
    "addr:full":"4400 Harding Pl Nashville TN 37205",
    "addr:housenumber":"4400",
    "addr:postcode":"37205",
    "addr:street":"Harding Pl",
    "iso:country":"US",
    "sg:address":"4400 Harding Pl",
    "sg:city":"Nashville",
    "sg:classifiers":[
        {
            "category":"Freight",
            "type":"Transportation"
        }
    ],
    "sg:phone":"+1 615 298 8200",
    "sg:postcode":"37205",
    "sg:province":"TN",
    "sg:tags":[
        "river"
    ],
    "wof:name":"Ohio River Company LLC",
    "wof:placetype":"venue"
},
  "geometry": {"coordinates":[-86.851156,36.093372],"type":"Point"}
}