{
  "type": "Feature",
  "properties": {
    "iso:country":"US",
    "sg:address":"389 Centerville Rd",
    "sg:city":"Lebanon",
    "sg:classifiers":[
        {
            "category":"Building & Trades",
            "subcategory":"Plumbing",
            "type":"Services"
        }
    ],
    "sg:phone":"+1 615 449 0322",
    "sg:postcode":"37087",
    "sg:province":"TN",
    "sg:tags":[
        "contractor"
    ],
    "wof:name":"Edl Plumbing",
    "wof:placetype":"venue"
},
  "geometry": {"coordinates":[-86.203496,36.284902],"type":"Point"}
}