{
  "type": "Feature",
  "properties": {
    "iso:country":"US",
    "sg:address":"11832 Chapman Hwy",
    "sg:city":"Seymour",
    "sg:classifiers":[
        {
            "category":"Professional",
            "type":"Services"
        }
    ],
    "sg:phone":"+1 865 577 6771",
    "sg:postcode":"37865",
    "sg:province":"TN",
    "wof:name":"Gods House of Hope",
    "wof:placetype":"venue"
},
  "geometry": {"coordinates":[-83.741461,35.861042],"type":"Point"}
}