{
  "type": "Feature",
  "properties": {
    "iso:country":"US",
    "sg:address":"163 Sammy Wright Rd",
    "sg:city":"Halls",
    "sg:classifiers":[
        {
            "category":"Professional",
            "subcategory":"Computer Services",
            "type":"Services"
        }
    ],
    "sg:phone":"+1 731 836 7891",
    "sg:postcode":"38040",
    "sg:province":"TN",
    "sg:tags":[
        "internet"
    ],
    "sg:website":"www.eetronics.com",
    "wof:name":"EETRONICS.COM",
    "wof:placetype":"venue"
},
  "geometry": {"coordinates":[-89.48971299999999,35.871535],"type":"Point"}
}