{
  "type": "Feature",
  "properties": {
    "addr:full":"405 Mc Nally Dr Nashville TN 37211",
    "addr:housenumber":"405",
    "addr:postcode":"37211",
    "addr:street":"Mc Nally Dr",
    "iso:country":"US",
    "sg:address":"405 Mc Nally Dr",
    "sg:city":"Nashville",
    "sg:classifiers":[
        {
            "category":"Autos & Motor Vehicles",
            "subcategory":"Automobile Sales",
            "type":"Retail Goods"
        }
    ],
    "sg:phone":"+1 615 832 8332",
    "sg:postcode":"37211",
    "sg:province":"TN",
    "sg:tags":[
        "car",
        "dealer"
    ],
    "wof:name":"Mexicali Motors",
    "wof:placetype":"venue"
},
  "geometry": {"coordinates":[-86.738077,36.092624],"type":"Point"}
}