{
  "type": "Feature",
  "properties": {
    "addr:full":"2182 US Hwy 70 Jackson TN 38305",
    "addr:housenumber":"2182",
    "addr:postcode":"38305",
    "addr:street":"Us Hwy 70",
    "iso:country":"US",
    "sg:address":"2182 US Hwy 70",
    "sg:city":"Jackson",
    "sg:classifiers":[
        {
            "category":"Building & Trades",
            "subcategory":"Construction",
            "type":"Services"
        },
        {
            "category":"Social Services",
            "type":"Services"
        }
    ],
    "sg:phone":"+1 731 424 1114",
    "sg:postcode":"38305",
    "sg:province":"TN",
    "sg:tags":[
        "shelter",
        "dealer",
        "storm",
        "contractor"
    ],
    "wof:name":"Fain Services",
    "wof:placetype":"venue"
},
  "geometry": {"coordinates":[-88.738823,35.685622],"type":"Point"}
}