{
  "type": "Feature",
  "properties": {
    "iso:country":"US",
    "sg:address":"2560 US Hwy 641 N",
    "sg:city":"Paris",
    "sg:classifiers":[
        {
            "category":"Retail",
            "subcategory":"Auto Repair",
            "type":"Services"
        }
    ],
    "sg:phone":"+1 731 782 3578",
    "sg:postcode":"38242",
    "sg:province":"TN",
    "sg:tags":[
        "general"
    ],
    "wof:name":"Hilltop Auto Repair",
    "wof:placetype":"venue"
},
  "geometry": {"coordinates":[-88.32874200000001,36.340269],"type":"Point"}
}