{
  "type": "Feature",
  "properties": {
    "addr:full":"111 S Munford St Covington TN 38019",
    "addr:housenumber":"111",
    "addr:postcode":"38019",
    "addr:street":"S Munford St",
    "iso:country":"US",
    "sg:address":"111 S Munford St",
    "sg:city":"Covington",
    "sg:classifiers":[
        {
            "category":"Professional",
            "subcategory":"Employment Agencies",
            "type":"Services"
        }
    ],
    "sg:phone":"+1 901 476 7114",
    "sg:postcode":"38019",
    "sg:province":"TN",
    "sg:tags":[
        "help",
        "contractor"
    ],
    "wof:name":"Express Personnel Svc",
    "wof:placetype":"venue"
},
  "geometry": {"coordinates":[-89.64793400000001,35.564515],"type":"Point"}
}