{
  "type": "Feature",
  "properties": {
    "iso:country":"US",
    "sg:address":"120 N Central Ave",
    "sg:city":"Humboldt",
    "sg:classifiers":[
        {
            "category":"Retail",
            "subcategory":"Auto Repair",
            "type":"Services"
        }
    ],
    "sg:phone":"+1 731 784 8384",
    "sg:postcode":"38343",
    "sg:province":"TN",
    "sg:tags":[
        "body"
    ],
    "wof:name":"Reasons Body Shop",
    "wof:placetype":"venue"
},
  "geometry": {"coordinates":[-88.91600699999999,35.820516],"type":"Point"}
}