{
  "type": "Feature",
  "properties": {
    "addr:full":"4520 Harding Pike Nashville TN 37205",
    "addr:housenumber":"4520",
    "addr:postcode":"37205",
    "addr:street":"Harding Pike",
    "iso:country":"US",
    "sg:address":"4520 Harding Pike",
    "sg:city":"Nashville",
    "sg:classifiers":[
        {
            "category":"Restaurant",
            "type":"Food & Drink"
        }
    ],
    "sg:phone":"+1 615 292 3589",
    "sg:postcode":"37205",
    "sg:province":"TN",
    "wof:name":"Goldies' Deli",
    "wof:placetype":"venue"
},
  "geometry": {"coordinates":[-86.84929,36.123912],"type":"Point"}
}