{
  "type": "Feature",
  "properties": {
    "iso:country":"US",
    "sg:address":"210 25th Ave N",
    "sg:city":"Nashville",
    "sg:classifiers":[
        {
            "category":"Manufacturing",
            "subcategory":"Tools & Machinery",
            "type":"Manufacturing & Wholesale Goods"
        }
    ],
    "sg:phone":"+1 615 321 5611",
    "sg:postcode":"37203",
    "sg:province":"TN",
    "sg:tags":[
        "eyes",
        "artificial"
    ],
    "wof:name":"Richardson Ocular Prosthetics",
    "wof:placetype":"venue"
},
  "geometry": {"coordinates":[-86.809203,36.148348],"type":"Point"}
}