{
  "type": "Feature",
  "properties": {
    "iso:country":"US",
    "sg:address":"71 Store Rd",
    "sg:city":"Rock Island",
    "sg:classifiers":[
        {
            "category":"Manufacturing",
            "subcategory":"Printing",
            "type":"Manufacturing & Wholesale Goods"
        }
    ],
    "sg:phone":"+1 931 686 7746",
    "sg:postcode":"38581",
    "sg:province":"TN",
    "sg:tags":[
        "printer"
    ],
    "wof:name":"Mak Design & Printing",
    "wof:placetype":"venue"
},
  "geometry": {"coordinates":[-85.632367,35.76998],"type":"Point"}
}