{
  "type": "Feature",
  "properties": {
    "addr:full":"182 W Main St Hendersonville TN 37075",
    "addr:housenumber":"182",
    "addr:postcode":"37075",
    "addr:street":"W Main St",
    "iso:country":"US",
    "sg:address":"182 W Main St",
    "sg:city":"Hendersonville",
    "sg:classifiers":[
        {
            "category":"Retail",
            "subcategory":"Funeral Services",
            "type":"Services"
        }
    ],
    "sg:phone":"+1 615 824 8605",
    "sg:postcode":"37075",
    "sg:province":"TN",
    "sg:tags":[
        "director"
    ],
    "wof:name":"Cole & Garrett Funeral Home",
    "wof:placetype":"venue"
},
  "geometry": {"coordinates":[-86.616174,36.30542],"type":"Point"}
}