{
  "type": "Feature",
  "properties": {
    "iso:country":"US",
    "sg:address":"318 Fesslers Ln",
    "sg:city":"Nashville",
    "sg:classifiers":[
        {
            "category":"Wholesale",
            "subcategory":"Machinery & Supplies",
            "type":"Manufacturing & Wholesale Goods"
        }
    ],
    "sg:phone":"+1 615 242 6410",
    "sg:postcode":"37210",
    "sg:province":"TN",
    "sg:tags":[
        "engine"
    ],
    "wof:name":"Diesel Sales & Svc",
    "wof:placetype":"venue"
},
  "geometry": {"coordinates":[-86.74303,36.149625],"type":"Point"}
}