{
  "type": "Feature",
  "properties": {
    "iso:country":"US",
    "sg:address":"150 Brentwood Pl",
    "sg:city":"Lenoir City",
    "sg:classifiers":[
        {
            "category":"Building & Trades",
            "subcategory":"Cleaning & Sanitation",
            "type":"Services"
        }
    ],
    "sg:phone":"+1 865 986 6764",
    "sg:postcode":"37772",
    "sg:province":"TN",
    "sg:tags":[
        "fireplace",
        "chimney"
    ],
    "wof:name":"East Tennessee Chimney Sweeps",
    "wof:placetype":"venue"
},
  "geometry": {"coordinates":[-84.252611,35.821966],"type":"Point"}
}