{
  "type": "Feature",
  "properties": {
    "iso:country":"US",
    "sg:address":"2148 Kilbirnie Dr",
    "sg:city":"Germantown",
    "sg:classifiers":[
        {
            "category":"Professional",
            "subcategory":"Business Services",
            "type":"Services"
        }
    ],
    "sg:phone":"+1 901 309 6899",
    "sg:postcode":"38139",
    "sg:province":"TN",
    "wof:name":"A Virtual Agency",
    "wof:placetype":"venue"
},
  "geometry": {"coordinates":[-89.769935,35.089829],"type":"Point"}
}