{
  "type": "Feature",
  "properties": {
    "addr:full":"1932 Cedar St Mc Kenzie TN 38201",
    "addr:housenumber":"1932",
    "addr:postcode":"38201",
    "addr:street":"Cedar St Mc",
    "iso:country":"US",
    "sg:address":"1932 Cedar St",
    "sg:city":"Mc Kenzie",
    "sg:classifiers":[
        {
            "category":"Food & Beverages",
            "subcategory":"Groceries & Convenience Stores",
            "type":"Retail Goods"
        }
    ],
    "sg:phone":"+1 731 352 9090",
    "sg:postcode":"38201",
    "sg:province":"TN",
    "wof:name":"Smoke Shack 8",
    "wof:placetype":"venue"
},
  "geometry": {"coordinates":[-88.512514,36.129612],"type":"Point"}
}