{
  "type": "Feature",
  "properties": {
    "iso:country":"US",
    "sg:address":"8695 Vandever Rd",
    "sg:city":"Crossville",
    "sg:classifiers":[
        {
            "category":"Farming",
            "subcategory":"Livestock Farm",
            "type":"Manufacturing & Wholesale Goods"
        }
    ],
    "sg:phone":"+1 931 788 2038",
    "sg:postcode":"38572",
    "sg:province":"TN",
    "sg:tags":[
        "equine",
        "animal"
    ],
    "wof:name":"Wintercrest Farms",
    "wof:placetype":"venue"
},
  "geometry": {"coordinates":[-85.051784,35.788355],"type":"Point"}
}