{
  "type": "Feature",
  "properties": {
    "addr:full":"725 Co Rd 100 Morrison TN 37303",
    "addr:housenumber":"725;100",
    "addr:postcode":"37303",
    "addr:street":"Co Rd",
    "iso:country":"US",
    "sg:address":"725 Co Rd 100",
    "sg:city":"Morrison",
    "sg:classifiers":[
        {
            "category":"Manufacturing",
            "subcategory":"Metals",
            "type":"Manufacturing & Wholesale Goods"
        }
    ],
    "sg:phone":"+1 931 668 9293",
    "sg:postcode":"37303",
    "sg:province":"TN",
    "sg:tags":[
        "fabrication",
        "structural"
    ],
    "wof:name":"Conservation Services Group",
    "wof:placetype":"venue"
},
  "geometry": {"coordinates":[-84.754285,35.454697],"type":"Point"}
}