{
  "type": "Feature",
  "properties": {
    "addr:full":"6005 Park Ave Memphis TN 38119",
    "addr:housenumber":"6005",
    "addr:postcode":"38119",
    "addr:street":"Park Ave",
    "iso:country":"US",
    "sg:address":"6005 Park Ave",
    "sg:city":"Memphis",
    "sg:classifiers":[
        {
            "category":"Health Services",
            "subcategory":"Doctor",
            "type":"Services"
        }
    ],
    "sg:phone":"+1 901 684 1322",
    "sg:postcode":"38119",
    "sg:province":"TN",
    "sg:tags":[
        "physician",
        "surgeon"
    ],
    "wof:name":"East Memphis Internal Medicine",
    "wof:placetype":"venue"
},
  "geometry": {"coordinates":[-89.861684,35.099917],"type":"Point"}
}