{
  "type": "Feature",
  "properties": {
    "iso:country":"US",
    "sg:address":"876 McMahan Rd",
    "sg:city":"Ramer",
    "sg:classifiers":[
        {
            "category":"Manufacturing",
            "subcategory":"Tools & Machinery",
            "type":"Manufacturing & Wholesale Goods"
        }
    ],
    "sg:phone":"+1 731 645 6798",
    "sg:postcode":"38367",
    "sg:province":"TN",
    "sg:tags":[
        "industrial",
        "mfg"
    ],
    "wof:name":"Ford Machine",
    "wof:placetype":"venue"
},
  "geometry": {"coordinates":[-88.563237,35.084657],"type":"Point"}
}