{
  "type": "Feature",
  "properties": {
    "iso:country":"US",
    "sg:address":"50 Hermitage Ave",
    "sg:city":"Nashville",
    "sg:classifiers":[
        {
            "category":"Government",
            "subcategory":"Office",
            "type":"Public Place"
        }
    ],
    "sg:phone":"+1 615 862 6777",
    "sg:postcode":"37210",
    "sg:province":"TN",
    "wof:name":"Davidson County Taxicab Lcnsng",
    "wof:placetype":"venue"
},
  "geometry": {"coordinates":[-86.76793499999999,36.156475],"type":"Point"}
}