{
  "type": "Feature",
  "properties": {
    "addr:full":"1701 Downtown West Blvd Knoxville TN 37919",
    "addr:housenumber":"1701",
    "addr:postcode":"37919",
    "addr:street":"Downtown West Blvd",
    "iso:country":"US",
    "sg:address":"1701 Downtown West Blvd",
    "sg:city":"Knoxville",
    "sg:classifiers":[
        {
            "category":"Personal",
            "subcategory":"Beauty Salon",
            "type":"Services"
        }
    ],
    "sg:phone":"+1 865 694 4000",
    "sg:postcode":"37919",
    "sg:province":"TN",
    "sg:tags":[
        "shop"
    ],
    "sg:website":"www.salonvisage.com",
    "wof:name":"Salon Visage Inc",
    "wof:placetype":"venue"
},
  "geometry": {"coordinates":[-84.05076699999999,35.92254],"type":"Point"}
}