{
  "type": "Feature",
  "properties": {
    "iso:country":"US",
    "sg:address":"100 Church St",
    "sg:city":"Centerville",
    "sg:classifiers":[
        {
            "category":"Real Estate",
            "subcategory":"Real Estate Agent",
            "type":"Services"
        }
    ],
    "sg:phone":"+1 931 729 5763",
    "sg:postcode":"37033",
    "sg:province":"TN",
    "wof:name":"Tennessee Properties",
    "wof:placetype":"venue"
},
  "geometry": {"coordinates":[-87.46625899999999,35.778306],"type":"Point"}
}