{
  "type": "Feature",
  "properties": {
    "iso:country":"US",
    "sg:address":"393 Co Rd 554",
    "sg:city":"Athens",
    "sg:classifiers":[
        {
            "category":"Government",
            "subcategory":"Office",
            "type":"Public Place"
        }
    ],
    "sg:phone":"+1 423 745 7431",
    "sg:postcode":"37303",
    "sg:province":"TN",
    "sg:tags":[
        "county",
        "program",
        "health"
    ],
    "wof:name":"Mc Minn County Health Unit",
    "wof:placetype":"venue"
},
  "geometry": {"coordinates":[-84.567924,35.396573],"type":"Point"}
}