{
  "type": "Feature",
  "properties": {
    "iso:country":"US",
    "sg:address":"7151 New Hope Rd",
    "sg:city":"Fairview",
    "sg:classifiers":[
        {
            "category":"Retail",
            "subcategory":"Repair Shop",
            "type":"Services"
        }
    ],
    "sg:phone":"+1 615 799 9217",
    "sg:postcode":"37062",
    "sg:province":"TN",
    "sg:tags":[
        "instrument",
        "musical"
    ],
    "wof:name":"C B Guitars",
    "wof:placetype":"venue"
},
  "geometry": {"coordinates":[-87.15465500000001,36.016227],"type":"Point"}
}