{
  "type": "Feature",
  "properties": {
    "iso:country":"US",
    "sg:address":"2613 Laurel Creek Dr",
    "sg:city":"Signal Mountain",
    "sg:classifiers":[
        {
            "category":"Professional",
            "type":"Services"
        }
    ],
    "sg:phone":"+1 423 886 5204",
    "sg:postcode":"37377",
    "sg:province":"TN",
    "wof:name":"Capture Information Llc",
    "wof:placetype":"venue"
},
  "geometry": {"coordinates":[-85.33373400000001,35.191428],"type":"Point"}
}