{
  "type": "Feature",
  "properties": {
    "iso:country":"US",
    "sg:address":"2255 Hollywood Dr",
    "sg:city":"Jackson",
    "sg:classifiers":[
        {
            "category":"Autos & Motor Vehicles",
            "subcategory":"Fuel & Gas Station",
            "type":"Retail Goods"
        }
    ],
    "sg:phone":"+1 731 668 4397",
    "sg:postcode":"38305",
    "sg:province":"TN",
    "sg:tags":[
        "station",
        "gasoline"
    ],
    "wof:name":"Hollywood Express",
    "wof:placetype":"venue"
},
  "geometry": {"coordinates":[-88.873148,35.655504],"type":"Point"}
}