{
  "type": "Feature",
  "properties": {
    "iso:country":"US",
    "sg:address":"537 Market St",
    "sg:city":"Chattanooga",
    "sg:classifiers":[
        {
            "category":"Professional",
            "subcategory":"Lawyer & Legal Services",
            "type":"Services"
        }
    ],
    "sg:phone":"+1 423 756 7117",
    "sg:postcode":"37402",
    "sg:province":"TN",
    "sg:tags":[
        "attorney",
        "law",
        "at"
    ],
    "wof:name":"Alday Cara J",
    "wof:placetype":"venue"
},
  "geometry": {"coordinates":[-85.30963300000001,35.050146],"type":"Point"}
}