{
  "type": "Feature",
  "properties": {
    "addr:full":"3080 Hwy 75 Johnson City TN 37617",
    "addr:housenumber":"3080",
    "addr:postcode":"37617",
    "addr:street":"Hwy 75",
    "iso:country":"US",
    "sg:address":"3080 Hwy 75",
    "sg:city":"Johnson City",
    "sg:classifiers":[
        {
            "category":"Manufacturing",
            "subcategory":"Printing",
            "type":"Manufacturing & Wholesale Goods"
        }
    ],
    "sg:phone":"+1 423 282 6660",
    "sg:postcode":"37617",
    "sg:province":"TN",
    "sg:tags":[
        "newspaper"
    ],
    "wof:name":"Tri-City Trading Post",
    "wof:placetype":"venue"
},
  "geometry": {"coordinates":[-82.418683,36.468125],"type":"Point"}
}