{
  "type": "Feature",
  "properties": {
    "addr:full":"401 3rd Ave N Nashville TN 37201",
    "addr:housenumber":"401",
    "addr:postcode":"37201",
    "addr:street":"3Rd Ave N",
    "iso:country":"US",
    "sg:address":"401 3rd Ave N",
    "sg:city":"Nashville",
    "sg:classifiers":[
        {
            "category":"Food & Beverages",
            "subcategory":"Groceries & Convenience Stores",
            "type":"Retail Goods"
        }
    ],
    "sg:phone":"+1 615 256 7553",
    "sg:postcode":"37201",
    "sg:province":"TN",
    "sg:tags":[
        "grocer"
    ],
    "wof:name":"Wang's Enterprises Inc",
    "wof:placetype":"venue"
},
  "geometry": {"coordinates":[-86.77907500000001,36.166343],"type":"Point"}
}