{
  "type": "Feature",
  "properties": {
    "iso:country":"US",
    "sg:address":"200 Kubo Rd",
    "sg:city":"Drummonds",
    "sg:classifiers":[
        {
            "category":"Sports & Exercise",
            "subcategory":"Golf",
            "type":"Entertainment"
        }
    ],
    "sg:phone":"+1 901 835 2152",
    "sg:postcode":"38023",
    "sg:province":"TN",
    "sg:tags":[
        "course",
        "range",
        "practice"
    ],
    "sg:website":"http://www.foresthillgolfcourse.com",
    "wof:name":"Forest Hill Golf Course",
    "wof:placetype":"venue"
},
  "geometry": {"coordinates":[-89.900719,35.43922],"type":"Point"}
}