{
  "type": "Feature",
  "properties": {
    "addr:full":"4180 Leroy Ave Memphis TN 38108",
    "addr:housenumber":"4180",
    "addr:postcode":"38108",
    "addr:street":"Leroy Ave",
    "iso:country":"US",
    "sg:address":"4180 Leroy Ave",
    "sg:city":"Memphis",
    "sg:classifiers":[
        {
            "category":"Organizations",
            "subcategory":"Religious Organization",
            "type":"Services"
        }
    ],
    "sg:phone":"+1 901 767 8672",
    "sg:postcode":"38108",
    "sg:province":"TN",
    "sg:tags":[
        "place",
        "worship",
        "church"
    ],
    "sg:website":"http://www.incarnationchurch.com",
    "wof:name":"Saint James Catholic Church",
    "wof:placetype":"venue"
},
  "geometry": {"coordinates":[-89.920883,35.175949],"type":"Point"}
}