{
  "type": "Feature",
  "properties": {
    "addr:full":"436 Main St Franklin TN 37064",
    "addr:housenumber":"436",
    "addr:postcode":"37064",
    "addr:street":"Main St",
    "iso:country":"US",
    "sg:address":"436 Main St",
    "sg:city":"Franklin",
    "sg:classifiers":[
        {
            "category":"Professional",
            "subcategory":"Business Services",
            "type":"Services"
        }
    ],
    "sg:phone":"+1 615 794 4299",
    "sg:postcode":"37064",
    "sg:province":"TN",
    "wof:name":"Dream Enterprises Internationa",
    "wof:placetype":"venue"
},
  "geometry": {"coordinates":[-86.870808,35.924395],"type":"Point"}
}