{
  "type": "Feature",
  "properties": {
    "addr:full":"1854 Hillsboro Blvd Manchester TN 37355",
    "addr:housenumber":"1854",
    "addr:postcode":"37355",
    "addr:street":"Hillsboro Blvd",
    "iso:country":"US",
    "sg:address":"1854 Hillsboro Blvd",
    "sg:city":"Manchester",
    "sg:classifiers":[
        {
            "category":"Freight",
            "type":"Transportation"
        }
    ],
    "sg:phone":"+1 931 728 6855",
    "sg:postcode":"37355",
    "sg:province":"TN",
    "sg:tags":[
        "general"
    ],
    "wof:name":"Video Corner",
    "wof:placetype":"venue"
},
  "geometry": {"coordinates":[-86.066956,35.46376],"type":"Point"}
}