{
  "type": "Feature",
  "properties": {
    "addr:full":"7994 State Hwy 297 Pioneer TN 37847",
    "addr:housenumber":"7994",
    "addr:postcode":"37847",
    "addr:street":"State Hwy 297",
    "iso:country":"US",
    "sg:address":"7994 State Hwy 297",
    "sg:city":"Pioneer",
    "sg:classifiers":[
        {
            "category":"Building & Trades",
            "subcategory":"Construction",
            "type":"Services"
        },
        {
            "category":"Home & Garden",
            "subcategory":"Furniture",
            "type":"Retail Goods"
        }
    ],
    "sg:phone":"+1 423 784 2960",
    "sg:postcode":"37847",
    "sg:province":"TN",
    "sg:tags":[
        "mfg",
        "kitchen",
        "cabinet",
        "wood",
        "contractor",
        "carpentry"
    ],
    "wof:name":"Bridges Elk Valley Cabinet Shp",
    "wof:placetype":"venue"
},
  "geometry": {"coordinates":[-84.285566,36.461339],"type":"Point"}
}