{
  "type": "Feature",
  "properties": {
    "iso:country":"US",
    "sg:address":"911 Jackson Love Hwy",
    "sg:city":"Erwin",
    "sg:classifiers":[
        {
            "category":"Insurance",
            "subcategory":"Insurance Agent",
            "type":"Services"
        }
    ],
    "sg:phone":"+1 423 743 2332",
    "sg:postcode":"37650",
    "sg:province":"TN",
    "wof:name":"Unico County Insurance Agency Inc",
    "wof:placetype":"venue"
},
  "geometry": {"coordinates":[-82.417768,36.13123],"type":"Point"}
}