{
  "type": "Feature",
  "properties": {
    "iso:country":"US",
    "sg:address":"6601 Maynardville Pike",
    "sg:city":"Knoxville",
    "sg:classifiers":[
        {
            "category":"Retail",
            "subcategory":"Auto Repair",
            "type":"Services"
        }
    ],
    "sg:phone":"+1 865 688 0911",
    "sg:postcode":"37918",
    "sg:province":"TN",
    "sg:tags":[
        "general"
    ],
    "wof:name":"East Tenn Collision & Service",
    "wof:placetype":"venue"
},
  "geometry": {"coordinates":[-83.926862,36.067783],"type":"Point"}
}