{
  "type": "Feature",
  "properties": {
    "iso:country":"US",
    "sg:address":"109 Green St",
    "sg:city":"Lafayette",
    "sg:classifiers":[
        {
            "category":"Professional",
            "subcategory":"Business Services",
            "type":"Services"
        }
    ],
    "sg:phone":"+1 615 666 5772",
    "sg:postcode":"37083",
    "sg:province":"TN",
    "sg:tags":[
        "embroidery"
    ],
    "wof:name":"TFG Marketing",
    "wof:placetype":"venue"
},
  "geometry": {"coordinates":[-86.018869,36.538897],"type":"Point"}
}