{
  "type": "Feature",
  "properties": {
    "iso:country":"US",
    "sg:address":"7313 Central Avenue Pike",
    "sg:city":"Powell",
    "sg:classifiers":[
        {
            "category":"Building & Trades",
            "subcategory":"Electrical",
            "type":"Services"
        }
    ],
    "sg:phone":"+1 865 938 5299",
    "sg:postcode":"37849",
    "sg:province":"TN",
    "sg:tags":[
        "electrical",
        "contractor"
    ],
    "wof:name":"Edmonson Allen H Elec Contr",
    "wof:placetype":"venue"
},
  "geometry": {"coordinates":[-84.00261,36.037897],"type":"Point"}
}