{
  "type": "Feature",
  "properties": {
    "iso:country":"US",
    "sg:address":"5321 Pleasant View Rd",
    "sg:city":"Memphis",
    "sg:classifiers":[
        {
            "category":"Retail",
            "subcategory":"Auto Repair",
            "type":"Services"
        }
    ],
    "sg:phone":"+1 901 384 3755",
    "sg:postcode":"38134",
    "sg:province":"TN",
    "sg:tags":[
        "body",
        "automobile",
        "painting",
        "repairing"
    ],
    "wof:name":"Auto Dealer Services Inc",
    "wof:placetype":"venue"
},
  "geometry": {"coordinates":[-89.883675,35.173805],"type":"Point"}
}