{
  "type": "Feature",
  "properties": {
    "addr:full":"768 S Jefferson Ave Cookeville TN 38501",
    "addr:housenumber":"768",
    "addr:postcode":"38501",
    "addr:street":"S Jefferson Ave",
    "iso:country":"US",
    "sg:address":"768 S Jefferson Ave",
    "sg:city":"Cookeville",
    "sg:classifiers":[
        {
            "category":"Personal",
            "subcategory":"Beauty Salon",
            "type":"Services"
        }
    ],
    "sg:phone":"+1 931 525 1375",
    "sg:postcode":"38501",
    "sg:province":"TN",
    "sg:tags":[
        "manicuring"
    ],
    "wof:name":"Bella Nails",
    "wof:placetype":"venue"
},
  "geometry": {"coordinates":[-85.500953,36.144455],"type":"Point"}
}