{
  "type": "Feature",
  "properties": {
    "addr:full":"1314 US Hwy 51 N Covington TN 38019",
    "addr:housenumber":"1314",
    "addr:postcode":"38019",
    "addr:street":"Us Hwy 51 N",
    "iso:country":"US",
    "sg:address":"1314 US Hwy 51 N",
    "sg:city":"Covington",
    "sg:classifiers":[
        {
            "category":"Autos & Motor Vehicles",
            "subcategory":"Automobile Sales",
            "type":"Retail Goods"
        }
    ],
    "sg:phone":"+1 901 476 3178",
    "sg:postcode":"38019",
    "sg:province":"TN",
    "sg:tags":[
        "car",
        "dealer"
    ],
    "wof:name":"Ken Gray Auto Sales",
    "wof:placetype":"venue"
},
  "geometry": {"coordinates":[-89.63252799999999,35.593763],"type":"Point"}
}