{
  "type": "Feature",
  "properties": {
    "addr:full":"1104 Faye St Kingsport TN 37660",
    "addr:housenumber":"1104",
    "addr:postcode":"37660",
    "addr:street":"Faye St",
    "iso:country":"US",
    "sg:address":"1104 Faye St",
    "sg:city":"Kingsport",
    "sg:classifiers":[
        {
            "category":"Personal",
            "subcategory":"Beauty Salon",
            "type":"Services"
        }
    ],
    "sg:phone":"+1 423 378 3884",
    "sg:postcode":"37660",
    "sg:province":"TN",
    "sg:tags":[
        "shop"
    ],
    "wof:name":"Stylz By Marti",
    "wof:placetype":"venue"
},
  "geometry": {"coordinates":[-82.623957,36.560023],"type":"Point"}
}