{
  "type": "Feature",
  "properties": {
    "addr:full":"129 Lakeshire Dr Crossville TN 38558",
    "addr:housenumber":"129",
    "addr:postcode":"38558",
    "addr:street":"Lakeshire Dr",
    "iso:country":"US",
    "sg:address":"129 Lakeshire Dr",
    "sg:city":"Crossville",
    "sg:classifiers":[
        {
            "category":"Organizations",
            "subcategory":"Religious Organization",
            "type":"Services"
        }
    ],
    "sg:phone":"+1 931 277 3111",
    "sg:postcode":"38558",
    "sg:province":"TN",
    "wof:name":"Cumberland Cnty Chrch Untd",
    "wof:placetype":"venue"
},
  "geometry": {"coordinates":[-84.90492399999999,35.985855],"type":"Point"}
}