{
  "type": "Feature",
  "properties": {
    "iso:country":"US",
    "sg:address":"2914 W End Ave",
    "sg:city":"Nashville",
    "sg:classifiers":[
        {
            "category":"Restaurant",
            "type":"Food & Drink"
        }
    ],
    "sg:phone":"+1 615 327 4772",
    "sg:postcode":"37203",
    "sg:province":"TN",
    "wof:name":"Obie's Pizza",
    "wof:placetype":"venue"
},
  "geometry": {"coordinates":[-86.81326799999999,36.144581],"type":"Point"}
}