{
  "type": "Feature",
  "properties": {
    "iso:country":"US",
    "sg:address":"1138 N Germantown Pkwy",
    "sg:city":"Cordova",
    "sg:classifiers":[
        {
            "category":"Personal",
            "subcategory":"Beauty Salon",
            "type":"Services"
        }
    ],
    "sg:phone":"+1 901 757 4600",
    "sg:postcode":"38016",
    "sg:province":"TN",
    "sg:website":"www.gouldsalons.com",
    "wof:name":"Gould's Day Spa & Salon",
    "wof:placetype":"venue"
},
  "geometry": {"coordinates":[-89.79531799999999,35.156074],"type":"Point"}
}