{
  "type": "Feature",
  "properties": {
    "iso:country":"US",
    "sg:address":"422 Bethlehem Church Rd",
    "sg:city":"Shelbyville",
    "sg:classifiers":[
        {
            "category":"Farming",
            "subcategory":"Farm",
            "type":"Manufacturing & Wholesale Goods"
        }
    ],
    "sg:phone":"+1 931 684 2578",
    "sg:postcode":"37160",
    "sg:province":"TN",
    "sg:tags":[
        "crop",
        "general"
    ],
    "wof:name":"Robert Kimbrell",
    "wof:placetype":"venue"
},
  "geometry": {"coordinates":[-86.574522,35.444612],"type":"Point"}
}