{
  "type": "Feature",
  "properties": {
    "iso:country":"US",
    "sg:address":"1013 Carden Dr",
    "sg:city":"Franklin",
    "sg:classifiers":[
        {
            "category":"Professional",
            "subcategory":"Computer Services",
            "type":"Services"
        }
    ],
    "sg:phone":"+1 615 591 9642",
    "sg:postcode":"37069",
    "sg:province":"TN",
    "sg:tags":[
        "related"
    ],
    "wof:name":"CL Carter Co LLC",
    "wof:placetype":"venue"
},
  "geometry": {"coordinates":[-86.899361,35.971364],"type":"Point"}
}