{
  "type": "Feature",
  "properties": {
    "iso:country":"US",
    "sg:address":"3231 6th Ave",
    "sg:city":"Chattanooga",
    "sg:classifiers":[
        {
            "category":"Retail",
            "subcategory":"Repair Shop",
            "type":"Services"
        }
    ],
    "sg:phone":"+1 423 698 3253",
    "sg:postcode":"37407",
    "sg:province":"TN",
    "sg:tags":[
        "appliance",
        "electrical"
    ],
    "wof:name":"T J Appliance Repair",
    "wof:placetype":"venue"
},
  "geometry": {"coordinates":[-85.284615,35.00426],"type":"Point"}
}