{
  "type": "Feature",
  "properties": {
    "iso:country":"US",
    "sg:address":"1131 Nashville Pike",
    "sg:city":"Gallatin",
    "sg:classifiers":[
        {
            "category":"Banks & Credit Unions",
            "subcategory":"Bank",
            "type":"Services"
        }
    ],
    "sg:phone":"+1 615 451 7001",
    "sg:postcode":"37066",
    "sg:province":"TN",
    "wof:name":"Fifth Third Bank",
    "wof:placetype":"venue"
},
  "geometry": {"coordinates":[-86.476805,36.374068],"type":"Point"}
}