{
  "type": "Feature",
  "properties": {
    "addr:full":"9231 Middlebrook Pike Knoxville TN 37931",
    "addr:housenumber":"9231",
    "addr:postcode":"37931",
    "addr:street":"Middlebrook Pike",
    "iso:country":"US",
    "sg:address":"9231 Middlebrook Pike",
    "sg:city":"Knoxville",
    "sg:classifiers":[
        {
            "category":"Real Estate",
            "subcategory":"Developer",
            "type":"Services"
        }
    ],
    "sg:phone":"+1 865 470 9393",
    "sg:postcode":"37931",
    "sg:province":"TN",
    "wof:name":"Epoch Projects Inc",
    "wof:placetype":"venue"
},
  "geometry": {"coordinates":[-84.09669,35.944343],"type":"Point"}
}