{
  "type": "Feature",
  "properties": {
    "iso:country":"US",
    "sg:address":"3080 W Lake Dr NW",
    "sg:city":"Cleveland",
    "sg:classifiers":[
        {
            "category":"Building & Trades",
            "subcategory":"Construction",
            "type":"Services"
        }
    ],
    "sg:phone":"+1 423 479 8414",
    "sg:postcode":"37312",
    "sg:province":"TN",
    "sg:tags":[
        "general",
        "contractor"
    ],
    "wof:name":"Greentree Construction Co",
    "wof:placetype":"venue"
},
  "geometry": {"coordinates":[-84.891216,35.199125],"type":"Point"}
}