{
  "type": "Feature",
  "properties": {
    "iso:country":"US",
    "sg:address":"2730 Colony Park Dr",
    "sg:city":"Memphis",
    "sg:classifiers":[
        {
            "category":"Personal",
            "subcategory":"Beauty Salon",
            "type":"Services"
        }
    ],
    "sg:phone":"+1 901 375 4211",
    "sg:postcode":"38118",
    "sg:province":"TN",
    "wof:name":"Advance Beauty Systems",
    "wof:placetype":"venue"
},
  "geometry": {"coordinates":[-89.92178699999999,35.073214],"type":"Point"}
}