{
  "type": "Feature",
  "properties": {
    "addr:full":"10015 E Andrew Johnson Hwy Limestone TN 37681",
    "addr:housenumber":"10015",
    "addr:postcode":"37681",
    "addr:street":"E Andrew Johnson Hwy",
    "iso:country":"US",
    "sg:address":"10015 E Andrew Johnson Hwy",
    "sg:city":"Limestone",
    "sg:classifiers":[
        {
            "category":"Retail",
            "subcategory":"Repair Shop",
            "type":"Services"
        }
    ],
    "sg:phone":"+1 423 257 3033",
    "sg:postcode":"37681",
    "sg:province":"TN",
    "sg:tags":[
        "farm",
        "equipment",
        "parts"
    ],
    "wof:name":"11 E Tractor Svc",
    "wof:placetype":"venue"
},
  "geometry": {"coordinates":[-82.67926,36.229772],"type":"Point"}
}