{
  "type": "Feature",
  "properties": {
    "iso:country":"US",
    "sg:address":"2315 Madison St",
    "sg:city":"Clarksville",
    "sg:classifiers":[
        {
            "category":"Health Services",
            "subcategory":"Optometrist",
            "type":"Services"
        }
    ],
    "sg:phone":"+1 931 645 6550",
    "sg:postcode":"37043",
    "sg:province":"TN",
    "wof:name":"Dorothy Thomason OD",
    "wof:placetype":"venue"
},
  "geometry": {"coordinates":[-87.273015,36.508553],"type":"Point"}
}