{
  "type": "Feature",
  "properties": {
    "addr:full":"7177 Lee Hwy Chattanooga TN 37421",
    "addr:housenumber":"7177",
    "addr:postcode":"37421",
    "addr:street":"Lee Hwy",
    "iso:country":"US",
    "sg:address":"7177 Lee Hwy",
    "sg:city":"Chattanooga",
    "sg:classifiers":[
        {
            "category":"Home & Garden",
            "subcategory":"Furniture",
            "type":"Retail Goods"
        }
    ],
    "sg:phone":"+1 423 899 6841",
    "sg:postcode":"37421",
    "sg:province":"TN",
    "sg:tags":[
        "mattress"
    ],
    "wof:name":"Murmaid Mattress Factory",
    "wof:placetype":"venue"
},
  "geometry": {"coordinates":[-85.15548099999999,35.049185],"type":"Point"}
}