{
  "type": "Feature",
  "properties": {
    "iso:country":"US",
    "sg:address":"4440 Malone Rd",
    "sg:city":"Memphis",
    "sg:classifiers":[
        {
            "category":"Freight",
            "type":"Transportation"
        }
    ],
    "sg:phone":"+1 901 794 3344",
    "sg:postcode":"38118",
    "sg:province":"TN",
    "sg:tags":[
        "broker",
        "trucking"
    ],
    "wof:name":"Alpha Logistics Inc",
    "wof:placetype":"venue"
},
  "geometry": {"coordinates":[-89.919329,35.028151],"type":"Point"}
}