{
  "type": "Feature",
  "properties": {
    "iso:country":"US",
    "sg:address":"1132 Water St",
    "sg:city":"Savannah",
    "sg:classifiers":[
        {
            "category":"Building & Trades",
            "subcategory":"Equipment Rental",
            "type":"Services"
        }
    ],
    "sg:phone":"+1 731 925 5542",
    "sg:postcode":"38372",
    "sg:province":"TN",
    "wof:name":"Rent-A-Center",
    "wof:placetype":"venue"
},
  "geometry": {"coordinates":[-88.24296,35.222688],"type":"Point"}
}