{
  "type": "Feature",
  "properties": {
    "iso:country":"US",
    "sg:address":"3300 Browns Mill Rd",
    "sg:city":"Johnson City",
    "sg:classifiers":[
        {
            "category":"Professional",
            "type":"Services"
        }
    ],
    "sg:phone":"+1 423 282 4841",
    "sg:postcode":"37604",
    "sg:province":"TN",
    "wof:name":"Story's Specialties Svc",
    "wof:placetype":"venue"
},
  "geometry": {"coordinates":[-82.402844,36.362204],"type":"Point"}
}