{
  "type": "Feature",
  "properties": {
    "iso:country":"US",
    "sg:address":"6217 Enterprise Dr",
    "sg:city":"Knoxville",
    "sg:classifiers":[
        {
            "category":"Restaurant",
            "type":"Food & Drink"
        }
    ],
    "sg:phone":"+1 865 693 2883",
    "sg:postcode":"37909",
    "sg:province":"TN",
    "sg:tags":[
        "eating"
    ],
    "wof:name":"Malt Beverage Media Service",
    "wof:placetype":"venue"
},
  "geometry": {"coordinates":[-84.022763,35.956623],"type":"Point"}
}