{
  "type": "Feature",
  "properties": {
    "iso:country":"US",
    "sg:address":"2220 Frayser Blvd",
    "sg:city":"Memphis",
    "sg:classifiers":[
        {
            "category":"Personal",
            "subcategory":"Beauty Salon",
            "type":"Services"
        }
    ],
    "sg:phone":"+1 901 358 9320",
    "sg:postcode":"38127",
    "sg:province":"TN",
    "wof:name":"Karla's Unique Designs Beauty",
    "wof:placetype":"venue"
},
  "geometry": {"coordinates":[-89.98669700000001,35.217154],"type":"Point"}
}