{
  "type": "Feature",
  "properties": {
    "iso:country":"US",
    "sg:address":"472 Simmons Branch Rd",
    "sg:city":"Centerville",
    "sg:classifiers":[
        {
            "category":"Wholesale",
            "subcategory":"Construction Materials",
            "type":"Manufacturing & Wholesale Goods"
        }
    ],
    "sg:phone":"+1 931 729 3400",
    "sg:postcode":"37033",
    "sg:province":"TN",
    "sg:tags":[
        "timberland",
        "company",
        "timber"
    ],
    "wof:name":"Quercus Forest Products",
    "wof:placetype":"venue"
},
  "geometry": {"coordinates":[-87.48956699999999,35.702009],"type":"Point"}
}