{
  "type": "Feature",
  "properties": {
    "iso:country":"US",
    "sg:address":"921 Beechwood Dr",
    "sg:city":"Kingsport",
    "sg:classifiers":[
        {
            "category":"Manufacturing",
            "subcategory":"Metals",
            "type":"Manufacturing & Wholesale Goods"
        }
    ],
    "sg:phone":"+1 423 239 5033",
    "sg:postcode":"37663",
    "sg:province":"TN",
    "sg:tags":[
        "small",
        "arms",
        "mfg"
    ],
    "wof:name":"Carrier Rifle Company",
    "wof:placetype":"venue"
},
  "geometry": {"coordinates":[-82.520376,36.472466],"type":"Point"}
}