{
  "type": "Feature",
  "properties": {
    "addr:full":"249 High St La Follette TN 37766",
    "addr:housenumber":"249",
    "addr:postcode":"37766",
    "addr:street":"High St",
    "iso:country":"US",
    "sg:address":"249 High St",
    "sg:city":"La Follette",
    "sg:classifiers":[
        {
            "category":"Professional",
            "type":"Services"
        }
    ],
    "sg:phone":"+1 423 562 1318",
    "sg:postcode":"37766",
    "sg:province":"TN",
    "wof:name":"Greg Vinsant",
    "wof:placetype":"venue"
},
  "geometry": {"coordinates":[-84.134463,36.376845],"type":"Point"}
}