{
  "type": "Feature",
  "properties": {
    "iso:country":"US",
    "sg:address":"13330 Hwy 125 S",
    "sg:city":"Bolivar",
    "sg:classifiers":[
        {
            "category":"Parking",
            "type":"Transportation"
        }
    ],
    "sg:phone":"+1 731 658 6371",
    "sg:postcode":"38008",
    "sg:province":"TN",
    "sg:tags":[
        "automobile",
        "repair"
    ],
    "wof:name":"S & H Garage",
    "wof:placetype":"venue"
},
  "geometry": {"coordinates":[-88.919258,35.180648],"type":"Point"}
}