{
  "type": "Feature",
  "properties": {
    "iso:country":"US",
    "sg:address":"9103 Garrison Dr",
    "sg:city":"Knoxville",
    "sg:classifiers":[
        {
            "category":"Retail",
            "subcategory":"Auto Repair",
            "type":"Services"
        }
    ],
    "sg:phone":"+1 865 691 9333",
    "sg:postcode":"37931",
    "sg:province":"TN",
    "sg:tags":[
        "body"
    ],
    "wof:name":"East Teneesse Hot Rod Parks",
    "wof:placetype":"venue"
},
  "geometry": {"coordinates":[-84.12192899999999,35.974213],"type":"Point"}
}