{
  "type": "Feature",
  "properties": {
    "addr:full":"1965 N Washington Ave Cookeville TN 38501",
    "addr:housenumber":"1965",
    "addr:postcode":"38501",
    "addr:street":"N Washington Ave",
    "iso:country":"US",
    "sg:address":"1965 N Washington Ave",
    "sg:city":"Cookeville",
    "sg:classifiers":[
        {
            "category":"Shopping",
            "subcategory":"Discount & Variety Stores",
            "type":"Retail Goods"
        },
        {
            "category":"Shopping",
            "subcategory":"Department Store",
            "type":"Retail Goods"
        }
    ],
    "sg:phone":"+1 931 526 1884",
    "sg:postcode":"38501",
    "sg:province":"TN",
    "sg:tags":[
        "shop"
    ],
    "wof:name":"Dollar General",
    "wof:placetype":"venue"
},
  "geometry": {"coordinates":[-85.496081,36.18671],"type":"Point"}
}