{
  "type": "Feature",
  "properties": {
    "iso:country":"US",
    "sg:address":"3333 Covington Pike",
    "sg:city":"Memphis",
    "sg:classifiers":[
        {
            "category":"Education",
            "subcategory":"School",
            "type":"Public Place"
        }
    ],
    "sg:phone":"+1 901 416 4312",
    "sg:postcode":"38128",
    "sg:province":"TN",
    "wof:name":"Craigmont High School",
    "wof:placetype":"venue"
},
  "geometry": {"coordinates":[-89.894419,35.216198],"type":"Point"}
}