{
  "type": "Feature",
  "properties": {
    "iso:country":"US",
    "sg:address":"204 Windover Rd",
    "sg:city":"Memphis",
    "sg:classifiers":[
        {
            "category":"Real Estate",
            "subcategory":"Real Estate Operator",
            "type":"Services"
        }
    ],
    "sg:phone":"+1 901 327 8861",
    "sg:postcode":"38111",
    "sg:province":"TN",
    "sg:tags":[
        "apartment"
    ],
    "wof:name":"Camellia-Magnolia Gardens Inc",
    "wof:placetype":"venue"
},
  "geometry": {"coordinates":[-89.944647,35.126288],"type":"Point"}
}