{
  "type": "Feature",
  "properties": {
    "iso:country":"US",
    "sg:address":"141 Parham Blvd",
    "sg:city":"Tullahoma",
    "sg:classifiers":[
        {
            "category":"Building & Trades",
            "subcategory":"Landscaping Services",
            "type":"Services"
        }
    ],
    "sg:phone":"+1 931 393 3744",
    "sg:postcode":"37388",
    "sg:province":"TN",
    "sg:tags":[
        "lawn",
        "maintenance",
        "grounds"
    ],
    "wof:name":"Southern Elegance Lawn Svc",
    "wof:placetype":"venue"
},
  "geometry": {"coordinates":[-86.182909,35.338164],"type":"Point"}
}