{
  "type": "Feature",
  "properties": {
    "iso:country":"US",
    "sg:address":"507 Betsy Pack Dr",
    "sg:city":"Jasper",
    "sg:classifiers":[
        {
            "category":"Health Services",
            "subcategory":"Doctor",
            "type":"Services"
        }
    ],
    "sg:phone":"+1 423 942 5508",
    "sg:postcode":"37347",
    "sg:province":"TN",
    "wof:name":"Louis R Filipelli DMD",
    "wof:placetype":"venue"
},
  "geometry": {"coordinates":[-85.62532299999999,35.077519],"type":"Point"}
}