{
  "type": "Feature",
  "properties": {
    "iso:country":"US",
    "sg:address":"2944 N Mall Rd",
    "sg:city":"Knoxville",
    "sg:classifiers":[
        {
            "category":"Shopping",
            "subcategory":"Stationery & Office Supplies",
            "type":"Retail Goods"
        }
    ],
    "sg:phone":"+1 865 525 8979",
    "sg:postcode":"37924",
    "sg:province":"TN",
    "wof:name":"Office Max",
    "wof:placetype":"venue"
},
  "geometry": {"coordinates":[-83.872804,36.031022],"type":"Point"}
}