{
  "type": "Feature",
  "properties": {
    "iso:country":"US",
    "sg:address":"3608 Meadowbrook Ave",
    "sg:city":"Nashville",
    "sg:classifiers":[
        {
            "category":"Real Estate",
            "subcategory":"Architect",
            "type":"Services"
        }
    ],
    "sg:phone":"+1 615 297 0120",
    "sg:postcode":"37205",
    "sg:province":"TN",
    "sg:tags":[
        "interior",
        "a",
        "architectural"
    ],
    "wof:name":"Overton Stnley D Jr Assoc Arch",
    "wof:placetype":"venue"
},
  "geometry": {"coordinates":[-86.827212,36.138267],"type":"Point"}
}