{
  "type": "Feature",
  "properties": {
    "addr:full":"193 Weldon Dr Martin TN 38237",
    "addr:housenumber":"193",
    "addr:postcode":"38237",
    "addr:street":"Weldon Dr",
    "iso:country":"US",
    "sg:address":"193 Weldon Dr",
    "sg:city":"Martin",
    "sg:classifiers":[
        {
            "category":"Insurance",
            "subcategory":"Life Insurance",
            "type":"Services"
        }
    ],
    "sg:phone":"+1 731 587 3033",
    "sg:postcode":"38237",
    "sg:province":"TN",
    "sg:tags":[
        "carrier"
    ],
    "wof:name":"Cary Insurance Services LLC",
    "wof:placetype":"venue"
},
  "geometry": {"coordinates":[-88.85626600000001,36.369122],"type":"Point"}
}