{
  "type": "Feature",
  "properties": {
    "iso:country":"US",
    "sg:address":"555 S Ocoee St",
    "sg:city":"Cleveland",
    "sg:classifiers":[
        {
            "category":"Government",
            "subcategory":"Fire Station",
            "type":"Public Place"
        }
    ],
    "sg:phone":"+1 423 559 3340",
    "sg:postcode":"37311",
    "sg:province":"TN",
    "sg:tags":[
        "department"
    ],
    "wof:name":"Fire Department",
    "wof:placetype":"venue"
},
  "geometry": {"coordinates":[-84.87898800000001,35.155593],"type":"Point"}
}