{
  "type": "Feature",
  "properties": {
    "addr:full":"390 Rock Bridge Rd Gallatin TN 37066",
    "addr:housenumber":"390",
    "addr:postcode":"37066",
    "addr:street":"Rock Bridge Rd",
    "iso:country":"US",
    "sg:address":"390 Rock Bridge Rd",
    "sg:city":"Gallatin",
    "sg:classifiers":[
        {
            "category":"Retail",
            "subcategory":"Auto Repair",
            "type":"Services"
        }
    ],
    "sg:phone":"+1 615 451 6777",
    "sg:postcode":"37066",
    "sg:province":"TN",
    "sg:tags":[
        "body",
        "automobile",
        "painting"
    ],
    "wof:name":"Ed's Auto Rebuilders",
    "wof:placetype":"venue"
},
  "geometry": {"coordinates":[-86.36172500000001,36.453731],"type":"Point"}
}