{
  "type": "Feature",
  "properties": {
    "addr:full":"504 Castlewood Trl Chattanooga TN 37421",
    "addr:housenumber":"504",
    "addr:postcode":"37421",
    "addr:street":"Castlewood Trl",
    "iso:country":"US",
    "sg:address":"504 Castlewood Trl",
    "sg:city":"Chattanooga",
    "sg:classifiers":[
        {
            "category":"Professional",
            "type":"Services"
        }
    ],
    "sg:phone":"+1 423 899 6185",
    "sg:postcode":"37421",
    "sg:province":"TN",
    "wof:name":"Pampered Chef",
    "wof:placetype":"venue"
},
  "geometry": {"coordinates":[-85.107073,35.013226],"type":"Point"}
}