{
  "type": "Feature",
  "properties": {
    "addr:full":"6320 Winchester Rd Memphis TN 38115",
    "addr:housenumber":"6320",
    "addr:postcode":"38115",
    "addr:street":"Winchester Rd",
    "iso:country":"US",
    "sg:address":"6320 Winchester Rd",
    "sg:city":"Memphis",
    "sg:classifiers":[
        {
            "category":"Shopping",
            "subcategory":"Department Store",
            "type":"Retail Goods"
        }
    ],
    "sg:phone":"+1 901 366 6261",
    "sg:postcode":"38115",
    "sg:province":"TN",
    "wof:name":"Da Bronx",
    "wof:placetype":"venue"
},
  "geometry": {"coordinates":[-89.85283,35.049728],"type":"Point"}
}