{
  "type": "Feature",
  "properties": {
    "addr:full":"4355 State Hwy 58 Chattanooga TN 37416",
    "addr:housenumber":"4355",
    "addr:postcode":"37416",
    "addr:street":"State Hwy 58",
    "iso:country":"US",
    "sg:address":"4355 State Hwy 58",
    "sg:city":"Chattanooga",
    "sg:classifiers":[
        {
            "category":"Health Services",
            "subcategory":"Doctor",
            "type":"Services"
        }
    ],
    "sg:phone":"+1 423 842 5260",
    "sg:postcode":"37416",
    "sg:province":"TN",
    "sg:tags":[
        "physician",
        "medical",
        "surgeon"
    ],
    "wof:name":"Joseph A Motto MD",
    "wof:placetype":"venue"
},
  "geometry": {"coordinates":[-85.202215,35.084172],"type":"Point"}
}