{
  "type": "Feature",
  "properties": {
    "iso:country":"US",
    "sg:address":"6910 Stroop Ln",
    "sg:city":"Smyrna",
    "sg:classifiers":[
        {
            "category":"Recreation",
            "type":"Entertainment"
        }
    ],
    "sg:phone":"+1 615 459 7676",
    "sg:postcode":"37129",
    "sg:province":"TN",
    "wof:name":"Hooptown",
    "wof:placetype":"venue"
},
  "geometry": {"coordinates":[-86.477341,35.936296],"type":"Point"}
}