{
  "type": "Feature",
  "properties": {
    "iso:country":"US",
    "sg:address":"943 Brynwood Dr",
    "sg:city":"Chattanooga",
    "sg:classifiers":[
        {
            "category":"Personal",
            "subcategory":"Beauty Salon",
            "type":"Services"
        }
    ],
    "sg:phone":"+1 423 870 2325",
    "sg:postcode":"37415",
    "sg:province":"TN",
    "wof:name":"Hair Plus Family Hair Stylist",
    "wof:placetype":"venue"
},
  "geometry": {"coordinates":[-85.26610700000001,35.120075],"type":"Point"}
}