{
  "type": "Feature",
  "properties": {
    "iso:country":"US",
    "sg:address":"5100 Poplar Ave",
    "sg:city":"Memphis",
    "sg:classifiers":[
        {
            "category":"Restaurant",
            "type":"Food & Drink"
        }
    ],
    "sg:phone":"+1 901 766 3600",
    "sg:postcode":"38117",
    "sg:province":"TN",
    "sg:tags":[
        "caterer"
    ],
    "wof:name":"Gate Gourmet Division-Americas",
    "wof:placetype":"venue"
},
  "geometry": {"coordinates":[-89.892369,35.111334],"type":"Point"}
}