{
  "type": "Feature",
  "properties": {
    "addr:full":"210 12th St South Pittsburg TN 37380",
    "addr:housenumber":"210",
    "addr:postcode":"37380",
    "addr:street":"12Th St",
    "iso:country":"US",
    "sg:address":"210 12th St",
    "sg:city":"South Pittsburg",
    "sg:classifiers":[
        {
            "category":"Health Services",
            "subcategory":"Doctor",
            "type":"Services"
        }
    ],
    "sg:phone":"+1 423 837 3366",
    "sg:postcode":"37380",
    "sg:province":"TN",
    "sg:tags":[
        "medical"
    ],
    "wof:name":"Omohundro Pain Clinic",
    "wof:placetype":"venue"
},
  "geometry": {"coordinates":[-85.714539,35.001054],"type":"Point"}
}