{
  "type": "Feature",
  "properties": {
    "addr:full":"3800 Tennessee Ave Chattanooga TN 37409",
    "addr:housenumber":"3800",
    "addr:postcode":"37409",
    "addr:street":"Tennessee Ave",
    "iso:country":"US",
    "sg:address":"3800 Tennessee Ave",
    "sg:city":"Chattanooga",
    "sg:classifiers":[
        {
            "category":"Deli",
            "type":"Food & Drink"
        }
    ],
    "sg:menulink":"http://www.allmenus.com/tn/chattanooga/126687-blimpie-subs--sandwiches/menu/",
    "sg:phone":"+1 423 825 0050",
    "sg:postcode":"37409",
    "sg:province":"TN",
    "sg:tags":[
        "wrap",
        "american",
        "sandwich"
    ],
    "wof:name":"Blimpie Subs & Sandwiches",
    "wof:placetype":"venue"
},
  "geometry": {"coordinates":[-85.32613000000001,35.009848],"type":"Point"}
}