{
  "type": "Feature",
  "properties": {
    "addr:full":"4661 Old Hickory Blvd Nashville TN 37218",
    "addr:housenumber":"4661",
    "addr:postcode":"37218",
    "addr:street":"Old Hickory Blvd",
    "iso:country":"US",
    "sg:address":"4661 Old Hickory Blvd",
    "sg:city":"Nashville",
    "sg:classifiers":[
        {
            "category":"Retail",
            "subcategory":"Repair Shop",
            "type":"Services"
        },
        {
            "category":"Building & Trades",
            "subcategory":"Construction",
            "type":"Services"
        }
    ],
    "sg:phone":"+1 615 349 5685",
    "sg:postcode":"37218",
    "sg:province":"TN",
    "sg:tags":[
        "home",
        "fix-it",
        "maintenance"
    ],
    "sg:website":"http://www.timbrownconst.net",
    "wof:name":"Tim Brown Home Repairs",
    "wof:placetype":"venue"
},
  "geometry": {"coordinates":[-86.929265,36.18427],"type":"Point"}
}