{
  "type": "Feature",
  "properties": {
    "addr:full":"5400 Poplar Ave Ste 310 Memphis TN 38119",
    "addr:housenumber":"5400",
    "addr:postcode":"38119",
    "addr:street":"Poplar Ave Ste 310",
    "iso:country":"US",
    "sg:address":"5400 Poplar Ave Ste 310",
    "sg:city":"Memphis",
    "sg:classifiers":[
        {
            "category":"Professional",
            "subcategory":"Business Services",
            "type":"Services"
        },
        {
            "category":"Banks & Credit Unions",
            "subcategory":"Investment Brokerage",
            "type":"Services"
        },
        {
            "category":"Banks & Credit Unions",
            "subcategory":"Bank",
            "type":"Services"
        },
        {
            "category":"Banks & Credit Unions",
            "subcategory":"Financial Services",
            "type":"Services"
        }
    ],
    "sg:phone":"+1 901 791 0313",
    "sg:postcode":"38119",
    "sg:province":"TN",
    "sg:tags":[
        "advisory",
        "planner",
        "broker",
        "management",
        "bond",
        "stock"
    ],
    "wof:name":"Raymond James",
    "wof:placetype":"venue"
},
  "geometry": {"coordinates":[-89.881828,35.106892],"type":"Point"}
}