{
  "type": "Feature",
  "properties": {
    "iso:country":"US",
    "sg:address":"644 Old Gainesboro Hwy",
    "sg:city":"Cookeville",
    "sg:classifiers":[
        {
            "category":"Autos & Motor Vehicles",
            "subcategory":"Automobile Sales",
            "type":"Retail Goods"
        }
    ],
    "sg:phone":"+1 931 268 0640",
    "sg:postcode":"38501",
    "sg:province":"TN",
    "sg:tags":[
        "used"
    ],
    "wof:name":"Ted Jones Auto Sales",
    "wof:placetype":"venue"
},
  "geometry": {"coordinates":[-85.60000700000001,36.236404],"type":"Point"}
}