{
  "type": "Feature",
  "properties": {
    "addr:full":"2819 N Clear Fork Rd Sevierville TN 37862",
    "addr:housenumber":"2819",
    "addr:postcode":"37862",
    "addr:street":"N Clear Fork Rd",
    "iso:country":"US",
    "sg:address":"2819 N Clear Fork Rd",
    "sg:city":"Sevierville",
    "sg:classifiers":[
        {
            "category":"Organizations",
            "subcategory":"Religious Organization",
            "type":"Services"
        }
    ],
    "sg:phone":"+1 865 453 5805",
    "sg:postcode":"37862",
    "sg:province":"TN",
    "wof:name":"Waldens Crk Missionry Baptist",
    "wof:placetype":"venue"
},
  "geometry": {"coordinates":[-83.659526,35.769621],"type":"Point"}
}