{
  "type": "Feature",
  "properties": {
    "iso:country":"US",
    "sg:address":"1901 Wartrace Pike",
    "sg:city":"Shelbyville",
    "sg:classifiers":[
        {
            "category":"Real Estate",
            "subcategory":"Real Estate Operator",
            "type":"Services"
        }
    ],
    "sg:phone":"+1 931 684 3868",
    "sg:postcode":"37160",
    "sg:province":"TN",
    "sg:tags":[
        "apartment"
    ],
    "wof:name":"Stonebrooke Apartments",
    "wof:placetype":"venue"
},
  "geometry": {"coordinates":[-86.426722,35.476468],"type":"Point"}
}