{
  "type": "Feature",
  "properties": {
    "iso:country":"US",
    "sg:address":"8530 N Ruggles Ferry Pike",
    "sg:city":"Strawberry Plns",
    "sg:classifiers":[
        {
            "category":"Sports & Exercise",
            "subcategory":"Golf",
            "type":"Entertainment"
        },
        {
            "category":"Recreation",
            "type":"Entertainment"
        }
    ],
    "sg:phone":"+1 865 932 4450",
    "sg:postcode":"37871",
    "sg:province":"TN",
    "sg:tags":[
        "course"
    ],
    "wof:name":"Ruggles Ferry Golf Club",
    "wof:placetype":"venue"
},
  "geometry": {"coordinates":[-83.75053200000001,36.041347],"type":"Point"}
}