{
  "type": "Feature",
  "properties": {
    "iso:country":"US",
    "sg:address":"1109 Sioux Ter",
    "sg:city":"Madison",
    "sg:classifiers":[
        {
            "category":"Building & Trades",
            "subcategory":"Cleaning & Sanitation",
            "type":"Services"
        }
    ],
    "sg:phone":"+1 615 860 9713",
    "sg:postcode":"37115",
    "sg:province":"TN",
    "sg:tags":[
        "maintenance"
    ],
    "wof:name":"Brass Elephant Maintenance",
    "wof:placetype":"venue"
},
  "geometry": {"coordinates":[-86.68104099999999,36.248012],"type":"Point"}
}