{
  "type": "Feature",
  "properties": {
    "addr:full":"2735 Charleston Rd Stanton TN 38069",
    "addr:housenumber":"2735",
    "addr:postcode":"38069",
    "addr:street":"Charleston Rd",
    "iso:country":"US",
    "sg:address":"2735 Charleston Rd",
    "sg:city":"Stanton",
    "sg:classifiers":[
        {
            "category":"Professional",
            "type":"Services"
        }
    ],
    "sg:phone":"+1 731 548 2054",
    "sg:postcode":"38069",
    "sg:province":"TN",
    "wof:name":"Joe Val Farmstables",
    "wof:placetype":"venue"
},
  "geometry": {"coordinates":[-89.445913,35.478251],"type":"Point"}
}