{
  "type": "Feature",
  "properties": {
    "iso:country":"US",
    "sg:address":"2508 Gardner Ln",
    "sg:city":"Nashville",
    "sg:classifiers":[
        {
            "category":"Building & Trades",
            "subcategory":"Construction",
            "type":"Services"
        }
    ],
    "sg:phone":"+1 615 228 0800",
    "sg:postcode":"37207",
    "sg:province":"TN",
    "sg:tags":[
        "home",
        "improvement"
    ],
    "wof:name":"Gray's Elecrtical & Hm Imprvmt",
    "wof:placetype":"venue"
},
  "geometry": {"coordinates":[-86.803861,36.215161],"type":"Point"}
}