{
  "type": "Feature",
  "properties": {
    "iso:country":"US",
    "sg:address":"2681 Juno - Bargerton Rd",
    "sg:city":"Lexington",
    "sg:classifiers":[
        {
            "category":"Building & Trades",
            "subcategory":"Electrical",
            "type":"Services"
        }
    ],
    "sg:phone":"+1 731 967 3239",
    "sg:postcode":"38351",
    "sg:province":"TN",
    "sg:tags":[
        "electric",
        "contractor"
    ],
    "wof:name":"Kovarik Electrical",
    "wof:placetype":"venue"
},
  "geometry": {"coordinates":[-88.520119,35.697576],"type":"Point"}
}