{
  "type": "Feature",
  "properties": {
    "addr:full":"10862 Highway 51 S Ste 6 Atoka TN 38004",
    "addr:housenumber":"10862",
    "addr:postcode":"38004",
    "addr:street":"Highway 51 S Ste 6",
    "iso:country":"US",
    "sg:address":"10862 Highway 51 S Ste 6",
    "sg:city":"Atoka",
    "sg:classifiers":[
        {
            "category":"Banks & Credit Unions",
            "subcategory":"Financial Services",
            "type":"Services"
        },
        {
            "category":"Real Estate",
            "subcategory":"Real Estate Services",
            "type":"Services"
        },
        {
            "category":"Real Estate",
            "subcategory":"Developer",
            "type":"Services"
        },
        {
            "category":"Real Estate",
            "subcategory":"Real Estate Agent",
            "type":"Services"
        }
    ],
    "sg:phone":"+1 901 837 3492",
    "sg:postcode":"38004",
    "sg:province":"TN",
    "sg:tags":[
        "buyer",
        "consultant",
        "loan",
        "commercial",
        "broker"
    ],
    "sg:website":"http://www.coldwellbanker.com",
    "wof:name":"Coldwell Banker",
    "wof:placetype":"venue"
},
  "geometry": {"coordinates":[-89.78180399999999,35.449523],"type":"Point"}
}