{
  "type": "Feature",
  "properties": {
    "iso:country":"US",
    "sg:address":"12312 Bluff Shore Dr",
    "sg:city":"Knoxville",
    "sg:classifiers":[
        {
            "category":"Communications",
            "subcategory":"Radio Station",
            "type":"Services"
        }
    ],
    "sg:phone":"+1 865 803 6633",
    "sg:postcode":"37922",
    "sg:province":"TN",
    "wof:name":"W O K I-FM",
    "wof:placetype":"venue"
},
  "geometry": {"coordinates":[-84.152102,35.797784],"type":"Point"}
}