{
  "type": "Feature",
  "properties": {
    "iso:country":"US",
    "sg:address":"5253 Lynchburg Rd",
    "sg:city":"Winchester",
    "sg:classifiers":[
        {
            "category":"Government",
            "subcategory":"Fire Station",
            "type":"Public Place"
        }
    ],
    "sg:phone":"+1 931 962 2006",
    "sg:postcode":"37398",
    "sg:province":"TN",
    "sg:tags":[
        "protection"
    ],
    "wof:name":"Broadview Volunteer Fire Dept",
    "wof:placetype":"venue"
},
  "geometry": {"coordinates":[-86.19327800000001,35.185229],"type":"Point"}
}