{
  "type": "Feature",
  "properties": {
    "addr:full":"1234 Owens Ln Dandridge TN 37725",
    "addr:housenumber":"1234",
    "addr:postcode":"37725",
    "addr:street":"Owens Ln",
    "iso:country":"US",
    "sg:address":"1234 Owens Ln",
    "sg:city":"Dandridge",
    "sg:classifiers":[
        {
            "category":"Autos & Motor Vehicles",
            "subcategory":"Automobile Sales",
            "type":"Retail Goods"
        }
    ],
    "sg:phone":"+1 865 397 4869",
    "sg:postcode":"37725",
    "sg:province":"TN",
    "sg:tags":[
        "used"
    ],
    "wof:name":"Layne S Auto Sales",
    "wof:placetype":"venue"
},
  "geometry": {"coordinates":[-83.410805,35.962322],"type":"Point"}
}