{
  "type": "Feature",
  "properties": {
    "addr:full":"7051 US Hwy 70 S Nashville TN 37221",
    "addr:housenumber":"7051",
    "addr:postcode":"37221",
    "addr:street":"Us Hwy 70 S",
    "iso:country":"US",
    "sg:address":"7051 US Hwy 70 S",
    "sg:city":"Nashville",
    "sg:classifiers":[
        {
            "category":"Professional",
            "subcategory":"Advertising",
            "type":"Services"
        },
        {
            "category":"Manufacturing",
            "subcategory":"Printing",
            "type":"Manufacturing & Wholesale Goods"
        }
    ],
    "sg:phone":"+1 615 662 9021",
    "sg:postcode":"37221",
    "sg:province":"TN",
    "sg:tags":[
        "postal",
        "mailing",
        "shipping",
        "business"
    ],
    "wof:name":"UPS Stores",
    "wof:placetype":"venue"
},
  "geometry": {"coordinates":[-86.917705,36.075455],"type":"Point"}
}