{
  "type": "Feature",
  "properties": {
    "addr:full":"104 N Greenwood St Lebanon TN 37087",
    "addr:housenumber":"104",
    "addr:postcode":"37087",
    "addr:street":"N Greenwood St",
    "iso:country":"US",
    "sg:address":"104 N Greenwood St",
    "sg:city":"Lebanon",
    "sg:classifiers":[
        {
            "category":"Personal",
            "subcategory":"Beauty Salon",
            "type":"Services"
        }
    ],
    "sg:phone":"+1 615 444 7477",
    "sg:postcode":"37087",
    "sg:province":"TN",
    "sg:tags":[
        "shop"
    ],
    "wof:name":"Machelle's Total Look",
    "wof:placetype":"venue"
},
  "geometry": {"coordinates":[-86.296009,36.210782],"type":"Point"}
}