{
  "type": "Feature",
  "properties": {
    "iso:country":"US",
    "sg:address":"112 Hyndsver Rd",
    "sg:city":"Martin",
    "sg:classifiers":[
        {
            "category":"Personal",
            "subcategory":"Beauty Salon",
            "type":"Services"
        }
    ],
    "sg:phone":"+1 731 587 9631",
    "sg:postcode":"38237",
    "sg:province":"TN",
    "wof:name":"Images Hair Studio",
    "wof:placetype":"venue"
},
  "geometry": {"coordinates":[-88.768564,36.370399],"type":"Point"}
}