{
  "type": "Feature",
  "properties": {
    "iso:country":"US",
    "sg:address":"3900 Tchulahoma Rd",
    "sg:city":"Memphis",
    "sg:classifiers":[
        {
            "category":"Social Services",
            "type":"Services"
        }
    ],
    "sg:phone":"+1 901 368 6448",
    "sg:postcode":"38118",
    "sg:province":"TN",
    "sg:tags":[
        "organization",
        "religious"
    ],
    "wof:name":"Healing Center",
    "wof:placetype":"venue"
},
  "geometry": {"coordinates":[-89.955546,35.039598],"type":"Point"}
}