{
  "type": "Feature",
  "properties": {
    "iso:country":"US",
    "sg:address":"113 Dellwood Dr",
    "sg:city":"Oliver Springs",
    "sg:classifiers":[
        {
            "category":"Professional",
            "subcategory":"Management & Consulting",
            "type":"Services"
        }
    ],
    "sg:phone":"+1 865 435 4005",
    "sg:postcode":"37840",
    "sg:province":"TN",
    "wof:name":"Lets Get Organized",
    "wof:placetype":"venue"
},
  "geometry": {"coordinates":[-84.333037,36.035303],"type":"Point"}
}