{
  "type": "Feature",
  "properties": {
    "iso:country":"US",
    "sg:address":"617 Potomac Pl",
    "sg:city":"Smyrna",
    "sg:classifiers":[
        {
            "category":"Real Estate",
            "subcategory":"Real Estate Services",
            "type":"Services"
        }
    ],
    "sg:phone":"+1 615 355 6225",
    "sg:postcode":"37167",
    "sg:province":"TN",
    "sg:tags":[
        "abstract",
        "title"
    ],
    "wof:name":"Fisher Title Services LLC",
    "wof:placetype":"venue"
},
  "geometry": {"coordinates":[-86.55767,35.977091],"type":"Point"}
}