{
  "type": "Feature",
  "properties": {
    "addr:full":"547 Womack Rd Bethpage TN 37022",
    "addr:housenumber":"547",
    "addr:postcode":"37022",
    "addr:street":"Womack Rd",
    "iso:country":"US",
    "sg:address":"547 Womack Rd",
    "sg:city":"Bethpage",
    "sg:classifiers":[
        {
            "category":"Professional",
            "subcategory":"Engineering",
            "type":"Services"
        }
    ],
    "sg:phone":"+1 615 888 3014",
    "sg:postcode":"37022",
    "sg:province":"TN",
    "wof:name":"New Creation Consulting Co",
    "wof:placetype":"venue"
},
  "geometry": {"coordinates":[-86.392555,36.518203],"type":"Point"}
}