{
  "type": "Feature",
  "properties": {
    "iso:country":"US",
    "sg:address":"3500 Alton Park Blvd",
    "sg:city":"Chattanooga",
    "sg:classifiers":[
        {
            "category":"Freight",
            "type":"Transportation"
        }
    ],
    "sg:phone":"+1 423 648 5355",
    "sg:postcode":"37410",
    "sg:province":"TN",
    "sg:tags":[
        "trucking"
    ],
    "wof:name":"S & H Trucking Inc",
    "wof:placetype":"venue"
},
  "geometry": {"coordinates":[-85.31725299999999,35.009525],"type":"Point"}
}