{
  "type": "Feature",
  "properties": {
    "iso:country":"US",
    "sg:address":"117 Williamsburg Ln",
    "sg:city":"Brownsville",
    "sg:phone":"+1 731 772 3873",
    "sg:postcode":"38012",
    "sg:province":"TN",
    "sg:tags":[
        "farm",
        "cotton"
    ],
    "wof:name":"Rick Turnage",
    "wof:placetype":"venue"
},
  "geometry": {"coordinates":[-89.274899,35.594723],"type":"Point"}
}