{
  "type": "Feature",
  "properties": {
    "addr:full":"1812 Cloverleaf Dr Nashville TN 37216",
    "addr:housenumber":"1812",
    "addr:postcode":"37216",
    "addr:street":"Cloverleaf Dr",
    "iso:country":"US",
    "sg:address":"1812 Cloverleaf Dr",
    "sg:city":"Nashville",
    "sg:classifiers":[
        {
            "category":"Professional",
            "subcategory":"Detective & Security Services",
            "type":"Services"
        },
        {
            "category":"Insurance",
            "subcategory":"Insurance Agent",
            "type":"Services"
        }
    ],
    "sg:phone":"+1 615 262 5727",
    "sg:postcode":"37216",
    "sg:province":"TN",
    "wof:name":"Search International Limited",
    "wof:placetype":"venue"
},
  "geometry": {"coordinates":[-86.712727,36.199083],"type":"Point"}
}