{
  "type": "Feature",
  "properties": {
    "iso:country":"US",
    "sg:address":"2119 E Broadway Ave",
    "sg:city":"Maryville",
    "sg:classifiers":[
        {
            "category":"Restaurant",
            "type":"Food & Drink"
        }
    ],
    "sg:phone":"+1 865 983 2111",
    "sg:postcode":"37804",
    "sg:province":"TN",
    "sg:tags":[
        "eating"
    ],
    "wof:name":"Major Phillys",
    "wof:placetype":"venue"
},
  "geometry": {"coordinates":[-83.951235,35.779158],"type":"Point"}
}