{
  "type": "Feature",
  "properties": {
    "iso:country":"US",
    "sg:address":"6432 Coconut Ridge Rd",
    "sg:city":"Smithville",
    "sg:classifiers":[
        {
            "category":"Health Services",
            "subcategory":"Doctor",
            "type":"Services"
        }
    ],
    "sg:phone":"+1 615 597 7252",
    "sg:postcode":"37166",
    "sg:province":"TN",
    "sg:tags":[
        "physician",
        "surgeon"
    ],
    "wof:name":"Jesse E Adams MD",
    "wof:placetype":"venue"
},
  "geometry": {"coordinates":[-85.80033899999999,35.991617],"type":"Point"}
}