{
  "type": "Feature",
  "properties": {
    "iso:country":"US",
    "sg:address":"111 Peach Rd",
    "sg:city":"Oak Ridge",
    "sg:classifiers":[
        {
            "category":"Food & Beverages",
            "subcategory":"Bakery",
            "type":"Retail Goods"
        }
    ],
    "sg:phone":"+1 865 483 7051",
    "sg:postcode":"37830",
    "sg:province":"TN",
    "wof:name":"Custom Cakes & Catering",
    "wof:placetype":"venue"
},
  "geometry": {"coordinates":[-84.258346,36.022051],"type":"Point"}
}