{
  "type": "Feature",
  "properties": {
    "addr:full":"8501 Macon Rd Cordova TN 38018",
    "addr:housenumber":"8501",
    "addr:postcode":"38018",
    "addr:street":"Macon Rd",
    "iso:country":"US",
    "sg:address":"8501 Macon Rd",
    "sg:city":"Cordova",
    "sg:classifiers":[
        {
            "category":"Personal",
            "subcategory":"Beauty Salon",
            "type":"Services"
        }
    ],
    "sg:phone":"+1 901 757 2100",
    "sg:postcode":"38018",
    "sg:province":"TN",
    "sg:tags":[
        "shop"
    ],
    "wof:name":"Fancy Fingers",
    "wof:placetype":"venue"
},
  "geometry": {"coordinates":[-89.779233,35.155846],"type":"Point"}
}