{
  "type": "Feature",
  "properties": {
    "iso:country":"US",
    "sg:address":"425 Raintree Pl",
    "sg:city":"Hermitage",
    "sg:classifiers":[
        {
            "category":"Professional",
            "subcategory":"Lawyer & Legal Services",
            "type":"Services"
        }
    ],
    "sg:phone":"+1 615 874 2688",
    "sg:postcode":"37076",
    "sg:province":"TN",
    "wof:name":"Hare Nchlas D Attorney At Law",
    "wof:placetype":"venue"
},
  "geometry": {"coordinates":[-86.602707,36.177448],"type":"Point"}
}