{
  "type": "Feature",
  "properties": {
    "iso:country":"US",
    "sg:address":"101 Holland Ave",
    "sg:city":"Jackson",
    "sg:classifiers":[
        {
            "category":"Social Services",
            "subcategory":"Child Care",
            "type":"Services"
        }
    ],
    "sg:phone":"+1 731 265 0436",
    "sg:postcode":"38301",
    "sg:province":"TN",
    "wof:name":"Evelyn's Learning Ctr-Day Care",
    "wof:placetype":"venue"
},
  "geometry": {"coordinates":[-88.79297099999999,35.614191],"type":"Point"}
}