{
  "type": "Feature",
  "properties": {
    "iso:country":"US",
    "sg:address":"658 Sneed Rd",
    "sg:city":"Soddy Daisy",
    "sg:classifiers":[
        {
            "category":"Building & Trades",
            "subcategory":"Construction",
            "type":"Services"
        }
    ],
    "sg:phone":"+1 423 332 8707",
    "sg:postcode":"37379",
    "sg:province":"TN",
    "sg:tags":[
        "house"
    ],
    "wof:name":"H&E Constrn Inc",
    "wof:placetype":"venue"
},
  "geometry": {"coordinates":[-85.168237,35.244001],"type":"Point"}
}