{
  "type": "Feature",
  "properties": {
    "iso:country":"US",
    "sg:address":"185 Vines Dr",
    "sg:city":"Jonesborough",
    "sg:classifiers":[
        {
            "category":"Building & Trades",
            "subcategory":"Construction",
            "type":"Services"
        }
    ],
    "sg:phone":"+1 423 753 6291",
    "sg:postcode":"37659",
    "sg:province":"TN",
    "sg:tags":[
        "house"
    ],
    "wof:name":"Mountain Leisure Co",
    "wof:placetype":"venue"
},
  "geometry": {"coordinates":[-82.456124,36.297394],"type":"Point"}
}