{
  "type": "Feature",
  "properties": {
    "addr:full":"13424 Chapman Hwy Seymour TN 37865",
    "addr:housenumber":"13424",
    "addr:postcode":"37865",
    "addr:street":"Chapman Hwy",
    "iso:country":"US",
    "sg:address":"13424 Chapman Hwy",
    "sg:city":"Seymour",
    "sg:classifiers":[
        {
            "category":"Personal",
            "subcategory":"Barber",
            "type":"Services"
        }
    ],
    "sg:phone":"+1 865 429 5995",
    "sg:postcode":"37865",
    "sg:province":"TN",
    "wof:name":"Sharps Barber Shop",
    "wof:placetype":"venue"
},
  "geometry": {"coordinates":[-83.677018,35.859582],"type":"Point"}
}