{
  "type": "Feature",
  "properties": {
    "iso:country":"US",
    "sg:address":"813 Lynn Garden Dr",
    "sg:city":"Kingsport",
    "sg:classifiers":[
        {
            "category":"Restaurant",
            "type":"Food & Drink"
        }
    ],
    "sg:menulink":"http://www.allmenus.com/tn/kingsport/176831-kfc---kentucky-fried-chicken/menu/",
    "sg:phone":"+1 423 245 4455",
    "sg:postcode":"37660",
    "sg:province":"TN",
    "sg:tags":[
        "american",
        "chicken"
    ],
    "wof:name":"KFC - Kentucky Fried Chicken",
    "wof:placetype":"venue"
},
  "geometry": {"coordinates":[-82.56486599999999,36.564132],"type":"Point"}
}