{
  "type": "Feature",
  "properties": {
    "addr:full":"213 Overlook Ct Brentwood TN 37027",
    "addr:housenumber":"213",
    "addr:postcode":"37027",
    "addr:street":"Overlook Ct",
    "iso:country":"US",
    "sg:address":"213 Overlook Ct",
    "sg:city":"Brentwood",
    "sg:classifiers":[
        {
            "category":"Health Services",
            "subcategory":"Doctor",
            "type":"Services"
        }
    ],
    "sg:phone":"+1 615 370 9486",
    "sg:postcode":"37027",
    "sg:province":"TN",
    "sg:tags":[
        "dentist"
    ],
    "wof:name":"Michael A Skinner DDS",
    "wof:placetype":"venue"
},
  "geometry": {"coordinates":[-86.776714,36.031014],"type":"Point"}
}