{
  "type": "Feature",
  "properties": {
    "iso:country":"US",
    "sg:address":"6872 Smithville Hwy",
    "sg:city":"Baxter",
    "sg:classifiers":[
        {
            "category":"Real Estate",
            "subcategory":"Real Estate Agent",
            "type":"Services"
        }
    ],
    "sg:phone":"+1 931 858 6258",
    "sg:postcode":"38583",
    "sg:province":"TN",
    "wof:name":"Center Hill Realty",
    "wof:placetype":"venue"
},
  "geometry": {"coordinates":[-85.599907,35.958512],"type":"Point"}
}