{
  "type": "Feature",
  "properties": {
    "addr:full":"2353 Gene Fitzgerald Rd Columbia TN 38401",
    "addr:housenumber":"2353",
    "addr:postcode":"38401",
    "addr:street":"Gene Fitzgerald Rd",
    "iso:country":"US",
    "sg:address":"2353 Gene Fitzgerald Rd",
    "sg:city":"Columbia",
    "sg:classifiers":[
        {
            "category":"Retail",
            "subcategory":"Car Wash",
            "type":"Services"
        }
    ],
    "sg:phone":"+1 931 381 7395",
    "sg:postcode":"38401",
    "sg:province":"TN",
    "sg:tags":[
        "polishing",
        "washing"
    ],
    "wof:name":"B & J Car Cleanup",
    "wof:placetype":"venue"
},
  "geometry": {"coordinates":[-87.063514,35.719498],"type":"Point"}
}