{
  "type": "Feature",
  "properties": {
    "iso:country":"US",
    "sg:address":"95 White Bridge Pike",
    "sg:city":"Nashville",
    "sg:classifiers":[
        {
            "category":"Professional",
            "subcategory":"Computer Services",
            "type":"Services"
        }
    ],
    "sg:phone":"+1 615 353 4838",
    "sg:postcode":"37205",
    "sg:province":"TN",
    "sg:tags":[
        "design",
        "system"
    ],
    "wof:name":"Lionzone",
    "wof:placetype":"venue"
},
  "geometry": {"coordinates":[-86.857643,36.131843],"type":"Point"}
}