{
  "type": "Feature",
  "properties": {
    "addr:full":"1236 Red Binkley Rd Joelton TN 37080",
    "addr:housenumber":"1236",
    "addr:postcode":"37080",
    "addr:street":"Red Binkley Rd",
    "iso:country":"US",
    "sg:address":"1236 Red Binkley Rd",
    "sg:city":"Joelton",
    "sg:classifiers":[
        {
            "category":"Professional",
            "subcategory":"Business Services",
            "type":"Services"
        }
    ],
    "sg:phone":"+1 615 299 9441",
    "sg:postcode":"37080",
    "sg:province":"TN",
    "wof:name":"Ryan Home Inspections",
    "wof:placetype":"venue"
},
  "geometry": {"coordinates":[-86.966222,36.350451],"type":"Point"}
}