{
  "type": "Feature",
  "properties": {
    "addr:full":"356 New Byhalia Rd Collierville TN 38017",
    "addr:housenumber":"356",
    "addr:postcode":"38017",
    "addr:street":"New Byhalia Rd",
    "iso:country":"US",
    "sg:address":"356 New Byhalia Rd",
    "sg:city":"Collierville",
    "sg:classifiers":[
        {
            "category":"Professional",
            "subcategory":"Lawyer & Legal Services",
            "type":"Services"
        }
    ],
    "sg:phone":"+1 901 853 0921",
    "sg:postcode":"38017",
    "sg:province":"TN",
    "sg:tags":[
        "attorney"
    ],
    "wof:name":"Hagan & Patterson",
    "wof:placetype":"venue"
},
  "geometry": {"coordinates":[-89.68782,35.050505],"type":"Point"}
}