{
  "type": "Feature",
  "properties": {
    "iso:country":"US",
    "sg:address":"437 Essex Park Cir",
    "sg:city":"Franklin",
    "sg:classifiers":[
        {
            "category":"Insurance",
            "subcategory":"Insurance Agent",
            "type":"Services"
        }
    ],
    "sg:phone":"+1 615 599 4987",
    "sg:postcode":"37069",
    "sg:province":"TN",
    "wof:name":"Spectrum Underwriting Services",
    "wof:placetype":"venue"
},
  "geometry": {"coordinates":[-86.897372,35.96419],"type":"Point"}
}