{
  "type": "Feature",
  "properties": {
    "addr:full":"3365 Waterlevel Hwy Cleveland TN 37323",
    "addr:housenumber":"3365",
    "addr:postcode":"37323",
    "addr:street":"Waterlevel Hwy",
    "iso:country":"US",
    "sg:address":"3365 Waterlevel Hwy",
    "sg:city":"Cleveland",
    "sg:classifiers":[
        {
            "category":"Shopping",
            "type":"Retail Goods"
        }
    ],
    "sg:phone":"+1 423 559 8844",
    "sg:postcode":"37323",
    "sg:province":"TN",
    "sg:tags":[
        "merchandise"
    ],
    "wof:name":"John Sanders Auction Co",
    "wof:placetype":"venue"
},
  "geometry": {"coordinates":[-84.83813499999999,35.147653],"type":"Point"}
}