{
  "type": "Feature",
  "properties": {
    "iso:country":"US",
    "sg:address":"1757 Daxa Way",
    "sg:city":"Sevierville",
    "sg:classifiers":[
        {
            "category":"Building & Trades",
            "subcategory":"Construction",
            "type":"Services"
        }
    ],
    "sg:phone":"+1 865 908 5525",
    "sg:postcode":"37876",
    "sg:province":"TN",
    "wof:name":"Packs Block Work",
    "wof:placetype":"venue"
},
  "geometry": {"coordinates":[-83.362672,35.823616],"type":"Point"}
}