{
  "type": "Feature",
  "properties": {
    "addr:full":"24 Campground Rd Manchester TN 37355",
    "addr:housenumber":"24",
    "addr:postcode":"37355",
    "addr:street":"Campground Rd",
    "iso:country":"US",
    "sg:address":"24 Campground Rd",
    "sg:city":"Manchester",
    "sg:classifiers":[
        {
            "category":"Travel",
            "subcategory":"Travel Agent",
            "type":"Entertainment"
        }
    ],
    "sg:phone":"+1 931 723 1323",
    "sg:postcode":"37355",
    "sg:province":"TN",
    "sg:tags":[
        "operator",
        "tour"
    ],
    "wof:name":"Arrowheads/Aerospace Museums",
    "wof:placetype":"venue"
},
  "geometry": {"coordinates":[-86.04856599999999,35.456602],"type":"Point"}
}