{
  "type": "Feature",
  "properties": {
    "iso:country":"US",
    "sg:address":"7735 Farmington Blvd",
    "sg:city":"Germantown",
    "sg:classifiers":[
        {
            "category":"Banks & Credit Unions",
            "subcategory":"Bank",
            "type":"Services"
        }
    ],
    "sg:phone":"+1 901 753 1042",
    "sg:postcode":"38138",
    "sg:province":"TN",
    "wof:name":"First Tennessee Bank",
    "wof:placetype":"venue"
},
  "geometry": {"coordinates":[-89.80553999999999,35.095335],"type":"Point"}
}