{
  "type": "Feature",
  "properties": {
    "iso:country":"US",
    "sg:address":"1231 Saxon Dr",
    "sg:city":"Nashville",
    "sg:classifiers":[
        {
            "category":"Manufacturing",
            "subcategory":"Metals",
            "type":"Manufacturing & Wholesale Goods"
        }
    ],
    "sg:phone":"+1 615 373 8940",
    "sg:postcode":"37215",
    "sg:province":"TN",
    "sg:tags":[
        "industrial",
        "valve",
        "mfg"
    ],
    "wof:name":"Automatic Switch Company Inc",
    "wof:placetype":"venue"
},
  "geometry": {"coordinates":[-86.813042,36.074227],"type":"Point"}
}