{
  "type": "Feature",
  "properties": {
    "iso:country":"US",
    "sg:address":"1303 Hixson Ave",
    "sg:city":"Hixson",
    "sg:classifiers":[
        {
            "category":"Professional",
            "type":"Services"
        }
    ],
    "sg:phone":"+1 423 756 0102",
    "sg:postcode":"37343",
    "sg:province":"TN",
    "wof:name":"Stephen A Eady General Contrac",
    "wof:placetype":"venue"
},
  "geometry": {"coordinates":[-85.259111,35.130862],"type":"Point"}
}