{
  "type": "Feature",
  "properties": {
    "iso:country":"US",
    "sg:address":"162 Yoshino Dr",
    "sg:city":"Jackson",
    "sg:classifiers":[
        {
            "category":"Insurance",
            "subcategory":"Insurance Agent",
            "type":"Services"
        }
    ],
    "sg:phone":"+1 731 423 1083",
    "sg:postcode":"38301",
    "sg:province":"TN",
    "wof:name":"Roe & Roe",
    "wof:placetype":"venue"
},
  "geometry": {"coordinates":[-88.84267199999999,35.557113],"type":"Point"}
}