{
  "type": "Feature",
  "properties": {
    "iso:country":"US",
    "sg:address":"375 S Main St",
    "sg:city":"Middleton",
    "sg:classifiers":[
        {
            "category":"Real Estate",
            "subcategory":"Real Estate Agent",
            "type":"Services"
        }
    ],
    "sg:phone":"+1 731 376 8033",
    "sg:postcode":"38052",
    "sg:province":"TN",
    "wof:name":"Nutt Auction & Realty",
    "wof:placetype":"venue"
},
  "geometry": {"coordinates":[-88.892692,35.058601],"type":"Point"}
}