{
  "type": "Feature",
  "properties": {
    "iso:country":"US",
    "sg:address":"1212 Scottsville Rd",
    "sg:city":"Lafayette",
    "sg:classifiers":[
        {
            "category":"Shopping",
            "subcategory":"Discount & Variety Stores",
            "type":"Retail Goods"
        }
    ],
    "sg:phone":"+1 615 666 4529",
    "sg:postcode":"37083",
    "sg:province":"TN",
    "wof:name":"Market Street Variety",
    "wof:placetype":"venue"
},
  "geometry": {"coordinates":[-86.030078,36.53355],"type":"Point"}
}