{
  "type": "Feature",
  "properties": {
    "iso:country":"US",
    "sg:address":"2217 US Hwy 45W Byp",
    "sg:city":"Trenton",
    "sg:classifiers":[
        {
            "category":"Wholesale",
            "subcategory":"Machinery & Supplies",
            "type":"Manufacturing & Wholesale Goods"
        }
    ],
    "sg:phone":"+1 731 855 2232",
    "sg:postcode":"38382",
    "sg:province":"TN",
    "sg:tags":[
        "tractor"
    ],
    "wof:name":"Tri-County Farmer's Equipment",
    "wof:placetype":"venue"
},
  "geometry": {"coordinates":[-88.93693399999999,35.951672],"type":"Point"}
}