{
  "type": "Feature",
  "properties": {
    "iso:country":"US",
    "sg:address":"3710 Vulcan Dr",
    "sg:city":"Nashville",
    "sg:classifiers":[
        {
            "category":"Food & Beverages",
            "subcategory":"Liquor & Beverages",
            "type":"Retail Goods"
        }
    ],
    "sg:phone":"+1 615 833 3322",
    "sg:postcode":"37211",
    "sg:province":"TN",
    "sg:tags":[
        "wine"
    ],
    "sg:website":"www.tnwineandspirits.com",
    "wof:name":"Tennessee Wine & Spirits Co",
    "wof:placetype":"venue"
},
  "geometry": {"coordinates":[-86.74626000000001,36.0961],"type":"Point"}
}