{
  "type": "Feature",
  "properties": {
    "iso:country":"US",
    "sg:address":"732 Dixie Park Dr",
    "sg:city":"Cookeville",
    "sg:classifiers":[
        {
            "category":"Professional",
            "subcategory":"Engineering",
            "type":"Services"
        }
    ],
    "sg:phone":"+1 931 528 4295",
    "sg:postcode":"38501",
    "sg:province":"TN",
    "sg:tags":[
        "engineer"
    ],
    "wof:name":"Vantage Consulting Svc",
    "wof:placetype":"venue"
},
  "geometry": {"coordinates":[-85.503361,36.14795],"type":"Point"}
}