{
  "type": "Feature",
  "properties": {
    "iso:country":"US",
    "sg:address":"3715 Clarksville Pike",
    "sg:city":"Nashville",
    "sg:classifiers":[
        {
            "category":"Shopping",
            "subcategory":"Clothing, Apparel, & Fashions",
            "type":"Retail Goods"
        }
    ],
    "sg:phone":"+1 615 248 6119",
    "sg:postcode":"37218",
    "sg:province":"TN",
    "wof:name":"Simply Fashions",
    "wof:placetype":"venue"
},
  "geometry": {"coordinates":[-86.83787100000001,36.197987],"type":"Point"}
}