{
  "type": "Feature",
  "properties": {
    "iso:country":"US",
    "sg:address":"926 W Hills Dr",
    "sg:city":"Sweetwater",
    "sg:classifiers":[
        {
            "category":"Real Estate",
            "subcategory":"Real Estate Operator",
            "type":"Services"
        }
    ],
    "sg:phone":"+1 423 337 9048",
    "sg:postcode":"37874",
    "sg:province":"TN",
    "sg:tags":[
        "apartment"
    ],
    "wof:name":"West Hills Apartments",
    "wof:placetype":"venue"
},
  "geometry": {"coordinates":[-84.48255899999999,35.591174],"type":"Point"}
}