{
  "type": "Feature",
  "properties": {
    "iso:country":"US",
    "sg:address":"414 W Oakland Ave",
    "sg:city":"Johnson City",
    "sg:classifiers":[
        {
            "category":"Professional",
            "subcategory":"Accounting & Tax Preparation",
            "type":"Services"
        },
        {
            "category":"Banks & Credit Unions",
            "subcategory":"Bank",
            "type":"Services"
        }
    ],
    "sg:phone":"+1 423 928 4224",
    "sg:postcode":"37604",
    "sg:province":"TN",
    "sg:tags":[
        "depository",
        "banking",
        "return",
        "filing"
    ],
    "wof:name":"Southeastern Lending",
    "wof:placetype":"venue"
},
  "geometry": {"coordinates":[-82.389513,36.358989],"type":"Point"}
}