{
  "type": "Feature",
  "properties": {
    "addr:full":"321 Walton Ln Madison TN 37115",
    "addr:housenumber":"321",
    "addr:postcode":"37115",
    "addr:street":"Walton Ln",
    "iso:country":"US",
    "sg:address":"321 Walton Ln",
    "sg:city":"Madison",
    "sg:classifiers":[
        {
            "category":"Restaurant",
            "type":"Food & Drink"
        }
    ],
    "sg:phone":"+1 615 573 2979",
    "sg:postcode":"37115",
    "sg:province":"TN",
    "sg:tags":[
        "parlor",
        "ice",
        "cream"
    ],
    "wof:name":"Dee B's",
    "wof:placetype":"venue"
},
  "geometry": {"coordinates":[-86.73378,36.239621],"type":"Point"}
}