{
  "type": "Feature",
  "properties": {
    "iso:country":"US",
    "sg:address":"8525 Rancho Dr",
    "sg:city":"Ooltewah",
    "sg:classifiers":[
        {
            "category":"Building & Trades",
            "subcategory":"Construction",
            "type":"Services"
        }
    ],
    "sg:phone":"+1 423 238 5239",
    "sg:postcode":"37363",
    "sg:province":"TN",
    "sg:tags":[
        "pipeline",
        "maintenance"
    ],
    "wof:name":"Holmes Construction Co Inc",
    "wof:placetype":"venue"
},
  "geometry": {"coordinates":[-85.049396,35.114137],"type":"Point"}
}