{
  "type": "Feature",
  "properties": {
    "iso:country":"US",
    "sg:address":"2899 S Mendenhall Rd",
    "sg:city":"Memphis",
    "sg:classifiers":[
        {
            "category":"Wholesale",
            "subcategory":"Durable Goods & Equipment",
            "type":"Manufacturing & Wholesale Goods"
        }
    ],
    "sg:phone":"+1 901 795 5000",
    "sg:postcode":"38115",
    "sg:province":"TN",
    "sg:tags":[
        "instrument",
        "aircraft"
    ],
    "wof:name":"Gemini Aviation",
    "wof:placetype":"venue"
},
  "geometry": {"coordinates":[-89.885558,35.069804],"type":"Point"}
}