{
  "type": "Feature",
  "properties": {
    "iso:country":"US",
    "sg:address":"2158 Co Rd 750",
    "sg:city":"Calhoun",
    "sg:classifiers":[
        {
            "category":"Shopping",
            "subcategory":"Gifts & Souvenirs",
            "type":"Retail Goods"
        }
    ],
    "sg:phone":"+1 423 336 5867",
    "sg:postcode":"37309",
    "sg:province":"TN",
    "sg:tags":[
        "shop"
    ],
    "wof:name":"Sher Co",
    "wof:placetype":"venue"
},
  "geometry": {"coordinates":[-84.66118,35.274638],"type":"Point"}
}