{
  "type": "Feature",
  "properties": {
    "addr:full":"644 Alabama Ave Memphis TN 38105",
    "addr:housenumber":"644",
    "addr:postcode":"38105",
    "addr:street":"Alabama Ave",
    "iso:country":"US",
    "sg:address":"644 Alabama Ave",
    "sg:city":"Memphis",
    "sg:classifiers":[
        {
            "category":"Real Estate",
            "subcategory":"Real Estate Agent",
            "type":"Services"
        }
    ],
    "sg:phone":"+1 901 544 1236",
    "sg:postcode":"38105",
    "sg:province":"TN",
    "sg:tags":[
        "authorities",
        "housing"
    ],
    "wof:name":"Memphis Housing Authority",
    "wof:placetype":"venue"
},
  "geometry": {"coordinates":[-90.036433,35.147025],"type":"Point"}
}