{
  "type": "Feature",
  "properties": {
    "iso:country":"US",
    "sg:address":"6200 Poplar Ave",
    "sg:city":"Memphis",
    "sg:classifiers":[
        {
            "category":"Banks & Credit Unions",
            "subcategory":"Bank",
            "type":"Services"
        }
    ],
    "sg:phone":"+1 901 580 6000",
    "sg:postcode":"38119",
    "sg:province":"TN",
    "sg:tags":[
        "loan",
        "real estate"
    ],
    "sg:website":"www.regionsmortgage.com",
    "wof:name":"Regions Mortgage Inc",
    "wof:placetype":"venue"
},
  "geometry": {"coordinates":[-89.855813,35.101306],"type":"Point"}
}