{
  "type": "Feature",
  "properties": {
    "iso:country":"US",
    "sg:address":"126 W Jackson St",
    "sg:city":"Cookeville",
    "sg:classifiers":[
        {
            "category":"Health Services",
            "subcategory":"Chiropractor",
            "type":"Services"
        }
    ],
    "sg:phone":"+1 931 526 5311",
    "sg:postcode":"38501",
    "sg:province":"TN",
    "wof:name":"Atnip Chiropractic",
    "wof:placetype":"venue"
},
  "geometry": {"coordinates":[-85.510498,36.154203],"type":"Point"}
}