{
  "type": "Feature",
  "properties": {
    "iso:country":"US",
    "sg:address":"1819 Taft Hwy",
    "sg:city":"Signal Mountain",
    "sg:classifiers":[
        {
            "category":"Restaurant",
            "type":"Food & Drink"
        }
    ],
    "sg:phone":"+1 423 886 3400",
    "sg:postcode":"37377",
    "sg:province":"TN",
    "sg:tags":[
        "caterer"
    ],
    "wof:name":"Churches Cafe & Catering",
    "wof:placetype":"venue"
},
  "geometry": {"coordinates":[-85.31552499999999,35.158213],"type":"Point"}
}