{
  "type": "Feature",
  "properties": {
    "iso:country":"US",
    "sg:address":"1728 N Eastman Rd",
    "sg:city":"Kingsport",
    "sg:classifiers":[
        {
            "category":"Professional",
            "subcategory":"Detective & Security Services",
            "type":"Services"
        }
    ],
    "sg:phone":"+1 423 246 6035",
    "sg:postcode":"37664",
    "sg:province":"TN",
    "sg:tags":[
        "information",
        "bureau"
    ],
    "wof:name":"Advanced Bio Services",
    "wof:placetype":"venue"
},
  "geometry": {"coordinates":[-82.522881,36.540302],"type":"Point"}
}