{
  "type": "Feature",
  "properties": {
    "iso:country":"US",
    "sg:address":"459 Flintsprings Rd SE",
    "sg:city":"Cleveland",
    "sg:classifiers":[
        {
            "category":"Wholesale",
            "subcategory":"Medical Equipment & Supplies",
            "type":"Manufacturing & Wholesale Goods"
        }
    ],
    "sg:phone":"+1 423 472 4300",
    "sg:postcode":"37323",
    "sg:province":"TN",
    "sg:tags":[
        "physician",
        "surgeon"
    ],
    "wof:name":"Bradley DME",
    "wof:placetype":"venue"
},
  "geometry": {"coordinates":[-84.906795,35.027453],"type":"Point"}
}