{
  "type": "Feature",
  "properties": {
    "iso:country":"US",
    "sg:address":"3108 Elm Hill Pike",
    "sg:city":"Nashville",
    "sg:classifiers":[
        {
            "category":"Professional",
            "type":"Services"
        }
    ],
    "sg:phone":"+1 615 391 3806",
    "sg:postcode":"37214",
    "sg:province":"TN",
    "wof:name":"Changing Spaces",
    "wof:placetype":"venue"
},
  "geometry": {"coordinates":[-86.64061100000001,36.141913],"type":"Point"}
}