{
  "type": "Feature",
  "properties": {
    "addr:full":"743 E Gage Ave Memphis TN 38106",
    "addr:housenumber":"743",
    "addr:postcode":"38106",
    "addr:street":"E Gage Ave",
    "iso:country":"US",
    "sg:address":"743 E Gage Ave",
    "sg:city":"Memphis",
    "sg:classifiers":[
        {
            "category":"Shopping",
            "subcategory":"Clothing, Apparel, & Fashions",
            "type":"Retail Goods"
        }
    ],
    "sg:phone":"+1 901 942 0275",
    "sg:postcode":"38106",
    "sg:province":"TN",
    "sg:tags":[
        "family"
    ],
    "wof:name":"C&R Fashion",
    "wof:placetype":"venue"
},
  "geometry": {"coordinates":[-90.038477,35.087128],"type":"Point"}
}