{
  "type": "Feature",
  "properties": {
    "iso:country":"US",
    "sg:address":"199 Walnut St",
    "sg:city":"Collierville",
    "sg:classifiers":[
        {
            "category":"Government",
            "subcategory":"Office",
            "type":"Public Place"
        }
    ],
    "sg:phone":"+1 901 853 8069",
    "sg:postcode":"38017",
    "sg:province":"TN",
    "sg:tags":[
        "village"
    ],
    "wof:name":"Collierville Community Room",
    "wof:placetype":"venue"
},
  "geometry": {"coordinates":[-89.666635,35.044323],"type":"Point"}
}