{
  "type": "Feature",
  "properties": {
    "iso:country":"US",
    "sg:address":"272 Warehouse Rd",
    "sg:city":"Oak Ridge",
    "sg:classifiers":[
        {
            "category":"Retail",
            "subcategory":"Repair Shop",
            "type":"Services"
        }
    ],
    "sg:phone":"+1 865 220 8005",
    "sg:postcode":"37830",
    "sg:province":"TN",
    "sg:tags":[
        "welding"
    ],
    "wof:name":"Hammonds Welding Svc",
    "wof:placetype":"venue"
},
  "geometry": {"coordinates":[-84.215841,36.039584],"type":"Point"}
}