{
  "type": "Feature",
  "properties": {
    "iso:country":"US",
    "sg:address":"1002 Industrial Dr",
    "sg:city":"Old Hickory",
    "sg:classifiers":[
        {
            "category":"Education",
            "subcategory":"Special Training",
            "type":"Public Place"
        }
    ],
    "sg:phone":"+1 615 847 9893",
    "sg:postcode":"37138",
    "sg:province":"TN",
    "sg:tags":[
        "program"
    ],
    "wof:name":"Tennessee Valley Training Ctr",
    "wof:placetype":"venue"
},
  "geometry": {"coordinates":[-86.65705800000001,36.266057],"type":"Point"}
}