{
  "type": "Feature",
  "properties": {
    "iso:country":"US",
    "sg:address":"3536 Canada Rd",
    "sg:city":"Lakeland",
    "sg:classifiers":[
        {
            "category":"Shopping",
            "subcategory":"Clothing, Apparel, & Fashions",
            "type":"Retail Goods"
        }
    ],
    "sg:phone":"+1 901 385 0639",
    "sg:postcode":"38002",
    "sg:province":"TN",
    "sg:tags":[
        "furnishing"
    ],
    "wof:name":"Casual Male Big & Tall",
    "wof:placetype":"venue"
},
  "geometry": {"coordinates":[-89.73636399999999,35.222236],"type":"Point"}
}