{
  "type": "Feature",
  "properties": {
    "iso:country":"US",
    "sg:address":"432 New Middleton Hwy",
    "sg:city":"Gordonsville",
    "sg:classifiers":[
        {
            "category":"Freight",
            "type":"Transportation"
        }
    ],
    "sg:phone":"+1 615 683 8745",
    "sg:postcode":"38563",
    "sg:province":"TN",
    "sg:tags":[
        "operator",
        "local",
        "trucking"
    ],
    "wof:name":"CJ Trucking",
    "wof:placetype":"venue"
},
  "geometry": {"coordinates":[-85.993281,36.176242],"type":"Point"}
}