{
  "type": "Feature",
  "properties": {
    "iso:country":"US",
    "sg:address":"4117 E Emory Rd",
    "sg:city":"Knoxville",
    "sg:classifiers":[
        {
            "category":"Professional",
            "type":"Services"
        }
    ],
    "sg:phone":"+1 865 922 6580",
    "sg:postcode":"37938",
    "sg:province":"TN",
    "sg:tags":[
        "establishment"
    ],
    "wof:name":"SBP",
    "wof:placetype":"venue"
},
  "geometry": {"coordinates":[-83.930877,36.08528],"type":"Point"}
}