{
  "type": "Feature",
  "properties": {
    "addr:full":"1008 Maple Ave Lawrenceburg TN 38464",
    "addr:housenumber":"1008",
    "addr:postcode":"38464",
    "addr:street":"Maple Ave",
    "iso:country":"US",
    "sg:address":"1008 Maple Ave",
    "sg:city":"Lawrenceburg",
    "sg:classifiers":[
        {
            "category":"Real Estate",
            "subcategory":"Real Estate Agent",
            "type":"Services"
        }
    ],
    "sg:phone":"+1 931 766 1862",
    "sg:postcode":"38464",
    "sg:province":"TN",
    "sg:tags":[
        "authorities",
        "housing"
    ],
    "wof:name":"Lawrenceburg Housing Auth",
    "wof:placetype":"venue"
},
  "geometry": {"coordinates":[-87.338504,35.254281],"type":"Point"}
}