{
  "type": "Feature",
  "properties": {
    "iso:country":"US",
    "sg:address":"3145 Monterey Hwy",
    "sg:city":"Sparta",
    "sg:classifiers":[
        {
            "category":"Autos & Motor Vehicles",
            "subcategory":"Boat Sales",
            "type":"Retail Goods"
        }
    ],
    "sg:phone":"+1 931 498 4577",
    "sg:postcode":"38583",
    "sg:province":"TN",
    "sg:tags":[
        "dealer",
        "sales"
    ],
    "wof:name":"Poly Lift Boat Lifts",
    "wof:placetype":"venue"
},
  "geometry": {"coordinates":[-85.44064299999999,35.963177],"type":"Point"}
}