{
  "type": "Feature",
  "properties": {
    "addr:full":"800 Stonegate Rd Kingsport TN 37660",
    "addr:housenumber":"800",
    "addr:postcode":"37660",
    "addr:street":"Stonegate Rd",
    "iso:country":"US",
    "sg:address":"800 Stonegate Rd",
    "sg:city":"Kingsport",
    "sg:classifiers":[
        {
            "category":"Shopping",
            "subcategory":"Discount & Variety Stores",
            "type":"Retail Goods"
        }
    ],
    "sg:phone":"+1 423 247 5717",
    "sg:postcode":"37660",
    "sg:province":"TN",
    "wof:name":"Dollar Tree",
    "wof:placetype":"venue"
},
  "geometry": {"coordinates":[-82.578908,36.557936],"type":"Point"}
}