{
  "type": "Feature",
  "properties": {
    "addr:full":"806 Bruce Ave Dyersburg TN 38024",
    "addr:housenumber":"806",
    "addr:postcode":"38024",
    "addr:street":"Bruce Ave",
    "iso:country":"US",
    "sg:address":"806 Bruce Ave",
    "sg:city":"Dyersburg",
    "sg:classifiers":[
        {
            "category":"Organizations",
            "subcategory":"Religious Organization",
            "type":"Services"
        }
    ],
    "sg:phone":"+1 731 286 0676",
    "sg:postcode":"38024",
    "sg:province":"TN",
    "sg:tags":[
        "church"
    ],
    "wof:name":"Macedonia Church Of God",
    "wof:placetype":"venue"
},
  "geometry": {"coordinates":[-89.37747,36.025322],"type":"Point"}
}