{
  "type": "Feature",
  "properties": {
    "iso:country":"US",
    "sg:address":"1615 Brown Ave",
    "sg:city":"Cookeville",
    "sg:classifiers":[
        {
            "category":"Manufacturing",
            "subcategory":"Signs",
            "type":"Manufacturing & Wholesale Goods"
        }
    ],
    "sg:phone":"+1 931 526 4462",
    "sg:postcode":"38501",
    "sg:province":"TN",
    "wof:name":"Pro Sign & Graphic Design",
    "wof:placetype":"venue"
},
  "geometry": {"coordinates":[-85.48823899999999,36.184711],"type":"Point"}
}