{
  "type": "Feature",
  "properties": {
    "iso:country":"US",
    "sg:address":"330 Frazier Ave",
    "sg:city":"Chattanooga",
    "sg:classifiers":[
        {
            "category":"Sports & Exercise",
            "subcategory":"Gym",
            "type":"Entertainment"
        }
    ],
    "sg:phone":"+1 423 634 0320",
    "sg:postcode":"37405",
    "sg:province":"TN",
    "sg:tags":[
        "personal",
        "trainer"
    ],
    "wof:name":"Fitness Together Chattanooga",
    "wof:placetype":"venue"
},
  "geometry": {"coordinates":[-85.305626,35.062182],"type":"Point"}
}