{
  "type": "Feature",
  "properties": {
    "iso:country":"US",
    "sg:address":"4614 Highway 58",
    "sg:city":"Chattanooga",
    "sg:classifiers":[
        {
            "category":"Banks & Credit Unions",
            "subcategory":"Bank",
            "type":"Services"
        },
        {
            "category":"Banks & Credit Unions",
            "subcategory":"Financial Services",
            "type":"Services"
        }
    ],
    "sg:phone":"+1 423 892 5178",
    "sg:postcode":"37416",
    "sg:province":"TN",
    "sg:tags":[
        "loan",
        "financing"
    ],
    "sg:website":"http://www.SunTrust.com",
    "wof:name":"SunTrust Bank - Highway 58",
    "wof:placetype":"venue"
},
  "geometry": {"coordinates":[-85.193108,35.085724],"type":"Point"}
}