{
  "type": "Feature",
  "properties": {
    "addr:full":"154 Hot Wheels Ln Mc Minnville TN 37110",
    "addr:housenumber":"154",
    "addr:postcode":"37110",
    "addr:street":"Wheels Ln Mc Minnville",
    "iso:country":"US",
    "sg:address":"154 Hot Wheels Ln",
    "sg:city":"Mc Minnville",
    "sg:classifiers":[
        {
            "category":"Recreation",
            "type":"Entertainment"
        }
    ],
    "sg:phone":"+1 931 474 7655",
    "sg:postcode":"37110",
    "sg:province":"TN",
    "sg:tags":[
        "skating",
        "rink"
    ],
    "wof:name":"Hot Wheels Skate Ctr LLC",
    "wof:placetype":"venue"
},
  "geometry": {"coordinates":[-85.757454,35.689816],"type":"Point"}
}