{
  "type": "Feature",
  "properties": {
    "iso:country":"US",
    "sg:address":"107 Flex Ave",
    "sg:city":"Portland",
    "sg:classifiers":[
        {
            "category":"Manufacturing",
            "subcategory":"Wood Products",
            "type":"Manufacturing & Wholesale Goods"
        }
    ],
    "sg:phone":"+1 615 325 2353",
    "sg:postcode":"37148",
    "sg:province":"TN",
    "sg:tags":[
        "pallet",
        "skid"
    ],
    "sg:website":"www.portlandpallet.com",
    "wof:name":"Portland Pallet Co",
    "wof:placetype":"venue"
},
  "geometry": {"coordinates":[-86.50623299999999,36.563957],"type":"Point"}
}