{
  "type": "Feature",
  "properties": {
    "iso:country":"US",
    "sg:address":"6517 N Country Oaks Cir",
    "sg:city":"Memphis",
    "sg:classifiers":[
        {
            "category":"Professional",
            "type":"Services"
        }
    ],
    "sg:phone":"+1 901 542 9527",
    "sg:postcode":"38115",
    "sg:province":"TN",
    "wof:name":"Party Mixers",
    "wof:placetype":"venue"
},
  "geometry": {"coordinates":[-89.845837,35.04437],"type":"Point"}
}