{
  "type": "Feature",
  "properties": {
    "iso:country":"US",
    "sg:address":"699 S Mount Juliet Rd",
    "sg:city":"Mt Juliet",
    "sg:classifiers":[
        {
            "category":"Real Estate",
            "subcategory":"Real Estate Operator",
            "type":"Services"
        }
    ],
    "sg:phone":"+1 615 758 2219",
    "sg:postcode":"37122",
    "sg:province":"TN",
    "sg:tags":[
        "mobile",
        "home",
        "community"
    ],
    "wof:name":"Stonegate Manufactured Housing",
    "wof:placetype":"venue"
},
  "geometry": {"coordinates":[-86.515182,36.161303],"type":"Point"}
}