{
  "type": "Feature",
  "properties": {
    "iso:country":"US",
    "sg:address":"25 W 20th St",
    "sg:city":"Chattanooga",
    "sg:classifiers":[
        {
            "category":"Professional",
            "subcategory":"Employment Agencies",
            "type":"Services"
        }
    ],
    "sg:phone":"+1 423 752 8500",
    "sg:postcode":"37408",
    "sg:province":"TN",
    "sg:tags":[
        "help",
        "contractor"
    ],
    "wof:name":"One Force Staffing",
    "wof:placetype":"venue"
},
  "geometry": {"coordinates":[-85.309833,35.031891],"type":"Point"}
}