{
  "type": "Feature",
  "properties": {
    "addr:full":"330 Wilson Boat Dock Rd Lebanon TN 37087",
    "addr:housenumber":"330",
    "addr:postcode":"37087",
    "addr:street":"Wilson Boat Dock Rd",
    "iso:country":"US",
    "sg:address":"330 Wilson Boat Dock Rd",
    "sg:city":"Lebanon",
    "sg:classifiers":[
        {
            "category":"Organizations",
            "subcategory":"Religious Organization",
            "type":"Services"
        }
    ],
    "sg:phone":"+1 615 444 7872",
    "sg:postcode":"37087",
    "sg:province":"TN",
    "sg:tags":[
        "church"
    ],
    "wof:name":"LA Guardo Church Of Christ",
    "wof:placetype":"venue"
},
  "geometry": {"coordinates":[-86.368236,36.340217],"type":"Point"}
}