{
  "type": "Feature",
  "properties": {
    "addr:full":"8101 Sue Dr Ooltewah TN 37363",
    "addr:housenumber":"8101",
    "addr:postcode":"37363",
    "addr:street":"Sue Dr",
    "iso:country":"US",
    "sg:address":"8101 Sue Dr",
    "sg:city":"Ooltewah",
    "sg:classifiers":[
        {
            "category":"Real Estate",
            "subcategory":"Real Estate Operator",
            "type":"Services"
        }
    ],
    "sg:phone":"+1 423 899 0809",
    "sg:postcode":"37363",
    "sg:province":"TN",
    "sg:tags":[
        "mobile",
        "home",
        "site"
    ],
    "wof:name":"Ponderosa Pines",
    "wof:placetype":"venue"
},
  "geometry": {"coordinates":[-85.10820699999999,35.059097],"type":"Point"}
}