{
  "type": "Feature",
  "properties": {
    "iso:country":"US",
    "sg:address":"12 Garden St",
    "sg:city":"Nashville",
    "sg:classifiers":[
        {
            "category":"Food & Beverages",
            "subcategory":"Groceries & Convenience Stores",
            "type":"Retail Goods"
        }
    ],
    "sg:phone":"+1 615 568 8141",
    "sg:postcode":"37210",
    "sg:province":"TN",
    "wof:name":"Deborah's",
    "wof:placetype":"venue"
},
  "geometry": {"coordinates":[-86.760473,36.143257],"type":"Point"}
}