{
  "type": "Feature",
  "properties": {
    "addr:full":"775 Raider Dr Cleveland TN 37312",
    "addr:housenumber":"775",
    "addr:postcode":"37312",
    "addr:street":"Raider Dr",
    "iso:country":"US",
    "sg:address":"775 Raider Dr",
    "sg:city":"Cleveland",
    "sg:classifiers":[
        {
            "category":"Professional",
            "subcategory":"Management & Consulting",
            "type":"Services"
        }
    ],
    "sg:phone":"+1 423 476 2140",
    "sg:postcode":"37312",
    "sg:province":"TN",
    "wof:name":"Brenda McKenzie & Associates",
    "wof:placetype":"venue"
},
  "geometry": {"coordinates":[-84.86446599999999,35.191375],"type":"Point"}
}