{
  "type": "Feature",
  "properties": {
    "iso:country":"US",
    "sg:address":"323 Dog Tail Rd",
    "sg:city":"Shelbyville",
    "sg:classifiers":[
        {
            "category":"Building & Trades",
            "subcategory":"Plumbing",
            "type":"Services"
        }
    ],
    "sg:phone":"+1 931 680 0609",
    "sg:postcode":"37160",
    "sg:province":"TN",
    "sg:tags":[
        "contractor"
    ],
    "wof:name":"Reeses Htg & Air",
    "wof:placetype":"venue"
},
  "geometry": {"coordinates":[-86.384665,35.323977],"type":"Point"}
}