{
  "type": "Feature",
  "properties": {
    "iso:country":"US",
    "sg:address":"357 S Seven Oaks Dr",
    "sg:city":"Knoxville",
    "sg:classifiers":[
        {
            "category":"Real Estate",
            "subcategory":"Real Estate Agent",
            "type":"Services"
        }
    ],
    "sg:phone":"+1 865 693 5055",
    "sg:postcode":"37922",
    "sg:province":"TN",
    "sg:tags":[
        "building",
        "operator",
        "apartment"
    ],
    "wof:name":"Fountain Brook Apartments",
    "wof:placetype":"venue"
},
  "geometry": {"coordinates":[-84.09793000000001,35.90302],"type":"Point"}
}