{
  "type": "Feature",
  "properties": {
    "iso:country":"US",
    "sg:address":"2430 Curve Nankipoo Rd",
    "sg:city":"Ripley",
    "sg:classifiers":[
        {
            "category":"Building & Trades",
            "subcategory":"Plumbing",
            "type":"Services"
        }
    ],
    "sg:phone":"+1 731 635 0237",
    "sg:postcode":"38063",
    "sg:province":"TN",
    "sg:tags":[
        "conditioning",
        "air",
        "system",
        "contractor"
    ],
    "wof:name":"Crowders Heating Cooling",
    "wof:placetype":"venue"
},
  "geometry": {"coordinates":[-89.487145,35.826575],"type":"Point"}
}