{
  "type": "Feature",
  "properties": {
    "iso:country":"US",
    "sg:address":"324 S James St",
    "sg:city":"Morristown",
    "sg:classifiers":[
        {
            "category":"Government",
            "subcategory":"Fire Station",
            "type":"Public Place"
        }
    ],
    "sg:phone":"+1 423 586 0280",
    "sg:postcode":"37813",
    "sg:province":"TN",
    "sg:tags":[
        "protection"
    ],
    "wof:name":"Recreation Building",
    "wof:placetype":"venue"
},
  "geometry": {"coordinates":[-83.287345,36.213797],"type":"Point"}
}