{
  "type": "Feature",
  "properties": {
    "iso:country":"US",
    "sg:address":"214 Centerview Dr",
    "sg:city":"Brentwood",
    "sg:classifiers":[
        {
            "category":"Real Estate",
            "subcategory":"Real Estate Agent",
            "type":"Services"
        }
    ],
    "sg:phone":"+1 615 371 3503",
    "sg:postcode":"37027",
    "sg:province":"TN",
    "wof:name":"Pride Brokerage Svc",
    "wof:placetype":"venue"
},
  "geometry": {"coordinates":[-86.786991,36.030933],"type":"Point"}
}