{
  "type": "Feature",
  "properties": {
    "iso:country":"US",
    "sg:address":"4454 Canada Rd",
    "sg:city":"Lakeland",
    "sg:classifiers":[
        {
            "category":"Building & Trades",
            "subcategory":"Construction",
            "type":"Services"
        }
    ],
    "sg:phone":"+1 901 335 1819",
    "sg:postcode":"38002",
    "sg:province":"TN",
    "sg:tags":[
        "concrete",
        "contractor"
    ],
    "wof:name":"A Weymouth Construction Co",
    "wof:placetype":"venue"
},
  "geometry": {"coordinates":[-89.74435800000001,35.245528],"type":"Point"}
}