{
  "type": "Feature",
  "properties": {
    "iso:country":"US",
    "sg:address":"144 Vann Dr",
    "sg:city":"Jackson",
    "sg:classifiers":[
        {
            "category":"Organizations",
            "subcategory":"Religious Organization",
            "type":"Services"
        }
    ],
    "sg:phone":"+1 731 424 9525",
    "sg:postcode":"38305",
    "sg:province":"TN",
    "wof:name":"Pentecostals Of Jackson",
    "wof:placetype":"venue"
},
  "geometry": {"coordinates":[-88.835531,35.67074],"type":"Point"}
}