{
  "type": "Feature",
  "properties": {
    "iso:country":"US",
    "sg:address":"104 Woodmont Blvd",
    "sg:city":"Nashville",
    "sg:classifiers":[
        {
            "category":"Wholesale",
            "subcategory":"Durable Goods & Equipment",
            "type":"Manufacturing & Wholesale Goods"
        }
    ],
    "sg:phone":"+1 615 292 7880",
    "sg:postcode":"37205",
    "sg:province":"TN",
    "sg:tags":[
        "antique"
    ],
    "wof:name":"Richards Antiques & ACC",
    "wof:placetype":"venue"
},
  "geometry": {"coordinates":[-86.84646600000001,36.123935],"type":"Point"}
}