{
  "type": "Feature",
  "properties": {
    "iso:country":"US",
    "sg:address":"212 E Duffle St",
    "sg:city":"Waverly",
    "sg:classifiers":[
        {
            "category":"Building & Trades",
            "subcategory":"Construction",
            "type":"Services"
        }
    ],
    "sg:phone":"+1 931 296 1186",
    "sg:postcode":"37185",
    "sg:province":"TN",
    "sg:tags":[
        "house"
    ],
    "wof:name":"Virgil Cochran Construction Co",
    "wof:placetype":"venue"
},
  "geometry": {"coordinates":[-87.791855,36.084701],"type":"Point"}
}