{
  "type": "Feature",
  "properties": {
    "addr:full":"606 S Jefferson St Tullahoma TN 37388",
    "addr:housenumber":"606",
    "addr:postcode":"37388",
    "addr:street":"S Jefferson St",
    "iso:country":"US",
    "sg:address":"606 S Jefferson St",
    "sg:city":"Tullahoma",
    "sg:classifiers":[
        {
            "category":"Retail",
            "subcategory":"Auto Repair",
            "type":"Services"
        }
    ],
    "sg:phone":"+1 931 461 0207",
    "sg:postcode":"37388",
    "sg:province":"TN",
    "sg:tags":[
        "body",
        "automobile",
        "painting"
    ],
    "wof:name":"Rodney's Body Shop",
    "wof:placetype":"venue"
},
  "geometry": {"coordinates":[-86.207697,35.355032],"type":"Point"}
}