{
  "type": "Feature",
  "properties": {
    "addr:full":"832 W Mountcastle St Jefferson City TN 37760",
    "addr:housenumber":"832",
    "addr:postcode":"37760",
    "addr:street":"W Mountcastle St",
    "iso:country":"US",
    "sg:address":"832 W Mountcastle St",
    "sg:city":"Jefferson City",
    "sg:classifiers":[
        {
            "category":"Health Services",
            "subcategory":"Clinic",
            "type":"Services"
        }
    ],
    "sg:phone":"+1 865 471 0300",
    "sg:postcode":"37760",
    "sg:province":"TN",
    "sg:tags":[
        "home"
    ],
    "wof:name":"St Mary's Home Health Svc",
    "wof:placetype":"venue"
},
  "geometry": {"coordinates":[-83.500243,36.119172],"type":"Point"}
}