{
  "type": "Feature",
  "properties": {
    "iso:country":"US",
    "sg:address":"9050 Carothers Pkwy",
    "sg:city":"Franklin",
    "sg:classifiers":[
        {
            "category":"Personal",
            "subcategory":"Massage",
            "type":"Services"
        },
        {
            "category":"Personal",
            "subcategory":"Beauty Salon",
            "type":"Services"
        },
        {
            "category":"Personal",
            "subcategory":"Day Spa",
            "type":"Services"
        },
        {
            "category":"Personal",
            "subcategory":"Skin Care",
            "type":"Services"
        },
        {
            "category":"Personal",
            "subcategory":"Nail Salon",
            "type":"Services"
        }
    ],
    "sg:phone":"+1 615 224 0770",
    "sg:postcode":"37067",
    "sg:province":"TN",
    "sg:tags":[
        "hair",
        "make-up",
        "therapist",
        "stylist",
        "artist"
    ],
    "sg:website":"http://www.amomentspeace.com",
    "wof:name":"A Moments Peace",
    "wof:placetype":"venue"
},
  "geometry": {"coordinates":[-86.803021,35.956891],"type":"Point"}
}