{
  "type": "Feature",
  "properties": {
    "iso:country":"US",
    "sg:address":"12 S Hill St",
    "sg:city":"Coalmont",
    "sg:classifiers":[
        {
            "category":"Organizations",
            "subcategory":"Religious Organization",
            "type":"Services"
        }
    ],
    "sg:phone":"+1 931 592 7729",
    "sg:postcode":"37303",
    "sg:province":"TN",
    "sg:tags":[
        "church"
    ],
    "wof:name":"Sweeton Hill Church",
    "wof:placetype":"venue"
},
  "geometry": {"coordinates":[-84.595508,35.441289],"type":"Point"}
}