{
  "type": "Feature",
  "properties": {
    "iso:country":"US",
    "sg:address":"5112 Walnut Park Dr",
    "sg:city":"Brentwood",
    "sg:classifiers":[
        {
            "category":"Banks & Credit Unions",
            "subcategory":"Financial Services",
            "type":"Services"
        }
    ],
    "sg:phone":"+1 615 376 8903",
    "sg:postcode":"37027",
    "sg:province":"TN",
    "sg:tags":[
        "investor"
    ],
    "wof:name":"L & L Rashmir Properties",
    "wof:placetype":"venue"
},
  "geometry": {"coordinates":[-86.814043,36.006057],"type":"Point"}
}