{
  "type": "Feature",
  "properties": {
    "iso:country":"US",
    "sg:address":"1065 Fayne Rd",
    "sg:city":"Brighton",
    "sg:classifiers":[
        {
            "category":"Retail",
            "subcategory":"Laundry & Dry Cleaning",
            "type":"Services"
        }
    ],
    "sg:phone":"+1 901 476 1197",
    "sg:postcode":"38011",
    "sg:province":"TN",
    "sg:tags":[
        "cleaners",
        "rug",
        "carpet"
    ],
    "wof:name":"Smith Carpet Clng & Upholstery",
    "wof:placetype":"venue"
},
  "geometry": {"coordinates":[-89.71789099999999,35.456279],"type":"Point"}
}