{
  "type": "Feature",
  "properties": {
    "iso:country":"US",
    "sg:address":"905 Dunlap Orphanage Rd",
    "sg:city":"Brighton",
    "sg:classifiers":[
        {
            "category":"Freight",
            "type":"Transportation"
        }
    ],
    "sg:phone":"+1 901 475 1518",
    "sg:postcode":"38011",
    "sg:province":"TN",
    "sg:tags":[
        "operator",
        "local",
        "trucking"
    ],
    "wof:name":"M8m Delivery Inc",
    "wof:placetype":"venue"
},
  "geometry": {"coordinates":[-89.672127,35.416389],"type":"Point"}
}