{
  "type": "Feature",
  "properties": {
    "iso:country":"US",
    "sg:address":"310 Westfield Rd",
    "sg:city":"Knoxville",
    "sg:classifiers":[
        {
            "category":"Insurance",
            "subcategory":"Insurance Agent",
            "type":"Services"
        }
    ],
    "sg:phone":"+1 865 584 7898",
    "sg:postcode":"37919",
    "sg:province":"TN",
    "wof:name":"Dynamic Consultants",
    "wof:placetype":"venue"
},
  "geometry": {"coordinates":[-84.01324,35.933421],"type":"Point"}
}