{
  "type": "Feature",
  "properties": {
    "addr:full":"25 Tipton St S Munford TN 38058",
    "addr:housenumber":"25",
    "addr:postcode":"38058",
    "addr:street":"Tipton St S",
    "iso:country":"US",
    "sg:address":"25 Tipton St S",
    "sg:city":"Munford",
    "sg:classifiers":[
        {
            "category":"Organizations",
            "subcategory":"Religious Organization",
            "type":"Services"
        }
    ],
    "sg:phone":"+1 901 837 6721",
    "sg:postcode":"38058",
    "sg:province":"TN",
    "sg:tags":[
        "church"
    ],
    "wof:name":"Munford Presbyterian Church",
    "wof:placetype":"venue"
},
  "geometry": {"coordinates":[-89.815156,35.448231],"type":"Point"}
}