{
  "type": "Feature",
  "properties": {
    "addr:full":"1305 E Broadway Ave Maryville TN 37804",
    "addr:housenumber":"1305",
    "addr:postcode":"37804",
    "addr:street":"E Broadway Ave",
    "iso:country":"US",
    "sg:address":"1305 E Broadway Ave",
    "sg:city":"Maryville",
    "sg:classifiers":[
        {
            "category":"Shopping",
            "subcategory":"Used Merchandise",
            "type":"Retail Goods"
        }
    ],
    "sg:phone":"+1 865 980 3550",
    "sg:postcode":"37804",
    "sg:province":"TN",
    "sg:tags":[
        "pawnbroker"
    ],
    "wof:name":"Quick Cash",
    "wof:placetype":"venue"
},
  "geometry": {"coordinates":[-83.959913,35.766549],"type":"Point"}
}