{
  "type": "Feature",
  "properties": {
    "iso:country":"US",
    "sg:address":"1805 15th Ave S",
    "sg:city":"Nashville",
    "sg:classifiers":[
        {
            "category":"Professional",
            "subcategory":"Art Services",
            "type":"Services"
        }
    ],
    "sg:phone":"+1 615 414 3016",
    "sg:postcode":"37212",
    "sg:province":"TN",
    "sg:tags":[
        "photographer"
    ],
    "wof:name":"Young's Photo Design",
    "wof:placetype":"venue"
},
  "geometry": {"coordinates":[-86.79207700000001,36.1354],"type":"Point"}
}