{
  "type": "Feature",
  "properties": {
    "addr:full":"5451 Waddell Hollow Rd Franklin TN 37064",
    "addr:housenumber":"5451",
    "addr:postcode":"37064",
    "addr:street":"Waddell Hollow Rd",
    "iso:country":"US",
    "sg:address":"5451 Waddell Hollow Rd",
    "sg:city":"Franklin",
    "sg:classifiers":[
        {
            "category":"Building & Trades",
            "subcategory":"Construction",
            "type":"Services"
        }
    ],
    "sg:phone":"+1 615 599 7400",
    "sg:postcode":"37064",
    "sg:province":"TN",
    "sg:tags":[
        "house"
    ],
    "wof:name":"Maxwell Co LLC",
    "wof:placetype":"venue"
},
  "geometry": {"coordinates":[-86.968305,35.935533],"type":"Point"}
}