{
  "type": "Feature",
  "properties": {
    "addr:full":"1673 Council Bend Rd Centerville TN 37033",
    "addr:housenumber":"1673",
    "addr:postcode":"37033",
    "addr:street":"Council Bend Rd",
    "iso:country":"US",
    "sg:address":"1673 Council Bend Rd",
    "sg:city":"Centerville",
    "sg:classifiers":[
        {
            "category":"Building & Trades",
            "subcategory":"Plumbing",
            "type":"Services"
        }
    ],
    "sg:phone":"+1 931 729 4508",
    "sg:postcode":"37033",
    "sg:province":"TN",
    "sg:tags":[
        "contractor"
    ],
    "wof:name":"Cmt",
    "wof:placetype":"venue"
},
  "geometry": {"coordinates":[-87.530332,35.787663],"type":"Point"}
}