{
  "type": "Feature",
  "properties": {
    "iso:country":"US",
    "sg:address":"5423 NW Broad St",
    "sg:city":"Murfreesboro",
    "sg:classifiers":[
        {
            "category":"Autos & Motor Vehicles",
            "subcategory":"Automobile Sales",
            "type":"Retail Goods"
        }
    ],
    "sg:phone":"+1 615 890 5596",
    "sg:postcode":"37129",
    "sg:province":"TN",
    "sg:tags":[
        "car",
        "dealer"
    ],
    "wof:name":"Tri-Star Motors-Murfreesboro",
    "wof:placetype":"venue"
},
  "geometry": {"coordinates":[-86.44725,35.90083],"type":"Point"}
}