{
  "type": "Feature",
  "properties": {
    "addr:full":"305 Poplar View Pkwy Collierville Collierville TN 38017",
    "addr:housenumber":"305",
    "addr:postcode":"38017",
    "addr:street":"Poplar View Pkwy",
    "iso:country":"US",
    "sg:address":"305 Poplar View Pkwy Collierville",
    "sg:city":"Collierville",
    "sg:classifiers":[
        {
            "category":"Banks & Credit Unions",
            "subcategory":"Bank",
            "type":"Services"
        },
        {
            "category":"Banks & Credit Unions",
            "subcategory":"Financial Services",
            "type":"Services"
        }
    ],
    "sg:phone":"+1 901 853 4781",
    "sg:postcode":"38017",
    "sg:province":"TN",
    "sg:tags":[
        "loan",
        "mortgage"
    ],
    "sg:website":"http://www.trustmark.com",
    "wof:name":"Trustmark Bank",
    "wof:placetype":"venue"
},
  "geometry": {"coordinates":[-89.700485,35.048161],"type":"Point"}
}