{
  "type": "Feature",
  "properties": {
    "iso:country":"US",
    "sg:address":"18 Fountain Sq",
    "sg:city":"Crossville",
    "sg:classifiers":[
        {
            "category":"Home & Garden",
            "subcategory":"Household Appliances",
            "type":"Retail Goods"
        }
    ],
    "sg:phone":"+1 931 456 0180",
    "sg:postcode":"38555",
    "sg:province":"TN",
    "sg:tags":[
        "cleaners",
        "vacuum"
    ],
    "wof:name":"Crossville Vacuum & Sewing",
    "wof:placetype":"venue"
},
  "geometry": {"coordinates":[-85.037131,35.971769],"type":"Point"}
}