{
  "type": "Feature",
  "properties": {
    "addr:full":"1001 Gouge Rd Unicoi TN 37692",
    "addr:housenumber":"1001",
    "addr:postcode":"37692",
    "addr:street":"Gouge Rd",
    "iso:country":"US",
    "sg:address":"1001 Gouge Rd",
    "sg:city":"Unicoi",
    "sg:classifiers":[
        {
            "category":"Shopping",
            "subcategory":"Computers & Home Electronics",
            "type":"Retail Goods"
        }
    ],
    "sg:phone":"+1 423 735 7800",
    "sg:postcode":"37692",
    "sg:province":"TN",
    "sg:tags":[
        "high",
        "fidelity",
        "stereophonic"
    ],
    "wof:name":"Direct Audio & Customs",
    "wof:placetype":"venue"
},
  "geometry": {"coordinates":[-82.350055,36.205619],"type":"Point"}
}