{
  "type": "Feature",
  "properties": {
    "iso:country":"US",
    "sg:address":"424 Church St",
    "sg:city":"Nashville",
    "sg:classifiers":[
        {
            "category":"Banks & Credit Unions",
            "subcategory":"Investment Brokerage",
            "type":"Services"
        }
    ],
    "sg:phone":"+1 615 256 2556",
    "sg:postcode":"37203",
    "sg:province":"TN",
    "sg:tags":[
        "security"
    ],
    "wof:name":"Synthesis Advisors Inc",
    "wof:placetype":"venue"
},
  "geometry": {"coordinates":[-86.779298,36.163635],"type":"Point"}
}