{
  "type": "Feature",
  "properties": {
    "iso:country":"US",
    "sg:address":"2928 Saint Paul Rd",
    "sg:city":"Woodlawn",
    "sg:phone":"+1 931 648 9480",
    "sg:postcode":"37191",
    "sg:province":"TN",
    "sg:tags":[
        "farm",
        "tobacco"
    ],
    "wof:name":"Robert Jackson",
    "wof:placetype":"venue"
},
  "geometry": {"coordinates":[-87.589789,36.521771],"type":"Point"}
}