{
  "type": "Feature",
  "properties": {
    "iso:country":"US",
    "sg:address":"2876 Jarrell Ridge Rd",
    "sg:city":"Clarksville",
    "sg:classifiers":[
        {
            "category":"Shopping",
            "subcategory":"Bicycles & Sporting Goods",
            "type":"Retail Goods"
        }
    ],
    "sg:phone":"+1 931 362 4155",
    "sg:postcode":"37043",
    "sg:province":"TN",
    "sg:tags":[
        "skating",
        "equipment"
    ],
    "wof:name":"Realm Skateshop The",
    "wof:placetype":"venue"
},
  "geometry": {"coordinates":[-87.23912300000001,36.410691],"type":"Point"}
}