{
  "type": "Feature",
  "properties": {
    "addr:full":"59 N Broad St Lexington TN 38351",
    "addr:housenumber":"59",
    "addr:postcode":"38351",
    "addr:street":"N Broad St",
    "iso:country":"US",
    "sg:address":"59 N Broad St",
    "sg:city":"Lexington",
    "sg:classifiers":[
        {
            "category":"Real Estate",
            "subcategory":"Real Estate Agent",
            "type":"Services"
        }
    ],
    "sg:phone":"+1 731 968 8328",
    "sg:postcode":"38351",
    "sg:province":"TN",
    "sg:tags":[
        "consulting",
        "management"
    ],
    "wof:name":"Preferred Realty",
    "wof:placetype":"venue"
},
  "geometry": {"coordinates":[-88.388473,35.654915],"type":"Point"}
}