{
  "type": "Feature",
  "properties": {
    "addr:full":"3425 Austin Peay Hwy Memphis TN 38135",
    "addr:housenumber":"3425",
    "addr:postcode":"38135",
    "addr:street":"Austin Peay Hwy",
    "iso:country":"US",
    "sg:address":"3425 Austin Peay Hwy",
    "sg:city":"Memphis",
    "sg:classifiers":[
        {
            "category":"Personal",
            "subcategory":"Beauty Salon",
            "type":"Services"
        }
    ],
    "sg:phone":"+1 901 213 1011",
    "sg:postcode":"38135",
    "sg:province":"TN",
    "wof:name":"Essecence Hair Studio",
    "wof:placetype":"venue"
},
  "geometry": {"coordinates":[-89.911614,35.218687],"type":"Point"}
}