{
  "type": "Feature",
  "properties": {
    "iso:country":"US",
    "sg:address":"1160 Gallatin Pike N",
    "sg:city":"Madison",
    "sg:classifiers":[
        {
            "category":"Government",
            "subcategory":"Office",
            "type":"Public Place"
        }
    ],
    "sg:phone":"+1 615 253 3888",
    "sg:postcode":"37115",
    "sg:province":"TN",
    "sg:tags":[
        "state",
        "inspection"
    ],
    "sg:website":"www.state.tn.us",
    "wof:name":"Housing Development Agency",
    "wof:placetype":"venue"
},
  "geometry": {"coordinates":[-86.708568,36.279751],"type":"Point"}
}