{
  "type": "Feature",
  "properties": {
    "iso:country":"US",
    "sg:address":"196 Sparks Rd",
    "sg:city":"La Follette",
    "sg:classifiers":[
        {
            "category":"Real Estate",
            "subcategory":"Real Estate Agent",
            "type":"Services"
        }
    ],
    "sg:phone":"+1 423 562 4466",
    "sg:postcode":"37737",
    "sg:province":"TN",
    "wof:name":"Powell Valley Realty",
    "wof:placetype":"venue"
},
  "geometry": {"coordinates":[-84.04526300000001,35.729151],"type":"Point"}
}