{
  "type": "Feature",
  "properties": {
    "iso:country":"US",
    "sg:address":"2325 E Andrew Johnson Hwy",
    "sg:city":"Morristown",
    "sg:classifiers":[
        {
            "category":"Shopping",
            "type":"Retail Goods"
        }
    ],
    "sg:phone":"+1 423 587 5188",
    "sg:postcode":"37814",
    "sg:province":"TN",
    "sg:tags":[
        "merchandise"
    ],
    "wof:name":"Fish Fair",
    "wof:placetype":"venue"
},
  "geometry": {"coordinates":[-83.26439000000001,36.226934],"type":"Point"}
}