{
  "type": "Feature",
  "properties": {
    "iso:country":"US",
    "sg:address":"326 Commerce St",
    "sg:city":"Kingsport",
    "sg:classifiers":[
        {
            "category":"Education",
            "subcategory":"School",
            "type":"Public Place"
        }
    ],
    "sg:phone":"+1 423 392 4643",
    "sg:postcode":"37660",
    "sg:province":"TN",
    "sg:tags":[
        "educational",
        "program"
    ],
    "wof:name":"Literacy Council Of Kingsport",
    "wof:placetype":"venue"
},
  "geometry": {"coordinates":[-82.558786,36.54705],"type":"Point"}
}