{
  "type": "Feature",
  "properties": {
    "iso:country":"US",
    "sg:address":"1120 Grove St",
    "sg:city":"Elizabethton",
    "sg:classifiers":[
        {
            "category":"Building & Trades",
            "subcategory":"Construction",
            "type":"Services"
        }
    ],
    "sg:phone":"+1 423 543 5363",
    "sg:postcode":"37643",
    "sg:province":"TN",
    "sg:tags":[
        "contractor"
    ],
    "wof:name":"Bowers Drywall",
    "wof:placetype":"venue"
},
  "geometry": {"coordinates":[-82.20998299999999,36.336607],"type":"Point"}
}