{
  "type": "Feature",
  "properties": {
    "iso:country":"US",
    "sg:address":"115 17th St SW",
    "sg:city":"Knoxville",
    "sg:classifiers":[
        {
            "category":"Restaurant",
            "type":"Food & Drink"
        }
    ],
    "sg:phone":"+1 865 673 4807",
    "sg:postcode":"37916",
    "sg:province":"TN",
    "sg:tags":[
        "grocery",
        "eating"
    ],
    "wof:name":"17th Street Market & Deli",
    "wof:placetype":"venue"
},
  "geometry": {"coordinates":[-83.93484599999999,35.960984],"type":"Point"}
}