{
  "type": "Feature",
  "properties": {
    "iso:country":"US",
    "sg:address":"110 Public Sq",
    "sg:city":"Lafayette",
    "sg:classifiers":[
        {
            "category":"Real Estate",
            "subcategory":"Real Estate Services",
            "type":"Services"
        }
    ],
    "sg:phone":"+1 615 666 8883",
    "sg:postcode":"37083",
    "sg:province":"TN",
    "sg:tags":[
        "company",
        "title"
    ],
    "sg:website":"www.benchmarktitle.com",
    "wof:name":"Benchmark Title Co",
    "wof:placetype":"venue"
},
  "geometry": {"coordinates":[-86.02598,36.521169],"type":"Point"}
}