{
  "type": "Feature",
  "properties": {
    "addr:full":"1105 E Reelfoot Ave Union City TN 38261",
    "addr:housenumber":"1105",
    "addr:postcode":"38261",
    "addr:street":"E Reelfoot Ave",
    "iso:country":"US",
    "sg:address":"1105 E Reelfoot Ave",
    "sg:city":"Union City",
    "sg:classifiers":[
        {
            "category":"Restaurant",
            "type":"Food & Drink"
        }
    ],
    "sg:phone":"+1 731 885 6118",
    "sg:postcode":"38261",
    "sg:province":"TN",
    "sg:tags":[
        "eating"
    ],
    "wof:name":"Hunan Palace",
    "wof:placetype":"venue"
},
  "geometry": {"coordinates":[-89.04775600000001,36.41365],"type":"Point"}
}