{
  "type": "Feature",
  "properties": {
    "addr:full":"3402 Park Ave Memphis TN 38111",
    "addr:housenumber":"3402",
    "addr:postcode":"38111",
    "addr:street":"Park Ave",
    "iso:country":"US",
    "sg:address":"3402 Park Ave",
    "sg:city":"Memphis",
    "sg:classifiers":[
        {
            "category":"Personal",
            "subcategory":"Beauty Salon",
            "type":"Services"
        },
        {
            "category":"Personal",
            "subcategory":"Barber",
            "type":"Services"
        }
    ],
    "sg:phone":"+1 901 325 7990",
    "sg:postcode":"38111",
    "sg:province":"TN",
    "wof:name":"Osheila Beauty",
    "wof:placetype":"venue"
},
  "geometry": {"coordinates":[-89.94994699999999,35.107826],"type":"Point"}
}