{
  "type": "Feature",
  "properties": {
    "iso:country":"US",
    "sg:address":"1228 Northgate Business Pkwy",
    "sg:city":"Madison",
    "sg:classifiers":[
        {
            "category":"Retail",
            "subcategory":"Auto Repair",
            "type":"Services"
        }
    ],
    "sg:phone":"+1 615 865 1800",
    "sg:postcode":"37115",
    "sg:province":"TN",
    "sg:tags":[
        "general"
    ],
    "wof:name":"On-Site Fleet Services Tenn",
    "wof:placetype":"venue"
},
  "geometry": {"coordinates":[-86.690305,36.285552],"type":"Point"}
}