{
  "type": "Feature",
  "properties": {
    "iso:country":"US",
    "sg:address":"2147 Canady Ave",
    "sg:city":"Nashville",
    "sg:classifiers":[
        {
            "category":"Retail",
            "subcategory":"Auto Repair",
            "type":"Services"
        }
    ],
    "sg:phone":"+1 615 254 8040",
    "sg:postcode":"37211",
    "sg:province":"TN",
    "sg:tags":[
        "repairing",
        "tire"
    ],
    "wof:name":"Hal Night Tire Svc",
    "wof:placetype":"venue"
},
  "geometry": {"coordinates":[-86.755264,36.126392],"type":"Point"}
}