{
  "type": "Feature",
  "properties": {
    "iso:country":"US",
    "sg:address":"1028 E Commerce St",
    "sg:city":"Lewisburg",
    "sg:classifiers":[
        {
            "category":"Home & Garden",
            "subcategory":"Mobile Homes",
            "type":"Retail Goods"
        }
    ],
    "sg:phone":"+1 931 270 7336",
    "sg:postcode":"37091",
    "sg:province":"TN",
    "wof:name":"Shade Tree Homes",
    "wof:placetype":"venue"
},
  "geometry": {"coordinates":[-86.767394,35.443327],"type":"Point"}
}