{
  "type": "Feature",
  "properties": {
    "iso:country":"US",
    "sg:address":"209 Advantage Pl",
    "sg:city":"Knoxville",
    "sg:classifiers":[
        {
            "category":"Travel",
            "subcategory":"Hotels & Motels",
            "type":"Entertainment"
        }
    ],
    "sg:phone":"+1 865 691 1664",
    "sg:postcode":"37922",
    "sg:province":"TN",
    "sg:tags":[
        "operation"
    ],
    "sg:website":"www.redroof.com",
    "wof:name":"Red Roof Inn",
    "wof:placetype":"venue"
},
  "geometry": {"coordinates":[-84.090401,35.915846],"type":"Point"}
}