{
  "type": "Feature",
  "properties": {
    "iso:country":"US",
    "sg:address":"210 E Main St",
    "sg:city":"Franklin",
    "sg:classifiers":[
        {
            "category":"Banks & Credit Unions",
            "subcategory":"Bank",
            "type":"Services"
        }
    ],
    "sg:phone":"+1 615 791 1978",
    "sg:postcode":"37064",
    "sg:province":"TN",
    "sg:tags":[
        "correspondent",
        "banker",
        "mortgage"
    ],
    "wof:name":"Fifth Third Mortgage",
    "wof:placetype":"venue"
},
  "geometry": {"coordinates":[-86.867706,35.92586],"type":"Point"}
}