{
  "type": "Feature",
  "properties": {
    "iso:country":"US",
    "sg:address":"2382 Frayser Blvd",
    "sg:city":"Memphis",
    "sg:classifiers":[
        {
            "category":"Retail",
            "subcategory":"Laundry & Dry Cleaning",
            "type":"Services"
        }
    ],
    "sg:phone":"+1 901 353 8455",
    "sg:postcode":"38127",
    "sg:province":"TN",
    "sg:tags":[
        "cleaners"
    ],
    "wof:name":"Get Fresh Cleaners",
    "wof:placetype":"venue"
},
  "geometry": {"coordinates":[-89.981938,35.218687],"type":"Point"}
}