{
  "type": "Feature",
  "properties": {
    "iso:country":"US",
    "sg:address":"110 N Kilgore St",
    "sg:city":"Athens",
    "sg:classifiers":[
        {
            "category":"Taxi",
            "type":"Transportation"
        }
    ],
    "sg:phone":"+1 423 744 3900",
    "sg:postcode":"37303",
    "sg:province":"TN",
    "sg:tags":[
        "taxicab"
    ],
    "wof:name":"J P Taxi Svc",
    "wof:placetype":"venue"
},
  "geometry": {"coordinates":[-84.59761899999999,35.441853],"type":"Point"}
}