{
  "type": "Feature",
  "properties": {
    "addr:full":"726 Lafayette Rd Red Boiling Spgs TN 37150",
    "addr:housenumber":"726",
    "addr:postcode":"37150",
    "iso:country":"US",
    "sg:address":"726 Lafayette Rd",
    "sg:city":"Red Boiling Spgs",
    "sg:classifiers":[
        {
            "category":"Shopping",
            "subcategory":"Used Merchandise",
            "type":"Retail Goods"
        }
    ],
    "sg:phone":"+1 615 699 4446",
    "sg:postcode":"37150",
    "sg:province":"TN",
    "sg:tags":[
        "antique"
    ],
    "wof:name":"Memories & More",
    "wof:placetype":"venue"
},
  "geometry": {"coordinates":[-85.863084,36.520406],"type":"Point"}
}