{
  "type": "Feature",
  "properties": {
    "addr:full":"4742 Franklin Rd Murfreesboro TN 37128",
    "addr:housenumber":"4742",
    "addr:postcode":"37128",
    "addr:street":"Franklin Rd",
    "iso:country":"US",
    "sg:address":"4742 Franklin Rd",
    "sg:city":"Murfreesboro",
    "sg:classifiers":[
        {
            "category":"Farming",
            "subcategory":"Livestock Farm",
            "type":"Manufacturing & Wholesale Goods"
        }
    ],
    "sg:phone":"+1 615 890 1165",
    "sg:postcode":"37128",
    "sg:province":"TN",
    "sg:tags":[
        "equine"
    ],
    "wof:name":"Lifes Mini Colors",
    "wof:placetype":"venue"
},
  "geometry": {"coordinates":[-86.586766,35.850866],"type":"Point"}
}