{
  "type": "Feature",
  "properties": {
    "iso:country":"US",
    "sg:address":"109 N Center St",
    "sg:city":"Collierville",
    "sg:classifiers":[
        {
            "category":"Real Estate",
            "subcategory":"Real Estate Agent",
            "type":"Services"
        }
    ],
    "sg:phone":"+1 901 853 2030",
    "sg:postcode":"38017",
    "sg:province":"TN",
    "sg:website":"www.kelseyproperties.com",
    "wof:name":"Kelsey Properties",
    "wof:placetype":"venue"
},
  "geometry": {"coordinates":[-89.66561400000001,35.042483],"type":"Point"}
}