{
  "type": "Feature",
  "properties": {
    "iso:country":"US",
    "sg:address":"1211 Southland Mall",
    "sg:city":"Memphis",
    "sg:classifiers":[
        {
            "category":"Shopping",
            "subcategory":"Jewelry",
            "type":"Retail Goods"
        }
    ],
    "sg:phone":"+1 901 396 7467",
    "sg:postcode":"38116",
    "sg:province":"TN",
    "sg:tags":[
        "jeweler"
    ],
    "wof:name":"G M Dimonds",
    "wof:placetype":"venue"
},
  "geometry": {"coordinates":[-90.022204,35.019826],"type":"Point"}
}