{
  "type": "Feature",
  "properties": {
    "addr:full":"3078 Board Valley Rd Sparta TN 38583",
    "addr:housenumber":"3078",
    "addr:postcode":"38583",
    "addr:street":"Board Valley Rd",
    "iso:country":"US",
    "sg:address":"3078 Board Valley Rd",
    "sg:city":"Sparta",
    "sg:classifiers":[
        {
            "category":"Manufacturing",
            "subcategory":"Lumber",
            "type":"Manufacturing & Wholesale Goods"
        }
    ],
    "sg:phone":"+1 931 738 3994",
    "sg:postcode":"38583",
    "sg:province":"TN",
    "sg:tags":[
        "logging"
    ],
    "wof:name":"Alan Baker Logging",
    "wof:placetype":"venue"
},
  "geometry": {"coordinates":[-85.375573,36.038293],"type":"Point"}
}