{
  "type": "Feature",
  "properties": {
    "iso:country":"US",
    "sg:address":"4884 Broyles Rd",
    "sg:city":"Christiana",
    "sg:classifiers":[
        {
            "category":"Manufacturing",
            "subcategory":"Printing",
            "type":"Manufacturing & Wholesale Goods"
        }
    ],
    "sg:phone":"+1 615 896 9830",
    "sg:postcode":"37037",
    "sg:province":"TN",
    "sg:tags":[
        "cards",
        "greeting",
        "mfg"
    ],
    "wof:name":"Blue Turtle Studio",
    "wof:placetype":"venue"
},
  "geometry": {"coordinates":[-86.34571,35.682074],"type":"Point"}
}