{
  "type": "Feature",
  "properties": {
    "iso:country":"US",
    "sg:address":"833 Magnolia Ct E",
    "sg:city":"Nashville",
    "sg:classifiers":[
        {
            "category":"Manufacturing",
            "subcategory":"Apparel",
            "type":"Manufacturing & Wholesale Goods"
        }
    ],
    "sg:phone":"+1 615 673 3540",
    "sg:postcode":"37221",
    "sg:province":"TN",
    "sg:tags":[
        "finishing",
        "plant",
        "cotton"
    ],
    "wof:name":"Enhance Your Image Apparel",
    "wof:placetype":"venue"
},
  "geometry": {"coordinates":[-86.93359599999999,36.067463],"type":"Point"}
}