{
  "type": "Feature",
  "properties": {
    "iso:country":"US",
    "sg:address":"2530 Crossfield Dr",
    "sg:city":"Nashville",
    "sg:classifiers":[
        {
            "category":"Organizations",
            "subcategory":"Religious Organization",
            "type":"Services"
        }
    ],
    "sg:phone":"+1 615 889 2107",
    "sg:postcode":"37214",
    "sg:province":"TN",
    "sg:tags":[
        "church"
    ],
    "wof:name":"Hispanic Ministry",
    "wof:placetype":"venue"
},
  "geometry": {"coordinates":[-86.675315,36.167546],"type":"Point"}
}