{
  "type": "Feature",
  "properties": {
    "iso:country":"US",
    "sg:address":"79 Milan Hwy",
    "sg:city":"Milan",
    "sg:classifiers":[
        {
            "category":"Retail",
            "subcategory":"Repair Shop",
            "type":"Services"
        }
    ],
    "sg:phone":"+1 731 783 1000",
    "sg:postcode":"38355",
    "sg:province":"TN",
    "sg:tags":[
        "lock",
        "locksmith"
    ],
    "wof:name":"Turn Key Locksmith",
    "wof:placetype":"venue"
},
  "geometry": {"coordinates":[-88.76391599999999,35.820806],"type":"Point"}
}