{
  "type": "Feature",
  "properties": {
    "addr:full":"6025 Brookvale Ln Knoxville TN 37919",
    "addr:postcode":"37919",
    "addr:street":"Brookvale Ln",
    "iso:country":"US",
    "sg:address":"6025 Brookvale Ln",
    "sg:city":"Knoxville",
    "sg:classifiers":[
        {
            "category":"Professional",
            "type":"Services"
        }
    ],
    "sg:phone":"+1 865 584 2966",
    "sg:postcode":"37919",
    "sg:province":"TN",
    "sg:tags":[
        "establishment"
    ],
    "wof:name":"Comag",
    "wof:placetype":"venue"
},
  "geometry": {"coordinates":[-84.00798399999999,35.936337],"type":"Point"}
}