{
  "type": "Feature",
  "properties": {
    "addr:full":"5032 Chadfield Way Antioch TN 37013",
    "addr:housenumber":"5032",
    "addr:postcode":"37013",
    "addr:street":"Chadfield Way",
    "iso:country":"US",
    "sg:address":"5032 Chadfield Way",
    "sg:city":"Antioch",
    "sg:classifiers":[
        {
            "category":"Farming",
            "subcategory":"Nursery",
            "type":"Manufacturing & Wholesale Goods"
        }
    ],
    "sg:phone":"+1 615 473 4032",
    "sg:postcode":"37013",
    "sg:province":"TN",
    "sg:tags":[
        "tree",
        "grower",
        "nursery-wholesale",
        "nurseries-plants"
    ],
    "wof:name":"4 Green Thumbs",
    "wof:placetype":"venue"
},
  "geometry": {"coordinates":[-86.66632799999999,36.062195],"type":"Point"}
}