{
  "type": "Feature",
  "properties": {
    "addr:full":"1214 Warren St Murfreesboro TN 37129",
    "addr:housenumber":"1214",
    "addr:postcode":"37129",
    "addr:street":"Warren St",
    "iso:country":"US",
    "sg:address":"1214 Warren St",
    "sg:city":"Murfreesboro",
    "sg:classifiers":[
        {
            "category":"Building & Trades",
            "subcategory":"Construction",
            "type":"Services"
        }
    ],
    "sg:phone":"+1 615 867 7062",
    "sg:postcode":"37129",
    "sg:province":"TN",
    "sg:tags":[
        "wallpaper"
    ],
    "wof:name":"Sonshine Wall Co",
    "wof:placetype":"venue"
},
  "geometry": {"coordinates":[-86.414765,35.858232],"type":"Point"}
}