{
  "type": "Feature",
  "properties": {
    "iso:country":"US",
    "sg:address":"1030 Tsatanuga Rd",
    "sg:city":"Hixson",
    "sg:classifiers":[
        {
            "category":"Building & Trades",
            "subcategory":"Construction",
            "type":"Services"
        }
    ],
    "sg:phone":"+1 423 842 5747",
    "sg:postcode":"37343",
    "sg:province":"TN",
    "sg:tags":[
        "designer",
        "dealer",
        "pool",
        "swimming"
    ],
    "wof:name":"Barber's Gunite Svc",
    "wof:placetype":"venue"
},
  "geometry": {"coordinates":[-85.23564399999999,35.181631],"type":"Point"}
}