{
  "type": "Feature",
  "properties": {
    "addr:full":"1961 Hillsboro Blvd Manchester TN 37355",
    "addr:housenumber":"1961",
    "addr:postcode":"37355",
    "addr:street":"Hillsboro Blvd",
    "iso:country":"US",
    "sg:address":"1961 Hillsboro Blvd",
    "sg:city":"Manchester",
    "sg:classifiers":[
        {
            "category":"Building & Trades",
            "subcategory":"Construction",
            "type":"Services"
        }
    ],
    "sg:phone":"+1 931 728 8468",
    "sg:postcode":"37355",
    "sg:province":"TN",
    "sg:tags":[
        "contractor"
    ],
    "wof:name":"Film -Fab Window Tinting",
    "wof:placetype":"venue"
},
  "geometry": {"coordinates":[-86.064576,35.462387],"type":"Point"}
}