{
  "type": "Feature",
  "properties": {
    "iso:country":"US",
    "sg:address":"4365 Walter Pigg Rd",
    "sg:city":"Cypress Inn",
    "sg:classifiers":[
        {
            "category":"Manufacturing",
            "subcategory":"Lumber",
            "type":"Manufacturing & Wholesale Goods"
        }
    ],
    "sg:phone":"+1 931 724 9471",
    "sg:postcode":"38452",
    "sg:province":"TN",
    "sg:tags":[
        "mill"
    ],
    "wof:name":"Berry Brothers Sawmill Inc",
    "wof:placetype":"venue"
},
  "geometry": {"coordinates":[-87.785292,35.091286],"type":"Point"}
}