{
  "type": "Feature",
  "properties": {
    "addr:full":"351 Dawson St Vonore TN 37885",
    "addr:housenumber":"351",
    "addr:postcode":"37885",
    "addr:street":"Dawson St",
    "iso:country":"US",
    "sg:address":"351 Dawson St",
    "sg:city":"Vonore",
    "sg:classifiers":[
        {
            "category":"Autos & Motor Vehicles",
            "subcategory":"Boat Sales",
            "type":"Retail Goods"
        }
    ],
    "sg:phone":"+1 423 884 2011",
    "sg:postcode":"37885",
    "sg:province":"TN",
    "sg:tags":[
        "equipment",
        "marine",
        "supply"
    ],
    "wof:name":"Marine Works",
    "wof:placetype":"venue"
},
  "geometry": {"coordinates":[-84.230785,35.590878],"type":"Point"}
}