{
  "type": "Feature",
  "properties": {
    "addr:full":"4417 Willow Rd Memphis TN 38117",
    "addr:housenumber":"4417",
    "addr:postcode":"38117",
    "addr:street":"Willow Rd",
    "iso:country":"US",
    "sg:address":"4417 Willow Rd",
    "sg:city":"Memphis",
    "sg:classifiers":[
        {
            "category":"Education",
            "subcategory":"School",
            "type":"Public Place"
        }
    ],
    "sg:phone":"+1 901 416 2196",
    "sg:postcode":"38117",
    "sg:province":"TN",
    "wof:name":"Willow Oaks Elementary School",
    "wof:placetype":"venue"
},
  "geometry": {"coordinates":[-89.915333,35.085753],"type":"Point"}
}