{
  "type": "Feature",
  "properties": {
    "iso:country":"US",
    "sg:address":"9456 Grove Trail Ln",
    "sg:city":"Germantown",
    "sg:classifiers":[
        {
            "category":"Wholesale",
            "subcategory":"Medical Equipment & Supplies",
            "type":"Manufacturing & Wholesale Goods"
        }
    ],
    "sg:phone":"+1 901 756 6640",
    "sg:postcode":"38139",
    "sg:province":"TN",
    "sg:tags":[
        "pharmaceutical"
    ],
    "wof:name":"Pfizer",
    "wof:placetype":"venue"
},
  "geometry": {"coordinates":[-89.746566,35.100388],"type":"Point"}
}