{
  "type": "Feature",
  "properties": {
    "iso:country":"US",
    "sg:address":"1019 W Broadway Ave",
    "sg:city":"Maryville",
    "sg:classifiers":[
        {
            "category":"Health Services",
            "subcategory":"Doctor",
            "type":"Services"
        }
    ],
    "sg:phone":"+1 865 984 1820",
    "sg:postcode":"37801",
    "sg:province":"TN",
    "wof:name":"William H Savell Jr DDS",
    "wof:placetype":"venue"
},
  "geometry": {"coordinates":[-83.982187,35.746769],"type":"Point"}
}