{
  "type": "Feature",
  "properties": {
    "iso:country":"US",
    "sg:address":"234 Choff Ln",
    "sg:city":"Sparta",
    "sg:classifiers":[
        {
            "category":"Home & Garden",
            "subcategory":"Building Materials",
            "type":"Retail Goods"
        }
    ],
    "sg:phone":"+1 931 738 2377",
    "sg:postcode":"38583",
    "sg:province":"TN",
    "wof:name":"Modem Interiors",
    "wof:placetype":"venue"
},
  "geometry": {"coordinates":[-85.46502599999999,35.956055],"type":"Point"}
}