{
  "type": "Feature",
  "properties": {
    "iso:country":"US",
    "sg:address":"1301 Winchester Rd",
    "sg:city":"Memphis",
    "sg:phone":"+1 901 332 8093",
    "sg:postcode":"38116",
    "sg:province":"TN",
    "wof:name":"L & S Fish & Hot Wings",
    "wof:placetype":"venue"
},
  "geometry": {"coordinates":[-90.0205,35.054165],"type":"Point"}
}