{
  "type": "Feature",
  "properties": {
    "addr:full":"10025 Kingston Pike Knoxville TN 37922",
    "addr:housenumber":"10025",
    "addr:postcode":"37922",
    "addr:street":"Kingston Pike",
    "iso:country":"US",
    "sg:address":"10025 Kingston Pike",
    "sg:city":"Knoxville",
    "sg:classifiers":[
        {
            "category":"Retail",
            "subcategory":"Auto Repair",
            "type":"Services"
        }
    ],
    "sg:phone":"+1 865 691 5005",
    "sg:postcode":"37922",
    "sg:province":"TN",
    "sg:tags":[
        "repairing",
        "automobile"
    ],
    "wof:name":"Midas Auto Svc Experts",
    "wof:placetype":"venue"
},
  "geometry": {"coordinates":[-84.114722,35.904036],"type":"Point"}
}