{
  "type": "Feature",
  "properties": {
    "addr:full":"60 E 2nd St Crossville TN 38555",
    "addr:housenumber":"60",
    "addr:postcode":"38555",
    "addr:street":"E 2Nd St",
    "iso:country":"US",
    "sg:address":"60 E 2nd St",
    "sg:city":"Crossville",
    "sg:classifiers":[
        {
            "category":"Insurance",
            "subcategory":"Hazard Insurance",
            "type":"Services"
        }
    ],
    "sg:phone":"+1 931 484 7785",
    "sg:postcode":"38555",
    "sg:province":"TN",
    "sg:tags":[
        "bond"
    ],
    "wof:name":"Marshall Bonding",
    "wof:placetype":"venue"
},
  "geometry": {"coordinates":[-85.024891,35.947819],"type":"Point"}
}