{
  "type": "Feature",
  "properties": {
    "iso:country":"US",
    "sg:address":"1801 Thrasher Pike",
    "sg:city":"Hixson",
    "sg:classifiers":[
        {
            "category":"Building & Trades",
            "subcategory":"Construction",
            "type":"Services"
        }
    ],
    "sg:phone":"+1 423 843 1886",
    "sg:postcode":"37343",
    "sg:province":"TN",
    "sg:tags":[
        "house"
    ],
    "wof:name":"Tony Burnette Construction",
    "wof:placetype":"venue"
},
  "geometry": {"coordinates":[-85.18248,35.18154],"type":"Point"}
}