{
  "type": "Feature",
  "properties": {
    "addr:full":"294 Friendship Rd Brownsville TN 38012",
    "addr:housenumber":"294",
    "addr:postcode":"38012",
    "addr:street":"Friendship Rd",
    "iso:country":"US",
    "sg:address":"294 Friendship Rd",
    "sg:city":"Brownsville",
    "sg:classifiers":[
        {
            "category":"Organizations",
            "subcategory":"Religious Organization",
            "type":"Services"
        }
    ],
    "sg:phone":"+1 731 772 8060",
    "sg:postcode":"38012",
    "sg:province":"TN",
    "wof:name":"Friendship Baptist Church",
    "wof:placetype":"venue"
},
  "geometry": {"coordinates":[-89.18714,35.558281],"type":"Point"}
}