{
  "type": "Feature",
  "properties": {
    "addr:full":"900 E Brooks Rd Memphis TN 38109",
    "addr:housenumber":"900",
    "addr:postcode":"38109",
    "addr:street":"E Brooks Rd",
    "iso:country":"US",
    "sg:address":"900 E Brooks Rd",
    "sg:city":"Memphis",
    "sg:classifiers":[
        {
            "category":"Home & Garden",
            "subcategory":"Carpets & Floor Coverings",
            "type":"Retail Goods"
        }
    ],
    "sg:phone":"+1 901 432 7283",
    "sg:postcode":"38109",
    "sg:province":"TN",
    "sg:tags":[
        "a",
        "as",
        "retailer",
        "operates"
    ],
    "wof:name":"Discount Flooring Co",
    "wof:placetype":"venue"
},
  "geometry": {"coordinates":[-90.033565,35.061847],"type":"Point"}
}