{
  "type": "Feature",
  "properties": {
    "iso:country":"US",
    "sg:address":"1216 Lee Brown Rd",
    "sg:city":"Bon Aqua",
    "sg:classifiers":[
        {
            "category":"Professional",
            "type":"Services"
        }
    ],
    "sg:phone":"+1 615 412 4944",
    "sg:postcode":"37025",
    "sg:province":"TN",
    "wof:name":"Pendergrass Construction",
    "wof:placetype":"venue"
},
  "geometry": {"coordinates":[-87.286479,35.972982],"type":"Point"}
}