{
  "type": "Feature",
  "properties": {
    "iso:country":"US",
    "sg:address":"503 N Petway St",
    "sg:city":"Franklin",
    "sg:classifiers":[
        {
            "category":"Building & Trades",
            "subcategory":"Plumbing",
            "type":"Services"
        }
    ],
    "sg:phone":"+1 615 790 1198",
    "sg:postcode":"37064",
    "sg:province":"TN",
    "sg:tags":[
        "conditioning",
        "air",
        "system",
        "contractor"
    ],
    "wof:name":"Harold Johnson Heat & Air Cond",
    "wof:placetype":"venue"
},
  "geometry": {"coordinates":[-86.885029,35.919326],"type":"Point"}
}