{
  "type": "Feature",
  "properties": {
    "iso:country":"US",
    "sg:address":"613 N James Campbell Blvd",
    "sg:city":"Columbia",
    "sg:classifiers":[
        {
            "category":"Shopping",
            "subcategory":"Tobacco",
            "type":"Retail Goods"
        }
    ],
    "sg:phone":"+1 931 388 5568",
    "sg:postcode":"38401",
    "sg:province":"TN",
    "sg:tags":[
        "product"
    ],
    "wof:name":"Discount Tobacco Outlet Inc",
    "wof:placetype":"venue"
},
  "geometry": {"coordinates":[-87.057879,35.627404],"type":"Point"}
}