{
  "type": "Feature",
  "properties": {
    "iso:country":"US",
    "sg:address":"565 S Jefferson Ave",
    "sg:city":"Cookeville",
    "sg:classifiers":[
        {
            "category":"Professional",
            "subcategory":"Management & Consulting",
            "type":"Services"
        }
    ],
    "sg:phone":"+1 931 528 3437",
    "sg:postcode":"38501",
    "sg:province":"TN",
    "sg:tags":[
        "business"
    ],
    "wof:name":"Fiesta Imports",
    "wof:placetype":"venue"
},
  "geometry": {"coordinates":[-85.500754,36.150311],"type":"Point"}
}