{
  "type": "Feature",
  "properties": {
    "iso:country":"US",
    "sg:address":"2769 Wolfcreek Pkwy #110",
    "sg:city":"Memphis",
    "sg:classifiers":[
        {
            "category":"Shopping",
            "subcategory":"Bicycles & Sporting Goods",
            "type":"Retail Goods"
        }
    ],
    "sg:phone":"+1 901 377 7677",
    "sg:postcode":"38133",
    "sg:province":"TN",
    "sg:tags":[
        "equipment",
        "golf",
        "supply"
    ],
    "wof:name":"Pro Golf Discount",
    "wof:placetype":"venue"
},
  "geometry": {"coordinates":[-89.79369699999999,35.199452],"type":"Point"}
}