{
  "type": "Feature",
  "properties": {
    "iso:country":"US",
    "sg:address":"4532 Scenic Point Dr",
    "sg:city":"Louisville",
    "sg:classifiers":[
        {
            "category":"Home & Garden",
            "subcategory":"Hardware",
            "type":"Retail Goods"
        }
    ],
    "sg:phone":"+1 865 977 6409",
    "sg:postcode":"37777",
    "sg:province":"TN",
    "wof:name":"McCurry Dennis",
    "wof:placetype":"venue"
},
  "geometry": {"coordinates":[-84.12878600000001,35.799995],"type":"Point"}
}