{
  "type": "Feature",
  "properties": {
    "iso:country":"US",
    "sg:address":"4198 Sulphur Springs Rd",
    "sg:city":"Murfreesboro",
    "sg:classifiers":[
        {
            "category":"Organizations",
            "subcategory":"Religious Organization",
            "type":"Services"
        }
    ],
    "sg:phone":"+1 615 890 9659",
    "sg:postcode":"37129",
    "sg:province":"TN",
    "wof:name":"Leanna Church Of Christ",
    "wof:placetype":"venue"
},
  "geometry": {"coordinates":[-86.431113,35.938133],"type":"Point"}
}