{
  "type": "Feature",
  "properties": {
    "addr:full":"1500 Broad St Chattanooga TN 37408",
    "addr:housenumber":"1500",
    "addr:postcode":"37408",
    "addr:street":"Broad St",
    "iso:country":"US",
    "sg:address":"1500 Broad St",
    "sg:city":"Chattanooga",
    "sg:classifiers":[
        {
            "category":"Food & Beverages",
            "subcategory":"Groceries & Convenience Stores",
            "type":"Retail Goods"
        },
        {
            "category":"Food & Beverages",
            "subcategory":"Meat & Fish",
            "type":"Retail Goods"
        }
    ],
    "sg:phone":"+1 423 634 0565",
    "sg:postcode":"37408",
    "sg:province":"TN",
    "sg:tags":[
        "market"
    ],
    "wof:name":"Carniceria Loa 7",
    "wof:placetype":"venue"
},
  "geometry": {"coordinates":[-85.311256,35.037609],"type":"Point"}
}