{
  "type": "Feature",
  "properties": {
    "addr:full":"413 W Gaines St Lawrenceburg TN 38464",
    "addr:housenumber":"413",
    "addr:postcode":"38464",
    "addr:street":"W Gaines St",
    "iso:country":"US",
    "sg:address":"413 W Gaines St",
    "sg:city":"Lawrenceburg",
    "sg:classifiers":[
        {
            "category":"Health Services",
            "subcategory":"Doctor",
            "type":"Services"
        }
    ],
    "sg:phone":"+1 931 762 5806",
    "sg:postcode":"38464",
    "sg:province":"TN",
    "sg:tags":[
        "dentist"
    ],
    "wof:name":"Gary L Kelly DDS",
    "wof:placetype":"venue"
},
  "geometry": {"coordinates":[-87.34044900000001,35.24363],"type":"Point"}
}