{
  "type": "Feature",
  "properties": {
    "iso:country":"US",
    "sg:address":"3866 Upper Finley Rd",
    "sg:city":"Dyersburg",
    "sg:classifiers":[
        {
            "category":"Farming",
            "subcategory":"Farm",
            "type":"Manufacturing & Wholesale Goods"
        }
    ],
    "sg:phone":"+1 731 285 5882",
    "sg:postcode":"38024",
    "sg:province":"TN",
    "sg:tags":[
        "crop",
        "general"
    ],
    "wof:name":"Crossroads Farms",
    "wof:placetype":"venue"
},
  "geometry": {"coordinates":[-89.4427,36.048476],"type":"Point"}
}