{
  "type": "Feature",
  "properties": {
    "iso:country":"US",
    "sg:address":"5120 Virginia Way",
    "sg:city":"Brentwood",
    "sg:classifiers":[
        {
            "category":"Real Estate",
            "subcategory":"Real Estate Agent",
            "type":"Services"
        }
    ],
    "sg:phone":"+1 615 377 6350",
    "sg:postcode":"37027",
    "sg:province":"TN",
    "wof:name":"Swh Construction LP",
    "wof:placetype":"venue"
},
  "geometry": {"coordinates":[-86.806192,36.032211],"type":"Point"}
}