{
  "type": "Feature",
  "properties": {
    "iso:country":"US",
    "sg:address":"3477 Hwy 126",
    "sg:city":"Blountville",
    "sg:classifiers":[
        {
            "category":"Home & Garden",
            "subcategory":"Building Materials",
            "type":"Retail Goods"
        }
    ],
    "sg:phone":"+1 423 323 5141",
    "sg:postcode":"37617",
    "sg:province":"TN",
    "sg:tags":[
        "glass",
        "window",
        "plate"
    ],
    "wof:name":"Mauk & Adams Glass Co",
    "wof:placetype":"venue"
},
  "geometry": {"coordinates":[-82.32857,36.532492],"type":"Point"}
}