{
  "type": "Feature",
  "properties": {
    "addr:full":"2321 US Hwy 45W Byp Trenton TN 38382",
    "addr:housenumber":"2321",
    "addr:postcode":"38382",
    "addr:street":"Us Hwy 45W Byp",
    "iso:country":"US",
    "sg:address":"2321 US Hwy 45W Byp",
    "sg:city":"Trenton",
    "sg:classifiers":[
        {
            "category":"Wholesale",
            "subcategory":"Machinery & Supplies",
            "type":"Manufacturing & Wholesale Goods"
        }
    ],
    "sg:phone":"+1 731 855 2123",
    "sg:postcode":"38382",
    "sg:province":"TN",
    "sg:tags":[
        "tractor"
    ],
    "wof:name":"Tennessee Tractor LLC",
    "wof:placetype":"venue"
},
  "geometry": {"coordinates":[-88.93746299999999,35.943834],"type":"Point"}
}