{
  "type": "Feature",
  "properties": {
    "iso:country":"US",
    "sg:address":"1180 Cotton Grove Rd",
    "sg:city":"Jackson",
    "sg:classifiers":[
        {
            "category":"Farming",
            "subcategory":"Farm",
            "type":"Manufacturing & Wholesale Goods"
        }
    ],
    "sg:phone":"+1 731 427 5960",
    "sg:postcode":"38305",
    "sg:province":"TN",
    "sg:tags":[
        "crop",
        "general"
    ],
    "wof:name":"McLeary Farms",
    "wof:placetype":"venue"
},
  "geometry": {"coordinates":[-88.694793,35.66582],"type":"Point"}
}