{
  "type": "Feature",
  "properties": {
    "addr:full":"8079 Kingston Pike Knoxville TN 37919",
    "addr:housenumber":"8079",
    "addr:postcode":"37919",
    "addr:street":"Kingston Pike",
    "iso:country":"US",
    "sg:address":"8079 Kingston Pike",
    "sg:city":"Knoxville",
    "sg:classifiers":[
        {
            "category":"Shopping",
            "subcategory":"Department Store",
            "type":"Retail Goods"
        }
    ],
    "sg:phone":"+1 865 531 1503",
    "sg:postcode":"37919",
    "sg:province":"TN",
    "sg:website":"www.homegoods.com",
    "wof:name":"Home Goods",
    "wof:placetype":"venue"
},
  "geometry": {"coordinates":[-84.045801,35.925453],"type":"Point"}
}