{
  "type": "Feature",
  "properties": {
    "iso:country":"US",
    "sg:address":"439 Athens Rd",
    "sg:city":"Delano",
    "sg:classifiers":[
        {
            "category":"Freight",
            "type":"Transportation"
        }
    ],
    "sg:phone":"+1 423 338 2190",
    "sg:postcode":"37325",
    "sg:province":"TN",
    "sg:tags":[
        "operator",
        "local",
        "trucking"
    ],
    "wof:name":"Guinn Trucking",
    "wof:placetype":"venue"
},
  "geometry": {"coordinates":[-84.666583,35.23056],"type":"Point"}
}