{
  "type": "Feature",
  "properties": {
    "iso:country":"US",
    "sg:address":"104 Cherokee Rd",
    "sg:city":"Hendersonville",
    "sg:classifiers":[
        {
            "category":"Social Services",
            "subcategory":"Child Care",
            "type":"Services"
        }
    ],
    "sg:phone":"+1 615 822 3858",
    "sg:postcode":"37075",
    "sg:province":"TN",
    "sg:tags":[
        "day"
    ],
    "wof:name":"Kidz Kastle Child Care Center",
    "wof:placetype":"venue"
},
  "geometry": {"coordinates":[-86.609487,36.305904],"type":"Point"}
}