{
  "type": "Feature",
  "properties": {
    "addr:full":"301 S College St Lebanon TN 37087",
    "addr:housenumber":"301",
    "addr:postcode":"37087",
    "addr:street":"S College St",
    "iso:country":"US",
    "sg:address":"301 S College St",
    "sg:city":"Lebanon",
    "sg:classifiers":[
        {
            "category":"Home & Garden",
            "subcategory":"Carpets & Floor Coverings",
            "type":"Retail Goods"
        }
    ],
    "sg:phone":"+1 615 444 8270",
    "sg:postcode":"37087",
    "sg:province":"TN",
    "sg:tags":[
        "vinyl"
    ],
    "wof:name":"All About Vinyl",
    "wof:placetype":"venue"
},
  "geometry": {"coordinates":[-86.29055200000001,36.201937],"type":"Point"}
}