{
  "type": "Feature",
  "properties": {
    "iso:country":"US",
    "sg:address":"1000 Rivergate Meadows Dr",
    "sg:city":"Goodlettsville",
    "sg:classifiers":[
        {
            "category":"Shopping",
            "subcategory":"Jewelry",
            "type":"Retail Goods"
        }
    ],
    "sg:phone":"+1 615 851 4498",
    "sg:postcode":"37072",
    "sg:province":"TN",
    "sg:tags":[
        "jeweler"
    ],
    "wof:name":"Intrique Jewelry",
    "wof:placetype":"venue"
},
  "geometry": {"coordinates":[-86.709311,36.297274],"type":"Point"}
}