{
  "type": "Feature",
  "properties": {
    "iso:country":"US",
    "sg:address":"1039 Cottage Stone Ln NE",
    "sg:city":"Cleveland",
    "sg:classifiers":[
        {
            "category":"Social Services",
            "subcategory":"Child Care",
            "type":"Services"
        }
    ],
    "sg:phone":"+1 423 559 9000",
    "sg:postcode":"37312",
    "sg:province":"TN",
    "wof:name":"Little Learners Academy",
    "wof:placetype":"venue"
},
  "geometry": {"coordinates":[-84.83799999999999,35.1797],"type":"Point"}
}