{
  "type": "Feature",
  "properties": {
    "iso:country":"US",
    "sg:address":"220 Browns Ferry Rd",
    "sg:city":"Chattanooga",
    "sg:classifiers":[
        {
            "category":"Restaurant",
            "type":"Food & Drink"
        }
    ],
    "sg:menulink":"http://www.allmenus.com/tn/lookout-mountain/154884-hardees/menu/",
    "sg:phone":"+1 423 821 0522",
    "sg:postcode":"37419",
    "sg:province":"TN",
    "sg:tags":[
        "burger",
        "american"
    ],
    "wof:name":"Hardee's",
    "wof:placetype":"venue"
},
  "geometry": {"coordinates":[-85.36339,35.026526],"type":"Point"}
}