{
  "type": "Feature",
  "properties": {
    "iso:country":"US",
    "sg:address":"4129 W Beaver Creek Dr",
    "sg:city":"Powell",
    "sg:classifiers":[
        {
            "category":"Building & Trades",
            "subcategory":"Construction",
            "type":"Services"
        }
    ],
    "sg:phone":"+1 423 280 4778",
    "sg:postcode":"37849",
    "sg:province":"TN",
    "sg:tags":[
        "contractor"
    ],
    "wof:name":"A & T",
    "wof:placetype":"venue"
},
  "geometry": {"coordinates":[-84.05663,36.009072],"type":"Point"}
}