{
  "type": "Feature",
  "properties": {
    "addr:full":"1222 Wilkinson Rd Knoxville TN 37923",
    "addr:housenumber":"1222",
    "addr:postcode":"37923",
    "addr:street":"Wilkinson Rd",
    "iso:country":"US",
    "sg:address":"1222 Wilkinson Rd",
    "sg:city":"Knoxville",
    "sg:classifiers":[
        {
            "category":"Food & Beverages",
            "subcategory":"Liquor & Beverages",
            "type":"Retail Goods"
        }
    ],
    "sg:phone":"+1 865 690 4038",
    "sg:postcode":"37923",
    "sg:province":"TN",
    "sg:tags":[
        "alcoholic"
    ],
    "wof:name":"Caseys Wines & Spirits LLC",
    "wof:placetype":"venue"
},
  "geometry": {"coordinates":[-84.110781,35.941463],"type":"Point"}
}