{
  "type": "Feature",
  "properties": {
    "iso:country":"US",
    "sg:address":"5847 Stage Rd",
    "sg:city":"Memphis",
    "sg:classifiers":[
        {
            "category":"Retail",
            "subcategory":"Auto Repair",
            "type":"Services"
        }
    ],
    "sg:phone":"+1 901 386 9329",
    "sg:postcode":"38134",
    "sg:province":"TN",
    "sg:tags":[
        "upholstery"
    ],
    "wof:name":"Bartlett Auto Upholstery",
    "wof:placetype":"venue"
},
  "geometry": {"coordinates":[-89.86445999999999,35.204635],"type":"Point"}
}