{
  "type": "Feature",
  "properties": {
    "iso:country":"US",
    "sg:address":"106 E Court St",
    "sg:city":"Somerville",
    "sg:classifiers":[
        {
            "category":"Professional",
            "subcategory":"Management & Consulting",
            "type":"Services"
        }
    ],
    "sg:phone":"+1 901 465 1800",
    "sg:postcode":"38024",
    "sg:province":"TN",
    "sg:tags":[
        "consultant",
        "business"
    ],
    "wof:name":"Corrections Management Corp",
    "wof:placetype":"venue"
},
  "geometry": {"coordinates":[-89.38569099999999,36.0328],"type":"Point"}
}