{
  "type": "Feature",
  "properties": {
    "iso:country":"US",
    "sg:address":"2814 Lebanon Pike",
    "sg:city":"Nashville",
    "sg:classifiers":[
        {
            "category":"Arena",
            "subcategory":"Sports Club",
            "type":"Entertainment"
        }
    ],
    "sg:phone":"+1 615 885 7733",
    "sg:postcode":"37214",
    "sg:province":"TN",
    "sg:tags":[
        "martial art",
        "instruction"
    ],
    "wof:name":"Cooper Karate",
    "wof:placetype":"venue"
},
  "geometry": {"coordinates":[-86.662153,36.167331],"type":"Point"}
}