{
  "type": "Feature",
  "properties": {
    "addr:full":"5933 Woodland Hills Dr Nashville TN 37211",
    "addr:housenumber":"5933",
    "addr:postcode":"37211",
    "addr:street":"Woodland Hills Dr",
    "iso:country":"US",
    "sg:address":"5933 Woodland Hills Dr",
    "sg:city":"Nashville",
    "sg:classifiers":[
        {
            "category":"Building & Trades",
            "subcategory":"Construction",
            "type":"Services"
        }
    ],
    "sg:phone":"+1 615 781 0999",
    "sg:postcode":"37211",
    "sg:province":"TN",
    "sg:tags":[
        "residential",
        "commercial",
        "paving"
    ],
    "wof:name":"Pavecoat Maintenance",
    "wof:placetype":"venue"
},
  "geometry": {"coordinates":[-86.73073599999999,36.038151],"type":"Point"}
}