{
  "type": "Feature",
  "properties": {
    "iso:country":"US",
    "sg:address":"7968 Maple St",
    "sg:city":"Lyles",
    "sg:classifiers":[
        {
            "category":"Shopping",
            "subcategory":"Tobacco",
            "type":"Retail Goods"
        }
    ],
    "sg:phone":"+1 931 670 0538",
    "sg:postcode":"37098",
    "sg:province":"TN",
    "sg:tags":[
        "product"
    ],
    "wof:name":"Smokin Discount Tobacco",
    "wof:placetype":"venue"
},
  "geometry": {"coordinates":[-87.347725,35.901136],"type":"Point"}
}