{
  "type": "Feature",
  "properties": {
    "iso:country":"US",
    "sg:address":"10702 Murdock Road",
    "sg:city":"Knoxville",
    "sg:classifiers":[
        {
            "category":"Professional",
            "subcategory":"Research",
            "type":"Services"
        }
    ],
    "sg:phone":"+1 865 777 1414",
    "sg:postcode":"37932",
    "sg:province":"TN",
    "sg:website":"http://www.nell-one.com",
    "wof:name":"NellOne Therapeutics",
    "wof:placetype":"venue"
},
  "geometry": {"coordinates":[-84.144368,35.915929],"type":"Point"}
}