{
  "type": "Feature",
  "properties": {
    "addr:full":"614 Hwy 76 White House TN 37188",
    "addr:housenumber":"614",
    "addr:postcode":"37188",
    "addr:street":"Hwy 76",
    "iso:country":"US",
    "sg:address":"614 Hwy 76",
    "sg:city":"White House",
    "sg:classifiers":[
        {
            "category":"Shopping",
            "subcategory":"Pharmacy",
            "type":"Retail Goods"
        }
    ],
    "sg:phone":"+1 615 672 4865",
    "sg:postcode":"37188",
    "sg:province":"TN",
    "wof:name":"Eckerd Drugs",
    "wof:placetype":"venue"
},
  "geometry": {"coordinates":[-86.67076299999999,36.469471],"type":"Point"}
}