{
  "type": "Feature",
  "properties": {
    "addr:full":"2350 SE Tater Peeler Rd Lebanon TN 37090",
    "addr:housenumber":"2350",
    "addr:postcode":"37090",
    "addr:street":"Se Tater Peeler Rd",
    "iso:country":"US",
    "sg:address":"2350 SE Tater Peeler Rd",
    "sg:city":"Lebanon",
    "sg:classifiers":[
        {
            "category":"Manufacturing",
            "subcategory":"Building Materials",
            "type":"Manufacturing & Wholesale Goods"
        },
        {
            "category":"Manufacturing",
            "subcategory":"Lumber",
            "type":"Manufacturing & Wholesale Goods"
        }
    ],
    "sg:phone":"+1 615 444 7370",
    "sg:postcode":"37090",
    "sg:province":"TN",
    "sg:tags":[
        "hardwood",
        "mill",
        "mfg"
    ],
    "wof:name":"Sunny's Hardwood",
    "wof:placetype":"venue"
},
  "geometry": {"coordinates":[-86.29391200000001,36.171047],"type":"Point"}
}