{
  "type": "Feature",
  "properties": {
    "addr:full":"4905 Jones Mill Crossland Rd Puryear TN 38251",
    "addr:housenumber":"4905",
    "addr:postcode":"38251",
    "addr:street":"Jones Mill Crossland Rd",
    "iso:country":"US",
    "sg:address":"4905 Jones Mill Crossland Rd",
    "sg:city":"Puryear",
    "sg:classifiers":[
        {
            "category":"Professional",
            "type":"Services"
        }
    ],
    "sg:phone":"+1 731 498 8324",
    "sg:postcode":"38251",
    "sg:province":"TN",
    "wof:name":"Compassionate Friends Inc",
    "wof:placetype":"venue"
},
  "geometry": {"coordinates":[-88.41784699999999,36.474613],"type":"Point"}
}