{
  "type": "Feature",
  "properties": {
    "addr:full":"293 S Walnut Bend Rd Cordova TN 38018",
    "addr:housenumber":"293",
    "addr:postcode":"38018",
    "addr:street":"S Walnut Bend Rd",
    "iso:country":"US",
    "sg:address":"293 S Walnut Bend Rd",
    "sg:city":"Cordova",
    "sg:classifiers":[
        {
            "category":"Professional",
            "type":"Services"
        }
    ],
    "sg:phone":"+1 901 757 5441",
    "sg:postcode":"38018",
    "sg:province":"TN",
    "sg:tags":[
        "establishment"
    ],
    "wof:name":"Mc Cord Enterrpises Inc",
    "wof:placetype":"venue"
},
  "geometry": {"coordinates":[-89.798439,35.121786],"type":"Point"}
}