{
  "type": "Feature",
  "properties": {
    "iso:country":"US",
    "sg:address":"8556 Macon Rd",
    "sg:city":"Cordova",
    "sg:classifiers":[
        {
            "category":"Real Estate",
            "subcategory":"Developer",
            "type":"Services"
        }
    ],
    "sg:phone":"+1 901 758 1100",
    "sg:postcode":"38018",
    "sg:province":"TN",
    "sg:tags":[
        "broker"
    ],
    "wof:name":"Raymond B Gill Co Inc",
    "wof:placetype":"venue"
},
  "geometry": {"coordinates":[-89.77768399999999,35.155968],"type":"Point"}
}