{
  "type": "Feature",
  "properties": {
    "iso:country":"US",
    "sg:address":"400 Enon Springs Rd W",
    "sg:city":"Smyrna",
    "sg:classifiers":[
        {
            "category":"Education",
            "subcategory":"Library",
            "type":"Public Place"
        }
    ],
    "sg:phone":"+1 615 459 4884",
    "sg:postcode":"37167",
    "sg:province":"TN",
    "sg:website":"www.linebaugh.org",
    "wof:name":"Smyrna Public Library",
    "wof:placetype":"venue"
},
  "geometry": {"coordinates":[-86.521759,35.977223],"type":"Point"}
}