{
  "type": "Feature",
  "properties": {
    "iso:country":"US",
    "sg:address":"282 Airways Blvd",
    "sg:city":"Jackson",
    "sg:classifiers":[
        {
            "category":"Professional",
            "subcategory":"Business Services",
            "type":"Services"
        }
    ],
    "sg:phone":"+1 731 427 0674",
    "sg:postcode":"38301",
    "sg:province":"TN",
    "sg:tags":[
        "appraiser"
    ],
    "wof:name":"Turner Realty",
    "wof:placetype":"venue"
},
  "geometry": {"coordinates":[-88.83044,35.616375],"type":"Point"}
}