{
  "type": "Feature",
  "properties": {
    "iso:country":"US",
    "sg:address":"588 Highcrest Dr",
    "sg:city":"Nashville",
    "sg:classifiers":[
        {
            "category":"Manufacturing",
            "subcategory":"Musical Instruments",
            "type":"Manufacturing & Wholesale Goods"
        }
    ],
    "sg:phone":"+1 615 331 4220",
    "sg:postcode":"37211",
    "sg:province":"TN",
    "wof:name":"Bardsong",
    "wof:placetype":"venue"
},
  "geometry": {"coordinates":[-86.728432,36.064213],"type":"Point"}
}