{
  "type": "Feature",
  "properties": {
    "iso:country":"US",
    "sg:address":"8428 Oak Dr",
    "sg:city":"Chattanooga",
    "sg:classifiers":[
        {
            "category":"Organizations",
            "subcategory":"Membership Organization",
            "type":"Services"
        }
    ],
    "sg:phone":"+1 423 899 1969",
    "sg:postcode":"37421",
    "sg:province":"TN",
    "wof:name":"India Assoc of Chattanoog",
    "wof:placetype":"venue"
},
  "geometry": {"coordinates":[-85.137985,34.990002],"type":"Point"}
}