{
  "type": "Feature",
  "properties": {
    "iso:country":"US",
    "sg:address":"2761 E Andrew Johnson Hwy",
    "sg:city":"Greeneville",
    "sg:classifiers":[
        {
            "category":"Restaurant",
            "type":"Food & Drink"
        }
    ],
    "sg:menulink":"http://www.allmenus.com/tn/greeneville/111497-waffle-house/menu/",
    "sg:phone":"+1 423 636 0222",
    "sg:postcode":"37745",
    "sg:province":"TN",
    "sg:tags":[
        "american"
    ],
    "wof:name":"Waffle House",
    "wof:placetype":"venue"
},
  "geometry": {"coordinates":[-82.775565,36.180347],"type":"Point"}
}