{
  "type": "Feature",
  "properties": {
    "iso:country":"US",
    "sg:address":"391 Andy Dr",
    "sg:city":"Atoka",
    "sg:classifiers":[
        {
            "category":"Retail",
            "subcategory":"Repair Shop",
            "type":"Services"
        }
    ],
    "sg:phone":"+1 901 386 8400",
    "sg:postcode":"38023",
    "sg:province":"TN",
    "sg:tags":[
        "lock",
        "locksmith"
    ],
    "wof:name":"Abracadabra Locksmith Svc",
    "wof:placetype":"venue"
},
  "geometry": {"coordinates":[-89.872799,35.403366],"type":"Point"}
}