{
  "type": "Feature",
  "properties": {
    "iso:country":"US",
    "sg:address":"8454 Steinerbridge Ln",
    "sg:city":"Germantown",
    "sg:classifiers":[
        {
            "category":"Retail",
            "subcategory":"Repair Shop",
            "type":"Services"
        }
    ],
    "sg:phone":"+1 901 754 8050",
    "sg:postcode":"38139",
    "sg:province":"TN",
    "wof:name":"G&G Watch & Clock Repair",
    "wof:placetype":"venue"
},
  "geometry": {"coordinates":[-89.77972,35.102363],"type":"Point"}
}