{
  "type": "Feature",
  "properties": {
    "addr:full":"109 W 5th Ave Springfield TN 37172",
    "addr:housenumber":"109",
    "addr:postcode":"37172",
    "addr:street":"W 5Th Ave",
    "iso:country":"US",
    "sg:address":"109 W 5th Ave",
    "sg:city":"Springfield",
    "sg:classifiers":[
        {
            "category":"Professional",
            "subcategory":"Lawyer & Legal Services",
            "type":"Services"
        }
    ],
    "sg:phone":"+1 615 384 5815",
    "sg:postcode":"37172",
    "sg:province":"TN",
    "wof:name":"Brasher Christine Atty At Law",
    "wof:placetype":"venue"
},
  "geometry": {"coordinates":[-86.88567399999999,36.509474],"type":"Point"}
}