{
  "type": "Feature",
  "properties": {
    "iso:country":"US",
    "sg:address":"803 S Cannon Blvd",
    "sg:city":"Shelbyville",
    "sg:classifiers":[
        {
            "category":"Retail",
            "subcategory":"Repair Shop",
            "type":"Services"
        }
    ],
    "sg:phone":"+1 931 684 6547",
    "sg:postcode":"37160",
    "sg:province":"TN",
    "sg:tags":[
        "furniture"
    ],
    "wof:name":"Larry Baucom Furniture RE",
    "wof:placetype":"venue"
},
  "geometry": {"coordinates":[-86.46666399999999,35.473128],"type":"Point"}
}