{
  "type": "Feature",
  "properties": {
    "iso:country":"US",
    "sg:address":"301 S Perimeter Park Dr",
    "sg:city":"Nashville",
    "sg:classifiers":[
        {
            "category":"Manufacturing",
            "subcategory":"Printing",
            "type":"Manufacturing & Wholesale Goods"
        }
    ],
    "sg:phone":"+1 615 893 3544",
    "sg:postcode":"37211",
    "sg:province":"TN",
    "sg:tags":[
        "publisher"
    ],
    "wof:name":"Elhi Publishers",
    "wof:placetype":"venue"
},
  "geometry": {"coordinates":[-86.695955,36.086867],"type":"Point"}
}