{
  "type": "Feature",
  "properties": {
    "iso:country":"US",
    "sg:address":"624 S Willett St",
    "sg:city":"Memphis",
    "sg:classifiers":[
        {
            "category":"Health Services",
            "subcategory":"Doctor",
            "type":"Services"
        }
    ],
    "sg:phone":"+1 901 276 2600",
    "sg:postcode":"38104",
    "sg:province":"TN",
    "sg:tags":[
        "physician",
        "surgeon"
    ],
    "wof:name":"William D Falvey MD",
    "wof:placetype":"venue"
},
  "geometry": {"coordinates":[-90.010198,35.128837],"type":"Point"}
}