{
  "type": "Feature",
  "properties": {
    "iso:country":"US",
    "sg:address":"4815 Nolensville Pike",
    "sg:city":"Nashville",
    "sg:classifiers":[
        {
            "category":"Autos & Motor Vehicles",
            "subcategory":"Auto Supplies",
            "type":"Retail Goods"
        }
    ],
    "sg:phone":"+1 615 832 6215",
    "sg:postcode":"37211",
    "sg:province":"TN",
    "sg:tags":[
        "automobile",
        "parts"
    ],
    "sg:website":"www.autozone.com",
    "wof:name":"Autozone",
    "wof:placetype":"venue"
},
  "geometry": {"coordinates":[-86.71708,36.063425],"type":"Point"}
}