{
  "type": "Feature",
  "properties": {
    "addr:full":"260 16th Ave Dayton TN 37321",
    "addr:housenumber":"260",
    "addr:postcode":"37321",
    "addr:street":"16Th Ave",
    "iso:country":"US",
    "sg:address":"260 16th Ave",
    "sg:city":"Dayton",
    "sg:classifiers":[
        {
            "category":"Shopping",
            "subcategory":"Department Store",
            "type":"Retail Goods"
        }
    ],
    "sg:phone":"+1 865 882 5500",
    "sg:postcode":"37321",
    "sg:province":"TN",
    "wof:name":"Sears Roebuck & Co",
    "wof:placetype":"venue"
},
  "geometry": {"coordinates":[-85.00309900000001,35.508831],"type":"Point"}
}