{
  "type": "Feature",
  "properties": {
    "addr:full":"1342 Church St Christiana TN 37037",
    "addr:housenumber":"1342",
    "addr:postcode":"37037",
    "addr:street":"Church St",
    "iso:country":"US",
    "sg:address":"1342 Church St",
    "sg:city":"Christiana",
    "sg:classifiers":[
        {
            "category":"Organizations",
            "subcategory":"Religious Organization",
            "type":"Services"
        }
    ],
    "sg:phone":"+1 615 890 5329",
    "sg:postcode":"37037",
    "sg:province":"TN",
    "sg:tags":[
        "church"
    ],
    "wof:name":"Christiana Baptist Church",
    "wof:placetype":"venue"
},
  "geometry": {"coordinates":[-86.39517600000001,35.709581],"type":"Point"}
}