{
  "type": "Feature",
  "properties": {
    "iso:country":"US",
    "sg:address":"1609 Keeble St",
    "sg:city":"Chattanooga",
    "sg:classifiers":[
        {
            "category":"Retail",
            "subcategory":"Auto Repair",
            "type":"Services"
        }
    ],
    "sg:phone":"+1 423 867 5829",
    "sg:postcode":"37412",
    "sg:province":"TN",
    "sg:tags":[
        "general"
    ],
    "wof:name":"Harrison Transmission",
    "wof:placetype":"venue"
},
  "geometry": {"coordinates":[-85.222148,34.987754],"type":"Point"}
}