{
  "type": "Feature",
  "properties": {
    "addr:full":"45 W Shelby Dr Memphis TN 38109",
    "addr:housenumber":"45",
    "addr:postcode":"38109",
    "addr:street":"W Shelby Dr",
    "iso:country":"US",
    "sg:address":"45 W Shelby Dr",
    "sg:city":"Memphis",
    "sg:classifiers":[
        {
            "category":"Organizations",
            "subcategory":"Religious Organization",
            "type":"Services"
        }
    ],
    "sg:phone":"+1 901 789 5182",
    "sg:postcode":"38109",
    "sg:province":"TN",
    "sg:tags":[
        "church"
    ],
    "wof:name":"St Matthews Temple Deliverance",
    "wof:placetype":"venue"
},
  "geometry": {"coordinates":[-90.06767499999999,35.020827],"type":"Point"}
}