{
  "type": "Feature",
  "properties": {
    "iso:country":"US",
    "sg:address":"2075 S Main St",
    "sg:city":"Milan",
    "sg:classifiers":[
        {
            "category":"Professional",
            "subcategory":"Lawyer & Legal Services",
            "type":"Services"
        }
    ],
    "sg:phone":"+1 731 686 7158",
    "sg:postcode":"38358",
    "sg:province":"TN",
    "sg:tags":[
        "attorney"
    ],
    "wof:name":"Knott & Herndon",
    "wof:placetype":"venue"
},
  "geometry": {"coordinates":[-88.75706599999999,35.917842],"type":"Point"}
}