{
  "type": "Feature",
  "properties": {
    "iso:country":"US",
    "sg:address":"410 Dinah Shore Blvd",
    "sg:city":"Winchester",
    "sg:classifiers":[
        {
            "category":"Government",
            "subcategory":"Office",
            "type":"Public Place"
        }
    ],
    "sg:phone":"+1 931 962 1140",
    "sg:postcode":"37398",
    "sg:province":"TN",
    "sg:tags":[
        "forestry"
    ],
    "wof:name":"Tennessee Forestry Division",
    "wof:placetype":"venue"
},
  "geometry": {"coordinates":[-86.108467,35.189143],"type":"Point"}
}