{
  "type": "Feature",
  "properties": {
    "iso:country":"US",
    "sg:address":"2670 Union Ave Exd",
    "sg:city":"Memphis",
    "sg:classifiers":[
        {
            "category":"Professional",
            "subcategory":"Detective & Security Services",
            "type":"Services"
        }
    ],
    "sg:phone":"+1 901 458 1294",
    "sg:postcode":"38112",
    "sg:province":"TN",
    "sg:website":"www.initialsecurity.com",
    "wof:name":"Initial Security",
    "wof:placetype":"venue"
},
  "geometry": {"coordinates":[-89.973664,35.135653],"type":"Point"}
}