{
  "type": "Feature",
  "properties": {
    "iso:country":"US",
    "sg:address":"1605 S High St",
    "sg:city":"Columbia",
    "sg:classifiers":[
        {
            "category":"Retail",
            "subcategory":"Auto Repair",
            "type":"Services"
        }
    ],
    "sg:phone":"+1 931 540 0234",
    "sg:postcode":"38401",
    "sg:province":"TN",
    "sg:tags":[
        "body"
    ],
    "wof:name":"Supercruiser",
    "wof:placetype":"venue"
},
  "geometry": {"coordinates":[-87.038816,35.603112],"type":"Point"}
}