{
  "type": "Feature",
  "properties": {
    "iso:country":"US",
    "sg:address":"221 Franklin Pl",
    "sg:city":"Clinton",
    "sg:classifiers":[
        {
            "category":"Retail",
            "subcategory":"Auto Repair",
            "type":"Services"
        }
    ],
    "sg:phone":"+1 865 463 0531",
    "sg:postcode":"37716",
    "sg:province":"TN",
    "sg:tags":[
        "repairing",
        "automobile"
    ],
    "wof:name":"Aisin Automotive",
    "wof:placetype":"venue"
},
  "geometry": {"coordinates":[-84.115488,36.108834],"type":"Point"}
}