{
  "type": "Feature",
  "properties": {
    "iso:country":"US",
    "sg:address":"2155 Ethlyn Ave",
    "sg:city":"Memphis",
    "sg:classifiers":[
        {
            "category":"Building & Trades",
            "subcategory":"Construction",
            "type":"Services"
        }
    ],
    "sg:phone":"+1 901 949 1583",
    "sg:postcode":"38114",
    "sg:province":"TN",
    "sg:tags":[
        "home",
        "improvement"
    ],
    "wof:name":"Payless Home Improvement",
    "wof:placetype":"venue"
},
  "geometry": {"coordinates":[-89.99230799999999,35.104197],"type":"Point"}
}