{
  "type": "Feature",
  "properties": {
    "addr:full":"831 Tusculum Blvd Greeneville TN 37745",
    "addr:housenumber":"831",
    "addr:postcode":"37745",
    "addr:street":"Tusculum Blvd",
    "iso:country":"US",
    "sg:address":"831 Tusculum Blvd",
    "sg:city":"Greeneville",
    "sg:classifiers":[
        {
            "category":"Banks & Credit Unions",
            "subcategory":"Bank",
            "type":"Services"
        }
    ],
    "sg:phone":"+1 423 639 6584",
    "sg:postcode":"37745",
    "sg:province":"TN",
    "sg:tags":[
        "cashing",
        "check"
    ],
    "wof:name":"Check Into Cash",
    "wof:placetype":"venue"
},
  "geometry": {"coordinates":[-82.81465,36.170512],"type":"Point"}
}