{
  "type": "Feature",
  "properties": {
    "addr:full":"1200 Davidson St Nashville TN 37213",
    "addr:housenumber":"1200",
    "addr:postcode":"37213",
    "addr:street":"Davidson St",
    "iso:country":"US",
    "sg:address":"1200 Davidson St",
    "sg:city":"Nashville",
    "sg:classifiers":[
        {
            "category":"Wholesale",
            "subcategory":"Auto Parts",
            "type":"Manufacturing & Wholesale Goods"
        }
    ],
    "sg:phone":"+1 615 226 4428",
    "sg:postcode":"37213",
    "sg:province":"TN",
    "sg:tags":[
        "tire"
    ],
    "sg:website":"www.ampactire.com",
    "wof:name":"AM Pac Tire Dist Inc",
    "wof:placetype":"venue"
},
  "geometry": {"coordinates":[-86.74879799999999,36.162593],"type":"Point"}
}