{
  "type": "Feature",
  "properties": {
    "addr:full":"121 Scott St Tellico Plains TN 37385",
    "addr:housenumber":"121",
    "addr:postcode":"37385",
    "addr:street":"Scott St",
    "iso:country":"US",
    "sg:address":"121 Scott St",
    "sg:city":"Tellico Plains",
    "sg:classifiers":[
        {
            "category":"Wholesale",
            "subcategory":"Plants",
            "type":"Manufacturing & Wholesale Goods"
        },
        {
            "category":"Shopping",
            "subcategory":"Gifts & Souvenirs",
            "type":"Retail Goods"
        }
    ],
    "sg:phone":"+1 423 253 2400",
    "sg:postcode":"37385",
    "sg:province":"TN",
    "sg:tags":[
        "shop",
        "supply"
    ],
    "wof:name":"Stone Cottage Shops & Gardens",
    "wof:placetype":"venue"
},
  "geometry": {"coordinates":[-84.295045,35.362219],"type":"Point"}
}