{
  "type": "Feature",
  "properties": {
    "iso:country":"US",
    "sg:address":"10825 State Hwy 28",
    "sg:city":"Whitwell",
    "sg:classifiers":[
        {
            "category":"Home & Garden",
            "subcategory":"Building Materials",
            "type":"Retail Goods"
        }
    ],
    "sg:phone":"+1 423 658 0999",
    "sg:postcode":"37397",
    "sg:province":"TN",
    "sg:tags":[
        "stone"
    ],
    "wof:name":"Seven Springs Stone",
    "wof:placetype":"venue"
},
  "geometry": {"coordinates":[-85.53872,35.159496],"type":"Point"}
}