{
  "type": "Feature",
  "properties": {
    "iso:country":"US",
    "sg:address":"200 E 4th Ave",
    "sg:city":"Dayton",
    "sg:classifiers":[
        {
            "category":"Social Services",
            "subcategory":"Job Training",
            "type":"Services"
        }
    ],
    "sg:phone":"+1 423 570 1107",
    "sg:postcode":"37321",
    "sg:province":"TN",
    "sg:tags":[
        "employment"
    ],
    "wof:name":"Southeast Career Ctr",
    "wof:placetype":"venue"
},
  "geometry": {"coordinates":[-85.010723,35.495672],"type":"Point"}
}