{
  "type": "Feature",
  "properties": {
    "iso:country":"US",
    "sg:address":"514 Parkway Blvd",
    "sg:city":"Elizabethton",
    "sg:classifiers":[
        {
            "category":"Building & Trades",
            "subcategory":"Construction",
            "type":"Services"
        }
    ],
    "sg:phone":"+1 423 542 9233",
    "sg:postcode":"37643",
    "sg:province":"TN",
    "sg:tags":[
        "contractor"
    ],
    "wof:name":"P & H Heating and AC",
    "wof:placetype":"venue"
},
  "geometry": {"coordinates":[-82.246242,36.338093],"type":"Point"}
}