{
  "type": "Feature",
  "properties": {
    "iso:country":"US",
    "sg:address":"485 E South St",
    "sg:city":"Collierville",
    "sg:phone":"+1 901 850 0661",
    "sg:postcode":"38017",
    "sg:province":"TN",
    "sg:website":"http://www.thecleaningauthority.com",
    "wof:name":"The Cleaning Authority",
    "wof:placetype":"venue"
},
  "geometry": {"coordinates":[-89.654551,35.03875],"type":"Point"}
}