{
  "type": "Feature",
  "properties": {
    "iso:country":"US",
    "sg:address":"82 Mason Pl",
    "sg:city":"Decherd",
    "sg:classifiers":[
        {
            "category":"Professional",
            "subcategory":"Secretarial Services",
            "type":"Services"
        }
    ],
    "sg:phone":"+1 931 967 6960",
    "sg:postcode":"37324",
    "sg:province":"TN",
    "sg:tags":[
        "reporting"
    ],
    "wof:name":"Desktop Cobb Publishing",
    "wof:placetype":"venue"
},
  "geometry": {"coordinates":[-86.04494800000001,35.209901],"type":"Point"}
}