{
  "type": "Feature",
  "properties": {
    "iso:country":"US",
    "sg:address":"5740 State Hwy 76 E",
    "sg:city":"Springfield",
    "sg:classifiers":[
        {
            "category":"Organizations",
            "subcategory":"Religious Organization",
            "type":"Services"
        }
    ],
    "sg:phone":"+1 615 384 4327",
    "sg:postcode":"37172",
    "sg:province":"TN",
    "wof:name":"Oakland Baptist Church",
    "wof:placetype":"venue"
},
  "geometry": {"coordinates":[-86.830588,36.500723],"type":"Point"}
}