{
  "type": "Feature",
  "properties": {
    "iso:country":"US",
    "sg:address":"2805 Clarke Rd",
    "sg:city":"Memphis",
    "sg:classifiers":[
        {
            "category":"Health Services",
            "subcategory":"Doctor",
            "type":"Services"
        }
    ],
    "sg:phone":"+1 901 363 3600",
    "sg:postcode":"38115",
    "sg:province":"TN",
    "sg:tags":[
        "clinic"
    ],
    "wof:name":"Mid South Pediatric & Adult",
    "wof:placetype":"venue"
},
  "geometry": {"coordinates":[-89.87562200000001,35.072147],"type":"Point"}
}