{
  "type": "Feature",
  "properties": {
    "iso:country":"US",
    "sg:address":"398 Dry Fork Rd S",
    "sg:city":"Gallatin",
    "sg:phone":"+1 615 452 2544",
    "sg:postcode":"37066",
    "sg:province":"TN",
    "sg:tags":[
        "farm",
        "corn",
        "tobacco"
    ],
    "wof:name":"Greenwood Farms",
    "wof:placetype":"venue"
},
  "geometry": {"coordinates":[-86.357674,36.459821],"type":"Point"}
}