{
  "type": "Feature",
  "properties": {
    "iso:country":"US",
    "sg:address":"3173 Newport Hwy",
    "sg:city":"Sevierville",
    "sg:classifiers":[
        {
            "category":"Education",
            "subcategory":"Special Training",
            "type":"Public Place"
        }
    ],
    "sg:phone":"+1 865 774 2777",
    "sg:postcode":"37876",
    "sg:province":"TN",
    "sg:tags":[
        "instruction",
        "driving"
    ],
    "wof:name":"Smokey Mountain Trucking Inst",
    "wof:placetype":"venue"
},
  "geometry": {"coordinates":[-83.415657,35.90581],"type":"Point"}
}