{
  "type": "Feature",
  "properties": {
    "iso:country":"US",
    "sg:address":"510 Hospital Dr",
    "sg:city":"Madison",
    "sg:classifiers":[
        {
            "category":"Health Services",
            "subcategory":"Doctor",
            "type":"Services"
        }
    ],
    "sg:phone":"+1 615 868 6181",
    "sg:postcode":"37115",
    "sg:province":"TN",
    "sg:tags":[
        "medical"
    ],
    "wof:name":"Jewett & Murphy M D P Dr",
    "wof:placetype":"venue"
},
  "geometry": {"coordinates":[-86.68436,36.254084],"type":"Point"}
}