{
  "type": "Feature",
  "properties": {
    "iso:country":"US",
    "sg:address":"2911 Brunswick Rd",
    "sg:city":"Memphis",
    "sg:classifiers":[
        {
            "category":"Education",
            "subcategory":"School",
            "type":"Public Place"
        }
    ],
    "sg:phone":"+1 901 373 0914",
    "sg:postcode":"38133",
    "sg:province":"TN",
    "wof:name":"Rennaissance Academy",
    "wof:placetype":"venue"
},
  "geometry": {"coordinates":[-89.775177,35.204781],"type":"Point"}
}