{
  "type": "Feature",
  "properties": {
    "addr:full":"110 Glancy St Goodlettsville TN 37072",
    "addr:housenumber":"110",
    "addr:postcode":"37072",
    "addr:street":"Glancy St",
    "iso:country":"US",
    "sg:address":"110 Glancy St",
    "sg:city":"Goodlettsville",
    "sg:classifiers":[
        {
            "category":"Professional",
            "subcategory":"Lawyer & Legal Services",
            "type":"Services"
        }
    ],
    "sg:phone":"+1 615 865 4750",
    "sg:postcode":"37072",
    "sg:province":"TN",
    "sg:tags":[
        "attorney"
    ],
    "wof:name":"Law Offices of W D Castleman",
    "wof:placetype":"venue"
},
  "geometry": {"coordinates":[-86.705179,36.296638],"type":"Point"}
}