{
  "type": "Feature",
  "properties": {
    "iso:country":"US",
    "sg:address":"4229 Brackenwood Dr",
    "sg:city":"Old Hickory",
    "sg:classifiers":[
        {
            "category":"Wholesale",
            "subcategory":"Farm Supplies",
            "type":"Manufacturing & Wholesale Goods"
        }
    ],
    "sg:phone":"+1 615 847 4292",
    "sg:postcode":"37138",
    "sg:province":"TN",
    "wof:name":"Garden Sales Associates Inc",
    "wof:placetype":"venue"
},
  "geometry": {"coordinates":[-86.627471,36.222766],"type":"Point"}
}