{
  "type": "Feature",
  "properties": {
    "iso:country":"US",
    "sg:address":"3145 E Andrew Johnson Hwy",
    "sg:city":"Greeneville",
    "sg:classifiers":[
        {
            "category":"Health Services",
            "subcategory":"Clinic",
            "type":"Services"
        },
        {
            "category":"Health Services",
            "subcategory":"Doctor",
            "type":"Services"
        }
    ],
    "sg:phone":"+1 423 638 0433",
    "sg:postcode":"37745",
    "sg:province":"TN",
    "sg:tags":[
        "physician",
        "surgeon",
        "specialty",
        "outpatient"
    ],
    "wof:name":"Weight Loss Management Center",
    "wof:placetype":"venue"
},
  "geometry": {"coordinates":[-82.770601,36.183403],"type":"Point"}
}