{
  "type": "Feature",
  "properties": {
    "iso:country":"US",
    "sg:address":"2080 Winchester Rd",
    "sg:city":"Memphis",
    "sg:classifiers":[
        {
            "category":"Real Estate",
            "subcategory":"Real Estate Agent",
            "type":"Services"
        }
    ],
    "sg:phone":"+1 901 345 3249",
    "sg:postcode":"38116",
    "sg:province":"TN",
    "wof:name":"Signature Realty",
    "wof:placetype":"venue"
},
  "geometry": {"coordinates":[-89.99153800000001,35.053382],"type":"Point"}
}