{
  "type": "Feature",
  "properties": {
    "iso:country":"US",
    "sg:address":"224 Bordeaux Ct",
    "sg:city":"Smyrna",
    "sg:classifiers":[
        {
            "category":"Building & Trades",
            "subcategory":"Cleaning & Sanitation",
            "type":"Services"
        }
    ],
    "sg:phone":"+1 615 223 1075",
    "sg:postcode":"37167",
    "sg:province":"TN",
    "sg:tags":[
        "maintenance"
    ],
    "wof:name":"Aprils Cleaning Service",
    "wof:placetype":"venue"
},
  "geometry": {"coordinates":[-86.494036,35.980408],"type":"Point"}
}