{
  "type": "Feature",
  "properties": {
    "addr:full":"4262 Rushing River Rd Sevierville TN 37876",
    "addr:housenumber":"4262",
    "addr:postcode":"37876",
    "addr:street":"Rushing River Rd",
    "iso:country":"US",
    "sg:address":"4262 Rushing River Rd",
    "sg:city":"Sevierville",
    "sg:classifiers":[
        {
            "category":"Banks & Credit Unions",
            "subcategory":"Investment Brokerage",
            "type":"Services"
        }
    ],
    "sg:phone":"+1 865 436 7598",
    "sg:postcode":"37876",
    "sg:province":"TN",
    "sg:tags":[
        "advisory"
    ],
    "wof:name":"Robert Manderscheid",
    "wof:placetype":"venue"
},
  "geometry": {"coordinates":[-83.40595999999999,35.775526],"type":"Point"}
}