{
  "type": "Feature",
  "properties": {
    "addr:full":"136 Flanary St Kingsport TN 37660",
    "addr:housenumber":"136",
    "addr:postcode":"37660",
    "addr:street":"Flanary St",
    "iso:country":"US",
    "sg:address":"136 Flanary St",
    "sg:city":"Kingsport",
    "sg:classifiers":[
        {
            "category":"Shopping",
            "type":"Retail Goods"
        }
    ],
    "sg:phone":"+1 423 247 9909",
    "sg:postcode":"37660",
    "sg:province":"TN",
    "sg:tags":[
        "merchandise"
    ],
    "wof:name":"Bill Begley Monument Co",
    "wof:placetype":"venue"
},
  "geometry": {"coordinates":[-82.558601,36.59474],"type":"Point"}
}