{
  "type": "Feature",
  "properties": {
    "addr:full":"4921 Hickory Hill Rd Memphis TN 38141",
    "addr:housenumber":"4921",
    "addr:postcode":"38141",
    "addr:street":"Hickory Hill Rd",
    "iso:country":"US",
    "sg:address":"4921 Hickory Hill Rd",
    "sg:city":"Memphis",
    "sg:classifiers":[
        {
            "category":"Building & Trades",
            "subcategory":"Landscaping Services",
            "type":"Services"
        }
    ],
    "sg:phone":"+1 901 521 0180",
    "sg:postcode":"38141",
    "sg:province":"TN",
    "wof:name":"All Memphis Lawn Maintenance",
    "wof:placetype":"venue"
},
  "geometry": {"coordinates":[-89.866131,35.015961],"type":"Point"}
}