{
  "type": "Feature",
  "properties": {
    "addr:full":"8145 US Hwy 51 N Millington TN 38053",
    "addr:housenumber":"8145",
    "addr:postcode":"38053",
    "addr:street":"Us Hwy 51 N",
    "iso:country":"US",
    "sg:address":"8145 US Hwy 51 N",
    "sg:city":"Millington",
    "sg:classifiers":[
        {
            "category":"Wholesale",
            "subcategory":"Stationery",
            "type":"Manufacturing & Wholesale Goods"
        }
    ],
    "sg:phone":"+1 901 873 0002",
    "sg:postcode":"38053",
    "sg:province":"TN",
    "sg:tags":[
        "paper"
    ],
    "wof:name":"Ryder Truck Rental-One-Way",
    "wof:placetype":"venue"
},
  "geometry": {"coordinates":[-89.90433400000001,35.346796],"type":"Point"}
}