{
  "type": "Feature",
  "properties": {
    "iso:country":"US",
    "sg:address":"5290 Crestview Dr",
    "sg:city":"Memphis",
    "sg:classifiers":[
        {
            "category":"Autos & Motor Vehicles",
            "subcategory":"Fuel & Gas Station",
            "type":"Retail Goods"
        },
        {
            "category":"Autos & Motor Vehicles",
            "subcategory":"Auto Supplies",
            "type":"Retail Goods"
        },
        {
            "category":"Retail",
            "subcategory":"Repair Shop",
            "type":"Services"
        },
        {
            "category":"Building & Trades",
            "subcategory":"Plumbing",
            "type":"Services"
        },
        {
            "category":"Retail",
            "subcategory":"Auto Repair",
            "type":"Services"
        }
    ],
    "sg:phone":"+1 901 273 7833",
    "sg:postcode":"38134",
    "sg:province":"TN",
    "sg:tags":[
        "radiators-repairing",
        "engine",
        "classic",
        "generators-automotive",
        "restoration-antique",
        "automobile",
        "lube",
        "equipment-service",
        "repair-automobile",
        "wheel",
        "rebuilding",
        "oil",
        "electric",
        "radiator",
        "exchange",
        "automotive",
        "emission",
        "diagnostic",
        "servicing-automotive",
        "axle",
        "alignment-frame",
        "injection",
        "air conditioning",
        "tune",
        "service-automotive",
        "repairing",
        "installation",
        "alternator",
        "transmission",
        "clutch",
        "sale",
        "truck",
        "customizing",
        "referral",
        "road"
    ],
    "sg:website":"http://www.yext.com/p/superpages/trotter-s-dealer-s-wholesale-repair-memphis-tennessee.html",
    "wof:name":"Trotter's Dealers Wholesale Repair",
    "wof:placetype":"venue"
},
  "geometry": {"coordinates":[-89.886315,35.170985],"type":"Point"}
}