{
  "type": "Feature",
  "properties": {
    "iso:country":"US",
    "sg:address":"6007 Ridan Dr",
    "sg:city":"Knoxville",
    "sg:classifiers":[
        {
            "category":"Shopping",
            "subcategory":"Discount & Variety Stores",
            "type":"Retail Goods"
        }
    ],
    "sg:phone":"+1 865 584 7289",
    "sg:postcode":"37909",
    "sg:province":"TN",
    "sg:tags":[
        "merchandise",
        "general"
    ],
    "wof:name":"Peacock Sales Co",
    "wof:placetype":"venue"
},
  "geometry": {"coordinates":[-84.016317,35.956441],"type":"Point"}
}