{
  "type": "Feature",
  "properties": {
    "iso:country":"US",
    "sg:address":"760 N Ocoee St",
    "sg:city":"Cleveland",
    "sg:classifiers":[
        {
            "category":"Real Estate",
            "subcategory":"Real Estate Agent",
            "type":"Services"
        }
    ],
    "sg:phone":"+1 423 614 0051",
    "sg:postcode":"37311",
    "sg:province":"TN",
    "wof:name":"New Venture Realty",
    "wof:placetype":"venue"
},
  "geometry": {"coordinates":[-84.87327399999999,35.16297],"type":"Point"}
}