{
  "type": "Feature",
  "properties": {
    "addr:full":"415 Sub Station Rd Unionville TN 37180",
    "addr:housenumber":"415",
    "addr:postcode":"37180",
    "addr:street":"Sub Station Rd",
    "iso:country":"US",
    "sg:address":"415 Sub Station Rd",
    "sg:city":"Unionville",
    "sg:classifiers":[
        {
            "category":"Farming",
            "subcategory":"Farm",
            "type":"Manufacturing & Wholesale Goods"
        }
    ],
    "sg:phone":"+1 931 294 5139",
    "sg:postcode":"37180",
    "sg:province":"TN",
    "wof:name":"Larry King Farms",
    "wof:placetype":"venue"
},
  "geometry": {"coordinates":[-86.57316899999999,35.625119],"type":"Point"}
}