{
  "type": "Feature",
  "properties": {
    "iso:country":"US",
    "sg:address":"1428 Bethvale Dr",
    "sg:city":"Greenback",
    "sg:classifiers":[
        {
            "category":"Building & Trades",
            "subcategory":"Construction",
            "type":"Services"
        }
    ],
    "sg:phone":"+1 865 856 0990",
    "sg:postcode":"37742",
    "sg:province":"TN",
    "sg:tags":[
        "hanging",
        "contractor"
    ],
    "wof:name":"Warwick Painting",
    "wof:placetype":"venue"
},
  "geometry": {"coordinates":[-84.12079900000001,35.700673],"type":"Point"}
}