{
  "type": "Feature",
  "properties": {
    "iso:country":"US",
    "sg:address":"227 Cheswick Ct",
    "sg:city":"Nashville",
    "sg:classifiers":[
        {
            "category":"Organizations",
            "subcategory":"Religious Organization",
            "type":"Services"
        }
    ],
    "sg:phone":"+1 615 665 8981",
    "sg:postcode":"37215",
    "sg:province":"TN",
    "wof:name":"Christ P Koulis",
    "wof:placetype":"venue"
},
  "geometry": {"coordinates":[-86.828363,36.092949],"type":"Point"}
}