{
  "type": "Feature",
  "properties": {
    "iso:country":"US",
    "sg:address":"2516 Old Hwy 68",
    "sg:city":"Sweetwater",
    "sg:classifiers":[
        {
            "category":"Shopping",
            "subcategory":"Computers & Home Electronics",
            "type":"Retail Goods"
        }
    ],
    "sg:phone":"+1 423 337 0866",
    "sg:postcode":"37874",
    "sg:province":"TN",
    "sg:tags":[
        "consumer"
    ],
    "wof:name":"Valley Satellite Inc",
    "wof:placetype":"venue"
},
  "geometry": {"coordinates":[-84.40089500000001,35.547187],"type":"Point"}
}