{
  "type": "Feature",
  "properties": {
    "iso:country":"US",
    "sg:address":"911 Auburntown Rd",
    "sg:city":"Woodbury",
    "sg:classifiers":[
        {
            "category":"Building & Trades",
            "subcategory":"Construction",
            "type":"Services"
        }
    ],
    "sg:phone":"+1 615 563 1204",
    "sg:postcode":"37190",
    "sg:province":"TN",
    "sg:tags":[
        "contractor"
    ],
    "wof:name":"Margie S Roofing",
    "wof:placetype":"venue"
},
  "geometry": {"coordinates":[-86.091685,35.837838],"type":"Point"}
}