{
  "type": "Feature",
  "properties": {
    "addr:full":"5445 Hill Road Cir Nashville TN 37220",
    "addr:housenumber":"5445",
    "addr:postcode":"37220",
    "addr:street":"Hill Road Cir",
    "iso:country":"US",
    "sg:address":"5445 Hill Road Cir",
    "sg:city":"Nashville",
    "sg:classifiers":[
        {
            "category":"Restaurant",
            "type":"Food & Drink"
        }
    ],
    "sg:phone":"+1 615 972 2433",
    "sg:postcode":"37220",
    "sg:province":"TN",
    "sg:tags":[
        "eating"
    ],
    "wof:name":"Dining At Your Place",
    "wof:placetype":"venue"
},
  "geometry": {"coordinates":[-86.753406,36.050265],"type":"Point"}
}