{
  "type": "Feature",
  "properties": {
    "iso:country":"US",
    "sg:address":"3521 Graceland Dr",
    "sg:city":"Memphis",
    "sg:classifiers":[
        {
            "category":"Building & Trades",
            "subcategory":"Construction",
            "type":"Services"
        }
    ],
    "sg:phone":"+1 901 346 2799",
    "sg:postcode":"38116",
    "sg:province":"TN",
    "sg:tags":[
        "painter"
    ],
    "wof:name":"Benchmark Painting",
    "wof:placetype":"venue"
},
  "geometry": {"coordinates":[-90.01581899999999,35.053131],"type":"Point"}
}