{
  "type": "Feature",
  "properties": {
    "addr:full":"2000 Richard Jones Rd Nashville TN 37215",
    "addr:housenumber":"2000",
    "addr:postcode":"37215",
    "addr:street":"Richard Jones Rd",
    "iso:country":"US",
    "sg:address":"2000 Richard Jones Rd",
    "sg:city":"Nashville",
    "sg:classifiers":[
        {
            "category":"Education",
            "subcategory":"Special Training",
            "type":"Public Place"
        }
    ],
    "sg:phone":"+1 615 292 3900",
    "sg:postcode":"37215",
    "sg:province":"TN",
    "sg:tags":[
        "tutoring"
    ],
    "sg:website":"www.educate.com",
    "wof:name":"Sylvan Learning Ctr",
    "wof:placetype":"venue"
},
  "geometry": {"coordinates":[-86.814601,36.1048],"type":"Point"}
}