{
  "type": "Feature",
  "properties": {
    "iso:country":"US",
    "sg:address":"117 W Court Ave",
    "sg:city":"Selmer",
    "sg:classifiers":[
        {
            "category":"Restaurant",
            "type":"Food & Drink"
        }
    ],
    "sg:phone":"+1 731 645 9188",
    "sg:postcode":"38375",
    "sg:province":"TN",
    "sg:tags":[
        "eating"
    ],
    "wof:name":"China King",
    "wof:placetype":"venue"
},
  "geometry": {"coordinates":[-88.59443899999999,35.171778],"type":"Point"}
}