{
  "type": "Feature",
  "properties": {
    "iso:country":"US",
    "sg:address":"2135 Chapman Rd",
    "sg:city":"Chattanooga",
    "sg:classifiers":[
        {
            "category":"Retail",
            "subcategory":"Auto Repair",
            "type":"Services"
        }
    ],
    "sg:phone":"+1 423 899 4510",
    "sg:postcode":"37421",
    "sg:province":"TN",
    "sg:tags":[
        "body",
        "automobile",
        "painting"
    ],
    "sg:website":"www.economyhonda.com",
    "wof:name":"Economy Honda Body Shop",
    "wof:placetype":"venue"
},
  "geometry": {"coordinates":[-85.188789,35.058141],"type":"Point"}
}