{
  "type": "Feature",
  "properties": {
    "iso:country":"US",
    "sg:address":"5984 Hickory Ridge Rd",
    "sg:city":"Lebanon",
    "sg:classifiers":[
        {
            "category":"Building & Trades",
            "subcategory":"Construction",
            "type":"Services"
        }
    ],
    "sg:phone":"+1 615 449 8812",
    "sg:postcode":"37090",
    "sg:province":"TN",
    "sg:tags":[
        "contractor"
    ],
    "wof:name":"Associated Roofing Inc",
    "wof:placetype":"venue"
},
  "geometry": {"coordinates":[-86.40231199999999,36.198674],"type":"Point"}
}