{
  "type": "Feature",
  "properties": {
    "addr:full":"4646 Poplar Ave Memphis TN 38117",
    "addr:housenumber":"4646",
    "addr:postcode":"38117",
    "addr:street":"Poplar Ave",
    "iso:country":"US",
    "sg:address":"4646 Poplar Ave",
    "sg:city":"Memphis",
    "sg:classifiers":[
        {
            "category":"Professional",
            "type":"Services"
        }
    ],
    "sg:phone":"+1 901 680 9201",
    "sg:postcode":"38117",
    "sg:province":"TN",
    "sg:tags":[
        "establishment"
    ],
    "wof:name":"Medical Reimbursement Review",
    "wof:placetype":"venue"
},
  "geometry": {"coordinates":[-89.90776099999999,35.116714],"type":"Point"}
}