{
  "type": "Feature",
  "properties": {
    "addr:full":"5330 State Hwy 91 Mountain City TN 37683",
    "addr:housenumber":"5330",
    "addr:postcode":"37683",
    "addr:street":"State Hwy 91",
    "iso:country":"US",
    "sg:address":"5330 State Hwy 91",
    "sg:city":"Mountain City",
    "sg:classifiers":[
        {
            "category":"Restaurant",
            "type":"Food & Drink"
        },
        {
            "category":"Bars & Pubs",
            "type":"Food & Drink"
        }
    ],
    "sg:phone":"+1 423 727 5188",
    "sg:postcode":"37683",
    "sg:province":"TN",
    "sg:tags":[
        "eating"
    ],
    "wof:name":"Dough Boy's",
    "wof:placetype":"venue"
},
  "geometry": {"coordinates":[-81.775243,36.544258],"type":"Point"}
}