{
  "type": "Feature",
  "properties": {
    "iso:country":"US",
    "sg:address":"2700 S Roan St",
    "sg:city":"Johnson City",
    "sg:classifiers":[
        {
            "category":"Professional",
            "subcategory":"Engineering",
            "type":"Services"
        }
    ],
    "sg:phone":"+1 423 926 2007",
    "sg:postcode":"37601",
    "sg:province":"TN",
    "sg:tags":[
        "engineer"
    ],
    "wof:name":"Highlands Engineering",
    "wof:placetype":"venue"
},
  "geometry": {"coordinates":[-82.32928,36.292141],"type":"Point"}
}