{
  "type": "Feature",
  "properties": {
    "addr:full":"2005 Hickory Ridge Cove Knoxville TN 37923",
    "addr:housenumber":"2005",
    "addr:postcode":"37923",
    "addr:street":"Hickory Ridge Cove",
    "iso:country":"US",
    "sg:address":"2005 Hickory Ridge Cove",
    "sg:city":"Knoxville",
    "sg:classifiers":[
        {
            "category":"Building & Trades",
            "subcategory":"Electrical",
            "type":"Services"
        }
    ],
    "sg:phone":"+1 865 470 9931",
    "sg:postcode":"37923",
    "sg:province":"TN",
    "sg:tags":[
        "electrical",
        "electric",
        "contractor"
    ],
    "wof:name":"Safety Electric Inc",
    "wof:placetype":"venue"
},
  "geometry": {"coordinates":[-84.063604,35.951313],"type":"Point"}
}