{
  "type": "Feature",
  "properties": {
    "addr:full":"3170 Southern Ave Memphis TN 38111",
    "addr:housenumber":"3170",
    "addr:postcode":"38111",
    "addr:street":"Southern Ave",
    "iso:country":"US",
    "sg:address":"3170 Southern Ave",
    "sg:city":"Memphis",
    "sg:classifiers":[
        {
            "category":"Real Estate",
            "subcategory":"Real Estate Operator",
            "type":"Services"
        }
    ],
    "sg:phone":"+1 901 327 4335",
    "sg:postcode":"38111",
    "sg:province":"TN",
    "sg:tags":[
        "building",
        "apartment",
        "condominium"
    ],
    "wof:name":"Country Club Apartments",
    "wof:placetype":"venue"
},
  "geometry": {"coordinates":[-89.95482699999999,35.115362],"type":"Point"}
}