{
  "type": "Feature",
  "properties": {
    "iso:country":"US",
    "sg:address":"107 W Blythe St",
    "sg:city":"Paris",
    "sg:classifiers":[
        {
            "category":"Professional",
            "subcategory":"Lawyer & Legal Services",
            "type":"Services"
        }
    ],
    "sg:phone":"+1 731 642 2555",
    "sg:postcode":"38242",
    "sg:province":"TN",
    "sg:tags":[
        "attorney"
    ],
    "wof:name":"Burch Porter & Johnson Pllc",
    "wof:placetype":"venue"
},
  "geometry": {"coordinates":[-88.326368,36.300979],"type":"Point"}
}