{
  "type": "Feature",
  "properties": {
    "addr:full":"3829 Creekwood Cir Nashville TN 37218",
    "addr:housenumber":"3829",
    "addr:postcode":"37218",
    "addr:street":"Creekwood Cir",
    "iso:country":"US",
    "sg:address":"3829 Creekwood Cir",
    "sg:city":"Nashville",
    "sg:classifiers":[
        {
            "category":"Shopping",
            "subcategory":"Clothing, Apparel, & Fashions",
            "type":"Retail Goods"
        }
    ],
    "sg:phone":"+1 615 876 7523",
    "sg:postcode":"37218",
    "sg:province":"TN",
    "sg:tags":[
        "wear"
    ],
    "wof:name":"Just For Kids (jfk)",
    "wof:placetype":"venue"
},
  "geometry": {"coordinates":[-86.847015,36.215765],"type":"Point"}
}