{
  "type": "Feature",
  "properties": {
    "iso:country":"US",
    "sg:address":"705 Main St",
    "sg:city":"Tracy City",
    "sg:classifiers":[
        {
            "category":"Restaurant",
            "type":"Food & Drink"
        }
    ],
    "sg:menulink":"http://www.allmenus.com/tn/tracy-city/141934-waffle-house/menu/",
    "sg:phone":"+1 931 924 3275",
    "sg:postcode":"37387",
    "sg:province":"TN",
    "sg:tags":[
        "american"
    ],
    "wof:name":"Waffle House",
    "wof:placetype":"venue"
},
  "geometry": {"coordinates":[-85.730138,35.259916],"type":"Point"}
}