{
  "type": "Feature",
  "properties": {
    "iso:country":"US",
    "sg:address":"210 W Fairview Ave",
    "sg:city":"Johnson City",
    "sg:classifiers":[
        {
            "category":"Social Services",
            "type":"Services"
        }
    ],
    "sg:phone":"+1 423 929 9967",
    "sg:postcode":"37604",
    "sg:province":"TN",
    "sg:tags":[
        "organization",
        "welfare"
    ],
    "wof:name":"Interfaith Hospitality Network",
    "wof:placetype":"venue"
},
  "geometry": {"coordinates":[-82.35681599999999,36.319012],"type":"Point"}
}