{
  "type": "Feature",
  "properties": {
    "addr:full":"130 Hawthorne Oaks Way Powell TN 37849",
    "addr:housenumber":"130",
    "addr:postcode":"37849",
    "addr:street":"Hawthorne Oaks Way",
    "iso:country":"US",
    "sg:address":"130 Hawthorne Oaks Way",
    "sg:city":"Powell",
    "sg:classifiers":[
        {
            "category":"Building & Trades",
            "subcategory":"Construction",
            "type":"Services"
        }
    ],
    "sg:phone":"+1 865 947 4855",
    "sg:postcode":"37849",
    "sg:province":"TN",
    "sg:tags":[
        "general",
        "contractor"
    ],
    "wof:name":"Prestige Homes",
    "wof:placetype":"venue"
},
  "geometry": {"coordinates":[-84.016732,36.049804],"type":"Point"}
}