{
  "type": "Feature",
  "properties": {
    "addr:full":"906 Shady Ln Manchester TN 37355",
    "addr:housenumber":"906",
    "addr:postcode":"37355",
    "addr:street":"Shady Ln",
    "iso:country":"US",
    "sg:address":"906 Shady Ln",
    "sg:city":"Manchester",
    "sg:classifiers":[
        {
            "category":"Retail",
            "subcategory":"Repair Shop",
            "type":"Services"
        }
    ],
    "sg:phone":"+1 931 728 2261",
    "sg:postcode":"37355",
    "sg:province":"TN",
    "sg:tags":[
        "refrigeration",
        "electrical"
    ],
    "wof:name":"Appliance Repair Speciali",
    "wof:placetype":"venue"
},
  "geometry": {"coordinates":[-86.094128,35.452158],"type":"Point"}
}