{
  "type": "Feature",
  "properties": {
    "addr:full":"1 Lion Dr Woodbury TN 37190",
    "addr:housenumber":"1",
    "addr:postcode":"37190",
    "addr:street":"Lion Dr",
    "iso:country":"US",
    "sg:address":"1 Lion Dr",
    "sg:city":"Woodbury",
    "sg:classifiers":[
        {
            "category":"Utilities",
            "subcategory":"Telephone",
            "type":"Services"
        }
    ],
    "sg:phone":"+1 615 563 3257",
    "sg:postcode":"37190",
    "sg:province":"TN",
    "sg:tags":[
        "company"
    ],
    "wof:name":"American Telephone Exchange",
    "wof:placetype":"venue"
},
  "geometry": {"coordinates":[-86.058882,35.822414],"type":"Point"}
}