{
  "type": "Feature",
  "properties": {
    "iso:country":"US",
    "sg:address":"7212 Old Blacks Ferry Ln",
    "sg:city":"Powell",
    "sg:classifiers":[
        {
            "category":"Building & Trades",
            "subcategory":"Construction",
            "type":"Services"
        }
    ],
    "sg:phone":"+1 865 938 7916",
    "sg:postcode":"37849",
    "sg:province":"TN",
    "sg:tags":[
        "house"
    ],
    "wof:name":"Gaddis Construction",
    "wof:placetype":"venue"
},
  "geometry": {"coordinates":[-84.07074799999999,36.001178],"type":"Point"}
}