{
  "type": "Feature",
  "properties": {
    "addr:full":"1068 Tanglewood Ct Hermitage TN 37076",
    "addr:housenumber":"1068",
    "addr:postcode":"37076",
    "addr:street":"Tanglewood Ct",
    "iso:country":"US",
    "sg:address":"1068 Tanglewood Ct",
    "sg:city":"Hermitage",
    "sg:classifiers":[
        {
            "category":"Professional",
            "subcategory":"Business Services",
            "type":"Services"
        }
    ],
    "sg:phone":"+1 615 977 1541",
    "sg:postcode":"37076",
    "sg:province":"TN",
    "wof:name":"Dmp Enterprize",
    "wof:placetype":"venue"
},
  "geometry": {"coordinates":[-86.569209,36.178076],"type":"Point"}
}