{
  "type": "Feature",
  "properties": {
    "iso:country":"US",
    "sg:address":"5955 N 1st St",
    "sg:city":"Russellville",
    "sg:classifiers":[
        {
            "category":"Building & Trades",
            "subcategory":"Construction",
            "type":"Services"
        }
    ],
    "sg:phone":"+1 423 587 5876",
    "sg:postcode":"37860",
    "sg:province":"TN",
    "sg:tags":[
        "siding",
        "contractor"
    ],
    "wof:name":"Morristown Siding & Guttering",
    "wof:placetype":"venue"
},
  "geometry": {"coordinates":[-83.194861,36.259973],"type":"Point"}
}