{
  "type": "Feature",
  "properties": {
    "addr:full":"488 Sparkman Rd Mc Minnville TN 37110",
    "addr:housenumber":"488",
    "addr:postcode":"37110",
    "addr:street":"Sparkman Rd",
    "iso:country":"US",
    "sg:address":"488 Sparkman Rd",
    "sg:city":"Mc Minnville",
    "sg:classifiers":[
        {
            "category":"Building & Trades",
            "subcategory":"Construction",
            "type":"Services"
        }
    ],
    "sg:phone":"+1 931 934 2378",
    "sg:postcode":"37110",
    "sg:province":"TN",
    "sg:tags":[
        "heavy"
    ],
    "wof:name":"Volunteer Backhoe Service",
    "wof:placetype":"venue"
},
  "geometry": {"coordinates":[-85.787347,35.791446],"type":"Point"}
}