{
  "type": "Feature",
  "properties": {
    "iso:country":"US",
    "sg:address":"117 Valley Crest Dr",
    "sg:city":"Mount Carmel",
    "sg:classifiers":[
        {
            "category":"Building & Trades",
            "subcategory":"Construction",
            "type":"Services"
        }
    ],
    "sg:phone":"+1 423 256 9898",
    "sg:postcode":"37645",
    "sg:province":"TN",
    "sg:tags":[
        "contractor"
    ],
    "wof:name":"Tri Cities Alarm Contractors",
    "wof:placetype":"venue"
},
  "geometry": {"coordinates":[-82.66909,36.559287],"type":"Point"}
}