{
  "type": "Feature",
  "properties": {
    "iso:country":"US",
    "sg:address":"640 US Hwy 51 Bus",
    "sg:city":"Dyersburg",
    "sg:classifiers":[
        {
            "category":"Personal",
            "subcategory":"Beauty Salon",
            "type":"Services"
        }
    ],
    "sg:phone":"+1 731 287 0440",
    "sg:postcode":"38024",
    "sg:province":"TN",
    "wof:name":"Cutting Edge",
    "wof:placetype":"venue"
},
  "geometry": {"coordinates":[-89.390348,36.021211],"type":"Point"}
}