{
  "type": "Feature",
  "properties": {
    "addr:full":"10901 Lake Ridge Dr Knoxville TN 37934",
    "addr:housenumber":"10901",
    "addr:postcode":"37934",
    "addr:street":"Lake Ridge Dr",
    "iso:country":"US",
    "sg:address":"10901 Lake Ridge Dr",
    "sg:city":"Knoxville",
    "sg:classifiers":[
        {
            "category":"Organizations",
            "subcategory":"Religious Organization",
            "type":"Services"
        }
    ],
    "sg:phone":"+1 865 675 4444",
    "sg:postcode":"37934",
    "sg:province":"TN",
    "sg:tags":[
        "church"
    ],
    "wof:name":"Grace & Glory Fellowship Chr",
    "wof:placetype":"venue"
},
  "geometry": {"coordinates":[-84.137485,35.86557],"type":"Point"}
}