{
  "type": "Feature",
  "properties": {
    "addr:full":"272 Murfreesboro Pike Nashville TN 37210",
    "addr:housenumber":"272",
    "addr:postcode":"37210",
    "addr:street":"Murfreesboro Pike",
    "iso:country":"US",
    "sg:address":"272 Murfreesboro Pike",
    "sg:city":"Nashville",
    "sg:classifiers":[
        {
            "category":"Personal",
            "subcategory":"Beauty Salon",
            "type":"Services"
        }
    ],
    "sg:phone":"+1 615 399 1177",
    "sg:postcode":"37210",
    "sg:province":"TN",
    "sg:tags":[
        "shop"
    ],
    "wof:name":"Taylor Made Cuts",
    "wof:placetype":"venue"
},
  "geometry": {"coordinates":[-86.755484,36.146422],"type":"Point"}
}