{
  "type": "Feature",
  "properties": {
    "addr:full":"1566 Povo Rd Madisonville TN 37354",
    "addr:housenumber":"1566",
    "addr:postcode":"37354",
    "addr:street":"Povo Rd",
    "iso:country":"US",
    "sg:address":"1566 Povo Rd",
    "sg:city":"Madisonville",
    "sg:classifiers":[
        {
            "category":"Freight",
            "type":"Transportation"
        }
    ],
    "sg:phone":"+1 423 442 4451",
    "sg:postcode":"37354",
    "sg:province":"TN",
    "sg:tags":[
        "operator",
        "automobile",
        "used",
        "local",
        "trucking"
    ],
    "wof:name":"Adams Auto Sales",
    "wof:placetype":"venue"
},
  "geometry": {"coordinates":[-84.269188,35.529788],"type":"Point"}
}