{
  "type": "Feature",
  "properties": {
    "addr:full":"430 Perkins Exd Memphis TN 38117",
    "addr:housenumber":"430",
    "addr:postcode":"38117",
    "addr:street":"Perkins Exd",
    "iso:country":"US",
    "sg:address":"430 Perkins Exd",
    "sg:city":"Memphis",
    "sg:classifiers":[
        {
            "category":"Shopping",
            "subcategory":"Used Merchandise",
            "type":"Retail Goods"
        }
    ],
    "sg:phone":"+1 901 683 8868",
    "sg:postcode":"38117",
    "sg:province":"TN",
    "sg:tags":[
        "antique"
    ],
    "wof:name":"Brice Antiques",
    "wof:placetype":"venue"
},
  "geometry": {"coordinates":[-89.908467,35.120257],"type":"Point"}
}