{
  "type": "Feature",
  "properties": {
    "addr:full":"491 E Walnut St Dickson TN 37055",
    "addr:housenumber":"491",
    "addr:postcode":"37055",
    "addr:street":"E Walnut St",
    "iso:country":"US",
    "sg:address":"491 E Walnut St",
    "sg:city":"Dickson",
    "sg:classifiers":[
        {
            "category":"Retail",
            "subcategory":"Auto Repair",
            "type":"Services"
        }
    ],
    "sg:phone":"+1 615 446 9422",
    "sg:postcode":"37055",
    "sg:province":"TN",
    "sg:tags":[
        "wrecker"
    ],
    "wof:name":"B J's Towing",
    "wof:placetype":"venue"
},
  "geometry": {"coordinates":[-87.38632800000001,36.071197],"type":"Point"}
}