{
  "type": "Feature",
  "properties": {
    "iso:country":"US",
    "sg:address":"685 Tiprell Rd",
    "sg:city":"Cumberland Gap",
    "sg:classifiers":[
        {
            "category":"Organizations",
            "subcategory":"Religious Organization",
            "type":"Services"
        }
    ],
    "sg:phone":"+1 423 626 1830",
    "sg:postcode":"37724",
    "sg:province":"TN",
    "wof:name":"House of God Worship Ctr Inc",
    "wof:placetype":"venue"
},
  "geometry": {"coordinates":[-83.679468,36.5841],"type":"Point"}
}