{
  "type": "Feature",
  "properties": {
    "iso:country":"US",
    "sg:address":"409 Park Ave",
    "sg:city":"Adamsville",
    "sg:classifiers":[
        {
            "category":"Health Services",
            "subcategory":"Nursing And Care Facility",
            "type":"Services"
        }
    ],
    "sg:phone":"+1 731 632 3301",
    "sg:postcode":"38310",
    "sg:province":"TN",
    "sg:tags":[
        "home",
        "convalescent"
    ],
    "wof:name":"Tri County Convalescent Home",
    "wof:placetype":"venue"
},
  "geometry": {"coordinates":[-88.382632,35.230603],"type":"Point"}
}