{
  "type": "Feature",
  "properties": {
    "iso:country":"US",
    "sg:address":"3526 Hobson Pike",
    "sg:city":"Hermitage",
    "sg:classifiers":[
        {
            "category":"Building & Trades",
            "subcategory":"Construction",
            "type":"Services"
        }
    ],
    "sg:phone":"+1 615 874 8770",
    "sg:postcode":"37076",
    "sg:province":"TN",
    "sg:tags":[
        "excavation",
        "contractor"
    ],
    "wof:name":"Bentley Backhoe Services Inc",
    "wof:placetype":"venue"
},
  "geometry": {"coordinates":[-86.530058,36.110342],"type":"Point"}
}