{
  "type": "Feature",
  "properties": {
    "iso:country":"US",
    "sg:address":"330 Franklin Rd",
    "sg:city":"Brentwood",
    "sg:classifiers":[
        {
            "category":"Restaurant",
            "type":"Food & Drink"
        }
    ],
    "sg:phone":"+1 615 373 4160",
    "sg:postcode":"37027",
    "sg:province":"TN",
    "sg:website":"www.chick-fil-a.com",
    "wof:name":"Chick-Fil-A",
    "wof:placetype":"venue"
},
  "geometry": {"coordinates":[-86.792039,36.027179],"type":"Point"}
}