{
  "type": "Feature",
  "properties": {
    "iso:country":"US",
    "sg:address":"518 E Baltimore St",
    "sg:city":"Jackson",
    "sg:classifiers":[
        {
            "category":"Manufacturing",
            "subcategory":"Building Materials",
            "type":"Manufacturing & Wholesale Goods"
        },
        {
            "category":"Home & Garden",
            "subcategory":"Furniture",
            "type":"Retail Goods"
        }
    ],
    "sg:phone":"+1 731 427 3565",
    "sg:postcode":"38301",
    "sg:province":"TN",
    "sg:tags":[
        "cabinet",
        "custom"
    ],
    "wof:name":"Tubbs Cabinet Shop Inc",
    "wof:placetype":"venue"
},
  "geometry": {"coordinates":[-88.812853,35.613211],"type":"Point"}
}