{
  "type": "Feature",
  "properties": {
    "iso:country":"US",
    "sg:address":"1348 N Wright Rd",
    "sg:city":"Alcoa",
    "sg:classifiers":[
        {
            "category":"Retail",
            "subcategory":"Auto Repair",
            "type":"Services"
        }
    ],
    "sg:phone":"+1 865 982 9851",
    "sg:postcode":"37701",
    "sg:province":"TN",
    "sg:tags":[
        "repairing",
        "automobile"
    ],
    "wof:name":"Whitehead Service Ctr",
    "wof:placetype":"venue"
},
  "geometry": {"coordinates":[-83.973589,35.795684],"type":"Point"}
}