{
  "type": "Feature",
  "properties": {
    "iso:country":"US",
    "sg:address":"70 Swindle Rd",
    "sg:city":"Lafayette",
    "sg:classifiers":[
        {
            "category":"Building & Trades",
            "subcategory":"Cleaning & Sanitation",
            "type":"Services"
        }
    ],
    "sg:phone":"+1 615 688 4136",
    "sg:postcode":"37083",
    "sg:province":"TN",
    "sg:tags":[
        "janitor"
    ],
    "wof:name":"Clean Sweep",
    "wof:placetype":"venue"
},
  "geometry": {"coordinates":[-85.962699,36.576632],"type":"Point"}
}