{
  "type": "Feature",
  "properties": {
    "iso:country":"US",
    "sg:address":"516 Tennessee St",
    "sg:city":"Memphis",
    "sg:classifiers":[
        {
            "category":"Retail",
            "subcategory":"Auto Repair",
            "type":"Services"
        },
        {
            "category":"Professional",
            "subcategory":"Computer Services",
            "type":"Services"
        }
    ],
    "sg:phone":"+1 901 333 3030",
    "sg:postcode":"38103",
    "sg:province":"TN",
    "sg:tags":[
        "general"
    ],
    "sg:website":"www.lanone.net",
    "wof:name":"Lan One",
    "wof:placetype":"venue"
},
  "geometry": {"coordinates":[-90.062484,35.133417],"type":"Point"}
}