{
  "type": "Feature",
  "properties": {
    "iso:country":"US",
    "sg:address":"390 Tackett Loop",
    "sg:city":"Caryville",
    "sg:classifiers":[
        {
            "category":"Building & Trades",
            "subcategory":"Landscaping Services",
            "type":"Services"
        }
    ],
    "sg:phone":"+1 865 426 7736",
    "sg:postcode":"37714",
    "sg:province":"TN",
    "sg:tags":[
        "landscape",
        "contractor"
    ],
    "wof:name":"Creative Bobcat Concepts",
    "wof:placetype":"venue"
},
  "geometry": {"coordinates":[-84.191334,36.258494],"type":"Point"}
}