{
  "type": "Feature",
  "properties": {
    "iso:country":"US",
    "sg:address":"120 Lampley Ct",
    "sg:city":"Goodlettsville",
    "sg:classifiers":[
        {
            "category":"Building & Trades",
            "subcategory":"Landscaping Services",
            "type":"Services"
        }
    ],
    "sg:phone":"+1 615 859 9816",
    "sg:postcode":"37072",
    "sg:province":"TN",
    "wof:name":"Perfection Lawn Care & Landsca",
    "wof:placetype":"venue"
},
  "geometry": {"coordinates":[-86.71082699999999,36.33801],"type":"Point"}
}