{
  "type": "Feature",
  "properties": {
    "iso:country":"US",
    "sg:address":"1657 S 3rd St",
    "sg:city":"Memphis",
    "sg:classifiers":[
        {
            "category":"Wholesale",
            "subcategory":"Auto Parts",
            "type":"Manufacturing & Wholesale Goods"
        }
    ],
    "sg:phone":"+1 901 522 8734",
    "sg:postcode":"38106",
    "sg:province":"TN",
    "sg:tags":[
        "tire"
    ],
    "wof:name":"V & V Used Tires",
    "wof:placetype":"venue"
},
  "geometry": {"coordinates":[-90.055559,35.103301],"type":"Point"}
}