{
  "type": "Feature",
  "properties": {
    "addr:full":"1467 W Natchez Trace Rd Parsons TN 38363",
    "addr:housenumber":"1467",
    "addr:postcode":"38363",
    "addr:street":"W Natchez Trace Rd",
    "iso:country":"US",
    "sg:address":"1467 W Natchez Trace Rd",
    "sg:city":"Parsons",
    "sg:classifiers":[
        {
            "category":"Organizations",
            "subcategory":"Religious Organization",
            "type":"Services"
        }
    ],
    "sg:phone":"+1 731 847 7125",
    "sg:postcode":"38363",
    "sg:province":"TN",
    "sg:tags":[
        "clergy"
    ],
    "wof:name":"Leon Chapman",
    "wof:placetype":"venue"
},
  "geometry": {"coordinates":[-88.170391,35.753201],"type":"Point"}
}