{
  "type": "Feature",
  "properties": {
    "addr:full":"372 Shelbyville Hwy Fayetteville TN 37334",
    "addr:housenumber":"372",
    "addr:postcode":"37334",
    "addr:street":"Shelbyville Hwy",
    "iso:country":"US",
    "sg:address":"372 Shelbyville Hwy",
    "sg:city":"Fayetteville",
    "sg:classifiers":[
        {
            "category":"Building & Trades",
            "subcategory":"Construction",
            "type":"Services"
        }
    ],
    "sg:phone":"+1 931 433 7938",
    "sg:postcode":"37334",
    "sg:province":"TN",
    "sg:tags":[
        "paving",
        "contractor"
    ],
    "wof:name":"Wright Paving Company",
    "wof:placetype":"venue"
},
  "geometry": {"coordinates":[-86.567412,35.193915],"type":"Point"}
}