{
  "type": "Feature",
  "properties": {
    "iso:country":"US",
    "sg:address":"981 Oak Ridge Tpke",
    "sg:city":"Oak Ridge",
    "sg:classifiers":[
        {
            "category":"Shopping",
            "subcategory":"Pharmacy",
            "type":"Retail Goods"
        }
    ],
    "sg:phone":"+1 865 483 8429",
    "sg:postcode":"37830",
    "sg:province":"TN",
    "sg:tags":[
        "drug"
    ],
    "wof:name":"Overtons Pharmacy Inc",
    "wof:placetype":"venue"
},
  "geometry": {"coordinates":[-84.243363,36.023768],"type":"Point"}
}