{
  "type": "Feature",
  "properties": {
    "iso:country":"US",
    "sg:address":"8207 E Andrew Johnson Hwy",
    "sg:city":"Whitesburg",
    "sg:classifiers":[
        {
            "category":"Retail",
            "subcategory":"Funeral Services",
            "type":"Services"
        }
    ],
    "sg:phone":"+1 423 235 5229",
    "sg:postcode":"37891",
    "sg:province":"TN",
    "sg:tags":[
        "director"
    ],
    "wof:name":"Stetzer Funeral Home",
    "wof:placetype":"venue"
},
  "geometry": {"coordinates":[-83.13120499999999,36.274492],"type":"Point"}
}