{
  "type": "Feature",
  "properties": {
    "iso:country":"US",
    "sg:address":"4900 Hooker Rd",
    "sg:city":"Chattanooga",
    "sg:classifiers":[
        {
            "category":"Manufacturing",
            "subcategory":"Metals",
            "type":"Manufacturing & Wholesale Goods"
        }
    ],
    "sg:phone":"+1 423 827 0667",
    "sg:postcode":"37410",
    "sg:province":"TN",
    "sg:tags":[
        "steel"
    ],
    "wof:name":"TSS Co Inc",
    "wof:placetype":"venue"
},
  "geometry": {"coordinates":[-85.294645,34.984612],"type":"Point"}
}