{
  "type": "Feature",
  "properties": {
    "iso:country":"US",
    "sg:address":"8100 US Hwy 64",
    "sg:city":"Oakland",
    "sg:classifiers":[
        {
            "category":"Wholesale",
            "subcategory":"Machinery & Supplies",
            "type":"Manufacturing & Wholesale Goods"
        },
        {
            "category":"Professional",
            "type":"Services"
        }
    ],
    "sg:phone":"+1 901 465 7575",
    "sg:postcode":"38060",
    "sg:province":"TN",
    "sg:tags":[
        "equipment",
        "industrial",
        "establishment"
    ],
    "wof:name":"Tennessee Equipment Company",
    "wof:placetype":"venue"
},
  "geometry": {"coordinates":[-89.50905899999999,35.22902],"type":"Point"}
}