{
  "type": "Feature",
  "properties": {
    "iso:country":"US",
    "sg:address":"1650 McArthur St",
    "sg:city":"Manchester",
    "sg:classifiers":[
        {
            "category":"Wholesale",
            "subcategory":"Electrical",
            "type":"Manufacturing & Wholesale Goods"
        }
    ],
    "sg:phone":"+1 931 723 8182",
    "sg:postcode":"37355",
    "sg:province":"TN",
    "sg:tags":[
        "alarm",
        "burglar",
        "system"
    ],
    "wof:name":"HSL",
    "wof:placetype":"venue"
},
  "geometry": {"coordinates":[-86.093346,35.454288],"type":"Point"}
}