{
  "type": "Feature",
  "properties": {
    "iso:country":"US",
    "sg:address":"104 W Moore St",
    "sg:city":"Tullahoma",
    "sg:classifiers":[
        {
            "category":"Real Estate",
            "subcategory":"Real Estate Services",
            "type":"Services"
        }
    ],
    "sg:phone":"+1 931 455 1060",
    "sg:postcode":"37388",
    "sg:province":"TN",
    "sg:tags":[
        "company",
        "title"
    ],
    "wof:name":"Fidelity Title & Escrow Co",
    "wof:placetype":"venue"
},
  "geometry": {"coordinates":[-86.21249899999999,35.364149],"type":"Point"}
}