{
  "type": "Feature",
  "properties": {
    "iso:country":"US",
    "sg:address":"305 Seaboard Ln",
    "sg:city":"Franklin",
    "sg:classifiers":[
        {
            "category":"Home & Garden",
            "subcategory":"Carpets & Floor Coverings",
            "type":"Retail Goods"
        }
    ],
    "sg:phone":"+1 615 771 1243",
    "sg:postcode":"37067",
    "sg:province":"TN",
    "wof:name":"L & L Carpet Discount Centers",
    "wof:placetype":"venue"
},
  "geometry": {"coordinates":[-86.831058,35.949299],"type":"Point"}
}