{
  "type": "Feature",
  "properties": {
    "iso:country":"US",
    "sg:address":"574 Scott St",
    "sg:city":"Memphis",
    "sg:classifiers":[
        {
            "category":"Wholesale",
            "subcategory":"Electrical",
            "type":"Manufacturing & Wholesale Goods"
        }
    ],
    "sg:phone":"+1 901 324 5588",
    "sg:postcode":"38112",
    "sg:province":"TN",
    "sg:tags":[
        "light",
        "tube",
        "bulb"
    ],
    "wof:name":"DYNA-Brite Lighting Inc",
    "wof:placetype":"venue"
},
  "geometry": {"coordinates":[-89.96705,35.148325],"type":"Point"}
}