{
  "type": "Feature",
  "properties": {
    "iso:country":"US",
    "sg:address":"1025 Summer Wood Rd",
    "sg:city":"Knoxville",
    "sg:classifiers":[
        {
            "category":"Insurance",
            "subcategory":"Insurance Agent",
            "type":"Services"
        }
    ],
    "sg:phone":"+1 865 692 1000",
    "sg:postcode":"37923",
    "sg:province":"TN",
    "wof:name":"Allstate Insurance Co",
    "wof:placetype":"venue"
},
  "geometry": {"coordinates":[-84.084335,35.941701],"type":"Point"}
}