{
  "type": "Feature",
  "properties": {
    "addr:full":"1019 Flint Dr Hendersonville TN 37075",
    "addr:housenumber":"1019",
    "addr:postcode":"37075",
    "addr:street":"Flint Dr",
    "iso:country":"US",
    "sg:address":"1019 Flint Dr",
    "sg:city":"Hendersonville",
    "sg:classifiers":[
        {
            "category":"Professional",
            "subcategory":"Business Services",
            "type":"Services"
        }
    ],
    "sg:phone":"+1 615 338 4199",
    "sg:postcode":"37075",
    "sg:province":"TN",
    "sg:tags":[
        "record",
        "medical"
    ],
    "wof:name":"Record Results",
    "wof:placetype":"venue"
},
  "geometry": {"coordinates":[-86.584537,36.33782],"type":"Point"}
}