{
  "type": "Feature",
  "properties": {
    "addr:full":"613 Hwy 52 E Lafayette TN 37083",
    "addr:housenumber":"613",
    "addr:postcode":"37083",
    "addr:street":"Hwy 52 E",
    "iso:country":"US",
    "sg:address":"613 Hwy 52 E",
    "sg:city":"Lafayette",
    "sg:classifiers":[
        {
            "category":"Recreation",
            "subcategory":"Marina",
            "type":"Entertainment"
        }
    ],
    "sg:phone":"+1 615 666 7440",
    "sg:postcode":"37083",
    "sg:province":"TN",
    "sg:tags":[
        "track",
        "operation",
        "racing",
        "or"
    ],
    "wof:name":"Precision Performance",
    "wof:placetype":"venue"
},
  "geometry": {"coordinates":[-86.01282500000001,36.516179],"type":"Point"}
}