{
  "type": "Feature",
  "properties": {
    "iso:country":"US",
    "sg:address":"769 National St",
    "sg:city":"Memphis",
    "sg:classifiers":[
        {
            "category":"Shopping",
            "subcategory":"Bicycles & Sporting Goods",
            "type":"Retail Goods"
        }
    ],
    "sg:phone":"+1 901 452 2535",
    "sg:postcode":"38122",
    "sg:province":"TN",
    "sg:tags":[
        "equipment",
        "repair",
        "made",
        "golf",
        "custom"
    ],
    "wof:name":"Memphis Golf Inc",
    "wof:placetype":"venue"
},
  "geometry": {"coordinates":[-89.947796,35.152514],"type":"Point"}
}