{
  "type": "Feature",
  "properties": {
    "iso:country":"US",
    "sg:address":"232 Heritage Park Dr",
    "sg:city":"Murfreesboro",
    "sg:classifiers":[
        {
            "category":"Wholesale",
            "subcategory":"Medical Equipment & Supplies",
            "type":"Manufacturing & Wholesale Goods"
        }
    ],
    "sg:phone":"+1 615 896 4237",
    "sg:postcode":"37129",
    "sg:province":"TN",
    "sg:tags":[
        "physician",
        "surgeon"
    ],
    "sg:website":"www.adsdiabetic.com",
    "wof:name":"Advanced Diabetic Svc",
    "wof:placetype":"venue"
},
  "geometry": {"coordinates":[-86.389678,35.873398],"type":"Point"}
}