{
  "type": "Feature",
  "properties": {
    "iso:country":"US",
    "sg:address":"320 Ridgetop Dr",
    "sg:city":"Bluff City",
    "sg:classifiers":[
        {
            "category":"Professional",
            "type":"Services"
        }
    ],
    "sg:phone":"+1 423 538 4394",
    "sg:postcode":"37618",
    "sg:province":"TN",
    "wof:name":"Michael E Reed",
    "wof:placetype":"venue"
},
  "geometry": {"coordinates":[-82.270016,36.513177],"type":"Point"}
}