{
  "type": "Feature",
  "properties": {
    "iso:country":"US",
    "sg:address":"1723 Pulaski Hwy",
    "sg:city":"Fayetteville",
    "sg:classifiers":[
        {
            "category":"Real Estate",
            "subcategory":"Real Estate Agent",
            "type":"Services"
        }
    ],
    "sg:phone":"+1 931 438 4492",
    "sg:postcode":"37334",
    "sg:province":"TN",
    "wof:name":"BMA Properties",
    "wof:placetype":"venue"
},
  "geometry": {"coordinates":[-86.599222,35.157661],"type":"Point"}
}