{
  "type": "Feature",
  "properties": {
    "iso:country":"US",
    "sg:address":"3230 Parkway",
    "sg:city":"Pigeon Forge",
    "sg:classifiers":[
        {
            "category":"Travel",
            "subcategory":"Hotels & Motels",
            "type":"Entertainment"
        }
    ],
    "sg:phone":"+1 865 428 2700",
    "sg:postcode":"37863",
    "sg:province":"TN",
    "sg:website":"www.4lodging.com",
    "wof:name":"Holiday Inn Pigeon Forge",
    "wof:placetype":"venue"
},
  "geometry": {"coordinates":[-83.558594,35.791583],"type":"Point"}
}