{
  "type": "Feature",
  "properties": {
    "iso:country":"US",
    "sg:address":"4148 E Ridge Dr",
    "sg:city":"East Ridge",
    "sg:classifiers":[
        {
            "category":"Banks & Credit Unions",
            "subcategory":"Bank",
            "type":"Services"
        }
    ],
    "sg:phone":"+1 423 697 0038",
    "sg:postcode":"37412",
    "sg:province":"TN",
    "sg:tags":[
        "other",
        "plan",
        "card"
    ],
    "wof:name":"Advanced Payment Solutions",
    "wof:placetype":"venue"
},
  "geometry": {"coordinates":[-85.249848,34.993379],"type":"Point"}
}