{
  "type": "Feature",
  "properties": {
    "iso:country":"US",
    "sg:address":"4008 US Hwy 43 S",
    "sg:city":"St Joseph",
    "sg:classifiers":[
        {
            "category":"Autos & Motor Vehicles",
            "subcategory":"Fuel & Gas Station",
            "type":"Retail Goods"
        }
    ],
    "sg:phone":"+1 931 845 4134",
    "sg:postcode":"38481",
    "sg:province":"TN",
    "sg:tags":[
        "station",
        "gasoline",
        "oil"
    ],
    "wof:name":"Stateline Station",
    "wof:placetype":"venue"
},
  "geometry": {"coordinates":[-87.509353,35.014522],"type":"Point"}
}