{
  "type": "Feature",
  "properties": {
    "iso:country":"US",
    "sg:address":"214 N Pine St",
    "sg:city":"Elizabethton",
    "sg:classifiers":[
        {
            "category":"Freight",
            "type":"Transportation"
        }
    ],
    "sg:phone":"+1 423 542 6418",
    "sg:postcode":"37643",
    "sg:province":"TN",
    "sg:tags":[
        "trucking"
    ],
    "wof:name":"Sam Ward Trucking",
    "wof:placetype":"venue"
},
  "geometry": {"coordinates":[-82.216508,36.349378],"type":"Point"}
}