{
  "type": "Feature",
  "properties": {
    "iso:country":"US",
    "sg:address":"651 Mimosa Dr",
    "sg:city":"Cleveland",
    "sg:classifiers":[
        {
            "category":"Museum",
            "subcategory":"Botanical Garden",
            "type":"Entertainment"
        },
        {
            "category":"Wholesale",
            "subcategory":"Non-durable Goods",
            "type":"Manufacturing & Wholesale Goods"
        }
    ],
    "sg:phone":"+1 423 478 5522",
    "sg:postcode":"37312",
    "sg:province":"TN",
    "sg:tags":[
        "aquarium"
    ],
    "wof:name":"Michael's Aquatic Den",
    "wof:placetype":"venue"
},
  "geometry": {"coordinates":[-84.855,35.201628],"type":"Point"}
}