{
  "type": "Feature",
  "properties": {
    "iso:country":"US",
    "sg:address":"116 Pineoak Dr",
    "sg:city":"Maryville",
    "sg:classifiers":[
        {
            "category":"Building & Trades",
            "subcategory":"Construction",
            "type":"Services"
        }
    ],
    "sg:phone":"+1 865 983 8769",
    "sg:postcode":"37803",
    "sg:province":"TN",
    "sg:tags":[
        "excavation",
        "work"
    ],
    "wof:name":"Halls Excavation",
    "wof:placetype":"venue"
},
  "geometry": {"coordinates":[-83.923323,35.713875],"type":"Point"}
}