{
  "type": "Feature",
  "properties": {
    "iso:country":"US",
    "sg:address":"321 Paine Lake Dr",
    "sg:city":"Sevierville",
    "sg:classifiers":[
        {
            "category":"Real Estate",
            "subcategory":"Real Estate Agent",
            "type":"Services"
        }
    ],
    "sg:phone":"+1 865 908 0203",
    "sg:postcode":"37862",
    "sg:province":"TN",
    "wof:name":"Jim Young Realtor",
    "wof:placetype":"venue"
},
  "geometry": {"coordinates":[-83.57462099999999,35.867111],"type":"Point"}
}