{
  "type": "Feature",
  "properties": {
    "iso:country":"US",
    "sg:address":"447 Harding Industrial Dr",
    "sg:city":"Nashville",
    "sg:classifiers":[
        {
            "category":"Wholesale",
            "subcategory":"Auto Parts",
            "type":"Manufacturing & Wholesale Goods"
        }
    ],
    "sg:phone":"+1 615 331 4323",
    "sg:postcode":"37211",
    "sg:province":"TN",
    "sg:tags":[
        "equipment",
        "tire",
        "supply"
    ],
    "wof:name":"Myers Tire Supply Distribution",
    "wof:placetype":"venue"
},
  "geometry": {"coordinates":[-86.696744,36.095229],"type":"Point"}
}