{
  "type": "Feature",
  "properties": {
    "iso:country":"US",
    "sg:address":"3005 S 3rd St",
    "sg:city":"Memphis",
    "sg:classifiers":[
        {
            "category":"Professional",
            "type":"Services"
        }
    ],
    "sg:phone":"+1 901 345 4977",
    "sg:postcode":"38109",
    "sg:province":"TN",
    "wof:name":"Barbara Cooper Headquarters",
    "wof:placetype":"venue"
},
  "geometry": {"coordinates":[-90.058124,35.073811],"type":"Point"}
}