{
  "type": "Feature",
  "properties": {
    "iso:country":"US",
    "sg:address":"30 S Kentucky Ave",
    "sg:city":"Parsons",
    "sg:classifiers":[
        {
            "category":"Personal",
            "subcategory":"Beauty Salon",
            "type":"Services"
        }
    ],
    "sg:phone":"+1 731 847 3600",
    "sg:postcode":"38363",
    "sg:province":"TN",
    "sg:tags":[
        "shop"
    ],
    "wof:name":"Tip To Toes Nail Spa",
    "wof:placetype":"venue"
},
  "geometry": {"coordinates":[-88.12517200000001,35.649129],"type":"Point"}
}