{
  "type": "Feature",
  "properties": {
    "iso:country":"US",
    "sg:address":"2124 Democrat Rd",
    "sg:city":"Memphis",
    "sg:classifiers":[
        {
            "category":"Banks & Credit Unions",
            "subcategory":"Bank",
            "type":"Services"
        }
    ],
    "sg:phone":"+1 901 332 9232",
    "sg:postcode":"38132",
    "sg:province":"TN",
    "wof:name":"Fed-Ex Employees Credit Assoc",
    "wof:placetype":"venue"
},
  "geometry": {"coordinates":[-89.99246599999999,35.068794],"type":"Point"}
}