{
  "type": "Feature",
  "properties": {
    "iso:country":"US",
    "sg:address":"211 Evergreen Dr",
    "sg:city":"Kingsport",
    "sg:classifiers":[
        {
            "category":"Professional",
            "type":"Services"
        }
    ],
    "sg:phone":"+1 423 279 7400",
    "sg:postcode":"37660",
    "sg:province":"TN",
    "wof:name":"Evergreen Cleaning Servic",
    "wof:placetype":"venue"
},
  "geometry": {"coordinates":[-82.410678,36.575393],"type":"Point"}
}