{
  "type": "Feature",
  "properties": {
    "iso:country":"US",
    "sg:address":"4670 Old Stage Rd",
    "sg:city":"Kingsport",
    "sg:classifiers":[
        {
            "category":"Manufacturing",
            "subcategory":"Wood Products",
            "type":"Manufacturing & Wholesale Goods"
        }
    ],
    "sg:phone":"+1 423 288 2174",
    "sg:postcode":"37664",
    "sg:province":"TN",
    "sg:tags":[
        "mfg"
    ],
    "wof:name":"D & J Crafts",
    "wof:placetype":"venue"
},
  "geometry": {"coordinates":[-82.477717,36.540351],"type":"Point"}
}