{
  "type": "Feature",
  "properties": {
    "iso:country":"US",
    "sg:address":"2738 Moss Valley Dr",
    "sg:city":"Memphis",
    "sg:classifiers":[
        {
            "category":"Building & Trades",
            "subcategory":"Construction",
            "type":"Services"
        }
    ],
    "sg:phone":"+1 901 338 8798",
    "sg:postcode":"38133",
    "sg:province":"TN",
    "sg:tags":[
        "home",
        "improvement"
    ],
    "wof:name":"Briley Painting & Home Imprvmt",
    "wof:placetype":"venue"
},
  "geometry": {"coordinates":[-89.83199,35.201587],"type":"Point"}
}