{
  "type": "Feature",
  "properties": {
    "iso:country":"US",
    "sg:address":"3311 S Christine Gardens",
    "sg:city":"Memphis",
    "sg:classifiers":[
        {
            "category":"Freight",
            "type":"Transportation"
        }
    ],
    "sg:phone":"+1 901 363 8628",
    "sg:postcode":"38118",
    "sg:province":"TN",
    "sg:tags":[
        "operator",
        "local",
        "trucking"
    ],
    "wof:name":"Harris Trucking",
    "wof:placetype":"venue"
},
  "geometry": {"coordinates":[-89.952382,35.040691],"type":"Point"}
}