{
  "type": "Feature",
  "properties": {
    "addr:full":"1143 Tambell St Brownsville TN 38012",
    "addr:housenumber":"1143",
    "addr:postcode":"38012",
    "addr:street":"Tambell St",
    "iso:country":"US",
    "sg:address":"1143 Tambell St",
    "sg:city":"Brownsville",
    "sg:classifiers":[
        {
            "category":"Restaurant",
            "type":"Food & Drink"
        }
    ],
    "sg:phone":"+1 731 772 9901",
    "sg:postcode":"38012",
    "sg:province":"TN",
    "wof:name":"Cafe Rhema",
    "wof:placetype":"venue"
},
  "geometry": {"coordinates":[-89.24899499999999,35.605049],"type":"Point"}
}