{
  "type": "Feature",
  "properties": {
    "iso:country":"US",
    "sg:address":"2248 Whitten Rd",
    "sg:city":"Memphis",
    "sg:classifiers":[
        {
            "category":"Banks & Credit Unions",
            "subcategory":"Bank",
            "type":"Services"
        }
    ],
    "sg:phone":"+1 901 383 2350",
    "sg:postcode":"38133",
    "sg:province":"TN",
    "sg:tags":[
        "cashing",
        "check"
    ],
    "sg:website":"www.money4u.net",
    "wof:name":"MONEY4U.NET",
    "wof:placetype":"venue"
},
  "geometry": {"coordinates":[-89.835882,35.187012],"type":"Point"}
}