{
  "type": "Feature",
  "properties": {
    "iso:country":"US",
    "sg:address":"18525 Horton Hwy",
    "sg:city":"Fall Branch",
    "sg:classifiers":[
        {
            "category":"Professional",
            "subcategory":"Secretarial Services",
            "type":"Services"
        }
    ],
    "sg:phone":"+1 423 348 7641",
    "sg:postcode":"37656",
    "sg:province":"TN",
    "sg:tags":[
        "reporting"
    ],
    "wof:name":"First Rate Transcription",
    "wof:placetype":"venue"
},
  "geometry": {"coordinates":[-82.669416,36.400513],"type":"Point"}
}