{
  "type": "Feature",
  "properties": {
    "iso:country":"US",
    "sg:address":"144 Bain St",
    "sg:city":"La Vergne",
    "sg:classifiers":[
        {
            "category":"Professional",
            "subcategory":"Management & Consulting",
            "type":"Services"
        }
    ],
    "sg:phone":"+1 615 287 5706",
    "sg:postcode":"37086",
    "sg:province":"TN",
    "sg:tags":[
        "fuel"
    ],
    "wof:name":"Asset Management & Sales LLC",
    "wof:placetype":"venue"
},
  "geometry": {"coordinates":[-86.59129,36.004139],"type":"Point"}
}