{
  "type": "Feature",
  "properties": {
    "iso:country":"US",
    "sg:address":"3723 Charlotte Ave",
    "sg:city":"Nashville",
    "sg:classifiers":[
        {
            "category":"Manufacturing",
            "subcategory":"Printing",
            "type":"Manufacturing & Wholesale Goods"
        }
    ],
    "sg:phone":"+1 615 298 5544",
    "sg:postcode":"37209",
    "sg:province":"TN",
    "sg:tags":[
        "print",
        "digital",
        "fulfillment",
        "offset"
    ],
    "wof:name":"Print and Copy Ctr Peripherals",
    "wof:placetype":"venue"
},
  "geometry": {"coordinates":[-86.82885400000001,36.15271],"type":"Point"}
}