{
  "type": "Feature",
  "properties": {
    "iso:country":"US",
    "sg:address":"9101 Amos Rd",
    "sg:city":"Ooltewah",
    "sg:classifiers":[
        {
            "category":"Farming",
            "subcategory":"Dairy Farm",
            "type":"Manufacturing & Wholesale Goods"
        }
    ],
    "sg:phone":"+1 423 238 4832",
    "sg:postcode":"37363",
    "sg:province":"TN",
    "wof:name":"Brooks Dairy Inc",
    "wof:placetype":"venue"
},
  "geometry": {"coordinates":[-85.05898999999999,35.094069],"type":"Point"}
}