{
  "type": "Feature",
  "properties": {
    "iso:country":"US",
    "sg:address":"240 Lower Station Camp Creek Rd",
    "sg:city":"Gallatin",
    "sg:classifiers":[
        {
            "category":"Manufacturing",
            "subcategory":"Glass & Minerals",
            "type":"Manufacturing & Wholesale Goods"
        }
    ],
    "sg:phone":"+1 615 452 4620",
    "sg:postcode":"37066",
    "sg:province":"TN",
    "sg:tags":[
        "concrete",
        "brick"
    ],
    "wof:name":"Alley-Cassetty Brick & Block",
    "wof:placetype":"venue"
},
  "geometry": {"coordinates":[-86.551653,36.364181],"type":"Point"}
}