{
  "type": "Feature",
  "properties": {
    "iso:country":"US",
    "sg:address":"1187 Old Hickory Blvd",
    "sg:city":"Brentwood",
    "sg:classifiers":[
        {
            "category":"Real Estate",
            "subcategory":"Real Estate Agent",
            "type":"Services"
        }
    ],
    "sg:phone":"+1 615 309 7100",
    "sg:postcode":"37027",
    "sg:province":"TN",
    "sg:website":"www.crye-leike.com",
    "wof:name":"Crye-Leike Commercial",
    "wof:placetype":"venue"
},
  "geometry": {"coordinates":[-86.814549,36.039674],"type":"Point"}
}