{
  "type": "Feature",
  "properties": {
    "iso:country":"US",
    "sg:address":"8422 Daisy Dallas Rd",
    "sg:city":"Hixson",
    "sg:classifiers":[
        {
            "category":"Utilities",
            "subcategory":"Water",
            "type":"Services"
        }
    ],
    "sg:phone":"+1 423 843 0565",
    "sg:postcode":"37343",
    "sg:province":"TN",
    "sg:tags":[
        "bulk",
        "companies-bottled"
    ],
    "wof:name":"Blue Water Creations",
    "wof:placetype":"venue"
},
  "geometry": {"coordinates":[-85.16643500000001,35.205842],"type":"Point"}
}