{
  "type": "Feature",
  "properties": {
    "iso:country":"US",
    "sg:address":"7131 Centennial Pl",
    "sg:city":"Nashville",
    "sg:classifiers":[
        {
            "category":"Building & Trades",
            "subcategory":"Equipment Rental",
            "type":"Services"
        }
    ],
    "sg:phone":"+1 615 369 8200",
    "sg:postcode":"37209",
    "sg:province":"TN",
    "sg:tags":[
        "aircraft",
        "leasing",
        "charter"
    ],
    "sg:website":"www.secureair.aero",
    "wof:name":"Secure Air Charter",
    "wof:placetype":"venue"
},
  "geometry": {"coordinates":[-86.876278,36.176124],"type":"Point"}
}