{
  "type": "Feature",
  "properties": {
    "iso:country":"US",
    "sg:address":"2401 Dickerson Pike",
    "sg:city":"Nashville",
    "sg:classifiers":[
        {
            "category":"Retail",
            "subcategory":"Auto Repair",
            "type":"Services"
        }
    ],
    "sg:phone":"+1 615 262 3007",
    "sg:postcode":"37207",
    "sg:province":"TN",
    "sg:tags":[
        "general"
    ],
    "wof:name":"Emad Auto Repair",
    "wof:placetype":"venue"
},
  "geometry": {"coordinates":[-86.76652799999999,36.20932],"type":"Point"}
}