{
  "type": "Feature",
  "properties": {
    "addr:full":"409 Chickasaw Trl Goodlettsville TN 37072",
    "addr:housenumber":"409",
    "addr:postcode":"37072",
    "addr:street":"Chickasaw Trl",
    "iso:country":"US",
    "sg:address":"409 Chickasaw Trl",
    "sg:city":"Goodlettsville",
    "sg:classifiers":[
        {
            "category":"Real Estate",
            "subcategory":"Real Estate Agent",
            "type":"Services"
        }
    ],
    "sg:phone":"+1 615 851 7114",
    "sg:postcode":"37072",
    "sg:province":"TN",
    "wof:name":"Century Group LLC",
    "wof:placetype":"venue"
},
  "geometry": {"coordinates":[-86.684995,36.323563],"type":"Point"}
}