{
  "type": "Feature",
  "properties": {
    "iso:country":"US",
    "sg:address":"204 US Hwy 51 S",
    "sg:city":"Covington",
    "sg:classifiers":[
        {
            "category":"Real Estate",
            "subcategory":"Real Estate Agent",
            "type":"Services"
        }
    ],
    "sg:phone":"+1 901 476 2121",
    "sg:postcode":"38019",
    "sg:province":"TN",
    "wof:name":"Property Place",
    "wof:placetype":"venue"
},
  "geometry": {"coordinates":[-89.649745,35.563746],"type":"Point"}
}