{
  "type": "Feature",
  "properties": {
    "iso:country":"US",
    "sg:address":"661 N Mendenhall Rd",
    "sg:city":"Memphis",
    "sg:classifiers":[
        {
            "category":"Shopping",
            "subcategory":"Computers & Home Electronics",
            "type":"Retail Goods"
        }
    ],
    "sg:phone":"+1 901 767 8914",
    "sg:postcode":"38122",
    "sg:province":"TN",
    "sg:tags":[
        "software",
        "accessory",
        "supply"
    ],
    "wof:name":"Stewart Computer & Supply Inc",
    "wof:placetype":"venue"
},
  "geometry": {"coordinates":[-89.89794000000001,35.149219],"type":"Point"}
}