{
  "type": "Feature",
  "properties": {
    "iso:country":"US",
    "sg:address":"110 Oak Ridge Tpke",
    "sg:city":"Oak Ridge",
    "sg:classifiers":[
        {
            "category":"Autos & Motor Vehicles",
            "subcategory":"Motorcycle Sales",
            "type":"Retail Goods"
        }
    ],
    "sg:phone":"+1 865 425 0801",
    "sg:postcode":"37830",
    "sg:province":"TN",
    "wof:name":"Ridley Motorcycle Sales",
    "wof:placetype":"venue"
},
  "geometry": {"coordinates":[-84.208229,36.046312],"type":"Point"}
}