{
  "type": "Feature",
  "properties": {
    "iso:country":"US",
    "sg:address":"9200 Kingston Pike",
    "sg:city":"Knoxville",
    "sg:classifiers":[
        {
            "category":"Food & Beverages",
            "subcategory":"Groceries & Convenience Stores",
            "type":"Retail Goods"
        }
    ],
    "sg:phone":"+1 865 531 2015",
    "sg:postcode":"37922",
    "sg:province":"TN",
    "wof:name":"E-Z Stop Food Marts Inc",
    "wof:placetype":"venue"
},
  "geometry": {"coordinates":[-84.09092,35.9109],"type":"Point"}
}