{
  "type": "Feature",
  "properties": {
    "addr:full":"2909 Southway Dr Memphis TN 38118",
    "addr:housenumber":"2909",
    "addr:postcode":"38118",
    "addr:street":"Southway Dr",
    "iso:country":"US",
    "sg:address":"2909 Southway Dr",
    "sg:city":"Memphis",
    "sg:classifiers":[
        {
            "category":"Professional",
            "type":"Services"
        }
    ],
    "sg:phone":"+1 901 369 2661",
    "sg:postcode":"38118",
    "sg:province":"TN",
    "sg:tags":[
        "establishment"
    ],
    "wof:name":"Facilities Performance Group",
    "wof:placetype":"venue"
},
  "geometry": {"coordinates":[-89.96964199999999,35.067931],"type":"Point"}
}