{
  "type": "Feature",
  "properties": {
    "iso:country":"US",
    "sg:address":"2110 Knob Creek Rd",
    "sg:city":"Johnson City",
    "sg:classifiers":[
        {
            "category":"Organizations",
            "subcategory":"Religious Organization",
            "type":"Services"
        }
    ],
    "sg:phone":"+1 423 282 3882",
    "sg:postcode":"37604",
    "sg:province":"TN",
    "sg:tags":[
        "church"
    ],
    "wof:name":"Grace Free-Will Baptist Church",
    "wof:placetype":"venue"
},
  "geometry": {"coordinates":[-82.38979999999999,36.336594],"type":"Point"}
}