{
  "type": "Feature",
  "properties": {
    "iso:country":"US",
    "sg:address":"19869 Alberta St",
    "sg:city":"Oneida",
    "sg:classifiers":[
        {
            "category":"Restaurant",
            "type":"Food & Drink"
        }
    ],
    "sg:phone":"+1 423 569 5544",
    "sg:postcode":"37841",
    "sg:province":"TN",
    "sg:tags":[
        "eating"
    ],
    "wof:name":"KFC",
    "wof:placetype":"venue"
},
  "geometry": {"coordinates":[-84.496683,36.52486],"type":"Point"}
}