{
  "type": "Feature",
  "properties": {
    "addr:full":"1259 Columbia Ave Franklin TN 37064",
    "addr:housenumber":"1259",
    "addr:postcode":"37064",
    "addr:street":"Columbia Ave",
    "iso:country":"US",
    "sg:address":"1259 Columbia Ave",
    "sg:city":"Franklin",
    "sg:classifiers":[
        {
            "category":"Restaurant",
            "type":"Food & Drink"
        }
    ],
    "sg:phone":"+1 615 794 2400",
    "sg:postcode":"37064",
    "sg:province":"TN",
    "sg:tags":[
        "eating"
    ],
    "wof:name":"Pizza Hut",
    "wof:placetype":"venue"
},
  "geometry": {"coordinates":[-86.873529,35.915137],"type":"Point"}
}