{
  "type": "Feature",
  "properties": {
    "iso:country":"US",
    "sg:address":"1818 Dalton Pike SE",
    "sg:city":"Cleveland",
    "sg:classifiers":[
        {
            "category":"Autos & Motor Vehicles",
            "subcategory":"Automobile Sales",
            "type":"Retail Goods"
        }
    ],
    "sg:phone":"+1 423 339 1194",
    "sg:postcode":"37311",
    "sg:province":"TN",
    "sg:tags":[
        "car",
        "dealer"
    ],
    "wof:name":"J & S Auto Brokers",
    "wof:placetype":"venue"
},
  "geometry": {"coordinates":[-84.844365,35.157555],"type":"Point"}
}