{
  "type": "Feature",
  "properties": {
    "iso:country":"US",
    "sg:address":"868 Meagher St",
    "sg:city":"Memphis",
    "sg:classifiers":[
        {
            "category":"Organizations",
            "subcategory":"Religious Organization",
            "type":"Services"
        }
    ],
    "sg:phone":"+1 901 327 9117",
    "sg:postcode":"38108",
    "sg:province":"TN",
    "sg:tags":[
        "church"
    ],
    "wof:name":"True Bibleway Church Memphis",
    "wof:placetype":"venue"
},
  "geometry": {"coordinates":[-89.972565,35.159762],"type":"Point"}
}