{
  "type": "Feature",
  "properties": {
    "iso:country":"US",
    "sg:address":"3030 Ned Shelton Rd # 218",
    "sg:city":"Nashville",
    "sg:classifiers":[
        {
            "category":"Sports & Exercise",
            "subcategory":"Sports Center",
            "type":"Entertainment"
        }
    ],
    "sg:phone":"+1 615 818 0784",
    "sg:postcode":"37217",
    "sg:province":"TN",
    "sg:tags":[
        "club",
        "football"
    ],
    "wof:name":"A.D.S. Football & Associates",
    "wof:placetype":"venue"
},
  "geometry": {"coordinates":[-86.633667,36.097342],"type":"Point"}
}