{
  "type": "Feature",
  "properties": {
    "addr:full":"600 W Summit Hill Dr Knoxville TN 37902",
    "addr:housenumber":"600",
    "addr:postcode":"37902",
    "addr:street":"W Summit Hill Dr",
    "iso:country":"US",
    "sg:address":"600 W Summit Hill Dr",
    "sg:city":"Knoxville",
    "sg:classifiers":[
        {
            "category":"Government",
            "subcategory":"Fire Station",
            "type":"Public Place"
        }
    ],
    "sg:phone":"+1 865 525 8771",
    "sg:postcode":"37902",
    "sg:province":"TN",
    "sg:tags":[
        "department"
    ],
    "wof:name":"Knoxville Fire Chief",
    "wof:placetype":"venue"
},
  "geometry": {"coordinates":[-83.923587,35.964791],"type":"Point"}
}