{
  "type": "Feature",
  "properties": {
    "addr:full":"103 College St Madisonville TN 37354",
    "addr:housenumber":"103",
    "addr:postcode":"37354",
    "addr:street":"College St",
    "iso:country":"US",
    "sg:address":"103 College St",
    "sg:city":"Madisonville",
    "sg:classifiers":[
        {
            "category":"Government",
            "subcategory":"Court House",
            "type":"Public Place"
        }
    ],
    "sg:phone":"+1 423 442 2220",
    "sg:postcode":"37354",
    "sg:province":"TN",
    "sg:tags":[
        "county"
    ],
    "wof:name":"Monroe County Court Clerk",
    "wof:placetype":"venue"
},
  "geometry": {"coordinates":[-84.363433,35.520117],"type":"Point"}
}