{
  "type": "Feature",
  "properties": {
    "iso:country":"US",
    "sg:address":"740 W Clover Dr",
    "sg:city":"Memphis",
    "sg:classifiers":[
        {
            "category":"Arts & Performance",
            "subcategory":"Theater",
            "type":"Entertainment"
        }
    ],
    "sg:phone":"+1 901 767 8320",
    "sg:postcode":"38120",
    "sg:province":"TN",
    "sg:tags":[
        "clown"
    ],
    "wof:name":"Tinker Tunes & Balloons",
    "wof:placetype":"venue"
},
  "geometry": {"coordinates":[-89.88605099999999,35.11313],"type":"Point"}
}