{
  "type": "Feature",
  "properties": {
    "iso:country":"US",
    "sg:address":"3 Trahern Ter",
    "sg:city":"Clarksville",
    "sg:classifiers":[
        {
            "category":"Professional",
            "type":"Services"
        }
    ],
    "sg:phone":"+1 931 906 8485",
    "sg:postcode":"37040",
    "sg:province":"TN",
    "wof:name":"Martin D Bruner",
    "wof:placetype":"venue"
},
  "geometry": {"coordinates":[-87.337684,36.524519],"type":"Point"}
}