{
  "type": "Feature",
  "properties": {
    "addr:full":"1272 Lawson White Dr Columbia TN 38401",
    "addr:housenumber":"1272",
    "addr:postcode":"38401",
    "addr:street":"Lawson White Dr",
    "iso:country":"US",
    "sg:address":"1272 Lawson White Dr",
    "sg:city":"Columbia",
    "sg:classifiers":[
        {
            "category":"Government",
            "subcategory":"Jail",
            "type":"Public Place"
        }
    ],
    "sg:phone":"+1 931 490 0030",
    "sg:postcode":"38401",
    "sg:province":"TN",
    "sg:tags":[
        "correctional",
        "institution"
    ],
    "wof:name":"Juvenile Detention Center",
    "wof:placetype":"venue"
},
  "geometry": {"coordinates":[-87.065712,35.643861],"type":"Point"}
}