{
  "type": "Feature",
  "properties": {
    "iso:country":"US",
    "sg:address":"1630 S Church St",
    "sg:city":"Murfreesboro",
    "sg:classifiers":[
        {
            "category":"Health Services",
            "subcategory":"Doctor",
            "type":"Services"
        }
    ],
    "sg:phone":"+1 615 907 2529",
    "sg:postcode":"37130",
    "sg:province":"TN",
    "sg:tags":[
        "medical"
    ],
    "wof:name":"Cumberline Psychiatric Svcs",
    "wof:placetype":"venue"
},
  "geometry": {"coordinates":[-86.395488,35.81982],"type":"Point"}
}