{
  "type": "Feature",
  "properties": {
    "iso:country":"US",
    "sg:address":"3855 Eastend Dr",
    "sg:city":"Humboldt",
    "sg:classifiers":[
        {
            "category":"Shopping",
            "type":"Retail Goods"
        }
    ],
    "sg:phone":"+1 731 784 7855",
    "sg:postcode":"38343",
    "sg:province":"TN",
    "sg:tags":[
        "equipment",
        "telephone",
        "supply"
    ],
    "sg:website":"www.c-o-systems.com",
    "wof:name":"Central Office Systems",
    "wof:placetype":"venue"
},
  "geometry": {"coordinates":[-88.88814000000001,35.840799],"type":"Point"}
}