{
  "type": "Feature",
  "properties": {
    "iso:country":"US",
    "sg:address":"2004 Dearborn Dr",
    "sg:city":"Nashville",
    "sg:classifiers":[
        {
            "category":"Professional",
            "subcategory":"Art Services",
            "type":"Services"
        }
    ],
    "sg:phone":"+1 615 874 0285",
    "sg:postcode":"37214",
    "sg:province":"TN",
    "sg:tags":[
        "commercial",
        "design"
    ],
    "wof:name":"Art & Display Service",
    "wof:placetype":"venue"
},
  "geometry": {"coordinates":[-86.70229,36.168487],"type":"Point"}
}