{
  "type": "Feature",
  "properties": {
    "iso:country":"US",
    "sg:address":"2512 W Emory Rd",
    "sg:city":"Powell",
    "sg:classifiers":[
        {
            "category":"Professional",
            "subcategory":"Accounting & Tax Preparation",
            "type":"Services"
        }
    ],
    "sg:phone":"+1 865 938 9096",
    "sg:postcode":"37849",
    "sg:province":"TN",
    "sg:tags":[
        "accountant"
    ],
    "wof:name":"Daniel F Cooper CPA",
    "wof:placetype":"venue"
},
  "geometry": {"coordinates":[-84.034958,36.026205],"type":"Point"}
}