{
  "type": "Feature",
  "properties": {
    "addr:full":"4681 N Lee Hwy Suite C Cleveland TN 37312",
    "addr:housenumber":"4681",
    "addr:postcode":"37312",
    "addr:street":"N Lee Hwy Suite C",
    "iso:country":"US",
    "sg:address":"4681 N Lee Hwy Suite C",
    "sg:city":"Cleveland",
    "sg:classifiers":[
        {
            "category":"Insurance",
            "subcategory":"Hazard Insurance",
            "type":"Services"
        },
        {
            "category":"Insurance",
            "subcategory":"Insurance Agent",
            "type":"Services"
        },
        {
            "category":"Insurance",
            "subcategory":"Life Insurance",
            "type":"Services"
        }
    ],
    "sg:phone":"+1 423 244 0600",
    "sg:postcode":"37312",
    "sg:province":"TN",
    "sg:tags":[
        "auto"
    ],
    "sg:website":"http://statefarm.mqgroup.com/url.asp?usr=421732",
    "wof:name":"Connell, Buell - State Farm Insurance Agent",
    "wof:placetype":"venue"
},
  "geometry": {"coordinates":[-84.849701,35.194139],"type":"Point"}
}