{
  "type": "Feature",
  "properties": {
    "iso:country":"US",
    "sg:address":"2166 Gallatin Pike N",
    "sg:city":"Madison",
    "sg:classifiers":[
        {
            "category":"Shopping",
            "subcategory":"Shoes",
            "type":"Retail Goods"
        }
    ],
    "sg:phone":"+1 615 851 9881",
    "sg:postcode":"37115",
    "sg:province":"TN",
    "sg:website":"www.shoecarnival.com",
    "wof:name":"Shoe Carnival 33",
    "wof:placetype":"venue"
},
  "geometry": {"coordinates":[-86.690234,36.303649],"type":"Point"}
}