{
  "type": "Feature",
  "properties": {
    "iso:country":"US",
    "sg:address":"3711 Hickory Hill Rd",
    "sg:city":"Memphis",
    "sg:classifiers":[
        {
            "category":"Professional",
            "subcategory":"Accounting & Tax Preparation",
            "type":"Services"
        }
    ],
    "sg:phone":"+1 901 547 6040",
    "sg:postcode":"38115",
    "sg:province":"TN",
    "sg:tags":[
        "return",
        "filing"
    ],
    "wof:name":"Mo Money Tax Svc",
    "wof:placetype":"venue"
},
  "geometry": {"coordinates":[-89.866457,35.048906],"type":"Point"}
}