{
  "type": "Feature",
  "properties": {
    "addr:full":"1515 N Pkwy Memphis TN 38112",
    "addr:housenumber":"1515",
    "addr:postcode":"38112",
    "addr:street":"N Pkwy",
    "iso:country":"US",
    "sg:address":"1515 N Pkwy",
    "sg:city":"Memphis",
    "sg:classifiers":[
        {
            "category":"Professional",
            "subcategory":"Management & Consulting",
            "type":"Services"
        }
    ],
    "sg:phone":"+1 901 327 3080",
    "sg:postcode":"38112",
    "sg:province":"TN",
    "sg:tags":[
        "consultant",
        "business"
    ],
    "wof:name":"Occupational Health Cnsltnts",
    "wof:placetype":"venue"
},
  "geometry": {"coordinates":[-90.00834999999999,35.153532],"type":"Point"}
}