{
  "type": "Feature",
  "properties": {
    "iso:country":"US",
    "sg:address":"634 Madison St",
    "sg:city":"Clarksville",
    "sg:classifiers":[
        {
            "category":"Shopping",
            "subcategory":"Florist",
            "type":"Retail Goods"
        }
    ],
    "sg:phone":"+1 931 503 1199",
    "sg:postcode":"37040",
    "sg:province":"TN",
    "wof:name":"Bella Fiori",
    "wof:placetype":"venue"
},
  "geometry": {"coordinates":[-87.350562,36.526692],"type":"Point"}
}