{
  "type": "Feature",
  "properties": {
    "iso:country":"US",
    "sg:address":"1005 Inglewood Dr",
    "sg:city":"Knoxville",
    "sg:classifiers":[
        {
            "category":"Professional",
            "type":"Services"
        }
    ],
    "sg:phone":"+1 865 524 0485",
    "sg:postcode":"37914",
    "sg:province":"TN",
    "wof:name":"Theophilus Studios",
    "wof:placetype":"venue"
},
  "geometry": {"coordinates":[-83.844751,35.997996],"type":"Point"}
}