{
  "type": "Feature",
  "properties": {
    "addr:full":"638 Rock Springs Midland Rd Christiana TN 37037",
    "addr:housenumber":"638",
    "addr:postcode":"37037",
    "addr:street":"Rock;Midland Rd",
    "iso:country":"US",
    "sg:address":"638 Rock Springs Midland Rd",
    "sg:city":"Christiana",
    "sg:classifiers":[
        {
            "category":"Freight",
            "type":"Transportation"
        }
    ],
    "sg:phone":"+1 615 890 5364",
    "sg:postcode":"37037",
    "sg:province":"TN",
    "wof:name":"L&D Transport Inc",
    "wof:placetype":"venue"
},
  "geometry": {"coordinates":[-86.43029,35.700743],"type":"Point"}
}