{
  "type": "Feature",
  "properties": {
    "iso:country":"US",
    "sg:address":"520 Hwy 76",
    "sg:city":"White House",
    "sg:classifiers":[
        {
            "category":"Restaurant",
            "type":"Food & Drink"
        }
    ],
    "sg:phone":"+1 615 672 1270",
    "sg:postcode":"37188",
    "sg:province":"TN",
    "wof:name":"Kobe's Asian Restaurant",
    "wof:placetype":"venue"
},
  "geometry": {"coordinates":[-86.666156,36.468824],"type":"Point"}
}