{
  "type": "Feature",
  "properties": {
    "addr:full":"8041 Esterbrook Dr Nashville TN 37221",
    "addr:housenumber":"8041",
    "addr:postcode":"37221",
    "addr:street":"Esterbrook Dr",
    "iso:country":"US",
    "sg:address":"8041 Esterbrook Dr",
    "sg:city":"Nashville",
    "sg:classifiers":[
        {
            "category":"Organizations",
            "subcategory":"Religious Organization",
            "type":"Services"
        }
    ],
    "sg:phone":"+1 615 646 7827",
    "sg:postcode":"37221",
    "sg:province":"TN",
    "wof:name":"Family Based Youth Ministries",
    "wof:placetype":"venue"
},
  "geometry": {"coordinates":[-86.940725,36.081484],"type":"Point"}
}