{
  "type": "Feature",
  "properties": {
    "iso:country":"US",
    "sg:address":"21 Stoneway",
    "sg:city":"Crossville",
    "sg:classifiers":[
        {
            "category":"Banks & Credit Unions",
            "subcategory":"Financial Services",
            "type":"Services"
        }
    ],
    "sg:phone":"+1 931 456 6463",
    "sg:postcode":"38555",
    "sg:province":"TN",
    "sg:tags":[
        "investor"
    ],
    "wof:name":"Cse Investments LLC",
    "wof:placetype":"venue"
},
  "geometry": {"coordinates":[-85.004514,35.9495],"type":"Point"}
}