{
  "type": "Feature",
  "properties": {
    "iso:country":"US",
    "sg:address":"1760 Madison St",
    "sg:city":"Clarksville",
    "sg:classifiers":[
        {
            "category":"Health Services",
            "subcategory":"Clinic",
            "type":"Services"
        }
    ],
    "sg:phone":"+1 931 648 4576",
    "sg:postcode":"37043",
    "sg:province":"TN",
    "sg:tags":[
        "home"
    ],
    "wof:name":"Gateway Home Care Of Gateway",
    "wof:placetype":"venue"
},
  "geometry": {"coordinates":[-87.317066,36.514282],"type":"Point"}
}