{
  "type": "Feature",
  "properties": {
    "iso:country":"US",
    "sg:address":"510 Cumberland St",
    "sg:city":"Bristol",
    "sg:classifiers":[
        {
            "category":"Wholesale",
            "subcategory":"Drugs",
            "type":"Manufacturing & Wholesale Goods"
        }
    ],
    "sg:phone":"+1 276 669 9174",
    "sg:postcode":"24201",
    "sg:province":"TN",
    "sg:tags":[
        "pharmaceutical",
        "product"
    ],
    "wof:name":"King Pharmaceuticals Inc",
    "wof:placetype":"venue"
},
  "geometry": {"coordinates":[-82.182967,36.596451],"type":"Point"}
}