{
  "type": "Feature",
  "properties": {
    "iso:country":"US",
    "sg:address":"8279 S Fletcher Run Cir",
    "sg:city":"Cordova",
    "sg:classifiers":[
        {
            "category":"Food & Beverages",
            "subcategory":"Groceries & Convenience Stores",
            "type":"Retail Goods"
        }
    ],
    "sg:phone":"+1 901 309 8672",
    "sg:postcode":"38016",
    "sg:province":"TN",
    "wof:name":"Club 83 Bemrs LLC",
    "wof:placetype":"venue"
},
  "geometry": {"coordinates":[-89.786986,35.175816],"type":"Point"}
}