{
  "type": "Feature",
  "properties": {
    "iso:country":"US",
    "sg:address":"151 Bank Ave",
    "sg:city":"Huntsville",
    "sg:classifiers":[
        {
            "category":"Education",
            "subcategory":"Library",
            "type":"Public Place"
        }
    ],
    "sg:phone":"+1 423 663 9230",
    "sg:postcode":"37769",
    "sg:province":"TN",
    "wof:name":"Huntsville Public Library",
    "wof:placetype":"venue"
},
  "geometry": {"coordinates":[-84.155164,36.214717],"type":"Point"}
}