{
  "type": "Feature",
  "properties": {
    "iso:country":"US",
    "sg:address":"403 N College St",
    "sg:city":"Mount Pleasant",
    "sg:classifiers":[
        {
            "category":"Building & Trades",
            "subcategory":"Electrical",
            "type":"Services"
        }
    ],
    "sg:phone":"+1 931 379 4564",
    "sg:postcode":"38474",
    "sg:province":"TN",
    "sg:tags":[
        "electrical",
        "contractor"
    ],
    "wof:name":"Jacksons Electric",
    "wof:placetype":"venue"
},
  "geometry": {"coordinates":[-87.21208,35.54308],"type":"Point"}
}