{
  "type": "Feature",
  "properties": {
    "iso:country":"US",
    "sg:address":"68 Academy Ln",
    "sg:city":"Mc Minnville",
    "sg:classifiers":[
        {
            "category":"Building & Trades",
            "subcategory":"Construction",
            "type":"Services"
        },
        {
            "category":"Home & Garden",
            "subcategory":"Furniture",
            "type":"Retail Goods"
        }
    ],
    "sg:phone":"+1 931 668 3362",
    "sg:postcode":"37110",
    "sg:province":"TN",
    "sg:tags":[
        "maker",
        "cabinet"
    ],
    "wof:name":"Baker's Cabinets",
    "wof:placetype":"venue"
},
  "geometry": {"coordinates":[-85.781498,35.714705],"type":"Point"}
}