{
  "type": "Feature",
  "properties": {
    "iso:country":"US",
    "sg:address":"1619 Hutchinson Ave",
    "sg:city":"Knoxville",
    "sg:classifiers":[
        {
            "category":"Real Estate",
            "subcategory":"Real Estate Operator",
            "type":"Services"
        }
    ],
    "sg:phone":"+1 865 637 2590",
    "sg:postcode":"37917",
    "sg:province":"TN",
    "sg:tags":[
        "apartment"
    ],
    "wof:name":"Blh Enterprises",
    "wof:placetype":"venue"
},
  "geometry": {"coordinates":[-83.923728,35.998879],"type":"Point"}
}