{
  "type": "Feature",
  "properties": {
    "iso:country":"US",
    "sg:address":"2709 Windthrush Dr",
    "sg:city":"Chattanooga",
    "sg:classifiers":[
        {
            "category":"Manufacturing",
            "subcategory":"Metals",
            "type":"Manufacturing & Wholesale Goods"
        },
        {
            "category":"Manufacturing",
            "subcategory":"Jewelry",
            "type":"Manufacturing & Wholesale Goods"
        }
    ],
    "sg:phone":"+1 423 855 9987",
    "sg:postcode":"37421",
    "sg:province":"TN",
    "sg:tags":[
        "platinum",
        "buyer",
        "metals-precious",
        "silver",
        "gold"
    ],
    "wof:name":"Simply Silver",
    "wof:placetype":"venue"
},
  "geometry": {"coordinates":[-85.108182,35.037908],"type":"Point"}
}