{
  "type": "Feature",
  "properties": {
    "addr:full":"494 N Spring St Sparta TN 38583",
    "addr:housenumber":"494",
    "addr:postcode":"38583",
    "addr:street":"N Spring St",
    "iso:country":"US",
    "sg:address":"494 N Spring St",
    "sg:city":"Sparta",
    "sg:classifiers":[
        {
            "category":"Real Estate",
            "subcategory":"Real Estate Agent",
            "type":"Services"
        }
    ],
    "sg:phone":"+1 931 836 6300",
    "sg:postcode":"38583",
    "sg:province":"TN",
    "wof:name":"M L Brown Realty",
    "wof:placetype":"venue"
},
  "geometry": {"coordinates":[-85.482872,35.962863],"type":"Point"}
}