{
  "type": "Feature",
  "properties": {
    "iso:country":"US",
    "sg:address":"4560 Neely Rd",
    "sg:city":"Memphis",
    "sg:classifiers":[
        {
            "category":"Personal",
            "type":"Services"
        }
    ],
    "sg:phone":"+1 901 786 0230",
    "sg:postcode":"38109",
    "sg:province":"TN",
    "sg:tags":[
        "home",
        "improvement"
    ],
    "wof:name":"House Sold Corp",
    "wof:placetype":"venue"
},
  "geometry": {"coordinates":[-90.056453,35.024948],"type":"Point"}
}