{
  "type": "Feature",
  "properties": {
    "iso:country":"US",
    "sg:address":"422 Beth Dr",
    "sg:city":"Mt Juliet",
    "sg:classifiers":[
        {
            "category":"Building & Trades",
            "subcategory":"Construction",
            "type":"Services"
        }
    ],
    "sg:phone":"+1 615 516 9438",
    "sg:postcode":"37122",
    "sg:province":"TN",
    "sg:tags":[
        "restoration",
        "cleaning",
        "patio",
        "deck"
    ],
    "wof:name":"Pressure Washing Unlimited Inc",
    "wof:placetype":"venue"
},
  "geometry": {"coordinates":[-86.546953,36.273021],"type":"Point"}
}