{
  "type": "Feature",
  "properties": {
    "iso:country":"US",
    "sg:address":"7537 US Hwy 64",
    "sg:city":"Bartlett",
    "sg:classifiers":[
        {
            "category":"Health Services",
            "subcategory":"Health Practitioner",
            "type":"Services"
        }
    ],
    "sg:phone":"+1 901 213 2900",
    "sg:postcode":"38133",
    "sg:province":"TN",
    "sg:tags":[
        "therapist",
        "physical"
    ],
    "wof:name":"Trace Caulkins Physiotherapy",
    "wof:placetype":"venue"
},
  "geometry": {"coordinates":[-89.81083599999999,35.204661],"type":"Point"}
}