{
  "type": "Feature",
  "properties": {
    "iso:country":"US",
    "sg:address":"9337 S Northshore Dr",
    "sg:city":"Knoxville",
    "sg:classifiers":[
        {
            "category":"Autos & Motor Vehicles",
            "subcategory":"Auto Supplies",
            "type":"Retail Goods"
        }
    ],
    "sg:phone":"+1 865 539 6322",
    "sg:postcode":"37922",
    "sg:province":"TN",
    "sg:tags":[
        "automobile",
        "part",
        "batteries-storage"
    ],
    "sg:website":"http://www.advanceautoparts.com",
    "wof:name":"Advance Auto Parts",
    "wof:placetype":"venue"
},
  "geometry": {"coordinates":[-84.06239100000001,35.864892],"type":"Point"}
}