{
  "type": "Feature",
  "properties": {
    "iso:country":"US",
    "sg:address":"712 Kendall Dr",
    "sg:city":"Nashville",
    "sg:classifiers":[
        {
            "category":"Manufacturing",
            "subcategory":"Textiles",
            "type":"Manufacturing & Wholesale Goods"
        }
    ],
    "sg:phone":"+1 615 352 2569",
    "sg:postcode":"37209",
    "sg:province":"TN",
    "sg:tags":[
        "mfg"
    ],
    "wof:name":"Bentley Prince Street Inc",
    "wof:placetype":"venue"
},
  "geometry": {"coordinates":[-86.86145500000001,36.136766],"type":"Point"}
}