{
  "type": "Feature",
  "properties": {
    "iso:country":"US",
    "sg:address":"6116 Strawberry Plains Pike",
    "sg:city":"Knoxville",
    "sg:classifiers":[
        {
            "category":"Shopping",
            "subcategory":"Luggage & Leather Goods",
            "type":"Retail Goods"
        }
    ],
    "sg:phone":"+1 865 898 8035",
    "sg:postcode":"37914",
    "sg:province":"TN",
    "wof:name":"Dixie Leather",
    "wof:placetype":"venue"
},
  "geometry": {"coordinates":[-83.803845,35.984023],"type":"Point"}
}