{
  "type": "Feature",
  "properties": {
    "iso:country":"US",
    "sg:address":"101 W Irving Ln",
    "sg:city":"Oak Ridge",
    "sg:classifiers":[
        {
            "category":"Building & Trades",
            "subcategory":"Construction",
            "type":"Services"
        }
    ],
    "sg:phone":"+1 865 389 2828",
    "sg:postcode":"37830",
    "sg:province":"TN",
    "sg:tags":[
        "dry wall",
        "contractor"
    ],
    "wof:name":"Shelton Family Drywall",
    "wof:placetype":"venue"
},
  "geometry": {"coordinates":[-84.280818,36.013451],"type":"Point"}
}