{
  "type": "Feature",
  "properties": {
    "iso:country":"US",
    "sg:address":"254 Harpeth Hills Dr",
    "sg:city":"Kingston Springs",
    "sg:classifiers":[
        {
            "category":"Retail",
            "subcategory":"Laundry & Dry Cleaning",
            "type":"Services"
        }
    ],
    "sg:phone":"+1 615 952 2808",
    "sg:postcode":"37082",
    "sg:province":"TN",
    "sg:tags":[
        "cleaners",
        "rug",
        "carpet"
    ],
    "wof:name":"Bane-Clene Way",
    "wof:placetype":"venue"
},
  "geometry": {"coordinates":[-87.099239,36.076202],"type":"Point"}
}