{
  "type": "Feature",
  "properties": {
    "iso:country":"US",
    "sg:address":"311 Lark St",
    "sg:city":"Bristol",
    "sg:classifiers":[
        {
            "category":"Personal",
            "subcategory":"Beauty Salon",
            "type":"Services"
        }
    ],
    "sg:phone":"+1 423 764 9741",
    "sg:postcode":"37620",
    "sg:province":"TN",
    "wof:name":"Creative Edge Hair Design",
    "wof:placetype":"venue"
},
  "geometry": {"coordinates":[-82.184921,36.577155],"type":"Point"}
}