{
  "type": "Feature",
  "properties": {
    "addr:full":"6817 Charlotte Pike Nashville TN 37209",
    "addr:housenumber":"6817",
    "addr:postcode":"37209",
    "addr:street":"Charlotte Pike",
    "iso:country":"US",
    "sg:address":"6817 Charlotte Pike",
    "sg:city":"Nashville",
    "sg:classifiers":[
        {
            "category":"Building & Trades",
            "subcategory":"Landscaping Services",
            "type":"Services"
        }
    ],
    "sg:phone":"+1 615 352 4446",
    "sg:postcode":"37209",
    "sg:province":"TN",
    "sg:tags":[
        "landscape"
    ],
    "wof:name":"Canady Landscape Management",
    "wof:placetype":"venue"
},
  "geometry": {"coordinates":[-86.88807199999999,36.134712],"type":"Point"}
}