{
  "type": "Feature",
  "properties": {
    "iso:country":"US",
    "sg:address":"4235 Summer Ave",
    "sg:city":"Memphis",
    "sg:classifiers":[
        {
            "category":"Shopping",
            "subcategory":"Computers & Home Electronics",
            "type":"Retail Goods"
        }
    ],
    "sg:phone":"+1 901 767 4851",
    "sg:postcode":"38122",
    "sg:province":"TN",
    "wof:name":"Radio Shack",
    "wof:placetype":"venue"
},
  "geometry": {"coordinates":[-89.91871999999999,35.148859],"type":"Point"}
}