{
  "type": "Feature",
  "properties": {
    "addr:full":"1205 Russell St Nashville TN 37206",
    "addr:housenumber":"1205",
    "addr:postcode":"37206",
    "addr:street":"Russell St",
    "iso:country":"US",
    "sg:address":"1205 Russell St",
    "sg:city":"Nashville",
    "sg:classifiers":[
        {
            "category":"Manufacturing",
            "subcategory":"Printing",
            "type":"Manufacturing & Wholesale Goods"
        }
    ],
    "sg:phone":"+1 615 228 5336",
    "sg:postcode":"37206",
    "sg:province":"TN",
    "sg:tags":[
        "screen"
    ],
    "wof:name":"M-Prints Inc",
    "wof:placetype":"venue"
},
  "geometry": {"coordinates":[-86.74819100000001,36.175136],"type":"Point"}
}