{
  "type": "Feature",
  "properties": {
    "addr:full":"1239 Hampshire Pike Columbia TN 38401",
    "addr:housenumber":"1239",
    "addr:postcode":"38401",
    "addr:street":"Hampshire Pike",
    "iso:country":"US",
    "sg:address":"1239 Hampshire Pike",
    "sg:city":"Columbia",
    "sg:classifiers":[
        {
            "category":"Shopping",
            "subcategory":"Used Merchandise",
            "type":"Retail Goods"
        }
    ],
    "sg:phone":"+1 931 388 6204",
    "sg:postcode":"38401",
    "sg:province":"TN",
    "wof:name":"French Tulip",
    "wof:placetype":"venue"
},
  "geometry": {"coordinates":[-87.072255,35.618124],"type":"Point"}
}