{
  "type": "Feature",
  "properties": {
    "addr:full":"412 Bantry Ln Knoxville TN 37934",
    "addr:housenumber":"412",
    "addr:postcode":"37934",
    "addr:street":"Bantry Ln",
    "iso:country":"US",
    "sg:address":"412 Bantry Ln",
    "sg:city":"Knoxville",
    "sg:classifiers":[
        {
            "category":"Shopping",
            "subcategory":"Beauty & Cosmetics",
            "type":"Retail Goods"
        }
    ],
    "sg:phone":"+1 865 675 7962",
    "sg:postcode":"37934",
    "sg:province":"TN",
    "sg:tags":[
        "surgical",
        "appliance"
    ],
    "wof:name":"Affordable Medical Air Devices",
    "wof:placetype":"venue"
},
  "geometry": {"coordinates":[-84.165395,35.866059],"type":"Point"}
}