{
  "type": "Feature",
  "properties": {
    "addr:full":"756 Beechcroft Rd Spring Hill TN 37174",
    "addr:housenumber":"756",
    "addr:postcode":"37174",
    "addr:street":"Beechcroft Rd",
    "iso:country":"US",
    "sg:address":"756 Beechcroft Rd",
    "sg:city":"Spring Hill",
    "sg:classifiers":[
        {
            "category":"Education",
            "subcategory":"Special Training",
            "type":"Public Place"
        }
    ],
    "sg:phone":"+1 931 486 1777",
    "sg:postcode":"37174",
    "sg:province":"TN",
    "sg:tags":[
        "program"
    ],
    "wof:name":"Saturn Technical Training Ctr",
    "wof:placetype":"venue"
},
  "geometry": {"coordinates":[-86.96677699999999,35.752927],"type":"Point"}
}