{
  "type": "Feature",
  "properties": {
    "iso:country":"US",
    "sg:address":"501 Broadway",
    "sg:city":"Nashville",
    "sg:classifiers":[
        {
            "category":"Professional",
            "subcategory":"Management & Consulting",
            "type":"Services"
        }
    ],
    "sg:phone":"+1 615 770 2470",
    "sg:postcode":"37203",
    "sg:province":"TN",
    "sg:tags":[
        "food"
    ],
    "sg:website":"www.levyrestaurants.com",
    "wof:name":"Levy Restaurant",
    "wof:placetype":"venue"
},
  "geometry": {"coordinates":[-86.779572,36.15999],"type":"Point"}
}