{
  "type": "Feature",
  "properties": {
    "iso:country":"US",
    "sg:address":"229 Ward Cir",
    "sg:city":"Brentwood",
    "sg:classifiers":[
        {
            "category":"Banks & Credit Unions",
            "subcategory":"Investment Brokerage",
            "type":"Services"
        },
        {
            "category":"Banks & Credit Unions",
            "subcategory":"Bank",
            "type":"Services"
        }
    ],
    "sg:phone":"+1 615 370 1242",
    "sg:postcode":"37027",
    "sg:province":"TN",
    "sg:tags":[
        "consultant",
        "security",
        "planning",
        "financial"
    ],
    "wof:name":"Trust Mark Financial Inc",
    "wof:placetype":"venue"
},
  "geometry": {"coordinates":[-86.80165100000001,36.033978],"type":"Point"}
}