{
  "type": "Feature",
  "properties": {
    "iso:country":"US",
    "sg:address":"108 W Cleveland Ave",
    "sg:city":"Monterey",
    "sg:classifiers":[
        {
            "category":"Organizations",
            "subcategory":"Community Association",
            "type":"Services"
        }
    ],
    "sg:phone":"+1 931 839 3350",
    "sg:postcode":"38574",
    "sg:province":"TN",
    "wof:name":"Civitan International",
    "wof:placetype":"venue"
},
  "geometry": {"coordinates":[-85.267048,36.150144],"type":"Point"}
}