{
  "type": "Feature",
  "properties": {
    "iso:country":"US",
    "sg:address":"1649 Spry Rd",
    "sg:city":"Bradyville",
    "sg:classifiers":[
        {
            "category":"Professional",
            "type":"Services"
        }
    ],
    "sg:phone":"+1 615 765 7376",
    "sg:postcode":"37026",
    "sg:province":"TN",
    "wof:name":"Kim Fann",
    "wof:placetype":"venue"
},
  "geometry": {"coordinates":[-86.08877699999999,35.647808],"type":"Point"}
}