{
  "type": "Feature",
  "properties": {
    "iso:country":"US",
    "sg:address":"315 Union St",
    "sg:city":"Nashville",
    "sg:classifiers":[
        {
            "category":"Professional",
            "subcategory":"Lawyer & Legal Services",
            "type":"Services"
        }
    ],
    "sg:phone":"+1 615 726 5461",
    "sg:postcode":"37201",
    "sg:province":"TN",
    "sg:tags":[
        "attorney"
    ],
    "wof:name":"King & Balow",
    "wof:placetype":"venue"
},
  "geometry": {"coordinates":[-86.779027,36.165322],"type":"Point"}
}