{
  "type": "Feature",
  "properties": {
    "iso:country":"US",
    "sg:address":"7224 Red Barn Ln",
    "sg:city":"Fairview",
    "sg:classifiers":[
        {
            "category":"Building & Trades",
            "subcategory":"Construction",
            "type":"Services"
        }
    ],
    "sg:phone":"+1 615 799 0062",
    "sg:postcode":"37062",
    "sg:province":"TN",
    "sg:tags":[
        "hanging",
        "contractor"
    ],
    "wof:name":"L & P Trim & Mill Work LLC",
    "wof:placetype":"venue"
},
  "geometry": {"coordinates":[-87.17028500000001,36.004791],"type":"Point"}
}