{
  "type": "Feature",
  "properties": {
    "iso:country":"US",
    "sg:address":"111 Choctaw Cir",
    "sg:city":"White House",
    "sg:classifiers":[
        {
            "category":"Professional",
            "type":"Services"
        }
    ],
    "sg:phone":"+1 615 672 0163",
    "sg:postcode":"37188",
    "sg:province":"TN",
    "sg:tags":[
        "establishment"
    ],
    "wof:name":"S T Dynamics",
    "wof:placetype":"venue"
},
  "geometry": {"coordinates":[-86.65680999999999,36.478533],"type":"Point"}
}