{
  "type": "Feature",
  "properties": {
    "iso:country":"US",
    "sg:address":"111 N Washington Ave",
    "sg:city":"Brownsville",
    "sg:classifiers":[
        {
            "category":"Professional",
            "type":"Services"
        },
        {
            "category":"Social Services",
            "type":"Services"
        }
    ],
    "sg:phone":"+1 731 772 0467",
    "sg:postcode":"38012",
    "sg:province":"TN",
    "wof:name":"Western Services Inc",
    "wof:placetype":"venue"
},
  "geometry": {"coordinates":[-89.262229,35.595604],"type":"Point"}
}