{
  "type": "Feature",
  "properties": {
    "addr:full":"403 Old Mill Rd Wartburg TN 37887",
    "addr:housenumber":"403",
    "addr:postcode":"37887",
    "addr:street":"Old Mill Rd",
    "iso:country":"US",
    "sg:address":"403 Old Mill Rd",
    "sg:city":"Wartburg",
    "sg:classifiers":[
        {
            "category":"Professional",
            "subcategory":"Management & Consulting",
            "type":"Services"
        }
    ],
    "sg:phone":"+1 423 346 6529",
    "sg:postcode":"37887",
    "sg:province":"TN",
    "sg:tags":[
        "business"
    ],
    "wof:name":"Potter Enterprise Company",
    "wof:placetype":"venue"
},
  "geometry": {"coordinates":[-84.59250400000001,36.103887],"type":"Point"}
}