{
  "type": "Feature",
  "properties": {
    "iso:country":"US",
    "sg:address":"347 Arrowhead Ct",
    "sg:city":"Kingston Springs",
    "sg:classifiers":[
        {
            "category":"Professional",
            "subcategory":"Business Services",
            "type":"Services"
        }
    ],
    "sg:phone":"+1 615 952 4422",
    "sg:postcode":"37082",
    "sg:province":"TN",
    "wof:name":"Promotional Allies",
    "wof:placetype":"venue"
},
  "geometry": {"coordinates":[-87.087137,36.102501],"type":"Point"}
}