{
  "type": "Feature",
  "properties": {
    "addr:full":"6325 N Quail Hollow Rd Memphis TN 38120",
    "addr:housenumber":"6325",
    "addr:postcode":"38120",
    "addr:street":"N Quail Hollow Rd",
    "iso:country":"US",
    "sg:address":"6325 N Quail Hollow Rd",
    "sg:city":"Memphis",
    "sg:classifiers":[
        {
            "category":"Travel",
            "subcategory":"Hotels & Motels",
            "type":"Entertainment"
        }
    ],
    "sg:phone":"+1 901 685 7575",
    "sg:postcode":"38120",
    "sg:province":"TN",
    "sg:tags":[
        "corporate",
        "lodging"
    ],
    "sg:website":"http://redirect.searchignite.com/si/cm/tracking/DGTrackingRedirect.aspx?siclientid=2918&siredirect=http%3A%2F%2Fwww%2Eextendedstayamerica%2Ecom%2FMPA&sisearchengine=155&siproduct=ESA+Memphis+%2D+Poplar+Avenue&clearppc=1",
    "wof:name":"Extended Stay America Memphis - Poplar Avenue",
    "wof:placetype":"venue"
},
  "geometry": {"coordinates":[-89.853228,35.104475],"type":"Point"}
}