{
  "type": "Feature",
  "properties": {
    "addr:full":"8005 Plaxco Dr Chattanooga TN 37421",
    "addr:housenumber":"8005",
    "addr:postcode":"37421",
    "addr:street":"Plaxco Dr",
    "iso:country":"US",
    "sg:address":"8005 Plaxco Dr",
    "sg:city":"Chattanooga",
    "sg:classifiers":[
        {
            "category":"Building & Trades",
            "subcategory":"Plumbing",
            "type":"Services"
        }
    ],
    "sg:phone":"+1 423 893 9381",
    "sg:postcode":"37421",
    "sg:province":"TN",
    "sg:tags":[
        "conditioning",
        "air",
        "system",
        "contractor"
    ],
    "wof:name":"Certified Gas Piping & Appls",
    "wof:placetype":"venue"
},
  "geometry": {"coordinates":[-85.15526800000001,34.993688],"type":"Point"}
}