{
  "type": "Feature",
  "properties": {
    "addr:full":"1412 McCallie Ave Chattanooga TN 37404",
    "addr:housenumber":"1412",
    "addr:postcode":"37404",
    "addr:street":"Mccallie Ave",
    "iso:country":"US",
    "sg:address":"1412 McCallie Ave",
    "sg:city":"Chattanooga",
    "sg:classifiers":[
        {
            "category":"Personal",
            "subcategory":"Beauty Salon",
            "type":"Services"
        }
    ],
    "sg:phone":"+1 423 698 5370",
    "sg:postcode":"37404",
    "sg:province":"TN",
    "wof:name":"Genos Salon",
    "wof:placetype":"venue"
},
  "geometry": {"coordinates":[-85.280399,35.03795],"type":"Point"}
}