{
  "type": "Feature",
  "properties": {
    "addr:full":"1995 Union Ave Memphis TN 38104",
    "addr:housenumber":"1995",
    "addr:postcode":"38104",
    "addr:street":"Union Ave",
    "iso:country":"US",
    "sg:address":"1995 Union Ave",
    "sg:city":"Memphis",
    "sg:classifiers":[
        {
            "category":"Manufacturing",
            "subcategory":"Wood Products",
            "type":"Manufacturing & Wholesale Goods"
        }
    ],
    "sg:phone":"+1 901 452 5565",
    "sg:postcode":"38104",
    "sg:province":"TN",
    "sg:tags":[
        "art",
        "framing",
        "custom"
    ],
    "wof:name":"Town & Country Custom Framing",
    "wof:placetype":"venue"
},
  "geometry": {"coordinates":[-89.994603,35.134531],"type":"Point"}
}