{
  "type": "Feature",
  "properties": {
    "iso:country":"US",
    "sg:address":"3825 Proffitt Ln",
    "sg:city":"Knoxville",
    "sg:classifiers":[
        {
            "category":"Restaurant",
            "type":"Food & Drink"
        }
    ],
    "sg:phone":"+1 865 539 1099",
    "sg:postcode":"37931",
    "sg:province":"TN",
    "sg:tags":[
        "personal",
        "bakery",
        "retail",
        "eating",
        "caterer"
    ],
    "wof:name":"Karen's Katering",
    "wof:placetype":"venue"
},
  "geometry": {"coordinates":[-84.133506,35.992265],"type":"Point"}
}