{
  "type": "Feature",
  "properties": {
    "addr:full":"480 Neal St Cookeville TN 38501",
    "addr:housenumber":"480",
    "addr:postcode":"38501",
    "addr:street":"Neal St",
    "iso:country":"US",
    "sg:address":"480 Neal St",
    "sg:city":"Cookeville",
    "sg:classifiers":[
        {
            "category":"Professional",
            "type":"Services"
        }
    ],
    "sg:phone":"+1 866 525 1430",
    "sg:postcode":"38501",
    "sg:province":"TN",
    "wof:name":"Secure Shred",
    "wof:placetype":"venue"
},
  "geometry": {"coordinates":[-85.49650800000001,36.137849],"type":"Point"}
}