{
  "type": "Feature",
  "properties": {
    "iso:country":"US",
    "sg:address":"1005 Massachusetts Ave",
    "sg:city":"Unicoi",
    "sg:classifiers":[
        {
            "category":"Professional",
            "subcategory":"Business Services",
            "type":"Services"
        }
    ],
    "sg:phone":"+1 423 743 7233",
    "sg:postcode":"37692",
    "sg:province":"TN",
    "wof:name":"Wade Enterprises",
    "wof:placetype":"venue"
},
  "geometry": {"coordinates":[-82.360569,36.194425],"type":"Point"}
}