{
  "type": "Feature",
  "properties": {
    "iso:country":"US",
    "sg:address":"1050 Old Hwy 33",
    "sg:city":"New Tazewell",
    "sg:classifiers":[
        {
            "category":"Autos & Motor Vehicles",
            "subcategory":"Recreational Vehicle Sales",
            "type":"Retail Goods"
        }
    ],
    "sg:phone":"+1 423 626 3401",
    "sg:postcode":"37825",
    "sg:province":"TN",
    "wof:name":"Pro Finish Line",
    "wof:placetype":"venue"
},
  "geometry": {"coordinates":[-83.625039,36.426089],"type":"Point"}
}