{
  "type": "Feature",
  "properties": {
    "iso:country":"US",
    "sg:address":"1310 Kensington Dr",
    "sg:city":"Knoxville",
    "sg:classifiers":[
        {
            "category":"Building & Trades",
            "subcategory":"Landscaping Services",
            "type":"Services"
        }
    ],
    "sg:phone":"+1 865 691 6985",
    "sg:postcode":"37922",
    "sg:province":"TN",
    "wof:name":"Martin Lawn & Trim LLC",
    "wof:placetype":"venue"
},
  "geometry": {"coordinates":[-84.048244,35.882823],"type":"Point"}
}