{
  "type": "Feature",
  "properties": {
    "iso:country":"US",
    "sg:address":"900 E Hill Ave",
    "sg:city":"Knoxville",
    "sg:classifiers":[
        {
            "category":"Social Services",
            "subcategory":"Adult Care",
            "type":"Services"
        }
    ],
    "sg:phone":"+1 865 633 9844",
    "sg:postcode":"37915",
    "sg:province":"TN",
    "sg:tags":[
        "foster"
    ],
    "sg:website":"www.holstonhome.org",
    "wof:name":"Holston United Methodist Home",
    "wof:placetype":"venue"
},
  "geometry": {"coordinates":[-83.90680999999999,35.969359],"type":"Point"}
}