{
  "type": "Feature",
  "properties": {
    "addr:full":"1317 Hildreth Dr Nashville TN 37215",
    "addr:housenumber":"1317",
    "addr:postcode":"37215",
    "addr:street":"Hildreth Dr",
    "iso:country":"US",
    "sg:address":"1317 Hildreth Dr",
    "sg:city":"Nashville",
    "sg:classifiers":[
        {
            "category":"Organizations",
            "subcategory":"Community Association",
            "type":"Services"
        }
    ],
    "sg:phone":"+1 615 665 0090",
    "sg:postcode":"37215",
    "sg:province":"TN",
    "sg:tags":[
        "club"
    ],
    "wof:name":"Seven Hills Pool",
    "wof:placetype":"venue"
},
  "geometry": {"coordinates":[-86.816754,36.083292],"type":"Point"}
}