{
  "type": "Feature",
  "properties": {
    "addr:full":"45 Old Hwy 31 No 1 E Gallatin TN 37066",
    "addr:housenumber":"45",
    "addr:postcode":"37066",
    "addr:street":"Old Hwy 31 No 1 E",
    "iso:country":"US",
    "sg:address":"45 Old Hwy 31 No 1 E",
    "sg:city":"Gallatin",
    "sg:classifiers":[
        {
            "category":"Professional",
            "subcategory":"Business Services",
            "type":"Services"
        }
    ],
    "sg:phone":"+1 615 230 3161",
    "sg:postcode":"37066",
    "sg:province":"TN",
    "wof:name":"Beasley Office",
    "wof:placetype":"venue"
},
  "geometry": {"coordinates":[-86.34375,36.458679],"type":"Point"}
}