{
  "type": "Feature",
  "properties": {
    "addr:full":"300 W Madison Ave Athens TN 37303",
    "addr:housenumber":"300",
    "addr:postcode":"37303",
    "addr:street":"W Madison Ave",
    "iso:country":"US",
    "sg:address":"300 W Madison Ave",
    "sg:city":"Athens",
    "sg:classifiers":[
        {
            "category":"Shopping",
            "subcategory":"Stationery & Office Supplies",
            "type":"Retail Goods"
        }
    ],
    "sg:phone":"+1 423 745 1200",
    "sg:postcode":"37303",
    "sg:province":"TN",
    "sg:tags":[
        "machine"
    ],
    "wof:name":"Purkey's Office Supply & Machs",
    "wof:placetype":"venue"
},
  "geometry": {"coordinates":[-84.597855,35.440796],"type":"Point"}
}