{
  "type": "Feature",
  "properties": {
    "iso:country":"US",
    "sg:address":"439 W Depot Ave",
    "sg:city":"Knoxville",
    "sg:classifiers":[
        {
            "category":"Utilities",
            "subcategory":"Telephone",
            "type":"Services"
        }
    ],
    "sg:phone":"+1 865 544 2700",
    "sg:postcode":"37917",
    "sg:province":"TN",
    "sg:tags":[
        "communications"
    ],
    "wof:name":"AT&T",
    "wof:placetype":"venue"
},
  "geometry": {"coordinates":[-83.923923,35.969472],"type":"Point"}
}