{
  "type": "Feature",
  "properties": {
    "iso:country":"US",
    "sg:address":"100 Powell Pl",
    "sg:city":"Nashville",
    "sg:classifiers":[
        {
            "category":"Shopping",
            "subcategory":"Computers & Home Electronics",
            "type":"Retail Goods"
        },
        {
            "category":"Wholesale",
            "subcategory":"Office Equipment",
            "type":"Manufacturing & Wholesale Goods"
        },
        {
            "category":"Professional",
            "subcategory":"Printing & Photocopies",
            "type":"Services"
        },
        {
            "category":"Professional",
            "subcategory":"Computer Services",
            "type":"Services"
        },
        {
            "category":"Shopping",
            "subcategory":"Stationery & Office Supplies",
            "type":"Retail Goods"
        },
        {
            "category":"Wholesale",
            "subcategory":"Computers",
            "type":"Manufacturing & Wholesale Goods"
        }
    ],
    "sg:phone":"+1 615 298 1178",
    "sg:postcode":"37204",
    "sg:province":"TN",
    "sg:tags":[
        "printer",
        "register",
        "autographic",
        "duplicating",
        "hardware",
        "copying",
        "software",
        "furniture"
    ],
    "sg:website":"http://www.staples.com",
    "wof:name":"STAPLES",
    "wof:placetype":"venue"
},
  "geometry": {"coordinates":[-86.766098,36.10582],"type":"Point"}
}