{
  "type": "Feature",
  "properties": {
    "addr:full":"52 Ables Ln Fayetteville TN 37334",
    "addr:housenumber":"52",
    "addr:postcode":"37334",
    "addr:street":"Ables Ln",
    "iso:country":"US",
    "sg:address":"52 Ables Ln",
    "sg:city":"Fayetteville",
    "sg:classifiers":[
        {
            "category":"Building & Trades",
            "subcategory":"Construction",
            "type":"Services"
        }
    ],
    "sg:phone":"+1 931 438 7077",
    "sg:postcode":"37334",
    "sg:province":"TN",
    "sg:tags":[
        "stucco",
        "contractor"
    ],
    "wof:name":"Southern Stucco",
    "wof:placetype":"venue"
},
  "geometry": {"coordinates":[-86.548975,35.068882],"type":"Point"}
}