{
  "type": "Feature",
  "properties": {
    "iso:country":"US",
    "sg:address":"644 Lemont Dr",
    "sg:city":"Nashville",
    "sg:classifiers":[
        {
            "category":"Building & Trades",
            "subcategory":"Landscaping Services",
            "type":"Services"
        }
    ],
    "sg:phone":"+1 615 578 0478",
    "sg:postcode":"37216",
    "sg:province":"TN",
    "sg:tags":[
        "landscape",
        "contractor"
    ],
    "wof:name":"Juan's Landscape Svc",
    "wof:placetype":"venue"
},
  "geometry": {"coordinates":[-86.743111,36.235285],"type":"Point"}
}