{
  "type": "Feature",
  "properties": {
    "iso:country":"US",
    "sg:address":"143 Bugg St",
    "sg:city":"Lynnville",
    "sg:classifiers":[
        {
            "category":"Organizations",
            "subcategory":"Religious Organization",
            "type":"Services"
        }
    ],
    "sg:phone":"+1 931 527 0040",
    "sg:postcode":"38472",
    "sg:province":"TN",
    "sg:tags":[
        "church"
    ],
    "wof:name":"Lynnville United Methodist Chr",
    "wof:placetype":"venue"
},
  "geometry": {"coordinates":[-87.00851299999999,35.378622],"type":"Point"}
}