{
  "type": "Feature",
  "properties": {
    "iso:country":"US",
    "sg:address":"982 Meagher St",
    "sg:city":"Memphis",
    "sg:classifiers":[
        {
            "category":"Organizations",
            "subcategory":"Religious Organization",
            "type":"Services"
        }
    ],
    "sg:phone":"+1 901 323 2006",
    "sg:postcode":"38108",
    "sg:province":"TN",
    "sg:tags":[
        "church"
    ],
    "wof:name":"Power Of The Word Ministry",
    "wof:placetype":"venue"
},
  "geometry": {"coordinates":[-89.972511,35.16267],"type":"Point"}
}