{
  "type": "Feature",
  "properties": {
    "addr:full":"2800 Vanderbilt Pl Nashville TN 37212",
    "addr:housenumber":"2800",
    "addr:postcode":"37212",
    "addr:street":"Vanderbilt Pl",
    "iso:country":"US",
    "sg:address":"2800 Vanderbilt Pl",
    "sg:city":"Nashville",
    "sg:classifiers":[
        {
            "category":"Education",
            "subcategory":"College",
            "type":"Public Place"
        }
    ],
    "sg:phone":"+1 615 343 0446",
    "sg:postcode":"37212",
    "sg:province":"TN",
    "wof:name":"Campus Security",
    "wof:placetype":"venue"
},
  "geometry": {"coordinates":[-86.810391,36.143242],"type":"Point"}
}