{
  "type": "Feature",
  "properties": {
    "iso:country":"US",
    "sg:address":"4616 Mill Branch Ln",
    "sg:city":"Knoxville",
    "sg:classifiers":[
        {
            "category":"Professional",
            "subcategory":"Lawyer & Legal Services",
            "type":"Services"
        }
    ],
    "sg:phone":"+1 865 922 7467",
    "sg:postcode":"37938",
    "sg:province":"TN",
    "sg:tags":[
        "attorney"
    ],
    "wof:name":"Byron D Bryant",
    "wof:placetype":"venue"
},
  "geometry": {"coordinates":[-83.919642,36.093509],"type":"Point"}
}