{
  "type": "Feature",
  "properties": {
    "iso:country":"US",
    "sg:address":"132 Ferry Rd",
    "sg:city":"Pikeville",
    "sg:classifiers":[
        {
            "category":"Manufacturing",
            "subcategory":"Motor Vehicles & Parts",
            "type":"Manufacturing & Wholesale Goods"
        }
    ],
    "sg:phone":"+1 423 447 6861",
    "sg:postcode":"37380",
    "sg:province":"TN",
    "sg:tags":[
        "automobile",
        "supply"
    ],
    "sg:website":"www.duraauto.com",
    "wof:name":"Dura Automotive Systems Inc",
    "wof:placetype":"venue"
},
  "geometry": {"coordinates":[-85.698269,35.00964],"type":"Point"}
}