{
  "type": "Feature",
  "properties": {
    "iso:country":"US",
    "sg:address":"2242 Rock Springs Rd",
    "sg:city":"Columbia",
    "sg:classifiers":[
        {
            "category":"Organizations",
            "subcategory":"Religious Organization",
            "type":"Services"
        }
    ],
    "sg:phone":"+1 931 381 0647",
    "sg:postcode":"38401",
    "sg:province":"TN",
    "sg:tags":[
        "church"
    ],
    "wof:name":"Rock Springs Baptist Church",
    "wof:placetype":"venue"
},
  "geometry": {"coordinates":[-86.92129,35.596642],"type":"Point"}
}