{
  "type": "Feature",
  "properties": {
    "iso:country":"US",
    "sg:address":"1811 Swinford Ct",
    "sg:city":"Knoxville",
    "sg:classifiers":[
        {
            "category":"Professional",
            "type":"Services"
        }
    ],
    "sg:phone":"+1 865 675 0585",
    "sg:postcode":"37922",
    "sg:province":"TN",
    "sg:tags":[
        "establishment"
    ],
    "wof:name":"Tinytumblers Inc",
    "wof:placetype":"venue"
},
  "geometry": {"coordinates":[-84.099009,35.853793],"type":"Point"}
}