{
  "type": "Feature",
  "properties": {
    "iso:country":"US",
    "sg:address":"818 18th Ave S",
    "sg:city":"Nashville",
    "sg:classifiers":[
        {
            "category":"Personal",
            "subcategory":"Beauty Salon",
            "type":"Services"
        }
    ],
    "sg:phone":"+1 615 279 5277",
    "sg:postcode":"37203",
    "sg:province":"TN",
    "wof:name":"Rapport Hair Studio",
    "wof:placetype":"venue"
},
  "geometry": {"coordinates":[-86.79466499999999,36.148927],"type":"Point"}
}