{
  "type": "Feature",
  "properties": {
    "iso:country":"US",
    "sg:address":"2505 US Hwy 79 S",
    "sg:city":"Paris",
    "sg:classifiers":[
        {
            "category":"Manufacturing",
            "subcategory":"Metals",
            "type":"Manufacturing & Wholesale Goods"
        }
    ],
    "sg:phone":"+1 731 642 2080",
    "sg:postcode":"38242",
    "sg:province":"TN",
    "sg:tags":[
        "fabricator",
        "sheet"
    ],
    "wof:name":"Custom Metal Fabricators Inc",
    "wof:placetype":"venue"
},
  "geometry": {"coordinates":[-88.331878,36.272211],"type":"Point"}
}