{
  "type": "Feature",
  "properties": {
    "iso:country":"US",
    "sg:address":"105 Flintlock Dr",
    "sg:city":"Franklin",
    "sg:classifiers":[
        {
            "category":"Building & Trades",
            "subcategory":"Construction",
            "type":"Services"
        }
    ],
    "sg:phone":"+1 615 790 7706",
    "sg:postcode":"37064",
    "sg:province":"TN",
    "sg:tags":[
        "contractor"
    ],
    "wof:name":"Almon and Associates",
    "wof:placetype":"venue"
},
  "geometry": {"coordinates":[-86.8441,35.930619],"type":"Point"}
}