{
  "type": "Feature",
  "properties": {
    "iso:country":"US",
    "sg:address":"143 New Shackle Island Rd Suite 15",
    "sg:city":"Hendersonville",
    "sg:classifiers":[
        {
            "category":"Insurance",
            "subcategory":"Insurance Agent",
            "type":"Services"
        },
        {
            "category":"Insurance",
            "subcategory":"Hazard Insurance",
            "type":"Services"
        },
        {
            "category":"Insurance",
            "subcategory":"Title Insurance",
            "type":"Services"
        }
    ],
    "sg:phone":"+1 615 824 9466",
    "sg:postcode":"37075",
    "sg:province":"TN",
    "sg:tags":[
        "auto",
        "homeowner"
    ],
    "sg:website":"http://www.nationwide.com",
    "wof:name":"Nationwide Insurance- Hendersonville",
    "wof:placetype":"venue"
},
  "geometry": {"coordinates":[-86.63256800000001,36.308971],"type":"Point"}
}