{
  "type": "Feature",
  "properties": {
    "iso:country":"US",
    "sg:address":"815 S Gateway Ave",
    "sg:city":"Rockwood",
    "sg:classifiers":[
        {
            "category":"Autos & Motor Vehicles",
            "subcategory":"Boat Sales",
            "type":"Retail Goods"
        },
        {
            "category":"Recreation",
            "subcategory":"Marina",
            "type":"Entertainment"
        }
    ],
    "sg:phone":"+1 865 354 4662",
    "sg:postcode":"37854",
    "sg:province":"TN",
    "sg:tags":[
        "operation",
        "dealer",
        "sales"
    ],
    "wof:name":"Arrow Head Marine",
    "wof:placetype":"venue"
},
  "geometry": {"coordinates":[-84.69391899999999,35.859863],"type":"Point"}
}