{
  "type": "Feature",
  "properties": {
    "iso:country":"US",
    "sg:address":"227 W Main St",
    "sg:city":"Johnson City",
    "sg:classifiers":[
        {
            "category":"Manufacturing",
            "subcategory":"Toys & Sporting Goods",
            "type":"Manufacturing & Wholesale Goods"
        }
    ],
    "sg:phone":"+1 423 926 4287",
    "sg:postcode":"37604",
    "sg:province":"TN",
    "wof:name":"T Re-Productions",
    "wof:placetype":"venue"
},
  "geometry": {"coordinates":[-82.355896,36.316518],"type":"Point"}
}