{
  "type": "Feature",
  "properties": {
    "iso:country":"US",
    "sg:address":"6040 White House Rd",
    "sg:city":"Greeneville",
    "sg:classifiers":[
        {
            "category":"Utilities",
            "subcategory":"Refuse",
            "type":"Services"
        }
    ],
    "sg:phone":"+1 423 638 3485",
    "sg:postcode":"37745",
    "sg:province":"TN",
    "sg:tags":[
        "garbage",
        "collection"
    ],
    "wof:name":"Transport Technology",
    "wof:placetype":"venue"
},
  "geometry": {"coordinates":[-82.815252,36.242105],"type":"Point"}
}