{
  "type": "Feature",
  "properties": {
    "iso:country":"US",
    "sg:address":"308 E Broadway St",
    "sg:city":"Lenoir City",
    "sg:classifiers":[
        {
            "category":"Shopping",
            "type":"Retail Goods"
        }
    ],
    "sg:phone":"+1 865 986 8212",
    "sg:postcode":"37771",
    "sg:province":"TN",
    "sg:tags":[
        "merchandise"
    ],
    "wof:name":"Family Hearing Centers",
    "wof:placetype":"venue"
},
  "geometry": {"coordinates":[-84.263882,35.792212],"type":"Point"}
}