{
  "type": "Feature",
  "properties": {
    "iso:country":"US",
    "sg:address":"924 N Highland Ave",
    "sg:city":"Jackson",
    "sg:classifiers":[
        {
            "category":"Communications",
            "subcategory":"Film & Video Production",
            "type":"Services"
        }
    ],
    "sg:phone":"+1 731 424 2140",
    "sg:postcode":"38301",
    "sg:province":"TN",
    "sg:tags":[
        "audio"
    ],
    "wof:name":"Highland House Productions",
    "wof:placetype":"venue"
},
  "geometry": {"coordinates":[-88.818678,35.629318],"type":"Point"}
}