{
  "type": "Feature",
  "properties": {
    "iso:country":"US",
    "sg:address":"2550 Bluebird Rd",
    "sg:city":"Lebanon",
    "sg:classifiers":[
        {
            "category":"Shopping",
            "subcategory":"Clothing, Apparel, & Fashions",
            "type":"Retail Goods"
        }
    ],
    "sg:phone":"+1 615 444 6304",
    "sg:postcode":"37087",
    "sg:province":"TN",
    "sg:tags":[
        "shop",
        "bridal"
    ],
    "wof:name":"Flights of Fantasy",
    "wof:placetype":"venue"
},
  "geometry": {"coordinates":[-86.245183,36.201157],"type":"Point"}
}