{
  "type": "Feature",
  "properties": {
    "iso:country":"US",
    "sg:address":"2507 Mineral Springs Ave NE",
    "sg:city":"Knoxville",
    "sg:classifiers":[
        {
            "category":"Health Services",
            "subcategory":"Health Practitioner",
            "type":"Services"
        }
    ],
    "sg:phone":"+1 865 637 3366",
    "sg:postcode":"37917",
    "sg:province":"TN",
    "sg:tags":[
        "psychologist"
    ],
    "wof:name":"Complete Counseling North",
    "wof:placetype":"venue"
},
  "geometry": {"coordinates":[-83.921212,36.015103],"type":"Point"}
}