{
  "type": "Feature",
  "properties": {
    "iso:country":"US",
    "sg:address":"4442 Highway 31 W",
    "sg:city":"Cottontown",
    "sg:classifiers":[
        {
            "category":"Health Services",
            "subcategory":"Chiropractor",
            "type":"Services"
        }
    ],
    "sg:phone":"+1 615 654 2721",
    "sg:postcode":"37048",
    "sg:province":"TN",
    "sg:tags":[
        "chiropractic"
    ],
    "wof:name":"Mark Rodewald Dc",
    "wof:placetype":"venue"
},
  "geometry": {"coordinates":[-86.633982,36.536356],"type":"Point"}
}