{
  "type": "Feature",
  "properties": {
    "iso:country":"US",
    "sg:address":"463 Davidson Chapel Ln",
    "sg:city":"Bloomington Springs",
    "sg:classifiers":[
        {
            "category":"Building & Trades",
            "subcategory":"Construction",
            "type":"Services"
        }
    ],
    "sg:phone":"+1 931 858 7389",
    "sg:postcode":"38545",
    "sg:province":"TN",
    "sg:tags":[
        "paper",
        "painting",
        "hanging"
    ],
    "wof:name":"Chinoy D J Wallpaper Hanging",
    "wof:placetype":"venue"
},
  "geometry": {"coordinates":[-85.724102,36.23446],"type":"Point"}
}