{
  "type": "Feature",
  "properties": {
    "addr:full":"2007 Jenkins Hollow Rd Mountain City TN 37683",
    "addr:housenumber":"2007",
    "addr:postcode":"37683",
    "addr:street":"Jenkins Hollow Rd",
    "iso:country":"US",
    "sg:address":"2007 Jenkins Hollow Rd",
    "sg:city":"Mountain City",
    "sg:classifiers":[
        {
            "category":"Professional",
            "type":"Services"
        }
    ],
    "sg:phone":"+1 423 727 5483",
    "sg:postcode":"37683",
    "sg:province":"TN",
    "wof:name":"James A Osborne",
    "wof:placetype":"venue"
},
  "geometry": {"coordinates":[-81.80817999999999,36.517857],"type":"Point"}
}