{
  "type": "Feature",
  "properties": {
    "iso:country":"US",
    "sg:address":"4462 Western Ave",
    "sg:city":"Knoxville",
    "sg:classifiers":[
        {
            "category":"Wholesale",
            "subcategory":"Medical Equipment & Supplies",
            "type":"Manufacturing & Wholesale Goods"
        }
    ],
    "sg:phone":"+1 865 558 8500",
    "sg:postcode":"37921",
    "sg:province":"TN",
    "sg:website":"www.respicare.com",
    "wof:name":"Resp-I-Care",
    "wof:placetype":"venue"
},
  "geometry": {"coordinates":[-83.987725,35.972672],"type":"Point"}
}