{
  "type": "Feature",
  "properties": {
    "iso:country":"US",
    "sg:address":"2245 Murfreesboro Pike",
    "sg:city":"Nashville",
    "sg:classifiers":[
        {
            "category":"Retail",
            "subcategory":"Car Wash",
            "type":"Services"
        }
    ],
    "sg:phone":"+1 615 367 3090",
    "sg:postcode":"37217",
    "sg:province":"TN",
    "sg:tags":[
        "carwash"
    ],
    "wof:name":"Spray & Shine Car Wash",
    "wof:placetype":"venue"
},
  "geometry": {"coordinates":[-86.649173,36.087613],"type":"Point"}
}