{
  "type": "Feature",
  "properties": {
    "iso:country":"US",
    "sg:address":"160 N Main St",
    "sg:city":"Memphis",
    "sg:classifiers":[
        {
            "category":"Real Estate",
            "subcategory":"Real Estate Services",
            "type":"Services"
        }
    ],
    "sg:phone":"+1 901 527 2589",
    "sg:postcode":"38103",
    "sg:province":"TN",
    "sg:tags":[
        "company",
        "title"
    ],
    "wof:name":"American Title Co",
    "wof:placetype":"venue"
},
  "geometry": {"coordinates":[-90.051204,35.148899],"type":"Point"}
}