{
  "type": "Feature",
  "properties": {
    "iso:country":"US",
    "sg:address":"607 Rutledge Pike",
    "sg:city":"Blaine",
    "sg:classifiers":[
        {
            "category":"Home & Garden",
            "subcategory":"Garden Supply",
            "type":"Retail Goods"
        }
    ],
    "sg:phone":"+1 865 933 1800",
    "sg:postcode":"37709",
    "sg:province":"TN",
    "sg:tags":[
        "nurseryman"
    ],
    "wof:name":"Four Seasons Nursery",
    "wof:placetype":"venue"
},
  "geometry": {"coordinates":[-83.703541,36.155539],"type":"Point"}
}