{
  "type": "Feature",
  "properties": {
    "iso:country":"US",
    "sg:address":"23 Cherokee Blvd",
    "sg:city":"Chattanooga",
    "sg:classifiers":[
        {
            "category":"Personal",
            "subcategory":"Beauty Salon",
            "type":"Services"
        }
    ],
    "sg:phone":"+1 423 267 0314",
    "sg:postcode":"37405",
    "sg:province":"TN",
    "sg:tags":[
        "manicuring"
    ],
    "wof:name":"Pat's Nails",
    "wof:placetype":"venue"
},
  "geometry": {"coordinates":[-85.31021200000001,35.063604],"type":"Point"}
}