{
  "type": "Feature",
  "properties": {
    "iso:country":"US",
    "sg:address":"10469 Lexington St",
    "sg:city":"Huntingdon",
    "sg:classifiers":[
        {
            "category":"Utilities",
            "subcategory":"Cable",
            "type":"Services"
        }
    ],
    "sg:phone":"+1 731 986 5471",
    "sg:postcode":"38344",
    "sg:province":"TN",
    "sg:tags":[
        "television"
    ],
    "wof:name":"Charter Communications",
    "wof:placetype":"venue"
},
  "geometry": {"coordinates":[-88.409901,35.964593],"type":"Point"}
}