{
  "type": "Feature",
  "properties": {
    "addr:full":"110 Cloverfield Ct Hendersonville TN 37075",
    "addr:housenumber":"110",
    "addr:postcode":"37075",
    "addr:street":"Cloverfield Ct",
    "iso:country":"US",
    "sg:address":"110 Cloverfield Ct",
    "sg:city":"Hendersonville",
    "sg:classifiers":[
        {
            "category":"Shopping",
            "type":"Retail Goods"
        }
    ],
    "sg:phone":"+1 615 822 3320",
    "sg:postcode":"37075",
    "sg:province":"TN",
    "sg:tags":[
        "plant",
        "flower",
        "tree",
        "artificial"
    ],
    "wof:name":"Floral Memoirs",
    "wof:placetype":"venue"
},
  "geometry": {"coordinates":[-86.613508,36.325303],"type":"Point"}
}