{
  "type": "Feature",
  "properties": {
    "iso:country":"US",
    "sg:address":"2601 W Blount Ave",
    "sg:city":"Knoxville",
    "sg:classifiers":[
        {
            "category":"Retail",
            "subcategory":"Repair Shop",
            "type":"Services"
        }
    ],
    "sg:phone":"+1 865 573 1009",
    "sg:postcode":"37920",
    "sg:province":"TN",
    "sg:tags":[
        "conditioning",
        "air"
    ],
    "wof:name":"Air Maintenance",
    "wof:placetype":"venue"
},
  "geometry": {"coordinates":[-83.920181,35.948046],"type":"Point"}
}