{
  "type": "Feature",
  "properties": {
    "addr:full":"10403 Lovell Center Dr Knoxville TN 37922",
    "addr:housenumber":"10403",
    "addr:postcode":"37922",
    "addr:street":"Lovell Center Dr",
    "iso:country":"US",
    "sg:address":"10403 Lovell Center Dr",
    "sg:city":"Knoxville",
    "sg:classifiers":[
        {
            "category":"Insurance",
            "subcategory":"Insurance Agent",
            "type":"Services"
        }
    ],
    "sg:phone":"+1 865 690 3419",
    "sg:postcode":"37922",
    "sg:province":"TN",
    "wof:name":"Primerica Financial Svc",
    "wof:placetype":"venue"
},
  "geometry": {"coordinates":[-84.126893,35.897814],"type":"Point"}
}