{
  "type": "Feature",
  "properties": {
    "iso:country":"US",
    "sg:address":"5603 Royal Ct",
    "sg:city":"Hermitage",
    "sg:classifiers":[
        {
            "category":"Personal",
            "subcategory":"Beauty Salon",
            "type":"Services"
        }
    ],
    "sg:phone":"+1 615 485 6061",
    "sg:postcode":"37076",
    "sg:province":"TN",
    "sg:tags":[
        "shop"
    ],
    "wof:name":"Perfect Touch",
    "wof:placetype":"venue"
},
  "geometry": {"coordinates":[-86.58838,36.183927],"type":"Point"}
}