{
  "type": "Feature",
  "properties": {
    "addr:full":"383 W Jackson St Cookeville TN 38501",
    "addr:housenumber":"383",
    "addr:postcode":"38501",
    "addr:street":"W Jackson St",
    "iso:country":"US",
    "sg:address":"383 W Jackson St",
    "sg:city":"Cookeville",
    "sg:classifiers":[
        {
            "category":"Shopping",
            "subcategory":"Department Store",
            "type":"Retail Goods"
        }
    ],
    "sg:phone":"+1 931 528 7270",
    "sg:postcode":"38501",
    "sg:province":"TN",
    "sg:tags":[
        "shop"
    ],
    "sg:website":"www.pier1.com",
    "wof:name":"Pier 1 Imports",
    "wof:placetype":"venue"
},
  "geometry": {"coordinates":[-85.51475600000001,36.154721],"type":"Point"}
}