{
  "type": "Feature",
  "properties": {
    "iso:country":"US",
    "sg:address":"815 Merchants Dr",
    "sg:city":"Knoxville",
    "sg:classifiers":[
        {
            "category":"Restaurant",
            "type":"Food & Drink"
        }
    ],
    "sg:phone":"+1 865 686 1260",
    "sg:postcode":"37912",
    "sg:province":"TN",
    "wof:name":"Nagoya Express",
    "wof:placetype":"venue"
},
  "geometry": {"coordinates":[-83.979867,36.005423],"type":"Point"}
}