{
  "type": "Feature",
  "properties": {
    "addr:full":"206 Morrell Rd Knoxville TN 37919",
    "addr:housenumber":"206",
    "addr:postcode":"37919",
    "addr:street":"Morrell Rd",
    "iso:country":"US",
    "sg:address":"206 Morrell Rd",
    "sg:city":"Knoxville",
    "sg:classifiers":[
        {
            "category":"Utilities",
            "subcategory":"Mobile Phone",
            "type":"Services"
        }
    ],
    "sg:phone":"+1 865 690 6363",
    "sg:postcode":"37919",
    "sg:province":"TN",
    "sg:tags":[
        "telephone",
        "cellular"
    ],
    "sg:website":"www.sprintpcs.com",
    "wof:name":"Sprint PCS",
    "wof:placetype":"venue"
},
  "geometry": {"coordinates":[-84.033776,35.92492],"type":"Point"}
}