{
  "type": "Feature",
  "properties": {
    "addr:full":"108 Crabtree Rd Roan Mountain TN 37687",
    "addr:housenumber":"108",
    "addr:postcode":"37687",
    "addr:street":"Crabtree Rd",
    "iso:country":"US",
    "sg:address":"108 Crabtree Rd",
    "sg:city":"Roan Mountain",
    "sg:classifiers":[
        {
            "category":"Building & Trades",
            "subcategory":"Construction",
            "type":"Services"
        }
    ],
    "sg:phone":"+1 423 772 4854",
    "sg:postcode":"37687",
    "sg:province":"TN",
    "wof:name":"Pendley Paving Service",
    "wof:placetype":"venue"
},
  "geometry": {"coordinates":[-82.10814499999999,36.207604],"type":"Point"}
}