{
  "type": "Feature",
  "properties": {
    "addr:full":"400 Goodys Ln Knoxville TN 37922",
    "addr:housenumber":"400",
    "addr:postcode":"37922",
    "addr:street":"Goodys Ln",
    "iso:country":"US",
    "sg:address":"400 Goodys Ln",
    "sg:city":"Knoxville",
    "sg:classifiers":[
        {
            "category":"Shopping",
            "subcategory":"Department Store",
            "type":"Retail Goods"
        }
    ],
    "sg:phone":"+1 865 966 2000",
    "sg:postcode":"37922",
    "sg:province":"TN",
    "sg:website":"www.goodysonline.com",
    "wof:name":"Goody's Family Clothing Inc",
    "wof:placetype":"venue"
},
  "geometry": {"coordinates":[-84.13661399999999,35.903801],"type":"Point"}
}