{
  "type": "Feature",
  "properties": {
    "iso:country":"US",
    "sg:address":"640 Hamilton Ave",
    "sg:city":"Nashville",
    "sg:classifiers":[
        {
            "category":"Professional",
            "type":"Services"
        }
    ],
    "sg:phone":"+1 615 255 4045",
    "sg:postcode":"37203",
    "sg:province":"TN",
    "sg:tags":[
        "establishment"
    ],
    "wof:name":"KERR Brothers & Assoc",
    "wof:placetype":"venue"
},
  "geometry": {"coordinates":[-86.773641,36.139145],"type":"Point"}
}