{
  "type": "Feature",
  "properties": {
    "addr:full":"109 Noblitt St Shelbyville TN 37160",
    "addr:housenumber":"109",
    "addr:postcode":"37160",
    "addr:street":"Noblitt St",
    "iso:country":"US",
    "sg:address":"109 Noblitt St",
    "sg:city":"Shelbyville",
    "sg:classifiers":[
        {
            "category":"Professional",
            "subcategory":"Employment Agencies",
            "type":"Services"
        }
    ],
    "sg:phone":"+1 931 680 0297",
    "sg:postcode":"37160",
    "sg:province":"TN",
    "sg:tags":[
        "opportunity"
    ],
    "wof:name":"Randstad",
    "wof:placetype":"venue"
},
  "geometry": {"coordinates":[-86.460317,35.493043],"type":"Point"}
}