{
  "type": "Feature",
  "properties": {
    "iso:country":"US",
    "sg:address":"4245 Demastus Ln",
    "sg:city":"Columbia",
    "sg:classifiers":[
        {
            "category":"Social Services",
            "subcategory":"Child Care",
            "type":"Services"
        }
    ],
    "sg:phone":"+1 931 381 7795",
    "sg:postcode":"38401",
    "sg:province":"TN",
    "sg:tags":[
        "day"
    ],
    "wof:name":"Charlene Burgess",
    "wof:placetype":"venue"
},
  "geometry": {"coordinates":[-87.099716,35.523322],"type":"Point"}
}