{
  "type": "Feature",
  "properties": {
    "iso:country":"US",
    "sg:address":"4635 Forest Oak Way",
    "sg:city":"Memphis",
    "sg:classifiers":[
        {
            "category":"Real Estate",
            "subcategory":"Real Estate Services",
            "type":"Services"
        },
        {
            "category":"Real Estate",
            "subcategory":"Real Estate Operator",
            "type":"Services"
        }
    ],
    "sg:phone":"+1 901 362 0475",
    "sg:postcode":"38118",
    "sg:province":"TN",
    "sg:tags":[
        "apartment",
        "vacancy",
        "listing",
        "rental",
        "finder"
    ],
    "wof:name":"Dogwood Trace Apartments",
    "wof:placetype":"venue"
},
  "geometry": {"coordinates":[-89.90998500000001,35.051913],"type":"Point"}
}