{
  "type": "Feature",
  "properties": {
    "iso:country":"US",
    "sg:address":"1583 Arden Ln",
    "sg:city":"Morristown",
    "sg:classifiers":[
        {
            "category":"Shopping",
            "type":"Retail Goods"
        }
    ],
    "sg:phone":"+1 423 581 1282",
    "sg:postcode":"37813",
    "sg:province":"TN",
    "sg:tags":[
        "picture",
        "frame"
    ],
    "wof:name":"Classic Creations Custom",
    "wof:placetype":"venue"
},
  "geometry": {"coordinates":[-83.255188,36.191943],"type":"Point"}
}