{
  "type": "Feature",
  "properties": {
    "addr:full":"3414 Dogwood Ln Memphis TN 38116",
    "addr:housenumber":"3414",
    "addr:postcode":"38116",
    "addr:street":"Dogwood Ln",
    "iso:country":"US",
    "sg:address":"3414 Dogwood Ln",
    "sg:city":"Memphis",
    "sg:classifiers":[
        {
            "category":"Freight",
            "type":"Transportation"
        }
    ],
    "sg:phone":"+1 901 396 7471",
    "sg:postcode":"38116",
    "sg:province":"TN",
    "wof:name":"Meadows Transportation",
    "wof:placetype":"venue"
},
  "geometry": {"coordinates":[-90.032982,35.06053],"type":"Point"}
}