{
  "type": "Feature",
  "properties": {
    "iso:country":"US",
    "sg:address":"6727 US Hwy 11 E",
    "sg:city":"Lenoir City",
    "sg:classifiers":[
        {
            "category":"Building & Trades",
            "subcategory":"Construction",
            "type":"Services"
        }
    ],
    "sg:phone":"+1 865 986 0656",
    "sg:postcode":"37772",
    "sg:province":"TN",
    "sg:tags":[
        "woodworker"
    ],
    "wof:name":"L & E Enterprises Moose Works",
    "wof:placetype":"venue"
},
  "geometry": {"coordinates":[-84.255191,35.811428],"type":"Point"}
}