{
  "type": "Feature",
  "properties": {
    "iso:country":"US",
    "sg:address":"3105 Dayton Blvd",
    "sg:city":"Chattanooga",
    "sg:classifiers":[
        {
            "category":"Building & Trades",
            "subcategory":"Plumbing",
            "type":"Services"
        }
    ],
    "sg:phone":"+1 423 756 6927",
    "sg:postcode":"37415",
    "sg:province":"TN",
    "sg:tags":[
        "plumbing",
        "contractor"
    ],
    "wof:name":"Action TL",
    "wof:placetype":"venue"
},
  "geometry": {"coordinates":[-85.29804799999999,35.105712],"type":"Point"}
}