{
  "type": "Feature",
  "properties": {
    "iso:country":"US",
    "sg:address":"848 Bogle Rd",
    "sg:city":"Woodbury",
    "sg:classifiers":[
        {
            "category":"Retail",
            "subcategory":"Auto Repair",
            "type":"Services"
        }
    ],
    "sg:phone":"+1 615 765 5161",
    "sg:postcode":"37190",
    "sg:province":"TN",
    "sg:tags":[
        "repairing",
        "automobile",
        "general"
    ],
    "wof:name":"Pleasant View Repair Service",
    "wof:placetype":"venue"
},
  "geometry": {"coordinates":[-85.984602,35.735774],"type":"Point"}
}