{
  "type": "Feature",
  "properties": {
    "iso:country":"US",
    "sg:address":"581 Vandalia St",
    "sg:city":"Memphis",
    "sg:classifiers":[
        {
            "category":"Building & Trades",
            "subcategory":"Construction",
            "type":"Services"
        }
    ],
    "sg:phone":"+1 901 452 2667",
    "sg:postcode":"38112",
    "sg:province":"TN",
    "sg:tags":[
        "refinishing",
        "floor",
        "laying",
        "improvement",
        "resurfacing",
        "home",
        "contractor"
    ],
    "wof:name":"A To Z Home Improvement Svc",
    "wof:placetype":"venue"
},
  "geometry": {"coordinates":[-89.956768,35.14884],"type":"Point"}
}