{
  "type": "Feature",
  "properties": {
    "iso:country":"US",
    "sg:address":"6563 Stage Rd",
    "sg:city":"Memphis",
    "sg:classifiers":[
        {
            "category":"Health Services",
            "subcategory":"Hospital",
            "type":"Services"
        }
    ],
    "sg:phone":"+1 901 213 0305",
    "sg:postcode":"38134",
    "sg:province":"TN",
    "sg:tags":[
        "specialty"
    ],
    "wof:name":"Michael A Patterson MD",
    "wof:placetype":"venue"
},
  "geometry": {"coordinates":[-89.844171,35.204651],"type":"Point"}
}