{
  "type": "Feature",
  "properties": {
    "iso:country":"US",
    "sg:address":"1808 Shelby Ave",
    "sg:city":"Nashville",
    "sg:classifiers":[
        {
            "category":"Building & Trades",
            "subcategory":"Construction",
            "type":"Services"
        }
    ],
    "sg:phone":"+1 615 227 1521",
    "sg:postcode":"37206",
    "sg:province":"TN",
    "sg:tags":[
        "house"
    ],
    "wof:name":"Parallax Remodeling",
    "wof:placetype":"venue"
},
  "geometry": {"coordinates":[-86.737543,36.169916],"type":"Point"}
}