{
  "type": "Feature",
  "properties": {
    "addr:full":"1109 S Main St Milan TN 38358",
    "addr:housenumber":"1109",
    "addr:postcode":"38358",
    "addr:street":"S Main St",
    "iso:country":"US",
    "sg:address":"1109 S Main St",
    "sg:city":"Milan",
    "sg:classifiers":[
        {
            "category":"Cinema",
            "subcategory":"Movie Theater",
            "type":"Entertainment"
        }
    ],
    "sg:phone":"+1 731 686 7691",
    "sg:postcode":"38358",
    "sg:province":"TN",
    "wof:name":"Ritz Theatre",
    "wof:placetype":"venue"
},
  "geometry": {"coordinates":[-88.759664,35.920374],"type":"Point"}
}