{
  "type": "Feature",
  "properties": {
    "iso:country":"US",
    "sg:address":"734 N Auburndale St",
    "sg:city":"Memphis",
    "sg:classifiers":[
        {
            "category":"Farming",
            "subcategory":"Farm",
            "type":"Manufacturing & Wholesale Goods"
        }
    ],
    "sg:phone":"+1 901 726 9291",
    "sg:postcode":"38107",
    "sg:province":"TN",
    "sg:tags":[
        "crop",
        "general"
    ],
    "wof:name":"T K Haseloff Industries",
    "wof:placetype":"venue"
},
  "geometry": {"coordinates":[-89.99993499999999,35.157999],"type":"Point"}
}