{
  "type": "Feature",
  "properties": {
    "iso:country":"US",
    "sg:address":"4864 Judy Lynn Ave",
    "sg:city":"Memphis",
    "sg:classifiers":[
        {
            "category":"Professional",
            "type":"Services"
        }
    ],
    "sg:phone":"+1 901 363 4565",
    "sg:postcode":"38118",
    "sg:province":"TN",
    "wof:name":"Memphis Area Youth Dev Ctr",
    "wof:placetype":"venue"
},
  "geometry": {"coordinates":[-89.901482,35.071791],"type":"Point"}
}