{
  "type": "Feature",
  "properties": {
    "iso:country":"US",
    "sg:address":"7305 Hines Valley Rd",
    "sg:city":"Lenoir City",
    "sg:classifiers":[
        {
            "category":"Manufacturing",
            "subcategory":"Motor Vehicles & Parts",
            "type":"Manufacturing & Wholesale Goods"
        }
    ],
    "sg:phone":"+1 865 986 4798",
    "sg:postcode":"37771",
    "sg:province":"TN",
    "sg:tags":[
        "farm",
        "mfg",
        "cattle",
        "trailer",
        "utility"
    ],
    "wof:name":"Rush & Son",
    "wof:placetype":"venue"
},
  "geometry": {"coordinates":[-84.322914,35.82664],"type":"Point"}
}