{
  "type": "Feature",
  "properties": {
    "addr:full":"2850 Austin Peay Hwy Memphis TN 38128",
    "addr:housenumber":"2850",
    "addr:postcode":"38128",
    "addr:street":"Austin Peay Hwy",
    "iso:country":"US",
    "sg:address":"2850 Austin Peay Hwy",
    "sg:city":"Memphis",
    "sg:classifiers":[
        {
            "category":"Taxi",
            "type":"Transportation"
        }
    ],
    "sg:phone":"+1 901 384 9364",
    "sg:postcode":"38128",
    "sg:province":"TN",
    "sg:tags":[
        "delivery"
    ],
    "wof:name":"Mr T's Courier Service Inc",
    "wof:placetype":"venue"
},
  "geometry": {"coordinates":[-89.92205800000001,35.203098],"type":"Point"}
}