{
  "type": "Feature",
  "properties": {
    "addr:full":"264 East Dr Oak Ridge TN 37830",
    "addr:housenumber":"264",
    "addr:postcode":"37830",
    "addr:street":"East Dr",
    "iso:country":"US",
    "sg:address":"264 East Dr",
    "sg:city":"Oak Ridge",
    "sg:classifiers":[
        {
            "category":"Retail",
            "subcategory":"Photofinishing",
            "type":"Services"
        }
    ],
    "sg:phone":"+1 865 482 3069",
    "sg:postcode":"37830",
    "sg:province":"TN",
    "sg:tags":[
        "laboratory"
    ],
    "wof:name":"Superior Video Photo",
    "wof:placetype":"venue"
},
  "geometry": {"coordinates":[-84.21142999999999,36.051184],"type":"Point"}
}