{
  "type": "Feature",
  "properties": {
    "iso:country":"US",
    "sg:address":"328 Broadway",
    "sg:city":"Hartsville",
    "sg:classifiers":[
        {
            "category":"Education",
            "subcategory":"Junior College",
            "type":"Public Place"
        }
    ],
    "sg:phone":"+1 615 374 9071",
    "sg:postcode":"37074",
    "sg:province":"TN",
    "sg:tags":[
        "technical",
        "institute"
    ],
    "wof:name":"Trousdale County Adult Eductn",
    "wof:placetype":"venue"
},
  "geometry": {"coordinates":[-86.163875,36.398546],"type":"Point"}
}