{
  "type": "Feature",
  "properties": {
    "iso:country":"US",
    "sg:address":"362 W Elk Ave",
    "sg:city":"Elizabethton",
    "sg:classifiers":[
        {
            "category":"Retail",
            "subcategory":"Auto Repair",
            "type":"Services"
        }
    ],
    "sg:phone":"+1 423 542 0865",
    "sg:postcode":"37643",
    "sg:province":"TN",
    "sg:tags":[
        "automotive"
    ],
    "wof:name":"Quality Radiator",
    "wof:placetype":"venue"
},
  "geometry": {"coordinates":[-82.228713,36.350929],"type":"Point"}
}