{
  "type": "Feature",
  "properties": {
    "iso:country":"US",
    "sg:address":"115 Enon Springs Rd W",
    "sg:city":"Smyrna",
    "sg:classifiers":[
        {
            "category":"Restaurant",
            "type":"Food & Drink"
        }
    ],
    "sg:phone":"+1 615 459 0041",
    "sg:postcode":"37167",
    "sg:province":"TN",
    "sg:tags":[
        "eating",
        "pizza"
    ],
    "wof:name":"Domino's Pizza",
    "wof:placetype":"venue"
},
  "geometry": {"coordinates":[-86.52828599999999,35.976659],"type":"Point"}
}