{
  "type": "Feature",
  "properties": {
    "addr:full":"510 S Jefferson Ave Cookeville TN 38501",
    "addr:housenumber":"510",
    "addr:postcode":"38501",
    "addr:street":"S Jefferson Ave",
    "iso:country":"US",
    "sg:address":"510 S Jefferson Ave",
    "sg:city":"Cookeville",
    "sg:classifiers":[
        {
            "category":"Cinema",
            "subcategory":"Movie Rental",
            "type":"Entertainment"
        }
    ],
    "sg:phone":"+1 931 520 1177",
    "sg:postcode":"38501",
    "sg:province":"TN",
    "sg:tags":[
        "leasing",
        "video",
        "disc",
        "tape"
    ],
    "wof:name":"Blockbuster Video",
    "wof:placetype":"venue"
},
  "geometry": {"coordinates":[-85.500507,36.152362],"type":"Point"}
}