{
  "type": "Feature",
  "properties": {
    "iso:country":"US",
    "sg:address":"2701 Kingston Pike",
    "sg:city":"Knoxville",
    "sg:classifiers":[
        {
            "category":"Health Services",
            "subcategory":"Doctor",
            "type":"Services"
        }
    ],
    "sg:phone":"+1 865 524 5365",
    "sg:postcode":"37919",
    "sg:province":"TN",
    "sg:tags":[
        "physician",
        "surgeon",
        "medical"
    ],
    "wof:name":"Burns E Brantley MD",
    "wof:placetype":"venue"
},
  "geometry": {"coordinates":[-83.94822499999999,35.951325],"type":"Point"}
}