{
  "type": "Feature",
  "properties": {
    "iso:country":"US",
    "sg:address":"400 Main St W",
    "sg:city":"Knoxville",
    "sg:classifiers":[
        {
            "category":"Government",
            "subcategory":"Police Station",
            "type":"Public Place"
        }
    ],
    "sg:phone":"+1 865 215 2432",
    "sg:postcode":"37902",
    "sg:province":"TN",
    "sg:tags":[
        "protection"
    ],
    "wof:name":"Knox County Sheriff",
    "wof:placetype":"venue"
},
  "geometry": {"coordinates":[-83.91838199999999,35.96093],"type":"Point"}
}