{
  "type": "Feature",
  "properties": {
    "iso:country":"US",
    "sg:address":"174 2nd Ave N",
    "sg:city":"Nashville",
    "sg:classifiers":[
        {
            "category":"Food & Beverages",
            "subcategory":"Bakery",
            "type":"Retail Goods"
        }
    ],
    "sg:phone":"+1 615 255 5272",
    "sg:postcode":"37201",
    "sg:province":"TN",
    "sg:tags":[
        "pretzel"
    ],
    "wof:name":"Auntie Anne's",
    "wof:placetype":"venue"
},
  "geometry": {"coordinates":[-86.77662,36.164239],"type":"Point"}
}