{
  "type": "Feature",
  "properties": {
    "iso:country":"US",
    "sg:address":"4285 Prescott Rd",
    "sg:city":"Memphis",
    "sg:classifiers":[
        {
            "category":"Building & Trades",
            "subcategory":"Construction",
            "type":"Services"
        }
    ],
    "sg:phone":"+1 901 375 4844",
    "sg:postcode":"38118",
    "sg:province":"TN",
    "sg:tags":[
        "designer",
        "dealer",
        "pool",
        "swimming"
    ],
    "wof:name":"Scotts The Pool People",
    "wof:placetype":"venue"
},
  "geometry": {"coordinates":[-89.94356399999999,35.031076],"type":"Point"}
}