{
  "type": "Feature",
  "properties": {
    "iso:country":"US",
    "sg:address":"4892 Weaver Pike",
    "sg:city":"Bluff City",
    "sg:classifiers":[
        {
            "category":"Professional",
            "type":"Services"
        }
    ],
    "sg:phone":"+1 423 538 6698",
    "sg:postcode":"37618",
    "sg:province":"TN",
    "wof:name":"Bb Landand Inc",
    "wof:placetype":"venue"
},
  "geometry": {"coordinates":[-82.20316,36.482388],"type":"Point"}
}