{
  "type": "Feature",
  "properties": {
    "addr:full":"2115 Stein Dr Chattanooga TN 37421",
    "addr:housenumber":"2115",
    "addr:postcode":"37421",
    "addr:street":"Stein Dr",
    "iso:country":"US",
    "sg:address":"2115 Stein Dr",
    "sg:city":"Chattanooga",
    "sg:classifiers":[
        {
            "category":"Professional",
            "subcategory":"Accounting & Tax Preparation",
            "type":"Services"
        }
    ],
    "sg:phone":"+1 423 894 3577",
    "sg:postcode":"37421",
    "sg:province":"TN",
    "sg:tags":[
        "accountant",
        "public",
        "certified"
    ],
    "wof:name":"Heinemann & Associates Cpas",
    "wof:placetype":"venue"
},
  "geometry": {"coordinates":[-85.18598,35.055308],"type":"Point"}
}