{
  "type": "Feature",
  "properties": {
    "iso:country":"US",
    "sg:address":"129 Samsonite Blvd",
    "sg:city":"Murfreesboro",
    "sg:classifiers":[
        {
            "category":"Professional",
            "subcategory":"Management & Consulting",
            "type":"Services"
        }
    ],
    "sg:phone":"+1 615 896 1577",
    "sg:postcode":"37129",
    "sg:province":"TN",
    "sg:tags":[
        "engineering",
        "system",
        "analysis"
    ],
    "wof:name":"A D S Environmental Srvs",
    "wof:placetype":"venue"
},
  "geometry": {"coordinates":[-86.39727600000001,35.827989],"type":"Point"}
}