{
  "type": "Feature",
  "properties": {
    "iso:country":"US",
    "sg:address":"6530 N Lee Hwy",
    "sg:city":"Cleveland",
    "sg:classifiers":[
        {
            "category":"Professional",
            "subcategory":"Business Services",
            "type":"Services"
        }
    ],
    "sg:phone":"+1 423 476 4697",
    "sg:postcode":"37312",
    "sg:province":"TN",
    "wof:name":"Design House",
    "wof:placetype":"venue"
},
  "geometry": {"coordinates":[-84.807338,35.238319],"type":"Point"}
}