{
  "type": "Feature",
  "properties": {
    "addr:full":"603 Eastern Dr Memphis TN 38122",
    "addr:housenumber":"603",
    "addr:postcode":"38122",
    "addr:street":"Eastern Dr",
    "iso:country":"US",
    "sg:address":"603 Eastern Dr",
    "sg:city":"Memphis",
    "sg:classifiers":[
        {
            "category":"Building & Trades",
            "subcategory":"Landscaping Services",
            "type":"Services"
        }
    ],
    "sg:phone":"+1 901 382 2157",
    "sg:postcode":"38122",
    "sg:province":"TN",
    "wof:name":"Tender Lawn Care",
    "wof:placetype":"venue"
},
  "geometry": {"coordinates":[-89.92014500000001,35.147342],"type":"Point"}
}