{
  "type": "Feature",
  "properties": {
    "iso:country":"US",
    "sg:address":"109 Spring St",
    "sg:city":"Pikeville",
    "sg:classifiers":[
        {
            "category":"Education",
            "subcategory":"School",
            "type":"Public Place"
        }
    ],
    "sg:phone":"+1 423 447 2914",
    "sg:postcode":"37367",
    "sg:province":"TN",
    "wof:name":"Bledsoe County Board Of Ed",
    "wof:placetype":"venue"
},
  "geometry": {"coordinates":[-85.19043600000001,35.606443],"type":"Point"}
}