{
  "type": "Feature",
  "properties": {
    "iso:country":"US",
    "sg:address":"260 Old Friendship Rd",
    "sg:city":"Finger",
    "sg:classifiers":[
        {
            "category":"Building & Trades",
            "subcategory":"Landscaping Services",
            "type":"Services"
        }
    ],
    "sg:phone":"+1 731 989 5346",
    "sg:postcode":"38334",
    "sg:province":"TN",
    "sg:tags":[
        "landscape"
    ],
    "wof:name":"Chickasaw Landscape Service",
    "wof:placetype":"venue"
},
  "geometry": {"coordinates":[-88.642764,35.360442],"type":"Point"}
}