{
  "type": "Feature",
  "properties": {
    "iso:country":"US",
    "sg:address":"447 N Evergreen St",
    "sg:city":"Memphis",
    "sg:classifiers":[
        {
            "category":"Organizations",
            "subcategory":"Religious Organization",
            "type":"Services"
        }
    ],
    "sg:phone":"+1 901 274 4091",
    "sg:postcode":"38112",
    "sg:province":"TN",
    "sg:tags":[
        "church"
    ],
    "wof:name":"Trinity Methodist",
    "wof:placetype":"venue"
},
  "geometry": {"coordinates":[-90.00251,35.150077],"type":"Point"}
}