{
  "type": "Feature",
  "properties": {
    "iso:country":"US",
    "sg:address":"951 Eastgate Loop",
    "sg:city":"Chattanooga",
    "sg:classifiers":[
        {
            "category":"Insurance",
            "subcategory":"Insurance Agent",
            "type":"Services"
        }
    ],
    "sg:phone":"+1 423 894 2380",
    "sg:postcode":"37411",
    "sg:province":"TN",
    "wof:name":"State Farm Insurance",
    "wof:placetype":"venue"
},
  "geometry": {"coordinates":[-85.213534,35.00979],"type":"Point"}
}