{
  "type": "Feature",
  "properties": {
    "iso:country":"US",
    "sg:address":"6107 Ringgold Rd",
    "sg:city":"Chattanooga",
    "sg:classifiers":[
        {
            "category":"Manufacturing",
            "subcategory":"Paper Products",
            "type":"Manufacturing & Wholesale Goods"
        }
    ],
    "sg:phone":"+1 423 894 1110",
    "sg:postcode":"37412",
    "sg:province":"TN",
    "sg:tags":[
        "box"
    ],
    "sg:website":"www.tpc-print.com",
    "wof:name":"Textile Printing Co",
    "wof:placetype":"venue"
},
  "geometry": {"coordinates":[-85.210538,34.989579],"type":"Point"}
}