{
  "type": "Feature",
  "properties": {
    "iso:country":"US",
    "sg:address":"15773 Scott Hwy",
    "sg:city":"Oneida",
    "sg:classifiers":[
        {
            "category":"Autos & Motor Vehicles",
            "subcategory":"Automobile Sales",
            "type":"Retail Goods"
        }
    ],
    "sg:phone":"+1 423 286 7648",
    "sg:postcode":"37841",
    "sg:province":"TN",
    "wof:name":"High Point Auto Sales Corp",
    "wof:placetype":"venue"
},
  "geometry": {"coordinates":[-84.54454699999999,36.471104],"type":"Point"}
}