{
  "type": "Feature",
  "properties": {
    "iso:country":"US",
    "sg:address":"3277 Old Brownsville Rd",
    "sg:city":"Memphis",
    "sg:classifiers":[
        {
            "category":"Real Estate",
            "subcategory":"Architect",
            "type":"Services"
        },
        {
            "category":"Professional",
            "subcategory":"Engineering",
            "type":"Services"
        }
    ],
    "sg:phone":"+1 901 377 5500",
    "sg:postcode":"38134",
    "sg:province":"TN",
    "sg:tags":[
        "building",
        "consultant",
        "estimate",
        "construction",
        "estimator"
    ],
    "wof:name":"Construction Support Services",
    "wof:placetype":"venue"
},
  "geometry": {"coordinates":[-89.88090099999999,35.214345],"type":"Point"}
}