{
  "type": "Feature",
  "properties": {
    "iso:country":"US",
    "sg:address":"518 Casto Knepp Rd",
    "sg:city":"Jamestown",
    "sg:classifiers":[
        {
            "category":"Personal",
            "subcategory":"Beauty Salon",
            "type":"Services"
        }
    ],
    "sg:phone":"+1 931 879 7752",
    "sg:postcode":"38556",
    "sg:province":"TN",
    "sg:tags":[
        "shop"
    ],
    "wof:name":"W Right Lane Kuts",
    "wof:placetype":"venue"
},
  "geometry": {"coordinates":[-84.919006,36.457421],"type":"Point"}
}