{
  "type": "Feature",
  "properties": {
    "iso:country":"US",
    "sg:address":"840 State St",
    "sg:city":"Bristol",
    "sg:classifiers":[
        {
            "category":"Banks & Credit Unions",
            "subcategory":"Investment Brokerage",
            "type":"Services"
        }
    ],
    "sg:phone":"+1 423 652 8507",
    "sg:postcode":"37620",
    "sg:province":"TN",
    "sg:tags":[
        "security"
    ],
    "wof:name":"AmSouth",
    "wof:placetype":"venue"
},
  "geometry": {"coordinates":[-82.188176,36.595126],"type":"Point"}
}