{
  "type": "Feature",
  "properties": {
    "iso:country":"US",
    "sg:address":"580 Donelson Pike",
    "sg:city":"Nashville",
    "sg:classifiers":[
        {
            "category":"Restaurant",
            "type":"Food & Drink"
        }
    ],
    "sg:menulink":"http://www.allmenus.com/tn/nashville/140229-subway/menu/",
    "sg:phone":"+1 615 885 5259",
    "sg:postcode":"37214",
    "sg:province":"TN",
    "sg:tags":[
        "american",
        "sandwich"
    ],
    "wof:name":"Subway",
    "wof:placetype":"venue"
},
  "geometry": {"coordinates":[-86.667776,36.143244],"type":"Point"}
}