{
  "type": "Feature",
  "properties": {
    "iso:country":"US",
    "sg:address":"131 Avant Ln",
    "sg:city":"Dayton",
    "sg:classifiers":[
        {
            "category":"Manufacturing",
            "subcategory":"Glass & Minerals",
            "type":"Manufacturing & Wholesale Goods"
        }
    ],
    "sg:phone":"+1 423 775 9787",
    "sg:postcode":"37321",
    "sg:province":"TN",
    "sg:tags":[
        "concrete",
        "brick"
    ],
    "wof:name":"Sequatchie Concrete Svc",
    "wof:placetype":"venue"
},
  "geometry": {"coordinates":[-85.01822199999999,35.498823],"type":"Point"}
}