{
  "type": "Feature",
  "properties": {
    "iso:country":"US",
    "sg:address":"2655 Union Hall Rd",
    "sg:city":"Clarksville",
    "sg:classifiers":[
        {
            "category":"Real Estate",
            "subcategory":"Real Estate Operator",
            "type":"Services"
        }
    ],
    "sg:phone":"+1 931 552 3087",
    "sg:postcode":"37040",
    "sg:province":"TN",
    "sg:tags":[
        "apartment"
    ],
    "wof:name":"Paddock Place Apartments",
    "wof:placetype":"venue"
},
  "geometry": {"coordinates":[-87.304801,36.583324],"type":"Point"}
}