{
  "type": "Feature",
  "properties": {
    "iso:country":"US",
    "sg:address":"1011 E Main St",
    "sg:city":"Jonesborough",
    "sg:classifiers":[
        {
            "category":"Retail",
            "subcategory":"Car Wash",
            "type":"Services"
        }
    ],
    "sg:phone":"+1 423 753 9357",
    "sg:postcode":"37659",
    "sg:province":"TN",
    "sg:tags":[
        "automobile",
        "detail",
        "clean"
    ],
    "wof:name":"Hensley Detail Shop",
    "wof:placetype":"venue"
},
  "geometry": {"coordinates":[-82.445317,36.300872],"type":"Point"}
}