{
  "type": "Feature",
  "properties": {
    "addr:full":"8247 US Hwy 51 N Millington TN 38053",
    "addr:housenumber":"8247",
    "addr:postcode":"38053",
    "addr:street":"Us Hwy 51 N",
    "iso:country":"US",
    "sg:address":"8247 US Hwy 51 N",
    "sg:city":"Millington",
    "sg:classifiers":[
        {
            "category":"Wholesale",
            "subcategory":"Machinery & Supplies",
            "type":"Manufacturing & Wholesale Goods"
        }
    ],
    "sg:phone":"+1 901 873 0233",
    "sg:postcode":"38053",
    "sg:province":"TN",
    "sg:tags":[
        "tractor"
    ],
    "wof:name":"Tractor Supply Co",
    "wof:placetype":"venue"
},
  "geometry": {"coordinates":[-89.89964500000001,35.351216],"type":"Point"}
}