{
  "type": "Feature",
  "properties": {
    "addr:full":"410 4th St South Pittsburg TN 37380",
    "addr:housenumber":"410",
    "addr:postcode":"37380",
    "addr:street":"4Th St",
    "iso:country":"US",
    "sg:address":"410 4th St",
    "sg:city":"South Pittsburg",
    "sg:classifiers":[
        {
            "category":"Organizations",
            "subcategory":"Religious Organization",
            "type":"Services"
        }
    ],
    "sg:phone":"+1 423 837 6088",
    "sg:postcode":"37380",
    "sg:province":"TN",
    "sg:tags":[
        "church"
    ],
    "wof:name":"South Pittsburg Church-Christ",
    "wof:placetype":"venue"
},
  "geometry": {"coordinates":[-85.70959000000001,35.012454],"type":"Point"}
}