{
  "type": "Feature",
  "properties": {
    "addr:full":"579 Stanley Dr Memphis TN 38122",
    "addr:housenumber":"579",
    "addr:postcode":"38122",
    "addr:street":"Stanley Dr",
    "iso:country":"US",
    "sg:address":"579 Stanley Dr",
    "sg:city":"Memphis",
    "sg:classifiers":[
        {
            "category":"Organizations",
            "subcategory":"Professional Association",
            "type":"Services"
        }
    ],
    "sg:phone":"+1 901 821 0559",
    "sg:postcode":"38122",
    "sg:province":"TN",
    "sg:tags":[
        "community"
    ],
    "wof:name":"EBDI Inc",
    "wof:placetype":"venue"
},
  "geometry": {"coordinates":[-89.91667200000001,35.147401],"type":"Point"}
}