{
  "type": "Feature",
  "properties": {
    "iso:country":"US",
    "sg:address":"2730 Sulphur College Rd",
    "sg:city":"Hartsville",
    "sg:classifiers":[
        {
            "category":"Retail",
            "subcategory":"Auto Repair",
            "type":"Services"
        }
    ],
    "sg:phone":"+1 615 374 9370",
    "sg:postcode":"37074",
    "sg:province":"TN",
    "sg:tags":[
        "general"
    ],
    "wof:name":"Pretty Quick Muffler & Brake",
    "wof:placetype":"venue"
},
  "geometry": {"coordinates":[-86.220821,36.406042],"type":"Point"}
}