{
  "type": "Feature",
  "properties": {
    "iso:country":"US",
    "sg:address":"112 Maureen Dr",
    "sg:city":"Hendersonville",
    "sg:classifiers":[
        {
            "category":"Insurance",
            "subcategory":"Insurance Agent",
            "type":"Services"
        }
    ],
    "sg:phone":"+1 615 822 6075",
    "sg:postcode":"37075",
    "sg:province":"TN",
    "wof:name":"Colonel Insurance Inc",
    "wof:placetype":"venue"
},
  "geometry": {"coordinates":[-86.624122,36.255471],"type":"Point"}
}