{
  "type": "Feature",
  "properties": {
    "iso:country":"US",
    "sg:address":"1569 Monterey Hwy",
    "sg:city":"Sparta",
    "sg:classifiers":[
        {
            "category":"Restaurant",
            "type":"Food & Drink"
        }
    ],
    "sg:phone":"+1 931 739 0064",
    "sg:postcode":"38583",
    "sg:province":"TN",
    "wof:name":"River Bar & Grill",
    "wof:placetype":"venue"
},
  "geometry": {"coordinates":[-85.452301,35.938762],"type":"Point"}
}