{
  "type": "Feature",
  "properties": {
    "iso:country":"US",
    "sg:address":"1215 Venido Dr",
    "sg:city":"Knoxville",
    "sg:classifiers":[
        {
            "category":"Shopping",
            "subcategory":"Hobbies, Toys, & Games",
            "type":"Retail Goods"
        }
    ],
    "sg:phone":"+1 865 966 6639",
    "sg:postcode":"37932",
    "sg:province":"TN",
    "sg:tags":[
        "shop"
    ],
    "wof:name":"Jvd Crafts",
    "wof:placetype":"venue"
},
  "geometry": {"coordinates":[-84.14605899999999,35.92569],"type":"Point"}
}