{
  "type": "Feature",
  "properties": {
    "addr:full":"3100 W End Ave Nashville TN 37203",
    "addr:housenumber":"3100",
    "addr:postcode":"37203",
    "addr:street":"W End Ave",
    "iso:country":"US",
    "sg:address":"3100 W End Ave",
    "sg:city":"Nashville",
    "sg:classifiers":[
        {
            "category":"Professional",
            "subcategory":"Lawyer & Legal Services",
            "type":"Services"
        }
    ],
    "sg:phone":"+1 615 269 5540",
    "sg:postcode":"37203",
    "sg:province":"TN",
    "sg:tags":[
        "attorney"
    ],
    "wof:name":"Lisa L Collins",
    "wof:placetype":"venue"
},
  "geometry": {"coordinates":[-86.816233,36.141952],"type":"Point"}
}