{
  "type": "Feature",
  "properties": {
    "addr:full":"6117 Charlotte Pike Nashville TN 37209",
    "addr:housenumber":"6117",
    "addr:postcode":"37209",
    "addr:street":"Charlotte Pike",
    "iso:country":"US",
    "sg:address":"6117 Charlotte Pike",
    "sg:city":"Nashville",
    "sg:classifiers":[
        {
            "category":"Freight",
            "type":"Transportation"
        }
    ],
    "sg:phone":"+1 877 256 1891",
    "sg:postcode":"37209",
    "sg:province":"TN",
    "sg:tags":[
        "special",
        "general"
    ],
    "sg:website":"www.publicstorage.com",
    "wof:name":"Public Storage Inc",
    "wof:placetype":"venue"
},
  "geometry": {"coordinates":[-86.867424,36.148171],"type":"Point"}
}