{
  "type": "Feature",
  "properties": {
    "iso:country":"US",
    "sg:address":"2430 Dove Ln",
    "sg:city":"Chattanooga",
    "sg:classifiers":[
        {
            "category":"Insurance",
            "subcategory":"Insurance Agent",
            "type":"Services"
        }
    ],
    "sg:phone":"+1 423 490 0251",
    "sg:postcode":"37421",
    "sg:province":"TN",
    "wof:name":"Edwards Insurance Service",
    "wof:placetype":"venue"
},
  "geometry": {"coordinates":[-85.09410699999999,35.02344],"type":"Point"}
}