{
  "type": "Feature",
  "properties": {
    "addr:full":"3006 Dunedin Ct Old Hickory TN 37138",
    "addr:housenumber":"3006",
    "addr:postcode":"37138",
    "addr:street":"Dunedin Ct",
    "iso:country":"US",
    "sg:address":"3006 Dunedin Ct",
    "sg:city":"Old Hickory",
    "sg:classifiers":[
        {
            "category":"Professional",
            "subcategory":"Management & Consulting",
            "type":"Services"
        }
    ],
    "sg:phone":"+1 615 754 1810",
    "sg:postcode":"37138",
    "sg:province":"TN",
    "sg:tags":[
        "business"
    ],
    "wof:name":"KCS",
    "wof:placetype":"venue"
},
  "geometry": {"coordinates":[-86.568066,36.21154],"type":"Point"}
}