{
  "type": "Feature",
  "properties": {
    "addr:full":"3711 Clarksville Pike Nashville TN 37218",
    "addr:housenumber":"3711",
    "addr:postcode":"37218",
    "addr:street":"Clarksville Pike",
    "iso:country":"US",
    "sg:address":"3711 Clarksville Pike",
    "sg:city":"Nashville",
    "sg:classifiers":[
        {
            "category":"Food & Beverages",
            "subcategory":"Liquor & Beverages",
            "type":"Retail Goods"
        }
    ],
    "sg:phone":"+1 615 256 5886",
    "sg:postcode":"37218",
    "sg:province":"TN",
    "sg:tags":[
        "alcoholic"
    ],
    "wof:name":"Pardue Pharmacy",
    "wof:placetype":"venue"
},
  "geometry": {"coordinates":[-86.838165,36.198438],"type":"Point"}
}