{
  "type": "Feature",
  "properties": {
    "iso:country":"US",
    "sg:address":"7100 Oakmeade Rd",
    "sg:city":"Powell",
    "sg:classifiers":[
        {
            "category":"Professional",
            "subcategory":"Art Services",
            "type":"Services"
        }
    ],
    "sg:phone":"+1 865 947 5563",
    "sg:postcode":"37849",
    "sg:province":"TN",
    "sg:tags":[
        "graphic",
        "design"
    ],
    "wof:name":"Desktop Design",
    "wof:placetype":"venue"
},
  "geometry": {"coordinates":[-84.010419,36.024322],"type":"Point"}
}