{
  "type": "Feature",
  "properties": {
    "iso:country":"US",
    "sg:address":"240 Rockland Rd",
    "sg:city":"Hendersonville",
    "sg:classifiers":[
        {
            "category":"Building & Trades",
            "subcategory":"Plumbing",
            "type":"Services"
        }
    ],
    "sg:phone":"+1 615 824 9393",
    "sg:postcode":"37075",
    "sg:province":"TN",
    "sg:tags":[
        "plumbing",
        "contractor"
    ],
    "wof:name":"Viking Building & Plumbing",
    "wof:placetype":"venue"
},
  "geometry": {"coordinates":[-86.63944499999999,36.300962],"type":"Point"}
}