{
  "type": "Feature",
  "properties": {
    "addr:full":"6215 Macon Rd Memphis TN 38134",
    "addr:housenumber":"6215",
    "addr:postcode":"38134",
    "addr:street":"Macon Rd",
    "iso:country":"US",
    "sg:address":"6215 Macon Rd",
    "sg:city":"Memphis",
    "sg:classifiers":[
        {
            "category":"Autos & Motor Vehicles",
            "subcategory":"Fuel & Gas Station",
            "type":"Retail Goods"
        }
    ],
    "sg:phone":"+1 901 372 2757",
    "sg:postcode":"38134",
    "sg:province":"TN",
    "sg:tags":[
        "convenience",
        "gasoline",
        "store"
    ],
    "wof:name":"Mapco Express",
    "wof:placetype":"venue"
},
  "geometry": {"coordinates":[-89.856163,35.162958],"type":"Point"}
}