{
  "type": "Feature",
  "properties": {
    "iso:country":"US",
    "sg:address":"1425 Davis St",
    "sg:city":"Memphis",
    "sg:classifiers":[
        {
            "category":"Freight",
            "type":"Transportation"
        }
    ],
    "sg:phone":"+1 901 276 9272",
    "sg:postcode":"38108",
    "sg:province":"TN",
    "sg:tags":[
        "delivery"
    ],
    "wof:name":"B C Delivery Svc",
    "wof:placetype":"venue"
},
  "geometry": {"coordinates":[-89.98899,35.174952],"type":"Point"}
}