{
  "type": "Feature",
  "properties": {
    "iso:country":"US",
    "sg:address":"3148 Kingston Pike",
    "sg:city":"Knoxville",
    "sg:classifiers":[
        {
            "category":"Recreation",
            "type":"Entertainment"
        }
    ],
    "sg:phone":"+1 865 522 2371",
    "sg:postcode":"37919",
    "sg:province":"TN",
    "sg:tags":[
        "historical"
    ],
    "wof:name":"Confederate Memorial Hall",
    "wof:placetype":"venue"
},
  "geometry": {"coordinates":[-83.953903,35.95076],"type":"Point"}
}