{
  "type": "Feature",
  "properties": {
    "addr:full":"1214 Murfreesboro Pike Nashville TN 37217",
    "addr:housenumber":"1214",
    "addr:postcode":"37217",
    "addr:street":"Murfreesboro Pike",
    "iso:country":"US",
    "sg:address":"1214 Murfreesboro Pike",
    "sg:city":"Nashville",
    "sg:classifiers":[
        {
            "category":"Banks & Credit Unions",
            "subcategory":"Bank",
            "type":"Services"
        }
    ],
    "sg:phone":"+1 615 748 8380",
    "sg:postcode":"37217",
    "sg:province":"TN",
    "wof:name":"First Tennessee Bank",
    "wof:placetype":"venue"
},
  "geometry": {"coordinates":[-86.703312,36.120725],"type":"Point"}
}