{
  "type": "Feature",
  "properties": {
    "iso:country":"US",
    "sg:address":"6991 Appling Farms Pkwy",
    "sg:city":"Memphis",
    "sg:classifiers":[
        {
            "category":"Health Services",
            "subcategory":"Doctor",
            "type":"Services"
        },
        {
            "category":"Personal",
            "type":"Services"
        }
    ],
    "sg:phone":"+1 901 382 7230",
    "sg:postcode":"38133",
    "sg:province":"TN",
    "sg:tags":[
        "fitness",
        "physician",
        "surgeon",
        "program",
        "consultant"
    ],
    "wof:name":"Universal Health Services",
    "wof:placetype":"venue"
},
  "geometry": {"coordinates":[-89.83314799999999,35.179306],"type":"Point"}
}