{
  "type": "Feature",
  "properties": {
    "iso:country":"US",
    "sg:address":"4300 Dodds Ave",
    "sg:city":"Chattanooga",
    "sg:classifiers":[
        {
            "category":"Autos & Motor Vehicles",
            "subcategory":"Automobile Sales",
            "type":"Retail Goods"
        }
    ],
    "sg:phone":"+1 423 867 9857",
    "sg:postcode":"37407",
    "sg:province":"TN",
    "wof:name":"United",
    "wof:placetype":"venue"
},
  "geometry": {"coordinates":[-85.286407,34.991447],"type":"Point"}
}