{
  "type": "Feature",
  "properties": {
    "addr:full":"166 Dale St Red Boiling Spgs TN 37150",
    "addr:housenumber":"166",
    "addr:postcode":"37150",
    "addr:street":"Dale St",
    "iso:country":"US",
    "sg:address":"166 Dale St",
    "sg:city":"Red Boiling Spgs",
    "sg:classifiers":[
        {
            "category":"Government",
            "subcategory":"Office",
            "type":"Public Place"
        }
    ],
    "sg:phone":"+1 615 699 2011",
    "sg:postcode":"37150",
    "sg:province":"TN",
    "sg:tags":[
        "city"
    ],
    "wof:name":"Red Boiling Springs City Hall",
    "wof:placetype":"venue"
},
  "geometry": {"coordinates":[-85.851589,36.533161],"type":"Point"}
}