{
  "type": "Feature",
  "properties": {
    "addr:full":"3711 Hillsboro Pike Nashville TN 37215",
    "addr:housenumber":"3711",
    "addr:postcode":"37215",
    "addr:street":"Hillsboro Pike",
    "iso:country":"US",
    "sg:address":"3711 Hillsboro Pike",
    "sg:city":"Nashville",
    "sg:classifiers":[
        {
            "category":"Restaurant",
            "type":"Food & Drink"
        }
    ],
    "sg:phone":"+1 615 269 8577",
    "sg:postcode":"37215",
    "sg:province":"TN",
    "wof:name":"Shalimar Restaurant",
    "wof:placetype":"venue"
},
  "geometry": {"coordinates":[-86.81182800000001,36.109435],"type":"Point"}
}