{
  "type": "Feature",
  "properties": {
    "iso:country":"US",
    "sg:address":"4515 Harding Pike",
    "sg:city":"Nashville",
    "sg:classifiers":[
        {
            "category":"Professional",
            "subcategory":"Business Services",
            "type":"Services"
        }
    ],
    "sg:phone":"+1 615 292 6889",
    "sg:postcode":"37205",
    "sg:province":"TN",
    "sg:tags":[
        "broker",
        "merchandise"
    ],
    "wof:name":"Criterion Capital Management",
    "wof:placetype":"venue"
},
  "geometry": {"coordinates":[-86.84933100000001,36.123713],"type":"Point"}
}