{
  "type": "Feature",
  "properties": {
    "iso:country":"US",
    "sg:address":"175 Bell Ln",
    "sg:city":"Savannah",
    "sg:classifiers":[
        {
            "category":"Health Services",
            "subcategory":"Optometrist",
            "type":"Services"
        }
    ],
    "sg:phone":"+1 731 925 4902",
    "sg:postcode":"38372",
    "sg:province":"TN",
    "wof:name":"Savannah Eye Clinic",
    "wof:placetype":"venue"
},
  "geometry": {"coordinates":[-88.216385,35.22452],"type":"Point"}
}