{
  "type": "Feature",
  "properties": {
    "iso:country":"US",
    "sg:address":"50 Old Hickory Blvd E",
    "sg:city":"Jackson",
    "sg:classifiers":[
        {
            "category":"Shopping",
            "subcategory":"Clothing, Apparel, & Fashions",
            "type":"Retail Goods"
        }
    ],
    "sg:phone":"+1 731 424 2886",
    "sg:postcode":"38305",
    "sg:province":"TN",
    "sg:website":"www.rainbowshops.com",
    "wof:name":"Rainbow",
    "wof:placetype":"venue"
},
  "geometry": {"coordinates":[-88.82600600000001,35.652729],"type":"Point"}
}