{
  "type": "Feature",
  "properties": {
    "iso:country":"US",
    "sg:address":"517 2nd St",
    "sg:city":"Newport",
    "sg:classifiers":[
        {
            "category":"Education",
            "subcategory":"School",
            "type":"Public Place"
        },
        {
            "category":"Social Services",
            "type":"Services"
        }
    ],
    "sg:phone":"+1 423 613 9748",
    "sg:postcode":"37821",
    "sg:province":"TN",
    "sg:tags":[
        "academic",
        "special"
    ],
    "wof:name":"D C I Early Intervention",
    "wof:placetype":"venue"
},
  "geometry": {"coordinates":[-83.18012899999999,35.963684],"type":"Point"}
}