{
  "type": "Feature",
  "properties": {
    "addr:full":"3853 Agawela Dr Chattanooga TN 37406",
    "addr:housenumber":"3853",
    "addr:postcode":"37406",
    "addr:street":"Agawela Dr",
    "iso:country":"US",
    "sg:address":"3853 Agawela Dr",
    "sg:city":"Chattanooga",
    "sg:classifiers":[
        {
            "category":"Professional",
            "type":"Services"
        }
    ],
    "sg:phone":"+1 423 698 6823",
    "sg:postcode":"37406",
    "sg:province":"TN",
    "sg:tags":[
        "establishment"
    ],
    "wof:name":"R David & Assoc",
    "wof:placetype":"venue"
},
  "geometry": {"coordinates":[-85.22483,35.045731],"type":"Point"}
}