{
  "type": "Feature",
  "properties": {
    "addr:full":"2017 8th Ave S Nashville TN 37204",
    "addr:housenumber":"2017",
    "addr:postcode":"37204",
    "addr:street":"8Th Ave S",
    "iso:country":"US",
    "sg:address":"2017 8th Ave S",
    "sg:city":"Nashville",
    "sg:classifiers":[
        {
            "category":"Autos & Motor Vehicles",
            "subcategory":"Fuel & Gas Station",
            "type":"Retail Goods"
        }
    ],
    "sg:phone":"+1 615 269 6403",
    "sg:postcode":"37204",
    "sg:province":"TN",
    "sg:tags":[
        "station",
        "gasoline"
    ],
    "wof:name":"Scot Market",
    "wof:placetype":"venue"
},
  "geometry": {"coordinates":[-86.779324,36.132616],"type":"Point"}
}