{
  "type": "Feature",
  "properties": {
    "addr:full":"717 N Central St Knoxville TN 37917",
    "addr:housenumber":"717",
    "addr:postcode":"37917",
    "addr:street":"N Central St",
    "iso:country":"US",
    "sg:address":"717 N Central St",
    "sg:city":"Knoxville",
    "sg:classifiers":[
        {
            "category":"Professional",
            "subcategory":"Lawyer & Legal Services",
            "type":"Services"
        }
    ],
    "sg:phone":"+1 865 673 0755",
    "sg:postcode":"37917",
    "sg:province":"TN",
    "sg:tags":[
        "attorney"
    ],
    "wof:name":"Slaybaugh & Skeens",
    "wof:placetype":"venue"
},
  "geometry": {"coordinates":[-83.923692,35.975952],"type":"Point"}
}