{
  "type": "Feature",
  "properties": {
    "iso:country":"US",
    "sg:address":"511 Lone Mountain Rd",
    "sg:city":"Tazewell",
    "sg:classifiers":[
        {
            "category":"Building & Trades",
            "subcategory":"Construction",
            "type":"Services"
        }
    ],
    "sg:phone":"+1 423 626 3614",
    "sg:postcode":"37879",
    "sg:province":"TN",
    "sg:tags":[
        "paving",
        "contractor"
    ],
    "wof:name":"Pioneer Paving",
    "wof:placetype":"venue"
},
  "geometry": {"coordinates":[-83.533812,36.41946],"type":"Point"}
}