{
  "type": "Feature",
  "properties": {
    "iso:country":"US",
    "sg:address":"500 E Unaka Ave",
    "sg:city":"Johnson City",
    "sg:classifiers":[
        {
            "category":"Real Estate",
            "subcategory":"Real Estate Agent",
            "type":"Services"
        }
    ],
    "sg:phone":"+1 423 926 2123",
    "sg:postcode":"37601",
    "sg:province":"TN",
    "sg:tags":[
        "management"
    ],
    "sg:website":"www.hrc4rent.com",
    "wof:name":"Heritage Realty",
    "wof:placetype":"venue"
},
  "geometry": {"coordinates":[-82.35138499999999,36.327805],"type":"Point"}
}