{
  "type": "Feature",
  "properties": {
    "iso:country":"US",
    "sg:address":"355 Tusculum Rd",
    "sg:city":"Nashville",
    "sg:classifiers":[
        {
            "category":"Organizations",
            "subcategory":"Religious Organization",
            "type":"Services"
        }
    ],
    "sg:phone":"+1 615 834 1936",
    "sg:postcode":"37211",
    "sg:province":"TN",
    "sg:tags":[
        "church"
    ],
    "wof:name":"St Basil's Orthodox Cathedral",
    "wof:placetype":"venue"
},
  "geometry": {"coordinates":[-86.708055,36.059273],"type":"Point"}
}