{
  "type": "Feature",
  "properties": {
    "iso:country":"US",
    "sg:address":"220 Broad St",
    "sg:city":"Kingsport",
    "sg:classifiers":[
        {
            "category":"Education",
            "subcategory":"Special Training",
            "type":"Public Place"
        }
    ],
    "sg:phone":"+1 423 247 9391",
    "sg:postcode":"37660",
    "sg:province":"TN",
    "sg:tags":[
        "instruction",
        "music"
    ],
    "wof:name":"Pine Tree Music",
    "wof:placetype":"venue"
},
  "geometry": {"coordinates":[-82.560046,36.547235],"type":"Point"}
}