{
  "type": "Feature",
  "properties": {
    "iso:country":"US",
    "sg:address":"1115 N Maple St",
    "sg:city":"Murfreesboro",
    "sg:classifiers":[
        {
            "category":"Personal",
            "subcategory":"Barber",
            "type":"Services"
        }
    ],
    "sg:phone":"+1 615 867 0301",
    "sg:postcode":"37130",
    "sg:province":"TN",
    "sg:tags":[
        "shop"
    ],
    "wof:name":"Dolittles Barber Shop",
    "wof:placetype":"venue"
},
  "geometry": {"coordinates":[-86.391144,35.855986],"type":"Point"}
}