{
  "type": "Feature",
  "properties": {
    "iso:country":"US",
    "sg:address":"1177 Madison Ave",
    "sg:city":"Memphis",
    "sg:classifiers":[
        {
            "category":"Travel",
            "subcategory":"Hotels & Motels",
            "type":"Entertainment"
        }
    ],
    "sg:phone":"+1 877 574 2464",
    "sg:postcode":"38104",
    "sg:province":"TN",
    "sg:tags":[
        "lodging"
    ],
    "sg:website":"http://book.bestwestern.com/bestwestern/priceAvail.do?propertyCode=43175&cm_mmc=IYP-_-YP-_-property-_-43175",
    "wof:name":"Best Western Gen X Inn",
    "wof:placetype":"venue"
},
  "geometry": {"coordinates":[-90.02179700000001,35.139431],"type":"Point"}
}