{
  "type": "Feature",
  "properties": {
    "addr:full":"2414 Jacksboro Pike La Follette TN 37766",
    "addr:housenumber":"2414",
    "addr:postcode":"37766",
    "addr:street":"Jacksboro Pike",
    "iso:country":"US",
    "sg:address":"2414 Jacksboro Pike",
    "sg:city":"La Follette",
    "sg:classifiers":[
        {
            "category":"Restaurant",
            "type":"Food & Drink"
        }
    ],
    "sg:menulink":"http://www.allmenus.com/tn/la-follette/140069-subway/menu/",
    "sg:phone":"+1 423 566 4742",
    "sg:postcode":"37766",
    "sg:province":"TN",
    "sg:tags":[
        "american",
        "sandwich"
    ],
    "wof:name":"Subway",
    "wof:placetype":"venue"
},
  "geometry": {"coordinates":[-84.167643,36.342019],"type":"Point"}
}