{
  "type": "Feature",
  "properties": {
    "iso:country":"US",
    "sg:address":"3491 Covemont Ln",
    "sg:city":"Sevierville",
    "sg:classifiers":[
        {
            "category":"Shopping",
            "subcategory":"Crafts & Fabrics",
            "type":"Retail Goods"
        }
    ],
    "sg:phone":"+1 865 429 3146",
    "sg:postcode":"37862",
    "sg:province":"TN",
    "sg:tags":[
        "sewing"
    ],
    "wof:name":"Needlecraft Cottage",
    "wof:placetype":"venue"
},
  "geometry": {"coordinates":[-83.619547,35.723446],"type":"Point"}
}