{
  "type": "Feature",
  "properties": {
    "addr:full":"1503 Nashville Hwy Columbia TN 38401",
    "addr:housenumber":"1503",
    "addr:postcode":"38401",
    "addr:street":"Nashville Hwy",
    "iso:country":"US",
    "sg:address":"1503 Nashville Hwy",
    "sg:city":"Columbia",
    "sg:classifiers":[
        {
            "category":"Manufacturing",
            "subcategory":"Motor Vehicles & Parts",
            "type":"Manufacturing & Wholesale Goods"
        }
    ],
    "sg:phone":"+1 931 486 6617",
    "sg:postcode":"38401",
    "sg:province":"TN",
    "sg:tags":[
        "body",
        "mfg"
    ],
    "wof:name":"Saturn",
    "wof:placetype":"venue"
},
  "geometry": {"coordinates":[-87.012387,35.647536],"type":"Point"}
}