{
  "type": "Feature",
  "properties": {
    "addr:full":"5100 Asbury Cemetery Rd Knoxville TN 37914",
    "addr:housenumber":"5100",
    "addr:postcode":"37914",
    "addr:street":"Asbury Cemetery Rd",
    "iso:country":"US",
    "sg:address":"5100 Asbury Cemetery Rd",
    "sg:city":"Knoxville",
    "sg:classifiers":[
        {
            "category":"Real Estate",
            "subcategory":"Developer",
            "type":"Services"
        }
    ],
    "sg:phone":"+1 865 524 2058",
    "sg:postcode":"37914",
    "sg:province":"TN",
    "sg:tags":[
        "cemetery",
        "association"
    ],
    "wof:name":"Asbury Cemetery",
    "wof:placetype":"venue"
},
  "geometry": {"coordinates":[-83.835386,35.945833],"type":"Point"}
}