{
  "type": "Feature",
  "properties": {
    "addr:full":"46 Chickasaw Oaks Dr Memphis TN 38111",
    "addr:housenumber":"46",
    "addr:postcode":"38111",
    "addr:street":"Chickasaw Oaks Dr",
    "iso:country":"US",
    "sg:address":"46 Chickasaw Oaks Dr",
    "sg:city":"Memphis",
    "sg:classifiers":[
        {
            "category":"Personal",
            "subcategory":"Beauty Salon",
            "type":"Services"
        }
    ],
    "sg:phone":"+1 901 320 0002",
    "sg:postcode":"38111",
    "sg:province":"TN",
    "sg:tags":[
        "shop"
    ],
    "wof:name":"Justina's Salon",
    "wof:placetype":"venue"
},
  "geometry": {"coordinates":[-89.958399,35.131578],"type":"Point"}
}