{
  "type": "Feature",
  "properties": {
    "iso:country":"US",
    "sg:address":"1912 Springcroft Dr",
    "sg:city":"Franklin",
    "sg:classifiers":[
        {
            "category":"Professional",
            "subcategory":"Art Services",
            "type":"Services"
        }
    ],
    "sg:phone":"+1 615 771 6726",
    "sg:postcode":"37067",
    "sg:province":"TN",
    "sg:tags":[
        "commercial",
        "design"
    ],
    "wof:name":"Blue Sky",
    "wof:placetype":"venue"
},
  "geometry": {"coordinates":[-86.752382,35.925951],"type":"Point"}
}