{
  "type": "Feature",
  "properties": {
    "iso:country":"US",
    "sg:address":"1617 16th Ave S",
    "sg:city":"Nashville",
    "sg:classifiers":[
        {
            "category":"Health Services",
            "subcategory":"Hospital",
            "type":"Services"
        },
        {
            "category":"Health Services",
            "subcategory":"Clinic",
            "type":"Services"
        }
    ],
    "sg:phone":"+1 615 269 9536",
    "sg:postcode":"37212",
    "sg:province":"TN",
    "sg:tags":[
        "mental",
        "outpatient",
        "specialty"
    ],
    "wof:name":"Friends Helping Friends Ctr",
    "wof:placetype":"venue"
},
  "geometry": {"coordinates":[-86.793756,36.140641],"type":"Point"}
}