{
  "type": "Feature",
  "properties": {
    "iso:country":"US",
    "sg:address":"7905 Giacosa Pl",
    "sg:city":"Memphis",
    "sg:classifiers":[
        {
            "category":"Travel",
            "subcategory":"Hotels & Motels",
            "type":"Entertainment"
        }
    ],
    "sg:phone":"+1 901 371 0010",
    "sg:postcode":"38133",
    "sg:province":"TN",
    "sg:tags":[
        "management"
    ],
    "wof:name":"Amerisuites",
    "wof:placetype":"venue"
},
  "geometry": {"coordinates":[-89.79644999999999,35.196562],"type":"Point"}
}