{
  "type": "Feature",
  "properties": {
    "addr:full":"7083 Bakers Bridge Rd Franklin TN 37067",
    "addr:housenumber":"7083",
    "addr:postcode":"37067",
    "addr:street":"Bakers Bridge Rd",
    "iso:country":"US",
    "sg:address":"7083 Bakers Bridge Rd",
    "sg:city":"Franklin",
    "sg:classifiers":[
        {
            "category":"Restaurant",
            "type":"Food & Drink"
        }
    ],
    "sg:menulink":"http://www.allmenus.com/tn/brentwood/114903-chilis/menu/",
    "sg:phone":"+1 615 771 7497",
    "sg:postcode":"37067",
    "sg:province":"TN",
    "sg:tags":[
        "burger",
        "american",
        "sandwich",
        "tex-mex",
        "soup"
    ],
    "wof:name":"Chili's",
    "wof:placetype":"venue"
},
  "geometry": {"coordinates":[-86.81308900000001,35.961187],"type":"Point"}
}