{
  "type": "Feature",
  "properties": {
    "iso:country":"US",
    "sg:address":"980 University St",
    "sg:city":"Memphis",
    "sg:classifiers":[
        {
            "category":"Shopping",
            "type":"Retail Goods"
        }
    ],
    "sg:phone":"+1 901 287 0534",
    "sg:postcode":"38107",
    "sg:province":"TN",
    "sg:tags":[
        "merchandise"
    ],
    "wof:name":"Perfect Fit Alteration Shop",
    "wof:placetype":"venue"
},
  "geometry": {"coordinates":[-89.990883,35.163925],"type":"Point"}
}