{
  "type": "Feature",
  "properties": {
    "iso:country":"US",
    "sg:address":"620 W College St",
    "sg:city":"Murfreesboro",
    "sg:classifiers":[
        {
            "category":"Building & Trades",
            "subcategory":"Cleaning & Sanitation",
            "type":"Services"
        }
    ],
    "sg:phone":"+1 615 890 0766",
    "sg:postcode":"37130",
    "sg:province":"TN",
    "sg:tags":[
        "janitor"
    ],
    "wof:name":"Todd Janitorial Svc & Supplies",
    "wof:placetype":"venue"
},
  "geometry": {"coordinates":[-86.397706,35.849317],"type":"Point"}
}