{
  "type": "Feature",
  "properties": {
    "addr:full":"2899 Cordie Lee Ln Germantown TN 38138",
    "addr:housenumber":"2899",
    "addr:postcode":"38138",
    "addr:street":"Cordie Lee Ln",
    "iso:country":"US",
    "sg:address":"2899 Cordie Lee Ln",
    "sg:city":"Germantown",
    "sg:classifiers":[
        {
            "category":"Communications",
            "subcategory":"Radio Station",
            "type":"Services"
        }
    ],
    "sg:phone":"+1 901 755 9475",
    "sg:postcode":"38138",
    "sg:province":"TN",
    "sg:tags":[
        "broadcast"
    ],
    "wof:name":"Jack Parnell Enterprises",
    "wof:placetype":"venue"
},
  "geometry": {"coordinates":[-89.800094,35.069643],"type":"Point"}
}