{
  "type": "Feature",
  "properties": {
    "iso:country":"US",
    "sg:address":"458 Academy Dr",
    "sg:city":"Friendsville",
    "sg:classifiers":[
        {
            "category":"Building & Trades",
            "subcategory":"Construction",
            "type":"Services"
        }
    ],
    "sg:phone":"+1 865 995 0637",
    "sg:postcode":"37737",
    "sg:province":"TN",
    "sg:tags":[
        "excavation",
        "contractor"
    ],
    "wof:name":"Armstrong Back Hoe Service",
    "wof:placetype":"venue"
},
  "geometry": {"coordinates":[-84.135553,35.749882],"type":"Point"}
}