{
  "type": "Feature",
  "properties": {
    "addr:full":"607 Craighead St Nashville TN 37204",
    "addr:housenumber":"607",
    "addr:postcode":"37204",
    "addr:street":"Craighead St",
    "iso:country":"US",
    "sg:address":"607 Craighead St",
    "sg:city":"Nashville",
    "sg:classifiers":[
        {
            "category":"Home & Garden",
            "subcategory":"Garden Supply",
            "type":"Retail Goods"
        }
    ],
    "sg:phone":"+1 615 254 1634",
    "sg:postcode":"37204",
    "sg:province":"TN",
    "sg:tags":[
        "lawn"
    ],
    "sg:website":"www.chiltoncompanies.com",
    "wof:name":"Chilton Air Cooled Engines Inc",
    "wof:placetype":"venue"
},
  "geometry": {"coordinates":[-86.774968,36.12655],"type":"Point"}
}