{
  "type": "Feature",
  "properties": {
    "iso:country":"US",
    "sg:address":"2433 Broad St",
    "sg:city":"Chattanooga",
    "sg:classifiers":[
        {
            "category":"Insurance",
            "subcategory":"Insurance Agent",
            "type":"Services"
        }
    ],
    "sg:phone":"+1 423 267 0046",
    "sg:postcode":"37402",
    "sg:province":"TN",
    "wof:name":"Solomon Financial Group",
    "wof:placetype":"venue"
},
  "geometry": {"coordinates":[-85.315107,35.030432],"type":"Point"}
}