{
  "type": "Feature",
  "properties": {
    "iso:country":"US",
    "sg:address":"1101 Sam Johnson Rd",
    "sg:city":"Columbia",
    "sg:classifiers":[
        {
            "category":"Manufacturing",
            "subcategory":"Printing",
            "type":"Manufacturing & Wholesale Goods"
        }
    ],
    "sg:phone":"+1 931 380 0850",
    "sg:postcode":"38401",
    "sg:province":"TN",
    "sg:tags":[
        "publisher"
    ],
    "wof:name":"Promise Publishing Inc",
    "wof:placetype":"venue"
},
  "geometry": {"coordinates":[-86.998698,35.656499],"type":"Point"}
}