{
  "type": "Feature",
  "properties": {
    "iso:country":"US",
    "sg:address":"1823 Shepherd Rd",
    "sg:city":"Chattanooga",
    "sg:classifiers":[
        {
            "category":"Organizations",
            "subcategory":"Religious Organization",
            "type":"Services"
        }
    ],
    "sg:phone":"+1 423 899 9408",
    "sg:postcode":"37421",
    "sg:province":"TN",
    "wof:name":"Washington Park Baptist Church",
    "wof:placetype":"venue"
},
  "geometry": {"coordinates":[-85.19053599999999,35.037459],"type":"Point"}
}