{
  "type": "Feature",
  "properties": {
    "addr:full":"2908 Hillhurst Dr Nashville TN 37207",
    "addr:housenumber":"2908",
    "addr:postcode":"37207",
    "addr:street":"Hillhurst Dr",
    "iso:country":"US",
    "sg:address":"2908 Hillhurst Dr",
    "sg:city":"Nashville",
    "sg:classifiers":[
        {
            "category":"Retail",
            "subcategory":"Car Wash",
            "type":"Services"
        }
    ],
    "sg:phone":"+1 615 228 1121",
    "sg:postcode":"37207",
    "sg:province":"TN",
    "sg:tags":[
        "carwash"
    ],
    "wof:name":"Leons Auto Detail & Service",
    "wof:placetype":"venue"
},
  "geometry": {"coordinates":[-86.768799,36.227429],"type":"Point"}
}