{
  "type": "Feature",
  "properties": {
    "iso:country":"US",
    "sg:address":"3876 Brunswick Rd",
    "sg:city":"Memphis",
    "sg:classifiers":[
        {
            "category":"Building & Trades",
            "subcategory":"Construction",
            "type":"Services"
        }
    ],
    "sg:phone":"+1 901 382 0183",
    "sg:postcode":"38133",
    "sg:province":"TN",
    "sg:tags":[
        "house"
    ],
    "wof:name":"Helverings Construction Co",
    "wof:placetype":"venue"
},
  "geometry": {"coordinates":[-89.771809,35.229072],"type":"Point"}
}