{
  "type": "Feature",
  "properties": {
    "iso:country":"US",
    "sg:address":"364 N Water Ave",
    "sg:city":"Gallatin",
    "sg:classifiers":[
        {
            "category":"Freight",
            "type":"Transportation"
        }
    ],
    "sg:phone":"+1 615 206 0880",
    "sg:postcode":"37066",
    "sg:province":"TN",
    "sg:tags":[
        "operator",
        "trucking"
    ],
    "wof:name":"Interstate Distributer Inc",
    "wof:placetype":"venue"
},
  "geometry": {"coordinates":[-86.446916,36.393596],"type":"Point"}
}