{
  "type": "Feature",
  "properties": {
    "iso:country":"US",
    "sg:address":"3105 Clintwood Way",
    "sg:city":"Pigeon Forge",
    "sg:classifiers":[
        {
            "category":"Building & Trades",
            "subcategory":"Construction",
            "type":"Services"
        }
    ],
    "sg:phone":"+1 865 453 8651",
    "sg:postcode":"37863",
    "sg:province":"TN",
    "sg:tags":[
        "concrete",
        "contractor"
    ],
    "wof:name":"Whaleys Concrete Finishing Svc",
    "wof:placetype":"venue"
},
  "geometry": {"coordinates":[-83.55328900000001,35.796359],"type":"Point"}
}