{
  "type": "Feature",
  "properties": {
    "iso:country":"US",
    "sg:address":"100 Ridgecrest Rd",
    "sg:city":"Jackson",
    "sg:classifiers":[
        {
            "category":"Social Services",
            "subcategory":"Child Care",
            "type":"Services"
        }
    ],
    "sg:phone":"+1 731 664 7001",
    "sg:postcode":"38305",
    "sg:province":"TN",
    "wof:name":"Jack N Jill Child Care Ctr",
    "wof:placetype":"venue"
},
  "geometry": {"coordinates":[-88.825107,35.667408],"type":"Point"}
}