{
  "type": "Feature",
  "properties": {
    "iso:country":"US",
    "sg:address":"179 Belle Forest Cir",
    "sg:city":"Nashville",
    "sg:classifiers":[
        {
            "category":"Professional",
            "subcategory":"Management & Consulting",
            "type":"Services"
        }
    ],
    "sg:phone":"+1 615 646 9600",
    "sg:postcode":"37221",
    "sg:province":"TN",
    "sg:tags":[
        "communications",
        "business",
        "consultant"
    ],
    "sg:website":"www.raymondtelecom.com",
    "wof:name":"Raymond Telecom",
    "wof:placetype":"venue"
},
  "geometry": {"coordinates":[-86.924311,36.075377],"type":"Point"}
}