{
  "type": "Feature",
  "properties": {
    "iso:country":"US",
    "sg:address":"2469 Cabin Hill Rd",
    "sg:city":"Nashville",
    "sg:classifiers":[
        {
            "category":"Organizations",
            "subcategory":"Religious Organization",
            "type":"Services"
        }
    ],
    "sg:phone":"+1 615 889 1616",
    "sg:postcode":"37214",
    "sg:province":"TN",
    "sg:tags":[
        "clergy"
    ],
    "wof:name":"Glen H Burks",
    "wof:placetype":"venue"
},
  "geometry": {"coordinates":[-86.674465,36.196371],"type":"Point"}
}