{
  "type": "Feature",
  "properties": {
    "addr:full":"1470 Olivet Mountain Rd Greeneville TN 37743",
    "addr:housenumber":"1470",
    "addr:postcode":"37743",
    "addr:street":"Olivet Mountain Rd",
    "iso:country":"US",
    "sg:address":"1470 Olivet Mountain Rd",
    "sg:city":"Greeneville",
    "sg:classifiers":[
        {
            "category":"Building & Trades",
            "subcategory":"Construction",
            "type":"Services"
        }
    ],
    "sg:phone":"+1 423 638 5031",
    "sg:postcode":"37743",
    "sg:province":"TN",
    "sg:tags":[
        "contractor"
    ],
    "wof:name":"Davis & Coakley Fencing",
    "wof:placetype":"venue"
},
  "geometry": {"coordinates":[-82.91733600000001,36.004345],"type":"Point"}
}