{
  "type": "Feature",
  "properties": {
    "addr:full":"1412 Camp Ravine Rd Burns TN 37029",
    "addr:housenumber":"1412",
    "addr:postcode":"37029",
    "addr:street":"Camp Ravine Rd",
    "iso:country":"US",
    "sg:address":"1412 Camp Ravine Rd",
    "sg:city":"Burns",
    "sg:phone":"+1 615 740 7040",
    "sg:postcode":"37029",
    "sg:province":"TN",
    "sg:tags":[
        "fuel",
        "diesel"
    ],
    "wof:name":"Flying J Inc-Fuel Marketing",
    "wof:placetype":"venue"
},
  "geometry": {"coordinates":[-87.25331,36.035042],"type":"Point"}
}