{
  "type": "Feature",
  "properties": {
    "addr:full":"112 N Main St Waynesboro TN 38485",
    "addr:housenumber":"112",
    "addr:postcode":"38485",
    "addr:street":"N Main St",
    "iso:country":"US",
    "sg:address":"112 N Main St",
    "sg:city":"Waynesboro",
    "sg:classifiers":[
        {
            "category":"Organizations",
            "subcategory":"Religious Organization",
            "type":"Services"
        }
    ],
    "sg:phone":"+1 931 722 3230",
    "sg:postcode":"38485",
    "sg:province":"TN",
    "wof:name":"First Baptist Church",
    "wof:placetype":"venue"
},
  "geometry": {"coordinates":[-87.762064,35.320751],"type":"Point"}
}