{
  "type": "Feature",
  "properties": {
    "addr:full":"1680 Carruthers Pl Memphis TN 38112",
    "addr:housenumber":"1680",
    "addr:postcode":"38112",
    "addr:street":"Carruthers Pl",
    "iso:country":"US",
    "sg:address":"1680 Carruthers Pl",
    "sg:city":"Memphis",
    "sg:classifiers":[
        {
            "category":"Professional",
            "subcategory":"Business Services",
            "type":"Services"
        }
    ],
    "sg:phone":"+1 901 728 5517",
    "sg:postcode":"38112",
    "sg:province":"TN",
    "sg:tags":[
        "interior",
        "consultant",
        "design",
        "decorator"
    ],
    "wof:name":"Just A Decorator",
    "wof:placetype":"venue"
},
  "geometry": {"coordinates":[-90.003896,35.146356],"type":"Point"}
}