{
  "type": "Feature",
  "properties": {
    "iso:country":"US",
    "sg:address":"224 Charles Haney Rd",
    "sg:city":"Cookeville",
    "sg:classifiers":[
        {
            "category":"Building & Trades",
            "subcategory":"Construction",
            "type":"Services"
        }
    ],
    "sg:phone":"+1 931 268 2783",
    "sg:postcode":"38501",
    "sg:province":"TN",
    "sg:tags":[
        "house"
    ],
    "wof:name":"M A Construction",
    "wof:placetype":"venue"
},
  "geometry": {"coordinates":[-85.602127,36.239627],"type":"Point"}
}