{
  "type": "Feature",
  "properties": {
    "addr:full":"2500 S Main St Springfield TN 37172",
    "addr:housenumber":"2500",
    "addr:postcode":"37172",
    "addr:street":"S Main St",
    "iso:country":"US",
    "sg:address":"2500 S Main St",
    "sg:city":"Springfield",
    "sg:classifiers":[
        {
            "category":"Wholesale",
            "subcategory":"Tobacco Products",
            "type":"Manufacturing & Wholesale Goods"
        }
    ],
    "sg:phone":"+1 615 384 9576",
    "sg:postcode":"37172",
    "sg:province":"TN",
    "sg:tags":[
        "buyer"
    ],
    "sg:website":"www.hailcotton.com",
    "wof:name":"Hail & Cotton",
    "wof:placetype":"venue"
},
  "geometry": {"coordinates":[-86.89198399999999,36.48439],"type":"Point"}
}