{
  "type": "Feature",
  "properties": {
    "iso:country":"US",
    "sg:address":"1901 Carmack Blvd",
    "sg:city":"Columbia",
    "sg:classifiers":[
        {
            "category":"Restaurant",
            "type":"Food & Drink"
        }
    ],
    "sg:phone":"+1 931 381 9776",
    "sg:postcode":"38401",
    "sg:province":"TN",
    "sg:tags":[
        "eating"
    ],
    "wof:name":"Good Ol Boy Biscuits",
    "wof:placetype":"venue"
},
  "geometry": {"coordinates":[-87.036559,35.599344],"type":"Point"}
}