{
  "type": "Feature",
  "properties": {
    "iso:country":"US",
    "sg:address":"358 Mesa Dr",
    "sg:city":"Kingsport",
    "sg:classifiers":[
        {
            "category":"Building & Trades",
            "subcategory":"Construction",
            "type":"Services"
        }
    ],
    "sg:phone":"+1 423 349 5055",
    "sg:postcode":"37664",
    "sg:province":"TN",
    "sg:tags":[
        "house"
    ],
    "wof:name":"Richards Home Improvement & MA",
    "wof:placetype":"venue"
},
  "geometry": {"coordinates":[-82.553862,36.469164],"type":"Point"}
}