{
  "type": "Feature",
  "properties": {
    "iso:country":"US",
    "sg:address":"803 Willowview Dr",
    "sg:city":"La Vergne",
    "sg:classifiers":[
        {
            "category":"Professional",
            "type":"Services"
        }
    ],
    "sg:phone":"+1 615 793 9775",
    "sg:postcode":"37086",
    "sg:province":"TN",
    "wof:name":"Kevin Voorhies",
    "wof:placetype":"venue"
},
  "geometry": {"coordinates":[-86.567735,36.030905],"type":"Point"}
}