{
  "type": "Feature",
  "properties": {
    "iso:country":"US",
    "sg:address":"4633 Marshall Dr",
    "sg:city":"Knoxville",
    "sg:classifiers":[
        {
            "category":"Professional",
            "subcategory":"Management & Consulting",
            "type":"Services"
        }
    ],
    "sg:phone":"+1 865 922 7259",
    "sg:postcode":"37918",
    "sg:province":"TN",
    "wof:name":"Bits n Pcs",
    "wof:placetype":"venue"
},
  "geometry": {"coordinates":[-83.915555,36.08272],"type":"Point"}
}