{
  "type": "Feature",
  "properties": {
    "iso:country":"US",
    "sg:address":"720 Murfreesboro Pike",
    "sg:city":"Nashville",
    "sg:classifiers":[
        {
            "category":"Personal",
            "subcategory":"Barber",
            "type":"Services"
        }
    ],
    "sg:phone":"+1 615 313 7337",
    "sg:postcode":"37217",
    "sg:province":"TN",
    "wof:name":"Unique Hair Design",
    "wof:placetype":"venue"
},
  "geometry": {"coordinates":[-86.72990299999999,36.138118],"type":"Point"}
}