{
  "type": "Feature",
  "properties": {
    "addr:full":"200 Bus Terminal Rd Oak Ridge TN 37830",
    "addr:housenumber":"200",
    "addr:postcode":"37830",
    "addr:street":"Terminal Rd",
    "iso:country":"US",
    "sg:address":"200 Bus Terminal Rd",
    "sg:city":"Oak Ridge",
    "sg:classifiers":[
        {
            "category":"Retail",
            "subcategory":"Auto Rental",
            "type":"Services"
        }
    ],
    "sg:phone":"+1 865 483 5252",
    "sg:postcode":"37830",
    "sg:province":"TN",
    "sg:tags":[
        "renting",
        "truck",
        "leasing"
    ],
    "wof:name":"U-Haul Co",
    "wof:placetype":"venue"
},
  "geometry": {"coordinates":[-84.23890400000001,36.02284],"type":"Point"}
}