{
  "type": "Feature",
  "properties": {
    "iso:country":"US",
    "sg:address":"39 Peter Cave Rd",
    "sg:city":"Lawrenceburg",
    "sg:classifiers":[
        {
            "category":"Shopping",
            "subcategory":"Bicycles & Sporting Goods",
            "type":"Retail Goods"
        }
    ],
    "sg:phone":"+1 931 762 7200",
    "sg:postcode":"38464",
    "sg:province":"TN",
    "sg:tags":[
        "bait",
        "fishing"
    ],
    "wof:name":"Laurel Hill Lake",
    "wof:placetype":"venue"
},
  "geometry": {"coordinates":[-87.55010900000001,35.333609],"type":"Point"}
}