{
  "type": "Feature",
  "properties": {
    "iso:country":"US",
    "sg:address":"801 W Main St",
    "sg:city":"Livingston",
    "sg:classifiers":[
        {
            "category":"Shopping",
            "subcategory":"Music",
            "type":"Retail Goods"
        }
    ],
    "sg:phone":"+1 931 823 9770",
    "sg:postcode":"38570",
    "sg:province":"TN",
    "sg:tags":[
        "compact",
        "record",
        "disc",
        "tape"
    ],
    "wof:name":"Music Factory",
    "wof:placetype":"venue"
},
  "geometry": {"coordinates":[-85.331764,36.379507],"type":"Point"}
}