{
  "type": "Feature",
  "properties": {
    "iso:country":"US",
    "sg:address":"170 Lewis Rd",
    "sg:city":"Medina",
    "sg:classifiers":[
        {
            "category":"Building & Trades",
            "subcategory":"Plumbing",
            "type":"Services"
        }
    ],
    "sg:phone":"+1 731 783 1210",
    "sg:postcode":"38355",
    "sg:province":"TN",
    "sg:tags":[
        "contractor"
    ],
    "wof:name":"Sydnor Construction Co LL",
    "wof:placetype":"venue"
},
  "geometry": {"coordinates":[-88.80642,35.793636],"type":"Point"}
}