{
  "type": "Feature",
  "properties": {
    "iso:country":"US",
    "sg:address":"929 William Blount Dr",
    "sg:city":"Maryville",
    "sg:classifiers":[
        {
            "category":"Travel",
            "subcategory":"Travel Agent",
            "type":"Entertainment"
        }
    ],
    "sg:phone":"+1 865 982 3455",
    "sg:postcode":"37801",
    "sg:province":"TN",
    "sg:tags":[
        "agency"
    ],
    "wof:name":"Executive Travel",
    "wof:placetype":"venue"
},
  "geometry": {"coordinates":[-84.032898,35.730698],"type":"Point"}
}