{
  "type": "Feature",
  "properties": {
    "iso:country":"US",
    "sg:address":"188 16th Ave",
    "sg:city":"Dayton",
    "sg:classifiers":[
        {
            "category":"Health Services",
            "subcategory":"Nursing And Care Facility",
            "type":"Services"
        }
    ],
    "sg:phone":"+1 423 775 1160",
    "sg:postcode":"37321",
    "sg:province":"TN",
    "sg:tags":[
        "medical",
        "intermediate"
    ],
    "wof:name":"Grundy County Primary Care",
    "wof:placetype":"venue"
},
  "geometry": {"coordinates":[-85.001874,35.507923],"type":"Point"}
}