{
  "type": "Feature",
  "properties": {
    "iso:country":"US",
    "sg:address":"9206 Park West Blvd",
    "sg:city":"Knoxville",
    "sg:classifiers":[
        {
            "category":"Banks & Credit Unions",
            "subcategory":"Bank",
            "type":"Services"
        }
    ],
    "sg:phone":"+1 865 521 5310",
    "sg:postcode":"37923",
    "sg:province":"TN",
    "sg:tags":[
        "state",
        "commercial"
    ],
    "wof:name":"AmSouth",
    "wof:placetype":"venue"
},
  "geometry": {"coordinates":[-84.09445599999999,35.918599],"type":"Point"}
}