{
  "type": "Feature",
  "properties": {
    "addr:full":"2080 Old Hillsboro Rd Franklin TN 37064",
    "addr:housenumber":"2080",
    "addr:postcode":"37064",
    "addr:street":"Old Hillsboro Rd",
    "iso:country":"US",
    "sg:address":"2080 Old Hillsboro Rd",
    "sg:city":"Franklin",
    "sg:classifiers":[
        {
            "category":"Professional",
            "type":"Services"
        }
    ],
    "sg:phone":"+1 615 591 0124",
    "sg:postcode":"37064",
    "sg:province":"TN",
    "wof:name":"Marvin Clements",
    "wof:placetype":"venue"
},
  "geometry": {"coordinates":[-86.96848799999999,35.929643],"type":"Point"}
}