{
  "type": "Feature",
  "properties": {
    "addr:full":"177 S Purdue Ave Oak Ridge TN 37830",
    "addr:housenumber":"177",
    "addr:postcode":"37830",
    "addr:street":"S Purdue Ave",
    "iso:country":"US",
    "sg:address":"177 S Purdue Ave",
    "sg:city":"Oak Ridge",
    "sg:classifiers":[
        {
            "category":"Building & Trades",
            "subcategory":"Pest Control",
            "type":"Services"
        }
    ],
    "sg:phone":"+1 865 482 4452",
    "sg:postcode":"37830",
    "sg:province":"TN",
    "wof:name":"Star Pest Control",
    "wof:placetype":"venue"
},
  "geometry": {"coordinates":[-84.244193,36.003907],"type":"Point"}
}