{
  "type": "Feature",
  "properties": {
    "addr:full":"109 Fred King Way Sevierville TN 37876",
    "addr:housenumber":"109",
    "addr:postcode":"37876",
    "addr:street":"Fred King Way",
    "iso:country":"US",
    "sg:address":"109 Fred King Way",
    "sg:city":"Sevierville",
    "sg:classifiers":[
        {
            "category":"Building & Trades",
            "subcategory":"Construction",
            "type":"Services"
        }
    ],
    "sg:phone":"+1 865 429 2239",
    "sg:postcode":"37876",
    "sg:province":"TN",
    "sg:tags":[
        "nonresidential"
    ],
    "wof:name":"McEuoy Sons",
    "wof:placetype":"venue"
},
  "geometry": {"coordinates":[-83.63623800000001,35.859451],"type":"Point"}
}