{
  "type": "Feature",
  "properties": {
    "addr:full":"1056 Mineral Wells Ave Paris TN 38242",
    "addr:housenumber":"1056",
    "addr:postcode":"38242",
    "addr:street":"Mineral Wells Ave",
    "iso:country":"US",
    "sg:address":"1056 Mineral Wells Ave",
    "sg:city":"Paris",
    "sg:classifiers":[
        {
            "category":"Cinema",
            "subcategory":"Movie Rental",
            "type":"Entertainment"
        }
    ],
    "sg:phone":"+1 731 642 1910",
    "sg:postcode":"38242",
    "sg:province":"TN",
    "sg:tags":[
        "leasing",
        "video",
        "disc",
        "tape"
    ],
    "wof:name":"Blockbuster Video",
    "wof:placetype":"venue"
},
  "geometry": {"coordinates":[-88.31181599999999,36.2876],"type":"Point"}
}