{
  "type": "Feature",
  "properties": {
    "addr:full":"485 Industrial Park Rd Piney Flats TN 37686",
    "addr:housenumber":"485",
    "addr:postcode":"37686",
    "addr:street":"Industrial Park Rd",
    "iso:country":"US",
    "sg:address":"485 Industrial Park Rd",
    "sg:city":"Piney Flats",
    "sg:classifiers":[
        {
            "category":"Home & Garden",
            "subcategory":"Building Materials",
            "type":"Retail Goods"
        }
    ],
    "sg:phone":"+1 423 538 5169",
    "sg:postcode":"37686",
    "sg:province":"TN",
    "sg:tags":[
        "roofing"
    ],
    "sg:website":"www.lyonroofing.com",
    "wof:name":"Lyon Roofing & Supply",
    "wof:placetype":"venue"
},
  "geometry": {"coordinates":[-82.29763,36.434033],"type":"Point"}
}