{
  "type": "Feature",
  "properties": {
    "iso:country":"US",
    "sg:address":"191 Church St NE",
    "sg:city":"Cleveland",
    "sg:classifiers":[
        {
            "category":"Banks & Credit Unions",
            "subcategory":"Bank",
            "type":"Services"
        }
    ],
    "sg:phone":"+1 423 478 8270",
    "sg:postcode":"37311",
    "sg:province":"TN",
    "sg:tags":[
        "national"
    ],
    "wof:name":"Bank/First Citizens Bank",
    "wof:placetype":"venue"
},
  "geometry": {"coordinates":[-84.874083,35.160526],"type":"Point"}
}