{
  "type": "Feature",
  "properties": {
    "iso:country":"US",
    "sg:address":"550 E South St",
    "sg:city":"Collierville",
    "sg:classifiers":[
        {
            "category":"Manufacturing",
            "subcategory":"Paper Products",
            "type":"Manufacturing & Wholesale Goods"
        }
    ],
    "sg:phone":"+1 901 853 2800",
    "sg:postcode":"38017",
    "sg:province":"TN",
    "sg:tags":[
        "box",
        "fiber",
        "mfg"
    ],
    "wof:name":"Smurfit-Stone",
    "wof:placetype":"venue"
},
  "geometry": {"coordinates":[-89.650783,35.038822],"type":"Point"}
}