{
  "type": "Feature",
  "properties": {
    "addr:full":"136 S Main St Ridgely TN 38080",
    "addr:housenumber":"136",
    "addr:postcode":"38080",
    "addr:street":"S Main St",
    "iso:country":"US",
    "sg:address":"136 S Main St",
    "sg:city":"Ridgely",
    "sg:classifiers":[
        {
            "category":"Social Services",
            "type":"Services"
        }
    ],
    "sg:phone":"+1 731 264 9929",
    "sg:postcode":"38080",
    "sg:province":"TN",
    "wof:name":"Lake Cnty Multipurpose Sr Citz",
    "wof:placetype":"venue"
},
  "geometry": {"coordinates":[-89.487415,36.263388],"type":"Point"}
}