{
  "type": "Feature",
  "properties": {
    "iso:country":"US",
    "sg:address":"11020 Roane Dr",
    "sg:city":"Knoxville",
    "sg:classifiers":[
        {
            "category":"Organizations",
            "subcategory":"Religious Organization",
            "type":"Services"
        }
    ],
    "sg:phone":"+1 865 966 6728",
    "sg:postcode":"37934",
    "sg:province":"TN",
    "sg:tags":[
        "church"
    ],
    "sg:website":"www.concordumc.com",
    "wof:name":"Concord United Methodist Chr",
    "wof:placetype":"venue"
},
  "geometry": {"coordinates":[-84.14721900000001,35.886605],"type":"Point"}
}