{
  "type": "Feature",
  "properties": {
    "iso:country":"US",
    "sg:address":"376 W Hills Dr",
    "sg:city":"Lenoir City",
    "sg:classifiers":[
        {
            "category":"Food & Beverages",
            "subcategory":"Groceries & Convenience Stores",
            "type":"Retail Goods"
        }
    ],
    "sg:phone":"+1 865 986 9695",
    "sg:postcode":"37771",
    "sg:province":"TN",
    "sg:tags":[
        "grocer"
    ],
    "wof:name":"West Hills Market",
    "wof:placetype":"venue"
},
  "geometry": {"coordinates":[-84.28927,35.797479],"type":"Point"}
}