{
  "type": "Feature",
  "properties": {
    "iso:country":"US",
    "sg:address":"1730 8th Ave N",
    "sg:city":"Nashville",
    "sg:classifiers":[
        {
            "category":"Retail",
            "subcategory":"Auto Repair",
            "type":"Services"
        }
    ],
    "sg:phone":"+1 615 254 1985",
    "sg:postcode":"37208",
    "sg:province":"TN",
    "sg:tags":[
        "shock",
        "brake",
        "tire"
    ],
    "wof:name":"Metro Tire Company Inc",
    "wof:placetype":"venue"
},
  "geometry": {"coordinates":[-86.797135,36.181866],"type":"Point"}
}