{
  "type": "Feature",
  "properties": {
    "addr:full":"2881 Directors Cove Memphis TN 38131",
    "addr:housenumber":"2881",
    "addr:postcode":"38131",
    "addr:street":"Directors Cove",
    "iso:country":"US",
    "sg:address":"2881 Directors Cove",
    "sg:city":"Memphis",
    "sg:classifiers":[
        {
            "category":"Manufacturing",
            "subcategory":"Chemicals & Compounds",
            "type":"Manufacturing & Wholesale Goods"
        }
    ],
    "sg:phone":"+1 901 346 9941",
    "sg:postcode":"38131",
    "sg:province":"TN",
    "sg:tags":[
        "preparation",
        "toilet",
        "mfg"
    ],
    "wof:name":"Estee Lauder",
    "wof:placetype":"venue"
},
  "geometry": {"coordinates":[-89.991309,35.066964],"type":"Point"}
}