{
  "type": "Feature",
  "properties": {
    "addr:full":"68 Doctors Dr Munford TN 38058",
    "addr:housenumber":"68",
    "addr:postcode":"38058",
    "addr:street":"Doctors Dr",
    "iso:country":"US",
    "sg:address":"68 Doctors Dr",
    "sg:city":"Munford",
    "sg:classifiers":[
        {
            "category":"Shopping",
            "subcategory":"Optical Goods",
            "type":"Retail Goods"
        }
    ],
    "sg:phone":"+1 901 837 0188",
    "sg:postcode":"38058",
    "sg:province":"TN",
    "wof:name":"Bierman Whitley & Hughes Od",
    "wof:placetype":"venue"
},
  "geometry": {"coordinates":[-89.79683,35.449354],"type":"Point"}
}