{
  "type": "Feature",
  "properties": {
    "iso:country":"US",
    "sg:address":"826 Rocky Hills Cv S",
    "sg:city":"Cordova",
    "sg:classifiers":[
        {
            "category":"Professional",
            "subcategory":"Advertising",
            "type":"Services"
        }
    ],
    "sg:phone":"+1 901 755 6344",
    "sg:postcode":"38018",
    "sg:province":"TN",
    "sg:tags":[
        "promotion",
        "sale"
    ],
    "wof:name":"Creative Specialties",
    "wof:placetype":"venue"
},
  "geometry": {"coordinates":[-89.75357,35.148473],"type":"Point"}
}