{
  "type": "Feature",
  "properties": {
    "iso:country":"US",
    "sg:address":"4839 Old Hwy 63",
    "sg:city":"Caryville",
    "sg:classifiers":[
        {
            "category":"Education",
            "subcategory":"Library",
            "type":"Public Place"
        }
    ],
    "sg:phone":"+1 423 562 1108",
    "sg:postcode":"37714",
    "sg:province":"TN",
    "wof:name":"Caryville Public Library",
    "wof:placetype":"venue"
},
  "geometry": {"coordinates":[-84.22274,36.303403],"type":"Point"}
}