{
  "type": "Feature",
  "properties": {
    "iso:country":"US",
    "sg:address":"1000 N Cumberland St",
    "sg:city":"Lebanon",
    "sg:classifiers":[
        {
            "category":"Shopping",
            "subcategory":"Music",
            "type":"Retail Goods"
        }
    ],
    "sg:phone":"+1 615 453 9494",
    "sg:postcode":"37087",
    "sg:province":"TN",
    "sg:tags":[
        "video",
        "disc",
        "tape",
        "cassette"
    ],
    "wof:name":"Captain Video",
    "wof:placetype":"venue"
},
  "geometry": {"coordinates":[-86.29025,36.225232],"type":"Point"}
}