{
  "type": "Feature",
  "properties": {
    "iso:country":"US",
    "sg:address":"2302 Dundee Ln",
    "sg:city":"Nashville",
    "sg:classifiers":[
        {
            "category":"Personal",
            "subcategory":"Piercing",
            "type":"Services"
        }
    ],
    "sg:phone":"+1 615 882 9020",
    "sg:postcode":"37214",
    "sg:province":"TN",
    "sg:tags":[
        "body"
    ],
    "wof:name":"Galaxy",
    "wof:placetype":"venue"
},
  "geometry": {"coordinates":[-86.681091,36.200048],"type":"Point"}
}