{
  "type": "Feature",
  "properties": {
    "iso:country":"US",
    "sg:address":"14930 Dayton Pike",
    "sg:city":"Sale Creek",
    "sg:classifiers":[
        {
            "category":"Retail",
            "subcategory":"Auto Repair",
            "type":"Services"
        }
    ],
    "sg:phone":"+1 423 332 3000",
    "sg:postcode":"37373",
    "sg:province":"TN",
    "sg:tags":[
        "automobile",
        "lubrication"
    ],
    "sg:website":"www.victorylane.net",
    "wof:name":"Victory Lane Quick Oil Change",
    "wof:placetype":"venue"
},
  "geometry": {"coordinates":[-85.109784,35.380019],"type":"Point"}
}