{
  "type": "Feature",
  "properties": {
    "iso:country":"US",
    "sg:address":"2927 N Roan St",
    "sg:city":"Johnson City",
    "sg:classifiers":[
        {
            "category":"Restaurant",
            "type":"Food & Drink"
        }
    ],
    "sg:phone":"+1 423 282 8600",
    "sg:postcode":"37601",
    "sg:province":"TN",
    "sg:tags":[
        "eating"
    ],
    "wof:name":"Bello Vita",
    "wof:placetype":"venue"
},
  "geometry": {"coordinates":[-82.38652999999999,36.359119],"type":"Point"}
}