{
  "type": "Feature",
  "properties": {
    "iso:country":"US",
    "sg:address":"104 S Thompson Ave",
    "sg:city":"Oneida",
    "sg:classifiers":[
        {
            "category":"Personal",
            "subcategory":"Barber",
            "type":"Services"
        }
    ],
    "sg:phone":"+1 423 569 6959",
    "sg:postcode":"37841",
    "sg:province":"TN",
    "sg:tags":[
        "shop",
        "beauty"
    ],
    "wof:name":"Mane Attraction",
    "wof:placetype":"venue"
},
  "geometry": {"coordinates":[-84.514675,36.501778],"type":"Point"}
}