{
  "type": "Feature",
  "properties": {
    "iso:country":"US",
    "sg:address":"784 Tigues Creek Rd",
    "sg:city":"Dayton",
    "sg:classifiers":[
        {
            "category":"Building & Trades",
            "subcategory":"Construction",
            "type":"Services"
        }
    ],
    "sg:phone":"+1 423 775 5011",
    "sg:postcode":"37321",
    "sg:province":"TN",
    "sg:tags":[
        "concrete",
        "contractor"
    ],
    "wof:name":"Tennessee Concrete",
    "wof:placetype":"venue"
},
  "geometry": {"coordinates":[-85.06567800000001,35.546699],"type":"Point"}
}