{
  "type": "Feature",
  "properties": {
    "addr:full":"49 Wellington Dr Jackson TN 38305",
    "addr:housenumber":"49",
    "addr:postcode":"38305",
    "addr:street":"Wellington Dr",
    "iso:country":"US",
    "sg:address":"49 Wellington Dr",
    "sg:city":"Jackson",
    "sg:classifiers":[
        {
            "category":"Banks & Credit Unions",
            "subcategory":"Financial Services",
            "type":"Services"
        }
    ],
    "sg:phone":"+1 731 664 3911",
    "sg:postcode":"38305",
    "sg:province":"TN",
    "sg:tags":[
        "trust",
        "management"
    ],
    "wof:name":"Gordon Pierson Trust",
    "wof:placetype":"venue"
},
  "geometry": {"coordinates":[-88.878455,35.689148],"type":"Point"}
}