{
  "type": "Feature",
  "properties": {
    "iso:country":"US",
    "sg:address":"404 E Cherry St",
    "sg:city":"Brownsville",
    "sg:classifiers":[
        {
            "category":"Organizations",
            "subcategory":"Religious Organization",
            "type":"Services"
        }
    ],
    "sg:phone":"+1 731 772 0064",
    "sg:postcode":"38012",
    "sg:province":"TN",
    "sg:tags":[
        "church"
    ],
    "wof:name":"Christ Temple Apostolic Church",
    "wof:placetype":"venue"
},
  "geometry": {"coordinates":[-89.25727,35.600208],"type":"Point"}
}