{
  "type": "Feature",
  "properties": {
    "iso:country":"US",
    "sg:address":"6230 Woodbury Pike",
    "sg:city":"Murfreesboro",
    "sg:classifiers":[
        {
            "category":"Building & Trades",
            "subcategory":"Construction",
            "type":"Services"
        }
    ],
    "sg:phone":"+1 615 405 6089",
    "sg:postcode":"37127",
    "sg:province":"TN",
    "sg:tags":[
        "contractor"
    ],
    "wof:name":"Escobar Masonry",
    "wof:placetype":"venue"
},
  "geometry": {"coordinates":[-86.289704,35.829745],"type":"Point"}
}