{
  "type": "Feature",
  "properties": {
    "addr:full":"201 2nd St South Pittsburg TN 37380",
    "addr:housenumber":"201",
    "addr:postcode":"37380",
    "addr:street":"2Nd St",
    "iso:country":"US",
    "sg:address":"201 2nd St",
    "sg:city":"South Pittsburg",
    "sg:classifiers":[
        {
            "category":"Personal",
            "subcategory":"Beauty Salon",
            "type":"Services"
        }
    ],
    "sg:phone":"+1 423 837 4558",
    "sg:postcode":"37380",
    "sg:province":"TN",
    "wof:name":"B & B Hair Design",
    "wof:placetype":"venue"
},
  "geometry": {"coordinates":[-85.70576800000001,35.014356],"type":"Point"}
}