{
  "type": "Feature",
  "properties": {
    "iso:country":"US",
    "sg:address":"680 Hanley St",
    "sg:city":"Memphis",
    "sg:classifiers":[
        {
            "category":"Social Services",
            "type":"Services"
        }
    ],
    "sg:phone":"+1 901 324 3962",
    "sg:postcode":"38114",
    "sg:province":"TN",
    "sg:tags":[
        "youth",
        "organization",
        "center"
    ],
    "wof:name":"Jabril World Institute-Memphis",
    "wof:placetype":"venue"
},
  "geometry": {"coordinates":[-89.97694199999999,35.113472],"type":"Point"}
}