{
  "type": "Feature",
  "properties": {
    "iso:country":"US",
    "sg:address":"407 Ridgewood Rd",
    "sg:city":"Franklin",
    "sg:classifiers":[
        {
            "category":"Real Estate",
            "subcategory":"Surveying",
            "type":"Services"
        }
    ],
    "sg:phone":"+1 615 794 5030",
    "sg:postcode":"37064",
    "sg:province":"TN",
    "wof:name":"Stanford & Associates",
    "wof:placetype":"venue"
},
  "geometry": {"coordinates":[-86.859059,35.860592],"type":"Point"}
}