{
  "type": "Feature",
  "properties": {
    "iso:country":"US",
    "sg:address":"808 Dickerson Pike",
    "sg:city":"Nashville",
    "sg:classifiers":[
        {
            "category":"Building & Trades",
            "subcategory":"Equipment Rental",
            "type":"Services"
        }
    ],
    "sg:phone":"+1 615 242 3433",
    "sg:postcode":"37207",
    "sg:province":"TN",
    "sg:tags":[
        "yard"
    ],
    "wof:name":"Capitol City Scaffolding & Eqp",
    "wof:placetype":"venue"
},
  "geometry": {"coordinates":[-86.773556,36.18639],"type":"Point"}
}