{
  "type": "Feature",
  "properties": {
    "iso:country":"US",
    "sg:address":"3912 Memphis Dr",
    "sg:city":"Chattanooga",
    "sg:classifiers":[
        {
            "category":"Professional",
            "type":"Services"
        }
    ],
    "sg:phone":"+1 423 875 2197",
    "sg:postcode":"37415",
    "sg:province":"TN",
    "sg:tags":[
        "establishment"
    ],
    "wof:name":"Bobby C Lowe Co",
    "wof:placetype":"venue"
},
  "geometry": {"coordinates":[-85.25363,35.110696],"type":"Point"}
}