{
  "type": "Feature",
  "properties": {
    "iso:country":"US",
    "sg:address":"1245 Sams Creek Rd",
    "sg:city":"Ashland City",
    "sg:classifiers":[
        {
            "category":"Building & Trades",
            "subcategory":"Cleaning & Sanitation",
            "type":"Services"
        }
    ],
    "sg:phone":"+1 615 792 7981",
    "sg:postcode":"37015",
    "sg:province":"TN",
    "sg:tags":[
        "maintenance"
    ],
    "wof:name":"Crouchs Cleaning Svc",
    "wof:placetype":"venue"
},
  "geometry": {"coordinates":[-87.04772800000001,36.216806],"type":"Point"}
}