{
  "type": "Feature",
  "properties": {
    "iso:country":"US",
    "sg:address":"8152 Tatum Creek Rd",
    "sg:city":"Lyles",
    "sg:classifiers":[
        {
            "category":"Manufacturing",
            "subcategory":"Signs",
            "type":"Manufacturing & Wholesale Goods"
        }
    ],
    "sg:phone":"+1 615 242 5751",
    "sg:postcode":"37098",
    "sg:province":"TN",
    "wof:name":"Tom Sanborn Commercial Art",
    "wof:placetype":"venue"
},
  "geometry": {"coordinates":[-87.283596,35.89496],"type":"Point"}
}