{
  "type": "Feature",
  "properties": {
    "iso:country":"US",
    "sg:address":"166 Cessna Cir",
    "sg:city":"Winchester",
    "sg:classifiers":[
        {
            "category":"Wholesale",
            "subcategory":"Machinery & Supplies",
            "type":"Manufacturing & Wholesale Goods"
        }
    ],
    "sg:phone":"+1 931 962 0929",
    "sg:postcode":"37398",
    "sg:province":"TN",
    "sg:tags":[
        "equipment",
        "establishment"
    ],
    "wof:name":"Cultures Beauty Supply & ACC",
    "wof:placetype":"venue"
},
  "geometry": {"coordinates":[-86.070222,35.18481],"type":"Point"}
}