{
  "type": "Feature",
  "properties": {
    "addr:full":"408 Broadway Nashville TN 37203",
    "addr:housenumber":"408",
    "addr:postcode":"37203",
    "addr:street":"Broadway",
    "iso:country":"US",
    "sg:address":"408 Broadway",
    "sg:city":"Nashville",
    "sg:classifiers":[
        {
            "category":"Restaurant",
            "type":"Food & Drink"
        }
    ],
    "sg:phone":"+1 615 254 5452",
    "sg:postcode":"37203",
    "sg:province":"TN",
    "sg:website":"www.tentcorp.com",
    "wof:name":"Bailey's Sports Grille",
    "wof:placetype":"venue"
},
  "geometry": {"coordinates":[-86.777744,36.160873],"type":"Point"}
}