{
  "type": "Feature",
  "properties": {
    "iso:country":"US",
    "sg:address":"5400 Meltech Blvd Memphis",
    "sg:city":"Memphis",
    "sg:classifiers":[
        {
            "category":"Wholesale",
            "subcategory":"Medical Equipment & Supplies",
            "type":"Manufacturing & Wholesale Goods"
        }
    ],
    "sg:phone":"+1 901 541 1360",
    "sg:postcode":"38118",
    "sg:province":"TN",
    "sg:tags":[
        "instrument",
        "surgical"
    ],
    "wof:name":"Sulzer Spine-Tech Inc",
    "wof:placetype":"venue"
},
  "geometry": {"coordinates":[-89.94860799999999,35.00054],"type":"Point"}
}