{
  "type": "Feature",
  "properties": {
    "iso:country":"US",
    "sg:address":"311 Kimberly Ct",
    "sg:city":"Mount Juliet",
    "sg:classifiers":[
        {
            "category":"Building & Trades",
            "subcategory":"Construction",
            "type":"Services"
        }
    ],
    "sg:phone":"+1 615 443 3480",
    "sg:postcode":"37122",
    "sg:province":"TN",
    "sg:tags":[
        "contractor"
    ],
    "wof:name":"Taylor Drywall Co",
    "wof:placetype":"venue"
},
  "geometry": {"coordinates":[-86.46404699999999,36.105126],"type":"Point"}
}