{
  "type": "Feature",
  "properties": {
    "iso:country":"US",
    "sg:address":"1008 Wiley Pardue Rd",
    "sg:city":"Ashland City",
    "sg:classifiers":[
        {
            "category":"Food & Beverages",
            "subcategory":"Groceries & Convenience Stores",
            "type":"Retail Goods"
        }
    ],
    "sg:phone":"+1 615 792 9144",
    "sg:postcode":"37015",
    "sg:province":"TN",
    "sg:tags":[
        "hardware",
        "co"
    ],
    "wof:name":"Lakeview Market & Hardware",
    "wof:placetype":"venue"
},
  "geometry": {"coordinates":[-87.0589,36.236388],"type":"Point"}
}