{
  "type": "Feature",
  "properties": {
    "iso:country":"US",
    "sg:address":"1140 E Northfield Blvd",
    "sg:city":"Murfreesboro",
    "sg:classifiers":[
        {
            "category":"Wholesale",
            "subcategory":"Vending Machines",
            "type":"Manufacturing & Wholesale Goods"
        }
    ],
    "sg:phone":"+1 615 896 0306",
    "sg:postcode":"37130",
    "sg:province":"TN",
    "sg:tags":[
        "operator"
    ],
    "wof:name":"Cw Vending",
    "wof:placetype":"venue"
},
  "geometry": {"coordinates":[-86.36748299999999,35.873423],"type":"Point"}
}