{
  "type": "Feature",
  "properties": {
    "iso:country":"US",
    "sg:address":"1548 Gallatin Pike N",
    "sg:city":"Madison",
    "sg:classifiers":[
        {
            "category":"Banks & Credit Unions",
            "subcategory":"Bank",
            "type":"Services"
        }
    ],
    "sg:phone":"+1 615 865 7998",
    "sg:postcode":"37115",
    "sg:province":"TN",
    "sg:tags":[
        "state",
        "commercial"
    ],
    "wof:name":"First Money Center",
    "wof:placetype":"venue"
},
  "geometry": {"coordinates":[-86.704662,36.287844],"type":"Point"}
}