{
  "type": "Feature",
  "properties": {
    "addr:full":"4550 Maynardville Hwy Maynardville TN 37807",
    "addr:housenumber":"4550",
    "addr:postcode":"37807",
    "addr:street":"Maynardville Hwy",
    "iso:country":"US",
    "sg:address":"4550 Maynardville Hwy",
    "sg:city":"Maynardville",
    "sg:classifiers":[
        {
            "category":"Shopping",
            "subcategory":"Discount & Variety Stores",
            "type":"Retail Goods"
        }
    ],
    "sg:phone":"+1 865 992 3088",
    "sg:postcode":"37807",
    "sg:province":"TN",
    "wof:name":"Dollar General",
    "wof:placetype":"venue"
},
  "geometry": {"coordinates":[-83.777818,36.264723],"type":"Point"}
}