{
  "type": "Feature",
  "properties": {
    "iso:country":"US",
    "sg:address":"1522 Riverview Dr",
    "sg:city":"Murfreesboro",
    "sg:classifiers":[
        {
            "category":"Building & Trades",
            "subcategory":"Construction",
            "type":"Services"
        }
    ],
    "sg:phone":"+1 615 890 6175",
    "sg:postcode":"37129",
    "sg:province":"TN",
    "sg:tags":[
        "house"
    ],
    "wof:name":"Faithway Builders",
    "wof:placetype":"venue"
},
  "geometry": {"coordinates":[-86.41050799999999,35.878105],"type":"Point"}
}