{
  "type": "Feature",
  "properties": {
    "addr:full":"1330 E Andrew Johnson Hwy Greeneville TN 37745",
    "addr:housenumber":"1330",
    "addr:postcode":"37745",
    "addr:street":"E Andrew Johnson Hwy",
    "iso:country":"US",
    "sg:address":"1330 E Andrew Johnson Hwy",
    "sg:city":"Greeneville",
    "sg:classifiers":[
        {
            "category":"Restaurant",
            "type":"Food & Drink"
        }
    ],
    "sg:menulink":"http://www.allmenus.com/tn/greeneville/173181-wendys/menu/",
    "sg:phone":"+1 423 638 3531",
    "sg:postcode":"37745",
    "sg:province":"TN",
    "sg:tags":[
        "burger",
        "american",
        "soup"
    ],
    "wof:name":"Wendy's",
    "wof:placetype":"venue"
},
  "geometry": {"coordinates":[-82.799243,36.176637],"type":"Point"}
}