{
  "type": "Feature",
  "properties": {
    "iso:country":"US",
    "sg:address":"69 N Cleveland St",
    "sg:city":"Memphis",
    "sg:classifiers":[
        {
            "category":"Social Services",
            "type":"Services"
        }
    ],
    "sg:phone":"+1 901 274 0595",
    "sg:postcode":"38104",
    "sg:province":"TN",
    "wof:name":"United People Of Somalia",
    "wof:placetype":"venue"
},
  "geometry": {"coordinates":[-90.016254,35.140343],"type":"Point"}
}