{
  "type": "Feature",
  "properties": {
    "addr:full":"358 Walnut St Memphis TN 38126",
    "addr:housenumber":"358",
    "addr:postcode":"38126",
    "addr:street":"Walnut St",
    "iso:country":"US",
    "sg:address":"358 Walnut St",
    "sg:city":"Memphis",
    "sg:classifiers":[
        {
            "category":"Professional",
            "subcategory":"Engineering",
            "type":"Services"
        }
    ],
    "sg:phone":"+1 901 526 8386",
    "sg:postcode":"38126",
    "sg:province":"TN",
    "sg:tags":[
        "s",
        "architectural",
        "surveying"
    ],
    "wof:name":"Jackson Person and Associates",
    "wof:placetype":"venue"
},
  "geometry": {"coordinates":[-90.03497,35.132012],"type":"Point"}
}