{
  "type": "Feature",
  "properties": {
    "iso:country":"US",
    "sg:address":"1233 Peabody Ave",
    "sg:city":"Memphis",
    "sg:classifiers":[
        {
            "category":"Social Services",
            "type":"Services"
        }
    ],
    "sg:phone":"+1 901 725 6730",
    "sg:postcode":"38104",
    "sg:province":"TN",
    "sg:tags":[
        "organization",
        "welfare"
    ],
    "wof:name":"Loving Arms",
    "wof:placetype":"venue"
},
  "geometry": {"coordinates":[-90.01702400000001,35.132529],"type":"Point"}
}