{
  "type": "Feature",
  "properties": {
    "iso:country":"US",
    "sg:address":"516 N Burns Rd",
    "sg:city":"Knoxville",
    "sg:classifiers":[
        {
            "category":"Building & Trades",
            "subcategory":"Construction",
            "type":"Services"
        }
    ],
    "sg:phone":"+1 865 523 1987",
    "sg:postcode":"37914",
    "sg:province":"TN",
    "sg:tags":[
        "house"
    ],
    "wof:name":"Thomas Bryan Construction",
    "wof:placetype":"venue"
},
  "geometry": {"coordinates":[-83.86532200000001,36.009987],"type":"Point"}
}