{
  "type": "Feature",
  "properties": {
    "iso:country":"US",
    "sg:address":"3678 Middleburg Rd",
    "sg:city":"Decaturville",
    "sg:classifiers":[
        {
            "category":"Manufacturing",
            "subcategory":"Apparel",
            "type":"Manufacturing & Wholesale Goods"
        }
    ],
    "sg:phone":"+1 731 852 2367",
    "sg:postcode":"38329",
    "sg:province":"TN",
    "wof:name":"Pennys Creations",
    "wof:placetype":"venue"
},
  "geometry": {"coordinates":[-88.17606600000001,35.602125],"type":"Point"}
}