{
  "type": "Feature",
  "properties": {
    "iso:country":"US",
    "sg:address":"2754 E Wood St",
    "sg:city":"Paris",
    "sg:classifiers":[
        {
            "category":"Autos & Motor Vehicles",
            "subcategory":"Automobile Sales",
            "type":"Retail Goods"
        }
    ],
    "sg:phone":"+1 731 642 9066",
    "sg:postcode":"38242",
    "sg:province":"TN",
    "sg:tags":[
        "used"
    ],
    "wof:name":"Scotts Auto Country Inc",
    "wof:placetype":"venue"
},
  "geometry": {"coordinates":[-88.272643,36.323498],"type":"Point"}
}