{
  "type": "Feature",
  "properties": {
    "iso:country":"US",
    "sg:address":"411 W Main St",
    "sg:city":"Waverly",
    "sg:classifiers":[
        {
            "category":"Home & Garden",
            "subcategory":"Household Appliances",
            "type":"Retail Goods"
        }
    ],
    "sg:phone":"+1 931 296 3932",
    "sg:postcode":"37185",
    "sg:province":"TN",
    "wof:name":"Discount Center",
    "wof:placetype":"venue"
},
  "geometry": {"coordinates":[-87.801564,36.084053],"type":"Point"}
}