{
  "type": "Feature",
  "properties": {
    "addr:full":"9111 Executive Park Dr NW Knoxville TN 37923",
    "addr:housenumber":"9111",
    "addr:postcode":"37923",
    "addr:street":"Executive Park Dr Nw",
    "iso:country":"US",
    "sg:address":"9111 Executive Park Dr NW",
    "sg:city":"Knoxville",
    "sg:classifiers":[
        {
            "category":"Health Services",
            "subcategory":"Doctor",
            "type":"Services"
        }
    ],
    "sg:phone":"+1 865 539 6219",
    "sg:postcode":"37923",
    "sg:province":"TN",
    "sg:tags":[
        "dentist",
        "clinic"
    ],
    "wof:name":"Dental Associates W Knoxville",
    "wof:placetype":"venue"
},
  "geometry": {"coordinates":[-84.08672799999999,35.92078],"type":"Point"}
}