{
  "type": "Feature",
  "properties": {
    "iso:country":"US",
    "sg:address":"525 S Main St",
    "sg:city":"Memphis",
    "sg:classifiers":[
        {
            "category":"Shopping",
            "subcategory":"Florist",
            "type":"Retail Goods"
        }
    ],
    "sg:phone":"+1 901 525 3323",
    "sg:postcode":"38103",
    "sg:province":"TN",
    "sg:website":"www.gesturesgifts.com",
    "wof:name":"Kim Jameson Design",
    "wof:placetype":"venue"
},
  "geometry": {"coordinates":[-90.05904,35.133864],"type":"Point"}
}