{
  "type": "Feature",
  "properties": {
    "iso:country":"US",
    "sg:address":"7726 US Hwy 51 N",
    "sg:city":"Millington",
    "sg:classifiers":[
        {
            "category":"Travel",
            "subcategory":"Hotels & Motels",
            "type":"Entertainment"
        }
    ],
    "sg:phone":"+1 901 873 2222",
    "sg:postcode":"38053",
    "sg:province":"TN",
    "sg:website":"www.bestwestern.com",
    "wof:name":"Best Western Inn",
    "wof:placetype":"venue"
},
  "geometry": {"coordinates":[-89.91343999999999,35.338198],"type":"Point"}
}