{
  "type": "Feature",
  "properties": {
    "addr:full":"447 Murfreesboro Pike Nashville TN 37210",
    "addr:housenumber":"447",
    "addr:postcode":"37210",
    "addr:street":"Murfreesboro Pike",
    "iso:country":"US",
    "sg:address":"447 Murfreesboro Pike",
    "sg:city":"Nashville",
    "sg:classifiers":[
        {
            "category":"Fast Food",
            "type":"Food & Drink"
        },
        {
            "category":"Restaurant",
            "type":"Food & Drink"
        }
    ],
    "sg:phone":"+1 615 242 2062",
    "sg:postcode":"37210",
    "sg:province":"TN",
    "sg:tags":[
        "chicken",
        "take"
    ],
    "sg:website":"http://www.churchschicken.com",
    "wof:name":"Church's Chicken",
    "wof:placetype":"venue"
},
  "geometry": {"coordinates":[-86.74668800000001,36.143593],"type":"Point"}
}