{
  "type": "Feature",
  "properties": {
    "iso:country":"US",
    "sg:address":"630 Vancurry Ln",
    "sg:city":"Knoxville",
    "sg:classifiers":[
        {
            "category":"Professional",
            "subcategory":"Management & Consulting",
            "type":"Services"
        }
    ],
    "sg:phone":"+1 865 671 4930",
    "sg:postcode":"37934",
    "sg:province":"TN",
    "wof:name":"Gorlo Assoc Inc",
    "wof:placetype":"venue"
},
  "geometry": {"coordinates":[-84.21153,35.88253],"type":"Point"}
}