{
  "type": "Feature",
  "properties": {
    "addr:full":"230 Broadway Hartsville TN 37074",
    "addr:housenumber":"230",
    "addr:postcode":"37074",
    "addr:street":"Broadway",
    "iso:country":"US",
    "sg:address":"230 Broadway",
    "sg:city":"Hartsville",
    "sg:classifiers":[
        {
            "category":"Shopping",
            "subcategory":"Discount & Variety Stores",
            "type":"Retail Goods"
        }
    ],
    "sg:phone":"+1 615 374 0011",
    "sg:postcode":"37074",
    "sg:province":"TN",
    "sg:website":"www.fredsinc.com",
    "wof:name":"Fred's Store",
    "wof:placetype":"venue"
},
  "geometry": {"coordinates":[-86.16555700000001,36.395693],"type":"Point"}
}