{
  "type": "Feature",
  "properties": {
    "addr:full":"6940 Lee Hwy Chattanooga TN 37421",
    "addr:housenumber":"6940",
    "addr:postcode":"37421",
    "addr:street":"Lee Hwy",
    "iso:country":"US",
    "sg:address":"6940 Lee Hwy",
    "sg:city":"Chattanooga",
    "sg:classifiers":[
        {
            "category":"Professional",
            "subcategory":"Accounting & Tax Preparation",
            "type":"Services"
        },
        {
            "category":"Banks & Credit Unions",
            "subcategory":"Bank",
            "type":"Services"
        }
    ],
    "sg:phone":"+1 423 855 0464",
    "sg:postcode":"37421",
    "sg:province":"TN",
    "sg:tags":[
        "company",
        "loan",
        "return",
        "filing"
    ],
    "wof:name":"World Finance Corporation",
    "wof:placetype":"venue"
},
  "geometry": {"coordinates":[-85.16254499999999,35.044728],"type":"Point"}
}