{
  "type": "Feature",
  "properties": {
    "addr:full":"143 4th Ave N Franklin TN 37064",
    "addr:housenumber":"143",
    "addr:postcode":"37064",
    "addr:street":"4Th Ave N",
    "iso:country":"US",
    "sg:address":"143 4th Ave N",
    "sg:city":"Franklin",
    "sg:classifiers":[
        {
            "category":"Health Services",
            "subcategory":"Doctor",
            "type":"Services"
        }
    ],
    "sg:phone":"+1 615 794 0756",
    "sg:postcode":"37064",
    "sg:province":"TN",
    "sg:tags":[
        "dentist"
    ],
    "wof:name":"Lee Palmer DDS PC",
    "wof:placetype":"venue"
},
  "geometry": {"coordinates":[-86.87124300000001,35.925742],"type":"Point"}
}