{
  "type": "Feature",
  "properties": {
    "iso:country":"US",
    "sg:address":"210 Memorial Dr",
    "sg:city":"Bristol",
    "sg:classifiers":[
        {
            "category":"Health Services",
            "subcategory":"Clinic",
            "type":"Services"
        }
    ],
    "sg:phone":"+1 423 573 0695",
    "sg:postcode":"37620",
    "sg:province":"TN",
    "sg:tags":[
        "welfare"
    ],
    "wof:name":"Tri-Cities Regional Health Fairs Inc",
    "wof:placetype":"venue"
},
  "geometry": {"coordinates":[-82.21704200000001,36.594972],"type":"Point"}
}