{
  "type": "Feature",
  "properties": {
    "iso:country":"US",
    "sg:address":"5025 Hillsboro Pike",
    "sg:city":"Nashville",
    "sg:classifiers":[
        {
            "category":"Building & Trades",
            "subcategory":"Landscaping Services",
            "type":"Services"
        }
    ],
    "sg:phone":"+1 615 405 6124",
    "sg:postcode":"37215",
    "sg:province":"TN",
    "sg:tags":[
        "designer",
        "landscape"
    ],
    "wof:name":"Landscape Design Unlimited",
    "wof:placetype":"venue"
},
  "geometry": {"coordinates":[-86.82308500000001,36.097857],"type":"Point"}
}