{
  "type": "Feature",
  "properties": {
    "iso:country":"US",
    "sg:address":"2123 Shannon Dr",
    "sg:city":"Murfreesboro",
    "sg:classifiers":[
        {
            "category":"Real Estate",
            "subcategory":"Real Estate Services",
            "type":"Services"
        }
    ],
    "sg:phone":"+1 615 848 0143",
    "sg:postcode":"37129",
    "sg:province":"TN",
    "sg:tags":[
        "abstract",
        "title"
    ],
    "wof:name":"Stores River Abstracting",
    "wof:placetype":"venue"
},
  "geometry": {"coordinates":[-86.42939200000001,35.891916],"type":"Point"}
}