{
  "type": "Feature",
  "properties": {
    "addr:full":"1382 E Shelby Dr Memphis TN 38116",
    "addr:housenumber":"1382",
    "addr:postcode":"38116",
    "addr:street":"E Shelby Dr",
    "iso:country":"US",
    "sg:address":"1382 E Shelby Dr",
    "sg:city":"Memphis",
    "sg:classifiers":[
        {
            "category":"Professional",
            "type":"Services"
        }
    ],
    "sg:phone":"+1 901 751 2646",
    "sg:postcode":"38116",
    "sg:province":"TN",
    "sg:tags":[
        "establishment"
    ],
    "wof:name":"Simply Splendid",
    "wof:placetype":"venue"
},
  "geometry": {"coordinates":[-90.016751,35.020962],"type":"Point"}
}