{
  "type": "Feature",
  "properties": {
    "addr:full":"102 E Brooks Rd Memphis TN 38109",
    "addr:housenumber":"102",
    "addr:postcode":"38109",
    "addr:street":"E Brooks Rd",
    "iso:country":"US",
    "sg:address":"102 E Brooks Rd",
    "sg:city":"Memphis",
    "sg:classifiers":[
        {
            "category":"Social Services",
            "subcategory":"Child Care",
            "type":"Services"
        }
    ],
    "sg:phone":"+1 901 332 1876",
    "sg:postcode":"38109",
    "sg:province":"TN",
    "sg:tags":[
        "organization",
        "religious",
        "day"
    ],
    "wof:name":"Union Baptist Church",
    "wof:placetype":"venue"
},
  "geometry": {"coordinates":[-90.062217,35.063252],"type":"Point"}
}