{
  "type": "Feature",
  "properties": {
    "iso:country":"US",
    "sg:address":"1959 US Hwy 41 S",
    "sg:city":"Greenbrier",
    "sg:classifiers":[
        {
            "category":"Food & Beverages",
            "subcategory":"Groceries & Convenience Stores",
            "type":"Retail Goods"
        },
        {
            "category":"Wholesale",
            "subcategory":"Farm Supplies",
            "type":"Manufacturing & Wholesale Goods"
        }
    ],
    "sg:phone":"+1 615 643 1301",
    "sg:postcode":"37073",
    "sg:province":"TN",
    "sg:tags":[
        "raw",
        "product",
        "material"
    ],
    "wof:name":"Quick Stop Discount Tobacco",
    "wof:placetype":"venue"
},
  "geometry": {"coordinates":[-86.778639,36.402642],"type":"Point"}
}