{
  "type": "Feature",
  "properties": {
    "addr:full":"7531 Twin Creek Rd Knoxville TN 37920",
    "addr:housenumber":"7531",
    "addr:postcode":"37920",
    "addr:street":"Twin Creek Rd",
    "iso:country":"US",
    "sg:address":"7531 Twin Creek Rd",
    "sg:city":"Knoxville",
    "sg:classifiers":[
        {
            "category":"Wholesale",
            "subcategory":"Machinery & Supplies",
            "type":"Manufacturing & Wholesale Goods"
        },
        {
            "category":"Building & Trades",
            "subcategory":"Plumbing",
            "type":"Services"
        }
    ],
    "sg:phone":"+1 865 573 7267",
    "sg:postcode":"37920",
    "sg:province":"TN",
    "sg:tags":[
        "fire",
        "system",
        "sprinkler",
        "contractor"
    ],
    "wof:name":"Cherokee Sprinkler Company",
    "wof:placetype":"venue"
},
  "geometry": {"coordinates":[-83.898877,35.890601],"type":"Point"}
}