{
  "type": "Feature",
  "properties": {
    "iso:country":"US",
    "sg:address":"167 Hickory Hollow Ter",
    "sg:city":"Antioch",
    "sg:classifiers":[
        {
            "category":"Professional",
            "subcategory":"Business Services",
            "type":"Services"
        }
    ],
    "sg:phone":"+1 615 589 1195",
    "sg:postcode":"37013",
    "sg:province":"TN",
    "sg:tags":[
        "repossessing"
    ],
    "wof:name":"Titan Auto Recovery",
    "wof:placetype":"venue"
},
  "geometry": {"coordinates":[-86.647013,36.050771],"type":"Point"}
}