{
  "type": "Feature",
  "properties": {
    "iso:country":"US",
    "sg:address":"4141 Sango Rd",
    "sg:city":"Clarksville",
    "sg:classifiers":[
        {
            "category":"Building & Trades",
            "subcategory":"Construction",
            "type":"Services"
        }
    ],
    "sg:phone":"+1 931 358 0843",
    "sg:postcode":"37043",
    "sg:province":"TN",
    "sg:tags":[
        "contractor"
    ],
    "wof:name":"D & G Contracting",
    "wof:placetype":"venue"
},
  "geometry": {"coordinates":[-87.18936100000001,36.498449],"type":"Point"}
}