{
  "type": "Feature",
  "properties": {
    "iso:country":"US",
    "sg:address":"2525 Perimeter Place Dr",
    "sg:city":"Nashville",
    "sg:classifiers":[
        {
            "category":"Professional",
            "subcategory":"Business Services",
            "type":"Services"
        }
    ],
    "sg:phone":"+1 615 883 2088",
    "sg:postcode":"37214",
    "sg:province":"TN",
    "sg:tags":[
        "telemarketing"
    ],
    "wof:name":"Centertel Management Group Inc",
    "wof:placetype":"venue"
},
  "geometry": {"coordinates":[-86.679849,36.1487],"type":"Point"}
}