{
  "type": "Feature",
  "properties": {
    "iso:country":"US",
    "sg:address":"905 New Beason Well Rd",
    "sg:city":"Kingsport",
    "sg:classifiers":[
        {
            "category":"Building & Trades",
            "subcategory":"Construction",
            "type":"Services"
        }
    ],
    "sg:phone":"+1 423 245 1618",
    "sg:postcode":"37660",
    "sg:province":"TN",
    "sg:tags":[
        "hanging",
        "contractor"
    ],
    "wof:name":"R&S Painting Inc",
    "wof:placetype":"venue"
},
  "geometry": {"coordinates":[-82.48834100000001,36.560491],"type":"Point"}
}