{
  "type": "Feature",
  "properties": {
    "iso:country":"US",
    "sg:address":"2732 Mossdale Dr",
    "sg:city":"Nashville",
    "sg:classifiers":[
        {
            "category":"Professional",
            "subcategory":"Business Services",
            "type":"Services"
        }
    ],
    "sg:phone":"+1 615 361 0861",
    "sg:postcode":"37217",
    "sg:province":"TN",
    "wof:name":"Wiseman Mac Enterprises",
    "wof:placetype":"venue"
},
  "geometry": {"coordinates":[-86.62455300000001,36.080429],"type":"Point"}
}