{
  "type": "Feature",
  "properties": {
    "iso:country":"US",
    "sg:address":"975 N Germantown Pkwy",
    "sg:city":"Cordova",
    "sg:classifiers":[
        {
            "category":"Shopping",
            "subcategory":"Computers & Home Electronics",
            "type":"Retail Goods"
        }
    ],
    "sg:phone":"+1 901 758 8008",
    "sg:postcode":"38018",
    "sg:province":"TN",
    "sg:tags":[
        "high",
        "fidelity",
        "stereophonic"
    ],
    "wof:name":"Auto Radio",
    "wof:placetype":"venue"
},
  "geometry": {"coordinates":[-89.795281,35.151738],"type":"Point"}
}