{
  "type": "Feature",
  "properties": {
    "iso:country":"US",
    "sg:address":"2824 Treasure Isle W",
    "sg:city":"Memphis",
    "sg:classifiers":[
        {
            "category":"Shopping",
            "type":"Retail Goods"
        }
    ],
    "sg:phone":"+1 901 754 9997",
    "sg:postcode":"38115",
    "sg:province":"TN",
    "sg:tags":[
        "merchandise"
    ],
    "wof:name":"Artistic Framing",
    "wof:placetype":"venue"
},
  "geometry": {"coordinates":[-89.883448,35.072699],"type":"Point"}
}