{
  "type": "Feature",
  "properties": {
    "addr:full":"287 Trivette Rd Mountain City TN 37683",
    "addr:housenumber":"287",
    "addr:postcode":"37683",
    "addr:street":"Trivette Rd",
    "iso:country":"US",
    "sg:address":"287 Trivette Rd",
    "sg:city":"Mountain City",
    "sg:classifiers":[
        {
            "category":"Organizations",
            "subcategory":"Religious Organization",
            "type":"Services"
        }
    ],
    "sg:phone":"+1 423 727 9956",
    "sg:postcode":"37683",
    "sg:province":"TN",
    "sg:tags":[
        "church"
    ],
    "wof:name":"Antioch Baptist Church",
    "wof:placetype":"venue"
},
  "geometry": {"coordinates":[-81.788411,36.453823],"type":"Point"}
}