{
  "type": "Feature",
  "properties": {
    "iso:country":"US",
    "sg:address":"1576 S White Station Rd",
    "sg:city":"Memphis",
    "sg:classifiers":[
        {
            "category":"Shopping",
            "subcategory":"Bicycles & Sporting Goods",
            "type":"Retail Goods"
        }
    ],
    "sg:phone":"+1 901 684 7467",
    "sg:postcode":"38117",
    "sg:province":"TN",
    "sg:tags":[
        "apparel",
        "equipment",
        "accessory",
        "bowling"
    ],
    "wof:name":"Bowling Difference Proshop",
    "wof:placetype":"venue"
},
  "geometry": {"coordinates":[-89.89211,35.088882],"type":"Point"}
}