{
  "type": "Feature",
  "properties": {
    "iso:country":"US",
    "sg:address":"3214 Peoples St",
    "sg:city":"Johnson City",
    "sg:classifiers":[
        {
            "category":"Restaurant",
            "type":"Food & Drink"
        }
    ],
    "sg:menulink":"http://www.allmenus.com/tn/johnson-city/95108-ihop/menu/",
    "sg:phone":"+1 423 952 0213",
    "sg:postcode":"37604",
    "sg:province":"TN",
    "sg:tags":[
        "sandwich",
        "salad",
        "burger",
        "soup",
        "american",
        "steakhouse",
        "wrap"
    ],
    "wof:name":"IHOP",
    "wof:placetype":"venue"
},
  "geometry": {"coordinates":[-82.399928,36.349602],"type":"Point"}
}