{
  "type": "Feature",
  "properties": {
    "iso:country":"US",
    "sg:address":"166 W Main St",
    "sg:city":"Morristown",
    "sg:classifiers":[
        {
            "category":"Shopping",
            "subcategory":"Clothing, Apparel, & Fashions",
            "type":"Retail Goods"
        }
    ],
    "sg:phone":"+1 423 587 1831",
    "sg:postcode":"37814",
    "sg:province":"TN",
    "sg:tags":[
        "jewelry",
        "costume",
        "lease"
    ],
    "wof:name":"Trinkets & Treasures",
    "wof:placetype":"venue"
},
  "geometry": {"coordinates":[-83.293317,36.213406],"type":"Point"}
}