{
  "type": "Feature",
  "properties": {
    "addr:full":"5426 Main St Spring Hill TN 37174",
    "addr:housenumber":"5426",
    "addr:postcode":"37174",
    "addr:street":"Main St",
    "iso:country":"US",
    "sg:address":"5426 Main St",
    "sg:city":"Spring Hill",
    "sg:classifiers":[
        {
            "category":"Professional",
            "type":"Services"
        }
    ],
    "sg:phone":"+1 931 490 7951",
    "sg:postcode":"37174",
    "sg:province":"TN",
    "sg:tags":[
        "establishment"
    ],
    "wof:name":"Parker Co Inc",
    "wof:placetype":"venue"
},
  "geometry": {"coordinates":[-86.938346,35.744592],"type":"Point"}
}