{
  "type": "Feature",
  "properties": {
    "iso:country":"US",
    "sg:address":"1608 E Wolf Valley Rd",
    "sg:city":"Heiskell",
    "sg:classifiers":[
        {
            "category":"Building & Trades",
            "subcategory":"Construction",
            "type":"Services"
        }
    ],
    "sg:phone":"+1 865 463 0377",
    "sg:postcode":"37754",
    "sg:province":"TN",
    "sg:tags":[
        "carpentry",
        "contractor"
    ],
    "wof:name":"Fisher Construction",
    "wof:placetype":"venue"
},
  "geometry": {"coordinates":[-84.082551,36.088139],"type":"Point"}
}