{
  "type": "Feature",
  "properties": {
    "iso:country":"US",
    "sg:address":"2020 Tiprell Rd",
    "sg:city":"Cumberland Gap",
    "sg:classifiers":[
        {
            "category":"Professional",
            "subcategory":"Business Services",
            "type":"Services"
        }
    ],
    "sg:phone":"+1 423 869 5380",
    "sg:postcode":"37724",
    "sg:province":"TN",
    "wof:name":"E & E Enterprises Inc",
    "wof:placetype":"venue"
},
  "geometry": {"coordinates":[-83.667548,36.552507],"type":"Point"}
}