{
  "type": "Feature",
  "properties": {
    "iso:country":"US",
    "sg:address":"6426 Baum Dr",
    "sg:city":"Knoxville",
    "sg:classifiers":[
        {
            "category":"Real Estate",
            "subcategory":"Real Estate Operator",
            "type":"Services"
        }
    ],
    "sg:phone":"+1 865 212 4909",
    "sg:postcode":"37919",
    "sg:province":"TN",
    "sg:tags":[
        "apartment"
    ],
    "wof:name":"Associate Property Management",
    "wof:placetype":"venue"
},
  "geometry": {"coordinates":[-84.006564,35.927771],"type":"Point"}
}