{
  "type": "Feature",
  "properties": {
    "iso:country":"US",
    "sg:address":"15 Congress Pkwy NW",
    "sg:city":"Athens",
    "sg:classifiers":[
        {
            "category":"Retail",
            "subcategory":"Car Wash",
            "type":"Services"
        }
    ],
    "sg:phone":"+1 423 507 7647",
    "sg:postcode":"37303",
    "sg:province":"TN",
    "sg:tags":[
        "automobile",
        "detail",
        "clean"
    ],
    "wof:name":"Majestic Car Care",
    "wof:placetype":"venue"
},
  "geometry": {"coordinates":[-84.606075,35.467394],"type":"Point"}
}