{
  "type": "Feature",
  "properties": {
    "iso:country":"US",
    "sg:address":"3422 Parkway",
    "sg:city":"Pigeon Forge",
    "sg:classifiers":[
        {
            "category":"Manufacturing",
            "subcategory":"Signs",
            "type":"Manufacturing & Wholesale Goods"
        }
    ],
    "sg:phone":"+1 865 429 7603",
    "sg:postcode":"37863",
    "sg:province":"TN",
    "wof:name":"B & B Creative Wood Designs",
    "wof:placetype":"venue"
},
  "geometry": {"coordinates":[-83.55493300000001,35.787606],"type":"Point"}
}