{
  "type": "Feature",
  "properties": {
    "addr:full":"300 E M L King Blvd Chattanooga TN 37403",
    "addr:housenumber":"300",
    "addr:postcode":"37403",
    "addr:street":"E M L King Blvd",
    "iso:country":"US",
    "sg:address":"300 E M L King Blvd",
    "sg:city":"Chattanooga",
    "sg:classifiers":[
        {
            "category":"Professional",
            "subcategory":"Advertising",
            "type":"Services"
        }
    ],
    "sg:phone":"+1 423 267 6220",
    "sg:postcode":"37403",
    "sg:province":"TN",
    "sg:tags":[
        "mail"
    ],
    "sg:website":"www.advo.com",
    "wof:name":"ADVO Inc",
    "wof:placetype":"venue"
},
  "geometry": {"coordinates":[-85.30481399999999,35.044473],"type":"Point"}
}