{
  "type": "Feature",
  "properties": {
    "addr:full":"222 W Bockman Way Sparta TN 38583",
    "addr:housenumber":"222",
    "addr:postcode":"38583",
    "addr:street":"W Bockman Way",
    "iso:country":"US",
    "sg:address":"222 W Bockman Way",
    "sg:city":"Sparta",
    "sg:classifiers":[
        {
            "category":"Shopping",
            "subcategory":"Used Merchandise",
            "type":"Retail Goods"
        }
    ],
    "sg:phone":"+1 931 837 2805",
    "sg:postcode":"38583",
    "sg:province":"TN",
    "sg:tags":[
        "antique"
    ],
    "wof:name":"Brasel's Antiques & Cllctbls",
    "wof:placetype":"venue"
},
  "geometry": {"coordinates":[-85.46874099999999,35.927515],"type":"Point"}
}