{
  "type": "Feature",
  "properties": {
    "addr:full":"123 Baker Rd Tellico Plains TN 37385",
    "addr:housenumber":"123",
    "addr:postcode":"37385",
    "addr:street":"Baker Rd",
    "iso:country":"US",
    "sg:address":"123 Baker Rd",
    "sg:city":"Tellico Plains",
    "sg:classifiers":[
        {
            "category":"Retail",
            "subcategory":"Auto Repair",
            "type":"Services"
        }
    ],
    "sg:phone":"+1 423 253 2621",
    "sg:postcode":"37385",
    "sg:province":"TN",
    "sg:tags":[
        "transmission",
        "general"
    ],
    "wof:name":"Huey's Transmission",
    "wof:placetype":"venue"
},
  "geometry": {"coordinates":[-84.239166,35.423481],"type":"Point"}
}