{
  "type": "Feature",
  "properties": {
    "addr:full":"4147 Callie Powell Cove Memphis TN 38135",
    "addr:housenumber":"4147",
    "addr:postcode":"38135",
    "addr:street":"Callie Powell Cove",
    "iso:country":"US",
    "sg:address":"4147 Callie Powell Cove",
    "sg:city":"Memphis",
    "sg:classifiers":[
        {
            "category":"Professional",
            "subcategory":"Advertising",
            "type":"Services"
        }
    ],
    "sg:phone":"+1 901 379 9991",
    "sg:postcode":"38135",
    "sg:province":"TN",
    "sg:tags":[
        "representative"
    ],
    "wof:name":"Memphis Tennessee FM Group",
    "wof:placetype":"venue"
},
  "geometry": {"coordinates":[-89.838599,35.238593],"type":"Point"}
}