{
  "type": "Feature",
  "properties": {
    "addr:full":"16 Dollar Rd Humboldt TN 38343",
    "addr:housenumber":"16",
    "addr:postcode":"38343",
    "addr:street":"Dollar Rd",
    "iso:country":"US",
    "sg:address":"16 Dollar Rd",
    "sg:city":"Humboldt",
    "sg:classifiers":[
        {
            "category":"Organizations",
            "subcategory":"Religious Organization",
            "type":"Services"
        }
    ],
    "sg:phone":"+1 731 787 7257",
    "sg:postcode":"38343",
    "sg:province":"TN",
    "sg:tags":[
        "church"
    ],
    "wof:name":"Smyrna Baptist Church Inc",
    "wof:placetype":"venue"
},
  "geometry": {"coordinates":[-88.85825,35.851092],"type":"Point"}
}