{
  "type": "Feature",
  "properties": {
    "addr:full":"2204 Midway St Johnson City TN 37601",
    "addr:housenumber":"2204",
    "addr:postcode":"37601",
    "addr:street":"Midway St",
    "iso:country":"US",
    "sg:address":"2204 Midway St",
    "sg:city":"Johnson City",
    "sg:classifiers":[
        {
            "category":"Organizations",
            "subcategory":"Religious Organization",
            "type":"Services"
        }
    ],
    "sg:phone":"+1 423 928 2032",
    "sg:postcode":"37601",
    "sg:province":"TN",
    "wof:name":"John R Davidson Rev",
    "wof:placetype":"venue"
},
  "geometry": {"coordinates":[-82.33237699999999,36.345761],"type":"Point"}
}