{
  "type": "Feature",
  "properties": {
    "iso:country":"US",
    "sg:address":"620 State St",
    "sg:city":"Bristol",
    "sg:classifiers":[
        {
            "category":"Shopping",
            "subcategory":"Used Merchandise",
            "type":"Retail Goods"
        },
        {
            "category":"Wholesale",
            "subcategory":"Durable Goods & Equipment",
            "type":"Manufacturing & Wholesale Goods"
        }
    ],
    "sg:phone":"+1 423 764 4211",
    "sg:postcode":"37620",
    "sg:province":"TN",
    "sg:tags":[
        "antique"
    ],
    "wof:name":"Antiques Unlimited Inc",
    "wof:placetype":"venue"
},
  "geometry": {"coordinates":[-82.184777,36.594975],"type":"Point"}
}