{
  "type": "Feature",
  "properties": {
    "iso:country":"US",
    "sg:address":"8702 Somerset Ln",
    "sg:city":"Germantown",
    "sg:classifiers":[
        {
            "category":"Health Services",
            "subcategory":"Doctor",
            "type":"Services"
        }
    ],
    "sg:phone":"+1 901 624 0766",
    "sg:postcode":"38138",
    "sg:province":"TN",
    "sg:tags":[
        "medical"
    ],
    "wof:name":"Anant V Shah MD PC",
    "wof:placetype":"venue"
},
  "geometry": {"coordinates":[-89.772823,35.074073],"type":"Point"}
}