{
  "type": "Feature",
  "properties": {
    "addr:full":"1431 Harrison Rd Murfreesboro TN 37128",
    "addr:housenumber":"1431",
    "addr:postcode":"37128",
    "addr:street":"Harrison Rd",
    "iso:country":"US",
    "sg:address":"1431 Harrison Rd",
    "sg:city":"Murfreesboro",
    "sg:classifiers":[
        {
            "category":"Organizations",
            "subcategory":"Community Association",
            "type":"Services"
        }
    ],
    "sg:phone":"+1 615 890 6639",
    "sg:postcode":"37128",
    "sg:province":"TN",
    "wof:name":"Special Military Active",
    "wof:placetype":"venue"
},
  "geometry": {"coordinates":[-86.450925,35.751168],"type":"Point"}
}