{
  "type": "Feature",
  "properties": {
    "iso:country":"US",
    "sg:address":"306 White Bridge Pike",
    "sg:city":"Nashville",
    "sg:classifiers":[
        {
            "category":"Building & Trades",
            "subcategory":"Pest Control",
            "type":"Services"
        }
    ],
    "sg:phone":"+1 615 354 8824",
    "sg:postcode":"37209",
    "sg:province":"TN",
    "wof:name":"Ortex Systems Inc",
    "wof:placetype":"venue"
},
  "geometry": {"coordinates":[-86.85784099999999,36.147991],"type":"Point"}
}