{
  "type": "Feature",
  "properties": {
    "addr:full":"4037 Beersheba Hwy Mc Minnville TN 37110",
    "addr:housenumber":"4037",
    "addr:postcode":"37110",
    "addr:street":"Beersheba Hwy Mc Minnville",
    "iso:country":"US",
    "sg:address":"4037 Beersheba Hwy",
    "sg:city":"Mc Minnville",
    "sg:classifiers":[
        {
            "category":"Farming",
            "subcategory":"Nursery",
            "type":"Manufacturing & Wholesale Goods"
        },
        {
            "category":"Home & Garden",
            "subcategory":"Garden Supply",
            "type":"Retail Goods"
        }
    ],
    "sg:phone":"+1 931 692 3771",
    "sg:postcode":"37110",
    "sg:province":"TN",
    "sg:tags":[
        "ornamental",
        "nurseryman"
    ],
    "wof:name":"Little River Nursery Co",
    "wof:placetype":"venue"
},
  "geometry": {"coordinates":[-85.722934,35.64395],"type":"Point"}
}