{
  "type": "Feature",
  "properties": {
    "addr:full":"201 Bluff Springs Rd Mc Minnville TN 37110",
    "addr:housenumber":"201",
    "addr:postcode":"37110",
    "addr:street":"Bluff Springs Rd",
    "iso:country":"US",
    "sg:address":"201 Bluff Springs Rd",
    "sg:city":"Mc Minnville",
    "sg:classifiers":[
        {
            "category":"Education",
            "subcategory":"School",
            "type":"Public Place"
        }
    ],
    "sg:phone":"+1 931 668 4092",
    "sg:postcode":"37110",
    "sg:province":"TN",
    "wof:name":"McMinnville SDA School",
    "wof:placetype":"venue"
},
  "geometry": {"coordinates":[-85.76465,35.716778],"type":"Point"}
}