{
  "type": "Feature",
  "properties": {
    "addr:full":"3524 Murphy Rd Nashville TN 37205",
    "addr:housenumber":"3524",
    "addr:postcode":"37205",
    "addr:street":"Murphy Rd",
    "iso:country":"US",
    "sg:address":"3524 Murphy Rd",
    "sg:city":"Nashville",
    "sg:classifiers":[
        {
            "category":"Restaurant",
            "type":"Food & Drink"
        }
    ],
    "sg:phone":"+1 615 479 5600",
    "sg:postcode":"37205",
    "sg:province":"TN",
    "sg:tags":[
        "caterer"
    ],
    "wof:name":"JSP Creations",
    "wof:placetype":"venue"
},
  "geometry": {"coordinates":[-86.82544900000001,36.139953],"type":"Point"}
}