{
  "type": "Feature",
  "properties": {
    "iso:country":"US",
    "sg:address":"140 Johnson Cir",
    "sg:city":"Clinton",
    "sg:classifiers":[
        {
            "category":"Building & Trades",
            "subcategory":"Construction",
            "type":"Services"
        }
    ],
    "sg:phone":"+1 865 457 5362",
    "sg:postcode":"37716",
    "sg:province":"TN",
    "sg:tags":[
        "hanging",
        "contractor"
    ],
    "wof:name":"CM Painting",
    "wof:placetype":"venue"
},
  "geometry": {"coordinates":[-84.186666,36.056235],"type":"Point"}
}