{
  "type": "Feature",
  "properties": {
    "iso:country":"US",
    "sg:address":"263 Pressley Rd",
    "sg:city":"Vonore",
    "sg:classifiers":[
        {
            "category":"Autos & Motor Vehicles",
            "subcategory":"Boat Sales",
            "type":"Retail Goods"
        }
    ],
    "sg:phone":"+1 423 884 3400",
    "sg:postcode":"37885",
    "sg:province":"TN",
    "sg:tags":[
        "dealer",
        "sales"
    ],
    "wof:name":"Bear Mountain Marine LLC",
    "wof:placetype":"venue"
},
  "geometry": {"coordinates":[-84.273824,35.59316],"type":"Point"}
}