{
  "type": "Feature",
  "properties": {
    "addr:full":"200 E Broadway St Lenoir City TN 37771",
    "addr:housenumber":"200",
    "addr:postcode":"37771",
    "addr:street":"E Broadway St",
    "iso:country":"US",
    "sg:address":"200 E Broadway St",
    "sg:city":"Lenoir City",
    "sg:classifiers":[
        {
            "category":"Professional",
            "subcategory":"Lawyer & Legal Services",
            "type":"Services"
        }
    ],
    "sg:phone":"+1 865 986 3552",
    "sg:postcode":"37771",
    "sg:province":"TN",
    "sg:tags":[
        "attorney"
    ],
    "wof:name":"Terry G Vann",
    "wof:placetype":"venue"
},
  "geometry": {"coordinates":[-84.263971,35.792251],"type":"Point"}
}