{
  "type": "Feature",
  "properties": {
    "addr:full":"2 International Plz Nashville TN 37217",
    "addr:housenumber":"2",
    "addr:postcode":"37217",
    "addr:street":"International Plz",
    "iso:country":"US",
    "sg:address":"2 International Plz",
    "sg:city":"Nashville",
    "sg:classifiers":[
        {
            "category":"Professional",
            "subcategory":"Engineering",
            "type":"Services"
        }
    ],
    "sg:phone":"+1 615 399 8991",
    "sg:postcode":"37217",
    "sg:province":"TN",
    "wof:name":"Cmd",
    "wof:placetype":"venue"
},
  "geometry": {"coordinates":[-86.693454,36.126792],"type":"Point"}
}