{
  "type": "Feature",
  "properties": {
    "addr:full":"8325 US Hwy 64 Memphis TN 38133",
    "addr:housenumber":"8325",
    "addr:postcode":"38133",
    "addr:street":"Us Hwy 64",
    "iso:country":"US",
    "sg:address":"8325 US Hwy 64",
    "sg:city":"Memphis",
    "sg:classifiers":[
        {
            "category":"Restaurant",
            "type":"Food & Drink"
        }
    ],
    "sg:phone":"+1 901 372 2539",
    "sg:postcode":"38133",
    "sg:province":"TN",
    "wof:name":"TGI Friday's",
    "wof:placetype":"venue"
},
  "geometry": {"coordinates":[-89.78739299999999,35.204415],"type":"Point"}
}