{
  "type": "Feature",
  "properties": {
    "iso:country":"US",
    "sg:address":"7217 Clinton Hwy",
    "sg:city":"Powell",
    "sg:classifiers":[
        {
            "category":"Shopping",
            "subcategory":"Tobacco",
            "type":"Retail Goods"
        },
        {
            "category":"Manufacturing",
            "subcategory":"Tobacco Products",
            "type":"Manufacturing & Wholesale Goods"
        }
    ],
    "sg:phone":"+1 865 947 3788",
    "sg:postcode":"37849",
    "sg:province":"TN",
    "sg:tags":[
        "cigarette",
        "cigar",
        "dealer",
        "mfg"
    ],
    "wof:name":"Smoky Mountain Smokes",
    "wof:placetype":"venue"
},
  "geometry": {"coordinates":[-84.04257,36.015279],"type":"Point"}
}