{
  "type": "Feature",
  "properties": {
    "addr:full":"103 Memorial Dr Goodlettsville TN 37072",
    "addr:housenumber":"103",
    "addr:postcode":"37072",
    "addr:street":"Memorial Dr",
    "iso:country":"US",
    "sg:address":"103 Memorial Dr",
    "sg:city":"Goodlettsville",
    "sg:classifiers":[
        {
            "category":"Professional",
            "subcategory":"Printing & Photocopies",
            "type":"Services"
        }
    ],
    "sg:phone":"+1 615 851 3915",
    "sg:postcode":"37072",
    "sg:province":"TN",
    "sg:tags":[
        "duplicating",
        "copying"
    ],
    "wof:name":"Giant Photos Of Tn",
    "wof:placetype":"venue"
},
  "geometry": {"coordinates":[-86.71452499999999,36.320971],"type":"Point"}
}