{
  "type": "Feature",
  "properties": {
    "iso:country":"US",
    "sg:address":"3891 Oak Forest Dr",
    "sg:city":"Memphis",
    "sg:classifiers":[
        {
            "category":"Manufacturing",
            "subcategory":"Chemicals & Compounds",
            "type":"Manufacturing & Wholesale Goods"
        },
        {
            "category":"Autos & Motor Vehicles",
            "subcategory":"Auto Supplies",
            "type":"Retail Goods"
        },
        {
            "category":"Manufacturing",
            "subcategory":"Petroleum Products",
            "type":"Manufacturing & Wholesale Goods"
        }
    ],
    "sg:phone":"+1 901 373 4228",
    "sg:postcode":"38135",
    "sg:province":"TN",
    "sg:tags":[
        "lubricant",
        "oils-synthetic",
        "oil",
        "lubricating"
    ],
    "sg:website":"http://www.lubedealer.com/oilsplus",
    "wof:name":"AMSOIL Products Distributor",
    "wof:placetype":"venue"
},
  "geometry": {"coordinates":[-89.855698,35.232269],"type":"Point"}
}