{
  "type": "Feature",
  "properties": {
    "iso:country":"US",
    "sg:address":"1180 Corn Tassel Rd",
    "sg:city":"Vonore",
    "sg:classifiers":[
        {
            "category":"Food & Beverages",
            "subcategory":"Groceries & Convenience Stores",
            "type":"Retail Goods"
        }
    ],
    "sg:phone":"+1 423 884 6378",
    "sg:postcode":"37885",
    "sg:province":"TN",
    "sg:tags":[
        "station",
        "gasoline"
    ],
    "wof:name":"Rasar Landing",
    "wof:placetype":"venue"
},
  "geometry": {"coordinates":[-84.239469,35.535497],"type":"Point"}
}