{
  "type": "Feature",
  "properties": {
    "iso:country":"US",
    "sg:address":"356 Sanderson St",
    "sg:city":"Alcoa",
    "sg:classifiers":[
        {
            "category":"Building & Trades",
            "subcategory":"Construction",
            "type":"Services"
        }
    ],
    "sg:phone":"+1 865 977 0769",
    "sg:postcode":"37701",
    "sg:province":"TN",
    "sg:tags":[
        "contractor"
    ],
    "wof:name":"Jim White Builders Inc",
    "wof:placetype":"venue"
},
  "geometry": {"coordinates":[-83.975498,35.761373],"type":"Point"}
}