{
  "type": "Feature",
  "properties": {
    "addr:full":"3255 Austin Peay Hwy Memphis TN 38128",
    "addr:housenumber":"3255",
    "addr:postcode":"38128",
    "addr:street":"Austin Peay Hwy",
    "iso:country":"US",
    "sg:address":"3255 Austin Peay Hwy",
    "sg:city":"Memphis",
    "sg:classifiers":[
        {
            "category":"Restaurant",
            "type":"Food & Drink"
        }
    ],
    "sg:menulink":"http://www.allmenus.com/tn/memphis/176868-kfc---kentucky-fried-chicken/menu/",
    "sg:phone":"+1 901 382 3520",
    "sg:postcode":"38128",
    "sg:province":"TN",
    "sg:tags":[
        "american",
        "chicken"
    ],
    "wof:name":"KFC - Kentucky Fried Chicken",
    "wof:placetype":"venue"
},
  "geometry": {"coordinates":[-89.916296,35.214756],"type":"Point"}
}