{
  "type": "Feature",
  "properties": {
    "addr:full":"3696 Battlefield Cv Memphis TN 38128",
    "addr:housenumber":"3696",
    "addr:postcode":"38128",
    "addr:street":"Battlefield Cv",
    "iso:country":"US",
    "sg:address":"3696 Battlefield Cv",
    "sg:city":"Memphis",
    "sg:classifiers":[
        {
            "category":"Manufacturing",
            "subcategory":"Buildings",
            "type":"Manufacturing & Wholesale Goods"
        },
        {
            "category":"Building & Trades",
            "subcategory":"Construction",
            "type":"Services"
        }
    ],
    "sg:phone":"+1 901 386 8720",
    "sg:postcode":"38128",
    "sg:province":"TN",
    "sg:tags":[
        "home",
        "builder",
        "contractor"
    ],
    "wof:name":"Watson & Burchett Concrete Construction Company",
    "wof:placetype":"venue"
},
  "geometry": {"coordinates":[-89.92724200000001,35.227286],"type":"Point"}
}