{
  "type": "Feature",
  "properties": {
    "iso:country":"US",
    "sg:address":"1427 Canterbury Ct",
    "sg:city":"Murfreesboro",
    "sg:classifiers":[
        {
            "category":"Wholesale",
            "subcategory":"Stationery",
            "type":"Manufacturing & Wholesale Goods"
        }
    ],
    "sg:phone":"+1 615 494 3171",
    "sg:postcode":"37130",
    "sg:province":"TN",
    "sg:tags":[
        "packaging",
        "material"
    ],
    "wof:name":"Bemis",
    "wof:placetype":"venue"
},
  "geometry": {"coordinates":[-86.37066799999999,35.817348],"type":"Point"}
}