{
  "type": "Feature",
  "properties": {
    "iso:country":"US",
    "sg:address":"1230 State St",
    "sg:city":"White Pine",
    "sg:classifiers":[
        {
            "category":"Autos & Motor Vehicles",
            "subcategory":"Automobile Sales",
            "type":"Retail Goods"
        }
    ],
    "sg:phone":"+1 865 674 6248",
    "sg:postcode":"37890",
    "sg:province":"TN",
    "sg:tags":[
        "car",
        "dealer"
    ],
    "wof:name":"Brian Ramsey Used Cars",
    "wof:placetype":"venue"
},
  "geometry": {"coordinates":[-83.283474,36.108647],"type":"Point"}
}