{
  "type": "Feature",
  "properties": {
    "addr:full":"625 Pumphouse Rd Rockwood TN 37854",
    "addr:housenumber":"625",
    "addr:postcode":"37854",
    "addr:street":"Pumphouse Rd",
    "iso:country":"US",
    "sg:address":"625 Pumphouse Rd",
    "sg:city":"Rockwood",
    "sg:classifiers":[
        {
            "category":"Education",
            "subcategory":"School",
            "type":"Public Place"
        }
    ],
    "sg:phone":"+1 865 354 2111",
    "sg:postcode":"37854",
    "sg:province":"TN",
    "wof:name":"Ridge View Elementary School",
    "wof:placetype":"venue"
},
  "geometry": {"coordinates":[-84.687106,35.855378],"type":"Point"}
}