{
  "type": "Feature",
  "properties": {
    "iso:country":"US",
    "sg:address":"6325 E Brainerd Rd",
    "sg:city":"Chattanooga",
    "sg:classifiers":[
        {
            "category":"Insurance",
            "subcategory":"Insurance Agent",
            "type":"Services"
        },
        {
            "category":"Insurance",
            "subcategory":"Hazard Insurance",
            "type":"Services"
        },
        {
            "category":"Insurance",
            "subcategory":"Title Insurance",
            "type":"Services"
        },
        {
            "category":"Insurance",
            "subcategory":"Life Insurance",
            "type":"Services"
        }
    ],
    "sg:phone":"+1 423 933 2166",
    "sg:postcode":"37421",
    "sg:province":"TN",
    "sg:tags":[
        "business",
        "auto",
        "commercial",
        "homeowner",
        "motorcycle",
        "renter"
    ],
    "wof:name":"Allstate Insurance Company - Esther Suggs",
    "wof:placetype":"venue"
},
  "geometry": {"coordinates":[-85.197073,35.017107],"type":"Point"}
}