{
  "type": "Feature",
  "properties": {
    "addr:full":"6709 Kingston Pike Knoxville TN 37919",
    "addr:housenumber":"6709",
    "addr:postcode":"37919",
    "addr:street":"Kingston Pike",
    "iso:country":"US",
    "sg:address":"6709 Kingston Pike",
    "sg:city":"Knoxville",
    "sg:classifiers":[
        {
            "category":"Retail",
            "subcategory":"Repair Shop",
            "type":"Services"
        }
    ],
    "sg:phone":"+1 865 909 0080",
    "sg:postcode":"37919",
    "sg:province":"TN",
    "sg:tags":[
        "upholsterer"
    ],
    "wof:name":"Special Touch Upholstery",
    "wof:placetype":"venue"
},
  "geometry": {"coordinates":[-84.01651099999999,35.93247],"type":"Point"}
}