{
  "type": "Feature",
  "properties": {
    "iso:country":"US",
    "sg:address":"140 Forrest Ct",
    "sg:city":"Ashland City",
    "sg:classifiers":[
        {
            "category":"Professional",
            "subcategory":"Advertising",
            "type":"Services"
        }
    ],
    "sg:phone":"+1 615 792 1718",
    "sg:postcode":"37015",
    "sg:province":"TN",
    "sg:tags":[
        "distribution"
    ],
    "wof:name":"VWR Intl",
    "wof:placetype":"venue"
},
  "geometry": {"coordinates":[-87.04834700000001,36.267129],"type":"Point"}
}