{
  "type": "Feature",
  "properties": {
    "addr:full":"7423 Eggleston Rd Memphis TN 38125",
    "addr:housenumber":"7423",
    "addr:postcode":"38125",
    "addr:street":"Eggleston Rd",
    "iso:country":"US",
    "sg:address":"7423 Eggleston Rd",
    "sg:city":"Memphis",
    "sg:classifiers":[
        {
            "category":"Building & Trades",
            "subcategory":"Plumbing",
            "type":"Services"
        }
    ],
    "sg:phone":"+1 901 757 5768",
    "sg:postcode":"38125",
    "sg:province":"TN",
    "sg:tags":[
        "conditioning",
        "air",
        "system",
        "contractor"
    ],
    "wof:name":"M & S Heating & Air",
    "wof:placetype":"venue"
},
  "geometry": {"coordinates":[-89.81774299999999,35.042372],"type":"Point"}
}