{
  "type": "Feature",
  "properties": {
    "iso:country":"US",
    "sg:address":"2555 Burgess School Rd",
    "sg:city":"Cookeville",
    "sg:classifiers":[
        {
            "category":"Building & Trades",
            "subcategory":"Construction",
            "type":"Services"
        }
    ],
    "sg:phone":"+1 931 432 2462",
    "sg:postcode":"38506",
    "sg:province":"TN",
    "sg:tags":[
        "designer",
        "business",
        "contractor",
        "merchandise",
        "dealer",
        "pool",
        "swimming"
    ],
    "wof:name":"Aqua Pools Construction Co",
    "wof:placetype":"venue"
},
  "geometry": {"coordinates":[-85.552573,36.105151],"type":"Point"}
}