{
  "type": "Feature",
  "properties": {
    "iso:country":"US",
    "sg:address":"9317 Hopi Trl",
    "sg:city":"Ooltewah",
    "sg:classifiers":[
        {
            "category":"Building & Trades",
            "subcategory":"Construction",
            "type":"Services"
        }
    ],
    "sg:phone":"+1 423 238 5298",
    "sg:postcode":"37363",
    "sg:province":"TN",
    "sg:tags":[
        "house"
    ],
    "wof:name":"Benton Construction",
    "wof:placetype":"venue"
},
  "geometry": {"coordinates":[-85.040656,35.093579],"type":"Point"}
}