{
  "type": "Feature",
  "properties": {
    "addr:full":"3907 Dodds Ave Chattanooga TN 37407",
    "addr:housenumber":"3907",
    "addr:postcode":"37407",
    "addr:street":"Dodds Ave",
    "iso:country":"US",
    "sg:address":"3907 Dodds Ave",
    "sg:city":"Chattanooga",
    "sg:classifiers":[
        {
            "category":"Building & Trades",
            "subcategory":"Electrical",
            "type":"Services"
        }
    ],
    "sg:phone":"+1 423 867 9324",
    "sg:postcode":"37407",
    "sg:province":"TN",
    "sg:tags":[
        "industrial",
        "electrical",
        "contractor"
    ],
    "wof:name":"Young Electric Co Inc",
    "wof:placetype":"venue"
},
  "geometry": {"coordinates":[-85.28364500000001,34.996743],"type":"Point"}
}