{
  "type": "Feature",
  "properties": {
    "iso:country":"US",
    "sg:address":"3018 Bristol Hwy",
    "sg:city":"Johnson City",
    "sg:classifiers":[
        {
            "category":"Wholesale",
            "subcategory":"Electrical",
            "type":"Manufacturing & Wholesale Goods"
        }
    ],
    "sg:phone":"+1 423 282 1106",
    "sg:postcode":"37601",
    "sg:province":"TN",
    "sg:tags":[
        "equipment"
    ],
    "wof:name":"American Lighting Inc",
    "wof:placetype":"venue"
},
  "geometry": {"coordinates":[-82.38411600000001,36.360263],"type":"Point"}
}