{
  "type": "Feature",
  "properties": {
    "addr:full":"456 Jessie Dr Nashville TN 37211",
    "addr:housenumber":"456",
    "addr:postcode":"37211",
    "addr:street":"Jessie Dr",
    "iso:country":"US",
    "sg:address":"456 Jessie Dr",
    "sg:city":"Nashville",
    "sg:classifiers":[
        {
            "category":"Building & Trades",
            "subcategory":"Construction",
            "type":"Services"
        }
    ],
    "sg:phone":"+1 615 347 5417",
    "sg:postcode":"37211",
    "sg:province":"TN",
    "sg:tags":[
        "house"
    ],
    "wof:name":"Chad Mabry Construction",
    "wof:placetype":"venue"
},
  "geometry": {"coordinates":[-86.712079,36.091929],"type":"Point"}
}