{
  "type": "Feature",
  "properties": {
    "addr:full":"3925 Pilot Dr Memphis TN 38118",
    "addr:housenumber":"3925",
    "addr:postcode":"38118",
    "addr:street":"Pilot Dr",
    "iso:country":"US",
    "sg:address":"3925 Pilot Dr",
    "sg:city":"Memphis",
    "sg:classifiers":[
        {
            "category":"Wholesale",
            "subcategory":"Hardware",
            "type":"Manufacturing & Wholesale Goods"
        }
    ],
    "sg:phone":"+1 901 362 8370",
    "sg:postcode":"38118",
    "sg:province":"TN",
    "sg:tags":[
        "plumbing",
        "fixture",
        "supply"
    ],
    "sg:website":"www.ferguson.com",
    "wof:name":"Ferguson Enterprises Inc",
    "wof:placetype":"venue"
},
  "geometry": {"coordinates":[-89.926287,35.032109],"type":"Point"}
}