{
  "type": "Feature",
  "properties": {
    "iso:country":"US",
    "sg:address":"5281 Pipers Gap Cove",
    "sg:city":"Memphis",
    "sg:classifiers":[
        {
            "category":"Professional",
            "subcategory":"Business Services",
            "type":"Services"
        },
        {
            "category":"Professional",
            "subcategory":"Advertising",
            "type":"Services"
        }
    ],
    "sg:phone":"+1 901 372 8909",
    "sg:postcode":"38134",
    "sg:province":"TN",
    "wof:name":"M E Promotional Products Inc",
    "wof:placetype":"venue"
},
  "geometry": {"coordinates":[-89.88589399999999,35.179489],"type":"Point"}
}