{
  "type": "Feature",
  "properties": {
    "addr:full":"916 W Market St Bolivar TN 38008",
    "addr:housenumber":"916",
    "addr:postcode":"38008",
    "addr:street":"W Market St",
    "iso:country":"US",
    "sg:address":"916 W Market St",
    "sg:city":"Bolivar",
    "sg:classifiers":[
        {
            "category":"Travel",
            "subcategory":"Hotels & Motels",
            "type":"Entertainment"
        }
    ],
    "sg:phone":"+1 731 658 7888",
    "sg:postcode":"38008",
    "sg:province":"TN",
    "wof:name":"Rodeway Inn",
    "wof:placetype":"venue"
},
  "geometry": {"coordinates":[-89.002494,35.256703],"type":"Point"}
}