{
  "type": "Feature",
  "properties": {
    "iso:country":"US",
    "sg:address":"1690 E 1st St",
    "sg:city":"Crossville",
    "sg:classifiers":[
        {
            "category":"Retail",
            "subcategory":"Animal Services",
            "type":"Services"
        }
    ],
    "sg:phone":"+1 931 456 6837",
    "sg:postcode":"38555",
    "sg:province":"TN",
    "wof:name":"Pampered Pets",
    "wof:placetype":"venue"
},
  "geometry": {"coordinates":[-84.99898899999999,35.958381],"type":"Point"}
}