{
  "type": "Feature",
  "properties": {
    "addr:full":"3667 Edd Ross Rd Cedar Hill TN 37032",
    "addr:housenumber":"3667",
    "addr:postcode":"37032",
    "addr:street":"Edd Ross Rd",
    "iso:country":"US",
    "sg:address":"3667 Edd Ross Rd",
    "sg:city":"Cedar Hill",
    "sg:classifiers":[
        {
            "category":"Professional",
            "type":"Services"
        }
    ],
    "sg:phone":"+1 615 696 1005",
    "sg:postcode":"37032",
    "sg:province":"TN",
    "wof:name":"Qpm Inc",
    "wof:placetype":"venue"
},
  "geometry": {"coordinates":[-87.039838,36.487835],"type":"Point"}
}