{
  "type": "Feature",
  "properties": {
    "iso:country":"US",
    "sg:address":"3533 Murfreesboro Pike",
    "sg:city":"Antioch",
    "sg:classifiers":[
        {
            "category":"Retail",
            "subcategory":"Auto Repair",
            "type":"Services"
        }
    ],
    "sg:phone":"+1 615 641 2200",
    "sg:postcode":"37013",
    "sg:province":"TN",
    "sg:tags":[
        "wrecker"
    ],
    "wof:name":"Cotton's Wrecker Svc",
    "wof:placetype":"venue"
},
  "geometry": {"coordinates":[-86.61845700000001,36.05394],"type":"Point"}
}