{
  "type": "Feature",
  "properties": {
    "addr:full":"1015 Sweetwater Rd Newport TN 37821",
    "addr:housenumber":"1015",
    "addr:postcode":"37821",
    "addr:street":"Sweetwater Rd",
    "iso:country":"US",
    "sg:address":"1015 Sweetwater Rd",
    "sg:city":"Newport",
    "sg:classifiers":[
        {
            "category":"Building & Trades",
            "subcategory":"Construction",
            "type":"Services"
        }
    ],
    "sg:phone":"+1 423 625 3833",
    "sg:postcode":"37821",
    "sg:province":"TN",
    "sg:tags":[
        "house"
    ],
    "wof:name":"Superior Home Builders",
    "wof:placetype":"venue"
},
  "geometry": {"coordinates":[-83.162785,35.902009],"type":"Point"}
}