{
  "type": "Feature",
  "properties": {
    "iso:country":"US",
    "sg:address":"2955 Kate Bond Rd",
    "sg:city":"Bartlett",
    "sg:classifiers":[
        {
            "category":"Building & Trades",
            "subcategory":"Construction",
            "type":"Services"
        },
        {
            "category":"Home & Garden",
            "subcategory":"Carpets & Floor Coverings",
            "type":"Retail Goods"
        }
    ],
    "sg:phone":"+1 901 385 1286",
    "sg:postcode":"38133",
    "sg:province":"TN",
    "sg:tags":[
        "tile",
        "dealer"
    ],
    "sg:website":"www.dixiefloors.com",
    "wof:name":"Dixie Floor Coverings",
    "wof:placetype":"venue"
},
  "geometry": {"coordinates":[-89.802426,35.207441],"type":"Point"}
}