{
  "type": "Feature",
  "properties": {
    "iso:country":"US",
    "sg:address":"20409 Alberta St",
    "sg:city":"Oneida",
    "sg:classifiers":[
        {
            "category":"Building & Trades",
            "subcategory":"Pest Control",
            "type":"Services"
        }
    ],
    "sg:phone":"+1 423 569 2118",
    "sg:postcode":"37841",
    "sg:province":"TN",
    "wof:name":"Volunteer Pest Control Inc",
    "wof:placetype":"venue"
},
  "geometry": {"coordinates":[-84.49695800000001,36.524537],"type":"Point"}
}