{
  "type": "Feature",
  "properties": {
    "addr:full":"2110 Portland Ave Nashville TN 37212",
    "addr:housenumber":"2110",
    "addr:postcode":"37212",
    "addr:street":"Portland Ave",
    "iso:country":"US",
    "sg:address":"2110 Portland Ave",
    "sg:city":"Nashville",
    "sg:classifiers":[
        {
            "category":"Real Estate",
            "subcategory":"Real Estate Agent",
            "type":"Services"
        }
    ],
    "sg:phone":"+1 615 292 8192",
    "sg:postcode":"37212",
    "sg:province":"TN",
    "wof:name":"Timmons Properties Inc",
    "wof:placetype":"venue"
},
  "geometry": {"coordinates":[-86.802457,36.133405],"type":"Point"}
}