{
  "type": "Feature",
  "properties": {
    "addr:full":"7500 Capital Dr Germantown TN 38138",
    "addr:postcode":"7500;38138",
    "addr:street":"Capital Dr",
    "iso:country":"US",
    "sg:address":"7500 Capital Dr",
    "sg:city":"Germantown",
    "sg:classifiers":[
        {
            "category":"Real Estate",
            "subcategory":"Real Estate Agent",
            "type":"Services"
        }
    ],
    "sg:phone":"+1 901 753 6977",
    "sg:postcode":"38138",
    "sg:province":"TN",
    "sg:tags":[
        "appraiser"
    ],
    "wof:name":"C & I Appraisal Svc Inc",
    "wof:placetype":"venue"
},
  "geometry": {"coordinates":[-89.81286299999999,35.090246],"type":"Point"}
}