{
  "type": "Feature",
  "properties": {
    "iso:country":"US",
    "sg:address":"470 N McNeil St",
    "sg:city":"Memphis",
    "sg:classifiers":[
        {
            "category":"Shopping",
            "subcategory":"Books",
            "type":"Retail Goods"
        }
    ],
    "sg:phone":"+1 901 725 6913",
    "sg:postcode":"38112",
    "sg:province":"TN",
    "sg:tags":[
        "dealer"
    ],
    "wof:name":"Good Dog Books & More",
    "wof:placetype":"venue"
},
  "geometry": {"coordinates":[-90.010907,35.149381],"type":"Point"}
}