{
  "type": "Feature",
  "properties": {
    "iso:country":"US",
    "sg:address":"5573 Walkup Rd",
    "sg:city":"Pegram",
    "sg:classifiers":[
        {
            "category":"Building & Trades",
            "subcategory":"Construction",
            "type":"Services"
        }
    ],
    "sg:phone":"+1 615 662 1214",
    "sg:postcode":"37143",
    "sg:province":"TN",
    "sg:tags":[
        "repairing",
        "remodeling",
        "contractor"
    ],
    "wof:name":"Quick Start Remodeling",
    "wof:placetype":"venue"
},
  "geometry": {"coordinates":[-87.04526,36.087476],"type":"Point"}
}