{
  "type": "Feature",
  "properties": {
    "addr:full":"2707 Longate Dr Memphis TN 38132",
    "addr:housenumber":"2707",
    "addr:postcode":"38132",
    "addr:street":"Longate Dr",
    "iso:country":"US",
    "sg:address":"2707 Longate Dr",
    "sg:city":"Memphis",
    "sg:classifiers":[
        {
            "category":"Wholesale",
            "subcategory":"Hardware",
            "type":"Manufacturing & Wholesale Goods"
        }
    ],
    "sg:phone":"+1 901 332 7714",
    "sg:postcode":"38132",
    "sg:province":"TN",
    "sg:tags":[
        "hardware-wholesale",
        "manufacturer"
    ],
    "wof:name":"Jfh Corporation",
    "wof:placetype":"venue"
},
  "geometry": {"coordinates":[-90.01049500000001,35.070978],"type":"Point"}
}