{
  "type": "Feature",
  "properties": {
    "iso:country":"US",
    "sg:address":"214 Fairfax Ave",
    "sg:city":"Nashville",
    "sg:classifiers":[
        {
            "category":"Building & Trades",
            "subcategory":"Landscaping Services",
            "type":"Services"
        }
    ],
    "sg:phone":"+1 615 292 8812",
    "sg:postcode":"37212",
    "sg:province":"TN",
    "sg:tags":[
        "landscape",
        "contractor"
    ],
    "wof:name":"Maverick Landscapes",
    "wof:placetype":"venue"
},
  "geometry": {"coordinates":[-86.819599,36.13652],"type":"Point"}
}