{
  "type": "Feature",
  "properties": {
    "iso:country":"US",
    "sg:address":"316 Dearman St",
    "sg:city":"Smithville",
    "sg:classifiers":[
        {
            "category":"Building & Trades",
            "subcategory":"Construction",
            "type":"Services"
        }
    ],
    "sg:phone":"+1 615 597 6778",
    "sg:postcode":"37166",
    "sg:province":"TN",
    "sg:tags":[
        "hanging",
        "painter",
        "contractor"
    ],
    "wof:name":"Pettit's Painting & Wall Cover",
    "wof:placetype":"venue"
},
  "geometry": {"coordinates":[-85.81214300000001,35.941479],"type":"Point"}
}