{
  "type": "Feature",
  "properties": {
    "iso:country":"US",
    "sg:address":"1720 S Bell Ave",
    "sg:city":"Paris",
    "sg:classifiers":[
        {
            "category":"Shopping",
            "subcategory":"Used Merchandise",
            "type":"Retail Goods"
        }
    ],
    "sg:phone":"+1 731 641 0872",
    "sg:postcode":"38242",
    "sg:province":"TN",
    "sg:tags":[
        "flea",
        "market"
    ],
    "wof:name":"Paris Flea Market",
    "wof:placetype":"venue"
},
  "geometry": {"coordinates":[-88.29304999999999,36.310708],"type":"Point"}
}