{
  "type": "Feature",
  "properties": {
    "addr:full":"107 W Market St Dyersburg TN 38024",
    "addr:housenumber":"107",
    "addr:postcode":"38024",
    "addr:street":"W Market St",
    "iso:country":"US",
    "sg:address":"107 W Market St",
    "sg:city":"Dyersburg",
    "sg:classifiers":[
        {
            "category":"Restaurant",
            "type":"Food & Drink"
        }
    ],
    "sg:phone":"+1 731 285 1054",
    "sg:postcode":"38024",
    "sg:province":"TN",
    "wof:name":"Cozy Kitchen",
    "wof:placetype":"venue"
},
  "geometry": {"coordinates":[-89.386702,36.031916],"type":"Point"}
}