{
  "type": "Feature",
  "properties": {
    "addr:full":"414 S Main St Goodlettsville TN 37072",
    "addr:housenumber":"414",
    "addr:postcode":"37072",
    "addr:street":"S Main St",
    "iso:country":"US",
    "sg:address":"414 S Main St",
    "sg:city":"Goodlettsville",
    "sg:classifiers":[
        {
            "category":"Shopping",
            "type":"Retail Goods"
        }
    ],
    "sg:phone":"+1 615 859 7165",
    "sg:postcode":"37072",
    "sg:province":"TN",
    "sg:tags":[
        "merchandise"
    ],
    "wof:name":"Nashville Waxworks",
    "wof:placetype":"venue"
},
  "geometry": {"coordinates":[-86.71325400000001,36.316243],"type":"Point"}
}