{
  "type": "Feature",
  "properties": {
    "addr:full":"819 Harbor Bend Rd Memphis TN 38103",
    "addr:housenumber":"819",
    "addr:postcode":"38103",
    "addr:street":"Harbor Bend Rd",
    "iso:country":"US",
    "sg:address":"819 Harbor Bend Rd",
    "sg:city":"Memphis",
    "sg:classifiers":[
        {
            "category":"Professional",
            "subcategory":"Management & Consulting",
            "type":"Services"
        }
    ],
    "sg:phone":"+1 901 529 8728",
    "sg:postcode":"38103",
    "sg:province":"TN",
    "sg:tags":[
        "chief",
        "diversity",
        "officer"
    ],
    "wof:name":"Rachelle Hood-Phillips",
    "wof:placetype":"venue"
},
  "geometry": {"coordinates":[-90.054238,35.163567],"type":"Point"}
}