{
  "type": "Feature",
  "properties": {
    "addr:full":"33 Music Sq W Nashville TN 37203",
    "addr:housenumber":"33",
    "addr:postcode":"37203",
    "addr:street":"Music Sq W",
    "iso:country":"US",
    "sg:address":"33 Music Sq W",
    "sg:city":"Nashville",
    "sg:classifiers":[
        {
            "category":"Manufacturing",
            "subcategory":"Printing",
            "type":"Manufacturing & Wholesale Goods"
        }
    ],
    "sg:phone":"+1 615 242 4452",
    "sg:postcode":"37203",
    "sg:province":"TN",
    "sg:tags":[
        "publisher",
        "music"
    ],
    "wof:name":"One Music Corp",
    "wof:placetype":"venue"
},
  "geometry": {"coordinates":[-86.793464,36.149112],"type":"Point"}
}