{
  "type": "Feature",
  "properties": {
    "addr:full":"7585 Crosswood Blvd Knoxville TN 37924",
    "addr:housenumber":"7585",
    "addr:postcode":"37924",
    "addr:street":"Crosswood Blvd",
    "iso:country":"US",
    "sg:address":"7585 Crosswood Blvd",
    "sg:city":"Knoxville",
    "sg:classifiers":[
        {
            "category":"Travel",
            "subcategory":"Hotels & Motels",
            "type":"Entertainment"
        }
    ],
    "sg:phone":"+1 865 524 0855",
    "sg:postcode":"37924",
    "sg:province":"TN",
    "sg:tags":[
        "operation"
    ],
    "sg:website":"www.super8.com",
    "wof:name":"Super 8 Motel",
    "wof:placetype":"venue"
},
  "geometry": {"coordinates":[-83.77674399999999,36.004509],"type":"Point"}
}