{
  "type": "Feature",
  "properties": {
    "iso:country":"US",
    "sg:address":"327 Railroad Ave",
    "sg:city":"Tracy City",
    "sg:classifiers":[
        {
            "category":"Restaurant",
            "type":"Food & Drink"
        }
    ],
    "sg:phone":"+1 931 592 7400",
    "sg:postcode":"37380",
    "sg:province":"TN",
    "wof:name":"Daryl's Pizza",
    "wof:placetype":"venue"
},
  "geometry": {"coordinates":[-85.70386000000001,35.011048],"type":"Point"}
}