{
  "type": "Feature",
  "properties": {
    "iso:country":"US",
    "sg:address":"2230 York Hwy",
    "sg:city":"Gainesboro",
    "sg:classifiers":[
        {
            "category":"Government",
            "subcategory":"Fire Station",
            "type":"Public Place"
        }
    ],
    "sg:phone":"+1 931 268 0324",
    "sg:postcode":"38562",
    "sg:province":"TN",
    "sg:tags":[
        "dept",
        "volunteer"
    ],
    "wof:name":"Fairveiw Volunteer Fire Dept",
    "wof:placetype":"venue"
},
  "geometry": {"coordinates":[-85.574066,36.38785],"type":"Point"}
}