{
  "type": "Feature",
  "properties": {
    "addr:full":"11 S Madison Ave Cookeville TN 38501",
    "addr:housenumber":"11",
    "addr:postcode":"38501",
    "addr:street":"S Madison Ave",
    "iso:country":"US",
    "sg:address":"11 S Madison Ave",
    "sg:city":"Cookeville",
    "sg:classifiers":[
        {
            "category":"Professional",
            "subcategory":"Advertising",
            "type":"Services"
        }
    ],
    "sg:phone":"+1 931 528 8266",
    "sg:postcode":"38501",
    "sg:province":"TN",
    "sg:tags":[
        "mailing",
        "shipping"
    ],
    "wof:name":"Fed Ex Freight",
    "wof:placetype":"venue"
},
  "geometry": {"coordinates":[-85.500888,36.162339],"type":"Point"}
}