{
  "type": "Feature",
  "properties": {
    "iso:country":"US",
    "sg:address":"3723 Brainerd Rd",
    "sg:city":"Chattanooga",
    "sg:classifiers":[
        {
            "category":"Autos & Motor Vehicles",
            "subcategory":"Auto Supplies",
            "type":"Retail Goods"
        }
    ],
    "sg:phone":"+1 423 622 4130",
    "sg:postcode":"37411",
    "sg:province":"TN",
    "wof:name":"Advance Auto Parts",
    "wof:placetype":"venue"
},
  "geometry": {"coordinates":[-85.24166200000001,35.022054],"type":"Point"}
}