{
  "type": "Feature",
  "properties": {
    "iso:country":"US",
    "sg:address":"415 Maryville Hwy",
    "sg:city":"Seymour",
    "sg:classifiers":[
        {
            "category":"Recreation",
            "type":"Entertainment"
        }
    ],
    "sg:phone":"+1 865 609 0221",
    "sg:postcode":"37865",
    "sg:province":"TN",
    "wof:name":"Tennessee Martial Arts Univ",
    "wof:placetype":"venue"
},
  "geometry": {"coordinates":[-83.765675,35.865422],"type":"Point"}
}