{
  "type": "Feature",
  "properties": {
    "iso:country":"US",
    "sg:address":"417 Erin Dr",
    "sg:city":"Knoxville",
    "sg:classifiers":[
        {
            "category":"Shopping",
            "subcategory":"Books",
            "type":"Retail Goods"
        }
    ],
    "sg:phone":"+1 865 588 0388",
    "sg:postcode":"37919",
    "sg:province":"TN",
    "wof:name":"Paraclete Catholic Bks & Gifts",
    "wof:placetype":"venue"
},
  "geometry": {"coordinates":[-84.000393,35.927822],"type":"Point"}
}