{
  "type": "Feature",
  "properties": {
    "iso:country":"US",
    "sg:address":"331 Harrington Ave",
    "sg:city":"Madison",
    "sg:classifiers":[
        {
            "category":"Building & Trades",
            "subcategory":"Construction",
            "type":"Services"
        }
    ],
    "sg:phone":"+1 615 977 0314",
    "sg:postcode":"37115",
    "sg:province":"TN",
    "sg:tags":[
        "general",
        "contractor"
    ],
    "wof:name":"A Randolph Construction Co",
    "wof:placetype":"venue"
},
  "geometry": {"coordinates":[-86.712414,36.257227],"type":"Point"}
}