{
  "type": "Feature",
  "properties": {
    "addr:full":"221 W Summer St Greeneville TN 37743",
    "addr:housenumber":"221",
    "addr:postcode":"37743",
    "addr:street":"W Summer St",
    "iso:country":"US",
    "sg:address":"221 W Summer St",
    "sg:city":"Greeneville",
    "sg:classifiers":[
        {
            "category":"Shopping",
            "subcategory":"Stationery & Office Supplies",
            "type":"Retail Goods"
        },
        {
            "category":"Home & Garden",
            "subcategory":"Household Appliances",
            "type":"Retail Goods"
        },
        {
            "category":"Home & Garden",
            "subcategory":"Carpets & Floor Coverings",
            "type":"Retail Goods"
        },
        {
            "category":"Home & Garden",
            "subcategory":"Furniture",
            "type":"Retail Goods"
        }
    ],
    "sg:phone":"+1 423 972 4179",
    "sg:postcode":"37743",
    "sg:province":"TN",
    "sg:tags":[
        "major",
        "store",
        "mattress"
    ],
    "wof:name":"Roberts Furniture Appliances Accents",
    "wof:placetype":"venue"
},
  "geometry": {"coordinates":[-82.834186,36.163245],"type":"Point"}
}