{
  "type": "Feature",
  "properties": {
    "iso:country":"US",
    "sg:address":"212 W Grundy St",
    "sg:city":"Tullahoma",
    "sg:classifiers":[
        {
            "category":"Social Services",
            "type":"Services"
        }
    ],
    "sg:phone":"+1 931 454 9397",
    "sg:postcode":"37388",
    "sg:province":"TN",
    "sg:tags":[
        "info",
        "program",
        "referral"
    ],
    "wof:name":"Coffee County Children Advcy",
    "wof:placetype":"venue"
},
  "geometry": {"coordinates":[-86.212473,35.362415],"type":"Point"}
}