{
  "type": "Feature",
  "properties": {
    "iso:country":"US",
    "sg:address":"2109 Blakewood Pl",
    "sg:city":"Memphis",
    "sg:classifiers":[
        {
            "category":"Professional",
            "subcategory":"Management & Consulting",
            "type":"Services"
        }
    ],
    "sg:phone":"+1 901 774 5985",
    "sg:postcode":"38106",
    "sg:province":"TN",
    "sg:tags":[
        "retail",
        "direct",
        "sales"
    ],
    "wof:name":"Decy Wright Enterprises",
    "wof:placetype":"venue"
},
  "geometry": {"coordinates":[-90.03854,35.090072],"type":"Point"}
}