{
  "type": "Feature",
  "properties": {
    "addr:full":"647 Red Bark Dr Collierville TN 38017",
    "addr:housenumber":"647",
    "addr:postcode":"38017",
    "addr:street":"Red Bark Dr",
    "iso:country":"US",
    "sg:address":"647 Red Bark Dr",
    "sg:city":"Collierville",
    "sg:classifiers":[
        {
            "category":"Restaurant",
            "type":"Food & Drink"
        }
    ],
    "sg:phone":"+1 901 854 8885",
    "sg:postcode":"38017",
    "sg:province":"TN",
    "sg:tags":[
        "eating"
    ],
    "wof:name":"Island Cafe",
    "wof:placetype":"venue"
},
  "geometry": {"coordinates":[-89.685857,35.077783],"type":"Point"}
}