{
  "type": "Feature",
  "properties": {
    "iso:country":"US",
    "sg:address":"1148 N Gateway Ave",
    "sg:city":"Rockwood",
    "sg:classifiers":[
        {
            "category":"Personal",
            "subcategory":"Beauty Salon",
            "type":"Services"
        }
    ],
    "sg:phone":"+1 865 354 1128",
    "sg:postcode":"37854",
    "sg:province":"TN",
    "sg:tags":[
        "shop"
    ],
    "wof:name":"Magic Nails",
    "wof:placetype":"venue"
},
  "geometry": {"coordinates":[-84.668345,35.878844],"type":"Point"}
}