{
  "type": "Feature",
  "properties": {
    "iso:country":"US",
    "sg:address":"4580 Quito-Drummonds Rd",
    "sg:city":"Munford",
    "sg:classifiers":[
        {
            "category":"Organizations",
            "subcategory":"Religious Organization",
            "type":"Services"
        }
    ],
    "sg:phone":"+1 901 835 2318",
    "sg:postcode":"38053",
    "sg:province":"TN",
    "sg:tags":[
        "church"
    ],
    "wof:name":"Quito United Methodist Church",
    "wof:placetype":"venue"
},
  "geometry": {"coordinates":[-89.934409,35.4124],"type":"Point"}
}