{
  "type": "Feature",
  "properties": {
    "iso:country":"US",
    "sg:address":"1729 US Hwy 19E",
    "sg:city":"Elizabethton",
    "sg:classifiers":[
        {
            "category":"Shopping",
            "subcategory":"Bicycles & Sporting Goods",
            "type":"Retail Goods"
        }
    ],
    "sg:phone":"+1 423 543 0555",
    "sg:postcode":"37643",
    "sg:province":"TN",
    "sg:tags":[
        "gun",
        "gunsmith"
    ],
    "wof:name":"Lane's Guns & Pawns",
    "wof:placetype":"venue"
},
  "geometry": {"coordinates":[-82.24886600000001,36.399703],"type":"Point"}
}