{
  "type": "Feature",
  "properties": {
    "addr:full":"108 Rand Pl Franklin TN 37064",
    "addr:housenumber":"108",
    "addr:postcode":"37064",
    "addr:street":"Rand Pl",
    "iso:country":"US",
    "sg:address":"108 Rand Pl",
    "sg:city":"Franklin",
    "sg:classifiers":[
        {
            "category":"Retail",
            "subcategory":"Auto Repair",
            "type":"Services"
        }
    ],
    "sg:phone":"+1 615 599 7313",
    "sg:postcode":"37064",
    "sg:province":"TN",
    "sg:tags":[
        "repairing",
        "automobile"
    ],
    "wof:name":"Tires Plus Total Car Care",
    "wof:placetype":"venue"
},
  "geometry": {"coordinates":[-86.83202799999999,35.910632],"type":"Point"}
}