{
  "type": "Feature",
  "properties": {
    "iso:country":"US",
    "sg:address":"410 Ruritan Rd",
    "sg:city":"Harriman",
    "sg:classifiers":[
        {
            "category":"Shopping",
            "subcategory":"Clothing, Apparel, & Fashions",
            "type":"Retail Goods"
        }
    ],
    "sg:phone":"+1 865 882 3026",
    "sg:postcode":"37748",
    "sg:province":"TN",
    "sg:tags":[
        "shop",
        "bridal"
    ],
    "wof:name":"Mc Kinney's Bridal Prom & Tux",
    "wof:placetype":"venue"
},
  "geometry": {"coordinates":[-84.562792,35.917991],"type":"Point"}
}