{
  "type": "Feature",
  "properties": {
    "addr:full":"330 Polk Ave Nashville TN 37210",
    "addr:housenumber":"330",
    "addr:postcode":"37210",
    "addr:street":"Polk Ave",
    "iso:country":"US",
    "sg:address":"330 Polk Ave",
    "sg:city":"Nashville",
    "sg:classifiers":[
        {
            "category":"Wholesale",
            "subcategory":"Machinery & Supplies",
            "type":"Manufacturing & Wholesale Goods"
        }
    ],
    "sg:phone":"+1 615 244 3661",
    "sg:postcode":"37210",
    "sg:province":"TN",
    "sg:tags":[
        "carpet",
        "cleaning",
        "rug"
    ],
    "wof:name":"Namco Of Nashville",
    "wof:placetype":"venue"
},
  "geometry": {"coordinates":[-86.75428100000001,36.130195],"type":"Point"}
}