{
  "type": "Feature",
  "properties": {
    "addr:full":"309 E Marthona Rd Madison TN 37115",
    "addr:housenumber":"309",
    "addr:postcode":"37115",
    "addr:street":"E Marthona Rd",
    "iso:country":"US",
    "sg:address":"309 E Marthona Rd",
    "sg:city":"Madison",
    "sg:classifiers":[
        {
            "category":"Shopping",
            "subcategory":"Used Merchandise",
            "type":"Retail Goods"
        }
    ],
    "sg:phone":"+1 615 868 0420",
    "sg:postcode":"37115",
    "sg:province":"TN",
    "wof:name":"Mtac",
    "wof:placetype":"venue"
},
  "geometry": {"coordinates":[-86.728066,36.257638],"type":"Point"}
}