{
  "type": "Feature",
  "properties": {
    "iso:country":"US",
    "sg:address":"2643 S Harper Rd",
    "sg:city":"Corinth",
    "sg:classifiers":[
        {
            "category":"Government",
            "subcategory":"Office",
            "type":"Public Place"
        }
    ],
    "sg:phone":"+1 662 286 8834",
    "sg:postcode":"38834",
    "sg:province":"TN",
    "sg:tags":[
        "village"
    ],
    "wof:name":"Corinth Sewage Treatment Plant",
    "wof:placetype":"venue"
},
  "geometry": {"coordinates":[-88.53259,34.908889],"type":"Point"}
}