{
  "type": "Feature",
  "properties": {
    "iso:country":"US",
    "sg:address":"745 S Church St",
    "sg:city":"Murfreesboro",
    "sg:classifiers":[
        {
            "category":"Professional",
            "subcategory":"Detective & Security Services",
            "type":"Services"
        },
        {
            "category":"Professional",
            "subcategory":"Management & Consulting",
            "type":"Services"
        }
    ],
    "sg:phone":"+1 615 867 7237",
    "sg:postcode":"37130",
    "sg:province":"TN",
    "sg:tags":[
        "car",
        "guard",
        "patrol",
        "se"
    ],
    "sg:website":"www.aristosecurity.com",
    "wof:name":"Aristo LLC",
    "wof:placetype":"venue"
},
  "geometry": {"coordinates":[-86.39259199999999,35.837705],"type":"Point"}
}