{
  "type": "Feature",
  "properties": {
    "addr:full":"411 W College St Summertown TN 38483",
    "addr:housenumber":"411",
    "addr:postcode":"38483",
    "addr:street":"W College St",
    "iso:country":"US",
    "sg:address":"411 W College St",
    "sg:city":"Summertown",
    "sg:classifiers":[
        {
            "category":"Education",
            "subcategory":"School",
            "type":"Public Place"
        }
    ],
    "sg:phone":"+1 931 964 3539",
    "sg:postcode":"38483",
    "sg:province":"TN",
    "sg:website":"www.myschoolonline.com",
    "wof:name":"Summertown High School",
    "wof:placetype":"venue"
},
  "geometry": {"coordinates":[-87.31262599999999,35.433697],"type":"Point"}
}