{
  "type": "Feature",
  "properties": {
    "addr:full":"74 Directors Row Jackson TN 38305",
    "addr:housenumber":"74",
    "addr:postcode":"38305",
    "addr:street":"Directors Row",
    "iso:country":"US",
    "sg:address":"74 Directors Row",
    "sg:city":"Jackson",
    "sg:classifiers":[
        {
            "category":"Professional",
            "subcategory":"Credit Reporting & Collection",
            "type":"Services"
        }
    ],
    "sg:phone":"+1 731 668 1136",
    "sg:postcode":"38305",
    "sg:province":"TN",
    "sg:tags":[
        "agency"
    ],
    "wof:name":"Collection Management Svc",
    "wof:placetype":"venue"
},
  "geometry": {"coordinates":[-88.824237,35.669342],"type":"Point"}
}