{
  "type": "Feature",
  "properties": {
    "addr:full":"1799 S 3rd St Memphis TN 38109",
    "addr:housenumber":"1799",
    "addr:postcode":"38109",
    "addr:street":"S 3Rd St",
    "iso:country":"US",
    "sg:address":"1799 S 3rd St",
    "sg:city":"Memphis",
    "sg:classifiers":[
        {
            "category":"Professional",
            "subcategory":"Accounting & Tax Preparation",
            "type":"Services"
        }
    ],
    "sg:phone":"+1 901 948 1040",
    "sg:postcode":"38109",
    "sg:province":"TN",
    "sg:tags":[
        "return",
        "filing"
    ],
    "wof:name":"Jackson Hewitt Tax Svc",
    "wof:placetype":"venue"
},
  "geometry": {"coordinates":[-90.055633,35.099316],"type":"Point"}
}