{
  "type": "Feature",
  "properties": {
    "iso:country":"US",
    "sg:address":"2926 Byington Solway Rd",
    "sg:city":"Knoxville",
    "sg:classifiers":[
        {
            "category":"Wholesale",
            "subcategory":"Durable Goods & Equipment",
            "type":"Manufacturing & Wholesale Goods"
        }
    ],
    "sg:phone":"+1 865 690 1814",
    "sg:postcode":"37931",
    "sg:province":"TN",
    "sg:tags":[
        "representative",
        "manufacturer"
    ],
    "sg:website":"www.chotaoutdoorgear.com",
    "wof:name":"Bryant Sales Co LLC",
    "wof:placetype":"venue"
},
  "geometry": {"coordinates":[-84.135048,35.969731],"type":"Point"}
}