{
  "type": "Feature",
  "properties": {
    "iso:country":"US",
    "sg:address":"1191 Claylick Rd",
    "sg:city":"White Bluff",
    "sg:classifiers":[
        {
            "category":"Manufacturing",
            "subcategory":"Building Materials",
            "type":"Manufacturing & Wholesale Goods"
        }
    ],
    "sg:phone":"+1 615 797 4234",
    "sg:postcode":"37187",
    "sg:province":"TN",
    "sg:tags":[
        "molding"
    ],
    "wof:name":"Trimco",
    "wof:placetype":"venue"
},
  "geometry": {"coordinates":[-87.226517,36.153574],"type":"Point"}
}