{
  "type": "Feature",
  "properties": {
    "iso:country":"US",
    "sg:address":"3748 Carters Valley Rd",
    "sg:city":"Church Hill",
    "sg:classifiers":[
        {
            "category":"Organizations",
            "subcategory":"Religious Organization",
            "type":"Services"
        }
    ],
    "sg:phone":"+1 423 357 4668",
    "sg:postcode":"37642",
    "sg:province":"TN",
    "wof:name":"Mt Mitchell Primitive Baptist",
    "wof:placetype":"venue"
},
  "geometry": {"coordinates":[-82.74381700000001,36.552321],"type":"Point"}
}