{
  "type": "Feature",
  "properties": {
    "iso:country":"US",
    "sg:address":"1324 Ely Rd",
    "sg:city":"Hixson",
    "sg:classifiers":[
        {
            "category":"Shopping",
            "subcategory":"Musical Instruments",
            "type":"Retail Goods"
        }
    ],
    "sg:phone":"+1 423 867 4910",
    "sg:postcode":"37343",
    "sg:province":"TN",
    "sg:tags":[
        "piano"
    ],
    "wof:name":"Maner Music Co",
    "wof:placetype":"venue"
},
  "geometry": {"coordinates":[-85.262377,35.121641],"type":"Point"}
}