{
  "type": "Feature",
  "properties": {
    "iso:country":"US",
    "sg:address":"135 Co Rd 781",
    "sg:city":"Riceville",
    "sg:classifiers":[
        {
            "category":"Autos & Motor Vehicles",
            "subcategory":"Automobile Sales",
            "type":"Retail Goods"
        }
    ],
    "sg:phone":"+1 423 336 1719",
    "sg:postcode":"37370",
    "sg:province":"TN",
    "sg:tags":[
        "sport",
        "trailer",
        "utility"
    ],
    "wof:name":"J & J Trailer Sales",
    "wof:placetype":"venue"
},
  "geometry": {"coordinates":[-84.62191799999999,35.283257],"type":"Point"}
}