{
  "type": "Feature",
  "properties": {
    "iso:country":"US",
    "sg:address":"2974 Green Fairway Cove N",
    "sg:city":"Collierville",
    "sg:classifiers":[
        {
            "category":"Food & Beverages",
            "subcategory":"Bakery",
            "type":"Retail Goods"
        }
    ],
    "sg:phone":"+1 901 854 1104",
    "sg:postcode":"38017",
    "sg:province":"TN",
    "sg:tags":[
        "baker"
    ],
    "wof:name":"Harriet's Creations Inc",
    "wof:placetype":"venue"
},
  "geometry": {"coordinates":[-89.72438,35.067048],"type":"Point"}
}