{
  "type": "Feature",
  "properties": {
    "addr:full":"3080 US Hwy 51 S Covington TN 38019",
    "addr:housenumber":"3080",
    "addr:postcode":"38019",
    "addr:street":"Us Hwy 51 S",
    "iso:country":"US",
    "sg:address":"3080 US Hwy 51 S",
    "sg:city":"Covington",
    "sg:classifiers":[
        {
            "category":"Professional",
            "subcategory":"Computer Services",
            "type":"Services"
        }
    ],
    "sg:phone":"+1 901 476 9992",
    "sg:postcode":"38019",
    "sg:province":"TN",
    "sg:tags":[
        "bar",
        "coding"
    ],
    "wof:name":"Bank Of Friendship Admin Ofc",
    "wof:placetype":"venue"
},
  "geometry": {"coordinates":[-89.683544,35.529501],"type":"Point"}
}