{
  "type": "Feature",
  "properties": {
    "addr:full":"901 E Summit Hill Dr Knoxville TN 37915",
    "addr:housenumber":"901",
    "addr:postcode":"37915",
    "addr:street":"E Summit Hill Dr",
    "iso:country":"US",
    "sg:address":"901 E Summit Hill Dr",
    "sg:city":"Knoxville",
    "sg:classifiers":[
        {
            "category":"Restaurant",
            "type":"Food & Drink"
        }
    ],
    "sg:phone":"+1 865 546 5810",
    "sg:postcode":"37915",
    "sg:province":"TN",
    "wof:name":"KFC",
    "wof:placetype":"venue"
},
  "geometry": {"coordinates":[-83.910123,35.970373],"type":"Point"}
}