{
  "type": "Feature",
  "properties": {
    "addr:full":"303 Russell St Petersburg TN 37144",
    "addr:housenumber":"303",
    "addr:postcode":"37144",
    "addr:street":"Russell St",
    "iso:country":"US",
    "sg:address":"303 Russell St",
    "sg:city":"Petersburg",
    "sg:classifiers":[
        {
            "category":"Organizations",
            "subcategory":"Religious Organization",
            "type":"Services"
        }
    ],
    "sg:phone":"+1 931 659 6207",
    "sg:postcode":"37144",
    "sg:province":"TN",
    "wof:name":"Cumberland and Presbt Church",
    "wof:placetype":"venue"
},
  "geometry": {"coordinates":[-86.637041,35.318291],"type":"Point"}
}