{
  "type": "Feature",
  "properties": {
    "addr:full":"18432 US Hwy 11 E Lenoir City TN 37772",
    "addr:housenumber":"18432",
    "addr:postcode":"37772",
    "addr:street":"Us Hwy 11 E",
    "iso:country":"US",
    "sg:address":"18432 US Hwy 11 E",
    "sg:city":"Lenoir City",
    "sg:classifiers":[
        {
            "category":"Shopping",
            "subcategory":"Stationery & Office Supplies",
            "type":"Retail Goods"
        }
    ],
    "sg:phone":"+1 865 986 7873",
    "sg:postcode":"37772",
    "sg:province":"TN",
    "wof:name":"Business Forms",
    "wof:placetype":"venue"
},
  "geometry": {"coordinates":[-84.22527100000001,35.853957],"type":"Point"}
}