{
  "type": "Feature",
  "properties": {
    "iso:country":"US",
    "sg:address":"1784 Frayser Blvd",
    "sg:city":"Memphis",
    "sg:classifiers":[
        {
            "category":"Shopping",
            "subcategory":"Pharmacy",
            "type":"Retail Goods"
        }
    ],
    "sg:phone":"+1 901 358 0818",
    "sg:postcode":"38127",
    "sg:province":"TN",
    "wof:name":"Super D Express",
    "wof:placetype":"venue"
},
  "geometry": {"coordinates":[-90.00467500000001,35.21768],"type":"Point"}
}