{
  "type": "Feature",
  "properties": {
    "iso:country":"US",
    "sg:address":"2543 E Wood St",
    "sg:city":"Paris",
    "sg:classifiers":[
        {
            "category":"Personal",
            "subcategory":"Barber",
            "type":"Services"
        }
    ],
    "sg:phone":"+1 731 642 4201",
    "sg:postcode":"38242",
    "sg:province":"TN",
    "sg:tags":[
        "shop",
        "beauty"
    ],
    "wof:name":"A Visible Change",
    "wof:placetype":"venue"
},
  "geometry": {"coordinates":[-88.278599,36.319665],"type":"Point"}
}