{
  "type": "Feature",
  "properties": {
    "addr:full":"629 N Main St Shelbyville TN 37160",
    "addr:housenumber":"629",
    "addr:postcode":"37160",
    "addr:street":"N Main St",
    "iso:country":"US",
    "sg:address":"629 N Main St",
    "sg:city":"Shelbyville",
    "sg:classifiers":[
        {
            "category":"Shopping",
            "subcategory":"Pharmacy",
            "type":"Retail Goods"
        }
    ],
    "sg:phone":"+1 931 684 1933",
    "sg:postcode":"37160",
    "sg:province":"TN",
    "sg:tags":[
        "item",
        "sundry",
        "drug"
    ],
    "wof:name":"Renegar's Drug Store",
    "wof:placetype":"venue"
},
  "geometry": {"coordinates":[-86.459174,35.488751],"type":"Point"}
}