{
  "type": "Feature",
  "properties": {
    "iso:country":"US",
    "sg:address":"566 Pond Apple Rd",
    "sg:city":"Clarksville",
    "sg:classifiers":[
        {
            "category":"Real Estate",
            "subcategory":"Real Estate Operator",
            "type":"Services"
        }
    ],
    "sg:phone":"+1 931 645 4867",
    "sg:postcode":"37043",
    "sg:province":"TN",
    "sg:tags":[
        "mobile",
        "home",
        "site"
    ],
    "wof:name":"River Ridge Mobile Park",
    "wof:placetype":"venue"
},
  "geometry": {"coordinates":[-87.274608,36.536365],"type":"Point"}
}