{
  "type": "Feature",
  "properties": {
    "iso:country":"US",
    "sg:address":"1410 Donelson Pike",
    "sg:city":"Nashville",
    "sg:classifiers":[
        {
            "category":"Real Estate",
            "subcategory":"Real Estate Agent",
            "type":"Services"
        }
    ],
    "sg:phone":"+1 615 366 6200",
    "sg:postcode":"37214",
    "sg:province":"TN",
    "wof:name":"Duke Weeks Realty Corp",
    "wof:placetype":"venue"
},
  "geometry": {"coordinates":[-86.678721,36.093393],"type":"Point"}
}