{
  "type": "Feature",
  "properties": {
    "iso:country":"US",
    "sg:address":"441 Clay St",
    "sg:city":"Kingsport",
    "sg:classifiers":[
        {
            "category":"Social Services",
            "type":"Services"
        }
    ],
    "sg:phone":"+1 423 392 8841",
    "sg:postcode":"37660",
    "sg:province":"TN",
    "wof:name":"Jr Achievement of Kingsport",
    "wof:placetype":"venue"
},
  "geometry": {"coordinates":[-82.561188,36.549371],"type":"Point"}
}