{
  "type": "Feature",
  "properties": {
    "addr:full":"313 S Washington St Tullahoma TN 37388",
    "addr:housenumber":"313",
    "addr:postcode":"37388",
    "addr:street":"S Washington St",
    "iso:country":"US",
    "sg:address":"313 S Washington St",
    "sg:city":"Tullahoma",
    "sg:classifiers":[
        {
            "category":"Freight",
            "type":"Transportation"
        }
    ],
    "sg:phone":"+1 931 455 2400",
    "sg:postcode":"37388",
    "sg:province":"TN",
    "sg:tags":[
        "special"
    ],
    "wof:name":"Extra Closets",
    "wof:placetype":"venue"
},
  "geometry": {"coordinates":[-86.205771,35.361419],"type":"Point"}
}