{
  "type": "Feature",
  "properties": {
    "addr:full":"2004 Joe Brown Rd Columbia TN 38401",
    "addr:housenumber":"2004",
    "addr:postcode":"38401",
    "addr:street":"Joe Brown Rd",
    "iso:country":"US",
    "sg:address":"2004 Joe Brown Rd",
    "sg:city":"Columbia",
    "sg:classifiers":[
        {
            "category":"Farming",
            "subcategory":"Livestock Farm",
            "type":"Manufacturing & Wholesale Goods"
        }
    ],
    "sg:phone":"+1 931 381 0884",
    "sg:postcode":"38401",
    "sg:province":"TN",
    "sg:tags":[
        "field",
        "animal",
        "crop",
        "general"
    ],
    "wof:name":"Woodstone Farms",
    "wof:placetype":"venue"
},
  "geometry": {"coordinates":[-86.871081,35.657781],"type":"Point"}
}