{
  "type": "Feature",
  "properties": {
    "iso:country":"US",
    "sg:address":"129 Magnolia Dr",
    "sg:city":"Dyersburg",
    "sg:classifiers":[
        {
            "category":"Banks & Credit Unions",
            "subcategory":"Bank",
            "type":"Services"
        }
    ],
    "sg:phone":"+1 731 285 0811",
    "sg:postcode":"38024",
    "sg:province":"TN",
    "sg:tags":[
        "loan",
        "real estate"
    ],
    "wof:name":"Assured Mortgage",
    "wof:placetype":"venue"
},
  "geometry": {"coordinates":[-89.35526900000001,36.026844],"type":"Point"}
}