{
  "type": "Feature",
  "properties": {
    "addr:full":"101 Par 5 Cir Rogersville TN 37857",
    "addr:housenumber":"101",
    "addr:postcode":"37857",
    "addr:street":"Par 5 Cir",
    "iso:country":"US",
    "sg:address":"101 Par 5 Cir",
    "sg:city":"Rogersville",
    "sg:classifiers":[
        {
            "category":"Retail",
            "subcategory":"Laundry & Dry Cleaning",
            "type":"Services"
        }
    ],
    "sg:phone":"+1 423 963 0812",
    "sg:postcode":"37857",
    "sg:province":"TN",
    "sg:tags":[
        "cleaners",
        "rug",
        "carpet"
    ],
    "wof:name":"Garys Clean-Ology Expert Crpt",
    "wof:placetype":"venue"
},
  "geometry": {"coordinates":[-82.98101699999999,36.394145],"type":"Point"}
}