{
  "type": "Feature",
  "properties": {
    "iso:country":"US",
    "sg:address":"121 Main St",
    "sg:city":"Portland",
    "sg:classifiers":[
        {
            "category":"Restaurant",
            "type":"Food & Drink"
        }
    ],
    "sg:phone":"+1 615 325 0095",
    "sg:postcode":"37148",
    "sg:province":"TN",
    "sg:tags":[
        "mexican"
    ],
    "sg:website":"http://www.aztecamex.com",
    "wof:name":"El Azteca Mexican Restaurant",
    "wof:placetype":"venue"
},
  "geometry": {"coordinates":[-86.51566099999999,36.580431],"type":"Point"}
}