{
  "type": "Feature",
  "properties": {
    "iso:country":"US",
    "sg:address":"3606 Martindale Dr",
    "sg:city":"Johnson City",
    "sg:classifiers":[
        {
            "category":"Recreation",
            "subcategory":"Arcade",
            "type":"Entertainment"
        }
    ],
    "sg:phone":"+1 310 374 4321",
    "sg:postcode":"37601",
    "sg:province":"TN",
    "sg:tags":[
        "machine",
        "rental",
        "amusement"
    ],
    "wof:name":"Special Events Attractions",
    "wof:placetype":"venue"
},
  "geometry": {"coordinates":[-82.313665,36.289669],"type":"Point"}
}