{
  "type": "Feature",
  "properties": {
    "iso:country":"US",
    "sg:address":"550 Darnell-Mealer Rd",
    "sg:city":"Lewisburg",
    "sg:classifiers":[
        {
            "category":"Freight",
            "type":"Transportation"
        }
    ],
    "sg:phone":"+1 931 359 3956",
    "sg:postcode":"37091",
    "sg:province":"TN",
    "sg:tags":[
        "heavy",
        "hauling",
        "trucking"
    ],
    "wof:name":"D J Mealer Trucking",
    "wof:placetype":"venue"
},
  "geometry": {"coordinates":[-86.765478,35.458267],"type":"Point"}
}