{
  "type": "Feature",
  "properties": {
    "iso:country":"US",
    "sg:address":"601 Highview Cir",
    "sg:city":"Chattanooga",
    "sg:classifiers":[
        {
            "category":"Professional",
            "type":"Services"
        }
    ],
    "sg:phone":"+1 423 875 3348",
    "sg:postcode":"37415",
    "sg:province":"TN",
    "wof:name":"Daniel P Jetter",
    "wof:placetype":"venue"
},
  "geometry": {"coordinates":[-85.27308600000001,35.117458],"type":"Point"}
}