{
  "type": "Feature",
  "properties": {
    "iso:country":"US",
    "sg:address":"250 Youth Home Rd",
    "sg:city":"Dyersburg",
    "sg:classifiers":[
        {
            "category":"Social Services",
            "subcategory":"Job Training",
            "type":"Services"
        }
    ],
    "sg:phone":"+1 731 286 1866",
    "sg:postcode":"38024",
    "sg:province":"TN",
    "sg:tags":[
        "rehabilitation"
    ],
    "wof:name":"New Life Youth Home",
    "wof:placetype":"venue"
},
  "geometry": {"coordinates":[-89.370655,36.070485],"type":"Point"}
}