{
  "type": "Feature",
  "properties": {
    "addr:full":"431 Alfred Thun Rd Clarksville TN 37040",
    "addr:housenumber":"431",
    "addr:postcode":"37040",
    "addr:street":"Alfred Thun Rd",
    "iso:country":"US",
    "sg:address":"431 Alfred Thun Rd",
    "sg:city":"Clarksville",
    "sg:classifiers":[
        {
            "category":"Sports & Exercise",
            "subcategory":"Race Track",
            "type":"Entertainment"
        },
        {
            "category":"Wholesale",
            "subcategory":"Auto Parts",
            "type":"Manufacturing & Wholesale Goods"
        }
    ],
    "sg:phone":"+1 931 552 4232",
    "sg:postcode":"37040",
    "sg:province":"TN",
    "sg:tags":[
        "equipment",
        "supply"
    ],
    "wof:name":"Scogin Enterprises LLC",
    "wof:placetype":"venue"
},
  "geometry": {"coordinates":[-87.278969,36.599634],"type":"Point"}
}