{
  "type": "Feature",
  "properties": {
    "iso:country":"US",
    "sg:address":"12121 Aspenwood Dr",
    "sg:city":"Knoxville",
    "sg:classifiers":[
        {
            "category":"Retail",
            "subcategory":"Repair Shop",
            "type":"Services"
        }
    ],
    "sg:phone":"+1 865 966 3065",
    "sg:postcode":"37934",
    "sg:province":"TN",
    "sg:tags":[
        "merchandise"
    ],
    "wof:name":"Stockbridge Gallery",
    "wof:placetype":"venue"
},
  "geometry": {"coordinates":[-84.185282,35.863615],"type":"Point"}
}