{
  "type": "Feature",
  "properties": {
    "iso:country":"US",
    "sg:address":"8608 High Cotton Cove",
    "sg:city":"Cordova",
    "sg:classifiers":[
        {
            "category":"Professional",
            "subcategory":"Accounting & Tax Preparation",
            "type":"Services"
        }
    ],
    "sg:phone":"+1 901 753 1618",
    "sg:postcode":"38018",
    "sg:province":"TN",
    "sg:tags":[
        "accountant"
    ],
    "wof:name":"Florence Marinelli CPA",
    "wof:placetype":"venue"
},
  "geometry": {"coordinates":[-89.77573,35.142028],"type":"Point"}
}