{
  "type": "Feature",
  "properties": {
    "addr:full":"3740 Park Ave Memphis TN 38111",
    "addr:housenumber":"3740",
    "addr:postcode":"38111",
    "addr:street":"Park Ave",
    "iso:country":"US",
    "sg:address":"3740 Park Ave",
    "sg:city":"Memphis",
    "sg:classifiers":[
        {
            "category":"Health Services",
            "subcategory":"Doctor",
            "type":"Services"
        }
    ],
    "sg:phone":"+1 901 458 9577",
    "sg:postcode":"38111",
    "sg:province":"TN",
    "sg:tags":[
        "dentist"
    ],
    "wof:name":"Family Dentistry",
    "wof:placetype":"venue"
},
  "geometry": {"coordinates":[-89.936387,35.107708],"type":"Point"}
}