{
  "type": "Feature",
  "properties": {
    "iso:country":"US",
    "sg:address":"8905 Kingston Pike",
    "sg:city":"Knoxville",
    "sg:classifiers":[
        {
            "category":"Wholesale",
            "subcategory":"Farm Supplies",
            "type":"Manufacturing & Wholesale Goods"
        },
        {
            "category":"Shopping",
            "subcategory":"Bicycles & Sporting Goods",
            "type":"Retail Goods"
        }
    ],
    "sg:phone":"+1 865 769 9336",
    "sg:postcode":"37923",
    "sg:province":"TN",
    "sg:tags":[
        "horse",
        "furnishing",
        "animal"
    ],
    "sg:website":"www.mbfellowship.com",
    "wof:name":"Mount & Rider",
    "wof:placetype":"venue"
},
  "geometry": {"coordinates":[-84.08183699999999,35.912874],"type":"Point"}
}