{
  "type": "Feature",
  "properties": {
    "addr:full":"4701 Old Hickory Blvd Old Hickory TN 37138",
    "addr:housenumber":"4701",
    "addr:postcode":"37138",
    "addr:street":"Old Hickory Blvd",
    "iso:country":"US",
    "sg:address":"4701 Old Hickory Blvd",
    "sg:city":"Old Hickory",
    "sg:classifiers":[
        {
            "category":"Real Estate",
            "subcategory":"Real Estate Operator",
            "type":"Services"
        }
    ],
    "sg:phone":"+1 615 883 6861",
    "sg:postcode":"37138",
    "sg:province":"TN",
    "sg:tags":[
        "building",
        "apartment"
    ],
    "wof:name":"Hermitage Grdn Apartments LLC",
    "wof:placetype":"venue"
},
  "geometry": {"coordinates":[-86.62092699999999,36.200552],"type":"Point"}
}