{
  "type": "Feature",
  "properties": {
    "iso:country":"US",
    "sg:address":"215 State Hwy 82 N",
    "sg:city":"Bell Buckle",
    "sg:classifiers":[
        {
            "category":"Building & Trades",
            "subcategory":"Construction",
            "type":"Services"
        }
    ],
    "sg:phone":"+1 931 389 9112",
    "sg:postcode":"37020",
    "sg:province":"TN",
    "sg:tags":[
        "house"
    ],
    "wof:name":"Jeff Ross Construction Co",
    "wof:placetype":"venue"
},
  "geometry": {"coordinates":[-86.42747,35.587243],"type":"Point"}
}