{
  "type": "Feature",
  "properties": {
    "addr:full":"366 Westview Dr White Bluff TN 37187",
    "addr:housenumber":"366",
    "addr:postcode":"37187",
    "addr:street":"Westview Dr White Bluff",
    "iso:country":"US",
    "sg:address":"366 Westview Dr",
    "sg:city":"White Bluff",
    "sg:classifiers":[
        {
            "category":"Building & Trades",
            "subcategory":"Construction",
            "type":"Services"
        }
    ],
    "sg:phone":"+1 615 797 2817",
    "sg:postcode":"37187",
    "sg:province":"TN",
    "sg:tags":[
        "house"
    ],
    "wof:name":"Philip Buttrey Const Co",
    "wof:placetype":"venue"
},
  "geometry": {"coordinates":[-87.24356400000001,36.127978],"type":"Point"}
}