{
  "type": "Feature",
  "properties": {
    "addr:full":"321 Aubrey Ferguson Rd Gadsden TN 38337",
    "addr:housenumber":"321",
    "addr:postcode":"38337",
    "addr:street":"Aubrey Ferguson Rd",
    "iso:country":"US",
    "sg:address":"321 Aubrey Ferguson Rd",
    "sg:city":"Gadsden",
    "sg:classifiers":[
        {
            "category":"Professional",
            "type":"Services"
        }
    ],
    "sg:phone":"+1 731 222 0505",
    "sg:postcode":"38337",
    "sg:province":"TN",
    "wof:name":"Jason Unruh",
    "wof:placetype":"venue"
},
  "geometry": {"coordinates":[-89.006877,35.803165],"type":"Point"}
}