{
  "type": "Feature",
  "properties": {
    "iso:country":"US",
    "sg:address":"6524 Banbury Xing",
    "sg:city":"Brentwood",
    "sg:classifiers":[
        {
            "category":"Wholesale",
            "subcategory":"Medical Equipment & Supplies",
            "type":"Manufacturing & Wholesale Goods"
        }
    ],
    "sg:phone":"+1 615 333 7043",
    "sg:postcode":"37027",
    "sg:province":"TN",
    "wof:name":"Matthew Thomas Industries Inc",
    "wof:placetype":"venue"
},
  "geometry": {"coordinates":[-86.748451,36.022242],"type":"Point"}
}