{
  "type": "Feature",
  "properties": {
    "iso:country":"US",
    "sg:address":"9040 Executive Park Dr",
    "sg:city":"Knoxville",
    "sg:classifiers":[
        {
            "category":"Retail",
            "subcategory":"Auto Rental",
            "type":"Services"
        }
    ],
    "sg:phone":"+1 865 470 9110",
    "sg:postcode":"37923",
    "sg:province":"TN",
    "sg:tags":[
        "renting",
        "automobile"
    ],
    "wof:name":"Cherokee Rental Inc",
    "wof:placetype":"venue"
},
  "geometry": {"coordinates":[-84.08044099999999,35.922207],"type":"Point"}
}