{
  "type": "Feature",
  "properties": {
    "iso:country":"US",
    "sg:address":"1702 W Madison Ave",
    "sg:city":"Athens",
    "sg:classifiers":[
        {
            "category":"Real Estate",
            "subcategory":"Real Estate Agent",
            "type":"Services"
        }
    ],
    "sg:phone":"+1 423 745 4131",
    "sg:postcode":"37303",
    "sg:province":"TN",
    "wof:name":"Premier Properties Realty",
    "wof:placetype":"venue"
},
  "geometry": {"coordinates":[-84.619409,35.439438],"type":"Point"}
}