{
  "type": "Feature",
  "properties": {
    "addr:full":"2114 E Andrew Johnson Hwy Morristown TN 37814",
    "addr:housenumber":"2114",
    "addr:postcode":"37814",
    "addr:street":"E Andrew Johnson Hwy",
    "iso:country":"US",
    "sg:address":"2114 E Andrew Johnson Hwy",
    "sg:city":"Morristown",
    "sg:classifiers":[
        {
            "category":"Shopping",
            "subcategory":"Pharmacy",
            "type":"Retail Goods"
        }
    ],
    "sg:phone":"+1 423 587 8074",
    "sg:postcode":"37814",
    "sg:province":"TN",
    "wof:name":"CVS",
    "wof:placetype":"venue"
},
  "geometry": {"coordinates":[-83.266842,36.226368],"type":"Point"}
}