{
  "type": "Feature",
  "properties": {
    "addr:full":"6925 Maynardville Pike Knoxville TN 37918",
    "addr:housenumber":"6925",
    "addr:postcode":"37918",
    "addr:street":"Maynardville Pike",
    "iso:country":"US",
    "sg:address":"6925 Maynardville Pike",
    "sg:city":"Knoxville",
    "sg:classifiers":[
        {
            "category":"Personal",
            "subcategory":"Beauty Salon",
            "type":"Services"
        }
    ],
    "sg:phone":"+1 865 925 0111",
    "sg:postcode":"37918",
    "sg:province":"TN",
    "wof:name":"Cutting Crew",
    "wof:placetype":"venue"
},
  "geometry": {"coordinates":[-83.927964,36.074426],"type":"Point"}
}