{
  "type": "Feature",
  "properties": {
    "addr:full":"83 Trenton Hwy Milan TN 38358",
    "addr:housenumber":"83",
    "addr:postcode":"38358",
    "addr:street":"Trenton Hwy",
    "iso:country":"US",
    "sg:address":"83 Trenton Hwy",
    "sg:city":"Milan",
    "sg:classifiers":[
        {
            "category":"Retail",
            "subcategory":"Auto Repair",
            "type":"Services"
        }
    ],
    "sg:phone":"+1 731 686 0546",
    "sg:postcode":"38358",
    "sg:province":"TN",
    "sg:tags":[
        "repairing",
        "automobile",
        "body",
        "general"
    ],
    "wof:name":"Keith Beard's Auto Body Works",
    "wof:placetype":"venue"
},
  "geometry": {"coordinates":[-88.792405,35.938596],"type":"Point"}
}