{
  "type": "Feature",
  "properties": {
    "addr:full":"3254 Elvis Presley Blvd Memphis TN 38116",
    "addr:housenumber":"3254",
    "addr:postcode":"38116",
    "addr:street":"Elvis Presley Blvd",
    "iso:country":"US",
    "sg:address":"3254 Elvis Presley Blvd",
    "sg:city":"Memphis",
    "sg:classifiers":[
        {
            "category":"Autos & Motor Vehicles",
            "subcategory":"Automobile Sales",
            "type":"Retail Goods"
        }
    ],
    "sg:phone":"+1 901 348 0099",
    "sg:postcode":"38116",
    "sg:province":"TN",
    "sg:tags":[
        "new",
        "car"
    ],
    "wof:name":"Aaron's Honda",
    "wof:placetype":"venue"
},
  "geometry": {"coordinates":[-90.02395,35.060047],"type":"Point"}
}