{
  "type": "Feature",
  "properties": {
    "iso:country":"US",
    "sg:address":"2500 Lebanon Pike",
    "sg:city":"Nashville",
    "sg:classifiers":[
        {
            "category":"Retail",
            "subcategory":"Photofinishing",
            "type":"Services"
        },
        {
            "category":"Shopping",
            "subcategory":"Pharmacy",
            "type":"Retail Goods"
        }
    ],
    "sg:phone":"+1 615 889 6300",
    "sg:postcode":"37214",
    "sg:province":"TN",
    "sg:tags":[
        "photo",
        "finishing",
        "first",
        "aid",
        "supply"
    ],
    "sg:website":"http://www.cvs.com",
    "wof:name":"CVS/pharmacy",
    "wof:placetype":"venue"
},
  "geometry": {"coordinates":[-86.67987100000001,36.169369],"type":"Point"}
}