{
  "type": "Feature",
  "properties": {
    "addr:full":"783 Old Hickory Blvd Brentwood TN 37027",
    "addr:housenumber":"783",
    "addr:postcode":"37027",
    "addr:street":"Old Hickory Blvd",
    "iso:country":"US",
    "sg:address":"783 Old Hickory Blvd",
    "sg:city":"Brentwood",
    "sg:classifiers":[
        {
            "category":"Freight",
            "type":"Transportation"
        },
        {
            "category":"Shopping",
            "type":"Retail Goods"
        }
    ],
    "sg:phone":"+1 615 371 1404",
    "sg:postcode":"37027",
    "sg:province":"TN",
    "sg:tags":[
        "equipment",
        "care",
        "health",
        "home"
    ],
    "wof:name":"Turner Logistics",
    "wof:placetype":"venue"
},
  "geometry": {"coordinates":[-86.78258099999999,36.038996],"type":"Point"}
}