{
  "type": "Feature",
  "properties": {
    "iso:country":"US",
    "sg:address":"1543 Downtown West Blvd",
    "sg:city":"Knoxville",
    "sg:classifiers":[
        {
            "category":"Retail",
            "subcategory":"Auto Rental",
            "type":"Services"
        }
    ],
    "sg:phone":"+1 865 694 7718",
    "sg:postcode":"37919",
    "sg:province":"TN",
    "sg:tags":[
        "passenger",
        "car"
    ],
    "wof:name":"Priceless Car Rental",
    "wof:placetype":"venue"
},
  "geometry": {"coordinates":[-84.051135,35.919308],"type":"Point"}
}