{
  "type": "Feature",
  "properties": {
    "iso:country":"US",
    "sg:address":"4945 American Way",
    "sg:city":"Memphis",
    "sg:classifiers":[
        {
            "category":"Personal",
            "subcategory":"Beauty Salon",
            "type":"Services"
        }
    ],
    "sg:phone":"+1 901 794 7572",
    "sg:postcode":"38118",
    "sg:province":"TN",
    "wof:name":"Fantasy Hair Salon",
    "wof:placetype":"venue"
},
  "geometry": {"coordinates":[-89.89802299999999,35.075125],"type":"Point"}
}