{
  "type": "Feature",
  "properties": {
    "iso:country":"US",
    "sg:address":"135 Frazier Ave",
    "sg:city":"Chattanooga",
    "sg:classifiers":[
        {
            "category":"Shopping",
            "subcategory":"Clothing, Apparel, & Fashions",
            "type":"Retail Goods"
        }
    ],
    "sg:phone":"+1 423 634 0822",
    "sg:postcode":"37411",
    "sg:province":"TN",
    "sg:tags":[
        "infant",
        "wear"
    ],
    "wof:name":"A Child's Garden Boutique",
    "wof:placetype":"venue"
},
  "geometry": {"coordinates":[-85.307737,35.062557],"type":"Point"}
}