{
  "type": "Feature",
  "properties": {
    "iso:country":"US",
    "sg:address":"247 Beaver Rd",
    "sg:city":"Bluff City",
    "sg:classifiers":[
        {
            "category":"Building & Trades",
            "subcategory":"Construction",
            "type":"Services"
        }
    ],
    "sg:phone":"+1 423 538 9482",
    "sg:postcode":"37618",
    "sg:province":"TN",
    "sg:tags":[
        "house"
    ],
    "wof:name":"Davidson Construction & Remode",
    "wof:placetype":"venue"
},
  "geometry": {"coordinates":[-82.27172400000001,36.505537],"type":"Point"}
}