{
  "type": "Feature",
  "properties": {
    "iso:country":"US",
    "sg:address":"3754 Mingo Rd",
    "sg:city":"Belvidere",
    "sg:classifiers":[
        {
            "category":"School Buses",
            "type":"Transportation"
        }
    ],
    "sg:phone":"+1 931 967 2321",
    "sg:postcode":"37306",
    "sg:province":"TN",
    "wof:name":"Jeremy Dotson Company",
    "wof:placetype":"venue"
},
  "geometry": {"coordinates":[-86.194517,35.164656],"type":"Point"}
}