{
  "type": "Feature",
  "properties": {
    "iso:country":"US",
    "sg:address":"3994 Dickerson Pike",
    "sg:city":"Nashville",
    "sg:classifiers":[
        {
            "category":"Autos & Motor Vehicles",
            "subcategory":"Automobile Sales",
            "type":"Retail Goods"
        }
    ],
    "sg:phone":"+1 615 865 0202",
    "sg:postcode":"37207",
    "sg:province":"TN",
    "sg:tags":[
        "car",
        "used",
        "dealer"
    ],
    "wof:name":"B and B Motors II",
    "wof:placetype":"venue"
},
  "geometry": {"coordinates":[-86.751599,36.277085],"type":"Point"}
}