{
  "type": "Feature",
  "properties": {
    "iso:country":"US",
    "sg:address":"1318 Pickwick St S",
    "sg:city":"Savannah",
    "sg:classifiers":[
        {
            "category":"Travel",
            "subcategory":"Hotels & Motels",
            "type":"Entertainment"
        }
    ],
    "sg:phone":"+1 731 925 5505",
    "sg:postcode":"38372",
    "sg:province":"TN",
    "sg:tags":[
        "operation"
    ],
    "wof:name":"Days Inn",
    "wof:placetype":"venue"
},
  "geometry": {"coordinates":[-88.245476,35.205159],"type":"Point"}
}