{
  "type": "Feature",
  "properties": {
    "addr:full":"207 W Bockman Way Sparta TN 38583",
    "addr:housenumber":"207",
    "addr:postcode":"38583",
    "addr:street":"W Bockman Way",
    "iso:country":"US",
    "sg:address":"207 W Bockman Way",
    "sg:city":"Sparta",
    "sg:classifiers":[
        {
            "category":"Health Services",
            "subcategory":"Doctor",
            "type":"Services"
        }
    ],
    "sg:phone":"+1 931 836 6461",
    "sg:postcode":"38583",
    "sg:province":"TN",
    "sg:tags":[
        "physician",
        "surgeon"
    ],
    "wof:name":"Sparta Medcial Clinic",
    "wof:placetype":"venue"
},
  "geometry": {"coordinates":[-85.468541,35.927334],"type":"Point"}
}