{
  "type": "Feature",
  "properties": {
    "iso:country":"US",
    "sg:address":"348 Red River Rd",
    "sg:city":"Gallatin",
    "sg:classifiers":[
        {
            "category":"Autos & Motor Vehicles",
            "subcategory":"Fuel & Gas Station",
            "type":"Retail Goods"
        }
    ],
    "sg:phone":"+1 615 451 0891",
    "sg:postcode":"37066",
    "sg:province":"TN",
    "sg:tags":[
        "station",
        "gasoline"
    ],
    "wof:name":"MAPCO Express",
    "wof:placetype":"venue"
},
  "geometry": {"coordinates":[-86.454476,36.388269],"type":"Point"}
}