{
  "type": "Feature",
  "properties": {
    "iso:country":"US",
    "sg:address":"3922 Mary Lee Dr",
    "sg:city":"Memphis",
    "sg:classifiers":[
        {
            "category":"Professional",
            "subcategory":"Business Services",
            "type":"Services"
        }
    ],
    "sg:phone":"+1 901 332 4727",
    "sg:postcode":"38116",
    "sg:province":"TN",
    "wof:name":"Big Pockets Enterprises Inc",
    "wof:placetype":"venue"
},
  "geometry": {"coordinates":[-90.00863699999999,35.041152],"type":"Point"}
}