{
  "type": "Feature",
  "properties": {
    "iso:country":"US",
    "sg:address":"1119 Alexander St",
    "sg:city":"Knoxville",
    "sg:classifiers":[
        {
            "category":"Professional",
            "type":"Services"
        }
    ],
    "sg:phone":"+1 865 300 5440",
    "sg:postcode":"37917",
    "sg:province":"TN",
    "wof:name":"Mantic Studio",
    "wof:placetype":"venue"
},
  "geometry": {"coordinates":[-83.92837,35.98214],"type":"Point"}
}