{
  "type": "Feature",
  "properties": {
    "iso:country":"US",
    "sg:address":"109 S Highland Ave",
    "sg:city":"Jackson",
    "sg:classifiers":[
        {
            "category":"Government",
            "subcategory":"Court House",
            "type":"Public Place"
        }
    ],
    "sg:phone":"+1 731 422 6220",
    "sg:postcode":"38301",
    "sg:province":"TN",
    "sg:tags":[
        "legal"
    ],
    "wof:name":"Attorneys Executive Off For US",
    "wof:placetype":"venue"
},
  "geometry": {"coordinates":[-88.819486,35.613542],"type":"Point"}
}