{
  "type": "Feature",
  "properties": {
    "iso:country":"US",
    "sg:address":"604 Co Rd 181",
    "sg:city":"Decatur",
    "sg:classifiers":[
        {
            "category":"Personal",
            "type":"Services"
        }
    ],
    "sg:phone":"+1 423 507 8797",
    "sg:postcode":"37322",
    "sg:province":"TN",
    "sg:tags":[
        "therapist",
        "massage"
    ],
    "wof:name":"Pamela Gilmore Massage",
    "wof:placetype":"venue"
},
  "geometry": {"coordinates":[-84.739887,35.492481],"type":"Point"}
}