{
  "type": "Feature",
  "properties": {
    "addr:full":"4427 Murphy Rd Nashville TN 37209",
    "addr:housenumber":"4427",
    "addr:postcode":"37209",
    "addr:street":"Murphy Rd",
    "iso:country":"US",
    "sg:address":"4427 Murphy Rd",
    "sg:city":"Nashville",
    "sg:classifiers":[
        {
            "category":"Restaurant",
            "type":"Food & Drink"
        },
        {
            "category":"Food & Beverages",
            "subcategory":"Groceries & Convenience Stores",
            "type":"Retail Goods"
        }
    ],
    "sg:menulink":"http://www.allmenus.com/tn/nashville/210149-caffe-nonna/menu/",
    "sg:phone":"+1 615 463 0133",
    "sg:postcode":"37209",
    "sg:province":"TN",
    "sg:tags":[
        "italian"
    ],
    "wof:name":"Caffe Nonna",
    "wof:placetype":"venue"
},
  "geometry": {"coordinates":[-86.84010499999999,36.140988],"type":"Point"}
}