{
  "type": "Feature",
  "properties": {
    "iso:country":"US",
    "sg:address":"1949 Kenmont Dr",
    "sg:city":"Cordova",
    "sg:classifiers":[
        {
            "category":"Organizations",
            "subcategory":"Religious Organization",
            "type":"Services"
        }
    ],
    "sg:phone":"+1 901 240 6855",
    "sg:postcode":"38016",
    "sg:province":"TN",
    "wof:name":"Pierce Ministries",
    "wof:placetype":"venue"
},
  "geometry": {"coordinates":[-89.754234,35.178995],"type":"Point"}
}