{
  "type": "Feature",
  "properties": {
    "iso:country":"US",
    "sg:address":"110 State Hwy 114 S",
    "sg:city":"Scotts Hill",
    "sg:classifiers":[
        {
            "category":"Personal",
            "type":"Services"
        }
    ],
    "sg:phone":"+1 731 549 2398",
    "sg:postcode":"38374",
    "sg:province":"TN",
    "sg:tags":[
        "person",
        "bureau",
        "missing"
    ],
    "wof:name":"Scotts Hill Police Dept Amber",
    "wof:placetype":"venue"
},
  "geometry": {"coordinates":[-88.245915,35.51692],"type":"Point"}
}