{
  "type": "Feature",
  "properties": {
    "iso:country":"US",
    "sg:address":"9414 Mercer Rd",
    "sg:city":"Brownsville",
    "sg:classifiers":[
        {
            "category":"Food & Beverages",
            "subcategory":"Groceries & Convenience Stores",
            "type":"Retail Goods"
        }
    ],
    "sg:phone":"+1 731 772 9729",
    "sg:postcode":"38012",
    "sg:province":"TN",
    "wof:name":"Rossons Grocery",
    "wof:placetype":"venue"
},
  "geometry": {"coordinates":[-89.12345000000001,35.525595],"type":"Point"}
}