{
  "type": "Feature",
  "properties": {
    "iso:country":"US",
    "sg:address":"2090 Kirby Pkwy",
    "sg:city":"Memphis",
    "sg:classifiers":[
        {
            "category":"Real Estate",
            "subcategory":"Real Estate Agent",
            "type":"Services"
        }
    ],
    "sg:phone":"+1 901 757 7911",
    "sg:postcode":"38119",
    "sg:province":"TN",
    "wof:name":"Eddins Appraisal Service",
    "wof:placetype":"venue"
},
  "geometry": {"coordinates":[-89.84009500000001,35.092353],"type":"Point"}
}