{
  "type": "Feature",
  "properties": {
    "iso:country":"US",
    "sg:address":"1107 N Durham Ave",
    "sg:city":"Sharon",
    "sg:classifiers":[
        {
            "category":"Manufacturing",
            "subcategory":"Tools & Machinery",
            "type":"Manufacturing & Wholesale Goods"
        }
    ],
    "sg:phone":"+1 731 456 2776",
    "sg:postcode":"38255",
    "sg:province":"TN",
    "sg:tags":[
        "machine",
        "shop",
        "industrial",
        "mfg"
    ],
    "wof:name":"Ary Tool and Die",
    "wof:placetype":"venue"
},
  "geometry": {"coordinates":[-88.82288200000001,36.252474],"type":"Point"}
}