{
  "type": "Feature",
  "properties": {
    "iso:country":"US",
    "sg:address":"3329 Pinewood Ave",
    "sg:city":"Chattanooga",
    "sg:classifiers":[
        {
            "category":"Real Estate",
            "subcategory":"Real Estate Agent",
            "type":"Services"
        }
    ],
    "sg:phone":"+1 423 629 8009",
    "sg:postcode":"37411",
    "sg:province":"TN",
    "wof:name":"Restis Properties Inc",
    "wof:placetype":"venue"
},
  "geometry": {"coordinates":[-85.251417,35.030232],"type":"Point"}
}