{
  "type": "Feature",
  "properties": {
    "iso:country":"US",
    "sg:address":"481 Railroad Ave",
    "sg:city":"Tracy City",
    "sg:classifiers":[
        {
            "category":"Government",
            "subcategory":"Office",
            "type":"Public Place"
        }
    ],
    "sg:phone":"+1 931 592 1111",
    "sg:postcode":"37380",
    "sg:province":"TN",
    "sg:tags":[
        "county"
    ],
    "wof:name":"Citizens Tri County Bank 24",
    "wof:placetype":"venue"
},
  "geometry": {"coordinates":[-85.705386,35.008697],"type":"Point"}
}