{
  "type": "Feature",
  "properties": {
    "iso:country":"US",
    "sg:address":"205 Ausmus Rd",
    "sg:city":"Speedwell",
    "sg:classifiers":[
        {
            "category":"Wholesale",
            "subcategory":"Auto Parts",
            "type":"Manufacturing & Wholesale Goods"
        }
    ],
    "sg:phone":"+1 423 869 4423",
    "sg:postcode":"37870",
    "sg:province":"TN",
    "sg:tags":[
        "automobile",
        "rebuilt",
        "used"
    ],
    "wof:name":"E & C Auto Cycle & Salvage",
    "wof:placetype":"venue"
},
  "geometry": {"coordinates":[-83.804304,36.496458],"type":"Point"}
}