{
  "type": "Feature",
  "properties": {
    "iso:country":"US",
    "sg:address":"2237 Forks River Rd",
    "sg:city":"Waverly",
    "sg:classifiers":[
        {
            "category":"Farming",
            "subcategory":"Farm",
            "type":"Manufacturing & Wholesale Goods"
        }
    ],
    "sg:phone":"+1 931 296 7819",
    "sg:postcode":"37185",
    "sg:province":"TN",
    "sg:tags":[
        "crop",
        "general"
    ],
    "wof:name":"William Lee Rushton",
    "wof:placetype":"venue"
},
  "geometry": {"coordinates":[-87.82374799999999,36.041462],"type":"Point"}
}