{
  "type": "Feature",
  "properties": {
    "iso:country":"US",
    "sg:address":"2007 Wayne Rd",
    "sg:city":"Savannah",
    "sg:classifiers":[
        {
            "category":"Shopping",
            "subcategory":"Discount & Variety Stores",
            "type":"Retail Goods"
        },
        {
            "category":"Shopping",
            "subcategory":"Department Store",
            "type":"Retail Goods"
        }
    ],
    "sg:phone":"+1 731 925 8035",
    "sg:postcode":"38372",
    "sg:province":"TN",
    "sg:tags":[
        "shop"
    ],
    "wof:name":"Family Dollar Stores",
    "wof:placetype":"venue"
},
  "geometry": {"coordinates":[-88.230486,35.227062],"type":"Point"}
}