{
  "type": "Feature",
  "properties": {
    "iso:country":"US",
    "sg:address":"2238 Pete Mitchell Rd",
    "sg:city":"Germantown",
    "sg:classifiers":[
        {
            "category":"Professional",
            "subcategory":"Business Services",
            "type":"Services"
        }
    ],
    "sg:phone":"+1 901 751 0484",
    "sg:postcode":"38138",
    "sg:province":"TN",
    "sg:tags":[
        "broker"
    ],
    "wof:name":"John Mc Cain Co",
    "wof:placetype":"venue"
},
  "geometry": {"coordinates":[-89.80297299999999,35.088811],"type":"Point"}
}