{
  "type": "Feature",
  "properties": {
    "iso:country":"US",
    "sg:address":"4782 Mallard Lake Cove",
    "sg:city":"Collierville",
    "sg:classifiers":[
        {
            "category":"Building & Trades",
            "subcategory":"Plumbing",
            "type":"Services"
        }
    ],
    "sg:phone":"+1 901 385 8115",
    "sg:postcode":"38017",
    "sg:province":"TN",
    "sg:tags":[
        "heating",
        "contractor"
    ],
    "wof:name":"B & K Appliance Repair & AC",
    "wof:placetype":"venue"
},
  "geometry": {"coordinates":[-89.742406,35.018105],"type":"Point"}
}