{
  "type": "Feature",
  "properties": {
    "addr:full":"6181 Greenbrier Cemetery Rd Greenbrier TN 37073",
    "addr:housenumber":"6181",
    "addr:postcode":"37073",
    "addr:street":"Greenbrier Cemetery Rd",
    "iso:country":"US",
    "sg:address":"6181 Greenbrier Cemetery Rd",
    "sg:city":"Greenbrier",
    "sg:classifiers":[
        {
            "category":"Shopping",
            "subcategory":"Clothing, Apparel, & Fashions",
            "type":"Retail Goods"
        }
    ],
    "sg:phone":"+1 615 643 0836",
    "sg:postcode":"37073",
    "sg:province":"TN",
    "wof:name":"Shirts More Ltd",
    "wof:placetype":"venue"
},
  "geometry": {"coordinates":[-86.799708,36.447284],"type":"Point"}
}