{
  "type": "Feature",
  "properties": {
    "iso:country":"US",
    "sg:address":"2038 W Van Hook St",
    "sg:city":"Milan",
    "sg:classifiers":[
        {
            "category":"Real Estate",
            "subcategory":"Real Estate Agent",
            "type":"Services"
        }
    ],
    "sg:phone":"+1 731 855 4585",
    "sg:postcode":"38358",
    "sg:province":"TN",
    "wof:name":"Coldwell Banker",
    "wof:placetype":"venue"
},
  "geometry": {"coordinates":[-88.758634,35.913071],"type":"Point"}
}