{
  "type": "Feature",
  "properties": {
    "iso:country":"US",
    "sg:address":"70 N 4th St",
    "sg:city":"Memphis",
    "sg:classifiers":[
        {
            "category":"Professional",
            "subcategory":"Management & Consulting",
            "type":"Services"
        }
    ],
    "sg:phone":"+1 901 522 9011",
    "sg:postcode":"38103",
    "sg:province":"TN",
    "sg:tags":[
        "marketing",
        "consultant"
    ],
    "wof:name":"Alternative Marketing & Design",
    "wof:placetype":"venue"
},
  "geometry": {"coordinates":[-90.04701900000001,35.144806],"type":"Point"}
}