{
  "type": "Feature",
  "properties": {
    "iso:country":"US",
    "sg:address":"7531 US Hwy 64",
    "sg:city":"Memphis",
    "sg:classifiers":[
        {
            "category":"Health Services",
            "subcategory":"Podiatrist",
            "type":"Services"
        }
    ],
    "sg:phone":"+1 901 377 0737",
    "sg:postcode":"38133",
    "sg:province":"TN",
    "wof:name":"Active Foot Supply",
    "wof:placetype":"venue"
},
  "geometry": {"coordinates":[-89.810644,35.204657],"type":"Point"}
}