{
  "type": "Feature",
  "properties": {
    "iso:country":"US",
    "sg:address":"2542 Lebanon Pike",
    "sg:city":"Nashville",
    "sg:classifiers":[
        {
            "category":"Shopping",
            "subcategory":"Florist",
            "type":"Retail Goods"
        }
    ],
    "sg:phone":"+1 615 883 4360",
    "sg:postcode":"37214",
    "sg:province":"TN",
    "sg:tags":[
        "personal",
        "eating"
    ],
    "wof:name":"Leaf & Petal Florist Inc",
    "wof:placetype":"venue"
},
  "geometry": {"coordinates":[-86.67752299999999,36.169701],"type":"Point"}
}