{
  "type": "Feature",
  "properties": {
    "addr:full":"2342 Southgate Blvd Murfreesboro TN 37128",
    "addr:housenumber":"2342",
    "addr:postcode":"37128",
    "addr:street":"Southgate Blvd",
    "iso:country":"US",
    "sg:address":"2342 Southgate Blvd",
    "sg:city":"Murfreesboro",
    "sg:classifiers":[
        {
            "category":"Real Estate",
            "subcategory":"Real Estate Agent",
            "type":"Services"
        }
    ],
    "sg:phone":"+1 615 217 4367",
    "sg:postcode":"37128",
    "sg:province":"TN",
    "wof:name":"Hearthwood Properties",
    "wof:placetype":"venue"
},
  "geometry": {"coordinates":[-86.39921200000001,35.810617],"type":"Point"}
}