{
  "type": "Feature",
  "properties": {
    "iso:country":"US",
    "sg:address":"629 Chelsea Ave",
    "sg:city":"Memphis",
    "sg:classifiers":[
        {
            "category":"Restaurant",
            "type":"Food & Drink"
        }
    ],
    "sg:phone":"+1 901 522 0145",
    "sg:postcode":"38107",
    "sg:province":"TN",
    "wof:name":"Curry's Hot Wings",
    "wof:placetype":"venue"
},
  "geometry": {"coordinates":[-90.038371,35.16315],"type":"Point"}
}