{
  "type": "Feature",
  "properties": {
    "iso:country":"US",
    "sg:address":"2400 Buena Vista Pike",
    "sg:city":"Nashville",
    "sg:classifiers":[
        {
            "category":"Real Estate",
            "subcategory":"Real Estate Operator",
            "type":"Services"
        }
    ],
    "sg:phone":"+1 615 256 7727",
    "sg:postcode":"37218",
    "sg:province":"TN",
    "sg:tags":[
        "building",
        "apartment"
    ],
    "wof:name":"Buena Vista Manor Apartments",
    "wof:placetype":"venue"
},
  "geometry": {"coordinates":[-86.823128,36.200894],"type":"Point"}
}