{
  "type": "Feature",
  "properties": {
    "addr:full":"4397 E Morris Blvd Morristown TN 37813",
    "addr:housenumber":"4397",
    "addr:postcode":"37813",
    "addr:street":"E Morris Blvd",
    "iso:country":"US",
    "sg:address":"4397 E Morris Blvd",
    "sg:city":"Morristown",
    "sg:classifiers":[
        {
            "category":"Restaurant",
            "type":"Food & Drink"
        }
    ],
    "sg:phone":"+1 423 587 1511",
    "sg:postcode":"37813",
    "sg:province":"TN",
    "wof:name":"G Z's Grill",
    "wof:placetype":"venue"
},
  "geometry": {"coordinates":[-83.23688,36.235708],"type":"Point"}
}