{
  "type": "Feature",
  "properties": {
    "iso:country":"US",
    "sg:address":"369 2nd Ave",
    "sg:city":"Dayton",
    "sg:classifiers":[
        {
            "category":"Professional",
            "type":"Services"
        }
    ],
    "sg:phone":"+1 423 775 5961",
    "sg:postcode":"37321",
    "sg:province":"TN",
    "sg:tags":[
        "establishment"
    ],
    "wof:name":"CIS",
    "wof:placetype":"venue"
},
  "geometry": {"coordinates":[-85.013426,35.494731],"type":"Point"}
}