{
  "type": "Feature",
  "properties": {
    "iso:country":"US",
    "sg:address":"100 Cherokee Blvd",
    "sg:city":"Chattanooga",
    "sg:classifiers":[
        {
            "category":"Wholesale",
            "subcategory":"Computers",
            "type":"Manufacturing & Wholesale Goods"
        }
    ],
    "sg:phone":"+1 423 267 7676",
    "sg:postcode":"37405",
    "sg:province":"TN",
    "sg:tags":[
        "software"
    ],
    "wof:name":"Bytes & Bytes LLC",
    "wof:placetype":"venue"
},
  "geometry": {"coordinates":[-85.311026,35.063983],"type":"Point"}
}