{
  "type": "Feature",
  "properties": {
    "iso:country":"US",
    "sg:address":"5402 Longview Dr",
    "sg:city":"Hixson",
    "sg:classifiers":[
        {
            "category":"Retail",
            "subcategory":"Portrait Studio",
            "type":"Services"
        }
    ],
    "sg:phone":"+1 423 842 9114",
    "sg:postcode":"37343",
    "sg:province":"TN",
    "sg:tags":[
        "photo"
    ],
    "sg:website":"www.aslingerphotography.com",
    "wof:name":"Barry Aslinger Photography",
    "wof:placetype":"venue"
},
  "geometry": {"coordinates":[-85.231499,35.140845],"type":"Point"}
}