{
  "type": "Feature",
  "properties": {
    "iso:country":"US",
    "sg:address":"9111 Executive Park Dr",
    "sg:city":"Knoxville",
    "sg:classifiers":[
        {
            "category":"Professional",
            "type":"Services"
        }
    ],
    "sg:phone":"+1 865 694 8317",
    "sg:postcode":"37923",
    "sg:province":"TN",
    "wof:name":"Far East Market",
    "wof:placetype":"venue"
},
  "geometry": {"coordinates":[-84.08672799999999,35.92078],"type":"Point"}
}