{
  "type": "Feature",
  "properties": {
    "addr:full":"873 S Shady St Mountain City TN 37683",
    "addr:housenumber":"873",
    "addr:postcode":"37683",
    "addr:street":"S Shady St",
    "iso:country":"US",
    "sg:address":"873 S Shady St",
    "sg:city":"Mountain City",
    "sg:classifiers":[
        {
            "category":"Food & Beverages",
            "subcategory":"Bakery",
            "type":"Retail Goods"
        }
    ],
    "sg:phone":"+1 423 727 4772",
    "sg:postcode":"37683",
    "sg:province":"TN",
    "sg:tags":[
        "doughnut"
    ],
    "wof:name":"Daylight Donuts",
    "wof:placetype":"venue"
},
  "geometry": {"coordinates":[-81.802268,36.466167],"type":"Point"}
}