{
  "type": "Feature",
  "properties": {
    "addr:full":"7697 Winchester Rd Memphis TN 38125",
    "addr:housenumber":"7697",
    "addr:postcode":"38125",
    "addr:street":"Winchester Rd",
    "iso:country":"US",
    "sg:address":"7697 Winchester Rd",
    "sg:city":"Memphis",
    "sg:phone":"+1 901 248 0250",
    "sg:postcode":"38125",
    "sg:province":"TN",
    "sg:website":"http://www.target.com",
    "wof:name":"Target",
    "wof:placetype":"venue"
},
  "geometry": {"coordinates":[-89.80674500000001,35.049563],"type":"Point"}
}