{
  "type": "Feature",
  "properties": {
    "iso:country":"US",
    "sg:address":"724 Liberty Bell Blvd",
    "sg:city":"Johnson City",
    "sg:classifiers":[
        {
            "category":"Recreation",
            "type":"Entertainment"
        }
    ],
    "sg:phone":"+1 423 926 2726",
    "sg:postcode":"37604",
    "sg:province":"TN",
    "sg:tags":[
        "skating",
        "rink"
    ],
    "wof:name":"Johnson City Family Skate Ctr",
    "wof:placetype":"venue"
},
  "geometry": {"coordinates":[-82.378879,36.327699],"type":"Point"}
}