{
  "type": "Feature",
  "properties": {
    "iso:country":"US",
    "sg:address":"705 Hill Ave",
    "sg:city":"Nashville",
    "sg:classifiers":[
        {
            "category":"Freight",
            "type":"Transportation"
        }
    ],
    "sg:phone":"+1 615 254 5751",
    "sg:postcode":"37210",
    "sg:province":"TN",
    "sg:tags":[
        "trucking"
    ],
    "wof:name":"Old Dominion Freight Line Inc",
    "wof:placetype":"venue"
},
  "geometry": {"coordinates":[-86.732855,36.137595],"type":"Point"}
}