{
  "type": "Feature",
  "properties": {
    "iso:country":"US",
    "sg:address":"2286 McFarlin Rd",
    "sg:city":"Nolensville",
    "sg:classifiers":[
        {
            "category":"Retail",
            "subcategory":"Auto Repair",
            "type":"Services"
        }
    ],
    "sg:phone":"+1 615 776 2858",
    "sg:postcode":"37135",
    "sg:province":"TN",
    "sg:tags":[
        "transmission"
    ],
    "wof:name":"Pomeroy's Auto Repair",
    "wof:placetype":"venue"
},
  "geometry": {"coordinates":[-86.6236,35.968767],"type":"Point"}
}