{
  "type": "Feature",
  "properties": {
    "iso:country":"US",
    "sg:address":"9129 Executive Park Dr",
    "sg:city":"Knoxville",
    "sg:classifiers":[
        {
            "category":"Shopping",
            "subcategory":"Discount & Variety Stores",
            "type":"Retail Goods"
        }
    ],
    "sg:phone":"+1 865 531 0663",
    "sg:postcode":"37923",
    "sg:province":"TN",
    "wof:name":"Dollar General",
    "wof:placetype":"venue"
},
  "geometry": {"coordinates":[-84.087785,35.920549],"type":"Point"}
}