{
  "type": "Feature",
  "properties": {
    "iso:country":"US",
    "sg:address":"205 S Washington St",
    "sg:city":"Bolivar",
    "sg:classifiers":[
        {
            "category":"Shopping",
            "subcategory":"Florist",
            "type":"Retail Goods"
        }
    ],
    "sg:phone":"+1 731 658 3518",
    "sg:postcode":"38008",
    "sg:province":"TN",
    "sg:tags":[
        "merchandise"
    ],
    "wof:name":"Bill's Flower Shop",
    "wof:placetype":"venue"
},
  "geometry": {"coordinates":[-88.989069,35.255371],"type":"Point"}
}