{
  "type": "Feature",
  "properties": {
    "iso:country":"US",
    "sg:address":"855 Willow Tree Cir",
    "sg:city":"Cordova",
    "sg:classifiers":[
        {
            "category":"Mining & Drilling",
            "type":"Manufacturing & Wholesale Goods"
        }
    ],
    "sg:phone":"+1 901 751 1130",
    "sg:postcode":"38018",
    "sg:province":"TN",
    "sg:tags":[
        "stone"
    ],
    "wof:name":"Romance The Stone",
    "wof:placetype":"venue"
},
  "geometry": {"coordinates":[-89.79298300000001,35.148464],"type":"Point"}
}