{
  "type": "Feature",
  "properties": {
    "iso:country":"US",
    "sg:address":"109 Jack White Dr",
    "sg:city":"Kingsport",
    "sg:classifiers":[
        {
            "category":"Restaurant",
            "type":"Food & Drink"
        }
    ],
    "sg:phone":"+1 423 245 2565",
    "sg:postcode":"37664",
    "sg:province":"TN",
    "sg:tags":[
        "eating"
    ],
    "wof:name":"Wrights Country Cuisine Inc",
    "wof:placetype":"venue"
},
  "geometry": {"coordinates":[-82.51875800000001,36.545412],"type":"Point"}
}