{
  "type": "Feature",
  "properties": {
    "iso:country":"US",
    "sg:address":"6730 Pennywell Dr",
    "sg:city":"Nashville",
    "sg:classifiers":[
        {
            "category":"Professional",
            "subcategory":"Computer Services",
            "type":"Services"
        }
    ],
    "sg:phone":"+1 615 579 7874",
    "sg:postcode":"37205",
    "sg:province":"TN",
    "wof:name":"Neopc Of Nashville",
    "wof:placetype":"venue"
},
  "geometry": {"coordinates":[-86.903656,36.111925],"type":"Point"}
}