{
  "type": "Feature",
  "properties": {
    "addr:full":"1037 Lake City Hwy Clinton TN 37716",
    "addr:housenumber":"1037",
    "addr:postcode":"37716",
    "addr:street":"Lake City Hwy",
    "iso:country":"US",
    "sg:address":"1037 Lake City Hwy",
    "sg:city":"Clinton",
    "sg:classifiers":[
        {
            "category":"Food & Beverages",
            "subcategory":"Fruits & Vegetables",
            "type":"Retail Goods"
        }
    ],
    "sg:phone":"+1 865 457 2903",
    "sg:postcode":"37716",
    "sg:province":"TN",
    "sg:tags":[
        "nursery"
    ],
    "wof:name":"Cumberland Mountain Nursey",
    "wof:placetype":"venue"
},
  "geometry": {"coordinates":[-84.14404999999999,36.124487],"type":"Point"}
}