{
  "type": "Feature",
  "properties": {
    "addr:full":"3150 Village Shops Dr Germantown TN 38138",
    "addr:housenumber":"3150",
    "addr:postcode":"38138",
    "addr:street":"Village Shops Dr",
    "iso:country":"US",
    "sg:address":"3150 Village Shops Dr",
    "sg:city":"Germantown",
    "sg:classifiers":[
        {
            "category":"Banks & Credit Unions",
            "subcategory":"Bank",
            "type":"Services"
        }
    ],
    "sg:phone":"+1 901 523 4444",
    "sg:postcode":"38138",
    "sg:province":"TN",
    "wof:name":"First Tennessee Bank-Grmntwn",
    "wof:placetype":"venue"
},
  "geometry": {"coordinates":[-89.75831599999999,35.06499],"type":"Point"}
}