{
  "type": "Feature",
  "properties": {
    "iso:country":"US",
    "sg:address":"1471 Lower Sharon Rd",
    "sg:city":"Dresden",
    "sg:phone":"+1 731 364 2845",
    "sg:postcode":"38225",
    "sg:province":"TN",
    "sg:tags":[
        "farm",
        "soybean"
    ],
    "wof:name":"Nanney Eulaine",
    "wof:placetype":"venue"
},
  "geometry": {"coordinates":[-88.753253,36.250058],"type":"Point"}
}