{
  "type": "Feature",
  "properties": {
    "addr:full":"8321 Sawyer Brown Rd Nashville TN 37221",
    "addr:housenumber":"8321",
    "addr:postcode":"37221",
    "addr:street":"Sawyer Brown Rd",
    "iso:country":"US",
    "sg:address":"8321 Sawyer Brown Rd",
    "sg:city":"Nashville",
    "sg:classifiers":[
        {
            "category":"Restaurant",
            "type":"Food & Drink"
        }
    ],
    "sg:phone":"+1 615 646 9116",
    "sg:postcode":"37221",
    "sg:province":"TN",
    "sg:tags":[
        "caterer"
    ],
    "wof:name":"Notable Coffee & Catering",
    "wof:placetype":"venue"
},
  "geometry": {"coordinates":[-86.94499500000001,36.077622],"type":"Point"}
}