{
  "type": "Feature",
  "properties": {
    "iso:country":"US",
    "sg:address":"403 E College St",
    "sg:city":"Pulaski",
    "sg:classifiers":[
        {
            "category":"Health Services",
            "subcategory":"Doctor",
            "type":"Services"
        }
    ],
    "sg:phone":"+1 931 424 7250",
    "sg:postcode":"38478",
    "sg:province":"TN",
    "sg:tags":[
        "dentist"
    ],
    "wof:name":"Matthew Mc Masters DDS",
    "wof:placetype":"venue"
},
  "geometry": {"coordinates":[-87.027433,35.195214],"type":"Point"}
}