{
  "type": "Feature",
  "properties": {
    "iso:country":"US",
    "sg:address":"614 S Highland St",
    "sg:city":"Memphis",
    "sg:classifiers":[
        {
            "category":"Deli",
            "type":"Food & Drink"
        },
        {
            "category":"Restaurant",
            "type":"Food & Drink"
        },
        {
            "category":"Food & Beverages",
            "subcategory":"Groceries & Convenience Stores",
            "type":"Retail Goods"
        }
    ],
    "sg:phone":"+1 901 324 3728",
    "sg:postcode":"38111",
    "sg:province":"TN",
    "sg:tags":[
        "shop",
        "delicatessen",
        "sandwich"
    ],
    "wof:name":"Super Submarine Sandwich Shops",
    "wof:placetype":"venue"
},
  "geometry": {"coordinates":[-89.945784,35.114693],"type":"Point"}
}