{
  "type": "Feature",
  "properties": {
    "iso:country":"US",
    "sg:address":"8047 Old Charlotte Pike",
    "sg:city":"Nashville",
    "sg:classifiers":[
        {
            "category":"Professional",
            "subcategory":"Business Services",
            "type":"Services"
        }
    ],
    "sg:phone":"+1 615 533 9492",
    "sg:postcode":"37209",
    "sg:province":"TN",
    "wof:name":"Keown Enterprises LLC",
    "wof:placetype":"venue"
},
  "geometry": {"coordinates":[-86.968458,36.118134],"type":"Point"}
}