{
  "type": "Feature",
  "properties": {
    "iso:country":"US",
    "sg:address":"3384 Austin Peay Hwy",
    "sg:city":"Memphis",
    "sg:classifiers":[
        {
            "category":"Shopping",
            "subcategory":"Jewelry",
            "type":"Retail Goods"
        }
    ],
    "sg:phone":"+1 901 388 8002",
    "sg:postcode":"38128",
    "sg:province":"TN",
    "wof:name":"Jewelry Center",
    "wof:placetype":"venue"
},
  "geometry": {"coordinates":[-89.912702,35.217359],"type":"Point"}
}