{
  "type": "Feature",
  "properties": {
    "addr:full":"1116 W 7th St Columbia TN 38401",
    "addr:housenumber":"1116",
    "addr:postcode":"38401",
    "addr:street":"W 7Th St",
    "iso:country":"US",
    "sg:address":"1116 W 7th St",
    "sg:city":"Columbia",
    "sg:classifiers":[
        {
            "category":"Building & Trades",
            "subcategory":"Construction",
            "type":"Services"
        }
    ],
    "sg:phone":"+1 931 381 1040",
    "sg:postcode":"38401",
    "sg:province":"TN",
    "sg:tags":[
        "sanitary",
        "marking",
        "con",
        "maintenance",
        "parking"
    ],
    "wof:name":"Volunteer State Sweepers",
    "wof:placetype":"venue"
},
  "geometry": {"coordinates":[-87.063936,35.617673],"type":"Point"}
}