{
  "type": "Feature",
  "properties": {
    "iso:country":"US",
    "sg:address":"914 N Union Grove Rd",
    "sg:city":"Friendsville",
    "sg:classifiers":[
        {
            "category":"Building & Trades",
            "subcategory":"Cleaning & Sanitation",
            "type":"Services"
        }
    ],
    "sg:phone":"+1 865 995 1699",
    "sg:postcode":"37737",
    "sg:province":"TN",
    "sg:tags":[
        "janitor"
    ],
    "wof:name":"Clean Sweep Maid Svc",
    "wof:placetype":"venue"
},
  "geometry": {"coordinates":[-84.080939,35.771162],"type":"Point"}
}