{
  "type": "Feature",
  "properties": {
    "addr:full":"347 Herrell Ln Powell TN 37849",
    "addr:housenumber":"347",
    "addr:postcode":"37849",
    "addr:street":"Herrell Ln",
    "iso:country":"US",
    "sg:address":"347 Herrell Ln",
    "sg:city":"Powell",
    "sg:classifiers":[
        {
            "category":"Manufacturing",
            "subcategory":"Lumber",
            "type":"Manufacturing & Wholesale Goods"
        }
    ],
    "sg:phone":"+1 865 945 5552",
    "sg:postcode":"37849",
    "sg:province":"TN",
    "sg:tags":[
        "planing",
        "mills",
        "sawmill"
    ],
    "wof:name":"Myers Excavating",
    "wof:placetype":"venue"
},
  "geometry": {"coordinates":[-84.087259,36.059448],"type":"Point"}
}