{
  "type": "Feature",
  "properties": {
    "iso:country":"US",
    "sg:address":"6133 E Brainerd Rd",
    "sg:city":"Chattanooga",
    "sg:classifiers":[
        {
            "category":"Real Estate",
            "subcategory":"Real Estate Agent",
            "type":"Services"
        }
    ],
    "sg:phone":"+1 423 894 2087",
    "sg:postcode":"37421",
    "sg:province":"TN",
    "wof:name":"Norman Caroldean",
    "wof:placetype":"venue"
},
  "geometry": {"coordinates":[-85.200937,35.016087],"type":"Point"}
}