{
  "type": "Feature",
  "properties": {
    "iso:country":"US",
    "sg:address":"1105 Congress Pkwy NW",
    "sg:city":"Athens",
    "sg:classifiers":[
        {
            "category":"Retail",
            "subcategory":"Auto Repair",
            "type":"Services"
        }
    ],
    "sg:phone":"+1 423 745 3017",
    "sg:postcode":"37303",
    "sg:province":"TN",
    "sg:tags":[
        "body",
        "automobile",
        "painting"
    ],
    "wof:name":"Service Body-Auto Clean-Up",
    "wof:placetype":"venue"
},
  "geometry": {"coordinates":[-84.618207,35.45584],"type":"Point"}
}