{
  "type": "Feature",
  "properties": {
    "iso:country":"US",
    "sg:address":"213 W Main St",
    "sg:city":"Gallatin",
    "sg:classifiers":[
        {
            "category":"Shopping",
            "subcategory":"Florist",
            "type":"Retail Goods"
        }
    ],
    "sg:phone":"+1 615 452 1679",
    "sg:postcode":"37066",
    "sg:province":"TN",
    "wof:name":"Gallatin Flwr Gift Shoppe LLC",
    "wof:placetype":"venue"
},
  "geometry": {"coordinates":[-86.44936800000001,36.387472],"type":"Point"}
}