{
  "type": "Feature",
  "properties": {
    "iso:country":"US",
    "sg:address":"1000 Val St",
    "sg:city":"Knoxville",
    "sg:classifiers":[
        {
            "category":"Real Estate",
            "subcategory":"Real Estate Agent",
            "type":"Services"
        }
    ],
    "sg:phone":"+1 865 470 2971",
    "sg:postcode":"37921",
    "sg:province":"TN",
    "sg:tags":[
        "appraiser"
    ],
    "wof:name":"Sara Long",
    "wof:placetype":"venue"
},
  "geometry": {"coordinates":[-83.933612,35.977579],"type":"Point"}
}