{
  "type": "Feature",
  "properties": {
    "addr:full":"2592 Memorial Blvd Springfield TN 37172",
    "addr:housenumber":"2592",
    "addr:postcode":"37172",
    "addr:street":"Memorial Blvd",
    "iso:country":"US",
    "sg:address":"2592 Memorial Blvd",
    "sg:city":"Springfield",
    "sg:classifiers":[
        {
            "category":"Shopping",
            "subcategory":"Beauty & Cosmetics",
            "type":"Retail Goods"
        }
    ],
    "sg:phone":"+1 615 384 9333",
    "sg:postcode":"37172",
    "sg:province":"TN",
    "sg:tags":[
        "merchandise"
    ],
    "wof:name":"Sally Beauty Supply",
    "wof:placetype":"venue"
},
  "geometry": {"coordinates":[-86.865959,36.488115],"type":"Point"}
}