{
  "type": "Feature",
  "properties": {
    "iso:country":"US",
    "sg:address":"3615 Western Ave",
    "sg:city":"Knoxville",
    "sg:classifiers":[
        {
            "category":"Shopping",
            "subcategory":"Music",
            "type":"Retail Goods"
        }
    ],
    "sg:phone":"+1 865 525 2626",
    "sg:postcode":"37921",
    "sg:province":"TN",
    "sg:tags":[
        "compact",
        "record",
        "disc",
        "tape"
    ],
    "sg:website":"www.jkmusiconline.com",
    "wof:name":"J K Music Inc",
    "wof:placetype":"venue"
},
  "geometry": {"coordinates":[-83.972638,35.974781],"type":"Point"}
}