{
  "type": "Feature",
  "properties": {
    "addr:full":"3700 Schaad Rd Knoxville TN 37921",
    "addr:postcode":"3700;37921",
    "addr:street":"Schaad Rd",
    "iso:country":"US",
    "sg:address":"3700 Schaad Rd",
    "sg:city":"Knoxville",
    "sg:classifiers":[
        {
            "category":"Organizations",
            "subcategory":"Religious Organization",
            "type":"Services"
        }
    ],
    "sg:phone":"+1 865 691 8331",
    "sg:postcode":"37921",
    "sg:province":"TN",
    "wof:name":"Tekoa Baptist Church",
    "wof:placetype":"venue"
},
  "geometry": {"coordinates":[-84.03747199999999,35.993584],"type":"Point"}
}