{
  "type": "Feature",
  "properties": {
    "iso:country":"US",
    "sg:address":"4280 Boyds Creek Hwy",
    "sg:city":"Sevierville",
    "sg:classifiers":[
        {
            "category":"Travel",
            "subcategory":"Travel Agent",
            "type":"Entertainment"
        }
    ],
    "sg:phone":"+1 865 908 3335",
    "sg:postcode":"37876",
    "sg:province":"TN",
    "sg:tags":[
        "operator",
        "tour"
    ],
    "wof:name":"Tour Tennessee Receptive LLC",
    "wof:placetype":"venue"
},
  "geometry": {"coordinates":[-83.587805,35.927528],"type":"Point"}
}