{
  "type": "Feature",
  "properties": {
    "iso:country":"US",
    "sg:address":"3301 Winbrook Dr",
    "sg:city":"Memphis",
    "sg:classifiers":[
        {
            "category":"Wholesale",
            "subcategory":"Groceries",
            "type":"Manufacturing & Wholesale Goods"
        }
    ],
    "sg:phone":"+1 901 398 4777",
    "sg:postcode":"38116",
    "sg:province":"TN",
    "sg:tags":[
        "produce"
    ],
    "wof:name":"Metro Foods of Memphis",
    "wof:placetype":"venue"
},
  "geometry": {"coordinates":[-89.997534,35.057147],"type":"Point"}
}