{
  "type": "Feature",
  "properties": {
    "addr:full":"10537 Lexington Dr Knoxville TN 37932",
    "addr:housenumber":"10537",
    "addr:postcode":"37932",
    "addr:street":"Lexington Dr",
    "iso:country":"US",
    "sg:address":"10537 Lexington Dr",
    "sg:city":"Knoxville",
    "sg:classifiers":[
        {
            "category":"Professional",
            "type":"Services"
        }
    ],
    "sg:phone":"+1 865 966 7164",
    "sg:postcode":"37932",
    "sg:province":"TN",
    "sg:tags":[
        "establishment"
    ],
    "wof:name":"TTL Medical",
    "wof:placetype":"venue"
},
  "geometry": {"coordinates":[-84.138622,35.91046],"type":"Point"}
}