{
  "type": "Feature",
  "properties": {
    "iso:country":"US",
    "sg:address":"3059 Jefferson Rd",
    "sg:city":"Smithville",
    "sg:phone":"+1 615 597 4137",
    "sg:postcode":"37166",
    "sg:province":"TN",
    "sg:tags":[
        "farm",
        "field",
        "crop",
        "preparation",
        "soil"
    ],
    "wof:name":"Aaron Webb",
    "wof:placetype":"venue"
},
  "geometry": {"coordinates":[-85.71033300000001,35.895276],"type":"Point"}
}