{
  "type": "Feature",
  "properties": {
    "iso:country":"US",
    "sg:address":"11 Rivers Run Way",
    "sg:city":"Oak Ridge",
    "sg:classifiers":[
        {
            "category":"Food & Beverages",
            "subcategory":"Bakery",
            "type":"Retail Goods"
        }
    ],
    "sg:phone":"+1 865 481 3568",
    "sg:postcode":"37830",
    "sg:province":"TN",
    "wof:name":"Great American Cookie Co",
    "wof:placetype":"venue"
},
  "geometry": {"coordinates":[-84.17832799999999,36.024011],"type":"Point"}
}