{
  "type": "Feature",
  "properties": {
    "iso:country":"US",
    "sg:address":"6727 Heritage Business Ct",
    "sg:city":"Chattanooga",
    "sg:classifiers":[
        {
            "category":"Professional",
            "subcategory":"Accounting & Tax Preparation",
            "type":"Services"
        }
    ],
    "sg:phone":"+1 423 499 5859",
    "sg:postcode":"37421",
    "sg:province":"TN",
    "sg:tags":[
        "bookkeeping",
        "general"
    ],
    "wof:name":"Bookkeeping Solutions",
    "wof:placetype":"venue"
},
  "geometry": {"coordinates":[-85.174482,35.035925],"type":"Point"}
}