{
  "type": "Feature",
  "properties": {
    "iso:country":"US",
    "sg:address":"5729 Collinwood Ct",
    "sg:city":"Antioch",
    "sg:classifiers":[
        {
            "category":"Social Services",
            "subcategory":"Child Care",
            "type":"Services"
        }
    ],
    "sg:phone":"+1 615 331 3939",
    "sg:postcode":"37013",
    "sg:province":"TN",
    "sg:tags":[
        "day"
    ],
    "wof:name":"After Care Birth Doulas",
    "wof:placetype":"venue"
},
  "geometry": {"coordinates":[-86.71016,36.02999],"type":"Point"}
}