{
  "type": "Feature",
  "properties": {
    "addr:full":"118 Parliament Dr Maryville TN 37804",
    "addr:housenumber":"118",
    "addr:postcode":"37804",
    "addr:street":"Parliament Dr",
    "iso:country":"US",
    "sg:address":"118 Parliament Dr",
    "sg:city":"Maryville",
    "sg:classifiers":[
        {
            "category":"Health Services",
            "subcategory":"Clinic",
            "type":"Services"
        }
    ],
    "sg:phone":"+1 865 982 0245",
    "sg:postcode":"37804",
    "sg:province":"TN",
    "sg:tags":[
        "home"
    ],
    "wof:name":"Housecall Home Healthcare",
    "wof:placetype":"venue"
},
  "geometry": {"coordinates":[-83.93989999999999,35.754606],"type":"Point"}
}