{
  "type": "Feature",
  "properties": {
    "iso:country":"US",
    "sg:address":"506 Bryant St",
    "sg:city":"Shelbyville",
    "sg:classifiers":[
        {
            "category":"Farming",
            "subcategory":"Fish & Marine Products",
            "type":"Manufacturing & Wholesale Goods"
        }
    ],
    "sg:phone":"+1 931 684 1772",
    "sg:postcode":"37160",
    "sg:province":"TN",
    "sg:tags":[
        "management"
    ],
    "wof:name":"James M Walker Enterprise",
    "wof:placetype":"venue"
},
  "geometry": {"coordinates":[-86.454235,35.486817],"type":"Point"}
}