{
  "type": "Feature",
  "properties": {
    "iso:country":"US",
    "sg:address":"1004 S Broad St",
    "sg:city":"New Tazewell",
    "sg:classifiers":[
        {
            "category":"Food & Beverages",
            "subcategory":"Groceries & Convenience Stores",
            "type":"Retail Goods"
        }
    ],
    "sg:phone":"+1 423 626 2992",
    "sg:postcode":"37825",
    "sg:province":"TN",
    "wof:name":"Citgo",
    "wof:placetype":"venue"
},
  "geometry": {"coordinates":[-83.626178,36.427519],"type":"Point"}
}