{
  "type": "Feature",
  "properties": {
    "iso:country":"US",
    "sg:address":"3350 Frayser Manor Dr",
    "sg:city":"Memphis",
    "sg:classifiers":[
        {
            "category":"Real Estate",
            "subcategory":"Real Estate Operator",
            "type":"Services"
        }
    ],
    "sg:phone":"+1 901 353 3397",
    "sg:postcode":"38127",
    "sg:province":"TN",
    "sg:tags":[
        "building",
        "apartment"
    ],
    "wof:name":"Frayser Manor Apartments",
    "wof:placetype":"venue"
},
  "geometry": {"coordinates":[-90.033675,35.216563],"type":"Point"}
}