{
  "type": "Feature",
  "properties": {
    "addr:full":"2572 Jackson Ave Memphis TN 38108",
    "addr:housenumber":"2572",
    "addr:postcode":"38108",
    "addr:street":"Jackson Ave",
    "iso:country":"US",
    "sg:address":"2572 Jackson Ave",
    "sg:city":"Memphis",
    "sg:classifiers":[
        {
            "category":"Communications",
            "subcategory":"Film & Video Production",
            "type":"Services"
        }
    ],
    "sg:phone":"+1 901 372 1118",
    "sg:postcode":"38108",
    "sg:province":"TN",
    "sg:tags":[
        "motion"
    ],
    "wof:name":"Master Video Productions",
    "wof:placetype":"venue"
},
  "geometry": {"coordinates":[-89.971416,35.158034],"type":"Point"}
}