{
  "type": "Feature",
  "properties": {
    "addr:full":"7405 Sturbridge Ct Knoxville TN 37931",
    "addr:postcode":"7405;37931",
    "addr:street":"Sturbridge Ct",
    "iso:country":"US",
    "sg:address":"7405 Sturbridge Ct",
    "sg:city":"Knoxville",
    "sg:classifiers":[
        {
            "category":"Professional",
            "subcategory":"Secretarial Services",
            "type":"Services"
        }
    ],
    "sg:phone":"+1 865 938 3125",
    "sg:postcode":"37931",
    "sg:province":"TN",
    "sg:tags":[
        "convention",
        "reporting",
        "court",
        "reporter"
    ],
    "wof:name":"Crabb J Wayne Court Reporters",
    "wof:placetype":"venue"
},
  "geometry": {"coordinates":[-84.08958699999999,36.001907],"type":"Point"}
}