{
  "type": "Feature",
  "properties": {
    "iso:country":"US",
    "sg:address":"23 Court Sq",
    "sg:city":"Charlotte",
    "sg:classifiers":[
        {
            "category":"Personal",
            "subcategory":"Beauty Salon",
            "type":"Services"
        }
    ],
    "sg:phone":"+1 615 789 5840",
    "sg:postcode":"37036",
    "sg:province":"TN",
    "sg:tags":[
        "shop"
    ],
    "wof:name":"First Impressions",
    "wof:placetype":"venue"
},
  "geometry": {"coordinates":[-87.339361,36.178875],"type":"Point"}
}