{
  "type": "Feature",
  "properties": {
    "addr:full":"2638 Hwy 79 Indian Mound TN 37079",
    "addr:housenumber":"2638",
    "addr:postcode":"37079",
    "addr:street":"Hwy 79",
    "iso:country":"US",
    "sg:address":"2638 Hwy 79",
    "sg:city":"Indian Mound",
    "sg:classifiers":[
        {
            "category":"Building & Trades",
            "subcategory":"Construction",
            "type":"Services"
        }
    ],
    "sg:phone":"+1 931 905 1553",
    "sg:postcode":"37079",
    "sg:province":"TN",
    "sg:tags":[
        "framing",
        "contractor"
    ],
    "wof:name":"Southeastern Structures Frmng",
    "wof:placetype":"venue"
},
  "geometry": {"coordinates":[-87.702713,36.555222],"type":"Point"}
}