{
  "type": "Feature",
  "properties": {
    "addr:full":"350 Harding Pl Nashville TN 37211",
    "addr:housenumber":"350",
    "addr:postcode":"37211",
    "addr:street":"Harding Pl",
    "iso:country":"US",
    "sg:address":"350 Harding Pl",
    "sg:city":"Nashville",
    "sg:classifiers":[
        {
            "category":"Restaurant",
            "type":"Food & Drink"
        }
    ],
    "sg:phone":"+1 615 331 3121",
    "sg:postcode":"37211",
    "sg:province":"TN",
    "wof:name":"City Cafe",
    "wof:placetype":"venue"
},
  "geometry": {"coordinates":[-86.70171499999999,36.085473],"type":"Point"}
}