{
  "type": "Feature",
  "properties": {
    "iso:country":"US",
    "sg:address":"296 James H Rice Rd",
    "sg:city":"Dyersburg",
    "sg:classifiers":[
        {
            "category":"Organizations",
            "subcategory":"Professional Association",
            "type":"Services"
        }
    ],
    "sg:phone":"+1 731 285 9388",
    "sg:postcode":"38024",
    "sg:province":"TN",
    "wof:name":"Dyer County Fair Assn",
    "wof:placetype":"venue"
},
  "geometry": {"coordinates":[-89.365377,36.066158],"type":"Point"}
}