{
  "type": "Feature",
  "properties": {
    "iso:country":"US",
    "sg:address":"284 Willow Creek Cv NE",
    "sg:city":"Cleveland",
    "sg:classifiers":[
        {
            "category":"Autos & Motor Vehicles",
            "subcategory":"Auto Supplies",
            "type":"Retail Goods"
        },
        {
            "category":"Retail",
            "subcategory":"Auto Repair",
            "type":"Services"
        }
    ],
    "sg:phone":"+1 423 478 1476",
    "sg:postcode":"37323",
    "sg:province":"TN",
    "sg:tags":[
        "body",
        "automobile",
        "truck",
        "painting",
        "repairing"
    ],
    "sg:website":"http://www.dentmastersusa.com",
    "wof:name":"Dentmasters",
    "wof:placetype":"venue"
},
  "geometry": {"coordinates":[-84.79067499999999,35.156296],"type":"Point"}
}