{
  "type": "Feature",
  "properties": {
    "iso:country":"US",
    "sg:address":"1080 Sandy Run",
    "sg:city":"Ashland City",
    "sg:classifiers":[
        {
            "category":"Building & Trades",
            "subcategory":"Landscaping Services",
            "type":"Services"
        }
    ],
    "sg:phone":"+1 615 792 6533",
    "sg:postcode":"37015",
    "sg:province":"TN",
    "sg:tags":[
        "tree"
    ],
    "wof:name":"Tree Care U Sav It",
    "wof:placetype":"venue"
},
  "geometry": {"coordinates":[-87.032319,36.251765],"type":"Point"}
}