{
  "type": "Feature",
  "properties": {
    "iso:country":"US",
    "sg:address":"1390 Whitlock Rd",
    "sg:city":"Paris",
    "sg:classifiers":[
        {
            "category":"Wholesale",
            "subcategory":"Electrical",
            "type":"Manufacturing & Wholesale Goods"
        }
    ],
    "sg:phone":"+1 731 642 3839",
    "sg:postcode":"38242",
    "sg:province":"TN",
    "sg:tags":[
        "alarm",
        "burglar",
        "system"
    ],
    "wof:name":"Ball Communications",
    "wof:placetype":"venue"
},
  "geometry": {"coordinates":[-88.356543,36.366006],"type":"Point"}
}