{
  "type": "Feature",
  "properties": {
    "iso:country":"US",
    "sg:address":"4105 Hickory Hill Rd",
    "sg:city":"Memphis",
    "sg:classifiers":[
        {
            "category":"Airline",
            "type":"Transportation"
        }
    ],
    "sg:phone":"+1 901 368 3000",
    "sg:postcode":"38115",
    "sg:province":"TN",
    "sg:tags":[
        "air",
        "freight",
        "forwarders"
    ],
    "wof:name":"Seko Worldwide",
    "wof:placetype":"venue"
},
  "geometry": {"coordinates":[-89.866508,35.035769],"type":"Point"}
}