{
  "type": "Feature",
  "properties": {
    "iso:country":"US",
    "sg:address":"147 W Baxter Ave",
    "sg:city":"Knoxville",
    "sg:classifiers":[
        {
            "category":"Home & Garden",
            "subcategory":"Building Materials",
            "type":"Retail Goods"
        }
    ],
    "sg:phone":"+1 865 523 6784",
    "sg:postcode":"37917",
    "sg:province":"TN",
    "sg:tags":[
        "cr",
        "product",
        "plastic",
        "sheet",
        "mfg"
    ],
    "wof:name":"Snapvent Plastics",
    "wof:placetype":"venue"
},
  "geometry": {"coordinates":[-83.92960100000001,35.980199],"type":"Point"}
}