{
  "type": "Feature",
  "properties": {
    "addr:full":"385 S 2nd St Memphis TN 38103",
    "addr:housenumber":"385",
    "addr:postcode":"38103",
    "addr:street":"S 2Nd St",
    "iso:country":"US",
    "sg:address":"385 S 2nd St",
    "sg:city":"Memphis",
    "sg:classifiers":[
        {
            "category":"Restaurant",
            "type":"Food & Drink"
        }
    ],
    "sg:phone":"+1 901 529 9991",
    "sg:postcode":"38103",
    "sg:province":"TN",
    "sg:tags":[
        "mexican"
    ],
    "sg:website":"http://www.happymexican.com/",
    "wof:name":"Happy Mexican Restaurante and Cantina",
    "wof:placetype":"venue"
},
  "geometry": {"coordinates":[-90.05632799999999,35.134927],"type":"Point"}
}