{
  "type": "Feature",
  "properties": {
    "iso:country":"US",
    "sg:address":"10215 Caneel Dr",
    "sg:city":"Knoxville",
    "sg:classifiers":[
        {
            "category":"Wholesale",
            "subcategory":"Machinery & Supplies",
            "type":"Manufacturing & Wholesale Goods"
        }
    ],
    "sg:phone":"+1 865 670 3252",
    "sg:postcode":"37931",
    "sg:province":"TN",
    "sg:tags":[
        "industrial"
    ],
    "wof:name":"Kennametal Inc",
    "wof:placetype":"venue"
},
  "geometry": {"coordinates":[-84.142259,35.966976],"type":"Point"}
}