{
  "type": "Feature",
  "properties": {
    "iso:country":"US",
    "sg:address":"2503 Wilma Rudolph Blvd",
    "sg:city":"Clarksville",
    "sg:classifiers":[
        {
            "category":"Food & Beverages",
            "subcategory":"Groceries & Convenience Stores",
            "type":"Retail Goods"
        },
        {
            "category":"Shopping",
            "subcategory":"Pharmacy",
            "type":"Retail Goods"
        }
    ],
    "sg:phone":"+1 931 245 6979",
    "sg:postcode":"37040",
    "sg:province":"TN",
    "sg:tags":[
        "grocer"
    ],
    "wof:name":"Albertson's",
    "wof:placetype":"venue"
},
  "geometry": {"coordinates":[-87.299294,36.579338],"type":"Point"}
}