{
  "type": "Feature",
  "properties": {
    "iso:country":"US",
    "sg:address":"153 Witherspoon Ave",
    "sg:city":"Gallatin",
    "sg:classifiers":[
        {
            "category":"Shopping",
            "subcategory":"Florist",
            "type":"Retail Goods"
        }
    ],
    "sg:phone":"+1 615 451 3333",
    "sg:postcode":"37066",
    "sg:province":"TN",
    "wof:name":"Mattie Lou's Flower & Gift",
    "wof:placetype":"venue"
},
  "geometry": {"coordinates":[-86.43710299999999,36.380517],"type":"Point"}
}