{
  "type": "Feature",
  "properties": {
    "addr:full":"455 Hannings Ln Martin TN 38237",
    "addr:housenumber":"455",
    "addr:postcode":"38237",
    "addr:street":"Hannings Ln",
    "iso:country":"US",
    "sg:address":"455 Hannings Ln",
    "sg:city":"Martin",
    "sg:classifiers":[
        {
            "category":"Professional",
            "subcategory":"Business Services",
            "type":"Services"
        }
    ],
    "sg:phone":"+1 731 587 0024",
    "sg:postcode":"38237",
    "sg:province":"TN",
    "wof:name":"Jwc Housing Corp",
    "wof:placetype":"venue"
},
  "geometry": {"coordinates":[-88.86956600000001,36.337566],"type":"Point"}
}