{
  "type": "Feature",
  "properties": {
    "iso:country":"US",
    "sg:address":"3419 American Way",
    "sg:city":"Memphis",
    "sg:classifiers":[
        {
            "category":"Travel",
            "subcategory":"Hotels & Motels",
            "type":"Entertainment"
        }
    ],
    "sg:phone":"+1 901 362 6600",
    "sg:postcode":"38118",
    "sg:province":"TN",
    "wof:name":"Garden Inn Suites",
    "wof:placetype":"venue"
},
  "geometry": {"coordinates":[-89.950446,35.076793],"type":"Point"}
}