{
  "type": "Feature",
  "properties": {
    "addr:full":"2993 Lake Park Rd Memphis TN 38127",
    "addr:housenumber":"2993",
    "addr:postcode":"38127",
    "addr:street":"Lake Park Rd",
    "iso:country":"US",
    "sg:address":"2993 Lake Park Rd",
    "sg:city":"Memphis",
    "sg:classifiers":[
        {
            "category":"Building & Trades",
            "subcategory":"Construction",
            "type":"Services"
        }
    ],
    "sg:phone":"+1 901 373 3908",
    "sg:postcode":"38127",
    "sg:province":"TN",
    "sg:tags":[
        "contractor"
    ],
    "wof:name":"Davis Drywall Painting",
    "wof:placetype":"venue"
},
  "geometry": {"coordinates":[-89.965191,35.230653],"type":"Point"}
}