{
  "type": "Feature",
  "properties": {
    "addr:full":"355 Paul Huff Pkwy NW Cleveland TN 37312",
    "addr:housenumber":"355",
    "addr:postcode":"37312",
    "addr:street":"Paul Huff Pkwy Nw",
    "iso:country":"US",
    "sg:address":"355 Paul Huff Pkwy NW",
    "sg:city":"Cleveland",
    "sg:classifiers":[
        {
            "category":"Restaurant",
            "type":"Food & Drink"
        }
    ],
    "sg:menulink":"http://www.allmenus.com/tn/cleveland/65588-cicis-pizza-buffet/menu/",
    "sg:phone":"+1 423 473 9550",
    "sg:postcode":"37312",
    "sg:province":"TN",
    "sg:tags":[
        "american",
        "pizza"
    ],
    "wof:name":"CiCi's Pizza Buffet",
    "wof:placetype":"venue"
},
  "geometry": {"coordinates":[-84.85202,35.207702],"type":"Point"}
}