{
  "type": "Feature",
  "properties": {
    "iso:country":"US",
    "sg:address":"6122 Henry Ford Dr",
    "sg:city":"Nashville",
    "sg:classifiers":[
        {
            "category":"Building & Trades",
            "subcategory":"Construction",
            "type":"Services"
        }
    ],
    "sg:phone":"+1 615 356 5824",
    "sg:postcode":"37209",
    "sg:province":"TN",
    "sg:tags":[
        "work",
        "laying",
        "floor"
    ],
    "wof:name":"Billy Kinslow Tile Setting",
    "wof:placetype":"venue"
},
  "geometry": {"coordinates":[-86.877729,36.150165],"type":"Point"}
}