{
  "type": "Feature",
  "properties": {
    "addr:full":"9051 Executive Park Dr Knoxville TN 37923",
    "addr:housenumber":"9051",
    "addr:postcode":"37923",
    "addr:street":"Executive Park Dr",
    "iso:country":"US",
    "sg:address":"9051 Executive Park Dr",
    "sg:city":"Knoxville",
    "sg:classifiers":[
        {
            "category":"Health Services",
            "subcategory":"Medical Lab",
            "type":"Services"
        }
    ],
    "sg:phone":"+1 865 691 5907",
    "sg:postcode":"37923",
    "sg:province":"TN",
    "sg:tags":[
        "examination",
        "insurance"
    ],
    "sg:website":"http://www.portamedic.com",
    "wof:name":"Portamedic",
    "wof:placetype":"venue"
},
  "geometry": {"coordinates":[-84.08301400000001,35.92165],"type":"Point"}
}