{
  "type": "Feature",
  "properties": {
    "iso:country":"US",
    "sg:address":"6910 Shallowford Rd",
    "sg:city":"Chattanooga",
    "sg:classifiers":[
        {
            "category":"Shopping",
            "subcategory":"Used Merchandise",
            "type":"Retail Goods"
        }
    ],
    "sg:phone":"+1 423 499 0114",
    "sg:postcode":"37421",
    "sg:province":"TN",
    "wof:name":"Scarletts Attic",
    "wof:placetype":"venue"
},
  "geometry": {"coordinates":[-85.162195,35.044747],"type":"Point"}
}