{
  "type": "Feature",
  "properties": {
    "addr:full":"412 Scott Farm Rd Afton TN 37745",
    "addr:housenumber":"412",
    "addr:postcode":"37745",
    "addr:street":"Scott Farm Rd",
    "iso:country":"US",
    "sg:address":"412 Scott Farm Rd",
    "sg:city":"Afton",
    "sg:classifiers":[
        {
            "category":"Manufacturing",
            "subcategory":"Lumber",
            "type":"Manufacturing & Wholesale Goods"
        }
    ],
    "sg:phone":"+1 423 783 0044",
    "sg:postcode":"37745",
    "sg:province":"TN",
    "sg:tags":[
        "product",
        "forest",
        "gathering"
    ],
    "wof:name":"Metcalfs Ginseng",
    "wof:placetype":"venue"
},
  "geometry": {"coordinates":[-82.788037,36.215788],"type":"Point"}
}