{
  "type": "Feature",
  "properties": {
    "iso:country":"US",
    "sg:address":"165 Missionary Grove Church",
    "sg:city":"Camden",
    "sg:classifiers":[
        {
            "category":"Organizations",
            "subcategory":"Religious Organization",
            "type":"Services"
        }
    ],
    "sg:phone":"+1 731 584 9465",
    "sg:postcode":"38320",
    "sg:province":"TN",
    "wof:name":"Missionary Grove Church",
    "wof:placetype":"venue"
},
  "geometry": {"coordinates":[-88.062021,36.022158],"type":"Point"}
}