{
  "type": "Feature",
  "properties": {
    "iso:country":"US",
    "sg:address":"4940 State Hwy 138",
    "sg:city":"Toone",
    "sg:classifiers":[
        {
            "category":"Manufacturing",
            "subcategory":"Lumber",
            "type":"Manufacturing & Wholesale Goods"
        }
    ],
    "sg:phone":"+1 731 658 6802",
    "sg:postcode":"38381",
    "sg:province":"TN",
    "sg:tags":[
        "hardwood",
        "mill"
    ],
    "wof:name":"Toone Sawmill",
    "wof:placetype":"venue"
},
  "geometry": {"coordinates":[-88.985085,35.377323],"type":"Point"}
}