{
  "type": "Feature",
  "properties": {
    "addr:full":"6911 Neal Chase Way Knoxville TN 37918",
    "addr:housenumber":"6911",
    "addr:postcode":"37918",
    "addr:street":"Neal Chase Way",
    "iso:country":"US",
    "sg:address":"6911 Neal Chase Way",
    "sg:city":"Knoxville",
    "sg:classifiers":[
        {
            "category":"Real Estate",
            "subcategory":"Real Estate Agent",
            "type":"Services"
        }
    ],
    "sg:phone":"+1 865 922 2600",
    "sg:postcode":"37918",
    "sg:province":"TN",
    "wof:name":"Worley Builders Inc",
    "wof:placetype":"venue"
},
  "geometry": {"coordinates":[-83.93708700000001,36.070355],"type":"Point"}
}