{
  "type": "Feature",
  "properties": {
    "addr:full":"835 S Bellevue Blvd Memphis TN 38104",
    "addr:housenumber":"835",
    "addr:postcode":"38104",
    "addr:street":"S Bellevue Blvd",
    "iso:country":"US",
    "sg:address":"835 S Bellevue Blvd",
    "sg:city":"Memphis",
    "sg:classifiers":[
        {
            "category":"Manufacturing",
            "subcategory":"Paper Products",
            "type":"Manufacturing & Wholesale Goods"
        }
    ],
    "sg:phone":"+1 901 725 5100",
    "sg:postcode":"38104",
    "sg:province":"TN",
    "sg:tags":[
        "box",
        "folding",
        "paperboard",
        "mfg"
    ],
    "wof:name":"Americraft Carton Inc",
    "wof:placetype":"venue"
},
  "geometry": {"coordinates":[-90.02137500000001,35.123163],"type":"Point"}
}