{
  "type": "Feature",
  "properties": {
    "addr:full":"3929 Senator St Memphis TN 38118",
    "addr:housenumber":"3929",
    "addr:postcode":"38118",
    "addr:street":"Senator St",
    "iso:country":"US",
    "sg:address":"3929 Senator St",
    "sg:city":"Memphis",
    "sg:classifiers":[
        {
            "category":"Building & Trades",
            "subcategory":"Construction",
            "type":"Services"
        }
    ],
    "sg:phone":"+1 901 365 8450",
    "sg:postcode":"38118",
    "sg:province":"TN",
    "sg:tags":[
        "acoustical",
        "contractor"
    ],
    "wof:name":"Acoustics & Specialties Inc",
    "wof:placetype":"venue"
},
  "geometry": {"coordinates":[-89.93418200000001,35.039161],"type":"Point"}
}