{
  "type": "Feature",
  "properties": {
    "iso:country":"US",
    "sg:address":"600 W Madison Ave",
    "sg:city":"Athens",
    "sg:classifiers":[
        {
            "category":"Organizations",
            "subcategory":"Religious Organization",
            "type":"Services"
        }
    ],
    "sg:phone":"+1 423 745 2612",
    "sg:postcode":"37303",
    "sg:province":"TN",
    "sg:tags":[
        "church"
    ],
    "sg:website":"www.keithumc.com",
    "wof:name":"Keith Memorial United Meth",
    "wof:placetype":"venue"
},
  "geometry": {"coordinates":[-84.60082800000001,35.439737],"type":"Point"}
}