{
  "type": "Feature",
  "properties": {
    "addr:full":"2113 Helton Dr Lawrenceburg TN 38464",
    "addr:housenumber":"2113",
    "addr:postcode":"38464",
    "addr:street":"Helton Dr",
    "iso:country":"US",
    "sg:address":"2113 Helton Dr",
    "sg:city":"Lawrenceburg",
    "sg:classifiers":[
        {
            "category":"Government",
            "subcategory":"Office",
            "type":"Public Place"
        }
    ],
    "sg:phone":"+1 931 766 1424",
    "sg:postcode":"38464",
    "sg:province":"TN",
    "sg:tags":[
        "state",
        "security"
    ],
    "wof:name":"National Guard Recruiting",
    "wof:placetype":"venue"
},
  "geometry": {"coordinates":[-87.329967,35.269746],"type":"Point"}
}