{
  "type": "Feature",
  "properties": {
    "addr:full":"1410 Smithville Hwy Mc Minnville TN 37110",
    "addr:housenumber":"1410",
    "addr:postcode":"37110",
    "addr:street":"Smithville Hwy Mc Minnville",
    "iso:country":"US",
    "sg:address":"1410 Smithville Hwy",
    "sg:city":"Mc Minnville",
    "sg:classifiers":[
        {
            "category":"Restaurant",
            "type":"Food & Drink"
        }
    ],
    "sg:menulink":"http://www.allmenus.com/tn/mcminnville/200224-long-john-silvers/menu/",
    "sg:phone":"+1 931 473 3348",
    "sg:postcode":"37110",
    "sg:province":"TN",
    "sg:tags":[
        "seafood",
        "american"
    ],
    "wof:name":"Long John Silver's",
    "wof:placetype":"venue"
},
  "geometry": {"coordinates":[-85.780901,35.703018],"type":"Point"}
}