{
  "type": "Feature",
  "properties": {
    "iso:country":"US",
    "sg:address":"229 Interstate Dr",
    "sg:city":"Crossville",
    "sg:classifiers":[
        {
            "category":"Food & Beverages",
            "subcategory":"Groceries & Convenience Stores",
            "type":"Retail Goods"
        }
    ],
    "sg:phone":"+1 931 484 4486",
    "sg:postcode":"38555",
    "sg:province":"TN",
    "sg:tags":[
        "grocer"
    ],
    "wof:name":"Crossville Save-A-Lot",
    "wof:placetype":"venue"
},
  "geometry": {"coordinates":[-85.02493699999999,35.983652],"type":"Point"}
}