{
  "type": "Feature",
  "properties": {
    "addr:full":"120 K St Martin TN 38237",
    "addr:housenumber":"120",
    "addr:postcode":"38237",
    "addr:street":"K St",
    "iso:country":"US",
    "sg:address":"120 K St",
    "sg:city":"Martin",
    "sg:classifiers":[
        {
            "category":"Organizations",
            "subcategory":"Religious Organization",
            "type":"Services"
        }
    ],
    "sg:phone":"+1 731 587 5124",
    "sg:postcode":"38237",
    "sg:province":"TN",
    "sg:tags":[
        "church"
    ],
    "wof:name":"Oak Grove Missionary Bapt Chr",
    "wof:placetype":"venue"
},
  "geometry": {"coordinates":[-88.84636999999999,36.345195],"type":"Point"}
}