{
  "type": "Feature",
  "properties": {
    "iso:country":"US",
    "sg:address":"574 S Water Ave",
    "sg:city":"Gallatin",
    "sg:classifiers":[
        {
            "category":"Wholesale",
            "subcategory":"Hardware",
            "type":"Manufacturing & Wholesale Goods"
        }
    ],
    "sg:phone":"+1 615 230 7900",
    "sg:postcode":"37066",
    "sg:province":"TN",
    "sg:tags":[
        "fastener"
    ],
    "sg:website":"www.fastenal.com",
    "wof:name":"Fastenal Co",
    "wof:placetype":"venue"
},
  "geometry": {"coordinates":[-86.44309199999999,36.379521],"type":"Point"}
}