{
  "type": "Feature",
  "properties": {
    "addr:full":"77 Upper Zion Rd Brownsville TN 38012",
    "addr:housenumber":"77",
    "addr:postcode":"38012",
    "addr:street":"Upper Zion Rd",
    "iso:country":"US",
    "sg:address":"77 Upper Zion Rd",
    "sg:city":"Brownsville",
    "sg:classifiers":[
        {
            "category":"Organizations",
            "subcategory":"Religious Organization",
            "type":"Services"
        }
    ],
    "sg:phone":"+1 731 772 1487",
    "sg:postcode":"38012",
    "sg:province":"TN",
    "sg:tags":[
        "church"
    ],
    "wof:name":"Zion Baptist Church",
    "wof:placetype":"venue"
},
  "geometry": {"coordinates":[-89.164511,35.598277],"type":"Point"}
}