{
  "type": "Feature",
  "properties": {
    "addr:full":"206 Sterling St Martin TN 38237",
    "addr:housenumber":"206",
    "addr:postcode":"38237",
    "addr:street":"Sterling St",
    "iso:country":"US",
    "sg:address":"206 Sterling St",
    "sg:city":"Martin",
    "sg:classifiers":[
        {
            "category":"Insurance",
            "subcategory":"Insurance Agent",
            "type":"Services"
        }
    ],
    "sg:phone":"+1 731 587 2138",
    "sg:postcode":"38237",
    "sg:province":"TN",
    "wof:name":"Modern Woodmen of America",
    "wof:placetype":"venue"
},
  "geometry": {"coordinates":[-88.845021,36.33887],"type":"Point"}
}