{
  "type": "Feature",
  "properties": {
    "addr:full":"11941 Chapman Hwy Seymour TN 37865",
    "addr:housenumber":"11941",
    "addr:postcode":"37865",
    "addr:street":"Chapman Hwy",
    "iso:country":"US",
    "sg:address":"11941 Chapman Hwy",
    "sg:city":"Seymour",
    "sg:classifiers":[
        {
            "category":"Shopping",
            "subcategory":"Used Merchandise",
            "type":"Retail Goods"
        }
    ],
    "sg:phone":"+1 865 609 6889",
    "sg:postcode":"37865",
    "sg:province":"TN",
    "wof:name":"A A Title Pawn",
    "wof:placetype":"venue"
},
  "geometry": {"coordinates":[-83.741461,35.861042],"type":"Point"}
}