{
  "type": "Feature",
  "properties": {
    "iso:country":"US",
    "sg:address":"641 Old Hickory Blvd",
    "sg:city":"Brentwood",
    "sg:classifiers":[
        {
            "category":"Wholesale",
            "subcategory":"Medical Equipment & Supplies",
            "type":"Manufacturing & Wholesale Goods"
        }
    ],
    "sg:phone":"+1 615 943 5002",
    "sg:postcode":"37027",
    "sg:province":"TN",
    "sg:tags":[
        "x",
        "apparatus"
    ],
    "wof:name":"Personalized Digital Images",
    "wof:placetype":"venue"
},
  "geometry": {"coordinates":[-86.768092,36.040186],"type":"Point"}
}