{
  "type": "Feature",
  "properties": {
    "iso:country":"US",
    "sg:address":"117 Nowlin Ln",
    "sg:city":"Chattanooga",
    "sg:classifiers":[
        {
            "category":"Education",
            "subcategory":"Vocational School",
            "type":"Public Place"
        }
    ],
    "sg:phone":"+1 423 499 4999",
    "sg:postcode":"37421",
    "sg:province":"TN",
    "wof:name":"Academy Allied Health Careers",
    "wof:placetype":"venue"
},
  "geometry": {"coordinates":[-85.20081399999999,35.027239],"type":"Point"}
}