{
  "type": "Feature",
  "properties": {
    "iso:country":"US",
    "sg:address":"214 Carriage House Dr",
    "sg:city":"Jackson",
    "sg:classifiers":[
        {
            "category":"Shopping",
            "subcategory":"Optical Goods",
            "type":"Retail Goods"
        },
        {
            "category":"Health Services",
            "subcategory":"Optometrist",
            "type":"Services"
        }
    ],
    "sg:phone":"+1 731 668 4881",
    "sg:postcode":"38305",
    "sg:province":"TN",
    "sg:tags":[
        "eyeglasses",
        "contact"
    ],
    "wof:name":"Burnett & Burnett Drs",
    "wof:placetype":"venue"
},
  "geometry": {"coordinates":[-88.836314,35.668066],"type":"Point"}
}