{
  "type": "Feature",
  "properties": {
    "addr:full":"1026 E Brooks Rd Memphis TN 38109",
    "addr:housenumber":"1026",
    "addr:postcode":"38109",
    "addr:street":"E Brooks Rd",
    "iso:country":"US",
    "sg:address":"1026 E Brooks Rd",
    "sg:city":"Memphis",
    "sg:classifiers":[
        {
            "category":"Insurance",
            "subcategory":"Insurance Agent",
            "type":"Services"
        }
    ],
    "sg:phone":"+1 901 396 8855",
    "sg:postcode":"38109",
    "sg:province":"TN",
    "wof:name":"Direct General Ins Agency",
    "wof:placetype":"venue"
},
  "geometry": {"coordinates":[-90.029529,35.06174],"type":"Point"}
}