{
  "type": "Feature",
  "properties": {
    "iso:country":"US",
    "sg:address":"5975 Stage Rd",
    "sg:city":"Memphis",
    "sg:classifiers":[
        {
            "category":"Shopping",
            "subcategory":"Books",
            "type":"Retail Goods"
        }
    ],
    "sg:phone":"+1 901 385 9168",
    "sg:postcode":"38134",
    "sg:province":"TN",
    "wof:name":"Batlett Book Center & Cafe-Boo",
    "wof:placetype":"venue"
},
  "geometry": {"coordinates":[-89.86306500000001,35.204758],"type":"Point"}
}