{
  "type": "Feature",
  "properties": {
    "addr:full":"3793 Coral Dr Memphis TN 38127",
    "addr:housenumber":"3793",
    "addr:postcode":"38127",
    "addr:street":"Coral Dr",
    "iso:country":"US",
    "sg:address":"3793 Coral Dr",
    "sg:city":"Memphis",
    "sg:classifiers":[
        {
            "category":"Recreation",
            "type":"Entertainment"
        }
    ],
    "sg:phone":"+1 901 358 8422",
    "sg:postcode":"38127",
    "sg:province":"TN",
    "sg:tags":[
        "carnival"
    ],
    "wof:name":"B's Amusement",
    "wof:placetype":"venue"
},
  "geometry": {"coordinates":[-89.97294599999999,35.22734],"type":"Point"}
}