{
  "type": "Feature",
  "properties": {
    "iso:country":"US",
    "sg:address":"731 S Spring St",
    "sg:city":"Manchester",
    "sg:classifiers":[
        {
            "category":"Home & Garden",
            "subcategory":"Furniture",
            "type":"Retail Goods"
        }
    ],
    "sg:phone":"+1 931 728 5619",
    "sg:postcode":"37355",
    "sg:province":"TN",
    "wof:name":"G & G Discount Furniture",
    "wof:placetype":"venue"
},
  "geometry": {"coordinates":[-86.089017,35.475752],"type":"Point"}
}