{
  "type": "Feature",
  "properties": {
    "iso:country":"US",
    "sg:address":"765 W Poplar Ave",
    "sg:city":"Collierville",
    "sg:classifiers":[
        {
            "category":"Banks & Credit Unions",
            "subcategory":"Bank",
            "type":"Services"
        }
    ],
    "sg:phone":"+1 901 861 0402",
    "sg:postcode":"38017",
    "sg:province":"TN",
    "sg:tags":[
        "federal"
    ],
    "sg:website":"www.beaconfederal.com",
    "wof:name":"Beacon Federal Credit Union",
    "wof:placetype":"venue"
},
  "geometry": {"coordinates":[-89.688935,35.046035],"type":"Point"}
}