{
  "type": "Feature",
  "properties": {
    "addr:full":"213 E Main St Rogersville TN 37857",
    "addr:housenumber":"213",
    "addr:postcode":"37857",
    "addr:street":"E Main St",
    "iso:country":"US",
    "sg:address":"213 E Main St",
    "sg:city":"Rogersville",
    "sg:classifiers":[
        {
            "category":"Personal",
            "type":"Services"
        }
    ],
    "sg:phone":"+1 423 921 9004",
    "sg:postcode":"37857",
    "sg:province":"TN",
    "wof:name":"Weight Loss Mgmnt Centers",
    "wof:placetype":"venue"
},
  "geometry": {"coordinates":[-83.004831,36.407497],"type":"Point"}
}