{
  "type": "Feature",
  "properties": {
    "iso:country":"US",
    "sg:address":"325 Gravel Hill Rd",
    "sg:city":"Limestone",
    "sg:phone":"+1 423 257 5070",
    "sg:postcode":"37681",
    "sg:province":"TN",
    "sg:tags":[
        "farm",
        "wheat",
        "corn",
        "dairy"
    ],
    "wof:name":"Gravil Hill",
    "wof:placetype":"venue"
},
  "geometry": {"coordinates":[-82.598725,36.208549],"type":"Point"}
}