{
  "type": "Feature",
  "properties": {
    "addr:full":"150 Timber Creek Dr Cordova TN 38018",
    "addr:housenumber":"150",
    "addr:postcode":"38018",
    "addr:street":"Timber Creek Dr",
    "iso:country":"US",
    "sg:address":"150 Timber Creek Dr",
    "sg:city":"Cordova",
    "sg:classifiers":[
        {
            "category":"Building & Trades",
            "subcategory":"Landscaping Services",
            "type":"Services"
        }
    ],
    "sg:phone":"+1 901 754 7285",
    "sg:postcode":"38018",
    "sg:province":"TN",
    "sg:tags":[
        "landscape"
    ],
    "wof:name":"Conrad Jim Ldscp Desgr & Contr",
    "wof:placetype":"venue"
},
  "geometry": {"coordinates":[-89.796623,35.126847],"type":"Point"}
}