{
  "type": "Feature",
  "properties": {
    "addr:full":"2106 College Park Ln Soddy Daisy TN 37379",
    "addr:housenumber":"2106",
    "addr:postcode":"37379",
    "addr:street":"College Park Ln",
    "iso:country":"US",
    "sg:address":"2106 College Park Ln",
    "sg:city":"Soddy Daisy",
    "sg:classifiers":[
        {
            "category":"Real Estate",
            "subcategory":"Real Estate Agent",
            "type":"Services"
        }
    ],
    "sg:phone":"+1 423 842 3226",
    "sg:postcode":"37379",
    "sg:province":"TN",
    "wof:name":"Bantrup Properties Group",
    "wof:placetype":"venue"
},
  "geometry": {"coordinates":[-85.13445,35.201813],"type":"Point"}
}