{
  "type": "Feature",
  "properties": {
    "iso:country":"US",
    "sg:address":"3585 Workman Rd",
    "sg:city":"Knoxville",
    "sg:classifiers":[
        {
            "category":"Shopping",
            "type":"Retail Goods"
        }
    ],
    "sg:phone":"+1 865 584 9228",
    "sg:postcode":"37921",
    "sg:province":"TN",
    "sg:tags":[
        "merchandise"
    ],
    "wof:name":"AT&T Wireless",
    "wof:placetype":"venue"
},
  "geometry": {"coordinates":[-84.01406299999999,35.961657],"type":"Point"}
}