{
  "type": "Feature",
  "properties": {
    "iso:country":"US",
    "sg:address":"309 W Morford St",
    "sg:city":"Mc Minnville",
    "sg:classifiers":[
        {
            "category":"Professional",
            "subcategory":"Lawyer & Legal Services",
            "type":"Services"
        }
    ],
    "sg:phone":"+1 931 473 2516",
    "sg:postcode":"37110",
    "sg:province":"TN",
    "sg:tags":[
        "attorney"
    ],
    "wof:name":"Cathleen G Conley",
    "wof:placetype":"venue"
},
  "geometry": {"coordinates":[-85.778589,35.682603],"type":"Point"}
}