{
  "type": "Feature",
  "properties": {
    "iso:country":"US",
    "sg:address":"108 Grant Ct",
    "sg:city":"Portland",
    "sg:classifiers":[
        {
            "category":"Personal",
            "subcategory":"Beauty Salon",
            "type":"Services"
        }
    ],
    "sg:phone":"+1 615 323 0420",
    "sg:postcode":"37148",
    "sg:province":"TN",
    "wof:name":"Off Broadway Hair Salon",
    "wof:placetype":"venue"
},
  "geometry": {"coordinates":[-86.564019,36.585544],"type":"Point"}
}