{
  "type": "Feature",
  "properties": {
    "addr:full":"125 Court Ave Sevierville TN 37862",
    "addr:housenumber":"125",
    "addr:postcode":"37862",
    "addr:street":"Court Ave",
    "iso:country":"US",
    "sg:address":"125 Court Ave",
    "sg:city":"Sevierville",
    "sg:classifiers":[
        {
            "category":"Building & Trades",
            "subcategory":"Construction",
            "type":"Services"
        }
    ],
    "sg:phone":"+1 865 453 3452",
    "sg:postcode":"37862",
    "sg:province":"TN",
    "wof:name":"Highway Department",
    "wof:placetype":"venue"
},
  "geometry": {"coordinates":[-83.56481100000001,35.869363],"type":"Point"}
}