{
  "type": "Feature",
  "properties": {
    "iso:country":"US",
    "sg:address":"4729 Adams Rd",
    "sg:city":"Hixson",
    "sg:classifiers":[
        {
            "category":"Wholesale",
            "subcategory":"Electrical",
            "type":"Manufacturing & Wholesale Goods"
        }
    ],
    "sg:phone":"+1 423 875 5112",
    "sg:postcode":"37343",
    "sg:province":"TN",
    "sg:tags":[
        "control"
    ],
    "wof:name":"Control Service",
    "wof:placetype":"venue"
},
  "geometry": {"coordinates":[-85.23342599999999,35.1343],"type":"Point"}
}