{
  "type": "Feature",
  "properties": {
    "iso:country":"US",
    "sg:address":"148 Broad St",
    "sg:city":"Baxter",
    "sg:classifiers":[
        {
            "category":"Manufacturing",
            "subcategory":"Wood Products",
            "type":"Manufacturing & Wholesale Goods"
        }
    ],
    "sg:phone":"+1 615 858 3710",
    "sg:postcode":"38544",
    "sg:province":"TN",
    "sg:tags":[
        "item",
        "mfr",
        "novelty"
    ],
    "wof:name":"Rollo-Laxer",
    "wof:placetype":"venue"
},
  "geometry": {"coordinates":[-85.642563,36.153677],"type":"Point"}
}