{
  "type": "Feature",
  "properties": {
    "iso:country":"US",
    "sg:address":"1992 Lake City Hwy",
    "sg:city":"Clinton",
    "sg:classifiers":[
        {
            "category":"Utilities",
            "subcategory":"Refuse",
            "type":"Services"
        }
    ],
    "sg:phone":"+1 865 457 9727",
    "sg:postcode":"37716",
    "sg:province":"TN",
    "sg:tags":[
        "garbage",
        "collection"
    ],
    "wof:name":"Waste Connections Of Tennesee",
    "wof:placetype":"venue"
},
  "geometry": {"coordinates":[-84.152827,36.142836],"type":"Point"}
}