{
  "type": "Feature",
  "properties": {
    "addr:full":"213 E Washington Ave Athens TN 37303",
    "addr:housenumber":"213",
    "addr:postcode":"37303",
    "addr:street":"E Washington Ave",
    "iso:country":"US",
    "sg:address":"213 E Washington Ave",
    "sg:city":"Athens",
    "sg:classifiers":[
        {
            "category":"Shopping",
            "type":"Retail Goods"
        }
    ],
    "sg:phone":"+1 423 744 1366",
    "sg:postcode":"37303",
    "sg:province":"TN",
    "sg:tags":[
        "cosmetic",
        "perfume"
    ],
    "wof:name":"Act III",
    "wof:placetype":"venue"
},
  "geometry": {"coordinates":[-84.591182,35.443519],"type":"Point"}
}