{
  "type": "Feature",
  "properties": {
    "iso:country":"US",
    "sg:address":"1420 Black Rd",
    "sg:city":"Prospect",
    "sg:classifiers":[
        {
            "category":"Health Services",
            "subcategory":"Doctor",
            "type":"Services"
        }
    ],
    "sg:phone":"+1 931 565 3122",
    "sg:postcode":"38477",
    "sg:province":"TN",
    "sg:tags":[
        "clinic"
    ],
    "wof:name":"Professional Medical Svc",
    "wof:placetype":"venue"
},
  "geometry": {"coordinates":[-87.12781099999999,35.088541],"type":"Point"}
}