{
  "type": "Feature",
  "properties": {
    "iso:country":"US",
    "sg:address":"171 W Mallory Ave",
    "sg:city":"Memphis",
    "sg:classifiers":[
        {
            "category":"Manufacturing",
            "subcategory":"Textiles",
            "type":"Manufacturing & Wholesale Goods"
        }
    ],
    "sg:phone":"+1 901 774 8635",
    "sg:postcode":"38109",
    "sg:province":"TN",
    "sg:tags":[
        "cotton"
    ],
    "wof:name":"Planters Gin Co",
    "wof:placetype":"venue"
},
  "geometry": {"coordinates":[-90.071978,35.086742],"type":"Point"}
}