{
  "type": "Feature",
  "properties": {
    "iso:country":"US",
    "sg:address":"2035 Pendleton St",
    "sg:city":"Memphis",
    "sg:classifiers":[
        {
            "category":"Building & Trades",
            "subcategory":"Construction",
            "type":"Services"
        }
    ],
    "sg:phone":"+1 901 357 0212",
    "sg:postcode":"38114",
    "sg:province":"TN",
    "sg:tags":[
        "residential",
        "commercial",
        "site",
        "clean"
    ],
    "wof:name":"Tunstall Construction Clean-Up",
    "wof:placetype":"venue"
},
  "geometry": {"coordinates":[-89.970493,35.088974],"type":"Point"}
}