{
  "type": "Feature",
  "properties": {
    "iso:country":"US",
    "sg:address":"1604 Westgate Cir",
    "sg:city":"Brentwood",
    "sg:classifiers":[
        {
            "category":"Insurance",
            "subcategory":"Insurance Agent",
            "type":"Services"
        }
    ],
    "sg:phone":"+1 615 377 9620",
    "sg:postcode":"37027",
    "sg:province":"TN",
    "wof:name":"AFLAC",
    "wof:placetype":"venue"
},
  "geometry": {"coordinates":[-86.803113,35.966578],"type":"Point"}
}