{
  "type": "Feature",
  "properties": {
    "addr:full":"1151 Needmore Rd Clarksville TN 37040",
    "addr:housenumber":"1151",
    "addr:postcode":"37040",
    "addr:street":"Needmore Rd",
    "iso:country":"US",
    "sg:address":"1151 Needmore Rd",
    "sg:city":"Clarksville",
    "sg:phone":"+1 931 552 6359",
    "sg:postcode":"37040",
    "sg:province":"TN",
    "sg:tags":[
        "farm",
        "corn",
        "soybean"
    ],
    "wof:name":"Kennedy Brothers Farm",
    "wof:placetype":"venue"
},
  "geometry": {"coordinates":[-87.343919,36.586371],"type":"Point"}
}