{
  "type": "Feature",
  "properties": {
    "iso:country":"US",
    "sg:address":"366 Pankey Ln",
    "sg:city":"Benton",
    "sg:classifiers":[
        {
            "category":"Building & Trades",
            "subcategory":"Plumbing",
            "type":"Services"
        }
    ],
    "sg:phone":"+1 423 338 4142",
    "sg:postcode":"37307",
    "sg:province":"TN",
    "sg:tags":[
        "plumbing",
        "contractor"
    ],
    "wof:name":"R B Clayton Plumbing",
    "wof:placetype":"venue"
},
  "geometry": {"coordinates":[-84.652511,35.154379],"type":"Point"}
}