{
  "type": "Feature",
  "properties": {
    "iso:country":"US",
    "sg:address":"80 Arsenal Ln",
    "sg:city":"Lavinia",
    "sg:classifiers":[
        {
            "category":"Restaurant",
            "type":"Food & Drink"
        }
    ],
    "sg:phone":"+1 731 783 5331",
    "sg:postcode":"38348",
    "sg:province":"TN",
    "sg:tags":[
        "eating"
    ],
    "wof:name":"Mama Judy's Country Kitchen",
    "wof:placetype":"venue"
},
  "geometry": {"coordinates":[-88.66761700000001,35.85262],"type":"Point"}
}