{
  "type": "Feature",
  "properties": {
    "iso:country":"US",
    "sg:address":"3025 Kirby Whitten Rd",
    "sg:city":"Memphis",
    "sg:classifiers":[
        {
            "category":"Banks & Credit Unions",
            "subcategory":"Bank",
            "type":"Services"
        }
    ],
    "sg:phone":"+1 901 388 3814",
    "sg:postcode":"38134",
    "sg:province":"TN",
    "sg:tags":[
        "loan"
    ],
    "wof:name":"First Metropolitan Financial",
    "wof:placetype":"venue"
},
  "geometry": {"coordinates":[-89.84072399999999,35.20721],"type":"Point"}
}