{
  "type": "Feature",
  "properties": {
    "addr:full":"8436 Old Charlotte Pike Pegram TN 37143",
    "addr:housenumber":"8436",
    "addr:postcode":"37143",
    "addr:street":"Old Charlotte Pike",
    "iso:country":"US",
    "sg:address":"8436 Old Charlotte Pike",
    "sg:city":"Pegram",
    "sg:classifiers":[
        {
            "category":"Building & Trades",
            "subcategory":"Construction",
            "type":"Services"
        }
    ],
    "sg:phone":"+1 615 353 0000",
    "sg:postcode":"37143",
    "sg:province":"TN",
    "sg:tags":[
        "house"
    ],
    "wof:name":"Old West Home Improvement",
    "wof:placetype":"venue"
},
  "geometry": {"coordinates":[-86.995887,36.119623],"type":"Point"}
}