{
  "type": "Feature",
  "properties": {
    "iso:country":"US",
    "sg:address":"813 W Main St",
    "sg:city":"Hohenwald",
    "sg:classifiers":[
        {
            "category":"Government",
            "subcategory":"Office",
            "type":"Public Place"
        }
    ],
    "sg:phone":"+1 931 796 1246",
    "sg:postcode":"38462",
    "sg:province":"TN",
    "wof:name":"State Government",
    "wof:placetype":"venue"
},
  "geometry": {"coordinates":[-87.574625,35.550943],"type":"Point"}
}