{
  "type": "Feature",
  "properties": {
    "addr:full":"845 Hornbuckle Rd Clarksville TN 37043",
    "addr:housenumber":"845",
    "addr:postcode":"37043",
    "addr:street":"Hornbuckle Rd",
    "iso:country":"US",
    "sg:address":"845 Hornbuckle Rd",
    "sg:city":"Clarksville",
    "sg:classifiers":[
        {
            "category":"Building & Trades",
            "subcategory":"Plumbing",
            "type":"Services"
        }
    ],
    "sg:phone":"+1 931 358 2129",
    "sg:postcode":"37043",
    "sg:province":"TN",
    "sg:tags":[
        "conditioning",
        "air",
        "system",
        "contractor"
    ],
    "wof:name":"All About Air",
    "wof:placetype":"venue"
},
  "geometry": {"coordinates":[-87.220431,36.529615],"type":"Point"}
}