{
  "type": "Feature",
  "properties": {
    "addr:full":"133 James Asbury Dr NW Cleveland TN 37312",
    "addr:housenumber":"133",
    "addr:postcode":"37312",
    "addr:street":"James Asbury Dr Nw",
    "iso:country":"US",
    "sg:address":"133 James Asbury Dr NW",
    "sg:city":"Cleveland",
    "sg:classifiers":[
        {
            "category":"Restaurant",
            "type":"Food & Drink"
        }
    ],
    "sg:menulink":"http://www.allmenus.com/tn/cleveland/141914-waffle-house/menu/",
    "sg:phone":"+1 432 339 8234",
    "sg:postcode":"37312",
    "sg:province":"TN",
    "sg:tags":[
        "american"
    ],
    "wof:name":"Waffle House",
    "wof:placetype":"venue"
},
  "geometry": {"coordinates":[-84.869119,35.212158],"type":"Point"}
}