{
  "type": "Feature",
  "properties": {
    "iso:country":"US",
    "sg:address":"609 S College St",
    "sg:city":"Winchester",
    "sg:classifiers":[
        {
            "category":"Manufacturing",
            "subcategory":"Metals",
            "type":"Manufacturing & Wholesale Goods"
        }
    ],
    "sg:phone":"+1 931 968 0750",
    "sg:postcode":"37398",
    "sg:province":"TN",
    "sg:tags":[
        "sheet",
        "precision",
        "fabrication"
    ],
    "wof:name":"Aero-Craft",
    "wof:placetype":"venue"
},
  "geometry": {"coordinates":[-86.106669,35.182395],"type":"Point"}
}