{
  "type": "Feature",
  "properties": {
    "iso:country":"US",
    "sg:address":"538 New Shackle Island Rd",
    "sg:city":"Hendersonville",
    "sg:classifiers":[
        {
            "category":"Retail",
            "subcategory":"Veterinary Services",
            "type":"Services"
        }
    ],
    "sg:phone":"+1 615 826 0014",
    "sg:postcode":"37075",
    "sg:province":"TN",
    "sg:tags":[
        "veterinarian"
    ],
    "wof:name":"New Shackle Island Veterinary",
    "wof:placetype":"venue"
},
  "geometry": {"coordinates":[-86.61837199999999,36.331587],"type":"Point"}
}