{
  "type": "Feature",
  "properties": {
    "iso:country":"US",
    "sg:address":"168 Willow Ln",
    "sg:city":"La Follette",
    "sg:classifiers":[
        {
            "category":"Organizations",
            "subcategory":"Religious Organization",
            "type":"Services"
        }
    ],
    "sg:phone":"+1 423 562 9583",
    "sg:postcode":"37766",
    "sg:province":"TN",
    "wof:name":"Well Spring Untd Mthdst Church",
    "wof:placetype":"venue"
},
  "geometry": {"coordinates":[-84.00241699999999,36.418288],"type":"Point"}
}