{
  "type": "Feature",
  "properties": {
    "iso:country":"US",
    "sg:address":"827 Broad St",
    "sg:city":"Chattanooga",
    "sg:classifiers":[
        {
            "category":"Restaurant",
            "type":"Food & Drink"
        }
    ],
    "sg:phone":"+1 423 643 1242",
    "sg:postcode":"37402",
    "sg:province":"TN",
    "sg:tags":[
        "shop",
        "coffee"
    ],
    "wof:name":"Starbucks",
    "wof:placetype":"venue"
},
  "geometry": {"coordinates":[-85.310636,35.046212],"type":"Point"}
}