{
  "type": "Feature",
  "properties": {
    "addr:full":"385 Jones Rd Henning TN 38041",
    "addr:housenumber":"385",
    "addr:postcode":"38041",
    "addr:street":"Jones Rd",
    "iso:country":"US",
    "sg:address":"385 Jones Rd",
    "sg:city":"Henning",
    "sg:phone":"+1 731 738 5310",
    "sg:postcode":"38041",
    "sg:province":"TN",
    "sg:tags":[
        "farm",
        "cotton"
    ],
    "wof:name":"Claude Drain Farm",
    "wof:placetype":"venue"
},
  "geometry": {"coordinates":[-89.669707,35.700225],"type":"Point"}
}