{
  "type": "Feature",
  "properties": {
    "iso:country":"US",
    "sg:address":"709 State Hwy 13 S",
    "sg:city":"Collinwood",
    "sg:classifiers":[
        {
            "category":"Shopping",
            "subcategory":"Discount & Variety Stores",
            "type":"Retail Goods"
        }
    ],
    "sg:phone":"+1 931 724 6770",
    "sg:postcode":"38450",
    "sg:province":"TN",
    "wof:name":"Dollar General",
    "wof:placetype":"venue"
},
  "geometry": {"coordinates":[-87.744471,35.166166],"type":"Point"}
}