{
  "type": "Feature",
  "properties": {
    "iso:country":"US",
    "sg:address":"2195 S Germantown Rd",
    "sg:city":"Germantown",
    "sg:classifiers":[
        {
            "category":"Real Estate",
            "subcategory":"Real Estate Services",
            "type":"Services"
        },
        {
            "category":"Real Estate",
            "subcategory":"Real Estate Agent",
            "type":"Services"
        }
    ],
    "sg:phone":"+1 901 753 6400",
    "sg:postcode":"38138",
    "sg:province":"TN",
    "sg:tags":[
        "buyer",
        "broker"
    ],
    "wof:name":"The Buyer's Agent",
    "wof:placetype":"venue"
},
  "geometry": {"coordinates":[-89.81070699999999,35.08902],"type":"Point"}
}