{
  "type": "Feature",
  "properties": {
    "iso:country":"US",
    "sg:address":"164 Henderson Ave",
    "sg:city":"Sevierville",
    "sg:classifiers":[
        {
            "category":"Banks & Credit Unions",
            "subcategory":"Bank",
            "type":"Services"
        }
    ],
    "sg:phone":"+1 865 428 4426",
    "sg:postcode":"37862",
    "sg:province":"TN",
    "sg:tags":[
        "federal"
    ],
    "wof:name":"Sevier Cnty Schols Fdral Cr Un",
    "wof:placetype":"venue"
},
  "geometry": {"coordinates":[-83.55288299999999,35.863731],"type":"Point"}
}