{
  "type": "Feature",
  "properties": {
    "iso:country":"US",
    "sg:address":"6760 Hickory Creek Rd",
    "sg:city":"Chattanooga",
    "sg:classifiers":[
        {
            "category":"Organizations",
            "subcategory":"Professional Association",
            "type":"Services"
        }
    ],
    "sg:phone":"+1 423 499 5576",
    "sg:postcode":"37421",
    "sg:province":"TN",
    "wof:name":"Hickory Creek Town Home Assn",
    "wof:placetype":"venue"
},
  "geometry": {"coordinates":[-85.16482600000001,35.051098],"type":"Point"}
}