{
  "type": "Feature",
  "properties": {
    "iso:country":"US",
    "sg:address":"5513 Charlotte Pike",
    "sg:city":"Nashville",
    "sg:classifiers":[
        {
            "category":"Banks & Credit Unions",
            "subcategory":"Bank",
            "type":"Services"
        }
    ],
    "sg:phone":"+1 615 356 5756",
    "sg:postcode":"37209",
    "sg:province":"TN",
    "sg:tags":[
        "sell",
        "cashing",
        "money",
        "check",
        "order",
        "store"
    ],
    "sg:website":"www.acecashexpress.com",
    "wof:name":"ACE Cash Express",
    "wof:placetype":"venue"
},
  "geometry": {"coordinates":[-86.857066,36.150307],"type":"Point"}
}