{
  "type": "Feature",
  "properties": {
    "iso:country":"US",
    "sg:address":"475 Cumberland Mountain Ln",
    "sg:city":"Hillsboro",
    "sg:classifiers":[
        {
            "category":"Mining & Drilling",
            "type":"Manufacturing & Wholesale Goods"
        }
    ],
    "sg:phone":"+1 931 596 2841",
    "sg:postcode":"37342",
    "sg:province":"TN",
    "sg:tags":[
        "sand",
        "industrial"
    ],
    "wof:name":"Cumberland Mountain Sand Co",
    "wof:placetype":"venue"
},
  "geometry": {"coordinates":[-85.913769,35.3773],"type":"Point"}
}