{
  "type": "Feature",
  "properties": {
    "iso:country":"US",
    "sg:address":"5715 Kingston Pike",
    "sg:city":"Knoxville",
    "sg:classifiers":[
        {
            "category":"Retail",
            "subcategory":"Auto Repair",
            "type":"Services"
        }
    ],
    "sg:phone":"+1 865 584 0757",
    "sg:postcode":"37919",
    "sg:province":"TN",
    "sg:tags":[
        "automotive",
        "general"
    ],
    "wof:name":"Precision Tune Auto Care",
    "wof:placetype":"venue"
},
  "geometry": {"coordinates":[-83.997073,35.934242],"type":"Point"}
}