{
  "type": "Feature",
  "properties": {
    "addr:full":"1069 Louisville Hwy Goodlettsville TN 37072",
    "addr:housenumber":"1069",
    "addr:postcode":"37072",
    "addr:street":"Louisville Hwy",
    "iso:country":"US",
    "sg:address":"1069 Louisville Hwy",
    "sg:city":"Goodlettsville",
    "sg:classifiers":[
        {
            "category":"Real Estate",
            "subcategory":"Real Estate Operator",
            "type":"Services"
        }
    ],
    "sg:phone":"+1 615 859 5407",
    "sg:postcode":"37072",
    "sg:province":"TN",
    "sg:tags":[
        "mobile",
        "home",
        "site"
    ],
    "wof:name":"Rays Rental",
    "wof:placetype":"venue"
},
  "geometry": {"coordinates":[-86.711552,36.364256],"type":"Point"}
}