{
  "type": "Feature",
  "properties": {
    "addr:full":"336 Sumner Hall Dr Gallatin TN 37066",
    "addr:housenumber":"336",
    "addr:postcode":"37066",
    "addr:street":"Sumner Hall Dr",
    "iso:country":"US",
    "sg:address":"336 Sumner Hall Dr",
    "sg:city":"Gallatin",
    "sg:classifiers":[
        {
            "category":"Health Services",
            "subcategory":"Doctor",
            "type":"Services"
        }
    ],
    "sg:phone":"+1 615 452 8899",
    "sg:postcode":"37066",
    "sg:province":"TN",
    "sg:tags":[
        "medical"
    ],
    "wof:name":"Roger Lavrin DPM",
    "wof:placetype":"venue"
},
  "geometry": {"coordinates":[-86.46432,36.381158],"type":"Point"}
}