{
  "type": "Feature",
  "properties": {
    "addr:full":"7229 Clinton Hwy Powell TN 37849",
    "addr:housenumber":"7229",
    "addr:postcode":"37849",
    "addr:street":"Clinton Hwy",
    "iso:country":"US",
    "sg:address":"7229 Clinton Hwy",
    "sg:city":"Powell",
    "sg:classifiers":[
        {
            "category":"Insurance",
            "subcategory":"Insurance Agent",
            "type":"Services"
        }
    ],
    "sg:phone":"+1 865 938 2801",
    "sg:postcode":"37849",
    "sg:province":"TN",
    "wof:name":"State Farm Insurance",
    "wof:placetype":"venue"
},
  "geometry": {"coordinates":[-84.042888,36.015334],"type":"Point"}
}