{
  "type": "Feature",
  "properties": {
    "iso:country":"US",
    "sg:address":"3744 Nolensville Pike",
    "sg:city":"Nashville",
    "sg:classifiers":[
        {
            "category":"Restaurant",
            "type":"Food & Drink"
        }
    ],
    "sg:phone":"+1 615 781 2902",
    "sg:postcode":"37211",
    "sg:province":"TN",
    "wof:name":"LA Hacienda Mansqueria",
    "wof:placetype":"venue"
},
  "geometry": {"coordinates":[-86.73578500000001,36.092767],"type":"Point"}
}