{
  "type": "Feature",
  "properties": {
    "addr:full":"3265 Cowpath Rd Buchanan TN 38222",
    "addr:housenumber":"3265",
    "addr:postcode":"38222",
    "addr:street":"Cowpath Rd",
    "iso:country":"US",
    "sg:address":"3265 Cowpath Rd",
    "sg:city":"Buchanan",
    "sg:classifiers":[
        {
            "category":"Freight",
            "type":"Transportation"
        }
    ],
    "sg:phone":"+1 731 247 5472",
    "sg:postcode":"38222",
    "sg:province":"TN",
    "sg:tags":[
        "trucking"
    ],
    "wof:name":"D & J Equipment",
    "wof:placetype":"venue"
},
  "geometry": {"coordinates":[-88.223574,36.425735],"type":"Point"}
}