{
  "type": "Feature",
  "properties": {
    "iso:country":"US",
    "sg:address":"3011 Poston Ave",
    "sg:city":"Nashville",
    "sg:classifiers":[
        {
            "category":"Recreation",
            "type":"Entertainment"
        },
        {
            "category":"Museum",
            "type":"Entertainment"
        }
    ],
    "sg:phone":"+1 615 298 4072",
    "sg:postcode":"37203",
    "sg:province":"TN",
    "sg:tags":[
        "organization",
        "arts",
        "gallery",
        "information"
    ],
    "wof:name":"Tennessee Art League Inc",
    "wof:placetype":"venue"
},
  "geometry": {"coordinates":[-86.81572799999999,36.144938],"type":"Point"}
}