{
  "type": "Feature",
  "properties": {
    "addr:full":"5805 Old Hickory Blvd Nashville TN 37218",
    "addr:housenumber":"5805",
    "addr:postcode":"37218",
    "addr:street":"Old Hickory Blvd",
    "iso:country":"US",
    "sg:address":"5805 Old Hickory Blvd",
    "sg:city":"Nashville",
    "sg:classifiers":[
        {
            "category":"Restaurant",
            "type":"Food & Drink"
        }
    ],
    "sg:menulink":"http://www.allmenus.com/tn/nashville/241087-white-castle/menu/",
    "sg:postcode":"37218",
    "sg:province":"TN",
    "sg:tags":[
        "burger",
        "american"
    ],
    "wof:name":"White Castle",
    "wof:placetype":"venue"
},
  "geometry": {"coordinates":[-86.89479300000001,36.255769],"type":"Point"}
}