{
  "type": "Feature",
  "properties": {
    "iso:country":"US",
    "sg:address":"242 River Rd",
    "sg:city":"Andersonville",
    "sg:classifiers":[
        {
            "category":"Professional",
            "subcategory":"Lawyer & Legal Services",
            "type":"Services"
        }
    ],
    "sg:phone":"+1 865 494 9044",
    "sg:postcode":"37705",
    "sg:province":"TN",
    "sg:tags":[
        "attorney"
    ],
    "wof:name":"Shea & Mc Reynolds Attorneys",
    "wof:placetype":"venue"
},
  "geometry": {"coordinates":[-84.092916,36.202131],"type":"Point"}
}