{
  "type": "Feature",
  "properties": {
    "addr:full":"616 N Dupont Ave Madison TN 37115",
    "addr:housenumber":"616",
    "addr:postcode":"37115",
    "addr:street":"N Dupont Ave",
    "iso:country":"US",
    "sg:address":"616 N Dupont Ave",
    "sg:city":"Madison",
    "sg:classifiers":[
        {
            "category":"Social Services",
            "type":"Services"
        }
    ],
    "sg:phone":"+1 615 627 0751",
    "sg:postcode":"37115",
    "sg:province":"TN",
    "wof:name":"Family Dynamics Institute Inc",
    "wof:placetype":"venue"
},
  "geometry": {"coordinates":[-86.697997,36.267257],"type":"Point"}
}