{
  "type": "Feature",
  "properties": {
    "iso:country":"US",
    "sg:address":"1301 E Carroll St",
    "sg:city":"Tullahoma",
    "sg:classifiers":[
        {
            "category":"Professional",
            "subcategory":"Lawyer & Legal Services",
            "type":"Services"
        }
    ],
    "sg:phone":"+1 931 461 9139",
    "sg:postcode":"37388",
    "sg:province":"TN",
    "sg:tags":[
        "attorney"
    ],
    "wof:name":"Van Cleave & Northcott PC",
    "wof:placetype":"venue"
},
  "geometry": {"coordinates":[-86.18522299999999,35.37009],"type":"Point"}
}