{
  "type": "Feature",
  "properties": {
    "addr:full":"9413 Apison Pike Ooltewah TN 37363",
    "addr:housenumber":"9413",
    "addr:postcode":"37363",
    "addr:street":"Apison Pike",
    "iso:country":"US",
    "sg:address":"9413 Apison Pike",
    "sg:city":"Ooltewah",
    "sg:classifiers":[
        {
            "category":"Personal",
            "type":"Services"
        }
    ],
    "sg:phone":"+1 423 396 4786",
    "sg:postcode":"37363",
    "sg:province":"TN",
    "wof:name":"Sunkissed Tanning Salon",
    "wof:placetype":"venue"
},
  "geometry": {"coordinates":[-85.069745,35.060844],"type":"Point"}
}