{
  "type": "Feature",
  "properties": {
    "addr:full":"2033 Chambliss Ave NW Cleveland TN 37311",
    "addr:housenumber":"2033",
    "addr:postcode":"37311",
    "addr:street":"Chambliss Ave Nw",
    "iso:country":"US",
    "sg:address":"2033 Chambliss Ave NW",
    "sg:city":"Cleveland",
    "sg:classifiers":[
        {
            "category":"Insurance",
            "subcategory":"Insurance Agent",
            "type":"Services"
        }
    ],
    "sg:phone":"+1 423 479 2349",
    "sg:postcode":"37311",
    "sg:province":"TN",
    "wof:name":"New York Life",
    "wof:placetype":"venue"
},
  "geometry": {"coordinates":[-84.870311,35.173345],"type":"Point"}
}