{
  "type": "Feature",
  "properties": {
    "iso:country":"US",
    "sg:address":"5747 Browntown Rd",
    "sg:city":"Chattanooga",
    "sg:classifiers":[
        {
            "category":"Restaurant",
            "type":"Food & Drink"
        }
    ],
    "sg:phone":"+1 423 877 8471",
    "sg:postcode":"37415",
    "sg:province":"TN",
    "sg:tags":[
        "eating"
    ],
    "wof:name":"EZ Gourmet",
    "wof:placetype":"venue"
},
  "geometry": {"coordinates":[-85.276869,35.162281],"type":"Point"}
}