{
  "type": "Feature",
  "properties": {
    "iso:country":"US",
    "sg:address":"4529 Holston Dr",
    "sg:city":"Knoxville",
    "sg:classifiers":[
        {
            "category":"Wholesale",
            "subcategory":"Groceries",
            "type":"Manufacturing & Wholesale Goods"
        }
    ],
    "sg:phone":"+1 865 546 5464",
    "sg:postcode":"37914",
    "sg:province":"TN",
    "sg:tags":[
        "baker"
    ],
    "wof:name":"Quality Bakers Inc",
    "wof:placetype":"venue"
},
  "geometry": {"coordinates":[-83.866174,36.003419],"type":"Point"}
}