{
  "type": "Feature",
  "properties": {
    "addr:full":"115 S Main St Sparta TN 38583",
    "addr:housenumber":"115",
    "addr:postcode":"38583",
    "addr:street":"S Main St",
    "iso:country":"US",
    "sg:address":"115 S Main St",
    "sg:city":"Sparta",
    "sg:classifiers":[
        {
            "category":"Professional",
            "subcategory":"Lawyer & Legal Services",
            "type":"Services"
        }
    ],
    "sg:phone":"+1 931 836 3300",
    "sg:postcode":"38583",
    "sg:province":"TN",
    "sg:tags":[
        "attorney"
    ],
    "wof:name":"Ricky L Jenkins",
    "wof:placetype":"venue"
},
  "geometry": {"coordinates":[-85.464541,35.924831],"type":"Point"}
}