{
  "type": "Feature",
  "properties": {
    "iso:country":"US",
    "sg:address":"202 N Thompson Ln",
    "sg:city":"Murfreesboro",
    "sg:classifiers":[
        {
            "category":"Shopping",
            "subcategory":"Tobacco",
            "type":"Retail Goods"
        }
    ],
    "sg:phone":"+1 615 896 6161",
    "sg:postcode":"37129",
    "sg:province":"TN",
    "sg:tags":[
        "product"
    ],
    "wof:name":"Discount Beer & Tobacco Outlet",
    "wof:placetype":"venue"
},
  "geometry": {"coordinates":[-86.42990899999999,35.850356],"type":"Point"}
}