{
  "type": "Feature",
  "properties": {
    "iso:country":"US",
    "sg:address":"7601 Bell Rd",
    "sg:city":"Knoxville",
    "sg:classifiers":[
        {
            "category":"Building & Trades",
            "subcategory":"Landscaping Services",
            "type":"Services"
        }
    ],
    "sg:phone":"+1 865 660 0790",
    "sg:postcode":"37938",
    "sg:province":"TN",
    "wof:name":"Yards Plus",
    "wof:placetype":"venue"
},
  "geometry": {"coordinates":[-83.898724,36.104921],"type":"Point"}
}