{
  "type": "Feature",
  "properties": {
    "iso:country":"US",
    "sg:address":"125 Wallen Town Rd",
    "sg:city":"Church Hill",
    "sg:classifiers":[
        {
            "category":"Shopping",
            "subcategory":"Bicycles & Sporting Goods",
            "type":"Retail Goods"
        }
    ],
    "sg:phone":"+1 423 357 1377",
    "sg:postcode":"37642",
    "sg:province":"TN",
    "sg:tags":[
        "regulation",
        "commercial"
    ],
    "wof:name":"Shooters Hunting Supplies",
    "wof:placetype":"venue"
},
  "geometry": {"coordinates":[-82.692607,36.573045],"type":"Point"}
}