{
  "type": "Feature",
  "properties": {
    "iso:country":"US",
    "sg:address":"523 Mainstream Dr",
    "sg:city":"Nashville",
    "sg:classifiers":[
        {
            "category":"Government",
            "subcategory":"Court House",
            "type":"Public Place"
        }
    ],
    "sg:phone":"+1 615 862 5187",
    "sg:postcode":"37228",
    "sg:province":"TN",
    "wof:name":"Circuit Court Nashville/Davids",
    "wof:placetype":"venue"
},
  "geometry": {"coordinates":[-86.809562,36.199852],"type":"Point"}
}