{
  "type": "Feature",
  "properties": {
    "iso:country":"US",
    "sg:address":"3719 Shelby Rd",
    "sg:city":"Millington",
    "sg:classifiers":[
        {
            "category":"Organizations",
            "subcategory":"Religious Organization",
            "type":"Services"
        }
    ],
    "sg:phone":"+1 901 873 3000",
    "sg:postcode":"38053",
    "sg:province":"TN",
    "sg:tags":[
        "church"
    ],
    "sg:website":"www.lighthousefellowship.com",
    "wof:name":"Lighthouse Fellowship",
    "wof:placetype":"venue"
},
  "geometry": {"coordinates":[-89.934273,35.349716],"type":"Point"}
}