{
  "type": "Feature",
  "properties": {
    "addr:full":"1588 Madison Ave Memphis TN 38104",
    "addr:housenumber":"1588",
    "addr:postcode":"38104",
    "addr:street":"Madison Ave",
    "iso:country":"US",
    "sg:address":"1588 Madison Ave",
    "sg:city":"Memphis",
    "sg:classifiers":[
        {
            "category":"Bars & Pubs",
            "type":"Food & Drink"
        }
    ],
    "sg:phone":"+1 901 278 9839",
    "sg:postcode":"38104",
    "sg:province":"TN",
    "sg:tags":[
        "drinking"
    ],
    "wof:name":"Madison Flame",
    "wof:placetype":"venue"
},
  "geometry": {"coordinates":[-90.00833299999999,35.138219],"type":"Point"}
}