{
  "type": "Feature",
  "properties": {
    "iso:country":"US",
    "sg:address":"2603 US Hwy 11 Bus",
    "sg:city":"Athens",
    "sg:classifiers":[
        {
            "category":"Building & Trades",
            "subcategory":"Construction",
            "type":"Services"
        }
    ],
    "sg:phone":"+1 423 745 2576",
    "sg:postcode":"37303",
    "sg:province":"TN",
    "sg:tags":[
        "water",
        "well",
        "drilling"
    ],
    "wof:name":"Morgan Well Drilling Co",
    "wof:placetype":"venue"
},
  "geometry": {"coordinates":[-84.632637,35.435365],"type":"Point"}
}