{
  "type": "Feature",
  "properties": {
    "iso:country":"US",
    "sg:address":"1608 Long Crescent Dr",
    "sg:city":"Bristol",
    "sg:classifiers":[
        {
            "category":"Shopping",
            "subcategory":"Beauty & Cosmetics",
            "type":"Retail Goods"
        }
    ],
    "sg:phone":"+1 276 669 3035",
    "sg:postcode":"24201",
    "sg:province":"TN",
    "sg:tags":[
        "merchandise"
    ],
    "wof:name":"Beauticontrol Cosmetics",
    "wof:placetype":"venue"
},
  "geometry": {"coordinates":[-82.176582,36.619666],"type":"Point"}
}