{
  "type": "Feature",
  "properties": {
    "iso:country":"US",
    "sg:address":"102 Professional Park Dr",
    "sg:city":"Kingsport",
    "sg:classifiers":[
        {
            "category":"Health Services",
            "subcategory":"Doctor",
            "type":"Services"
        }
    ],
    "sg:phone":"+1 423 224 3370",
    "sg:postcode":"37663",
    "sg:province":"TN",
    "sg:tags":[
        "medical"
    ],
    "wof:name":"Colonial Heights Quick Care",
    "wof:placetype":"venue"
},
  "geometry": {"coordinates":[-82.50153299999999,36.483861],"type":"Point"}
}