{
  "type": "Feature",
  "properties": {
    "iso:country":"US",
    "sg:address":"1195 Quito-Drummonds Rd",
    "sg:city":"Drummonds",
    "sg:classifiers":[
        {
            "category":"Home & Garden",
            "subcategory":"Building Materials",
            "type":"Retail Goods"
        }
    ],
    "sg:phone":"+1 901 835 2125",
    "sg:postcode":"38023",
    "sg:province":"TN",
    "sg:website":"www.doitbest.com",
    "wof:name":"Cole Lumber Co",
    "wof:placetype":"venue"
},
  "geometry": {"coordinates":[-89.921907,35.449077],"type":"Point"}
}