{
  "type": "Feature",
  "properties": {
    "iso:country":"US",
    "sg:address":"4001 Anderson Rd",
    "sg:city":"Nashville",
    "sg:classifiers":[
        {
            "category":"Professional",
            "subcategory":"Business Services",
            "type":"Services"
        }
    ],
    "sg:phone":"+1 615 367 0975",
    "sg:postcode":"37217",
    "sg:province":"TN",
    "wof:name":"Reinforced Concrete Hm Designs",
    "wof:placetype":"venue"
},
  "geometry": {"coordinates":[-86.603217,36.104561],"type":"Point"}
}