{
  "type": "Feature",
  "properties": {
    "iso:country":"US",
    "sg:address":"1824 Old Fort Pkwy",
    "sg:city":"Murfreesboro",
    "sg:classifiers":[
        {
            "category":"Restaurant",
            "type":"Food & Drink"
        }
    ],
    "sg:phone":"+1 615 890 3030",
    "sg:postcode":"37129",
    "sg:province":"TN",
    "sg:tags":[
        "out"
    ],
    "wof:name":"Santa Fe Cantina & Cttlmns Clb",
    "wof:placetype":"venue"
},
  "geometry": {"coordinates":[-86.428512,35.846043],"type":"Point"}
}