{
  "type": "Feature",
  "properties": {
    "iso:country":"US",
    "sg:address":"90 Fesslers Ln",
    "sg:city":"Nashville",
    "sg:classifiers":[
        {
            "category":"Autos & Motor Vehicles",
            "subcategory":"Auto Supplies",
            "type":"Retail Goods"
        }
    ],
    "sg:phone":"+1 615 248 9471",
    "sg:postcode":"37210",
    "sg:province":"TN",
    "sg:tags":[
        "filter",
        "gas"
    ],
    "wof:name":"Camfil Farr",
    "wof:placetype":"venue"
},
  "geometry": {"coordinates":[-86.74327700000001,36.154679],"type":"Point"}
}