{
  "type": "Feature",
  "properties": {
    "addr:full":"730 N Broadway St Knoxville TN 37917",
    "addr:housenumber":"730",
    "addr:postcode":"37917",
    "addr:street":"N Broadway St",
    "iso:country":"US",
    "sg:address":"730 N Broadway St",
    "sg:city":"Knoxville",
    "sg:classifiers":[
        {
            "category":"Professional",
            "subcategory":"Business Services",
            "type":"Services"
        }
    ],
    "sg:phone":"+1 865 633 5079",
    "sg:postcode":"37917",
    "sg:province":"TN",
    "sg:tags":[
        "notary"
    ],
    "wof:name":"NNBS Inc",
    "wof:placetype":"venue"
},
  "geometry": {"coordinates":[-83.92352700000001,35.97739],"type":"Point"}
}