{
  "type": "Feature",
  "properties": {
    "addr:full":"307 29th Ave N Nashville TN 37203",
    "addr:housenumber":"307",
    "addr:postcode":"37203",
    "addr:street":"29Th Ave N",
    "iso:country":"US",
    "sg:address":"307 29th Ave N",
    "sg:city":"Nashville",
    "sg:classifiers":[
        {
            "category":"Wholesale",
            "subcategory":"Medical Equipment & Supplies",
            "type":"Manufacturing & Wholesale Goods"
        }
    ],
    "sg:phone":"+1 615 320 3760",
    "sg:postcode":"37203",
    "sg:province":"TN",
    "sg:tags":[
        "physician",
        "surgeon"
    ],
    "wof:name":"Surgical Resource",
    "wof:placetype":"venue"
},
  "geometry": {"coordinates":[-86.815473,36.147425],"type":"Point"}
}