{
  "type": "Feature",
  "properties": {
    "iso:country":"US",
    "sg:address":"577 E Raines Rd",
    "sg:city":"Memphis",
    "sg:classifiers":[
        {
            "category":"Health Services",
            "subcategory":"Doctor",
            "type":"Services"
        }
    ],
    "sg:phone":"+1 901 345 8582",
    "sg:postcode":"38109",
    "sg:province":"TN",
    "sg:tags":[
        "dentist"
    ],
    "wof:name":"Joyce Franklin-Fresh DDS",
    "wof:placetype":"venue"
},
  "geometry": {"coordinates":[-90.04422,35.034873],"type":"Point"}
}