{
  "type": "Feature",
  "properties": {
    "iso:country":"US",
    "sg:address":"3120 Washington Pike NE",
    "sg:city":"Knoxville",
    "sg:classifiers":[
        {
            "category":"Building & Trades",
            "subcategory":"Cleaning & Sanitation",
            "type":"Services"
        }
    ],
    "sg:phone":"+1 865 971 6810",
    "sg:postcode":"37917",
    "sg:province":"TN",
    "wof:name":"Sparkling Inc",
    "wof:placetype":"venue"
},
  "geometry": {"coordinates":[-83.902704,36.009042],"type":"Point"}
}