{
  "type": "Feature",
  "properties": {
    "iso:country":"US",
    "sg:address":"6 E Main St",
    "sg:city":"Munford",
    "sg:classifiers":[
        {
            "category":"Personal",
            "subcategory":"Beauty Salon",
            "type":"Services"
        }
    ],
    "sg:phone":"+1 901 837 1310",
    "sg:postcode":"38058",
    "sg:province":"TN",
    "sg:tags":[
        "nail",
        "shop"
    ],
    "wof:name":"10 Perfect Nails",
    "wof:placetype":"venue"
},
  "geometry": {"coordinates":[-89.814824,35.449471],"type":"Point"}
}