{
  "type": "Feature",
  "properties": {
    "iso:country":"US",
    "sg:address":"3601 Curtis Ln NE",
    "sg:city":"Knoxville",
    "sg:classifiers":[
        {
            "category":"Shopping",
            "type":"Retail Goods"
        }
    ],
    "sg:phone":"+1 865 688 5158",
    "sg:postcode":"37918",
    "sg:province":"TN",
    "sg:tags":[
        "product",
        "wood",
        "merchandise",
        "mfg"
    ],
    "wof:name":"Moultons Mats & Moulding",
    "wof:placetype":"venue"
},
  "geometry": {"coordinates":[-83.93704,36.04974],"type":"Point"}
}