{
  "type": "Feature",
  "properties": {
    "iso:country":"US",
    "sg:address":"2409 W Main St",
    "sg:city":"Union City",
    "sg:classifiers":[
        {
            "category":"Home & Garden",
            "subcategory":"Hardware",
            "type":"Retail Goods"
        }
    ],
    "sg:phone":"+1 731 884 0058",
    "sg:postcode":"38261",
    "sg:province":"TN",
    "sg:tags":[
        "nut",
        "bolt"
    ],
    "sg:website":"www.fastenal.com",
    "wof:name":"Fastenal Co",
    "wof:placetype":"venue"
},
  "geometry": {"coordinates":[-89.08703300000001,36.434905],"type":"Point"}
}