{
  "type": "Feature",
  "properties": {
    "iso:country":"US",
    "sg:address":"311 Dill Ln",
    "sg:city":"Murfreesboro",
    "sg:classifiers":[
        {
            "category":"Building & Trades",
            "subcategory":"Landscaping Services",
            "type":"Services"
        }
    ],
    "sg:phone":"+1 615 867 3035",
    "sg:postcode":"37130",
    "sg:province":"TN",
    "wof:name":"Nelson Jones Tree Service",
    "wof:placetype":"venue"
},
  "geometry": {"coordinates":[-86.353492,35.83727],"type":"Point"}
}