{
  "type": "Feature",
  "properties": {
    "iso:country":"US",
    "sg:address":"691 Avon Rd",
    "sg:city":"Memphis",
    "sg:classifiers":[
        {
            "category":"Shopping",
            "subcategory":"Beauty & Cosmetics",
            "type":"Retail Goods"
        },
        {
            "category":"Personal",
            "subcategory":"Barber",
            "type":"Services"
        }
    ],
    "sg:phone":"+1 901 767 0659",
    "sg:postcode":"38122",
    "sg:province":"TN",
    "sg:tags":[
        "equipment",
        "salons-equipment",
        "supply"
    ],
    "wof:name":"Terrell Heaton Supply Co",
    "wof:placetype":"venue"
},
  "geometry": {"coordinates":[-89.90201999999999,35.150146],"type":"Point"}
}