{
  "type": "Feature",
  "properties": {
    "addr:full":"2115 Exeter Rd Germantown TN 38138",
    "addr:housenumber":"2115",
    "addr:postcode":"38138",
    "addr:street":"Exeter Rd",
    "iso:country":"US",
    "sg:address":"2115 Exeter Rd",
    "sg:city":"Germantown",
    "sg:classifiers":[
        {
            "category":"Autos & Motor Vehicles",
            "subcategory":"Auto Supplies",
            "type":"Retail Goods"
        },
        {
            "category":"Retail",
            "subcategory":"Auto Repair",
            "type":"Services"
        }
    ],
    "sg:phone":"+1 901 757 2003",
    "sg:postcode":"38138",
    "sg:province":"TN",
    "sg:tags":[
        "lube",
        "oil",
        "tire"
    ],
    "sg:website":"http://www.firestonecompleteautocare.com/?s_kwcid=IYP_NTL",
    "wof:name":"Firestone Complete Auto Care Store",
    "wof:placetype":"venue"
},
  "geometry": {"coordinates":[-89.802576,35.091613],"type":"Point"}
}