{
  "type": "Feature",
  "properties": {
    "iso:country":"US",
    "sg:address":"706 E Central Ave",
    "sg:city":"La Follette",
    "sg:classifiers":[
        {
            "category":"Autos & Motor Vehicles",
            "subcategory":"Fuel & Gas Station",
            "type":"Retail Goods"
        }
    ],
    "sg:phone":"+1 423 563 7514",
    "sg:postcode":"37766",
    "sg:province":"TN",
    "sg:tags":[
        "oil"
    ],
    "wof:name":"West End BP",
    "wof:placetype":"venue"
},
  "geometry": {"coordinates":[-84.114566,36.387206],"type":"Point"}
}