{
  "type": "Feature",
  "properties": {
    "iso:country":"US",
    "sg:address":"141 E Market St",
    "sg:city":"Johnson City",
    "sg:classifiers":[
        {
            "category":"Organizations",
            "subcategory":"Religious Organization",
            "type":"Services"
        }
    ],
    "sg:phone":"+1 423 926 3410",
    "sg:postcode":"37604",
    "sg:province":"TN",
    "wof:name":"Church of Our Lord Jesus",
    "wof:placetype":"venue"
},
  "geometry": {"coordinates":[-82.350989,36.317714],"type":"Point"}
}