{
  "type": "Feature",
  "properties": {
    "addr:full":"1922 E Magnolia Ave Knoxville TN 37917",
    "addr:housenumber":"1922",
    "addr:postcode":"37917",
    "addr:street":"E Magnolia Ave",
    "iso:country":"US",
    "sg:address":"1922 E Magnolia Ave",
    "sg:city":"Knoxville",
    "sg:classifiers":[
        {
            "category":"Manufacturing",
            "subcategory":"Printing",
            "type":"Manufacturing & Wholesale Goods"
        }
    ],
    "sg:phone":"+1 865 523 6427",
    "sg:postcode":"37917",
    "sg:province":"TN",
    "sg:tags":[
        "commercial",
        "letterpress",
        "offset"
    ],
    "wof:name":"Trent Printing Co Inc",
    "wof:placetype":"venue"
},
  "geometry": {"coordinates":[-83.90466600000001,35.97976],"type":"Point"}
}