{
  "type": "Feature",
  "properties": {
    "addr:full":"3080 Williamsport Pike Columbia TN 38401",
    "addr:housenumber":"3080",
    "addr:postcode":"38401",
    "addr:street":"Williamsport Pike",
    "iso:country":"US",
    "sg:address":"3080 Williamsport Pike",
    "sg:city":"Columbia",
    "sg:classifiers":[
        {
            "category":"Building & Trades",
            "subcategory":"Construction",
            "type":"Services"
        }
    ],
    "sg:phone":"+1 931 583 0055",
    "sg:postcode":"38401",
    "sg:province":"TN",
    "sg:tags":[
        "home",
        "builder"
    ],
    "wof:name":"Miric Construction Inc",
    "wof:placetype":"venue"
},
  "geometry": {"coordinates":[-87.168924,35.651969],"type":"Point"}
}