{
  "type": "Feature",
  "properties": {
    "addr:full":"384 Linden St Dresden TN 38225",
    "addr:housenumber":"384",
    "addr:postcode":"38225",
    "addr:street":"Linden St",
    "iso:country":"US",
    "sg:address":"384 Linden St",
    "sg:city":"Dresden",
    "sg:classifiers":[
        {
            "category":"Social Services",
            "subcategory":"Child Care",
            "type":"Services"
        }
    ],
    "sg:phone":"+1 731 364 3462",
    "sg:postcode":"38225",
    "sg:province":"TN",
    "sg:tags":[
        "day"
    ],
    "wof:name":"Gingerbread Junction",
    "wof:placetype":"venue"
},
  "geometry": {"coordinates":[-88.70598,36.286635],"type":"Point"}
}