{
  "type": "Feature",
  "properties": {
    "addr:full":"6401 Ringgold Rd Chattanooga TN 37412",
    "addr:housenumber":"6401",
    "addr:postcode":"37412",
    "addr:street":"Ringgold Rd",
    "iso:country":"US",
    "sg:address":"6401 Ringgold Rd",
    "sg:city":"Chattanooga",
    "sg:classifiers":[
        {
            "category":"Restaurant",
            "type":"Food & Drink"
        }
    ],
    "sg:menulink":"http://www.allmenus.com/tn/east-ridge/203545-mcdonalds/menu/",
    "sg:postcode":"37412",
    "sg:province":"TN",
    "sg:tags":[
        "burger",
        "american"
    ],
    "wof:name":"McDonald's",
    "wof:placetype":"venue"
},
  "geometry": {"coordinates":[-85.210009,34.990015],"type":"Point"}
}