{
  "type": "Feature",
  "properties": {
    "addr:full":"425 Harding Rd Kingsport TN 37663",
    "addr:housenumber":"425",
    "addr:postcode":"37663",
    "addr:street":"Harding Rd",
    "iso:country":"US",
    "sg:address":"425 Harding Rd",
    "sg:city":"Kingsport",
    "sg:classifiers":[
        {
            "category":"Personal",
            "subcategory":"Beauty Salon",
            "type":"Services"
        }
    ],
    "sg:phone":"+1 423 247 6245",
    "sg:postcode":"37663",
    "sg:province":"TN",
    "sg:tags":[
        "shop"
    ],
    "wof:name":"Nail Paparazzi",
    "wof:placetype":"venue"
},
  "geometry": {"coordinates":[-82.50506,36.472148],"type":"Point"}
}