{
  "type": "Feature",
  "properties": {
    "addr:full":"617 Elkins Rd Woodbury TN 37190",
    "addr:housenumber":"617",
    "addr:postcode":"37190",
    "addr:street":"Elkins Rd",
    "iso:country":"US",
    "sg:address":"617 Elkins Rd",
    "sg:city":"Woodbury",
    "sg:classifiers":[
        {
            "category":"Farming",
            "subcategory":"Farm",
            "type":"Manufacturing & Wholesale Goods"
        }
    ],
    "sg:phone":"+1 615 563 8311",
    "sg:postcode":"37190",
    "sg:province":"TN",
    "sg:tags":[
        "crop",
        "general"
    ],
    "wof:name":"Roger Martin",
    "wof:placetype":"venue"
},
  "geometry": {"coordinates":[-85.96590999999999,35.783274],"type":"Point"}
}