{
  "type": "Feature",
  "properties": {
    "addr:full":"500 Pickwick St S Savannah TN 38372",
    "addr:housenumber":"500",
    "addr:postcode":"38372",
    "addr:street":"Pickwick St S",
    "iso:country":"US",
    "sg:address":"500 Pickwick St S",
    "sg:city":"Savannah",
    "sg:classifiers":[
        {
            "category":"Autos & Motor Vehicles",
            "subcategory":"Auto Supplies",
            "type":"Retail Goods"
        }
    ],
    "sg:phone":"+1 731 925 1180",
    "sg:postcode":"38372",
    "sg:province":"TN",
    "wof:name":"Quality Tire & Service Center",
    "wof:placetype":"venue"
},
  "geometry": {"coordinates":[-88.246082,35.218489],"type":"Point"}
}