{
  "type": "Feature",
  "properties": {
    "iso:country":"US",
    "sg:address":"39 N Lambert Ln",
    "sg:city":"Westmoreland",
    "sg:classifiers":[
        {
            "category":"Home & Garden",
            "subcategory":"Carpets & Floor Coverings",
            "type":"Retail Goods"
        }
    ],
    "sg:phone":"+1 615 644 3627",
    "sg:postcode":"37186",
    "sg:province":"TN",
    "wof:name":"Home Sweet Homes",
    "wof:placetype":"venue"
},
  "geometry": {"coordinates":[-86.21015800000001,36.544477],"type":"Point"}
}