{
  "type": "Feature",
  "properties": {
    "iso:country":"US",
    "sg:address":"595 Moore Rd",
    "sg:city":"Savannah",
    "sg:classifiers":[
        {
            "category":"Restaurant",
            "type":"Food & Drink"
        }
    ],
    "sg:phone":"+1 731 925 6422",
    "sg:postcode":"38372",
    "sg:province":"TN",
    "wof:name":"Shelly's Restaurant & Catering",
    "wof:placetype":"venue"
},
  "geometry": {"coordinates":[-88.185954,35.243387],"type":"Point"}
}