{
  "type": "Feature",
  "properties": {
    "addr:full":"1776 Fort Henry Dr Kingsport TN 37664",
    "addr:housenumber":"1776",
    "addr:postcode":"37664",
    "addr:street":"Fort Henry Dr",
    "iso:country":"US",
    "sg:address":"1776 Fort Henry Dr",
    "sg:city":"Kingsport",
    "sg:classifiers":[
        {
            "category":"Banks & Credit Unions",
            "subcategory":"Bank",
            "type":"Services"
        }
    ],
    "sg:phone":"+1 423 245 5509",
    "sg:postcode":"37664",
    "sg:province":"TN",
    "wof:name":"B B & T",
    "wof:placetype":"venue"
},
  "geometry": {"coordinates":[-82.525904,36.531035],"type":"Point"}
}