{
  "type": "Feature",
  "properties": {
    "addr:full":"5714 Benjestown Rd Memphis TN 38127",
    "addr:housenumber":"5714",
    "addr:postcode":"38127",
    "addr:street":"Benjestown Rd",
    "iso:country":"US",
    "sg:address":"5714 Benjestown Rd",
    "sg:city":"Memphis",
    "sg:classifiers":[
        {
            "category":"Organizations",
            "subcategory":"Religious Organization",
            "type":"Services"
        }
    ],
    "sg:phone":"+1 901 353 4730",
    "sg:postcode":"38127",
    "sg:province":"TN",
    "wof:name":"Oaklawn Baptist Church",
    "wof:placetype":"venue"
},
  "geometry": {"coordinates":[-90.03947700000001,35.277391],"type":"Point"}
}