{
  "type": "Feature",
  "properties": {
    "iso:country":"US",
    "sg:address":"2051 Hamill Rd",
    "sg:city":"Hixson",
    "sg:classifiers":[
        {
            "category":"Health Services",
            "subcategory":"Doctor",
            "type":"Services"
        }
    ],
    "sg:phone":"+1 423 877 8131",
    "sg:postcode":"37343",
    "sg:province":"TN",
    "sg:tags":[
        "medicine",
        "injury",
        "sport"
    ],
    "wof:name":"Thomas E Moses MD",
    "wof:placetype":"venue"
},
  "geometry": {"coordinates":[-85.237669,35.123491],"type":"Point"}
}