{
  "type": "Feature",
  "properties": {
    "addr:full":"1600 Sparta St Mc Minnville TN 37110",
    "addr:housenumber":"1600",
    "addr:postcode":"37110",
    "addr:street":"Sparta St",
    "iso:country":"US",
    "sg:address":"1600 Sparta St",
    "sg:city":"Mc Minnville",
    "sg:classifiers":[
        {
            "category":"Autos & Motor Vehicles",
            "subcategory":"Automobile Sales",
            "type":"Retail Goods"
        }
    ],
    "sg:phone":"+1 931 473 1535",
    "sg:postcode":"37110",
    "sg:province":"TN",
    "sg:tags":[
        "car",
        "dealer"
    ],
    "wof:name":"Edd Rogers Automotive",
    "wof:placetype":"venue"
},
  "geometry": {"coordinates":[-85.74104199999999,35.699674],"type":"Point"}
}