{
  "type": "Feature",
  "properties": {
    "iso:country":"US",
    "sg:address":"1000 Halcyon Ave",
    "sg:city":"Nashville",
    "sg:classifiers":[
        {
            "category":"Organizations",
            "subcategory":"Religious Organization",
            "type":"Services"
        }
    ],
    "sg:phone":"+1 615 298 1832",
    "sg:postcode":"37204",
    "sg:province":"TN",
    "sg:tags":[
        "church"
    ],
    "wof:name":"Second Missionary Baptist Chr",
    "wof:placetype":"venue"
},
  "geometry": {"coordinates":[-86.78818200000001,36.122493],"type":"Point"}
}