{
  "type": "Feature",
  "properties": {
    "addr:full":"3755 Range Line Rd Memphis TN 38127",
    "addr:housenumber":"3755",
    "addr:postcode":"38127",
    "addr:street":"Range Line Rd",
    "iso:country":"US",
    "sg:address":"3755 Range Line Rd",
    "sg:city":"Memphis",
    "sg:classifiers":[
        {
            "category":"Organizations",
            "subcategory":"Religious Organization",
            "type":"Services"
        }
    ],
    "sg:phone":"+1 901 358 4773",
    "sg:postcode":"38127",
    "sg:province":"TN",
    "wof:name":"Jehovah Witnesses Kingdom Hall",
    "wof:placetype":"venue"
},
  "geometry": {"coordinates":[-89.975632,35.227478],"type":"Point"}
}