{
  "type": "Feature",
  "properties": {
    "iso:country":"US",
    "sg:address":"5733 Nanjack Cir",
    "sg:city":"Memphis",
    "sg:classifiers":[
        {
            "category":"Manufacturing",
            "subcategory":"Printing",
            "type":"Manufacturing & Wholesale Goods"
        }
    ],
    "sg:phone":"+1 901 363 1994",
    "sg:postcode":"38115",
    "sg:province":"TN",
    "sg:tags":[
        "commercial"
    ],
    "wof:name":"R R Donnelley & Sons Company",
    "wof:placetype":"venue"
},
  "geometry": {"coordinates":[-89.872148,35.073169],"type":"Point"}
}