{
  "type": "Feature",
  "properties": {
    "iso:country":"US",
    "sg:address":"1450 Spring Place Rd SE",
    "sg:city":"Cleveland",
    "sg:classifiers":[
        {
            "category":"Shopping",
            "subcategory":"Music",
            "type":"Retail Goods"
        },
        {
            "category":"Cinema",
            "subcategory":"Movie Rental",
            "type":"Entertainment"
        }
    ],
    "sg:phone":"+1 423 479 9201",
    "sg:postcode":"37323",
    "sg:province":"TN",
    "sg:tags":[
        "video",
        "disc",
        "tape",
        "cassette"
    ],
    "wof:name":"Parker's Video Rentals",
    "wof:placetype":"venue"
},
  "geometry": {"coordinates":[-84.867645,35.1395],"type":"Point"}
}