{
  "type": "Feature",
  "properties": {
    "iso:country":"US",
    "sg:address":"7603 Maynardville Pike",
    "sg:city":"Knoxville",
    "sg:classifiers":[
        {
            "category":"Building & Trades",
            "subcategory":"Construction",
            "type":"Services"
        }
    ],
    "sg:phone":"+1 865 922 7473",
    "sg:postcode":"37938",
    "sg:province":"TN",
    "sg:tags":[
        "pavement",
        "marking"
    ],
    "wof:name":"Volunteer Highway Supply Co",
    "wof:placetype":"venue"
},
  "geometry": {"coordinates":[-83.917512,36.09428],"type":"Point"}
}