{
  "type": "Feature",
  "properties": {
    "addr:full":"726 W Old Hickory Blvd Madison TN 37115",
    "addr:housenumber":"726",
    "addr:postcode":"37115",
    "addr:street":"W Old Hickory Blvd",
    "iso:country":"US",
    "sg:address":"726 W Old Hickory Blvd",
    "sg:city":"Madison",
    "sg:classifiers":[
        {
            "category":"Organizations",
            "subcategory":"Religious Organization",
            "type":"Services"
        }
    ],
    "sg:phone":"+1 615 865 6655",
    "sg:postcode":"37115",
    "sg:province":"TN",
    "sg:tags":[
        "god",
        "assembly"
    ],
    "sg:website":"www.cornerstonenashville.org",
    "wof:name":"Cornerstone Church",
    "wof:placetype":"venue"
},
  "geometry": {"coordinates":[-86.733895,36.264288],"type":"Point"}
}