{
  "type": "Feature",
  "properties": {
    "iso:country":"US",
    "sg:address":"637 Hwy 120",
    "sg:city":"Big Rock",
    "sg:classifiers":[
        {
            "category":"Professional",
            "subcategory":"Business Services",
            "type":"Services"
        }
    ],
    "sg:phone":"+1 931 232 8900",
    "sg:postcode":"37023",
    "sg:province":"TN",
    "wof:name":"Keatts Enterprises Inc",
    "wof:placetype":"venue"
},
  "geometry": {"coordinates":[-87.73538499999999,36.570882],"type":"Point"}
}