{
  "type": "Feature",
  "properties": {
    "addr:full":"207 Lynnwood Blvd Nashville TN 37205",
    "addr:housenumber":"207",
    "addr:postcode":"37205",
    "addr:street":"Lynnwood Blvd",
    "iso:country":"US",
    "sg:address":"207 Lynnwood Blvd",
    "sg:city":"Nashville",
    "sg:classifiers":[
        {
            "category":"Professional",
            "subcategory":"Business Services",
            "type":"Services"
        }
    ],
    "sg:phone":"+1 615 948 1464",
    "sg:postcode":"37205",
    "sg:province":"TN",
    "wof:name":"Teri Worthington Interiors",
    "wof:placetype":"venue"
},
  "geometry": {"coordinates":[-86.847938,36.116101],"type":"Point"}
}