{
  "type": "Feature",
  "properties": {
    "iso:country":"US",
    "sg:address":"60 E Frank Ave",
    "sg:city":"Memphis",
    "sg:classifiers":[
        {
            "category":"Manufacturing",
            "subcategory":"Food",
            "type":"Manufacturing & Wholesale Goods"
        }
    ],
    "sg:phone":"+1 901 942 7498",
    "sg:postcode":"38109",
    "sg:province":"TN",
    "sg:tags":[
        "mfg"
    ],
    "wof:name":"Stephanie Newson",
    "wof:placetype":"venue"
},
  "geometry": {"coordinates":[-90.062646,35.090716],"type":"Point"}
}