{
  "type": "Feature",
  "properties": {
    "iso:country":"US",
    "sg:address":"113 W Main St",
    "sg:city":"Halls",
    "sg:classifiers":[
        {
            "category":"Social Services",
            "type":"Services"
        }
    ],
    "sg:phone":"+1 731 836 7079",
    "sg:postcode":"38040",
    "sg:province":"TN",
    "sg:tags":[
        "mission"
    ],
    "wof:name":"Hall's Union Mission",
    "wof:placetype":"venue"
},
  "geometry": {"coordinates":[-89.396581,35.875353],"type":"Point"}
}