{
  "type": "Feature",
  "properties": {
    "iso:country":"US",
    "sg:address":"4926 Leven Rd",
    "sg:city":"Memphis",
    "sg:classifiers":[
        {
            "category":"Professional",
            "subcategory":"Business Services",
            "type":"Services"
        }
    ],
    "sg:phone":"+1 901 565 8977",
    "sg:postcode":"38118",
    "sg:province":"TN",
    "wof:name":"CC USA Askew Enterprises LLC",
    "wof:placetype":"venue"
},
  "geometry": {"coordinates":[-89.898155,35.044711],"type":"Point"}
}