{
  "type": "Feature",
  "properties": {
    "iso:country":"US",
    "sg:address":"119 S Crest Rd",
    "sg:city":"Chattanooga",
    "sg:classifiers":[
        {
            "category":"Manufacturing",
            "subcategory":"Metals",
            "type":"Manufacturing & Wholesale Goods"
        }
    ],
    "sg:phone":"+1 423 624 8992",
    "sg:postcode":"37404",
    "sg:province":"TN",
    "sg:tags":[
        "repair",
        "condenser",
        "boiler"
    ],
    "wof:name":"Condenser & Boiler Tools Inc",
    "wof:placetype":"venue"
},
  "geometry": {"coordinates":[-85.263795,35.019131],"type":"Point"}
}