{
  "type": "Feature",
  "properties": {
    "iso:country":"US",
    "sg:address":"377 Co Rd 752",
    "sg:city":"Riceville",
    "sg:classifiers":[
        {
            "category":"Shopping",
            "subcategory":"Discount & Variety Stores",
            "type":"Retail Goods"
        }
    ],
    "sg:phone":"+1 423 507 8080",
    "sg:postcode":"37370",
    "sg:province":"TN",
    "wof:name":"Variety Outlet",
    "wof:placetype":"venue"
},
  "geometry": {"coordinates":[-84.64826100000001,35.348334],"type":"Point"}
}