{
  "type": "Feature",
  "properties": {
    "iso:country":"US",
    "sg:address":"3890 Jackson Ave",
    "sg:city":"Memphis",
    "sg:classifiers":[
        {
            "category":"Wholesale",
            "subcategory":"Auto Parts",
            "type":"Manufacturing & Wholesale Goods"
        }
    ],
    "sg:phone":"+1 901 388 4791",
    "sg:postcode":"38128",
    "sg:province":"TN",
    "sg:tags":[
        "repair",
        "supply"
    ],
    "wof:name":"American Battery Company Inc",
    "wof:placetype":"venue"
},
  "geometry": {"coordinates":[-89.931641,35.18461],"type":"Point"}
}