{
  "type": "Feature",
  "properties": {
    "addr:full":"4707 Dayton Blvd Chattanooga TN 37415",
    "addr:housenumber":"4707",
    "addr:postcode":"37415",
    "addr:street":"Dayton Blvd",
    "iso:country":"US",
    "sg:address":"4707 Dayton Blvd",
    "sg:city":"Chattanooga",
    "sg:classifiers":[
        {
            "category":"Shopping",
            "subcategory":"Discount & Variety Stores",
            "type":"Retail Goods"
        }
    ],
    "sg:phone":"+1 423 875 9100",
    "sg:postcode":"37415",
    "sg:province":"TN",
    "wof:name":"Dollar General",
    "wof:placetype":"venue"
},
  "geometry": {"coordinates":[-85.280824,35.135065],"type":"Point"}
}