{
  "type": "Feature",
  "properties": {
    "addr:full":"1329 Mari Jon Dr Chattanooga TN 37421",
    "addr:housenumber":"1329",
    "addr:postcode":"37421",
    "addr:street":"Mari Jon Dr",
    "iso:country":"US",
    "sg:address":"1329 Mari Jon Dr",
    "sg:city":"Chattanooga",
    "sg:classifiers":[
        {
            "category":"Health Services",
            "subcategory":"Doctor",
            "type":"Services"
        }
    ],
    "sg:phone":"+1 423 855 4738",
    "sg:postcode":"37421",
    "sg:province":"TN",
    "sg:tags":[
        "medical"
    ],
    "wof:name":"Lonnie R Boaz III MD",
    "wof:placetype":"venue"
},
  "geometry": {"coordinates":[-85.182277,35.021532],"type":"Point"}
}