{
  "type": "Feature",
  "properties": {
    "iso:country":"US",
    "sg:address":"81 Monroe Ave",
    "sg:city":"Memphis",
    "sg:classifiers":[
        {
            "category":"Professional",
            "subcategory":"Lawyer & Legal Services",
            "type":"Services"
        }
    ],
    "sg:phone":"+1 901 507 2524",
    "sg:postcode":"38103",
    "sg:province":"TN",
    "sg:tags":[
        "attorney"
    ],
    "wof:name":"Julian Bolton",
    "wof:placetype":"venue"
},
  "geometry": {"coordinates":[-90.053438,35.144181],"type":"Point"}
}