{
  "type": "Feature",
  "properties": {
    "iso:country":"US",
    "sg:address":"6075 Winchester Rd",
    "sg:city":"Memphis",
    "sg:classifiers":[
        {
            "category":"Shopping",
            "subcategory":"Gifts & Souvenirs",
            "type":"Retail Goods"
        }
    ],
    "sg:phone":"+1 901 363 4405",
    "sg:postcode":"38115",
    "sg:province":"TN",
    "sg:tags":[
        "shop"
    ],
    "wof:name":"Briar Patch Store",
    "wof:placetype":"venue"
},
  "geometry": {"coordinates":[-89.85878599999999,35.049739],"type":"Point"}
}