{
  "type": "Feature",
  "properties": {
    "addr:full":"1563 Grant Rd Sevierville TN 37876",
    "addr:housenumber":"1563",
    "addr:postcode":"37876",
    "addr:street":"Grant Rd",
    "iso:country":"US",
    "sg:address":"1563 Grant Rd",
    "sg:city":"Sevierville",
    "sg:classifiers":[
        {
            "category":"Building & Trades",
            "subcategory":"Equipment Rental",
            "type":"Services"
        },
        {
            "category":"Travel",
            "subcategory":"Hotels & Motels",
            "type":"Entertainment"
        }
    ],
    "sg:phone":"+1 865 429 5194",
    "sg:postcode":"37876",
    "sg:province":"TN",
    "sg:tags":[
        "resort"
    ],
    "wof:name":"River Mist Log Cabin Rentals",
    "wof:placetype":"venue"
},
  "geometry": {"coordinates":[-83.420693,35.797866],"type":"Point"}
}