{
  "type": "Feature",
  "properties": {
    "iso:country":"US",
    "sg:address":"463 S Water Ave",
    "sg:city":"Gallatin",
    "sg:classifiers":[
        {
            "category":"Home & Garden",
            "subcategory":"Carpets & Floor Coverings",
            "type":"Retail Goods"
        }
    ],
    "sg:phone":"+1 615 451 4838",
    "sg:postcode":"37066",
    "sg:province":"TN",
    "sg:tags":[
        "dealer",
        "rug"
    ],
    "wof:name":"Foster's Floor Covering",
    "wof:placetype":"venue"
},
  "geometry": {"coordinates":[-86.443831,36.381843],"type":"Point"}
}