{
  "type": "Feature",
  "properties": {
    "iso:country":"US",
    "sg:address":"720 Smelcer St",
    "sg:city":"Seymour",
    "sg:classifiers":[
        {
            "category":"Retail",
            "subcategory":"Repair Shop",
            "type":"Services"
        }
    ],
    "sg:phone":"+1 865 577 3726",
    "sg:postcode":"37865",
    "sg:province":"TN",
    "sg:tags":[
        "welding"
    ],
    "wof:name":"Louis Branch",
    "wof:placetype":"venue"
},
  "geometry": {"coordinates":[-83.760375,35.846799],"type":"Point"}
}