{
  "type": "Feature",
  "properties": {
    "iso:country":"US",
    "sg:address":"615 Woodland St",
    "sg:city":"Nashville",
    "sg:classifiers":[
        {
            "category":"Professional",
            "type":"Services"
        }
    ],
    "sg:phone":"+1 615 369 3278",
    "sg:postcode":"37206",
    "sg:province":"TN",
    "wof:name":"Villiage Real Estate",
    "wof:placetype":"venue"
},
  "geometry": {"coordinates":[-86.76064599999999,36.17347],"type":"Point"}
}