{
  "type": "Feature",
  "properties": {
    "iso:country":"US",
    "sg:address":"5640 Summer Ave Ste 3",
    "sg:city":"Memphis",
    "sg:classifiers":[
        {
            "category":"Wholesale",
            "subcategory":"Medical Equipment & Supplies",
            "type":"Manufacturing & Wholesale Goods"
        },
        {
            "category":"Shopping",
            "subcategory":"Pharmacy",
            "type":"Retail Goods"
        }
    ],
    "sg:phone":"+1 901 373 0095",
    "sg:postcode":"38134",
    "sg:province":"TN",
    "sg:tags":[
        "home",
        "wheelchair",
        "health",
        "care"
    ],
    "sg:website":"http://www.handicapunlimited.com",
    "wof:name":"Handicap Unlimited Inc",
    "wof:placetype":"venue"
},
  "geometry": {"coordinates":[-89.874641,35.165871],"type":"Point"}
}