{
  "type": "Feature",
  "properties": {
    "iso:country":"US",
    "sg:address":"408 Andover Dr",
    "sg:city":"Smyrna",
    "sg:classifiers":[
        {
            "category":"Organizations",
            "subcategory":"Religious Organization",
            "type":"Services"
        }
    ],
    "sg:phone":"+1 615 220 1934",
    "sg:postcode":"37167",
    "sg:province":"TN",
    "wof:name":"Grace Christian Assembly",
    "wof:placetype":"venue"
},
  "geometry": {"coordinates":[-86.512534,35.937446],"type":"Point"}
}