{
  "type": "Feature",
  "properties": {
    "iso:country":"US",
    "sg:address":"1113 S Spring Hollow Rd",
    "sg:city":"Sevierville",
    "sg:classifiers":[
        {
            "category":"Home & Garden",
            "subcategory":"Furniture",
            "type":"Retail Goods"
        }
    ],
    "sg:phone":"+1 865 436 5127",
    "sg:postcode":"37876",
    "sg:province":"TN",
    "wof:name":"Southern Plantations Furniture",
    "wof:placetype":"venue"
},
  "geometry": {"coordinates":[-83.50073500000001,35.752633],"type":"Point"}
}