{
  "type": "Feature",
  "properties": {
    "addr:full":"396 W Bockman Way Sparta TN 38583",
    "addr:housenumber":"396",
    "addr:postcode":"38583",
    "addr:street":"W Bockman Way",
    "iso:country":"US",
    "sg:address":"396 W Bockman Way",
    "sg:city":"Sparta",
    "sg:classifiers":[
        {
            "category":"Wholesale",
            "subcategory":"Furniture",
            "type":"Manufacturing & Wholesale Goods"
        }
    ],
    "sg:phone":"+1 931 836 3055",
    "sg:postcode":"38583",
    "sg:province":"TN",
    "wof:name":"This N That",
    "wof:placetype":"venue"
},
  "geometry": {"coordinates":[-85.472132,35.929681],"type":"Point"}
}