{
  "type": "Feature",
  "properties": {
    "iso:country":"US",
    "sg:address":"7720 State Hwy 54 N",
    "sg:city":"Brownsville",
    "sg:classifiers":[
        {
            "category":"Organizations",
            "subcategory":"Religious Organization",
            "type":"Services"
        }
    ],
    "sg:phone":"+1 731 772 4791",
    "sg:postcode":"38012",
    "sg:province":"TN",
    "sg:tags":[
        "church"
    ],
    "wof:name":"Family Life Fellowship Church",
    "wof:placetype":"venue"
},
  "geometry": {"coordinates":[-89.22162899999999,35.692781],"type":"Point"}
}