{
  "type": "Feature",
  "properties": {
    "iso:country":"US",
    "sg:address":"1511 Foust St",
    "sg:city":"Chattanooga",
    "sg:classifiers":[
        {
            "category":"Retail",
            "subcategory":"Funeral Services",
            "type":"Services"
        }
    ],
    "sg:phone":"+1 423 622 1707",
    "sg:postcode":"37404",
    "sg:province":"TN",
    "wof:name":"K A R C Funeral Escort & Secur",
    "wof:placetype":"venue"
},
  "geometry": {"coordinates":[-85.291005,35.01628],"type":"Point"}
}