{
  "type": "Feature",
  "properties": {
    "iso:country":"US",
    "sg:address":"1750 Newport Hwy",
    "sg:city":"Sevierville",
    "sg:classifiers":[
        {
            "category":"Banks & Credit Unions",
            "subcategory":"Investment Brokerage",
            "type":"Services"
        }
    ],
    "sg:phone":"+1 865 774 5513",
    "sg:postcode":"37876",
    "sg:province":"TN",
    "sg:tags":[
        "consultant",
        "financing"
    ],
    "wof:name":"Dollars 4U",
    "wof:placetype":"venue"
},
  "geometry": {"coordinates":[-83.500012,35.869511],"type":"Point"}
}