{
  "type": "Feature",
  "properties": {
    "iso:country":"US",
    "sg:address":"1658 Jackson Love Hwy",
    "sg:city":"Erwin",
    "sg:classifiers":[
        {
            "category":"Taxi",
            "type":"Transportation"
        }
    ],
    "sg:phone":"+1 423 743 6248",
    "sg:postcode":"37650",
    "sg:province":"TN",
    "sg:tags":[
        "taxicab"
    ],
    "wof:name":"Erwin Taxi Co",
    "wof:placetype":"venue"
},
  "geometry": {"coordinates":[-82.435822,36.125289],"type":"Point"}
}