{
  "type": "Feature",
  "properties": {
    "addr:full":"183 John McGhee Blvd Caryville TN 37714",
    "addr:housenumber":"183",
    "addr:postcode":"37714",
    "addr:street":"John Mcghee Blvd",
    "iso:country":"US",
    "sg:address":"183 John McGhee Blvd",
    "sg:city":"Caryville",
    "sg:classifiers":[
        {
            "category":"Shopping",
            "subcategory":"Used Merchandise",
            "type":"Retail Goods"
        }
    ],
    "sg:phone":"+1 423 562 7144",
    "sg:postcode":"37714",
    "sg:province":"TN",
    "sg:tags":[
        "pawnbroker"
    ],
    "wof:name":"Caryville Pawn Shop",
    "wof:placetype":"venue"
},
  "geometry": {"coordinates":[-84.213488,36.2939],"type":"Point"}
}