{
  "type": "Feature",
  "properties": {
    "iso:country":"US",
    "sg:address":"165 Alpha Dr",
    "sg:city":"Gallatin",
    "sg:classifiers":[
        {
            "category":"Building & Trades",
            "subcategory":"Landscaping Services",
            "type":"Services"
        }
    ],
    "sg:phone":"+1 615 452 2826",
    "sg:postcode":"37066",
    "sg:province":"TN",
    "wof:name":"Corley Landscaping",
    "wof:placetype":"venue"
},
  "geometry": {"coordinates":[-86.409435,36.412462],"type":"Point"}
}