{
  "type": "Feature",
  "properties": {
    "iso:country":"US",
    "sg:address":"3 Belvoir Cir",
    "sg:city":"Chattanooga",
    "sg:classifiers":[
        {
            "category":"Manufacturing",
            "subcategory":"Retail Goods",
            "type":"Manufacturing & Wholesale Goods"
        }
    ],
    "sg:phone":"+1 423 698 5685",
    "sg:postcode":"37412",
    "sg:province":"TN",
    "sg:tags":[
        "product",
        "mfg"
    ],
    "wof:name":"Carr Enterprises",
    "wof:placetype":"venue"
},
  "geometry": {"coordinates":[-85.245739,35.006461],"type":"Point"}
}