{
  "type": "Feature",
  "properties": {
    "iso:country":"US",
    "sg:address":"5575 Poplar Ave Ste 811",
    "sg:city":"Memphis",
    "sg:classifiers":[
        {
            "category":"Wholesale",
            "subcategory":"Medical Equipment & Supplies",
            "type":"Manufacturing & Wholesale Goods"
        },
        {
            "category":"Shopping",
            "subcategory":"Pharmacy",
            "type":"Retail Goods"
        }
    ],
    "sg:phone":"+1 901 761 9798",
    "sg:postcode":"38119",
    "sg:province":"TN",
    "sg:tags":[
        "home",
        "health",
        "care"
    ],
    "wof:name":"Stf Medical Inc",
    "wof:placetype":"venue"
},
  "geometry": {"coordinates":[-89.876352,35.105521],"type":"Point"}
}