{
  "type": "Feature",
  "properties": {
    "addr:full":"2812 Hidden Trail Ln Chattanooga TN 37421",
    "addr:housenumber":"2812",
    "addr:postcode":"37421",
    "addr:street":"Hidden Trail Ln",
    "iso:country":"US",
    "sg:address":"2812 Hidden Trail Ln",
    "sg:city":"Chattanooga",
    "sg:classifiers":[
        {
            "category":"Wholesale",
            "subcategory":"Machinery & Supplies",
            "type":"Manufacturing & Wholesale Goods"
        }
    ],
    "sg:phone":"+1 423 510 9383",
    "sg:postcode":"37421",
    "sg:province":"TN",
    "sg:tags":[
        "industrial"
    ],
    "wof:name":"TCI Powder Co",
    "wof:placetype":"venue"
},
  "geometry": {"coordinates":[-85.101038,35.040201],"type":"Point"}
}