{
  "type": "Feature",
  "properties": {
    "addr:full":"2180 Raines Dr NW Cleveland TN 37311",
    "addr:housenumber":"2180",
    "addr:postcode":"37311",
    "addr:street":"Raines Dr Nw",
    "iso:country":"US",
    "sg:address":"2180 Raines Dr NW",
    "sg:city":"Cleveland",
    "sg:classifiers":[
        {
            "category":"Building & Trades",
            "subcategory":"Construction",
            "type":"Services"
        }
    ],
    "sg:phone":"+1 423 479 1439",
    "sg:postcode":"37311",
    "sg:province":"TN",
    "sg:tags":[
        "painter"
    ],
    "wof:name":"Don Stewart's Painting",
    "wof:placetype":"venue"
},
  "geometry": {"coordinates":[-84.91271500000001,35.177816],"type":"Point"}
}