{
  "type": "Feature",
  "properties": {
    "addr:full":"2121 Holston Bend Dr Mascot TN 37806",
    "addr:housenumber":"2121",
    "addr:postcode":"37806",
    "addr:street":"Holston Bend Dr",
    "iso:country":"US",
    "sg:address":"2121 Holston Bend Dr",
    "sg:city":"Mascot",
    "sg:classifiers":[
        {
            "category":"Professional",
            "type":"Services"
        }
    ],
    "sg:phone":"+1 865 932 3700",
    "sg:postcode":"37806",
    "sg:province":"TN",
    "sg:tags":[
        "establishment"
    ],
    "sg:website":"www.ddcc.com",
    "wof:name":"Daikin Drivetrain Components",
    "wof:placetype":"venue"
},
  "geometry": {"coordinates":[-83.727627,36.07619],"type":"Point"}
}