{
  "type": "Feature",
  "properties": {
    "iso:country":"US",
    "sg:address":"118 E Kingwood Dr",
    "sg:city":"Murfreesboro",
    "sg:classifiers":[
        {
            "category":"Communications",
            "subcategory":"Film & Video Production",
            "type":"Services"
        }
    ],
    "sg:phone":"+1 615 217 4792",
    "sg:postcode":"37130",
    "sg:province":"TN",
    "sg:tags":[
        "motion"
    ],
    "wof:name":"B Watts Productions Inc",
    "wof:placetype":"venue"
},
  "geometry": {"coordinates":[-86.388555,35.863046],"type":"Point"}
}