{
  "type": "Feature",
  "properties": {
    "iso:country":"US",
    "sg:address":"6081 Braxton Ln",
    "sg:city":"Memphis",
    "sg:classifiers":[
        {
            "category":"Communications",
            "type":"Services"
        }
    ],
    "sg:phone":"+1 901 565 7300",
    "sg:postcode":"38115",
    "sg:province":"TN",
    "wof:name":"L & G Communications",
    "wof:placetype":"venue"
},
  "geometry": {"coordinates":[-89.860378,35.058436],"type":"Point"}
}