{
  "type": "Feature",
  "properties": {
    "iso:country":"US",
    "sg:address":"400 Harding Industrial Dr",
    "sg:city":"Nashville",
    "sg:classifiers":[
        {
            "category":"Home & Garden",
            "subcategory":"Furniture",
            "type":"Retail Goods"
        }
    ],
    "sg:phone":"+1 615 331 7888",
    "sg:postcode":"37211",
    "sg:province":"TN",
    "sg:tags":[
        "house",
        "furnishing"
    ],
    "wof:name":"Bedroom Store",
    "wof:placetype":"venue"
},
  "geometry": {"coordinates":[-86.6991,36.097006],"type":"Point"}
}