{
  "type": "Feature",
  "properties": {
    "iso:country":"US",
    "sg:address":"6142 Hwy 14 S",
    "sg:city":"Brighton",
    "sg:classifiers":[
        {
            "category":"Retail",
            "subcategory":"Auto Repair",
            "type":"Services"
        }
    ],
    "sg:phone":"+1 901 476 2165",
    "sg:postcode":"38011",
    "sg:province":"TN",
    "sg:tags":[
        "general"
    ],
    "wof:name":"Billys Auto Shop",
    "wof:placetype":"venue"
},
  "geometry": {"coordinates":[-89.680857,35.4296],"type":"Point"}
}