{
  "type": "Feature",
  "properties": {
    "addr:full":"2091 Lee Pl Memphis TN 38104",
    "addr:housenumber":"2091",
    "addr:postcode":"38104",
    "addr:street":"Lee Pl",
    "iso:country":"US",
    "sg:address":"2091 Lee Pl",
    "sg:city":"Memphis",
    "sg:classifiers":[
        {
            "category":"Social Services",
            "type":"Services"
        }
    ],
    "sg:phone":"+1 901 725 1318",
    "sg:postcode":"38104",
    "sg:province":"TN",
    "wof:name":"Tell-A-Story",
    "wof:placetype":"venue"
},
  "geometry": {"coordinates":[-89.990224,35.139661],"type":"Point"}
}