{
  "type": "Feature",
  "properties": {
    "iso:country":"US",
    "sg:address":"24 V F W Rd",
    "sg:city":"Elora",
    "sg:classifiers":[
        {
            "category":"Bars & Pubs",
            "type":"Food & Drink"
        }
    ],
    "sg:phone":"+1 931 937 0064",
    "sg:postcode":"37328",
    "sg:province":"TN",
    "sg:tags":[
        "drinking"
    ],
    "wof:name":"Double Deuce",
    "wof:placetype":"venue"
},
  "geometry": {"coordinates":[-86.37165,35.071069],"type":"Point"}
}