{
  "type": "Feature",
  "properties": {
    "addr:full":"9147 Cross Park Dr Knoxville TN 37923",
    "addr:housenumber":"9147",
    "addr:postcode":"37923",
    "addr:street":"Cross Park Dr",
    "iso:country":"US",
    "sg:address":"9147 Cross Park Dr",
    "sg:city":"Knoxville",
    "sg:classifiers":[
        {
            "category":"Manufacturing",
            "subcategory":"Printing",
            "type":"Manufacturing & Wholesale Goods"
        }
    ],
    "sg:phone":"+1 865 691 6716",
    "sg:postcode":"37923",
    "sg:province":"TN",
    "sg:tags":[
        "lithographic",
        "b",
        "commercial",
        "typesetting"
    ],
    "sg:website":"www.printedge.com",
    "wof:name":"PRINTING Edge",
    "wof:placetype":"venue"
},
  "geometry": {"coordinates":[-84.08955400000001,35.921681],"type":"Point"}
}