{
  "type": "Feature",
  "properties": {
    "iso:country":"US",
    "sg:address":"51 N Cleveland St",
    "sg:city":"Memphis",
    "sg:classifiers":[
        {
            "category":"Restaurant",
            "type":"Food & Drink"
        }
    ],
    "sg:phone":"+1 901 276 5326",
    "sg:postcode":"38104",
    "sg:province":"TN",
    "sg:tags":[
        "eating"
    ],
    "wof:name":"Saigon Le",
    "wof:placetype":"venue"
},
  "geometry": {"coordinates":[-90.01618999999999,35.140251],"type":"Point"}
}