{
  "type": "Feature",
  "properties": {
    "iso:country":"US",
    "sg:address":"123 Gowan Rd",
    "sg:city":"Lexington",
    "sg:classifiers":[
        {
            "category":"Retail",
            "subcategory":"Auto Repair",
            "type":"Services"
        }
    ],
    "sg:phone":"+1 731 935 2561",
    "sg:postcode":"38351",
    "sg:province":"TN",
    "sg:tags":[
        "repairing",
        "automobile"
    ],
    "wof:name":"Gowan Automotive Svc",
    "wof:placetype":"venue"
},
  "geometry": {"coordinates":[-88.62043799999999,35.75067],"type":"Point"}
}