{
  "type": "Feature",
  "properties": {
    "addr:full":"125 Indian Lake Blvd Hendersonville TN 37075",
    "addr:housenumber":"125",
    "addr:postcode":"37075",
    "addr:street":"Indian Lake Blvd",
    "iso:country":"US",
    "sg:address":"125 Indian Lake Blvd",
    "sg:city":"Hendersonville",
    "sg:classifiers":[
        {
            "category":"Sports & Exercise",
            "subcategory":"Gym",
            "type":"Entertainment"
        }
    ],
    "sg:phone":"+1 615 264 9331",
    "sg:postcode":"37075",
    "sg:province":"TN",
    "sg:tags":[
        "fitness",
        "physical",
        "facility"
    ],
    "wof:name":"Curves For Women",
    "wof:placetype":"venue"
},
  "geometry": {"coordinates":[-86.600573,36.31906],"type":"Point"}
}