{
  "type": "Feature",
  "properties": {
    "iso:country":"US",
    "sg:address":"3007 Johnson Ave",
    "sg:city":"Memphis",
    "sg:classifiers":[
        {
            "category":"Food & Beverages",
            "subcategory":"Supermarket",
            "type":"Retail Goods"
        }
    ],
    "sg:phone":"+1 901 454 0497",
    "sg:postcode":"38112",
    "sg:province":"TN",
    "sg:tags":[
        "super",
        "store"
    ],
    "wof:name":"Sheger Market",
    "wof:placetype":"venue"
},
  "geometry": {"coordinates":[-89.96117700000001,35.141815],"type":"Point"}
}