{
  "type": "Feature",
  "properties": {
    "addr:full":"111 W Court Sq Covington TN 38019",
    "addr:housenumber":"111",
    "addr:postcode":"38019",
    "addr:street":"W Court Sq",
    "iso:country":"US",
    "sg:address":"111 W Court Sq",
    "sg:city":"Covington",
    "sg:classifiers":[
        {
            "category":"Personal",
            "subcategory":"Tanning Parlor",
            "type":"Services"
        }
    ],
    "sg:phone":"+1 901 465 8269",
    "sg:postcode":"38019",
    "sg:province":"TN",
    "sg:tags":[
        "salon"
    ],
    "wof:name":"Darker Image",
    "wof:placetype":"venue"
},
  "geometry": {"coordinates":[-89.64658300000001,35.564556],"type":"Point"}
}