{
  "type": "Feature",
  "properties": {
    "iso:country":"US",
    "sg:address":"236 Old Shackle Island Rd",
    "sg:city":"Hendersonville",
    "sg:classifiers":[
        {
            "category":"Professional",
            "subcategory":"Employment Agencies",
            "type":"Services"
        }
    ],
    "sg:phone":"+1 615 264 4747",
    "sg:postcode":"37075",
    "sg:province":"TN",
    "wof:name":"Lassister Barbara R Msn Rn Cs",
    "wof:placetype":"venue"
},
  "geometry": {"coordinates":[-86.61854700000001,36.317414],"type":"Point"}
}