{
  "type": "Feature",
  "properties": {
    "iso:country":"US",
    "sg:address":"265 Penix Ln",
    "sg:city":"Wildersville",
    "sg:classifiers":[
        {
            "category":"Professional",
            "subcategory":"Business Services",
            "type":"Services"
        }
    ],
    "sg:phone":"+1 731 968 0969",
    "sg:postcode":"38388",
    "sg:province":"TN",
    "wof:name":"Don Penix Enterprises Inc",
    "wof:placetype":"venue"
},
  "geometry": {"coordinates":[-88.394628,35.741715],"type":"Point"}
}