{
  "type": "Feature",
  "properties": {
    "iso:country":"US",
    "sg:address":"1100 Central Church Rd",
    "sg:city":"Morristown",
    "sg:classifiers":[
        {
            "category":"Organizations",
            "subcategory":"Religious Organization",
            "type":"Services"
        }
    ],
    "sg:phone":"+1 423 581 3379",
    "sg:postcode":"37814",
    "sg:province":"TN",
    "sg:tags":[
        "church"
    ],
    "wof:name":"Central Baptist Church",
    "wof:placetype":"venue"
},
  "geometry": {"coordinates":[-83.357055,36.215119],"type":"Point"}
}