{
  "type": "Feature",
  "properties": {
    "iso:country":"US",
    "sg:address":"2126 Abbott Martin Rd",
    "sg:city":"Nashville",
    "sg:classifiers":[
        {
            "category":"Personal",
            "type":"Services"
        }
    ],
    "sg:phone":"+1 615 269 9195",
    "sg:postcode":"37215",
    "sg:province":"TN",
    "sg:tags":[
        "engraver",
        "jewelry"
    ],
    "wof:name":"Silverado",
    "wof:placetype":"venue"
},
  "geometry": {"coordinates":[-86.81619499999999,36.106229],"type":"Point"}
}