{
  "type": "Feature",
  "properties": {
    "iso:country":"US",
    "sg:address":"7 Bradford Hill Rd",
    "sg:city":"Brush Creek",
    "sg:classifiers":[
        {
            "category":"Autos & Motor Vehicles",
            "subcategory":"Auto Supplies",
            "type":"Retail Goods"
        }
    ],
    "sg:phone":"+1 615 735 2135",
    "sg:postcode":"38547",
    "sg:province":"TN",
    "sg:tags":[
        "automobile",
        "parts"
    ],
    "wof:name":"Swann's Rebuilding Svc",
    "wof:placetype":"venue"
},
  "geometry": {"coordinates":[-85.95865499999999,36.229571],"type":"Point"}
}