{
  "type": "Feature",
  "properties": {
    "iso:country":"US",
    "sg:address":"3941 Nolensville Pike",
    "sg:city":"Nashville",
    "sg:classifiers":[
        {
            "category":"Restaurant",
            "type":"Food & Drink"
        }
    ],
    "sg:phone":"+1 615 834 1818",
    "sg:postcode":"37211",
    "sg:province":"TN",
    "sg:tags":[
        "eating"
    ],
    "wof:name":"Mazatian Mexican Restaurant",
    "wof:placetype":"venue"
},
  "geometry": {"coordinates":[-86.72860300000001,36.085257],"type":"Point"}
}