{
  "type": "Feature",
  "properties": {
    "addr:full":"519 Mount Pelia Rd Martin TN 38237",
    "addr:housenumber":"519",
    "addr:postcode":"38237",
    "addr:street":"Mount Pelia Rd",
    "iso:country":"US",
    "sg:address":"519 Mount Pelia Rd",
    "sg:city":"Martin",
    "sg:classifiers":[
        {
            "category":"Real Estate",
            "subcategory":"Real Estate Operator",
            "type":"Services"
        }
    ],
    "sg:phone":"+1 731 587 5545",
    "sg:postcode":"38237",
    "sg:province":"TN",
    "sg:tags":[
        "building",
        "apartment"
    ],
    "wof:name":"Westwood Townhouse Apartments",
    "wof:placetype":"venue"
},
  "geometry": {"coordinates":[-88.889152,36.324381],"type":"Point"}
}