{
  "type": "Feature",
  "properties": {
    "iso:country":"US",
    "sg:address":"1152 Park Ave",
    "sg:city":"Murfreesboro",
    "sg:classifiers":[
        {
            "category":"Retail",
            "subcategory":"Auto Rental",
            "type":"Services"
        }
    ],
    "sg:phone":"+1 615 896 1652",
    "sg:postcode":"37129",
    "sg:province":"TN",
    "sg:tags":[
        "mobile",
        "wholesale",
        "work",
        "integrator"
    ],
    "wof:name":"Enovateit LLC",
    "wof:placetype":"venue"
},
  "geometry": {"coordinates":[-86.39772000000001,35.831387],"type":"Point"}
}