{
  "type": "Feature",
  "properties": {
    "iso:country":"US",
    "sg:address":"191 Charter Pl",
    "sg:city":"La Vergne",
    "sg:classifiers":[
        {
            "category":"Wholesale",
            "subcategory":"Books, Periodicals, & Newspapers",
            "type":"Manufacturing & Wholesale Goods"
        },
        {
            "category":"Professional",
            "subcategory":"Advertising",
            "type":"Services"
        }
    ],
    "sg:phone":"+1 615 793 3800",
    "sg:postcode":"37086",
    "sg:province":"TN",
    "sg:tags":[
        "distribution"
    ],
    "wof:name":"Southwestern Co",
    "wof:placetype":"venue"
},
  "geometry": {"coordinates":[-86.59639300000001,35.991495],"type":"Point"}
}