{
  "type": "Feature",
  "properties": {
    "iso:country":"US",
    "sg:address":"54 Peachtree St",
    "sg:city":"Nashville",
    "sg:classifiers":[
        {
            "category":"Freight",
            "type":"Transportation"
        }
    ],
    "sg:phone":"+1 615 456 6775",
    "sg:postcode":"37210",
    "sg:province":"TN",
    "sg:tags":[
        "delivery"
    ],
    "wof:name":"Snappy Delivery",
    "wof:placetype":"venue"
},
  "geometry": {"coordinates":[-86.737317,36.119882],"type":"Point"}
}