{
  "type": "Feature",
  "properties": {
    "iso:country":"US",
    "sg:address":"72 W Biscayne Rd",
    "sg:city":"Memphis",
    "sg:classifiers":[
        {
            "category":"Insurance",
            "subcategory":"Insurance Agent",
            "type":"Services"
        }
    ],
    "sg:phone":"+1 901 396 2323",
    "sg:postcode":"38109",
    "sg:province":"TN",
    "wof:name":"Apex Insurance Agency Inc",
    "wof:placetype":"venue"
},
  "geometry": {"coordinates":[-90.065198,35.061873],"type":"Point"}
}