{
  "type": "Feature",
  "properties": {
    "addr:full":"3575 US Hwy 11 E Limestone TN 37690",
    "addr:housenumber":"3575",
    "addr:postcode":"37690",
    "addr:street":"Us Hwy 11 E Limestone",
    "iso:country":"US",
    "sg:address":"3575 US Hwy 11 E",
    "sg:city":"Limestone",
    "sg:classifiers":[
        {
            "category":"Professional",
            "type":"Services"
        }
    ],
    "sg:phone":"+1 423 257 2628",
    "sg:postcode":"37690",
    "sg:province":"TN",
    "sg:tags":[
        "establishment"
    ],
    "wof:name":"L & J Enterprise Inc",
    "wof:placetype":"venue"
},
  "geometry": {"coordinates":[-82.602255,36.249982],"type":"Point"}
}