{
  "type": "Feature",
  "properties": {
    "addr:full":"1331 Hillsboro St Union City TN 38261",
    "addr:housenumber":"1331",
    "addr:postcode":"38261",
    "addr:street":"Hillsboro St",
    "iso:country":"US",
    "sg:address":"1331 Hillsboro St",
    "sg:city":"Union City",
    "sg:classifiers":[
        {
            "category":"Shopping",
            "subcategory":"Computers & Home Electronics",
            "type":"Retail Goods"
        }
    ],
    "sg:phone":"+1 731 886 0398",
    "sg:postcode":"38261",
    "sg:province":"TN",
    "sg:tags":[
        "parts",
        "supply"
    ],
    "wof:name":"CENTRALBESTPC.COM",
    "wof:placetype":"venue"
},
  "geometry": {"coordinates":[-89.01061300000001,36.407385],"type":"Point"}
}