{
  "type": "Feature",
  "properties": {
    "iso:country":"US",
    "sg:address":"102 Scott Rd",
    "sg:city":"White House",
    "sg:classifiers":[
        {
            "category":"Wholesale",
            "subcategory":"Sporting Goods",
            "type":"Manufacturing & Wholesale Goods"
        }
    ],
    "sg:phone":"+1 615 285 0611",
    "sg:postcode":"37110",
    "sg:province":"TN",
    "sg:tags":[
        "equipment",
        "boat",
        "supply"
    ],
    "wof:name":"Inverter Generator Sales & Svc",
    "wof:placetype":"venue"
},
  "geometry": {"coordinates":[-85.708941,35.559935],"type":"Point"}
}