{
  "type": "Feature",
  "properties": {
    "iso:country":"US",
    "sg:address":"1012 Old Hwy 70",
    "sg:city":"Camden",
    "sg:classifiers":[
        {
            "category":"Freight",
            "type":"Transportation"
        }
    ],
    "sg:phone":"+1 731 584 5576",
    "sg:postcode":"38320",
    "sg:province":"TN",
    "wof:name":"Tdy Transport LLC",
    "wof:placetype":"venue"
},
  "geometry": {"coordinates":[-88.077016,36.039495],"type":"Point"}
}