{
  "type": "Feature",
  "properties": {
    "addr:full":"788 Nissan Dr Smyrna TN 37167",
    "addr:housenumber":"788",
    "addr:postcode":"37167",
    "addr:street":"Nissan Dr",
    "iso:country":"US",
    "sg:address":"788 Nissan Dr",
    "sg:city":"Smyrna",
    "sg:classifiers":[
        {
            "category":"Shopping",
            "subcategory":"Clothing, Apparel, & Fashions",
            "type":"Retail Goods"
        }
    ],
    "sg:phone":"+1 615 355 1664",
    "sg:postcode":"37167",
    "sg:province":"TN",
    "wof:name":"Chatterbox Coffee & Tea Cafe",
    "wof:placetype":"venue"
},
  "geometry": {"coordinates":[-86.49405,35.985569],"type":"Point"}
}