{
  "type": "Feature",
  "properties": {
    "iso:country":"US",
    "sg:address":"70 Sykes Rd",
    "sg:city":"Hickman",
    "sg:classifiers":[
        {
            "category":"Manufacturing",
            "subcategory":"Tools & Machinery",
            "type":"Manufacturing & Wholesale Goods"
        }
    ],
    "sg:phone":"+1 615 683 4766",
    "sg:postcode":"38567",
    "sg:province":"TN",
    "sg:tags":[
        "machine",
        "shop"
    ],
    "wof:name":"T & G Machine",
    "wof:placetype":"venue"
},
  "geometry": {"coordinates":[-85.942081,36.143489],"type":"Point"}
}