{
  "type": "Feature",
  "properties": {
    "addr:full":"911 State Hwy 165 Tellico Plains TN 37385",
    "addr:housenumber":"911",
    "addr:postcode":"37385",
    "addr:street":"State Hwy 165",
    "iso:country":"US",
    "sg:address":"911 State Hwy 165",
    "sg:city":"Tellico Plains",
    "sg:classifiers":[
        {
            "category":"Manufacturing",
            "subcategory":"Lumber",
            "type":"Manufacturing & Wholesale Goods"
        }
    ],
    "sg:phone":"+1 423 253 2323",
    "sg:postcode":"37385",
    "sg:province":"TN",
    "sg:tags":[
        "planing",
        "mills",
        "sawmill"
    ],
    "wof:name":"Everhart Gray Lumber",
    "wof:placetype":"venue"
},
  "geometry": {"coordinates":[-84.28581699999999,35.363049],"type":"Point"}
}