{
  "type": "Feature",
  "properties": {
    "iso:country":"US",
    "sg:address":"7029 Still Spring Hollow D",
    "sg:city":"Nashville",
    "sg:classifiers":[
        {
            "category":"Building & Trades",
            "subcategory":"Construction",
            "type":"Services"
        }
    ],
    "sg:phone":"+1 615 851 6799",
    "sg:postcode":"37221",
    "sg:province":"TN",
    "sg:tags":[
        "contractor"
    ],
    "wof:name":"T&T Roofing",
    "wof:placetype":"venue"
},
  "geometry": {"coordinates":[-86.92482699999999,36.079381],"type":"Point"}
}