{
  "type": "Feature",
  "properties": {
    "iso:country":"US",
    "sg:address":"4714 Yale Rd",
    "sg:city":"Memphis",
    "sg:classifiers":[
        {
            "category":"Professional",
            "subcategory":"Accounting & Tax Preparation",
            "type":"Services"
        }
    ],
    "sg:phone":"+1 901 380 3973",
    "sg:postcode":"38128",
    "sg:province":"TN",
    "sg:tags":[
        "return",
        "filing"
    ],
    "wof:name":"CMG Tax Express",
    "wof:placetype":"venue"
},
  "geometry": {"coordinates":[-89.90306099999999,35.221654],"type":"Point"}
}