{
  "type": "Feature",
  "properties": {
    "iso:country":"US",
    "sg:address":"641 Thorngrove Pike",
    "sg:city":"Strawberry Plns",
    "sg:classifiers":[
        {
            "category":"Professional",
            "type":"Services"
        }
    ],
    "sg:phone":"+1 865 932 6031",
    "sg:postcode":"37871",
    "sg:province":"TN",
    "sg:tags":[
        "establishment"
    ],
    "wof:name":"Morgan Indoor & Outdoor Stge",
    "wof:placetype":"venue"
},
  "geometry": {"coordinates":[-83.642702,36.009453],"type":"Point"}
}