{
  "type": "Feature",
  "properties": {
    "iso:country":"US",
    "sg:address":"126 Dupree Rd",
    "sg:city":"Brownsville",
    "sg:classifiers":[
        {
            "category":"Organizations",
            "subcategory":"Religious Organization",
            "type":"Services"
        }
    ],
    "sg:phone":"+1 731 772 4826",
    "sg:postcode":"38012",
    "sg:province":"TN",
    "wof:name":"Haywood Baptist Association",
    "wof:placetype":"venue"
},
  "geometry": {"coordinates":[-89.361795,35.670894],"type":"Point"}
}