{
  "type": "Feature",
  "properties": {
    "addr:full":"205 Robert Ave White House TN 37188",
    "addr:housenumber":"205",
    "addr:postcode":"37188",
    "addr:street":"Robert Ave",
    "iso:country":"US",
    "sg:address":"205 Robert Ave",
    "sg:city":"White House",
    "sg:classifiers":[
        {
            "category":"Sports & Exercise",
            "subcategory":"Gym",
            "type":"Entertainment"
        }
    ],
    "sg:phone":"+1 615 672 7776",
    "sg:postcode":"37188",
    "sg:province":"TN",
    "sg:tags":[
        "fitness",
        "physical",
        "facility"
    ],
    "wof:name":"Fitness Lifestyles LLC",
    "wof:placetype":"venue"
},
  "geometry": {"coordinates":[-86.642053,36.470007],"type":"Point"}
}