{
  "type": "Feature",
  "properties": {
    "iso:country":"US",
    "sg:address":"2544 Jacksboro Pike",
    "sg:city":"Jacksboro",
    "sg:classifiers":[
        {
            "category":"Restaurant",
            "type":"Food & Drink"
        }
    ],
    "sg:menulink":"http://www.allmenus.com/tn/la-follette/95941-charleys-grilled-subs/menu/",
    "sg:phone":"+1 423 907 9924",
    "sg:postcode":"37757",
    "sg:province":"TN",
    "sg:tags":[
        "wrap",
        "american",
        "sandwich"
    ],
    "wof:name":"Charley's Grilled Subs",
    "wof:placetype":"venue"
},
  "geometry": {"coordinates":[-84.168066,36.341461],"type":"Point"}
}