{
  "type": "Feature",
  "properties": {
    "iso:country":"US",
    "sg:address":"212 Fite Ave W",
    "sg:city":"Carthage",
    "sg:classifiers":[
        {
            "category":"Banks & Credit Unions",
            "subcategory":"Investment Brokerage",
            "type":"Services"
        }
    ],
    "sg:phone":"+1 615 735 9807",
    "sg:postcode":"37030",
    "sg:province":"TN",
    "sg:tags":[
        "advisory",
        "insurance"
    ],
    "wof:name":"Campbell Group",
    "wof:placetype":"venue"
},
  "geometry": {"coordinates":[-85.952984,36.254142],"type":"Point"}
}