{
  "type": "Feature",
  "properties": {
    "iso:country":"US",
    "sg:address":"1552 Cherry Park Dr",
    "sg:city":"Memphis",
    "sg:classifiers":[
        {
            "category":"Professional",
            "subcategory":"Management & Consulting",
            "type":"Services"
        }
    ],
    "sg:phone":"+1 901 757 2479",
    "sg:postcode":"38120",
    "sg:province":"TN",
    "sg:tags":[
        "business"
    ],
    "wof:name":"Rol Designs",
    "wof:placetype":"venue"
},
  "geometry": {"coordinates":[-89.84488899999999,35.106564],"type":"Point"}
}