{
  "type": "Feature",
  "properties": {
    "addr:full":"4630 Shallowford Rd Chattanooga TN 37411",
    "addr:housenumber":"4630",
    "addr:postcode":"37411",
    "addr:street":"Shallowford Rd",
    "iso:country":"US",
    "sg:address":"4630 Shallowford Rd",
    "sg:city":"Chattanooga",
    "sg:classifiers":[
        {
            "category":"Banks & Credit Unions",
            "subcategory":"Investment Brokerage",
            "type":"Services"
        }
    ],
    "sg:phone":"+1 423 894 9662",
    "sg:postcode":"37411",
    "sg:province":"TN",
    "sg:tags":[
        "advisory"
    ],
    "wof:name":"Boyd Investments",
    "wof:placetype":"venue"
},
  "geometry": {"coordinates":[-85.21333799999999,35.050413],"type":"Point"}
}