{
  "type": "Feature",
  "properties": {
    "iso:country":"US",
    "sg:address":"364 Lindsay St",
    "sg:city":"Alcoa",
    "sg:classifiers":[
        {
            "category":"Shopping",
            "subcategory":"Computers & Home Electronics",
            "type":"Retail Goods"
        }
    ],
    "sg:phone":"+1 865 983 4850",
    "sg:postcode":"37701",
    "sg:province":"TN",
    "sg:tags":[
        "equipment",
        "radio"
    ],
    "wof:name":"Southern T V Sales & Service",
    "wof:placetype":"venue"
},
  "geometry": {"coordinates":[-83.976412,35.76209],"type":"Point"}
}