{
  "type": "Feature",
  "properties": {
    "addr:full":"1810 Old Fort Pkwy Murfreesboro TN 37129",
    "addr:housenumber":"1810",
    "addr:postcode":"37129",
    "addr:street":"Old Fort Pkwy",
    "iso:country":"US",
    "sg:address":"1810 Old Fort Pkwy",
    "sg:city":"Murfreesboro",
    "sg:classifiers":[
        {
            "category":"Insurance",
            "subcategory":"Insurance Agent",
            "type":"Services"
        }
    ],
    "sg:phone":"+1 615 217 1020",
    "sg:postcode":"37129",
    "sg:province":"TN",
    "wof:name":"Allstate Insurance Co",
    "wof:placetype":"venue"
},
  "geometry": {"coordinates":[-86.428574,35.846015],"type":"Point"}
}