{
  "type": "Feature",
  "properties": {
    "iso:country":"US",
    "sg:address":"2851 Logan St",
    "sg:city":"Nashville",
    "sg:classifiers":[
        {
            "category":"Health Services",
            "subcategory":"Doctor",
            "type":"Services"
        }
    ],
    "sg:phone":"+1 615 781 2333",
    "sg:postcode":"37211",
    "sg:province":"TN",
    "sg:tags":[
        "dr"
    ],
    "wof:name":"Y K Ahn MD",
    "wof:placetype":"venue"
},
  "geometry": {"coordinates":[-86.74166099999999,36.112104],"type":"Point"}
}