{
  "type": "Feature",
  "properties": {
    "addr:full":"227 French Landing Dr Nashville TN 37228",
    "addr:housenumber":"227",
    "addr:postcode":"37228",
    "addr:street":"French Landing Dr",
    "iso:country":"US",
    "sg:address":"227 French Landing Dr",
    "sg:city":"Nashville",
    "sg:classifiers":[
        {
            "category":"Restaurant",
            "type":"Food & Drink"
        }
    ],
    "sg:phone":"+1 615 255 5560",
    "sg:postcode":"37228",
    "sg:province":"TN",
    "wof:name":"P J's Deli & Catering",
    "wof:placetype":"venue"
},
  "geometry": {"coordinates":[-86.796824,36.194816],"type":"Point"}
}