{
  "type": "Feature",
  "properties": {
    "iso:country":"US",
    "sg:address":"111 Bybee Dr",
    "sg:city":"Mc Minnville",
    "sg:classifiers":[
        {
            "category":"Building & Trades",
            "subcategory":"Construction",
            "type":"Services"
        }
    ],
    "sg:phone":"+1 931 474 6857",
    "sg:postcode":"37110",
    "sg:province":"TN",
    "sg:tags":[
        "light",
        "c",
        "commercial",
        "housing",
        "family"
    ],
    "wof:name":"Canterbury Icf Construction",
    "wof:placetype":"venue"
},
  "geometry": {"coordinates":[-85.79534099999999,35.704301],"type":"Point"}
}