{
  "type": "Feature",
  "properties": {
    "iso:country":"US",
    "sg:address":"880 Mohawk Dr",
    "sg:city":"Cleveland",
    "sg:classifiers":[
        {
            "category":"Education",
            "subcategory":"Special Training",
            "type":"Public Place"
        }
    ],
    "sg:phone":"+1 423 476 1942",
    "sg:postcode":"37312",
    "sg:province":"TN",
    "wof:name":"Art &3 RS Center",
    "wof:placetype":"venue"
},
  "geometry": {"coordinates":[-84.85368800000001,35.212831],"type":"Point"}
}