{
  "type": "Feature",
  "properties": {
    "addr:full":"363 E Main St Newport TN 37821",
    "addr:housenumber":"363",
    "addr:postcode":"37821",
    "addr:street":"E Main St",
    "iso:country":"US",
    "sg:address":"363 E Main St",
    "sg:city":"Newport",
    "sg:classifiers":[
        {
            "category":"Retail",
            "subcategory":"Funeral Services",
            "type":"Services"
        }
    ],
    "sg:phone":"+1 423 623 6952",
    "sg:postcode":"37821",
    "sg:province":"TN",
    "sg:tags":[
        "director"
    ],
    "wof:name":"Manes Funeral Home",
    "wof:placetype":"venue"
},
  "geometry": {"coordinates":[-83.183521,35.967372],"type":"Point"}
}