{
  "type": "Feature",
  "properties": {
    "addr:full":"4075 Canehill Cove Memphis TN 38135",
    "addr:housenumber":"4075",
    "addr:postcode":"38135",
    "addr:street":"Canehill Cove",
    "iso:country":"US",
    "sg:address":"4075 Canehill Cove",
    "sg:city":"Memphis",
    "sg:classifiers":[
        {
            "category":"Building & Trades",
            "subcategory":"Cleaning & Sanitation",
            "type":"Services"
        }
    ],
    "sg:phone":"+1 901 383 7212",
    "sg:postcode":"38135",
    "sg:province":"TN",
    "sg:tags":[
        "maintenance"
    ],
    "wof:name":"Bright Lights Cleaning Service",
    "wof:placetype":"venue"
},
  "geometry": {"coordinates":[-89.828896,35.236257],"type":"Point"}
}