{
  "type": "Feature",
  "properties": {
    "iso:country":"US",
    "sg:address":"2541 E Broadway Ave",
    "sg:city":"Maryville",
    "sg:classifiers":[
        {
            "category":"Shopping",
            "subcategory":"Pharmacy",
            "type":"Retail Goods"
        }
    ],
    "sg:phone":"+1 865 983 9590",
    "sg:postcode":"37804",
    "sg:province":"TN",
    "wof:name":"Medicine Shoppe The",
    "wof:placetype":"venue"
},
  "geometry": {"coordinates":[-83.946622,35.790776],"type":"Point"}
}