{
  "type": "Feature",
  "properties": {
    "iso:country":"US",
    "sg:address":"720 Cornersville Rd",
    "sg:city":"Lewisburg",
    "sg:classifiers":[
        {
            "category":"Insurance",
            "subcategory":"Insurance Agent",
            "type":"Services"
        }
    ],
    "sg:phone":"+1 931 359 8070",
    "sg:postcode":"37091",
    "sg:province":"TN",
    "wof:name":"Clift Insurance Agency Inc",
    "wof:placetype":"venue"
},
  "geometry": {"coordinates":[-86.79383,35.437949],"type":"Point"}
}