{
  "type": "Feature",
  "properties": {
    "iso:country":"US",
    "sg:address":"560 E Commerce St",
    "sg:city":"Lewisburg",
    "sg:classifiers":[
        {
            "category":"Organizations",
            "subcategory":"Religious Organization",
            "type":"Services"
        }
    ],
    "sg:phone":"+1 931 359 1027",
    "sg:postcode":"37091",
    "sg:province":"TN",
    "sg:tags":[
        "church"
    ],
    "wof:name":"East Commerce Baptist Church",
    "wof:placetype":"venue"
},
  "geometry": {"coordinates":[-86.78053800000001,35.447161],"type":"Point"}
}