{
  "type": "Feature",
  "properties": {
    "addr:full":"1351 S Germantown Rd Germantown TN 38138",
    "addr:housenumber":"1351",
    "addr:postcode":"38138",
    "addr:street":"S Germantown Rd",
    "iso:country":"US",
    "sg:address":"1351 S Germantown Rd",
    "sg:city":"Germantown",
    "sg:classifiers":[
        {
            "category":"Food & Beverages",
            "subcategory":"Groceries & Convenience Stores",
            "type":"Retail Goods"
        }
    ],
    "sg:phone":"+1 901 757 0034",
    "sg:postcode":"38138",
    "sg:province":"TN",
    "sg:tags":[
        "grocer"
    ],
    "wof:name":"Circle K",
    "wof:placetype":"venue"
},
  "geometry": {"coordinates":[-89.802104,35.112975],"type":"Point"}
}