{
  "type": "Feature",
  "properties": {
    "iso:country":"US",
    "sg:address":"4664 Quince Rd",
    "sg:city":"Memphis",
    "sg:classifiers":[
        {
            "category":"Real Estate",
            "subcategory":"Real Estate Agent",
            "type":"Services"
        }
    ],
    "sg:phone":"+1 901 818 0007",
    "sg:postcode":"38117",
    "sg:province":"TN",
    "sg:tags":[
        "appraiser"
    ],
    "sg:website":"www.remacllc.com",
    "wof:name":"Remac",
    "wof:placetype":"venue"
},
  "geometry": {"coordinates":[-89.90613500000001,35.091473],"type":"Point"}
}