{
  "type": "Feature",
  "properties": {
    "addr:full":"651 Parkway Gatlinburg TN 37738",
    "addr:housenumber":"651",
    "addr:postcode":"37738",
    "addr:street":"Parkway",
    "iso:country":"US",
    "sg:address":"651 Parkway",
    "sg:city":"Gatlinburg",
    "sg:classifiers":[
        {
            "category":"Shopping",
            "subcategory":"Gifts & Souvenirs",
            "type":"Retail Goods"
        }
    ],
    "sg:phone":"+1 865 436 0061",
    "sg:postcode":"37738",
    "sg:province":"TN",
    "sg:tags":[
        "shop"
    ],
    "wof:name":"No Place Like Home",
    "wof:placetype":"venue"
},
  "geometry": {"coordinates":[-83.514331,35.712729],"type":"Point"}
}