{
  "type": "Feature",
  "properties": {
    "iso:country":"US",
    "sg:address":"125 Leconte Creek Rd",
    "sg:city":"Gatlinburg",
    "sg:classifiers":[
        {
            "category":"Building & Trades",
            "subcategory":"Construction",
            "type":"Services"
        }
    ],
    "sg:phone":"+1 423 581 3228",
    "sg:postcode":"37738",
    "sg:province":"TN",
    "sg:tags":[
        "general",
        "contractor"
    ],
    "wof:name":"Sorey Construction",
    "wof:placetype":"venue"
},
  "geometry": {"coordinates":[-83.520448,35.70797],"type":"Point"}
}