{
  "type": "Feature",
  "properties": {
    "iso:country":"US",
    "sg:address":"1423 Ordway Pl",
    "sg:city":"Nashville",
    "sg:classifiers":[
        {
            "category":"Real Estate",
            "subcategory":"Architect",
            "type":"Services"
        }
    ],
    "sg:phone":"+1 615 397 8335",
    "sg:postcode":"37206",
    "sg:province":"TN",
    "wof:name":"Astikon Architecture/Constr",
    "wof:placetype":"venue"
},
  "geometry": {"coordinates":[-86.74354099999999,36.180071],"type":"Point"}
}