{
  "type": "Feature",
  "properties": {
    "iso:country":"US",
    "sg:address":"7022 Shallowford Rd",
    "sg:city":"Chattanooga",
    "sg:classifiers":[
        {
            "category":"Food & Beverages",
            "subcategory":"Groceries & Convenience Stores",
            "type":"Retail Goods"
        }
    ],
    "sg:phone":"+1 423 899 1442",
    "sg:postcode":"37421",
    "sg:province":"TN",
    "wof:name":"Favorite Markets 321",
    "wof:placetype":"venue"
},
  "geometry": {"coordinates":[-85.156971,35.042828],"type":"Point"}
}