{
  "type": "Feature",
  "properties": {
    "iso:country":"US",
    "sg:address":"6535 Premier Dr",
    "sg:city":"Nashville",
    "sg:classifiers":[
        {
            "category":"Professional",
            "subcategory":"Business Services",
            "type":"Services"
        }
    ],
    "sg:phone":"+1 615 356 2323",
    "sg:postcode":"37209",
    "sg:province":"TN",
    "wof:name":"Ledic Management Company",
    "wof:placetype":"venue"
},
  "geometry": {"coordinates":[-86.879606,36.144558],"type":"Point"}
}