{
  "type": "Feature",
  "properties": {
    "iso:country":"US",
    "sg:address":"2457 Beacon Light Rd",
    "sg:city":"Morrison",
    "sg:classifiers":[
        {
            "category":"Professional",
            "subcategory":"Management & Consulting",
            "type":"Services"
        },
        {
            "category":"Professional",
            "subcategory":"Research",
            "type":"Services"
        }
    ],
    "sg:phone":"+1 931 635 3675",
    "sg:postcode":"37357",
    "sg:province":"TN",
    "sg:tags":[
        "consultant",
        "ecological",
        "environmental"
    ],
    "wof:name":"Nature Conservancy",
    "wof:placetype":"venue"
},
  "geometry": {"coordinates":[-85.87752999999999,35.596809],"type":"Point"}
}