{
  "type": "Feature",
  "properties": {
    "iso:country":"US",
    "sg:address":"625 Harris Chapel Rd",
    "sg:city":"Estill Springs",
    "sg:classifiers":[
        {
            "category":"Organizations",
            "subcategory":"Religious Organization",
            "type":"Services"
        }
    ],
    "sg:phone":"+1 931 967 9309",
    "sg:postcode":"37330",
    "sg:province":"TN",
    "wof:name":"United Methodist Church",
    "wof:placetype":"venue"
},
  "geometry": {"coordinates":[-86.16250599999999,35.22716],"type":"Point"}
}