{
  "type": "Feature",
  "properties": {
    "iso:country":"US",
    "sg:address":"2120 Parris Dr",
    "sg:city":"Lenoir City",
    "sg:classifiers":[
        {
            "category":"Recreation",
            "type":"Entertainment"
        }
    ],
    "sg:phone":"+1 865 988 9638",
    "sg:postcode":"37772",
    "sg:province":"TN",
    "wof:name":"Rob Cameron Tennis Academ",
    "wof:placetype":"venue"
},
  "geometry": {"coordinates":[-84.212231,35.7845],"type":"Point"}
}