{
  "type": "Feature",
  "properties": {
    "iso:country":"US",
    "sg:address":"1008 N Tennessee Blvd",
    "sg:city":"Murfreesboro",
    "sg:classifiers":[
        {
            "category":"Food & Beverages",
            "subcategory":"Liquor & Beverages",
            "type":"Retail Goods"
        }
    ],
    "sg:phone":"+1 615 895 4434",
    "sg:postcode":"37130",
    "sg:province":"TN",
    "wof:name":"University Liquor Inc",
    "wof:placetype":"venue"
},
  "geometry": {"coordinates":[-86.37018999999999,35.855763],"type":"Point"}
}