{
  "type": "Feature",
  "properties": {
    "iso:country":"US",
    "sg:address":"100 N Humphreys Blvd",
    "sg:city":"Memphis",
    "sg:classifiers":[
        {
            "category":"Health Services",
            "subcategory":"Doctor",
            "type":"Services"
        }
    ],
    "sg:phone":"+1 901 683 0055",
    "sg:postcode":"38120",
    "sg:province":"TN",
    "sg:tags":[
        "physician",
        "reproductive",
        "endocrinology",
        "surgeons",
        "surgeon",
        "metabolism",
        "diabetes"
    ],
    "wof:name":"Imseis Raed MD",
    "wof:placetype":"venue"
},
  "geometry": {"coordinates":[-89.858598,35.132839],"type":"Point"}
}