{
  "type": "Feature",
  "properties": {
    "iso:country":"US",
    "sg:address":"185 Oneal Ln",
    "sg:city":"Oneida",
    "sg:classifiers":[
        {
            "category":"Freight",
            "type":"Transportation"
        }
    ],
    "sg:phone":"+1 423 569 2144",
    "sg:postcode":"37841",
    "sg:province":"TN",
    "sg:tags":[
        "special"
    ],
    "wof:name":"Big South Fork Storage",
    "wof:placetype":"venue"
},
  "geometry": {"coordinates":[-84.639454,36.552525],"type":"Point"}
}