{
  "type": "Feature",
  "properties": {
    "addr:full":"6201 Baum Dr Knoxville TN 37919",
    "addr:housenumber":"6201",
    "addr:postcode":"37919",
    "addr:street":"Baum Dr",
    "iso:country":"US",
    "sg:address":"6201 Baum Dr",
    "sg:city":"Knoxville",
    "sg:classifiers":[
        {
            "category":"Wholesale",
            "subcategory":"Painting Supplies",
            "type":"Manufacturing & Wholesale Goods"
        },
        {
            "category":"Manufacturing",
            "subcategory":"Tools & Machinery",
            "type":"Manufacturing & Wholesale Goods"
        },
        {
            "category":"Building & Trades",
            "subcategory":"Construction",
            "type":"Services"
        },
        {
            "category":"Professional",
            "subcategory":"Art Services",
            "type":"Services"
        },
        {
            "category":"Home & Garden",
            "subcategory":"Building Materials",
            "type":"Retail Goods"
        },
        {
            "category":"Manufacturing",
            "subcategory":"Chemicals & Compounds",
            "type":"Manufacturing & Wholesale Goods"
        },
        {
            "category":"Autos & Motor Vehicles",
            "subcategory":"Auto Supplies",
            "type":"Retail Goods"
        },
        {
            "category":"Building & Trades",
            "subcategory":"Equipment Rental",
            "type":"Services"
        },
        {
            "category":"Manufacturing",
            "subcategory":"Building Materials",
            "type":"Manufacturing & Wholesale Goods"
        }
    ],
    "sg:phone":"+1 865 584 8624",
    "sg:postcode":"37919",
    "sg:province":"TN",
    "sg:tags":[
        "shop",
        "body",
        "designer",
        "paint",
        "wall",
        "automobile",
        "wallpaper",
        "coating",
        "contractor",
        "paint-wholesale",
        "spraying",
        "plastering",
        "decorator",
        "wallcoverings-installation",
        "wallcoverings",
        "interior",
        "equipment-renting",
        "painter",
        "manufacturer"
    ],
    "sg:website":"http://knoxville.citysearch.com/profile/external/9420163/knoxville_tn/sherwin_williams.html?publisher=yellowpages&reference_id=1&placement=ypwebsitemip",
    "wof:name":"Sherwin-Williams",
    "wof:placetype":"venue"
},
  "geometry": {"coordinates":[-84.001999,35.930141],"type":"Point"}
}