{
  "type": "Feature",
  "properties": {
    "iso:country":"US",
    "sg:address":"3411 Knight Rd",
    "sg:city":"Memphis",
    "sg:classifiers":[
        {
            "category":"Autos & Motor Vehicles",
            "subcategory":"Automobile Sales",
            "type":"Retail Goods"
        }
    ],
    "sg:phone":"+1 901 276 7611",
    "sg:postcode":"38118",
    "sg:province":"TN",
    "sg:tags":[
        "used"
    ],
    "wof:name":"Nirro Inc",
    "wof:placetype":"venue"
},
  "geometry": {"coordinates":[-89.91072699999999,35.054858],"type":"Point"}
}