{
  "type": "Feature",
  "properties": {
    "iso:country":"US",
    "sg:address":"1731 Carriage Ct",
    "sg:city":"Brentwood",
    "sg:classifiers":[
        {
            "category":"Professional",
            "subcategory":"Business Services",
            "type":"Services"
        }
    ],
    "sg:phone":"+1 615 370 3120",
    "sg:postcode":"37027",
    "sg:province":"TN",
    "sg:tags":[
        "production",
        "music"
    ],
    "wof:name":"Richard Dodd Productions",
    "wof:placetype":"venue"
},
  "geometry": {"coordinates":[-86.77229,35.956659],"type":"Point"}
}