{
  "type": "Feature",
  "properties": {
    "iso:country":"US",
    "sg:address":"566 Mainstream Dr",
    "sg:city":"Nashville",
    "sg:classifiers":[
        {
            "category":"Manufacturing",
            "subcategory":"Tools & Machinery",
            "type":"Manufacturing & Wholesale Goods"
        }
    ],
    "sg:phone":"+1 615 734 6400",
    "sg:postcode":"37228",
    "sg:province":"TN",
    "sg:tags":[
        "equipment",
        "recycling",
        "develop",
        "mfg"
    ],
    "wof:name":"N R T",
    "wof:placetype":"venue"
},
  "geometry": {"coordinates":[-86.81249200000001,36.199456],"type":"Point"}
}