{
  "type": "Feature",
  "properties": {
    "iso:country":"US",
    "sg:address":"704 Poplar Grove Cem Rd",
    "sg:city":"Henning",
    "sg:classifiers":[
        {
            "category":"Professional",
            "subcategory":"Engineering",
            "type":"Services"
        }
    ],
    "sg:phone":"+1 731 738 2637",
    "sg:postcode":"38041",
    "sg:province":"TN",
    "sg:tags":[
        "civil",
        "construction"
    ],
    "wof:name":"Ballard Enterprises",
    "wof:placetype":"venue"
},
  "geometry": {"coordinates":[-89.57916,35.689456],"type":"Point"}
}