{
  "type": "Feature",
  "properties": {
    "iso:country":"US",
    "sg:address":"110 4th Ave S",
    "sg:city":"Franklin",
    "sg:classifiers":[
        {
            "category":"Food & Beverages",
            "subcategory":"Bakery",
            "type":"Retail Goods"
        }
    ],
    "sg:phone":"+1 615 790 3755",
    "sg:postcode":"37064",
    "sg:province":"TN",
    "sg:tags":[
        "baker"
    ],
    "wof:name":"Merridee's Breadbasket",
    "wof:placetype":"venue"
},
  "geometry": {"coordinates":[-86.870132,35.924202],"type":"Point"}
}