{
  "type": "Feature",
  "properties": {
    "iso:country":"US",
    "sg:address":"1625 Dry Hollow Rd",
    "sg:city":"Mc Ewen",
    "sg:classifiers":[
        {
            "category":"Insurance",
            "subcategory":"Insurance Agent",
            "type":"Services"
        }
    ],
    "sg:phone":"+1 931 582 3177",
    "sg:postcode":"37101",
    "sg:province":"TN",
    "wof:name":"Auto-Owners Insurance Company",
    "wof:placetype":"venue"
},
  "geometry": {"coordinates":[-87.739152,36.159293],"type":"Point"}
}