{
  "type": "Feature",
  "properties": {
    "iso:country":"US",
    "sg:address":"1313 Decatur Pike",
    "sg:city":"Athens",
    "sg:classifiers":[
        {
            "category":"Personal",
            "subcategory":"Beauty Salon",
            "type":"Services"
        }
    ],
    "sg:phone":"+1 423 744 7338",
    "sg:postcode":"37303",
    "sg:province":"TN",
    "sg:tags":[
        "shop"
    ],
    "wof:name":"Reflections",
    "wof:placetype":"venue"
},
  "geometry": {"coordinates":[-84.61510800000001,35.448691],"type":"Point"}
}