{
  "type": "Feature",
  "properties": {
    "addr:full":"230 E Court Ave Selmer TN 38375",
    "addr:housenumber":"230",
    "addr:postcode":"38375",
    "addr:street":"E Court Ave",
    "iso:country":"US",
    "sg:address":"230 E Court Ave",
    "sg:city":"Selmer",
    "sg:classifiers":[
        {
            "category":"Shopping",
            "subcategory":"Discount & Variety Stores",
            "type":"Retail Goods"
        }
    ],
    "sg:phone":"+1 731 645 4165",
    "sg:postcode":"38375",
    "sg:province":"TN",
    "wof:name":"Dollar General",
    "wof:placetype":"venue"
},
  "geometry": {"coordinates":[-88.591173,35.169281],"type":"Point"}
}