{
  "type": "Feature",
  "properties": {
    "iso:country":"US",
    "sg:address":"306 W Depot St",
    "sg:city":"Greeneville",
    "sg:classifiers":[
        {
            "category":"Personal",
            "subcategory":"Tattoo Parlor",
            "type":"Services"
        }
    ],
    "sg:phone":"+1 423 787 0050",
    "sg:postcode":"37743",
    "sg:province":"TN",
    "sg:tags":[
        "tattooing"
    ],
    "wof:name":"Craven Ink",
    "wof:placetype":"venue"
},
  "geometry": {"coordinates":[-82.835846,36.165149],"type":"Point"}
}