{
  "type": "Feature",
  "properties": {
    "iso:country":"US",
    "sg:address":"215 Becky Ln",
    "sg:city":"Bean Station",
    "sg:classifiers":[
        {
            "category":"Home & Garden",
            "subcategory":"Furniture",
            "type":"Retail Goods"
        }
    ],
    "sg:phone":"+1 865 993 4202",
    "sg:postcode":"37724",
    "sg:province":"TN",
    "wof:name":"Furniture Jobbers Outlet",
    "wof:placetype":"venue"
},
  "geometry": {"coordinates":[-83.714659,36.525551],"type":"Point"}
}