{
  "type": "Feature",
  "properties": {
    "iso:country":"US",
    "sg:address":"3412 Hwy 79",
    "sg:city":"Indian Mound",
    "sg:classifiers":[
        {
            "category":"Professional",
            "subcategory":"Accounting & Tax Preparation",
            "type":"Services"
        }
    ],
    "sg:phone":"+1 931 232 4787",
    "sg:postcode":"37079",
    "sg:province":"TN",
    "sg:tags":[
        "return",
        "filing"
    ],
    "wof:name":"Donna Patrick Svc",
    "wof:placetype":"venue"
},
  "geometry": {"coordinates":[-87.644775,36.544624],"type":"Point"}
}