{
  "type": "Feature",
  "properties": {
    "addr:full":"125 Allen St Smithville TN 37110",
    "addr:housenumber":"125",
    "addr:postcode":"37110",
    "addr:street":"Allen St",
    "iso:country":"US",
    "sg:address":"125 Allen St",
    "sg:city":"Smithville",
    "sg:classifiers":[
        {
            "category":"Professional",
            "type":"Services"
        }
    ],
    "sg:phone":"+1 615 597 4161",
    "sg:postcode":"37110",
    "sg:province":"TN",
    "wof:name":"Willa B Pack",
    "wof:placetype":"venue"
},
  "geometry": {"coordinates":[-85.788358,35.696694],"type":"Point"}
}