{
  "type": "Feature",
  "properties": {
    "iso:country":"US",
    "sg:address":"408 Stonemeadow Rd",
    "sg:city":"Clarksville",
    "sg:classifiers":[
        {
            "category":"Professional",
            "subcategory":"Detective & Security Services",
            "type":"Services"
        }
    ],
    "sg:phone":"+1 770 623 3086",
    "sg:postcode":"37043",
    "sg:province":"TN",
    "sg:tags":[
        "system"
    ],
    "wof:name":"Bes Security Systems Inc",
    "wof:placetype":"venue"
},
  "geometry": {"coordinates":[-87.276732,36.527312],"type":"Point"}
}