{
  "type": "Feature",
  "properties": {
    "iso:country":"US",
    "sg:address":"508 N 3rd St",
    "sg:city":"Memphis",
    "sg:classifiers":[
        {
            "category":"Organizations",
            "subcategory":"Religious Organization",
            "type":"Services"
        }
    ],
    "sg:phone":"+1 901 525 0722",
    "sg:postcode":"38105",
    "sg:province":"TN",
    "sg:tags":[
        "baptist",
        "church"
    ],
    "wof:name":"Saint Stephen Baptist Church",
    "wof:placetype":"venue"
},
  "geometry": {"coordinates":[-90.04502599999999,35.157505],"type":"Point"}
}