{
  "type": "Feature",
  "properties": {
    "addr:full":"1025 Cedar Springs Rd Athens TN 37303",
    "addr:housenumber":"1025",
    "addr:postcode":"37303",
    "addr:street":"Cedar Springs Rd",
    "iso:country":"US",
    "sg:address":"1025 Cedar Springs Rd",
    "sg:city":"Athens",
    "sg:classifiers":[
        {
            "category":"Building & Trades",
            "subcategory":"Cleaning & Sanitation",
            "type":"Services"
        }
    ],
    "sg:phone":"+1 423 744 7053",
    "sg:postcode":"37303",
    "sg:province":"TN",
    "sg:tags":[
        "production",
        "engaged"
    ],
    "wof:name":"Power Management Inc",
    "wof:placetype":"venue"
},
  "geometry": {"coordinates":[-84.60917499999999,35.424224],"type":"Point"}
}