{
  "type": "Feature",
  "properties": {
    "iso:country":"US",
    "sg:address":"4534 Harding Pl",
    "sg:city":"Nashville",
    "sg:classifiers":[
        {
            "category":"Restaurant",
            "type":"Food & Drink"
        }
    ],
    "sg:phone":"+1 615 298 5571",
    "sg:postcode":"37205",
    "sg:province":"TN",
    "sg:tags":[
        "theatrical",
        "eating"
    ],
    "wof:name":"Belle Meade Buffet",
    "wof:placetype":"venue"
},
  "geometry": {"coordinates":[-86.856397,36.095732],"type":"Point"}
}