{
  "type": "Feature",
  "properties": {
    "addr:full":"608 Glendale Pl Tullahoma TN 37388",
    "addr:housenumber":"608",
    "addr:postcode":"37388",
    "addr:street":"Glendale Pl",
    "iso:country":"US",
    "sg:address":"608 Glendale Pl",
    "sg:city":"Tullahoma",
    "sg:classifiers":[
        {
            "category":"Personal",
            "subcategory":"Beauty Salon",
            "type":"Services"
        }
    ],
    "sg:phone":"+1 931 461 9928",
    "sg:postcode":"37388",
    "sg:province":"TN",
    "wof:name":"Hatfield Inc",
    "wof:placetype":"venue"
},
  "geometry": {"coordinates":[-86.232748,35.359945],"type":"Point"}
}