{
  "type": "Feature",
  "properties": {
    "iso:country":"US",
    "sg:address":"920 Estate Dr",
    "sg:city":"Memphis",
    "sg:classifiers":[
        {
            "category":"Health Services",
            "subcategory":"Doctor",
            "type":"Services"
        }
    ],
    "sg:phone":"+1 901 226 5716",
    "sg:postcode":"38119",
    "sg:province":"TN",
    "sg:tags":[
        "physician",
        "surgeon"
    ],
    "wof:name":"Anesthesia Specialist Of Tn",
    "wof:placetype":"venue"
},
  "geometry": {"coordinates":[-89.884157,35.106613],"type":"Point"}
}