{
  "type": "Feature",
  "properties": {
    "addr:full":"4040 Dayton Blvd Chattanooga TN 37415",
    "addr:housenumber":"4040",
    "addr:postcode":"37415",
    "addr:street":"Dayton Blvd",
    "iso:country":"US",
    "sg:address":"4040 Dayton Blvd",
    "sg:city":"Chattanooga",
    "sg:classifiers":[
        {
            "category":"Health Services",
            "subcategory":"Doctor",
            "type":"Services"
        }
    ],
    "sg:phone":"+1 423 870 5301",
    "sg:postcode":"37415",
    "sg:province":"TN",
    "sg:tags":[
        "dentist"
    ],
    "wof:name":"William D Kirkpatrick DDS",
    "wof:placetype":"venue"
},
  "geometry": {"coordinates":[-85.28752299999999,35.122043],"type":"Point"}
}