{
  "type": "Feature",
  "properties": {
    "iso:country":"US",
    "sg:address":"2300 4th Ave",
    "sg:city":"Chattanooga",
    "sg:classifiers":[
        {
            "category":"Food & Beverages",
            "subcategory":"Groceries & Convenience Stores",
            "type":"Retail Goods"
        }
    ],
    "sg:phone":"+1 423 624 2276",
    "sg:postcode":"37404",
    "sg:province":"TN",
    "wof:name":"Parth Grocery",
    "wof:placetype":"venue"
},
  "geometry": {"coordinates":[-85.280126,35.017105],"type":"Point"}
}