{
  "type": "Feature",
  "properties": {
    "iso:country":"US",
    "sg:address":"4711 Trousdale Dr",
    "sg:city":"Nashville",
    "sg:classifiers":[
        {
            "category":"Insurance",
            "subcategory":"Insurance Agent",
            "type":"Services"
        }
    ],
    "sg:phone":"+1 615 837 2400",
    "sg:postcode":"37220",
    "sg:province":"TN",
    "wof:name":"Gill & Assoc",
    "wof:placetype":"venue"
},
  "geometry": {"coordinates":[-86.758867,36.077901],"type":"Point"}
}