{
  "type": "Feature",
  "properties": {
    "iso:country":"US",
    "sg:address":"1626 State Hwy 12 S",
    "sg:city":"Ashland City",
    "sg:classifiers":[
        {
            "category":"Restaurant",
            "type":"Food & Drink"
        }
    ],
    "sg:phone":"+1 615 792 2075",
    "sg:postcode":"37015",
    "sg:province":"TN",
    "sg:website":"www.subway.com",
    "wof:name":"Subway Sandwiches & Salads",
    "wof:placetype":"venue"
},
  "geometry": {"coordinates":[-87.030795,36.248505],"type":"Point"}
}