{
  "type": "Feature",
  "properties": {
    "addr:full":"104 Southside Park Dr Lebanon TN 37090",
    "addr:housenumber":"104",
    "addr:postcode":"37090",
    "addr:street":"Southside Park Dr",
    "iso:country":"US",
    "sg:address":"104 Southside Park Dr",
    "sg:city":"Lebanon",
    "sg:classifiers":[
        {
            "category":"Wholesale",
            "subcategory":"Machinery & Supplies",
            "type":"Manufacturing & Wholesale Goods"
        }
    ],
    "sg:phone":"+1 615 449 7277",
    "sg:postcode":"37090",
    "sg:province":"TN",
    "sg:tags":[
        "mower",
        "industrial",
        "maintenance",
        "contractor"
    ],
    "wof:name":"Diamond Mowers Inc",
    "wof:placetype":"venue"
},
  "geometry": {"coordinates":[-86.30313,36.171311],"type":"Point"}
}