{
  "type": "Feature",
  "properties": {
    "addr:full":"5515 E Holmes Rd Memphis TN 38118",
    "addr:housenumber":"5515",
    "addr:postcode":"38118",
    "addr:street":"E Holmes Rd",
    "iso:country":"US",
    "sg:address":"5515 E Holmes Rd",
    "sg:city":"Memphis",
    "sg:classifiers":[
        {
            "category":"Retail",
            "subcategory":"Auto Repair",
            "type":"Services"
        }
    ],
    "sg:phone":"+1 901 362 6800",
    "sg:postcode":"38118",
    "sg:province":"TN",
    "sg:tags":[
        "trailer"
    ],
    "wof:name":"M S Trailer & Truck Repair",
    "wof:placetype":"venue"
},
  "geometry": {"coordinates":[-89.8772,35.005886],"type":"Point"}
}