{
  "type": "Feature",
  "properties": {
    "addr:full":"718 Harold Dr Maryville TN 37803",
    "addr:housenumber":"718",
    "addr:postcode":"37803",
    "addr:street":"Harold Dr",
    "iso:country":"US",
    "sg:address":"718 Harold Dr",
    "sg:city":"Maryville",
    "sg:classifiers":[
        {
            "category":"Manufacturing",
            "subcategory":"Tools & Machinery",
            "type":"Manufacturing & Wholesale Goods"
        }
    ],
    "sg:phone":"+1 865 982 6623",
    "sg:postcode":"37803",
    "sg:province":"TN",
    "sg:tags":[
        "equipment",
        "mfg"
    ],
    "wof:name":"Beals Heat & Air",
    "wof:placetype":"venue"
},
  "geometry": {"coordinates":[-83.875895,35.744088],"type":"Point"}
}