{
  "type": "Feature",
  "properties": {
    "iso:country":"US",
    "sg:address":"112 Shivel Dr",
    "sg:city":"Hendersonville",
    "sg:classifiers":[
        {
            "category":"Building & Trades",
            "subcategory":"Landscaping Services",
            "type":"Services"
        }
    ],
    "sg:phone":"+1 615 826 0390",
    "sg:postcode":"37075",
    "sg:province":"TN",
    "wof:name":"Lawns & Landscaping",
    "wof:placetype":"venue"
},
  "geometry": {"coordinates":[-86.623437,36.303323],"type":"Point"}
}