{
  "type": "Feature",
  "properties": {
    "addr:full":"1071 N Main St Dyer TN 38330",
    "addr:housenumber":"1071",
    "addr:postcode":"38330",
    "addr:street":"N Main St",
    "iso:country":"US",
    "sg:address":"1071 N Main St",
    "sg:city":"Dyer",
    "sg:classifiers":[
        {
            "category":"Retail",
            "subcategory":"Auto Rental",
            "type":"Services"
        }
    ],
    "sg:phone":"+1 731 692 3110",
    "sg:postcode":"38330",
    "sg:province":"TN",
    "sg:tags":[
        "trailer",
        "utility"
    ],
    "wof:name":"U-Haul",
    "wof:placetype":"venue"
},
  "geometry": {"coordinates":[-89.002613,36.089264],"type":"Point"}
}