{
  "type": "Feature",
  "properties": {
    "iso:country":"US",
    "sg:address":"2329 E Morris Blvd",
    "sg:city":"Morristown",
    "sg:classifiers":[
        {
            "category":"Banks & Credit Unions",
            "subcategory":"Bank",
            "type":"Services"
        }
    ],
    "sg:phone":"+1 423 317 7352",
    "sg:postcode":"37813",
    "sg:province":"TN",
    "wof:name":"Greene County Bank",
    "wof:placetype":"venue"
},
  "geometry": {"coordinates":[-83.265895,36.221067],"type":"Point"}
}