{
  "type": "Feature",
  "properties": {
    "iso:country":"US",
    "sg:address":"1007 Thomas St",
    "sg:city":"Memphis",
    "sg:classifiers":[
        {
            "category":"Personal",
            "subcategory":"Beauty Salon",
            "type":"Services"
        }
    ],
    "sg:phone":"+1 901 526 1810",
    "sg:postcode":"38107",
    "sg:province":"TN",
    "wof:name":"Robinson Barber & Beauty Shop",
    "wof:placetype":"venue"
},
  "geometry": {"coordinates":[-90.036278,35.167677],"type":"Point"}
}