{
  "type": "Feature",
  "properties": {
    "addr:full":"6004 Lee Hwy Chattanooga TN 37421",
    "addr:housenumber":"6004",
    "addr:postcode":"37421",
    "addr:street":"Lee Hwy",
    "iso:country":"US",
    "sg:address":"6004 Lee Hwy",
    "sg:city":"Chattanooga",
    "sg:classifiers":[
        {
            "category":"Home & Garden",
            "subcategory":"Furniture",
            "type":"Retail Goods"
        }
    ],
    "sg:phone":"+1 423 892 3306",
    "sg:postcode":"37421",
    "sg:province":"TN",
    "wof:name":"Unfinished Furniture Megamart",
    "wof:placetype":"venue"
},
  "geometry": {"coordinates":[-85.194839,35.024516],"type":"Point"}
}