{
  "type": "Feature",
  "properties": {
    "iso:country":"US",
    "sg:address":"2539 Newport Hwy",
    "sg:city":"Sevierville",
    "sg:classifiers":[
        {
            "category":"Organizations",
            "subcategory":"Religious Organization",
            "type":"Services"
        }
    ],
    "sg:phone":"+1 865 453 0522",
    "sg:postcode":"37876",
    "sg:province":"TN",
    "wof:name":"Grace Baptist Church",
    "wof:placetype":"venue"
},
  "geometry": {"coordinates":[-83.45178199999999,35.885796],"type":"Point"}
}