{
  "type": "Feature",
  "properties": {
    "iso:country":"US",
    "sg:address":"1232 17th Ave S",
    "sg:city":"Nashville",
    "sg:classifiers":[
        {
            "category":"Professional",
            "subcategory":"Business Services",
            "type":"Services"
        }
    ],
    "sg:phone":"+1 615 320 5050",
    "sg:postcode":"37212",
    "sg:province":"TN",
    "sg:tags":[
        "recording",
        "studio"
    ],
    "wof:name":"Jam Sync",
    "wof:placetype":"venue"
},
  "geometry": {"coordinates":[-86.794853,36.141337],"type":"Point"}
}