{
  "type": "Feature",
  "properties": {
    "iso:country":"US",
    "sg:address":"1182 Floyd Walker Rd",
    "sg:city":"Maryville",
    "sg:classifiers":[
        {
            "category":"Building & Trades",
            "subcategory":"Construction",
            "type":"Services"
        }
    ],
    "sg:phone":"+1 865 856 2803",
    "sg:postcode":"37801",
    "sg:province":"TN",
    "sg:tags":[
        "repair",
        "line",
        "sewer",
        "rehabilitation"
    ],
    "wof:name":"Underground Technologies Inc",
    "wof:placetype":"venue"
},
  "geometry": {"coordinates":[-84.141756,35.614056],"type":"Point"}
}