{
  "type": "Feature",
  "properties": {
    "iso:country":"US",
    "sg:address":"417 E Burwell Ave",
    "sg:city":"Knoxville",
    "sg:classifiers":[
        {
            "category":"Retail",
            "subcategory":"Auto Repair",
            "type":"Services"
        }
    ],
    "sg:phone":"+1 865 686 0175",
    "sg:postcode":"37917",
    "sg:province":"TN",
    "wof:name":"Barba Auto Repair",
    "wof:placetype":"venue"
},
  "geometry": {"coordinates":[-83.936607,35.994443],"type":"Point"}
}