{
  "type": "Feature",
  "properties": {
    "iso:country":"US",
    "sg:address":"5508 Hunter Rd",
    "sg:city":"Ooltewah",
    "sg:classifiers":[
        {
            "category":"Retail",
            "subcategory":"Auto Repair",
            "type":"Services"
        }
    ],
    "sg:phone":"+1 423 238 3861",
    "sg:postcode":"37363",
    "sg:province":"TN",
    "sg:tags":[
        "repairing",
        "automobile"
    ],
    "wof:name":"Blaylocks Auto Repair",
    "wof:placetype":"venue"
},
  "geometry": {"coordinates":[-85.07861699999999,35.095388],"type":"Point"}
}