{
  "type": "Feature",
  "properties": {
    "iso:country":"US",
    "sg:address":"1262 Jackson Felts Rd",
    "sg:city":"Joelton",
    "sg:classifiers":[
        {
            "category":"Restaurant",
            "type":"Food & Drink"
        }
    ],
    "sg:phone":"+1 615 746 3901",
    "sg:postcode":"37080",
    "sg:province":"TN",
    "sg:tags":[
        "eating"
    ],
    "wof:name":"Pear Tree Cafe",
    "wof:placetype":"venue"
},
  "geometry": {"coordinates":[-86.93490799999999,36.345603],"type":"Point"}
}