{
  "type": "Feature",
  "properties": {
    "iso:country":"US",
    "sg:address":"109 Kenner Ave",
    "sg:city":"Nashville",
    "sg:classifiers":[
        {
            "category":"Real Estate",
            "subcategory":"Real Estate Services",
            "type":"Services"
        }
    ],
    "sg:phone":"+1 615 292 2665",
    "sg:postcode":"37205",
    "sg:province":"TN",
    "sg:tags":[
        "company",
        "title"
    ],
    "wof:name":"Advantage Title & Escrow",
    "wof:placetype":"venue"
},
  "geometry": {"coordinates":[-86.846435,36.125702],"type":"Point"}
}