{
  "type": "Feature",
  "properties": {
    "iso:country":"US",
    "sg:address":"5250 Sycamore Grove Ln",
    "sg:city":"Memphis",
    "sg:classifiers":[
        {
            "category":"Professional",
            "subcategory":"Art Services",
            "type":"Services"
        }
    ],
    "sg:phone":"+1 901 761 4204",
    "sg:postcode":"38120",
    "sg:province":"TN",
    "sg:tags":[
        "commercial",
        "design"
    ],
    "sg:website":"www.kellybrother.com",
    "wof:name":"Kelly Brother Illustration",
    "wof:placetype":"venue"
},
  "geometry": {"coordinates":[-89.884783,35.125713],"type":"Point"}
}