{
  "type": "Feature",
  "properties": {
    "iso:country":"US",
    "sg:address":"800 Harrison St",
    "sg:city":"Nashville",
    "sg:classifiers":[
        {
            "category":"Manufacturing",
            "subcategory":"Tobacco Products",
            "type":"Manufacturing & Wholesale Goods"
        }
    ],
    "sg:phone":"+1 615 880 4600",
    "sg:postcode":"37203",
    "sg:province":"TN",
    "sg:tags":[
        "smokeless"
    ],
    "wof:name":"U S Smokeless Tob Brands Inc",
    "wof:placetype":"venue"
},
  "geometry": {"coordinates":[-86.789176,36.168209],"type":"Point"}
}