{
  "type": "Feature",
  "properties": {
    "addr:full":"117 Huxley Rd Knoxville TN 37922",
    "addr:housenumber":"117",
    "addr:postcode":"37922",
    "addr:street":"Huxley Rd",
    "iso:country":"US",
    "sg:address":"117 Huxley Rd",
    "sg:city":"Knoxville",
    "sg:classifiers":[
        {
            "category":"Wholesale",
            "subcategory":"Vending Machines",
            "type":"Manufacturing & Wholesale Goods"
        }
    ],
    "sg:phone":"+1 865 692 8787",
    "sg:postcode":"37922",
    "sg:province":"TN",
    "wof:name":"DCR",
    "wof:placetype":"venue"
},
  "geometry": {"coordinates":[-84.13323099999999,35.896682],"type":"Point"}
}