{
  "type": "Feature",
  "properties": {
    "iso:country":"US",
    "sg:address":"3070 Williamsport Pike",
    "sg:city":"Columbia",
    "sg:classifiers":[
        {
            "category":"Wholesale",
            "subcategory":"Meat",
            "type":"Manufacturing & Wholesale Goods"
        }
    ],
    "sg:phone":"+1 931 583 0452",
    "sg:postcode":"38401",
    "sg:province":"TN",
    "wof:name":"Warpware",
    "wof:placetype":"venue"
},
  "geometry": {"coordinates":[-87.16919799999999,35.652268],"type":"Point"}
}