{
  "type": "Feature",
  "properties": {
    "iso:country":"US",
    "sg:address":"762 Batley Rd",
    "sg:city":"Clinton",
    "sg:classifiers":[
        {
            "category":"Organizations",
            "subcategory":"Religious Organization",
            "type":"Services"
        }
    ],
    "sg:phone":"+1 865 435 2400",
    "sg:postcode":"37716",
    "sg:province":"TN",
    "wof:name":"Batley Baptist Church",
    "wof:placetype":"venue"
},
  "geometry": {"coordinates":[-84.28556500000001,36.02974],"type":"Point"}
}