{
  "type": "Feature",
  "properties": {
    "iso:country":"US",
    "sg:address":"2311 W Emory Rd",
    "sg:city":"Powell",
    "sg:classifiers":[
        {
            "category":"Retail",
            "subcategory":"Animal Services",
            "type":"Services"
        }
    ],
    "sg:phone":"+1 865 947 0437",
    "sg:postcode":"37849",
    "sg:province":"TN",
    "sg:tags":[
        "veterinary"
    ],
    "wof:name":"Emory Animal Hospital",
    "wof:placetype":"venue"
},
  "geometry": {"coordinates":[-84.032933,36.027953],"type":"Point"}
}