{
  "type": "Feature",
  "properties": {
    "iso:country":"US",
    "sg:address":"7333 Chapman Hwy",
    "sg:city":"Knoxville",
    "sg:classifiers":[
        {
            "category":"Shopping",
            "subcategory":"Stationery & Office Supplies",
            "type":"Retail Goods"
        }
    ],
    "sg:phone":"+1 865 609 1212",
    "sg:postcode":"37920",
    "sg:province":"TN",
    "sg:tags":[
        "educational",
        "material"
    ],
    "wof:name":"Education Station",
    "wof:placetype":"venue"
},
  "geometry": {"coordinates":[-83.847532,35.908959],"type":"Point"}
}