{
  "type": "Feature",
  "properties": {
    "iso:country":"US",
    "sg:address":"911 20th Ave S",
    "sg:city":"Nashville",
    "sg:classifiers":[
        {
            "category":"Restaurant",
            "type":"Food & Drink"
        }
    ],
    "sg:menulink":"http://www.allmenus.com/tn/nashville/278438-boundry/menu/",
    "sg:phone":"+1 615 321 3043",
    "sg:postcode":"37212",
    "sg:province":"TN",
    "sg:tags":[
        "new",
        "american"
    ],
    "wof:name":"Bound'Ry",
    "wof:placetype":"venue"
},
  "geometry": {"coordinates":[-86.798323,36.14822],"type":"Point"}
}