{
  "type": "Feature",
  "properties": {
    "iso:country":"US",
    "sg:address":"9332 Curling Pond Ln",
    "sg:city":"Arlington",
    "sg:classifiers":[
        {
            "category":"Wholesale",
            "subcategory":"Jewelry",
            "type":"Manufacturing & Wholesale Goods"
        }
    ],
    "sg:phone":"+1 901 373 3759",
    "sg:postcode":"38002",
    "sg:province":"TN",
    "sg:tags":[
        "stone"
    ],
    "wof:name":"Babs Fashion Jewelry & ACC",
    "wof:placetype":"venue"
},
  "geometry": {"coordinates":[-89.753941,35.211082],"type":"Point"}
}