{
  "type": "Feature",
  "properties": {
    "addr:full":"7121 Manor Woods Ct Germantown TN 38138",
    "addr:housenumber":"7121",
    "addr:postcode":"38138",
    "addr:street":"Manor Woods Ct",
    "iso:country":"US",
    "sg:address":"7121 Manor Woods Ct",
    "sg:city":"Germantown",
    "sg:classifiers":[
        {
            "category":"Professional",
            "type":"Services"
        }
    ],
    "sg:phone":"+1 901 757 2650",
    "sg:postcode":"38138",
    "sg:province":"TN",
    "sg:tags":[
        "establishment"
    ],
    "wof:name":"Taylor Bruce Cameron & Melody",
    "wof:placetype":"venue"
},
  "geometry": {"coordinates":[-89.82584300000001,35.108368],"type":"Point"}
}