{
  "type": "Feature",
  "properties": {
    "iso:country":"US",
    "sg:address":"113 Westhill Dr",
    "sg:city":"Lebanon",
    "sg:classifiers":[
        {
            "category":"Organizations",
            "subcategory":"Religious Organization",
            "type":"Services"
        }
    ],
    "sg:phone":"+1 615 443 4845",
    "sg:postcode":"37087",
    "sg:province":"TN",
    "sg:tags":[
        "church"
    ],
    "wof:name":"Convenant Life Church",
    "wof:placetype":"venue"
},
  "geometry": {"coordinates":[-86.32204900000001,36.213084],"type":"Point"}
}