{
  "type": "Feature",
  "properties": {
    "addr:full":"5208 Catalina Rd Knoxville TN 37918",
    "addr:housenumber":"5208",
    "addr:postcode":"37918",
    "addr:street":"Catalina Rd",
    "iso:country":"US",
    "sg:address":"5208 Catalina Rd",
    "sg:city":"Knoxville",
    "sg:classifiers":[
        {
            "category":"Health Services",
            "subcategory":"Doctor",
            "type":"Services"
        }
    ],
    "sg:phone":"+1 865 688 9180",
    "sg:postcode":"37918",
    "sg:province":"TN",
    "sg:tags":[
        "dentist"
    ],
    "wof:name":"J Randall Hutton DDS",
    "wof:placetype":"venue"
},
  "geometry": {"coordinates":[-83.901882,36.058981],"type":"Point"}
}