{
  "type": "Feature",
  "properties": {
    "iso:country":"US",
    "sg:address":"6307 Stinking Creek Rd",
    "sg:city":"Pioneer",
    "sg:classifiers":[
        {
            "category":"Professional",
            "subcategory":"Advertising",
            "type":"Services"
        }
    ],
    "sg:phone":"+1 423 784 9418",
    "sg:postcode":"37847",
    "sg:province":"TN",
    "wof:name":"RIDEROYALBLUE.COM",
    "wof:placetype":"venue"
},
  "geometry": {"coordinates":[-84.147244,36.504919],"type":"Point"}
}