{
  "type": "Feature",
  "properties": {
    "iso:country":"US",
    "sg:address":"2412 Potter Rd",
    "sg:city":"Maryville",
    "sg:classifiers":[
        {
            "category":"Building & Trades",
            "subcategory":"Construction",
            "type":"Services"
        }
    ],
    "sg:phone":"+1 865 977 0657",
    "sg:postcode":"37803",
    "sg:province":"TN",
    "sg:tags":[
        "excavation",
        "contractor"
    ],
    "wof:name":"Pg Excavating",
    "wof:placetype":"venue"
},
  "geometry": {"coordinates":[-83.983107,35.660449],"type":"Point"}
}