{
  "type": "Feature",
  "properties": {
    "iso:country":"US",
    "sg:address":"4014 Outland Rd",
    "sg:city":"Memphis",
    "sg:classifiers":[
        {
            "category":"Freight",
            "type":"Transportation"
        }
    ],
    "sg:phone":"+1 901 367 9610",
    "sg:postcode":"38118",
    "sg:province":"TN",
    "sg:tags":[
        "arrangement"
    ],
    "wof:name":"Reach America",
    "wof:placetype":"venue"
},
  "geometry": {"coordinates":[-89.901523,35.040991],"type":"Point"}
}