{
  "type": "Feature",
  "properties": {
    "iso:country":"US",
    "sg:address":"1202 Murfreesboro Rd",
    "sg:city":"Franklin",
    "sg:classifiers":[
        {
            "category":"Utilities",
            "subcategory":"Mobile Phone",
            "type":"Services"
        }
    ],
    "sg:phone":"+1 615 794 6044",
    "sg:postcode":"37064",
    "sg:province":"TN",
    "sg:tags":[
        "telephone",
        "cellular"
    ],
    "wof:name":"Radio Shack",
    "wof:placetype":"venue"
},
  "geometry": {"coordinates":[-86.831491,35.91562],"type":"Point"}
}