{
  "type": "Feature",
  "properties": {
    "iso:country":"US",
    "sg:address":"345 Huffman St",
    "sg:city":"Normandy",
    "sg:classifiers":[
        {
            "category":"Food & Beverages",
            "subcategory":"Groceries & Convenience Stores",
            "type":"Retail Goods"
        }
    ],
    "sg:phone":"+1 931 857 3004",
    "sg:postcode":"37360",
    "sg:province":"TN",
    "wof:name":"Lakeside Market",
    "wof:placetype":"venue"
},
  "geometry": {"coordinates":[-86.25653699999999,35.458673],"type":"Point"}
}