{
  "type": "Feature",
  "properties": {
    "iso:country":"US",
    "sg:address":"302 E Main Blvd",
    "sg:city":"Church Hill",
    "sg:classifiers":[
        {
            "category":"Government",
            "subcategory":"Office",
            "type":"Public Place"
        }
    ],
    "sg:phone":"+1 423 357 4391",
    "sg:postcode":"37642",
    "sg:province":"TN",
    "wof:name":"Hawkins County Trustee",
    "wof:placetype":"venue"
},
  "geometry": {"coordinates":[-82.70612199999999,36.522906],"type":"Point"}
}