{
  "type": "Feature",
  "properties": {
    "addr:full":"2362 Ketchum Rd Memphis TN 38114",
    "addr:housenumber":"2362",
    "addr:postcode":"38114",
    "addr:street":"Ketchum Rd",
    "iso:country":"US",
    "sg:address":"2362 Ketchum Rd",
    "sg:city":"Memphis",
    "sg:classifiers":[
        {
            "category":"Retail",
            "subcategory":"Laundry & Dry Cleaning",
            "type":"Services"
        }
    ],
    "sg:phone":"+1 901 743 4991",
    "sg:postcode":"38114",
    "sg:province":"TN",
    "sg:tags":[
        "cleaners"
    ],
    "wof:name":"Airways Blvd Qulty One Hr Clrs",
    "wof:placetype":"venue"
},
  "geometry": {"coordinates":[-89.98411900000001,35.079425],"type":"Point"}
}