{
  "type": "Feature",
  "properties": {
    "iso:country":"US",
    "sg:address":"222 Friendship Rd",
    "sg:city":"Newport",
    "sg:classifiers":[
        {
            "category":"Professional",
            "subcategory":"Business Services",
            "type":"Services"
        }
    ],
    "sg:phone":"+1 423 623 7579",
    "sg:postcode":"37821",
    "sg:province":"TN",
    "wof:name":"Ruble Flea Market",
    "wof:placetype":"venue"
},
  "geometry": {"coordinates":[-83.228024,35.907859],"type":"Point"}
}