{
  "type": "Feature",
  "properties": {
    "iso:country":"US",
    "sg:address":"7041 US Hwy 70 S",
    "sg:city":"Nashville",
    "sg:classifiers":[
        {
            "category":"Shopping",
            "type":"Retail Goods"
        }
    ],
    "sg:phone":"+1 615 673 2311",
    "sg:postcode":"37221",
    "sg:province":"TN",
    "sg:tags":[
        "merchandise"
    ],
    "wof:name":"T-Mobile USA Inc",
    "wof:placetype":"venue"
},
  "geometry": {"coordinates":[-86.916594,36.075816],"type":"Point"}
}