{
  "type": "Feature",
  "properties": {
    "iso:country":"US",
    "sg:address":"2619 Barwood Dr",
    "sg:city":"Greenbrier",
    "sg:classifiers":[
        {
            "category":"Food & Beverages",
            "subcategory":"Bakery",
            "type":"Retail Goods"
        }
    ],
    "sg:phone":"+1 615 855 0606",
    "sg:postcode":"37073",
    "sg:province":"TN",
    "sg:tags":[
        "baker"
    ],
    "wof:name":"Walls Treat Bakery",
    "wof:placetype":"venue"
},
  "geometry": {"coordinates":[-86.772509,36.410299],"type":"Point"}
}