{
  "type": "Feature",
  "properties": {
    "iso:country":"US",
    "sg:address":"5461 North Ter",
    "sg:city":"Chattanooga",
    "sg:classifiers":[
        {
            "category":"Community Center",
            "type":"Public Place"
        }
    ],
    "sg:phone":"+1 423 493 0270",
    "sg:postcode":"37411",
    "sg:province":"TN",
    "sg:tags":[
        "recreation"
    ],
    "sg:website":"http://www.jcfgc.com",
    "wof:name":"Jewish Community Federation Of Greater Chattonooga Inc",
    "wof:placetype":"venue"
},
  "geometry": {"coordinates":[-85.221947,35.004829],"type":"Point"}
}