{
  "type": "Feature",
  "properties": {
    "iso:country":"US",
    "sg:address":"3862 Hurst Ct",
    "sg:city":"Memphis",
    "sg:classifiers":[
        {
            "category":"Food & Beverages",
            "subcategory":"Supermarket",
            "type":"Retail Goods"
        }
    ],
    "sg:phone":"+1 901 373 6756",
    "sg:postcode":"38135",
    "sg:province":"TN",
    "sg:tags":[
        "super",
        "store"
    ],
    "wof:name":"O K Foods Inc",
    "wof:placetype":"venue"
},
  "geometry": {"coordinates":[-89.812815,35.231089],"type":"Point"}
}