{
  "type": "Feature",
  "properties": {
    "addr:full":"504 Geneva Dr Goodlettsville TN 37072",
    "addr:housenumber":"504",
    "addr:postcode":"37072",
    "addr:street":"Geneva Dr",
    "iso:country":"US",
    "sg:address":"504 Geneva Dr",
    "sg:city":"Goodlettsville",
    "sg:classifiers":[
        {
            "category":"Building & Trades",
            "subcategory":"Construction",
            "type":"Services"
        }
    ],
    "sg:phone":"+1 615 859 7604",
    "sg:postcode":"37072",
    "sg:province":"TN",
    "sg:tags":[
        "concrete",
        "cutting",
        "breaking",
        "sawing"
    ],
    "wof:name":"Binkley's Concrete & General",
    "wof:placetype":"venue"
},
  "geometry": {"coordinates":[-86.69768500000001,36.333854],"type":"Point"}
}