{
  "type": "Feature",
  "properties": {
    "addr:full":"4008 Industry Dr Chattanooga TN 37416",
    "addr:housenumber":"4008",
    "addr:postcode":"37416",
    "addr:street":"Industry Dr",
    "iso:country":"US",
    "sg:address":"4008 Industry Dr",
    "sg:city":"Chattanooga",
    "sg:classifiers":[
        {
            "category":"Freight",
            "type":"Transportation"
        }
    ],
    "sg:phone":"+1 423 867 7109",
    "sg:postcode":"37416",
    "sg:province":"TN",
    "sg:tags":[
        "mover"
    ],
    "wof:name":"Al Lockwood Movers",
    "wof:placetype":"venue"
},
  "geometry": {"coordinates":[-85.20219899999999,35.073797],"type":"Point"}
}