{
  "type": "Feature",
  "properties": {
    "addr:full":"215 E Main St Watertown TN 37184",
    "addr:housenumber":"215",
    "addr:postcode":"37184",
    "addr:street":"E Main St",
    "iso:country":"US",
    "sg:address":"215 E Main St",
    "sg:city":"Watertown",
    "sg:classifiers":[
        {
            "category":"Shopping",
            "subcategory":"Used Merchandise",
            "type":"Retail Goods"
        }
    ],
    "sg:phone":"+1 615 237 9873",
    "sg:postcode":"37184",
    "sg:province":"TN",
    "wof:name":"Hidden Treasures Antique Maps",
    "wof:placetype":"venue"
},
  "geometry": {"coordinates":[-86.131608,36.100194],"type":"Point"}
}