{
  "type": "Feature",
  "properties": {
    "iso:country":"US",
    "sg:address":"2200 Jones Bend Rd",
    "sg:city":"Paris",
    "sg:phone":"+1 731 642 4396",
    "sg:postcode":"38242",
    "sg:province":"TN",
    "sg:tags":[
        "farm",
        "soybean"
    ],
    "wof:name":"Ernie Diggs",
    "wof:placetype":"venue"
},
  "geometry": {"coordinates":[-88.376941,36.319125],"type":"Point"}
}