{
  "type": "Feature",
  "properties": {
    "iso:country":"US",
    "sg:address":"463 Harding Industrial Dr",
    "sg:city":"Nashville",
    "sg:classifiers":[
        {
            "category":"Manufacturing",
            "subcategory":"Rubber & Plastics",
            "type":"Manufacturing & Wholesale Goods"
        }
    ],
    "sg:phone":"+1 615 833 1572",
    "sg:postcode":"37211",
    "sg:province":"TN",
    "sg:tags":[
        "product"
    ],
    "wof:name":"Clopay Plastic Products Co",
    "wof:placetype":"venue"
},
  "geometry": {"coordinates":[-86.696073,36.0946],"type":"Point"}
}