{
  "type": "Feature",
  "properties": {
    "addr:full":"3926 Asheville Hwy Knoxville TN 37914",
    "addr:housenumber":"3926",
    "addr:postcode":"37914",
    "addr:street":"Asheville Hwy",
    "iso:country":"US",
    "sg:address":"3926 Asheville Hwy",
    "sg:city":"Knoxville",
    "sg:classifiers":[
        {
            "category":"Restaurant",
            "type":"Food & Drink"
        }
    ],
    "sg:phone":"+1 865 524 3507",
    "sg:postcode":"37914",
    "sg:province":"TN",
    "wof:name":"Hardee's",
    "wof:placetype":"venue"
},
  "geometry": {"coordinates":[-83.87368499999999,36.001571],"type":"Point"}
}