{
  "type": "Feature",
  "properties": {
    "iso:country":"US",
    "sg:address":"435 N Manassas St",
    "sg:city":"Memphis",
    "sg:classifiers":[
        {
            "category":"Manufacturing",
            "subcategory":"Signs",
            "type":"Manufacturing & Wholesale Goods"
        }
    ],
    "sg:phone":"+1 901 528 2937",
    "sg:postcode":"38105",
    "sg:province":"TN",
    "sg:tags":[
        "specialty",
        "mfg"
    ],
    "wof:name":"Engineering Dept",
    "wof:placetype":"venue"
},
  "geometry": {"coordinates":[-90.03404999999999,35.151969],"type":"Point"}
}