{
  "type": "Feature",
  "properties": {
    "iso:country":"US",
    "sg:address":"4587 Kingston Pike",
    "sg:city":"Knoxville",
    "sg:classifiers":[
        {
            "category":"Sports & Exercise",
            "subcategory":"Bowling",
            "type":"Entertainment"
        }
    ],
    "sg:phone":"+1 865 588 0556",
    "sg:postcode":"37919",
    "sg:province":"TN",
    "sg:tags":[
        "eating",
        "center"
    ],
    "wof:name":"Western Plaza Bowling Lanes",
    "wof:placetype":"venue"
},
  "geometry": {"coordinates":[-83.978379,35.941133],"type":"Point"}
}