{
  "type": "Feature",
  "properties": {
    "iso:country":"US",
    "sg:address":"3489 Parkwin Pl",
    "sg:city":"Memphis",
    "sg:classifiers":[
        {
            "category":"Professional",
            "subcategory":"Secretarial Services",
            "type":"Services"
        }
    ],
    "sg:phone":"+1 901 546 9967",
    "sg:postcode":"38118",
    "sg:province":"TN",
    "sg:tags":[
        "resume"
    ],
    "wof:name":"Leron's Resume Svc",
    "wof:placetype":"venue"
},
  "geometry": {"coordinates":[-89.947648,35.047339],"type":"Point"}
}