{
  "type": "Feature",
  "properties": {
    "iso:country":"US",
    "sg:address":"4513 Ernie Dr",
    "sg:city":"Memphis",
    "sg:classifiers":[
        {
            "category":"Professional",
            "type":"Services"
        }
    ],
    "sg:phone":"+1 901 346 2859",
    "sg:postcode":"38116",
    "sg:province":"TN",
    "wof:name":"River City Romance Writer",
    "wof:placetype":"venue"
},
  "geometry": {"coordinates":[-90.01461,35.025928],"type":"Point"}
}