{
  "type": "Feature",
  "properties": {
    "addr:full":"822 O'Sage Dr Soddy Daisy TN 37379",
    "addr:housenumber":"822",
    "addr:postcode":"37379",
    "addr:street":"O'Sage Dr",
    "iso:country":"US",
    "sg:address":"822 O'Sage Dr",
    "sg:city":"Soddy Daisy",
    "sg:classifiers":[
        {
            "category":"Building & Trades",
            "subcategory":"Construction",
            "type":"Services"
        }
    ],
    "sg:phone":"+1 423 332 1013",
    "sg:postcode":"37379",
    "sg:province":"TN",
    "sg:tags":[
        "downspouts",
        "gutter",
        "contractor"
    ],
    "wof:name":"Chattanooga Seamless Guttering",
    "wof:placetype":"venue"
},
  "geometry": {"coordinates":[-86.086134,35.517246],"type":"Point"}
}