{
  "type": "Feature",
  "properties": {
    "iso:country":"US",
    "sg:address":"350 Sales Landing Rd",
    "sg:city":"Camden",
    "sg:classifiers":[
        {
            "category":"Real Estate",
            "subcategory":"Real Estate Operator",
            "type":"Services"
        }
    ],
    "sg:phone":"+1 731 584 9755",
    "sg:postcode":"38320",
    "sg:province":"TN",
    "sg:tags":[
        "building",
        "apartment"
    ],
    "wof:name":"Riverview Townhomes Inc",
    "wof:placetype":"venue"
},
  "geometry": {"coordinates":[-88.05629500000001,36.056473],"type":"Point"}
}