{
  "type": "Feature",
  "properties": {
    "addr:full":"517 Watt Rd Knoxville TN 37934",
    "addr:housenumber":"517",
    "addr:postcode":"37934",
    "addr:street":"Watt Rd",
    "iso:country":"US",
    "sg:address":"517 Watt Rd",
    "sg:city":"Knoxville",
    "sg:classifiers":[
        {
            "category":"Communications",
            "subcategory":"Radio Station",
            "type":"Services"
        }
    ],
    "sg:phone":"+1 865 983 4310",
    "sg:postcode":"37934",
    "sg:province":"TN",
    "sg:tags":[
        "company",
        "broadcasting"
    ],
    "wof:name":"WGAP",
    "wof:placetype":"venue"
},
  "geometry": {"coordinates":[-84.23289200000001,35.872656],"type":"Point"}
}