{
  "type": "Feature",
  "properties": {
    "addr:full":"8043 Regency Dr Nashville TN 37221",
    "addr:housenumber":"8043",
    "addr:postcode":"37221",
    "addr:street":"Regency Dr",
    "iso:country":"US",
    "sg:address":"8043 Regency Dr",
    "sg:city":"Nashville",
    "sg:classifiers":[
        {
            "category":"Building & Trades",
            "subcategory":"Landscaping Services",
            "type":"Services"
        }
    ],
    "sg:phone":"+1 615 646 1372",
    "sg:postcode":"37221",
    "sg:province":"TN",
    "sg:tags":[
        "landscape",
        "contractor"
    ],
    "wof:name":"Anderson Lawn & Landscape",
    "wof:placetype":"venue"
},
  "geometry": {"coordinates":[-86.94274799999999,36.082914],"type":"Point"}
}