{
  "type": "Feature",
  "properties": {
    "iso:country":"US",
    "sg:address":"2908 Huntsville Hwy",
    "sg:city":"Fayetteville",
    "sg:classifiers":[
        {
            "category":"Autos & Motor Vehicles",
            "subcategory":"Motorcycle Sales",
            "type":"Retail Goods"
        }
    ],
    "sg:phone":"+1 931 433 0006",
    "sg:postcode":"37334",
    "sg:province":"TN",
    "sg:tags":[
        "scooter"
    ],
    "sg:website":"www.fayettevillecycle.com",
    "wof:name":"Fayetteville Cycle Ctr",
    "wof:placetype":"venue"
},
  "geometry": {"coordinates":[-86.57331600000001,35.055132],"type":"Point"}
}