{
  "type": "Feature",
  "properties": {
    "iso:country":"US",
    "sg:address":"245 Lackey Ln",
    "sg:city":"Ripley",
    "sg:classifiers":[
        {
            "category":"Professional",
            "subcategory":"Lawyer & Legal Services",
            "type":"Services"
        }
    ],
    "sg:phone":"+1 731 635 9425",
    "sg:postcode":"38063",
    "sg:province":"TN",
    "wof:name":"Thomas J Caldwell",
    "wof:placetype":"venue"
},
  "geometry": {"coordinates":[-89.542513,35.740688],"type":"Point"}
}