{
  "type": "Feature",
  "properties": {
    "iso:country":"US",
    "sg:address":"117 Co Rd 552",
    "sg:city":"Athens",
    "sg:classifiers":[
        {
            "category":"Organizations",
            "subcategory":"Professional Association",
            "type":"Services"
        }
    ],
    "sg:phone":"+1 423 745 9547",
    "sg:postcode":"37303",
    "sg:province":"TN",
    "wof:name":"Swift Association",
    "wof:placetype":"venue"
},
  "geometry": {"coordinates":[-84.561114,35.394421],"type":"Point"}
}