{
  "type": "Feature",
  "properties": {
    "addr:full":"6351 Craddock Ln Lascassas TN 37085",
    "addr:housenumber":"6351",
    "addr:postcode":"37085",
    "addr:street":"Craddock Ln",
    "iso:country":"US",
    "sg:address":"6351 Craddock Ln",
    "sg:city":"Lascassas",
    "sg:classifiers":[
        {
            "category":"Communications",
            "type":"Services"
        }
    ],
    "sg:phone":"+1 615 273 4064",
    "sg:postcode":"37085",
    "sg:province":"TN",
    "sg:tags":[
        "carrier"
    ],
    "wof:name":"Crown Castle USA",
    "wof:placetype":"venue"
},
  "geometry": {"coordinates":[-86.24606900000001,35.92624],"type":"Point"}
}