{
  "type": "Feature",
  "properties": {
    "iso:country":"US",
    "sg:address":"712 W 1st North St",
    "sg:city":"Morristown",
    "sg:classifiers":[
        {
            "category":"Food & Beverages",
            "subcategory":"Specialty",
            "type":"Retail Goods"
        }
    ],
    "sg:phone":"+1 423 585 4332",
    "sg:postcode":"37814",
    "sg:province":"TN",
    "wof:name":"Lifespan Health & Wellness Ctr",
    "wof:placetype":"venue"
},
  "geometry": {"coordinates":[-83.300409,36.210918],"type":"Point"}
}