{
  "type": "Feature",
  "properties": {
    "iso:country":"US",
    "sg:address":"1906 Exeter Rd Ste 1",
    "sg:city":"Germantown",
    "sg:classifiers":[
        {
            "category":"Banks & Credit Unions",
            "subcategory":"Financial Services",
            "type":"Services"
        }
    ],
    "sg:phone":"+1 901 844 4663",
    "sg:postcode":"38138",
    "sg:province":"TN",
    "sg:tags":[
        "loan",
        "mortgage"
    ],
    "wof:name":"Southern States Mortgage Co",
    "wof:placetype":"venue"
},
  "geometry": {"coordinates":[-89.801965,35.09726],"type":"Point"}
}