{
  "type": "Feature",
  "properties": {
    "addr:full":"2805 Azalea Pl Nashville TN 37204",
    "addr:housenumber":"2805",
    "addr:postcode":"37204",
    "addr:street":"Azalea Pl",
    "iso:country":"US",
    "sg:address":"2805 Azalea Pl",
    "sg:city":"Nashville",
    "sg:classifiers":[
        {
            "category":"Manufacturing",
            "subcategory":"Printing",
            "type":"Manufacturing & Wholesale Goods"
        }
    ],
    "sg:phone":"+1 615 851 4450",
    "sg:postcode":"37204",
    "sg:province":"TN",
    "sg:tags":[
        "periodical"
    ],
    "wof:name":"Performing Songwriter Magazine",
    "wof:placetype":"venue"
},
  "geometry": {"coordinates":[-86.76787299999999,36.115977],"type":"Point"}
}