{
  "type": "Feature",
  "properties": {
    "addr:full":"3319 W End Ave Nashville TN 37203",
    "addr:housenumber":"3319",
    "addr:postcode":"37203",
    "addr:street":"W End Ave",
    "iso:country":"US",
    "sg:address":"3319 W End Ave",
    "sg:city":"Nashville",
    "sg:classifiers":[
        {
            "category":"Health Services",
            "subcategory":"Doctor",
            "type":"Services"
        }
    ],
    "sg:phone":"+1 615 297 7440",
    "sg:postcode":"37203",
    "sg:province":"TN",
    "sg:tags":[
        "dentist"
    ],
    "wof:name":"Mcpherson Wallace Dentistry",
    "wof:placetype":"venue"
},
  "geometry": {"coordinates":[-86.818871,36.139497],"type":"Point"}
}