{
  "type": "Feature",
  "properties": {
    "iso:country":"US",
    "sg:address":"908 Main St N",
    "sg:city":"Carthage",
    "sg:classifiers":[
        {
            "category":"Professional",
            "subcategory":"Employment Agencies",
            "type":"Services"
        }
    ],
    "sg:phone":"+1 615 735 1157",
    "sg:postcode":"37030",
    "sg:province":"TN",
    "sg:tags":[
        "management",
        "help",
        "supply"
    ],
    "wof:name":"Holland Employment",
    "wof:placetype":"venue"
},
  "geometry": {"coordinates":[-85.95165,36.262321],"type":"Point"}
}