{
  "type": "Feature",
  "properties": {
    "iso:country":"US",
    "sg:address":"1345 College St",
    "sg:city":"Clarksville",
    "sg:classifiers":[
        {
            "category":"Building & Trades",
            "subcategory":"Construction",
            "type":"Services"
        }
    ],
    "sg:phone":"+1 931 645 3961",
    "sg:postcode":"37040",
    "sg:province":"TN",
    "sg:tags":[
        "roofing",
        "contractor"
    ],
    "wof:name":"Ray Marable Contractor Roofing",
    "wof:placetype":"venue"
},
  "geometry": {"coordinates":[-87.33784900000001,36.537852],"type":"Point"}
}