{
  "type": "Feature",
  "properties": {
    "iso:country":"US",
    "sg:address":"1488 Madison Ave",
    "sg:city":"Memphis",
    "sg:classifiers":[
        {
            "category":"Health Services",
            "subcategory":"Health Practitioner",
            "type":"Services"
        }
    ],
    "sg:phone":"+1 901 726 4110",
    "sg:postcode":"38104",
    "sg:province":"TN",
    "sg:tags":[
        "therapist",
        "physical"
    ],
    "wof:name":"Midtown Injury & Physical",
    "wof:placetype":"venue"
},
  "geometry": {"coordinates":[-90.008994,35.138281],"type":"Point"}
}