{
  "type": "Feature",
  "properties": {
    "iso:country":"US",
    "sg:address":"905 Locklaine Rd",
    "sg:city":"Johnson City",
    "sg:classifiers":[
        {
            "category":"Freight",
            "type":"Transportation"
        }
    ],
    "sg:phone":"+1 423 915 1209",
    "sg:postcode":"37601",
    "sg:province":"TN",
    "sg:tags":[
        "operator",
        "trucking"
    ],
    "wof:name":"Robert W Humphrey",
    "wof:placetype":"venue"
},
  "geometry": {"coordinates":[-82.38220699999999,36.372531],"type":"Point"}
}