{
  "type": "Feature",
  "properties": {
    "iso:country":"US",
    "sg:address":"11504 Bates Rd",
    "sg:city":"Apison",
    "sg:classifiers":[
        {
            "category":"Wholesale",
            "subcategory":"Machinery & Supplies",
            "type":"Manufacturing & Wholesale Goods"
        }
    ],
    "sg:phone":"+1 423 236 4381",
    "sg:postcode":"37302",
    "sg:province":"TN",
    "sg:tags":[
        "equipment",
        "industrial"
    ],
    "wof:name":"Jeske Heavy Equipment Repair",
    "wof:placetype":"venue"
},
  "geometry": {"coordinates":[-85.016777,35.02209],"type":"Point"}
}