{
  "type": "Feature",
  "properties": {
    "iso:country":"US",
    "sg:address":"570 Foster Rd",
    "sg:city":"Adamsville",
    "sg:classifiers":[
        {
            "category":"Building & Trades",
            "subcategory":"Construction",
            "type":"Services"
        }
    ],
    "sg:phone":"+1 731 632 0556",
    "sg:postcode":"38361",
    "sg:province":"TN",
    "sg:tags":[
        "maker",
        "cabinet"
    ],
    "wof:name":"Americab Supply Co",
    "wof:placetype":"venue"
},
  "geometry": {"coordinates":[-88.336899,35.25699],"type":"Point"}
}