{
  "type": "Feature",
  "properties": {
    "iso:country":"US",
    "sg:address":"4901 Midland Pike",
    "sg:city":"Chattanooga",
    "sg:classifiers":[
        {
            "category":"Organizations",
            "subcategory":"Religious Organization",
            "type":"Services"
        }
    ],
    "sg:phone":"+1 423 624 7170",
    "sg:postcode":"37411",
    "sg:province":"TN",
    "wof:name":"Vision Church Of God",
    "wof:placetype":"venue"
},
  "geometry": {"coordinates":[-85.221007,35.026202],"type":"Point"}
}