{
  "type": "Feature",
  "properties": {
    "iso:country":"US",
    "sg:address":"171 Myers Ln",
    "sg:city":"La Follette",
    "sg:classifiers":[
        {
            "category":"Shopping",
            "type":"Retail Goods"
        },
        {
            "category":"Wholesale",
            "subcategory":"Non-durable Goods",
            "type":"Manufacturing & Wholesale Goods"
        }
    ],
    "sg:phone":"+1 423 562 7731",
    "sg:postcode":"37766",
    "sg:province":"TN",
    "sg:tags":[
        "art",
        "gallery",
        "dealer"
    ],
    "wof:name":"Precious Treasurers",
    "wof:placetype":"venue"
},
  "geometry": {"coordinates":[-84.12141800000001,36.363199],"type":"Point"}
}