{
  "type": "Feature",
  "properties": {
    "iso:country":"US",
    "sg:address":"407 S Wilson Blvd",
    "sg:city":"Nashville",
    "sg:classifiers":[
        {
            "category":"Professional",
            "subcategory":"Art Services",
            "type":"Services"
        }
    ],
    "sg:phone":"+1 615 298 3487",
    "sg:postcode":"37205",
    "sg:province":"TN",
    "sg:tags":[
        "graphic",
        "designer"
    ],
    "wof:name":"No Diehl Design",
    "wof:placetype":"venue"
},
  "geometry": {"coordinates":[-86.83353700000001,36.125694],"type":"Point"}
}