{
  "type": "Feature",
  "properties": {
    "iso:country":"US",
    "sg:address":"222 3rd Ave N",
    "sg:city":"Nashville",
    "sg:classifiers":[
        {
            "category":"Organizations",
            "subcategory":"Non-profit Organization",
            "type":"Services"
        }
    ],
    "sg:phone":"+1 615 862 6492",
    "sg:postcode":"37201",
    "sg:province":"TN",
    "sg:tags":[
        "disability"
    ],
    "wof:name":"Disability Information Office",
    "wof:placetype":"venue"
},
  "geometry": {"coordinates":[-86.777051,36.16326],"type":"Point"}
}