{
  "type": "Feature",
  "properties": {
    "iso:country":"US",
    "sg:address":"119 Jennings Ave",
    "sg:city":"Knoxville",
    "sg:classifiers":[
        {
            "category":"Retail",
            "subcategory":"Auto Repair",
            "type":"Services"
        }
    ],
    "sg:phone":"+1 865 633 5525",
    "sg:postcode":"37917",
    "sg:province":"TN",
    "sg:tags":[
        "engine",
        "shop",
        "replacement"
    ],
    "wof:name":"American Engine Installations",
    "wof:placetype":"venue"
},
  "geometry": {"coordinates":[-83.924801,35.976257],"type":"Point"}
}