{
  "type": "Feature",
  "properties": {
    "iso:country":"US",
    "sg:address":"2275 Murfreesboro Pike",
    "sg:city":"Nashville",
    "sg:classifiers":[
        {
            "category":"Insurance",
            "subcategory":"Insurance Agent",
            "type":"Services"
        }
    ],
    "sg:phone":"+1 615 360 6061",
    "sg:postcode":"37217",
    "sg:province":"TN",
    "wof:name":"Allstate Insurance Co",
    "wof:placetype":"venue"
},
  "geometry": {"coordinates":[-86.64963899999999,36.088408],"type":"Point"}
}