{
  "type": "Feature",
  "properties": {
    "iso:country":"US",
    "sg:address":"136 Mc Clain Ct",
    "sg:city":"Johnson City",
    "sg:classifiers":[
        {
            "category":"Building & Trades",
            "subcategory":"Construction",
            "type":"Services"
        }
    ],
    "sg:phone":"+1 423 282 0902",
    "sg:postcode":"37615",
    "sg:province":"TN",
    "sg:tags":[
        "heavy",
        "except"
    ],
    "wof:name":"Southeastern Cnstr Svcs Co",
    "wof:placetype":"venue"
},
  "geometry": {"coordinates":[-82.4109,36.398749],"type":"Point"}
}