{
  "type": "Feature",
  "properties": {
    "iso:country":"US",
    "sg:address":"212 Oriole Dr",
    "sg:city":"Lebanon",
    "sg:classifiers":[
        {
            "category":"Retail",
            "subcategory":"Auto Repair",
            "type":"Services"
        }
    ],
    "sg:phone":"+1 615 449 8478",
    "sg:postcode":"37087",
    "sg:province":"TN",
    "sg:tags":[
        "automotive"
    ],
    "wof:name":"Watkins Mobile Algnmt Svcs LLC",
    "wof:placetype":"venue"
},
  "geometry": {"coordinates":[-86.358205,36.256923],"type":"Point"}
}