{
  "type": "Feature",
  "properties": {
    "iso:country":"US",
    "sg:address":"1758 Long Hollow Pike",
    "sg:city":"Gallatin",
    "sg:classifiers":[
        {
            "category":"Wholesale",
            "subcategory":"Machinery & Supplies",
            "type":"Manufacturing & Wholesale Goods"
        }
    ],
    "sg:phone":"+1 615 452 7852",
    "sg:postcode":"37066",
    "sg:province":"TN",
    "sg:tags":[
        "pump"
    ],
    "wof:name":"H & H Design",
    "wof:placetype":"venue"
},
  "geometry": {"coordinates":[-86.558797,36.382628],"type":"Point"}
}