{
  "type": "Feature",
  "properties": {
    "iso:country":"US",
    "sg:address":"1488 Maurine Dr",
    "sg:city":"Memphis",
    "sg:classifiers":[
        {
            "category":"Organizations",
            "subcategory":"Religious Organization",
            "type":"Services"
        }
    ],
    "sg:phone":"+1 901 346 0251",
    "sg:postcode":"38116",
    "sg:province":"TN",
    "sg:tags":[
        "monastery",
        "place",
        "worship",
        "convent",
        "church"
    ],
    "wof:name":"St Paul Convent",
    "wof:placetype":"venue"
},
  "geometry": {"coordinates":[-90.012986,35.019576],"type":"Point"}
}