{
  "type": "Feature",
  "properties": {
    "iso:country":"US",
    "sg:address":"1129 Frayser Blvd Apt 3",
    "sg:city":"Memphis",
    "sg:classifiers":[
        {
            "category":"Personal",
            "subcategory":"Beauty Salon",
            "type":"Services"
        }
    ],
    "sg:phone":"+1 901 353 2956",
    "sg:postcode":"38127",
    "sg:province":"TN",
    "wof:name":"Tracey Hair Care",
    "wof:placetype":"venue"
},
  "geometry": {"coordinates":[-90.024635,35.216595],"type":"Point"}
}