{
  "type": "Feature",
  "properties": {
    "iso:country":"US",
    "sg:address":"738 Nissan Dr",
    "sg:city":"Smyrna",
    "sg:classifiers":[
        {
            "category":"Retail",
            "subcategory":"Laundry & Dry Cleaning",
            "type":"Services"
        }
    ],
    "sg:phone":"+1 615 449 8200",
    "sg:postcode":"37167",
    "sg:province":"TN",
    "sg:tags":[
        "cleaners",
        "rug",
        "carpet"
    ],
    "sg:website":"www.thecleanest.com",
    "wof:name":"Chem Dry Of Tennessee",
    "wof:placetype":"venue"
},
  "geometry": {"coordinates":[-86.492689,35.973662],"type":"Point"}
}