{
  "type": "Feature",
  "properties": {
    "iso:country":"US",
    "sg:address":"3095 Northgate St",
    "sg:city":"Memphis",
    "sg:classifiers":[
        {
            "category":"Retail",
            "subcategory":"Auto Repair",
            "type":"Services"
        }
    ],
    "sg:phone":"+1 901 409 6996",
    "sg:postcode":"38127",
    "sg:province":"TN",
    "wof:name":"Affordable Automotive",
    "wof:placetype":"venue"
},
  "geometry": {"coordinates":[-90.035331,35.209479],"type":"Point"}
}