{
  "type": "Feature",
  "properties": {
    "iso:country":"US",
    "sg:address":"890 Kraft St",
    "sg:city":"Clarksville",
    "sg:classifiers":[
        {
            "category":"Travel",
            "subcategory":"Hotels & Motels",
            "type":"Entertainment"
        }
    ],
    "sg:phone":"+1 931 647 6536",
    "sg:postcode":"37040",
    "sg:province":"TN",
    "sg:tags":[
        "lodging"
    ],
    "wof:name":"Mid-Town Inn",
    "wof:placetype":"venue"
},
  "geometry": {"coordinates":[-87.365432,36.540524],"type":"Point"}
}