{
  "type": "Feature",
  "properties": {
    "iso:country":"US",
    "sg:address":"4965 Willow Rd",
    "sg:city":"Memphis",
    "sg:classifiers":[
        {
            "category":"Social Services",
            "type":"Services"
        },
        {
            "category":"Education",
            "subcategory":"Special Training",
            "type":"Public Place"
        },
        {
            "category":"Education",
            "subcategory":"Preschool",
            "type":"Public Place"
        }
    ],
    "sg:phone":"+1 901 683 2100",
    "sg:postcode":"38117",
    "sg:province":"TN",
    "sg:tags":[
        "disabled",
        "kindergarten",
        "product",
        "need",
        "developmentally"
    ],
    "wof:name":"Special Kids & Family Inc",
    "wof:placetype":"venue"
},
  "geometry": {"coordinates":[-89.89678600000001,35.085635],"type":"Point"}
}