{
  "type": "Feature",
  "properties": {
    "addr:full":"699 Waring Rd Memphis TN 38122",
    "addr:housenumber":"699",
    "addr:postcode":"38122",
    "addr:street":"Waring Rd",
    "iso:country":"US",
    "sg:address":"699 Waring Rd",
    "sg:city":"Memphis",
    "sg:classifiers":[
        {
            "category":"Personal",
            "subcategory":"Shoe Repair & Shine",
            "type":"Services"
        }
    ],
    "sg:phone":"+1 901 682 2511",
    "sg:postcode":"38122",
    "sg:province":"TN",
    "sg:tags":[
        "parlor"
    ],
    "wof:name":"Nu Life Shoe Repair",
    "wof:placetype":"venue"
},
  "geometry": {"coordinates":[-89.91605800000001,35.14931],"type":"Point"}
}