{
  "type": "Feature",
  "properties": {
    "addr:full":"18157 Alberta St Oneida TN 37841",
    "addr:housenumber":"18157",
    "addr:postcode":"37841",
    "addr:street":"Alberta St",
    "iso:country":"US",
    "sg:address":"18157 Alberta St",
    "sg:city":"Oneida",
    "sg:classifiers":[
        {
            "category":"Shopping",
            "subcategory":"Gifts & Souvenirs",
            "type":"Retail Goods"
        }
    ],
    "sg:phone":"+1 423 569 5555",
    "sg:postcode":"37841",
    "sg:province":"TN",
    "sg:tags":[
        "shop"
    ],
    "wof:name":"Hallmark Unicorn Shoppe",
    "wof:placetype":"venue"
},
  "geometry": {"coordinates":[-84.49558,36.525885],"type":"Point"}
}