{
  "type": "Feature",
  "properties": {
    "iso:country":"US",
    "sg:address":"66 Park Cove",
    "sg:city":"Lexington",
    "sg:classifiers":[
        {
            "category":"Professional",
            "subcategory":"Management & Consulting",
            "type":"Services"
        }
    ],
    "sg:phone":"+1 731 967 3883",
    "sg:postcode":"38351",
    "sg:province":"TN",
    "sg:tags":[
        "consultant",
        "industrial"
    ],
    "wof:name":"Diagnostic Services Inc",
    "wof:placetype":"venue"
},
  "geometry": {"coordinates":[-88.252656,35.649558],"type":"Point"}
}