{
  "type": "Feature",
  "properties": {
    "iso:country":"US",
    "sg:address":"123 Blue Ridge Ct",
    "sg:city":"Oak Ridge",
    "sg:classifiers":[
        {
            "category":"Retail",
            "subcategory":"Self-service Laundry",
            "type":"Services"
        }
    ],
    "sg:phone":"+1 865 481 0229",
    "sg:postcode":"37830",
    "sg:province":"TN",
    "sg:tags":[
        "coin"
    ],
    "wof:name":"Lanes Homestyle Laundry",
    "wof:placetype":"venue"
},
  "geometry": {"coordinates":[-84.20941500000001,36.022328],"type":"Point"}
}