{
  "type": "Feature",
  "properties": {
    "iso:country":"US",
    "sg:address":"951 Cheatham Springs Rd",
    "sg:city":"Wartrace",
    "sg:classifiers":[
        {
            "category":"Wholesale",
            "subcategory":"Non-durable Goods",
            "type":"Manufacturing & Wholesale Goods"
        }
    ],
    "sg:phone":"+1 931 394 2929",
    "sg:postcode":"37183",
    "sg:province":"TN",
    "sg:tags":[
        "advertising"
    ],
    "wof:name":"Brantley Advertising",
    "wof:placetype":"venue"
},
  "geometry": {"coordinates":[-86.227782,35.576798],"type":"Point"}
}