{
  "type": "Feature",
  "properties": {
    "iso:country":"US",
    "sg:address":"476 Cloud Land Dr",
    "sg:city":"Roan Mountain",
    "sg:classifiers":[
        {
            "category":"Education",
            "subcategory":"School",
            "type":"Public Place"
        }
    ],
    "sg:phone":"+1 423 772 5300",
    "sg:postcode":"37687",
    "sg:province":"TN",
    "wof:name":"Cloudland Jr Sr High School",
    "wof:placetype":"venue"
},
  "geometry": {"coordinates":[-82.065798,36.194345],"type":"Point"}
}