{
  "type": "Feature",
  "properties": {
    "addr:full":"700 Garrett Pkwy Lewisburg TN 37091",
    "addr:housenumber":"700",
    "addr:postcode":"37091",
    "addr:street":"Garrett Pkwy",
    "iso:country":"US",
    "sg:address":"700 Garrett Pkwy",
    "sg:city":"Lewisburg",
    "sg:classifiers":[
        {
            "category":"Manufacturing",
            "subcategory":"Paper Products",
            "type":"Manufacturing & Wholesale Goods"
        }
    ],
    "sg:phone":"+1 931 359 4575",
    "sg:postcode":"37091",
    "sg:province":"TN",
    "sg:tags":[
        "box"
    ],
    "wof:name":"Smurfit-Stone Container",
    "wof:placetype":"venue"
},
  "geometry": {"coordinates":[-86.75637399999999,35.434611],"type":"Point"}
}