{
  "type": "Feature",
  "properties": {
    "iso:country":"US",
    "sg:address":"315 Welch Ln",
    "sg:city":"New Tazewell",
    "sg:classifiers":[
        {
            "category":"Building & Trades",
            "subcategory":"Construction",
            "type":"Services"
        }
    ],
    "sg:phone":"+1 423 626 4351",
    "sg:postcode":"37825",
    "sg:province":"TN",
    "sg:tags":[
        "home",
        "contractor",
        "general",
        "new"
    ],
    "wof:name":"Hardwick Construction Inc",
    "wof:placetype":"venue"
},
  "geometry": {"coordinates":[-83.683216,36.458449],"type":"Point"}
}