{
  "type": "Feature",
  "properties": {
    "iso:country":"US",
    "sg:address":"303 Meadows Pl",
    "sg:city":"Rockwood",
    "sg:classifiers":[
        {
            "category":"Real Estate",
            "subcategory":"Real Estate Operator",
            "type":"Services"
        }
    ],
    "sg:phone":"+1 865 354 4015",
    "sg:postcode":"37854",
    "sg:province":"TN",
    "wof:name":"Meadows Apts",
    "wof:placetype":"venue"
},
  "geometry": {"coordinates":[-84.700569,35.859632],"type":"Point"}
}