{
  "type": "Feature",
  "properties": {
    "iso:country":"US",
    "sg:address":"6101 Lottie Ln",
    "sg:city":"Chattanooga",
    "sg:classifiers":[
        {
            "category":"Restaurant",
            "type":"Food & Drink"
        }
    ],
    "sg:phone":"+1 423 344 3753",
    "sg:postcode":"37416",
    "sg:province":"TN",
    "sg:tags":[
        "eating"
    ],
    "wof:name":"Lacreole Cuisine Party Planer",
    "wof:placetype":"venue"
},
  "geometry": {"coordinates":[-85.15663000000001,35.130978],"type":"Point"}
}