{
  "type": "Feature",
  "properties": {
    "iso:country":"US",
    "sg:address":"4223 Dew Mist Cv",
    "sg:city":"Memphis",
    "sg:classifiers":[
        {
            "category":"Shopping",
            "type":"Retail Goods"
        }
    ],
    "sg:phone":"+1 901 367 2096",
    "sg:postcode":"38141",
    "sg:province":"TN",
    "sg:tags":[
        "merchandise"
    ],
    "wof:name":"Discount Days, Inc.",
    "wof:placetype":"venue"
},
  "geometry": {"coordinates":[-89.846063,35.033814],"type":"Point"}
}