{
  "type": "Feature",
  "properties": {
    "iso:country":"US",
    "sg:address":"4681 Burbank Rd",
    "sg:city":"Memphis",
    "sg:classifiers":[
        {
            "category":"Professional",
            "type":"Services"
        }
    ],
    "sg:phone":"+1 901 797 4065",
    "sg:postcode":"38118",
    "sg:province":"TN",
    "sg:tags":[
        "establishment"
    ],
    "wof:name":"Fixture Shop",
    "wof:placetype":"venue"
},
  "geometry": {"coordinates":[-89.90564999999999,35.041486],"type":"Point"}
}