{
  "type": "Feature",
  "properties": {
    "addr:full":"602 Wayne St Waynesboro TN 38485",
    "addr:housenumber":"602",
    "addr:postcode":"38485",
    "addr:street":"Wayne St",
    "iso:country":"US",
    "sg:address":"602 Wayne St",
    "sg:city":"Waynesboro",
    "sg:classifiers":[
        {
            "category":"Shopping",
            "subcategory":"Shoes",
            "type":"Retail Goods"
        }
    ],
    "sg:phone":"+1 931 722 3499",
    "sg:postcode":"38485",
    "sg:province":"TN",
    "wof:name":"Shoe Hut",
    "wof:placetype":"venue"
},
  "geometry": {"coordinates":[-87.762103,35.307821],"type":"Point"}
}