{
  "type": "Feature",
  "properties": {
    "iso:country":"US",
    "sg:address":"871 Dove Rd",
    "sg:city":"Rock Island",
    "sg:classifiers":[
        {
            "category":"Manufacturing",
            "subcategory":"Tools & Machinery",
            "type":"Manufacturing & Wholesale Goods"
        }
    ],
    "sg:phone":"+1 931 686 8788",
    "sg:postcode":"38581",
    "sg:province":"TN",
    "sg:tags":[
        "industrial",
        "mfg"
    ],
    "wof:name":"Bolding Bros Machine & Welding",
    "wof:placetype":"venue"
},
  "geometry": {"coordinates":[-85.660946,35.810032],"type":"Point"}
}