{
  "type": "Feature",
  "properties": {
    "addr:full":"5102 Woodglen Dr NW Knoxville TN 37921",
    "addr:housenumber":"5102",
    "addr:postcode":"37921",
    "addr:street":"Woodglen Dr Nw",
    "iso:country":"US",
    "sg:address":"5102 Woodglen Dr NW",
    "sg:city":"Knoxville",
    "sg:classifiers":[
        {
            "category":"Building & Trades",
            "subcategory":"Construction",
            "type":"Services"
        }
    ],
    "sg:phone":"+1 865 588 5870",
    "sg:postcode":"37921",
    "sg:province":"TN",
    "sg:tags":[
        "house"
    ],
    "wof:name":"K & W Builders LLC",
    "wof:placetype":"venue"
},
  "geometry": {"coordinates":[-84.002432,35.964168],"type":"Point"}
}