{
  "type": "Feature",
  "properties": {
    "iso:country":"US",
    "sg:address":"15 Hopewell Rd",
    "sg:city":"Dyer",
    "sg:phone":"+1 731 643 6747",
    "sg:postcode":"38330",
    "sg:province":"TN",
    "sg:tags":[
        "farm",
        "cotton"
    ],
    "wof:name":"Don Todd",
    "wof:placetype":"venue"
},
  "geometry": {"coordinates":[-89.079058,36.079099],"type":"Point"}
}