{
  "type": "Feature",
  "properties": {
    "addr:full":"696 S Willow Ave Cookeville TN 38501",
    "addr:housenumber":"696",
    "addr:postcode":"38501",
    "addr:street":"S Willow Ave",
    "iso:country":"US",
    "sg:address":"696 S Willow Ave",
    "sg:city":"Cookeville",
    "sg:classifiers":[
        {
            "category":"Shopping",
            "subcategory":"Gifts & Souvenirs",
            "type":"Retail Goods"
        }
    ],
    "sg:phone":"+1 931 526 4569",
    "sg:postcode":"38501",
    "sg:province":"TN",
    "wof:name":"Illusions",
    "wof:placetype":"venue"
},
  "geometry": {"coordinates":[-85.51912400000001,36.148373],"type":"Point"}
}