{
  "type": "Feature",
  "properties": {
    "iso:country":"US",
    "sg:address":"119 Wears Valley Rd",
    "sg:city":"Pigeon Forge",
    "sg:classifiers":[
        {
            "category":"Restaurant",
            "type":"Food & Drink"
        }
    ],
    "sg:phone":"+1 865 429 2184",
    "sg:postcode":"37863",
    "sg:province":"TN",
    "wof:name":"Mel's Diner Inc",
    "wof:placetype":"venue"
},
  "geometry": {"coordinates":[-83.576358,35.804233],"type":"Point"}
}