{
  "type": "Feature",
  "properties": {
    "iso:country":"US",
    "sg:address":"324 W Burton St",
    "sg:city":"Murfreesboro",
    "sg:classifiers":[
        {
            "category":"Personal",
            "subcategory":"Beauty Salon",
            "type":"Services"
        }
    ],
    "sg:phone":"+1 615 849 1045",
    "sg:postcode":"37130",
    "sg:province":"TN",
    "wof:name":"Hair Doctor Ect",
    "wof:placetype":"venue"
},
  "geometry": {"coordinates":[-86.393092,35.84936],"type":"Point"}
}