{
  "type": "Feature",
  "properties": {
    "addr:full":"210 Commerce St Nashville TN 37201",
    "addr:housenumber":"210",
    "addr:postcode":"37201",
    "addr:street":"Commerce St",
    "iso:country":"US",
    "sg:address":"210 Commerce St",
    "sg:city":"Nashville",
    "sg:classifiers":[
        {
            "category":"Parking",
            "type":"Transportation"
        }
    ],
    "sg:phone":"+1 615 242 8776",
    "sg:postcode":"37201",
    "sg:province":"TN",
    "sg:tags":[
        "garage"
    ],
    "wof:name":"Central Parking System",
    "wof:placetype":"venue"
},
  "geometry": {"coordinates":[-86.77641,36.163188],"type":"Point"}
}