{
  "type": "Feature",
  "properties": {
    "addr:full":"2034 N Highland Ave Jackson TN 38305",
    "addr:housenumber":"2034",
    "addr:postcode":"38305",
    "addr:street":"N Highland Ave",
    "iso:country":"US",
    "sg:address":"2034 N Highland Ave",
    "sg:city":"Jackson",
    "sg:classifiers":[
        {
            "category":"Restaurant",
            "type":"Food & Drink"
        }
    ],
    "sg:menulink":"http://www.allmenus.com/tn/jackson/100955-captain-ds-seafood/menu/",
    "sg:phone":"+1 731 668 0983",
    "sg:postcode":"38305",
    "sg:province":"TN",
    "sg:tags":[
        "seafood",
        "american"
    ],
    "wof:name":"Captain D's Seafood",
    "wof:placetype":"venue"
},
  "geometry": {"coordinates":[-88.827778,35.656865],"type":"Point"}
}