{
  "type": "Feature",
  "properties": {
    "iso:country":"US",
    "sg:address":"1323 Buffalo Trl",
    "sg:city":"Morristown",
    "sg:classifiers":[
        {
            "category":"Retail",
            "subcategory":"Auto Repair",
            "type":"Services"
        }
    ],
    "sg:phone":"+1 423 586 6228",
    "sg:postcode":"37814",
    "sg:province":"TN",
    "sg:tags":[
        "repairing",
        "automobile"
    ],
    "wof:name":"K & R Automotive",
    "wof:placetype":"venue"
},
  "geometry": {"coordinates":[-83.29285400000001,36.228002],"type":"Point"}
}