{
  "type": "Feature",
  "properties": {
    "iso:country":"US",
    "sg:address":"77 Lynchburg Hwy",
    "sg:city":"Fayetteville",
    "sg:classifiers":[
        {
            "category":"Real Estate",
            "subcategory":"Real Estate Agent",
            "type":"Services"
        }
    ],
    "sg:phone":"+1 931 433 3245",
    "sg:postcode":"37334",
    "sg:province":"TN",
    "sg:tags":[
        "appraiser"
    ],
    "wof:name":"Thompson Appraisal Services",
    "wof:placetype":"venue"
},
  "geometry": {"coordinates":[-86.51970900000001,35.178093],"type":"Point"}
}