{
  "type": "Feature",
  "properties": {
    "iso:country":"US",
    "sg:address":"12 E Belz Blvd",
    "sg:city":"Memphis",
    "sg:classifiers":[
        {
            "category":"Freight",
            "type":"Transportation"
        }
    ],
    "sg:phone":"+1 901 774 2197",
    "sg:postcode":"38109",
    "sg:province":"TN",
    "sg:tags":[
        "mover"
    ],
    "sg:website":"www.ewingmovingservice.com",
    "wof:name":"Ewing Moving Svc",
    "wof:placetype":"venue"
},
  "geometry": {"coordinates":[-90.0617,35.095563],"type":"Point"}
}