{
  "type": "Feature",
  "properties": {
    "iso:country":"US",
    "sg:address":"204 Warwick Park Ln",
    "sg:city":"Franklin",
    "sg:classifiers":[
        {
            "category":"Wholesale",
            "subcategory":"Medical Equipment & Supplies",
            "type":"Manufacturing & Wholesale Goods"
        }
    ],
    "sg:phone":"+1 615 595 8793",
    "sg:postcode":"37069",
    "sg:province":"TN",
    "wof:name":"Motorvations Inc",
    "wof:placetype":"venue"
},
  "geometry": {"coordinates":[-86.87566099999999,35.959144],"type":"Point"}
}