{
  "type": "Feature",
  "properties": {
    "addr:full":"385 W Main St Gallatin TN 37066",
    "addr:housenumber":"385",
    "addr:postcode":"37066",
    "addr:street":"W Main St",
    "iso:country":"US",
    "sg:address":"385 W Main St",
    "sg:city":"Gallatin",
    "sg:phone":"+1 615 452 5373",
    "sg:postcode":"37066",
    "sg:province":"TN",
    "sg:tags":[
        "oil"
    ],
    "wof:name":"Rail Petroleum Co",
    "wof:placetype":"venue"
},
  "geometry": {"coordinates":[-86.45178199999999,36.386938],"type":"Point"}
}