{
  "type": "Feature",
  "properties": {
    "iso:country":"US",
    "sg:address":"981 N Germantown Pkwy",
    "sg:city":"Cordova",
    "sg:classifiers":[
        {
            "category":"Shopping",
            "subcategory":"Bicycles & Sporting Goods",
            "type":"Retail Goods"
        }
    ],
    "sg:phone":"+1 901 751 9988",
    "sg:postcode":"38018",
    "sg:province":"TN",
    "sg:website":"www.dowdlesports.com",
    "wof:name":"Dowdle Sports Inc",
    "wof:placetype":"venue"
},
  "geometry": {"coordinates":[-89.79528999999999,35.151557],"type":"Point"}
}