{
  "type": "Feature",
  "properties": {
    "addr:full":"654 N Edgewood Dr Sparta TN 38583",
    "addr:housenumber":"654",
    "addr:postcode":"38583",
    "addr:street":"N Edgewood Dr",
    "iso:country":"US",
    "sg:address":"654 N Edgewood Dr",
    "sg:city":"Sparta",
    "sg:classifiers":[
        {
            "category":"Professional",
            "type":"Services"
        }
    ],
    "sg:phone":"+1 931 738 2760",
    "sg:postcode":"38583",
    "sg:province":"TN",
    "wof:name":"Cardwell Amusement Company",
    "wof:placetype":"venue"
},
  "geometry": {"coordinates":[-85.48150099999999,35.964977],"type":"Point"}
}