{
  "type": "Feature",
  "properties": {
    "iso:country":"US",
    "sg:address":"3352 Democrat Rd",
    "sg:city":"Memphis",
    "sg:classifiers":[
        {
            "category":"Military Area",
            "type":"Public Place"
        },
        {
            "category":"Personal",
            "subcategory":"Barber",
            "type":"Services"
        },
        {
            "category":"Recreation",
            "subcategory":"Gun Range",
            "type":"Entertainment"
        },
        {
            "category":"Organizations",
            "subcategory":"Professional Association",
            "type":"Services"
        }
    ],
    "sg:phone":"+1 901 362 5034",
    "sg:postcode":"38118",
    "sg:province":"TN",
    "sg:tags":[
        "business",
        "supply",
        "sale",
        "guns-manufacturers",
        "trade",
        "equipment",
        "ammunition"
    ],
    "wof:name":"Ferguson Enterprises, Inc.",
    "wof:placetype":"venue"
},
  "geometry": {"coordinates":[-89.951076,35.068691],"type":"Point"}
}