{
  "type": "Feature",
  "properties": {
    "addr:full":"3481 Poplar Ave Memphis TN 38111",
    "addr:housenumber":"3481",
    "addr:postcode":"38111",
    "addr:street":"Poplar Ave",
    "iso:country":"US",
    "sg:address":"3481 Poplar Ave",
    "sg:city":"Memphis",
    "sg:classifiers":[
        {
            "category":"Health Services",
            "subcategory":"Doctor",
            "type":"Services"
        }
    ],
    "sg:phone":"+1 901 320 9301",
    "sg:postcode":"38111",
    "sg:province":"TN",
    "sg:tags":[
        "dentist"
    ],
    "wof:name":"Affordable Dentures",
    "wof:placetype":"venue"
},
  "geometry": {"coordinates":[-89.94766,35.128359],"type":"Point"}
}