{
  "type": "Feature",
  "properties": {
    "addr:full":"725 Milk Plant Rd Sparta TN 38583",
    "addr:housenumber":"725",
    "addr:postcode":"38583",
    "addr:street":"Milk Plant Rd",
    "iso:country":"US",
    "sg:address":"725 Milk Plant Rd",
    "sg:city":"Sparta",
    "sg:classifiers":[
        {
            "category":"Home & Garden",
            "subcategory":"Garden Supply",
            "type":"Retail Goods"
        }
    ],
    "sg:phone":"+1 931 761 3456",
    "sg:postcode":"38583",
    "sg:province":"TN",
    "sg:tags":[
        "nurseryman"
    ],
    "wof:name":"White County Nursery",
    "wof:placetype":"venue"
},
  "geometry": {"coordinates":[-85.52864599999999,36.010606],"type":"Point"}
}