{
  "type": "Feature",
  "properties": {
    "iso:country":"US",
    "sg:address":"206 Tremont St",
    "sg:city":"Chattanooga",
    "sg:classifiers":[
        {
            "category":"Shopping",
            "subcategory":"Florist",
            "type":"Retail Goods"
        }
    ],
    "sg:phone":"+1 423 756 8603",
    "sg:postcode":"37405",
    "sg:province":"TN",
    "sg:website":"www.flowersbygilandcurt.com",
    "wof:name":"Gil & Curt's Flowers",
    "wof:placetype":"venue"
},
  "geometry": {"coordinates":[-85.30366600000001,35.062903],"type":"Point"}
}