{
  "type": "Feature",
  "properties": {
    "iso:country":"US",
    "sg:address":"400 Bowling Ave",
    "sg:city":"Nashville",
    "sg:classifiers":[
        {
            "category":"Shopping",
            "subcategory":"Florist",
            "type":"Retail Goods"
        }
    ],
    "sg:phone":"+1 615 297 2296",
    "sg:postcode":"37205",
    "sg:province":"TN",
    "wof:name":"Nashville Foliage",
    "wof:placetype":"venue"
},
  "geometry": {"coordinates":[-86.82628200000001,36.127227],"type":"Point"}
}