{
  "type": "Feature",
  "properties": {
    "iso:country":"US",
    "sg:address":"320 E Market St",
    "sg:city":"Bolivar",
    "sg:classifiers":[
        {
            "category":"Food & Beverages",
            "subcategory":"Groceries & Convenience Stores",
            "type":"Retail Goods"
        }
    ],
    "sg:phone":"+1 731 658 3189",
    "sg:postcode":"38008",
    "sg:province":"TN",
    "sg:tags":[
        "grocer"
    ],
    "wof:name":"Eastside Market",
    "wof:placetype":"venue"
},
  "geometry": {"coordinates":[-88.98392200000001,35.256083],"type":"Point"}
}