{
  "type": "Feature",
  "properties": {
    "addr:full":"9009 State Rte 111 Byrdstown TN 38549",
    "addr:housenumber":"9009",
    "addr:postcode":"38549",
    "addr:street":"State Rte 111",
    "iso:country":"US",
    "sg:address":"9009 State Rte 111",
    "sg:city":"Byrdstown",
    "sg:classifiers":[
        {
            "category":"Professional",
            "subcategory":"Accounting & Tax Preparation",
            "type":"Services"
        }
    ],
    "sg:phone":"+1 931 864 8231",
    "sg:postcode":"38549",
    "sg:province":"TN",
    "sg:tags":[
        "return",
        "filing"
    ],
    "wof:name":"Byrdstown Tax Svc",
    "wof:placetype":"venue"
},
  "geometry": {"coordinates":[-85.08663799999999,36.621576],"type":"Point"}
}