{
  "type": "Feature",
  "properties": {
    "iso:country":"US",
    "sg:address":"5378 Farm Ridge Dr",
    "sg:city":"Memphis",
    "sg:classifiers":[
        {
            "category":"Professional",
            "subcategory":"Computer Services",
            "type":"Services"
        }
    ],
    "sg:phone":"+1 901 292 3467",
    "sg:postcode":"38141",
    "sg:province":"TN",
    "wof:name":"Computer Network Specialists",
    "wof:placetype":"venue"
},
  "geometry": {"coordinates":[-89.85111499999999,35.002861],"type":"Point"}
}