{
  "type": "Feature",
  "properties": {
    "addr:full":"1268 Douglas Cove Rd Mc Minnville TN 37110",
    "addr:housenumber":"1268",
    "addr:postcode":"37110",
    "addr:street":"Douglas Cove Rd",
    "iso:country":"US",
    "sg:address":"1268 Douglas Cove Rd",
    "sg:city":"Mc Minnville",
    "sg:classifiers":[
        {
            "category":"Professional",
            "type":"Services"
        }
    ],
    "sg:phone":"+1 931 668 9749",
    "sg:postcode":"37110",
    "sg:province":"TN",
    "wof:name":"Buford Ayers",
    "wof:placetype":"venue"
},
  "geometry": {"coordinates":[-85.624888,35.694833],"type":"Point"}
}