{
  "type": "Feature",
  "properties": {
    "iso:country":"US",
    "sg:address":"125 Cedar St",
    "sg:city":"Norris",
    "sg:classifiers":[
        {
            "category":"Government",
            "subcategory":"Office",
            "type":"Public Place"
        }
    ],
    "sg:phone":"+1 865 494 0351",
    "sg:postcode":"37874",
    "sg:province":"TN",
    "sg:tags":[
        "village"
    ],
    "wof:name":"Norris Public Svc Building",
    "wof:placetype":"venue"
},
  "geometry": {"coordinates":[-84.446122,35.602973],"type":"Point"}
}