{
  "type": "Feature",
  "properties": {
    "iso:country":"US",
    "sg:address":"4709 Illinois Ave",
    "sg:city":"Nashville",
    "sg:classifiers":[
        {
            "category":"Building & Trades",
            "subcategory":"Construction",
            "type":"Services"
        }
    ],
    "sg:phone":"+1 615 582 1571",
    "sg:postcode":"37209",
    "sg:province":"TN",
    "sg:tags":[
        "painter"
    ],
    "wof:name":"Nestor's Painting",
    "wof:placetype":"venue"
},
  "geometry": {"coordinates":[-86.84492,36.157729],"type":"Point"}
}