{
  "type": "Feature",
  "properties": {
    "iso:country":"US",
    "sg:address":"103 Hillwood Dr",
    "sg:city":"Hendersonville",
    "sg:classifiers":[
        {
            "category":"Building & Trades",
            "subcategory":"Construction",
            "type":"Services"
        }
    ],
    "sg:phone":"+1 615 264 0509",
    "sg:postcode":"37075",
    "sg:province":"TN",
    "wof:name":"Data Connection",
    "wof:placetype":"venue"
},
  "geometry": {"coordinates":[-86.627506,36.323855],"type":"Point"}
}