{
  "type": "Feature",
  "properties": {
    "iso:country":"US",
    "sg:address":"5512 Ringgold Rd",
    "sg:city":"Chattanooga",
    "sg:classifiers":[
        {
            "category":"Shopping",
            "subcategory":"Computers & Home Electronics",
            "type":"Retail Goods"
        }
    ],
    "sg:phone":"+1 423 510 8445",
    "sg:postcode":"37412",
    "sg:province":"TN",
    "sg:tags":[
        "software"
    ],
    "wof:name":"Accounting Software Pros Inc",
    "wof:placetype":"venue"
},
  "geometry": {"coordinates":[-85.227256,34.992447],"type":"Point"}
}