{
  "type": "Feature",
  "properties": {
    "iso:country":"US",
    "sg:address":"3951 Homewood Rd",
    "sg:city":"Memphis",
    "sg:classifiers":[
        {
            "category":"Freight",
            "type":"Transportation"
        }
    ],
    "sg:phone":"+1 901 375 4558",
    "sg:postcode":"38118",
    "sg:province":"TN",
    "sg:tags":[
        "operator",
        "trucking"
    ],
    "wof:name":"PTL",
    "wof:placetype":"venue"
},
  "geometry": {"coordinates":[-89.92574999999999,35.040683],"type":"Point"}
}