{
  "type": "Feature",
  "properties": {
    "addr:full":"214 W Jackson Ave Knoxville TN 37902",
    "addr:housenumber":"214",
    "addr:postcode":"37902",
    "addr:street":"W Jackson Ave",
    "iso:country":"US",
    "sg:address":"214 W Jackson Ave",
    "sg:city":"Knoxville",
    "sg:classifiers":[
        {
            "category":"Restaurant",
            "type":"Food & Drink"
        }
    ],
    "sg:phone":"+1 865 522 2178",
    "sg:postcode":"37902",
    "sg:province":"TN",
    "wof:name":"Lord Lindsey",
    "wof:placetype":"venue"
},
  "geometry": {"coordinates":[-83.920588,35.968872],"type":"Point"}
}