{
  "type": "Feature",
  "properties": {
    "addr:full":"322 Grinders Creek Rd Hohenwald TN 38462",
    "addr:housenumber":"322",
    "addr:postcode":"38462",
    "addr:street":"Grinders Creek Rd",
    "iso:country":"US",
    "sg:address":"322 Grinders Creek Rd",
    "sg:city":"Hohenwald",
    "sg:classifiers":[
        {
            "category":"Wholesale",
            "subcategory":"Construction Materials",
            "type":"Manufacturing & Wholesale Goods"
        }
    ],
    "sg:phone":"+1 931 796 7776",
    "sg:postcode":"38462",
    "sg:province":"TN",
    "sg:tags":[
        "fence"
    ],
    "wof:name":"Ace Fence & Ornamental Iron",
    "wof:placetype":"venue"
},
  "geometry": {"coordinates":[-87.494506,35.510383],"type":"Point"}
}