{
  "type": "Feature",
  "properties": {
    "addr:full":"3200 Park Ave Memphis TN 38111",
    "addr:housenumber":"3200",
    "addr:postcode":"38111",
    "addr:street":"Park Ave",
    "iso:country":"US",
    "sg:address":"3200 Park Ave",
    "sg:city":"Memphis",
    "sg:classifiers":[
        {
            "category":"Personal",
            "subcategory":"Beauty Salon",
            "type":"Services"
        }
    ],
    "sg:phone":"+1 901 458 3964",
    "sg:postcode":"38111",
    "sg:province":"TN",
    "sg:tags":[
        "shop"
    ],
    "wof:name":"Mirror's Up By Maxine",
    "wof:placetype":"venue"
},
  "geometry": {"coordinates":[-89.95428200000001,35.107805],"type":"Point"}
}