{
  "type": "Feature",
  "properties": {
    "iso:country":"US",
    "sg:address":"6636 Shallowford Rd",
    "sg:city":"Chattanooga",
    "sg:classifiers":[
        {
            "category":"Professional",
            "type":"Services"
        }
    ],
    "sg:phone":"+1 423 855 0303",
    "sg:postcode":"37421",
    "sg:province":"TN",
    "wof:name":"Unicorn Meadows Art Studio",
    "wof:placetype":"venue"
},
  "geometry": {"coordinates":[-85.169055,35.047215],"type":"Point"}
}