{
  "type": "Feature",
  "properties": {
    "addr:full":"2100 W End Ave Nashville TN 37203",
    "addr:housenumber":"2100",
    "addr:postcode":"37203",
    "addr:street":"W End Ave",
    "iso:country":"US",
    "sg:address":"2100 W End Ave",
    "sg:city":"Nashville",
    "sg:classifiers":[
        {
            "category":"Restaurant",
            "type":"Food & Drink"
        }
    ],
    "sg:menulink":"http://www.allmenus.com/tn/nashville/14345-ruths-chris-steak-house/menu/",
    "sg:phone":"+1 615 320 0163",
    "sg:postcode":"37203",
    "sg:province":"TN",
    "sg:tags":[
        "american",
        "steakhouse"
    ],
    "wof:name":"Ruth's Chris Steak House",
    "wof:placetype":"venue"
},
  "geometry": {"coordinates":[-86.80156100000001,36.150441],"type":"Point"}
}