{
  "type": "Feature",
  "properties": {
    "iso:country":"US",
    "sg:address":"494 N Hollywood St",
    "sg:city":"Memphis",
    "sg:classifiers":[
        {
            "category":"Manufacturing",
            "subcategory":"Building Materials",
            "type":"Manufacturing & Wholesale Goods"
        }
    ],
    "sg:phone":"+1 901 323 1622",
    "sg:postcode":"38112",
    "sg:province":"TN",
    "sg:tags":[
        "mfg",
        "drape",
        "piece"
    ],
    "wof:name":"J & L Shutters Inc",
    "wof:placetype":"venue"
},
  "geometry": {"coordinates":[-89.977187,35.148203],"type":"Point"}
}