{
  "type": "Feature",
  "properties": {
    "iso:country":"US",
    "sg:address":"6257 E Brainerd Rd",
    "sg:city":"Chattanooga",
    "sg:classifiers":[
        {
            "category":"Real Estate",
            "subcategory":"Real Estate Agent",
            "type":"Services"
        }
    ],
    "sg:phone":"+1 423 892 0051",
    "sg:postcode":"37421",
    "sg:province":"TN",
    "wof:name":"Donald L Tindell Inc",
    "wof:placetype":"venue"
},
  "geometry": {"coordinates":[-85.19681,35.017217],"type":"Point"}
}