{
  "type": "Feature",
  "properties": {
    "iso:country":"US",
    "sg:address":"903 W Broadway Ave",
    "sg:city":"Maryville",
    "sg:classifiers":[
        {
            "category":"Insurance",
            "subcategory":"Insurance Agent",
            "type":"Services"
        }
    ],
    "sg:phone":"+1 865 983 3872",
    "sg:postcode":"37801",
    "sg:province":"TN",
    "wof:name":"Blackwood Insurance Inc",
    "wof:placetype":"venue"
},
  "geometry": {"coordinates":[-83.98028600000001,35.748296],"type":"Point"}
}