{
  "type": "Feature",
  "properties": {
    "addr:full":"114 Union Valley Rd Oak Ridge TN 37830",
    "addr:housenumber":"114",
    "addr:postcode":"37830",
    "addr:street":"Union Valley Rd",
    "iso:country":"US",
    "sg:address":"114 Union Valley Rd",
    "sg:city":"Oak Ridge",
    "sg:classifiers":[
        {
            "category":"Manufacturing",
            "subcategory":"Tools & Machinery",
            "type":"Manufacturing & Wholesale Goods"
        }
    ],
    "sg:phone":"+1 865 483 0228",
    "sg:postcode":"37830",
    "sg:province":"TN",
    "sg:tags":[
        "robot"
    ],
    "wof:name":"Northrop Grumman Remotec",
    "wof:placetype":"venue"
},
  "geometry": {"coordinates":[-84.226033,35.999513],"type":"Point"}
}