{
  "type": "Feature",
  "properties": {
    "iso:country":"US",
    "sg:address":"810 S Washington St",
    "sg:city":"Tullahoma",
    "sg:classifiers":[
        {
            "category":"Manufacturing",
            "subcategory":"Paper Products",
            "type":"Manufacturing & Wholesale Goods"
        }
    ],
    "sg:phone":"+1 931 455 9585",
    "sg:postcode":"37388",
    "sg:province":"TN",
    "sg:tags":[
        "box"
    ],
    "sg:website":"www.linpac.com",
    "wof:name":"LIN Pac Displays Inc",
    "wof:placetype":"venue"
},
  "geometry": {"coordinates":[-86.200981,35.355938],"type":"Point"}
}