{
  "type": "Feature",
  "properties": {
    "addr:full":"500 N Sycamore St Elizabethton TN 37643",
    "addr:housenumber":"500",
    "addr:postcode":"37643",
    "addr:street":"N Sycamore St",
    "iso:country":"US",
    "sg:address":"500 N Sycamore St",
    "sg:city":"Elizabethton",
    "sg:classifiers":[
        {
            "category":"Shopping",
            "subcategory":"Discount & Variety Stores",
            "type":"Retail Goods"
        },
        {
            "category":"Shopping",
            "subcategory":"Department Store",
            "type":"Retail Goods"
        }
    ],
    "sg:phone":"+1 423 543 4749",
    "sg:postcode":"37643",
    "sg:province":"TN",
    "wof:name":"Family Dollar Stores",
    "wof:placetype":"venue"
},
  "geometry": {"coordinates":[-82.21564600000001,36.352425],"type":"Point"}
}