{
  "type": "Feature",
  "properties": {
    "addr:full":"6835 Southknoll Ave Millington TN 38053",
    "addr:housenumber":"6835",
    "addr:postcode":"38053",
    "addr:street":"Southknoll Ave",
    "iso:country":"US",
    "sg:address":"6835 Southknoll Ave",
    "sg:city":"Millington",
    "sg:classifiers":[
        {
            "category":"Retail",
            "subcategory":"Auto Repair",
            "type":"Services"
        }
    ],
    "sg:phone":"+1 901 857 6005",
    "sg:postcode":"38053",
    "sg:province":"TN",
    "sg:tags":[
        "glass",
        "replacement"
    ],
    "wof:name":"Smart Auto Glass",
    "wof:placetype":"venue"
},
  "geometry": {"coordinates":[-89.835615,35.329288],"type":"Point"}
}