{
  "type": "Feature",
  "properties": {
    "addr:full":"2600 Thousand Oaks Blvd Memphis TN 38118",
    "addr:housenumber":"2600",
    "addr:postcode":"38118",
    "addr:street":"Thousand Oaks Blvd",
    "iso:country":"US",
    "sg:address":"2600 Thousand Oaks Blvd",
    "sg:city":"Memphis",
    "sg:classifiers":[
        {
            "category":"Insurance",
            "subcategory":"Life Insurance",
            "type":"Services"
        }
    ],
    "sg:phone":"+1 901 369 7880",
    "sg:postcode":"38118",
    "sg:province":"TN",
    "sg:tags":[
        "carrier"
    ],
    "wof:name":"Provident",
    "wof:placetype":"venue"
},
  "geometry": {"coordinates":[-89.90193499999999,35.076747],"type":"Point"}
}