{
  "type": "Feature",
  "properties": {
    "addr:full":"5370 Old Rome Pike Lebanon TN 37087",
    "addr:housenumber":"5370",
    "addr:postcode":"37087",
    "addr:street":"Old Rome Pike",
    "iso:country":"US",
    "sg:address":"5370 Old Rome Pike",
    "sg:city":"Lebanon",
    "sg:classifiers":[
        {
            "category":"Building & Trades",
            "subcategory":"Construction",
            "type":"Services"
        }
    ],
    "sg:phone":"+1 615 453 9479",
    "sg:postcode":"37087",
    "sg:province":"TN",
    "sg:tags":[
        "contractor"
    ],
    "wof:name":"Hucks Siding",
    "wof:placetype":"venue"
},
  "geometry": {"coordinates":[-86.127319,36.252011],"type":"Point"}
}