{
  "type": "Feature",
  "properties": {
    "iso:country":"US",
    "sg:address":"2101 Brimstone Creek Rd",
    "sg:city":"Moss",
    "sg:classifiers":[
        {
            "category":"Building & Trades",
            "subcategory":"Construction",
            "type":"Services"
        }
    ],
    "sg:phone":"+1 931 258 3090",
    "sg:postcode":"38575",
    "sg:province":"TN",
    "sg:tags":[
        "utility",
        "contractor"
    ],
    "wof:name":"Twin States Utilities",
    "wof:placetype":"venue"
},
  "geometry": {"coordinates":[-85.65543099999999,36.583647],"type":"Point"}
}