{
  "type": "Feature",
  "properties": {
    "iso:country":"US",
    "sg:address":"1176 Bethel Rd",
    "sg:city":"Pulaski",
    "sg:classifiers":[
        {
            "category":"Food & Beverages",
            "subcategory":"Groceries & Convenience Stores",
            "type":"Retail Goods"
        }
    ],
    "sg:phone":"+1 931 363 2097",
    "sg:postcode":"38478",
    "sg:province":"TN",
    "wof:name":"Winners Circle Market",
    "wof:placetype":"venue"
},
  "geometry": {"coordinates":[-87.048676,35.152466],"type":"Point"}
}