{
  "type": "Feature",
  "properties": {
    "iso:country":"US",
    "sg:address":"790 Chestnut Mountain Rd",
    "sg:city":"Reliance",
    "sg:classifiers":[
        {
            "category":"Autos & Motor Vehicles",
            "subcategory":"Automobile Sales",
            "type":"Retail Goods"
        }
    ],
    "sg:phone":"+1 423 338 5360",
    "sg:postcode":"37369",
    "sg:province":"TN",
    "wof:name":"Wilcoxon Auto Sales",
    "wof:placetype":"venue"
},
  "geometry": {"coordinates":[-84.501733,35.122367],"type":"Point"}
}