{
  "type": "Feature",
  "properties": {
    "addr:full":"1024 Shawnee Rd Madison TN 37115",
    "addr:housenumber":"1024",
    "addr:postcode":"37115",
    "addr:street":"Shawnee Rd",
    "iso:country":"US",
    "sg:address":"1024 Shawnee Rd",
    "sg:city":"Madison",
    "sg:classifiers":[
        {
            "category":"Professional",
            "subcategory":"Management & Consulting",
            "type":"Services"
        }
    ],
    "sg:phone":"+1 615 868 6527",
    "sg:postcode":"37115",
    "sg:province":"TN",
    "sg:tags":[
        "consultant"
    ],
    "wof:name":"Third World Enterprises",
    "wof:placetype":"venue"
},
  "geometry": {"coordinates":[-86.672246,36.252043],"type":"Point"}
}