{
  "type": "Feature",
  "properties": {
    "addr:full":"329 Warfield Blvd Ct Clarksville TN 37043",
    "addr:housenumber":"329",
    "addr:postcode":"37043",
    "addr:street":"Warfield Blvd Ct",
    "iso:country":"US",
    "sg:address":"329 Warfield Blvd Ct",
    "sg:city":"Clarksville",
    "sg:classifiers":[
        {
            "category":"Health Services",
            "subcategory":"Chiropractor",
            "type":"Services"
        }
    ],
    "sg:phone":"+1 931 648 3000",
    "sg:postcode":"37043",
    "sg:province":"TN",
    "sg:website":"www.medsr.com",
    "wof:name":"United Chiropractic Clinic",
    "wof:placetype":"venue"
},
  "geometry": {"coordinates":[-87.285836,36.566674],"type":"Point"}
}