{
  "type": "Feature",
  "properties": {
    "iso:country":"US",
    "sg:address":"1849 US Hwy 45 Byp",
    "sg:city":"Jackson",
    "sg:classifiers":[
        {
            "category":"Travel",
            "subcategory":"Hotels & Motels",
            "type":"Entertainment"
        }
    ],
    "sg:phone":"+1 731 668 4222",
    "sg:postcode":"38305",
    "sg:province":"TN",
    "wof:name":"Old Hickory Inn",
    "wof:placetype":"venue"
},
  "geometry": {"coordinates":[-88.853483,35.659044],"type":"Point"}
}