{
  "type": "Feature",
  "properties": {
    "iso:country":"US",
    "sg:address":"103 Polo Dr",
    "sg:city":"Blountville",
    "sg:classifiers":[
        {
            "category":"Organizations",
            "subcategory":"Religious Organization",
            "type":"Services"
        }
    ],
    "sg:phone":"+1 423 323 1715",
    "sg:postcode":"37617",
    "sg:province":"TN",
    "sg:tags":[
        "a",
        "as",
        "specialized",
        "operates"
    ],
    "wof:name":"Church God Svnth Day Adventist",
    "wof:placetype":"venue"
},
  "geometry": {"coordinates":[-82.342731,36.533735],"type":"Point"}
}