{
  "type": "Feature",
  "properties": {
    "iso:country":"US",
    "sg:address":"125 N Maple St",
    "sg:city":"Murfreesboro",
    "sg:classifiers":[
        {
            "category":"Restaurant",
            "type":"Food & Drink"
        }
    ],
    "sg:phone":"+1 615 849 8881",
    "sg:postcode":"37130",
    "sg:province":"TN",
    "sg:tags":[
        "italian"
    ],
    "wof:name":"Marinas On The Square Inc",
    "wof:placetype":"venue"
},
  "geometry": {"coordinates":[-86.392686,35.846254],"type":"Point"}
}