{
  "type": "Feature",
  "properties": {
    "addr:full":"262 W Park Ct Smithville TN 37129",
    "addr:housenumber":"262",
    "addr:postcode":"37129",
    "addr:street":"W Park Ct",
    "iso:country":"US",
    "sg:address":"262 W Park Ct",
    "sg:city":"Smithville",
    "sg:classifiers":[
        {
            "category":"Wholesale",
            "subcategory":"Machinery & Supplies",
            "type":"Manufacturing & Wholesale Goods"
        }
    ],
    "sg:phone":"+1 615 890 5216",
    "sg:postcode":"37129",
    "sg:province":"TN",
    "sg:tags":[
        "equipment",
        "industrial"
    ],
    "wof:name":"Ceco",
    "wof:placetype":"venue"
},
  "geometry": {"coordinates":[-85.697779,35.935553],"type":"Point"}
}