{
  "type": "Feature",
  "properties": {
    "addr:full":"110 E Proffitt St Cookeville TN 38501",
    "addr:housenumber":"110",
    "addr:postcode":"38501",
    "addr:street":"E Proffitt St",
    "iso:country":"US",
    "sg:address":"110 E Proffitt St",
    "sg:city":"Cookeville",
    "sg:classifiers":[
        {
            "category":"Food & Beverages",
            "subcategory":"Fruits & Vegetables",
            "type":"Retail Goods"
        }
    ],
    "sg:phone":"+1 931 528 5438",
    "sg:postcode":"38501",
    "sg:province":"TN",
    "wof:name":"Salads & More",
    "wof:placetype":"venue"
},
  "geometry": {"coordinates":[-85.503753,36.159159],"type":"Point"}
}