{
  "type": "Feature",
  "properties": {
    "addr:full":"124 Dale Ave Knoxville TN 37921",
    "addr:housenumber":"124",
    "addr:postcode":"37921",
    "addr:street":"Dale Ave",
    "iso:country":"US",
    "sg:address":"124 Dale Ave",
    "sg:city":"Knoxville",
    "sg:classifiers":[
        {
            "category":"Restaurant",
            "type":"Food & Drink"
        }
    ],
    "sg:phone":"+1 865 546 0383",
    "sg:postcode":"37921",
    "sg:province":"TN",
    "sg:tags":[
        "eating"
    ],
    "wof:name":"Louises Country Kitchen",
    "wof:placetype":"venue"
},
  "geometry": {"coordinates":[-83.932118,35.964521],"type":"Point"}
}