{
  "type": "Feature",
  "properties": {
    "iso:country":"US",
    "sg:address":"3202 State Hwy 107",
    "sg:city":"Chuckey",
    "sg:classifiers":[
        {
            "category":"Manufacturing",
            "subcategory":"Food",
            "type":"Manufacturing & Wholesale Goods"
        }
    ],
    "sg:phone":"+1 423 257 4712",
    "sg:postcode":"37641",
    "sg:province":"TN",
    "sg:tags":[
        "building",
        "preparation",
        "construction",
        "industrial",
        "mfg"
    ],
    "wof:name":"Moody Dunbar Inc",
    "wof:placetype":"venue"
},
  "geometry": {"coordinates":[-82.63061399999999,36.158686],"type":"Point"}
}