{
  "type": "Feature",
  "properties": {
    "addr:full":"4003 Clarksville Pike Nashville TN 37218",
    "addr:housenumber":"4003",
    "addr:postcode":"37218",
    "addr:street":"Clarksville Pike",
    "iso:country":"US",
    "sg:address":"4003 Clarksville Pike",
    "sg:city":"Nashville",
    "sg:classifiers":[
        {
            "category":"Personal",
            "subcategory":"Beauty Salon",
            "type":"Services"
        }
    ],
    "sg:phone":"+1 615 876 4555",
    "sg:postcode":"37218",
    "sg:province":"TN",
    "sg:tags":[
        "shop"
    ],
    "wof:name":"H & S Prime Time Barber Shop",
    "wof:placetype":"venue"
},
  "geometry": {"coordinates":[-86.838689,36.212297],"type":"Point"}
}