{
  "type": "Feature",
  "properties": {
    "addr:full":"1112 N Main Ave Erwin TN 37650",
    "addr:housenumber":"1112",
    "addr:postcode":"37650",
    "addr:street":"N Main Ave",
    "iso:country":"US",
    "sg:address":"1112 N Main Ave",
    "sg:city":"Erwin",
    "sg:classifiers":[
        {
            "category":"Restaurant",
            "type":"Food & Drink"
        }
    ],
    "sg:phone":"+1 423 743 9755",
    "sg:postcode":"37650",
    "sg:province":"TN",
    "wof:name":"Backwoods B-B-Q & Ribs",
    "wof:placetype":"venue"
},
  "geometry": {"coordinates":[-82.40460899999999,36.157455],"type":"Point"}
}