{
  "type": "Feature",
  "properties": {
    "addr:full":"50 Music Sq E Nashville TN 37203",
    "addr:housenumber":"50",
    "addr:postcode":"37203",
    "addr:street":"Music Sq E",
    "iso:country":"US",
    "sg:address":"50 Music Sq E",
    "sg:city":"Nashville",
    "sg:classifiers":[
        {
            "category":"Restaurant",
            "type":"Food & Drink"
        }
    ],
    "sg:phone":"+1 615 740 1897",
    "sg:postcode":"37203",
    "sg:province":"TN",
    "sg:tags":[
        "shop",
        "coffee"
    ],
    "wof:name":"Perky's",
    "wof:placetype":"venue"
},
  "geometry": {"coordinates":[-86.792526,36.14675],"type":"Point"}
}