{
  "type": "Feature",
  "properties": {
    "iso:country":"US",
    "sg:address":"1488 Anthony Way",
    "sg:city":"Mount Juliet",
    "sg:classifiers":[
        {
            "category":"Building & Trades",
            "subcategory":"Construction",
            "type":"Services"
        }
    ],
    "sg:phone":"+1 615 773 9213",
    "sg:postcode":"37122",
    "sg:province":"TN",
    "sg:tags":[
        "contractor"
    ],
    "wof:name":"Bobby Rankin Drywall Co",
    "wof:placetype":"venue"
},
  "geometry": {"coordinates":[-86.551012,36.174174],"type":"Point"}
}