{
  "type": "Feature",
  "properties": {
    "addr:full":"3916 Boyds Bridge Pike Knoxville TN 37914",
    "addr:housenumber":"3916",
    "addr:postcode":"37914",
    "addr:street":"Boyds Bridge Pike",
    "iso:country":"US",
    "sg:address":"3916 Boyds Bridge Pike",
    "sg:city":"Knoxville",
    "sg:classifiers":[
        {
            "category":"Health Services",
            "subcategory":"Hospital",
            "type":"Services"
        }
    ],
    "sg:phone":"+1 865 524 1500",
    "sg:postcode":"37914",
    "sg:province":"TN",
    "wof:name":"Holston Health & Rehab Ctr",
    "wof:placetype":"venue"
},
  "geometry": {"coordinates":[-83.858394,35.984626],"type":"Point"}
}