{
  "type": "Feature",
  "properties": {
    "iso:country":"US",
    "sg:address":"144 River Bend Dr",
    "sg:city":"Sevierville",
    "sg:classifiers":[
        {
            "category":"Manufacturing",
            "subcategory":"Tools & Machinery",
            "type":"Manufacturing & Wholesale Goods"
        }
    ],
    "sg:phone":"+1 865 774 8364",
    "sg:postcode":"37876",
    "sg:province":"TN",
    "sg:tags":[
        "lighting",
        "fixture",
        "mfg"
    ],
    "wof:name":"Quality Solutions Group  LLC",
    "wof:placetype":"venue"
},
  "geometry": {"coordinates":[-83.498188,35.867081],"type":"Point"}
}