{
  "type": "Feature",
  "properties": {
    "iso:country":"US",
    "sg:address":"7107 Old Millington Rd",
    "sg:city":"Millington",
    "sg:classifiers":[
        {
            "category":"Utilities",
            "subcategory":"Refuse",
            "type":"Services"
        }
    ],
    "sg:phone":"+1 901 794 3800",
    "sg:postcode":"38053",
    "sg:province":"TN",
    "sg:tags":[
        "landfill"
    ],
    "wof:name":"Allied Waste",
    "wof:placetype":"venue"
},
  "geometry": {"coordinates":[-89.938852,35.320486],"type":"Point"}
}