{
  "type": "Feature",
  "properties": {
    "addr:full":"202 Island Dr Hendersonville TN 37075",
    "addr:housenumber":"202",
    "addr:postcode":"37075",
    "addr:street":"Island Dr",
    "iso:country":"US",
    "sg:address":"202 Island Dr",
    "sg:city":"Hendersonville",
    "sg:classifiers":[
        {
            "category":"Building & Trades",
            "subcategory":"Cleaning & Sanitation",
            "type":"Services"
        }
    ],
    "sg:phone":"+1 615 822 1035",
    "sg:postcode":"37075",
    "sg:province":"TN",
    "sg:tags":[
        "maintenance",
        "contractor"
    ],
    "wof:name":"Hendersonville Chimney Sweep",
    "wof:placetype":"venue"
},
  "geometry": {"coordinates":[-86.59237400000001,36.283287],"type":"Point"}
}