{
  "type": "Feature",
  "properties": {
    "addr:full":"940 Walker School Rd Maryville TN 37803",
    "addr:housenumber":"940",
    "addr:postcode":"37803",
    "addr:street":"Walker School Rd",
    "iso:country":"US",
    "sg:address":"940 Walker School Rd",
    "sg:city":"Maryville",
    "sg:classifiers":[
        {
            "category":"Building & Trades",
            "subcategory":"Construction",
            "type":"Services"
        }
    ],
    "sg:phone":"+1 865 984 3780",
    "sg:postcode":"37803",
    "sg:province":"TN",
    "sg:tags":[
        "contractor"
    ],
    "wof:name":"Bob Hearon Builders",
    "wof:placetype":"venue"
},
  "geometry": {"coordinates":[-84.044692,35.663499],"type":"Point"}
}