{
  "type": "Feature",
  "properties": {
    "addr:full":"840 S Highland St Memphis TN 38111",
    "addr:housenumber":"840",
    "addr:postcode":"38111",
    "addr:street":"S Highland St",
    "iso:country":"US",
    "sg:address":"840 S Highland St",
    "sg:city":"Memphis",
    "sg:classifiers":[
        {
            "category":"Organizations",
            "subcategory":"Religious Organization",
            "type":"Services"
        }
    ],
    "sg:phone":"+1 901 452 6153",
    "sg:postcode":"38111",
    "sg:province":"TN",
    "wof:name":"Nichiren Shoshu of America",
    "wof:placetype":"venue"
},
  "geometry": {"coordinates":[-89.945955,35.108223],"type":"Point"}
}