{
  "type": "Feature",
  "properties": {
    "iso:country":"US",
    "sg:address":"588 Waldron Rd",
    "sg:city":"La Vergne",
    "sg:classifiers":[
        {
            "category":"Autos & Motor Vehicles",
            "subcategory":"Fuel & Gas Station",
            "type":"Retail Goods"
        }
    ],
    "sg:phone":"+1 615 793 6680",
    "sg:postcode":"37086",
    "sg:province":"TN",
    "sg:tags":[
        "convenience",
        "gasoline",
        "store"
    ],
    "wof:name":"Mapco Express",
    "wof:placetype":"venue"
},
  "geometry": {"coordinates":[-86.584506,36.015915],"type":"Point"}
}