{
  "type": "Feature",
  "properties": {
    "addr:full":"15554 Old Hickory Blvd Nashville TN 37211",
    "addr:housenumber":"15554",
    "addr:postcode":"37211",
    "addr:street":"Old Hickory Blvd",
    "iso:country":"US",
    "sg:address":"15554 Old Hickory Blvd",
    "sg:city":"Nashville",
    "sg:classifiers":[
        {
            "category":"Retail",
            "subcategory":"Laundry & Dry Cleaning",
            "type":"Services"
        }
    ],
    "sg:phone":"+1 615 833 3262",
    "sg:postcode":"37211",
    "sg:province":"TN",
    "sg:tags":[
        "cleaners"
    ],
    "wof:name":"Nippers Corner Cleaners",
    "wof:placetype":"venue"
},
  "geometry": {"coordinates":[-86.742126,36.039986],"type":"Point"}
}