{
  "type": "Feature",
  "properties": {
    "addr:full":"808 Cotton Grove Rd Jackson TN 38305",
    "addr:housenumber":"808",
    "addr:postcode":"38305",
    "addr:street":"Cotton Grove Rd",
    "iso:country":"US",
    "sg:address":"808 Cotton Grove Rd",
    "sg:city":"Jackson",
    "sg:classifiers":[
        {
            "category":"Building & Trades",
            "subcategory":"Construction",
            "type":"Services"
        }
    ],
    "sg:phone":"+1 731 427 2171",
    "sg:postcode":"38305",
    "sg:province":"TN",
    "sg:tags":[
        "contractor"
    ],
    "wof:name":"Jackie Smythe Masonry",
    "wof:placetype":"venue"
},
  "geometry": {"coordinates":[-88.696866,35.664601],"type":"Point"}
}