{
  "type": "Feature",
  "properties": {
    "addr:full":"1104 Cedar Grove Rd Iron City TN 38463",
    "addr:housenumber":"1104",
    "addr:postcode":"38463",
    "addr:street":"Cedar Grove Rd",
    "iso:country":"US",
    "sg:address":"1104 Cedar Grove Rd",
    "sg:city":"Iron City",
    "sg:classifiers":[
        {
            "category":"Retail",
            "subcategory":"Auto Repair",
            "type":"Services"
        }
    ],
    "sg:phone":"+1 931 724 4567",
    "sg:postcode":"38463",
    "sg:province":"TN",
    "sg:tags":[
        "general",
        "supply"
    ],
    "wof:name":"Hunts Garage",
    "wof:placetype":"venue"
},
  "geometry": {"coordinates":[-87.637173,35.068662],"type":"Point"}
}