{
  "type": "Feature",
  "properties": {
    "addr:full":"1868 Newport Hwy Sevierville TN 37876",
    "addr:housenumber":"1868",
    "addr:postcode":"37876",
    "addr:street":"Newport Hwy",
    "iso:country":"US",
    "sg:address":"1868 Newport Hwy",
    "sg:city":"Sevierville",
    "sg:classifiers":[
        {
            "category":"Real Estate",
            "subcategory":"Developer",
            "type":"Services"
        }
    ],
    "sg:phone":"+1 865 428 6181",
    "sg:postcode":"37876",
    "sg:province":"TN",
    "wof:name":"White Rock Developers LLC",
    "wof:placetype":"venue"
},
  "geometry": {"coordinates":[-83.491973,35.872939],"type":"Point"}
}