{
  "type": "Feature",
  "properties": {
    "iso:country":"US",
    "sg:address":"5301 Virginia Way",
    "sg:city":"Brentwood",
    "sg:classifiers":[
        {
            "category":"Insurance",
            "subcategory":"Insurance Agent",
            "type":"Services"
        }
    ],
    "sg:phone":"+1 615 373 1621",
    "sg:postcode":"37027",
    "sg:province":"TN",
    "wof:name":"Great River Insurance Co",
    "wof:placetype":"venue"
},
  "geometry": {"coordinates":[-86.81108999999999,36.03281],"type":"Point"}
}