{
  "type": "Feature",
  "properties": {
    "addr:full":"4017 Central Pike Hermitage TN 37076",
    "addr:housenumber":"4017",
    "addr:postcode":"37076",
    "addr:street":"Central Pike",
    "iso:country":"US",
    "sg:address":"4017 Central Pike",
    "sg:city":"Hermitage",
    "sg:classifiers":[
        {
            "category":"Shopping",
            "subcategory":"Used Merchandise",
            "type":"Retail Goods"
        }
    ],
    "sg:phone":"+1 615 884 6776",
    "sg:postcode":"37076",
    "sg:province":"TN",
    "sg:tags":[
        "antique"
    ],
    "wof:name":"Farmhouse Antiques & Gifts",
    "wof:placetype":"venue"
},
  "geometry": {"coordinates":[-86.599788,36.172688],"type":"Point"}
}