{
  "type": "Feature",
  "properties": {
    "iso:country":"US",
    "sg:address":"105 W End Hts",
    "sg:city":"Lebanon",
    "sg:classifiers":[
        {
            "category":"Personal",
            "subcategory":"Beauty Salon",
            "type":"Services"
        }
    ],
    "sg:phone":"+1 615 449 7880",
    "sg:postcode":"37087",
    "sg:province":"TN",
    "wof:name":"Mojave Rock Day Spa",
    "wof:placetype":"venue"
},
  "geometry": {"coordinates":[-86.320171,36.213982],"type":"Point"}
}