{
  "type": "Feature",
  "properties": {
    "iso:country":"US",
    "sg:address":"3131 Valley Bend Rd",
    "sg:city":"Murfreesboro",
    "sg:classifiers":[
        {
            "category":"Freight",
            "type":"Transportation"
        }
    ],
    "sg:phone":"+1 615 542 6493",
    "sg:postcode":"37129",
    "sg:province":"TN",
    "sg:tags":[
        "operator",
        "trucking"
    ],
    "wof:name":"Iron Horse Transporters",
    "wof:placetype":"venue"
},
  "geometry": {"coordinates":[-86.505718,35.879915],"type":"Point"}
}