{
  "type": "Feature",
  "properties": {
    "iso:country":"US",
    "sg:address":"11 Cedar Grove Ln",
    "sg:city":"Lebanon",
    "sg:classifiers":[
        {
            "category":"Professional",
            "type":"Services"
        }
    ],
    "sg:phone":"+1 615 444 2283",
    "sg:postcode":"37087",
    "sg:province":"TN",
    "wof:name":"Ducktrail Inc",
    "wof:placetype":"venue"
},
  "geometry": {"coordinates":[-86.08496,36.264872],"type":"Point"}
}