{
  "type": "Feature",
  "properties": {
    "iso:country":"US",
    "sg:address":"1017 Nave St",
    "sg:city":"Elizabethton",
    "sg:classifiers":[
        {
            "category":"Building & Trades",
            "subcategory":"Construction",
            "type":"Services"
        }
    ],
    "sg:phone":"+1 423 543 7004",
    "sg:postcode":"37643",
    "sg:province":"TN",
    "sg:tags":[
        "insulation",
        "heat",
        "contractor"
    ],
    "wof:name":"Elizabethton Insulation",
    "wof:placetype":"venue"
},
  "geometry": {"coordinates":[-82.196819,36.336486],"type":"Point"}
}