{
  "type": "Feature",
  "properties": {
    "iso:country":"US",
    "sg:address":"421 N Watkins St",
    "sg:city":"Memphis",
    "sg:classifiers":[
        {
            "category":"Shopping",
            "subcategory":"Used Merchandise",
            "type":"Retail Goods"
        }
    ],
    "sg:phone":"+1 901 278 8965",
    "sg:postcode":"38104",
    "sg:province":"TN",
    "sg:tags":[
        "antique"
    ],
    "wof:name":"Tut-Uncommon Antiques",
    "wof:placetype":"venue"
},
  "geometry": {"coordinates":[-90.013042,35.150574],"type":"Point"}
}