{
  "type": "Feature",
  "properties": {
    "addr:full":"600 Tremont St Chattanooga TN 37405",
    "addr:housenumber":"600",
    "addr:postcode":"37405",
    "addr:street":"Tremont St",
    "iso:country":"US",
    "sg:address":"600 Tremont St",
    "sg:city":"Chattanooga",
    "sg:classifiers":[
        {
            "category":"Personal",
            "subcategory":"Beauty Salon",
            "type":"Services"
        }
    ],
    "sg:phone":"+1 423 267 3281",
    "sg:postcode":"37405",
    "sg:province":"TN",
    "sg:tags":[
        "shop"
    ],
    "wof:name":"Tremont Beauty Salon",
    "wof:placetype":"venue"
},
  "geometry": {"coordinates":[-85.29802599999999,35.068329],"type":"Point"}
}