{
  "type": "Feature",
  "properties": {
    "addr:full":"175 Patton May Rd Telford TN 37690",
    "addr:housenumber":"175",
    "addr:postcode":"37690",
    "addr:street":"Patton May Rd",
    "iso:country":"US",
    "sg:address":"175 Patton May Rd",
    "sg:city":"Telford",
    "sg:classifiers":[
        {
            "category":"Building & Trades",
            "subcategory":"Construction",
            "type":"Services"
        }
    ],
    "sg:phone":"+1 423 753 8295",
    "sg:postcode":"37690",
    "sg:province":"TN",
    "sg:tags":[
        "paper",
        "painting",
        "hanging"
    ],
    "wof:name":"Harvey H Canters Painting",
    "wof:placetype":"venue"
},
  "geometry": {"coordinates":[-82.519319,36.26199],"type":"Point"}
}