{
  "type": "Feature",
  "properties": {
    "iso:country":"US",
    "sg:address":"708 S Illinois Ave",
    "sg:city":"Oak Ridge",
    "sg:classifiers":[
        {
            "category":"Professional",
            "subcategory":"Art Services",
            "type":"Services"
        }
    ],
    "sg:phone":"+1 865 220 9920",
    "sg:postcode":"37830",
    "sg:province":"TN",
    "sg:tags":[
        "photographer",
        "photography",
        "commercial"
    ],
    "wof:name":"Tennessee Geographic Info",
    "wof:placetype":"venue"
},
  "geometry": {"coordinates":[-84.233902,36.004602],"type":"Point"}
}