{
  "type": "Feature",
  "properties": {
    "iso:country":"US",
    "sg:address":"209 S Royal Oaks Blvd",
    "sg:city":"Franklin",
    "sg:classifiers":[
        {
            "category":"Professional",
            "subcategory":"Accounting & Tax Preparation",
            "type":"Services"
        }
    ],
    "sg:phone":"+1 615 790 1216",
    "sg:postcode":"37064",
    "sg:province":"TN",
    "sg:tags":[
        "return",
        "filing"
    ],
    "wof:name":"Liberty Tax Svc",
    "wof:placetype":"venue"
},
  "geometry": {"coordinates":[-86.83019299999999,35.913467],"type":"Point"}
}