{
  "type": "Feature",
  "properties": {
    "iso:country":"US",
    "sg:address":"1641 Blackwell Rd",
    "sg:city":"Cookeville",
    "sg:classifiers":[
        {
            "category":"Building & Trades",
            "subcategory":"Landscaping Services",
            "type":"Services"
        }
    ],
    "sg:phone":"+1 931 528 5177",
    "sg:postcode":"38506",
    "sg:province":"TN",
    "sg:tags":[
        "topsoil"
    ],
    "wof:name":"Quality Soils",
    "wof:placetype":"venue"
},
  "geometry": {"coordinates":[-85.495511,36.115381],"type":"Point"}
}