{
  "type": "Feature",
  "properties": {
    "iso:country":"US",
    "sg:address":"201 Draughon Dr",
    "sg:city":"Greenbrier",
    "sg:classifiers":[
        {
            "category":"Professional",
            "subcategory":"Employment Agencies",
            "type":"Services"
        }
    ],
    "sg:phone":"+1 615 643 1300",
    "sg:postcode":"37073",
    "sg:province":"TN",
    "wof:name":"Able Nrses Rgstry Plcement Svc",
    "wof:placetype":"venue"
},
  "geometry": {"coordinates":[-86.809288,36.432321],"type":"Point"}
}