{
  "type": "Feature",
  "properties": {
    "addr:full":"714 Walker Dr Smithville TN 37166",
    "addr:housenumber":"714",
    "addr:postcode":"37166",
    "addr:street":"Walker Dr",
    "iso:country":"US",
    "sg:address":"714 Walker Dr",
    "sg:city":"Smithville",
    "sg:classifiers":[
        {
            "category":"Social Services",
            "subcategory":"Child Care",
            "type":"Services"
        }
    ],
    "sg:phone":"+1 615 597 8777",
    "sg:postcode":"37166",
    "sg:province":"TN",
    "sg:tags":[
        "day"
    ],
    "wof:name":"Rainbow Playschool",
    "wof:placetype":"venue"
},
  "geometry": {"coordinates":[-85.809867,35.950193],"type":"Point"}
}