{
  "type": "Feature",
  "properties": {
    "iso:country":"US",
    "sg:address":"520 Oak St",
    "sg:city":"Chattanooga",
    "sg:classifiers":[
        {
            "category":"Social Services",
            "type":"Services"
        }
    ],
    "sg:phone":"+1 423 755 4475",
    "sg:postcode":"37403",
    "sg:province":"TN",
    "wof:name":"Career Educational Center",
    "wof:placetype":"venue"
},
  "geometry": {"coordinates":[-85.301654,35.046984],"type":"Point"}
}