{
  "type": "Feature",
  "properties": {
    "iso:country":"US",
    "sg:address":"4232 Asheville Hwy",
    "sg:city":"Knoxville",
    "sg:classifiers":[
        {
            "category":"Cinema",
            "subcategory":"Movie Rental",
            "type":"Entertainment"
        }
    ],
    "sg:phone":"+1 865 522 7808",
    "sg:postcode":"37914",
    "sg:province":"TN",
    "sg:tags":[
        "leasing",
        "video",
        "disc",
        "tape"
    ],
    "wof:name":"Blockbuster Video",
    "wof:placetype":"venue"
},
  "geometry": {"coordinates":[-83.86878299999999,36.003468],"type":"Point"}
}