{
  "type": "Feature",
  "properties": {
    "addr:full":"6069 Scarlet Leaf Dr Memphis TN 38141",
    "addr:housenumber":"6069",
    "addr:postcode":"38141",
    "addr:street":"Scarlet Leaf Dr",
    "iso:country":"US",
    "sg:address":"6069 Scarlet Leaf Dr",
    "sg:city":"Memphis",
    "sg:classifiers":[
        {
            "category":"Autos & Motor Vehicles",
            "subcategory":"Fuel & Gas Station",
            "type":"Retail Goods"
        }
    ],
    "sg:phone":"+1 901 690 3089",
    "sg:postcode":"38141",
    "sg:province":"TN",
    "sg:tags":[
        "station",
        "gasoline"
    ],
    "wof:name":"Mobile Oil Solutions",
    "wof:placetype":"venue"
},
  "geometry": {"coordinates":[-89.862852,35.025944],"type":"Point"}
}