{
  "type": "Feature",
  "properties": {
    "iso:country":"US",
    "sg:address":"338 White Bridge Pike",
    "sg:city":"Nashville",
    "sg:classifiers":[
        {
            "category":"Retail",
            "subcategory":"Laundry & Dry Cleaning",
            "type":"Services"
        },
        {
            "category":"Shopping",
            "subcategory":"Clothing, Apparel, & Fashions",
            "type":"Retail Goods"
        }
    ],
    "sg:phone":"+1 615 356 0277",
    "sg:postcode":"37209",
    "sg:province":"TN",
    "sg:tags":[
        "alteration"
    ],
    "wof:name":"Kim's Alterations & Reweaving",
    "wof:placetype":"venue"
},
  "geometry": {"coordinates":[-86.857958,36.14572],"type":"Point"}
}