{
  "type": "Feature",
  "properties": {
    "iso:country":"US",
    "sg:address":"6703 Garden Oaks Dr",
    "sg:city":"Memphis",
    "sg:classifiers":[
        {
            "category":"Manufacturing",
            "subcategory":"Tools & Machinery",
            "type":"Manufacturing & Wholesale Goods"
        }
    ],
    "sg:phone":"+1 901 754 5708",
    "sg:postcode":"38120",
    "sg:province":"TN",
    "sg:tags":[
        "automotive",
        "parts",
        "racing",
        "mfg"
    ],
    "wof:name":"Doc Enterprises Inc",
    "wof:placetype":"venue"
},
  "geometry": {"coordinates":[-89.840361,35.108645],"type":"Point"}
}