{
  "type": "Feature",
  "properties": {
    "addr:full":"621 Shallowford Rd Chattanooga TN 37411",
    "addr:housenumber":"621",
    "addr:postcode":"37411",
    "addr:street":"Shallowford Rd",
    "iso:country":"US",
    "sg:address":"621 Shallowford Rd",
    "sg:city":"Chattanooga",
    "sg:classifiers":[
        {
            "category":"Personal",
            "subcategory":"Beauty Salon",
            "type":"Services"
        }
    ],
    "sg:phone":"+1 423 629 8881",
    "sg:postcode":"37411",
    "sg:province":"TN",
    "wof:name":"Trinity Learning Ctr",
    "wof:placetype":"venue"
},
  "geometry": {"coordinates":[-85.243115,35.038106],"type":"Point"}
}