{
  "type": "Feature",
  "properties": {
    "addr:full":"288 Cartwright Rd Shelbyville TN 37160",
    "addr:housenumber":"288",
    "addr:postcode":"37160",
    "addr:street":"Cartwright Rd",
    "iso:country":"US",
    "sg:address":"288 Cartwright Rd",
    "sg:city":"Shelbyville",
    "sg:classifiers":[
        {
            "category":"Building & Trades",
            "subcategory":"Landscaping Services",
            "type":"Services"
        }
    ],
    "sg:phone":"+1 931 680 8999",
    "sg:postcode":"37160",
    "sg:province":"TN",
    "wof:name":"Knotts Lawncare Services LLC",
    "wof:placetype":"venue"
},
  "geometry": {"coordinates":[-86.509101,35.544223],"type":"Point"}
}