{
  "type": "Feature",
  "properties": {
    "addr:full":"105 S Lauderdale St Bolivar TN 38008",
    "addr:housenumber":"105",
    "addr:postcode":"38008",
    "addr:street":"S Lauderdale St",
    "iso:country":"US",
    "sg:address":"105 S Lauderdale St",
    "sg:city":"Bolivar",
    "sg:classifiers":[
        {
            "category":"Personal",
            "type":"Services"
        }
    ],
    "sg:phone":"+1 731 658 9600",
    "sg:postcode":"38008",
    "sg:province":"TN",
    "sg:tags":[
        "credit",
        "debt",
        "counseling"
    ],
    "wof:name":"Bolivar Credit",
    "wof:placetype":"venue"
},
  "geometry": {"coordinates":[-88.99157,35.256225],"type":"Point"}
}