{
  "type": "Feature",
  "properties": {
    "iso:country":"US",
    "sg:address":"618 Georgia Ave",
    "sg:city":"Chattanooga",
    "sg:classifiers":[
        {
            "category":"Restaurant",
            "type":"Food & Drink"
        }
    ],
    "sg:menulink":"http://www.allmenus.com/tn/chattanooga/280161-murphys-ale-house/menu/",
    "sg:phone":"+1 423 648 4360",
    "sg:postcode":"37402",
    "sg:province":"TN",
    "sg:tags":[
        "american",
        "pub"
    ],
    "wof:name":"Murphy's Ale House",
    "wof:placetype":"venue"
},
  "geometry": {"coordinates":[-85.305696,35.049224],"type":"Point"}
}