{
  "type": "Feature",
  "properties": {
    "iso:country":"US",
    "sg:address":"1125 Cedarview Ln",
    "sg:city":"Franklin",
    "sg:classifiers":[
        {
            "category":"Social Services",
            "subcategory":"Job Training",
            "type":"Services"
        }
    ],
    "sg:phone":"+1 615 591 4737",
    "sg:postcode":"37067",
    "sg:province":"TN",
    "sg:tags":[
        "rehabilitation"
    ],
    "wof:name":"Pro Health Rehab Facility",
    "wof:placetype":"venue"
},
  "geometry": {"coordinates":[-86.796395,35.888371],"type":"Point"}
}