{
  "type": "Feature",
  "properties": {
    "addr:full":"727 Sand Road Cir Henderson TN 38340",
    "addr:housenumber":"727",
    "addr:postcode":"38340",
    "addr:street":"Sand Road Cir",
    "iso:country":"US",
    "sg:address":"727 Sand Road Cir",
    "sg:city":"Henderson",
    "sg:classifiers":[
        {
            "category":"Freight",
            "type":"Transportation"
        }
    ],
    "sg:phone":"+1 731 983 2766",
    "sg:postcode":"38340",
    "sg:province":"TN",
    "sg:tags":[
        "commercial",
        "storage"
    ],
    "wof:name":"Another Attic Mini Storage",
    "wof:placetype":"venue"
},
  "geometry": {"coordinates":[-88.665857,35.450677],"type":"Point"}
}