{
  "type": "Feature",
  "properties": {
    "iso:country":"US",
    "sg:address":"2211 Green Pond Rd",
    "sg:city":"Soddy Daisy",
    "sg:classifiers":[
        {
            "category":"Building & Trades",
            "subcategory":"Construction",
            "type":"Services"
        }
    ],
    "sg:phone":"+1 423 332 2499",
    "sg:postcode":"37379",
    "sg:province":"TN",
    "sg:tags":[
        "contractor"
    ],
    "wof:name":"Simmons Kelley Dry Wall",
    "wof:placetype":"venue"
},
  "geometry": {"coordinates":[-85.11245099999999,35.24238],"type":"Point"}
}