{
  "type": "Feature",
  "properties": {
    "addr:full":"92 Thomas Rd Lebanon TN 37087",
    "addr:housenumber":"92",
    "addr:postcode":"37087",
    "addr:street":"Thomas Rd",
    "iso:country":"US",
    "sg:address":"92 Thomas Rd",
    "sg:city":"Lebanon",
    "sg:classifiers":[
        {
            "category":"Professional",
            "type":"Services"
        }
    ],
    "sg:phone":"+1 615 444 8309",
    "sg:postcode":"37087",
    "sg:province":"TN",
    "wof:name":"B&C Machine & Tool",
    "wof:placetype":"venue"
},
  "geometry": {"coordinates":[-86.27604700000001,36.298936],"type":"Point"}
}