{
  "type": "Feature",
  "properties": {
    "iso:country":"US",
    "sg:address":"2337 Madison St",
    "sg:city":"Clarksville",
    "sg:classifiers":[
        {
            "category":"Shopping",
            "type":"Retail Goods"
        }
    ],
    "sg:phone":"+1 931 648 2224",
    "sg:postcode":"37043",
    "sg:province":"TN",
    "sg:tags":[
        "merchandise"
    ],
    "sg:website":"www.americancellular.com",
    "wof:name":"American Cellular",
    "wof:placetype":"venue"
},
  "geometry": {"coordinates":[-87.272289,36.508382],"type":"Point"}
}