{
  "type": "Feature",
  "properties": {
    "iso:country":"US",
    "sg:address":"1359 Promiseland Way",
    "sg:city":"Parrottsville",
    "sg:classifiers":[
        {
            "category":"Organizations",
            "subcategory":"Religious Organization",
            "type":"Services"
        }
    ],
    "sg:phone":"+1 423 823 1643",
    "sg:postcode":"37843",
    "sg:province":"TN",
    "sg:tags":[
        "church"
    ],
    "wof:name":"Oak Hill Chapel",
    "wof:placetype":"venue"
},
  "geometry": {"coordinates":[-82.95355000000001,35.990606],"type":"Point"}
}