{
  "type": "Feature",
  "properties": {
    "addr:full":"5668 S Rex Rd Memphis TN 38119",
    "addr:housenumber":"5668",
    "addr:postcode":"38119",
    "addr:street":"S Rex Rd",
    "iso:country":"US",
    "sg:address":"5668 S Rex Rd",
    "sg:city":"Memphis",
    "sg:classifiers":[
        {
            "category":"Professional",
            "subcategory":"Lawyer & Legal Services",
            "type":"Services"
        }
    ],
    "sg:phone":"+1 901 683 2822",
    "sg:postcode":"38119",
    "sg:province":"TN",
    "sg:tags":[
        "attorney"
    ],
    "wof:name":"Jeff Crow Law Office",
    "wof:placetype":"venue"
},
  "geometry": {"coordinates":[-89.873272,35.101907],"type":"Point"}
}