{
  "type": "Feature",
  "properties": {
    "iso:country":"US",
    "sg:address":"951 Market St",
    "sg:city":"Dayton",
    "sg:classifiers":[
        {
            "category":"Utilities",
            "subcategory":"Natural Gas",
            "type":"Services"
        }
    ],
    "sg:phone":"+1 423 775 2422",
    "sg:postcode":"37321",
    "sg:province":"TN",
    "sg:website":"www.mtng.com",
    "wof:name":"Middle Tennessee Natural Gas",
    "wof:placetype":"venue"
},
  "geometry": {"coordinates":[-85.018095,35.488977],"type":"Point"}
}