{
  "type": "Feature",
  "properties": {
    "addr:full":"303 N 7th St La Follette TN 37766",
    "addr:housenumber":"303",
    "addr:postcode":"37766",
    "addr:street":"N 7Th St",
    "iso:country":"US",
    "sg:address":"303 N 7th St",
    "sg:city":"La Follette",
    "sg:classifiers":[
        {
            "category":"Railroad",
            "type":"Transportation"
        }
    ],
    "sg:phone":"+1 423 562 7001",
    "sg:postcode":"37766",
    "sg:province":"TN",
    "sg:tags":[
        "operator",
        "line"
    ],
    "wof:name":"CSX",
    "wof:placetype":"venue"
},
  "geometry": {"coordinates":[-84.128067,36.380718],"type":"Point"}
}