{
  "type": "Feature",
  "properties": {
    "iso:country":"US",
    "sg:address":"1644 Fort Campbell Blvd",
    "sg:city":"Clarksville",
    "sg:classifiers":[
        {
            "category":"Restaurant",
            "type":"Food & Drink"
        }
    ],
    "sg:menulink":"http://www.allmenus.com/tn/clarksville/203419-mcdonalds/menu/",
    "sg:postcode":"37042",
    "sg:province":"TN",
    "sg:tags":[
        "burger",
        "american"
    ],
    "wof:name":"McDonald's",
    "wof:placetype":"venue"
},
  "geometry": {"coordinates":[-87.409009,36.576787],"type":"Point"}
}