{
  "type": "Feature",
  "properties": {
    "addr:full":"1536 Genesis Rd Crossville TN 38555",
    "addr:housenumber":"1536",
    "addr:postcode":"38555",
    "addr:street":"Genesis Rd",
    "iso:country":"US",
    "sg:address":"1536 Genesis Rd",
    "sg:city":"Crossville",
    "sg:classifiers":[
        {
            "category":"Wholesale",
            "subcategory":"Machinery & Supplies",
            "type":"Manufacturing & Wholesale Goods"
        }
    ],
    "sg:phone":"+1 931 456 6000",
    "sg:postcode":"38555",
    "sg:province":"TN",
    "sg:tags":[
        "equipment",
        "industrial",
        "special"
    ],
    "wof:name":"Colinx LLC",
    "wof:placetype":"venue"
},
  "geometry": {"coordinates":[-85.01593699999999,35.973558],"type":"Point"}
}