{
  "type": "Feature",
  "properties": {
    "iso:country":"US",
    "sg:address":"419 W Elk Ave",
    "sg:city":"Elizabethton",
    "sg:classifiers":[
        {
            "category":"Government",
            "subcategory":"Office",
            "type":"Public Place"
        }
    ],
    "sg:phone":"+1 423 542 6461",
    "sg:postcode":"37643",
    "sg:province":"TN",
    "sg:tags":[
        "federal"
    ],
    "wof:name":"Natural Resources Conservation",
    "wof:placetype":"venue"
},
  "geometry": {"coordinates":[-82.227943,36.350806],"type":"Point"}
}