{
  "type": "Feature",
  "properties": {
    "addr:full":"211 W 8th St Columbia TN 38401",
    "addr:housenumber":"211",
    "addr:postcode":"38401",
    "addr:street":"W 8Th St",
    "iso:country":"US",
    "sg:address":"211 W 8th St",
    "sg:city":"Columbia",
    "sg:classifiers":[
        {
            "category":"Education",
            "subcategory":"Library",
            "type":"Public Place"
        }
    ],
    "sg:phone":"+1 931 388 6332",
    "sg:postcode":"38401",
    "sg:province":"TN",
    "wof:name":"Maury County Public Library",
    "wof:placetype":"venue"
},
  "geometry": {"coordinates":[-87.037246,35.613721],"type":"Point"}
}