{
  "type": "Feature",
  "properties": {
    "addr:full":"3990 Stephanie Ln Memphis TN 38128",
    "addr:housenumber":"3990",
    "addr:postcode":"38128",
    "addr:street":"Stephanie Ln",
    "iso:country":"US",
    "sg:address":"3990 Stephanie Ln",
    "sg:city":"Memphis",
    "sg:classifiers":[
        {
            "category":"Real Estate",
            "subcategory":"Real Estate Operator",
            "type":"Services"
        }
    ],
    "sg:phone":"+1 901 386 9508",
    "sg:postcode":"38128",
    "sg:province":"TN",
    "sg:tags":[
        "building",
        "apartment"
    ],
    "wof:name":"Country View",
    "wof:placetype":"venue"
},
  "geometry": {"coordinates":[-89.924537,35.235581],"type":"Point"}
}