{
  "type": "Feature",
  "properties": {
    "iso:country":"US",
    "sg:address":"1515 Rockland Dr",
    "sg:city":"Columbia",
    "sg:classifiers":[
        {
            "category":"Building & Trades",
            "subcategory":"Construction",
            "type":"Services"
        }
    ],
    "sg:phone":"+1 931 381 3535",
    "sg:postcode":"38401",
    "sg:province":"TN",
    "sg:tags":[
        "paving",
        "contractor"
    ],
    "wof:name":"Advance Paving Co Inc",
    "wof:placetype":"venue"
},
  "geometry": {"coordinates":[-87.09407899999999,35.577666],"type":"Point"}
}