{
  "type": "Feature",
  "properties": {
    "iso:country":"US",
    "sg:address":"3024 State Hwy 67",
    "sg:city":"Mountain City",
    "sg:classifiers":[
        {
            "category":"Freight",
            "type":"Transportation"
        }
    ],
    "sg:phone":"+1 423 727 4840",
    "sg:postcode":"37683",
    "sg:province":"TN",
    "sg:tags":[
        "operator",
        "local",
        "trucking"
    ],
    "wof:name":"Lindas Trucking",
    "wof:placetype":"venue"
},
  "geometry": {"coordinates":[-81.85144699999999,36.464748],"type":"Point"}
}