{
  "type": "Feature",
  "properties": {
    "iso:country":"US",
    "sg:address":"1014 Dallas Rd",
    "sg:city":"Chattanooga",
    "sg:classifiers":[
        {
            "category":"Freight",
            "type":"Transportation"
        }
    ],
    "sg:phone":"+1 423 267 8975",
    "sg:postcode":"37405",
    "sg:province":"TN",
    "sg:tags":[
        "trucking"
    ],
    "wof:name":"T-L-K-A Energies Co",
    "wof:placetype":"venue"
},
  "geometry": {"coordinates":[-85.305464,35.073889],"type":"Point"}
}