{
  "type": "Feature",
  "properties": {
    "iso:country":"US",
    "sg:address":"1635 Bell Rd",
    "sg:city":"Nashville",
    "sg:classifiers":[
        {
            "category":"Autos & Motor Vehicles",
            "subcategory":"Automobile Sales",
            "type":"Retail Goods"
        }
    ],
    "sg:phone":"+1 615 332 9000",
    "sg:postcode":"37211",
    "sg:province":"TN",
    "sg:tags":[
        "car",
        "dealer"
    ],
    "wof:name":"Suzuki Of Nashville",
    "wof:placetype":"venue"
},
  "geometry": {"coordinates":[-86.702758,36.045448],"type":"Point"}
}