{
  "type": "Feature",
  "properties": {
    "iso:country":"US",
    "sg:address":"5005 Wolfchase Farms Pkwy",
    "sg:city":"Arlington",
    "sg:classifiers":[
        {
            "category":"Professional",
            "subcategory":"Computer Services",
            "type":"Services"
        }
    ],
    "sg:phone":"+1 901 381 4357",
    "sg:postcode":"38002",
    "sg:province":"TN",
    "sg:tags":[
        "related"
    ],
    "wof:name":"Netx LLC",
    "wof:placetype":"venue"
},
  "geometry": {"coordinates":[-89.788669,35.262399],"type":"Point"}
}