{
  "type": "Feature",
  "properties": {
    "addr:full":"140 Music St Paris TN 38242",
    "addr:housenumber":"140",
    "addr:postcode":"38242",
    "addr:street":"Music St",
    "iso:country":"US",
    "sg:address":"140 Music St",
    "sg:city":"Paris",
    "sg:classifiers":[
        {
            "category":"Professional",
            "subcategory":"Business Services",
            "type":"Services"
        }
    ],
    "sg:phone":"+1 731 644 7111",
    "sg:postcode":"38242",
    "sg:province":"TN",
    "sg:tags":[
        "recording",
        "studio"
    ],
    "wof:name":"Clifty Studios",
    "wof:placetype":"venue"
},
  "geometry": {"coordinates":[-88.285844,36.27048],"type":"Point"}
}