{
  "type": "Feature",
  "properties": {
    "addr:full":"111 Chesapeake Harbor Blvd Hendersonville TN 37075",
    "addr:housenumber":"111",
    "addr:postcode":"37075",
    "addr:street":"Chesapeake Harbor Blvd",
    "iso:country":"US",
    "sg:address":"111 Chesapeake Harbor Blvd",
    "sg:city":"Hendersonville",
    "sg:classifiers":[
        {
            "category":"Building & Trades",
            "subcategory":"Construction",
            "type":"Services"
        }
    ],
    "sg:phone":"+1 615 826 6579",
    "sg:postcode":"37075",
    "sg:province":"TN",
    "sg:tags":[
        "home",
        "builder"
    ],
    "wof:name":"Randall Phillips Homes",
    "wof:placetype":"venue"
},
  "geometry": {"coordinates":[-86.62606599999999,36.272037],"type":"Point"}
}