{
  "type": "Feature",
  "properties": {
    "addr:full":"314 Meadowlawn Dr Franklin TN 37064",
    "addr:housenumber":"314",
    "addr:postcode":"37064",
    "addr:street":"Meadowlawn Dr",
    "iso:country":"US",
    "sg:address":"314 Meadowlawn Dr",
    "sg:city":"Franklin",
    "sg:classifiers":[
        {
            "category":"Professional",
            "subcategory":"Business Services",
            "type":"Services"
        }
    ],
    "sg:phone":"+1 615 599 3486",
    "sg:postcode":"37064",
    "sg:province":"TN",
    "wof:name":"Cryptic Globe Recording",
    "wof:placetype":"venue"
},
  "geometry": {"coordinates":[-86.869371,35.912092],"type":"Point"}
}