{
  "type": "Feature",
  "properties": {
    "iso:country":"US",
    "sg:address":"60 Shiloh Rd",
    "sg:city":"Greeneville",
    "sg:classifiers":[
        {
            "category":"Education",
            "subcategory":"Library",
            "type":"Public Place"
        }
    ],
    "sg:phone":"+1 423 636 7320",
    "sg:postcode":"37743",
    "sg:province":"TN",
    "wof:name":"Tate Library",
    "wof:placetype":"venue"
},
  "geometry": {"coordinates":[-82.75979599999999,36.173921],"type":"Point"}
}