{
  "type": "Feature",
  "properties": {
    "iso:country":"US",
    "sg:address":"2693 Park Ave",
    "sg:city":"Memphis",
    "sg:classifiers":[
        {
            "category":"Organizations",
            "subcategory":"Professional Association",
            "type":"Services"
        }
    ],
    "sg:phone":"+1 901 324 2078",
    "sg:postcode":"38114",
    "sg:province":"TN",
    "wof:name":"Orange Mound Collaborative",
    "wof:placetype":"venue"
},
  "geometry": {"coordinates":[-89.97259099999999,35.108076],"type":"Point"}
}