{
  "type": "Feature",
  "properties": {
    "iso:country":"US",
    "sg:address":"2625 Thousand Oaks Blvd",
    "sg:city":"Memphis",
    "sg:classifiers":[
        {
            "category":"Travel",
            "subcategory":"Hotels & Motels",
            "type":"Entertainment"
        }
    ],
    "sg:phone":"+1 901 362 6200",
    "sg:postcode":"38118",
    "sg:province":"TN",
    "sg:website":"http://marriott.com/MEMTN",
    "wof:name":"Memphis Marriott East",
    "wof:placetype":"venue"
},
  "geometry": {"coordinates":[-89.902,35.076769],"type":"Point"}
}