{
  "type": "Feature",
  "properties": {
    "iso:country":"US",
    "sg:address":"307 Southgate Ct",
    "sg:city":"Brentwood",
    "sg:classifiers":[
        {
            "category":"Professional",
            "subcategory":"Advertising",
            "type":"Services"
        }
    ],
    "sg:phone":"+1 615 377 3322",
    "sg:postcode":"37027",
    "sg:province":"TN",
    "sg:tags":[
        "publisher"
    ],
    "sg:website":"www.sunbeltfs.com",
    "wof:name":"Sunbelt Fulfillment Svc",
    "wof:placetype":"venue"
},
  "geometry": {"coordinates":[-86.820915,35.957203],"type":"Point"}
}