{
  "type": "Feature",
  "properties": {
    "addr:full":"5756 State Hwy 153 Hixson TN 37343",
    "addr:housenumber":"5756",
    "addr:postcode":"37343",
    "addr:street":"State Hwy 153",
    "iso:country":"US",
    "sg:address":"5756 State Hwy 153",
    "sg:city":"Hixson",
    "sg:classifiers":[
        {
            "category":"Shopping",
            "subcategory":"Department Store",
            "type":"Retail Goods"
        }
    ],
    "sg:phone":"+1 423 875 4680",
    "sg:postcode":"37343",
    "sg:province":"TN",
    "wof:name":"Marshalls",
    "wof:placetype":"venue"
},
  "geometry": {"coordinates":[-85.24844299999999,35.157976],"type":"Point"}
}