{
  "type": "Feature",
  "properties": {
    "iso:country":"US",
    "sg:address":"4230 Harding Pike",
    "sg:city":"Nashville",
    "sg:classifiers":[
        {
            "category":"Health Services",
            "subcategory":"Doctor",
            "type":"Services"
        }
    ],
    "sg:phone":"+1 615 385 3705",
    "sg:postcode":"37205",
    "sg:province":"TN",
    "sg:tags":[
        "physician",
        "surgeon"
    ],
    "wof:name":"Cardiovascular Ansthslgst PC",
    "wof:placetype":"venue"
},
  "geometry": {"coordinates":[-86.846185,36.126176],"type":"Point"}
}