{
  "type": "Feature",
  "properties": {
    "iso:country":"US",
    "sg:address":"234 Spruce Dr",
    "sg:city":"Wartburg",
    "sg:phone":"+1 423 346 8821",
    "sg:postcode":"37887",
    "sg:province":"TN",
    "sg:tags":[
        "bio",
        "diesel"
    ],
    "wof:name":"Blue Sky Biodiesel Inc",
    "wof:placetype":"venue"
},
  "geometry": {"coordinates":[-84.53523300000001,36.087044],"type":"Point"}
}