{
  "type": "Feature",
  "properties": {
    "iso:country":"US",
    "sg:address":"128 S Willow Ave",
    "sg:city":"Cookeville",
    "sg:classifiers":[
        {
            "category":"Shopping",
            "subcategory":"Jewelry",
            "type":"Retail Goods"
        }
    ],
    "sg:phone":"+1 931 526 8366",
    "sg:postcode":"38501",
    "sg:province":"TN",
    "sg:tags":[
        "jeweler"
    ],
    "sg:website":"www.tndiamonds.com",
    "wof:name":"Jewelry The Emporium",
    "wof:placetype":"venue"
},
  "geometry": {"coordinates":[-85.513008,36.160669],"type":"Point"}
}