{
  "type": "Feature",
  "properties": {
    "iso:country":"US",
    "sg:address":"330 Finch Rd",
    "sg:city":"Gleason",
    "sg:classifiers":[
        {
            "category":"Wholesale",
            "subcategory":"Farm Supplies",
            "type":"Manufacturing & Wholesale Goods"
        }
    ],
    "sg:phone":"+1 731 648 0111",
    "sg:postcode":"38229",
    "sg:province":"TN",
    "sg:tags":[
        "auction",
        "livestock",
        "market"
    ],
    "wof:name":"Tennessee West Auction Barn",
    "wof:placetype":"venue"
},
  "geometry": {"coordinates":[-88.628641,36.211424],"type":"Point"}
}