{
  "type": "Feature",
  "properties": {
    "iso:country":"US",
    "sg:address":"1821 Violet Ct",
    "sg:city":"Murfreesboro",
    "sg:classifiers":[
        {
            "category":"Professional",
            "subcategory":"Business Services",
            "type":"Services"
        }
    ],
    "sg:phone":"+1 615 904 2049",
    "sg:postcode":"37128",
    "sg:province":"TN",
    "wof:name":"James Bonding Co",
    "wof:placetype":"venue"
},
  "geometry": {"coordinates":[-86.402062,35.80961],"type":"Point"}
}