{
  "type": "Feature",
  "properties": {
    "addr:full":"2804 Columbine Pl Nashville TN 37204",
    "addr:housenumber":"2804",
    "addr:postcode":"37204",
    "addr:street":"Columbine Pl",
    "iso:country":"US",
    "sg:address":"2804 Columbine Pl",
    "sg:city":"Nashville",
    "sg:classifiers":[
        {
            "category":"Professional",
            "subcategory":"Lawyer & Legal Services",
            "type":"Services"
        }
    ],
    "sg:phone":"+1 615 383 3787",
    "sg:postcode":"37204",
    "sg:province":"TN",
    "sg:tags":[
        "attorney"
    ],
    "wof:name":"James A Freeman & Assoc",
    "wof:placetype":"venue"
},
  "geometry": {"coordinates":[-86.765017,36.115669],"type":"Point"}
}