{
  "type": "Feature",
  "properties": {
    "addr:full":"905 Pitts Dr Smithville TN 37166",
    "addr:housenumber":"905",
    "addr:postcode":"37166",
    "addr:street":"Pitts Dr",
    "iso:country":"US",
    "sg:address":"905 Pitts Dr",
    "sg:city":"Smithville",
    "sg:classifiers":[
        {
            "category":"Professional",
            "type":"Services"
        }
    ],
    "sg:phone":"+1 615 597 4989",
    "sg:postcode":"37166",
    "sg:province":"TN",
    "wof:name":"Camp Samaritan",
    "wof:placetype":"venue"
},
  "geometry": {"coordinates":[-85.766918,36.007001],"type":"Point"}
}