{
  "type": "Feature",
  "properties": {
    "addr:full":"627 N 2nd St Clarksville TN 37040",
    "addr:housenumber":"627",
    "addr:postcode":"37040",
    "addr:street":"N 2Nd St",
    "iso:country":"US",
    "sg:address":"627 N 2nd St",
    "sg:city":"Clarksville",
    "sg:classifiers":[
        {
            "category":"Professional",
            "subcategory":"Lawyer & Legal Services",
            "type":"Services"
        }
    ],
    "sg:phone":"+1 931 645 1844",
    "sg:postcode":"37040",
    "sg:province":"TN",
    "wof:name":"Lovitt Worth",
    "wof:placetype":"venue"
},
  "geometry": {"coordinates":[-87.361378,36.535725],"type":"Point"}
}