{
  "type": "Feature",
  "properties": {
    "iso:country":"US",
    "sg:address":"124 Essex Dr",
    "sg:city":"Knoxville",
    "sg:classifiers":[
        {
            "category":"Professional",
            "type":"Services"
        }
    ],
    "sg:phone":"+1 865 693 8889",
    "sg:postcode":"37922",
    "sg:province":"TN",
    "sg:tags":[
        "establishment"
    ],
    "wof:name":"Zaveri Rojesh",
    "wof:placetype":"venue"
},
  "geometry": {"coordinates":[-84.095265,35.909758],"type":"Point"}
}