{
  "type": "Feature",
  "properties": {
    "iso:country":"US",
    "sg:address":"1350 Dolly Parton Pkwy",
    "sg:city":"Sevierville",
    "sg:classifiers":[
        {
            "category":"Organizations",
            "subcategory":"Religious Organization",
            "type":"Services"
        }
    ],
    "sg:phone":"+1 865 428 4520",
    "sg:postcode":"37862",
    "sg:province":"TN",
    "sg:tags":[
        "church"
    ],
    "wof:name":"Sevierville Church",
    "wof:placetype":"venue"
},
  "geometry": {"coordinates":[-83.52178000000001,35.863883],"type":"Point"}
}