{
  "type": "Feature",
  "properties": {
    "iso:country":"US",
    "sg:address":"3706 S Mendenhall Rd",
    "sg:city":"Memphis",
    "sg:classifiers":[
        {
            "category":"Restaurant",
            "type":"Food & Drink"
        }
    ],
    "sg:phone":"+1 901 366 6967",
    "sg:postcode":"38115",
    "sg:province":"TN",
    "sg:tags":[
        "seafood",
        "soul"
    ],
    "wof:name":"James' & Jacks' Catfish Shack",
    "wof:placetype":"venue"
},
  "geometry": {"coordinates":[-89.88603500000001,35.047556],"type":"Point"}
}