{
  "type": "Feature",
  "properties": {
    "iso:country":"US",
    "sg:address":"2733 Mountain Terrace St",
    "sg:city":"Memphis",
    "sg:classifiers":[
        {
            "category":"Organizations",
            "subcategory":"Religious Organization",
            "type":"Services"
        }
    ],
    "sg:phone":"+1 901 358 6778",
    "sg:postcode":"38127",
    "sg:province":"TN",
    "wof:name":"Let Christians Work For You Hm",
    "wof:placetype":"venue"
},
  "geometry": {"coordinates":[-89.983564,35.201678],"type":"Point"}
}