{
  "type": "Feature",
  "properties": {
    "iso:country":"US",
    "sg:address":"415 Pine Ridge Rd",
    "sg:city":"Bluff City",
    "sg:classifiers":[
        {
            "category":"Building & Trades",
            "subcategory":"Electrical",
            "type":"Services"
        }
    ],
    "sg:phone":"+1 423 538 4265",
    "sg:postcode":"37618",
    "sg:province":"TN",
    "sg:tags":[
        "electrical",
        "contractor"
    ],
    "wof:name":"Bos Electric",
    "wof:placetype":"venue"
},
  "geometry": {"coordinates":[-82.253175,36.445861],"type":"Point"}
}