{
  "type": "Feature",
  "properties": {
    "iso:country":"US",
    "sg:address":"1517 S Lowry St",
    "sg:city":"Smyrna",
    "sg:classifiers":[
        {
            "category":"Wholesale",
            "subcategory":"Medical Equipment & Supplies",
            "type":"Manufacturing & Wholesale Goods"
        }
    ],
    "sg:phone":"+1 615 355 0700",
    "sg:postcode":"37167",
    "sg:province":"TN",
    "sg:tags":[
        "physician",
        "surgeon"
    ],
    "wof:name":"Bell Furniture",
    "wof:placetype":"venue"
},
  "geometry": {"coordinates":[-86.479732,35.937906],"type":"Point"}
}