{
  "type": "Feature",
  "properties": {
    "addr:full":"4772 Navy Rd Millington TN 38053",
    "addr:housenumber":"4772",
    "addr:postcode":"38053",
    "addr:street":"Navy Rd",
    "iso:country":"US",
    "sg:address":"4772 Navy Rd",
    "sg:city":"Millington",
    "sg:classifiers":[
        {
            "category":"Health Services",
            "subcategory":"Doctor",
            "type":"Services"
        }
    ],
    "sg:phone":"+1 901 873 4501",
    "sg:postcode":"38053",
    "sg:province":"TN",
    "sg:tags":[
        "physician",
        "surgeon"
    ],
    "wof:name":"Regina Lindsey MD",
    "wof:placetype":"venue"
},
  "geometry": {"coordinates":[-89.903953,35.341444],"type":"Point"}
}