{
  "type": "Feature",
  "properties": {
    "addr:full":"1614 Industrial Rd Greeneville TN 37745",
    "addr:housenumber":"1614",
    "addr:postcode":"37745",
    "addr:street":"Industrial Rd",
    "iso:country":"US",
    "sg:address":"1614 Industrial Rd",
    "sg:city":"Greeneville",
    "sg:classifiers":[
        {
            "category":"Food & Beverages",
            "subcategory":"Specialty",
            "type":"Retail Goods"
        }
    ],
    "sg:phone":"+1 423 787 0537",
    "sg:postcode":"37745",
    "sg:province":"TN",
    "sg:tags":[
        "water",
        "bulk",
        "company"
    ],
    "wof:name":"Premium Waters Inc",
    "wof:placetype":"venue"
},
  "geometry": {"coordinates":[-82.79584800000001,36.189123],"type":"Point"}
}