{
  "type": "Feature",
  "properties": {
    "iso:country":"US",
    "sg:address":"121 21st Ave N",
    "sg:city":"Nashville",
    "sg:classifiers":[
        {
            "category":"Banks & Credit Unions",
            "subcategory":"Bank",
            "type":"Services"
        }
    ],
    "sg:phone":"+1 615 320 5000",
    "sg:postcode":"37203",
    "sg:province":"TN",
    "sg:tags":[
        "loan",
        "real estate"
    ],
    "wof:name":"Fidelity Mortgage Funding Inc",
    "wof:placetype":"venue"
},
  "geometry": {"coordinates":[-86.802661,36.15228],"type":"Point"}
}