{
  "type": "Feature",
  "properties": {
    "addr:full":"171 Court Sq Sneedville TN 37869",
    "addr:housenumber":"171",
    "addr:postcode":"37869",
    "addr:street":"Court Sq",
    "iso:country":"US",
    "sg:address":"171 Court Sq",
    "sg:city":"Sneedville",
    "sg:classifiers":[
        {
            "category":"Restaurant",
            "type":"Food & Drink"
        }
    ],
    "sg:menulink":"http://www.allmenus.com/tn/sneedville/139998-subway/menu/",
    "sg:phone":"+1 423 733 1288",
    "sg:postcode":"37869",
    "sg:province":"TN",
    "sg:tags":[
        "american",
        "sandwich"
    ],
    "wof:name":"Subway",
    "wof:placetype":"venue"
},
  "geometry": {"coordinates":[-83.21726099999999,36.529544],"type":"Point"}
}