{
  "type": "Feature",
  "properties": {
    "addr:full":"5409 Maryland Way Ste 140 Brentwood TN 37027\t",
    "addr:housenumber":"5409",
    "addr:postcode":"37027",
    "addr:street":"Maryland Way Ste 140",
    "iso:country":"US",
    "sg:address":"5409 Maryland Way Ste 140",
    "sg:city":"Brentwood",
    "sg:classifiers":[
        {
            "category":"Professional",
            "subcategory":"Computer Services",
            "type":"Services"
        }
    ],
    "sg:phone":"+1 615 599 9555",
    "sg:postcode":"37027\t",
    "sg:province":"TN",
    "wof:name":"Global Trade Technologies",
    "wof:placetype":"venue"
},
  "geometry": {"coordinates":[-86.814865,36.036792],"type":"Point"}
}