{
  "type": "Feature",
  "properties": {
    "iso:country":"US",
    "sg:address":"4924 Fort Henry Dr",
    "sg:city":"Kingsport",
    "sg:classifiers":[
        {
            "category":"Personal",
            "subcategory":"Beauty Salon",
            "type":"Services"
        }
    ],
    "sg:phone":"+1 423 239 3471",
    "sg:postcode":"37663",
    "sg:province":"TN",
    "wof:name":"Hair Biz",
    "wof:placetype":"venue"
},
  "geometry": {"coordinates":[-82.48359000000001,36.467672],"type":"Point"}
}