{
  "type": "Feature",
  "properties": {
    "iso:country":"US",
    "sg:address":"3402 Tuckaleechee Pike",
    "sg:city":"Maryville",
    "sg:classifiers":[
        {
            "category":"Sports & Exercise",
            "subcategory":"Golf",
            "type":"Entertainment"
        },
        {
            "category":"Recreation",
            "type":"Entertainment"
        }
    ],
    "sg:phone":"+1 865 982 9838",
    "sg:postcode":"37803",
    "sg:province":"TN",
    "sg:tags":[
        "course"
    ],
    "wof:name":"Lambert Acres Golf Club Inc",
    "wof:placetype":"venue"
},
  "geometry": {"coordinates":[-83.893512,35.749945],"type":"Point"}
}