{
  "type": "Feature",
  "properties": {
    "addr:full":"3302 McKinley Rd Johnson City TN 37604",
    "addr:housenumber":"3302",
    "addr:postcode":"37604",
    "addr:street":"Mckinley Rd",
    "iso:country":"US",
    "sg:address":"3302 McKinley Rd",
    "sg:city":"Johnson City",
    "sg:classifiers":[
        {
            "category":"Organizations",
            "subcategory":"Religious Organization",
            "type":"Services"
        }
    ],
    "sg:phone":"+1 423 928 3294",
    "sg:postcode":"37604",
    "sg:province":"TN",
    "wof:name":"McKinnley Memorial Bb Church",
    "wof:placetype":"venue"
},
  "geometry": {"coordinates":[-82.416332,36.306222],"type":"Point"}
}