{
  "type": "Feature",
  "properties": {
    "addr:full":"222 W Brooks Rd Memphis TN 38109",
    "addr:housenumber":"222",
    "addr:postcode":"38109",
    "addr:street":"W Brooks Rd",
    "iso:country":"US",
    "sg:address":"222 W Brooks Rd",
    "sg:city":"Memphis",
    "sg:classifiers":[
        {
            "category":"Professional",
            "subcategory":"Management & Consulting",
            "type":"Services"
        }
    ],
    "sg:phone":"+1 901 789 7373",
    "sg:postcode":"38109",
    "sg:province":"TN",
    "sg:tags":[
        "consultant",
        "business"
    ],
    "wof:name":"Ultimate Management Svc",
    "wof:placetype":"venue"
},
  "geometry": {"coordinates":[-90.07203199999999,35.063386],"type":"Point"}
}