{
  "type": "Feature",
  "properties": {
    "iso:country":"US",
    "sg:address":"112 Gann Rd",
    "sg:city":"Milan",
    "sg:classifiers":[
        {
            "category":"Home & Garden",
            "subcategory":"Garden Supply",
            "type":"Retail Goods"
        }
    ],
    "sg:phone":"+1 731 686 3227",
    "sg:postcode":"38358",
    "sg:province":"TN",
    "sg:tags":[
        "engine",
        "lawn",
        "all",
        "terrain",
        "sales",
        "mower",
        "chainsaw",
        "vehicle",
        "se"
    ],
    "wof:name":"Harris Small Engine Sales Co",
    "wof:placetype":"venue"
},
  "geometry": {"coordinates":[-88.752612,35.957885],"type":"Point"}
}