{
  "type": "Feature",
  "properties": {
    "iso:country":"US",
    "sg:address":"2330 Merchants Dr",
    "sg:city":"Knoxville",
    "sg:classifiers":[
        {
            "category":"Health Services",
            "subcategory":"Chiropractor",
            "type":"Services"
        }
    ],
    "sg:phone":"+1 865 405 0655",
    "sg:postcode":"37912",
    "sg:province":"TN",
    "wof:name":"Franya Peterson DC",
    "wof:placetype":"venue"
},
  "geometry": {"coordinates":[-83.997208,35.994028],"type":"Point"}
}