{
  "type": "Feature",
  "properties": {
    "addr:full":"6012 W Andrew Johnson Hwy Talbott TN 37877",
    "addr:housenumber":"6012",
    "addr:postcode":"37877",
    "addr:street":"W Andrew Johnson Hwy",
    "iso:country":"US",
    "sg:address":"6012 W Andrew Johnson Hwy",
    "sg:city":"Talbott",
    "sg:classifiers":[
        {
            "category":"Autos & Motor Vehicles",
            "subcategory":"Auto Supplies",
            "type":"Retail Goods"
        }
    ],
    "sg:phone":"+1 423 581 9420",
    "sg:postcode":"37877",
    "sg:province":"TN",
    "sg:tags":[
        "tire"
    ],
    "wof:name":"Porter's Tire Stores",
    "wof:placetype":"venue"
},
  "geometry": {"coordinates":[-83.393406,36.178542],"type":"Point"}
}