{
  "type": "Feature",
  "properties": {
    "iso:country":"US",
    "sg:address":"2369 Covington Pike",
    "sg:city":"Memphis",
    "sg:classifiers":[
        {
            "category":"Shopping",
            "subcategory":"Clothing, Apparel, & Fashions",
            "type":"Retail Goods"
        }
    ],
    "sg:phone":"+1 901 266 5100",
    "sg:postcode":"38128",
    "sg:province":"TN",
    "wof:name":"Autobody America Inc",
    "wof:placetype":"venue"
},
  "geometry": {"coordinates":[-89.895898,35.190175],"type":"Point"}
}