{
  "type": "Feature",
  "properties": {
    "addr:full":"1638 Sycamore View Rd Memphis TN 38134",
    "addr:housenumber":"1638",
    "addr:postcode":"38134",
    "addr:street":"Sycamore View Rd",
    "iso:country":"US",
    "sg:address":"1638 Sycamore View Rd",
    "sg:city":"Memphis",
    "sg:classifiers":[
        {
            "category":"Wholesale",
            "subcategory":"Office Equipment",
            "type":"Manufacturing & Wholesale Goods"
        }
    ],
    "sg:phone":"+1 901 387 5600",
    "sg:postcode":"38134",
    "sg:province":"TN",
    "sg:tags":[
        "repair",
        "electrical"
    ],
    "wof:name":"Danka Sales & Service",
    "wof:placetype":"venue"
},
  "geometry": {"coordinates":[-89.866322,35.170017],"type":"Point"}
}