{
  "type": "Feature",
  "properties": {
    "iso:country":"US",
    "sg:address":"1421 W G St",
    "sg:city":"Elizabethton",
    "sg:classifiers":[
        {
            "category":"Sports & Exercise",
            "subcategory":"Gym",
            "type":"Entertainment"
        }
    ],
    "sg:phone":"+1 423 542 9413",
    "sg:postcode":"37643",
    "sg:province":"TN",
    "sg:tags":[
        "club",
        "health",
        "studio",
        "gymnasium"
    ],
    "wof:name":"Elizabethon Fitness Ctr",
    "wof:placetype":"venue"
},
  "geometry": {"coordinates":[-82.248194,36.340562],"type":"Point"}
}