{
  "type": "Feature",
  "properties": {
    "addr:full":"5870 State Hwy 153 Hixson TN 37343",
    "addr:housenumber":"5870",
    "addr:postcode":"37343",
    "addr:street":"State Hwy 153",
    "iso:country":"US",
    "sg:address":"5870 State Hwy 153",
    "sg:city":"Hixson",
    "sg:classifiers":[
        {
            "category":"Health Services",
            "subcategory":"Doctor",
            "type":"Services"
        }
    ],
    "sg:phone":"+1 423 870 1999",
    "sg:postcode":"37343",
    "sg:province":"TN",
    "sg:tags":[
        "physician",
        "surgeon"
    ],
    "wof:name":"Chattanooga Family Medicine",
    "wof:placetype":"venue"
},
  "geometry": {"coordinates":[-85.248288,35.159692],"type":"Point"}
}