{
  "type": "Feature",
  "properties": {
    "iso:country":"US",
    "sg:address":"2591 S Roan St",
    "sg:city":"Johnson City",
    "sg:classifiers":[
        {
            "category":"Government",
            "subcategory":"Office",
            "type":"Public Place"
        }
    ],
    "sg:phone":"+1 423 928 5134",
    "sg:postcode":"37601",
    "sg:province":"TN",
    "sg:tags":[
        "state",
        "program"
    ],
    "wof:name":"Transportation Dept",
    "wof:placetype":"venue"
},
  "geometry": {"coordinates":[-82.33388100000001,36.299803],"type":"Point"}
}