{
  "type": "Feature",
  "properties": {
    "iso:country":"US",
    "sg:address":"61 N Mclean Blvd",
    "sg:city":"Memphis",
    "sg:classifiers":[
        {
            "category":"Place Of Worship",
            "subcategory":"Church",
            "type":"Public Place"
        },
        {
            "category":"Place Of Worship",
            "type":"Public Place"
        }
    ],
    "sg:phone":"+1 901 726 4446",
    "sg:postcode":"38104",
    "sg:province":"TN",
    "sg:tags":[
        "churches-catholic-traditional",
        "churches-catholic"
    ],
    "wof:name":"Catholic Diocese Of Memphis Department Of Education",
    "wof:placetype":"venue"
},
  "geometry": {"coordinates":[-89.99950699999999,35.139046],"type":"Point"}
}