{
  "type": "Feature",
  "properties": {
    "iso:country":"US",
    "sg:address":"272 Haywood Ln",
    "sg:city":"Nashville",
    "sg:classifiers":[
        {
            "category":"Building & Trades",
            "subcategory":"Cleaning & Sanitation",
            "type":"Services"
        }
    ],
    "sg:phone":"+1 615 831 1273",
    "sg:postcode":"37211",
    "sg:province":"TN",
    "sg:tags":[
        "window"
    ],
    "wof:name":"America Window Cleaning",
    "wof:placetype":"venue"
},
  "geometry": {"coordinates":[-86.70187300000001,36.070425],"type":"Point"}
}