{
  "type": "Feature",
  "properties": {
    "addr:full":"3144 Wilcox Ave Memphis TN 38111",
    "addr:housenumber":"3144",
    "addr:postcode":"38111",
    "addr:street":"Wilcox Ave",
    "iso:country":"US",
    "sg:address":"3144 Wilcox Ave",
    "sg:city":"Memphis",
    "sg:classifiers":[
        {
            "category":"Building & Trades",
            "subcategory":"Construction",
            "type":"Services"
        }
    ],
    "sg:phone":"+1 901 458 2423",
    "sg:postcode":"38111",
    "sg:province":"TN",
    "sg:tags":[
        "contractor"
    ],
    "wof:name":"Genos Roofing Co",
    "wof:placetype":"venue"
},
  "geometry": {"coordinates":[-89.95609,35.125753],"type":"Point"}
}