{
  "type": "Feature",
  "properties": {
    "iso:country":"US",
    "sg:address":"7694 Hurricane Creek Rd",
    "sg:city":"Mc Ewen",
    "sg:classifiers":[
        {
            "category":"Shopping",
            "subcategory":"Shoes",
            "type":"Retail Goods"
        }
    ],
    "sg:phone":"+1 931 582 3136",
    "sg:postcode":"37101",
    "sg:province":"TN",
    "wof:name":"Bucksnort Boot Outlet",
    "wof:placetype":"venue"
},
  "geometry": {"coordinates":[-87.639752,36.039557],"type":"Point"}
}