{
  "type": "Feature",
  "properties": {
    "iso:country":"US",
    "sg:address":"7324 Meadow Creek Trl",
    "sg:city":"Knoxville",
    "sg:classifiers":[
        {
            "category":"Food & Beverages",
            "subcategory":"Fruits & Vegetables",
            "type":"Retail Goods"
        }
    ],
    "sg:phone":"+1 865 531 4876",
    "sg:postcode":"37931",
    "sg:province":"TN",
    "sg:tags":[
        "produce"
    ],
    "wof:name":"Proctor Hensley",
    "wof:placetype":"venue"
},
  "geometry": {"coordinates":[-84.109002,35.988777],"type":"Point"}
}