{
  "type": "Feature",
  "properties": {
    "iso:country":"US",
    "sg:address":"505 E Main Blvd",
    "sg:city":"Church Hill",
    "sg:phone":"+1 423 357 2226",
    "sg:postcode":"37642",
    "sg:province":"TN",
    "sg:tags":[
        "machine",
        "parts",
        "vending",
        "supply"
    ],
    "wof:name":"Crown Vending Coffee Svc",
    "wof:placetype":"venue"
},
  "geometry": {"coordinates":[-82.688537,36.528108],"type":"Point"}
}