{
  "type": "Feature",
  "properties": {
    "iso:country":"US",
    "sg:address":"60 S Auburndale St",
    "sg:city":"Memphis",
    "sg:classifiers":[
        {
            "category":"Organizations",
            "subcategory":"Religious Organization",
            "type":"Services"
        }
    ],
    "sg:phone":"+1 901 272 2808",
    "sg:postcode":"38104",
    "sg:province":"TN",
    "sg:tags":[
        "monastery",
        "convent"
    ],
    "wof:name":"Marist Missionary Sisters",
    "wof:placetype":"venue"
},
  "geometry": {"coordinates":[-90.002419,35.137239],"type":"Point"}
}