{
  "type": "Feature",
  "properties": {
    "iso:country":"US",
    "sg:address":"2950 Michigan Ave Rd NE",
    "sg:city":"Cleveland",
    "sg:classifiers":[
        {
            "category":"Retail",
            "subcategory":"Laundry & Dry Cleaning",
            "type":"Services"
        }
    ],
    "sg:phone":"+1 423 614 0720",
    "sg:postcode":"37323",
    "sg:province":"TN",
    "sg:tags":[
        "uniform",
        "supply"
    ],
    "sg:website":"www.amuniform.com",
    "wof:name":"American Uniform Co",
    "wof:placetype":"venue"
},
  "geometry": {"coordinates":[-84.824561,35.167485],"type":"Point"}
}