{
  "type": "Feature",
  "properties": {
    "iso:country":"US",
    "sg:address":"400 Main St W",
    "sg:city":"Knoxville",
    "sg:classifiers":[
        {
            "category":"Government",
            "subcategory":"Office",
            "type":"Public Place"
        }
    ],
    "sg:phone":"+1 865 215 2350",
    "sg:postcode":"37902",
    "sg:province":"TN",
    "sg:tags":[
        "county",
        "taxation"
    ],
    "sg:website":"www.knoxcounty.org",
    "wof:name":"KNOX County Finance Dept",
    "wof:placetype":"venue"
},
  "geometry": {"coordinates":[-83.91838199999999,35.96093],"type":"Point"}
}