{
  "type": "Feature",
  "properties": {
    "iso:country":"US",
    "sg:address":"748 Tell St",
    "sg:city":"Athens",
    "sg:classifiers":[
        {
            "category":"Health Services",
            "subcategory":"Hospital",
            "type":"Services"
        }
    ],
    "sg:phone":"+1 423 744 8734",
    "sg:postcode":"37303",
    "sg:province":"TN",
    "sg:tags":[
        "mental"
    ],
    "wof:name":"Daystar Counseling Ctr",
    "wof:placetype":"venue"
},
  "geometry": {"coordinates":[-84.605041,35.442823],"type":"Point"}
}