{
  "type": "Feature",
  "properties": {
    "addr:full":"10923 Parkside Dr Knoxville TN 37934",
    "addr:housenumber":"10923",
    "addr:postcode":"37934",
    "addr:street":"Parkside Dr",
    "iso:country":"US",
    "sg:address":"10923 Parkside Dr",
    "sg:city":"Knoxville",
    "sg:phone":"+1 865 966 4392",
    "sg:postcode":"37934",
    "sg:province":"TN",
    "sg:website":"http://www.olivegarden.com",
    "wof:name":"Olive Garden",
    "wof:placetype":"venue"
},
  "geometry": {"coordinates":[-84.147713,35.90295],"type":"Point"}
}