{
  "type": "Feature",
  "properties": {
    "iso:country":"US",
    "sg:address":"1420 Donelson Pike Suite B12",
    "sg:city":"Nashville",
    "sg:classifiers":[
        {
            "category":"Shopping",
            "subcategory":"Stationery & Office Supplies",
            "type":"Retail Goods"
        },
        {
            "category":"Retail",
            "subcategory":"Repair Shop",
            "type":"Services"
        },
        {
            "category":"Shopping",
            "subcategory":"Computers & Home Electronics",
            "type":"Retail Goods"
        }
    ],
    "sg:phone":"+1 901 737 8910",
    "sg:postcode":"37217",
    "sg:province":"TN",
    "sg:tags":[
        "machine",
        "copy",
        "printer"
    ],
    "sg:website":"http://findxeroxagents.com/Copiers-in-nashville-tennessee_1126",
    "wof:name":"Xmc- Nashville",
    "wof:placetype":"venue"
},
  "geometry": {"coordinates":[-86.677795,36.095045],"type":"Point"}
}