{
  "type": "Feature",
  "properties": {
    "addr:full":"1329 Gunbarrel Rd Chattanooga TN 37421",
    "addr:postcode":"37421",
    "addr:street":"1329 Gunbarrel Rd",
    "iso:country":"US",
    "sg:address":"1329 Gunbarrel Rd",
    "sg:city":"Chattanooga",
    "sg:classifiers":[
        {
            "category":"Communications",
            "subcategory":"Film & Video Production",
            "type":"Services"
        }
    ],
    "sg:phone":"+1 423 400 4177",
    "sg:postcode":"37421",
    "sg:province":"TN",
    "sg:tags":[
        "motion"
    ],
    "wof:name":"Media Results",
    "wof:placetype":"venue"
},
  "geometry": {"coordinates":[-85.16522399999999,35.012464],"type":"Point"}
}