{
  "type": "Feature",
  "properties": {
    "addr:full":"193 Dr Hess Rd Bells TN 38006",
    "addr:housenumber":"193",
    "addr:postcode":"38006",
    "addr:street":"Dr Hess Rd",
    "iso:country":"US",
    "sg:address":"193 Dr Hess Rd",
    "sg:city":"Bells",
    "sg:phone":"+1 731 772 3529",
    "sg:postcode":"38006",
    "sg:province":"TN",
    "sg:tags":[
        "farm",
        "cotton"
    ],
    "wof:name":"Everett Williams",
    "wof:placetype":"venue"
},
  "geometry": {"coordinates":[-89.119534,35.590467],"type":"Point"}
}