{
  "type": "Feature",
  "properties": {
    "iso:country":"US",
    "sg:address":"1639 Lamb Rd",
    "sg:city":"Maryville",
    "sg:classifiers":[
        {
            "category":"Shopping",
            "subcategory":"Florist",
            "type":"Retail Goods"
        }
    ],
    "sg:phone":"+1 865 983 8279",
    "sg:postcode":"37803",
    "sg:province":"TN",
    "wof:name":"D's Flowers & Things",
    "wof:placetype":"venue"
},
  "geometry": {"coordinates":[-84.027637,35.646095],"type":"Point"}
}