{
  "type": "Feature",
  "properties": {
    "iso:country":"US",
    "sg:address":"134 Maryville Pike",
    "sg:city":"Knoxville",
    "sg:classifiers":[
        {
            "category":"Personal",
            "subcategory":"Beauty Salon",
            "type":"Services"
        }
    ],
    "sg:phone":"+1 865 579 5288",
    "sg:postcode":"37920",
    "sg:province":"TN",
    "wof:name":"Unique Cuts & Styles",
    "wof:placetype":"venue"
},
  "geometry": {"coordinates":[-83.912267,35.941326],"type":"Point"}
}