{
  "type": "Feature",
  "properties": {
    "iso:country":"US",
    "sg:address":"7544 Lakeview Dr",
    "sg:city":"Nashville",
    "sg:classifiers":[
        {
            "category":"Food & Beverages",
            "subcategory":"Bakery",
            "type":"Retail Goods"
        }
    ],
    "sg:phone":"+1 615 356 3746",
    "sg:postcode":"37209",
    "sg:province":"TN",
    "sg:tags":[
        "cake",
        "decorating"
    ],
    "wof:name":"Cake Creations By Claudette",
    "wof:placetype":"venue"
},
  "geometry": {"coordinates":[-86.954841,36.158024],"type":"Point"}
}