{
  "type": "Feature",
  "properties": {
    "addr:full":"505 Tennessee St Ste 117 Memphis TN 38103",
    "addr:housenumber":"505",
    "addr:postcode":"38103",
    "addr:street":"Tennessee St Ste 117",
    "iso:country":"US",
    "sg:address":"505 Tennessee St Ste 117",
    "sg:city":"Memphis",
    "sg:classifiers":[
        {
            "category":"Real Estate",
            "subcategory":"Architect",
            "type":"Services"
        }
    ],
    "sg:phone":"+1 901 526 5523",
    "sg:postcode":"38103",
    "sg:province":"TN",
    "sg:tags":[
        "specification",
        "construction",
        "architectural",
        "engineer"
    ],
    "wof:name":"Atkins Jr, Bemis - Atkins Buchner Price Archts",
    "wof:placetype":"venue"
},
  "geometry": {"coordinates":[-90.062569,35.133621],"type":"Point"}
}