{
  "type": "Feature",
  "properties": {
    "iso:country":"US",
    "sg:address":"1503 Mcdonald Rd",
    "sg:city":"Chattanooga",
    "sg:classifiers":[
        {
            "category":"Banks & Credit Unions",
            "subcategory":"Investment Brokerage",
            "type":"Services"
        }
    ],
    "sg:phone":"+1 423 893 6988",
    "sg:postcode":"37412",
    "sg:province":"TN",
    "sg:tags":[
        "tape",
        "video",
        "sale",
        "dvds-rental"
    ],
    "wof:name":"Sues Market & Video",
    "wof:placetype":"venue"
},
  "geometry": {"coordinates":[-85.206818,34.98909],"type":"Point"}
}