{
  "type": "Feature",
  "properties": {
    "addr:full":"3507 W Market St Johnson City TN 37604",
    "addr:housenumber":"3507",
    "addr:postcode":"37604",
    "addr:street":"W Market St",
    "iso:country":"US",
    "sg:address":"3507 W Market St",
    "sg:city":"Johnson City",
    "sg:classifiers":[
        {
            "category":"Real Estate",
            "subcategory":"Real Estate Agent",
            "type":"Services"
        }
    ],
    "sg:phone":"+1 423 928 6033",
    "sg:postcode":"37604",
    "sg:province":"TN",
    "wof:name":"Squibb Land Co",
    "wof:placetype":"venue"
},
  "geometry": {"coordinates":[-82.418131,36.312777],"type":"Point"}
}