{
  "type": "Feature",
  "properties": {
    "iso:country":"US",
    "sg:address":"65 Germantown Ct",
    "sg:city":"Cordova",
    "sg:classifiers":[
        {
            "category":"Health Services",
            "subcategory":"Health Practitioner",
            "type":"Services"
        }
    ],
    "sg:phone":"+1 901 624 3939",
    "sg:postcode":"38018",
    "sg:province":"TN",
    "sg:tags":[
        "psychologist"
    ],
    "wof:name":"Denise Landau PHD",
    "wof:placetype":"venue"
},
  "geometry": {"coordinates":[-89.795649,35.129621],"type":"Point"}
}