{
  "type": "Feature",
  "properties": {
    "iso:country":"US",
    "sg:address":"3600 Keith St",
    "sg:city":"Cleveland",
    "sg:classifiers":[
        {
            "category":"Wholesale",
            "subcategory":"Electrical",
            "type":"Manufacturing & Wholesale Goods"
        }
    ],
    "sg:phone":"+1 423 559 0728",
    "sg:postcode":"37312",
    "sg:province":"TN",
    "sg:tags":[
        "fire",
        "equipment",
        "protection"
    ],
    "wof:name":"Tame The Flame",
    "wof:placetype":"venue"
},
  "geometry": {"coordinates":[-84.863247,35.191337],"type":"Point"}
}