{
  "type": "Feature",
  "properties": {
    "iso:country":"US",
    "sg:address":"382 Mountain View Rd",
    "sg:city":"Church Hill",
    "sg:classifiers":[
        {
            "category":"Professional",
            "subcategory":"Business Services",
            "type":"Services"
        }
    ],
    "sg:phone":"+1 423 357 3449",
    "sg:postcode":"37642",
    "sg:province":"TN",
    "wof:name":"Fast Lane Enterprise",
    "wof:placetype":"venue"
},
  "geometry": {"coordinates":[-82.703819,36.485565],"type":"Point"}
}