{
  "type": "Feature",
  "properties": {
    "addr:full":"84 Shoemake Rd Crossville TN 38571",
    "addr:housenumber":"84",
    "addr:postcode":"38571",
    "addr:street":"Shoemake Rd",
    "iso:country":"US",
    "sg:address":"84 Shoemake Rd",
    "sg:city":"Crossville",
    "sg:classifiers":[
        {
            "category":"Building & Trades",
            "subcategory":"Landscaping Services",
            "type":"Services"
        }
    ],
    "sg:phone":"+1 931 456 9861",
    "sg:postcode":"38571",
    "sg:province":"TN",
    "sg:tags":[
        "tree"
    ],
    "wof:name":"Bowman Tree Svc",
    "wof:placetype":"venue"
},
  "geometry": {"coordinates":[-85.08340800000001,36.013548],"type":"Point"}
}