{
  "type": "Feature",
  "properties": {
    "iso:country":"US",
    "sg:address":"2700 Lake Rd",
    "sg:city":"Dyersburg",
    "sg:classifiers":[
        {
            "category":"Shopping",
            "subcategory":"Clothing, Apparel, & Fashions",
            "type":"Retail Goods"
        }
    ],
    "sg:phone":"+1 731 285 8010",
    "sg:postcode":"38024",
    "sg:province":"TN",
    "wof:name":"Southern Heritage",
    "wof:placetype":"venue"
},
  "geometry": {"coordinates":[-89.39605299999999,36.066607],"type":"Point"}
}