{
  "type": "Feature",
  "properties": {
    "addr:full":"719 Space Park S Nashville TN 37211",
    "addr:postcode":"37211",
    "addr:street":"S",
    "iso:country":"US",
    "sg:address":"719 Space Park S",
    "sg:city":"Nashville",
    "sg:classifiers":[
        {
            "category":"Autos & Motor Vehicles",
            "subcategory":"Auto Supplies",
            "type":"Retail Goods"
        }
    ],
    "sg:phone":"+1 615 727 0040",
    "sg:postcode":"37211",
    "sg:province":"TN",
    "sg:tags":[
        "tire"
    ],
    "wof:name":"Soliddeal Industrial Tire",
    "wof:placetype":"venue"
},
  "geometry": {"coordinates":[-86.70804699999999,36.100036],"type":"Point"}
}