{
  "type": "Feature",
  "properties": {
    "iso:country":"US",
    "sg:address":"311 Ellis Ave",
    "sg:city":"Maryville",
    "sg:classifiers":[
        {
            "category":"Real Estate",
            "subcategory":"Developer",
            "type":"Services"
        },
        {
            "category":"Building & Trades",
            "subcategory":"Construction",
            "type":"Services"
        }
    ],
    "sg:phone":"+1 865 984 2917",
    "sg:postcode":"37804",
    "sg:province":"TN",
    "sg:tags":[
        "contractor"
    ],
    "wof:name":"Lynn Sanford Development",
    "wof:placetype":"venue"
},
  "geometry": {"coordinates":[-83.967336,35.756648],"type":"Point"}
}