{
  "type": "Feature",
  "properties": {
    "iso:country":"US",
    "sg:address":"412 Sanders Bluff Rd",
    "sg:city":"Humboldt",
    "sg:classifiers":[
        {
            "category":"Building & Trades",
            "subcategory":"Electrical",
            "type":"Services"
        }
    ],
    "sg:phone":"+1 731 467 1421",
    "sg:postcode":"38343",
    "sg:province":"TN",
    "sg:tags":[
        "electric",
        "contractor"
    ],
    "wof:name":"REC Co Inc",
    "wof:placetype":"venue"
},
  "geometry": {"coordinates":[-88.864859,35.769342],"type":"Point"}
}