{
  "type": "Feature",
  "properties": {
    "iso:country":"US",
    "sg:address":"2686 Liberty Valley Rd",
    "sg:city":"Lewisburg",
    "sg:classifiers":[
        {
            "category":"Professional",
            "type":"Services"
        }
    ],
    "sg:phone":"+1 931 276 2826",
    "sg:postcode":"37091",
    "sg:province":"TN",
    "wof:name":"Pat J Green",
    "wof:placetype":"venue"
},
  "geometry": {"coordinates":[-86.67372,35.416156],"type":"Point"}
}