{
  "type": "Feature",
  "properties": {
    "iso:country":"US",
    "sg:address":"115 Luyben Hills Rd",
    "sg:city":"Kingston Springs",
    "sg:classifiers":[
        {
            "category":"Restaurant",
            "type":"Food & Drink"
        }
    ],
    "sg:phone":"+1 615 952 2095",
    "sg:postcode":"37082",
    "sg:province":"TN",
    "wof:name":"Lighthouse Family",
    "wof:placetype":"venue"
},
  "geometry": {"coordinates":[-87.100814,36.087334],"type":"Point"}
}