{
  "type": "Feature",
  "properties": {
    "iso:country":"US",
    "sg:address":"3675 New Getwell Rd",
    "sg:city":"Memphis",
    "sg:classifiers":[
        {
            "category":"Wholesale",
            "subcategory":"Durable Goods & Equipment",
            "type":"Manufacturing & Wholesale Goods"
        }
    ],
    "sg:phone":"+1 901 366 1318",
    "sg:postcode":"38118",
    "sg:province":"TN",
    "sg:tags":[
        "representative",
        "manufacturer"
    ],
    "wof:name":"Gap & Assoc",
    "wof:placetype":"venue"
},
  "geometry": {"coordinates":[-89.933369,35.047387],"type":"Point"}
}