{
  "type": "Feature",
  "properties": {
    "addr:full":"2101 N Berrys Chapel Rd Franklin TN 37069",
    "addr:housenumber":"2101",
    "addr:postcode":"37069",
    "addr:street":"N Berrys Chapel Rd",
    "iso:country":"US",
    "sg:address":"2101 N Berrys Chapel Rd",
    "sg:city":"Franklin",
    "sg:classifiers":[
        {
            "category":"Professional",
            "subcategory":"Business Services",
            "type":"Services"
        }
    ],
    "sg:phone":"+1 615 791 9966",
    "sg:postcode":"37069",
    "sg:province":"TN",
    "wof:name":"Eakes Enterprises LLC",
    "wof:placetype":"venue"
},
  "geometry": {"coordinates":[-86.876063,35.978317],"type":"Point"}
}