{
  "type": "Feature",
  "properties": {
    "iso:country":"US",
    "sg:address":"7031 Lee Hwy",
    "sg:city":"Chattanooga",
    "sg:classifiers":[
        {
            "category":"Autos & Motor Vehicles",
            "subcategory":"Boat Sales",
            "type":"Retail Goods"
        }
    ],
    "sg:phone":"+1 423 855 7373",
    "sg:postcode":"37421",
    "sg:province":"TN",
    "sg:tags":[
        "dealer",
        "sales"
    ],
    "wof:name":"Anchor High Sales",
    "wof:placetype":"venue"
},
  "geometry": {"coordinates":[-85.159364,35.046899],"type":"Point"}
}