{
  "type": "Feature",
  "properties": {
    "iso:country":"US",
    "sg:address":"316 S Anderson St",
    "sg:city":"Tullahoma",
    "sg:classifiers":[
        {
            "category":"Building & Trades",
            "subcategory":"Construction",
            "type":"Services"
        }
    ],
    "sg:phone":"+1 931 455 8174",
    "sg:postcode":"37388",
    "sg:province":"TN",
    "sg:tags":[
        "merchandise",
        "animal",
        "contractor"
    ],
    "wof:name":"Bedford Quality Fencing",
    "wof:placetype":"venue"
},
  "geometry": {"coordinates":[-86.203,35.362929],"type":"Point"}
}