{
  "type": "Feature",
  "properties": {
    "iso:country":"US",
    "sg:address":"248 N McLean Blvd",
    "sg:city":"Memphis",
    "sg:classifiers":[
        {
            "category":"Organizations",
            "subcategory":"Membership Organization",
            "type":"Services"
        }
    ],
    "sg:phone":"+1 901 278 8332",
    "sg:postcode":"38112",
    "sg:province":"TN",
    "wof:name":"Key Mid-America Inc",
    "wof:placetype":"venue"
},
  "geometry": {"coordinates":[-89.99831399999999,35.146357],"type":"Point"}
}