{
  "type": "Feature",
  "properties": {
    "addr:full":"501 19th St Knoxville TN 37916",
    "addr:housenumber":"501",
    "addr:postcode":"37916",
    "addr:street":"19Th St",
    "iso:country":"US",
    "sg:address":"501 19th St",
    "sg:city":"Knoxville",
    "sg:classifiers":[
        {
            "category":"Health Services",
            "subcategory":"Doctor",
            "type":"Services"
        }
    ],
    "sg:phone":"+1 865 541 1810",
    "sg:postcode":"37916",
    "sg:province":"TN",
    "sg:tags":[
        "physician",
        "surgeon"
    ],
    "wof:name":"Lacy E Harville MD",
    "wof:placetype":"venue"
},
  "geometry": {"coordinates":[-83.93621,35.957171],"type":"Point"}
}