{
  "type": "Feature",
  "properties": {
    "iso:country":"US",
    "sg:address":"1870 Dunbar Rd",
    "sg:city":"Woodlawn",
    "sg:classifiers":[
        {
            "category":"Organizations",
            "subcategory":"Religious Organization",
            "type":"Services"
        }
    ],
    "sg:phone":"+1 931 503 2045",
    "sg:postcode":"37191",
    "sg:province":"TN",
    "sg:tags":[
        "church"
    ],
    "wof:name":"Dotsonville Baptist Church",
    "wof:placetype":"venue"
},
  "geometry": {"coordinates":[-87.487092,36.476988],"type":"Point"}
}