{
  "type": "Feature",
  "properties": {
    "addr:full":"1655 Sams Creek Rd Ashland City TN 37015",
    "addr:housenumber":"1655",
    "addr:postcode":"37015",
    "addr:street":"Sams Creek Rd",
    "iso:country":"US",
    "sg:address":"1655 Sams Creek Rd",
    "sg:city":"Ashland City",
    "sg:classifiers":[
        {
            "category":"Professional",
            "type":"Services"
        }
    ],
    "sg:phone":"+1 615 792 7699",
    "sg:postcode":"37015",
    "sg:province":"TN",
    "wof:name":"Douglas Logan",
    "wof:placetype":"venue"
},
  "geometry": {"coordinates":[-87.02793,36.186524],"type":"Point"}
}