{
  "type": "Feature",
  "properties": {
    "iso:country":"US",
    "sg:address":"2721 Lebanon Pike",
    "sg:city":"Nashville",
    "sg:classifiers":[
        {
            "category":"Shopping",
            "subcategory":"Clothing, Apparel, & Fashions",
            "type":"Retail Goods"
        }
    ],
    "sg:phone":"+1 615 883 1530",
    "sg:postcode":"37214",
    "sg:province":"TN",
    "sg:tags":[
        "uniform"
    ],
    "wof:name":"Scrub Hub Of Nashville",
    "wof:placetype":"venue"
},
  "geometry": {"coordinates":[-86.66816300000001,36.168923],"type":"Point"}
}