{
  "type": "Feature",
  "properties": {
    "iso:country":"US",
    "sg:address":"8159 Standifer Gap Rd",
    "sg:city":"Chattanooga",
    "sg:classifiers":[
        {
            "category":"Organizations",
            "subcategory":"Religious Organization",
            "type":"Services"
        }
    ],
    "sg:phone":"+1 423 892 8596",
    "sg:postcode":"37421",
    "sg:province":"TN",
    "wof:name":"Standifer Gap Baptist Church",
    "wof:placetype":"venue"
},
  "geometry": {"coordinates":[-85.113146,35.041531],"type":"Point"}
}