{
  "type": "Feature",
  "properties": {
    "iso:country":"US",
    "sg:address":"201 Court Ave",
    "sg:city":"Memphis",
    "sg:classifiers":[
        {
            "category":"Organizations",
            "subcategory":"Professional Association",
            "type":"Services"
        }
    ],
    "sg:phone":"+1 901 527 3621",
    "sg:postcode":"38103",
    "sg:province":"TN",
    "wof:name":"Downtown Neighborhood Assn",
    "wof:placetype":"venue"
},
  "geometry": {"coordinates":[-90.048119,35.14498],"type":"Point"}
}