{
  "type": "Feature",
  "properties": {
    "iso:country":"US",
    "sg:address":"2194 Clinton Hwy",
    "sg:city":"Powell",
    "sg:classifiers":[
        {
            "category":"Government",
            "subcategory":"Fire Station",
            "type":"Public Place"
        }
    ],
    "sg:phone":"+1 865 945 1314",
    "sg:postcode":"37849",
    "sg:province":"TN",
    "sg:tags":[
        "protection"
    ],
    "sg:website":"www.claxtonvfd.org",
    "wof:name":"Claxton Volunteer Fire Dept",
    "wof:placetype":"venue"
},
  "geometry": {"coordinates":[-84.117172,36.048759],"type":"Point"}
}