{
  "type": "Feature",
  "properties": {
    "iso:country":"US",
    "sg:address":"7191 Plantation Cir",
    "sg:city":"Germantown",
    "sg:classifiers":[
        {
            "category":"Wholesale",
            "subcategory":"Machinery & Supplies",
            "type":"Manufacturing & Wholesale Goods"
        },
        {
            "category":"Freight",
            "type":"Transportation"
        }
    ],
    "sg:phone":"+1 901 754 1261",
    "sg:postcode":"38138",
    "sg:province":"TN",
    "sg:tags":[
        "aircraft",
        "broker",
        "arrangement"
    ],
    "wof:name":"Atchley & Associates",
    "wof:placetype":"venue"
},
  "geometry": {"coordinates":[-89.821817,35.094728],"type":"Point"}
}