{
  "type": "Feature",
  "properties": {
    "addr:full":"1283 Walter Head Rd Cedar Hill TN 37032",
    "addr:housenumber":"1283",
    "addr:postcode":"37032",
    "addr:street":"Walter Head Rd",
    "iso:country":"US",
    "sg:address":"1283 Walter Head Rd",
    "sg:city":"Cedar Hill",
    "sg:classifiers":[
        {
            "category":"Building & Trades",
            "subcategory":"Construction",
            "type":"Services"
        }
    ],
    "sg:phone":"+1 615 505 3701",
    "sg:postcode":"37032",
    "sg:province":"TN",
    "sg:tags":[
        "excavation",
        "contractor"
    ],
    "wof:name":"Clarkville Construction Co",
    "wof:placetype":"venue"
},
  "geometry": {"coordinates":[-87.125219,36.478662],"type":"Point"}
}