{
  "type": "Feature",
  "properties": {
    "iso:country":"US",
    "sg:address":"10620 State Hwy 109",
    "sg:city":"Lebanon",
    "sg:classifiers":[
        {
            "category":"Freight",
            "type":"Transportation"
        }
    ],
    "sg:phone":"+1 615 444 4800",
    "sg:postcode":"37087",
    "sg:province":"TN",
    "sg:tags":[
        "special",
        "merchandise"
    ],
    "wof:name":"Advance Stor-N-Loc",
    "wof:placetype":"venue"
},
  "geometry": {"coordinates":[-86.436395,36.330903],"type":"Point"}
}