{
  "type": "Feature",
  "properties": {
    "addr:full":"44 Crosswinds Blvd Crossville TN 38555",
    "addr:housenumber":"44",
    "addr:postcode":"38555",
    "addr:street":"Crosswinds Blvd",
    "iso:country":"US",
    "sg:address":"44 Crosswinds Blvd",
    "sg:city":"Crossville",
    "sg:classifiers":[
        {
            "category":"Restaurant",
            "type":"Food & Drink"
        }
    ],
    "sg:phone":"+1 931 707 8229",
    "sg:postcode":"38555",
    "sg:province":"TN",
    "sg:tags":[
        "parlor",
        "ice",
        "cream"
    ],
    "wof:name":"TCBY",
    "wof:placetype":"venue"
},
  "geometry": {"coordinates":[-85.08734200000001,35.760802],"type":"Point"}
}