{
  "type": "Feature",
  "properties": {
    "iso:country":"US",
    "sg:address":"1702 S Rutherford Blvd",
    "sg:city":"Murfreesboro",
    "sg:classifiers":[
        {
            "category":"Restaurant",
            "type":"Food & Drink"
        }
    ],
    "sg:menulink":"http://www.allmenus.com/tn/murfreesboro/116204-quiznos-sub/menu/",
    "sg:phone":"+1 615 494 0536",
    "sg:postcode":"37130",
    "sg:province":"TN",
    "sg:tags":[
        "wrap",
        "american",
        "sandwich"
    ],
    "wof:name":"Quiznos Sub",
    "wof:placetype":"venue"
},
  "geometry": {"coordinates":[-86.368771,35.811378],"type":"Point"}
}