{
  "type": "Feature",
  "properties": {
    "addr:full":"2214 Windswept View Way Sevierville TN 37876",
    "addr:housenumber":"2214",
    "addr:postcode":"37876",
    "addr:street":"Windswept View Way",
    "iso:country":"US",
    "sg:address":"2214 Windswept View Way",
    "sg:city":"Sevierville",
    "sg:classifiers":[
        {
            "category":"Building & Trades",
            "subcategory":"Construction",
            "type":"Services"
        }
    ],
    "sg:phone":"+1 865 774 8862",
    "sg:postcode":"37876",
    "sg:province":"TN",
    "sg:tags":[
        "contractor"
    ],
    "wof:name":"Building Resources Inc",
    "wof:placetype":"venue"
},
  "geometry": {"coordinates":[-83.654279,35.797314],"type":"Point"}
}