{
  "type": "Feature",
  "properties": {
    "iso:country":"US",
    "sg:address":"5851 Bethel Rd",
    "sg:city":"Pulaski",
    "sg:classifiers":[
        {
            "category":"Professional",
            "subcategory":"Business Services",
            "type":"Services"
        }
    ],
    "sg:phone":"+1 931 424 3864",
    "sg:postcode":"38478",
    "sg:province":"TN",
    "wof:name":"Powers Express",
    "wof:placetype":"venue"
},
  "geometry": {"coordinates":[-87.030136,35.086794],"type":"Point"}
}