{
  "type": "Feature",
  "properties": {
    "iso:country":"US",
    "sg:address":"1219 Golf Course Rd",
    "sg:city":"Newport",
    "sg:classifiers":[
        {
            "category":"Freight",
            "type":"Transportation"
        }
    ],
    "sg:phone":"+1 423 625 1222",
    "sg:postcode":"37821",
    "sg:province":"TN",
    "sg:tags":[
        "distance",
        "long",
        "trucking"
    ],
    "wof:name":"Payne Trucking Of Tennessee",
    "wof:placetype":"venue"
},
  "geometry": {"coordinates":[-83.185446,35.93245],"type":"Point"}
}