{
  "type": "Feature",
  "properties": {
    "iso:country":"US",
    "sg:address":"710 W Race St",
    "sg:city":"Kingston",
    "sg:classifiers":[
        {
            "category":"Restaurant",
            "type":"Food & Drink"
        }
    ],
    "sg:phone":"+1 865 376 9027",
    "sg:postcode":"37763",
    "sg:province":"TN",
    "sg:tags":[
        "eating"
    ],
    "wof:name":"Roadside Cafe",
    "wof:placetype":"venue"
},
  "geometry": {"coordinates":[-84.52341,35.883322],"type":"Point"}
}