{
  "type": "Feature",
  "properties": {
    "iso:country":"US",
    "sg:address":"401 Anderson Hollow Rd",
    "sg:city":"Huntsville",
    "sg:classifiers":[
        {
            "category":"Retail",
            "subcategory":"Repair Shop",
            "type":"Services"
        },
        {
            "category":"Building & Trades",
            "subcategory":"Construction",
            "type":"Services"
        }
    ],
    "sg:phone":"+1 423 663 3407",
    "sg:postcode":"37756",
    "sg:province":"TN",
    "sg:tags":[
        "fabricator",
        "welding"
    ],
    "wof:name":"Shafer & Shafer LLC",
    "wof:placetype":"venue"
},
  "geometry": {"coordinates":[-84.375221,36.377581],"type":"Point"}
}