{
  "type": "Feature",
  "properties": {
    "addr:full":"5647 Brainerd Rd Chattanooga TN 37411",
    "addr:housenumber":"5647",
    "addr:postcode":"37411",
    "addr:street":"Brainerd Rd",
    "iso:country":"US",
    "sg:address":"5647 Brainerd Rd",
    "sg:city":"Chattanooga",
    "sg:classifiers":[
        {
            "category":"Restaurant",
            "type":"Food & Drink"
        }
    ],
    "sg:phone":"+1 423 553 6645",
    "sg:postcode":"37411",
    "sg:province":"TN",
    "wof:name":"Chattanooga Food & Drink",
    "wof:placetype":"venue"
},
  "geometry": {"coordinates":[-85.215091,35.011343],"type":"Point"}
}