{
  "type": "Feature",
  "properties": {
    "iso:country":"US",
    "sg:address":"10025 Parkside Dr",
    "sg:city":"Knoxville",
    "sg:classifiers":[
        {
            "category":"Home & Garden",
            "subcategory":"Building Materials",
            "type":"Retail Goods"
        }
    ],
    "sg:phone":"+1 865 675 2506",
    "sg:postcode":"37922",
    "sg:province":"TN",
    "wof:name":"Knoxville Wall Paper",
    "wof:placetype":"venue"
},
  "geometry": {"coordinates":[-84.116446,35.909776],"type":"Point"}
}