{
  "type": "Feature",
  "properties": {
    "iso:country":"US",
    "sg:address":"5504 Middlebrook Pike",
    "sg:city":"Knoxville",
    "sg:classifiers":[
        {
            "category":"Personal",
            "subcategory":"Beauty Salon",
            "type":"Services"
        }
    ],
    "sg:phone":"+1 865 588 1356",
    "sg:postcode":"37921",
    "sg:province":"TN",
    "sg:tags":[
        "shop"
    ],
    "wof:name":"Jessie's Hair Salon",
    "wof:placetype":"venue"
},
  "geometry": {"coordinates":[-84.011731,35.95271],"type":"Point"}
}