{
  "type": "Feature",
  "properties": {
    "iso:country":"US",
    "sg:address":"391 S 3rd St",
    "sg:city":"Memphis",
    "sg:classifiers":[
        {
            "category":"Freight",
            "type":"Transportation"
        },
        {
            "category":"Retail",
            "subcategory":"Auto Repair",
            "type":"Services"
        }
    ],
    "sg:phone":"+1 901 523 7039",
    "sg:postcode":"38106",
    "sg:province":"TN",
    "sg:tags":[
        "engine",
        "distance",
        "diesel",
        "long",
        "trucking",
        "truck"
    ],
    "wof:name":"Tristate Transportation Svcs",
    "wof:placetype":"venue"
},
  "geometry": {"coordinates":[-90.054897,35.135076],"type":"Point"}
}