{
  "type": "Feature",
  "properties": {
    "iso:country":"US",
    "sg:address":"807 River Rd",
    "sg:city":"Jacksboro",
    "sg:classifiers":[
        {
            "category":"Government",
            "subcategory":"Fire Station",
            "type":"Public Place"
        }
    ],
    "sg:phone":"+1 423 562 7333",
    "sg:postcode":"37757",
    "sg:province":"TN",
    "sg:tags":[
        "protection"
    ],
    "wof:name":"Fire Hall",
    "wof:placetype":"venue"
},
  "geometry": {"coordinates":[-84.147558,36.326546],"type":"Point"}
}