{
  "type": "Feature",
  "properties": {
    "iso:country":"US",
    "sg:address":"1318 Hardwood Trl",
    "sg:city":"Cordova",
    "sg:classifiers":[
        {
            "category":"Real Estate",
            "subcategory":"Real Estate Agent",
            "type":"Services"
        }
    ],
    "sg:phone":"+1 901 758 9777",
    "sg:postcode":"38016",
    "sg:province":"TN",
    "wof:name":"Lenox Realty",
    "wof:placetype":"venue"
},
  "geometry": {"coordinates":[-89.790952,35.160875],"type":"Point"}
}