{
  "type": "Feature",
  "properties": {
    "addr:full":"1765 Hollywood Dr Jackson TN 38305",
    "addr:housenumber":"1765",
    "addr:postcode":"38305",
    "addr:street":"Hollywood Dr",
    "iso:country":"US",
    "sg:address":"1765 Hollywood Dr",
    "sg:city":"Jackson",
    "sg:classifiers":[
        {
            "category":"Professional",
            "subcategory":"Business Services",
            "type":"Services"
        }
    ],
    "sg:phone":"+1 731 664 1575",
    "sg:postcode":"38305",
    "sg:province":"TN",
    "wof:name":"United States Amateur Box",
    "wof:placetype":"venue"
},
  "geometry": {"coordinates":[-88.858062,35.643901],"type":"Point"}
}