{
  "type": "Feature",
  "properties": {
    "iso:country":"US",
    "sg:address":"1000 S Jefferson Ave",
    "sg:city":"Cookeville",
    "sg:classifiers":[
        {
            "category":"Shopping",
            "type":"Retail Goods"
        }
    ],
    "sg:phone":"+1 931 528 9362",
    "sg:postcode":"38501",
    "sg:province":"TN",
    "sg:tags":[
        "trade",
        "merchandise",
        "contractor"
    ],
    "wof:name":"Pool & Spa Depot Outlet",
    "wof:placetype":"venue"
},
  "geometry": {"coordinates":[-85.501693,36.138382],"type":"Point"}
}