{
  "type": "Feature",
  "properties": {
    "iso:country":"US",
    "sg:address":"3177 Newport Hwy",
    "sg:city":"Sevierville",
    "sg:classifiers":[
        {
            "category":"Autos & Motor Vehicles",
            "subcategory":"Fuel & Gas Station",
            "type":"Retail Goods"
        },
        {
            "category":"Autos & Motor Vehicles",
            "subcategory":"Auto Supplies",
            "type":"Retail Goods"
        }
    ],
    "sg:phone":"+1 865 453 1163",
    "sg:postcode":"37876",
    "sg:province":"TN",
    "sg:tags":[
        "automobile",
        "au",
        "parts",
        "gasoline",
        "station"
    ],
    "wof:name":"Sammy's Auto Parts",
    "wof:placetype":"venue"
},
  "geometry": {"coordinates":[-83.415908,35.905633],"type":"Point"}
}