{
  "type": "Feature",
  "properties": {
    "addr:full":"6370 Hickory Valley Rd Heiskell TN 37754",
    "addr:housenumber":"6370",
    "addr:postcode":"37754",
    "addr:street":"Hickory Valley Rd",
    "iso:country":"US",
    "sg:address":"6370 Hickory Valley Rd",
    "sg:city":"Heiskell",
    "sg:classifiers":[
        {
            "category":"Retail",
            "subcategory":"Repair Shop",
            "type":"Services"
        }
    ],
    "sg:phone":"+1 865 494 7575",
    "sg:postcode":"37754",
    "sg:province":"TN",
    "sg:tags":[
        "taxidermist"
    ],
    "wof:name":"Buckshot Taxidermy",
    "wof:placetype":"venue"
},
  "geometry": {"coordinates":[-84.01628700000001,36.163933],"type":"Point"}
}