{
  "type": "Feature",
  "properties": {
    "addr:full":"502 Norris Fwy Lake City TN 37769",
    "addr:housenumber":"502",
    "addr:postcode":"37769",
    "addr:street":"Norris Fwy",
    "iso:country":"US",
    "sg:address":"502 Norris Fwy",
    "sg:city":"Lake City",
    "sg:classifiers":[
        {
            "category":"Food & Beverages",
            "subcategory":"Groceries & Convenience Stores",
            "type":"Retail Goods"
        }
    ],
    "sg:phone":"+1 865 426 6030",
    "sg:postcode":"37769",
    "sg:province":"TN",
    "wof:name":"Norris Dam BP",
    "wof:placetype":"venue"
},
  "geometry": {"coordinates":[-84.15705,36.228755],"type":"Point"}
}