{
  "type": "Feature",
  "properties": {
    "addr:full":"102 Mitchell Dr Smyrna TN 37167",
    "addr:housenumber":"102",
    "addr:postcode":"37167",
    "addr:street":"Mitchell Dr",
    "iso:country":"US",
    "sg:address":"102 Mitchell Dr",
    "sg:city":"Smyrna",
    "sg:classifiers":[
        {
            "category":"Restaurant",
            "type":"Food & Drink"
        }
    ],
    "sg:phone":"+1 615 223 6240",
    "sg:postcode":"37167",
    "sg:province":"TN",
    "sg:tags":[
        "eating"
    ],
    "wof:name":"Lc Country Kitchen Catering",
    "wof:placetype":"venue"
},
  "geometry": {"coordinates":[-86.49528100000001,36.004774],"type":"Point"}
}