{
  "type": "Feature",
  "properties": {
    "iso:country":"US",
    "sg:address":"1409 Ruth Brook Dr",
    "sg:city":"Mt Carmel",
    "sg:classifiers":[
        {
            "category":"Manufacturing",
            "subcategory":"Electronics",
            "type":"Manufacturing & Wholesale Goods"
        },
        {
            "category":"Shopping",
            "subcategory":"Computers & Home Electronics",
            "type":"Retail Goods"
        }
    ],
    "sg:phone":"+1 423 245 0005",
    "sg:postcode":"37645",
    "sg:province":"TN",
    "sg:tags":[
        "satellite",
        "mfg",
        "component",
        "system",
        "equipment",
        "electronic"
    ],
    "wof:name":"M C Satellite",
    "wof:placetype":"venue"
},
  "geometry": {"coordinates":[-82.64615499999999,36.581419],"type":"Point"}
}