{
  "type": "Feature",
  "properties": {
    "iso:country":"US",
    "sg:address":"130 W Doak Rd",
    "sg:city":"Manchester",
    "sg:classifiers":[
        {
            "category":"Shopping",
            "subcategory":"Crafts & Fabrics",
            "type":"Retail Goods"
        }
    ],
    "sg:phone":"+1 931 723 4728",
    "sg:postcode":"37355",
    "sg:province":"TN",
    "sg:tags":[
        "sewing"
    ],
    "wof:name":"Haymar Enterprises LLC",
    "wof:placetype":"venue"
},
  "geometry": {"coordinates":[-86.07676499999999,35.45621],"type":"Point"}
}