{
  "type": "Feature",
  "properties": {
    "iso:country":"US",
    "sg:address":"350 E Main St",
    "sg:city":"Adamsville",
    "sg:classifiers":[
        {
            "category":"Shopping",
            "subcategory":"Florist",
            "type":"Retail Goods"
        }
    ],
    "sg:phone":"+1 731 632 3423",
    "sg:postcode":"38310",
    "sg:province":"TN",
    "wof:name":"Nan's Flower's & Crafts",
    "wof:placetype":"venue"
},
  "geometry": {"coordinates":[-88.384449,35.235391],"type":"Point"}
}