{
  "type": "Feature",
  "properties": {
    "iso:country":"US",
    "sg:address":"140 Brookridge Trl",
    "sg:city":"Nashville",
    "sg:classifiers":[
        {
            "category":"Professional",
            "subcategory":"Business Services",
            "type":"Services"
        }
    ],
    "sg:phone":"+1 615 500 4503",
    "sg:postcode":"37211",
    "sg:province":"TN",
    "wof:name":"Classic Mailboxes By Dedrick",
    "wof:placetype":"venue"
},
  "geometry": {"coordinates":[-86.723951,36.077993],"type":"Point"}
}