{
  "type": "Feature",
  "properties": {
    "iso:country":"US",
    "sg:address":"2631 Waynesboro Hwy",
    "sg:city":"Lawrenceburg",
    "sg:classifiers":[
        {
            "category":"Retail",
            "subcategory":"Veterinary Services",
            "type":"Services"
        }
    ],
    "sg:phone":"+1 931 762 1754",
    "sg:postcode":"38464",
    "sg:province":"TN",
    "wof:name":"Large Animal Clinic Inc",
    "wof:placetype":"venue"
},
  "geometry": {"coordinates":[-87.392146,35.27541],"type":"Point"}
}