{
  "type": "Feature",
  "properties": {
    "iso:country":"US",
    "sg:address":"305 Deery St",
    "sg:city":"Shelbyville",
    "sg:classifiers":[
        {
            "category":"Retail",
            "subcategory":"Car Wash",
            "type":"Services"
        }
    ],
    "sg:phone":"+1 931 684 1034",
    "sg:postcode":"37160",
    "sg:province":"TN",
    "sg:tags":[
        "automobile",
        "detail",
        "clean"
    ],
    "wof:name":"Swing's Car Brite Ctr",
    "wof:placetype":"venue"
},
  "geometry": {"coordinates":[-86.45585199999999,35.484515],"type":"Point"}
}