{
  "type": "Feature",
  "properties": {
    "addr:full":"3525 Brick Church Pike Nashville TN 37207",
    "addr:housenumber":"3525",
    "addr:postcode":"37207",
    "addr:street":"Brick Church Pike",
    "iso:country":"US",
    "sg:address":"3525 Brick Church Pike",
    "sg:city":"Nashville",
    "sg:classifiers":[
        {
            "category":"Building & Trades",
            "subcategory":"Cleaning & Sanitation",
            "type":"Services"
        },
        {
            "category":"Retail",
            "subcategory":"Repair Shop",
            "type":"Services"
        }
    ],
    "sg:phone":"+1 615 226 7357",
    "sg:postcode":"37207",
    "sg:province":"TN",
    "sg:tags":[
        "janitor"
    ],
    "wof:name":"Jonesrific Cleaning Co",
    "wof:placetype":"venue"
},
  "geometry": {"coordinates":[-86.77677,36.258275],"type":"Point"}
}