{
  "type": "Feature",
  "properties": {
    "iso:country":"US",
    "sg:address":"45 N 3rd St Ste 201",
    "sg:city":"Memphis",
    "sg:classifiers":[
        {
            "category":"Professional",
            "subcategory":"Lawyer & Legal Services",
            "type":"Services"
        }
    ],
    "sg:phone":"+1 901 522 0050",
    "sg:postcode":"38103",
    "sg:province":"TN",
    "sg:tags":[
        "attorney",
        "practice"
    ],
    "sg:website":"http://www.mortongermany.com",
    "wof:name":"Morrell, Gary K",
    "wof:placetype":"venue"
},
  "geometry": {"coordinates":[-90.049818,35.145719],"type":"Point"}
}