{
  "type": "Feature",
  "properties": {
    "addr:full":"8349 Honey Dew Cove Cordova TN 38016",
    "addr:housenumber":"8349",
    "addr:postcode":"38016",
    "addr:street":"Honey Dew Cove",
    "iso:country":"US",
    "sg:address":"8349 Honey Dew Cove",
    "sg:city":"Cordova",
    "sg:classifiers":[
        {
            "category":"Professional",
            "type":"Services"
        }
    ],
    "sg:phone":"+1 901 624 3743",
    "sg:postcode":"38016",
    "sg:province":"TN",
    "wof:name":"John M Thompson",
    "wof:placetype":"venue"
},
  "geometry": {"coordinates":[-89.78486700000001,35.16803],"type":"Point"}
}