{
  "type": "Feature",
  "properties": {
    "iso:country":"US",
    "sg:address":"5929 Clinton Hwy",
    "sg:city":"Knoxville",
    "sg:classifiers":[
        {
            "category":"Autos & Motor Vehicles",
            "subcategory":"Automobile Sales",
            "type":"Retail Goods"
        }
    ],
    "sg:phone":"+1 865 689 2577",
    "sg:postcode":"37912",
    "sg:province":"TN",
    "sg:tags":[
        "used"
    ],
    "wof:name":"Rent A Handy Car",
    "wof:placetype":"venue"
},
  "geometry": {"coordinates":[-83.993048,36.007679],"type":"Point"}
}