{
  "type": "Feature",
  "properties": {
    "addr:full":"1601 Murfreesboro Pike Nashville TN 37217",
    "addr:housenumber":"1601",
    "addr:postcode":"37217",
    "addr:street":"Murfreesboro Pike",
    "iso:country":"US",
    "sg:address":"1601 Murfreesboro Pike",
    "sg:city":"Nashville",
    "sg:classifiers":[
        {
            "category":"Government",
            "subcategory":"Office",
            "type":"Public Place"
        }
    ],
    "sg:phone":"+1 615 741 2541",
    "sg:postcode":"37217",
    "sg:province":"TN",
    "sg:tags":[
        "state",
        "program"
    ],
    "wof:name":"Drivers License Examining Sta",
    "wof:placetype":"venue"
},
  "geometry": {"coordinates":[-86.669951,36.10488],"type":"Point"}
}