{
  "type": "Feature",
  "properties": {
    "iso:country":"US",
    "sg:address":"2220 E 25th St",
    "sg:city":"Chattanooga",
    "sg:classifiers":[
        {
            "category":"Personal",
            "subcategory":"Beauty Salon",
            "type":"Services"
        }
    ],
    "sg:phone":"+1 423 622 6870",
    "sg:postcode":"37407",
    "sg:province":"TN",
    "wof:name":"Nisha's Beauty Salon",
    "wof:placetype":"venue"
},
  "geometry": {"coordinates":[-85.281226,35.014522],"type":"Point"}
}