{
  "type": "Feature",
  "properties": {
    "addr:full":"1000 Co Rd 250 Niota TN 37826",
    "addr:housenumber":"1000",
    "addr:postcode":"37826",
    "addr:street":"Co Rd 250",
    "iso:country":"US",
    "sg:address":"1000 Co Rd 250",
    "sg:city":"Niota",
    "sg:classifiers":[
        {
            "category":"Building & Trades",
            "subcategory":"Construction",
            "type":"Services"
        }
    ],
    "sg:phone":"+1 423 746 1241",
    "sg:postcode":"37826",
    "sg:province":"TN",
    "sg:tags":[
        "insulation",
        "heat",
        "contractor"
    ],
    "wof:name":"Den-Gen Insulation",
    "wof:placetype":"venue"
},
  "geometry": {"coordinates":[-84.61785,35.568723],"type":"Point"}
}