{
  "type": "Feature",
  "properties": {
    "iso:country":"US",
    "sg:address":"362 New Byhalia Rd",
    "sg:city":"Collierville",
    "sg:classifiers":[
        {
            "category":"Professional",
            "type":"Services"
        }
    ],
    "sg:phone":"+1 901 854 7721",
    "sg:postcode":"38017",
    "sg:province":"TN",
    "sg:tags":[
        "establishment"
    ],
    "wof:name":"Cole Hays Bookkeeper",
    "wof:placetype":"venue"
},
  "geometry": {"coordinates":[-89.687659,35.050641],"type":"Point"}
}