{
  "type": "Feature",
  "properties": {
    "iso:country":"US",
    "sg:address":"968 Stanhope Rd",
    "sg:city":"Collierville",
    "sg:classifiers":[
        {
            "category":"Manufacturing",
            "subcategory":"Glass & Minerals",
            "type":"Manufacturing & Wholesale Goods"
        }
    ],
    "sg:phone":"+1 901 854 5099",
    "sg:postcode":"38017",
    "sg:province":"TN",
    "sg:tags":[
        "refractory",
        "mfg"
    ],
    "wof:name":"Vesuvius USA Corporation",
    "wof:placetype":"venue"
},
  "geometry": {"coordinates":[-89.694457,35.084783],"type":"Point"}
}