{
  "type": "Feature",
  "properties": {
    "addr:full":"2461 Dalebrook Cove Memphis TN 38127",
    "addr:housenumber":"2461",
    "addr:postcode":"38127",
    "addr:street":"Dalebrook Cove",
    "iso:country":"US",
    "sg:address":"2461 Dalebrook Cove",
    "sg:city":"Memphis",
    "sg:classifiers":[
        {
            "category":"Social Services",
            "subcategory":"Child Care",
            "type":"Services"
        }
    ],
    "sg:phone":"+1 901 353 2571",
    "sg:postcode":"38127",
    "sg:province":"TN",
    "sg:tags":[
        "day"
    ],
    "wof:name":"Granny S Playhouse",
    "wof:placetype":"venue"
},
  "geometry": {"coordinates":[-89.982079,35.206029],"type":"Point"}
}