{
  "type": "Feature",
  "properties": {
    "addr:full":"312 Nancy Lynn Ln Knoxville TN 37919",
    "addr:housenumber":"312",
    "addr:postcode":"37919",
    "addr:street":"Nancy Lynn Ln",
    "iso:country":"US",
    "sg:address":"312 Nancy Lynn Ln",
    "sg:city":"Knoxville",
    "sg:classifiers":[
        {
            "category":"Banks & Credit Unions",
            "subcategory":"Bank",
            "type":"Services"
        }
    ],
    "sg:phone":"+1 865 450 9182",
    "sg:postcode":"37919",
    "sg:province":"TN",
    "sg:tags":[
        "loan",
        "real estate"
    ],
    "wof:name":"Rio Santee Home Loans",
    "wof:placetype":"venue"
},
  "geometry": {"coordinates":[-84.00941400000001,35.926474],"type":"Point"}
}