{
  "type": "Feature",
  "properties": {
    "iso:country":"US",
    "sg:address":"1000 Burnham Cir",
    "sg:city":"Hendersonville",
    "sg:classifiers":[
        {
            "category":"Wholesale",
            "subcategory":"Construction Materials",
            "type":"Manufacturing & Wholesale Goods"
        }
    ],
    "sg:phone":"+1 615 945 8541",
    "sg:postcode":"37075",
    "sg:province":"TN",
    "sg:tags":[
        "fence"
    ],
    "wof:name":"Discount Fence Co",
    "wof:placetype":"venue"
},
  "geometry": {"coordinates":[-86.63357499999999,36.330467],"type":"Point"}
}