{
  "type": "Feature",
  "properties": {
    "iso:country":"US",
    "sg:address":"446 Chestnut St",
    "sg:city":"Nashville",
    "sg:classifiers":[
        {
            "category":"Manufacturing",
            "subcategory":"Printing",
            "type":"Manufacturing & Wholesale Goods"
        }
    ],
    "sg:phone":"+1 615 383 5535",
    "sg:postcode":"37210",
    "sg:province":"TN",
    "sg:tags":[
        "publishing",
        "general"
    ],
    "wof:name":"Spring Hill Music Group Inc",
    "wof:placetype":"venue"
},
  "geometry": {"coordinates":[-86.76666400000001,36.144936],"type":"Point"}
}