{
  "type": "Feature",
  "properties": {
    "iso:country":"US",
    "sg:address":"114 Franklin Cir",
    "sg:city":"Portland",
    "sg:classifiers":[
        {
            "category":"Farming",
            "subcategory":"Farm",
            "type":"Manufacturing & Wholesale Goods"
        }
    ],
    "sg:phone":"+1 615 451 4031",
    "sg:postcode":"37148",
    "sg:province":"TN",
    "wof:name":"Solomon Phoenix Farms",
    "wof:placetype":"venue"
},
  "geometry": {"coordinates":[-86.48630799999999,36.482684],"type":"Point"}
}