{
  "type": "Feature",
  "properties": {
    "iso:country":"US",
    "sg:address":"3409 Henson Rd",
    "sg:city":"Knoxville",
    "sg:classifiers":[
        {
            "category":"Real Estate",
            "subcategory":"Real Estate Agent",
            "type":"Services"
        }
    ],
    "sg:phone":"+1 865 588 5655",
    "sg:postcode":"37921",
    "sg:province":"TN",
    "wof:name":"Brownlee Realty Co",
    "wof:placetype":"venue"
},
  "geometry": {"coordinates":[-84.00383600000001,35.959009],"type":"Point"}
}