{
  "type": "Feature",
  "properties": {
    "iso:country":"US",
    "sg:address":"5592 Central Valley Rd",
    "sg:city":"Murfreesboro",
    "sg:classifiers":[
        {
            "category":"Building & Trades",
            "subcategory":"Construction",
            "type":"Services"
        }
    ],
    "sg:phone":"+1 615 895 4454",
    "sg:postcode":"37129",
    "sg:province":"TN",
    "sg:tags":[
        "company"
    ],
    "wof:name":"Judy Construction",
    "wof:placetype":"venue"
},
  "geometry": {"coordinates":[-86.449754,35.978419],"type":"Point"}
}