{
  "type": "Feature",
  "properties": {
    "iso:country":"US",
    "sg:address":"144 Westbrook Cir NW",
    "sg:city":"Cleveland",
    "sg:classifiers":[
        {
            "category":"Professional",
            "type":"Services"
        }
    ],
    "sg:phone":"+1 423 336 5189",
    "sg:postcode":"37312",
    "sg:province":"TN",
    "wof:name":"Tennessee Athens Civitian Club",
    "wof:placetype":"venue"
},
  "geometry": {"coordinates":[-84.80776299999999,35.254951],"type":"Point"}
}