{
  "type": "Feature",
  "properties": {
    "addr:full":"213 Spivey Ln Gainesboro TN 38562",
    "addr:housenumber":"213",
    "addr:postcode":"38562",
    "addr:street":"Spivey Ln",
    "iso:country":"US",
    "sg:address":"213 Spivey Ln",
    "sg:city":"Gainesboro",
    "sg:classifiers":[
        {
            "category":"Building & Trades",
            "subcategory":"Construction",
            "type":"Services"
        }
    ],
    "sg:phone":"+1 931 268 5194",
    "sg:postcode":"38562",
    "sg:province":"TN",
    "sg:tags":[
        "painter"
    ],
    "wof:name":"Proficient Painting",
    "wof:placetype":"venue"
},
  "geometry": {"coordinates":[-85.61456099999999,36.417136],"type":"Point"}
}