{
  "type": "Feature",
  "properties": {
    "iso:country":"US",
    "sg:address":"730 Mc Ferrin Ave",
    "sg:city":"Nashville",
    "sg:classifiers":[
        {
            "category":"Restaurant",
            "type":"Food & Drink"
        }
    ],
    "sg:phone":"+1 615 226 4722",
    "sg:postcode":"37206",
    "sg:province":"TN",
    "sg:tags":[
        "eating"
    ],
    "wof:name":"Whites Fish & Bbq",
    "wof:placetype":"venue"
},
  "geometry": {"coordinates":[-86.75442700000001,36.184799],"type":"Point"}
}