{
  "type": "Feature",
  "properties": {
    "addr:full":"114 Westwood Rd Knoxville TN 37919",
    "addr:housenumber":"114",
    "addr:postcode":"37919",
    "addr:street":"Westwood Rd",
    "iso:country":"US",
    "sg:address":"114 Westwood Rd",
    "sg:city":"Knoxville",
    "sg:classifiers":[
        {
            "category":"Professional",
            "subcategory":"Business Services",
            "type":"Services"
        }
    ],
    "sg:phone":"+1 865 584 5586",
    "sg:postcode":"37919",
    "sg:province":"TN",
    "wof:name":"Marcia Wasserman Design Studio",
    "wof:placetype":"venue"
},
  "geometry": {"coordinates":[-83.996532,35.93844],"type":"Point"}
}