{
  "type": "Feature",
  "properties": {
    "iso:country":"US",
    "sg:address":"106 Columbia Ave",
    "sg:city":"Centerville",
    "sg:classifiers":[
        {
            "category":"Manufacturing",
            "subcategory":"Apparel",
            "type":"Manufacturing & Wholesale Goods"
        }
    ],
    "sg:phone":"+1 931 729 9709",
    "sg:postcode":"37033",
    "sg:province":"TN",
    "wof:name":"Signature Embrodery",
    "wof:placetype":"venue"
},
  "geometry": {"coordinates":[-87.464151,35.777743],"type":"Point"}
}