{
  "type": "Feature",
  "properties": {
    "iso:country":"US",
    "sg:address":"7335 Lee Hwy",
    "sg:city":"Chattanooga",
    "sg:classifiers":[
        {
            "category":"Shopping",
            "subcategory":"Discount & Variety Stores",
            "type":"Retail Goods"
        }
    ],
    "sg:phone":"+1 423 499 2755",
    "sg:postcode":"37421",
    "sg:province":"TN",
    "wof:name":"Dollar General",
    "wof:placetype":"venue"
},
  "geometry": {"coordinates":[-85.147014,35.053691],"type":"Point"}
}