{
  "type": "Feature",
  "properties": {
    "iso:country":"US",
    "sg:address":"200 Forrest Ave",
    "sg:city":"Athens",
    "sg:classifiers":[
        {
            "category":"Building & Trades",
            "subcategory":"Construction",
            "type":"Services"
        }
    ],
    "sg:phone":"+1 423 745 1326",
    "sg:postcode":"37303",
    "sg:province":"TN",
    "sg:tags":[
        "downspouts",
        "gutter"
    ],
    "wof:name":"Kirk's Guttering",
    "wof:placetype":"venue"
},
  "geometry": {"coordinates":[-84.590397,35.449196],"type":"Point"}
}