{
  "type": "Feature",
  "properties": {
    "addr:full":"843 Harbor Isle Cir E Memphis TN 38103",
    "addr:housenumber":"843",
    "addr:postcode":"38103",
    "addr:street":"Harbor Isle Cir E",
    "iso:country":"US",
    "sg:address":"843 Harbor Isle Cir E",
    "sg:city":"Memphis",
    "sg:classifiers":[
        {
            "category":"Wholesale",
            "subcategory":"Groceries",
            "type":"Manufacturing & Wholesale Goods"
        }
    ],
    "sg:phone":"+1 901 578 1229",
    "sg:postcode":"38103",
    "sg:province":"TN",
    "sg:tags":[
        "tea",
        "coffee"
    ],
    "wof:name":"RSV Tea",
    "wof:placetype":"venue"
},
  "geometry": {"coordinates":[-90.051349,35.164186],"type":"Point"}
}