{
  "type": "Feature",
  "properties": {
    "addr:full":"4665 Knight Arnold Rd Memphis TN 38118",
    "addr:housenumber":"4665",
    "addr:postcode":"38118",
    "addr:street":"Knight Arnold Rd",
    "iso:country":"US",
    "sg:address":"4665 Knight Arnold Rd",
    "sg:city":"Memphis",
    "sg:classifiers":[
        {
            "category":"Wholesale",
            "subcategory":"Non-durable Goods",
            "type":"Manufacturing & Wholesale Goods"
        }
    ],
    "sg:phone":"+1 901 375 4377",
    "sg:postcode":"38118",
    "sg:province":"TN",
    "wof:name":"Ruby Imports",
    "wof:placetype":"venue"
},
  "geometry": {"coordinates":[-89.907741,35.06236],"type":"Point"}
}