{
  "type": "Feature",
  "properties": {
    "addr:full":"6310 Dayton Blvd Hixson TN 37343",
    "addr:housenumber":"6310",
    "addr:postcode":"37343",
    "addr:street":"Dayton Blvd",
    "iso:country":"US",
    "sg:address":"6310 Dayton Blvd",
    "sg:city":"Hixson",
    "sg:classifiers":[
        {
            "category":"Organizations",
            "subcategory":"Religious Organization",
            "type":"Services"
        }
    ],
    "sg:phone":"+1 423 842 5919",
    "sg:postcode":"37343",
    "sg:province":"TN",
    "sg:tags":[
        "church"
    ],
    "wof:name":"Grace Church Of The Nazarene",
    "wof:placetype":"venue"
},
  "geometry": {"coordinates":[-85.24679,35.182271],"type":"Point"}
}