{
  "type": "Feature",
  "properties": {
    "iso:country":"US",
    "sg:address":"1195 Nashville Pike",
    "sg:city":"Gallatin",
    "sg:classifiers":[
        {
            "category":"Recreation",
            "type":"Entertainment"
        }
    ],
    "sg:phone":"+1 615 452 1376",
    "sg:postcode":"37066",
    "sg:province":"TN",
    "sg:tags":[
        "stable"
    ],
    "wof:name":"Bowtie Quarter Horses",
    "wof:placetype":"venue"
},
  "geometry": {"coordinates":[-86.48242399999999,36.371001],"type":"Point"}
}