{
  "type": "Feature",
  "properties": {
    "addr:full":"175 Bullard Hollow Rd Harriman TN 37748",
    "addr:housenumber":"175",
    "addr:postcode":"37748",
    "addr:street":"Bullard Hollow Rd",
    "iso:country":"US",
    "sg:address":"175 Bullard Hollow Rd",
    "sg:city":"Harriman",
    "sg:classifiers":[
        {
            "category":"Building & Trades",
            "subcategory":"Electrical",
            "type":"Services"
        }
    ],
    "sg:phone":"+1 865 882 1855",
    "sg:postcode":"37748",
    "sg:province":"TN",
    "sg:tags":[
        "electrical",
        "contractor"
    ],
    "wof:name":"Bullard Electric",
    "wof:placetype":"venue"
},
  "geometry": {"coordinates":[-84.53070200000001,35.94226],"type":"Point"}
}