{
  "type": "Feature",
  "properties": {
    "iso:country":"US",
    "sg:address":"7833 Ooltewah Georgetown Rd",
    "sg:city":"Ooltewah",
    "sg:classifiers":[
        {
            "category":"Professional",
            "type":"Services"
        }
    ],
    "sg:phone":"+1 423 238 6794",
    "sg:postcode":"37363",
    "sg:province":"TN",
    "wof:name":"Doublegate Incorporated",
    "wof:placetype":"venue"
},
  "geometry": {"coordinates":[-85.044714,35.138276],"type":"Point"}
}