{
  "type": "Feature",
  "properties": {
    "iso:country":"US",
    "sg:address":"1597 York Ave",
    "sg:city":"Memphis",
    "sg:classifiers":[
        {
            "category":"Shopping",
            "subcategory":"Gifts & Souvenirs",
            "type":"Retail Goods"
        }
    ],
    "sg:phone":"+1 901 726 5749",
    "sg:postcode":"38104",
    "sg:province":"TN",
    "wof:name":"Jocol Gifts",
    "wof:placetype":"venue"
},
  "geometry": {"coordinates":[-90.00997599999999,35.12526],"type":"Point"}
}