{
  "type": "Feature",
  "properties": {
    "iso:country":"US",
    "sg:address":"115 Academy St",
    "sg:city":"Greeneville",
    "sg:classifiers":[
        {
            "category":"Social Services",
            "type":"Services"
        }
    ],
    "sg:phone":"+1 423 639 9361",
    "sg:postcode":"37743",
    "sg:province":"TN",
    "sg:tags":[
        "organization",
        "welfare"
    ],
    "wof:name":"United Way",
    "wof:placetype":"venue"
},
  "geometry": {"coordinates":[-82.827918,36.163109],"type":"Point"}
}