{
  "type": "Feature",
  "properties": {
    "iso:country":"US",
    "sg:address":"154 Schrock Ln",
    "sg:city":"Monterey",
    "sg:classifiers":[
        {
            "category":"Building & Trades",
            "subcategory":"Construction",
            "type":"Services"
        }
    ],
    "sg:phone":"+1 931 445 7010",
    "sg:postcode":"38574",
    "sg:province":"TN",
    "sg:tags":[
        "house"
    ],
    "wof:name":"Schrock Builders LLC",
    "wof:placetype":"venue"
},
  "geometry": {"coordinates":[-85.128339,36.19714],"type":"Point"}
}