{
  "type": "Feature",
  "properties": {
    "addr:full":"4295 Cromwell Rd Chattanooga TN 37421",
    "addr:housenumber":"4295",
    "addr:postcode":"37421",
    "addr:street":"Cromwell Rd",
    "iso:country":"US",
    "sg:address":"4295 Cromwell Rd",
    "sg:city":"Chattanooga",
    "sg:classifiers":[
        {
            "category":"Insurance",
            "subcategory":"Insurance Agent",
            "type":"Services"
        }
    ],
    "sg:phone":"+1 423 899 9800",
    "sg:postcode":"37421",
    "sg:province":"TN",
    "wof:name":"Mutual Of Omaha Insurance Co",
    "wof:placetype":"venue"
},
  "geometry": {"coordinates":[-85.198635,35.066118],"type":"Point"}
}