{
  "type": "Feature",
  "properties": {
    "addr:full":"98 Neecham St Crossville TN 38555",
    "addr:housenumber":"98",
    "addr:postcode":"38555",
    "addr:street":"Neecham St",
    "iso:country":"US",
    "sg:address":"98 Neecham St",
    "sg:city":"Crossville",
    "sg:classifiers":[
        {
            "category":"Home & Garden",
            "subcategory":"Furniture",
            "type":"Retail Goods"
        }
    ],
    "sg:phone":"+1 931 484 7049",
    "sg:postcode":"38555",
    "sg:province":"TN",
    "wof:name":"Smith Furniture",
    "wof:placetype":"venue"
},
  "geometry": {"coordinates":[-85.026233,35.951337],"type":"Point"}
}