{
  "type": "Feature",
  "properties": {
    "iso:country":"US",
    "sg:address":"100 Rose Dr",
    "sg:city":"Knoxville",
    "sg:classifiers":[
        {
            "category":"Professional",
            "subcategory":"Management & Consulting",
            "type":"Services"
        }
    ],
    "sg:phone":"+1 865 689 2423",
    "sg:postcode":"37918",
    "sg:province":"TN",
    "sg:tags":[
        "security"
    ],
    "wof:name":"American Express",
    "wof:placetype":"venue"
},
  "geometry": {"coordinates":[-83.924373,36.025387],"type":"Point"}
}