{
  "type": "Feature",
  "properties": {
    "iso:country":"US",
    "sg:address":"401 Mc Adoo Ave",
    "sg:city":"Nashville",
    "sg:classifiers":[
        {
            "category":"Shopping",
            "subcategory":"Computers & Home Electronics",
            "type":"Retail Goods"
        }
    ],
    "sg:phone":"+1 615 297 1086",
    "sg:postcode":"37205",
    "sg:province":"TN",
    "wof:name":"Urban Move Electronics",
    "wof:placetype":"venue"
},
  "geometry": {"coordinates":[-86.823813,36.146147],"type":"Point"}
}