{
  "type": "Feature",
  "properties": {
    "iso:country":"US",
    "sg:address":"460 10th Cir N",
    "sg:city":"Nashville",
    "sg:classifiers":[
        {
            "category":"Organizations",
            "subcategory":"Religious Organization",
            "type":"Services"
        }
    ],
    "sg:phone":"+1 615 255 6108",
    "sg:postcode":"37203",
    "sg:province":"TN",
    "wof:name":"Ennix-Jones Ctr First Baptist",
    "wof:placetype":"venue"
},
  "geometry": {"coordinates":[-86.788217,36.163815],"type":"Point"}
}