{
  "type": "Feature",
  "properties": {
    "addr:full":"6148 Lee Hwy Chattanooga TN 37421",
    "addr:housenumber":"6148",
    "addr:postcode":"37421",
    "addr:street":"Lee Hwy",
    "iso:country":"US",
    "sg:address":"6148 Lee Hwy",
    "sg:city":"Chattanooga",
    "sg:classifiers":[
        {
            "category":"Banks & Credit Unions",
            "subcategory":"Bank",
            "type":"Services"
        }
    ],
    "sg:phone":"+1 423 899 6944",
    "sg:postcode":"37421",
    "sg:province":"TN",
    "sg:tags":[
        "loan",
        "real estate"
    ],
    "wof:name":"Financial Solutions",
    "wof:placetype":"venue"
},
  "geometry": {"coordinates":[-85.189043,35.028069],"type":"Point"}
}