{
  "type": "Feature",
  "properties": {
    "addr:full":"1209 N Eastman Rd Kingsport TN 37664",
    "addr:housenumber":"1209",
    "addr:postcode":"37664",
    "addr:street":"N Eastman Rd",
    "iso:country":"US",
    "sg:address":"1209 N Eastman Rd",
    "sg:city":"Kingsport",
    "sg:classifiers":[
        {
            "category":"Restaurant",
            "type":"Food & Drink"
        }
    ],
    "sg:menulink":"http://www.allmenus.com/tn/kingsport/214988-burger-king/menu/",
    "sg:phone":"+1 423 247 7787",
    "sg:postcode":"37664",
    "sg:province":"TN",
    "sg:tags":[
        "burger",
        "american"
    ],
    "wof:name":"Burger King",
    "wof:placetype":"venue"
},
  "geometry": {"coordinates":[-82.528492,36.531552],"type":"Point"}
}