{
  "type": "Feature",
  "properties": {
    "addr:full":"149 E Main St Bradford TN 38316",
    "addr:housenumber":"149",
    "addr:postcode":"38316",
    "addr:street":"E Main St",
    "iso:country":"US",
    "sg:address":"149 E Main St",
    "sg:city":"Bradford",
    "sg:classifiers":[
        {
            "category":"Insurance",
            "subcategory":"Insurance Agent",
            "type":"Services"
        }
    ],
    "sg:phone":"+1 731 742 3581",
    "sg:postcode":"38316",
    "sg:province":"TN",
    "wof:name":"Alexander Insurance",
    "wof:placetype":"venue"
},
  "geometry": {"coordinates":[-88.811972,36.076274],"type":"Point"}
}