{
  "type": "Feature",
  "properties": {
    "iso:country":"US",
    "sg:address":"332 Troy Cir SW",
    "sg:city":"Knoxville",
    "sg:classifiers":[
        {
            "category":"Wholesale",
            "subcategory":"Metals & Minerals",
            "type":"Manufacturing & Wholesale Goods"
        }
    ],
    "sg:phone":"+1 865 558 0521",
    "sg:postcode":"37919",
    "sg:province":"TN",
    "sg:tags":[
        "air",
        "equipment",
        "warm",
        "conditioning",
        "heating"
    ],
    "wof:name":"E T T C",
    "wof:placetype":"venue"
},
  "geometry": {"coordinates":[-84.004673,35.927479],"type":"Point"}
}