{
  "type": "Feature",
  "properties": {
    "iso:country":"US",
    "sg:address":"295 Stoner Ct",
    "sg:city":"Mount Juliet",
    "sg:classifiers":[
        {
            "category":"Professional",
            "subcategory":"Business Services",
            "type":"Services"
        }
    ],
    "sg:phone":"+1 615 754 4048",
    "sg:postcode":"37122",
    "sg:province":"TN",
    "wof:name":"Paul Amy Breeding",
    "wof:placetype":"venue"
},
  "geometry": {"coordinates":[-86.48903,36.171353],"type":"Point"}
}