{
  "type": "Feature",
  "properties": {
    "iso:country":"US",
    "sg:address":"7715 US Hwy 70",
    "sg:city":"Bartlett",
    "sg:classifiers":[
        {
            "category":"Wholesale",
            "subcategory":"Machinery & Supplies",
            "type":"Manufacturing & Wholesale Goods"
        }
    ],
    "sg:phone":"+1 901 266 1030",
    "sg:postcode":"38133",
    "sg:province":"TN",
    "sg:tags":[
        "packing",
        "industrial"
    ],
    "wof:name":"Fluid Management Corp",
    "wof:placetype":"venue"
},
  "geometry": {"coordinates":[-89.807249,35.231718],"type":"Point"}
}