{
  "type": "Feature",
  "properties": {
    "addr:full":"3242 Players Club Cir Memphis TN 38125",
    "addr:housenumber":"3242",
    "addr:postcode":"38125",
    "addr:street":"Players Club Cir",
    "iso:country":"US",
    "sg:address":"3242 Players Club Cir",
    "sg:city":"Memphis",
    "sg:classifiers":[
        {
            "category":"Real Estate",
            "subcategory":"Real Estate Agent",
            "type":"Services"
        }
    ],
    "sg:phone":"+1 901 748 3242",
    "sg:postcode":"38125",
    "sg:province":"TN",
    "sg:tags":[
        "desk",
        "space"
    ],
    "wof:name":"Alliance Business Ctr Network",
    "wof:placetype":"venue"
},
  "geometry": {"coordinates":[-89.790702,35.062976],"type":"Point"}
}