{
  "type": "Feature",
  "properties": {
    "iso:country":"US",
    "sg:address":"3732 E Raines Rd",
    "sg:city":"Memphis",
    "sg:classifiers":[
        {
            "category":"Wholesale",
            "subcategory":"Farm Supplies",
            "type":"Manufacturing & Wholesale Goods"
        }
    ],
    "sg:phone":"+1 901 751 6241",
    "sg:postcode":"38118",
    "sg:province":"TN",
    "sg:tags":[
        "grain",
        "elevator"
    ],
    "wof:name":"Lurgi, Inc.",
    "wof:placetype":"venue"
},
  "geometry": {"coordinates":[-89.938879,35.036815],"type":"Point"}
}