{
  "type": "Feature",
  "properties": {
    "iso:country":"US",
    "sg:address":"111 Underwood Rd",
    "sg:city":"Newport",
    "sg:classifiers":[
        {
            "category":"Government",
            "subcategory":"Fire Station",
            "type":"Public Place"
        }
    ],
    "sg:phone":"+1 423 623 2046",
    "sg:postcode":"37821",
    "sg:province":"TN",
    "sg:tags":[
        "department"
    ],
    "wof:name":"Newport Rescue Squad",
    "wof:placetype":"venue"
},
  "geometry": {"coordinates":[-83.23771499999999,35.974137],"type":"Point"}
}