{
  "type": "Feature",
  "properties": {
    "addr:full":"9195 Loganberry Ln Cordova TN 38016",
    "addr:housenumber":"9195",
    "addr:postcode":"38016",
    "addr:street":"Loganberry Ln",
    "iso:country":"US",
    "sg:address":"9195 Loganberry Ln",
    "sg:city":"Cordova",
    "sg:classifiers":[
        {
            "category":"Manufacturing",
            "subcategory":"Tools & Machinery",
            "type":"Manufacturing & Wholesale Goods"
        }
    ],
    "sg:phone":"+1 901 753 7035",
    "sg:postcode":"38016",
    "sg:province":"TN",
    "sg:tags":[
        "springs-wholesale",
        "manufacturer"
    ],
    "wof:name":"Spring Paul",
    "wof:placetype":"venue"
},
  "geometry": {"coordinates":[-89.754023,35.166622],"type":"Point"}
}