{
  "type": "Feature",
  "properties": {
    "iso:country":"US",
    "sg:address":"130 W Main St",
    "sg:city":"Jonesborough",
    "sg:classifiers":[
        {
            "category":"Travel",
            "subcategory":"Hotels & Motels",
            "type":"Entertainment"
        }
    ],
    "sg:phone":"+1 423 753 7568",
    "sg:postcode":"37659",
    "sg:province":"TN",
    "sg:tags":[
        "operation"
    ],
    "wof:name":"May Ledbetter House",
    "wof:placetype":"venue"
},
  "geometry": {"coordinates":[-82.473938,36.294051],"type":"Point"}
}