{
  "type": "Feature",
  "properties": {
    "iso:country":"US",
    "sg:address":"4015 Pheasant Ct",
    "sg:city":"Greenbrier",
    "sg:classifiers":[
        {
            "category":"Manufacturing",
            "subcategory":"Signs",
            "type":"Manufacturing & Wholesale Goods"
        }
    ],
    "sg:phone":"+1 615 650 1144",
    "sg:postcode":"37073",
    "sg:province":"TN",
    "sg:tags":[
        "specialty",
        "mfg"
    ],
    "wof:name":"S & R Signs",
    "wof:placetype":"venue"
},
  "geometry": {"coordinates":[-86.797743,36.437515],"type":"Point"}
}