{
  "type": "Feature",
  "properties": {
    "iso:country":"US",
    "sg:address":"139 Roaring River Rd",
    "sg:city":"Livingston",
    "sg:classifiers":[
        {
            "category":"Wholesale",
            "subcategory":"Machinery & Supplies",
            "type":"Manufacturing & Wholesale Goods"
        }
    ],
    "sg:phone":"+1 931 498 2747",
    "sg:postcode":"38570",
    "sg:province":"TN",
    "sg:tags":[
        "equipment",
        "establishment"
    ],
    "wof:name":"Carter Enterprises",
    "wof:placetype":"venue"
},
  "geometry": {"coordinates":[-85.34634,36.304444],"type":"Point"}
}