{
  "type": "Feature",
  "properties": {
    "addr:full":"926 SE Broad St Murfreesboro TN 37130",
    "addr:housenumber":"926",
    "addr:postcode":"37130",
    "addr:street":"Se Broad St",
    "iso:country":"US",
    "sg:address":"926 SE Broad St",
    "sg:city":"Murfreesboro",
    "sg:classifiers":[
        {
            "category":"Building & Trades",
            "subcategory":"Construction",
            "type":"Services"
        }
    ],
    "sg:phone":"+1 615 895 0707",
    "sg:postcode":"37130",
    "sg:province":"TN",
    "sg:tags":[
        "home",
        "improvement"
    ],
    "wof:name":"Sawhorse",
    "wof:placetype":"venue"
},
  "geometry": {"coordinates":[-86.38391900000001,35.83343],"type":"Point"}
}