{
  "type": "Feature",
  "properties": {
    "iso:country":"US",
    "sg:address":"1015 Brynewood Ter",
    "sg:city":"Chattanooga",
    "sg:classifiers":[
        {
            "category":"Restaurant",
            "type":"Food & Drink"
        }
    ],
    "sg:phone":"+1 423 875 6898",
    "sg:postcode":"37415",
    "sg:province":"TN",
    "sg:tags":[
        "decorating",
        "catering"
    ],
    "wof:name":"Good Things",
    "wof:placetype":"venue"
},
  "geometry": {"coordinates":[-85.27110500000001,35.125162],"type":"Point"}
}