{
  "type": "Feature",
  "properties": {
    "addr:full":"9122 State Hwy 49 E Orlinda TN 37141",
    "addr:housenumber":"9122",
    "addr:postcode":"37141",
    "addr:street":"State Hwy 49 E Orlinda",
    "iso:country":"US",
    "sg:address":"9122 State Hwy 49 E",
    "sg:city":"Orlinda",
    "sg:classifiers":[
        {
            "category":"Education",
            "subcategory":"Dance Studio",
            "type":"Public Place"
        }
    ],
    "sg:phone":"+1 615 654 0005",
    "sg:postcode":"37141",
    "sg:province":"TN",
    "wof:name":"Elite Dance Cheer & Gymnastics",
    "wof:placetype":"venue"
},
  "geometry": {"coordinates":[-86.714326,36.602494],"type":"Point"}
}