{
  "type": "Feature",
  "properties": {
    "iso:country":"US",
    "sg:address":"4900 Outland Center Dr",
    "sg:city":"Memphis",
    "sg:classifiers":[
        {
            "category":"Wholesale",
            "subcategory":"Medical Equipment & Supplies",
            "type":"Manufacturing & Wholesale Goods"
        }
    ],
    "sg:phone":"+1 901 366 9713",
    "sg:postcode":"38118",
    "sg:province":"TN",
    "wof:name":"GE",
    "wof:placetype":"venue"
},
  "geometry": {"coordinates":[-89.895338,35.041139],"type":"Point"}
}