{
  "type": "Feature",
  "properties": {
    "iso:country":"US",
    "sg:address":"3984 Old Rock Island Rd",
    "sg:city":"Rock Island",
    "sg:classifiers":[
        {
            "category":"Home & Garden",
            "subcategory":"Garden Supply",
            "type":"Retail Goods"
        }
    ],
    "sg:phone":"+1 931 686 9004",
    "sg:postcode":"38581",
    "sg:province":"TN",
    "sg:tags":[
        "nurseryman"
    ],
    "wof:name":"Triple B Nursery",
    "wof:placetype":"venue"
},
  "geometry": {"coordinates":[-85.637388,35.75848],"type":"Point"}
}