{
  "type": "Feature",
  "properties": {
    "iso:country":"US",
    "sg:address":"3124 Trough Springs Rd",
    "sg:city":"Clarksville",
    "sg:classifiers":[
        {
            "category":"Farming",
            "subcategory":"Farm",
            "type":"Manufacturing & Wholesale Goods"
        }
    ],
    "sg:phone":"+1 931 358 4709",
    "sg:postcode":"37043",
    "sg:province":"TN",
    "sg:tags":[
        "crop",
        "general"
    ],
    "wof:name":"Richardson Family Partnr Lmtd",
    "wof:placetype":"venue"
},
  "geometry": {"coordinates":[-87.22204000000001,36.51609],"type":"Point"}
}