{
  "type": "Feature",
  "properties": {
    "addr:full":"2251 Hwy 127 S Crossville TN 38572",
    "addr:housenumber":"2251",
    "addr:postcode":"38572",
    "addr:street":"Hwy 127 S",
    "iso:country":"US",
    "sg:address":"2251 Hwy 127 S",
    "sg:city":"Crossville",
    "sg:classifiers":[
        {
            "category":"Travel",
            "subcategory":"Hotels & Motels",
            "type":"Entertainment"
        }
    ],
    "sg:phone":"+1 931 484 2261",
    "sg:postcode":"38572",
    "sg:province":"TN",
    "sg:tags":[
        "operation"
    ],
    "wof:name":"Budget Motel",
    "wof:placetype":"venue"
},
  "geometry": {"coordinates":[-85.00135899999999,35.923085],"type":"Point"}
}