{
  "type": "Feature",
  "properties": {
    "iso:country":"US",
    "sg:address":"634 Parkway",
    "sg:city":"Gatlinburg",
    "sg:classifiers":[
        {
            "category":"Shopping",
            "subcategory":"Clothing, Apparel, & Fashions",
            "type":"Retail Goods"
        }
    ],
    "sg:phone":"+1 865 436 0976",
    "sg:postcode":"37738",
    "sg:province":"TN",
    "sg:tags":[
        "lingerie"
    ],
    "wof:name":"L C's Intimate Apparel & Fine",
    "wof:placetype":"venue"
},
  "geometry": {"coordinates":[-83.513918,35.712984],"type":"Point"}
}