{
  "type": "Feature",
  "properties": {
    "iso:country":"US",
    "sg:address":"1185 Old Hickory Rd",
    "sg:city":"Memphis",
    "sg:classifiers":[
        {
            "category":"Professional",
            "subcategory":"Business Services",
            "type":"Services"
        }
    ],
    "sg:phone":"+1 901 842 0590",
    "sg:postcode":"38116",
    "sg:province":"TN",
    "sg:tags":[
        "foreground",
        "music"
    ],
    "wof:name":"Jea Music",
    "wof:placetype":"venue"
},
  "geometry": {"coordinates":[-90.023685,35.051198],"type":"Point"}
}