{
  "type": "Feature",
  "properties": {
    "iso:country":"US",
    "sg:address":"214 Overlook Ct",
    "sg:city":"Brentwood",
    "sg:classifiers":[
        {
            "category":"Banks & Credit Unions",
            "subcategory":"Investment Brokerage",
            "type":"Services"
        }
    ],
    "sg:phone":"+1 615 371 1222",
    "sg:postcode":"37027",
    "sg:province":"TN",
    "sg:tags":[
        "consultant",
        "planning",
        "financial"
    ],
    "wof:name":"Earth To Air Systems",
    "wof:placetype":"venue"
},
  "geometry": {"coordinates":[-86.776813,36.031131],"type":"Point"}
}