{
  "type": "Feature",
  "properties": {
    "iso:country":"US",
    "sg:address":"2175 State Hwy 128",
    "sg:city":"Savannah",
    "sg:classifiers":[
        {
            "category":"Food & Beverages",
            "subcategory":"Meat & Fish",
            "type":"Retail Goods"
        }
    ],
    "sg:phone":"+1 731 926 4009",
    "sg:postcode":"38372",
    "sg:province":"TN",
    "sg:tags":[
        "seafood"
    ],
    "wof:name":"Adam's Fish Market & Fish Supl",
    "wof:placetype":"venue"
},
  "geometry": {"coordinates":[-88.25411099999999,35.081134],"type":"Point"}
}