{
  "type": "Feature",
  "properties": {
    "addr:full":"50 Industrial Dr Bristol TN 37620",
    "addr:housenumber":"50",
    "addr:postcode":"37620",
    "addr:street":"Industrial Dr",
    "iso:country":"US",
    "sg:address":"50 Industrial Dr",
    "sg:city":"Bristol",
    "sg:classifiers":[
        {
            "category":"Wholesale",
            "subcategory":"Machinery & Supplies",
            "type":"Manufacturing & Wholesale Goods"
        }
    ],
    "sg:phone":"+1 423 968 9700",
    "sg:postcode":"37620",
    "sg:province":"TN",
    "sg:tags":[
        "equipment",
        "industrial"
    ],
    "wof:name":"Cobra America LLC",
    "wof:placetype":"venue"
},
  "geometry": {"coordinates":[-82.177402,36.560409],"type":"Point"}
}