{
  "type": "Feature",
  "properties": {
    "iso:country":"US",
    "sg:address":"3061 US Hwy 41A S",
    "sg:city":"Clarksville",
    "sg:classifiers":[
        {
            "category":"Education",
            "subcategory":"Dance Studio",
            "type":"Public Place"
        }
    ],
    "sg:phone":"+1 931 358 5883",
    "sg:postcode":"37043",
    "sg:province":"TN",
    "sg:tags":[
        "instruction",
        "dancing"
    ],
    "wof:name":"Christy's Dance Connection",
    "wof:placetype":"venue"
},
  "geometry": {"coordinates":[-87.23759099999999,36.500283],"type":"Point"}
}