{
  "type": "Feature",
  "properties": {
    "iso:country":"US",
    "sg:address":"1788 W Point Rd",
    "sg:city":"Columbia",
    "sg:classifiers":[
        {
            "category":"Manufacturing",
            "subcategory":"Motor Vehicles & Parts",
            "type":"Manufacturing & Wholesale Goods"
        }
    ],
    "sg:phone":"+1 931 381 0003",
    "sg:postcode":"38486",
    "sg:province":"TN",
    "sg:tags":[
        "automotive",
        "system"
    ],
    "wof:name":"Arvinmeritor Exhaust",
    "wof:placetype":"venue"
},
  "geometry": {"coordinates":[-87.494491,35.141622],"type":"Point"}
}