{
  "type": "Feature",
  "properties": {
    "iso:country":"US",
    "sg:address":"1009 Cedar Dr",
    "sg:city":"Lobelville",
    "sg:classifiers":[
        {
            "category":"Professional",
            "type":"Services"
        }
    ],
    "sg:phone":"+1 931 593 2954",
    "sg:postcode":"37097",
    "sg:province":"TN",
    "wof:name":"Driftwood Water Co Inc",
    "wof:placetype":"venue"
},
  "geometry": {"coordinates":[-87.974861,35.781836],"type":"Point"}
}