{
  "type": "Feature",
  "properties": {
    "iso:country":"US",
    "sg:address":"1120 Sussex Dr",
    "sg:city":"Kingsport",
    "sg:classifiers":[
        {
            "category":"Education",
            "subcategory":"School",
            "type":"Public Place"
        }
    ],
    "sg:phone":"+1 423 288 0365",
    "sg:postcode":"37660",
    "sg:province":"TN",
    "sg:tags":[
        "k-",
        "private"
    ],
    "wof:name":"School Band Booster",
    "wof:placetype":"venue"
},
  "geometry": {"coordinates":[-82.48981499999999,36.556011],"type":"Point"}
}