{
  "type": "Feature",
  "properties": {
    "addr:full":"27 Fairway Dr Nashville TN 37214",
    "addr:housenumber":"27",
    "addr:postcode":"37214",
    "addr:street":"Fairway Dr",
    "iso:country":"US",
    "sg:address":"27 Fairway Dr",
    "sg:city":"Nashville",
    "sg:classifiers":[
        {
            "category":"Social Services",
            "subcategory":"Child Care",
            "type":"Services"
        }
    ],
    "sg:phone":"+1 615 885 8088",
    "sg:postcode":"37214",
    "sg:province":"TN",
    "wof:name":"Kidz Clubhouse Daycare Inc",
    "wof:placetype":"venue"
},
  "geometry": {"coordinates":[-86.681061,36.176294],"type":"Point"}
}