{
  "type": "Feature",
  "properties": {
    "addr:full":"1837 Air Lane Dr Nashville TN 37210",
    "addr:housenumber":"1837",
    "addr:postcode":"37210",
    "addr:street":"Air Lane Dr",
    "iso:country":"US",
    "sg:address":"1837 Air Lane Dr",
    "sg:city":"Nashville",
    "sg:classifiers":[
        {
            "category":"Professional",
            "type":"Services"
        },
        {
            "category":"Wholesale",
            "subcategory":"Furniture",
            "type":"Manufacturing & Wholesale Goods"
        }
    ],
    "sg:phone":"+1 615 874 1151",
    "sg:postcode":"37210",
    "sg:province":"TN",
    "wof:name":"Facility Installation Services",
    "wof:placetype":"venue"
},
  "geometry": {"coordinates":[-86.697243,36.148228],"type":"Point"}
}