{
  "type": "Feature",
  "properties": {
    "iso:country":"US",
    "sg:address":"1300 Colony Ct W",
    "sg:city":"Mount Juliet",
    "sg:classifiers":[
        {
            "category":"Professional",
            "subcategory":"Management & Consulting",
            "type":"Services"
        }
    ],
    "sg:phone":"+1 615 210 1968",
    "sg:postcode":"37122",
    "sg:province":"TN",
    "wof:name":"K B Management Services",
    "wof:placetype":"venue"
},
  "geometry": {"coordinates":[-86.546204,36.211332],"type":"Point"}
}