{
  "type": "Feature",
  "properties": {
    "iso:country":"US",
    "sg:address":"1700 W Reelfoot Ave",
    "sg:city":"Union City",
    "sg:classifiers":[
        {
            "category":"Restaurant",
            "type":"Food & Drink"
        }
    ],
    "sg:menulink":"http://www.allmenus.com/tn/union-city/215245-burger-king/menu/",
    "sg:phone":"+1 901 884 0107",
    "sg:postcode":"38261",
    "sg:province":"TN",
    "sg:tags":[
        "burger",
        "american"
    ],
    "wof:name":"Burger King",
    "wof:placetype":"venue"
},
  "geometry": {"coordinates":[-89.078248,36.411449],"type":"Point"}
}