{
  "type": "Feature",
  "properties": {
    "iso:country":"US",
    "sg:address":"126 Scotch St",
    "sg:city":"Hendersonville",
    "sg:classifiers":[
        {
            "category":"Building & Trades",
            "subcategory":"Landscaping Services",
            "type":"Services"
        }
    ],
    "sg:phone":"+1 615 824 8518",
    "sg:postcode":"37075",
    "sg:province":"TN",
    "wof:name":"Scapes LLC",
    "wof:placetype":"venue"
},
  "geometry": {"coordinates":[-86.6039,36.329319],"type":"Point"}
}