{
  "type": "Feature",
  "properties": {
    "iso:country":"US",
    "sg:address":"119 Wilson Ln",
    "sg:city":"Oliver Springs",
    "sg:classifiers":[
        {
            "category":"Retail",
            "subcategory":"Auto Repair",
            "type":"Services"
        }
    ],
    "sg:phone":"+1 865 435 5274",
    "sg:postcode":"37840",
    "sg:province":"TN",
    "sg:tags":[
        "exhaust"
    ],
    "wof:name":"Go Quiet Muffler & Brakes",
    "wof:placetype":"venue"
},
  "geometry": {"coordinates":[-84.365458,36.029852],"type":"Point"}
}