{
  "type": "Feature",
  "properties": {
    "addr:full":"274 E Main St Gallatin TN 37066",
    "addr:housenumber":"274",
    "addr:postcode":"37066",
    "addr:street":"E Main St",
    "iso:country":"US",
    "sg:address":"274 E Main St",
    "sg:city":"Gallatin",
    "sg:classifiers":[
        {
            "category":"Government",
            "subcategory":"Office",
            "type":"Public Place"
        }
    ],
    "sg:phone":"+1 615 452 3998",
    "sg:postcode":"37066",
    "sg:province":"TN",
    "sg:tags":[
        "federal",
        "planning",
        "dev"
    ],
    "wof:name":"USDA Rural Development",
    "wof:placetype":"venue"
},
  "geometry": {"coordinates":[-86.44310400000001,36.389186],"type":"Point"}
}