{
  "type": "Feature",
  "properties": {
    "iso:country":"US",
    "sg:address":"3334 Old Niles Ferry Rd",
    "sg:city":"Maryville",
    "sg:classifiers":[
        {
            "category":"Farming",
            "subcategory":"Farm",
            "type":"Manufacturing & Wholesale Goods"
        }
    ],
    "sg:phone":"+1 865 379 2645",
    "sg:postcode":"37803",
    "sg:province":"TN",
    "sg:tags":[
        "crop",
        "general"
    ],
    "wof:name":"Robert Herron",
    "wof:placetype":"venue"
},
  "geometry": {"coordinates":[-84.03508600000001,35.693226],"type":"Point"}
}