{
  "type": "Feature",
  "properties": {
    "iso:country":"US",
    "sg:address":"1415 Elm Hill Pike",
    "sg:city":"Nashville",
    "sg:classifiers":[
        {
            "category":"Real Estate",
            "subcategory":"Real Estate Agent",
            "type":"Services"
        }
    ],
    "sg:phone":"+1 615 252 2587",
    "sg:postcode":"37210",
    "sg:province":"TN",
    "wof:name":"Rollins Associates LP",
    "wof:placetype":"venue"
},
  "geometry": {"coordinates":[-86.722753,36.14388],"type":"Point"}
}