{
  "type": "Feature",
  "properties": {
    "iso:country":"US",
    "sg:address":"97 Franklin Heights Dr",
    "sg:city":"Winchester",
    "sg:classifiers":[
        {
            "category":"Professional",
            "subcategory":"Lawyer & Legal Services",
            "type":"Services"
        },
        {
            "category":"Professional",
            "subcategory":"Business Services",
            "type":"Services"
        }
    ],
    "sg:phone":"+1 931 967 4114",
    "sg:postcode":"37398",
    "sg:province":"TN",
    "wof:name":"Financial Solutions Inc",
    "wof:placetype":"venue"
},
  "geometry": {"coordinates":[-86.11854,35.213672],"type":"Point"}
}