{
  "type": "Feature",
  "properties": {
    "iso:country":"US",
    "sg:address":"349 Lafe Cox Rd",
    "sg:city":"Johnson City",
    "sg:classifiers":[
        {
            "category":"Freight",
            "type":"Transportation"
        },
        {
            "category":"Manufacturing",
            "subcategory":"Tools & Machinery",
            "type":"Manufacturing & Wholesale Goods"
        }
    ],
    "sg:phone":"+1 423 975 6934",
    "sg:postcode":"37604",
    "sg:province":"TN",
    "sg:tags":[
        "masters",
        "shipping",
        "mfg"
    ],
    "sg:website":"www.technipak.com",
    "wof:name":"Technipak LLC",
    "wof:placetype":"venue"
},
  "geometry": {"coordinates":[-82.341846,36.300878],"type":"Point"}
}