{
  "type": "Feature",
  "properties": {
    "iso:country":"US",
    "sg:address":"2801 Wilma Rudolph Blvd",
    "sg:city":"Clarksville",
    "sg:classifiers":[
        {
            "category":"Shopping",
            "subcategory":"Clothing, Apparel, & Fashions",
            "type":"Retail Goods"
        }
    ],
    "sg:phone":"+1 931 647 9373",
    "sg:postcode":"37040",
    "sg:province":"TN",
    "sg:tags":[
        "sportswear"
    ],
    "sg:website":"www.champssports.com",
    "wof:name":"Champs Sports",
    "wof:placetype":"venue"
},
  "geometry": {"coordinates":[-87.293587,36.588066],"type":"Point"}
}