{
  "type": "Feature",
  "properties": {
    "iso:country":"US",
    "sg:address":"407 E Main St",
    "sg:city":"Rogersville",
    "sg:classifiers":[
        {
            "category":"Social Services",
            "type":"Services"
        }
    ],
    "sg:phone":"+1 423 272 7835",
    "sg:postcode":"37857",
    "sg:province":"TN",
    "sg:tags":[
        "senior",
        "citizen"
    ],
    "wof:name":"Access To Community Svc",
    "wof:placetype":"venue"
},
  "geometry": {"coordinates":[-83.003742,36.408117],"type":"Point"}
}