{
  "type": "Feature",
  "properties": {
    "addr:full":"608 Harpeth Ct Clarksville TN 37043",
    "addr:housenumber":"608",
    "addr:postcode":"37043",
    "addr:street":"Harpeth Ct",
    "iso:country":"US",
    "sg:address":"608 Harpeth Ct",
    "sg:city":"Clarksville",
    "sg:classifiers":[
        {
            "category":"Building & Trades",
            "subcategory":"Construction",
            "type":"Services"
        }
    ],
    "sg:phone":"+1 931 216 4395",
    "sg:postcode":"37043",
    "sg:province":"TN",
    "sg:tags":[
        "painter"
    ],
    "wof:name":"Harry's Painting & Consulting",
    "wof:placetype":"venue"
},
  "geometry": {"coordinates":[-87.220179,36.519374],"type":"Point"}
}