{
  "type": "Feature",
  "properties": {
    "addr:full":"2104 Crestmoor Rd Nashville TN 37215",
    "addr:housenumber":"2104",
    "addr:postcode":"37215",
    "addr:street":"Crestmoor Rd",
    "iso:country":"US",
    "sg:address":"2104 Crestmoor Rd",
    "sg:city":"Nashville",
    "sg:classifiers":[
        {
            "category":"Shopping",
            "type":"Retail Goods"
        }
    ],
    "sg:phone":"+1 615 297 3201",
    "sg:postcode":"37215",
    "sg:province":"TN",
    "sg:tags":[
        "picture",
        "frame"
    ],
    "sg:website":"www.bennettgalleriesnashville.com",
    "wof:name":"Frames By U",
    "wof:placetype":"venue"
},
  "geometry": {"coordinates":[-86.81523900000001,36.109418],"type":"Point"}
}