{
  "type": "Feature",
  "properties": {
    "addr:full":"1852 Terrace Ave Knoxville TN 37916",
    "addr:housenumber":"1852",
    "addr:postcode":"37916",
    "addr:street":"Terrace Ave",
    "iso:country":"US",
    "sg:address":"1852 Terrace Ave",
    "sg:city":"Knoxville",
    "sg:classifiers":[
        {
            "category":"Government",
            "subcategory":"Office",
            "type":"Public Place"
        }
    ],
    "sg:phone":"+1 865 974 6065",
    "sg:postcode":"37916",
    "sg:province":"TN",
    "sg:tags":[
        "state",
        "taxation"
    ],
    "wof:name":"State Comptroller",
    "wof:placetype":"venue"
},
  "geometry": {"coordinates":[-83.93485099999999,35.953631],"type":"Point"}
}