{
  "type": "Feature",
  "properties": {
    "addr:full":"5509 Lamb Rd Arlington TN 38002",
    "addr:housenumber":"5509",
    "addr:postcode":"38002",
    "addr:street":"Lamb Rd",
    "iso:country":"US",
    "sg:address":"5509 Lamb Rd",
    "sg:city":"Arlington",
    "sg:classifiers":[
        {
            "category":"Building & Trades",
            "subcategory":"Electrical",
            "type":"Services"
        }
    ],
    "sg:phone":"+1 901 867 7173",
    "sg:postcode":"38002",
    "sg:province":"TN",
    "sg:tags":[
        "electrical",
        "contractor"
    ],
    "wof:name":"H&H Electric",
    "wof:placetype":"venue"
},
  "geometry": {"coordinates":[-89.694519,35.276628],"type":"Point"}
}