{
  "type": "Feature",
  "properties": {
    "addr:full":"210 NE Atlantic St Tullahoma TN 37388",
    "addr:housenumber":"210",
    "addr:postcode":"37388",
    "addr:street":"Ne Atlantic St",
    "iso:country":"US",
    "sg:address":"210 NE Atlantic St",
    "sg:city":"Tullahoma",
    "sg:classifiers":[
        {
            "category":"Insurance",
            "subcategory":"Insurance Agent",
            "type":"Services"
        }
    ],
    "sg:phone":"+1 931 455 2679",
    "sg:postcode":"37388",
    "sg:province":"TN",
    "sg:tags":[
        "agency"
    ],
    "wof:name":"Busch Thoma and Sons",
    "wof:placetype":"venue"
},
  "geometry": {"coordinates":[-86.211057,35.364861],"type":"Point"}
}