{
  "type": "Feature",
  "properties": {
    "addr:full":"507 Hannaway St Columbia TN 38401",
    "addr:housenumber":"507",
    "addr:postcode":"38401",
    "addr:street":"Hannaway St",
    "iso:country":"US",
    "sg:address":"507 Hannaway St",
    "sg:city":"Columbia",
    "sg:classifiers":[
        {
            "category":"Organizations",
            "subcategory":"Religious Organization",
            "type":"Services"
        }
    ],
    "sg:phone":"+1 931 540 0782",
    "sg:postcode":"38401",
    "sg:province":"TN",
    "wof:name":"Hannahway St Orgnal Church God",
    "wof:placetype":"venue"
},
  "geometry": {"coordinates":[-87.02713799999999,35.61374],"type":"Point"}
}