{
  "type": "Feature",
  "properties": {
    "addr:full":"1060 Brookfield Rd Memphis TN 38119",
    "addr:housenumber":"1060",
    "addr:postcode":"38119",
    "addr:street":"Brookfield Rd",
    "iso:country":"US",
    "sg:address":"1060 Brookfield Rd",
    "sg:city":"Memphis",
    "sg:classifiers":[
        {
            "category":"Professional",
            "subcategory":"Business Services",
            "type":"Services"
        }
    ],
    "sg:phone":"+1 901 761 0665",
    "sg:postcode":"38119",
    "sg:province":"TN",
    "sg:tags":[
        "appraiser"
    ],
    "wof:name":"E & A Appraisal Svc",
    "wof:placetype":"venue"
},
  "geometry": {"coordinates":[-89.873727,35.102477],"type":"Point"}
}