{
  "type": "Feature",
  "properties": {
    "addr:full":"391 S Bells St Alamo TN 38001",
    "addr:housenumber":"391",
    "addr:postcode":"38001",
    "addr:street":"S Bells St",
    "iso:country":"US",
    "sg:address":"391 S Bells St",
    "sg:city":"Alamo",
    "sg:classifiers":[
        {
            "category":"Banks & Credit Unions",
            "subcategory":"Bank",
            "type":"Services"
        }
    ],
    "sg:phone":"+1 731 696 3559",
    "sg:postcode":"38001",
    "sg:province":"TN",
    "sg:tags":[
        "cashing",
        "check"
    ],
    "wof:name":"Fast Money LLC",
    "wof:placetype":"venue"
},
  "geometry": {"coordinates":[-89.117485,35.779578],"type":"Point"}
}