{
  "type": "Feature",
  "properties": {
    "iso:country":"US",
    "sg:address":"160 Wheeler Ave",
    "sg:city":"Nashville",
    "sg:classifiers":[
        {
            "category":"Retail",
            "subcategory":"Repair Shop",
            "type":"Services"
        }
    ],
    "sg:phone":"+1 615 226 0999",
    "sg:postcode":"37211",
    "sg:province":"TN",
    "sg:tags":[
        "lock",
        "locksmith"
    ],
    "wof:name":"Affordable Lock & Key",
    "wof:placetype":"venue"
},
  "geometry": {"coordinates":[-86.726161,36.094999],"type":"Point"}
}