{
  "type": "Feature",
  "properties": {
    "iso:country":"US",
    "sg:address":"380 Carriage House Dr",
    "sg:city":"Jackson",
    "sg:classifiers":[
        {
            "category":"Insurance",
            "subcategory":"Insurance Agent",
            "type":"Services"
        }
    ],
    "sg:phone":"+1 731 664 1614",
    "sg:postcode":"38305",
    "sg:province":"TN",
    "wof:name":"McDonald Insurance Services",
    "wof:placetype":"venue"
},
  "geometry": {"coordinates":[-88.843941,35.666423],"type":"Point"}
}