{
  "type": "Feature",
  "properties": {
    "addr:full":"4050 State Hwy 67 Mountain City TN 37683",
    "addr:housenumber":"4050",
    "addr:postcode":"37683",
    "addr:street":"State Hwy 67",
    "iso:country":"US",
    "sg:address":"4050 State Hwy 67",
    "sg:city":"Mountain City",
    "sg:classifiers":[
        {
            "category":"Wholesale",
            "subcategory":"Medical Equipment & Supplies",
            "type":"Manufacturing & Wholesale Goods"
        },
        {
            "category":"Retail",
            "subcategory":"Auto Repair",
            "type":"Services"
        }
    ],
    "sg:phone":"+1 423 727 5421",
    "sg:postcode":"37683",
    "sg:province":"TN",
    "sg:tags":[
        "hospital",
        "rent"
    ],
    "wof:name":"Appalachian Medical Equip Co",
    "wof:placetype":"venue"
},
  "geometry": {"coordinates":[-81.780124,36.428491],"type":"Point"}
}