{
  "type": "Feature",
  "properties": {
    "iso:country":"US",
    "sg:address":"730 Old Hwy 68",
    "sg:city":"Sweetwater",
    "sg:classifiers":[
        {
            "category":"Restaurant",
            "type":"Food & Drink"
        }
    ],
    "sg:phone":"+1 423 337 5883",
    "sg:postcode":"37874",
    "sg:province":"TN",
    "wof:name":"Hardee's",
    "wof:placetype":"venue"
},
  "geometry": {"coordinates":[-84.457286,35.593269],"type":"Point"}
}