{
  "type": "Feature",
  "properties": {
    "addr:full":"14855 Highland Dr Mc Kenzie TN 38201",
    "addr:housenumber":"14855",
    "addr:postcode":"38201",
    "addr:street":"Highland Dr",
    "iso:country":"US",
    "sg:address":"14855 Highland Dr",
    "sg:city":"Mc Kenzie",
    "sg:classifiers":[
        {
            "category":"Autos & Motor Vehicles",
            "subcategory":"Automobile Sales",
            "type":"Retail Goods"
        }
    ],
    "sg:phone":"+1 731 352 0441",
    "sg:postcode":"38201",
    "sg:province":"TN",
    "sg:tags":[
        "car",
        "dealer"
    ],
    "wof:name":"Gary Simmons Lease-Sales",
    "wof:placetype":"venue"
},
  "geometry": {"coordinates":[-88.52360400000001,36.117997],"type":"Point"}
}