{
  "type": "Feature",
  "properties": {
    "iso:country":"US",
    "sg:address":"1001 Murfree Ave",
    "sg:city":"Murfreesboro",
    "sg:classifiers":[
        {
            "category":"Personal",
            "subcategory":"Beauty Salon",
            "type":"Services"
        }
    ],
    "sg:phone":"+1 615 367 3870",
    "sg:postcode":"37129",
    "sg:province":"TN",
    "sg:tags":[
        "shop"
    ],
    "wof:name":"A Plus Cuts",
    "wof:placetype":"venue"
},
  "geometry": {"coordinates":[-86.398011,35.85727],"type":"Point"}
}