{
  "type": "Feature",
  "properties": {
    "iso:country":"US",
    "sg:address":"92 Cave House Rd",
    "sg:city":"Jackson",
    "sg:classifiers":[
        {
            "category":"Insurance",
            "subcategory":"Insurance Agent",
            "type":"Services"
        }
    ],
    "sg:phone":"+1 731 668 9040",
    "sg:postcode":"38305",
    "sg:province":"TN",
    "wof:name":"National Business Association",
    "wof:placetype":"venue"
},
  "geometry": {"coordinates":[-88.733137,35.684005],"type":"Point"}
}