{
  "type": "Feature",
  "properties": {
    "iso:country":"US",
    "sg:address":"188 Mill St",
    "sg:city":"Cookeville",
    "sg:classifiers":[
        {
            "category":"Professional",
            "type":"Services"
        }
    ],
    "sg:phone":"+1 931 537 9515",
    "sg:postcode":"38506",
    "sg:province":"TN",
    "sg:tags":[
        "establishment"
    ],
    "wof:name":"Mid State Material Co Inc",
    "wof:placetype":"venue"
},
  "geometry": {"coordinates":[-85.45801299999999,36.191448],"type":"Point"}
}