{
  "type": "Feature",
  "properties": {
    "addr:full":"1635 Pistol Ln Oneida TN 37841",
    "addr:housenumber":"1635",
    "addr:postcode":"37841",
    "addr:street":"Pistol Ln",
    "iso:country":"US",
    "sg:address":"1635 Pistol Ln",
    "sg:city":"Oneida",
    "sg:classifiers":[
        {
            "category":"Building & Trades",
            "subcategory":"Plumbing",
            "type":"Services"
        }
    ],
    "sg:phone":"+1 423 569 3737",
    "sg:postcode":"37841",
    "sg:province":"TN",
    "sg:tags":[
        "conditioning",
        "air",
        "system",
        "contractor"
    ],
    "wof:name":"Oneida Heating and Air",
    "wof:placetype":"venue"
},
  "geometry": {"coordinates":[-84.579335,36.474696],"type":"Point"}
}