{
  "type": "Feature",
  "properties": {
    "iso:country":"US",
    "sg:address":"6157 McCormick Ridge Rd",
    "sg:city":"Whitleyville",
    "sg:classifiers":[
        {
            "category":"Food & Beverages",
            "subcategory":"Groceries & Convenience Stores",
            "type":"Retail Goods"
        }
    ],
    "sg:phone":"+1 931 258 4524",
    "sg:postcode":"38588",
    "sg:province":"TN",
    "wof:name":"Mount Vernon Market",
    "wof:placetype":"venue"
},
  "geometry": {"coordinates":[-85.69213000000001,36.530971],"type":"Point"}
}