{
  "type": "Feature",
  "properties": {
    "iso:country":"US",
    "sg:address":"1180 N Poplar St",
    "sg:city":"Paris",
    "sg:classifiers":[
        {
            "category":"Home & Garden",
            "subcategory":"Building Materials",
            "type":"Retail Goods"
        }
    ],
    "sg:phone":"+1 731 642 0223",
    "sg:postcode":"38242",
    "sg:province":"TN",
    "wof:name":"Paris Building Supply",
    "wof:placetype":"venue"
},
  "geometry": {"coordinates":[-88.32487,36.31601],"type":"Point"}
}