{
  "type": "Feature",
  "properties": {
    "iso:country":"US",
    "sg:address":"602 Perkins St",
    "sg:city":"Union City",
    "sg:classifiers":[
        {
            "category":"Home & Garden",
            "subcategory":"Carpets & Floor Coverings",
            "type":"Retail Goods"
        }
    ],
    "sg:phone":"+1 731 885 2830",
    "sg:postcode":"38261",
    "sg:province":"TN",
    "sg:tags":[
        "dealer",
        "rug"
    ],
    "wof:name":"Union City Carpet Center",
    "wof:placetype":"venue"
},
  "geometry": {"coordinates":[-89.05585499999999,36.422264],"type":"Point"}
}