{
  "type": "Feature",
  "properties": {
    "addr:full":"14891 Natchez Trace Rd Lexington TN 38351",
    "addr:housenumber":"14891",
    "addr:postcode":"38351",
    "addr:street":"Natchez Trace Rd",
    "iso:country":"US",
    "sg:address":"14891 Natchez Trace Rd",
    "sg:city":"Lexington",
    "sg:classifiers":[
        {
            "category":"Farming",
            "subcategory":"Livestock Farm",
            "type":"Manufacturing & Wholesale Goods"
        }
    ],
    "sg:phone":"+1 731 968 7951",
    "sg:postcode":"38351",
    "sg:province":"TN",
    "sg:tags":[
        "beef",
        "feedlot",
        "cattle"
    ],
    "wof:name":"Lee Hopper",
    "wof:placetype":"venue"
},
  "geometry": {"coordinates":[-88.359942,35.701813],"type":"Point"}
}