{
  "type": "Feature",
  "properties": {
    "iso:country":"US",
    "sg:address":"2403 W Broad St",
    "sg:city":"Cookeville",
    "sg:classifiers":[
        {
            "category":"Building & Trades",
            "subcategory":"Construction",
            "type":"Services"
        }
    ],
    "sg:phone":"+1 931 261 9866",
    "sg:postcode":"38501",
    "sg:province":"TN",
    "sg:tags":[
        "residential",
        "commercial"
    ],
    "wof:name":"Able Contractors Inc",
    "wof:placetype":"venue"
},
  "geometry": {"coordinates":[-85.57320300000001,36.17618],"type":"Point"}
}