{
  "type": "Feature",
  "properties": {
    "addr:full":"2344 Unionville Rd Halls TN 38040",
    "addr:postcode":"2344;38040",
    "addr:street":"Unionville Rd",
    "iso:country":"US",
    "sg:address":"2344 Unionville Rd",
    "sg:city":"Halls",
    "sg:classifiers":[
        {
            "category":"Freight",
            "type":"Transportation"
        }
    ],
    "sg:phone":"+1 731 285 2572",
    "sg:postcode":"38040",
    "sg:province":"TN",
    "sg:tags":[
        "operator",
        "local",
        "trucking"
    ],
    "wof:name":"Bill ONeal Trucking",
    "wof:placetype":"venue"
},
  "geometry": {"coordinates":[-89.42887399999999,35.965954],"type":"Point"}
}