{
  "type": "Feature",
  "properties": {
    "addr:full":"2105 Burton Branch Rd Cookeville TN 38506",
    "addr:housenumber":"2105",
    "addr:postcode":"38506",
    "addr:street":"Burton Branch Rd",
    "iso:country":"US",
    "sg:address":"2105 Burton Branch Rd",
    "sg:city":"Cookeville",
    "sg:classifiers":[
        {
            "category":"Freight",
            "type":"Transportation"
        }
    ],
    "sg:phone":"+1 931 537 6590",
    "sg:postcode":"38506",
    "sg:province":"TN",
    "sg:tags":[
        "warehouse",
        "self",
        "storage"
    ],
    "wof:name":"MKS Svc",
    "wof:placetype":"venue"
},
  "geometry": {"coordinates":[-85.459502,36.178447],"type":"Point"}
}