{
  "type": "Feature",
  "properties": {
    "addr:full":"1321 Livingston Hwy Byrdstown TN 38549",
    "addr:housenumber":"1321",
    "addr:postcode":"38549",
    "addr:street":"Livingston Hwy",
    "iso:country":"US",
    "sg:address":"1321 Livingston Hwy",
    "sg:city":"Byrdstown",
    "sg:classifiers":[
        {
            "category":"Shopping",
            "subcategory":"Gifts & Souvenirs",
            "type":"Retail Goods"
        }
    ],
    "sg:phone":"+1 931 864 4808",
    "sg:postcode":"38549",
    "sg:province":"TN",
    "sg:tags":[
        "shop"
    ],
    "wof:name":"Alice's Treasures",
    "wof:placetype":"venue"
},
  "geometry": {"coordinates":[-85.16786399999999,36.556998],"type":"Point"}
}