{
  "type": "Feature",
  "properties": {
    "iso:country":"US",
    "sg:address":"1301 16th Ave S",
    "sg:city":"Nashville",
    "sg:classifiers":[
        {
            "category":"Professional",
            "subcategory":"Management & Consulting",
            "type":"Services"
        }
    ],
    "sg:phone":"+1 615 322 9909",
    "sg:postcode":"37212",
    "sg:province":"TN",
    "wof:name":"T K O Marketing",
    "wof:placetype":"venue"
},
  "geometry": {"coordinates":[-86.79449700000001,36.137121],"type":"Point"}
}