{
  "type": "Feature",
  "properties": {
    "addr:full":"2635 US Hwy 411 S Maryville TN 37801",
    "addr:housenumber":"2635",
    "addr:postcode":"37801",
    "addr:street":"Us Hwy 411 S",
    "iso:country":"US",
    "sg:address":"2635 US Hwy 411 S",
    "sg:city":"Maryville",
    "sg:classifiers":[
        {
            "category":"Restaurant",
            "type":"Food & Drink"
        }
    ],
    "sg:phone":"+1 865 380 8880",
    "sg:postcode":"37801",
    "sg:province":"TN",
    "wof:name":"Four Eleven Restaurant",
    "wof:placetype":"venue"
},
  "geometry": {"coordinates":[-84.019029,35.714805],"type":"Point"}
}