{
  "type": "Feature",
  "properties": {
    "iso:country":"US",
    "sg:address":"3401 W End Ave",
    "sg:city":"Nashville",
    "sg:classifiers":[
        {
            "category":"Banks & Credit Unions",
            "subcategory":"Financial Services",
            "type":"Services"
        }
    ],
    "sg:phone":"+1 615 665 3818",
    "sg:postcode":"37203",
    "sg:province":"TN",
    "sg:tags":[
        "investment",
        "closed"
    ],
    "wof:name":"Solidus Co",
    "wof:placetype":"venue"
},
  "geometry": {"coordinates":[-86.820881,36.137624],"type":"Point"}
}