{
  "type": "Feature",
  "properties": {
    "iso:country":"US",
    "sg:address":"1400 Davidson St",
    "sg:city":"Nashville",
    "sg:classifiers":[
        {
            "category":"Wholesale",
            "subcategory":"Construction Materials",
            "type":"Manufacturing & Wholesale Goods"
        }
    ],
    "sg:phone":"+1 615 425 2700",
    "sg:postcode":"37206",
    "sg:province":"TN",
    "sg:tags":[
        "insulation"
    ],
    "wof:name":"Insulation Supply Co",
    "wof:placetype":"venue"
},
  "geometry": {"coordinates":[-86.744404,36.16316],"type":"Point"}
}