{
  "type": "Feature",
  "properties": {
    "iso:country":"US",
    "sg:address":"34 Oak Tree Dr",
    "sg:city":"Mc Minnville",
    "sg:classifiers":[
        {
            "category":"Organizations",
            "subcategory":"Religious Organization",
            "type":"Services"
        }
    ],
    "sg:phone":"+1 931 668 8648",
    "sg:postcode":"37110",
    "sg:province":"TN",
    "sg:tags":[
        "church"
    ],
    "wof:name":"Temple Baptist Church ( Inc)",
    "wof:placetype":"venue"
},
  "geometry": {"coordinates":[-85.847257,35.708264],"type":"Point"}
}