{
  "type": "Feature",
  "properties": {
    "iso:country":"US",
    "sg:address":"1630 Lakeshore Dr",
    "sg:city":"Murfreesboro",
    "sg:classifiers":[
        {
            "category":"Retail",
            "subcategory":"Repair Shop",
            "type":"Services"
        }
    ],
    "sg:phone":"+1 615 438 8241",
    "sg:postcode":"37130",
    "sg:province":"TN",
    "sg:tags":[
        "bathtub",
        "sink",
        "refinishing"
    ],
    "wof:name":"Wes & Assoc",
    "wof:placetype":"venue"
},
  "geometry": {"coordinates":[-86.366208,35.819515],"type":"Point"}
}