{
  "type": "Feature",
  "properties": {
    "iso:country":"US",
    "sg:address":"312 High St",
    "sg:city":"Maryville",
    "sg:classifiers":[
        {
            "category":"Health Services",
            "subcategory":"Doctor",
            "type":"Services"
        }
    ],
    "sg:phone":"+1 865 982 8000",
    "sg:postcode":"37804",
    "sg:province":"TN",
    "sg:tags":[
        "dentist"
    ],
    "wof:name":"John B Briley DDS",
    "wof:placetype":"venue"
},
  "geometry": {"coordinates":[-83.966352,35.755889],"type":"Point"}
}