{
  "type": "Feature",
  "properties": {
    "iso:country":"US",
    "sg:address":"5593 Bates Pike SE",
    "sg:city":"Cleveland",
    "sg:classifiers":[
        {
            "category":"Retail",
            "subcategory":"Animal Services",
            "type":"Services"
        }
    ],
    "sg:phone":"+1 423 892 6725",
    "sg:postcode":"37323",
    "sg:province":"TN",
    "wof:name":"Pet Inn Kennels",
    "wof:placetype":"venue"
},
  "geometry": {"coordinates":[-84.780987,35.112357],"type":"Point"}
}