{
  "type": "Feature",
  "properties": {
    "addr:full":"907 Ski Mountain Rd Gatlinburg TN 37738",
    "addr:housenumber":"907",
    "addr:postcode":"37738",
    "addr:street":"Ski Mountain Rd",
    "iso:country":"US",
    "sg:address":"907 Ski Mountain Rd",
    "sg:city":"Gatlinburg",
    "sg:classifiers":[
        {
            "category":"Restaurant",
            "type":"Food & Drink"
        }
    ],
    "sg:phone":"+1 865 436 7431",
    "sg:postcode":"37738",
    "sg:province":"TN",
    "sg:tags":[
        "eating"
    ],
    "wof:name":"A Pizza & Video Delivered",
    "wof:placetype":"venue"
},
  "geometry": {"coordinates":[-83.54576900000001,35.710777],"type":"Point"}
}