{
  "type": "Feature",
  "properties": {
    "iso:country":"US",
    "sg:address":"303 Henderson Chapel Rd",
    "sg:city":"Pigeon Forge",
    "sg:classifiers":[
        {
            "category":"Travel",
            "subcategory":"Hotels & Motels",
            "type":"Entertainment"
        }
    ],
    "sg:phone":"+1 865 429 7700",
    "sg:postcode":"37863",
    "sg:province":"TN",
    "sg:website":"www.musicroadhotel.com",
    "wof:name":"Music Road Hotel",
    "wof:placetype":"venue"
},
  "geometry": {"coordinates":[-83.579674,35.813846],"type":"Point"}
}