{
  "type": "Feature",
  "properties": {
    "iso:country":"US",
    "sg:address":"1309 Darlene Cir",
    "sg:city":"Chattanooga",
    "sg:classifiers":[
        {
            "category":"Building & Trades",
            "subcategory":"Construction",
            "type":"Services"
        }
    ],
    "sg:phone":"+1 423 867 9294",
    "sg:postcode":"37412",
    "sg:province":"TN",
    "sg:tags":[
        "residential"
    ],
    "wof:name":"Jason Heltons S",
    "wof:placetype":"venue"
},
  "geometry": {"coordinates":[-85.257339,34.991513],"type":"Point"}
}