{
  "type": "Feature",
  "properties": {
    "iso:country":"US",
    "sg:address":"291 S Washington St",
    "sg:city":"Ripley",
    "sg:classifiers":[
        {
            "category":"Shopping",
            "subcategory":"Clothing, Apparel, & Fashions",
            "type":"Retail Goods"
        }
    ],
    "sg:phone":"+1 731 635 3007",
    "sg:postcode":"38063",
    "sg:province":"TN",
    "sg:tags":[
        "woman"
    ],
    "wof:name":"New York Fashions",
    "wof:placetype":"venue"
},
  "geometry": {"coordinates":[-89.53911600000001,35.739964],"type":"Point"}
}