{
  "type": "Feature",
  "properties": {
    "iso:country":"US",
    "sg:address":"2794 Bartlett Blvd",
    "sg:city":"Bartlett",
    "sg:classifiers":[
        {
            "category":"Real Estate",
            "subcategory":"Real Estate Agent",
            "type":"Services"
        }
    ],
    "sg:phone":"+1 901 384 7888",
    "sg:postcode":"38134",
    "sg:province":"TN",
    "sg:tags":[
        "appraiser"
    ],
    "wof:name":"Appraisal Group",
    "wof:placetype":"venue"
},
  "geometry": {"coordinates":[-89.864818,35.202083],"type":"Point"}
}