{
  "type": "Feature",
  "properties": {
    "addr:full":"20 Depot Rd Cookeville TN 38581",
    "addr:housenumber":"20",
    "addr:postcode":"38581",
    "addr:street":"Depot Rd",
    "iso:country":"US",
    "sg:address":"20 Depot Rd",
    "sg:city":"Cookeville",
    "sg:classifiers":[
        {
            "category":"Railroad",
            "type":"Transportation"
        }
    ],
    "sg:phone":"+1 931 526 3704",
    "sg:postcode":"38581",
    "sg:province":"TN",
    "wof:name":"Nashville Eastern Railroad",
    "wof:placetype":"venue"
},
  "geometry": {"coordinates":[-85.63378400000001,35.774084],"type":"Point"}
}