{
  "type": "Feature",
  "properties": {
    "addr:full":"702 W Emory Rd Powell TN 37849",
    "addr:housenumber":"702",
    "addr:postcode":"37849",
    "addr:street":"W Emory Rd",
    "iso:country":"US",
    "sg:address":"702 W Emory Rd",
    "sg:city":"Powell",
    "sg:classifiers":[
        {
            "category":"Social Services",
            "type":"Services"
        }
    ],
    "sg:phone":"+1 865 938 1243",
    "sg:postcode":"37849",
    "sg:province":"TN",
    "sg:tags":[
        "counseling"
    ],
    "wof:name":"Pamela Hall Mathews",
    "wof:placetype":"venue"
},
  "geometry": {"coordinates":[-84.024862,36.034432],"type":"Point"}
}