{
  "type": "Feature",
  "properties": {
    "addr:full":"6629 Rocky Park Dr Memphis TN 38141",
    "addr:housenumber":"6629",
    "addr:postcode":"38141",
    "addr:street":"Rocky Park Dr",
    "iso:country":"US",
    "sg:address":"6629 Rocky Park Dr",
    "sg:city":"Memphis",
    "sg:classifiers":[
        {
            "category":"Shopping",
            "subcategory":"Clothing, Apparel, & Fashions",
            "type":"Retail Goods"
        }
    ],
    "sg:phone":"+1 901 566 0871",
    "sg:postcode":"38141",
    "sg:province":"TN",
    "sg:tags":[
        "co",
        "glove"
    ],
    "wof:name":"Bonijans Boni Bnwear Bonisport",
    "wof:placetype":"venue"
},
  "geometry": {"coordinates":[-89.842001,35.032047],"type":"Point"}
}