{
  "type": "Feature",
  "properties": {
    "iso:country":"US",
    "sg:address":"4649 Kirby Pkwy",
    "sg:city":"Memphis",
    "sg:classifiers":[
        {
            "category":"Insurance",
            "subcategory":"Insurance Agent",
            "type":"Services"
        }
    ],
    "sg:phone":"+1 901 794 2038",
    "sg:postcode":"38141",
    "sg:province":"TN",
    "wof:name":"Primerica Financial Svc",
    "wof:placetype":"venue"
},
  "geometry": {"coordinates":[-89.84876199999999,35.021784],"type":"Point"}
}