{
  "type": "Feature",
  "properties": {
    "iso:country":"US",
    "sg:address":"124 S Carter St",
    "sg:city":"Sparta",
    "sg:classifiers":[
        {
            "category":"Manufacturing",
            "subcategory":"Printing",
            "type":"Manufacturing & Wholesale Goods"
        }
    ],
    "sg:phone":"+1 931 836 3361",
    "sg:postcode":"38583",
    "sg:province":"TN",
    "sg:tags":[
        "newspaper"
    ],
    "wof:name":"Tennessean Substation",
    "wof:placetype":"venue"
},
  "geometry": {"coordinates":[-85.471172,35.92355],"type":"Point"}
}