{
  "type": "Feature",
  "properties": {
    "iso:country":"US",
    "sg:address":"2450 Martin Luther King Jr Ave",
    "sg:city":"Knoxville",
    "sg:classifiers":[
        {
            "category":"Food & Beverages",
            "subcategory":"Groceries & Convenience Stores",
            "type":"Retail Goods"
        }
    ],
    "sg:phone":"+1 865 521 6522",
    "sg:postcode":"37915",
    "sg:province":"TN",
    "sg:tags":[
        "grocer"
    ],
    "wof:name":"Holiday Discount",
    "wof:placetype":"venue"
},
  "geometry": {"coordinates":[-83.894043,35.982574],"type":"Point"}
}