{
  "type": "Feature",
  "properties": {
    "addr:full":"369 Grandview Dr Smithville TN 37166",
    "addr:housenumber":"369",
    "addr:postcode":"37166",
    "addr:street":"Grandview Dr",
    "iso:country":"US",
    "sg:address":"369 Grandview Dr",
    "sg:city":"Smithville",
    "sg:classifiers":[
        {
            "category":"Autos & Motor Vehicles",
            "subcategory":"Automobile Sales",
            "type":"Retail Goods"
        }
    ],
    "sg:phone":"+1 615 215 9188",
    "sg:postcode":"37166",
    "sg:province":"TN",
    "sg:tags":[
        "car",
        "dealer"
    ],
    "wof:name":"Fasco AC Motor",
    "wof:placetype":"venue"
},
  "geometry": {"coordinates":[-85.77581499999999,35.981082],"type":"Point"}
}