{
  "type": "Feature",
  "properties": {
    "addr:full":"1527 Arden Ln Morristown TN 37813",
    "addr:housenumber":"1527",
    "addr:postcode":"37813",
    "addr:street":"Arden Ln",
    "iso:country":"US",
    "sg:address":"1527 Arden Ln",
    "sg:city":"Morristown",
    "sg:classifiers":[
        {
            "category":"Personal",
            "subcategory":"Beauty Salon",
            "type":"Services"
        }
    ],
    "sg:phone":"+1 423 587 1984",
    "sg:postcode":"37813",
    "sg:province":"TN",
    "sg:tags":[
        "shop"
    ],
    "wof:name":"Hair Unlimited",
    "wof:placetype":"venue"
},
  "geometry": {"coordinates":[-83.254451,36.191595],"type":"Point"}
}