{
  "type": "Feature",
  "properties": {
    "iso:country":"US",
    "sg:address":"1105 Whitney Dr",
    "sg:city":"Columbia",
    "sg:classifiers":[
        {
            "category":"Retail",
            "subcategory":"Portrait Studio",
            "type":"Services"
        }
    ],
    "sg:phone":"+1 931 388 3143",
    "sg:postcode":"38401",
    "sg:province":"TN",
    "sg:tags":[
        "photo"
    ],
    "wof:name":"Horsepix Photography",
    "wof:placetype":"venue"
},
  "geometry": {"coordinates":[-87.082052,35.590117],"type":"Point"}
}