{
  "type": "Feature",
  "properties": {
    "addr:full":"732 W Main St Chattanooga TN 37402",
    "addr:housenumber":"732",
    "addr:postcode":"37402",
    "addr:street":"W Main St",
    "iso:country":"US",
    "sg:address":"732 W Main St",
    "sg:city":"Chattanooga",
    "sg:classifiers":[
        {
            "category":"Building & Trades",
            "subcategory":"Construction",
            "type":"Services"
        }
    ],
    "sg:phone":"+1 423 265 2379",
    "sg:postcode":"37402",
    "sg:province":"TN",
    "sg:tags":[
        "waterproofing",
        "contractor"
    ],
    "wof:name":"B-Dry Waterproofing Systems",
    "wof:placetype":"venue"
},
  "geometry": {"coordinates":[-85.317573,35.039867],"type":"Point"}
}