{
  "type": "Feature",
  "properties": {
    "iso:country":"US",
    "sg:address":"998 Thompson Rd",
    "sg:city":"Pegram",
    "sg:classifiers":[
        {
            "category":"Marine",
            "type":"Transportation"
        }
    ],
    "sg:phone":"+1 615 646 0491",
    "sg:postcode":"37143",
    "sg:province":"TN",
    "sg:tags":[
        "surveyor"
    ],
    "wof:name":"Southwind Marine Svc",
    "wof:placetype":"venue"
},
  "geometry": {"coordinates":[-87.08526999999999,36.086172],"type":"Point"}
}