{
  "type": "Feature",
  "properties": {
    "iso:country":"US",
    "sg:address":"705 Murfreesboro Rd",
    "sg:city":"Franklin",
    "sg:classifiers":[
        {
            "category":"Building & Trades",
            "subcategory":"Construction",
            "type":"Services"
        }
    ],
    "sg:phone":"+1 615 794 4766",
    "sg:postcode":"37064",
    "sg:province":"TN",
    "sg:tags":[
        "general",
        "contractor"
    ],
    "wof:name":"Ralston Creek Co LLC",
    "wof:placetype":"venue"
},
  "geometry": {"coordinates":[-86.856996,35.91854],"type":"Point"}
}