{
  "type": "Feature",
  "properties": {
    "iso:country":"US",
    "sg:address":"860 Willow St",
    "sg:city":"Selmer",
    "sg:classifiers":[
        {
            "category":"Professional",
            "subcategory":"Art Services",
            "type":"Services"
        }
    ],
    "sg:phone":"+1 731 646 2551",
    "sg:postcode":"38375",
    "sg:province":"TN",
    "sg:tags":[
        "graphic",
        "designer"
    ],
    "wof:name":"King Arley",
    "wof:placetype":"venue"
},
  "geometry": {"coordinates":[-88.598491,35.182404],"type":"Point"}
}