{
  "type": "Feature",
  "properties": {
    "iso:country":"US",
    "sg:address":"502 Lost Tree Ln",
    "sg:city":"Knoxville",
    "sg:classifiers":[
        {
            "category":"Shopping",
            "type":"Retail Goods"
        }
    ],
    "sg:phone":"+1 865 675 4412",
    "sg:postcode":"37934",
    "sg:province":"TN",
    "sg:tags":[
        "art",
        "gallery",
        "dealer"
    ],
    "wof:name":"Bobbie Crews Studio",
    "wof:placetype":"venue"
},
  "geometry": {"coordinates":[-84.185215,35.882071],"type":"Point"}
}