{
  "type": "Feature",
  "properties": {
    "iso:country":"US",
    "sg:address":"1917 Edward Cove",
    "sg:city":"Memphis",
    "sg:classifiers":[
        {
            "category":"Wholesale",
            "subcategory":"Machinery & Supplies",
            "type":"Manufacturing & Wholesale Goods"
        }
    ],
    "sg:phone":"+1 901 722 8383",
    "sg:postcode":"38107",
    "sg:province":"TN",
    "sg:tags":[
        "shop",
        "equipment",
        "establishment",
        "beauty"
    ],
    "wof:name":"Dudley Products 165",
    "wof:placetype":"venue"
},
  "geometry": {"coordinates":[-89.993379,35.166675],"type":"Point"}
}