{
  "type": "Feature",
  "properties": {
    "iso:country":"US",
    "sg:address":"21 White Bridge Pike",
    "sg:city":"Nashville",
    "sg:classifiers":[
        {
            "category":"Retail",
            "subcategory":"Laundry & Dry Cleaning",
            "type":"Services"
        }
    ],
    "sg:phone":"+1 615 352 8004",
    "sg:postcode":"37205",
    "sg:province":"TN",
    "sg:tags":[
        "cleaners"
    ],
    "wof:name":"Dryclean USA",
    "wof:placetype":"venue"
},
  "geometry": {"coordinates":[-86.85060300000001,36.127113],"type":"Point"}
}