{
  "type": "Feature",
  "properties": {
    "addr:full":"214 Gallatin Pike S Madison TN 37115",
    "addr:housenumber":"214",
    "addr:postcode":"37115",
    "addr:street":"Gallatin Pike",
    "iso:country":"US",
    "sg:address":"214 Gallatin Pike S",
    "sg:city":"Madison",
    "sg:classifiers":[
        {
            "category":"Restaurant",
            "type":"Food & Drink"
        }
    ],
    "sg:phone":"+1 615 868 9291",
    "sg:postcode":"37115",
    "sg:province":"TN",
    "sg:tags":[
        "out"
    ],
    "sg:website":"www.mrswinners.com",
    "wof:name":"Mrs Winners Chicken & Biscuits",
    "wof:placetype":"venue"
},
  "geometry": {"coordinates":[-86.71278100000001,36.260387],"type":"Point"}
}