{
  "type": "Feature",
  "properties": {
    "iso:country":"US",
    "sg:address":"4117 Yale Rd",
    "sg:city":"Memphis",
    "sg:classifiers":[
        {
            "category":"Autos & Motor Vehicles",
            "subcategory":"Fuel & Gas Station",
            "type":"Retail Goods"
        }
    ],
    "sg:phone":"+1 901 385 1455",
    "sg:postcode":"38128",
    "sg:province":"TN",
    "sg:tags":[
        "station",
        "gasoline"
    ],
    "wof:name":"Express Gas",
    "wof:placetype":"venue"
},
  "geometry": {"coordinates":[-89.925803,35.220439],"type":"Point"}
}