{
  "type": "Feature",
  "properties": {
    "iso:country":"US",
    "sg:address":"1305 Chisholm Rd",
    "sg:city":"Cypress Inn",
    "sg:classifiers":[
        {
            "category":"Professional",
            "type":"Services"
        }
    ],
    "sg:phone":"+1 931 724 5257",
    "sg:postcode":"38450",
    "sg:province":"TN",
    "wof:name":"Darrin Ward",
    "wof:placetype":"venue"
},
  "geometry": {"coordinates":[-87.753952,35.136676],"type":"Point"}
}