{
  "type": "Feature",
  "properties": {
    "addr:full":"330 Sam Davis Rd Smyrna TN 37167",
    "addr:housenumber":"330",
    "addr:postcode":"37167",
    "addr:street":"Sam Davis Rd",
    "iso:country":"US",
    "sg:address":"330 Sam Davis Rd",
    "sg:city":"Smyrna",
    "sg:classifiers":[
        {
            "category":"Health Services",
            "subcategory":"Hospital",
            "type":"Services"
        }
    ],
    "sg:phone":"+1 615 355 8960",
    "sg:postcode":"37167",
    "sg:province":"TN",
    "sg:tags":[
        "specialty"
    ],
    "wof:name":"Alcohol Rutherford & Drug",
    "wof:placetype":"venue"
},
  "geometry": {"coordinates":[-86.51691700000001,35.98489],"type":"Point"}
}