{
  "type": "Feature",
  "properties": {
    "iso:country":"US",
    "sg:address":"5500 Mary Ln",
    "sg:city":"Arlington",
    "sg:classifiers":[
        {
            "category":"Real Estate",
            "subcategory":"Real Estate Agent",
            "type":"Services"
        }
    ],
    "sg:phone":"+1 901 867 7904",
    "sg:postcode":"38002",
    "sg:province":"TN",
    "sg:website":"www.bowdenbuilding.com",
    "wof:name":"Bowden Homes",
    "wof:placetype":"venue"
},
  "geometry": {"coordinates":[-89.69207900000001,35.278169],"type":"Point"}
}