{
  "type": "Feature",
  "properties": {
    "iso:country":"US",
    "sg:address":"1760 Oak Grove Rd S",
    "sg:city":"Springville",
    "sg:classifiers":[
        {
            "category":"Organizations",
            "subcategory":"Religious Organization",
            "type":"Services"
        }
    ],
    "sg:phone":"+1 731 644 0419",
    "sg:postcode":"38256",
    "sg:province":"TN",
    "wof:name":"Sulphur Well Church Of Christ",
    "wof:placetype":"venue"
},
  "geometry": {"coordinates":[-88.16904100000001,36.362278],"type":"Point"}
}