{
  "type": "Feature",
  "properties": {
    "iso:country":"US",
    "sg:address":"6208 Mountain Park Dr",
    "sg:city":"Knoxville",
    "sg:classifiers":[
        {
            "category":"Banks & Credit Unions",
            "subcategory":"Financial Services",
            "type":"Services"
        }
    ],
    "sg:phone":"+1 865 687 3247",
    "sg:postcode":"37918",
    "sg:province":"TN",
    "sg:tags":[
        "fund",
        "investment"
    ],
    "wof:name":"Dempster Family Ltd Partnr",
    "wof:placetype":"venue"
},
  "geometry": {"coordinates":[-83.871793,36.079052],"type":"Point"}
}