{
  "type": "Feature",
  "properties": {
    "addr:full":"9 Culver Cove Jackson TN 38305",
    "addr:housenumber":"9",
    "addr:postcode":"38305",
    "addr:street":"Culver Cove",
    "iso:country":"US",
    "sg:address":"9 Culver Cove",
    "sg:city":"Jackson",
    "sg:classifiers":[
        {
            "category":"Professional",
            "subcategory":"Business Services",
            "type":"Services"
        }
    ],
    "sg:phone":"+1 731 423 3287",
    "sg:postcode":"38305",
    "sg:province":"TN",
    "wof:name":"Sk Enterprises Inc",
    "wof:placetype":"venue"
},
  "geometry": {"coordinates":[-88.797845,35.688622],"type":"Point"}
}