{
  "type": "Feature",
  "properties": {
    "addr:full":"208 W Fairview Ave Johnson City TN 37604",
    "addr:housenumber":"208",
    "addr:postcode":"37604",
    "addr:street":"W Fairview Ave",
    "iso:country":"US",
    "sg:address":"208 W Fairview Ave",
    "sg:city":"Johnson City",
    "sg:classifiers":[
        {
            "category":"Health Services",
            "subcategory":"Clinic",
            "type":"Services"
        }
    ],
    "sg:phone":"+1 423 928 7261",
    "sg:postcode":"37604",
    "sg:province":"TN",
    "sg:tags":[
        "specialty",
        "outpatient"
    ],
    "wof:name":"Fairview Associates",
    "wof:placetype":"venue"
},
  "geometry": {"coordinates":[-82.356863,36.318994],"type":"Point"}
}