{
  "type": "Feature",
  "properties": {
    "iso:country":"US",
    "sg:address":"124 E Main St",
    "sg:city":"Rogersville",
    "sg:classifiers":[
        {
            "category":"Shopping",
            "type":"Retail Goods"
        }
    ],
    "sg:phone":"+1 423 921 7656",
    "sg:postcode":"37857",
    "sg:province":"TN",
    "sg:tags":[
        "art",
        "gallery",
        "dealer"
    ],
    "wof:name":"Local Artists Gallery",
    "wof:placetype":"venue"
},
  "geometry": {"coordinates":[-83.006664,36.40696],"type":"Point"}
}