{
  "type": "Feature",
  "properties": {
    "addr:full":"1015 W Kirkland Ave Nashville TN 37216",
    "addr:housenumber":"1015",
    "addr:postcode":"37216",
    "addr:street":"W Kirkland Ave",
    "iso:country":"US",
    "sg:address":"1015 W Kirkland Ave",
    "sg:city":"Nashville",
    "sg:classifiers":[
        {
            "category":"Professional",
            "type":"Services"
        }
    ],
    "sg:phone":"+1 615 226 5936",
    "sg:postcode":"37216",
    "sg:province":"TN",
    "sg:tags":[
        "establishment"
    ],
    "wof:name":"Wrightway Enterprises",
    "wof:placetype":"venue"
},
  "geometry": {"coordinates":[-86.735024,36.209084],"type":"Point"}
}