{
  "type": "Feature",
  "properties": {
    "addr:full":"535 Todd Long Rd Scotts Hill TN 38374",
    "addr:housenumber":"535",
    "addr:postcode":"38374",
    "addr:street":"Todd Long Rd",
    "iso:country":"US",
    "sg:address":"535 Todd Long Rd",
    "sg:city":"Scotts Hill",
    "sg:classifiers":[
        {
            "category":"Building & Trades",
            "subcategory":"Construction",
            "type":"Services"
        }
    ],
    "sg:phone":"+1 731 968 5047",
    "sg:postcode":"38374",
    "sg:province":"TN",
    "sg:tags":[
        "dry wall",
        "contractor"
    ],
    "wof:name":"West Tennesse Dry Wall",
    "wof:placetype":"venue"
},
  "geometry": {"coordinates":[-88.251045,35.595942],"type":"Point"}
}