{
  "type": "Feature",
  "properties": {
    "iso:country":"US",
    "sg:address":"6420 Shallowford Rd",
    "sg:city":"Chattanooga",
    "sg:classifiers":[
        {
            "category":"Retail",
            "subcategory":"Auto Repair",
            "type":"Services"
        }
    ],
    "sg:phone":"+1 423 855 2072",
    "sg:postcode":"37421",
    "sg:province":"TN",
    "sg:tags":[
        "automotive"
    ],
    "wof:name":"Carter Towing",
    "wof:placetype":"venue"
},
  "geometry": {"coordinates":[-85.17486700000001,35.049622],"type":"Point"}
}