{
  "type": "Feature",
  "properties": {
    "iso:country":"US",
    "sg:address":"1846 Winfield Dunn Pkwy",
    "sg:city":"Sevierville",
    "sg:classifiers":[
        {
            "category":"Food & Beverages",
            "subcategory":"Groceries & Convenience Stores",
            "type":"Retail Goods"
        }
    ],
    "sg:phone":"+1 865 774 1969",
    "sg:postcode":"37876",
    "sg:province":"TN",
    "sg:tags":[
        "market"
    ],
    "wof:name":"Marketplace",
    "wof:placetype":"venue"
},
  "geometry": {"coordinates":[-83.580224,35.917071],"type":"Point"}
}