{
  "type": "Feature",
  "properties": {
    "addr:full":"415 Jonquil Ct Murfreesboro TN 37128",
    "addr:housenumber":"415",
    "addr:postcode":"37128",
    "addr:street":"Jonquil Ct",
    "iso:country":"US",
    "sg:address":"415 Jonquil Ct",
    "sg:city":"Murfreesboro",
    "sg:classifiers":[
        {
            "category":"Building & Trades",
            "subcategory":"Construction",
            "type":"Services"
        }
    ],
    "sg:phone":"+1 615 867 3801",
    "sg:postcode":"37128",
    "sg:province":"TN",
    "sg:tags":[
        "insulation",
        "heat",
        "contractor"
    ],
    "wof:name":"Mid Tennessee Insulation Contr",
    "wof:placetype":"venue"
},
  "geometry": {"coordinates":[-86.403538,35.809764],"type":"Point"}
}