{
  "type": "Feature",
  "properties": {
    "iso:country":"US",
    "sg:address":"4115 Rossville Blvd",
    "sg:city":"Chattanooga",
    "sg:classifiers":[
        {
            "category":"Fast Food",
            "type":"Food & Drink"
        },
        {
            "category":"Restaurant",
            "type":"Food & Drink"
        }
    ],
    "sg:phone":"+1 423 867 4226",
    "sg:postcode":"37407",
    "sg:province":"TN",
    "sg:tags":[
        "mexican"
    ],
    "sg:website":"http://www.tacobell.com",
    "wof:name":"Taco Bell",
    "wof:placetype":"venue"
},
  "geometry": {"coordinates":[-85.29114800000001,34.996232],"type":"Point"}
}