{
  "type": "Feature",
  "properties": {
    "iso:country":"US",
    "sg:address":"8625 Flagstone Way",
    "sg:city":"Knoxville",
    "sg:classifiers":[
        {
            "category":"Professional",
            "subcategory":"Business Services",
            "type":"Services"
        }
    ],
    "sg:phone":"+1 865 691 8111",
    "sg:postcode":"37923",
    "sg:province":"TN",
    "sg:tags":[
        "interior",
        "consultant",
        "design",
        "decorator"
    ],
    "wof:name":"Shirley B Sturm Interiors",
    "wof:placetype":"venue"
},
  "geometry": {"coordinates":[-84.071482,35.941537],"type":"Point"}
}