{
  "type": "Feature",
  "properties": {
    "addr:full":"1601 Hatcher Ln Columbia TN 38401",
    "addr:housenumber":"1601",
    "addr:postcode":"38401",
    "addr:street":"Hatcher Ln",
    "iso:country":"US",
    "sg:address":"1601 Hatcher Ln",
    "sg:city":"Columbia",
    "sg:classifiers":[
        {
            "category":"Health Services",
            "subcategory":"Doctor",
            "type":"Services"
        }
    ],
    "sg:phone":"+1 931 381 2802",
    "sg:postcode":"38401",
    "sg:province":"TN",
    "sg:tags":[
        "medical"
    ],
    "wof:name":"Fulks K Dwayne MD",
    "wof:placetype":"venue"
},
  "geometry": {"coordinates":[-87.064213,35.604147],"type":"Point"}
}