{
  "type": "Feature",
  "properties": {
    "addr:full":"2101 N Roan St Johnson City TN 37601",
    "addr:housenumber":"2101",
    "addr:postcode":"37601",
    "addr:street":"N Roan St",
    "iso:country":"US",
    "sg:address":"2101 N Roan St",
    "sg:city":"Johnson City",
    "sg:classifiers":[
        {
            "category":"Restaurant",
            "type":"Food & Drink"
        }
    ],
    "sg:menulink":"http://www.allmenus.com/tn/johnson-city/203550-mcdonalds/menu/",
    "sg:phone":"+1 423 282 5663",
    "sg:postcode":"37601",
    "sg:province":"TN",
    "sg:tags":[
        "burger",
        "american"
    ],
    "wof:name":"McDonald's",
    "wof:placetype":"venue"
},
  "geometry": {"coordinates":[-82.375646,36.340559],"type":"Point"}
}