{
  "type": "Feature",
  "properties": {
    "iso:country":"US",
    "sg:address":"2484 Franklin Ln",
    "sg:city":"Murfreesboro",
    "sg:classifiers":[
        {
            "category":"Personal",
            "subcategory":"Beauty Salon",
            "type":"Services"
        }
    ],
    "sg:phone":"+1 615 890 7115",
    "sg:postcode":"37130",
    "sg:province":"TN",
    "sg:tags":[
        "shop"
    ],
    "wof:name":"Kens Kut & Kurl",
    "wof:placetype":"venue"
},
  "geometry": {"coordinates":[-86.370997,35.890633],"type":"Point"}
}