{
  "type": "Feature",
  "properties": {
    "iso:country":"US",
    "sg:address":"1741 Disneyland Rd",
    "sg:city":"Sparta",
    "sg:classifiers":[
        {
            "category":"Building & Trades",
            "subcategory":"Pest Control",
            "type":"Services"
        }
    ],
    "sg:phone":"+1 931 657 5449",
    "sg:postcode":"38583",
    "sg:province":"TN",
    "wof:name":"Hawkins Termite & Pest Control",
    "wof:placetype":"venue"
},
  "geometry": {"coordinates":[-85.516261,35.877589],"type":"Point"}
}