{
  "type": "Feature",
  "properties": {
    "iso:country":"US",
    "sg:address":"3451 Tightfit Rd",
    "sg:city":"Baxter",
    "sg:classifiers":[
        {
            "category":"Farming",
            "subcategory":"Farm",
            "type":"Manufacturing & Wholesale Goods"
        }
    ],
    "sg:phone":"+1 931 858 0792",
    "sg:postcode":"38544",
    "sg:province":"TN",
    "sg:tags":[
        "crop",
        "general"
    ],
    "wof:name":"S & S Farms",
    "wof:placetype":"venue"
},
  "geometry": {"coordinates":[-85.682609,36.127848],"type":"Point"}
}