{
  "type": "Feature",
  "properties": {
    "iso:country":"US",
    "sg:address":"7524 Chapman Hwy",
    "sg:city":"Knoxville",
    "sg:classifiers":[
        {
            "category":"Professional",
            "subcategory":"Business Services",
            "type":"Services"
        }
    ],
    "sg:phone":"+1 865 579 0110",
    "sg:postcode":"37920",
    "sg:province":"TN",
    "wof:name":"U F O Unclaimed Freight",
    "wof:placetype":"venue"
},
  "geometry": {"coordinates":[-83.838459,35.907392],"type":"Point"}
}