{
  "type": "Feature",
  "properties": {
    "addr:full":"5201 Kingston Pike Knoxville TN 37919",
    "addr:housenumber":"5201",
    "addr:postcode":"37919",
    "addr:street":"Kingston Pike",
    "iso:country":"US",
    "sg:address":"5201 Kingston Pike",
    "sg:city":"Knoxville",
    "sg:classifiers":[
        {
            "category":"Personal",
            "subcategory":"Beauty Salon",
            "type":"Services"
        }
    ],
    "sg:phone":"+1 865 584 4422",
    "sg:postcode":"37919",
    "sg:province":"TN",
    "wof:name":"Cutting Crew",
    "wof:placetype":"venue"
},
  "geometry": {"coordinates":[-83.991328,35.936752],"type":"Point"}
}