{
  "type": "Feature",
  "properties": {
    "addr:full":"3073 Range Line Rd Memphis TN 38127",
    "addr:housenumber":"3073",
    "addr:postcode":"38127",
    "addr:street":"Range Line Rd",
    "iso:country":"US",
    "sg:address":"3073 Range Line Rd",
    "sg:city":"Memphis",
    "sg:classifiers":[
        {
            "category":"Organizations",
            "subcategory":"Religious Organization",
            "type":"Services"
        }
    ],
    "sg:phone":"+1 901 358 5752",
    "sg:postcode":"38127",
    "sg:province":"TN",
    "sg:tags":[
        "church"
    ],
    "wof:name":"Christian Love Fellowship",
    "wof:placetype":"venue"
},
  "geometry": {"coordinates":[-89.975673,35.209729],"type":"Point"}
}