{
  "type": "Feature",
  "properties": {
    "iso:country":"US",
    "sg:address":"110 Weaver Dr",
    "sg:city":"Dickson",
    "sg:classifiers":[
        {
            "category":"Retail",
            "subcategory":"Repair Shop",
            "type":"Services"
        }
    ],
    "sg:phone":"+1 615 446 3146",
    "sg:postcode":"37055",
    "sg:province":"TN",
    "sg:tags":[
        "ironwork"
    ],
    "wof:name":"Paul Taylor's Ornamental Iron",
    "wof:placetype":"venue"
},
  "geometry": {"coordinates":[-87.40225100000001,36.080175],"type":"Point"}
}