{
  "type": "Feature",
  "properties": {
    "addr:full":"200 Hayden Ln Lafayette TN 37083",
    "addr:housenumber":"200",
    "addr:postcode":"37083",
    "addr:street":"Hayden Ln",
    "iso:country":"US",
    "sg:address":"200 Hayden Ln",
    "sg:city":"Lafayette",
    "sg:classifiers":[
        {
            "category":"Professional",
            "subcategory":"Management & Consulting",
            "type":"Services"
        }
    ],
    "sg:phone":"+1 615 688 4418",
    "sg:postcode":"37083",
    "sg:province":"TN",
    "sg:tags":[
        "employee",
        "consultant",
        "benefit"
    ],
    "wof:name":"Teresa A Wilson Benefits",
    "wof:placetype":"venue"
},
  "geometry": {"coordinates":[-86.040015,36.515421],"type":"Point"}
}