{
  "type": "Feature",
  "properties": {
    "addr:full":"5266 Stewarts Ferry Pike Mount Juliet TN 37122",
    "addr:housenumber":"5266",
    "addr:postcode":"37122",
    "addr:street":"Stewarts Ferry Pike",
    "iso:country":"US",
    "sg:address":"5266 Stewarts Ferry Pike",
    "sg:city":"Mount Juliet",
    "sg:classifiers":[
        {
            "category":"Professional",
            "type":"Services"
        }
    ],
    "sg:phone":"+1 615 449 7987",
    "sg:postcode":"37122",
    "sg:province":"TN",
    "wof:name":"Pzp Inc",
    "wof:placetype":"venue"
},
  "geometry": {"coordinates":[-86.48158599999999,36.116931],"type":"Point"}
}