{
  "type": "Feature",
  "properties": {
    "addr:full":"1418 Monroe Ave Maryville TN 37804",
    "addr:housenumber":"1418",
    "addr:postcode":"37804",
    "addr:street":"Monroe Ave",
    "iso:country":"US",
    "sg:address":"1418 Monroe Ave",
    "sg:city":"Maryville",
    "sg:classifiers":[
        {
            "category":"Building & Trades",
            "subcategory":"Plumbing",
            "type":"Services"
        }
    ],
    "sg:phone":"+1 865 681 8797",
    "sg:postcode":"37804",
    "sg:province":"TN",
    "sg:tags":[
        "conditioning",
        "air",
        "system",
        "contractor"
    ],
    "wof:name":"A & L Heating & Air",
    "wof:placetype":"venue"
},
  "geometry": {"coordinates":[-83.96306800000001,35.770109],"type":"Point"}
}