{
  "type": "Feature",
  "properties": {
    "iso:country":"US",
    "sg:address":"123 Ewing Dr",
    "sg:city":"Nashville",
    "sg:classifiers":[
        {
            "category":"Restaurant",
            "type":"Food & Drink"
        }
    ],
    "sg:phone":"+1 615 262 8009",
    "sg:postcode":"37207",
    "sg:province":"TN",
    "sg:tags":[
        "eating"
    ],
    "wof:name":"China Village",
    "wof:placetype":"venue"
},
  "geometry": {"coordinates":[-86.76451400000001,36.230444],"type":"Point"}
}