{
  "type": "Feature",
  "properties": {
    "iso:country":"US",
    "sg:address":"580 Matson Rd",
    "sg:city":"Jonesborough",
    "sg:classifiers":[
        {
            "category":"Real Estate",
            "subcategory":"Real Estate Operator",
            "type":"Services"
        }
    ],
    "sg:phone":"+1 423 926 2100",
    "sg:postcode":"37659",
    "sg:province":"TN",
    "sg:tags":[
        "apartment"
    ],
    "wof:name":"Matson Village Apartments",
    "wof:placetype":"venue"
},
  "geometry": {"coordinates":[-82.42143900000001,36.292835],"type":"Point"}
}