{
  "type": "Feature",
  "properties": {
    "iso:country":"US",
    "sg:address":"208 4th Ave",
    "sg:city":"Murfreesboro",
    "sg:classifiers":[
        {
            "category":"Organizations",
            "subcategory":"Religious Organization",
            "type":"Services"
        }
    ],
    "sg:phone":"+1 615 895 4124",
    "sg:postcode":"37130",
    "sg:province":"TN",
    "sg:tags":[
        "church"
    ],
    "wof:name":"Victory Assembly Of God",
    "wof:placetype":"venue"
},
  "geometry": {"coordinates":[-86.37144000000001,35.841568],"type":"Point"}
}