{
  "type": "Feature",
  "properties": {
    "iso:country":"US",
    "sg:address":"1678 Camille Way",
    "sg:city":"Cordova",
    "sg:classifiers":[
        {
            "category":"Retail",
            "subcategory":"Repair Shop",
            "type":"Services"
        }
    ],
    "sg:phone":"+1 901 737 1189",
    "sg:postcode":"38016",
    "sg:province":"TN",
    "wof:name":"A 24 Mobile Locksmith",
    "wof:placetype":"venue"
},
  "geometry": {"coordinates":[-89.78388699999999,35.171199],"type":"Point"}
}