{
  "type": "Feature",
  "properties": {
    "iso:country":"US",
    "sg:address":"3300 Rifle Range Rd",
    "sg:city":"Knoxville",
    "sg:classifiers":[
        {
            "category":"Building & Trades",
            "subcategory":"Construction",
            "type":"Services"
        }
    ],
    "sg:phone":"+1 865 686 0154",
    "sg:postcode":"37918",
    "sg:province":"TN",
    "sg:tags":[
        "stucco",
        "contractor"
    ],
    "wof:name":"Precision Stucco LLC",
    "wof:placetype":"venue"
},
  "geometry": {"coordinates":[-83.926109,36.057661],"type":"Point"}
}