{
  "type": "Feature",
  "properties": {
    "iso:country":"US",
    "sg:address":"1075 Lynn Garden Dr",
    "sg:city":"Kingsport",
    "sg:classifiers":[
        {
            "category":"Retail",
            "subcategory":"Repair Shop",
            "type":"Services"
        }
    ],
    "sg:phone":"+1 423 247 0053",
    "sg:postcode":"37665",
    "sg:province":"TN",
    "wof:name":"AAA Discount Plumbing",
    "wof:placetype":"venue"
},
  "geometry": {"coordinates":[-82.566759,36.574571],"type":"Point"}
}