{
  "type": "Feature",
  "properties": {
    "addr:full":"6783 Lee Hwy Chattanooga TN 37421",
    "addr:housenumber":"6783",
    "addr:postcode":"37421",
    "addr:street":"Lee Hwy",
    "iso:country":"US",
    "sg:address":"6783 Lee Hwy",
    "sg:city":"Chattanooga",
    "sg:classifiers":[
        {
            "category":"Real Estate",
            "subcategory":"Real Estate Services",
            "type":"Services"
        },
        {
            "category":"Real Estate",
            "subcategory":"Real Estate Agent",
            "type":"Services"
        }
    ],
    "sg:phone":"+1 423 475 5880",
    "sg:postcode":"37421",
    "sg:province":"TN",
    "sg:tags":[
        "management"
    ],
    "wof:name":"Avenue Real Estate Services",
    "wof:placetype":"venue"
},
  "geometry": {"coordinates":[-85.170269,35.040013],"type":"Point"}
}