{
  "type": "Feature",
  "properties": {
    "iso:country":"US",
    "sg:address":"1121 Union Ave",
    "sg:city":"Memphis",
    "sg:classifiers":[
        {
            "category":"Health Services",
            "subcategory":"Doctor",
            "type":"Services"
        }
    ],
    "sg:phone":"+1 901 448 7131",
    "sg:postcode":"38104",
    "sg:province":"TN",
    "sg:tags":[
        "clinic",
        "practice",
        "family"
    ],
    "wof:name":"Healthplex Family Practice Ctr",
    "wof:placetype":"venue"
},
  "geometry": {"coordinates":[-90.026686,35.137766],"type":"Point"}
}