{
  "type": "Feature",
  "properties": {
    "iso:country":"US",
    "sg:address":"2640 Airpark Dr",
    "sg:city":"Nashville",
    "sg:classifiers":[
        {
            "category":"Autos & Motor Vehicles",
            "subcategory":"Automobile Sales",
            "type":"Retail Goods"
        }
    ],
    "sg:phone":"+1 615 226 4256",
    "sg:postcode":"37206",
    "sg:province":"TN",
    "sg:tags":[
        "aircraft"
    ],
    "sg:website":"www.colemill.com",
    "wof:name":"Colemill Enterprises Inc",
    "wof:placetype":"venue"
},
  "geometry": {"coordinates":[-86.706316,36.190451],"type":"Point"}
}