{
  "type": "Feature",
  "properties": {
    "iso:country":"US",
    "sg:address":"1341 Farrington Dr",
    "sg:city":"Knoxville",
    "sg:classifiers":[
        {
            "category":"Shopping",
            "type":"Retail Goods"
        }
    ],
    "sg:phone":"+1 865 531 3392",
    "sg:postcode":"37923",
    "sg:province":"TN",
    "sg:tags":[
        "merchandise"
    ],
    "wof:name":"Energy Products of TN",
    "wof:placetype":"venue"
},
  "geometry": {"coordinates":[-84.060023,35.888831],"type":"Point"}
}