{
  "type": "Feature",
  "properties": {
    "addr:full":"65 E Carolina Ave Memphis TN 38103",
    "addr:housenumber":"65",
    "addr:postcode":"38103",
    "addr:street":"E Carolina Ave",
    "iso:country":"US",
    "sg:address":"65 E Carolina Ave",
    "sg:city":"Memphis",
    "sg:classifiers":[
        {
            "category":"Freight",
            "type":"Transportation"
        }
    ],
    "sg:phone":"+1 901 521 8238",
    "sg:postcode":"38103",
    "sg:province":"TN",
    "sg:tags":[
        "hauling",
        "trucking"
    ],
    "wof:name":"Somner Express Flatbed Truck",
    "wof:placetype":"venue"
},
  "geometry": {"coordinates":[-90.059299,35.128112],"type":"Point"}
}