{
  "type": "Feature",
  "properties": {
    "iso:country":"US",
    "sg:address":"419 McClain Rd",
    "sg:city":"Martin",
    "sg:phone":"+1 731 587 6674",
    "sg:postcode":"38237",
    "sg:province":"TN",
    "sg:tags":[
        "farm",
        "corn",
        "wheat"
    ],
    "wof:name":"Steve Tuck",
    "wof:placetype":"venue"
},
  "geometry": {"coordinates":[-88.834147,36.310351],"type":"Point"}
}