{
  "type": "Feature",
  "properties": {
    "iso:country":"US",
    "sg:address":"5016 Trailwater Dr",
    "sg:city":"Antioch",
    "sg:classifiers":[
        {
            "category":"Retail",
            "subcategory":"Auto Rental",
            "type":"Services"
        }
    ],
    "sg:phone":"+1 615 268 4471",
    "sg:postcode":"37013",
    "sg:province":"TN",
    "sg:tags":[
        "passenger",
        "car"
    ],
    "wof:name":"Rent A Honey Do",
    "wof:placetype":"venue"
},
  "geometry": {"coordinates":[-86.576027,36.03904],"type":"Point"}
}