{
  "type": "Feature",
  "properties": {
    "addr:full":"6273 E Stage Plz Bartlett TN 38134",
    "addr:housenumber":"6273",
    "addr:postcode":"38134",
    "addr:street":"E Stage Plz",
    "iso:country":"US",
    "sg:address":"6273 E Stage Plz",
    "sg:city":"Bartlett",
    "sg:classifiers":[
        {
            "category":"Personal",
            "subcategory":"Beauty Salon",
            "type":"Services"
        }
    ],
    "sg:phone":"+1 901 388 0217",
    "sg:postcode":"38134",
    "sg:province":"TN",
    "sg:tags":[
        "manicuring"
    ],
    "wof:name":"Nail Care By Kayoua",
    "wof:placetype":"venue"
},
  "geometry": {"coordinates":[-89.854776,35.205681],"type":"Point"}
}