{
  "type": "Feature",
  "properties": {
    "iso:country":"US",
    "sg:address":"2055 Covington Pike",
    "sg:city":"Memphis",
    "sg:classifiers":[
        {
            "category":"Professional",
            "subcategory":"Management & Consulting",
            "type":"Services"
        }
    ],
    "sg:phone":"+1 901 213 5234",
    "sg:postcode":"38128",
    "sg:province":"TN",
    "wof:name":"Curbo Financial Solutions",
    "wof:placetype":"venue"
},
  "geometry": {"coordinates":[-89.896469,35.181778],"type":"Point"}
}