{
  "type": "Feature",
  "properties": {
    "iso:country":"US",
    "sg:address":"1808 Norway St",
    "sg:city":"Bristol",
    "sg:classifiers":[
        {
            "category":"Health Services",
            "subcategory":"Clinic",
            "type":"Services"
        }
    ],
    "sg:phone":"+1 276 494 6183",
    "sg:postcode":"24201",
    "sg:province":"TN",
    "sg:tags":[
        "transcription"
    ],
    "wof:name":"Cmt Home Corp",
    "wof:placetype":"venue"
},
  "geometry": {"coordinates":[-82.202727,36.597536],"type":"Point"}
}