{
  "type": "Feature",
  "properties": {
    "iso:country":"US",
    "sg:address":"727 Parkway",
    "sg:city":"Gatlinburg",
    "sg:classifiers":[
        {
            "category":"Retail",
            "subcategory":"Laundry & Dry Cleaning",
            "type":"Services"
        }
    ],
    "sg:phone":"+1 865 436 4828",
    "sg:postcode":"37738",
    "sg:province":"TN",
    "sg:tags":[
        "uniform",
        "supply"
    ],
    "wof:name":"Gatlinburg Supply Co",
    "wof:placetype":"venue"
},
  "geometry": {"coordinates":[-83.51602699999999,35.712203],"type":"Point"}
}