{
  "type": "Feature",
  "properties": {
    "iso:country":"US",
    "sg:address":"4155 Getwell Rd",
    "sg:city":"Memphis",
    "sg:classifiers":[
        {
            "category":"Wholesale",
            "subcategory":"Stationery",
            "type":"Manufacturing & Wholesale Goods"
        }
    ],
    "sg:phone":"+1 901 367 1177",
    "sg:postcode":"38118",
    "sg:province":"TN",
    "sg:tags":[
        "distributor",
        "product",
        "paper"
    ],
    "wof:name":"Athens Paper Co Inc",
    "wof:placetype":"venue"
},
  "geometry": {"coordinates":[-89.936654,35.035993],"type":"Point"}
}