{
  "type": "Feature",
  "properties": {
    "addr:full":"11110 Kingston Pike Knoxville TN 37934",
    "addr:housenumber":"11110",
    "addr:postcode":"37934",
    "addr:street":"Kingston Pike",
    "iso:country":"US",
    "sg:address":"11110 Kingston Pike",
    "sg:city":"Knoxville",
    "sg:classifiers":[
        {
            "category":"Home & Garden",
            "subcategory":"Furniture",
            "type":"Retail Goods"
        }
    ],
    "sg:phone":"+1 865 966 5909",
    "sg:postcode":"37934",
    "sg:province":"TN",
    "wof:name":"Tattered Rabbit",
    "wof:placetype":"venue"
},
  "geometry": {"coordinates":[-84.148725,35.888279],"type":"Point"}
}