{
  "type": "Feature",
  "properties": {
    "iso:country":"US",
    "sg:address":"708 S Illinois Ave",
    "sg:city":"Oak Ridge",
    "sg:classifiers":[
        {
            "category":"Organizations",
            "subcategory":"Labor Organization",
            "type":"Services"
        }
    ],
    "sg:phone":"+1 865 481 0009",
    "sg:postcode":"37830",
    "sg:province":"TN",
    "wof:name":"Knoxvlle-Oak Ridge Bldg Trades",
    "wof:placetype":"venue"
},
  "geometry": {"coordinates":[-84.233902,36.004602],"type":"Point"}
}