{
  "type": "Feature",
  "properties": {
    "addr:full":"204 Kentucky St Hickman TN 42050",
    "addr:housenumber":"204",
    "addr:postcode":"42050",
    "addr:street":"Kentucky St",
    "iso:country":"US",
    "sg:address":"204 Kentucky St",
    "sg:city":"Hickman",
    "sg:classifiers":[
        {
            "category":"Health Services",
            "subcategory":"Chiropractor",
            "type":"Services"
        }
    ],
    "sg:phone":"+1 270 236 3210",
    "sg:postcode":"42050",
    "sg:province":"TN",
    "wof:name":"Hickman Chiropractic Ctr",
    "wof:placetype":"venue"
},
  "geometry": {"coordinates":[-89.19288,36.573076],"type":"Point"}
}