{
  "type": "Feature",
  "properties": {
    "iso:country":"US",
    "sg:address":"353 Old Airport Rd",
    "sg:city":"Bristol",
    "sg:classifiers":[
        {
            "category":"Manufacturing",
            "subcategory":"Signs",
            "type":"Manufacturing & Wholesale Goods"
        }
    ],
    "sg:phone":"+1 276 669 8630",
    "sg:postcode":"24201",
    "sg:province":"TN",
    "sg:tags":[
        "specialty",
        "mfg"
    ],
    "wof:name":"L A Design Graphics",
    "wof:placetype":"venue"
},
  "geometry": {"coordinates":[-82.132017,36.616822],"type":"Point"}
}