{
  "type": "Feature",
  "properties": {
    "iso:country":"US",
    "sg:address":"215 Stiles Ln",
    "sg:city":"Harriman",
    "sg:classifiers":[
        {
            "category":"Professional",
            "subcategory":"Engineering",
            "type":"Services"
        }
    ],
    "sg:phone":"+1 865 882 1542",
    "sg:postcode":"37748",
    "sg:province":"TN",
    "wof:name":"Jacks Shop",
    "wof:placetype":"venue"
},
  "geometry": {"coordinates":[-84.536807,35.952917],"type":"Point"}
}