{
  "type": "Feature",
  "properties": {
    "iso:country":"US",
    "sg:address":"1 Jim Bob Scruggs Rd",
    "sg:city":"Humboldt",
    "sg:classifiers":[
        {
            "category":"Retail",
            "subcategory":"Auto Repair",
            "type":"Services"
        }
    ],
    "sg:phone":"+1 731 787 7200",
    "sg:postcode":"38343",
    "sg:province":"TN",
    "sg:tags":[
        "automotive"
    ],
    "wof:name":"Dentons Lynn Wrecker Service",
    "wof:placetype":"venue"
},
  "geometry": {"coordinates":[-88.87862699999999,35.847245],"type":"Point"}
}