{
  "type": "Feature",
  "properties": {
    "addr:full":"75 Carriage Pl Clinton TN 37716",
    "addr:housenumber":"75",
    "addr:postcode":"37716",
    "addr:street":"Carriage Pl",
    "iso:country":"US",
    "sg:address":"75 Carriage Pl",
    "sg:city":"Clinton",
    "sg:classifiers":[
        {
            "category":"Professional",
            "subcategory":"Management & Consulting",
            "type":"Services"
        }
    ],
    "sg:phone":"+1 865 457 8552",
    "sg:postcode":"37716",
    "sg:province":"TN",
    "sg:tags":[
        "business"
    ],
    "wof:name":"SLM Consulting",
    "wof:placetype":"venue"
},
  "geometry": {"coordinates":[-84.123878,36.120672],"type":"Point"}
}