{
  "type": "Feature",
  "properties": {
    "iso:country":"US",
    "sg:address":"475 Klinke Ave",
    "sg:city":"Memphis",
    "sg:classifiers":[
        {
            "category":"Government",
            "subcategory":"Police Station",
            "type":"Public Place"
        }
    ],
    "sg:phone":"+1 901 353 8211",
    "sg:postcode":"38127",
    "sg:province":"TN",
    "sg:tags":[
        "department"
    ],
    "sg:website":"www.cityofmemphis.org",
    "wof:name":"Memphis Police Crime Scene",
    "wof:placetype":"venue"
},
  "geometry": {"coordinates":[-90.054096,35.209916],"type":"Point"}
}