{
  "type": "Feature",
  "properties": {
    "addr:full":"2130 W Poplar Ave Ste 104 Collierville TN 38017",
    "addr:housenumber":"2130",
    "addr:postcode":"38017",
    "addr:street":"W Poplar Ave Ste 104",
    "iso:country":"US",
    "sg:address":"2130 W Poplar Ave Ste 104",
    "sg:city":"Collierville",
    "sg:classifiers":[
        {
            "category":"Communications",
            "subcategory":"Television Station",
            "type":"Services"
        }
    ],
    "sg:phone":"+1 901 850 8852",
    "sg:postcode":"38017",
    "sg:province":"TN",
    "sg:tags":[
        "satellite",
        "cable"
    ],
    "sg:website":"http://www.oceanic.com",
    "wof:name":"Time Warner",
    "wof:placetype":"venue"
},
  "geometry": {"coordinates":[-89.731115,35.051262],"type":"Point"}
}