{
  "type": "Feature",
  "properties": {
    "addr:full":"7475 Willey Rd Germantown TN 38138",
    "addr:housenumber":"7475",
    "addr:postcode":"38138",
    "addr:street":"Willey Rd",
    "iso:country":"US",
    "sg:address":"7475 Willey Rd",
    "sg:city":"Germantown",
    "sg:classifiers":[
        {
            "category":"Real Estate",
            "subcategory":"Real Estate Agent",
            "type":"Services"
        }
    ],
    "sg:phone":"+1 901 757 0052",
    "sg:postcode":"38138",
    "sg:province":"TN",
    "wof:name":"River Town Realtors",
    "wof:placetype":"venue"
},
  "geometry": {"coordinates":[-89.813964,35.096458],"type":"Point"}
}