{
  "type": "Feature",
  "properties": {
    "addr:full":"2214 Whites Creek Pike Nashville TN 37207",
    "addr:housenumber":"2214",
    "addr:postcode":"37207",
    "addr:street":"Whites Creek Pike",
    "iso:country":"US",
    "sg:address":"2214 Whites Creek Pike",
    "sg:city":"Nashville",
    "sg:classifiers":[
        {
            "category":"Retail",
            "subcategory":"Funeral Services",
            "type":"Services"
        }
    ],
    "sg:phone":"+1 615 227 6094",
    "sg:postcode":"37207",
    "sg:province":"TN",
    "sg:tags":[
        "director"
    ],
    "wof:name":"Dennis Funeral Home",
    "wof:placetype":"venue"
},
  "geometry": {"coordinates":[-86.792942,36.208019],"type":"Point"}
}