{
  "type": "Feature",
  "properties": {
    "iso:country":"US",
    "sg:address":"940 S Lauderdale St",
    "sg:city":"Memphis",
    "sg:classifiers":[
        {
            "category":"Organizations",
            "subcategory":"Religious Organization",
            "type":"Services"
        }
    ],
    "sg:phone":"+1 901 774 2427",
    "sg:postcode":"38126",
    "sg:province":"TN",
    "sg:tags":[
        "church"
    ],
    "wof:name":"St Mark's Baptist Church",
    "wof:placetype":"venue"
},
  "geometry": {"coordinates":[-90.04407399999999,35.121754],"type":"Point"}
}