{
  "type": "Feature",
  "properties": {
    "addr:full":"204 Maxwell Dr Clarksville TN 37043",
    "addr:housenumber":"204",
    "addr:postcode":"37043",
    "addr:street":"Maxwell Dr",
    "iso:country":"US",
    "sg:address":"204 Maxwell Dr",
    "sg:city":"Clarksville",
    "sg:classifiers":[
        {
            "category":"Building & Trades",
            "subcategory":"Construction",
            "type":"Services"
        }
    ],
    "sg:phone":"+1 931 645 2873",
    "sg:postcode":"37043",
    "sg:province":"TN",
    "sg:tags":[
        "painter"
    ],
    "wof:name":"J J's Interiors",
    "wof:placetype":"venue"
},
  "geometry": {"coordinates":[-87.289513,36.519349],"type":"Point"}
}