{
  "type": "Feature",
  "properties": {
    "iso:country":"US",
    "sg:address":"4755 SE Tater Peeler Rd",
    "sg:city":"Lebanon",
    "sg:classifiers":[
        {
            "category":"Retail",
            "subcategory":"Laundry & Dry Cleaning",
            "type":"Services"
        }
    ],
    "sg:phone":"+1 615 444 8171",
    "sg:postcode":"37090",
    "sg:province":"TN",
    "wof:name":"A & R Carpet Cleaning",
    "wof:placetype":"venue"
},
  "geometry": {"coordinates":[-86.276749,36.140452],"type":"Point"}
}