{
  "type": "Feature",
  "properties": {
    "iso:country":"US",
    "sg:address":"110B Perimeter Park Rd",
    "sg:city":"Knoxville",
    "sg:classifiers":[
        {
            "category":"Professional",
            "subcategory":"Lawyer & Legal Services",
            "type":"Services"
        }
    ],
    "sg:phone":"+1 865 971 1701",
    "sg:postcode":"37922",
    "sg:province":"TN",
    "sg:tags":[
        "attorney",
        "business",
        "estate",
        "tax",
        "planning",
        "law"
    ],
    "wof:name":"Taylor & Wills Inc",
    "wof:placetype":"venue"
},
  "geometry": {"coordinates":[-84.11113,35.905811],"type":"Point"}
}