{
  "type": "Feature",
  "properties": {
    "iso:country":"US",
    "sg:address":"213 Summer Pl",
    "sg:city":"Mt Juliet",
    "sg:classifiers":[
        {
            "category":"Building & Trades",
            "subcategory":"Construction",
            "type":"Services"
        }
    ],
    "sg:phone":"+1 615 754 5034",
    "sg:postcode":"37122",
    "sg:province":"TN",
    "sg:tags":[
        "housing",
        "restoration",
        "preservation"
    ],
    "wof:name":"Legacy Restorations",
    "wof:placetype":"venue"
},
  "geometry": {"coordinates":[-86.48672000000001,36.169657],"type":"Point"}
}