{
  "type": "Feature",
  "properties": {
    "iso:country":"US",
    "sg:address":"215 N Main St",
    "sg:city":"Dickson",
    "sg:classifiers":[
        {
            "category":"Organizations",
            "subcategory":"Religious Organization",
            "type":"Services"
        }
    ],
    "sg:phone":"+1 615 446 2917",
    "sg:postcode":"37055",
    "sg:province":"TN",
    "wof:name":"Dickson Frst Untd Mthdst Chrch",
    "wof:placetype":"venue"
},
  "geometry": {"coordinates":[-87.385552,36.07833],"type":"Point"}
}