{
  "type": "Feature",
  "properties": {
    "addr:full":"7 Henderson St Middleton TN 38037",
    "addr:housenumber":"7",
    "addr:postcode":"38037",
    "addr:street":"Henderson St",
    "iso:country":"US",
    "sg:address":"7 Henderson St",
    "sg:city":"Middleton",
    "sg:classifiers":[
        {
            "category":"Manufacturing",
            "subcategory":"Printing",
            "type":"Manufacturing & Wholesale Goods"
        }
    ],
    "sg:phone":"+1 731 376 8546",
    "sg:postcode":"38037",
    "sg:province":"TN",
    "sg:tags":[
        "newspaper",
        "publishing"
    ],
    "wof:name":"Dixie Publications",
    "wof:placetype":"venue"
},
  "geometry": {"coordinates":[-89.404239,35.843489],"type":"Point"}
}