{
  "type": "Feature",
  "properties": {
    "iso:country":"US",
    "sg:address":"301 Tyson Store-Mason Hall Rd",
    "sg:city":"Kenton",
    "sg:classifiers":[
        {
            "category":"Farming",
            "subcategory":"Fish & Marine Products",
            "type":"Manufacturing & Wholesale Goods"
        }
    ],
    "sg:phone":"+1 731 673 4125",
    "sg:postcode":"38233",
    "sg:province":"TN",
    "sg:tags":[
        "preserves",
        "fishing",
        "hunting"
    ],
    "wof:name":"Grassy Creek Hunting Preserve",
    "wof:placetype":"venue"
},
  "geometry": {"coordinates":[-89.08252400000001,36.183642],"type":"Point"}
}