{
  "type": "Feature",
  "properties": {
    "iso:country":"US",
    "sg:address":"3917 Weaver Pike",
    "sg:city":"Bluff City",
    "sg:classifiers":[
        {
            "category":"Retail",
            "subcategory":"Auto Repair",
            "type":"Services"
        }
    ],
    "sg:phone":"+1 423 878 3511",
    "sg:postcode":"37618",
    "sg:province":"TN",
    "sg:tags":[
        "transmission"
    ],
    "wof:name":"East Transmission Service",
    "wof:placetype":"venue"
},
  "geometry": {"coordinates":[-82.202501,36.512891],"type":"Point"}
}