{
  "type": "Feature",
  "properties": {
    "iso:country":"US",
    "sg:address":"1323 Vanessa Dr",
    "sg:city":"Hixson",
    "sg:classifiers":[
        {
            "category":"Insurance",
            "subcategory":"Insurance Agent",
            "type":"Services"
        }
    ],
    "sg:phone":"+1 423 877 1100",
    "sg:postcode":"37343",
    "sg:province":"TN",
    "wof:name":"Horace Barker & Assoc",
    "wof:placetype":"venue"
},
  "geometry": {"coordinates":[-85.258229,35.13547],"type":"Point"}
}