{
  "type": "Feature",
  "properties": {
    "iso:country":"US",
    "sg:address":"7935 Hixson Pike",
    "sg:city":"Hixson",
    "sg:classifiers":[
        {
            "category":"Home & Garden",
            "subcategory":"Home Furnishings",
            "type":"Retail Goods"
        }
    ],
    "sg:phone":"+1 423 842 1531",
    "sg:postcode":"37343",
    "sg:province":"TN",
    "sg:tags":[
        "quilting"
    ],
    "wof:name":"Custom Quilting",
    "wof:placetype":"venue"
},
  "geometry": {"coordinates":[-85.168266,35.186237],"type":"Point"}
}