{
  "type": "Feature",
  "properties": {
    "addr:full":"3507 Village Ln Louisville TN 37777",
    "addr:housenumber":"3507",
    "addr:postcode":"37777",
    "addr:street":"Village Ln",
    "iso:country":"US",
    "sg:address":"3507 Village Ln",
    "sg:city":"Louisville",
    "sg:classifiers":[
        {
            "category":"Professional",
            "type":"Services"
        }
    ],
    "sg:phone":"+1 865 977 7090",
    "sg:postcode":"37777",
    "sg:province":"TN",
    "wof:name":"Seven Pines Devl",
    "wof:placetype":"venue"
},
  "geometry": {"coordinates":[-84.134111,35.800013],"type":"Point"}
}