{
  "type": "Feature",
  "properties": {
    "iso:country":"US",
    "sg:address":"151 Co Rd 622",
    "sg:city":"Etowah",
    "sg:classifiers":[
        {
            "category":"Retail",
            "subcategory":"Auto Repair",
            "type":"Services"
        }
    ],
    "sg:phone":"+1 423 263 6698",
    "sg:postcode":"37331",
    "sg:province":"TN",
    "sg:tags":[
        "body",
        "automobile",
        "painting"
    ],
    "wof:name":"Dent Specialist",
    "wof:placetype":"venue"
},
  "geometry": {"coordinates":[-84.545897,35.341388],"type":"Point"}
}