{
  "type": "Feature",
  "properties": {
    "iso:country":"US",
    "sg:address":"1800 Kilgore Cir SW",
    "sg:city":"Cleveland",
    "sg:classifiers":[
        {
            "category":"Professional",
            "subcategory":"Advertising",
            "type":"Services"
        }
    ],
    "sg:phone":"+1 423 559 1839",
    "sg:postcode":"37311",
    "sg:province":"TN",
    "sg:tags":[
        "distribution"
    ],
    "wof:name":"America Supermart",
    "wof:placetype":"venue"
},
  "geometry": {"coordinates":[-84.89979599999999,35.146732],"type":"Point"}
}