{
  "type": "Feature",
  "properties": {
    "iso:country":"US",
    "sg:address":"2122 Hwy 116",
    "sg:city":"Caryville",
    "sg:classifiers":[
        {
            "category":"Autos & Motor Vehicles",
            "subcategory":"Auto Supplies",
            "type":"Retail Goods"
        }
    ],
    "sg:phone":"+1 865 426 9573",
    "sg:postcode":"37714",
    "sg:province":"TN",
    "sg:tags":[
        "automobile",
        "parts"
    ],
    "wof:name":"Cupp Shop",
    "wof:placetype":"venue"
},
  "geometry": {"coordinates":[-84.178676,36.252183],"type":"Point"}
}