{
  "type": "Feature",
  "properties": {
    "addr:full":"2800 Westside Dr NW Cleveland TN 37312",
    "addr:housenumber":"2800",
    "addr:postcode":"37312",
    "addr:street":"Westside Dr Nw",
    "iso:country":"US",
    "sg:address":"2800 Westside Dr NW",
    "sg:city":"Cleveland",
    "sg:classifiers":[
        {
            "category":"Organizations",
            "subcategory":"Non-profit Organization",
            "type":"Services"
        }
    ],
    "sg:phone":"+1 423 479 4673",
    "sg:postcode":"37312",
    "sg:province":"TN",
    "sg:tags":[
        "info",
        "addiction",
        "abuse",
        "treatment",
        "drug"
    ],
    "wof:name":"Pine Ridge Treatment Ctr",
    "wof:placetype":"venue"
},
  "geometry": {"coordinates":[-84.87696,35.198665],"type":"Point"}
}