{
  "type": "Feature",
  "properties": {
    "iso:country":"US",
    "sg:address":"1311 N Liberty Hill Rd",
    "sg:city":"Morristown",
    "sg:classifiers":[
        {
            "category":"Building & Trades",
            "subcategory":"Equipment Rental",
            "type":"Services"
        },
        {
            "category":"Cinema",
            "subcategory":"Movie Rental",
            "type":"Entertainment"
        }
    ],
    "sg:phone":"+1 423 587 2269",
    "sg:postcode":"37814",
    "sg:province":"TN",
    "sg:tags":[
        "player",
        "recorder",
        "video",
        "tape"
    ],
    "sg:website":"www.videoexpressandtan.net",
    "wof:name":"Video Express & Tanning",
    "wof:placetype":"venue"
},
  "geometry": {"coordinates":[-83.276606,36.230276],"type":"Point"}
}