{
  "type": "Feature",
  "properties": {
    "iso:country":"US",
    "sg:address":"1795 Ashland City Rd",
    "sg:city":"Clarksville",
    "sg:classifiers":[
        {
            "category":"Wholesale",
            "subcategory":"Machinery & Supplies",
            "type":"Manufacturing & Wholesale Goods"
        }
    ],
    "sg:phone":"+1 931 552 7373",
    "sg:postcode":"37043",
    "sg:province":"TN",
    "sg:tags":[
        "equipment",
        "parts",
        "tractor"
    ],
    "wof:name":"Clarksville New Holland",
    "wof:placetype":"venue"
},
  "geometry": {"coordinates":[-87.323037,36.503406],"type":"Point"}
}