{
  "type": "Feature",
  "properties": {
    "iso:country":"US",
    "sg:address":"4714 State Hwy 49 W",
    "sg:city":"Vanleer",
    "sg:classifiers":[
        {
            "category":"Utilities",
            "subcategory":"Water",
            "type":"Services"
        }
    ],
    "sg:phone":"+1 615 763 2823",
    "sg:postcode":"37181",
    "sg:province":"TN",
    "sg:tags":[
        "company",
        "sewage"
    ],
    "wof:name":"Water Works Dept",
    "wof:placetype":"venue"
},
  "geometry": {"coordinates":[-87.443928,36.233499],"type":"Point"}
}