{
  "type": "Feature",
  "properties": {
    "addr:full":"620 Cherokee Blvd Chattanooga TN 37405",
    "addr:housenumber":"620",
    "addr:postcode":"37405",
    "addr:street":"Cherokee Blvd",
    "iso:country":"US",
    "sg:address":"620 Cherokee Blvd",
    "sg:city":"Chattanooga",
    "sg:classifiers":[
        {
            "category":"Health Services",
            "subcategory":"Clinic",
            "type":"Services"
        }
    ],
    "sg:phone":"+1 423 265 4397",
    "sg:postcode":"37405",
    "sg:province":"TN",
    "sg:tags":[
        "kidney",
        "dialysis",
        "center"
    ],
    "wof:name":"Kidney Foundation",
    "wof:placetype":"venue"
},
  "geometry": {"coordinates":[-85.317752,35.069215],"type":"Point"}
}