{
  "type": "Feature",
  "properties": {
    "addr:full":"1434 Roberts Ave Nashville TN 37206",
    "addr:housenumber":"1434",
    "addr:postcode":"37206",
    "addr:street":"Roberts Ave",
    "iso:country":"US",
    "sg:address":"1434 Roberts Ave",
    "sg:city":"Nashville",
    "sg:classifiers":[
        {
            "category":"Professional",
            "type":"Services"
        }
    ],
    "sg:phone":"+1 615 228 4890",
    "sg:postcode":"37206",
    "sg:province":"TN",
    "wof:name":"Romancing Walls",
    "wof:placetype":"venue"
},
  "geometry": {"coordinates":[-86.740143,36.18862],"type":"Point"}
}