{
  "type": "Feature",
  "properties": {
    "iso:country":"US",
    "sg:address":"1901 Washington Pike",
    "sg:city":"Knoxville",
    "sg:classifiers":[
        {
            "category":"Health Services",
            "subcategory":"Nursing And Care Facility",
            "type":"Services"
        }
    ],
    "sg:phone":"+1 865 523 8031",
    "sg:postcode":"37917",
    "sg:province":"TN",
    "wof:name":"McClanahan Manor Inc",
    "wof:placetype":"venue"
},
  "geometry": {"coordinates":[-83.916656,35.998711],"type":"Point"}
}