{
  "type": "Feature",
  "properties": {
    "iso:country":"US",
    "sg:address":"349 E Pkwy",
    "sg:city":"Gatlinburg",
    "sg:classifiers":[
        {
            "category":"Retail",
            "subcategory":"Auto Rental",
            "type":"Services"
        }
    ],
    "sg:phone":"+1 865 430 3445",
    "sg:postcode":"37738",
    "sg:province":"TN",
    "sg:tags":[
        "passenger",
        "car"
    ],
    "wof:name":"Fun Time Scooter & Jeep Rental",
    "wof:placetype":"venue"
},
  "geometry": {"coordinates":[-83.506484,35.716034],"type":"Point"}
}