{
  "type": "Feature",
  "properties": {
    "iso:country":"US",
    "sg:address":"253 Airways Blvd",
    "sg:city":"Jackson",
    "sg:classifiers":[
        {
            "category":"Food & Beverages",
            "subcategory":"Groceries & Convenience Stores",
            "type":"Retail Goods"
        },
        {
            "category":"Sports & Exercise",
            "subcategory":"Race Track",
            "type":"Entertainment"
        }
    ],
    "sg:phone":"+1 731 427 7763",
    "sg:postcode":"38301",
    "sg:province":"TN",
    "sg:tags":[
        "operation",
        "racing",
        "or"
    ],
    "wof:name":"Abel's Raceway",
    "wof:placetype":"venue"
},
  "geometry": {"coordinates":[-88.830032,35.616398],"type":"Point"}
}