{
  "type": "Feature",
  "properties": {
    "iso:country":"US",
    "sg:address":"135 Poplar St",
    "sg:city":"Benton",
    "sg:classifiers":[
        {
            "category":"Arts & Performance",
            "subcategory":"Theater",
            "type":"Entertainment"
        }
    ],
    "sg:phone":"+1 423 263 3366",
    "sg:postcode":"37307",
    "sg:province":"TN",
    "sg:tags":[
        "dance",
        "company"
    ],
    "wof:name":"Chilhowee Dance & Performing",
    "wof:placetype":"venue"
},
  "geometry": {"coordinates":[-84.651408,35.171668],"type":"Point"}
}