{
  "type": "Feature",
  "properties": {
    "iso:country":"US",
    "sg:address":"115 Blue Heron Dr",
    "sg:city":"Lenoir City",
    "sg:classifiers":[
        {
            "category":"Wholesale",
            "subcategory":"Machinery & Supplies",
            "type":"Manufacturing & Wholesale Goods"
        }
    ],
    "sg:phone":"+1 865 988 8881",
    "sg:postcode":"37772",
    "sg:province":"TN",
    "sg:tags":[
        "sprinkler"
    ],
    "wof:name":"Allied Fire Protection",
    "wof:placetype":"venue"
},
  "geometry": {"coordinates":[-84.17913799999999,35.785941],"type":"Point"}
}