{
  "type": "Feature",
  "properties": {
    "addr:full":"505 Cherokee Blvd Chattanooga TN 37405",
    "addr:housenumber":"505",
    "addr:postcode":"37405",
    "addr:street":"Cherokee Blvd",
    "iso:country":"US",
    "sg:address":"505 Cherokee Blvd",
    "sg:city":"Chattanooga",
    "sg:classifiers":[
        {
            "category":"Professional",
            "subcategory":"Engineering",
            "type":"Services"
        }
    ],
    "sg:phone":"+1 423 267 0874",
    "sg:postcode":"37405",
    "sg:province":"TN",
    "sg:tags":[
        "engineer"
    ],
    "wof:name":"Davies Engineering Co Inc",
    "wof:placetype":"venue"
},
  "geometry": {"coordinates":[-85.31548100000001,35.06749],"type":"Point"}
}