{
  "type": "Feature",
  "properties": {
    "iso:country":"US",
    "sg:address":"904 High Rigger Ct",
    "sg:city":"Nashville",
    "sg:classifiers":[
        {
            "category":"Education",
            "subcategory":"Special Training",
            "type":"Public Place"
        }
    ],
    "sg:phone":"+1 615 365 8052",
    "sg:postcode":"37217",
    "sg:province":"TN",
    "wof:name":"Mark Corradetti",
    "wof:placetype":"venue"
},
  "geometry": {"coordinates":[-86.611002,36.078433],"type":"Point"}
}