{
  "type": "Feature",
  "properties": {
    "addr:full":"104 Chestnut St Nashville TN 37210",
    "addr:housenumber":"104",
    "addr:postcode":"37210",
    "addr:street":"Chestnut St",
    "iso:country":"US",
    "sg:address":"104 Chestnut St",
    "sg:city":"Nashville",
    "sg:classifiers":[
        {
            "category":"Organizations",
            "subcategory":"Religious Organization",
            "type":"Services"
        }
    ],
    "sg:phone":"+1 615 591 2597",
    "sg:postcode":"37210",
    "sg:province":"TN",
    "wof:name":"Christ Fellowship",
    "wof:placetype":"venue"
},
  "geometry": {"coordinates":[-86.764061,36.146136],"type":"Point"}
}