{
  "type": "Feature",
  "properties": {
    "addr:full":"8174 E Brainerd Rd Chattanooga TN 37421",
    "addr:housenumber":"8174",
    "addr:postcode":"37421",
    "addr:street":"E Brainerd Rd",
    "iso:country":"US",
    "sg:address":"8174 E Brainerd Rd",
    "sg:city":"Chattanooga",
    "sg:classifiers":[
        {
            "category":"Restaurant",
            "type":"Food & Drink"
        }
    ],
    "sg:phone":"+1 423 490 0640",
    "sg:postcode":"37421",
    "sg:province":"TN",
    "wof:name":"Blimpie Subs & Salads",
    "wof:placetype":"venue"
},
  "geometry": {"coordinates":[-85.148839,35.003671],"type":"Point"}
}