{
  "type": "Feature",
  "properties": {
    "iso:country":"US",
    "sg:address":"702 E 13th St",
    "sg:city":"Chattanooga",
    "sg:classifiers":[
        {
            "category":"Utilities",
            "subcategory":"Electric",
            "type":"Services"
        }
    ],
    "sg:phone":"+1 423 265 5700",
    "sg:postcode":"37408",
    "sg:province":"TN",
    "wof:name":"Tva Emplyee Vly Rsidence Legal",
    "wof:placetype":"venue"
},
  "geometry": {"coordinates":[-85.295351,35.033891],"type":"Point"}
}