{
  "type": "Feature",
  "properties": {
    "iso:country":"US",
    "sg:address":"9941 State Hwy 56",
    "sg:city":"Coalmont",
    "sg:classifiers":[
        {
            "category":"Wholesale",
            "subcategory":"Farm Supplies",
            "type":"Manufacturing & Wholesale Goods"
        }
    ],
    "sg:phone":"+1 931 779 3276",
    "sg:postcode":"37376",
    "sg:province":"TN",
    "sg:tags":[
        "feed"
    ],
    "wof:name":"Grundy Farmers Cooperative",
    "wof:placetype":"venue"
},
  "geometry": {"coordinates":[-85.92200699999999,35.073692],"type":"Point"}
}