{
  "type": "Feature",
  "properties": {
    "addr:full":"1310 Ordway Pl Nashville TN 37206",
    "addr:housenumber":"1310",
    "addr:postcode":"37206",
    "addr:street":"Ordway Pl",
    "iso:country":"US",
    "sg:address":"1310 Ordway Pl",
    "sg:city":"Nashville",
    "sg:classifiers":[
        {
            "category":"Social Services",
            "subcategory":"Child Care",
            "type":"Services"
        }
    ],
    "sg:phone":"+1 615 862 8878",
    "sg:postcode":"37206",
    "sg:province":"TN",
    "sg:tags":[
        "day"
    ],
    "wof:name":"Metro Head Start-Ross",
    "wof:placetype":"venue"
},
  "geometry": {"coordinates":[-86.74679500000001,36.180265],"type":"Point"}
}