{
  "type": "Feature",
  "properties": {
    "iso:country":"US",
    "sg:address":"3100 Reservoir Rd",
    "sg:city":"Kingsport",
    "sg:classifiers":[
        {
            "category":"Education",
            "subcategory":"Special Training",
            "type":"Public Place"
        }
    ],
    "sg:phone":"+1 423 292 6052",
    "sg:postcode":"37660",
    "sg:province":"TN",
    "sg:tags":[
        "instruction",
        "music"
    ],
    "wof:name":"Bays Mountain Music Academy",
    "wof:placetype":"venue"
},
  "geometry": {"coordinates":[-82.58984700000001,36.499506],"type":"Point"}
}