{
  "type": "Feature",
  "properties": {
    "iso:country":"US",
    "sg:address":"4053 Nolensville Pike",
    "sg:city":"Nashville",
    "sg:classifiers":[
        {
            "category":"Health Services",
            "subcategory":"Doctor",
            "type":"Services"
        }
    ],
    "sg:phone":"+1 615 627 1282",
    "sg:postcode":"37211",
    "sg:province":"TN",
    "sg:tags":[
        "physician",
        "clinic",
        "surgeon"
    ],
    "wof:name":"Lapaz Hispanic Clinic",
    "wof:placetype":"venue"
},
  "geometry": {"coordinates":[-86.726848,36.080991],"type":"Point"}
}