{
  "type": "Feature",
  "properties": {
    "iso:country":"US",
    "sg:address":"509 Allison St",
    "sg:city":"Morristown",
    "sg:classifiers":[
        {
            "category":"Professional",
            "subcategory":"Lawyer & Legal Services",
            "type":"Services"
        }
    ],
    "sg:phone":"+1 423 586 8110",
    "sg:postcode":"37814",
    "sg:province":"TN",
    "sg:tags":[
        "attorney"
    ],
    "wof:name":"Wayne Stambaugh & Assoc",
    "wof:placetype":"venue"
},
  "geometry": {"coordinates":[-83.298992,36.214635],"type":"Point"}
}