{
  "type": "Feature",
  "properties": {
    "iso:country":"US",
    "sg:address":"6756 Cold Stream Dr",
    "sg:city":"Nashville",
    "sg:classifiers":[
        {
            "category":"Utilities",
            "subcategory":"Mobile Phone",
            "type":"Services"
        }
    ],
    "sg:phone":"+1 615 481 2735",
    "sg:postcode":"37221",
    "sg:province":"TN",
    "sg:tags":[
        "telephone",
        "cellular"
    ],
    "wof:name":"Wireless FX",
    "wof:placetype":"venue"
},
  "geometry": {"coordinates":[-86.967104,36.055868],"type":"Point"}
}