{
  "type": "Feature",
  "properties": {
    "iso:country":"US",
    "sg:address":"708 Parkway",
    "sg:city":"Gatlinburg",
    "sg:classifiers":[
        {
            "category":"Food & Beverages",
            "subcategory":"Candy",
            "type":"Retail Goods"
        }
    ],
    "sg:phone":"+1 423 436 5369",
    "sg:postcode":"37738",
    "sg:province":"TN",
    "wof:name":"Aunt Mahalias Candies 3 Inc",
    "wof:placetype":"venue"
},
  "geometry": {"coordinates":[-83.51567,35.712471],"type":"Point"}
}