{
  "type": "Feature",
  "properties": {
    "iso:country":"US",
    "sg:address":"7922 Brickyard Rd",
    "sg:city":"Powell",
    "sg:classifiers":[
        {
            "category":"Building & Trades",
            "subcategory":"Construction",
            "type":"Services"
        }
    ],
    "sg:phone":"+1 865 938 7899",
    "sg:postcode":"37849",
    "sg:province":"TN",
    "sg:tags":[
        "house"
    ],
    "wof:name":"Jeffs Handyman Service",
    "wof:placetype":"venue"
},
  "geometry": {"coordinates":[-84.032895,36.032881],"type":"Point"}
}