{
  "type": "Feature",
  "properties": {
    "addr:full":"886 S Cox St Memphis TN 38104",
    "addr:housenumber":"886",
    "addr:postcode":"38104",
    "addr:street":"S Cox St",
    "iso:country":"US",
    "sg:address":"886 S Cox St",
    "sg:city":"Memphis",
    "sg:classifiers":[
        {
            "category":"Building & Trades",
            "subcategory":"Construction",
            "type":"Services"
        }
    ],
    "sg:phone":"+1 901 491 0503",
    "sg:postcode":"38104",
    "sg:province":"TN",
    "sg:tags":[
        "hanging",
        "contractor"
    ],
    "wof:name":"Lewis Custom Painting",
    "wof:placetype":"venue"
},
  "geometry": {"coordinates":[-89.987938,35.120981],"type":"Point"}
}