{
  "type": "Feature",
  "properties": {
    "iso:country":"US",
    "sg:address":"1409 E Magnolia Ave",
    "sg:city":"Knoxville",
    "sg:classifiers":[
        {
            "category":"Social Services",
            "type":"Services"
        }
    ],
    "sg:phone":"+1 865 974 9888",
    "sg:postcode":"37917",
    "sg:province":"TN",
    "sg:tags":[
        "hospital",
        "specialty"
    ],
    "wof:name":"East Tennessee Intergroup AA",
    "wof:placetype":"venue"
},
  "geometry": {"coordinates":[-83.91013,35.978042],"type":"Point"}
}