{
  "type": "Feature",
  "properties": {
    "iso:country":"US",
    "sg:address":"110 Applewood Valley Dr",
    "sg:city":"Hendersonville",
    "sg:classifiers":[
        {
            "category":"Freight",
            "type":"Transportation"
        }
    ],
    "sg:phone":"+1 615 826 5661",
    "sg:postcode":"37075",
    "sg:province":"TN",
    "sg:tags":[
        "fixed",
        "motor",
        "facility"
    ],
    "wof:name":"Premium Home Inspections LLC",
    "wof:placetype":"venue"
},
  "geometry": {"coordinates":[-86.585703,36.267549],"type":"Point"}
}