{
  "type": "Feature",
  "properties": {
    "iso:country":"US",
    "sg:address":"186 Warren St",
    "sg:city":"Madisonville",
    "sg:classifiers":[
        {
            "category":"Farming",
            "subcategory":"Vineyard",
            "type":"Manufacturing & Wholesale Goods"
        }
    ],
    "sg:phone":"+1 423 420 9835",
    "sg:postcode":"37354",
    "sg:province":"TN",
    "wof:name":"Vineyard Productions",
    "wof:placetype":"venue"
},
  "geometry": {"coordinates":[-84.358966,35.51988],"type":"Point"}
}