{
  "type": "Feature",
  "properties": {
    "iso:country":"US",
    "sg:address":"401 N Military Ave",
    "sg:city":"Lawrenceburg",
    "sg:classifiers":[
        {
            "category":"Shopping",
            "subcategory":"Used Merchandise",
            "type":"Retail Goods"
        }
    ],
    "sg:phone":"+1 931 762 4118",
    "sg:postcode":"38464",
    "sg:province":"TN",
    "wof:name":"Dig Store",
    "wof:placetype":"venue"
},
  "geometry": {"coordinates":[-87.33247799999999,35.246572],"type":"Point"}
}