{
  "type": "Feature",
  "properties": {
    "iso:country":"US",
    "sg:address":"258 N Peters Rd",
    "sg:city":"Knoxville",
    "sg:classifiers":[
        {
            "category":"Travel",
            "subcategory":"Hotels & Motels",
            "type":"Entertainment"
        }
    ],
    "sg:phone":"+1 865 690 9777",
    "sg:postcode":"37923",
    "sg:province":"TN",
    "wof:name":"LA Quinta Inn Knoxville West",
    "wof:placetype":"venue"
},
  "geometry": {"coordinates":[-84.087484,35.91565],"type":"Point"}
}