{
  "type": "Feature",
  "properties": {
    "iso:country":"US",
    "sg:address":"669 E Church St",
    "sg:city":"Lexington",
    "sg:classifiers":[
        {
            "category":"Personal",
            "type":"Services"
        }
    ],
    "sg:phone":"+1 731 967 5265",
    "sg:postcode":"38351",
    "sg:province":"TN",
    "sg:tags":[
        "therapist",
        "massage"
    ],
    "wof:name":"Right Touch Massage",
    "wof:placetype":"venue"
},
  "geometry": {"coordinates":[-88.378944,35.641812],"type":"Point"}
}