{
  "type": "Feature",
  "properties": {
    "iso:country":"US",
    "sg:address":"2147 Bend Rd",
    "sg:city":"Clarksville",
    "sg:classifiers":[
        {
            "category":"Building & Trades",
            "subcategory":"Construction",
            "type":"Services"
        }
    ],
    "sg:phone":"+1 931 645 8359",
    "sg:postcode":"37040",
    "sg:province":"TN",
    "sg:tags":[
        "house"
    ],
    "wof:name":"Blackwell Construction",
    "wof:placetype":"venue"
},
  "geometry": {"coordinates":[-87.325152,36.464148],"type":"Point"}
}