{
  "type": "Feature",
  "properties": {
    "iso:country":"US",
    "sg:address":"319 Bethany Ln",
    "sg:city":"Shelbyville",
    "sg:classifiers":[
        {
            "category":"Social Services",
            "type":"Services"
        }
    ],
    "sg:phone":"+1 931 684 5222",
    "sg:postcode":"37160",
    "sg:province":"TN",
    "sg:tags":[
        "organization",
        "welfare"
    ],
    "wof:name":"Epilepsy Foundation",
    "wof:placetype":"venue"
},
  "geometry": {"coordinates":[-86.439589,35.484965],"type":"Point"}
}