{
  "type": "Feature",
  "properties": {
    "iso:country":"US",
    "sg:address":"2622 Texas Ave",
    "sg:city":"Knoxville",
    "sg:classifiers":[
        {
            "category":"Wholesale",
            "subcategory":"Wine & Distilled Alcoholic Beverages",
            "type":"Manufacturing & Wholesale Goods"
        }
    ],
    "sg:phone":"+1 865 637 9411",
    "sg:postcode":"37921",
    "sg:province":"TN",
    "sg:tags":[
        "liquor"
    ],
    "wof:name":"Knoxville Beverage Co",
    "wof:placetype":"venue"
},
  "geometry": {"coordinates":[-83.964625,35.97865],"type":"Point"}
}