{
  "type": "Feature",
  "properties": {
    "addr:full":"300 Stanley Blvd Shelbyville TN 37160",
    "addr:housenumber":"300",
    "addr:postcode":"37160",
    "addr:street":"Stanley Blvd",
    "iso:country":"US",
    "sg:address":"300 Stanley Blvd",
    "sg:city":"Shelbyville",
    "sg:classifiers":[
        {
            "category":"Retail",
            "subcategory":"Auto Repair",
            "type":"Services"
        }
    ],
    "sg:phone":"+1 931 684 3170",
    "sg:postcode":"37160",
    "sg:province":"TN",
    "sg:tags":[
        "body",
        "automobile",
        "painting"
    ],
    "wof:name":"Brown's Body Shop",
    "wof:placetype":"venue"
},
  "geometry": {"coordinates":[-86.4036,35.489305],"type":"Point"}
}