{
  "type": "Feature",
  "properties": {
    "addr:full":"203 Red Bird Ct Soddy Daisy TN 37379",
    "addr:housenumber":"203",
    "addr:postcode":"37379",
    "addr:street":"Red Bird Ct",
    "iso:country":"US",
    "sg:address":"203 Red Bird Ct",
    "sg:city":"Soddy Daisy",
    "sg:classifiers":[
        {
            "category":"Professional",
            "type":"Services"
        }
    ],
    "sg:phone":"+1 423 843 9427",
    "sg:postcode":"37379",
    "sg:province":"TN",
    "wof:name":"James A Bradley",
    "wof:placetype":"venue"
},
  "geometry": {"coordinates":[-85.23007200000001,35.216312],"type":"Point"}
}