{
  "type": "Feature",
  "properties": {
    "addr:full":"201 Mulberry Ave Fayetteville TN 37334",
    "addr:housenumber":"201",
    "addr:postcode":"37334",
    "addr:street":"Mulberry Ave",
    "iso:country":"US",
    "sg:address":"201 Mulberry Ave",
    "sg:city":"Fayetteville",
    "sg:classifiers":[
        {
            "category":"Retail",
            "subcategory":"Auto Repair",
            "type":"Services"
        }
    ],
    "sg:phone":"+1 931 433 1036",
    "sg:postcode":"37334",
    "sg:province":"TN",
    "sg:tags":[
        "general"
    ],
    "wof:name":"Davis Auto Repair",
    "wof:placetype":"venue"
},
  "geometry": {"coordinates":[-86.56514300000001,35.153449],"type":"Point"}
}