{
  "type": "Feature",
  "properties": {
    "iso:country":"US",
    "sg:address":"850 Raider Dr",
    "sg:city":"Cleveland",
    "sg:classifiers":[
        {
            "category":"Education",
            "subcategory":"School",
            "type":"Public Place"
        }
    ],
    "sg:phone":"+1 423 478 1116",
    "sg:postcode":"37312",
    "sg:province":"TN",
    "wof:name":"Clevland Highschool",
    "wof:placetype":"venue"
},
  "geometry": {"coordinates":[-84.868287,35.193277],"type":"Point"}
}