{
  "type": "Feature",
  "properties": {
    "iso:country":"US",
    "sg:address":"6525 N Quail Hollow Rd",
    "sg:city":"Memphis",
    "sg:classifiers":[
        {
            "category":"Real Estate",
            "subcategory":"Real Estate Agent",
            "type":"Services"
        }
    ],
    "sg:phone":"+1 901 756 9193",
    "sg:postcode":"38119",
    "sg:province":"TN",
    "wof:name":"Tommie Criswell-Jones",
    "wof:placetype":"venue"
},
  "geometry": {"coordinates":[-89.846475,35.104747],"type":"Point"}
}