{
  "type": "Feature",
  "properties": {
    "iso:country":"US",
    "sg:address":"250 Country Village Dr",
    "sg:city":"Smyrna",
    "sg:classifiers":[
        {
            "category":"Food & Beverages",
            "subcategory":"Groceries & Convenience Stores",
            "type":"Retail Goods"
        }
    ],
    "sg:phone":"+1 615 459 0795",
    "sg:postcode":"37167",
    "sg:province":"TN",
    "sg:tags":[
        "grocer"
    ],
    "wof:name":"Food Lion",
    "wof:placetype":"venue"
},
  "geometry": {"coordinates":[-86.52795999999999,35.957942],"type":"Point"}
}