{
  "type": "Feature",
  "properties": {
    "iso:country":"US",
    "sg:address":"1446 Munford Ave",
    "sg:city":"Munford",
    "sg:classifiers":[
        {
            "category":"Personal",
            "subcategory":"Beauty Salon",
            "type":"Services"
        }
    ],
    "sg:phone":"+1 901 837 9000",
    "sg:postcode":"38058",
    "sg:province":"TN",
    "wof:name":"Changes Hair Salon",
    "wof:placetype":"venue"
},
  "geometry": {"coordinates":[-89.813371,35.448203],"type":"Point"}
}