{
  "type": "Feature",
  "properties": {
    "iso:country":"US",
    "sg:address":"1000 Jetton Dr",
    "sg:city":"Covington",
    "sg:classifiers":[
        {
            "category":"Manufacturing",
            "subcategory":"Tools & Machinery",
            "type":"Manufacturing & Wholesale Goods"
        }
    ],
    "sg:phone":"+1 901 475 4493",
    "sg:postcode":"38019",
    "sg:province":"TN",
    "sg:tags":[
        "mfg"
    ],
    "wof:name":"Mueller Industries Inc",
    "wof:placetype":"venue"
},
  "geometry": {"coordinates":[-89.61045900000001,35.622066],"type":"Point"}
}