{
  "type": "Feature",
  "properties": {
    "iso:country":"US",
    "sg:address":"3056 US Hwy 11 Bus",
    "sg:city":"Athens",
    "sg:classifiers":[
        {
            "category":"Freight",
            "type":"Transportation"
        }
    ],
    "sg:phone":"+1 423 745 9196",
    "sg:postcode":"37303",
    "sg:province":"TN",
    "sg:tags":[
        "trucking"
    ],
    "wof:name":"Lloyd's Trucking",
    "wof:placetype":"venue"
},
  "geometry": {"coordinates":[-84.66229800000001,35.411466],"type":"Point"}
}