{
  "type": "Feature",
  "properties": {
    "iso:country":"US",
    "sg:address":"640 Grassmere Park",
    "sg:city":"Nashville",
    "sg:classifiers":[
        {
            "category":"Shopping",
            "subcategory":"Discount & Variety Stores",
            "type":"Retail Goods"
        }
    ],
    "sg:phone":"+1 615 332 0622",
    "sg:postcode":"37211",
    "sg:province":"TN",
    "sg:tags":[
        "merchandise",
        "general"
    ],
    "wof:name":"Nrd Nashville Supply",
    "wof:placetype":"venue"
},
  "geometry": {"coordinates":[-86.74839799999999,36.087296],"type":"Point"}
}