{
  "type": "Feature",
  "properties": {
    "iso:country":"US",
    "sg:address":"2596 Sunny Glade Cove",
    "sg:city":"Memphis",
    "sg:classifiers":[
        {
            "category":"Shopping",
            "subcategory":"Jewelry",
            "type":"Retail Goods"
        }
    ],
    "sg:phone":"+1 901 388 9423",
    "sg:postcode":"38133",
    "sg:province":"TN",
    "wof:name":"Lindas Jewelry Creation",
    "wof:placetype":"venue"
},
  "geometry": {"coordinates":[-89.824158,35.196519],"type":"Point"}
}