{
  "type": "Feature",
  "properties": {
    "addr:full":"1750 Linden Hwy Clifton TN 38425",
    "addr:housenumber":"1750",
    "addr:postcode":"38425",
    "addr:street":"Linden Hwy",
    "iso:country":"US",
    "sg:address":"1750 Linden Hwy",
    "sg:city":"Clifton",
    "sg:classifiers":[
        {
            "category":"Mining & Drilling",
            "type":"Manufacturing & Wholesale Goods"
        }
    ],
    "sg:phone":"+1 931 676 3598",
    "sg:postcode":"38425",
    "sg:province":"TN",
    "sg:tags":[
        "stone",
        "produce",
        "crushed"
    ],
    "wof:name":"Vulcan Materials Company",
    "wof:placetype":"venue"
},
  "geometry": {"coordinates":[-87.964771,35.425184],"type":"Point"}
}