{
  "type": "Feature",
  "properties": {
    "iso:country":"US",
    "sg:address":"1543 Nicholson Schoolhouse Rd",
    "sg:city":"Columbia",
    "sg:classifiers":[
        {
            "category":"Building & Trades",
            "subcategory":"Construction",
            "type":"Services"
        }
    ],
    "sg:phone":"+1 931 381 1652",
    "sg:postcode":"38401",
    "sg:province":"TN",
    "sg:tags":[
        "general",
        "contractor"
    ],
    "sg:website":"www.espsecuritysystems.com",
    "wof:name":"ESP Security Systems",
    "wof:placetype":"venue"
},
  "geometry": {"coordinates":[-86.914781,35.642638],"type":"Point"}
}