{
  "type": "Feature",
  "properties": {
    "addr:full":"75 N Old Military Rd Summertown TN 38483",
    "addr:housenumber":"75",
    "addr:postcode":"38483",
    "addr:street":"N Old Military Rd",
    "iso:country":"US",
    "sg:address":"75 N Old Military Rd",
    "sg:city":"Summertown",
    "sg:classifiers":[
        {
            "category":"Sports & Exercise",
            "subcategory":"Race Track",
            "type":"Entertainment"
        }
    ],
    "sg:phone":"+1 931 964 2120",
    "sg:postcode":"38483",
    "sg:province":"TN",
    "wof:name":"Thunderhill Raceway",
    "wof:placetype":"venue"
},
  "geometry": {"coordinates":[-87.25796699999999,35.394366],"type":"Point"}
}