{
  "type": "Feature",
  "properties": {
    "iso:country":"US",
    "sg:address":"712 Fisher Ave",
    "sg:city":"Smithville",
    "sg:classifiers":[
        {
            "category":"Autos & Motor Vehicles",
            "subcategory":"Automobile Sales",
            "type":"Retail Goods"
        }
    ],
    "sg:phone":"+1 615 597 5565",
    "sg:postcode":"37166",
    "sg:province":"TN",
    "sg:tags":[
        "used"
    ],
    "wof:name":"Summers Auto Salvage",
    "wof:placetype":"venue"
},
  "geometry": {"coordinates":[-85.81876800000001,35.952503],"type":"Point"}
}