{
  "type": "Feature",
  "properties": {
    "iso:country":"US",
    "sg:address":"300 Sunset Dr",
    "sg:city":"Livingston",
    "sg:classifiers":[
        {
            "category":"Retail",
            "subcategory":"Auto Repair",
            "type":"Services"
        }
    ],
    "sg:phone":"+1 931 823 5865",
    "sg:postcode":"38570",
    "sg:province":"TN",
    "sg:tags":[
        "body",
        "automobile",
        "painting"
    ],
    "wof:name":"Classy Corvettes & Autocraft",
    "wof:placetype":"venue"
},
  "geometry": {"coordinates":[-85.33640699999999,36.369403],"type":"Point"}
}