{
  "type": "Feature",
  "properties": {
    "addr:full":"5009 Florida Ave Chattanooga TN 37409",
    "addr:housenumber":"5009",
    "addr:postcode":"37409",
    "addr:street":"Florida Ave",
    "iso:country":"US",
    "sg:address":"5009 Florida Ave",
    "sg:city":"Chattanooga",
    "sg:classifiers":[
        {
            "category":"Organizations",
            "subcategory":"Community Association",
            "type":"Services"
        }
    ],
    "sg:phone":"+1 423 821 4260",
    "sg:postcode":"37409",
    "sg:province":"TN",
    "wof:name":"All Gods Chldren Cllecters CLB",
    "wof:placetype":"venue"
},
  "geometry": {"coordinates":[-85.328149,34.994043],"type":"Point"}
}