{
  "type": "Feature",
  "properties": {
    "iso:country":"US",
    "sg:address":"114 Fairway Blvd",
    "sg:city":"Jackson",
    "sg:classifiers":[
        {
            "category":"Social Services",
            "subcategory":"Adult Care",
            "type":"Services"
        }
    ],
    "sg:phone":"+1 731 512 1931",
    "sg:postcode":"38305",
    "sg:province":"TN",
    "sg:tags":[
        "home",
        "group"
    ],
    "wof:name":"Fairway Group Home",
    "wof:placetype":"venue"
},
  "geometry": {"coordinates":[-88.838202,35.705967],"type":"Point"}
}