{
  "type": "Feature",
  "properties": {
    "addr:full":"33 Finger Bluff Rd Morrison TN 37357",
    "addr:housenumber":"33",
    "addr:postcode":"37357",
    "addr:street":"Finger Bluff Rd",
    "iso:country":"US",
    "sg:address":"33 Finger Bluff Rd",
    "sg:city":"Morrison",
    "sg:classifiers":[
        {
            "category":"Wholesale",
            "subcategory":"Metals & Minerals",
            "type":"Manufacturing & Wholesale Goods"
        }
    ],
    "sg:phone":"+1 931 635 3100",
    "sg:postcode":"37357",
    "sg:province":"TN",
    "sg:tags":[
        "steel",
        "warehouse"
    ],
    "wof:name":"Morrison Tank & Vault",
    "wof:placetype":"venue"
},
  "geometry": {"coordinates":[-85.88432299999999,35.616961],"type":"Point"}
}