{
  "type": "Feature",
  "properties": {
    "iso:country":"US",
    "sg:address":"765 Old Hwy 68",
    "sg:city":"Sweetwater",
    "sg:classifiers":[
        {
            "category":"Restaurant",
            "type":"Food & Drink"
        }
    ],
    "sg:phone":"+1 423 337 6165",
    "sg:postcode":"37874",
    "sg:province":"TN",
    "sg:tags":[
        "eating"
    ],
    "wof:name":"Uncle Bobs B B Q Barn",
    "wof:placetype":"venue"
},
  "geometry": {"coordinates":[-84.459379,35.59342],"type":"Point"}
}