{
  "type": "Feature",
  "properties": {
    "iso:country":"US",
    "sg:address":"1717 Morningside Dr",
    "sg:city":"Morristown",
    "sg:classifiers":[
        {
            "category":"Real Estate",
            "subcategory":"Real Estate Agent",
            "type":"Services"
        }
    ],
    "sg:phone":"+1 423 586 1840",
    "sg:postcode":"37814",
    "sg:province":"TN",
    "wof:name":"Plankenhorn Rental",
    "wof:placetype":"venue"
},
  "geometry": {"coordinates":[-83.271416,36.220812],"type":"Point"}
}