{
  "type": "Feature",
  "properties": {
    "iso:country":"US",
    "sg:address":"410 N Collins St",
    "sg:city":"Tullahoma",
    "sg:classifiers":[
        {
            "category":"Social Services",
            "type":"Services"
        }
    ],
    "sg:phone":"+1 931 455 1787",
    "sg:postcode":"37388",
    "sg:province":"TN",
    "sg:tags":[
        "senior",
        "citizen"
    ],
    "sg:website":"www.coffeecountyseniors.org",
    "wof:name":"Coffee County Senior Citizens",
    "wof:placetype":"venue"
},
  "geometry": {"coordinates":[-86.219578,35.361135],"type":"Point"}
}