{
  "type": "Feature",
  "properties": {
    "addr:full":"185 Gentry Ln Bloomington Spgs TN 38545",
    "addr:housenumber":"185",
    "addr:postcode":"38545",
    "addr:street":"Gentry Ln",
    "iso:country":"US",
    "sg:address":"185 Gentry Ln",
    "sg:city":"Bloomington Spgs",
    "sg:classifiers":[
        {
            "category":"Retail",
            "subcategory":"Laundry & Dry Cleaning",
            "type":"Services"
        }
    ],
    "sg:phone":"+1 931 268 9678",
    "sg:postcode":"38545",
    "sg:province":"TN",
    "sg:tags":[
        "cleaners",
        "rug",
        "carpet"
    ],
    "wof:name":"Ridge Line Professional Svc",
    "wof:placetype":"venue"
},
  "geometry": {"coordinates":[-85.625759,36.218071],"type":"Point"}
}