{
  "type": "Feature",
  "properties": {
    "iso:country":"US",
    "sg:address":"9931 Smith Morgan Rd",
    "sg:city":"Soddy Daisy",
    "sg:classifiers":[
        {
            "category":"Organizations",
            "subcategory":"Religious Organization",
            "type":"Services"
        }
    ],
    "sg:phone":"+1 423 847 6600",
    "sg:postcode":"37379",
    "sg:province":"TN",
    "wof:name":"Straight Way Holiness Church",
    "wof:placetype":"venue"
},
  "geometry": {"coordinates":[-85.145295,35.232436],"type":"Point"}
}