{
  "type": "Feature",
  "properties": {
    "addr:full":"7341 Tazewell Pike Corryton TN 37721",
    "addr:housenumber":"7341",
    "addr:postcode":"37721",
    "addr:street":"Tazewell Pike",
    "iso:country":"US",
    "sg:address":"7341 Tazewell Pike",
    "sg:city":"Corryton",
    "sg:classifiers":[
        {
            "category":"Shopping",
            "subcategory":"Pharmacy",
            "type":"Retail Goods"
        }
    ],
    "sg:phone":"+1 865 219 6092",
    "sg:postcode":"37721",
    "sg:province":"TN",
    "sg:website":"www.cvs.com",
    "wof:name":"CVS Pharmacy",
    "wof:placetype":"venue"
},
  "geometry": {"coordinates":[-83.854338,36.114912],"type":"Point"}
}