{
  "type": "Feature",
  "properties": {
    "iso:country":"US",
    "sg:address":"7187 Smithville Hwy",
    "sg:city":"Mc Minnville",
    "sg:classifiers":[
        {
            "category":"Farming",
            "subcategory":"Nursery",
            "type":"Manufacturing & Wholesale Goods"
        }
    ],
    "sg:phone":"+1 931 934 2124",
    "sg:postcode":"37110",
    "sg:province":"TN",
    "sg:tags":[
        "ornamental",
        "supply"
    ],
    "wof:name":"Four M Greenhouses",
    "wof:placetype":"venue"
},
  "geometry": {"coordinates":[-85.79107,35.782811],"type":"Point"}
}