{
  "type": "Feature",
  "properties": {
    "iso:country":"US",
    "sg:address":"109 Green St",
    "sg:city":"Petersburg",
    "sg:classifiers":[
        {
            "category":"Government",
            "subcategory":"Fire Station",
            "type":"Public Place"
        }
    ],
    "sg:phone":"+1 931 438 1575",
    "sg:postcode":"37144",
    "sg:province":"TN",
    "wof:name":"Lincoln County Vlntr Fire Dept",
    "wof:placetype":"venue"
},
  "geometry": {"coordinates":[-86.64856399999999,35.32261],"type":"Point"}
}