{
  "type": "Feature",
  "properties": {
    "addr:full":"23 S Park St Hohenwald TN 38462",
    "addr:housenumber":"23",
    "addr:postcode":"38462",
    "addr:street":"S Park St",
    "iso:country":"US",
    "sg:address":"23 S Park St",
    "sg:city":"Hohenwald",
    "sg:classifiers":[
        {
            "category":"Utilities",
            "subcategory":"Fuel Oil & Lpg",
            "type":"Services"
        }
    ],
    "sg:phone":"+1 931 796 7428",
    "sg:postcode":"38462",
    "sg:province":"TN",
    "sg:tags":[
        "liquefied",
        "gas",
        "petroleum"
    ],
    "wof:name":"All Service Propane",
    "wof:placetype":"venue"
},
  "geometry": {"coordinates":[-87.55221400000001,35.547032],"type":"Point"}
}