{
  "type": "Feature",
  "properties": {
    "addr:full":"881 Lower Brownsville Rd Jackson TN 38301",
    "addr:housenumber":"881",
    "addr:postcode":"38301",
    "addr:street":"Lower Brownsville Rd",
    "iso:country":"US",
    "sg:address":"881 Lower Brownsville Rd",
    "sg:city":"Jackson",
    "sg:classifiers":[
        {
            "category":"Manufacturing",
            "subcategory":"Metals",
            "type":"Manufacturing & Wholesale Goods"
        }
    ],
    "sg:phone":"+1 731 989 4449",
    "sg:postcode":"38301",
    "sg:province":"TN",
    "sg:tags":[
        "hardware"
    ],
    "wof:name":"Jarvis South",
    "wof:placetype":"venue"
},
  "geometry": {"coordinates":[-88.894651,35.633006],"type":"Point"}
}