{
  "type": "Feature",
  "properties": {
    "addr:full":"5 Concord Cades Rd Milan TN 38358",
    "addr:housenumber":"5",
    "addr:postcode":"38358",
    "addr:street":"Concord Cades Rd",
    "iso:country":"US",
    "sg:address":"5 Concord Cades Rd",
    "sg:city":"Milan",
    "sg:classifiers":[
        {
            "category":"Utilities",
            "subcategory":"Mobile Phone",
            "type":"Services"
        }
    ],
    "sg:phone":"+1 731 686 0370",
    "sg:postcode":"38358",
    "sg:province":"TN",
    "sg:tags":[
        "communication",
        "radiotelephone",
        "house"
    ],
    "wof:name":"Ram Jack Tenn Fndtion Repr LLC",
    "wof:placetype":"venue"
},
  "geometry": {"coordinates":[-88.783894,35.975693],"type":"Point"}
}