{
  "type": "Feature",
  "properties": {
    "iso:country":"US",
    "sg:address":"2217 Ladd Dr",
    "sg:city":"Clarksville",
    "sg:classifiers":[
        {
            "category":"Social Services",
            "type":"Services"
        }
    ],
    "sg:phone":"+1 931 645 4561",
    "sg:postcode":"37043",
    "sg:province":"TN",
    "sg:tags":[
        "youth",
        "organization",
        "center"
    ],
    "wof:name":"Mentor One Inc",
    "wof:placetype":"venue"
},
  "geometry": {"coordinates":[-87.278306,36.507179],"type":"Point"}
}