{
  "type": "Feature",
  "properties": {
    "iso:country":"US",
    "sg:address":"226 Grammer Hill Rd",
    "sg:city":"Lynchburg",
    "sg:classifiers":[
        {
            "category":"Personal",
            "subcategory":"Beauty Salon",
            "type":"Services"
        }
    ],
    "sg:phone":"+1 931 759 7920",
    "sg:postcode":"37352",
    "sg:province":"TN",
    "wof:name":"Susie's House Of Beauty",
    "wof:placetype":"venue"
},
  "geometry": {"coordinates":[-86.34569999999999,35.238394],"type":"Point"}
}