{
  "type": "Feature",
  "properties": {
    "addr:full":"2845 E Wood St Paris TN 38242",
    "addr:housenumber":"2845",
    "addr:postcode":"38242",
    "addr:street":"E Wood St",
    "iso:country":"US",
    "sg:address":"2845 E Wood St",
    "sg:city":"Paris",
    "sg:classifiers":[
        {
            "category":"Autos & Motor Vehicles",
            "subcategory":"Recreational Vehicle Sales",
            "type":"Retail Goods"
        }
    ],
    "sg:phone":"+1 731 642 3124",
    "sg:postcode":"38242",
    "sg:province":"TN",
    "wof:name":"Sines & Son Rv",
    "wof:placetype":"venue"
},
  "geometry": {"coordinates":[-88.270186,36.324844],"type":"Point"}
}