{
  "type": "Feature",
  "properties": {
    "addr:full":"105 Springfield Ln Jonesborough TN 37659",
    "addr:housenumber":"105",
    "addr:postcode":"37659",
    "addr:street":"Springfield Ln",
    "iso:country":"US",
    "sg:address":"105 Springfield Ln",
    "sg:city":"Jonesborough",
    "sg:classifiers":[
        {
            "category":"Professional",
            "type":"Services"
        }
    ],
    "sg:phone":"+1 423 257 6217",
    "sg:postcode":"37659",
    "sg:province":"TN",
    "wof:name":"Jessie Fellers",
    "wof:placetype":"venue"
},
  "geometry": {"coordinates":[-82.538309,36.160546],"type":"Point"}
}