{
  "type": "Feature",
  "properties": {
    "iso:country":"US",
    "sg:address":"302 W Bank St",
    "sg:city":"Athens",
    "sg:classifiers":[
        {
            "category":"Shopping",
            "subcategory":"Beauty & Cosmetics",
            "type":"Retail Goods"
        }
    ],
    "sg:phone":"+1 423 745 4284",
    "sg:postcode":"37303",
    "sg:province":"TN",
    "sg:tags":[
        "jewelry",
        "merchandise"
    ],
    "wof:name":"Merle Norman Cosmetics",
    "wof:placetype":"venue"
},
  "geometry": {"coordinates":[-84.595911,35.440414],"type":"Point"}
}