{
  "type": "Feature",
  "properties": {
    "iso:country":"US",
    "sg:address":"2140 Ember Brook Ln",
    "sg:city":"Powell",
    "sg:classifiers":[
        {
            "category":"Organizations",
            "subcategory":"Religious Organization",
            "type":"Services"
        }
    ],
    "sg:phone":"+1 865 938 8655",
    "sg:postcode":"37849",
    "sg:province":"TN",
    "wof:name":"Gale L Lyon",
    "wof:placetype":"venue"
},
  "geometry": {"coordinates":[-84.047793,36.038657],"type":"Point"}
}