{
  "type": "Feature",
  "properties": {
    "addr:full":"1840 Black Fox Xing Murfreesboro TN 37127",
    "addr:housenumber":"1840",
    "addr:postcode":"37127",
    "addr:street":"Black Fox Xing",
    "iso:country":"US",
    "sg:address":"1840 Black Fox Xing",
    "sg:city":"Murfreesboro",
    "sg:classifiers":[
        {
            "category":"Professional",
            "subcategory":"Business Services",
            "type":"Services"
        }
    ],
    "sg:phone":"+1 615 896 1566",
    "sg:postcode":"37127",
    "sg:province":"TN",
    "wof:name":"Players Directory",
    "wof:placetype":"venue"
},
  "geometry": {"coordinates":[-86.364812,35.811063],"type":"Point"}
}