{
  "type": "Feature",
  "properties": {
    "iso:country":"US",
    "sg:address":"315 Transport Dr",
    "sg:city":"Cookeville",
    "sg:classifiers":[
        {
            "category":"Building & Trades",
            "subcategory":"Plumbing",
            "type":"Services"
        }
    ],
    "sg:phone":"+1 931 537 9114",
    "sg:postcode":"38506",
    "sg:province":"TN",
    "sg:tags":[
        "mechanical",
        "contractor"
    ],
    "wof:name":"D & H Mechanical",
    "wof:placetype":"venue"
},
  "geometry": {"coordinates":[-85.448955,36.205205],"type":"Point"}
}