{
  "type": "Feature",
  "properties": {
    "iso:country":"US",
    "sg:address":"9087 Poplar Ave",
    "sg:city":"Germantown",
    "sg:classifiers":[
        {
            "category":"Food & Beverages",
            "subcategory":"Liquor & Beverages",
            "type":"Retail Goods"
        },
        {
            "category":"Wholesale",
            "subcategory":"Wine & Distilled Alcoholic Beverages",
            "type":"Manufacturing & Wholesale Goods"
        }
    ],
    "sg:phone":"+1 901 757 1903",
    "sg:postcode":"38138",
    "sg:province":"TN",
    "sg:tags":[
        "broker"
    ],
    "wof:name":"Forest Hill Wine Merchants",
    "wof:placetype":"venue"
},
  "geometry": {"coordinates":[-89.759652,35.068352],"type":"Point"}
}