{
  "type": "Feature",
  "properties": {
    "addr:full":"12871 Abernathy Rd Byhalia TN 38611",
    "addr:housenumber":"12871",
    "addr:postcode":"38611",
    "addr:street":"Abernathy Rd",
    "iso:country":"US",
    "sg:address":"12871 Abernathy Rd",
    "sg:city":"Byhalia",
    "sg:classifiers":[
        {
            "category":"Building & Trades",
            "subcategory":"Construction",
            "type":"Services"
        }
    ],
    "sg:phone":"+1 662 838 6787",
    "sg:postcode":"38611",
    "sg:province":"TN",
    "sg:tags":[
        "contractor"
    ],
    "wof:name":"Clark Construction",
    "wof:placetype":"venue"
},
  "geometry": {"coordinates":[-89.759058,34.794599],"type":"Point"}
}