{
  "type": "Feature",
  "properties": {
    "iso:country":"US",
    "sg:address":"3546 Southridge Blvd",
    "sg:city":"Murfreesboro",
    "sg:classifiers":[
        {
            "category":"Manufacturing",
            "subcategory":"Toys & Sporting Goods",
            "type":"Manufacturing & Wholesale Goods"
        }
    ],
    "sg:phone":"+1 615 895 1088",
    "sg:postcode":"37128",
    "sg:province":"TN",
    "sg:tags":[
        "mfg"
    ],
    "wof:name":"Perfect Putter",
    "wof:placetype":"venue"
},
  "geometry": {"coordinates":[-86.412684,35.7934],"type":"Point"}
}