{
  "type": "Feature",
  "properties": {
    "iso:country":"US",
    "sg:address":"7399 US Hwy 64",
    "sg:city":"Memphis",
    "sg:classifiers":[
        {
            "category":"Freight",
            "type":"Transportation"
        }
    ],
    "sg:phone":"+1 901 368 0800",
    "sg:postcode":"38133",
    "sg:province":"TN",
    "sg:tags":[
        "special",
        "general"
    ],
    "wof:name":"American Mini Storage LLC",
    "wof:placetype":"venue"
},
  "geometry": {"coordinates":[-89.817052,35.204428],"type":"Point"}
}