{
  "type": "Feature",
  "properties": {
    "iso:country":"US",
    "sg:address":"130 E Charlemont Ave",
    "sg:city":"Kingsport",
    "sg:classifiers":[
        {
            "category":"Shopping",
            "subcategory":"Florist",
            "type":"Retail Goods"
        }
    ],
    "sg:phone":"+1 423 246 4177",
    "sg:postcode":"37660",
    "sg:province":"TN",
    "sg:tags":[
        "shop",
        "gift"
    ],
    "sg:website":"http://www.downtownflowers-giftshop.com",
    "wof:name":"Downtown Flowers & Gift Shop",
    "wof:placetype":"venue"
},
  "geometry": {"coordinates":[-82.55654699999999,36.550185],"type":"Point"}
}