{
  "type": "Feature",
  "properties": {
    "iso:country":"US",
    "sg:address":"2803 Lark Dr",
    "sg:city":"Clarksville",
    "sg:classifiers":[
        {
            "category":"Professional",
            "subcategory":"Business Services",
            "type":"Services"
        },
        {
            "category":"Manufacturing",
            "subcategory":"Apparel",
            "type":"Manufacturing & Wholesale Goods"
        }
    ],
    "sg:phone":"+1 931 645 6532",
    "sg:postcode":"37040",
    "sg:province":"TN",
    "sg:tags":[
        "embroidery"
    ],
    "wof:name":"Carol's Creative Embroidery",
    "wof:placetype":"venue"
},
  "geometry": {"coordinates":[-87.32089000000001,36.585552],"type":"Point"}
}