{
  "type": "Feature",
  "properties": {
    "iso:country":"US",
    "sg:address":"476 Mall Blvd",
    "sg:city":"Dyersburg",
    "sg:classifiers":[
        {
            "category":"Government",
            "subcategory":"Office",
            "type":"Public Place"
        }
    ],
    "sg:phone":"+1 731 288 0724",
    "sg:postcode":"38024",
    "sg:province":"TN",
    "sg:tags":[
        "village"
    ],
    "wof:name":"Hawkins Water Plant",
    "wof:placetype":"venue"
},
  "geometry": {"coordinates":[-89.39227099999999,36.064581],"type":"Point"}
}