{
  "type": "Feature",
  "properties": {
    "iso:country":"US",
    "sg:address":"4180 Millbranch Rd",
    "sg:city":"Memphis",
    "sg:classifiers":[
        {
            "category":"Retail",
            "subcategory":"Auto Repair",
            "type":"Services"
        }
    ],
    "sg:phone":"+1 901 396 1774",
    "sg:postcode":"38116",
    "sg:province":"TN",
    "sg:tags":[
        "automotive",
        "general",
        "exhaust"
    ],
    "wof:name":"Express Muffler & Brakes",
    "wof:placetype":"venue"
},
  "geometry": {"coordinates":[-90.00751700000001,35.031516],"type":"Point"}
}