{
  "type": "Feature",
  "properties": {
    "iso:country":"US",
    "sg:address":"1037 9th Ave N",
    "sg:city":"Nashville",
    "sg:classifiers":[
        {
            "category":"Shopping",
            "subcategory":"Clothing, Apparel, & Fashions",
            "type":"Retail Goods"
        }
    ],
    "sg:phone":"+1 615 256 9180",
    "sg:postcode":"37208",
    "sg:province":"TN",
    "sg:tags":[
        "boutique"
    ],
    "wof:name":"Kims Hair Plus Inc",
    "wof:placetype":"venue"
},
  "geometry": {"coordinates":[-86.792072,36.172369],"type":"Point"}
}