{
  "type": "Feature",
  "properties": {
    "iso:country":"US",
    "sg:address":"2051 Maple Ln",
    "sg:city":"Franklin",
    "sg:classifiers":[
        {
            "category":"Professional",
            "subcategory":"Secretarial Services",
            "type":"Services"
        }
    ],
    "sg:phone":"+1 615 395 4085",
    "sg:postcode":"37067",
    "sg:province":"TN",
    "sg:tags":[
        "reporting",
        "court"
    ],
    "wof:name":"Cooper Court Reporting",
    "wof:placetype":"venue"
},
  "geometry": {"coordinates":[-86.72566999999999,35.878629],"type":"Point"}
}