{
  "type": "Feature",
  "properties": {
    "iso:country":"US",
    "sg:address":"1075 Rolling Fields Cir",
    "sg:city":"Columbia",
    "sg:classifiers":[
        {
            "category":"Building & Trades",
            "subcategory":"Landscaping Services",
            "type":"Services"
        }
    ],
    "sg:phone":"+1 931 388 6145",
    "sg:postcode":"38401",
    "sg:province":"TN",
    "wof:name":"B C Mulch",
    "wof:placetype":"venue"
},
  "geometry": {"coordinates":[-87.05921600000001,35.608664],"type":"Point"}
}