{
  "type": "Feature",
  "properties": {
    "iso:country":"US",
    "sg:address":"109 W Main St",
    "sg:city":"Alexandria",
    "sg:classifiers":[
        {
            "category":"Organizations",
            "subcategory":"Religious Organization",
            "type":"Services"
        }
    ],
    "sg:phone":"+1 615 529 4068",
    "sg:postcode":"37012",
    "sg:province":"TN",
    "wof:name":"Alexandria Church Of Christ",
    "wof:placetype":"venue"
},
  "geometry": {"coordinates":[-86.035909,36.077609],"type":"Point"}
}