{
  "type": "Feature",
  "properties": {
    "addr:full":"2635 Upper Hilham Rd Livingston TN 38570",
    "addr:housenumber":"2635",
    "addr:postcode":"38570",
    "addr:street":"Upper Hilham Rd",
    "iso:country":"US",
    "sg:address":"2635 Upper Hilham Rd",
    "sg:city":"Livingston",
    "sg:classifiers":[
        {
            "category":"Building & Trades",
            "subcategory":"Construction",
            "type":"Services"
        }
    ],
    "sg:phone":"+1 931 823 0179",
    "sg:postcode":"38570",
    "sg:province":"TN",
    "sg:tags":[
        "general",
        "contractor"
    ],
    "wof:name":"Coffman Construction Contr",
    "wof:placetype":"venue"
},
  "geometry": {"coordinates":[-85.401815,36.418916],"type":"Point"}
}