{
  "type": "Feature",
  "properties": {
    "addr:full":"2329 Tarbet Dr Memphis TN 38119",
    "addr:housenumber":"2329",
    "addr:postcode":"38119",
    "addr:street":"Tarbet Dr",
    "iso:country":"US",
    "sg:address":"2329 Tarbet Dr",
    "sg:city":"Memphis",
    "sg:classifiers":[
        {
            "category":"Building & Trades",
            "subcategory":"Construction",
            "type":"Services"
        }
    ],
    "sg:phone":"+1 901 685 2874",
    "sg:postcode":"38119",
    "sg:province":"TN",
    "sg:tags":[
        "carpentry",
        "carpenter",
        "contractor"
    ],
    "wof:name":"Stephenson Trim Company",
    "wof:placetype":"venue"
},
  "geometry": {"coordinates":[-89.856315,35.08433],"type":"Point"}
}