{
  "type": "Feature",
  "properties": {
    "iso:country":"US",
    "sg:address":"3551 Kings Arms Cove",
    "sg:city":"Memphis",
    "sg:classifiers":[
        {
            "category":"Building & Trades",
            "subcategory":"Construction",
            "type":"Services"
        }
    ],
    "sg:phone":"+1 901 797 9292",
    "sg:postcode":"38115",
    "sg:province":"TN",
    "sg:tags":[
        "hanging",
        "contractor"
    ],
    "wof:name":"Rescue Painting Svcs",
    "wof:placetype":"venue"
},
  "geometry": {"coordinates":[-89.87748999999999,35.051455],"type":"Point"}
}