{
  "type": "Feature",
  "properties": {
    "iso:country":"US",
    "sg:address":"475 Metroplex Dr",
    "sg:city":"Nashville",
    "sg:classifiers":[
        {
            "category":"Wholesale",
            "subcategory":"Stationery",
            "type":"Manufacturing & Wholesale Goods"
        }
    ],
    "sg:phone":"+1 615 777 4731",
    "sg:postcode":"37211",
    "sg:province":"TN",
    "sg:tags":[
        "business",
        "form",
        "system"
    ],
    "wof:name":"Perfect Business Forms",
    "wof:placetype":"venue"
},
  "geometry": {"coordinates":[-86.699607,36.089559],"type":"Point"}
}