{
  "type": "Feature",
  "properties": {
    "addr:full":"4741 Mint Rd Maryville TN 37803",
    "addr:housenumber":"4741",
    "addr:postcode":"37803",
    "addr:street":"Mint Rd",
    "iso:country":"US",
    "sg:address":"4741 Mint Rd",
    "sg:city":"Maryville",
    "sg:classifiers":[
        {
            "category":"Home & Garden",
            "subcategory":"Building Materials",
            "type":"Retail Goods"
        }
    ],
    "sg:phone":"+1 865 977 1634",
    "sg:postcode":"37803",
    "sg:province":"TN",
    "sg:tags":[
        "downspouts",
        "gutter"
    ],
    "wof:name":"G & S Continuous Guttering",
    "wof:placetype":"venue"
},
  "geometry": {"coordinates":[-84.03844700000001,35.645337],"type":"Point"}
}