{
  "type": "Feature",
  "properties": {
    "iso:country":"US",
    "sg:address":"103 Public Sq",
    "sg:city":"Mt Pleasant",
    "sg:classifiers":[
        {
            "category":"Home & Garden",
            "subcategory":"Hardware",
            "type":"Retail Goods"
        }
    ],
    "sg:phone":"+1 931 379 7822",
    "sg:postcode":"38474",
    "sg:province":"TN",
    "wof:name":"Wren Hardware",
    "wof:placetype":"venue"
},
  "geometry": {"coordinates":[-87.20728699999999,35.534532],"type":"Point"}
}