{
  "type": "Feature",
  "properties": {
    "addr:full":"5617 Meadowcrest Ln Nashville TN 37209",
    "addr:housenumber":"5617",
    "addr:postcode":"37209",
    "addr:street":"Meadowcrest Ln",
    "iso:country":"US",
    "sg:address":"5617 Meadowcrest Ln",
    "sg:city":"Nashville",
    "sg:classifiers":[
        {
            "category":"Manufacturing",
            "subcategory":"Metals",
            "type":"Manufacturing & Wholesale Goods"
        }
    ],
    "sg:phone":"+1 615 352 8797",
    "sg:postcode":"37209",
    "sg:province":"TN",
    "sg:tags":[
        "finisher"
    ],
    "wof:name":"Fireside Designs",
    "wof:placetype":"venue"
},
  "geometry": {"coordinates":[-86.853568,36.144818],"type":"Point"}
}