{
  "type": "Feature",
  "properties": {
    "iso:country":"US",
    "sg:address":"803 Valley View Dr",
    "sg:city":"Sparta",
    "sg:classifiers":[
        {
            "category":"Travel",
            "subcategory":"Hotels & Motels",
            "type":"Entertainment"
        }
    ],
    "sg:phone":"+1 931 738 8585",
    "sg:postcode":"38583",
    "sg:province":"TN",
    "sg:tags":[
        "operation"
    ],
    "wof:name":"Royal Inn Motel",
    "wof:placetype":"venue"
},
  "geometry": {"coordinates":[-85.484308,35.952047],"type":"Point"}
}