{
  "type": "Feature",
  "properties": {
    "iso:country":"US",
    "sg:address":"5401 Kingston Pike",
    "sg:city":"Knoxville",
    "sg:classifiers":[
        {
            "category":"Professional",
            "subcategory":"Employment Agencies",
            "type":"Services"
        }
    ],
    "sg:phone":"+1 865 584 3009",
    "sg:postcode":"37919",
    "sg:province":"TN",
    "sg:tags":[
        "help",
        "supply"
    ],
    "wof:name":"Stat Medical Services Inc",
    "wof:placetype":"venue"
},
  "geometry": {"coordinates":[-83.99298899999999,35.935582],"type":"Point"}
}