{
  "type": "Feature",
  "properties": {
    "addr:full":"2841 US Hwy 45 S Jackson TN 38301",
    "addr:housenumber":"2841",
    "addr:postcode":"38301",
    "addr:street":"Us Hwy 45 S",
    "iso:country":"US",
    "sg:address":"2841 US Hwy 45 S",
    "sg:city":"Jackson",
    "sg:classifiers":[
        {
            "category":"Freight",
            "type":"Transportation"
        }
    ],
    "sg:phone":"+1 731 427 3041",
    "sg:postcode":"38301",
    "sg:province":"TN",
    "sg:tags":[
        "commercial",
        "storage"
    ],
    "wof:name":"Stanfield Storage Svc",
    "wof:placetype":"venue"
},
  "geometry": {"coordinates":[-88.78800099999999,35.536248],"type":"Point"}
}