{
  "type": "Feature",
  "properties": {
    "iso:country":"US",
    "sg:address":"3331 Leadvale Rd",
    "sg:city":"White Pine",
    "sg:classifiers":[
        {
            "category":"Sports & Exercise",
            "subcategory":"Golf",
            "type":"Entertainment"
        }
    ],
    "sg:phone":"+1 865 674 9986",
    "sg:postcode":"37890",
    "sg:province":"TN",
    "sg:tags":[
        "course"
    ],
    "wof:name":"White Pine Golf Club",
    "wof:placetype":"venue"
},
  "geometry": {"coordinates":[-83.263518,36.08613],"type":"Point"}
}