{
  "type": "Feature",
  "properties": {
    "iso:country":"US",
    "sg:address":"2403 12th Ave S",
    "sg:city":"Nashville",
    "sg:classifiers":[
        {
            "category":"Professional",
            "type":"Services"
        }
    ],
    "sg:phone":"+1 615 298 9853",
    "sg:postcode":"37204",
    "sg:province":"TN",
    "wof:name":"Marimba Inc",
    "wof:placetype":"venue"
},
  "geometry": {"coordinates":[-86.789361,36.126102],"type":"Point"}
}