{
  "type": "Feature",
  "properties": {
    "addr:full":"95 Stone Ln Springville TN 38256",
    "addr:housenumber":"95",
    "addr:postcode":"38256",
    "addr:street":"Stone Ln",
    "iso:country":"US",
    "sg:address":"95 Stone Ln",
    "sg:city":"Springville",
    "sg:classifiers":[
        {
            "category":"Building & Trades",
            "subcategory":"Equipment Rental",
            "type":"Services"
        }
    ],
    "sg:phone":"+1 731 641 0070",
    "sg:postcode":"38256",
    "sg:province":"TN",
    "wof:name":"Bostian Rentals",
    "wof:placetype":"venue"
},
  "geometry": {"coordinates":[-88.121611,36.362913],"type":"Point"}
}