{
  "type": "Feature",
  "properties": {
    "iso:country":"US",
    "sg:address":"1221 Meadowlark Ln",
    "sg:city":"Memphis",
    "sg:classifiers":[
        {
            "category":"Building & Trades",
            "subcategory":"Cleaning & Sanitation",
            "type":"Services"
        }
    ],
    "sg:phone":"+1 901 396 9370",
    "sg:postcode":"38116",
    "sg:province":"TN",
    "sg:tags":[
        "janitor"
    ],
    "wof:name":"HFM Cleaning Svc",
    "wof:placetype":"venue"
},
  "geometry": {"coordinates":[-90.022302,35.016558],"type":"Point"}
}