{
  "type": "Feature",
  "properties": {
    "addr:full":"2723 McLemore Way Franklin TN 37064",
    "addr:housenumber":"2723",
    "addr:postcode":"37064",
    "addr:street":"Mclemore Way",
    "iso:country":"US",
    "sg:address":"2723 McLemore Way",
    "sg:city":"Franklin",
    "sg:classifiers":[
        {
            "category":"Wholesale",
            "subcategory":"Electrical",
            "type":"Manufacturing & Wholesale Goods"
        }
    ],
    "sg:phone":"+1 615 726 5191",
    "sg:postcode":"37064",
    "sg:province":"TN",
    "sg:tags":[
        "recording",
        "studio"
    ],
    "wof:name":"Nagra USA Inc",
    "wof:placetype":"venue"
},
  "geometry": {"coordinates":[-86.868431,35.840115],"type":"Point"}
}