{
  "type": "Feature",
  "properties": {
    "iso:country":"US",
    "sg:address":"2000 Enterprise Rd",
    "sg:city":"Piney Flats",
    "sg:classifiers":[
        {
            "category":"Organizations",
            "subcategory":"Religious Organization",
            "type":"Services"
        }
    ],
    "sg:phone":"+1 423 538 5511",
    "sg:postcode":"37618",
    "sg:province":"TN",
    "wof:name":"Enterprise Untd Methdst Church",
    "wof:placetype":"venue"
},
  "geometry": {"coordinates":[-82.32847,36.468064],"type":"Point"}
}