{
  "type": "Feature",
  "properties": {
    "addr:full":"4762 State Hwy 58 Chattanooga TN 37416",
    "addr:housenumber":"4762",
    "addr:postcode":"37416",
    "addr:street":"State Hwy 58",
    "iso:country":"US",
    "sg:address":"4762 State Hwy 58",
    "sg:city":"Chattanooga",
    "sg:classifiers":[
        {
            "category":"Insurance",
            "subcategory":"Insurance Agent",
            "type":"Services"
        }
    ],
    "sg:phone":"+1 423 899 4159",
    "sg:postcode":"37416",
    "sg:province":"TN",
    "wof:name":"State Farm Insurance",
    "wof:placetype":"venue"
},
  "geometry": {"coordinates":[-85.188829,35.087979],"type":"Point"}
}