{
  "type": "Feature",
  "properties": {
    "iso:country":"US",
    "sg:address":"2516 Mahala Ln",
    "sg:city":"Chattanooga",
    "sg:classifiers":[
        {
            "category":"Wholesale",
            "subcategory":"Chemicals & Plastics",
            "type":"Manufacturing & Wholesale Goods"
        }
    ],
    "sg:phone":"+1 423 894 6855",
    "sg:postcode":"37421",
    "sg:province":"TN",
    "sg:tags":[
        "cleaning",
        "compound"
    ],
    "wof:name":"Stanley Home Products",
    "wof:placetype":"venue"
},
  "geometry": {"coordinates":[-85.173196,35.056071],"type":"Point"}
}