{
  "type": "Feature",
  "properties": {
    "addr:full":"610 Smith St Charlotte TN 37036",
    "addr:housenumber":"610",
    "addr:postcode":"37036",
    "addr:street":"Smith St",
    "iso:country":"US",
    "sg:address":"610 Smith St",
    "sg:city":"Charlotte",
    "sg:classifiers":[
        {
            "category":"Building & Trades",
            "subcategory":"Electrical",
            "type":"Services"
        }
    ],
    "sg:phone":"+1 615 789 5955",
    "sg:postcode":"37036",
    "sg:province":"TN",
    "sg:tags":[
        "electrical",
        "contractor"
    ],
    "wof:name":"Telephone Wirg & Installation",
    "wof:placetype":"venue"
},
  "geometry": {"coordinates":[-87.344775,36.176253],"type":"Point"}
}