{
  "type": "Feature",
  "properties": {
    "iso:country":"US",
    "sg:address":"150 Lynn Dr",
    "sg:city":"Benton",
    "sg:classifiers":[
        {
            "category":"Building & Trades",
            "subcategory":"Plumbing",
            "type":"Services"
        }
    ],
    "sg:phone":"+1 423 338 9789",
    "sg:postcode":"37307",
    "sg:province":"TN",
    "sg:tags":[
        "conditioning",
        "air",
        "system",
        "contractor"
    ],
    "wof:name":"Key Electric Heating & Air",
    "wof:placetype":"venue"
},
  "geometry": {"coordinates":[-84.60961500000001,35.205024],"type":"Point"}
}