{
  "type": "Feature",
  "properties": {
    "iso:country":"US",
    "sg:address":"155 Gant Hollow Rd",
    "sg:city":"Shelbyville",
    "sg:classifiers":[
        {
            "category":"Professional",
            "type":"Services"
        }
    ],
    "sg:phone":"+1 931 684 0736",
    "sg:postcode":"37160",
    "sg:province":"TN",
    "wof:name":"Kenneth Wayne Williams",
    "wof:placetype":"venue"
},
  "geometry": {"coordinates":[-86.56619000000001,35.38464],"type":"Point"}
}