{
  "type": "Feature",
  "properties": {
    "iso:country":"US",
    "sg:address":"527 Perry Way",
    "sg:city":"Sevierville",
    "sg:classifiers":[
        {
            "category":"Building & Trades",
            "subcategory":"Plumbing",
            "type":"Services"
        }
    ],
    "sg:phone":"+1 865 429 5253",
    "sg:postcode":"37876",
    "sg:province":"TN",
    "sg:tags":[
        "plumbing",
        "contractor"
    ],
    "wof:name":"Smoky Mountain Sewer & Drain",
    "wof:placetype":"venue"
},
  "geometry": {"coordinates":[-83.42110099999999,35.754129],"type":"Point"}
}