{
  "type": "Feature",
  "properties": {
    "addr:full":"3211 Crystal Spring Ln Hermitage TN 37076",
    "addr:housenumber":"3211",
    "addr:postcode":"37076",
    "addr:street":"Crystal Spring Ln",
    "iso:country":"US",
    "sg:address":"3211 Crystal Spring Ln",
    "sg:city":"Hermitage",
    "sg:classifiers":[
        {
            "category":"Professional",
            "type":"Services"
        }
    ],
    "sg:phone":"+1 615 316 9092",
    "sg:postcode":"37076",
    "sg:province":"TN",
    "wof:name":"Prime Products Int",
    "wof:placetype":"venue"
},
  "geometry": {"coordinates":[-86.61079700000001,36.174002],"type":"Point"}
}