{
  "type": "Feature",
  "properties": {
    "iso:country":"US",
    "sg:address":"6020 Newton Rd",
    "sg:city":"Crossville",
    "sg:classifiers":[
        {
            "category":"Professional",
            "subcategory":"Employment Agencies",
            "type":"Services"
        }
    ],
    "sg:phone":"+1 931 788 1416",
    "sg:postcode":"38572",
    "sg:province":"TN",
    "sg:tags":[
        "help",
        "supply"
    ],
    "wof:name":"Bolin Farm & Equipment",
    "wof:placetype":"venue"
},
  "geometry": {"coordinates":[-85.182013,35.824252],"type":"Point"}
}