{
  "type": "Feature",
  "properties": {
    "iso:country":"US",
    "sg:address":"93 Big Creek Dr",
    "sg:city":"Atoka",
    "sg:classifiers":[
        {
            "category":"Manufacturing",
            "subcategory":"Buildings",
            "type":"Manufacturing & Wholesale Goods"
        },
        {
            "category":"Building & Trades",
            "subcategory":"Construction",
            "type":"Services"
        }
    ],
    "sg:phone":"+1 901 840 1467",
    "sg:postcode":"38004",
    "sg:province":"TN",
    "sg:tags":[
        "roofing",
        "industrial",
        "system",
        "builder",
        "specialty",
        "heating",
        "contractors-commercial",
        "home",
        "contractor",
        "air conditioning"
    ],
    "wof:name":"Stubblefield Brothers Roofing",
    "wof:placetype":"venue"
},
  "geometry": {"coordinates":[-89.83446600000001,35.411495],"type":"Point"}
}