{
  "type": "Feature",
  "properties": {
    "iso:country":"US",
    "sg:address":"508 Autumn Springs Ct",
    "sg:city":"Franklin",
    "sg:classifiers":[
        {
            "category":"Professional",
            "subcategory":"Research",
            "type":"Services"
        },
        {
            "category":"Professional",
            "subcategory":"Management & Consulting",
            "type":"Services"
        }
    ],
    "sg:phone":"+1 615 771 9962",
    "sg:postcode":"37067",
    "sg:province":"TN",
    "sg:tags":[
        "environmental",
        "ecological",
        "business"
    ],
    "wof:name":"Safe Harbor Ecological Develop",
    "wof:placetype":"venue"
},
  "geometry": {"coordinates":[-86.82799300000001,35.948879],"type":"Point"}
}