{
  "type": "Feature",
  "properties": {
    "iso:country":"US",
    "sg:address":"460 West Ave",
    "sg:city":"Crossville",
    "sg:classifiers":[
        {
            "category":"Shopping",
            "type":"Retail Goods"
        }
    ],
    "sg:phone":"+1 931 484 4497",
    "sg:postcode":"38555",
    "sg:province":"TN",
    "sg:tags":[
        "spa",
        "hot",
        "tub"
    ],
    "wof:name":"Hot Springs Spas",
    "wof:placetype":"venue"
},
  "geometry": {"coordinates":[-85.02965500000001,35.94985],"type":"Point"}
}