{
  "type": "Feature",
  "properties": {
    "iso:country":"US",
    "sg:address":"2626 Music Valley Dr",
    "sg:city":"Nashville",
    "sg:classifiers":[
        {
            "category":"Travel",
            "subcategory":"Campground",
            "type":"Entertainment"
        }
    ],
    "sg:phone":"+1 615 889 0286",
    "sg:postcode":"37214",
    "sg:province":"TN",
    "sg:tags":[
        "campsite",
        "park",
        "trailer"
    ],
    "wof:name":"K L A",
    "wof:placetype":"venue"
},
  "geometry": {"coordinates":[-86.69902999999999,36.228882],"type":"Point"}
}