{
  "type": "Feature",
  "properties": {
    "iso:country":"US",
    "sg:address":"2106 Buena Vista Pike",
    "sg:city":"Nashville",
    "sg:classifiers":[
        {
            "category":"Manufacturing",
            "subcategory":"Signs",
            "type":"Manufacturing & Wholesale Goods"
        }
    ],
    "sg:phone":"+1 615 242 9037",
    "sg:postcode":"37218",
    "sg:province":"TN",
    "wof:name":"Jackson Sign",
    "wof:placetype":"venue"
},
  "geometry": {"coordinates":[-86.831217,36.193659],"type":"Point"}
}