{
  "type": "Feature",
  "properties": {
    "addr:full":"6537 Chapman Hwy Knoxville TN 37920",
    "addr:housenumber":"6537",
    "addr:postcode":"37920",
    "addr:street":"Chapman Hwy",
    "iso:country":"US",
    "sg:address":"6537 Chapman Hwy",
    "sg:city":"Knoxville",
    "sg:classifiers":[
        {
            "category":"Retail",
            "subcategory":"Auto Repair",
            "type":"Services"
        }
    ],
    "sg:phone":"+1 865 609 9922",
    "sg:postcode":"37920",
    "sg:province":"TN",
    "sg:tags":[
        "automotive"
    ],
    "wof:name":"Shell Rapid Lube",
    "wof:placetype":"venue"
},
  "geometry": {"coordinates":[-83.863748,35.921063],"type":"Point"}
}