{
  "type": "Feature",
  "properties": {
    "iso:country":"US",
    "sg:address":"411 W 25th St",
    "sg:city":"Chattanooga",
    "sg:classifiers":[
        {
            "category":"Professional",
            "subcategory":"Management & Consulting",
            "type":"Services"
        }
    ],
    "sg:phone":"+1 423 265 6035",
    "sg:postcode":"37408",
    "sg:province":"TN",
    "sg:tags":[
        "employment",
        "screening"
    ],
    "sg:website":"www.applicationresearchers.com",
    "wof:name":"Application Researchers",
    "wof:placetype":"venue"
},
  "geometry": {"coordinates":[-85.317123,35.028886],"type":"Point"}
}