{
  "type": "Feature",
  "properties": {
    "addr:full":"549 Ford St Clarksville TN 37040",
    "addr:housenumber":"549",
    "addr:postcode":"37040",
    "addr:street":"Ford St",
    "iso:country":"US",
    "sg:address":"549 Ford St",
    "sg:city":"Clarksville",
    "sg:classifiers":[
        {
            "category":"Organizations",
            "subcategory":"Religious Organization",
            "type":"Services"
        }
    ],
    "sg:phone":"+1 931 906 2141",
    "sg:postcode":"37040",
    "sg:province":"TN",
    "sg:tags":[
        "church"
    ],
    "sg:website":"www.libertychurch.org",
    "wof:name":"Liberty Church",
    "wof:placetype":"venue"
},
  "geometry": {"coordinates":[-87.34876800000001,36.536494],"type":"Point"}
}