{
  "type": "Feature",
  "properties": {
    "addr:full":"111 W Washington Ave Covington TN 38019",
    "addr:housenumber":"111",
    "addr:postcode":"38019",
    "addr:street":"W Washington Ave",
    "iso:country":"US",
    "sg:address":"111 W Washington Ave",
    "sg:city":"Covington",
    "sg:classifiers":[
        {
            "category":"Government",
            "subcategory":"Office",
            "type":"Public Place"
        }
    ],
    "sg:phone":"+1 901 476 0231",
    "sg:postcode":"38019",
    "sg:province":"TN",
    "sg:tags":[
        "county",
        "program"
    ],
    "wof:name":"Tipton Agriculture Extension",
    "wof:placetype":"venue"
},
  "geometry": {"coordinates":[-89.647796,35.56287],"type":"Point"}
}