{
  "type": "Feature",
  "properties": {
    "addr:full":"819 Seahorn Rd Jefferson City TN 37760",
    "addr:housenumber":"819",
    "addr:postcode":"37760",
    "addr:street":"Seahorn Rd",
    "iso:country":"US",
    "sg:address":"819 Seahorn Rd",
    "sg:city":"Jefferson City",
    "sg:classifiers":[
        {
            "category":"Farming",
            "subcategory":"Dairy Farm",
            "type":"Manufacturing & Wholesale Goods"
        }
    ],
    "sg:phone":"+1 865 475 8158",
    "sg:postcode":"37760",
    "sg:province":"TN",
    "wof:name":"Brian Stooksbury",
    "wof:placetype":"venue"
},
  "geometry": {"coordinates":[-83.506675,36.084897],"type":"Point"}
}