{
  "type": "Feature",
  "properties": {
    "addr:full":"1837 Edmondson Ave Memphis TN 38114",
    "addr:housenumber":"1837",
    "addr:postcode":"38114",
    "addr:street":"Edmondson Ave",
    "iso:country":"US",
    "sg:address":"1837 Edmondson Ave",
    "sg:city":"Memphis",
    "sg:classifiers":[
        {
            "category":"Building & Trades",
            "subcategory":"Construction",
            "type":"Services"
        }
    ],
    "sg:phone":"+1 901 274 7754",
    "sg:postcode":"38114",
    "sg:province":"TN",
    "sg:tags":[
        "system",
        "specialty",
        "heating",
        "contractor",
        "air conditioning"
    ],
    "wof:name":"J&J Filters",
    "wof:placetype":"venue"
},
  "geometry": {"coordinates":[-90.000373,35.107203],"type":"Point"}
}