{
  "type": "Feature",
  "properties": {
    "addr:full":"6125 Preservation Dr Chattanooga TN 37416",
    "addr:housenumber":"6125",
    "addr:postcode":"37416",
    "addr:street":"Preservation Dr",
    "iso:country":"US",
    "sg:address":"6125 Preservation Dr",
    "sg:city":"Chattanooga",
    "sg:classifiers":[
        {
            "category":"Government",
            "subcategory":"Office",
            "type":"Public Place"
        }
    ],
    "sg:phone":"+1 423 643 5970",
    "sg:postcode":"37416",
    "sg:province":"TN",
    "sg:tags":[
        "city",
        "program"
    ],
    "wof:name":"Chattanooga Air Pollution Cntl",
    "wof:placetype":"venue"
},
  "geometry": {"coordinates":[-85.184422,35.075058],"type":"Point"}
}