{
  "type": "Feature",
  "properties": {
    "addr:full":"104 University Pkwy Johnson City TN 37604",
    "addr:housenumber":"104",
    "addr:postcode":"37604",
    "addr:street":"University Pkwy",
    "iso:country":"US",
    "sg:address":"104 University Pkwy",
    "sg:city":"Johnson City",
    "sg:classifiers":[
        {
            "category":"Insurance",
            "subcategory":"Insurance Agent",
            "type":"Services"
        }
    ],
    "sg:phone":"+1 423 929 9457",
    "sg:postcode":"37604",
    "sg:province":"TN",
    "wof:name":"State Farm Insurance",
    "wof:placetype":"venue"
},
  "geometry": {"coordinates":[-82.34230599999999,36.307178],"type":"Point"}
}