{
  "type": "Feature",
  "properties": {
    "addr:full":"245 Hidden Acres Rd Kingsport TN 37664",
    "addr:housenumber":"245",
    "addr:postcode":"37664",
    "addr:street":"Hidden Acres Rd",
    "iso:country":"US",
    "sg:address":"245 Hidden Acres Rd",
    "sg:city":"Kingsport",
    "sg:classifiers":[
        {
            "category":"Freight",
            "type":"Transportation"
        }
    ],
    "sg:phone":"+1 423 967 9180",
    "sg:postcode":"37664",
    "sg:province":"TN",
    "sg:tags":[
        "operator",
        "trucking"
    ],
    "wof:name":"Pbs Xpress",
    "wof:placetype":"venue"
},
  "geometry": {"coordinates":[-82.56100499999999,36.445458],"type":"Point"}
}