{
  "type": "Feature",
  "properties": {
    "addr:full":"615 E Broadway St Lenoir City TN 37771",
    "addr:housenumber":"615",
    "addr:postcode":"37771",
    "addr:street":"E Broadway St",
    "iso:country":"US",
    "sg:address":"615 E Broadway St",
    "sg:city":"Lenoir City",
    "sg:classifiers":[
        {
            "category":"Sports & Exercise",
            "subcategory":"Gym",
            "type":"Entertainment"
        }
    ],
    "sg:phone":"+1 865 986 5555",
    "sg:postcode":"37771",
    "sg:province":"TN",
    "sg:tags":[
        "club",
        "health",
        "studio",
        "gymnasium"
    ],
    "wof:name":"Curves For Women",
    "wof:placetype":"venue"
},
  "geometry": {"coordinates":[-84.260262,35.794692],"type":"Point"}
}