{
  "type": "Feature",
  "properties": {
    "iso:country":"US",
    "sg:address":"20205 Hwy 64",
    "sg:city":"Bolivar",
    "sg:classifiers":[
        {
            "category":"Organizations",
            "subcategory":"Religious Organization",
            "type":"Services"
        }
    ],
    "sg:phone":"+1 731 658 2451",
    "sg:postcode":"38008",
    "sg:province":"TN",
    "wof:name":"Forest Hill Pentecostal Church",
    "wof:placetype":"venue"
},
  "geometry": {"coordinates":[-88.878069,35.236592],"type":"Point"}
}