{
  "type": "Feature",
  "properties": {
    "iso:country":"US",
    "sg:address":"1104 Wagner Dr",
    "sg:city":"Sevierville",
    "sg:classifiers":[
        {
            "category":"Government",
            "subcategory":"Office",
            "type":"Public Place"
        }
    ],
    "sg:phone":"+1 865 429 7017",
    "sg:postcode":"37862",
    "sg:province":"TN",
    "sg:tags":[
        "transportation"
    ],
    "wof:name":"Tennessee State Transportation",
    "wof:placetype":"venue"
},
  "geometry": {"coordinates":[-83.532381,35.860304],"type":"Point"}
}