{
  "type": "Feature",
  "properties": {
    "iso:country":"US",
    "sg:address":"155 N Hood Rd",
    "sg:city":"Lawrenceburg",
    "sg:classifiers":[
        {
            "category":"Farming",
            "subcategory":"Dairy Farm",
            "type":"Manufacturing & Wholesale Goods"
        }
    ],
    "sg:phone":"+1 931 762 5429",
    "sg:postcode":"38464",
    "sg:province":"TN",
    "wof:name":"Dairy Barn",
    "wof:placetype":"venue"
},
  "geometry": {"coordinates":[-87.483108,35.282908],"type":"Point"}
}