{
  "type": "Feature",
  "properties": {
    "iso:country":"US",
    "sg:address":"5325 Old Hixson Pike",
    "sg:city":"Hixson",
    "sg:classifiers":[
        {
            "category":"Wholesale",
            "subcategory":"Non-durable Goods",
            "type":"Manufacturing & Wholesale Goods"
        },
        {
            "category":"Manufacturing",
            "subcategory":"Printing",
            "type":"Manufacturing & Wholesale Goods"
        }
    ],
    "sg:phone":"+1 423 870 3917",
    "sg:postcode":"37343",
    "sg:province":"TN",
    "sg:tags":[
        "printer",
        "advertising"
    ],
    "wof:name":"Paragon Printing Inc",
    "wof:placetype":"venue"
},
  "geometry": {"coordinates":[-85.23511499999999,35.143463],"type":"Point"}
}