{
  "type": "Feature",
  "properties": {
    "iso:country":"US",
    "sg:address":"140 W Main St",
    "sg:city":"Mountain City",
    "sg:classifiers":[
        {
            "category":"Health Services",
            "subcategory":"Optometrist",
            "type":"Services"
        }
    ],
    "sg:phone":"+1 423 727 7241",
    "sg:postcode":"37683",
    "sg:province":"TN",
    "wof:name":"George A Cunningham OD",
    "wof:placetype":"venue"
},
  "geometry": {"coordinates":[-81.804587,36.474621],"type":"Point"}
}