{
  "type": "Feature",
  "properties": {
    "addr:full":"4574 Hwy 11 E Bluff City TN 37618",
    "addr:housenumber":"4574",
    "addr:postcode":"37618",
    "addr:street":"Hwy 11 E Bluff",
    "iso:country":"US",
    "sg:address":"4574 Hwy 11 E",
    "sg:city":"Bluff City",
    "sg:classifiers":[
        {
            "category":"Professional",
            "subcategory":"Computer Services",
            "type":"Services"
        }
    ],
    "sg:phone":"+1 423 538 1700",
    "sg:postcode":"37618",
    "sg:province":"TN",
    "sg:tags":[
        "repair"
    ],
    "wof:name":"Noble's Electronic Surplus",
    "wof:placetype":"venue"
},
  "geometry": {"coordinates":[-82.28513,36.463146],"type":"Point"}
}