{
  "type": "Feature",
  "properties": {
    "addr:full":"9828 US Hwy 70 E Bells TN 38006",
    "addr:housenumber":"9828",
    "addr:postcode":"38006",
    "addr:street":"Us Hwy 70 E Bells",
    "iso:country":"US",
    "sg:address":"9828 US Hwy 70 E",
    "sg:city":"Bells",
    "sg:classifiers":[
        {
            "category":"Autos & Motor Vehicles",
            "subcategory":"Auto Supplies",
            "type":"Retail Goods"
        }
    ],
    "sg:phone":"+1 731 779 1000",
    "sg:postcode":"38006",
    "sg:province":"TN",
    "sg:tags":[
        "tire"
    ],
    "wof:name":"Love's Truck & Tire",
    "wof:placetype":"venue"
},
  "geometry": {"coordinates":[-89.088634,35.583908],"type":"Point"}
}