{
  "type": "Feature",
  "properties": {
    "iso:country":"US",
    "sg:address":"3006 Johnson Ave",
    "sg:city":"Memphis",
    "sg:classifiers":[
        {
            "category":"Restaurant",
            "type":"Food & Drink"
        }
    ],
    "sg:phone":"+1 901 454 1009",
    "sg:postcode":"38112",
    "sg:province":"TN",
    "wof:name":"Allen's Kream KONE",
    "wof:placetype":"venue"
},
  "geometry": {"coordinates":[-89.95984799999999,35.141864],"type":"Point"}
}