{
  "type": "Feature",
  "properties": {
    "iso:country":"US",
    "sg:address":"4990 Poplar Ave",
    "sg:city":"Memphis",
    "sg:classifiers":[
        {
            "category":"Real Estate",
            "subcategory":"Real Estate Agent",
            "type":"Services"
        }
    ],
    "sg:phone":"+1 901 684 1141",
    "sg:postcode":"38117",
    "sg:province":"TN",
    "wof:name":"Freeburg Investment Co",
    "wof:placetype":"venue"
},
  "geometry": {"coordinates":[-89.89299,35.111691],"type":"Point"}
}