{
  "type": "Feature",
  "properties": {
    "iso:country":"US",
    "sg:address":"142 S Union Ave",
    "sg:city":"Henderson",
    "sg:classifiers":[
        {
            "category":"Autos & Motor Vehicles",
            "subcategory":"Auto Supplies",
            "type":"Retail Goods"
        },
        {
            "category":"Wholesale",
            "subcategory":"Auto Parts",
            "type":"Manufacturing & Wholesale Goods"
        }
    ],
    "sg:phone":"+1 731 989 3599",
    "sg:postcode":"38340",
    "sg:province":"TN",
    "sg:tags":[
        "tire"
    ],
    "wof:name":"Henderson Tire Company",
    "wof:placetype":"venue"
},
  "geometry": {"coordinates":[-88.64142699999999,35.438182],"type":"Point"}
}