{
  "type": "Feature",
  "properties": {
    "iso:country":"US",
    "sg:address":"613 US Hwy 11E",
    "sg:city":"Jefferson City",
    "sg:classifiers":[
        {
            "category":"Professional",
            "subcategory":"Advertising",
            "type":"Services"
        }
    ],
    "sg:phone":"+1 865 471 1120",
    "sg:postcode":"37760",
    "sg:province":"TN",
    "sg:website":"www.pcpartfinder.com",
    "wof:name":"PCPARTFINDER.COM",
    "wof:placetype":"venue"
},
  "geometry": {"coordinates":[-83.467868,36.126927],"type":"Point"}
}