{
  "type": "Feature",
  "properties": {
    "iso:country":"US",
    "sg:address":"521 Airport Rd",
    "sg:city":"Chattanooga",
    "sg:classifiers":[
        {
            "category":"Autos & Motor Vehicles",
            "subcategory":"Automobile Sales",
            "type":"Retail Goods"
        }
    ],
    "sg:phone":"+1 423 499 1100",
    "sg:postcode":"37421",
    "sg:province":"TN",
    "sg:tags":[
        "equipment",
        "aircraft",
        "parts",
        "supply"
    ],
    "wof:name":"Star Avionics Inc",
    "wof:placetype":"venue"
},
  "geometry": {"coordinates":[-85.19714999999999,35.025224],"type":"Point"}
}