{
  "type": "Feature",
  "properties": {
    "iso:country":"US",
    "sg:address":"222 N Church St",
    "sg:city":"Murfreesboro",
    "sg:classifiers":[
        {
            "category":"Travel",
            "subcategory":"Hotels & Motels",
            "type":"Entertainment"
        }
    ],
    "sg:phone":"+1 615 849 1150",
    "sg:postcode":"37130",
    "sg:province":"TN",
    "wof:name":"Fairfield Inn",
    "wof:placetype":"venue"
},
  "geometry": {"coordinates":[-86.39106700000001,35.847834],"type":"Point"}
}