{
  "type": "Feature",
  "properties": {
    "iso:country":"US",
    "sg:address":"100 Ossie Cir",
    "sg:city":"Jefferson City",
    "sg:classifiers":[
        {
            "category":"Real Estate",
            "subcategory":"Real Estate Operator",
            "type":"Services"
        }
    ],
    "sg:phone":"+1 865 471 6800",
    "sg:postcode":"37760",
    "sg:province":"TN",
    "sg:tags":[
        "building",
        "apartment"
    ],
    "wof:name":"Bradford Square Apartments",
    "wof:placetype":"venue"
},
  "geometry": {"coordinates":[-83.472555,36.091432],"type":"Point"}
}