{
  "type": "Feature",
  "properties": {
    "addr:full":"1601 Skyline Dr Johnson City TN 37604",
    "addr:housenumber":"1601",
    "addr:postcode":"37604",
    "addr:street":"Skyline Dr",
    "iso:country":"US",
    "sg:address":"1601 Skyline Dr",
    "sg:city":"Johnson City",
    "sg:classifiers":[
        {
            "category":"Organizations",
            "subcategory":"Religious Organization",
            "type":"Services"
        }
    ],
    "sg:phone":"+1 423 928 2473",
    "sg:postcode":"37604",
    "sg:province":"TN",
    "wof:name":"Skyline Heights Baptist Church",
    "wof:placetype":"venue"
},
  "geometry": {"coordinates":[-82.389121,36.319339],"type":"Point"}
}