{
  "type": "Feature",
  "properties": {
    "addr:full":"909 US Hwy 11 Sweetwater TN 37874",
    "addr:housenumber":"909",
    "addr:postcode":"37874",
    "addr:street":"Us Hwy 11",
    "iso:country":"US",
    "sg:address":"909 US Hwy 11",
    "sg:city":"Sweetwater",
    "sg:classifiers":[
        {
            "category":"Autos & Motor Vehicles",
            "subcategory":"Automobile Sales",
            "type":"Retail Goods"
        }
    ],
    "sg:phone":"+1 423 337 5001",
    "sg:postcode":"37874",
    "sg:province":"TN",
    "sg:tags":[
        "car",
        "dealer"
    ],
    "sg:website":"www.rwchev-pont.com",
    "wof:name":"Ronnie Williams Chevrolet-Pont",
    "wof:placetype":"venue"
},
  "geometry": {"coordinates":[-84.461249,35.60666],"type":"Point"}
}