{
  "type": "Feature",
  "properties": {
    "iso:country":"US",
    "sg:address":"3288 Ball Rd",
    "sg:city":"Cunningham",
    "sg:classifiers":[
        {
            "category":"Farming",
            "subcategory":"Livestock Farm",
            "type":"Manufacturing & Wholesale Goods"
        }
    ],
    "sg:phone":"+1 931 387 2007",
    "sg:postcode":"37052",
    "sg:province":"TN",
    "sg:tags":[
        "beef",
        "feedlot",
        "cattle"
    ],
    "wof:name":"O Smithson",
    "wof:placetype":"venue"
},
  "geometry": {"coordinates":[-87.37819500000001,36.423611],"type":"Point"}
}