{
  "type": "Feature",
  "properties": {
    "addr:full":"606 Belvoir Ave Chattanooga TN 37412",
    "addr:housenumber":"606",
    "addr:postcode":"37412",
    "addr:street":"Belvoir Ave",
    "iso:country":"US",
    "sg:address":"606 Belvoir Ave",
    "sg:city":"Chattanooga",
    "sg:classifiers":[
        {
            "category":"Organizations",
            "subcategory":"Religious Organization",
            "type":"Services"
        }
    ],
    "sg:phone":"+1 423 622 8233",
    "sg:postcode":"37412",
    "sg:province":"TN",
    "wof:name":"Renewed Eagle Love Ministry",
    "wof:placetype":"venue"
},
  "geometry": {"coordinates":[-85.24466099999999,35.009584],"type":"Point"}
}