{
  "type": "Feature",
  "properties": {
    "iso:country":"US",
    "sg:address":"4228 Eastwind Dr",
    "sg:city":"Memphis",
    "sg:classifiers":[
        {
            "category":"Food & Beverages",
            "subcategory":"Groceries & Convenience Stores",
            "type":"Retail Goods"
        }
    ],
    "sg:phone":"+1 901 332 4424",
    "sg:postcode":"38116",
    "sg:province":"TN",
    "sg:tags":[
        "grocer"
    ],
    "wof:name":"Joseph's Drive In Grocery",
    "wof:placetype":"venue"
},
  "geometry": {"coordinates":[-90.01726499999999,35.03349],"type":"Point"}
}