{
  "type": "Feature",
  "properties": {
    "iso:country":"US",
    "sg:address":"605 Merritt Ave",
    "sg:city":"Nashville",
    "sg:classifiers":[
        {
            "category":"Manufacturing",
            "subcategory":"Building Materials",
            "type":"Manufacturing & Wholesale Goods"
        }
    ],
    "sg:phone":"+1 615 259 8111",
    "sg:postcode":"37203",
    "sg:province":"TN",
    "wof:name":"Xelica",
    "wof:placetype":"venue"
},
  "geometry": {"coordinates":[-86.771212,36.139865],"type":"Point"}
}