{
  "type": "Feature",
  "properties": {
    "iso:country":"US",
    "sg:address":"520 Heather Pl",
    "sg:city":"Nashville",
    "sg:classifiers":[
        {
            "category":"Manufacturing",
            "subcategory":"Printing",
            "type":"Manufacturing & Wholesale Goods"
        }
    ],
    "sg:phone":"+1 615 297 3134",
    "sg:postcode":"37204",
    "sg:province":"TN",
    "sg:tags":[
        "publisher",
        "music"
    ],
    "wof:name":"Bursen Music Group Inc",
    "wof:placetype":"venue"
},
  "geometry": {"coordinates":[-86.764822,36.113079],"type":"Point"}
}