{
  "type": "Feature",
  "properties": {
    "iso:country":"US",
    "sg:address":"350 Browder St",
    "sg:city":"Fulton",
    "sg:classifiers":[
        {
            "category":"Building & Trades",
            "subcategory":"Construction",
            "type":"Services"
        }
    ],
    "sg:phone":"+1 270 472 3674",
    "sg:postcode":"42041",
    "sg:province":"TN",
    "sg:tags":[
        "home",
        "builder"
    ],
    "wof:name":"Ky Home Place",
    "wof:placetype":"venue"
},
  "geometry": {"coordinates":[-88.875686,36.509876],"type":"Point"}
}