{
  "type": "Feature",
  "properties": {
    "iso:country":"US",
    "sg:address":"1797 Knob Creek Rd",
    "sg:city":"Columbia",
    "sg:classifiers":[
        {
            "category":"Manufacturing",
            "subcategory":"Tools & Machinery",
            "type":"Manufacturing & Wholesale Goods"
        }
    ],
    "sg:phone":"+1 931 381 4599",
    "sg:postcode":"38401",
    "sg:province":"TN",
    "sg:tags":[
        "industrial",
        "mfg"
    ],
    "wof:name":"Southgate Machine Co Inc",
    "wof:placetype":"venue"
},
  "geometry": {"coordinates":[-87.08309300000001,35.688363],"type":"Point"}
}