{
  "type": "Feature",
  "properties": {
    "addr:full":"20150 Alberta St Oneida TN 37841",
    "addr:housenumber":"20150",
    "addr:postcode":"37841",
    "addr:street":"Alberta St",
    "iso:country":"US",
    "sg:address":"20150 Alberta St",
    "sg:city":"Oneida",
    "sg:classifiers":[
        {
            "category":"Autos & Motor Vehicles",
            "subcategory":"Automobile Sales",
            "type":"Retail Goods"
        }
    ],
    "sg:phone":"+1 423 569 5577",
    "sg:postcode":"37841",
    "sg:province":"TN",
    "sg:tags":[
        "car",
        "dealer"
    ],
    "wof:name":"Scott County Auto Sales",
    "wof:placetype":"venue"
},
  "geometry": {"coordinates":[-84.496826,36.524692],"type":"Point"}
}