{
  "type": "Feature",
  "properties": {
    "iso:country":"US",
    "sg:address":"205 S Mount Pleasant Rd",
    "sg:city":"Collierville",
    "sg:classifiers":[
        {
            "category":"Building & Trades",
            "subcategory":"Construction",
            "type":"Services"
        }
    ],
    "sg:phone":"+1 901 365 7711",
    "sg:postcode":"38017",
    "sg:province":"TN",
    "sg:tags":[
        "home",
        "builder"
    ],
    "wof:name":"Robert J Denley Co",
    "wof:placetype":"venue"
},
  "geometry": {"coordinates":[-89.66076200000001,35.038999],"type":"Point"}
}