{
  "type": "Feature",
  "properties": {
    "iso:country":"US",
    "sg:address":"1439 N Broad St",
    "sg:city":"Tazewell",
    "sg:classifiers":[
        {
            "category":"Retail",
            "subcategory":"Auto Repair",
            "type":"Services"
        }
    ],
    "sg:phone":"+1 423 626 8200",
    "sg:postcode":"37879",
    "sg:province":"TN",
    "sg:tags":[
        "general"
    ],
    "wof:name":"MOR Automotive",
    "wof:placetype":"venue"
},
  "geometry": {"coordinates":[-83.57301099999999,36.447966],"type":"Point"}
}