{
  "type": "Feature",
  "properties": {
    "iso:country":"US",
    "sg:address":"700 Nuckolls Rd",
    "sg:city":"Bolivar",
    "sg:classifiers":[
        {
            "category":"Health Services",
            "subcategory":"Nursing And Care Facility",
            "type":"Services"
        }
    ],
    "sg:phone":"+1 731 658 4707",
    "sg:postcode":"38008",
    "sg:province":"TN",
    "sg:tags":[
        "home",
        "convalescent"
    ],
    "wof:name":"Pine Meadows Healthcare Ctr",
    "wof:placetype":"venue"
},
  "geometry": {"coordinates":[-89.000457,35.269421],"type":"Point"}
}