{
  "type": "Feature",
  "properties": {
    "iso:country":"US",
    "sg:address":"332 Jacksonian Dr",
    "sg:city":"Hermitage",
    "sg:classifiers":[
        {
            "category":"Retail",
            "subcategory":"Repair Shop",
            "type":"Services"
        }
    ],
    "sg:phone":"+1 615 406 1028",
    "sg:postcode":"37076",
    "sg:province":"TN",
    "sg:tags":[
        "welding"
    ],
    "wof:name":"Excel Die Cutting Svc",
    "wof:placetype":"venue"
},
  "geometry": {"coordinates":[-86.623937,36.192858],"type":"Point"}
}