{
  "type": "Feature",
  "properties": {
    "iso:country":"US",
    "sg:address":"387 Jeanne Dr",
    "sg:city":"Memphis",
    "sg:classifiers":[
        {
            "category":"Organizations",
            "subcategory":"Religious Organization",
            "type":"Services"
        }
    ],
    "sg:phone":"+1 901 398 6304",
    "sg:postcode":"38109",
    "sg:province":"TN",
    "sg:tags":[
        "church"
    ],
    "wof:name":"Jeanne Drive Church Of Christ",
    "wof:placetype":"venue"
},
  "geometry": {"coordinates":[-90.05102599999999,35.037973],"type":"Point"}
}