{
  "type": "Feature",
  "properties": {
    "iso:country":"US",
    "sg:address":"1150 Mineral Wells Ave",
    "sg:city":"Paris",
    "sg:classifiers":[
        {
            "category":"Shopping",
            "subcategory":"Shoes",
            "type":"Retail Goods"
        }
    ],
    "sg:phone":"+1 731 642 6931",
    "sg:postcode":"38242",
    "sg:province":"TN",
    "wof:name":"Shoe Show 507",
    "wof:placetype":"venue"
},
  "geometry": {"coordinates":[-88.308273,36.284378],"type":"Point"}
}