{
  "type": "Feature",
  "properties": {
    "addr:full":"4770 Linda Ln Memphis TN 38117",
    "addr:housenumber":"4770",
    "addr:postcode":"38117",
    "addr:street":"Linda Ln",
    "iso:country":"US",
    "sg:address":"4770 Linda Ln",
    "sg:city":"Memphis",
    "sg:classifiers":[
        {
            "category":"Building & Trades",
            "subcategory":"Construction",
            "type":"Services"
        }
    ],
    "sg:phone":"+1 901 458 7746",
    "sg:postcode":"38117",
    "sg:province":"TN",
    "sg:tags":[
        "resurfacing",
        "laying",
        "refinishing",
        "floor"
    ],
    "wof:name":"Classic Hardwood Floors",
    "wof:placetype":"venue"
},
  "geometry": {"coordinates":[-89.903497,35.136303],"type":"Point"}
}