{
  "type": "Feature",
  "properties": {
    "iso:country":"US",
    "sg:address":"1203 Venido Dr",
    "sg:city":"Knoxville",
    "sg:classifiers":[
        {
            "category":"Professional",
            "type":"Services"
        }
    ],
    "sg:phone":"+1 865 671 1635",
    "sg:postcode":"37932",
    "sg:province":"TN",
    "wof:name":"Fidelity Franchise Services",
    "wof:placetype":"venue"
},
  "geometry": {"coordinates":[-84.146642,35.92492],"type":"Point"}
}