{
  "type": "Feature",
  "properties": {
    "iso:country":"US",
    "sg:address":"731 Mc Ferrin Ave",
    "sg:city":"Nashville",
    "sg:classifiers":[
        {
            "category":"Social Services",
            "type":"Services"
        }
    ],
    "sg:phone":"+1 615 227 0745",
    "sg:postcode":"37206",
    "sg:province":"TN",
    "wof:name":"TS Learning Center",
    "wof:placetype":"venue"
},
  "geometry": {"coordinates":[-86.75452,36.184317],"type":"Point"}
}