{
  "type": "Feature",
  "properties": {
    "addr:full":"711 Gallatin Ave Nashville TN 37206",
    "addr:housenumber":"711",
    "addr:postcode":"37206",
    "addr:street":"Gallatin Ave",
    "iso:country":"US",
    "sg:address":"711 Gallatin Ave",
    "sg:city":"Nashville",
    "sg:classifiers":[
        {
            "category":"Food & Beverages",
            "subcategory":"Groceries & Convenience Stores",
            "type":"Retail Goods"
        }
    ],
    "sg:phone":"+1 615 226 6880",
    "sg:postcode":"37206",
    "sg:province":"TN",
    "sg:tags":[
        "grocer"
    ],
    "wof:name":"Kroger",
    "wof:placetype":"venue"
},
  "geometry": {"coordinates":[-86.748149,36.184051],"type":"Point"}
}