{
  "type": "Feature",
  "properties": {
    "addr:full":"4148 Ringgold Rd Chattanooga TN 37412",
    "addr:housenumber":"4148",
    "addr:postcode":"37412",
    "addr:street":"Ringgold Rd",
    "iso:country":"US",
    "sg:address":"4148 Ringgold Rd",
    "sg:city":"Chattanooga",
    "sg:classifiers":[
        {
            "category":"Personal",
            "subcategory":"Beauty Salon",
            "type":"Services"
        }
    ],
    "sg:phone":"+1 423 698 6622",
    "sg:postcode":"37412",
    "sg:province":"TN",
    "sg:tags":[
        "shop"
    ],
    "wof:name":"Buddys Hair Force",
    "wof:placetype":"venue"
},
  "geometry": {"coordinates":[-85.24448599999999,34.997397],"type":"Point"}
}