{
  "type": "Feature",
  "properties": {
    "iso:country":"US",
    "sg:address":"232 Newcastle Dr",
    "sg:city":"Murfreesboro",
    "sg:classifiers":[
        {
            "category":"Building & Trades",
            "subcategory":"Construction",
            "type":"Services"
        }
    ],
    "sg:phone":"+1 615 893 1056",
    "sg:postcode":"37129",
    "sg:province":"TN",
    "sg:tags":[
        "contractor"
    ],
    "wof:name":"Alvin Rigsby",
    "wof:placetype":"venue"
},
  "geometry": {"coordinates":[-86.387788,35.888811],"type":"Point"}
}