{
  "type": "Feature",
  "properties": {
    "addr:full":"875 River Village Ln Afton TN 37616",
    "addr:housenumber":"875",
    "addr:postcode":"37616",
    "addr:street":"River Village Ln",
    "iso:country":"US",
    "sg:address":"875 River Village Ln",
    "sg:city":"Afton",
    "sg:classifiers":[
        {
            "category":"Building & Trades",
            "subcategory":"Construction",
            "type":"Services"
        }
    ],
    "sg:phone":"+1 423 798 0218",
    "sg:postcode":"37616",
    "sg:province":"TN",
    "sg:tags":[
        "contractor"
    ],
    "wof:name":"Metal Roofing Specialists",
    "wof:placetype":"venue"
},
  "geometry": {"coordinates":[-82.698769,36.187726],"type":"Point"}
}