{
  "type": "Feature",
  "properties": {
    "iso:country":"US",
    "sg:address":"418 Wanda Dr",
    "sg:city":"Nashville",
    "sg:classifiers":[
        {
            "category":"Manufacturing",
            "subcategory":"Glass & Minerals",
            "type":"Manufacturing & Wholesale Goods"
        }
    ],
    "sg:phone":"+1 615 889 6956",
    "sg:postcode":"37214",
    "sg:province":"TN",
    "sg:tags":[
        "product",
        "nonmetallic",
        "mfg"
    ],
    "wof:name":"Academy Arts",
    "wof:placetype":"venue"
},
  "geometry": {"coordinates":[-86.689981,36.157886],"type":"Point"}
}