{
  "type": "Feature",
  "properties": {
    "addr:full":"119 Dyer St Columbia TN 38401",
    "addr:housenumber":"119",
    "addr:postcode":"38401",
    "addr:street":"Dyer St",
    "iso:country":"US",
    "sg:address":"119 Dyer St",
    "sg:city":"Columbia",
    "sg:classifiers":[
        {
            "category":"Manufacturing",
            "subcategory":"Metals",
            "type":"Manufacturing & Wholesale Goods"
        }
    ],
    "sg:phone":"+1 931 381 0856",
    "sg:postcode":"38401",
    "sg:province":"TN",
    "sg:tags":[
        "coating"
    ],
    "wof:name":"Total Customs & Coatings",
    "wof:placetype":"venue"
},
  "geometry": {"coordinates":[-87.038324,35.590076],"type":"Point"}
}