{
  "type": "Feature",
  "properties": {
    "iso:country":"US",
    "sg:address":"1340 Oregon Trl",
    "sg:city":"Greeneville",
    "sg:classifiers":[
        {
            "category":"Insurance",
            "subcategory":"Insurance Agent",
            "type":"Services"
        }
    ],
    "sg:phone":"+1 423 638 4300",
    "sg:postcode":"37743",
    "sg:province":"TN",
    "wof:name":"Andrew Johnson Agency",
    "wof:placetype":"venue"
},
  "geometry": {"coordinates":[-82.924645,36.12424],"type":"Point"}
}