{
  "type": "Feature",
  "properties": {
    "iso:country":"US",
    "sg:address":"911 Westside Ct",
    "sg:city":"Murfreesboro",
    "sg:classifiers":[
        {
            "category":"Organizations",
            "subcategory":"Community Association",
            "type":"Services"
        }
    ],
    "sg:phone":"+1 615 849 8200",
    "sg:postcode":"37130",
    "sg:province":"TN",
    "sg:tags":[
        "club"
    ],
    "wof:name":"Middle Tennessee Lions Sight",
    "wof:placetype":"venue"
},
  "geometry": {"coordinates":[-86.38047400000001,35.831522],"type":"Point"}
}