{
  "type": "Feature",
  "properties": {
    "addr:full":"504 Arlington Ave Nashville TN 37210",
    "addr:housenumber":"504",
    "addr:postcode":"37210",
    "addr:street":"Arlington Ave",
    "iso:country":"US",
    "sg:address":"504 Arlington Ave",
    "sg:city":"Nashville",
    "sg:classifiers":[
        {
            "category":"Building & Trades",
            "subcategory":"Construction",
            "type":"Services"
        }
    ],
    "sg:phone":"+1 615 742 5551",
    "sg:postcode":"37210",
    "sg:province":"TN",
    "sg:tags":[
        "floor",
        "laying",
        "contractor"
    ],
    "wof:name":"Color Court Surfacing Systems",
    "wof:placetype":"venue"
},
  "geometry": {"coordinates":[-86.730451,36.143757],"type":"Point"}
}