{
  "type": "Feature",
  "properties": {
    "iso:country":"US",
    "sg:address":"7275 Erwin Hwy",
    "sg:city":"Chuckey",
    "sg:classifiers":[
        {
            "category":"Organizations",
            "subcategory":"Religious Organization",
            "type":"Services"
        }
    ],
    "sg:phone":"+1 423 257 3193",
    "sg:postcode":"37641",
    "sg:province":"TN",
    "wof:name":"Ceder Grove Untd Mthdst Church",
    "wof:placetype":"venue"
},
  "geometry": {"coordinates":[-82.662702,36.148624],"type":"Point"}
}