{
  "type": "Feature",
  "properties": {
    "iso:country":"US",
    "sg:address":"2035 Hines Creek Rd",
    "sg:city":"Heiskell",
    "sg:classifiers":[
        {
            "category":"Retail",
            "subcategory":"Auto Repair",
            "type":"Services"
        }
    ],
    "sg:phone":"+1 865 494 7891",
    "sg:postcode":"37754",
    "sg:province":"TN",
    "sg:tags":[
        "transmission"
    ],
    "wof:name":"Team Transmissions and Repairs",
    "wof:placetype":"venue"
},
  "geometry": {"coordinates":[-83.96808,36.178495],"type":"Point"}
}