{
  "type": "Feature",
  "properties": {
    "iso:country":"US",
    "sg:address":"3024 Covington Pike",
    "sg:city":"Memphis",
    "sg:classifiers":[
        {
            "category":"Banks & Credit Unions",
            "subcategory":"Bank",
            "type":"Services"
        }
    ],
    "sg:phone":"+1 901 383 9080",
    "sg:postcode":"38128",
    "sg:province":"TN",
    "sg:tags":[
        "using",
        "loan",
        "temporary",
        "paycheck"
    ],
    "wof:name":"Cash Quick Inc",
    "wof:placetype":"venue"
},
  "geometry": {"coordinates":[-89.894504,35.207961],"type":"Point"}
}