{
  "type": "Feature",
  "properties": {
    "addr:full":"5049 Summer Ave Memphis TN 38122",
    "addr:housenumber":"5049",
    "addr:postcode":"38122",
    "addr:street":"Summer Ave",
    "iso:country":"US",
    "sg:address":"5049 Summer Ave",
    "sg:city":"Memphis",
    "sg:classifiers":[
        {
            "category":"Banks & Credit Unions",
            "subcategory":"Bank",
            "type":"Services"
        },
        {
            "category":"Banks & Credit Unions",
            "subcategory":"Financial Services",
            "type":"Services"
        }
    ],
    "sg:phone":"+1 901 762 4360",
    "sg:postcode":"38122",
    "sg:province":"TN",
    "sg:tags":[
        "loan",
        "financing"
    ],
    "sg:website":"http://www.SunTrust.com",
    "wof:name":"SunTrust Bank - Cloverleaf",
    "wof:placetype":"venue"
},
  "geometry": {"coordinates":[-89.892262,35.150277],"type":"Point"}
}