{
  "type": "Feature",
  "properties": {
    "iso:country":"US",
    "sg:address":"3245 Trewhitt Rd SE",
    "sg:city":"Cleveland",
    "sg:classifiers":[
        {
            "category":"Freight",
            "type":"Transportation"
        }
    ],
    "sg:phone":"+1 423 476 5307",
    "sg:postcode":"37323",
    "sg:province":"TN",
    "sg:tags":[
        "operator",
        "local",
        "trucking"
    ],
    "wof:name":"Perry Backhoe Trucking",
    "wof:placetype":"venue"
},
  "geometry": {"coordinates":[-84.855148,35.116939],"type":"Point"}
}