{
  "type": "Feature",
  "properties": {
    "iso:country":"US",
    "sg:address":"4023 Billion Rd",
    "sg:city":"Memphis",
    "sg:classifiers":[
        {
            "category":"Personal",
            "type":"Services"
        }
    ],
    "sg:phone":"+1 901 354 0940",
    "sg:postcode":"38127",
    "sg:province":"TN",
    "sg:tags":[
        "towing"
    ],
    "wof:name":"Culp & Sons Towing",
    "wof:placetype":"venue"
},
  "geometry": {"coordinates":[-90.05750399999999,35.233853],"type":"Point"}
}