{
  "type": "Feature",
  "properties": {
    "addr:full":"802 3rd Ave S Nashville TN 37210",
    "addr:housenumber":"802",
    "addr:postcode":"37210",
    "addr:street":"3Rd Ave S",
    "iso:country":"US",
    "sg:address":"802 3rd Ave S",
    "sg:city":"Nashville",
    "sg:classifiers":[
        {
            "category":"Shopping",
            "subcategory":"Discount & Variety Stores",
            "type":"Retail Goods"
        }
    ],
    "sg:phone":"+1 615 256 7321",
    "sg:postcode":"37210",
    "sg:province":"TN",
    "wof:name":"Friedmans Army-Navy Store",
    "wof:placetype":"venue"
},
  "geometry": {"coordinates":[-86.769955,36.152021],"type":"Point"}
}