{
  "type": "Feature",
  "properties": {
    "addr:full":"118 N Walnut St Murfreesboro TN 37130",
    "addr:housenumber":"118",
    "addr:postcode":"37130",
    "addr:street":"N Walnut St",
    "iso:country":"US",
    "sg:address":"118 N Walnut St",
    "sg:city":"Murfreesboro",
    "sg:classifiers":[
        {
            "category":"Manufacturing",
            "subcategory":"Glass & Minerals",
            "type":"Manufacturing & Wholesale Goods"
        }
    ],
    "sg:phone":"+1 615 890 6344",
    "sg:postcode":"37130",
    "sg:province":"TN",
    "sg:tags":[
        "product",
        "nonmetallic",
        "mfg"
    ],
    "wof:name":"Wholesale Tops Inc",
    "wof:placetype":"venue"
},
  "geometry": {"coordinates":[-86.39366800000001,35.847062],"type":"Point"}
}