{
  "type": "Feature",
  "properties": {
    "iso:country":"US",
    "sg:address":"6645 Poplar Ave",
    "sg:city":"Germantown",
    "sg:classifiers":[
        {
            "category":"Professional",
            "subcategory":"Business Services",
            "type":"Services"
        }
    ],
    "sg:phone":"+1 901 753 0010",
    "sg:postcode":"38138",
    "sg:province":"TN",
    "sg:tags":[
        "interior",
        "consultant",
        "design",
        "decorator"
    ],
    "wof:name":"Designer Services",
    "wof:placetype":"venue"
},
  "geometry": {"coordinates":[-89.84154100000001,35.098527],"type":"Point"}
}