{
  "type": "Feature",
  "properties": {
    "iso:country":"US",
    "sg:address":"22 N Front St",
    "sg:city":"Memphis",
    "sg:classifiers":[
        {
            "category":"Organizations",
            "subcategory":"Non-profit Organization",
            "type":"Services"
        }
    ],
    "sg:phone":"+1 901 322 8080",
    "sg:postcode":"38103",
    "sg:province":"TN",
    "wof:name":"Memphis Tommorrow Inc",
    "wof:placetype":"venue"
},
  "geometry": {"coordinates":[-90.05371599999999,35.14656],"type":"Point"}
}