{
  "type": "Feature",
  "properties": {
    "iso:country":"US",
    "sg:address":"5238 Memorial Blvd",
    "sg:city":"Kingsport",
    "sg:classifiers":[
        {
            "category":"Building & Trades",
            "subcategory":"Construction",
            "type":"Services"
        },
        {
            "category":"Home & Garden",
            "subcategory":"Furniture",
            "type":"Retail Goods"
        }
    ],
    "sg:phone":"+1 423 323 9899",
    "sg:postcode":"37664",
    "sg:province":"TN",
    "sg:tags":[
        "top",
        "counter",
        "contractor"
    ],
    "sg:website":"www.thetop.net",
    "wof:name":"Art-Tech Surfacing Corp",
    "wof:placetype":"venue"
},
  "geometry": {"coordinates":[-82.44228,36.550097],"type":"Point"}
}