{
  "type": "Feature",
  "properties": {
    "addr:full":"5430 S Lamont Rd Springfield TN 37172",
    "addr:housenumber":"5430",
    "addr:postcode":"37172",
    "addr:street":"S Lamont Rd",
    "iso:country":"US",
    "sg:address":"5430 S Lamont Rd",
    "sg:city":"Springfield",
    "sg:classifiers":[
        {
            "category":"Farming",
            "subcategory":"Nursery",
            "type":"Manufacturing & Wholesale Goods"
        }
    ],
    "sg:phone":"+1 615 654 4851",
    "sg:postcode":"37172",
    "sg:province":"TN",
    "sg:tags":[
        "tropical"
    ],
    "wof:name":"L&M Greenhouse",
    "wof:placetype":"venue"
},
  "geometry": {"coordinates":[-86.76502000000001,36.599049],"type":"Point"}
}