{
  "type": "Feature",
  "properties": {
    "iso:country":"US",
    "sg:address":"170 E Main St",
    "sg:city":"Hendersonville",
    "sg:classifiers":[
        {
            "category":"Personal",
            "subcategory":"Barber",
            "type":"Services"
        }
    ],
    "sg:phone":"+1 615 826 1555",
    "sg:postcode":"37075",
    "sg:province":"TN",
    "sg:website":"www.greatclips.com",
    "wof:name":"Great Clips",
    "wof:placetype":"venue"
},
  "geometry": {"coordinates":[-86.606112,36.307665],"type":"Point"}
}