{
  "type": "Feature",
  "properties": {
    "addr:full":"855 Jenkinsville-Jamestown Rd Dyersburg TN 38024",
    "addr:housenumber":"855",
    "addr:postcode":"38024",
    "addr:street":"Jenkinsville-Jamestown Rd",
    "iso:country":"US",
    "sg:address":"855 Jenkinsville-Jamestown Rd",
    "sg:city":"Dyersburg",
    "sg:classifiers":[
        {
            "category":"Building & Trades",
            "subcategory":"Construction",
            "type":"Services"
        }
    ],
    "sg:phone":"+1 731 286 0256",
    "sg:postcode":"38024",
    "sg:province":"TN",
    "sg:tags":[
        "home",
        "improvement"
    ],
    "wof:name":"Benthal Construction",
    "wof:placetype":"venue"
},
  "geometry": {"coordinates":[-89.416152,36.055844],"type":"Point"}
}