{
  "type": "Feature",
  "properties": {
    "addr:full":"616 Cavendish Ct Antioch TN 37013",
    "addr:housenumber":"616",
    "addr:postcode":"37013",
    "addr:street":"Cavendish Ct",
    "iso:country":"US",
    "sg:address":"616 Cavendish Ct",
    "sg:city":"Antioch",
    "sg:classifiers":[
        {
            "category":"Communications",
            "subcategory":"Radio Station",
            "type":"Services"
        }
    ],
    "sg:phone":"+1 615 365 3934",
    "sg:postcode":"37013",
    "sg:province":"TN",
    "sg:tags":[
        "broadcast"
    ],
    "wof:name":"Salem Radio Representatives I",
    "wof:placetype":"venue"
},
  "geometry": {"coordinates":[-86.665701,36.077478],"type":"Point"}
}