{
  "type": "Feature",
  "properties": {
    "iso:country":"US",
    "sg:address":"621 S Cumberland St",
    "sg:city":"Lebanon",
    "sg:classifiers":[
        {
            "category":"Shopping",
            "type":"Retail Goods"
        }
    ],
    "sg:phone":"+1 615 443 3183",
    "sg:postcode":"37087",
    "sg:province":"TN",
    "sg:tags":[
        "cosmetic",
        "perfume"
    ],
    "wof:name":"Sally Beauty Supply",
    "wof:placetype":"venue"
},
  "geometry": {"coordinates":[-86.29456399999999,36.191644],"type":"Point"}
}