{
  "type": "Feature",
  "properties": {
    "iso:country":"US",
    "sg:address":"2955 Pine Haven Dr",
    "sg:city":"Sevierville",
    "sg:classifiers":[
        {
            "category":"Real Estate",
            "subcategory":"Real Estate Agent",
            "type":"Services"
        }
    ],
    "sg:phone":"+1 865 774 0164",
    "sg:postcode":"37862",
    "sg:province":"TN",
    "wof:name":"Smokey Mountain Properties",
    "wof:placetype":"venue"
},
  "geometry": {"coordinates":[-83.609263,35.799113],"type":"Point"}
}