{
  "type": "Feature",
  "properties": {
    "iso:country":"US",
    "sg:address":"9501 William Little Dr",
    "sg:city":"Arlington",
    "sg:classifiers":[
        {
            "category":"Freight",
            "type":"Transportation"
        }
    ],
    "sg:phone":"+1 901 379 0151",
    "sg:postcode":"38002",
    "sg:province":"TN",
    "sg:tags":[
        "operator",
        "trucking"
    ],
    "wof:name":"Quinn Cargo Carriers Inc",
    "wof:placetype":"venue"
},
  "geometry": {"coordinates":[-89.746292,35.235625],"type":"Point"}
}