{
  "type": "Feature",
  "properties": {
    "addr:full":"221 S 2nd St Clarksville TN 37040",
    "addr:housenumber":"221",
    "addr:postcode":"37040",
    "addr:street":"S 2Nd St",
    "iso:country":"US",
    "sg:address":"221 S 2nd St",
    "sg:city":"Clarksville",
    "sg:classifiers":[
        {
            "category":"Professional",
            "subcategory":"Business Services",
            "type":"Services"
        }
    ],
    "sg:phone":"+1 931 321 0202",
    "sg:postcode":"37040",
    "sg:province":"TN",
    "wof:name":"Nan Shelby Calloway",
    "wof:placetype":"venue"
},
  "geometry": {"coordinates":[-87.358053,36.525852],"type":"Point"}
}