{
  "type": "Feature",
  "properties": {
    "addr:full":"5817 Northwoods Dr Hixson TN 37343",
    "addr:housenumber":"5817",
    "addr:postcode":"37343",
    "addr:street":"Northwoods Dr",
    "iso:country":"US",
    "sg:address":"5817 Northwoods Dr",
    "sg:city":"Hixson",
    "sg:classifiers":[
        {
            "category":"Organizations",
            "subcategory":"Professional Association",
            "type":"Services"
        }
    ],
    "sg:phone":"+1 423 870 3090",
    "sg:postcode":"37343",
    "sg:province":"TN",
    "wof:name":"Arthritis Foundation",
    "wof:placetype":"venue"
},
  "geometry": {"coordinates":[-85.253551,35.15545],"type":"Point"}
}