{
  "type": "Feature",
  "properties": {
    "addr:full":"167 N Lowry St Smyrna TN 37167",
    "addr:housenumber":"167",
    "addr:postcode":"37167",
    "addr:street":"N Lowry St",
    "iso:country":"US",
    "sg:address":"167 N Lowry St",
    "sg:city":"Smyrna",
    "sg:classifiers":[
        {
            "category":"Personal",
            "subcategory":"Beauty Salon",
            "type":"Services"
        }
    ],
    "sg:phone":"+1 615 355 4520",
    "sg:postcode":"37167",
    "sg:province":"TN",
    "wof:name":"Salon De Belleza",
    "wof:placetype":"venue"
},
  "geometry": {"coordinates":[-86.520366,35.98417],"type":"Point"}
}