{
  "type": "Feature",
  "properties": {
    "iso:country":"US",
    "sg:address":"901 Pardee St",
    "sg:city":"Johnson City",
    "sg:classifiers":[
        {
            "category":"Real Estate",
            "subcategory":"Real Estate Agent",
            "type":"Services"
        }
    ],
    "sg:phone":"+1 423 232 4784",
    "sg:postcode":"37601",
    "sg:province":"TN",
    "sg:tags":[
        "authorities",
        "housing"
    ],
    "wof:name":"Johnson City Housing Authority",
    "wof:placetype":"venue"
},
  "geometry": {"coordinates":[-82.334484,36.323143],"type":"Point"}
}