{
  "type": "Feature",
  "properties": {
    "addr:full":"3084 Village Shops Dr Germantown TN 38138",
    "addr:housenumber":"3084",
    "addr:postcode":"38138",
    "addr:street":"Village Shops Dr",
    "iso:country":"US",
    "sg:address":"3084 Village Shops Dr",
    "sg:city":"Germantown",
    "sg:classifiers":[
        {
            "category":"Home & Garden",
            "subcategory":"Household Appliances",
            "type":"Retail Goods"
        }
    ],
    "sg:phone":"+1 901 624 0774",
    "sg:postcode":"38138",
    "sg:province":"TN",
    "sg:tags":[
        "cleaners",
        "vacuum"
    ],
    "sg:website":"www.oreck.com",
    "wof:name":"Oreck",
    "wof:placetype":"venue"
},
  "geometry": {"coordinates":[-89.756951,35.065257],"type":"Point"}
}