{
  "type": "Feature",
  "properties": {
    "addr:full":"2707 Kanasita Dr Hixson TN 37343",
    "addr:housenumber":"2707",
    "addr:postcode":"37343",
    "addr:street":"Kanasita Dr",
    "iso:country":"US",
    "sg:address":"2707 Kanasita Dr",
    "sg:city":"Hixson",
    "sg:classifiers":[
        {
            "category":"Building & Trades",
            "subcategory":"Construction",
            "type":"Services"
        },
        {
            "category":"Home & Garden",
            "subcategory":"Furniture",
            "type":"Retail Goods"
        }
    ],
    "sg:phone":"+1 423 876 0299",
    "sg:postcode":"37343",
    "sg:province":"TN",
    "sg:tags":[
        "top",
        "counter",
        "contractor"
    ],
    "wof:name":"Rocky Tops Custom Countertops",
    "wof:placetype":"venue"
},
  "geometry": {"coordinates":[-85.228797,35.13379],"type":"Point"}
}