{
  "type": "Feature",
  "properties": {
    "iso:country":"US",
    "sg:address":"7074 Johnsons Grove Rd",
    "sg:city":"Alamo",
    "sg:classifiers":[
        {
            "category":"Organizations",
            "subcategory":"Religious Organization",
            "type":"Services"
        }
    ],
    "sg:phone":"+1 731 656 4249",
    "sg:postcode":"38001",
    "sg:province":"TN",
    "wof:name":"Prayer Of Faith",
    "wof:placetype":"venue"
},
  "geometry": {"coordinates":[-89.204043,35.768126],"type":"Point"}
}