{
  "type": "Feature",
  "properties": {
    "addr:full":"7141 Periwinkle Rd Knoxville TN 37918",
    "addr:housenumber":"7141",
    "addr:postcode":"37918",
    "addr:street":"Periwinkle Rd",
    "iso:country":"US",
    "sg:address":"7141 Periwinkle Rd",
    "sg:city":"Knoxville",
    "sg:classifiers":[
        {
            "category":"Professional",
            "type":"Services"
        }
    ],
    "sg:phone":"+1 865 922 3788",
    "sg:postcode":"37918",
    "sg:province":"TN",
    "wof:name":"Nationwide Hope Centers",
    "wof:placetype":"venue"
},
  "geometry": {"coordinates":[-83.904931,36.081944],"type":"Point"}
}