{
  "type": "Feature",
  "properties": {
    "iso:country":"US",
    "sg:address":"500 Hospital Dr",
    "sg:city":"Madison",
    "sg:classifiers":[
        {
            "category":"Professional",
            "subcategory":"Management & Consulting",
            "type":"Services"
        }
    ],
    "sg:phone":"+1 615 865 0300",
    "sg:postcode":"37115",
    "sg:province":"TN",
    "sg:tags":[
        "physician"
    ],
    "wof:name":"Florida Physicians Med Group",
    "wof:placetype":"venue"
},
  "geometry": {"coordinates":[-86.684421,36.254085],"type":"Point"}
}