{
  "type": "Feature",
  "properties": {
    "iso:country":"US",
    "sg:address":"4291 Highway 58",
    "sg:city":"Chattanooga",
    "sg:classifiers":[
        {
            "category":"Professional",
            "subcategory":"Employment Agencies",
            "type":"Services"
        }
    ],
    "sg:phone":"+1 423 894 1500",
    "sg:postcode":"37416",
    "sg:province":"TN",
    "sg:tags":[
        "opportunity"
    ],
    "sg:website":"http://www.willstaff.net",
    "wof:name":"Willstaff Worldwide",
    "wof:placetype":"venue"
},
  "geometry": {"coordinates":[-85.208794,35.081783],"type":"Point"}
}