{
  "type": "Feature",
  "properties": {
    "iso:country":"US",
    "sg:address":"2393 Lake Rd",
    "sg:city":"Dyersburg",
    "sg:classifiers":[
        {
            "category":"Restaurant",
            "type":"Food & Drink"
        }
    ],
    "sg:phone":"+1 731 286 4711",
    "sg:postcode":"38024",
    "sg:province":"TN",
    "sg:tags":[
        "eating"
    ],
    "wof:name":"China King",
    "wof:placetype":"venue"
},
  "geometry": {"coordinates":[-89.39510199999999,36.059043],"type":"Point"}
}