{
  "type": "Feature",
  "properties": {
    "iso:country":"US",
    "sg:address":"617 Signal Mountain Blvd",
    "sg:city":"Chattanooga",
    "sg:classifiers":[
        {
            "category":"Food & Beverages",
            "subcategory":"Fruits & Vegetables",
            "type":"Retail Goods"
        }
    ],
    "sg:phone":"+1 423 265 8451",
    "sg:postcode":"37405",
    "sg:province":"TN",
    "wof:name":"Ronnies Firewood",
    "wof:placetype":"venue"
},
  "geometry": {"coordinates":[-85.32758699999999,35.097291],"type":"Point"}
}