{
  "type": "Feature",
  "properties": {
    "addr:full":"1301 Myron Cory Dr Hickman TN 42050",
    "addr:housenumber":"1301",
    "addr:postcode":"42050",
    "addr:street":"Myron Cory Dr",
    "iso:country":"US",
    "sg:address":"1301 Myron Cory Dr",
    "sg:city":"Hickman",
    "sg:classifiers":[
        {
            "category":"Farming",
            "subcategory":"Farm",
            "type":"Manufacturing & Wholesale Goods"
        }
    ],
    "sg:phone":"+1 270 236 2663",
    "sg:postcode":"42050",
    "sg:province":"TN",
    "sg:tags":[
        "crop",
        "general"
    ],
    "wof:name":"Henry Sanger",
    "wof:placetype":"venue"
},
  "geometry": {"coordinates":[-89.186832,36.567188],"type":"Point"}
}