{
  "type": "Feature",
  "properties": {
    "addr:full":"2948 Chelsea Ave Memphis TN 38108",
    "addr:housenumber":"2948",
    "addr:postcode":"38108",
    "addr:street":"Chelsea Ave",
    "iso:country":"US",
    "sg:address":"2948 Chelsea Ave",
    "sg:city":"Memphis",
    "sg:classifiers":[
        {
            "category":"Food & Beverages",
            "subcategory":"Groceries & Convenience Stores",
            "type":"Retail Goods"
        }
    ],
    "sg:phone":"+1 901 452 2658",
    "sg:postcode":"38108",
    "sg:province":"TN",
    "sg:tags":[
        "super",
        "supermarket"
    ],
    "wof:name":"Louie & Wu Supermarket",
    "wof:placetype":"venue"
},
  "geometry": {"coordinates":[-89.962096,35.174191],"type":"Point"}
}