{
  "type": "Feature",
  "properties": {
    "iso:country":"US",
    "sg:address":"835 Bell Rd",
    "sg:city":"Antioch",
    "sg:classifiers":[
        {
            "category":"Home & Garden",
            "subcategory":"Furniture",
            "type":"Retail Goods"
        }
    ],
    "sg:phone":"+1 615 731 3390",
    "sg:postcode":"37013",
    "sg:province":"TN",
    "wof:name":"Sofa Express Inc",
    "wof:placetype":"venue"
},
  "geometry": {"coordinates":[-86.64734300000001,36.050699],"type":"Point"}
}