{
  "type": "Feature",
  "properties": {
    "iso:country":"US",
    "sg:address":"2544 S Mount Pleasant Rd",
    "sg:city":"Greenbrier",
    "sg:classifiers":[
        {
            "category":"Wholesale",
            "subcategory":"Apparel",
            "type":"Manufacturing & Wholesale Goods"
        }
    ],
    "sg:phone":"+1 615 643 2539",
    "sg:postcode":"37073",
    "sg:province":"TN",
    "sg:tags":[
        "hosiery"
    ],
    "wof:name":"Sock Depot",
    "wof:placetype":"venue"
},
  "geometry": {"coordinates":[-86.738969,36.435737],"type":"Point"}
}