{
  "type": "Feature",
  "properties": {
    "iso:country":"US",
    "sg:address":"1336 Poplar Ave",
    "sg:city":"Memphis",
    "sg:classifiers":[
        {
            "category":"Food & Beverages",
            "subcategory":"Groceries & Convenience Stores",
            "type":"Retail Goods"
        }
    ],
    "sg:phone":"+1 901 278 5649",
    "sg:postcode":"38104",
    "sg:province":"TN",
    "sg:tags":[
        "market"
    ],
    "wof:name":"Super 1 Market",
    "wof:placetype":"venue"
},
  "geometry": {"coordinates":[-90.016079,35.144076],"type":"Point"}
}