{
  "type": "Feature",
  "properties": {
    "iso:country":"US",
    "sg:address":"1057 N Broadway",
    "sg:city":"Portland",
    "sg:classifiers":[
        {
            "category":"Manufacturing",
            "subcategory":"Tools & Machinery",
            "type":"Manufacturing & Wholesale Goods"
        }
    ],
    "sg:phone":"+1 615 325 3280",
    "sg:postcode":"37148",
    "sg:province":"TN",
    "sg:tags":[
        "industrial",
        "mfg"
    ],
    "wof:name":"Freeman Machine & Tool",
    "wof:placetype":"venue"
},
  "geometry": {"coordinates":[-86.534189,36.60037],"type":"Point"}
}