{
  "type": "Feature",
  "properties": {
    "addr:full":"4600 Hurricane Creek Rd Woodbury TN 37190",
    "addr:housenumber":"4600",
    "addr:postcode":"37190",
    "addr:street":"Hurricane Creek Rd",
    "iso:country":"US",
    "sg:address":"4600 Hurricane Creek Rd",
    "sg:city":"Woodbury",
    "sg:classifiers":[
        {
            "category":"Professional",
            "subcategory":"Lawyer & Legal Services",
            "type":"Services"
        }
    ],
    "sg:phone":"+1 931 424 3180",
    "sg:postcode":"37190",
    "sg:province":"TN",
    "wof:name":"Prepaid Legal Independent",
    "wof:placetype":"venue"
},
  "geometry": {"coordinates":[-86.07419899999999,35.929198],"type":"Point"}
}