{
  "type": "Feature",
  "properties": {
    "iso:country":"US",
    "sg:address":"2104 Fir St",
    "sg:city":"Morristown",
    "sg:classifiers":[
        {
            "category":"Professional",
            "subcategory":"Business Services",
            "type":"Services"
        }
    ],
    "sg:phone":"+1 423 318 0527",
    "sg:postcode":"37813",
    "sg:province":"TN",
    "wof:name":"Southeast Sourcing Solutions",
    "wof:placetype":"venue"
},
  "geometry": {"coordinates":[-83.266386,36.217839],"type":"Point"}
}