{
  "type": "Feature",
  "properties": {
    "addr:full":"162 E Main St Adamsville TN 38310",
    "addr:housenumber":"162",
    "addr:postcode":"38310",
    "addr:street":"E Main St",
    "iso:country":"US",
    "sg:address":"162 E Main St",
    "sg:city":"Adamsville",
    "sg:classifiers":[
        {
            "category":"Insurance",
            "subcategory":"Insurance Agent",
            "type":"Services"
        }
    ],
    "sg:phone":"+1 731 632 9820",
    "sg:postcode":"38310",
    "sg:province":"TN",
    "sg:tags":[
        "accident"
    ],
    "wof:name":"Harvey Durham Health",
    "wof:placetype":"venue"
},
  "geometry": {"coordinates":[-88.39281200000001,35.236001],"type":"Point"}
}