{
  "type": "Feature",
  "properties": {
    "addr:full":"1033 Robbie Dr Ashland City TN 37015",
    "addr:housenumber":"1033",
    "addr:postcode":"37015",
    "addr:street":"Robbie Dr",
    "iso:country":"US",
    "sg:address":"1033 Robbie Dr",
    "sg:city":"Ashland City",
    "sg:classifiers":[
        {
            "category":"Building & Trades",
            "subcategory":"Cleaning & Sanitation",
            "type":"Services"
        }
    ],
    "sg:phone":"+1 615 792 3831",
    "sg:postcode":"37015",
    "sg:province":"TN",
    "sg:tags":[
        "maintenance"
    ],
    "wof:name":"C&S Custom Cleaning Service",
    "wof:placetype":"venue"
},
  "geometry": {"coordinates":[-87.062152,36.201127],"type":"Point"}
}