{
  "type": "Feature",
  "properties": {
    "addr:full":"1705 Chapel Hill Pike Eagleville TN 37060",
    "addr:housenumber":"1705",
    "addr:postcode":"37060",
    "addr:street":"Chapel Hill Pike",
    "iso:country":"US",
    "sg:address":"1705 Chapel Hill Pike",
    "sg:city":"Eagleville",
    "sg:classifiers":[
        {
            "category":"Building & Trades",
            "subcategory":"Construction",
            "type":"Services"
        }
    ],
    "sg:phone":"+1 615 274 3796",
    "sg:postcode":"37060",
    "sg:province":"TN",
    "sg:tags":[
        "downspouts",
        "gutter"
    ],
    "wof:name":"Driver Guttering",
    "wof:placetype":"venue"
},
  "geometry": {"coordinates":[-86.64743300000001,35.699496],"type":"Point"}
}