{
  "type": "Feature",
  "properties": {
    "addr:full":"1664 E Stone Dr Kingsport TN 37660",
    "addr:housenumber":"1664",
    "addr:postcode":"37660",
    "addr:street":"E Stone Dr",
    "iso:country":"US",
    "sg:address":"1664 E Stone Dr",
    "sg:city":"Kingsport",
    "sg:classifiers":[
        {
            "category":"Personal",
            "subcategory":"Beauty Salon",
            "type":"Services"
        }
    ],
    "sg:phone":"+1 423 245 2787",
    "sg:postcode":"37660",
    "sg:province":"TN",
    "sg:tags":[
        "shop"
    ],
    "wof:name":"Cuts On The Corner",
    "wof:placetype":"venue"
},
  "geometry": {"coordinates":[-82.518259,36.547875],"type":"Point"}
}