{
  "type": "Feature",
  "properties": {
    "iso:country":"US",
    "sg:address":"876 Lone Oak Dr",
    "sg:city":"Cookeville",
    "sg:classifiers":[
        {
            "category":"Real Estate",
            "subcategory":"Real Estate Agent",
            "type":"Services"
        }
    ],
    "sg:phone":"+1 931 526 5188",
    "sg:postcode":"38501",
    "sg:province":"TN",
    "wof:name":"Stevens Rental Property",
    "wof:placetype":"venue"
},
  "geometry": {"coordinates":[-85.529775,36.14986],"type":"Point"}
}