{
  "type": "Feature",
  "properties": {
    "iso:country":"US",
    "sg:address":"6801 Conner Ln",
    "sg:city":"Chattanooga",
    "sg:classifiers":[
        {
            "category":"Retail",
            "subcategory":"Auto Repair",
            "type":"Services"
        }
    ],
    "sg:phone":"+1 423 894 0143",
    "sg:postcode":"37421",
    "sg:province":"TN",
    "sg:tags":[
        "wrecker"
    ],
    "wof:name":"Johnny's Wrecker Svc",
    "wof:placetype":"venue"
},
  "geometry": {"coordinates":[-85.16655299999999,35.042321],"type":"Point"}
}