{
  "type": "Feature",
  "properties": {
    "addr:full":"782 Melrose Ave Nashville TN 37211",
    "addr:housenumber":"782",
    "addr:postcode":"37211",
    "addr:street":"Melrose Ave",
    "iso:country":"US",
    "sg:address":"782 Melrose Ave",
    "sg:city":"Nashville",
    "sg:classifiers":[
        {
            "category":"Real Estate",
            "subcategory":"Real Estate Agent",
            "type":"Services"
        }
    ],
    "sg:phone":"+1 615 884 2300",
    "sg:postcode":"37211",
    "sg:province":"TN",
    "sg:tags":[
        "management"
    ],
    "sg:website":"www.dukerealty.com",
    "wof:name":"Duke Weeks Realty Corp",
    "wof:placetype":"venue"
},
  "geometry": {"coordinates":[-86.76509,36.120185],"type":"Point"}
}