{
  "type": "Feature",
  "properties": {
    "addr:full":"305 Hillsboro Blvd Manchester TN 37355",
    "addr:housenumber":"305",
    "addr:postcode":"37355",
    "addr:street":"Hillsboro Blvd",
    "iso:country":"US",
    "sg:address":"305 Hillsboro Blvd",
    "sg:city":"Manchester",
    "sg:classifiers":[
        {
            "category":"Shopping",
            "subcategory":"Books",
            "type":"Retail Goods"
        }
    ],
    "sg:phone":"+1 931 728 9733",
    "sg:postcode":"37355",
    "sg:province":"TN",
    "sg:tags":[
        "dealer"
    ],
    "wof:name":"James' Book & Novelty Shop",
    "wof:placetype":"venue"
},
  "geometry": {"coordinates":[-86.08474200000001,35.479585],"type":"Point"}
}