{
  "type": "Feature",
  "properties": {
    "iso:country":"US",
    "sg:address":"3206 Wilson Ave",
    "sg:city":"Signal Mountain",
    "sg:classifiers":[
        {
            "category":"Building & Trades",
            "subcategory":"Construction",
            "type":"Services"
        }
    ],
    "sg:phone":"+1 423 886 7796",
    "sg:postcode":"37377",
    "sg:province":"TN",
    "sg:tags":[
        "sun",
        "solarium",
        "rooms"
    ],
    "sg:website":"www.sundeckdesigns.com",
    "wof:name":"Sun Deck Designs",
    "wof:placetype":"venue"
},
  "geometry": {"coordinates":[-85.31118600000001,35.158131],"type":"Point"}
}