{
  "type": "Feature",
  "properties": {
    "iso:country":"US",
    "sg:address":"560 E Tri County Blvd",
    "sg:city":"Oliver Springs",
    "sg:classifiers":[
        {
            "category":"Autos & Motor Vehicles",
            "subcategory":"Automobile Sales",
            "type":"Retail Goods"
        }
    ],
    "sg:phone":"+1 865 435 1679",
    "sg:postcode":"37840",
    "sg:province":"TN",
    "sg:tags":[
        "car",
        "used",
        "dealer"
    ],
    "wof:name":"Bel Aire Auto Sales Inc",
    "wof:placetype":"venue"
},
  "geometry": {"coordinates":[-84.328739,36.034846],"type":"Point"}
}