{
  "type": "Feature",
  "properties": {
    "iso:country":"US",
    "sg:address":"1502 Brayton Ave",
    "sg:city":"Dyersburg",
    "sg:classifiers":[
        {
            "category":"Shopping",
            "subcategory":"Pharmacy",
            "type":"Retail Goods"
        }
    ],
    "sg:phone":"+1 731 285 7267",
    "sg:postcode":"38024",
    "sg:province":"TN",
    "wof:name":"Super D Express",
    "wof:placetype":"venue"
},
  "geometry": {"coordinates":[-89.379764,36.047328],"type":"Point"}
}