{
  "type": "Feature",
  "properties": {
    "iso:country":"US",
    "sg:address":"833 Nashville Hwy",
    "sg:city":"Columbia",
    "sg:classifiers":[
        {
            "category":"Health Services",
            "subcategory":"Health Practitioner",
            "type":"Services"
        }
    ],
    "sg:phone":"+1 931 540 0018",
    "sg:postcode":"38401",
    "sg:province":"TN",
    "sg:tags":[
        "therapist",
        "physical"
    ],
    "wof:name":"Healthsouth Sports Medicine",
    "wof:placetype":"venue"
},
  "geometry": {"coordinates":[-87.026701,35.628631],"type":"Point"}
}