{
  "type": "Feature",
  "properties": {
    "iso:country":"US",
    "sg:address":"2341 Pagely Pl",
    "sg:city":"Memphis",
    "sg:classifiers":[
        {
            "category":"Professional",
            "type":"Services"
        }
    ],
    "sg:phone":"+1 901 372 3167",
    "sg:postcode":"38134",
    "sg:province":"TN",
    "wof:name":"Up In Arms",
    "wof:placetype":"venue"
},
  "geometry": {"coordinates":[-89.875254,35.190187],"type":"Point"}
}