{
  "type": "Feature",
  "properties": {
    "iso:country":"US",
    "sg:address":"8102 Chapman Hwy",
    "sg:city":"Knoxville",
    "sg:classifiers":[
        {
            "category":"Retail",
            "subcategory":"Auto Repair",
            "type":"Services"
        }
    ],
    "sg:phone":"+1 865 573 6829",
    "sg:postcode":"37920",
    "sg:province":"TN",
    "sg:tags":[
        "repairing",
        "automobile"
    ],
    "wof:name":"Steve's Service Ctr",
    "wof:placetype":"venue"
},
  "geometry": {"coordinates":[-83.826178,35.902798],"type":"Point"}
}