{
  "type": "Feature",
  "properties": {
    "addr:full":"3010 Park Ave Memphis TN 38114",
    "addr:housenumber":"3010",
    "addr:postcode":"38114",
    "addr:street":"Park Ave",
    "iso:country":"US",
    "sg:address":"3010 Park Ave",
    "sg:city":"Memphis",
    "sg:classifiers":[
        {
            "category":"Shopping",
            "subcategory":"Gifts & Souvenirs",
            "type":"Retail Goods"
        }
    ],
    "sg:phone":"+1 901 324 1474",
    "sg:postcode":"38114",
    "sg:province":"TN",
    "sg:tags":[
        "shop"
    ],
    "wof:name":"Moore Comm's Gifts-N-Things",
    "wof:placetype":"venue"
},
  "geometry": {"coordinates":[-89.961851,35.107919],"type":"Point"}
}