{
  "type": "Feature",
  "properties": {
    "iso:country":"US",
    "sg:address":"796 West Ave",
    "sg:city":"Crossville",
    "sg:classifiers":[
        {
            "category":"Shopping",
            "type":"Retail Goods"
        }
    ],
    "sg:phone":"+1 931 484 2102",
    "sg:postcode":"38555",
    "sg:province":"TN",
    "sg:tags":[
        "supply",
        "hearing",
        "equipment",
        "electrical",
        "impaired",
        "merchandise"
    ],
    "wof:name":"Cumberland Hearing Aid Center",
    "wof:placetype":"venue"
},
  "geometry": {"coordinates":[-85.035731,35.952958],"type":"Point"}
}