{
  "type": "Feature",
  "properties": {
    "iso:country":"US",
    "sg:address":"280 Cherokee Dr",
    "sg:city":"Newport",
    "sg:classifiers":[
        {
            "category":"Cinema",
            "subcategory":"Movie Rental",
            "type":"Entertainment"
        }
    ],
    "sg:phone":"+1 423 623 4376",
    "sg:postcode":"37821",
    "sg:province":"TN",
    "sg:tags":[
        "video",
        "tape"
    ],
    "wof:name":"Show Time Video Rental",
    "wof:placetype":"venue"
},
  "geometry": {"coordinates":[-83.183196,35.961897],"type":"Point"}
}