{
  "type": "Feature",
  "properties": {
    "iso:country":"US",
    "sg:address":"103 Cherokee Rd",
    "sg:city":"Nashville",
    "sg:classifiers":[
        {
            "category":"Utilities",
            "subcategory":"Mobile Phone",
            "type":"Services"
        }
    ],
    "sg:phone":"+1 615 269 7747",
    "sg:postcode":"37205",
    "sg:province":"TN",
    "sg:tags":[
        "telephone",
        "cellular"
    ],
    "wof:name":"Airspeed Communications Inc",
    "wof:placetype":"venue"
},
  "geometry": {"coordinates":[-86.83902999999999,36.13199],"type":"Point"}
}