{
  "type": "Feature",
  "properties": {
    "addr:full":"10722 Dutchtown Rd Knoxville TN 37932",
    "addr:housenumber":"10722",
    "addr:postcode":"37932",
    "addr:street":"Dutchtown Rd",
    "iso:country":"US",
    "sg:address":"10722 Dutchtown Rd",
    "sg:city":"Knoxville",
    "sg:classifiers":[
        {
            "category":"Manufacturing",
            "subcategory":"Metals",
            "type":"Manufacturing & Wholesale Goods"
        }
    ],
    "sg:phone":"+1 865 675 1225",
    "sg:postcode":"37932",
    "sg:province":"TN",
    "sg:tags":[
        "lifting",
        "mfg"
    ],
    "wof:name":"Ashley Sling Inc",
    "wof:placetype":"venue"
},
  "geometry": {"coordinates":[-84.14561399999999,35.90987],"type":"Point"}
}