{
  "type": "Feature",
  "properties": {
    "iso:country":"US",
    "sg:address":"3806 Amnicola Hwy",
    "sg:city":"Chattanooga",
    "sg:classifiers":[
        {
            "category":"Wholesale",
            "subcategory":"Electrical",
            "type":"Manufacturing & Wholesale Goods"
        }
    ],
    "sg:phone":"+1 423 698 2860",
    "sg:postcode":"37406",
    "sg:province":"TN",
    "sg:tags":[
        "equipment",
        "electric",
        "motor",
        "supply"
    ],
    "wof:name":"Electric Motors Sales & Supply",
    "wof:placetype":"venue"
},
  "geometry": {"coordinates":[-85.256584,35.092513],"type":"Point"}
}