{
  "type": "Feature",
  "properties": {
    "iso:country":"US",
    "sg:address":"210 Woodruff St",
    "sg:city":"Madison",
    "sg:classifiers":[
        {
            "category":"Retail",
            "subcategory":"Auto Repair",
            "type":"Services"
        }
    ],
    "sg:phone":"+1 615 868 5121",
    "sg:postcode":"37115",
    "sg:province":"TN",
    "sg:tags":[
        "clutches"
    ],
    "wof:name":"Madison Masonic Lodge #72",
    "wof:placetype":"venue"
},
  "geometry": {"coordinates":[-86.71432299999999,36.260233],"type":"Point"}
}