{
  "type": "Feature",
  "properties": {
    "addr:full":"204 Watt Rd Knoxville TN 37934",
    "addr:housenumber":"204",
    "addr:postcode":"37934",
    "addr:street":"Watt Rd",
    "iso:country":"US",
    "sg:address":"204 Watt Rd",
    "sg:city":"Knoxville",
    "sg:classifiers":[
        {
            "category":"Retail",
            "subcategory":"Veterinary Services",
            "type":"Services"
        }
    ],
    "sg:phone":"+1 865 675 1833",
    "sg:postcode":"37934",
    "sg:province":"TN",
    "sg:tags":[
        "veterinarian"
    ],
    "wof:name":"Admiral Veterinary Hospital",
    "wof:placetype":"venue"
},
  "geometry": {"coordinates":[-84.226427,35.867102],"type":"Point"}
}