{
  "type": "Feature",
  "properties": {
    "iso:country":"US",
    "sg:address":"944 Garrison Ridge Blvd",
    "sg:city":"Knoxville",
    "sg:classifiers":[
        {
            "category":"Professional",
            "subcategory":"Research",
            "type":"Services"
        }
    ],
    "sg:phone":"+1 865 898 2061",
    "sg:postcode":"37922",
    "sg:province":"TN",
    "sg:tags":[
        "commercial",
        "physical"
    ],
    "wof:name":"Suntech Engineered Materials",
    "wof:placetype":"venue"
},
  "geometry": {"coordinates":[-84.101029,35.877631],"type":"Point"}
}