{
  "type": "Feature",
  "properties": {
    "iso:country":"US",
    "sg:address":"3555 Bobwhite Cove",
    "sg:city":"Memphis",
    "sg:classifiers":[
        {
            "category":"Building & Trades",
            "subcategory":"Construction",
            "type":"Services"
        }
    ],
    "sg:phone":"+1 901 380 3730",
    "sg:postcode":"38128",
    "sg:province":"TN",
    "sg:tags":[
        "resurfacing",
        "laying",
        "refinishing",
        "floor"
    ],
    "wof:name":"ABC Carpet Cleaning Co",
    "wof:placetype":"venue"
},
  "geometry": {"coordinates":[-89.94528800000001,35.206903],"type":"Point"}
}