{
  "type": "Feature",
  "properties": {
    "iso:country":"US",
    "sg:address":"5817 Robertson Ave",
    "sg:city":"Nashville",
    "sg:classifiers":[
        {
            "category":"Building & Trades",
            "subcategory":"Construction",
            "type":"Services"
        }
    ],
    "sg:phone":"+1 615 356 7903",
    "sg:postcode":"37209",
    "sg:province":"TN",
    "sg:tags":[
        "house"
    ],
    "wof:name":"T & M Construction",
    "wof:placetype":"venue"
},
  "geometry": {"coordinates":[-86.862143,36.15543],"type":"Point"}
}