{
  "type": "Feature",
  "properties": {
    "addr:full":"154 Chapel Hill Rd Milan TN 38358",
    "addr:housenumber":"154",
    "addr:postcode":"38358",
    "addr:street":"Chapel Hill Rd",
    "iso:country":"US",
    "sg:address":"154 Chapel Hill Rd",
    "sg:city":"Milan",
    "sg:classifiers":[
        {
            "category":"Farming",
            "subcategory":"Livestock Farm",
            "type":"Manufacturing & Wholesale Goods"
        }
    ],
    "sg:phone":"+1 731 686 1373",
    "sg:postcode":"38358",
    "sg:province":"TN",
    "sg:tags":[
        "beef",
        "feedlot",
        "cattle"
    ],
    "wof:name":"Mike Rushing",
    "wof:placetype":"venue"
},
  "geometry": {"coordinates":[-88.769271,35.852558],"type":"Point"}
}