{
  "type": "Feature",
  "properties": {
    "iso:country":"US",
    "sg:address":"2615 Peach Orchard Hill Rd NE",
    "sg:city":"Cleveland",
    "sg:classifiers":[
        {
            "category":"Organizations",
            "subcategory":"Religious Organization",
            "type":"Services"
        }
    ],
    "sg:phone":"+1 423 472 1040",
    "sg:postcode":"37323",
    "sg:province":"TN",
    "wof:name":"Bedenpauk House of Prayers",
    "wof:placetype":"venue"
},
  "geometry": {"coordinates":[-84.803561,35.165245],"type":"Point"}
}