{
  "type": "Feature",
  "properties": {
    "iso:country":"US",
    "sg:address":"1511 Getwell Rd",
    "sg:city":"Memphis",
    "sg:classifiers":[
        {
            "category":"Place Of Worship",
            "subcategory":"Church",
            "type":"Public Place"
        },
        {
            "category":"Place Of Worship",
            "type":"Public Place"
        }
    ],
    "sg:phone":"+1 901 743 0464",
    "sg:postcode":"38111",
    "sg:province":"TN",
    "sg:tags":[
        "churches-church",
        "christ"
    ],
    "sg:website":"http://www.getwellchurchofchrist.org",
    "wof:name":"Getwell Church Of Christ",
    "wof:placetype":"venue"
},
  "geometry": {"coordinates":[-89.93107999999999,35.090401],"type":"Point"}
}