{
  "type": "Feature",
  "properties": {
    "iso:country":"US",
    "sg:address":"614 Garfield St",
    "sg:city":"Nashville",
    "sg:classifiers":[
        {
            "category":"Food & Beverages",
            "subcategory":"Groceries & Convenience Stores",
            "type":"Retail Goods"
        }
    ],
    "sg:phone":"+1 615 244 7080",
    "sg:postcode":"37208",
    "sg:province":"TN",
    "sg:tags":[
        "market"
    ],
    "wof:name":"Community Market",
    "wof:placetype":"venue"
},
  "geometry": {"coordinates":[-86.794349,36.181537],"type":"Point"}
}