{
  "type": "Feature",
  "properties": {
    "addr:full":"157 Western Plaza Dr Newport TN 37821",
    "addr:housenumber":"157",
    "addr:postcode":"37821",
    "addr:street":"Western Plaza Dr",
    "iso:country":"US",
    "sg:address":"157 Western Plaza Dr",
    "sg:city":"Newport",
    "sg:classifiers":[
        {
            "category":"Personal",
            "subcategory":"Beauty Salon",
            "type":"Services"
        }
    ],
    "sg:phone":"+1 423 613 0888",
    "sg:postcode":"37821",
    "sg:province":"TN",
    "sg:tags":[
        "school"
    ],
    "wof:name":"Stylemasters Academy-Csmtlgy",
    "wof:placetype":"venue"
},
  "geometry": {"coordinates":[-83.207429,35.972187],"type":"Point"}
}