{
  "type": "Feature",
  "properties": {
    "iso:country":"US",
    "sg:address":"1512 Elmwood Ave",
    "sg:city":"Nashville",
    "sg:classifiers":[
        {
            "category":"Building & Trades",
            "subcategory":"Landscaping Services",
            "type":"Services"
        }
    ],
    "sg:phone":"+1 615 463 8683",
    "sg:postcode":"37212",
    "sg:province":"TN",
    "wof:name":"Shelton & Sons",
    "wof:placetype":"venue"
},
  "geometry": {"coordinates":[-86.792742,36.126848],"type":"Point"}
}