{
  "type": "Feature",
  "properties": {
    "addr:full":"3182 Jean Dr Memphis TN 38118",
    "addr:housenumber":"3182",
    "addr:postcode":"38118",
    "addr:street":"Jean Dr",
    "iso:country":"US",
    "sg:address":"3182 Jean Dr",
    "sg:city":"Memphis",
    "sg:classifiers":[
        {
            "category":"Shopping",
            "subcategory":"Discount & Variety Stores",
            "type":"Retail Goods"
        }
    ],
    "sg:phone":"+1 901 362 2508",
    "sg:postcode":"38118",
    "sg:province":"TN",
    "sg:tags":[
        "merchandise",
        "general"
    ],
    "wof:name":"Salvage 1 Com",
    "wof:placetype":"venue"
},
  "geometry": {"coordinates":[-89.947559,35.060511],"type":"Point"}
}