{
  "type": "Feature",
  "properties": {
    "iso:country":"US",
    "sg:address":"1517 Union Ave",
    "sg:city":"Memphis",
    "sg:classifiers":[
        {
            "category":"Insurance",
            "subcategory":"Insurance Agent",
            "type":"Services"
        },
        {
            "category":"Banks & Credit Unions",
            "subcategory":"Investment Brokerage",
            "type":"Services"
        },
        {
            "category":"Insurance",
            "subcategory":"Hazard Insurance",
            "type":"Services"
        }
    ],
    "sg:phone":"+1 901 276 3233",
    "sg:postcode":"38104",
    "sg:province":"TN",
    "sg:tags":[
        "auto",
        "motorcycle",
        "resume"
    ],
    "sg:website":"http://www.directgeneral.com",
    "wof:name":"Direct Auto Insurance",
    "wof:placetype":"venue"
},
  "geometry": {"coordinates":[-90.010814,35.136269],"type":"Point"}
}