{
  "type": "Feature",
  "properties": {
    "iso:country":"US",
    "sg:address":"1064 N State Hwy 340",
    "sg:city":"Parrottsville",
    "sg:classifiers":[
        {
            "category":"Building & Trades",
            "subcategory":"Electrical",
            "type":"Services"
        }
    ],
    "sg:phone":"+1 423 623 1144",
    "sg:postcode":"37843",
    "sg:province":"TN",
    "sg:tags":[
        "electrical",
        "contractor"
    ],
    "wof:name":"Jerry Morrow",
    "wof:placetype":"venue"
},
  "geometry": {"coordinates":[-83.0806,36.050936],"type":"Point"}
}