{
  "type": "Feature",
  "properties": {
    "iso:country":"US",
    "sg:address":"600 Russell St",
    "sg:city":"Paris",
    "sg:phone":"+1 731 642 6600",
    "sg:postcode":"38242",
    "sg:province":"TN",
    "sg:tags":[
        "oil"
    ],
    "wof:name":"Greer & Hamilton",
    "wof:placetype":"venue"
},
  "geometry": {"coordinates":[-88.311587,36.283731],"type":"Point"}
}