{
  "type": "Feature",
  "properties": {
    "addr:full":"1105 N Houston Levee Rd Cordova TN 38018",
    "addr:housenumber":"1105",
    "addr:postcode":"38018",
    "addr:street":"N Houston Levee Rd",
    "iso:country":"US",
    "sg:address":"1105 N Houston Levee Rd",
    "sg:city":"Cordova",
    "sg:classifiers":[
        {
            "category":"Ice Cream",
            "type":"Food & Drink"
        }
    ],
    "sg:menulink":"http://www.allmenus.com/tn/fisherville/228160-emack--bolios-ice-cream/menu/",
    "sg:phone":"+1 901 755 0202",
    "sg:postcode":"38018",
    "sg:province":"TN",
    "sg:tags":[
        "american"
    ],
    "wof:name":"Emack & Bolio's Ice Cream",
    "wof:placetype":"venue"
},
  "geometry": {"coordinates":[-89.727817,35.155232],"type":"Point"}
}