{
  "type": "Feature",
  "properties": {
    "iso:country":"US",
    "sg:address":"4216 Queensbury Ave",
    "sg:city":"Memphis",
    "sg:classifiers":[
        {
            "category":"Retail",
            "subcategory":"Repair Shop",
            "type":"Services"
        }
    ],
    "sg:phone":"+1 901 763 3166",
    "sg:postcode":"38108",
    "sg:province":"TN",
    "wof:name":"R L Upholstery",
    "wof:placetype":"venue"
},
  "geometry": {"coordinates":[-89.919517,35.167922],"type":"Point"}
}