{
  "type": "Feature",
  "properties": {
    "iso:country":"US",
    "sg:address":"521 Airway Dr",
    "sg:city":"Alcoa",
    "sg:classifiers":[
        {
            "category":"Insurance",
            "subcategory":"Insurance Agent",
            "type":"Services"
        }
    ],
    "sg:phone":"+1 865 970 7500",
    "sg:postcode":"37701",
    "sg:province":"TN",
    "sg:website":"www.earlwhaley.com",
    "wof:name":"Earl Whaley & Co",
    "wof:placetype":"venue"
},
  "geometry": {"coordinates":[-83.969233,35.840935],"type":"Point"}
}