{
  "type": "Feature",
  "properties": {
    "iso:country":"US",
    "sg:address":"7085 Bakers Bridge Ave",
    "sg:city":"Franklin",
    "sg:classifiers":[
        {
            "category":"Shopping",
            "subcategory":"Shoes",
            "type":"Retail Goods"
        }
    ],
    "sg:phone":"+1 615 771 7786",
    "sg:postcode":"37067",
    "sg:province":"TN",
    "sg:tags":[
        "sales"
    ],
    "sg:website":"www.shoecarnival.com",
    "wof:name":"Shoe Carnival 68",
    "wof:placetype":"venue"
},
  "geometry": {"coordinates":[-86.814564,35.961787],"type":"Point"}
}