{
  "type": "Feature",
  "properties": {
    "iso:country":"US",
    "sg:address":"694 Madison Ave",
    "sg:city":"Memphis",
    "sg:classifiers":[
        {
            "category":"Restaurant",
            "type":"Food & Drink"
        }
    ],
    "sg:phone":"+1 901 527 0860",
    "sg:postcode":"38103",
    "sg:province":"TN",
    "wof:name":"Bluff City Bayou",
    "wof:placetype":"venue"
},
  "geometry": {"coordinates":[-90.037768,35.141256],"type":"Point"}
}