{
  "type": "Feature",
  "properties": {
    "iso:country":"US",
    "sg:address":"7760 Yellowbrick Way",
    "sg:city":"Knoxville",
    "sg:classifiers":[
        {
            "category":"Autos & Motor Vehicles",
            "subcategory":"Auto Supplies",
            "type":"Retail Goods"
        }
    ],
    "sg:phone":"+1 865 933 3929",
    "sg:postcode":"37938",
    "sg:province":"TN",
    "wof:name":"Country Boys Auto Parts",
    "wof:placetype":"venue"
},
  "geometry": {"coordinates":[-83.975781,36.067251],"type":"Point"}
}