{
  "type": "Feature",
  "properties": {
    "iso:country":"US",
    "sg:address":"762 Rankin Hill Rd",
    "sg:city":"Newport",
    "sg:classifiers":[
        {
            "category":"Building & Trades",
            "subcategory":"Construction",
            "type":"Services"
        }
    ],
    "sg:phone":"+1 423 613 0404",
    "sg:postcode":"37821",
    "sg:province":"TN",
    "sg:tags":[
        "hanging",
        "contractor"
    ],
    "wof:name":"Gaylas Wdding Dcrtons Phtgrphy",
    "wof:placetype":"venue"
},
  "geometry": {"coordinates":[-83.22240499999999,36.051945],"type":"Point"}
}