{
  "type": "Feature",
  "properties": {
    "addr:full":"6206 Bridlewood Ln Brentwood TN 37027",
    "addr:housenumber":"6206",
    "addr:postcode":"37027",
    "addr:street":"Bridlewood Ln",
    "iso:country":"US",
    "sg:address":"6206 Bridlewood Ln",
    "sg:city":"Brentwood",
    "sg:classifiers":[
        {
            "category":"Travel",
            "subcategory":"Travel Agent",
            "type":"Entertainment"
        }
    ],
    "sg:phone":"+1 615 377 8783",
    "sg:postcode":"37027",
    "sg:province":"TN",
    "sg:tags":[
        "agency",
        "bureau"
    ],
    "wof:name":"Chalfant Travel Svc",
    "wof:placetype":"venue"
},
  "geometry": {"coordinates":[-86.82832399999999,36.037698],"type":"Point"}
}