{
  "type": "Feature",
  "properties": {
    "addr:full":"2300 Kline Ave Nashville TN 37211",
    "addr:housenumber":"2300",
    "addr:postcode":"37211",
    "addr:street":"Kline Ave",
    "iso:country":"US",
    "sg:address":"2300 Kline Ave",
    "sg:city":"Nashville",
    "sg:classifiers":[
        {
            "category":"Building & Trades",
            "subcategory":"Electrical",
            "type":"Services"
        }
    ],
    "sg:phone":"+1 615 244 4443",
    "sg:postcode":"37211",
    "sg:province":"TN",
    "sg:tags":[
        "electric",
        "contractor"
    ],
    "wof:name":"A & F Electric Co",
    "wof:placetype":"venue"
},
  "geometry": {"coordinates":[-86.75244000000001,36.120013],"type":"Point"}
}