{
  "type": "Feature",
  "properties": {
    "iso:country":"US",
    "sg:address":"538 Rushing Springs Rd",
    "sg:city":"Monterey",
    "sg:phone":"+1 931 445 7701",
    "sg:postcode":"38574",
    "sg:province":"TN",
    "sg:tags":[
        "farm",
        "tobacco",
        "beef",
        "feedlot",
        "cattle"
    ],
    "wof:name":"Krantz Farms",
    "wof:placetype":"venue"
},
  "geometry": {"coordinates":[-85.252222,36.242041],"type":"Point"}
}