{
  "type": "Feature",
  "properties": {
    "addr:full":"405 State Rte 125 Henderson TN 38340",
    "addr:housenumber":"405",
    "addr:postcode":"38340",
    "addr:street":"State Rte 125",
    "iso:country":"US",
    "sg:address":"405 State Rte 125",
    "sg:city":"Henderson",
    "sg:classifiers":[
        {
            "category":"Building & Trades",
            "subcategory":"Electrical",
            "type":"Services"
        }
    ],
    "sg:phone":"+1 731 989 9985",
    "sg:postcode":"38340",
    "sg:province":"TN",
    "sg:tags":[
        "electrical",
        "contractor"
    ],
    "wof:name":"K T Electric",
    "wof:placetype":"venue"
},
  "geometry": {"coordinates":[-88.804284,35.383658],"type":"Point"}
}