{
  "type": "Feature",
  "properties": {
    "iso:country":"US",
    "sg:address":"26 Hickory Dr",
    "sg:city":"Crossville",
    "sg:classifiers":[
        {
            "category":"Wholesale",
            "subcategory":"Machinery & Supplies",
            "type":"Manufacturing & Wholesale Goods"
        }
    ],
    "sg:phone":"+1 931 707 7348",
    "sg:postcode":"38571",
    "sg:province":"TN",
    "sg:tags":[
        "equipment",
        "clea",
        "cleaning",
        "carpet"
    ],
    "wof:name":"Imperial Research",
    "wof:placetype":"venue"
},
  "geometry": {"coordinates":[-84.988744,36.016792],"type":"Point"}
}