{
  "type": "Feature",
  "properties": {
    "iso:country":"US",
    "sg:address":"125 W Arrowwood Rd",
    "sg:city":"Oak Ridge",
    "sg:classifiers":[
        {
            "category":"Retail",
            "subcategory":"Repair Shop",
            "type":"Services"
        }
    ],
    "sg:phone":"+1 865 482 7718",
    "sg:postcode":"37830",
    "sg:province":"TN",
    "wof:name":"Tony & Sons",
    "wof:placetype":"venue"
},
  "geometry": {"coordinates":[-84.21990599999999,36.040628],"type":"Point"}
}