{
  "type": "Feature",
  "properties": {
    "iso:country":"US",
    "sg:address":"6784 Hickory Creek Rd",
    "sg:city":"Chattanooga",
    "sg:classifiers":[
        {
            "category":"Organizations",
            "subcategory":"Religious Organization",
            "type":"Services"
        }
    ],
    "sg:phone":"+1 423 499 9822",
    "sg:postcode":"37421",
    "sg:province":"TN",
    "wof:name":"Pilgrim Congregational Church",
    "wof:placetype":"venue"
},
  "geometry": {"coordinates":[-85.16415600000001,35.050835],"type":"Point"}
}