{
  "type": "Feature",
  "properties": {
    "addr:full":"202 Hiway Dr Clinton TN 37716",
    "addr:housenumber":"202",
    "addr:postcode":"37716",
    "addr:street":"Hiway Dr",
    "iso:country":"US",
    "sg:address":"202 Hiway Dr",
    "sg:city":"Clinton",
    "sg:classifiers":[
        {
            "category":"Organizations",
            "subcategory":"Religious Organization",
            "type":"Services"
        }
    ],
    "sg:phone":"+1 865 463 7071",
    "sg:postcode":"37716",
    "sg:province":"TN",
    "wof:name":"Mount Olive Baptist Church",
    "wof:placetype":"venue"
},
  "geometry": {"coordinates":[-84.132299,36.082036],"type":"Point"}
}