{
  "type": "Feature",
  "properties": {
    "iso:country":"US",
    "sg:address":"115 Choate Cemetery Rd",
    "sg:city":"Cookeville",
    "sg:classifiers":[
        {
            "category":"Retail",
            "subcategory":"Auto Repair",
            "type":"Services"
        }
    ],
    "sg:phone":"+1 931 528 5366",
    "sg:postcode":"38501",
    "sg:province":"TN",
    "sg:tags":[
        "general"
    ],
    "wof:name":"Morris Auto Repair",
    "wof:placetype":"venue"
},
  "geometry": {"coordinates":[-85.496658,36.193003],"type":"Point"}
}