{
  "type": "Feature",
  "properties": {
    "iso:country":"US",
    "sg:address":"345 Thompson Rd",
    "sg:city":"Madisonville",
    "sg:classifiers":[
        {
            "category":"Building & Trades",
            "subcategory":"Construction",
            "type":"Services"
        }
    ],
    "sg:phone":"+1 423 442 1622",
    "sg:postcode":"37354",
    "sg:province":"TN",
    "sg:tags":[
        "masonry",
        "contractor"
    ],
    "wof:name":"Eddie Goines Masonry Contr",
    "wof:placetype":"venue"
},
  "geometry": {"coordinates":[-84.408299,35.52784],"type":"Point"}
}