{
  "type": "Feature",
  "properties": {
    "addr:full":"155 S Jefferson Ave Cookeville TN 38501",
    "addr:housenumber":"155",
    "addr:postcode":"38501",
    "addr:street":"S Jefferson Ave",
    "iso:country":"US",
    "sg:address":"155 S Jefferson Ave",
    "sg:city":"Cookeville",
    "sg:classifiers":[
        {
            "category":"Banks & Credit Unions",
            "subcategory":"Bank",
            "type":"Services"
        }
    ],
    "sg:phone":"+1 931 520 8101",
    "sg:postcode":"38501",
    "sg:province":"TN",
    "sg:tags":[
        "state"
    ],
    "wof:name":"Union Planters Bank",
    "wof:placetype":"venue"
},
  "geometry": {"coordinates":[-85.50041400000001,36.160296],"type":"Point"}
}