{
  "type": "Feature",
  "properties": {
    "addr:full":"8535 Saundersville Rd Mount Juliet TN 37122",
    "addr:postcode":"8535;37122",
    "addr:street":"Saundersville Rd",
    "iso:country":"US",
    "sg:address":"8535 Saundersville Rd",
    "sg:city":"Mount Juliet",
    "sg:classifiers":[
        {
            "category":"Manufacturing",
            "subcategory":"Motor Vehicles & Parts",
            "type":"Manufacturing & Wholesale Goods"
        }
    ],
    "sg:phone":"+1 615 754 9052",
    "sg:postcode":"37122",
    "sg:province":"TN",
    "sg:tags":[
        "body",
        "mfg"
    ],
    "wof:name":"Welch Trucking",
    "wof:placetype":"venue"
},
  "geometry": {"coordinates":[-86.51786300000001,36.265608],"type":"Point"}
}