{
  "type": "Feature",
  "properties": {
    "iso:country":"US",
    "sg:address":"330 W Central Ave",
    "sg:city":"Jamestown",
    "sg:classifiers":[
        {
            "category":"Autos & Motor Vehicles",
            "subcategory":"Automobile Sales",
            "type":"Retail Goods"
        }
    ],
    "sg:phone":"+1 931 879 9668",
    "sg:postcode":"38556",
    "sg:province":"TN",
    "sg:tags":[
        "car",
        "dealer"
    ],
    "wof:name":"J C Copley Auto Truck Co",
    "wof:placetype":"venue"
},
  "geometry": {"coordinates":[-84.940522,36.430449],"type":"Point"}
}