{
  "type": "Feature",
  "properties": {
    "addr:full":"4712 Nolensville Pike Nashville TN 37211",
    "addr:housenumber":"4712",
    "addr:postcode":"37211",
    "addr:street":"Nolensville Pike",
    "iso:country":"US",
    "sg:address":"4712 Nolensville Pike",
    "sg:city":"Nashville",
    "sg:classifiers":[
        {
            "category":"Personal",
            "subcategory":"Barber",
            "type":"Services"
        }
    ],
    "sg:phone":"+1 615 833 9985",
    "sg:postcode":"37211",
    "sg:province":"TN",
    "sg:tags":[
        "shop"
    ],
    "wof:name":"Tusculum Barber Shop",
    "wof:placetype":"venue"
},
  "geometry": {"coordinates":[-86.718011,36.066896],"type":"Point"}
}