{
  "type": "Feature",
  "properties": {
    "iso:country":"US",
    "sg:address":"580 Mitchell Rd",
    "sg:city":"Kingsport",
    "sg:classifiers":[
        {
            "category":"Retail",
            "subcategory":"Animal Services",
            "type":"Services"
        }
    ],
    "sg:phone":"+1 423 239 6934",
    "sg:postcode":"37663",
    "sg:province":"TN",
    "sg:tags":[
        "pet"
    ],
    "wof:name":"No Place Like Hm Pet Sitting",
    "wof:placetype":"venue"
},
  "geometry": {"coordinates":[-82.51535699999999,36.442659],"type":"Point"}
}