{
  "type": "Feature",
  "properties": {
    "addr:full":"10553 Highway 67 W Butler TN 37640",
    "addr:housenumber":"10553",
    "addr:postcode":"37640",
    "addr:street":"Highway 67 W",
    "iso:country":"US",
    "sg:address":"10553 Highway 67 W",
    "sg:city":"Butler",
    "sg:classifiers":[
        {
            "category":"Building & Trades",
            "subcategory":"Construction",
            "type":"Services"
        }
    ],
    "sg:phone":"+1 423 727 8104",
    "sg:postcode":"37640",
    "sg:province":"TN",
    "sg:tags":[
        "altering",
        "industrial",
        "remodeling",
        "contractors-commercial",
        "contractor"
    ],
    "wof:name":"Dunn Construction Co",
    "wof:placetype":"venue"
},
  "geometry": {"coordinates":[-81.959825,36.409735],"type":"Point"}
}