{
  "type": "Feature",
  "properties": {
    "addr:full":"7657 Highway 70 S Nashville TN 37221",
    "addr:housenumber":"7657",
    "addr:postcode":"37221",
    "addr:street":"Highway 70 S",
    "iso:country":"US",
    "sg:address":"7657 Highway 70 S",
    "sg:city":"Nashville",
    "sg:classifiers":[
        {
            "category":"Restaurant",
            "type":"Food & Drink"
        }
    ],
    "sg:menulink":"http://www.allmenus.com/tn/nashville/116208-quiznos-sub/menu/",
    "sg:phone":"+1 615 646 4874",
    "sg:postcode":"37221",
    "sg:province":"TN",
    "sg:tags":[
        "wrap",
        "american",
        "sandwich"
    ],
    "wof:name":"Quiznos Sub",
    "wof:placetype":"venue"
},
  "geometry": {"coordinates":[-86.950743,36.07698],"type":"Point"}
}