{
  "type": "Feature",
  "properties": {
    "addr:full":"1770 N Germantown Pkwy Cordova TN 38016",
    "addr:housenumber":"1770",
    "addr:postcode":"38016",
    "addr:street":"N Germantown Pkwy",
    "iso:country":"US",
    "sg:address":"1770 N Germantown Pkwy",
    "sg:city":"Cordova",
    "sg:classifiers":[
        {
            "category":"Shopping",
            "subcategory":"Tobacco",
            "type":"Retail Goods"
        }
    ],
    "sg:phone":"+1 901 758 0118",
    "sg:postcode":"38016",
    "sg:province":"TN",
    "sg:tags":[
        "product"
    ],
    "wof:name":"Cigar Depot",
    "wof:placetype":"venue"
},
  "geometry": {"coordinates":[-89.79280799999999,35.175312],"type":"Point"}
}