{
  "type": "Feature",
  "properties": {
    "iso:country":"US",
    "sg:address":"255 Union Ave",
    "sg:city":"Memphis",
    "sg:classifiers":[
        {
            "category":"Autos & Motor Vehicles",
            "subcategory":"Boat Sales",
            "type":"Retail Goods"
        }
    ],
    "sg:phone":"+1 901 527 8396",
    "sg:postcode":"38103",
    "sg:province":"TN",
    "sg:tags":[
        "equipment",
        "marine",
        "supply"
    ],
    "wof:name":"Marine Supply Co",
    "wof:placetype":"venue"
},
  "geometry": {"coordinates":[-90.046019,35.141125],"type":"Point"}
}