{
  "type": "Feature",
  "properties": {
    "addr:full":"9159 Telecom Dr Milan TN 38358",
    "addr:housenumber":"9159",
    "addr:postcode":"38358",
    "addr:street":"Telecom Dr",
    "iso:country":"US",
    "sg:address":"9159 Telecom Dr",
    "sg:city":"Milan",
    "sg:classifiers":[
        {
            "category":"Manufacturing",
            "subcategory":"Building Materials",
            "type":"Manufacturing & Wholesale Goods"
        }
    ],
    "sg:phone":"+1 731 686 8345",
    "sg:postcode":"38358",
    "sg:province":"TN",
    "sg:tags":[
        "door"
    ],
    "sg:website":"www.cecodoor.com",
    "wof:name":"Ceco Door Products",
    "wof:placetype":"venue"
},
  "geometry": {"coordinates":[-88.757914,35.889382],"type":"Point"}
}