{
  "type": "Feature",
  "properties": {
    "iso:country":"US",
    "sg:address":"725 Vauxhall Dr",
    "sg:city":"Nashville",
    "sg:classifiers":[
        {
            "category":"Retail",
            "subcategory":"Auto Rental",
            "type":"Services"
        }
    ],
    "sg:phone":"+1 615 242 6060",
    "sg:postcode":"37221",
    "sg:province":"TN",
    "sg:tags":[
        "automobile",
        "leasing"
    ],
    "wof:name":"Performance Leasing & Sales",
    "wof:placetype":"venue"
},
  "geometry": {"coordinates":[-86.978465,36.061716],"type":"Point"}
}