{
  "type": "Feature",
  "properties": {
    "iso:country":"US",
    "sg:address":"1831 Heritage Park Plz",
    "sg:city":"Murfreesboro",
    "sg:classifiers":[
        {
            "category":"Professional",
            "subcategory":"Accounting & Tax Preparation",
            "type":"Services"
        }
    ],
    "sg:phone":"+1 615 907 0444",
    "sg:postcode":"37129",
    "sg:province":"TN",
    "sg:tags":[
        "accountant"
    ],
    "wof:name":"Jack Ditraglia CPA",
    "wof:placetype":"venue"
},
  "geometry": {"coordinates":[-86.38717699999999,35.873025],"type":"Point"}
}