{
  "type": "Feature",
  "properties": {
    "iso:country":"US",
    "sg:address":"75 Landfill Rd",
    "sg:city":"Bolivar",
    "sg:classifiers":[
        {
            "category":"Government",
            "subcategory":"Office",
            "type":"Public Place"
        }
    ],
    "sg:phone":"+1 731 658 2020",
    "sg:postcode":"38012",
    "sg:province":"TN",
    "sg:tags":[
        "village"
    ],
    "wof:name":"Bolivar Recycling Ctr",
    "wof:placetype":"venue"
},
  "geometry": {"coordinates":[-89.299007,35.573346],"type":"Point"}
}