{
  "type": "Feature",
  "properties": {
    "addr:full":"140 Suzanne Dr Dickson TN 37055",
    "addr:housenumber":"140",
    "addr:postcode":"37055",
    "addr:street":"Suzanne Dr",
    "iso:country":"US",
    "sg:address":"140 Suzanne Dr",
    "sg:city":"Dickson",
    "sg:classifiers":[
        {
            "category":"Restaurant",
            "type":"Food & Drink"
        }
    ],
    "sg:menulink":"http://www.allmenus.com/tn/burns-white-bluff/104015-ruby-tuesdays/menu/",
    "sg:phone":"+1 615 740 1488",
    "sg:postcode":"37055",
    "sg:province":"TN",
    "sg:tags":[
        "burger",
        "american"
    ],
    "wof:name":"Ruby Tuesdays",
    "wof:placetype":"venue"
},
  "geometry": {"coordinates":[-87.337487,36.023225],"type":"Point"}
}