{
  "type": "Feature",
  "properties": {
    "iso:country":"US",
    "sg:address":"5180 Elmore Rd",
    "sg:city":"Memphis",
    "sg:classifiers":[
        {
            "category":"Retail",
            "subcategory":"Auto Repair",
            "type":"Services"
        }
    ],
    "sg:phone":"+1 901 373 3072",
    "sg:postcode":"38134",
    "sg:province":"TN",
    "sg:tags":[
        "automotive",
        "general"
    ],
    "wof:name":"Grammers Automotive Service",
    "wof:placetype":"venue"
},
  "geometry": {"coordinates":[-89.89073,35.18519],"type":"Point"}
}