{
  "type": "Feature",
  "properties": {
    "addr:full":"629 Monroe Ave Memphis TN 38103",
    "addr:housenumber":"629",
    "addr:postcode":"38103",
    "addr:street":"Monroe Ave",
    "iso:country":"US",
    "sg:address":"629 Monroe Ave",
    "sg:city":"Memphis",
    "sg:classifiers":[
        {
            "category":"Wholesale",
            "subcategory":"Machinery & Supplies",
            "type":"Manufacturing & Wholesale Goods"
        }
    ],
    "sg:phone":"+1 901 272 0934",
    "sg:postcode":"38103",
    "sg:province":"TN",
    "sg:tags":[
        "contractor"
    ],
    "wof:name":"Equipment Ambulance",
    "wof:placetype":"venue"
},
  "geometry": {"coordinates":[-90.04053999999999,35.140764],"type":"Point"}
}