{
  "type": "Feature",
  "properties": {
    "iso:country":"US",
    "sg:address":"202 Carriage House Dr",
    "sg:city":"Jackson",
    "sg:classifiers":[
        {
            "category":"Wholesale",
            "subcategory":"Computers",
            "type":"Manufacturing & Wholesale Goods"
        }
    ],
    "sg:phone":"+1 731 286 5256",
    "sg:postcode":"38305",
    "sg:province":"TN",
    "sg:tags":[
        "consulting",
        "software"
    ],
    "wof:name":"Southern Comfort Software",
    "wof:placetype":"venue"
},
  "geometry": {"coordinates":[-88.836859,35.668259],"type":"Point"}
}