{
  "type": "Feature",
  "properties": {
    "iso:country":"US",
    "sg:address":"109 E Turkey Creek Rd",
    "sg:city":"Cookeville",
    "sg:classifiers":[
        {
            "category":"Autos & Motor Vehicles",
            "subcategory":"Automobile Sales",
            "type":"Retail Goods"
        }
    ],
    "sg:phone":"+1 931 498 5858",
    "sg:postcode":"38506",
    "sg:province":"TN",
    "sg:tags":[
        "car",
        "dealer"
    ],
    "wof:name":"Hwy 111 Auto Sales Auto",
    "wof:placetype":"venue"
},
  "geometry": {"coordinates":[-85.40046,36.23616],"type":"Point"}
}