{
  "type": "Feature",
  "properties": {
    "iso:country":"US",
    "sg:address":"630 Tulane Cove N",
    "sg:city":"Memphis",
    "sg:classifiers":[
        {
            "category":"Real Estate",
            "subcategory":"Real Estate Operator",
            "type":"Services"
        }
    ],
    "sg:phone":"+1 901 346 3254",
    "sg:postcode":"38109",
    "sg:province":"TN",
    "sg:tags":[
        "apartment"
    ],
    "wof:name":"Fairways Apartments",
    "wof:placetype":"venue"
},
  "geometry": {"coordinates":[-90.04242600000001,35.008028],"type":"Point"}
}