{
  "type": "Feature",
  "properties": {
    "addr:full":"601 Dickerson Rd Goodlettsville TN 37072",
    "addr:housenumber":"601",
    "addr:postcode":"37072",
    "addr:street":"Dickerson Rd",
    "iso:country":"US",
    "sg:address":"601 Dickerson Rd",
    "sg:city":"Goodlettsville",
    "sg:classifiers":[
        {
            "category":"Health Services",
            "subcategory":"Chiropractor",
            "type":"Services"
        }
    ],
    "sg:phone":"+1 615 851 6161",
    "sg:postcode":"37072",
    "sg:province":"TN",
    "wof:name":"Sickels Chiropractic",
    "wof:placetype":"venue"
},
  "geometry": {"coordinates":[-86.71454799999999,36.313285],"type":"Point"}
}