{
  "type": "Feature",
  "properties": {
    "iso:country":"US",
    "sg:address":"6141 Poplar Springs Bargerton Rd",
    "sg:city":"Lexington",
    "sg:classifiers":[
        {
            "category":"Education",
            "subcategory":"School",
            "type":"Public Place"
        }
    ],
    "sg:phone":"+1 731 968 7484",
    "sg:postcode":"38351",
    "sg:province":"TN",
    "wof:name":"Bargerton School",
    "wof:placetype":"venue"
},
  "geometry": {"coordinates":[-88.494777,35.7325],"type":"Point"}
}