{
  "type": "Feature",
  "properties": {
    "iso:country":"US",
    "sg:address":"5001 Calhoun Ave",
    "sg:city":"Chattanooga",
    "sg:classifiers":[
        {
            "category":"Utilities",
            "subcategory":"Telephone",
            "type":"Services"
        }
    ],
    "sg:phone":"+1 423 867 9010",
    "sg:postcode":"37407",
    "sg:province":"TN",
    "sg:tags":[
        "communications"
    ],
    "wof:name":"Salvage Telecom",
    "wof:placetype":"venue"
},
  "geometry": {"coordinates":[-85.291274,34.985098],"type":"Point"}
}