{
  "type": "Feature",
  "properties": {
    "addr:full":"813 Barclay Dr Knoxville TN 37920",
    "addr:housenumber":"813",
    "addr:postcode":"37920",
    "addr:street":"Barclay Dr",
    "iso:country":"US",
    "sg:address":"813 Barclay Dr",
    "sg:city":"Knoxville",
    "sg:classifiers":[
        {
            "category":"Professional",
            "type":"Services"
        }
    ],
    "sg:phone":"+1 865 577 9445",
    "sg:postcode":"37920",
    "sg:province":"TN",
    "wof:name":"Dorothy W Waddell",
    "wof:placetype":"venue"
},
  "geometry": {"coordinates":[-83.894425,35.935688],"type":"Point"}
}