{
  "type": "Feature",
  "properties": {
    "addr:full":"2934 Sidco Dr Nashville TN 37204",
    "addr:housenumber":"2934",
    "addr:postcode":"37204",
    "addr:street":"Sidco Dr",
    "iso:country":"US",
    "sg:address":"2934 Sidco Dr",
    "sg:city":"Nashville",
    "sg:classifiers":[
        {
            "category":"Retail",
            "subcategory":"Veterinary Services",
            "type":"Services"
        }
    ],
    "sg:phone":"+1 615 255 5887",
    "sg:postcode":"37204",
    "sg:province":"TN",
    "sg:tags":[
        "veterinarian"
    ],
    "wof:name":"Tennessee Veterinary Spclst",
    "wof:placetype":"venue"
},
  "geometry": {"coordinates":[-86.755805,36.105943],"type":"Point"}
}