{
  "type": "Feature",
  "properties": {
    "iso:country":"US",
    "sg:address":"429 Union Ave",
    "sg:city":"Memphis",
    "sg:classifiers":[
        {
            "category":"Autos & Motor Vehicles",
            "subcategory":"Automobile Sales",
            "type":"Retail Goods"
        }
    ],
    "sg:phone":"+1 901 526 1550",
    "sg:postcode":"38103",
    "sg:province":"TN",
    "sg:tags":[
        "car",
        "dealer"
    ],
    "wof:name":"Union Avenue Motors",
    "wof:placetype":"venue"
},
  "geometry": {"coordinates":[-90.04501500000001,35.140844],"type":"Point"}
}