{
  "type": "Feature",
  "properties": {
    "iso:country":"US",
    "sg:address":"1308 Wendover Rd",
    "sg:city":"Knoxville",
    "sg:classifiers":[
        {
            "category":"Manufacturing",
            "subcategory":"Buildings",
            "type":"Manufacturing & Wholesale Goods"
        }
    ],
    "sg:phone":"+1 865 380 3000",
    "sg:postcode":"37932",
    "sg:province":"TN",
    "sg:tags":[
        "mobile",
        "home",
        "mfg"
    ],
    "wof:name":"Clayton Homes Inc",
    "wof:placetype":"venue"
},
  "geometry": {"coordinates":[-84.20557700000001,35.899732],"type":"Point"}
}