{
  "type": "Feature",
  "properties": {
    "addr:full":"1501 23rd Ave N Nashville TN 37208",
    "addr:housenumber":"1501",
    "addr:postcode":"37208",
    "addr:street":"23Rd Ave N",
    "iso:country":"US",
    "sg:address":"1501 23rd Ave N",
    "sg:city":"Nashville",
    "sg:classifiers":[
        {
            "category":"Organizations",
            "subcategory":"Religious Organization",
            "type":"Services"
        }
    ],
    "sg:phone":"+1 615 320 0892",
    "sg:postcode":"37208",
    "sg:province":"TN",
    "wof:name":"House of God Church",
    "wof:placetype":"venue"
},
  "geometry": {"coordinates":[-86.81277,36.172295],"type":"Point"}
}