{
  "type": "Feature",
  "properties": {
    "addr:full":"210 N Cedar Ave Cookeville TN 38501",
    "addr:housenumber":"210",
    "addr:postcode":"38501",
    "addr:street":"N Cedar Ave",
    "iso:country":"US",
    "sg:address":"210 N Cedar Ave",
    "sg:city":"Cookeville",
    "sg:classifiers":[
        {
            "category":"Health Services",
            "subcategory":"Medical Lab",
            "type":"Services"
        }
    ],
    "sg:phone":"+1 931 528 4032",
    "sg:postcode":"38501",
    "sg:province":"TN",
    "sg:tags":[
        "laboratory"
    ],
    "wof:name":"Laboratory Corp Of America",
    "wof:placetype":"venue"
},
  "geometry": {"coordinates":[-85.507547,36.167243],"type":"Point"}
}