{
  "type": "Feature",
  "properties": {
    "iso:country":"US",
    "sg:address":"2005 Stuart St",
    "sg:city":"Chattanooga",
    "sg:classifiers":[
        {
            "category":"Building & Trades",
            "subcategory":"Construction",
            "type":"Services"
        }
    ],
    "sg:phone":"+1 423 493 0906",
    "sg:postcode":"37406",
    "sg:province":"TN",
    "sg:tags":[
        "designer",
        "dealer",
        "pool",
        "swimming"
    ],
    "wof:name":"Royal Pools",
    "wof:placetype":"venue"
},
  "geometry": {"coordinates":[-85.252797,35.072878],"type":"Point"}
}