{
  "type": "Feature",
  "properties": {
    "iso:country":"US",
    "sg:address":"4439 Blaylock Rd",
    "sg:city":"Crossville",
    "sg:classifiers":[
        {
            "category":"Home & Garden",
            "subcategory":"Garden Supply",
            "type":"Retail Goods"
        }
    ],
    "sg:phone":"+1 931 788 0455",
    "sg:postcode":"38572",
    "sg:province":"TN",
    "sg:tags":[
        "tree",
        "christmas"
    ],
    "wof:name":"Arcy Acres Xmas Tree Farm",
    "wof:placetype":"venue"
},
  "geometry": {"coordinates":[-85.092009,35.780468],"type":"Point"}
}