{
  "type": "Feature",
  "properties": {
    "iso:country":"US",
    "sg:address":"1800 Galleria Blvd",
    "sg:city":"Franklin",
    "sg:classifiers":[
        {
            "category":"Restaurant",
            "type":"Food & Drink"
        }
    ],
    "sg:menulink":"http://www.allmenus.com/tn/brentwood/179187-chick-fil-a/menu/",
    "sg:phone":"+1 615 771 7300",
    "sg:postcode":"37067",
    "sg:province":"TN",
    "sg:tags":[
        "wrap",
        "soup",
        "american",
        "sandwich",
        "salad"
    ],
    "wof:name":"Chick-fil-A",
    "wof:placetype":"venue"
},
  "geometry": {"coordinates":[-86.81488,35.956],"type":"Point"}
}