{
  "type": "Feature",
  "properties": {
    "iso:country":"US",
    "sg:address":"1411 Gallatin Ave",
    "sg:city":"Nashville",
    "sg:classifiers":[
        {
            "category":"Retail",
            "subcategory":"Car Wash",
            "type":"Services"
        }
    ],
    "sg:phone":"+1 615 227 3766",
    "sg:postcode":"37206",
    "sg:province":"TN",
    "sg:tags":[
        "polishing",
        "carwash",
        "washing"
    ],
    "wof:name":"Smith Brothers Car Wash",
    "wof:placetype":"venue"
},
  "geometry": {"coordinates":[-86.743149,36.19501],"type":"Point"}
}