{
  "type": "Feature",
  "properties": {
    "iso:country":"US",
    "sg:address":"5508 Nickle Rd",
    "sg:city":"Knoxville",
    "sg:classifiers":[
        {
            "category":"Building & Trades",
            "subcategory":"Landscaping Services",
            "type":"Services"
        }
    ],
    "sg:phone":"+1 865 212 3131",
    "sg:postcode":"37921",
    "sg:province":"TN",
    "sg:tags":[
        "lawn",
        "maintenance",
        "grounds"
    ],
    "wof:name":"American Lawn & Landscape",
    "wof:placetype":"venue"
},
  "geometry": {"coordinates":[-84.02848899999999,35.986292],"type":"Point"}
}