{
  "type": "Feature",
  "properties": {
    "addr:full":"5169 Winchester Rd Memphis TN 38118",
    "addr:housenumber":"5169",
    "addr:postcode":"38118",
    "addr:street":"Winchester Rd",
    "iso:country":"US",
    "sg:address":"5169 Winchester Rd",
    "sg:city":"Memphis",
    "sg:classifiers":[
        {
            "category":"Banks & Credit Unions",
            "subcategory":"Bank",
            "type":"Services"
        }
    ],
    "sg:phone":"+1 901 795 6072",
    "sg:postcode":"38118",
    "sg:province":"TN",
    "sg:tags":[
        "depository",
        "banking"
    ],
    "sg:website":"www.acecashexpress.com",
    "wof:name":"ACE Cash Express",
    "wof:placetype":"venue"
},
  "geometry": {"coordinates":[-89.889712,35.050537],"type":"Point"}
}