{
  "type": "Feature",
  "properties": {
    "iso:country":"US",
    "sg:address":"401 Old Hickory Blvd",
    "sg:city":"Old Hickory",
    "sg:classifiers":[
        {
            "category":"Building & Trades",
            "subcategory":"Plumbing",
            "type":"Services"
        }
    ],
    "sg:phone":"+1 615 847 0794",
    "sg:postcode":"37138",
    "sg:province":"TN",
    "sg:tags":[
        "pipe"
    ],
    "wof:name":"Colt Atlantic Svc Inc",
    "wof:placetype":"venue"
},
  "geometry": {"coordinates":[-86.652579,36.266649],"type":"Point"}
}