{
  "type": "Feature",
  "properties": {
    "addr:full":"7181 Chevy Chase Dr Memphis TN 38125",
    "addr:housenumber":"7181",
    "addr:postcode":"38125",
    "addr:street":"Chevy Chase Dr",
    "iso:country":"US",
    "sg:address":"7181 Chevy Chase Dr",
    "sg:city":"Memphis",
    "sg:classifiers":[
        {
            "category":"Food & Beverages",
            "subcategory":"Groceries & Convenience Stores",
            "type":"Retail Goods"
        }
    ],
    "sg:phone":"+1 901 529 4399",
    "sg:postcode":"38125",
    "sg:province":"TN",
    "wof:name":"Food Rite",
    "wof:placetype":"venue"
},
  "geometry": {"coordinates":[-89.82344500000001,35.034068],"type":"Point"}
}