{
  "type": "Feature",
  "properties": {
    "iso:country":"US",
    "sg:address":"193 S Tulane Ave",
    "sg:city":"Oak Ridge",
    "sg:classifiers":[
        {
            "category":"Professional",
            "subcategory":"Employment Agencies",
            "type":"Services"
        }
    ],
    "sg:phone":"+1 865 482 0091",
    "sg:postcode":"37830",
    "sg:province":"TN",
    "sg:tags":[
        "help",
        "supply"
    ],
    "wof:name":"Staffing Solutions",
    "wof:placetype":"venue"
},
  "geometry": {"coordinates":[-84.25732600000001,36.013303],"type":"Point"}
}