{
  "type": "Feature",
  "properties": {
    "addr:full":"100 Vermont Ave Oak Ridge TN 37830",
    "addr:housenumber":"100",
    "addr:postcode":"37830",
    "addr:street":"Vermont Ave",
    "iso:country":"US",
    "sg:address":"100 Vermont Ave",
    "sg:city":"Oak Ridge",
    "sg:classifiers":[
        {
            "category":"Professional",
            "type":"Services"
        }
    ],
    "sg:phone":"+1 865 482 9510",
    "sg:postcode":"37830",
    "sg:province":"TN",
    "sg:tags":[
        "establishment"
    ],
    "wof:name":"Referrals",
    "wof:placetype":"venue"
},
  "geometry": {"coordinates":[-84.248333,36.020599],"type":"Point"}
}