{
  "type": "Feature",
  "properties": {
    "iso:country":"US",
    "sg:address":"3013 Huntsville Hwy",
    "sg:city":"Fayetteville",
    "sg:classifiers":[
        {
            "category":"Manufacturing",
            "subcategory":"Tools & Machinery",
            "type":"Manufacturing & Wholesale Goods"
        }
    ],
    "sg:phone":"+1 931 433 4330",
    "sg:postcode":"37334",
    "sg:province":"TN",
    "sg:tags":[
        "structural",
        "industrial",
        "sheet",
        "metalwork",
        "mfg"
    ],
    "wof:name":"Alaten Product",
    "wof:placetype":"venue"
},
  "geometry": {"coordinates":[-86.574668,35.040033],"type":"Point"}
}