{
  "type": "Feature",
  "properties": {
    "addr:full":"733 Bell Buckle Wartrace Rd Wartrace TN 37183",
    "addr:housenumber":"733",
    "addr:postcode":"37183",
    "addr:street":"Bell Buckle Wartrace Rd",
    "iso:country":"US",
    "sg:address":"733 Bell Buckle Wartrace Rd",
    "sg:city":"Wartrace",
    "sg:classifiers":[
        {
            "category":"Recreation",
            "type":"Entertainment"
        }
    ],
    "sg:phone":"+1 931 684 0200",
    "sg:postcode":"37183",
    "sg:province":"TN",
    "sg:tags":[
        "stable"
    ],
    "wof:name":"Guthrie Stables",
    "wof:placetype":"venue"
},
  "geometry": {"coordinates":[-86.341596,35.530693],"type":"Point"}
}