{
  "type": "Feature",
  "properties": {
    "iso:country":"US",
    "sg:address":"199 Benford Rd",
    "sg:city":"Shelbyville",
    "sg:classifiers":[
        {
            "category":"Farming",
            "subcategory":"Dairy Farm",
            "type":"Manufacturing & Wholesale Goods"
        }
    ],
    "sg:phone":"+1 931 684 9812",
    "sg:postcode":"37160",
    "sg:province":"TN",
    "wof:name":"Davhil Farms",
    "wof:placetype":"venue"
},
  "geometry": {"coordinates":[-86.42544599999999,35.563983],"type":"Point"}
}