{
  "type": "Feature",
  "properties": {
    "iso:country":"US",
    "sg:address":"2749 Park Ave",
    "sg:city":"Memphis",
    "sg:classifiers":[
        {
            "category":"Wholesale",
            "subcategory":"Hardware",
            "type":"Manufacturing & Wholesale Goods"
        }
    ],
    "sg:phone":"+1 901 458 8333",
    "sg:postcode":"38114",
    "sg:province":"TN",
    "sg:tags":[
        "supply",
        "fixture",
        "equipment",
        "part",
        "plumbing",
        "retail",
        "supplies-wholesale",
        "manufacturer"
    ],
    "sg:website":"http://www.allriteplumbingparts.com",
    "wof:name":"All-Rite Plumbing Parts Inc",
    "wof:placetype":"venue"
},
  "geometry": {"coordinates":[-89.970551,35.108089],"type":"Point"}
}