{
  "type": "Feature",
  "properties": {
    "iso:country":"US",
    "sg:address":"9514 Daybreak Dr",
    "sg:city":"Knoxville",
    "sg:classifiers":[
        {
            "category":"Home & Garden",
            "subcategory":"Building Materials",
            "type":"Retail Goods"
        }
    ],
    "sg:phone":"+1 865 693 0016",
    "sg:postcode":"37931",
    "sg:province":"TN",
    "sg:tags":[
        "glass",
        "window",
        "plate"
    ],
    "wof:name":"Hatchett Automotive Glass",
    "wof:placetype":"venue"
},
  "geometry": {"coordinates":[-84.11911600000001,35.956585],"type":"Point"}
}