{
  "type": "Feature",
  "properties": {
    "addr:full":"2884 Kenneth St Memphis TN 38128",
    "addr:housenumber":"2884",
    "addr:postcode":"38128",
    "addr:street":"Kenneth St",
    "iso:country":"US",
    "sg:address":"2884 Kenneth St",
    "sg:city":"Memphis",
    "sg:classifiers":[
        {
            "category":"Manufacturing",
            "subcategory":"Buildings",
            "type":"Manufacturing & Wholesale Goods"
        },
        {
            "category":"Home & Garden",
            "subcategory":"Building Materials",
            "type":"Retail Goods"
        },
        {
            "category":"Building & Trades",
            "subcategory":"Construction",
            "type":"Services"
        }
    ],
    "sg:phone":"+1 901 313 4831",
    "sg:postcode":"38128",
    "sg:province":"TN",
    "sg:tags":[
        "roofing",
        "industrial",
        "altering",
        "consultant",
        "builder",
        "siding",
        "contractor",
        "window",
        "contractors-commercial",
        "remodeling"
    ],
    "sg:website":"http://morrisgeneralcontracting.com",
    "wof:name":"Morris General Construction & Remodeling, Inc.",
    "wof:placetype":"venue"
},
  "geometry": {"coordinates":[-89.90538599999999,35.204386],"type":"Point"}
}