{
  "type": "Feature",
  "properties": {
    "addr:full":"7313 Valley Ln Hixson TN 37343",
    "addr:housenumber":"7313",
    "addr:postcode":"37343",
    "addr:street":"Valley Ln",
    "iso:country":"US",
    "sg:address":"7313 Valley Ln",
    "sg:city":"Hixson",
    "sg:classifiers":[
        {
            "category":"Professional",
            "subcategory":"Business Services",
            "type":"Services"
        }
    ],
    "sg:phone":"+1 423 842 7944",
    "sg:postcode":"37343",
    "sg:province":"TN",
    "wof:name":"Three Blind Mice",
    "wof:placetype":"venue"
},
  "geometry": {"coordinates":[-85.195994,35.189791],"type":"Point"}
}