{
  "type": "Feature",
  "properties": {
    "iso:country":"US",
    "sg:address":"302 3rd St",
    "sg:city":"Lawrenceburg",
    "sg:classifiers":[
        {
            "category":"Home & Garden",
            "subcategory":"Building Materials",
            "type":"Retail Goods"
        }
    ],
    "sg:phone":"+1 931 762 4185",
    "sg:postcode":"38464",
    "sg:province":"TN",
    "sg:tags":[
        "paint"
    ],
    "wof:name":"Sutton's Decorating Ctr",
    "wof:placetype":"venue"
},
  "geometry": {"coordinates":[-87.32790799999999,35.246307],"type":"Point"}
}