{
  "type": "Feature",
  "properties": {
    "addr:full":"715 Church St Nashville TN 37219",
    "addr:housenumber":"715",
    "addr:postcode":"37219",
    "addr:street":"Church St",
    "iso:country":"US",
    "sg:address":"715 Church St",
    "sg:city":"Nashville",
    "sg:classifiers":[
        {
            "category":"Personal",
            "subcategory":"Beauty Salon",
            "type":"Services"
        }
    ],
    "sg:phone":"+1 615 255 8617",
    "sg:postcode":"37219",
    "sg:province":"TN",
    "sg:tags":[
        "shop"
    ],
    "wof:name":"Flanarys Salon of Beauty",
    "wof:placetype":"venue"
},
  "geometry": {"coordinates":[-86.782715,36.162015],"type":"Point"}
}