{
  "type": "Feature",
  "properties": {
    "iso:country":"US",
    "sg:address":"3646 Murfreesboro Pike",
    "sg:city":"Antioch",
    "sg:classifiers":[
        {
            "category":"Organizations",
            "subcategory":"Religious Organization",
            "type":"Services"
        }
    ],
    "sg:phone":"+1 615 641 5433",
    "sg:postcode":"37013",
    "sg:province":"TN",
    "sg:tags":[
        "church"
    ],
    "sg:website":"www.renewedmind.com",
    "wof:name":"Spirit Of Life Church",
    "wof:placetype":"venue"
},
  "geometry": {"coordinates":[-86.611791,36.047822],"type":"Point"}
}