{
  "type": "Feature",
  "properties": {
    "iso:country":"US",
    "sg:address":"134 White Oak Ln",
    "sg:city":"Townsend",
    "sg:classifiers":[
        {
            "category":"Travel",
            "subcategory":"Hotels & Motels",
            "type":"Entertainment"
        }
    ],
    "sg:phone":"+1 865 448 6715",
    "sg:postcode":"37882",
    "sg:province":"TN",
    "sg:tags":[
        "chalet",
        "rental",
        "cabin"
    ],
    "wof:name":"Rustling Pines Cabins",
    "wof:placetype":"venue"
},
  "geometry": {"coordinates":[-83.793137,35.677079],"type":"Point"}
}