{
  "type": "Feature",
  "properties": {
    "iso:country":"US",
    "sg:address":"702 Adams Dr",
    "sg:city":"Shelbyville",
    "sg:classifiers":[
        {
            "category":"Shopping",
            "subcategory":"Florist",
            "type":"Retail Goods"
        }
    ],
    "sg:phone":"+1 931 684 3151",
    "sg:postcode":"37160",
    "sg:province":"TN",
    "wof:name":"Mary's Flowers & Gifts",
    "wof:placetype":"venue"
},
  "geometry": {"coordinates":[-86.470213,35.473128],"type":"Point"}
}