{
  "type": "Feature",
  "properties": {
    "iso:country":"US",
    "sg:address":"23 Lock Seven Ln",
    "sg:city":"Carthage",
    "sg:classifiers":[
        {
            "category":"Organizations",
            "subcategory":"Religious Organization",
            "type":"Services"
        }
    ],
    "sg:phone":"+1 615 444 1136",
    "sg:postcode":"37030",
    "sg:province":"TN",
    "wof:name":"Harbor of Love Chapel",
    "wof:placetype":"venue"
},
  "geometry": {"coordinates":[-86.01687200000001,36.269507],"type":"Point"}
}