{
  "type": "Feature",
  "properties": {
    "addr:full":"1407 Union Ave Memphis TN 38104",
    "addr:housenumber":"1407",
    "addr:postcode":"38104",
    "addr:street":"Union Ave",
    "iso:country":"US",
    "sg:address":"1407 Union Ave",
    "sg:city":"Memphis",
    "sg:classifiers":[
        {
            "category":"Government",
            "subcategory":"Office",
            "type":"Public Place"
        }
    ],
    "sg:phone":"+1 901 820 3400",
    "sg:postcode":"38104",
    "sg:province":"TN",
    "sg:tags":[
        "administrative",
        "program",
        "health"
    ],
    "wof:name":"Mpca Admin Office",
    "wof:placetype":"venue"
},
  "geometry": {"coordinates":[-90.01529600000001,35.136703],"type":"Point"}
}