{
  "type": "Feature",
  "properties": {
    "iso:country":"US",
    "sg:address":"6910 Central Avenue Pike",
    "sg:city":"Knoxville",
    "sg:classifiers":[
        {
            "category":"Wholesale",
            "subcategory":"Machinery & Supplies",
            "type":"Manufacturing & Wholesale Goods"
        }
    ],
    "sg:phone":"+1 865 688 0943",
    "sg:postcode":"37918",
    "sg:province":"TN",
    "sg:tags":[
        "industrial"
    ],
    "wof:name":"Contractor & Industrial Sup Co",
    "wof:placetype":"venue"
},
  "geometry": {"coordinates":[-83.99548900000001,36.029963],"type":"Point"}
}