{
  "type": "Feature",
  "properties": {
    "addr:full":"1127 US Hwy 412 E Jackson TN 38305",
    "addr:housenumber":"1127",
    "addr:postcode":"38305",
    "addr:street":"Us Hwy 412 E",
    "iso:country":"US",
    "sg:address":"1127 US Hwy 412 E",
    "sg:city":"Jackson",
    "sg:classifiers":[
        {
            "category":"Manufacturing",
            "subcategory":"Wood Products",
            "type":"Manufacturing & Wholesale Goods"
        }
    ],
    "sg:phone":"+1 731 424 7269",
    "sg:postcode":"38305",
    "sg:province":"TN",
    "sg:tags":[
        "pallet",
        "skid"
    ],
    "wof:name":"Mc Kees' & Essary Pallet Shop",
    "wof:placetype":"venue"
},
  "geometry": {"coordinates":[-88.65233499999999,35.703442],"type":"Point"}
}