{
  "type": "Feature",
  "properties": {
    "iso:country":"US",
    "sg:address":"928 N Jackson St",
    "sg:city":"Tullahoma",
    "sg:classifiers":[
        {
            "category":"Shopping",
            "type":"Retail Goods"
        }
    ],
    "sg:phone":"+1 931 461 5250",
    "sg:postcode":"37388",
    "sg:province":"TN",
    "sg:tags":[
        "equipment",
        "care",
        "health",
        "home"
    ],
    "wof:name":"Gap Home Medical",
    "wof:placetype":"venue"
},
  "geometry": {"coordinates":[-86.222371,35.373985],"type":"Point"}
}