{
  "type": "Feature",
  "properties": {
    "iso:country":"US",
    "sg:address":"2317 Johnston St",
    "sg:city":"Knoxville",
    "sg:classifiers":[
        {
            "category":"Building & Trades",
            "subcategory":"Cleaning & Sanitation",
            "type":"Services"
        },
        {
            "category":"Building & Trades",
            "subcategory":"Construction",
            "type":"Services"
        }
    ],
    "sg:phone":"+1 865 971 4871",
    "sg:postcode":"37921",
    "sg:province":"TN",
    "sg:tags":[
        "system",
        "specialty",
        "duct",
        "heating",
        "contractor",
        "air conditioning"
    ],
    "wof:name":"Air Comfort Supply Co",
    "wof:placetype":"venue"
},
  "geometry": {"coordinates":[-83.94805599999999,35.982209],"type":"Point"}
}