{
  "type": "Feature",
  "properties": {
    "addr:full":"4481 US Hwy 11W Blountville TN 37617",
    "addr:housenumber":"4481",
    "addr:postcode":"37617",
    "addr:street":"Us Hwy 11W",
    "iso:country":"US",
    "sg:address":"4481 US Hwy 11W",
    "sg:city":"Blountville",
    "sg:phone":"+1 423 323 5131",
    "sg:postcode":"37617",
    "sg:province":"TN",
    "sg:tags":[
        "farm",
        "field",
        "tobacco",
        "crop"
    ],
    "wof:name":"D Justice",
    "wof:placetype":"venue"
},
  "geometry": {"coordinates":[-82.39147,36.571531],"type":"Point"}
}