{
  "type": "Feature",
  "properties": {
    "addr:full":"505 Waxwood Dr Brentwood TN 37027",
    "addr:housenumber":"505",
    "addr:postcode":"37027",
    "addr:street":"Waxwood Dr",
    "iso:country":"US",
    "sg:address":"505 Waxwood Dr",
    "sg:city":"Brentwood",
    "sg:classifiers":[
        {
            "category":"Professional",
            "subcategory":"Business Services",
            "type":"Services"
        }
    ],
    "sg:phone":"+1 615 373 7327",
    "sg:postcode":"37027",
    "sg:province":"TN",
    "wof:name":"Laura Coyle Interior Allied",
    "wof:placetype":"venue"
},
  "geometry": {"coordinates":[-86.83435900000001,36.028257],"type":"Point"}
}