{
  "type": "Feature",
  "properties": {
    "iso:country":"US",
    "sg:address":"1634 Rocky Hollow Rd",
    "sg:city":"Germantown",
    "sg:classifiers":[
        {
            "category":"Building & Trades",
            "subcategory":"Landscaping Services",
            "type":"Services"
        }
    ],
    "sg:phone":"+1 901 309 2900",
    "sg:postcode":"38138",
    "sg:province":"TN",
    "sg:tags":[
        "landscape",
        "contractor"
    ],
    "wof:name":"Wine Landscaping",
    "wof:placetype":"venue"
},
  "geometry": {"coordinates":[-89.79439000000001,35.10526],"type":"Point"}
}