{
  "type": "Feature",
  "properties": {
    "iso:country":"US",
    "sg:address":"3434 Golf Club Ln",
    "sg:city":"Nashville",
    "sg:classifiers":[
        {
            "category":"Wholesale",
            "subcategory":"Apparel",
            "type":"Manufacturing & Wholesale Goods"
        }
    ],
    "sg:phone":"+1 877 718 9403",
    "sg:postcode":"37215",
    "sg:province":"TN",
    "sg:tags":[
        "swimwear",
        "manufacturer"
    ],
    "wof:name":"Agon Swimcom",
    "wof:placetype":"venue"
},
  "geometry": {"coordinates":[-86.809816,36.117924],"type":"Point"}
}