{
  "type": "Feature",
  "properties": {
    "iso:country":"US",
    "sg:address":"821 Samaria Bend Rd",
    "sg:city":"Dyersburg",
    "sg:classifiers":[
        {
            "category":"Food & Beverages",
            "subcategory":"Bakery",
            "type":"Retail Goods"
        }
    ],
    "sg:phone":"+1 731 285 5391",
    "sg:postcode":"38024",
    "sg:province":"TN",
    "sg:tags":[
        "grocery"
    ],
    "wof:name":"Bunny Bread",
    "wof:placetype":"venue"
},
  "geometry": {"coordinates":[-89.40097799999999,36.011909],"type":"Point"}
}