{
  "type": "Feature",
  "properties": {
    "iso:country":"US",
    "sg:address":"1544 Bear Creek Pike",
    "sg:city":"Columbia",
    "sg:classifiers":[
        {
            "category":"Travel",
            "subcategory":"Hotels & Motels",
            "type":"Entertainment"
        }
    ],
    "sg:phone":"+1 931 388 2500",
    "sg:postcode":"38401",
    "sg:province":"TN",
    "wof:name":"Comfort Inn",
    "wof:placetype":"venue"
},
  "geometry": {"coordinates":[-86.89876599999999,35.643052],"type":"Point"}
}