{
  "type": "Feature",
  "properties": {
    "iso:country":"US",
    "sg:address":"1204 Kenesaw Ave SW",
    "sg:city":"Knoxville",
    "sg:classifiers":[
        {
            "category":"Health Services",
            "subcategory":"Health Practitioner",
            "type":"Services"
        }
    ],
    "sg:phone":"+1 865 363 0240",
    "sg:postcode":"37919",
    "sg:province":"TN",
    "wof:name":"Barbara L Taylor",
    "wof:placetype":"venue"
},
  "geometry": {"coordinates":[-83.963567,35.93475],"type":"Point"}
}