{
  "type": "Feature",
  "properties": {
    "addr:full":"805 Neelys Chase Dr Madison TN 37115",
    "addr:housenumber":"805",
    "addr:postcode":"37115",
    "addr:street":"Neelys Chase Dr",
    "iso:country":"US",
    "sg:address":"805 Neelys Chase Dr",
    "sg:city":"Madison",
    "sg:classifiers":[
        {
            "category":"Communications",
            "subcategory":"Film & Video Production",
            "type":"Services"
        }
    ],
    "sg:phone":"+1 615 860 8944",
    "sg:postcode":"37115",
    "sg:province":"TN",
    "sg:tags":[
        "audio"
    ],
    "sg:website":"www.doormanproductions.com",
    "wof:name":"Doorman Productions",
    "wof:placetype":"venue"
},
  "geometry": {"coordinates":[-86.703264,36.254008],"type":"Point"}
}