{
  "type": "Feature",
  "properties": {
    "addr:full":"6115 Charlotte Pike Nashville TN 37209",
    "addr:housenumber":"6115",
    "addr:postcode":"37209",
    "addr:street":"Charlotte Pike",
    "iso:country":"US",
    "sg:address":"6115 Charlotte Pike",
    "sg:city":"Nashville",
    "sg:classifiers":[
        {
            "category":"Building & Trades",
            "subcategory":"Landscaping Services",
            "type":"Services"
        }
    ],
    "sg:phone":"+1 615 352 1965",
    "sg:postcode":"37209",
    "sg:province":"TN",
    "sg:tags":[
        "landscape",
        "contractor"
    ],
    "wof:name":"Tritschler's Landscape Contrs",
    "wof:placetype":"venue"
},
  "geometry": {"coordinates":[-86.86758399999999,36.148028],"type":"Point"}
}