{
  "type": "Feature",
  "properties": {
    "iso:country":"US",
    "sg:address":"672 Cole Rd",
    "sg:city":"Sevierville",
    "sg:classifiers":[
        {
            "category":"Building & Trades",
            "subcategory":"Construction",
            "type":"Services"
        }
    ],
    "sg:phone":"+1 865 453 2611",
    "sg:postcode":"37876",
    "sg:province":"TN",
    "sg:tags":[
        "water",
        "well",
        "drilling"
    ],
    "wof:name":"Ronald E Cole Well Drilling",
    "wof:placetype":"venue"
},
  "geometry": {"coordinates":[-83.563472,35.883283],"type":"Point"}
}