{
  "type": "Feature",
  "properties": {
    "iso:country":"US",
    "sg:address":"4389 New Getwell Rd",
    "sg:city":"Memphis",
    "sg:classifiers":[
        {
            "category":"Wholesale",
            "subcategory":"Durable Goods & Equipment",
            "type":"Manufacturing & Wholesale Goods"
        }
    ],
    "sg:phone":"+1 901 843 7696",
    "sg:postcode":"38118",
    "sg:province":"TN",
    "sg:tags":[
        "optical"
    ],
    "wof:name":"AES Optics LLC",
    "wof:placetype":"venue"
},
  "geometry": {"coordinates":[-89.937072,35.028928],"type":"Point"}
}