{
  "type": "Feature",
  "properties": {
    "addr:full":"311 Gray Station Sulphur Springs Rd Jonesborough TN 37659",
    "addr:housenumber":"311",
    "addr:postcode":"37659",
    "addr:street":"Gray Station Sulphur Springs Rd",
    "iso:country":"US",
    "sg:address":"311 Gray Station Sulphur Springs Rd",
    "sg:city":"Jonesborough",
    "sg:classifiers":[
        {
            "category":"Organizations",
            "subcategory":"Religious Organization",
            "type":"Services"
        }
    ],
    "sg:phone":"+1 423 753 8860",
    "sg:postcode":"37659",
    "sg:province":"TN",
    "sg:tags":[
        "church"
    ],
    "wof:name":"Gray Church of God",
    "wof:placetype":"venue"
},
  "geometry": {"coordinates":[-82.509069,36.380917],"type":"Point"}
}