{
  "type": "Feature",
  "properties": {
    "addr:full":"50 N Dunlap St Memphis TN 38103",
    "addr:housenumber":"50",
    "addr:postcode":"38103",
    "addr:street":"N Dunlap St",
    "iso:country":"US",
    "sg:address":"50 N Dunlap St",
    "sg:city":"Memphis",
    "sg:classifiers":[
        {
            "category":"Health Services",
            "subcategory":"Doctor",
            "type":"Services"
        }
    ],
    "sg:phone":"+1 901 572 3132",
    "sg:postcode":"38103",
    "sg:province":"TN",
    "sg:tags":[
        "physician",
        "surgeon"
    ],
    "wof:name":"Helen G Beeman MD",
    "wof:placetype":"venue"
},
  "geometry": {"coordinates":[-90.03330099999999,35.141225],"type":"Point"}
}