{
  "type": "Feature",
  "properties": {
    "iso:country":"US",
    "sg:address":"123 E Main St",
    "sg:city":"Jonesborough",
    "sg:classifiers":[
        {
            "category":"Shopping",
            "subcategory":"Hobbies, Toys, & Games",
            "type":"Retail Goods"
        }
    ],
    "sg:phone":"+1 423 913 2663",
    "sg:postcode":"37659",
    "sg:province":"TN",
    "wof:name":"Lollipop Shop",
    "wof:placetype":"venue"
},
  "geometry": {"coordinates":[-82.47208500000001,36.2947],"type":"Point"}
}