{
  "type": "Feature",
  "properties": {
    "iso:country":"US",
    "sg:address":"290 Jaco St",
    "sg:city":"Rock Island",
    "sg:classifiers":[
        {
            "category":"Government",
            "subcategory":"Office",
            "type":"Public Place"
        }
    ],
    "sg:phone":"+1 931 686 8422",
    "sg:postcode":"38581",
    "sg:province":"TN",
    "sg:tags":[
        "county",
        "program"
    ],
    "wof:name":"Warren County Sanitation Dept",
    "wof:placetype":"venue"
},
  "geometry": {"coordinates":[-85.63285500000001,35.77337],"type":"Point"}
}