{
  "type": "Feature",
  "properties": {
    "iso:country":"US",
    "sg:address":"12114 Nashville Hwy",
    "sg:city":"Mc Minnville",
    "sg:phone":"+1 931 939 2069",
    "sg:postcode":"37110",
    "sg:province":"TN",
    "sg:tags":[
        "farm",
        "wheat"
    ],
    "wof:name":"Jimmy Ford",
    "wof:placetype":"venue"
},
  "geometry": {"coordinates":[-85.96284199999999,35.75159],"type":"Point"}
}