{
  "type": "Feature",
  "properties": {
    "iso:country":"US",
    "sg:address":"476 Watkins Chapel Rd",
    "sg:city":"Morristown",
    "sg:classifiers":[
        {
            "category":"Professional",
            "type":"Services"
        }
    ],
    "sg:phone":"+1 423 587 1371",
    "sg:postcode":"37813",
    "sg:province":"TN",
    "sg:tags":[
        "establishment"
    ],
    "wof:name":"Global General Corp",
    "wof:placetype":"venue"
},
  "geometry": {"coordinates":[-83.278499,36.159345],"type":"Point"}
}