{
  "type": "Feature",
  "properties": {
    "iso:country":"US",
    "sg:address":"223 Campus Dr",
    "sg:city":"Hendersonville",
    "sg:classifiers":[
        {
            "category":"Organizations",
            "subcategory":"Religious Organization",
            "type":"Services"
        }
    ],
    "sg:phone":"+1 615 851 4440",
    "sg:postcode":"37075",
    "sg:province":"TN",
    "sg:tags":[
        "church"
    ],
    "sg:website":"www.bbfhtn.org",
    "wof:name":"Believers Baptist Fellowship",
    "wof:placetype":"venue"
},
  "geometry": {"coordinates":[-86.62528500000001,36.30042],"type":"Point"}
}