{
  "type": "Feature",
  "properties": {
    "addr:full":"1114 19th Ave S Nashville TN 37212",
    "addr:housenumber":"1114",
    "addr:postcode":"37212",
    "addr:street":"19Th Ave S",
    "iso:country":"US",
    "sg:address":"1114 19th Ave S",
    "sg:city":"Nashville",
    "sg:classifiers":[
        {
            "category":"Organizations",
            "subcategory":"Non-profit Organization",
            "type":"Services"
        }
    ],
    "sg:phone":"+1 615 936 5000",
    "sg:postcode":"37212",
    "sg:province":"TN",
    "sg:tags":[
        "medicine",
        "practitioner",
        "alternative",
        "health"
    ],
    "sg:website":"http://www.peabody.vanderbilt.edu",
    "wof:name":"Vanderbilt Bill Wilkerson Center",
    "wof:placetype":"venue"
},
  "geometry": {"coordinates":[-86.79750799999999,36.144711],"type":"Point"}
}