{
  "type": "Feature",
  "properties": {
    "iso:country":"US",
    "sg:address":"2066 Hwy 68",
    "sg:city":"Crossville",
    "sg:classifiers":[
        {
            "category":"Retail",
            "subcategory":"Animal Services",
            "type":"Services"
        }
    ],
    "sg:phone":"+1 931 456 8170",
    "sg:postcode":"38555",
    "sg:province":"TN",
    "sg:tags":[
        "pet",
        "grooming",
        "washing"
    ],
    "wof:name":"Pawfect Style",
    "wof:placetype":"venue"
},
  "geometry": {"coordinates":[-84.95339,35.901601],"type":"Point"}
}