{
  "type": "Feature",
  "properties": {
    "addr:full":"941 Lake Forrest Dr Spring City TN 37381",
    "addr:housenumber":"941",
    "addr:postcode":"37381",
    "addr:street":"Lake Forrest Dr",
    "iso:country":"US",
    "sg:address":"941 Lake Forrest Dr",
    "sg:city":"Spring City",
    "sg:classifiers":[
        {
            "category":"Shopping",
            "subcategory":"Pharmacy",
            "type":"Retail Goods"
        }
    ],
    "sg:phone":"+1 423 452 0999",
    "sg:postcode":"37381",
    "sg:province":"TN",
    "sg:tags":[
        "mail",
        "ship",
        "medic",
        "through",
        "order"
    ],
    "wof:name":"Owens Country Herbs Inc",
    "wof:placetype":"venue"
},
  "geometry": {"coordinates":[-84.805577,35.649607],"type":"Point"}
}