{
  "type": "Feature",
  "properties": {
    "iso:country":"US",
    "sg:address":"3514 Buchanan Ave",
    "sg:city":"Memphis",
    "sg:classifiers":[
        {
            "category":"Building & Trades",
            "subcategory":"Cleaning & Sanitation",
            "type":"Services"
        }
    ],
    "sg:phone":"+1 901 327 3686",
    "sg:postcode":"38122",
    "sg:province":"TN",
    "sg:tags":[
        "janitor"
    ],
    "wof:name":"Rodney & Darrell Strong Clean",
    "wof:placetype":"venue"
},
  "geometry": {"coordinates":[-89.945205,35.165137],"type":"Point"}
}