{
  "type": "Feature",
  "properties": {
    "iso:country":"US",
    "sg:address":"1902 Taft Hwy",
    "sg:city":"Signal Mountain",
    "sg:classifiers":[
        {
            "category":"Personal",
            "subcategory":"Beauty Salon",
            "type":"Services"
        }
    ],
    "sg:phone":"+1 423 886 9098",
    "sg:postcode":"37377",
    "sg:province":"TN",
    "wof:name":"Diva's Hair & Tanning",
    "wof:placetype":"venue"
},
  "geometry": {"coordinates":[-85.31602700000001,35.156797],"type":"Point"}
}