{
  "type": "Feature",
  "properties": {
    "iso:country":"US",
    "sg:address":"110 E Main St",
    "sg:city":"Jonesborough",
    "sg:classifiers":[
        {
            "category":"Government",
            "subcategory":"Court House",
            "type":"Public Place"
        }
    ],
    "sg:phone":"+1 423 753 1688",
    "sg:postcode":"37659",
    "sg:province":"TN",
    "wof:name":"Washington County Court House",
    "wof:placetype":"venue"
},
  "geometry": {"coordinates":[-82.473069,36.294397],"type":"Point"}
}