{
  "type": "Feature",
  "properties": {
    "addr:full":"373 Inman St E Cleveland TN 37311",
    "addr:housenumber":"373",
    "addr:postcode":"37311",
    "addr:street":"Inman St E",
    "iso:country":"US",
    "sg:address":"373 Inman St E",
    "sg:city":"Cleveland",
    "sg:classifiers":[
        {
            "category":"Autos & Motor Vehicles",
            "subcategory":"Automobile Sales",
            "type":"Retail Goods"
        }
    ],
    "sg:phone":"+1 423 339 3999",
    "sg:postcode":"37311",
    "sg:province":"TN",
    "sg:tags":[
        "used"
    ],
    "wof:name":"Cars Of Cleveland",
    "wof:placetype":"venue"
},
  "geometry": {"coordinates":[-84.871965,35.157393],"type":"Point"}
}