{
  "type": "Feature",
  "properties": {
    "addr:full":"8979 Big Oak Dr Murfreesboro TN 37129",
    "addr:housenumber":"8979",
    "addr:postcode":"37129",
    "addr:street":"Big Oak Dr",
    "iso:country":"US",
    "sg:address":"8979 Big Oak Dr",
    "sg:city":"Murfreesboro",
    "sg:classifiers":[
        {
            "category":"Home & Garden",
            "subcategory":"Mobile Homes",
            "type":"Retail Goods"
        }
    ],
    "sg:phone":"+1 615 896 2309",
    "sg:postcode":"37129",
    "sg:province":"TN",
    "wof:name":"Holly Grove Homes",
    "wof:placetype":"venue"
},
  "geometry": {"coordinates":[-86.38217899999999,35.966581],"type":"Point"}
}