{
  "type": "Feature",
  "properties": {
    "iso:country":"US",
    "sg:address":"111 Buffalo Valley Church Rd",
    "sg:city":"Johnson City",
    "sg:classifiers":[
        {
            "category":"Organizations",
            "subcategory":"Religious Organization",
            "type":"Services"
        }
    ],
    "sg:phone":"+1 423 926 8368",
    "sg:postcode":"37601",
    "sg:province":"TN",
    "sg:tags":[
        "church"
    ],
    "wof:name":"Buffalo Valley Christn Church",
    "wof:placetype":"venue"
},
  "geometry": {"coordinates":[-82.32207099999999,36.286327],"type":"Point"}
}