{
  "type": "Feature",
  "properties": {
    "addr:full":"5751 Uptain Rd Chattanooga TN 37411",
    "addr:housenumber":"5751",
    "addr:postcode":"37411",
    "addr:street":"Uptain Rd",
    "iso:country":"US",
    "sg:address":"5751 Uptain Rd",
    "sg:city":"Chattanooga",
    "sg:classifiers":[
        {
            "category":"Banks & Credit Unions",
            "subcategory":"Bank",
            "type":"Services"
        }
    ],
    "sg:phone":"+1 423 485 9963",
    "sg:postcode":"37411",
    "sg:province":"TN",
    "sg:tags":[
        "broker",
        "mortgage"
    ],
    "wof:name":"Christian Mortgage Corp",
    "wof:placetype":"venue"
},
  "geometry": {"coordinates":[-85.241891,35.02862],"type":"Point"}
}