{
  "type": "Feature",
  "properties": {
    "iso:country":"US",
    "sg:address":"137 Quail Ridge Rd",
    "sg:city":"Johnson City",
    "sg:classifiers":[
        {
            "category":"Autos & Motor Vehicles",
            "subcategory":"Auto Supplies",
            "type":"Retail Goods"
        }
    ],
    "sg:phone":"+1 423 543 0468",
    "sg:postcode":"37601",
    "sg:province":"TN",
    "sg:tags":[
        "automotive",
        "parts"
    ],
    "wof:name":"Ball Parts Supply",
    "wof:placetype":"venue"
},
  "geometry": {"coordinates":[-82.27173500000001,36.299702],"type":"Point"}
}