{
  "type": "Feature",
  "properties": {
    "addr:full":"692 Plantation Rd Munford TN 38058",
    "addr:housenumber":"692",
    "addr:postcode":"38058",
    "addr:street":"Plantation Rd",
    "iso:country":"US",
    "sg:address":"692 Plantation Rd",
    "sg:city":"Munford",
    "sg:classifiers":[
        {
            "category":"Retail",
            "subcategory":"Veterinary Services",
            "type":"Services"
        }
    ],
    "sg:phone":"+1 901 837 2205",
    "sg:postcode":"38058",
    "sg:province":"TN",
    "sg:tags":[
        "veterinarian",
        "specialty"
    ],
    "wof:name":"Robert Y Hanks",
    "wof:placetype":"venue"
},
  "geometry": {"coordinates":[-89.828281,35.474864],"type":"Point"}
}