{
  "type": "Feature",
  "properties": {
    "addr:full":"363 Oak Hill Dr Sparta TN 38583",
    "addr:housenumber":"363",
    "addr:postcode":"38583",
    "addr:street":"Oak Hill Dr",
    "iso:country":"US",
    "sg:address":"363 Oak Hill Dr",
    "sg:city":"Sparta",
    "sg:classifiers":[
        {
            "category":"Real Estate",
            "subcategory":"Real Estate Operator",
            "type":"Services"
        }
    ],
    "sg:phone":"+1 931 836 8127",
    "sg:postcode":"38583",
    "sg:province":"TN",
    "sg:tags":[
        "building",
        "apartment"
    ],
    "wof:name":"Volunteer Housing",
    "wof:placetype":"venue"
},
  "geometry": {"coordinates":[-85.452917,35.927643],"type":"Point"}
}