{
  "type": "Feature",
  "properties": {
    "addr:full":"1204 Houston Levee Rd Arlington TN 38018",
    "addr:housenumber":"1204",
    "addr:postcode":"38018",
    "addr:street":"Houston Levee Rd",
    "iso:country":"US",
    "sg:address":"1204 Houston Levee Rd",
    "sg:city":"Arlington",
    "sg:classifiers":[
        {
            "category":"Insurance",
            "subcategory":"Insurance Agent",
            "type":"Services"
        }
    ],
    "sg:phone":"+1 901 380 8477",
    "sg:postcode":"38018",
    "sg:province":"TN",
    "wof:name":"Workplace",
    "wof:placetype":"venue"
},
  "geometry": {"coordinates":[-89.72743199999999,35.159152],"type":"Point"}
}