{
  "type": "Feature",
  "properties": {
    "addr:full":"4965 Peavine Rd Crossville TN 38571",
    "addr:housenumber":"4965",
    "addr:postcode":"38571",
    "addr:street":"Peavine Rd",
    "iso:country":"US",
    "sg:address":"4965 Peavine Rd",
    "sg:city":"Crossville",
    "sg:classifiers":[
        {
            "category":"Organizations",
            "subcategory":"Religious Organization",
            "type":"Services"
        }
    ],
    "sg:phone":"+1 931 456 7626",
    "sg:postcode":"38571",
    "sg:province":"TN",
    "sg:website":"www.geffairfield.com",
    "wof:name":"Grace Evangelical Fellowship",
    "wof:placetype":"venue"
},
  "geometry": {"coordinates":[-84.91934999999999,35.999936],"type":"Point"}
}