{
  "type": "Feature",
  "properties": {
    "iso:country":"US",
    "sg:address":"221 N Church St",
    "sg:city":"Murfreesboro",
    "sg:classifiers":[
        {
            "category":"Shopping",
            "type":"Retail Goods"
        }
    ],
    "sg:phone":"+1 615 217 9342",
    "sg:postcode":"37130",
    "sg:province":"TN",
    "sg:tags":[
        "equipment",
        "telephone",
        "supply"
    ],
    "wof:name":"EMG Communications",
    "wof:placetype":"venue"
},
  "geometry": {"coordinates":[-86.39121299999999,35.847876],"type":"Point"}
}