{
  "type": "Feature",
  "properties": {
    "iso:country":"US",
    "sg:address":"1519 E Spring St",
    "sg:city":"Cookeville",
    "sg:classifiers":[
        {
            "category":"Social Services",
            "type":"Services"
        }
    ],
    "sg:phone":"+1 931 372 8001",
    "sg:postcode":"38506",
    "sg:province":"TN",
    "wof:name":"Faith",
    "wof:placetype":"venue"
},
  "geometry": {"coordinates":[-85.47000199999999,36.149952],"type":"Point"}
}