{
  "type": "Feature",
  "properties": {
    "iso:country":"US",
    "sg:address":"94 Magnolia Ln",
    "sg:city":"Normandy",
    "sg:classifiers":[
        {
            "category":"Professional",
            "subcategory":"Computer Services",
            "type":"Services"
        }
    ],
    "sg:phone":"+1 931 455 8658",
    "sg:postcode":"37360",
    "sg:province":"TN",
    "sg:tags":[
        "datum"
    ],
    "wof:name":"Web Whisper",
    "wof:placetype":"venue"
},
  "geometry": {"coordinates":[-86.254237,35.412887],"type":"Point"}
}