{
  "type": "Feature",
  "properties": {
    "iso:country":"US",
    "sg:address":"2137 Antioch Pike",
    "sg:city":"Antioch",
    "sg:classifiers":[
        {
            "category":"Autos & Motor Vehicles",
            "subcategory":"Automobile Sales",
            "type":"Retail Goods"
        }
    ],
    "sg:phone":"+1 615 333 2505",
    "sg:postcode":"37013",
    "sg:province":"TN",
    "sg:tags":[
        "car",
        "used",
        "dealer"
    ],
    "wof:name":"Dixie Land Motors",
    "wof:placetype":"venue"
},
  "geometry": {"coordinates":[-86.68056900000001,36.065813],"type":"Point"}
}