{
  "type": "Feature",
  "properties": {
    "addr:full":"715 Greenwood Ave Clarksville TN 37040",
    "addr:housenumber":"715",
    "addr:postcode":"37040",
    "addr:street":"Greenwood Ave",
    "iso:country":"US",
    "sg:address":"715 Greenwood Ave",
    "sg:city":"Clarksville",
    "sg:classifiers":[
        {
            "category":"Professional",
            "subcategory":"Business Services",
            "type":"Services"
        }
    ],
    "sg:phone":"+1 931 552 3771",
    "sg:postcode":"37040",
    "sg:province":"TN",
    "wof:name":"Niko Records Studio",
    "wof:placetype":"venue"
},
  "geometry": {"coordinates":[-87.347189,36.519669],"type":"Point"}
}