{
  "type": "Feature",
  "properties": {
    "iso:country":"US",
    "sg:address":"1021 6th St",
    "sg:city":"Nashville",
    "sg:classifiers":[
        {
            "category":"Freight",
            "type":"Transportation"
        }
    ],
    "sg:phone":"+1 615 248 4112",
    "sg:postcode":"37213",
    "sg:province":"TN",
    "wof:name":"ARC Pickup Svc Davidson Cnty",
    "wof:placetype":"venue"
},
  "geometry": {"coordinates":[-86.75630700000001,36.161665],"type":"Point"}
}