{
  "type": "Feature",
  "properties": {
    "iso:country":"US",
    "sg:address":"727 N Eastman Rd",
    "sg:city":"Kingsport",
    "sg:classifiers":[
        {
            "category":"Social Services",
            "subcategory":"Child Care",
            "type":"Services"
        }
    ],
    "sg:phone":"+1 423 378 3369",
    "sg:postcode":"37664",
    "sg:province":"TN",
    "sg:tags":[
        "day"
    ],
    "wof:name":"Children of Tri Cities",
    "wof:placetype":"venue"
},
  "geometry": {"coordinates":[-82.536556,36.52784],"type":"Point"}
}