{
  "type": "Feature",
  "properties": {
    "iso:country":"US",
    "sg:address":"200 Castle Heights Ave N",
    "sg:city":"Lebanon",
    "sg:classifiers":[
        {
            "category":"Government",
            "subcategory":"Office",
            "type":"Public Place"
        }
    ],
    "sg:phone":"+1 615 443 3605",
    "sg:postcode":"37087",
    "sg:province":"TN",
    "sg:tags":[
        "village"
    ],
    "wof:name":"Lebanon Accounting Dept",
    "wof:placetype":"venue"
},
  "geometry": {"coordinates":[-86.306585,36.212835],"type":"Point"}
}