{
  "type": "Feature",
  "properties": {
    "addr:full":"5656 Old Hickory Blvd Hermitage TN 37076",
    "addr:housenumber":"5656",
    "addr:postcode":"37076",
    "addr:street":"Old Hickory Blvd",
    "iso:country":"US",
    "sg:address":"5656 Old Hickory Blvd",
    "sg:city":"Hermitage",
    "sg:classifiers":[
        {
            "category":"Restaurant",
            "type":"Food & Drink"
        }
    ],
    "sg:menulink":"http://www.allmenus.com/tn/nashville/177831-jack-in-the-box/menu/",
    "sg:phone":"+1 615 883 5191",
    "sg:postcode":"37076",
    "sg:province":"TN",
    "sg:tags":[
        "burger",
        "american"
    ],
    "wof:name":"Jack in the Box",
    "wof:placetype":"venue"
},
  "geometry": {"coordinates":[-86.601578,36.174305],"type":"Point"}
}