{
  "type": "Feature",
  "properties": {
    "iso:country":"US",
    "sg:address":"425 Foothills Mall Dr",
    "sg:city":"Maryville",
    "sg:classifiers":[
        {
            "category":"Banks & Credit Unions",
            "subcategory":"Bank",
            "type":"Services"
        }
    ],
    "sg:phone":"+1 865 977 1112",
    "sg:postcode":"37801",
    "sg:province":"TN",
    "sg:tags":[
        "federal"
    ],
    "wof:name":"Alcoa Tenn Federal Credit Un",
    "wof:placetype":"venue"
},
  "geometry": {"coordinates":[-83.99634500000001,35.739913],"type":"Point"}
}