{
  "type": "Feature",
  "properties": {
    "addr:full":"1125 Bolton Rd Greeneville TN 37745",
    "addr:housenumber":"1125",
    "addr:postcode":"37745",
    "addr:street":"Bolton Rd",
    "iso:country":"US",
    "sg:address":"1125 Bolton Rd",
    "sg:city":"Greeneville",
    "sg:classifiers":[
        {
            "category":"Recreation",
            "type":"Entertainment"
        }
    ],
    "sg:phone":"+1 423 636 1829",
    "sg:postcode":"37745",
    "sg:province":"TN",
    "sg:tags":[
        "club",
        "membership"
    ],
    "wof:name":"Houston Valley Club Inc",
    "wof:placetype":"venue"
},
  "geometry": {"coordinates":[-82.794454,36.196836],"type":"Point"}
}