{
  "type": "Feature",
  "properties": {
    "iso:country":"US",
    "sg:address":"232 Old Pelham Rd",
    "sg:city":"Decherd",
    "sg:classifiers":[
        {
            "category":"Real Estate",
            "subcategory":"Surveying",
            "type":"Services"
        }
    ],
    "sg:phone":"+1 931 967 4317",
    "sg:postcode":"37324",
    "sg:province":"TN",
    "sg:tags":[
        "surveyor"
    ],
    "wof:name":"Jerry Lawrence & Associates",
    "wof:placetype":"venue"
},
  "geometry": {"coordinates":[-85.916107,35.279363],"type":"Point"}
}