{
  "type": "Feature",
  "properties": {
    "addr:full":"421 Anderson Ave Brownsville TN 38012",
    "addr:housenumber":"421",
    "addr:postcode":"38012",
    "addr:street":"Anderson Ave",
    "iso:country":"US",
    "sg:address":"421 Anderson Ave",
    "sg:city":"Brownsville",
    "sg:classifiers":[
        {
            "category":"Manufacturing",
            "subcategory":"Tools & Machinery",
            "type":"Manufacturing & Wholesale Goods"
        }
    ],
    "sg:phone":"+1 731 772 3767",
    "sg:postcode":"38012",
    "sg:province":"TN",
    "sg:tags":[
        "industry",
        "industrial",
        "mfg"
    ],
    "wof:name":"Hydro Systems Supply",
    "wof:placetype":"venue"
},
  "geometry": {"coordinates":[-89.25129099999999,35.589349],"type":"Point"}
}