{
  "type": "Feature",
  "properties": {
    "addr:full":"3103 Middleford Dr Cookeville TN 38506",
    "addr:housenumber":"3103",
    "addr:postcode":"38506",
    "addr:street":"Middleford Dr",
    "iso:country":"US",
    "sg:address":"3103 Middleford Dr",
    "sg:city":"Cookeville",
    "sg:classifiers":[
        {
            "category":"Food & Beverages",
            "subcategory":"Dairy",
            "type":"Retail Goods"
        }
    ],
    "sg:phone":"+1 931 520 3139",
    "sg:postcode":"38506",
    "sg:province":"TN",
    "sg:tags":[
        "product"
    ],
    "wof:name":"Snodaze",
    "wof:placetype":"venue"
},
  "geometry": {"coordinates":[-85.44740400000001,36.176633],"type":"Point"}
}