{
  "type": "Feature",
  "properties": {
    "addr:full":"1819 Memorial Blvd Murfreesboro TN 37129",
    "addr:housenumber":"1819",
    "addr:postcode":"37129",
    "addr:street":"Memorial Blvd",
    "iso:country":"US",
    "sg:address":"1819 Memorial Blvd",
    "sg:city":"Murfreesboro",
    "sg:classifiers":[
        {
            "category":"Health Services",
            "subcategory":"Doctor",
            "type":"Services"
        }
    ],
    "sg:phone":"+1 615 896 7002",
    "sg:postcode":"37129",
    "sg:province":"TN",
    "sg:tags":[
        "dentist"
    ],
    "wof:name":"Beth Keen DDS LLC",
    "wof:placetype":"venue"
},
  "geometry": {"coordinates":[-86.39772600000001,35.851672],"type":"Point"}
}