{
  "type": "Feature",
  "properties": {
    "addr:full":"3522 Tom Austin Hwy Springfield TN 37172",
    "addr:housenumber":"3522",
    "addr:postcode":"37172",
    "addr:street":"Tom Austin Hwy",
    "iso:country":"US",
    "sg:address":"3522 Tom Austin Hwy",
    "sg:city":"Springfield",
    "sg:classifiers":[
        {
            "category":"Restaurant",
            "type":"Food & Drink"
        }
    ],
    "sg:menulink":"http://www.allmenus.com/tn/springfield-greenbrier/73066-pizza-hut/menu/",
    "sg:phone":"+1 615 384 4600",
    "sg:postcode":"37172",
    "sg:province":"TN",
    "sg:tags":[
        "american",
        "pizza"
    ],
    "wof:name":"Pizza Hut",
    "wof:placetype":"venue"
},
  "geometry": {"coordinates":[-86.88099800000001,36.489871],"type":"Point"}
}