{
  "type": "Feature",
  "properties": {
    "addr:full":"646 Pollard Rd Clarksville TN 37042",
    "addr:housenumber":"646",
    "addr:postcode":"37042",
    "addr:street":"Pollard Rd",
    "iso:country":"US",
    "sg:address":"646 Pollard Rd",
    "sg:city":"Clarksville",
    "sg:classifiers":[
        {
            "category":"Professional",
            "type":"Services"
        }
    ],
    "sg:phone":"+1 931 645 2168",
    "sg:postcode":"37042",
    "sg:province":"TN",
    "wof:name":"Gold Star Wives of Americ",
    "wof:placetype":"venue"
},
  "geometry": {"coordinates":[-87.370017,36.569141],"type":"Point"}
}