{
  "type": "Feature",
  "properties": {
    "iso:country":"US",
    "sg:address":"320 Industrial Rd",
    "sg:city":"Adamsville",
    "sg:classifiers":[
        {
            "category":"Home & Garden",
            "subcategory":"Building Materials",
            "type":"Retail Goods"
        }
    ],
    "sg:phone":"+1 731 632 2300",
    "sg:postcode":"38320",
    "sg:province":"TN",
    "sg:tags":[
        "glass",
        "window",
        "plate"
    ],
    "wof:name":"Aqua Glass Corp",
    "wof:placetype":"venue"
},
  "geometry": {"coordinates":[-88.110857,36.053162],"type":"Point"}
}