{
  "type": "Feature",
  "properties": {
    "iso:country":"US",
    "sg:address":"1107 Chapel Ave",
    "sg:city":"Nashville",
    "sg:classifiers":[
        {
            "category":"Professional",
            "type":"Services"
        }
    ],
    "sg:phone":"+1 615 227 3830",
    "sg:postcode":"37206",
    "sg:province":"TN",
    "sg:tags":[
        "establishment"
    ],
    "wof:name":"Y Esss",
    "wof:placetype":"venue"
},
  "geometry": {"coordinates":[-86.738513,36.189577],"type":"Point"}
}