{
  "type": "Feature",
  "properties": {
    "iso:country":"US",
    "sg:address":"60 25th St NW",
    "sg:city":"Cleveland",
    "sg:classifiers":[
        {
            "category":"Home & Garden",
            "subcategory":"Furniture",
            "type":"Retail Goods"
        }
    ],
    "sg:phone":"+1 423 478 8004",
    "sg:postcode":"37311",
    "sg:province":"TN",
    "sg:tags":[
        "mattress"
    ],
    "wof:name":"Mattress City",
    "wof:placetype":"venue"
},
  "geometry": {"coordinates":[-84.86459499999999,35.178618],"type":"Point"}
}