{
  "type": "Feature",
  "properties": {
    "iso:country":"US",
    "sg:address":"904 Potts Chapel Rd",
    "sg:city":"Jackson",
    "sg:classifiers":[
        {
            "category":"Insurance",
            "subcategory":"Insurance Agent",
            "type":"Services"
        }
    ],
    "sg:phone":"+1 731 664 0047",
    "sg:postcode":"38305",
    "sg:province":"TN",
    "wof:name":"Paul D Hare",
    "wof:placetype":"venue"
},
  "geometry": {"coordinates":[-88.694329,35.660809],"type":"Point"}
}