{
  "type": "Feature",
  "properties": {
    "iso:country":"US",
    "sg:address":"1156 Bristol Caverns Hwy",
    "sg:city":"Bristol",
    "sg:classifiers":[
        {
            "category":"Retail",
            "subcategory":"Repair Shop",
            "type":"Services"
        }
    ],
    "sg:phone":"+1 423 990 2004",
    "sg:postcode":"37620",
    "sg:province":"TN",
    "wof:name":"A To Z Small Engine Repair",
    "wof:placetype":"venue"
},
  "geometry": {"coordinates":[-82.125897,36.547498],"type":"Point"}
}