{
  "type": "Feature",
  "properties": {
    "iso:country":"US",
    "sg:address":"2835 New Jersey Ave",
    "sg:city":"Chattanooga",
    "sg:classifiers":[
        {
            "category":"Building & Trades",
            "subcategory":"Landscaping Services",
            "type":"Services"
        }
    ],
    "sg:phone":"+1 423 629 0890",
    "sg:postcode":"37406",
    "sg:province":"TN",
    "sg:tags":[
        "lawn",
        "maintenance",
        "grounds"
    ],
    "wof:name":"Bardin & Bardin Lawn Care",
    "wof:placetype":"venue"
},
  "geometry": {"coordinates":[-85.235283,35.06877],"type":"Point"}
}