{
  "type": "Feature",
  "properties": {
    "iso:country":"US",
    "sg:address":"1225 N Eastman Rd",
    "sg:city":"Kingsport",
    "sg:classifiers":[
        {
            "category":"Professional",
            "subcategory":"Business Services",
            "type":"Services"
        },
        {
            "category":"Professional",
            "subcategory":"Printing & Photocopies",
            "type":"Services"
        }
    ],
    "sg:phone":"+1 423 378 5243",
    "sg:postcode":"37664",
    "sg:province":"TN",
    "sg:tags":[
        "mail",
        "shipping"
    ],
    "wof:name":"Mail Specialty Shop",
    "wof:placetype":"venue"
},
  "geometry": {"coordinates":[-82.530036,36.531213],"type":"Point"}
}