{
  "type": "Feature",
  "properties": {
    "iso:country":"US",
    "sg:address":"127 Hardy Rd",
    "sg:city":"Kenton",
    "sg:classifiers":[
        {
            "category":"Retail",
            "subcategory":"Repair Shop",
            "type":"Services"
        }
    ],
    "sg:phone":"+1 731 665 7220",
    "sg:postcode":"38233",
    "sg:province":"TN",
    "wof:name":"Goodguys Service & Repair",
    "wof:placetype":"venue"
},
  "geometry": {"coordinates":[-88.955287,36.166239],"type":"Point"}
}