{
  "type": "Feature",
  "properties": {
    "iso:country":"US",
    "sg:address":"1539 W Andrew Johnson Hwy",
    "sg:city":"Morristown",
    "sg:classifiers":[
        {
            "category":"Health Services",
            "subcategory":"Chiropractor",
            "type":"Services"
        }
    ],
    "sg:phone":"+1 423 585 5556",
    "sg:postcode":"37814",
    "sg:province":"TN",
    "wof:name":"KIRK & KIRK Health Clinic",
    "wof:placetype":"venue"
},
  "geometry": {"coordinates":[-83.31124800000001,36.207618],"type":"Point"}
}