{
  "type": "Feature",
  "properties": {
    "iso:country":"US",
    "sg:address":"703 K St",
    "sg:city":"Greeneville",
    "sg:classifiers":[
        {
            "category":"Health Services",
            "subcategory":"Doctor",
            "type":"Services"
        }
    ],
    "sg:phone":"+1 423 639 6769",
    "sg:postcode":"37745",
    "sg:province":"TN",
    "sg:tags":[
        "dentist"
    ],
    "wof:name":"Ronald G Bonnett DMD PC",
    "wof:placetype":"venue"
},
  "geometry": {"coordinates":[-82.8176,36.161997],"type":"Point"}
}