{
  "type": "Feature",
  "properties": {
    "iso:country":"US",
    "sg:address":"3452 Fisk Rd",
    "sg:city":"Cookeville",
    "sg:classifiers":[
        {
            "category":"Retail",
            "subcategory":"Auto Repair",
            "type":"Services"
        }
    ],
    "sg:phone":"+1 931 537 9197",
    "sg:postcode":"38506",
    "sg:province":"TN",
    "sg:tags":[
        "wrecker"
    ],
    "wof:name":"Affordable Towing & Recovery",
    "wof:placetype":"venue"
},
  "geometry": {"coordinates":[-85.480035,36.212753],"type":"Point"}
}