{
  "type": "Feature",
  "properties": {
    "addr:full":"499 Clark Aly Memphis TN 38117",
    "addr:housenumber":"499",
    "addr:postcode":"38117",
    "addr:street":"Clark Aly",
    "iso:country":"US",
    "sg:address":"499 Clark Aly",
    "sg:city":"Memphis",
    "sg:classifiers":[
        {
            "category":"Building & Trades",
            "subcategory":"Construction",
            "type":"Services"
        }
    ],
    "sg:phone":"+1 901 831 2509",
    "sg:postcode":"38117",
    "sg:province":"TN",
    "sg:tags":[
        "roofing",
        "contractor"
    ],
    "wof:name":"Mark Vickery Roofing",
    "wof:placetype":"venue"
},
  "geometry": {"coordinates":[-89.894333,35.144819],"type":"Point"}
}