{
  "type": "Feature",
  "properties": {
    "iso:country":"US",
    "sg:address":"3506 Coffee Dr",
    "sg:city":"Memphis",
    "sg:classifiers":[
        {
            "category":"Building & Trades",
            "subcategory":"Cleaning & Sanitation",
            "type":"Services"
        }
    ],
    "sg:phone":"+1 901 340 1907",
    "sg:postcode":"38118",
    "sg:province":"TN",
    "sg:tags":[
        "janitor"
    ],
    "wof:name":"James Patton Bonus Bldg Care",
    "wof:placetype":"venue"
},
  "geometry": {"coordinates":[-89.905501,35.053281],"type":"Point"}
}