{
  "type": "Feature",
  "properties": {
    "addr:full":"115 W Church St Lewisburg TN 37091",
    "addr:housenumber":"115",
    "addr:postcode":"37091",
    "addr:street":"W Church St",
    "iso:country":"US",
    "sg:address":"115 W Church St",
    "sg:city":"Lewisburg",
    "sg:classifiers":[
        {
            "category":"Retail",
            "subcategory":"Repair Shop",
            "type":"Services"
        }
    ],
    "sg:phone":"+1 931 359 8199",
    "sg:postcode":"37091",
    "sg:province":"TN",
    "sg:tags":[
        "jewelry"
    ],
    "wof:name":"Buy Sell Trade Repair Jewelry",
    "wof:placetype":"venue"
},
  "geometry": {"coordinates":[-86.788881,35.449946],"type":"Point"}
}