{
  "type": "Feature",
  "properties": {
    "addr:full":"4817 Murfreesboro Rd Arrington TN 37014",
    "addr:housenumber":"4817",
    "addr:postcode":"37014",
    "addr:street":"Murfreesboro Rd",
    "iso:country":"US",
    "sg:address":"4817 Murfreesboro Rd",
    "sg:city":"Arrington",
    "sg:classifiers":[
        {
            "category":"Government",
            "subcategory":"Post Office",
            "type":"Public Place"
        }
    ],
    "sg:phone":"+1 615 395 7259",
    "sg:postcode":"37014",
    "sg:province":"TN",
    "wof:name":"Arrington Post Office",
    "wof:placetype":"venue"
},
  "geometry": {"coordinates":[-86.704925,35.868041],"type":"Point"}
}