{
  "type": "Feature",
  "properties": {
    "iso:country":"US",
    "sg:address":"1531 Dick Lonas Rd NW",
    "sg:city":"Knoxville",
    "sg:classifiers":[
        {
            "category":"Social Services",
            "type":"Services"
        }
    ],
    "sg:phone":"+1 865 602 2021",
    "sg:postcode":"37909",
    "sg:province":"TN",
    "sg:tags":[
        "organization",
        "care",
        "residential",
        "welfare"
    ],
    "sg:website":"www.fcaknox.org",
    "wof:name":"Florence Crittenton Agency",
    "wof:placetype":"venue"
},
  "geometry": {"coordinates":[-84.026566,35.950884],"type":"Point"}
}