{
  "type": "Feature",
  "properties": {
    "iso:country":"US",
    "sg:address":"1195 Nashville Pike",
    "sg:city":"Gallatin",
    "sg:classifiers":[
        {
            "category":"Real Estate",
            "subcategory":"Real Estate Agent",
            "type":"Services"
        }
    ],
    "sg:phone":"+1 615 452 5341",
    "sg:postcode":"37066",
    "sg:province":"TN",
    "sg:website":"http://carmanrealestate.com",
    "wof:name":"Carman Gene Real Estate & Auctions",
    "wof:placetype":"venue"
},
  "geometry": {"coordinates":[-86.48274000000001,36.370989],"type":"Point"}
}