{
  "type": "Feature",
  "properties": {
    "iso:country":"US",
    "sg:address":"2323 Dover Rd",
    "sg:city":"Morristown",
    "sg:classifiers":[
        {
            "category":"Professional",
            "type":"Services"
        }
    ],
    "sg:phone":"+1 423 581 7999",
    "sg:postcode":"37813",
    "sg:province":"TN",
    "wof:name":"PC To Go",
    "wof:placetype":"venue"
},
  "geometry": {"coordinates":[-83.21455899999999,36.205098],"type":"Point"}
}