{
  "type": "Feature",
  "properties": {
    "iso:country":"US",
    "sg:address":"5219 Nashville Hwy",
    "sg:city":"Baxter",
    "sg:classifiers":[
        {
            "category":"Building & Trades",
            "subcategory":"Construction",
            "type":"Services"
        }
    ],
    "sg:phone":"+1 931 858 1444",
    "sg:postcode":"38544",
    "sg:province":"TN",
    "sg:tags":[
        "siding",
        "contractor"
    ],
    "wof:name":"M & G Vinyl Siding",
    "wof:placetype":"venue"
},
  "geometry": {"coordinates":[-85.60528600000001,36.170254],"type":"Point"}
}