{
  "type": "Feature",
  "properties": {
    "iso:country":"US",
    "sg:address":"4592 Sunvalley Dr",
    "sg:city":"Memphis",
    "sg:classifiers":[
        {
            "category":"Social Services",
            "subcategory":"Child Care",
            "type":"Services"
        }
    ],
    "sg:phone":"+1 901 785 2103",
    "sg:postcode":"38109",
    "sg:province":"TN",
    "sg:tags":[
        "day"
    ],
    "wof:name":"Loveling Care Day Care",
    "wof:placetype":"venue"
},
  "geometry": {"coordinates":[-90.104466,35.023003],"type":"Point"}
}