{
  "type": "Feature",
  "properties": {
    "iso:country":"US",
    "sg:address":"1328 Trotwood Ave",
    "sg:city":"Columbia",
    "sg:classifiers":[
        {
            "category":"Autos & Motor Vehicles",
            "subcategory":"Automobile Sales",
            "type":"Retail Goods"
        }
    ],
    "sg:phone":"+1 931 381 5432",
    "sg:postcode":"38401",
    "sg:province":"TN",
    "sg:tags":[
        "used"
    ],
    "wof:name":"Billys Auto Sales",
    "wof:placetype":"venue"
},
  "geometry": {"coordinates":[-87.07221,35.600715],"type":"Point"}
}