{
  "type": "Feature",
  "properties": {
    "iso:country":"US",
    "sg:address":"55 William Blaydes St",
    "sg:city":"Atoka",
    "sg:classifiers":[
        {
            "category":"Banks & Credit Unions",
            "subcategory":"Bank",
            "type":"Services"
        }
    ],
    "sg:phone":"+1 901 837 9566",
    "sg:postcode":"38004",
    "sg:province":"TN",
    "sg:tags":[
        "loan",
        "real estate"
    ],
    "wof:name":"G N Mortgage LLC",
    "wof:placetype":"venue"
},
  "geometry": {"coordinates":[-89.770759,35.408619],"type":"Point"}
}