{
  "type": "Feature",
  "properties": {
    "iso:country":"US",
    "sg:address":"835 Dickerson Pike",
    "sg:city":"Nashville",
    "sg:classifiers":[
        {
            "category":"Home & Garden",
            "subcategory":"Carpets & Floor Coverings",
            "type":"Retail Goods"
        }
    ],
    "sg:phone":"+1 615 228 0701",
    "sg:postcode":"37207",
    "sg:province":"TN",
    "sg:tags":[
        "material"
    ],
    "wof:name":"Flooring Center",
    "wof:placetype":"venue"
},
  "geometry": {"coordinates":[-86.773453,36.185932],"type":"Point"}
}