{
  "type": "Feature",
  "properties": {
    "addr:full":"200 E 8th Ave Springfield TN 37172",
    "addr:housenumber":"200",
    "addr:postcode":"37172",
    "addr:street":"E 8Th Ave",
    "iso:country":"US",
    "sg:address":"200 E 8th Ave",
    "sg:city":"Springfield",
    "sg:classifiers":[
        {
            "category":"Restaurant",
            "type":"Food & Drink"
        }
    ],
    "sg:phone":"+1 615 382 4377",
    "sg:postcode":"37172",
    "sg:province":"TN",
    "sg:tags":[
        "shop",
        "coffee"
    ],
    "wof:name":"Talents Coffee Studio",
    "wof:placetype":"venue"
},
  "geometry": {"coordinates":[-86.884199,36.506859],"type":"Point"}
}