{
  "type": "Feature",
  "properties": {
    "addr:full":"850 McMinnville Hwy Sparta TN 38583",
    "addr:housenumber":"850",
    "addr:postcode":"38583",
    "addr:street":"Mcminnville Hwy",
    "iso:country":"US",
    "sg:address":"850 McMinnville Hwy",
    "sg:city":"Sparta",
    "sg:classifiers":[
        {
            "category":"Building & Trades",
            "subcategory":"Construction",
            "type":"Services"
        }
    ],
    "sg:phone":"+1 931 738 8598",
    "sg:postcode":"38583",
    "sg:province":"TN",
    "sg:tags":[
        "floor",
        "laying",
        "contractor"
    ],
    "wof:name":"Eugene Howell",
    "wof:placetype":"venue"
},
  "geometry": {"coordinates":[-85.485151,35.91068],"type":"Point"}
}