{
  "type": "Feature",
  "properties": {
    "iso:country":"US",
    "sg:address":"2512 Essex Dr",
    "sg:city":"Kingsport",
    "sg:classifiers":[
        {
            "category":"Professional",
            "subcategory":"Engineering",
            "type":"Services"
        }
    ],
    "sg:phone":"+1 423 288 3921",
    "sg:postcode":"37660",
    "sg:province":"TN",
    "wof:name":"Bete Inc",
    "wof:placetype":"venue"
},
  "geometry": {"coordinates":[-82.50479900000001,36.552101],"type":"Point"}
}