{
  "type": "Feature",
  "properties": {
    "iso:country":"US",
    "sg:address":"3359 Ambrose Ave",
    "sg:city":"Nashville",
    "sg:classifiers":[
        {
            "category":"Building & Trades",
            "subcategory":"Equipment Rental",
            "type":"Services"
        }
    ],
    "sg:phone":"+1 615 627 4197",
    "sg:postcode":"37207",
    "sg:province":"TN",
    "sg:tags":[
        "instrument",
        "musical"
    ],
    "wof:name":"Vango Digital",
    "wof:placetype":"venue"
},
  "geometry": {"coordinates":[-86.748487,36.208909],"type":"Point"}
}