{
  "type": "Feature",
  "properties": {
    "addr:full":"359 Lane Ave Jackson TN 38301",
    "addr:housenumber":"359",
    "addr:postcode":"38301",
    "addr:street":"Lane Ave",
    "iso:country":"US",
    "sg:address":"359 Lane Ave",
    "sg:city":"Jackson",
    "sg:classifiers":[
        {
            "category":"Personal",
            "subcategory":"Barber",
            "type":"Services"
        }
    ],
    "sg:phone":"+1 731 425 9268",
    "sg:postcode":"38301",
    "sg:province":"TN",
    "wof:name":"Tight Cuts",
    "wof:placetype":"venue"
},
  "geometry": {"coordinates":[-88.81108,35.627966],"type":"Point"}
}