{
  "type": "Feature",
  "properties": {
    "addr:full":"1159 Volunteer Pkwy Bristol TN 37620",
    "addr:housenumber":"1159",
    "addr:postcode":"37620",
    "addr:street":"Volunteer Pkwy",
    "iso:country":"US",
    "sg:address":"1159 Volunteer Pkwy",
    "sg:city":"Bristol",
    "sg:classifiers":[
        {
            "category":"Banks & Credit Unions",
            "subcategory":"Bank",
            "type":"Services"
        }
    ],
    "sg:phone":"+1 423 989 9325",
    "sg:postcode":"37620",
    "sg:province":"TN",
    "sg:tags":[
        "cashing",
        "check"
    ],
    "wof:name":"Mr Cash",
    "wof:placetype":"venue"
},
  "geometry": {"coordinates":[-82.19668,36.570395],"type":"Point"}
}