{
  "type": "Feature",
  "properties": {
    "iso:country":"US",
    "sg:address":"1304 E 39th St",
    "sg:city":"Chattanooga",
    "sg:classifiers":[
        {
            "category":"Manufacturing",
            "subcategory":"Metals",
            "type":"Manufacturing & Wholesale Goods"
        },
        {
            "category":"Building & Trades",
            "subcategory":"Construction",
            "type":"Services"
        }
    ],
    "sg:phone":"+1 423 892 1209",
    "sg:postcode":"37407",
    "sg:province":"TN",
    "sg:tags":[
        "steel",
        "crane",
        "erectors"
    ],
    "wof:name":"Sterchi Steel Constructors",
    "wof:placetype":"venue"
},
  "geometry": {"coordinates":[-85.297301,34.99818],"type":"Point"}
}