{
  "type": "Feature",
  "properties": {
    "iso:country":"US",
    "sg:address":"1008 Pine Tree Rd",
    "sg:city":"Jamestown",
    "sg:classifiers":[
        {
            "category":"Shopping",
            "type":"Retail Goods"
        }
    ],
    "sg:phone":"+1 931 879 9080",
    "sg:postcode":"38556",
    "sg:province":"TN",
    "sg:tags":[
        "product",
        "wood"
    ],
    "wof:name":"G & G Rock & Wood Yard Stone",
    "wof:placetype":"venue"
},
  "geometry": {"coordinates":[-84.921941,36.413673],"type":"Point"}
}