{
  "type": "Feature",
  "properties": {
    "iso:country":"US",
    "sg:address":"1629 Huntsville Hwy",
    "sg:city":"Fayetteville",
    "sg:classifiers":[
        {
            "category":"Shopping",
            "type":"Retail Goods"
        }
    ],
    "sg:phone":"+1 931 438 0602",
    "sg:postcode":"37334",
    "sg:province":"TN",
    "sg:tags":[
        "ice"
    ],
    "wof:name":"Locker Ice Co",
    "wof:placetype":"venue"
},
  "geometry": {"coordinates":[-86.56630699999999,35.129807],"type":"Point"}
}