{
  "type": "Feature",
  "properties": {
    "iso:country":"US",
    "sg:address":"2438 State Hwy 209 N",
    "sg:city":"Ripley",
    "sg:classifiers":[
        {
            "category":"Professional",
            "type":"Services"
        }
    ],
    "sg:phone":"+1 731 635 4967",
    "sg:postcode":"38063",
    "sg:province":"TN",
    "wof:name":"Hayes Dennie",
    "wof:placetype":"venue"
},
  "geometry": {"coordinates":[-89.50542299999999,35.781662],"type":"Point"}
}