{
  "type": "Feature",
  "properties": {
    "addr:full":"146 Miller Ave Jackson TN 38305",
    "addr:housenumber":"146",
    "addr:postcode":"38305",
    "addr:street":"Miller Ave",
    "iso:country":"US",
    "sg:address":"146 Miller Ave",
    "sg:city":"Jackson",
    "sg:classifiers":[
        {
            "category":"Retail",
            "subcategory":"Animal Services",
            "type":"Services"
        }
    ],
    "sg:phone":"+1 731 668 4211",
    "sg:postcode":"38305",
    "sg:province":"TN",
    "sg:tags":[
        "shelter"
    ],
    "wof:name":"Jackson Madison Rabies Control",
    "wof:placetype":"venue"
},
  "geometry": {"coordinates":[-88.86269799999999,35.639032],"type":"Point"}
}