{
  "type": "Feature",
  "properties": {
    "iso:country":"US",
    "sg:address":"3163 N Trezevant St",
    "sg:city":"Memphis",
    "sg:classifiers":[
        {
            "category":"Organizations",
            "subcategory":"Religious Organization",
            "type":"Services"
        }
    ],
    "sg:phone":"+1 901 358 7451",
    "sg:postcode":"38127",
    "sg:province":"TN",
    "sg:tags":[
        "church"
    ],
    "wof:name":"Faith Pentecostal Temple",
    "wof:placetype":"venue"
},
  "geometry": {"coordinates":[-89.97877200000001,35.213409],"type":"Point"}
}