{
  "type": "Feature",
  "properties": {
    "addr:full":"1835 Ridge Rd Caryville TN 37714",
    "addr:housenumber":"1835",
    "addr:postcode":"37714",
    "addr:street":"Ridge Rd",
    "iso:country":"US",
    "sg:address":"1835 Ridge Rd",
    "sg:city":"Caryville",
    "sg:classifiers":[
        {
            "category":"Recreation",
            "subcategory":"Marina",
            "type":"Entertainment"
        }
    ],
    "sg:phone":"+1 423 566 0976",
    "sg:postcode":"37714",
    "sg:province":"TN",
    "sg:tags":[
        "operation"
    ],
    "wof:name":"Twin Cove Marina",
    "wof:placetype":"venue"
},
  "geometry": {"coordinates":[-84.178163,36.28826],"type":"Point"}
}