{
  "type": "Feature",
  "properties": {
    "iso:country":"US",
    "sg:address":"707 S Main St",
    "sg:city":"Crossville",
    "sg:classifiers":[
        {
            "category":"Health Services",
            "subcategory":"Health Practitioner",
            "type":"Services"
        }
    ],
    "sg:phone":"+1 931 456 1818",
    "sg:postcode":"38555",
    "sg:province":"TN",
    "wof:name":"Plateau Physical Therapy",
    "wof:placetype":"venue"
},
  "geometry": {"coordinates":[-85.018718,35.939359],"type":"Point"}
}