{
  "type": "Feature",
  "properties": {
    "iso:country":"US",
    "sg:address":"2978 Carters Creek Station Rd",
    "sg:city":"Columbia",
    "sg:classifiers":[
        {
            "category":"Shopping",
            "subcategory":"Used Merchandise",
            "type":"Retail Goods"
        }
    ],
    "sg:phone":"+1 931 486 0405",
    "sg:postcode":"38401",
    "sg:province":"TN",
    "sg:tags":[
        "antique"
    ],
    "wof:name":"Carter's Creek Station",
    "wof:placetype":"venue"
},
  "geometry": {"coordinates":[-86.989182,35.713524],"type":"Point"}
}