{
  "type": "Feature",
  "properties": {
    "addr:full":"127 9th Ave N Nashville TN 37203",
    "addr:housenumber":"127",
    "addr:postcode":"37203",
    "addr:street":"9Th Ave N",
    "iso:country":"US",
    "sg:address":"127 9th Ave N",
    "sg:city":"Nashville",
    "sg:classifiers":[
        {
            "category":"Manufacturing",
            "subcategory":"Printing",
            "type":"Manufacturing & Wholesale Goods"
        }
    ],
    "sg:phone":"+1 615 251 2520",
    "sg:postcode":"37203",
    "sg:province":"TN",
    "sg:tags":[
        "publisher"
    ],
    "sg:website":"www.broadmanholman.com",
    "wof:name":"Holman Bible Publishers",
    "wof:placetype":"venue"
},
  "geometry": {"coordinates":[-86.783272,36.159519],"type":"Point"}
}