{
  "type": "Feature",
  "properties": {
    "addr:full":"8233 Ewing Rd Powell TN 37849",
    "addr:housenumber":"8233",
    "addr:postcode":"37849",
    "addr:street":"Ewing Rd",
    "iso:country":"US",
    "sg:address":"8233 Ewing Rd",
    "sg:city":"Powell",
    "sg:classifiers":[
        {
            "category":"Building & Trades",
            "subcategory":"Construction",
            "type":"Services"
        }
    ],
    "sg:phone":"+1 865 938 6233",
    "sg:postcode":"37849",
    "sg:province":"TN",
    "sg:tags":[
        "contractor"
    ],
    "wof:name":"Ken Campbell Construction Co",
    "wof:placetype":"venue"
},
  "geometry": {"coordinates":[-84.03572200000001,36.041256],"type":"Point"}
}