{
  "type": "Feature",
  "properties": {
    "iso:country":"US",
    "sg:address":"266 S Front St Ste 206",
    "sg:city":"Memphis",
    "sg:classifiers":[
        {
            "category":"Professional",
            "subcategory":"Lawyer & Legal Services",
            "type":"Services"
        }
    ],
    "sg:phone":"+1 901 527 1319",
    "sg:postcode":"38103",
    "sg:province":"TN",
    "sg:tags":[
        "attorney",
        "practice"
    ],
    "wof:name":"Kriegel Law Firm",
    "wof:placetype":"venue"
},
  "geometry": {"coordinates":[-90.057098,35.139568],"type":"Point"}
}