{
  "type": "Feature",
  "properties": {
    "iso:country":"US",
    "sg:address":"7171 Lawn Ln",
    "sg:city":"Memphis",
    "sg:classifiers":[
        {
            "category":"Building & Trades",
            "subcategory":"Construction",
            "type":"Services"
        }
    ],
    "sg:phone":"+1 901 385 8177",
    "sg:postcode":"38133",
    "sg:province":"TN",
    "sg:tags":[
        "resurfacing",
        "laying",
        "refinishing",
        "floor"
    ],
    "wof:name":"Bartlett Hardwood Floor Svc",
    "wof:placetype":"venue"
},
  "geometry": {"coordinates":[-89.823007,35.206084],"type":"Point"}
}