{
  "type": "Feature",
  "properties": {
    "addr:full":"5102 Simsbury Cv Memphis TN 38118",
    "addr:housenumber":"5102",
    "addr:postcode":"38118",
    "addr:street":"Simsbury Cv",
    "iso:country":"US",
    "sg:address":"5102 Simsbury Cv",
    "sg:city":"Memphis",
    "sg:classifiers":[
        {
            "category":"Organizations",
            "subcategory":"Community Association",
            "type":"Services"
        }
    ],
    "sg:phone":"+1 901 336 2065",
    "sg:postcode":"38118",
    "sg:province":"TN",
    "wof:name":"Association Of Civilian Technicians",
    "wof:placetype":"venue"
},
  "geometry": {"coordinates":[-89.893952,35.043552],"type":"Point"}
}