{
  "type": "Feature",
  "properties": {
    "iso:country":"US",
    "sg:address":"5658 Lakeview Rd",
    "sg:city":"Springfield",
    "sg:classifiers":[
        {
            "category":"Freight",
            "type":"Transportation"
        }
    ],
    "sg:phone":"+1 615 384 1956",
    "sg:postcode":"37172",
    "sg:province":"TN",
    "wof:name":"B & E Transport LP",
    "wof:placetype":"venue"
},
  "geometry": {"coordinates":[-86.84890300000001,36.565367],"type":"Point"}
}