{
  "type": "Feature",
  "properties": {
    "addr:full":"1154 Stage Ave Memphis TN 38127",
    "addr:housenumber":"1154",
    "addr:postcode":"38127",
    "addr:street":"Stage Ave",
    "iso:country":"US",
    "sg:address":"1154 Stage Ave",
    "sg:city":"Memphis",
    "sg:classifiers":[
        {
            "category":"Professional",
            "subcategory":"Detective & Security Services",
            "type":"Services"
        }
    ],
    "sg:phone":"+1 901 353 5492",
    "sg:postcode":"38127",
    "sg:province":"TN",
    "sg:tags":[
        "information",
        "bureau"
    ],
    "wof:name":"C&T Products & Services",
    "wof:placetype":"venue"
},
  "geometry": {"coordinates":[-90.02531399999999,35.202146],"type":"Point"}
}