{
  "type": "Feature",
  "properties": {
    "addr:full":"3595 Regal Blvd Memphis TN 38118",
    "addr:housenumber":"3595",
    "addr:postcode":"38118",
    "addr:street":"Regal Blvd",
    "iso:country":"US",
    "sg:address":"3595 Regal Blvd",
    "sg:city":"Memphis",
    "sg:classifiers":[
        {
            "category":"Railroad",
            "type":"Transportation"
        }
    ],
    "sg:phone":"+1 901 365 1611",
    "sg:postcode":"38118",
    "sg:province":"TN",
    "sg:tags":[
        "import",
        "representative"
    ],
    "wof:name":"Great Southern Corp",
    "wof:placetype":"venue"
},
  "geometry": {"coordinates":[-89.9295,35.050094],"type":"Point"}
}