{
  "type": "Feature",
  "properties": {
    "iso:country":"US",
    "sg:address":"109 W Tennessee St",
    "sg:city":"Collinwood",
    "sg:classifiers":[
        {
            "category":"Personal",
            "subcategory":"Beauty Salon",
            "type":"Services"
        }
    ],
    "sg:phone":"+1 931 724 4732",
    "sg:postcode":"38450",
    "sg:province":"TN",
    "sg:tags":[
        "shop"
    ],
    "wof:name":"Smith Beauty Shop",
    "wof:placetype":"venue"
},
  "geometry": {"coordinates":[-87.74053600000001,35.175206],"type":"Point"}
}