{
  "type": "Feature",
  "properties": {
    "iso:country":"US",
    "sg:address":"1801 N Washington St",
    "sg:city":"Tullahoma",
    "sg:classifiers":[
        {
            "category":"Health Services",
            "subcategory":"Doctor",
            "type":"Services"
        }
    ],
    "sg:phone":"+1 931 455 1902",
    "sg:postcode":"37388",
    "sg:province":"TN",
    "sg:tags":[
        "physician",
        "surgeon"
    ],
    "wof:name":"James H Lindsay Jr MD",
    "wof:placetype":"venue"
},
  "geometry": {"coordinates":[-86.22577,35.383311],"type":"Point"}
}