{
  "type": "Feature",
  "properties": {
    "addr:full":"1020 King St Chattanooga TN 37403",
    "addr:housenumber":"1020",
    "addr:postcode":"37403",
    "addr:street":"King St",
    "iso:country":"US",
    "sg:address":"1020 King St",
    "sg:city":"Chattanooga",
    "sg:classifiers":[
        {
            "category":"Travel",
            "subcategory":"Hotels & Motels",
            "type":"Entertainment"
        }
    ],
    "sg:phone":"+1 423 266 0701",
    "sg:postcode":"37403",
    "sg:province":"TN",
    "wof:name":"Lamar's Motel",
    "wof:placetype":"venue"
},
  "geometry": {"coordinates":[-85.305689,35.042728],"type":"Point"}
}