{
  "type": "Feature",
  "properties": {
    "iso:country":"US",
    "sg:address":"29 Lafayette St",
    "sg:city":"Nashville",
    "sg:classifiers":[
        {
            "category":"Autos & Motor Vehicles",
            "subcategory":"Automobile Sales",
            "type":"Retail Goods"
        }
    ],
    "sg:phone":"+1 615 259 2207",
    "sg:postcode":"37210",
    "sg:province":"TN",
    "sg:tags":[
        "used"
    ],
    "wof:name":"Lafayette Motors",
    "wof:placetype":"venue"
},
  "geometry": {"coordinates":[-86.766577,36.150131],"type":"Point"}
}