{
  "type": "Feature",
  "properties": {
    "iso:country":"US",
    "sg:address":"1012 Beason Rd",
    "sg:city":"Byrdstown",
    "sg:classifiers":[
        {
            "category":"Social Services",
            "subcategory":"Child Care",
            "type":"Services"
        }
    ],
    "sg:phone":"+1 931 864 3575",
    "sg:postcode":"38549",
    "sg:province":"TN",
    "sg:tags":[
        "day"
    ],
    "wof:name":"Byrdstown Head Start Center",
    "wof:placetype":"venue"
},
  "geometry": {"coordinates":[-85.13743599999999,36.578316],"type":"Point"}
}