{
  "type": "Feature",
  "properties": {
    "iso:country":"US",
    "sg:address":"130 S Maple St",
    "sg:city":"Lebanon",
    "sg:classifiers":[
        {
            "category":"Autos & Motor Vehicles",
            "subcategory":"Automobile Sales",
            "type":"Retail Goods"
        },
        {
            "category":"Restaurant",
            "type":"Food & Drink"
        }
    ],
    "sg:phone":"+1 615 444 0121",
    "sg:postcode":"37087",
    "sg:province":"TN",
    "sg:tags":[
        "car",
        "eating",
        "dealer"
    ],
    "wof:name":"Ray's Motors",
    "wof:placetype":"venue"
},
  "geometry": {"coordinates":[-86.292768,36.206611],"type":"Point"}
}