{
  "type": "Feature",
  "properties": {
    "iso:country":"US",
    "sg:address":"1755 Appling Rd",
    "sg:city":"Cordova",
    "sg:classifiers":[
        {
            "category":"Organizations",
            "subcategory":"Religious Organization",
            "type":"Services"
        }
    ],
    "sg:phone":"+1 901 384 0340",
    "sg:postcode":"38016",
    "sg:province":"TN",
    "sg:tags":[
        "church"
    ],
    "wof:name":"Israel Of God",
    "wof:placetype":"venue"
},
  "geometry": {"coordinates":[-89.814575,35.173507],"type":"Point"}
}