{
  "type": "Feature",
  "properties": {
    "iso:country":"US",
    "sg:address":"4600 Centennial Blvd",
    "sg:city":"Nashville",
    "sg:classifiers":[
        {
            "category":"Manufacturing",
            "subcategory":"Chemicals & Compounds",
            "type":"Manufacturing & Wholesale Goods"
        }
    ],
    "sg:phone":"+1 615 269 3414",
    "sg:postcode":"37209",
    "sg:province":"TN",
    "wof:name":"Innophos",
    "wof:placetype":"venue"
},
  "geometry": {"coordinates":[-86.843794,36.163344],"type":"Point"}
}