{
  "type": "Feature",
  "properties": {
    "iso:country":"US",
    "sg:address":"6303 State Hwy 89",
    "sg:city":"Palmersville",
    "sg:classifiers":[
        {
            "category":"Government",
            "subcategory":"Fire Station",
            "type":"Public Place"
        }
    ],
    "sg:phone":"+1 731 822 7000",
    "sg:postcode":"38241",
    "sg:province":"TN",
    "sg:tags":[
        "department"
    ],
    "wof:name":"Palmersville Volunteer Fire",
    "wof:placetype":"venue"
},
  "geometry": {"coordinates":[-88.583074,36.425353],"type":"Point"}
}