{
  "type": "Feature",
  "properties": {
    "iso:country":"US",
    "sg:address":"352 Poplar View Ln E",
    "sg:city":"Collierville",
    "sg:classifiers":[
        {
            "category":"Wholesale",
            "subcategory":"Farm Supplies",
            "type":"Manufacturing & Wholesale Goods"
        },
        {
            "category":"Shopping",
            "type":"Retail Goods"
        }
    ],
    "sg:phone":"+1 901 854 5204",
    "sg:postcode":"38017",
    "sg:province":"TN",
    "sg:tags":[
        "control",
        "equipment",
        "pest",
        "merchandise"
    ],
    "wof:name":"Flymaster Of North America Inc",
    "wof:placetype":"venue"
},
  "geometry": {"coordinates":[-89.698897,35.049281],"type":"Point"}
}