{
  "type": "Feature",
  "properties": {
    "addr:full":"2668 Highland Ave Lenoir City TN 37771",
    "addr:housenumber":"2668",
    "addr:postcode":"37771",
    "addr:street":"Highland Ave",
    "iso:country":"US",
    "sg:address":"2668 Highland Ave",
    "sg:city":"Lenoir City",
    "sg:classifiers":[
        {
            "category":"Education",
            "subcategory":"Special Training",
            "type":"Public Place"
        }
    ],
    "sg:phone":"+1 865 986 5432",
    "sg:postcode":"37771",
    "sg:province":"TN",
    "sg:tags":[
        "center"
    ],
    "wof:name":"Bright Side Learning Ctr",
    "wof:placetype":"venue"
},
  "geometry": {"coordinates":[-84.28275600000001,35.774106],"type":"Point"}
}