{
  "type": "Feature",
  "properties": {
    "iso:country":"US",
    "sg:address":"2930 US Hwy 79 N",
    "sg:city":"Brownsville",
    "sg:classifiers":[
        {
            "category":"Building & Trades",
            "subcategory":"Construction",
            "type":"Services"
        }
    ],
    "sg:phone":"+1 731 772 0428",
    "sg:postcode":"38012",
    "sg:province":"TN",
    "sg:tags":[
        "contractor"
    ],
    "wof:name":"Moores Drywall",
    "wof:placetype":"venue"
},
  "geometry": {"coordinates":[-89.226724,35.618266],"type":"Point"}
}