{
  "type": "Feature",
  "properties": {
    "iso:country":"US",
    "sg:address":"585 Erin Dr",
    "sg:city":"Memphis",
    "sg:classifiers":[
        {
            "category":"Restaurant",
            "type":"Food & Drink"
        }
    ],
    "sg:phone":"+1 901 763 4499",
    "sg:postcode":"38117",
    "sg:province":"TN",
    "sg:tags":[
        "delicatessen"
    ],
    "sg:website":"www.holidaydeli.com",
    "wof:name":"Holiday Ham & Deli",
    "wof:placetype":"venue"
},
  "geometry": {"coordinates":[-89.89885700000001,35.115917],"type":"Point"}
}