{
  "type": "Feature",
  "properties": {
    "iso:country":"US",
    "sg:address":"9314 Park West Blvd",
    "sg:city":"Knoxville",
    "sg:classifiers":[
        {
            "category":"Health Services",
            "subcategory":"Doctor",
            "type":"Services"
        }
    ],
    "sg:phone":"+1 865 694 9676",
    "sg:postcode":"37923",
    "sg:province":"TN",
    "sg:tags":[
        "physician",
        "surgeon"
    ],
    "sg:website":"www.premiersurgical.com",
    "wof:name":"Premier Surgical Assoc West",
    "wof:placetype":"venue"
},
  "geometry": {"coordinates":[-84.10107499999999,35.917796],"type":"Point"}
}