{
  "type": "Feature",
  "properties": {
    "addr:full":"669 S Mendenhall Rd Memphis TN 38117",
    "addr:housenumber":"669",
    "addr:postcode":"38117",
    "addr:street":"S Mendenhall Rd",
    "iso:country":"US",
    "sg:address":"669 S Mendenhall Rd",
    "sg:city":"Memphis",
    "sg:classifiers":[
        {
            "category":"Shopping",
            "subcategory":"Tobacco",
            "type":"Retail Goods"
        }
    ],
    "sg:phone":"+1 901 682 3326",
    "sg:postcode":"38117",
    "sg:province":"TN",
    "sg:tags":[
        "cigarette",
        "cigar"
    ],
    "sg:website":"http://www.realpagessites.com/tobaccocorner",
    "wof:name":"Tobacco Corner Ltd",
    "wof:placetype":"venue"
},
  "geometry": {"coordinates":[-89.896264,35.11227],"type":"Point"}
}