{
  "type": "Feature",
  "properties": {
    "addr:full":"729 N Chancery St Mc Minnville TN 37110",
    "addr:housenumber":"729",
    "addr:postcode":"37110",
    "addr:street":"N Chancery St",
    "iso:country":"US",
    "sg:address":"729 N Chancery St",
    "sg:city":"Mc Minnville",
    "sg:classifiers":[
        {
            "category":"Wholesale",
            "subcategory":"Electrical",
            "type":"Manufacturing & Wholesale Goods"
        }
    ],
    "sg:phone":"+1 931 473 5312",
    "sg:postcode":"37110",
    "sg:province":"TN",
    "sg:tags":[
        "wireless",
        "communications",
        "sales"
    ],
    "wof:name":"Communications Evolutions",
    "wof:placetype":"venue"
},
  "geometry": {"coordinates":[-85.782067,35.695969],"type":"Point"}
}