{
  "type": "Feature",
  "properties": {
    "iso:country":"US",
    "sg:address":"300 S Tennessee Ave",
    "sg:city":"La Follette",
    "sg:classifiers":[
        {
            "category":"Taxi",
            "type":"Transportation"
        }
    ],
    "sg:phone":"+1 423 566 6116",
    "sg:postcode":"37766",
    "sg:province":"TN",
    "sg:tags":[
        "taxicab"
    ],
    "wof:name":"Discount Cab",
    "wof:placetype":"venue"
},
  "geometry": {"coordinates":[-84.121275,36.378968],"type":"Point"}
}