{
  "type": "Feature",
  "properties": {
    "iso:country":"US",
    "sg:address":"2118 Lowes Dr",
    "sg:city":"Clarksville",
    "sg:classifiers":[
        {
            "category":"Building & Trades",
            "subcategory":"Equipment Rental",
            "type":"Services"
        }
    ],
    "sg:phone":"+1 931 906 5944",
    "sg:postcode":"37040",
    "sg:province":"TN",
    "sg:tags":[
        "yard"
    ],
    "sg:website":"www.nationsrent.com",
    "wof:name":"Nations Rent",
    "wof:placetype":"venue"
},
  "geometry": {"coordinates":[-87.30981800000001,36.574843],"type":"Point"}
}