{
  "type": "Feature",
  "properties": {
    "iso:country":"US",
    "sg:address":"2304 Tuckaleechee Pike",
    "sg:city":"Maryville",
    "sg:classifiers":[
        {
            "category":"Shopping",
            "type":"Retail Goods"
        }
    ],
    "sg:phone":"+1 865 982 3730",
    "sg:postcode":"37803",
    "sg:province":"TN",
    "sg:tags":[
        "monument"
    ],
    "sg:website":"www.grandviewcemetery.com",
    "wof:name":"Grandview Cemetery",
    "wof:placetype":"venue"
},
  "geometry": {"coordinates":[-83.934724,35.751836],"type":"Point"}
}