{
  "type": "Feature",
  "properties": {
    "addr:full":"5100 Poplar Ave Memphis TN 38117",
    "addr:housenumber":"5100",
    "addr:postcode":"38117",
    "addr:street":"Poplar Ave",
    "iso:country":"US",
    "sg:address":"5100 Poplar Ave",
    "sg:city":"Memphis",
    "sg:classifiers":[
        {
            "category":"Restaurant",
            "type":"Food & Drink"
        }
    ],
    "sg:phone":"+1 901 683 2342",
    "sg:postcode":"38117",
    "sg:province":"TN",
    "sg:tags":[
        "bagel",
        "delicatessen",
        "bar"
    ],
    "wof:name":"Bronx Bagel Bar LLC",
    "wof:placetype":"venue"
},
  "geometry": {"coordinates":[-89.892369,35.111334],"type":"Point"}
}