{
  "type": "Feature",
  "properties": {
    "addr:full":"4859 S Germantown Rd Memphis TN 38141",
    "addr:housenumber":"4859",
    "addr:postcode":"38141",
    "addr:street":"S Germantown Rd",
    "iso:country":"US",
    "sg:address":"4859 S Germantown Rd",
    "sg:city":"Memphis",
    "sg:classifiers":[
        {
            "category":"Restaurant",
            "type":"Food & Drink"
        }
    ],
    "sg:phone":"+1 901 753 3671",
    "sg:postcode":"38141",
    "sg:province":"TN",
    "sg:tags":[
        "eating"
    ],
    "wof:name":"Expressions Restaurant",
    "wof:placetype":"venue"
},
  "geometry": {"coordinates":[-89.82316899999999,35.018607],"type":"Point"}
}