{
  "type": "Feature",
  "properties": {
    "addr:full":"57 N Mud Island Rd Memphis TN 38103",
    "addr:housenumber":"57",
    "addr:postcode":"38103",
    "addr:street":"N Mud Island Rd",
    "iso:country":"US",
    "sg:address":"57 N Mud Island Rd",
    "sg:city":"Memphis",
    "sg:classifiers":[
        {
            "category":"Social Services",
            "type":"Services"
        },
        {
            "category":"Professional",
            "subcategory":"Employment Agencies",
            "type":"Services"
        },
        {
            "category":"Organizations",
            "subcategory":"Community Association",
            "type":"Services"
        }
    ],
    "sg:phone":"+1 901 525 3808",
    "sg:postcode":"38103",
    "sg:province":"TN",
    "sg:tags":[
        "club",
        "placement",
        "workers'",
        "volunteer"
    ],
    "sg:website":"http://www.memphisyachtclub.com",
    "wof:name":"Memphis Yacht Club",
    "wof:placetype":"venue"
},
  "geometry": {"coordinates":[-90.05877,35.150135],"type":"Point"}
}