{
  "type": "Feature",
  "properties": {
    "iso:country":"US",
    "sg:address":"1230 Industrial Park Rd",
    "sg:city":"Columbia",
    "sg:classifiers":[
        {
            "category":"Insurance",
            "subcategory":"Hazard Insurance",
            "type":"Services"
        },
        {
            "category":"Professional",
            "subcategory":"Business Services",
            "type":"Services"
        }
    ],
    "sg:phone":"+1 931 490 1900",
    "sg:postcode":"38401",
    "sg:province":"TN",
    "sg:tags":[
        "bond"
    ],
    "wof:name":"Stoney's Bail Bonds",
    "wof:placetype":"venue"
},
  "geometry": {"coordinates":[-87.067368,35.646651],"type":"Point"}
}