{
  "type": "Feature",
  "properties": {
    "iso:country":"US",
    "sg:address":"120 Circle Dr",
    "sg:city":"Dickson",
    "sg:classifiers":[
        {
            "category":"Home & Garden",
            "subcategory":"Building Materials",
            "type":"Retail Goods"
        }
    ],
    "sg:phone":"+1 615 740 0111",
    "sg:postcode":"37058",
    "sg:province":"TN",
    "sg:tags":[
        "glass",
        "window",
        "plate"
    ],
    "wof:name":"Lawrence Glass Co Inc",
    "wof:placetype":"venue"
},
  "geometry": {"coordinates":[-87.834431,36.482072],"type":"Point"}
}