{
  "type": "Feature",
  "properties": {
    "iso:country":"US",
    "sg:address":"3058 Southwall St",
    "sg:city":"Memphis",
    "sg:classifiers":[
        {
            "category":"Manufacturing",
            "subcategory":"Paper Products",
            "type":"Manufacturing & Wholesale Goods"
        }
    ],
    "sg:phone":"+1 901 743 3304",
    "sg:postcode":"38114",
    "sg:province":"TN",
    "sg:tags":[
        "envelope"
    ],
    "wof:name":"Tension Envelope Corp",
    "wof:placetype":"venue"
},
  "geometry": {"coordinates":[-89.961731,35.080152],"type":"Point"}
}