{
  "type": "Feature",
  "properties": {
    "addr:full":"1357 Tusculum Blvd Greeneville TN 37745",
    "addr:housenumber":"1357",
    "addr:postcode":"37745",
    "addr:street":"Tusculum Blvd",
    "iso:country":"US",
    "sg:address":"1357 Tusculum Blvd",
    "sg:city":"Greeneville",
    "sg:classifiers":[
        {
            "category":"Restaurant",
            "type":"Food & Drink"
        }
    ],
    "sg:menulink":"http://www.allmenus.com/tn/greeneville/231727-pals-sudden-service/menu/",
    "sg:phone":"+1 423 638 7555",
    "sg:postcode":"37745",
    "sg:province":"TN",
    "sg:tags":[
        "american"
    ],
    "wof:name":"Pal's Sudden Service",
    "wof:placetype":"venue"
},
  "geometry": {"coordinates":[-82.795542,36.172931],"type":"Point"}
}