{
  "type": "Feature",
  "properties": {
    "iso:country":"US",
    "sg:address":"180 Bear Creek Pike",
    "sg:city":"Columbia",
    "sg:classifiers":[
        {
            "category":"Insurance",
            "subcategory":"Insurance Agent",
            "type":"Services"
        }
    ],
    "sg:phone":"+1 931 381 9512",
    "sg:postcode":"38401",
    "sg:province":"TN",
    "wof:name":"Frank Cole Insurance Inc",
    "wof:placetype":"venue"
},
  "geometry": {"coordinates":[-87.013164,35.634747],"type":"Point"}
}