{
  "type": "Feature",
  "properties": {
    "iso:country":"US",
    "sg:address":"810 NW Broad St",
    "sg:city":"Murfreesboro",
    "sg:classifiers":[
        {
            "category":"Sports & Exercise",
            "subcategory":"Gym",
            "type":"Entertainment"
        }
    ],
    "sg:phone":"+1 615 895 6637",
    "sg:postcode":"37129",
    "sg:province":"TN",
    "sg:tags":[
        "club",
        "health",
        "studio",
        "gymnasium"
    ],
    "wof:name":"Southeastern Fitness Ctr",
    "wof:placetype":"venue"
},
  "geometry": {"coordinates":[-86.394976,35.844931],"type":"Point"}
}