{
  "type": "Feature",
  "properties": {
    "iso:country":"US",
    "sg:address":"2655 Maxwell Rd",
    "sg:city":"Bolivar",
    "sg:classifiers":[
        {
            "category":"Retail",
            "subcategory":"Repair Shop",
            "type":"Services"
        }
    ],
    "sg:phone":"+1 731 376 0578",
    "sg:postcode":"38008",
    "sg:province":"TN",
    "wof:name":"Taylor Farrier",
    "wof:placetype":"venue"
},
  "geometry": {"coordinates":[-88.952409,35.145731],"type":"Point"}
}