{
  "type": "Feature",
  "properties": {
    "addr:full":"6525 N Quail Hollow Rd Memphis TN 38120",
    "addr:housenumber":"6525",
    "addr:postcode":"38120",
    "addr:street":"N Quail Hollow Rd",
    "iso:country":"US",
    "sg:address":"6525 N Quail Hollow Rd",
    "sg:city":"Memphis",
    "sg:phone":"+1 901 756 8900",
    "sg:postcode":"38120",
    "sg:province":"TN",
    "sg:website":"http://www.cryeleike.com",
    "wof:name":"Crye-Leike Auctions",
    "wof:placetype":"venue"
},
  "geometry": {"coordinates":[-89.84572900000001,35.10505],"type":"Point"}
}