{
  "type": "Feature",
  "properties": {
    "iso:country":"US",
    "sg:address":"112 30th Avenue North",
    "sg:city":"Nashville",
    "sg:classifiers":[
        {
            "category":"Professional",
            "subcategory":"Computer Services",
            "type":"Services"
        }
    ],
    "sg:phone":"+1 615 351 2489",
    "sg:postcode":"37203",
    "sg:province":"TN",
    "sg:tags":[
        "events",
        "local",
        "search",
        "entertainment",
        "music",
        "movies",
        "restaurants"
    ],
    "sg:website":"http://www.eviesays.com/",
    "wof:name":"Eviesays",
    "wof:placetype":"venue"
},
  "geometry": {"coordinates":[-86.814898,36.144737],"type":"Point"}
}