{
  "type": "Feature",
  "properties": {
    "iso:country":"US",
    "sg:address":"6025 Walnut Grove Rd",
    "sg:city":"Memphis",
    "sg:classifiers":[
        {
            "category":"Health Services",
            "subcategory":"Doctor",
            "type":"Services"
        }
    ],
    "sg:phone":"+1 901 328 6031",
    "sg:postcode":"38120",
    "sg:province":"TN",
    "sg:tags":[
        "physician",
        "surgeon"
    ],
    "sg:website":"www.wlightmd.com",
    "wof:name":"William H Light MD",
    "wof:placetype":"venue"
},
  "geometry": {"coordinates":[-89.85512799999999,35.132802],"type":"Point"}
}