{
  "type": "Feature",
  "properties": {
    "iso:country":"US",
    "sg:address":"5320 Windingbrooke Ln",
    "sg:city":"Knoxville",
    "sg:classifiers":[
        {
            "category":"Health Services",
            "subcategory":"Doctor",
            "type":"Services"
        }
    ],
    "sg:phone":"+1 865 525 9934",
    "sg:postcode":"37918",
    "sg:province":"TN",
    "sg:tags":[
        "dentist"
    ],
    "wof:name":"Robert R Wallace DDS",
    "wof:placetype":"venue"
},
  "geometry": {"coordinates":[-83.889556,36.06652],"type":"Point"}
}