{
  "type": "Feature",
  "properties": {
    "iso:country":"US",
    "sg:address":"308 Twelve Oaks Rd",
    "sg:city":"Tullahoma",
    "sg:classifiers":[
        {
            "category":"Building & Trades",
            "subcategory":"Landscaping Services",
            "type":"Services"
        }
    ],
    "sg:phone":"+1 931 454 9190",
    "sg:postcode":"37388",
    "sg:province":"TN",
    "sg:tags":[
        "lawn",
        "maintenance",
        "grounds"
    ],
    "wof:name":"Southern Elegance Lawn Svc",
    "wof:placetype":"venue"
},
  "geometry": {"coordinates":[-86.19890700000001,35.385632],"type":"Point"}
}