{
  "type": "Feature",
  "properties": {
    "iso:country":"US",
    "sg:address":"111 N Columbia Ave",
    "sg:city":"Lawrenceburg",
    "sg:classifiers":[
        {
            "category":"Professional",
            "type":"Services"
        }
    ],
    "sg:phone":"+1 931 766 9999",
    "sg:postcode":"38464",
    "sg:province":"TN",
    "sg:tags":[
        "establishment"
    ],
    "wof:name":"Mortar & Pestle",
    "wof:placetype":"venue"
},
  "geometry": {"coordinates":[-87.33345,35.241493],"type":"Point"}
}