{
  "type": "Feature",
  "properties": {
    "iso:country":"US",
    "sg:address":"2650 Ottway Rd",
    "sg:city":"Greeneville",
    "sg:classifiers":[
        {
            "category":"Organizations",
            "subcategory":"Religious Organization",
            "type":"Services"
        }
    ],
    "sg:phone":"+1 423 234 9901",
    "sg:postcode":"37745",
    "sg:province":"TN",
    "wof:name":"Ottway United Methodist Church",
    "wof:placetype":"venue"
},
  "geometry": {"coordinates":[-82.868548,36.267924],"type":"Point"}
}