{
  "type": "Feature",
  "properties": {
    "addr:full":"336 Eleazar Rd Tellico Plains TN 37385",
    "addr:housenumber":"336",
    "addr:postcode":"37385",
    "addr:street":"Eleazar Rd",
    "iso:country":"US",
    "sg:address":"336 Eleazar Rd",
    "sg:city":"Tellico Plains",
    "sg:classifiers":[
        {
            "category":"Banks & Credit Unions",
            "subcategory":"Financial Services",
            "type":"Services"
        }
    ],
    "sg:phone":"+1 423 253 6592",
    "sg:postcode":"37385",
    "sg:province":"TN",
    "sg:tags":[
        "investor"
    ],
    "wof:name":"Tyboh Investors",
    "wof:placetype":"venue"
},
  "geometry": {"coordinates":[-84.356172,35.404534],"type":"Point"}
}