{
  "type": "Feature",
  "properties": {
    "addr:full":"8370 Cainsville Rd Lebanon TN 37090",
    "addr:postcode":"8370;37090",
    "addr:street":"Cainsville Rd",
    "iso:country":"US",
    "sg:address":"8370 Cainsville Rd",
    "sg:city":"Lebanon",
    "sg:classifiers":[
        {
            "category":"Professional",
            "subcategory":"Business Services",
            "type":"Services"
        }
    ],
    "sg:phone":"+1 615 286 2199",
    "sg:postcode":"37090",
    "sg:province":"TN",
    "wof:name":"Zebrasoft Technologies",
    "wof:placetype":"venue"
},
  "geometry": {"coordinates":[-86.238642,36.095663],"type":"Point"}
}