{
  "type": "Feature",
  "properties": {
    "addr:full":"152 Broad St Kingsport TN 37660",
    "addr:housenumber":"152",
    "addr:postcode":"37660",
    "addr:street":"Broad St",
    "iso:country":"US",
    "sg:address":"152 Broad St",
    "sg:city":"Kingsport",
    "sg:classifiers":[
        {
            "category":"Professional",
            "subcategory":"Accounting & Tax Preparation",
            "type":"Services"
        }
    ],
    "sg:phone":"+1 423 245 5611",
    "sg:postcode":"37660",
    "sg:province":"TN",
    "sg:tags":[
        "return",
        "filing"
    ],
    "wof:name":"B & B Tax & Bookkeeping Svc",
    "wof:placetype":"venue"
},
  "geometry": {"coordinates":[-82.561054,36.54614],"type":"Point"}
}