{
  "type": "Feature",
  "properties": {
    "addr:full":"525 Industrial Dr SW Cleveland TN 37311",
    "addr:housenumber":"525",
    "addr:postcode":"37311",
    "addr:street":"Industrial Dr Sw",
    "iso:country":"US",
    "sg:address":"525 Industrial Dr SW",
    "sg:city":"Cleveland",
    "sg:classifiers":[
        {
            "category":"Manufacturing",
            "subcategory":"Food",
            "type":"Manufacturing & Wholesale Goods"
        }
    ],
    "sg:phone":"+1 423 476 1302",
    "sg:postcode":"37311",
    "sg:province":"TN",
    "sg:tags":[
        "mfg"
    ],
    "wof:name":"Sunkids",
    "wof:placetype":"venue"
},
  "geometry": {"coordinates":[-84.90290299999999,35.133245],"type":"Point"}
}