{
  "type": "Feature",
  "properties": {
    "addr:full":"8532 Neubert Springs Rd Knoxville TN 37920",
    "addr:postcode":"8532;37920",
    "addr:street":"Neubert Springs Rd",
    "iso:country":"US",
    "sg:address":"8532 Neubert Springs Rd",
    "sg:city":"Knoxville",
    "sg:classifiers":[
        {
            "category":"Building & Trades",
            "subcategory":"Construction",
            "type":"Services"
        }
    ],
    "sg:phone":"+1 865 577 1299",
    "sg:postcode":"37920",
    "sg:province":"TN",
    "sg:tags":[
        "eating"
    ],
    "wof:name":"Gerald W Lane Sub Contractors",
    "wof:placetype":"venue"
},
  "geometry": {"coordinates":[-83.866141,35.865647],"type":"Point"}
}