{
  "type": "Feature",
  "properties": {
    "iso:country":"US",
    "sg:address":"624 E 11th St",
    "sg:city":"Chattanooga",
    "sg:classifiers":[
        {
            "category":"Food & Beverages",
            "subcategory":"Fruits & Vegetables",
            "type":"Retail Goods"
        },
        {
            "category":"Wholesale",
            "subcategory":"Fruits & Vegetables",
            "type":"Manufacturing & Wholesale Goods"
        }
    ],
    "sg:phone":"+1 423 267 8802",
    "sg:postcode":"37403",
    "sg:province":"TN",
    "sg:tags":[
        "produce",
        "shipper",
        "market"
    ],
    "wof:name":"P & P Produce",
    "wof:placetype":"venue"
},
  "geometry": {"coordinates":[-85.301508,35.040848],"type":"Point"}
}