{
  "type": "Feature",
  "properties": {
    "iso:country":"US",
    "sg:address":"2128 Fort Campbell Blvd",
    "sg:city":"Clarksville",
    "sg:classifiers":[
        {
            "category":"Professional",
            "subcategory":"Computer Services",
            "type":"Services"
        }
    ],
    "sg:phone":"+1 931 553 8954",
    "sg:postcode":"37042",
    "sg:province":"TN",
    "sg:tags":[
        "internet"
    ],
    "wof:name":"Advanced Internet",
    "wof:placetype":"venue"
},
  "geometry": {"coordinates":[-87.424143,36.602996],"type":"Point"}
}