{
  "type": "Feature",
  "properties": {
    "addr:full":"3141 Farrisview Blvd Memphis TN 38118",
    "addr:housenumber":"3141",
    "addr:postcode":"38118",
    "addr:street":"Farrisview Blvd",
    "iso:country":"US",
    "sg:address":"3141 Farrisview Blvd",
    "sg:city":"Memphis",
    "sg:classifiers":[
        {
            "category":"Professional",
            "subcategory":"Advertising",
            "type":"Services"
        }
    ],
    "sg:phone":"+1 901 365 8600",
    "sg:postcode":"38118",
    "sg:province":"TN",
    "sg:tags":[
        "distribution"
    ],
    "wof:name":"Jefferson Randolph Corp",
    "wof:placetype":"venue"
},
  "geometry": {"coordinates":[-89.959146,35.078377],"type":"Point"}
}