{
  "type": "Feature",
  "properties": {
    "addr:full":"300 Noel Ln Smyrna TN 37167",
    "addr:housenumber":"300",
    "addr:postcode":"37167",
    "addr:street":"Noel Ln",
    "iso:country":"US",
    "sg:address":"300 Noel Ln",
    "sg:city":"Smyrna",
    "sg:classifiers":[
        {
            "category":"Professional",
            "subcategory":"Business Services",
            "type":"Services"
        }
    ],
    "sg:phone":"+1 615 220 4378",
    "sg:postcode":"37167",
    "sg:province":"TN",
    "wof:name":"Montgomery Jarred",
    "wof:placetype":"venue"
},
  "geometry": {"coordinates":[-86.53448400000001,35.980025],"type":"Point"}
}