{
  "type": "Feature",
  "properties": {
    "iso:country":"US",
    "sg:address":"123 S Horton Pkwy",
    "sg:city":"Chapel Hill",
    "sg:classifiers":[
        {
            "category":"Retail",
            "subcategory":"Veterinary Services",
            "type":"Services"
        }
    ],
    "sg:phone":"+1 931 364 7799",
    "sg:postcode":"37034",
    "sg:province":"TN",
    "sg:tags":[
        "veterinarian"
    ],
    "wof:name":"Veterinary Services",
    "wof:placetype":"venue"
},
  "geometry": {"coordinates":[-86.693656,35.625475],"type":"Point"}
}