{
  "type": "Feature",
  "properties": {
    "iso:country":"US",
    "sg:address":"3962 Willow Lake Blvd # 5",
    "sg:city":"Memphis",
    "sg:classifiers":[
        {
            "category":"Organizations",
            "subcategory":"Community Association",
            "type":"Services"
        }
    ],
    "sg:phone":"+1 901 367 8200",
    "sg:postcode":"38118",
    "sg:province":"TN",
    "sg:tags":[
        "program",
        "incentive"
    ],
    "sg:website":"http://www.goqic.com",
    "wof:name":"Qic",
    "wof:placetype":"venue"
},
  "geometry": {"coordinates":[-89.89134799999999,35.038079],"type":"Point"}
}