{
  "type": "Feature",
  "properties": {
    "iso:country":"US",
    "sg:address":"1614 Glenhaven Dr",
    "sg:city":"Murfreesboro",
    "sg:classifiers":[
        {
            "category":"Professional",
            "subcategory":"Business Services",
            "type":"Services"
        }
    ],
    "sg:phone":"+1 615 896 2260",
    "sg:postcode":"37130",
    "sg:province":"TN",
    "wof:name":"JRS Advantage Enterprises",
    "wof:placetype":"venue"
},
  "geometry": {"coordinates":[-86.372532,35.822206],"type":"Point"}
}