{
  "type": "Feature",
  "properties": {
    "addr:full":"1765 Chisholm Rd Cypress Inn TN 38452",
    "addr:housenumber":"1765",
    "addr:postcode":"38452",
    "addr:street":"Chisholm Rd",
    "iso:country":"US",
    "sg:address":"1765 Chisholm Rd",
    "sg:city":"Cypress Inn",
    "sg:classifiers":[
        {
            "category":"Retail",
            "subcategory":"Auto Repair",
            "type":"Services"
        }
    ],
    "sg:phone":"+1 931 724 4929",
    "sg:postcode":"38452",
    "sg:province":"TN",
    "sg:tags":[
        "general"
    ],
    "wof:name":"Lees Garage",
    "wof:placetype":"venue"
},
  "geometry": {"coordinates":[-87.759513,35.118832],"type":"Point"}
}