{
  "type": "Feature",
  "properties": {
    "iso:country":"US",
    "sg:address":"1410 Sparta St",
    "sg:city":"Mc Minnville",
    "sg:classifiers":[
        {
            "category":"Real Estate",
            "subcategory":"Real Estate Operator",
            "type":"Services"
        }
    ],
    "sg:phone":"+1 931 507 1035",
    "sg:postcode":"37110",
    "sg:province":"TN",
    "sg:tags":[
        "mall",
        "shopping",
        "center"
    ],
    "wof:name":"Us Factory Outlets",
    "wof:placetype":"venue"
},
  "geometry": {"coordinates":[-85.74619199999999,35.695634],"type":"Point"}
}