{
  "type": "Feature",
  "properties": {
    "iso:country":"US",
    "sg:address":"721 Kempton Rd",
    "sg:city":"Knoxville",
    "sg:classifiers":[
        {
            "category":"Health Services",
            "subcategory":"Chiropractor",
            "type":"Services"
        }
    ],
    "sg:phone":"+1 865 690 5556",
    "sg:postcode":"37909",
    "sg:province":"TN",
    "wof:name":"Carlos Velado MD",
    "wof:placetype":"venue"
},
  "geometry": {"coordinates":[-84.05679600000001,35.940849],"type":"Point"}
}