{
  "type": "Feature",
  "properties": {
    "iso:country":"US",
    "sg:address":"151 Parks Dr",
    "sg:city":"Turtletown",
    "sg:classifiers":[
        {
            "category":"Building & Trades",
            "subcategory":"Construction",
            "type":"Services"
        }
    ],
    "sg:phone":"+1 423 496 5988",
    "sg:postcode":"37391",
    "sg:province":"TN",
    "sg:tags":[
        "general",
        "contractor"
    ],
    "wof:name":"Custom Design Woodcraft",
    "wof:placetype":"venue"
},
  "geometry": {"coordinates":[-84.388166,35.060031],"type":"Point"}
}