{
  "type": "Feature",
  "properties": {
    "iso:country":"US",
    "sg:address":"840 Sharp Springs Rd",
    "sg:city":"Winchester",
    "sg:classifiers":[
        {
            "category":"Professional",
            "subcategory":"Business Services",
            "type":"Services"
        }
    ],
    "sg:phone":"+1 931 967 7270",
    "sg:postcode":"37398",
    "sg:province":"TN",
    "wof:name":"Custom Interiors By Homescapes",
    "wof:placetype":"venue"
},
  "geometry": {"coordinates":[-86.10668099999999,35.201474],"type":"Point"}
}