{
  "type": "Feature",
  "properties": {
    "iso:country":"US",
    "sg:address":"6426 Summer Gale Dr",
    "sg:city":"Memphis",
    "sg:classifiers":[
        {
            "category":"Professional",
            "subcategory":"Engineering",
            "type":"Services"
        },
        {
            "category":"Home & Garden",
            "subcategory":"Building Materials",
            "type":"Retail Goods"
        },
        {
            "category":"Building & Trades",
            "subcategory":"Construction",
            "type":"Services"
        }
    ],
    "sg:phone":"+1 901 384 3511",
    "sg:postcode":"38134",
    "sg:province":"TN",
    "sg:tags":[
        "system",
        "specialty",
        "heating",
        "equipment",
        "contractor",
        "air conditioning"
    ],
    "sg:website":"http://find.trane.com/tcs-dealer-409921?utm_source=YP&utm_medium=banner&utm_campaign=TL",
    "wof:name":"Conway Services Heating, Cooling And Plumbing",
    "wof:placetype":"venue"
},
  "geometry": {"coordinates":[-89.8506,35.188591],"type":"Point"}
}