{
  "type": "Feature",
  "properties": {
    "iso:country":"US",
    "sg:address":"750 Cherokee Dr",
    "sg:city":"New Johnsonville",
    "sg:classifiers":[
        {
            "category":"Organizations",
            "subcategory":"Religious Organization",
            "type":"Services"
        }
    ],
    "sg:phone":"+1 931 535 2021",
    "sg:postcode":"37134",
    "sg:province":"TN",
    "sg:tags":[
        "clergy"
    ],
    "wof:name":"Jim Reeves",
    "wof:placetype":"venue"
},
  "geometry": {"coordinates":[-87.95799599999999,35.998698],"type":"Point"}
}