{
  "type": "Feature",
  "properties": {
    "iso:country":"US",
    "sg:address":"2235 Covington Pike",
    "sg:city":"Memphis",
    "sg:classifiers":[
        {
            "category":"Personal",
            "subcategory":"Tattoo Parlor",
            "type":"Services"
        },
        {
            "category":"Personal",
            "subcategory":"Piercing",
            "type":"Services"
        }
    ],
    "sg:phone":"+1 901 266 5255",
    "sg:postcode":"38128",
    "sg:province":"TN",
    "sg:tags":[
        "body"
    ],
    "wof:name":"Famous Tattoo Studio",
    "wof:placetype":"venue"
},
  "geometry": {"coordinates":[-89.89634700000001,35.185907],"type":"Point"}
}