{
  "type": "Feature",
  "properties": {
    "iso:country":"US",
    "sg:address":"7525 Old State Hwy 73",
    "sg:city":"Townsend",
    "sg:classifiers":[
        {
            "category":"Building & Trades",
            "subcategory":"Construction",
            "type":"Services"
        }
    ],
    "sg:phone":"+1 865 448 8102",
    "sg:postcode":"37882",
    "sg:province":"TN",
    "sg:tags":[
        "home",
        "builder"
    ],
    "wof:name":"Woodland Homes",
    "wof:placetype":"venue"
},
  "geometry": {"coordinates":[-83.762766,35.675565],"type":"Point"}
}