{
  "type": "Feature",
  "properties": {
    "iso:country":"US",
    "sg:address":"206 Ridgeview Dr",
    "sg:city":"Clinton",
    "sg:classifiers":[
        {
            "category":"Restaurant",
            "type":"Food & Drink"
        }
    ],
    "sg:phone":"+1 865 463 7801",
    "sg:postcode":"37716",
    "sg:province":"TN",
    "sg:tags":[
        "eating"
    ],
    "wof:name":"Sarahs Kitchen",
    "wof:placetype":"venue"
},
  "geometry": {"coordinates":[-84.133871,36.08015],"type":"Point"}
}