{
  "type": "Feature",
  "properties": {
    "addr:full":"3865 Highland Ln Crossville TN 38555",
    "addr:housenumber":"3865",
    "addr:postcode":"38555",
    "addr:street":"Highland Ln",
    "iso:country":"US",
    "sg:address":"3865 Highland Ln",
    "sg:city":"Crossville",
    "sg:classifiers":[
        {
            "category":"Retail",
            "subcategory":"Auto Repair",
            "type":"Services"
        }
    ],
    "sg:phone":"+1 931 484 4854",
    "sg:postcode":"38555",
    "sg:province":"TN",
    "sg:tags":[
        "industrial",
        "general"
    ],
    "wof:name":"Smith Equipment Co",
    "wof:placetype":"venue"
},
  "geometry": {"coordinates":[-84.95599199999999,35.947199],"type":"Point"}
}