{
  "type": "Feature",
  "properties": {
    "addr:full":"3849 US Hwy 41A N Unionville TN 37180",
    "addr:housenumber":"3849",
    "addr:postcode":"37180",
    "addr:street":"Us Hwy 41A N",
    "iso:country":"US",
    "sg:address":"3849 US Hwy 41A N",
    "sg:city":"Unionville",
    "sg:classifiers":[
        {
            "category":"Wholesale",
            "subcategory":"Farm Supplies",
            "type":"Manufacturing & Wholesale Goods"
        }
    ],
    "sg:phone":"+1 931 294 5101",
    "sg:postcode":"37180",
    "sg:province":"TN",
    "sg:tags":[
        "livestock"
    ],
    "wof:name":"Mid South Livestock Center LLC",
    "wof:placetype":"venue"
},
  "geometry": {"coordinates":[-86.593084,35.634602],"type":"Point"}
}