{
  "type": "Feature",
  "properties": {
    "iso:country":"US",
    "sg:address":"318 W Morford St",
    "sg:city":"Mc Minnville",
    "sg:classifiers":[
        {
            "category":"Autos & Motor Vehicles",
            "subcategory":"Automobile Sales",
            "type":"Retail Goods"
        }
    ],
    "sg:phone":"+1 931 474 1918",
    "sg:postcode":"37110",
    "sg:province":"TN",
    "sg:tags":[
        "used"
    ],
    "wof:name":"Just Rite Cars",
    "wof:placetype":"venue"
},
  "geometry": {"coordinates":[-85.778226,35.682723],"type":"Point"}
}