{
  "type": "Feature",
  "properties": {
    "iso:country":"US",
    "sg:address":"2956 N Thompson Ln",
    "sg:city":"Murfreesboro",
    "sg:classifiers":[
        {
            "category":"Retail",
            "subcategory":"Repair Shop",
            "type":"Services"
        }
    ],
    "sg:phone":"+1 615 893 8388",
    "sg:postcode":"37129",
    "sg:province":"TN",
    "wof:name":"Drivers Backhoe Service",
    "wof:placetype":"venue"
},
  "geometry": {"coordinates":[-86.410079,35.912775],"type":"Point"}
}