{
  "type": "Feature",
  "properties": {
    "iso:country":"US",
    "sg:address":"3099 Leeville Rd",
    "sg:city":"Mount Juliet",
    "sg:phone":"+1 615 444 2344",
    "sg:postcode":"37122",
    "sg:province":"TN",
    "sg:tags":[
        "farm",
        "field",
        "crop"
    ],
    "wof:name":"Michael Harris",
    "wof:placetype":"venue"
},
  "geometry": {"coordinates":[-86.420197,36.150918],"type":"Point"}
}