{
  "type": "Feature",
  "properties": {
    "addr:full":"4736 Midland Rd Christiana TN 37037",
    "addr:housenumber":"4736",
    "addr:postcode":"37037",
    "addr:street":"Midland Rd",
    "iso:country":"US",
    "sg:address":"4736 Midland Rd",
    "sg:city":"Christiana",
    "sg:classifiers":[
        {
            "category":"Building & Trades",
            "subcategory":"Electrical",
            "type":"Services"
        }
    ],
    "sg:phone":"+1 615 895 7667",
    "sg:postcode":"37037",
    "sg:province":"TN",
    "sg:tags":[
        "electrical",
        "contractor"
    ],
    "wof:name":"Safe T Lighting",
    "wof:placetype":"venue"
},
  "geometry": {"coordinates":[-86.46150799999999,35.725259],"type":"Point"}
}