{
  "type": "Feature",
  "properties": {
    "iso:country":"US",
    "sg:address":"2817 W End Ave",
    "sg:city":"Nashville",
    "sg:classifiers":[
        {
            "category":"Professional",
            "subcategory":"Computer Services",
            "type":"Services"
        }
    ],
    "sg:phone":"+1 615 596 3444",
    "sg:postcode":"37203",
    "sg:province":"TN",
    "sg:tags":[
        "repair"
    ],
    "sg:website":"www.servicetech.com",
    "wof:name":"SERVICETECH.COM",
    "wof:placetype":"venue"
},
  "geometry": {"coordinates":[-86.812361,36.145058],"type":"Point"}
}