{
  "type": "Feature",
  "properties": {
    "iso:country":"US",
    "sg:address":"826 E Main St",
    "sg:city":"Gallatin",
    "sg:classifiers":[
        {
            "category":"Professional",
            "type":"Services"
        }
    ],
    "sg:phone":"+1 615 206 0213",
    "sg:postcode":"37066",
    "sg:province":"TN",
    "wof:name":"Gaebony S Leath",
    "wof:placetype":"venue"
},
  "geometry": {"coordinates":[-86.428764,36.39768],"type":"Point"}
}