{
  "type": "Feature",
  "properties": {
    "addr:full":"1724 State St White Pine TN 37890",
    "addr:housenumber":"1724",
    "addr:postcode":"37890",
    "addr:street":"State St",
    "iso:country":"US",
    "sg:address":"1724 State St",
    "sg:city":"White Pine",
    "sg:classifiers":[
        {
            "category":"Shopping",
            "subcategory":"Used Merchandise",
            "type":"Retail Goods"
        }
    ],
    "sg:phone":"+1 865 674 6194",
    "sg:postcode":"37890",
    "sg:province":"TN",
    "sg:tags":[
        "pawnbroker"
    ],
    "wof:name":"Capital Pawn",
    "wof:placetype":"venue"
},
  "geometry": {"coordinates":[-83.282353,36.128823],"type":"Point"}
}