{
  "type": "Feature",
  "properties": {
    "iso:country":"US",
    "sg:address":"8865 Kingston Pike",
    "sg:city":"Knoxville",
    "sg:classifiers":[
        {
            "category":"Manufacturing",
            "subcategory":"Signs",
            "type":"Manufacturing & Wholesale Goods"
        }
    ],
    "sg:phone":"+1 865 531 3801",
    "sg:postcode":"37923",
    "sg:province":"TN",
    "wof:name":"About Signs & Graphics",
    "wof:placetype":"venue"
},
  "geometry": {"coordinates":[-84.079472,35.913759],"type":"Point"}
}