{
  "type": "Feature",
  "properties": {
    "addr:full":"694 Brewer Dr Nashville TN 37211",
    "addr:housenumber":"694",
    "addr:postcode":"37211",
    "addr:street":"Brewer Dr",
    "iso:country":"US",
    "sg:address":"694 Brewer Dr",
    "sg:city":"Nashville",
    "sg:classifiers":[
        {
            "category":"Home & Garden",
            "subcategory":"Household Appliances",
            "type":"Retail Goods"
        },
        {
            "category":"Building & Trades",
            "subcategory":"Construction",
            "type":"Services"
        },
        {
            "category":"Professional",
            "subcategory":"Engineering",
            "type":"Services"
        }
    ],
    "sg:phone":"+1 615 834 1636",
    "sg:postcode":"37211",
    "sg:province":"TN",
    "sg:tags":[
        "purifying",
        "system",
        "specialty",
        "equipment",
        "heating",
        "cleaning",
        "contractor",
        "air conditioning"
    ],
    "sg:website":"http://find.americanstandardair.com/customer-care-dealer-423020?utm_source=YP&utm_medium=banner&utm_campaign=TL",
    "wof:name":"South Nashville Htg & Clg",
    "wof:placetype":"venue"
},
  "geometry": {"coordinates":[-86.73764199999999,36.065795],"type":"Point"}
}