{
  "type": "Feature",
  "properties": {
    "iso:country":"US",
    "sg:address":"3809 Covington Pike",
    "sg:city":"Memphis",
    "sg:classifiers":[
        {
            "category":"Health Services",
            "subcategory":"Doctor",
            "type":"Services"
        }
    ],
    "sg:phone":"+1 901 328 2800",
    "sg:postcode":"38135",
    "sg:province":"TN",
    "sg:tags":[
        "physician",
        "surgeon"
    ],
    "wof:name":"Kerry Milligan MD",
    "wof:placetype":"venue"
},
  "geometry": {"coordinates":[-89.892781,35.228393],"type":"Point"}
}