{
  "type": "Feature",
  "properties": {
    "iso:country":"US",
    "sg:address":"203 Donna Ave",
    "sg:city":"Elizabethton",
    "sg:classifiers":[
        {
            "category":"Social Services",
            "subcategory":"Child Care",
            "type":"Services"
        }
    ],
    "sg:phone":"+1 423 543 5077",
    "sg:postcode":"37643",
    "sg:province":"TN",
    "sg:tags":[
        "day"
    ],
    "wof:name":"Roger & Nina Day",
    "wof:placetype":"venue"
},
  "geometry": {"coordinates":[-82.243691,36.342529],"type":"Point"}
}