{
  "type": "Feature",
  "properties": {
    "iso:country":"US",
    "sg:address":"407 Arendall St",
    "sg:city":"Adamsville",
    "sg:classifiers":[
        {
            "category":"Manufacturing",
            "subcategory":"Printing",
            "type":"Manufacturing & Wholesale Goods"
        }
    ],
    "sg:phone":"+1 731 632 9313",
    "sg:postcode":"38310",
    "sg:province":"TN",
    "sg:tags":[
        "publisher"
    ],
    "wof:name":"Fundco Printers/Keepsake",
    "wof:placetype":"venue"
},
  "geometry": {"coordinates":[-88.394054,35.24519],"type":"Point"}
}