{
  "type": "Feature",
  "properties": {
    "addr:full":"406 Union Ave Knoxville TN 37902",
    "addr:housenumber":"406",
    "addr:postcode":"37902",
    "addr:street":"Union Ave",
    "iso:country":"US",
    "sg:address":"406 Union Ave",
    "sg:city":"Knoxville",
    "sg:classifiers":[
        {
            "category":"Utilities",
            "subcategory":"Telephone",
            "type":"Services"
        }
    ],
    "sg:phone":"+1 865 291 0276",
    "sg:postcode":"37902",
    "sg:province":"TN",
    "sg:tags":[
        "communications"
    ],
    "wof:name":"Planet Connect Internet",
    "wof:placetype":"venue"
},
  "geometry": {"coordinates":[-83.91936099999999,35.964594],"type":"Point"}
}