{
  "type": "Feature",
  "properties": {
    "iso:country":"US",
    "sg:address":"1217 16th Ave S",
    "sg:city":"Nashville",
    "sg:classifiers":[
        {
            "category":"Shopping",
            "subcategory":"Computers & Home Electronics",
            "type":"Retail Goods"
        }
    ],
    "sg:phone":"+1 615 321 0511",
    "sg:postcode":"37212",
    "sg:province":"TN",
    "sg:tags":[
        "audio"
    ],
    "wof:name":"Digital Audio Post",
    "wof:placetype":"venue"
},
  "geometry": {"coordinates":[-86.793649,36.14118],"type":"Point"}
}