{
  "type": "Feature",
  "properties": {
    "iso:country":"US",
    "sg:address":"2756 Hwy 70 E",
    "sg:city":"Jackson",
    "sg:classifiers":[
        {
            "category":"Building & Trades",
            "subcategory":"Construction",
            "type":"Services"
        }
    ],
    "sg:phone":"+1 731 423 3488",
    "sg:postcode":"38305",
    "sg:province":"TN",
    "sg:tags":[
        "contractor"
    ],
    "wof:name":"Charles Dew Contracting",
    "wof:placetype":"venue"
},
  "geometry": {"coordinates":[-88.71619099999999,35.728968],"type":"Point"}
}