{
  "type": "Feature",
  "properties": {
    "addr:full":"596 State Hwy 431 Martin TN 38237",
    "addr:housenumber":"596",
    "addr:postcode":"38237",
    "addr:street":"State Hwy 431",
    "iso:country":"US",
    "sg:address":"596 State Hwy 431",
    "sg:city":"Martin",
    "sg:classifiers":[
        {
            "category":"Real Estate",
            "subcategory":"Real Estate Agent",
            "type":"Services"
        }
    ],
    "sg:phone":"+1 731 587 9595",
    "sg:postcode":"38237",
    "sg:province":"TN",
    "wof:name":"Reelfood Bank",
    "wof:placetype":"venue"
},
  "geometry": {"coordinates":[-88.84187900000001,36.341869],"type":"Point"}
}