{
  "type": "Feature",
  "properties": {
    "addr:full":"2466 Stafford Rd Loudon TN 37774",
    "addr:housenumber":"2466",
    "addr:postcode":"37774",
    "addr:street":"Stafford Rd",
    "iso:country":"US",
    "sg:address":"2466 Stafford Rd",
    "sg:city":"Loudon",
    "sg:classifiers":[
        {
            "category":"Farming",
            "subcategory":"Dairy Farm",
            "type":"Manufacturing & Wholesale Goods"
        }
    ],
    "sg:phone":"+1 865 458 4087",
    "sg:postcode":"37774",
    "sg:province":"TN",
    "wof:name":"Stockon Valley Dairy",
    "wof:placetype":"venue"
},
  "geometry": {"coordinates":[-84.467979,35.733562],"type":"Point"}
}