{
  "type": "Feature",
  "properties": {
    "addr:full":"6 E Main St Munford TN 38058",
    "addr:housenumber":"6",
    "addr:postcode":"38058",
    "addr:street":"E Main St",
    "iso:country":"US",
    "sg:address":"6 E Main St",
    "sg:city":"Munford",
    "sg:classifiers":[
        {
            "category":"Building & Trades",
            "subcategory":"Plumbing",
            "type":"Services"
        }
    ],
    "sg:phone":"+1 901 837 0366",
    "sg:postcode":"38058",
    "sg:province":"TN",
    "sg:tags":[
        "conditioning",
        "air",
        "system",
        "contractor"
    ],
    "wof:name":"Munford Heating & Air Cond Co",
    "wof:placetype":"venue"
},
  "geometry": {"coordinates":[-89.81523,35.449572],"type":"Point"}
}