{
  "type": "Feature",
  "properties": {
    "iso:country":"US",
    "sg:address":"3200 Old Hwy 46 S",
    "sg:city":"Dickson",
    "sg:classifiers":[
        {
            "category":"Food & Beverages",
            "subcategory":"Groceries & Convenience Stores",
            "type":"Retail Goods"
        }
    ],
    "sg:phone":"+1 615 412 6071",
    "sg:postcode":"37055",
    "sg:province":"TN",
    "sg:tags":[
        "grocer"
    ],
    "wof:name":"Jerry's Country Store",
    "wof:placetype":"venue"
},
  "geometry": {"coordinates":[-87.321341,35.978157],"type":"Point"}
}