{
  "type": "Feature",
  "properties": {
    "iso:country":"US",
    "sg:address":"109 Mofield St",
    "sg:city":"Livingston",
    "sg:classifiers":[
        {
            "category":"Professional",
            "type":"Services"
        }
    ],
    "sg:phone":"+1 931 823 5689",
    "sg:postcode":"38570",
    "sg:province":"TN",
    "wof:name":"Trauger Ney & Tuke",
    "wof:placetype":"venue"
},
  "geometry": {"coordinates":[-85.319644,36.383742],"type":"Point"}
}