{
  "type": "Feature",
  "properties": {
    "iso:country":"US",
    "sg:address":"1221 Buchanan St",
    "sg:city":"Nashville",
    "sg:classifiers":[
        {
            "category":"Education",
            "subcategory":"Dance Studio",
            "type":"Public Place"
        }
    ],
    "sg:phone":"+1 615 254 9848",
    "sg:postcode":"37208",
    "sg:province":"TN",
    "wof:name":"Dancearts Centre",
    "wof:placetype":"venue"
},
  "geometry": {"coordinates":[-86.806945,36.180096],"type":"Point"}
}