{
  "type": "Feature",
  "properties": {
    "iso:country":"US",
    "sg:address":"420 W Burt Dr",
    "sg:city":"Columbia",
    "sg:classifiers":[
        {
            "category":"Building & Trades",
            "subcategory":"Pest Control",
            "type":"Services"
        }
    ],
    "sg:phone":"+1 931 388 8800",
    "sg:postcode":"38401",
    "sg:province":"TN",
    "wof:name":"Orkin Exterminating Co Inc",
    "wof:placetype":"venue"
},
  "geometry": {"coordinates":[-87.01838499999999,35.652826],"type":"Point"}
}