{
  "type": "Feature",
  "properties": {
    "iso:country":"US",
    "sg:address":"116 N Water Ave",
    "sg:city":"Gallatin",
    "sg:classifiers":[
        {
            "category":"Shopping",
            "type":"Retail Goods"
        }
    ],
    "sg:phone":"+1 615 206 9777",
    "sg:postcode":"37066",
    "sg:province":"TN",
    "sg:tags":[
        "gallery",
        "merchandise"
    ],
    "wof:name":"Govan Gallery",
    "wof:placetype":"venue"
},
  "geometry": {"coordinates":[-86.446523,36.388551],"type":"Point"}
}