{
  "type": "Feature",
  "properties": {
    "iso:country":"US",
    "sg:address":"1406 McGavock Pike",
    "sg:city":"Nashville",
    "sg:classifiers":[
        {
            "category":"Personal",
            "subcategory":"Barber",
            "type":"Services"
        }
    ],
    "sg:phone":"+1 615 226 4644",
    "sg:postcode":"37216",
    "sg:province":"TN",
    "wof:name":"Moore's Barber Shop",
    "wof:placetype":"venue"
},
  "geometry": {"coordinates":[-86.72444,36.204767],"type":"Point"}
}