{
  "type": "Feature",
  "properties": {
    "iso:country":"US",
    "sg:address":"400 Dice St",
    "sg:city":"Morristown",
    "sg:classifiers":[
        {
            "category":"Building & Trades",
            "subcategory":"Construction",
            "type":"Services"
        }
    ],
    "sg:phone":"+1 423 585 4658",
    "sg:postcode":"37813",
    "sg:province":"TN",
    "sg:tags":[
        "marking",
        "maintenance",
        "parking"
    ],
    "wof:name":"Morristown Public Works Dept",
    "wof:placetype":"venue"
},
  "geometry": {"coordinates":[-83.299837,36.20711],"type":"Point"}
}