{
  "type": "Feature",
  "properties": {
    "iso:country":"US",
    "sg:address":"4750 Hwy 70 N",
    "sg:city":"Crossville",
    "sg:classifiers":[
        {
            "category":"Food & Beverages",
            "subcategory":"Groceries & Convenience Stores",
            "type":"Retail Goods"
        }
    ],
    "sg:phone":"+1 931 456 7599",
    "sg:postcode":"38571",
    "sg:province":"TN",
    "wof:name":"Little Brad's",
    "wof:placetype":"venue"
},
  "geometry": {"coordinates":[-85.076561,35.995233],"type":"Point"}
}