{
  "type": "Feature",
  "properties": {
    "addr:full":"794 Clark Rd Fulton TN 42041",
    "addr:housenumber":"794",
    "addr:postcode":"42041",
    "addr:street":"Clark Rd",
    "iso:country":"US",
    "sg:address":"794 Clark Rd",
    "sg:city":"Fulton",
    "sg:classifiers":[
        {
            "category":"Farming",
            "subcategory":"Poultry Farm",
            "type":"Manufacturing & Wholesale Goods"
        }
    ],
    "sg:phone":"+1 270 472 0171",
    "sg:postcode":"42041",
    "sg:province":"TN",
    "sg:tags":[
        "chicken"
    ],
    "wof:name":"Hidden Hills Poultry",
    "wof:placetype":"venue"
},
  "geometry": {"coordinates":[-88.96242599999999,36.583525],"type":"Point"}
}