{
  "type": "Feature",
  "properties": {
    "iso:country":"US",
    "sg:address":"2909 Millers Way",
    "sg:city":"Sevierville",
    "sg:classifiers":[
        {
            "category":"Recreation",
            "type":"Entertainment"
        }
    ],
    "sg:phone":"+1 865 428 8363",
    "sg:postcode":"37876",
    "sg:province":"TN",
    "wof:name":"Middle Creek Riding Stables",
    "wof:placetype":"venue"
},
  "geometry": {"coordinates":[-83.526566,35.780037],"type":"Point"}
}