{
  "type": "Feature",
  "properties": {
    "iso:country":"US",
    "sg:address":"3172 Lewisburg Hwy",
    "sg:city":"Petersburg",
    "sg:classifiers":[
        {
            "category":"Farming",
            "subcategory":"Farm",
            "type":"Manufacturing & Wholesale Goods"
        }
    ],
    "sg:phone":"+1 931 659 6657",
    "sg:postcode":"37144",
    "sg:province":"TN",
    "wof:name":"Mc Gee Livestock Farms",
    "wof:placetype":"venue"
},
  "geometry": {"coordinates":[-86.63533099999999,35.30273],"type":"Point"}
}