{
  "type": "Feature",
  "properties": {
    "iso:country":"US",
    "sg:address":"3048 Sax Rd",
    "sg:city":"Memphis",
    "sg:classifiers":[
        {
            "category":"Building & Trades",
            "subcategory":"Landscaping Services",
            "type":"Services"
        }
    ],
    "sg:phone":"+1 901 789 2663",
    "sg:postcode":"38109",
    "sg:province":"TN",
    "sg:tags":[
        "lawn",
        "maintenance",
        "grounds"
    ],
    "wof:name":"Thompson Lawn Svc",
    "wof:placetype":"venue"
},
  "geometry": {"coordinates":[-90.086586,35.066823],"type":"Point"}
}