{
  "type": "Feature",
  "properties": {
    "addr:full":"3150 NW Park Dr Knoxville TN 37921",
    "addr:housenumber":"3150",
    "addr:postcode":"37921",
    "addr:street":"Nw Park Dr",
    "iso:country":"US",
    "sg:address":"3150 NW Park Dr",
    "sg:city":"Knoxville",
    "sg:classifiers":[
        {
            "category":"Professional",
            "type":"Services"
        }
    ],
    "sg:phone":"+1 865 938 4552",
    "sg:postcode":"37921",
    "sg:province":"TN",
    "wof:name":"Rual Metro Fleet Svc",
    "wof:placetype":"venue"
},
  "geometry": {"coordinates":[-84.030536,36.001684],"type":"Point"}
}