{
  "type": "Feature",
  "properties": {
    "addr:full":"2994 Lamar Ave Memphis TN 38114",
    "addr:housenumber":"2994",
    "addr:postcode":"38114",
    "addr:street":"Lamar Ave",
    "iso:country":"US",
    "sg:address":"2994 Lamar Ave",
    "sg:city":"Memphis",
    "sg:classifiers":[
        {
            "category":"Retail",
            "subcategory":"Repair Shop",
            "type":"Services"
        }
    ],
    "sg:phone":"+1 901 744 6370",
    "sg:postcode":"38114",
    "sg:province":"TN",
    "sg:tags":[
        "equipment",
        "video"
    ],
    "wof:name":"Jim's TV & VCR Repair",
    "wof:placetype":"venue"
},
  "geometry": {"coordinates":[-89.963506,35.087314],"type":"Point"}
}