{
  "type": "Feature",
  "properties": {
    "iso:country":"US",
    "sg:address":"774 Flinn Dr",
    "sg:city":"Chattanooga",
    "sg:classifiers":[
        {
            "category":"Professional",
            "subcategory":"Management & Consulting",
            "type":"Services"
        }
    ],
    "sg:phone":"+1 423 894 7662",
    "sg:postcode":"37412",
    "sg:province":"TN",
    "wof:name":"ABC Computer Learning Center",
    "wof:placetype":"venue"
},
  "geometry": {"coordinates":[-85.179107,34.994236],"type":"Point"}
}