{
  "type": "Feature",
  "properties": {
    "iso:country":"US",
    "sg:address":"330 Franklin Rd",
    "sg:city":"Brentwood",
    "sg:classifiers":[
        {
            "category":"Food & Beverages",
            "subcategory":"Groceries & Convenience Stores",
            "type":"Retail Goods"
        }
    ],
    "sg:phone":"+1 615 377 3690",
    "sg:postcode":"37027",
    "sg:province":"TN",
    "sg:tags":[
        "grocer"
    ],
    "sg:website":"www.kroger.com",
    "wof:name":"Kroger",
    "wof:placetype":"venue"
},
  "geometry": {"coordinates":[-86.792039,36.027179],"type":"Point"}
}