{
  "type": "Feature",
  "properties": {
    "addr:full":"184 Shady Loop Crossville TN 38571",
    "addr:housenumber":"184",
    "addr:postcode":"38571",
    "addr:street":"Shady Loop",
    "iso:country":"US",
    "sg:address":"184 Shady Loop",
    "sg:city":"Crossville",
    "sg:classifiers":[
        {
            "category":"Building & Trades",
            "subcategory":"Construction",
            "type":"Services"
        }
    ],
    "sg:phone":"+1 931 277 3278",
    "sg:postcode":"38571",
    "sg:province":"TN",
    "sg:tags":[
        "contractor"
    ],
    "wof:name":"Comfort Zone",
    "wof:placetype":"venue"
},
  "geometry": {"coordinates":[-85.20154100000001,36.042479],"type":"Point"}
}