{
  "type": "Feature",
  "properties": {
    "iso:country":"US",
    "sg:address":"349 Foutch Dr",
    "sg:city":"Cookeville",
    "sg:classifiers":[
        {
            "category":"Professional",
            "subcategory":"Employment Agencies",
            "type":"Services"
        }
    ],
    "sg:phone":"+1 931 520 6005",
    "sg:postcode":"38501",
    "sg:province":"TN",
    "wof:name":"Wise Staffing",
    "wof:placetype":"venue"
},
  "geometry": {"coordinates":[-85.501558,36.155537],"type":"Point"}
}