{
  "type": "Feature",
  "properties": {
    "iso:country":"US",
    "sg:address":"1903 Sweetbriar Ave",
    "sg:city":"Nashville",
    "sg:classifiers":[
        {
            "category":"Building & Trades",
            "subcategory":"Construction",
            "type":"Services"
        }
    ],
    "sg:phone":"+1 615 460 1110",
    "sg:postcode":"37212",
    "sg:province":"TN",
    "sg:tags":[
        "house"
    ],
    "wof:name":"Ben Dodd Remodeler",
    "wof:placetype":"venue"
},
  "geometry": {"coordinates":[-86.801985,36.125502],"type":"Point"}
}