{
  "type": "Feature",
  "properties": {
    "iso:country":"US",
    "sg:address":"6107 Wendover Glen",
    "sg:city":"Brentwood",
    "sg:classifiers":[
        {
            "category":"Professional",
            "subcategory":"Management & Consulting",
            "type":"Services"
        }
    ],
    "sg:phone":"+1 615 371 4292",
    "sg:postcode":"37027",
    "sg:province":"TN",
    "sg:tags":[
        "agency",
        "advertising"
    ],
    "wof:name":"Synergy Associates Inc",
    "wof:placetype":"venue"
},
  "geometry": {"coordinates":[-86.830523,36.01614],"type":"Point"}
}