{
  "type": "Feature",
  "properties": {
    "iso:country":"US",
    "sg:address":"2183 Old Knoxville Hwy",
    "sg:city":"New Market",
    "sg:classifiers":[
        {
            "category":"Farming",
            "subcategory":"Livestock Farm",
            "type":"Manufacturing & Wholesale Goods"
        }
    ],
    "sg:phone":"+1 865 933 6903",
    "sg:postcode":"37820",
    "sg:province":"TN",
    "sg:tags":[
        "beef",
        "feedlot",
        "cattle"
    ],
    "wof:name":"Darrell Mundy",
    "wof:placetype":"venue"
},
  "geometry": {"coordinates":[-83.60069,36.019896],"type":"Point"}
}