{
  "type": "Feature",
  "properties": {
    "addr:full":"3355 Poplar Ave Memphis TN 38111",
    "addr:housenumber":"3355",
    "addr:postcode":"38111",
    "addr:street":"Poplar Ave",
    "iso:country":"US",
    "sg:address":"3355 Poplar Ave",
    "sg:city":"Memphis",
    "sg:classifiers":[
        {
            "category":"Building & Trades",
            "subcategory":"Plumbing",
            "type":"Services"
        }
    ],
    "sg:phone":"+1 901 324 6092",
    "sg:postcode":"38111",
    "sg:province":"TN",
    "sg:tags":[
        "conditioning",
        "air",
        "system",
        "contractor"
    ],
    "wof:name":"Hawks Brothers Hvac",
    "wof:placetype":"venue"
},
  "geometry": {"coordinates":[-89.949815,35.128909],"type":"Point"}
}