{
  "type": "Feature",
  "properties": {
    "addr:full":"517 E 5th St Chattanooga TN 37403",
    "addr:housenumber":"517",
    "addr:postcode":"37403",
    "addr:street":"E 5Th St",
    "iso:country":"US",
    "sg:address":"517 E 5th St",
    "sg:city":"Chattanooga",
    "sg:classifiers":[
        {
            "category":"Professional",
            "type":"Services"
        }
    ],
    "sg:phone":"+1 423 756 0763",
    "sg:postcode":"37403",
    "sg:province":"TN",
    "sg:tags":[
        "establishment"
    ],
    "wof:name":"Community Impact Fund",
    "wof:placetype":"venue"
},
  "geometry": {"coordinates":[-85.302376,35.050341],"type":"Point"}
}