{
  "type": "Feature",
  "properties": {
    "addr:full":"204 Sunrise Ave Morristown TN 37813",
    "addr:housenumber":"204",
    "addr:postcode":"37813",
    "addr:street":"Sunrise Ave",
    "iso:country":"US",
    "sg:address":"204 Sunrise Ave",
    "sg:city":"Morristown",
    "sg:classifiers":[
        {
            "category":"Personal",
            "subcategory":"Beauty Salon",
            "type":"Services"
        }
    ],
    "sg:phone":"+1 423 586 5023",
    "sg:postcode":"37813",
    "sg:province":"TN",
    "sg:tags":[
        "shop"
    ],
    "wof:name":"Hair Connections",
    "wof:placetype":"venue"
},
  "geometry": {"coordinates":[-83.289359,36.205006],"type":"Point"}
}