{
  "type": "Feature",
  "properties": {
    "addr:full":"3212 Bloomingdale Rd Kingsport TN 37660",
    "addr:housenumber":"3212",
    "addr:postcode":"37660",
    "addr:street":"Bloomingdale Rd",
    "iso:country":"US",
    "sg:address":"3212 Bloomingdale Rd",
    "sg:city":"Kingsport",
    "sg:classifiers":[
        {
            "category":"Utilities",
            "subcategory":"Water",
            "type":"Services"
        }
    ],
    "sg:phone":"+1 423 288 6551",
    "sg:postcode":"37660",
    "sg:province":"TN",
    "sg:tags":[
        "company",
        "sewage"
    ],
    "wof:name":"Bloomingdale Water Dept",
    "wof:placetype":"venue"
},
  "geometry": {"coordinates":[-82.488421,36.584879],"type":"Point"}
}