{
  "type": "Feature",
  "properties": {
    "addr:full":"5412 Kingston Pike Knoxville TN 37919",
    "addr:housenumber":"5412",
    "addr:postcode":"37919",
    "addr:street":"Kingston Pike",
    "iso:country":"US",
    "sg:address":"5412 Kingston Pike",
    "sg:city":"Knoxville",
    "sg:classifiers":[
        {
            "category":"Personal",
            "subcategory":"Beauty Salon",
            "type":"Services"
        }
    ],
    "sg:phone":"+1 865 584 3158",
    "sg:postcode":"37919",
    "sg:province":"TN",
    "sg:tags":[
        "shop"
    ],
    "wof:name":"Bellas Hair Salon Etc",
    "wof:placetype":"venue"
},
  "geometry": {"coordinates":[-83.992769,35.935653],"type":"Point"}
}