{
  "type": "Feature",
  "properties": {
    "iso:country":"US",
    "sg:address":"224 N Maple St",
    "sg:city":"Adamsville",
    "sg:classifiers":[
        {
            "category":"Banks & Credit Unions",
            "subcategory":"Bank",
            "type":"Services"
        }
    ],
    "sg:phone":"+1 731 632 5441",
    "sg:postcode":"38310",
    "sg:province":"TN",
    "sg:tags":[
        "depository",
        "banking"
    ],
    "wof:name":"Cash of Adamsville",
    "wof:placetype":"venue"
},
  "geometry": {"coordinates":[-88.39070599999999,35.236945],"type":"Point"}
}