{
  "type": "Feature",
  "properties": {
    "iso:country":"US",
    "sg:address":"627 Signal Mountain Blvd",
    "sg:city":"Chattanooga",
    "sg:classifiers":[
        {
            "category":"Food & Beverages",
            "subcategory":"Groceries & Convenience Stores",
            "type":"Retail Goods"
        }
    ],
    "sg:phone":"+1 423 756 6995",
    "sg:postcode":"37405",
    "sg:province":"TN",
    "wof:name":"Favorite Market",
    "wof:placetype":"venue"
},
  "geometry": {"coordinates":[-85.32776,35.096849],"type":"Point"}
}