{
  "type": "Feature",
  "properties": {
    "iso:country":"US",
    "sg:address":"2301 N Ocoee St",
    "sg:city":"Cleveland",
    "sg:classifiers":[
        {
            "category":"Health Services",
            "subcategory":"Doctor",
            "type":"Services"
        }
    ],
    "sg:phone":"+1 423 339 0007",
    "sg:postcode":"37311",
    "sg:province":"TN",
    "sg:tags":[
        "medical"
    ],
    "wof:name":"Cherokee Womens Center PC",
    "wof:placetype":"venue"
},
  "geometry": {"coordinates":[-84.86691399999999,35.176922],"type":"Point"}
}