{
  "type": "Feature",
  "properties": {
    "iso:country":"US",
    "sg:address":"166 Rock Dr",
    "sg:city":"Palmer",
    "sg:classifiers":[
        {
            "category":"Retail",
            "subcategory":"Auto Repair",
            "type":"Services"
        }
    ],
    "sg:phone":"+1 931 779 3830",
    "sg:postcode":"37307",
    "sg:province":"TN",
    "sg:tags":[
        "body",
        "automobile",
        "painting"
    ],
    "wof:name":"James Harold Body Shop",
    "wof:placetype":"venue"
},
  "geometry": {"coordinates":[-84.645786,35.163321],"type":"Point"}
}