{
  "type": "Feature",
  "properties": {
    "addr:full":"1479 John Ridge Dr Collierville TN 38017",
    "addr:housenumber":"1479",
    "addr:postcode":"38017",
    "addr:street":"John Ridge Dr",
    "iso:country":"US",
    "sg:address":"1479 John Ridge Dr",
    "sg:city":"Collierville",
    "sg:classifiers":[
        {
            "category":"Building & Trades",
            "subcategory":"Electrical",
            "type":"Services"
        }
    ],
    "sg:phone":"+1 901 861 1546",
    "sg:postcode":"38017",
    "sg:province":"TN",
    "sg:tags":[
        "contractor"
    ],
    "wof:name":"Johnson Safety Equipment Co",
    "wof:placetype":"venue"
},
  "geometry": {"coordinates":[-89.691427,35.081105],"type":"Point"}
}