{
  "type": "Feature",
  "properties": {
    "addr:full":"263 Hurd Rd Church Hill TN 37642",
    "addr:housenumber":"263",
    "addr:postcode":"37642",
    "addr:street":"Hurd Rd",
    "iso:country":"US",
    "sg:address":"263 Hurd Rd",
    "sg:city":"Church Hill",
    "sg:classifiers":[
        {
            "category":"Building & Trades",
            "subcategory":"Construction",
            "type":"Services"
        }
    ],
    "sg:phone":"+1 423 357 7095",
    "sg:postcode":"37642",
    "sg:province":"TN",
    "sg:tags":[
        "house"
    ],
    "wof:name":"J Johnson Jr Const",
    "wof:placetype":"venue"
},
  "geometry": {"coordinates":[-82.69528699999999,36.569975],"type":"Point"}
}