{
  "type": "Feature",
  "properties": {
    "addr:full":"3585 Elvis Presley Blvd Memphis TN 38116",
    "addr:housenumber":"3585",
    "addr:postcode":"38116",
    "addr:street":"Elvis Presley Blvd",
    "iso:country":"US",
    "sg:address":"3585 Elvis Presley Blvd",
    "sg:city":"Memphis",
    "sg:classifiers":[
        {
            "category":"Autos & Motor Vehicles",
            "subcategory":"Auto Supplies",
            "type":"Retail Goods"
        }
    ],
    "sg:phone":"+1 901 396 3302",
    "sg:postcode":"38116",
    "sg:province":"TN",
    "sg:tags":[
        "equipment",
        "part",
        "electrical",
        "batteries-storage",
        "automobile"
    ],
    "sg:website":"http://www.advanceautoparts.com",
    "wof:name":"Advance Auto Parts",
    "wof:placetype":"venue"
},
  "geometry": {"coordinates":[-90.025051,35.050501],"type":"Point"}
}