{
  "type": "Feature",
  "properties": {
    "addr:full":"1125 Frayser Blvd Memphis TN 38127",
    "addr:housenumber":"1125",
    "addr:postcode":"38127",
    "addr:street":"Frayser Blvd",
    "iso:country":"US",
    "sg:address":"1125 Frayser Blvd",
    "sg:city":"Memphis",
    "sg:classifiers":[
        {
            "category":"Building & Trades",
            "subcategory":"Construction",
            "type":"Services"
        }
    ],
    "sg:phone":"+1 901 643 0813",
    "sg:postcode":"38127",
    "sg:province":"TN",
    "sg:tags":[
        "wallcoverings-installation",
        "wallpaper",
        "painting",
        "contractor"
    ],
    "wof:name":"Darnell Painting",
    "wof:placetype":"venue"
},
  "geometry": {"coordinates":[-90.024642,35.216593],"type":"Point"}
}