{
  "type": "Feature",
  "properties": {
    "iso:country":"US",
    "sg:address":"4388 Forest Valley Cove",
    "sg:city":"Memphis",
    "sg:classifiers":[
        {
            "category":"Organizations",
            "subcategory":"Religious Organization",
            "type":"Services"
        }
    ],
    "sg:phone":"+1 901 367 2479",
    "sg:postcode":"38141",
    "sg:province":"TN",
    "wof:name":"Bethel Communications",
    "wof:placetype":"venue"
},
  "geometry": {"coordinates":[-89.86802400000001,35.028516],"type":"Point"}
}