{
  "type": "Feature",
  "properties": {
    "addr:full":"100 Elk Ave S Fayetteville TN 37334",
    "addr:housenumber":"100",
    "addr:postcode":"37334",
    "addr:street":"Elk Ave S",
    "iso:country":"US",
    "sg:address":"100 Elk Ave S",
    "sg:city":"Fayetteville",
    "sg:classifiers":[
        {
            "category":"Shopping",
            "subcategory":"Used Merchandise",
            "type":"Retail Goods"
        }
    ],
    "sg:phone":"+1 931 438 0058",
    "sg:postcode":"37334",
    "sg:province":"TN",
    "sg:tags":[
        "antique"
    ],
    "wof:name":"Mockingbird Antique Mall & Ice",
    "wof:placetype":"venue"
},
  "geometry": {"coordinates":[-86.56923999999999,35.152103],"type":"Point"}
}