{
  "type": "Feature",
  "properties": {
    "iso:country":"US",
    "sg:address":"4116 Taft Hwy",
    "sg:city":"Signal Mountain",
    "sg:classifiers":[
        {
            "category":"Building & Trades",
            "subcategory":"Landscaping Services",
            "type":"Services"
        }
    ],
    "sg:phone":"+1 423 843 2553",
    "sg:postcode":"37377",
    "sg:province":"TN",
    "sg:tags":[
        "lawn",
        "maintenance",
        "grounds"
    ],
    "wof:name":"Middle Valley Lawn Care",
    "wof:placetype":"venue"
},
  "geometry": {"coordinates":[-85.335948,35.179403],"type":"Point"}
}