{
  "type": "Feature",
  "properties": {
    "iso:country":"US",
    "sg:address":"2121 S Germantown Rd",
    "sg:city":"Germantown",
    "sg:classifiers":[
        {
            "category":"Professional",
            "subcategory":"Printing & Photocopies",
            "type":"Services"
        }
    ],
    "sg:phone":"+1 901 755 1190",
    "sg:postcode":"38138",
    "sg:province":"TN",
    "wof:name":"Clarke's Quick Print",
    "wof:placetype":"venue"
},
  "geometry": {"coordinates":[-89.809512,35.090738],"type":"Point"}
}