{
  "type": "Feature",
  "properties": {
    "iso:country":"US",
    "sg:address":"2 W 2nd St",
    "sg:city":"Chattanooga",
    "sg:classifiers":[
        {
            "category":"Restaurant",
            "type":"Food & Drink"
        }
    ],
    "sg:phone":"+1 423 648 0880",
    "sg:postcode":"37402",
    "sg:province":"TN",
    "wof:name":"Tallan Cellar",
    "wof:placetype":"venue"
},
  "geometry": {"coordinates":[-85.31065599999999,35.054748],"type":"Point"}
}