{
  "type": "Feature",
  "properties": {
    "iso:country":"US",
    "sg:address":"2518 Fite Rd",
    "sg:city":"Memphis",
    "sg:classifiers":[
        {
            "category":"Organizations",
            "subcategory":"Religious Organization",
            "type":"Services"
        }
    ],
    "sg:phone":"+1 901 357 6902",
    "sg:postcode":"38127",
    "sg:province":"TN",
    "sg:tags":[
        "church"
    ],
    "wof:name":"Greenleaf C M E Church",
    "wof:placetype":"venue"
},
  "geometry": {"coordinates":[-89.981139,35.272425],"type":"Point"}
}