{
  "type": "Feature",
  "properties": {
    "addr:full":"345 Fairway Dr Clarksville TN 37043",
    "addr:housenumber":"345",
    "addr:postcode":"37043",
    "addr:street":"Fairway Dr",
    "iso:country":"US",
    "sg:address":"345 Fairway Dr",
    "sg:city":"Clarksville",
    "sg:classifiers":[
        {
            "category":"Manufacturing",
            "subcategory":"Printing",
            "type":"Manufacturing & Wholesale Goods"
        }
    ],
    "sg:phone":"+1 931 350 0204",
    "sg:postcode":"37043",
    "sg:province":"TN",
    "sg:tags":[
        "lithographic",
        "commercial"
    ],
    "wof:name":"Hammer Lithograph Corp",
    "wof:placetype":"venue"
},
  "geometry": {"coordinates":[-87.288766,36.529795],"type":"Point"}
}