{
  "type": "Feature",
  "properties": {
    "addr:full":"1921 Elm Hill Pike Nashville TN 37210",
    "addr:housenumber":"1921",
    "addr:postcode":"37210",
    "addr:street":"Elm Hill Pike",
    "iso:country":"US",
    "sg:address":"1921 Elm Hill Pike",
    "sg:city":"Nashville",
    "sg:classifiers":[
        {
            "category":"Manufacturing",
            "subcategory":"Printing",
            "type":"Manufacturing & Wholesale Goods"
        }
    ],
    "sg:phone":"+1 615 885 8206",
    "sg:postcode":"37210",
    "sg:province":"TN",
    "sg:tags":[
        "printer"
    ],
    "sg:website":"www.sirspeedy3032.com",
    "wof:name":"Sir Speedy Printing Ctr",
    "wof:placetype":"venue"
},
  "geometry": {"coordinates":[-86.700901,36.15003],"type":"Point"}
}