{
  "type": "Feature",
  "properties": {
    "iso:country":"US",
    "sg:address":"266 Shrum Cemetery Rd",
    "sg:city":"Westmoreland",
    "sg:classifiers":[
        {
            "category":"Professional",
            "subcategory":"Management & Consulting",
            "type":"Services"
        }
    ],
    "sg:phone":"+1 615 666 5882",
    "sg:postcode":"37186",
    "sg:province":"TN",
    "wof:name":"Kateryne LLC",
    "wof:placetype":"venue"
},
  "geometry": {"coordinates":[-86.15560600000001,36.532036],"type":"Point"}
}