{
  "type": "Feature",
  "properties": {
    "addr:full":"112 N Main St Kenton TN 38233",
    "addr:housenumber":"112",
    "addr:postcode":"38233",
    "addr:street":"N Main St",
    "iso:country":"US",
    "sg:address":"112 N Main St",
    "sg:city":"Kenton",
    "sg:classifiers":[
        {
            "category":"Social Services",
            "subcategory":"Child Care",
            "type":"Services"
        }
    ],
    "sg:phone":"+1 731 749 0098",
    "sg:postcode":"38233",
    "sg:province":"TN",
    "wof:name":"Small Blessings",
    "wof:placetype":"venue"
},
  "geometry": {"coordinates":[-89.011319,36.203005],"type":"Point"}
}