{
  "type": "Feature",
  "properties": {
    "addr:full":"534 Rural Hill Rd Nashville TN 37217",
    "addr:housenumber":"534",
    "addr:postcode":"37217",
    "addr:street":"Rural Hill Rd",
    "iso:country":"US",
    "sg:address":"534 Rural Hill Rd",
    "sg:city":"Nashville",
    "sg:classifiers":[
        {
            "category":"Building & Trades",
            "subcategory":"Construction",
            "type":"Services"
        }
    ],
    "sg:phone":"+1 615 365 0729",
    "sg:postcode":"37217",
    "sg:province":"TN",
    "sg:tags":[
        "hanging",
        "contractor"
    ],
    "wof:name":"S Puckett Custom Coatings",
    "wof:placetype":"venue"
},
  "geometry": {"coordinates":[-86.6232,36.084876],"type":"Point"}
}