{
  "type": "Feature",
  "properties": {
    "iso:country":"US",
    "sg:address":"711 Hill Ave",
    "sg:city":"Nashville",
    "sg:classifiers":[
        {
            "category":"Utilities",
            "subcategory":"Telephone",
            "type":"Services"
        },
        {
            "category":"Wholesale",
            "subcategory":"Electrical",
            "type":"Manufacturing & Wholesale Goods"
        }
    ],
    "sg:phone":"+1 615 256 3975",
    "sg:postcode":"37210",
    "sg:province":"TN",
    "sg:tags":[
        "system",
        "business",
        "telecommunication"
    ],
    "sg:website":"www.tbcsinc.com",
    "wof:name":"Tennessee Business Comm Svcs",
    "wof:placetype":"venue"
},
  "geometry": {"coordinates":[-86.73051100000001,36.136931],"type":"Point"}
}