{
  "type": "Feature",
  "properties": {
    "addr:full":"4513 Alabama Ave Chattanooga TN 37409",
    "addr:housenumber":"4513",
    "addr:postcode":"37409",
    "addr:street":"Alabama Ave",
    "iso:country":"US",
    "sg:address":"4513 Alabama Ave",
    "sg:city":"Chattanooga",
    "sg:classifiers":[
        {
            "category":"Building & Trades",
            "subcategory":"Construction",
            "type":"Services"
        }
    ],
    "sg:phone":"+1 423 821 0631",
    "sg:postcode":"37409",
    "sg:province":"TN",
    "sg:tags":[
        "house",
        "nonresidential"
    ],
    "wof:name":"Spires Baker",
    "wof:placetype":"venue"
},
  "geometry": {"coordinates":[-85.330523,34.998832],"type":"Point"}
}