{
  "type": "Feature",
  "properties": {
    "iso:country":"US",
    "sg:address":"1800 N Broadway St",
    "sg:city":"Knoxville",
    "sg:classifiers":[
        {
            "category":"Retail",
            "subcategory":"Auto Repair",
            "type":"Services"
        }
    ],
    "sg:phone":"+1 865 691 4848",
    "sg:postcode":"37917",
    "sg:province":"TN",
    "sg:tags":[
        "transmission"
    ],
    "wof:name":"Action Transmissions",
    "wof:placetype":"venue"
},
  "geometry": {"coordinates":[-83.920047,35.990043],"type":"Point"}
}