{
  "type": "Feature",
  "properties": {
    "iso:country":"US",
    "sg:address":"402 12th Ave S",
    "sg:city":"Nashville",
    "sg:phone":"+1 615 255 3307",
    "sg:postcode":"37203",
    "sg:province":"TN",
    "sg:website":"http://www.stationinn.com",
    "wof:name":"The Station Inn",
    "wof:placetype":"venue"
},
  "geometry": {"coordinates":[-86.78469,36.152301],"type":"Point"}
}