{
  "type": "Feature",
  "properties": {
    "addr:full":"390 Rob Rd Clarksville TN 37040",
    "addr:housenumber":"390",
    "addr:postcode":"37040",
    "addr:street":"Rob Rd",
    "iso:country":"US",
    "sg:address":"390 Rob Rd",
    "sg:city":"Clarksville",
    "sg:classifiers":[
        {
            "category":"Building & Trades",
            "subcategory":"Plumbing",
            "type":"Services"
        }
    ],
    "sg:phone":"+1 931 552 4209",
    "sg:postcode":"37040",
    "sg:province":"TN",
    "sg:tags":[
        "plumbing",
        "contractor"
    ],
    "wof:name":"Reynolds Plumbing",
    "wof:placetype":"venue"
},
  "geometry": {"coordinates":[-87.371578,36.450538],"type":"Point"}
}