{
  "type": "Feature",
  "properties": {
    "addr:full":"942 Battlefield Dr Nashville TN 37204",
    "addr:housenumber":"942",
    "addr:postcode":"37204",
    "addr:street":"Battlefield Dr",
    "iso:country":"US",
    "sg:address":"942 Battlefield Dr",
    "sg:city":"Nashville",
    "sg:classifiers":[
        {
            "category":"Real Estate",
            "subcategory":"Real Estate Agent",
            "type":"Services"
        }
    ],
    "sg:phone":"+1 615 385 7730",
    "sg:postcode":"37204",
    "sg:province":"TN",
    "wof:name":"America's Home Buyers",
    "wof:placetype":"venue"
},
  "geometry": {"coordinates":[-86.786653,36.11472],"type":"Point"}
}