{
  "type": "Feature",
  "properties": {
    "iso:country":"US",
    "sg:address":"802 Old McGinley Dr",
    "sg:city":"Maryville",
    "sg:classifiers":[
        {
            "category":"Shopping",
            "subcategory":"Gifts & Souvenirs",
            "type":"Retail Goods"
        }
    ],
    "sg:phone":"+1 865 681 1303",
    "sg:postcode":"37803",
    "sg:province":"TN",
    "wof:name":"E & R Gifts & Collectables",
    "wof:placetype":"venue"
},
  "geometry": {"coordinates":[-83.911666,35.735172],"type":"Point"}
}