{
  "type": "Feature",
  "properties": {
    "iso:country":"US",
    "sg:address":"2833 Galesburg Dr",
    "sg:city":"Nashville",
    "sg:classifiers":[
        {
            "category":"Building & Trades",
            "subcategory":"Construction",
            "type":"Services"
        }
    ],
    "sg:phone":"+1 615 366 0703",
    "sg:postcode":"37217",
    "sg:province":"TN",
    "sg:tags":[
        "residential"
    ],
    "wof:name":"Francisco Contreras Framing",
    "wof:placetype":"venue"
},
  "geometry": {"coordinates":[-86.626155,36.075406],"type":"Point"}
}