{
  "type": "Feature",
  "properties": {
    "iso:country":"US",
    "sg:address":"3452 Woodwind Dr",
    "sg:city":"Memphis",
    "sg:classifiers":[
        {
            "category":"Professional",
            "subcategory":"Art Services",
            "type":"Services"
        }
    ],
    "sg:phone":"+1 901 372 9339",
    "sg:postcode":"38128",
    "sg:province":"TN",
    "sg:tags":[
        "commercial",
        "design",
        "typesetting"
    ],
    "wof:name":"G F R Composition Service",
    "wof:placetype":"venue"
},
  "geometry": {"coordinates":[-89.934731,35.21809],"type":"Point"}
}