{
  "type": "Feature",
  "properties": {
    "iso:country":"US",
    "sg:address":"3709 Charlotte Ave",
    "sg:city":"Nashville",
    "sg:classifiers":[
        {
            "category":"Shopping",
            "subcategory":"Tobacco",
            "type":"Retail Goods"
        }
    ],
    "sg:phone":"+1 615 279 1999",
    "sg:postcode":"37209",
    "sg:province":"TN",
    "sg:tags":[
        "product"
    ],
    "wof:name":"Major Discount Tobacco",
    "wof:placetype":"venue"
},
  "geometry": {"coordinates":[-86.828189,36.15274],"type":"Point"}
}