{
  "type": "Feature",
  "properties": {
    "iso:country":"US",
    "sg:address":"4064 Nolensville Pike",
    "sg:city":"Nashville",
    "sg:classifiers":[
        {
            "category":"Building & Trades",
            "subcategory":"Landscaping Services",
            "type":"Services"
        }
    ],
    "sg:phone":"+1 615 771 8580",
    "sg:postcode":"37211",
    "sg:province":"TN",
    "sg:tags":[
        "tree"
    ],
    "wof:name":"Tree Doctors",
    "wof:placetype":"venue"
},
  "geometry": {"coordinates":[-86.726884,36.081814],"type":"Point"}
}