{
  "type": "Feature",
  "properties": {
    "iso:country":"US",
    "sg:address":"2427 Old Fort Pkwy",
    "sg:city":"Murfreesboro",
    "sg:classifiers":[
        {
            "category":"Restaurant",
            "type":"Food & Drink"
        }
    ],
    "sg:phone":"+1 615 898 1527",
    "sg:postcode":"37128",
    "sg:province":"TN",
    "sg:tags":[
        "eating"
    ],
    "wof:name":"Waffle House",
    "wof:placetype":"venue"
},
  "geometry": {"coordinates":[-86.447474,35.844946],"type":"Point"}
}