{
  "type": "Feature",
  "properties": {
    "iso:country":"US",
    "sg:address":"950 Robin Hood Dr NW",
    "sg:city":"Cleveland",
    "sg:classifiers":[
        {
            "category":"Building & Trades",
            "subcategory":"Construction",
            "type":"Services"
        }
    ],
    "sg:phone":"+1 423 284 6655",
    "sg:postcode":"37312",
    "sg:province":"TN",
    "sg:tags":[
        "excavating",
        "contractor"
    ],
    "wof:name":"Bauknecht Excavating",
    "wof:placetype":"venue"
},
  "geometry": {"coordinates":[-84.858056,35.213144],"type":"Point"}
}