{
  "type": "Feature",
  "properties": {
    "iso:country":"US",
    "sg:address":"373 W Church St",
    "sg:city":"Lexington",
    "sg:classifiers":[
        {
            "category":"Travel",
            "subcategory":"Travel Agent",
            "type":"Entertainment"
        }
    ],
    "sg:phone":"+1 731 968 0141",
    "sg:postcode":"38351",
    "sg:province":"TN",
    "sg:tags":[
        "agency",
        "bureau"
    ],
    "wof:name":"Traveler",
    "wof:placetype":"venue"
},
  "geometry": {"coordinates":[-88.405308,35.655744],"type":"Point"}
}