{
  "type": "Feature",
  "properties": {
    "addr:full":"5040 Sanderlin Ave Memphis TN 38117",
    "addr:housenumber":"5040",
    "addr:postcode":"38117",
    "addr:street":"Sanderlin Ave",
    "iso:country":"US",
    "sg:address":"5040 Sanderlin Ave",
    "sg:city":"Memphis",
    "sg:classifiers":[
        {
            "category":"Bars & Pubs",
            "type":"Food & Drink"
        }
    ],
    "sg:menulink":"http://www.allmenus.com/tn/memphis/33017-interim-restaurant--bar/menu/",
    "sg:phone":"+1 901 818 0821",
    "sg:postcode":"38117",
    "sg:province":"TN",
    "sg:tags":[
        "american"
    ],
    "wof:name":"Interim Restaurant & Bar",
    "wof:placetype":"venue"
},
  "geometry": {"coordinates":[-89.893128,35.117177],"type":"Point"}
}