{
  "type": "Feature",
  "properties": {
    "iso:country":"US",
    "sg:address":"1414 Border Line Rd",
    "sg:city":"Hazel Green",
    "sg:classifiers":[
        {
            "category":"Shopping",
            "subcategory":"Computers & Home Electronics",
            "type":"Retail Goods"
        }
    ],
    "sg:phone":"+1 256 828 3021",
    "sg:postcode":"35750",
    "sg:province":"TN",
    "wof:name":"Tunstill T V Satellite Sls Svc",
    "wof:placetype":"venue"
},
  "geometry": {"coordinates":[-86.469328,34.990435],"type":"Point"}
}