{
  "type": "Feature",
  "properties": {
    "addr:full":"1005 Columbia Ave Franklin TN 37064",
    "addr:housenumber":"1005",
    "addr:postcode":"37064",
    "addr:street":"Columbia Ave",
    "iso:country":"US",
    "sg:address":"1005 Columbia Ave",
    "sg:city":"Franklin",
    "sg:classifiers":[
        {
            "category":"Retail",
            "subcategory":"Auto Repair",
            "type":"Services"
        }
    ],
    "sg:phone":"+1 615 794 3136",
    "sg:postcode":"37064",
    "sg:province":"TN",
    "sg:tags":[
        "repairing",
        "automobile"
    ],
    "wof:name":"Pewitt Brothers Tune & Tire",
    "wof:placetype":"venue"
},
  "geometry": {"coordinates":[-86.87272,35.918968],"type":"Point"}
}