{
  "type": "Feature",
  "properties": {
    "iso:country":"US",
    "sg:address":"4532 Getwell Rd",
    "sg:city":"Memphis",
    "sg:classifiers":[
        {
            "category":"Organizations",
            "subcategory":"Labor Organization",
            "type":"Services"
        }
    ],
    "sg:phone":"+1 901 794 3001",
    "sg:postcode":"38118",
    "sg:province":"TN",
    "wof:name":"Unite'",
    "wof:placetype":"venue"
},
  "geometry": {"coordinates":[-89.936875,35.025494],"type":"Point"}
}