{
  "type": "Feature",
  "properties": {
    "iso:country":"US",
    "sg:address":"3060 Eastend Dr",
    "sg:city":"Humboldt",
    "sg:classifiers":[
        {
            "category":"Wholesale",
            "subcategory":"Auto Parts",
            "type":"Manufacturing & Wholesale Goods"
        }
    ],
    "sg:phone":"+1 731 784 3419",
    "sg:postcode":"38343",
    "sg:province":"TN",
    "sg:tags":[
        "body",
        "shop",
        "glass",
        "automotive",
        "supply",
        "paint"
    ],
    "wof:name":"Body Shop Paint & Supply",
    "wof:placetype":"venue"
},
  "geometry": {"coordinates":[-88.889899,35.839299],"type":"Point"}
}