{
  "type": "Feature",
  "properties": {
    "addr:full":"203 Bonnavue Dr Hermitage TN 37076",
    "addr:housenumber":"203",
    "addr:postcode":"37076",
    "addr:street":"Bonnavue Dr",
    "iso:country":"US",
    "sg:address":"203 Bonnavue Dr",
    "sg:city":"Hermitage",
    "sg:classifiers":[
        {
            "category":"Building & Trades",
            "subcategory":"Cleaning & Sanitation",
            "type":"Services"
        }
    ],
    "sg:phone":"+1 615 882 0135",
    "sg:postcode":"37076",
    "sg:province":"TN",
    "sg:tags":[
        "janitor"
    ],
    "wof:name":"Marchena Commercial Clean Svc",
    "wof:placetype":"venue"
},
  "geometry": {"coordinates":[-86.627883,36.204432],"type":"Point"}
}