{
  "type": "Feature",
  "properties": {
    "addr:full":"4227 Harry Smith Rd Kenton TN 38233",
    "addr:housenumber":"4227",
    "addr:postcode":"38233",
    "addr:street":"Harry Smith Rd",
    "iso:country":"US",
    "sg:address":"4227 Harry Smith Rd",
    "sg:city":"Kenton",
    "sg:classifiers":[
        {
            "category":"Real Estate",
            "subcategory":"Real Estate Operator",
            "type":"Services"
        }
    ],
    "sg:phone":"+1 731 749 5564",
    "sg:postcode":"38233",
    "sg:province":"TN",
    "sg:tags":[
        "property",
        "lessor"
    ],
    "wof:name":"Yates BT",
    "wof:placetype":"venue"
},
  "geometry": {"coordinates":[-89.044062,36.224475],"type":"Point"}
}