{
  "type": "Feature",
  "properties": {
    "addr:full":"2801 Kirby Rd Memphis TN 38119",
    "addr:housenumber":"2801",
    "addr:postcode":"38119",
    "addr:street":"Kirby Rd",
    "iso:country":"US",
    "sg:address":"2801 Kirby Rd",
    "sg:city":"Memphis",
    "sg:classifiers":[
        {
            "category":"Retail",
            "subcategory":"Laundry & Dry Cleaning",
            "type":"Services"
        }
    ],
    "sg:phone":"+1 901 752 6637",
    "sg:postcode":"38119",
    "sg:province":"TN",
    "sg:tags":[
        "cleaners"
    ],
    "wof:name":"Dryve Cleaners",
    "wof:placetype":"venue"
},
  "geometry": {"coordinates":[-89.84250900000001,35.073012],"type":"Point"}
}