{
  "type": "Feature",
  "properties": {
    "iso:country":"US",
    "sg:address":"19 Co Rd 324",
    "sg:city":"Corinth",
    "sg:classifiers":[
        {
            "category":"Retail",
            "subcategory":"Auto Repair",
            "type":"Services"
        }
    ],
    "sg:phone":"+1 662 286 6158",
    "sg:postcode":"38834",
    "sg:province":"TN",
    "sg:tags":[
        "body",
        "automobile",
        "painting"
    ],
    "wof:name":"Counce Auto Body",
    "wof:placetype":"venue"
},
  "geometry": {"coordinates":[-88.479928,34.868646],"type":"Point"}
}