{
  "type": "Feature",
  "properties": {
    "iso:country":"US",
    "sg:address":"165 Stones River Rd",
    "sg:city":"La Vergne",
    "sg:classifiers":[
        {
            "category":"Shopping",
            "subcategory":"Discount & Variety Stores",
            "type":"Retail Goods"
        }
    ],
    "sg:phone":"+1 615 793 3055",
    "sg:postcode":"37086",
    "sg:province":"TN",
    "sg:tags":[
        "merchandise",
        "general"
    ],
    "wof:name":"Merchandise Liquidators Furn",
    "wof:placetype":"venue"
},
  "geometry": {"coordinates":[-86.57302900000001,36.018815],"type":"Point"}
}