{
  "type": "Feature",
  "properties": {
    "iso:country":"US",
    "sg:address":"4646 Poplar Ave",
    "sg:city":"Memphis",
    "sg:classifiers":[
        {
            "category":"Restaurant",
            "type":"Food & Drink"
        }
    ],
    "sg:phone":"+1 901 682 7735",
    "sg:postcode":"38117",
    "sg:province":"TN",
    "sg:tags":[
        "delicatessen"
    ],
    "wof:name":"LA Jewell's Deli",
    "wof:placetype":"venue"
},
  "geometry": {"coordinates":[-89.90776099999999,35.116714],"type":"Point"}
}