{
  "type": "Feature",
  "properties": {
    "iso:country":"US",
    "sg:address":"5304 McGavock Rd",
    "sg:city":"Brentwood",
    "sg:classifiers":[
        {
            "category":"Wholesale",
            "subcategory":"Non-durable Goods",
            "type":"Manufacturing & Wholesale Goods"
        }
    ],
    "sg:phone":"+1 615 373 1045",
    "sg:postcode":"37027",
    "sg:province":"TN",
    "wof:name":"Salamon & Assoc",
    "wof:placetype":"venue"
},
  "geometry": {"coordinates":[-86.81315499999999,36.020717],"type":"Point"}
}