{
  "type": "Feature",
  "properties": {
    "iso:country":"US",
    "sg:address":"6710 Albunda Dr NW",
    "sg:city":"Knoxville",
    "sg:classifiers":[
        {
            "category":"Health Services",
            "subcategory":"Medical Lab",
            "type":"Services"
        }
    ],
    "sg:phone":"+1 865 584 8003",
    "sg:postcode":"37919",
    "sg:province":"TN",
    "sg:tags":[
        "laboratory",
        "dental"
    ],
    "wof:name":"Dental Workshop",
    "wof:placetype":"venue"
},
  "geometry": {"coordinates":[-84.014838,35.930434],"type":"Point"}
}