{
  "type": "Feature",
  "properties": {
    "iso:country":"US",
    "sg:address":"1301 Murfreesboro Pike",
    "sg:city":"Nashville",
    "sg:classifiers":[
        {
            "category":"Autos & Motor Vehicles",
            "subcategory":"Auto Supplies",
            "type":"Retail Goods"
        }
    ],
    "sg:phone":"+1 615 361 4197",
    "sg:postcode":"37217",
    "sg:province":"TN",
    "sg:tags":[
        "tire"
    ],
    "wof:name":"Tires Plus",
    "wof:placetype":"venue"
},
  "geometry": {"coordinates":[-86.69922099999999,36.117433],"type":"Point"}
}