{
  "type": "Feature",
  "properties": {
    "iso:country":"US",
    "sg:address":"725 Pickwick St S",
    "sg:city":"Savannah",
    "sg:classifiers":[
        {
            "category":"Manufacturing",
            "subcategory":"Tools & Machinery",
            "type":"Manufacturing & Wholesale Goods"
        }
    ],
    "sg:phone":"+1 731 925 7993",
    "sg:postcode":"38372",
    "sg:province":"TN",
    "sg:tags":[
        "battery"
    ],
    "wof:name":"Savannah Discount Battery",
    "wof:placetype":"venue"
},
  "geometry": {"coordinates":[-88.24481900000001,35.21313],"type":"Point"}
}