{
  "type": "Feature",
  "properties": {
    "iso:country":"US",
    "sg:address":"617 Asheville Hwy",
    "sg:city":"Greeneville",
    "sg:classifiers":[
        {
            "category":"Health Services",
            "subcategory":"Chiropractor",
            "type":"Services"
        }
    ],
    "sg:phone":"+1 423 798 1925",
    "sg:postcode":"37743",
    "sg:province":"TN",
    "wof:name":"Greeneville Community Chiro",
    "wof:placetype":"venue"
},
  "geometry": {"coordinates":[-82.84774899999999,36.145372],"type":"Point"}
}