{
  "type": "Feature",
  "properties": {
    "addr:full":"9398 Reco Dr Soddy Daisy TN 37379",
    "addr:housenumber":"9398",
    "addr:postcode":"37379",
    "addr:street":"Reco Dr",
    "iso:country":"US",
    "sg:address":"9398 Reco Dr",
    "sg:city":"Soddy Daisy",
    "sg:classifiers":[
        {
            "category":"Restaurant",
            "type":"Food & Drink"
        }
    ],
    "sg:menulink":"http://www.allmenus.com/tn/soddy-daisy/155004-hardees/menu/",
    "sg:phone":"+1 423 332 4494",
    "sg:postcode":"37379",
    "sg:province":"TN",
    "sg:tags":[
        "burger",
        "american"
    ],
    "wof:name":"Hardee's",
    "wof:placetype":"venue"
},
  "geometry": {"coordinates":[-85.197413,35.236487],"type":"Point"}
}