{
  "type": "Feature",
  "properties": {
    "iso:country":"US",
    "sg:address":"2549 Murfreesboro Pike",
    "sg:city":"Nashville",
    "sg:classifiers":[
        {
            "category":"Personal",
            "subcategory":"Beauty Salon",
            "type":"Services"
        }
    ],
    "sg:phone":"+1 615 399 2229",
    "sg:postcode":"37217",
    "sg:province":"TN",
    "sg:tags":[
        "shop",
        "manicuring"
    ],
    "wof:name":"Sation Nail Salon",
    "wof:placetype":"venue"
},
  "geometry": {"coordinates":[-86.64242400000001,36.077767],"type":"Point"}
}