{
  "type": "Feature",
  "properties": {
    "addr:full":"280 White Bridge Pike Nashville TN 37209",
    "addr:housenumber":"280",
    "addr:postcode":"37209",
    "addr:street":"White Bridge Pike",
    "iso:country":"US",
    "sg:address":"280 White Bridge Pike",
    "sg:city":"Nashville",
    "sg:classifiers":[
        {
            "category":"Health Services",
            "subcategory":"Doctor",
            "type":"Services"
        }
    ],
    "sg:phone":"+1 615 356 1795",
    "sg:postcode":"37209",
    "sg:province":"TN",
    "sg:tags":[
        "medical"
    ],
    "wof:name":"Medicine At Work",
    "wof:placetype":"venue"
},
  "geometry": {"coordinates":[-86.857901,36.144501],"type":"Point"}
}