{
  "type": "Feature",
  "properties": {
    "addr:full":"5400 Park Ave Memphis TN 38119",
    "addr:housenumber":"5400",
    "addr:postcode":"38119",
    "addr:street":"Park Ave",
    "iso:country":"US",
    "sg:address":"5400 Park Ave",
    "sg:city":"Memphis",
    "sg:classifiers":[
        {
            "category":"Real Estate",
            "subcategory":"Real Estate Agent",
            "type":"Services"
        }
    ],
    "sg:phone":"+1 901 683 5013",
    "sg:postcode":"38119",
    "sg:province":"TN",
    "wof:name":"Hobson Co Realtors",
    "wof:placetype":"venue"
},
  "geometry": {"coordinates":[-89.88064199999999,35.102488],"type":"Point"}
}