{
  "type": "Feature",
  "properties": {
    "iso:country":"US",
    "sg:address":"8269 Kimbrough Woods Cove",
    "sg:city":"Germantown",
    "sg:classifiers":[
        {
            "category":"Wholesale",
            "subcategory":"Durable Goods & Equipment",
            "type":"Manufacturing & Wholesale Goods"
        },
        {
            "category":"Shopping",
            "subcategory":"Computers & Home Electronics",
            "type":"Retail Goods"
        }
    ],
    "sg:phone":"+1 901 751 6711",
    "sg:postcode":"38139",
    "sg:province":"TN",
    "sg:tags":[
        "communications",
        "telephone",
        "software"
    ],
    "wof:name":"Supplier Info Inc",
    "wof:placetype":"venue"
},
  "geometry": {"coordinates":[-89.787254,35.085361],"type":"Point"}
}