{
  "type": "Feature",
  "properties": {
    "addr:full":"3355 Elvis Presley Blvd Memphis TN 38116",
    "addr:postcode":"3355;38116",
    "addr:street":"Elvis Presley Blvd",
    "iso:country":"US",
    "sg:address":"3355 Elvis Presley Blvd",
    "sg:city":"Memphis",
    "sg:classifiers":[
        {
            "category":"Autos & Motor Vehicles",
            "subcategory":"Automobile Sales",
            "type":"Retail Goods"
        }
    ],
    "sg:phone":"+1 901 346 7040",
    "sg:postcode":"38116",
    "sg:province":"TN",
    "wof:name":"E P Motors",
    "wof:placetype":"venue"
},
  "geometry": {"coordinates":[-90.024624,35.057589],"type":"Point"}
}