{
  "type": "Feature",
  "properties": {
    "iso:country":"US",
    "sg:address":"3554 Park Ave",
    "sg:city":"Memphis",
    "sg:classifiers":[
        {
            "category":"Home & Garden",
            "subcategory":"Carpets & Floor Coverings",
            "type":"Retail Goods"
        }
    ],
    "sg:phone":"+1 901 327 5033",
    "sg:postcode":"38111",
    "sg:province":"TN",
    "sg:tags":[
        "rug"
    ],
    "sg:website":"http://www.taghavirugs.com",
    "wof:name":"Ali A Taghavi Master Weaver",
    "wof:placetype":"venue"
},
  "geometry": {"coordinates":[-89.944101,35.107845],"type":"Point"}
}