{
  "type": "Feature",
  "properties": {
    "iso:country":"US",
    "sg:address":"6415 Hixson Pike",
    "sg:city":"Hixson",
    "sg:classifiers":[
        {
            "category":"Building & Trades",
            "subcategory":"Construction",
            "type":"Services"
        }
    ],
    "sg:phone":"+1 423 843 0033",
    "sg:postcode":"37343",
    "sg:province":"TN",
    "sg:tags":[
        "contractor"
    ],
    "wof:name":"Signature Land Co",
    "wof:placetype":"venue"
},
  "geometry": {"coordinates":[-85.196482,35.157031],"type":"Point"}
}