{
  "type": "Feature",
  "properties": {
    "addr:full":"1110 Stonewall Dr Nashville TN 37220",
    "addr:housenumber":"1110",
    "addr:postcode":"37220",
    "addr:street":"Stonewall Dr",
    "iso:country":"US",
    "sg:address":"1110 Stonewall Dr",
    "sg:city":"Nashville",
    "sg:classifiers":[
        {
            "category":"Home & Garden",
            "subcategory":"Building Materials",
            "type":"Retail Goods"
        }
    ],
    "sg:phone":"+1 615 373 2374",
    "sg:postcode":"37220",
    "sg:province":"TN",
    "sg:tags":[
        "door"
    ],
    "wof:name":"Dr Dave's Doors",
    "wof:placetype":"venue"
},
  "geometry": {"coordinates":[-86.798934,36.085986],"type":"Point"}
}