{
  "type": "Feature",
  "properties": {
    "addr:full":"3483 Vista Cir Cookeville TN 38506",
    "addr:housenumber":"3483",
    "addr:postcode":"38506",
    "addr:street":"Vista Cir",
    "iso:country":"US",
    "sg:address":"3483 Vista Cir",
    "sg:city":"Cookeville",
    "sg:classifiers":[
        {
            "category":"Building & Trades",
            "subcategory":"Pest Control",
            "type":"Services"
        }
    ],
    "sg:phone":"+1 931 526 2033",
    "sg:postcode":"38506",
    "sg:province":"TN",
    "wof:name":"Central Tennessee Termite",
    "wof:placetype":"venue"
},
  "geometry": {"coordinates":[-85.43850500000001,36.170469],"type":"Point"}
}