{
  "type": "Feature",
  "properties": {
    "iso:country":"US",
    "sg:address":"501 Maryville Hwy",
    "sg:city":"Seymour",
    "sg:classifiers":[
        {
            "category":"Home & Garden",
            "subcategory":"Building Materials",
            "type":"Retail Goods"
        }
    ],
    "sg:phone":"+1 865 573 4191",
    "sg:postcode":"37865",
    "sg:province":"TN",
    "wof:name":"Vinyl Corners Inc",
    "wof:placetype":"venue"
},
  "geometry": {"coordinates":[-83.769701,35.862511],"type":"Point"}
}