{
  "type": "Feature",
  "properties": {
    "iso:country":"US",
    "sg:address":"208 Leake Ave",
    "sg:city":"Nashville",
    "sg:classifiers":[
        {
            "category":"Organizations",
            "subcategory":"Religious Organization",
            "type":"Services"
        }
    ],
    "sg:phone":"+1 615 356 4454",
    "sg:postcode":"37205",
    "sg:province":"TN",
    "wof:name":"Parish Twining Program",
    "wof:placetype":"venue"
},
  "geometry": {"coordinates":[-86.86157900000001,36.103092],"type":"Point"}
}