{
  "type": "Feature",
  "properties": {
    "iso:country":"US",
    "sg:address":"3 Busby Rd",
    "sg:city":"Loretto",
    "sg:classifiers":[
        {
            "category":"Shopping",
            "subcategory":"Clothing, Apparel, & Fashions",
            "type":"Retail Goods"
        }
    ],
    "sg:phone":"+1 931 853 7233",
    "sg:postcode":"38469",
    "sg:province":"TN",
    "sg:tags":[
        "sportswear"
    ],
    "wof:name":"Perry Enterprises Plant",
    "wof:placetype":"venue"
},
  "geometry": {"coordinates":[-87.41052500000001,35.106839],"type":"Point"}
}