{
  "type": "Feature",
  "properties": {
    "iso:country":"US",
    "sg:address":"200 N Mahr Ave",
    "sg:city":"Lawrenceburg",
    "sg:classifiers":[
        {
            "category":"Professional",
            "subcategory":"Lawyer & Legal Services",
            "type":"Services"
        }
    ],
    "sg:phone":"+1 931 762 4641",
    "sg:postcode":"38464",
    "sg:province":"TN",
    "sg:tags":[
        "attorney"
    ],
    "wof:name":"Wayne F Hairrell",
    "wof:placetype":"venue"
},
  "geometry": {"coordinates":[-87.33502799999999,35.243857],"type":"Point"}
}