{
  "type": "Feature",
  "properties": {
    "iso:country":"US",
    "sg:address":"3316 Trevor St",
    "sg:city":"Nashville",
    "sg:classifiers":[
        {
            "category":"Shopping",
            "subcategory":"Gifts & Souvenirs",
            "type":"Retail Goods"
        }
    ],
    "sg:phone":"+1 615 320 1912",
    "sg:postcode":"37209",
    "sg:province":"TN",
    "sg:tags":[
        "basket"
    ],
    "wof:name":"Sweet Blessings",
    "wof:placetype":"venue"
},
  "geometry": {"coordinates":[-86.824195,36.154259],"type":"Point"}
}