{
  "type": "Feature",
  "properties": {
    "iso:country":"US",
    "sg:address":"121 N Russell St",
    "sg:city":"Portland",
    "sg:classifiers":[
        {
            "category":"Manufacturing",
            "subcategory":"Paper Products",
            "type":"Manufacturing & Wholesale Goods"
        }
    ],
    "sg:phone":"+1 615 325 5578",
    "sg:postcode":"37148",
    "sg:province":"TN",
    "sg:tags":[
        "packaging",
        "material"
    ],
    "sg:website":"www.flexpac.com",
    "wof:name":"Flexpac Inc",
    "wof:placetype":"venue"
},
  "geometry": {"coordinates":[-86.51533000000001,36.582549],"type":"Point"}
}