{
  "type": "Feature",
  "properties": {
    "addr:full":"210 Tune Airport Dr Nashville TN 37209",
    "addr:housenumber":"210",
    "addr:postcode":"37209",
    "addr:street":"Tune Airport Dr",
    "iso:country":"US",
    "sg:address":"210 Tune Airport Dr",
    "sg:city":"Nashville",
    "sg:classifiers":[
        {
            "category":"Retail",
            "subcategory":"Repair Shop",
            "type":"Services"
        }
    ],
    "sg:phone":"+1 615 350 5015",
    "sg:postcode":"37209",
    "sg:province":"TN",
    "sg:tags":[
        "nonscheduled",
        "transportation",
        "airport",
        "air"
    ],
    "sg:website":"www.helicorp.org",
    "wof:name":"Helicorp",
    "wof:placetype":"venue"
},
  "geometry": {"coordinates":[-86.880438,36.184414],"type":"Point"}
}