{
  "type": "Feature",
  "properties": {
    "iso:country":"US",
    "sg:address":"617 S Main St",
    "sg:city":"Sweetwater",
    "sg:classifiers":[
        {
            "category":"Organizations",
            "subcategory":"Religious Organization",
            "type":"Services"
        }
    ],
    "sg:phone":"+1 423 351 7486",
    "sg:postcode":"37874",
    "sg:province":"TN",
    "sg:tags":[
        "church"
    ],
    "wof:name":"Valley Park Community Ctr",
    "wof:placetype":"venue"
},
  "geometry": {"coordinates":[-84.468643,35.591828],"type":"Point"}
}