{
  "type": "Feature",
  "properties": {
    "iso:country":"US",
    "sg:address":"3305 S 3rd St",
    "sg:city":"Memphis",
    "sg:classifiers":[
        {
            "category":"Food & Beverages",
            "subcategory":"Liquor & Beverages",
            "type":"Retail Goods"
        }
    ],
    "sg:phone":"+1 901 398 2214",
    "sg:postcode":"38109",
    "sg:province":"TN",
    "sg:tags":[
        "alcoholic"
    ],
    "wof:name":"Three Star Liquor Store",
    "wof:placetype":"venue"
},
  "geometry": {"coordinates":[-90.059742,35.058319],"type":"Point"}
}