{
  "type": "Feature",
  "properties": {
    "addr:full":"5100 Poplar Ave Memphis TN 38117",
    "addr:housenumber":"5100",
    "addr:postcode":"38117",
    "addr:street":"Poplar Ave",
    "iso:country":"US",
    "sg:address":"5100 Poplar Ave",
    "sg:city":"Memphis",
    "sg:classifiers":[
        {
            "category":"Shopping",
            "type":"Retail Goods"
        }
    ],
    "sg:phone":"+1 901 682 9660",
    "sg:postcode":"38117",
    "sg:province":"TN",
    "sg:tags":[
        "sundries",
        "store"
    ],
    "wof:name":"Clark Tower Sundry",
    "wof:placetype":"venue"
},
  "geometry": {"coordinates":[-89.892369,35.111334],"type":"Point"}
}