{
  "type": "Feature",
  "properties": {
    "addr:full":"2504 Dickerson Pike Nashville TN 37207",
    "addr:housenumber":"2504",
    "addr:postcode":"37207",
    "addr:street":"Dickerson Pike",
    "iso:country":"US",
    "sg:address":"2504 Dickerson Pike",
    "sg:city":"Nashville",
    "sg:classifiers":[
        {
            "category":"Bars & Pubs",
            "type":"Food & Drink"
        }
    ],
    "sg:phone":"+1 615 228 0902",
    "sg:postcode":"37207",
    "sg:province":"TN",
    "sg:tags":[
        "club",
        "night"
    ],
    "wof:name":"Crash Site",
    "wof:placetype":"venue"
},
  "geometry": {"coordinates":[-86.765529,36.210911],"type":"Point"}
}