{
  "type": "Feature",
  "properties": {
    "iso:country":"US",
    "sg:address":"2996 N Mount Juliet Rd",
    "sg:city":"Mt Juliet",
    "sg:classifiers":[
        {
            "category":"Building & Trades",
            "subcategory":"Construction",
            "type":"Services"
        }
    ],
    "sg:phone":"+1 615 754 8474",
    "sg:postcode":"37122",
    "sg:province":"TN",
    "sg:tags":[
        "home",
        "builder"
    ],
    "wof:name":"Beazer Homes",
    "wof:placetype":"venue"
},
  "geometry": {"coordinates":[-86.51636999999999,36.2118],"type":"Point"}
}