{
  "type": "Feature",
  "properties": {
    "iso:country":"US",
    "sg:address":"8923 Linksvue Dr",
    "sg:city":"Knoxville",
    "sg:classifiers":[
        {
            "category":"Shopping",
            "subcategory":"Gifts & Souvenirs",
            "type":"Retail Goods"
        }
    ],
    "sg:phone":"+1 865 531 7789",
    "sg:postcode":"37922",
    "sg:province":"TN",
    "wof:name":"Village Party Land",
    "wof:placetype":"venue"
},
  "geometry": {"coordinates":[-84.072243,35.89415],"type":"Point"}
}