{
  "type": "Feature",
  "properties": {
    "iso:country":"US",
    "sg:address":"701 N State of Franklin Rd",
    "sg:city":"Johnson City",
    "sg:classifiers":[
        {
            "category":"Shopping",
            "subcategory":"Computers & Home Electronics",
            "type":"Retail Goods"
        }
    ],
    "sg:phone":"+1 423 928 4081",
    "sg:postcode":"37604",
    "sg:province":"TN",
    "sg:tags":[
        "software"
    ],
    "sg:website":"www.osisoft.com",
    "wof:name":"OSI Soft",
    "wof:placetype":"venue"
},
  "geometry": {"coordinates":[-82.39057099999999,36.316691],"type":"Point"}
}