{
  "type": "Feature",
  "properties": {
    "iso:country":"US",
    "sg:address":"227 Mountain St",
    "sg:city":"Mc Minnville",
    "sg:classifiers":[
        {
            "category":"Manufacturing",
            "subcategory":"Food",
            "type":"Manufacturing & Wholesale Goods"
        }
    ],
    "sg:phone":"+1 931 473 2108",
    "sg:postcode":"37110",
    "sg:province":"TN",
    "sg:tags":[
        "bottler"
    ],
    "wof:name":"Dr Pepper Bottling Co",
    "wof:placetype":"venue"
},
  "geometry": {"coordinates":[-85.76419799999999,35.695048],"type":"Point"}
}