{
  "type": "Feature",
  "properties": {
    "addr:full":"2903 Vinemont Dr Murfreesboro TN 37130",
    "addr:housenumber":"2903",
    "addr:postcode":"37130",
    "addr:street":"Vinemont Dr",
    "iso:country":"US",
    "sg:address":"2903 Vinemont Dr",
    "sg:city":"Murfreesboro",
    "sg:classifiers":[
        {
            "category":"Social Services",
            "subcategory":"Child Care",
            "type":"Services"
        }
    ],
    "sg:phone":"+1 615 867 1375",
    "sg:postcode":"37130",
    "sg:province":"TN",
    "sg:tags":[
        "day"
    ],
    "wof:name":"Totslanding Learning Centers",
    "wof:placetype":"venue"
},
  "geometry": {"coordinates":[-86.37751799999999,35.901611],"type":"Point"}
}