{
  "type": "Feature",
  "properties": {
    "iso:country":"US",
    "sg:address":"278 Florence Ave",
    "sg:city":"Selmer",
    "sg:classifiers":[
        {
            "category":"Real Estate",
            "subcategory":"Real Estate Agent",
            "type":"Services"
        }
    ],
    "sg:phone":"+1 731 645 6595",
    "sg:postcode":"38375",
    "sg:province":"TN",
    "sg:tags":[
        "appraiser"
    ],
    "wof:name":"TP Research",
    "wof:placetype":"venue"
},
  "geometry": {"coordinates":[-88.593139,35.174412],"type":"Point"}
}