{
  "type": "Feature",
  "properties": {
    "iso:country":"US",
    "sg:address":"12 Van Hicks Rd",
    "sg:city":"Oak Ridge",
    "sg:classifiers":[
        {
            "category":"Health Services",
            "subcategory":"Clinic",
            "type":"Services"
        }
    ],
    "sg:phone":"+1 865 482 4041",
    "sg:postcode":"37830",
    "sg:province":"TN",
    "wof:name":"Anderson County Health Council",
    "wof:placetype":"venue"
},
  "geometry": {"coordinates":[-84.275068,36.008437],"type":"Point"}
}