{
  "type": "Feature",
  "properties": {
    "iso:country":"US",
    "sg:address":"7010 Nature Trails Blvd",
    "sg:city":"Knoxville",
    "sg:classifiers":[
        {
            "category":"Professional",
            "subcategory":"Business Services",
            "type":"Services"
        }
    ],
    "sg:phone":"+1 865 670 9604",
    "sg:postcode":"37931",
    "sg:province":"TN",
    "wof:name":"Ellingson Enterprises",
    "wof:placetype":"venue"
},
  "geometry": {"coordinates":[-84.065119,35.957862],"type":"Point"}
}