{
  "type": "Feature",
  "properties": {
    "addr:full":"7088 Martin Creek Rd Bloomington Spgs TN 38545",
    "addr:housenumber":"7088",
    "addr:postcode":"38545",
    "addr:street":"Martin Creek Rd",
    "iso:country":"US",
    "sg:address":"7088 Martin Creek Rd",
    "sg:city":"Bloomington Spgs",
    "sg:classifiers":[
        {
            "category":"Retail",
            "subcategory":"Auto Repair",
            "type":"Services"
        }
    ],
    "sg:phone":"+1 931 858 5919",
    "sg:postcode":"38545",
    "sg:province":"TN",
    "sg:tags":[
        "wrecker"
    ],
    "wof:name":"Johns Garage & Wrecker Svc",
    "wof:placetype":"venue"
},
  "geometry": {"coordinates":[-85.635273,36.206033],"type":"Point"}
}