{
  "type": "Feature",
  "properties": {
    "iso:country":"US",
    "sg:address":"6821 Summer Ave",
    "sg:city":"Memphis",
    "sg:classifiers":[
        {
            "category":"Home & Garden",
            "subcategory":"Furniture",
            "type":"Retail Goods"
        }
    ],
    "sg:phone":"+1 901 386 4551",
    "sg:postcode":"38134",
    "sg:province":"TN",
    "wof:name":"Big River Distributors",
    "wof:placetype":"venue"
},
  "geometry": {"coordinates":[-89.835351,35.204337],"type":"Point"}
}