{
  "type": "Feature",
  "properties": {
    "iso:country":"US",
    "sg:address":"802 Rozelle St",
    "sg:city":"Memphis",
    "sg:classifiers":[
        {
            "category":"Wholesale",
            "subcategory":"Hardware",
            "type":"Manufacturing & Wholesale Goods"
        }
    ],
    "sg:phone":"+1 901 272 0276",
    "sg:postcode":"38104",
    "sg:province":"TN",
    "sg:tags":[
        "hardware-wholesale",
        "manufacturer"
    ],
    "wof:name":"Delta Wholesale",
    "wof:placetype":"venue"
},
  "geometry": {"coordinates":[-90.006355,35.124231],"type":"Point"}
}