{
  "type": "Feature",
  "properties": {
    "iso:country":"US",
    "sg:address":"2535 E Wood St",
    "sg:city":"Paris",
    "sg:classifiers":[
        {
            "category":"Education",
            "subcategory":"School",
            "type":"Public Place"
        }
    ],
    "sg:phone":"+1 731 644 0011",
    "sg:postcode":"38242",
    "sg:province":"TN",
    "wof:name":"Gateway Extention Program",
    "wof:placetype":"venue"
},
  "geometry": {"coordinates":[-88.278517,36.319728],"type":"Point"}
}