{
  "type": "Feature",
  "properties": {
    "addr:full":"298 Decatur St Memphis TN 38105",
    "addr:housenumber":"298",
    "addr:postcode":"38105",
    "addr:street":"Decatur St",
    "iso:country":"US",
    "sg:address":"298 Decatur St",
    "sg:city":"Memphis",
    "sg:classifiers":[
        {
            "category":"Food & Beverages",
            "subcategory":"Groceries & Convenience Stores",
            "type":"Retail Goods"
        }
    ],
    "sg:phone":"+1 901 523 1383",
    "sg:postcode":"38105",
    "sg:province":"TN",
    "wof:name":"L & L Supermarket",
    "wof:placetype":"venue"
},
  "geometry": {"coordinates":[-90.02590499999999,35.148474],"type":"Point"}
}