{
  "type": "Feature",
  "properties": {
    "addr:full":"117 Flint Rd Oak Ridge TN 37830",
    "addr:housenumber":"117",
    "addr:postcode":"37830",
    "addr:street":"Flint Rd",
    "iso:country":"US",
    "sg:address":"117 Flint Rd",
    "sg:city":"Oak Ridge",
    "sg:classifiers":[
        {
            "category":"Social Services",
            "subcategory":"Child Care",
            "type":"Services"
        }
    ],
    "sg:phone":"+1 865 482 1239",
    "sg:postcode":"37830",
    "sg:province":"TN",
    "sg:tags":[
        "day"
    ],
    "wof:name":"Stepping Stone Ridgeview",
    "wof:placetype":"venue"
},
  "geometry": {"coordinates":[-84.239694,36.014412],"type":"Point"}
}