{
  "type": "Feature",
  "properties": {
    "iso:country":"US",
    "sg:address":"3092 E Raines Rd",
    "sg:city":"Memphis",
    "sg:classifiers":[
        {
            "category":"Utilities",
            "subcategory":"Refuse",
            "type":"Services"
        }
    ],
    "sg:phone":"+1 901 794 2227",
    "sg:postcode":"38118",
    "sg:province":"TN",
    "sg:tags":[
        "garbage",
        "collection"
    ],
    "wof:name":"J & J Waste",
    "wof:placetype":"venue"
},
  "geometry": {"coordinates":[-89.962028,35.036082],"type":"Point"}
}