{
  "type": "Feature",
  "properties": {
    "addr:full":"6066 Shallowford Rd Chattanooga TN 37421",
    "addr:housenumber":"6066",
    "addr:postcode":"37421",
    "addr:street":"Shallowford Rd",
    "iso:country":"US",
    "sg:address":"6066 Shallowford Rd",
    "sg:city":"Chattanooga",
    "sg:classifiers":[
        {
            "category":"Real Estate",
            "subcategory":"Real Estate Agent",
            "type":"Services"
        }
    ],
    "sg:phone":"+1 423 756 3500",
    "sg:postcode":"37421",
    "sg:province":"TN",
    "wof:name":"Realty Center GMAC",
    "wof:placetype":"venue"
},
  "geometry": {"coordinates":[-85.186286,35.053636],"type":"Point"}
}