{
  "type": "Feature",
  "properties": {
    "iso:country":"US",
    "sg:address":"2957 N John B Dennis Hwy",
    "sg:city":"Kingsport",
    "sg:classifiers":[
        {
            "category":"Autos & Motor Vehicles",
            "subcategory":"Auto Supplies",
            "type":"Retail Goods"
        }
    ],
    "sg:phone":"+1 423 288 7926",
    "sg:postcode":"37660",
    "sg:province":"TN",
    "sg:tags":[
        "car",
        "used",
        "parts"
    ],
    "wof:name":"Hilltop Auto Parts & Repair",
    "wof:placetype":"venue"
},
  "geometry": {"coordinates":[-82.50649199999999,36.571697],"type":"Point"}
}