{
  "type": "Feature",
  "properties": {
    "addr:full":"235 Dixon Springs Hwy Carthage TN 37030",
    "addr:housenumber":"235",
    "addr:postcode":"37030",
    "addr:street":"Dixon Springs Hwy",
    "iso:country":"US",
    "sg:address":"235 Dixon Springs Hwy",
    "sg:city":"Carthage",
    "sg:classifiers":[
        {
            "category":"Autos & Motor Vehicles",
            "subcategory":"Fuel & Gas Station",
            "type":"Retail Goods"
        }
    ],
    "sg:phone":"+1 615 735 0684",
    "sg:postcode":"37030",
    "sg:province":"TN",
    "sg:tags":[
        "station",
        "gasoline",
        "oil"
    ],
    "wof:name":"Bob Wilmores Tanglewood Market",
    "wof:placetype":"venue"
},
  "geometry": {"coordinates":[-85.96579800000001,36.268513],"type":"Point"}
}