{
  "type": "Feature",
  "properties": {
    "iso:country":"US",
    "sg:address":"149 Wexler St",
    "sg:city":"Kingsport",
    "sg:classifiers":[
        {
            "category":"Real Estate",
            "subcategory":"Real Estate Agent",
            "type":"Services"
        }
    ],
    "sg:phone":"+1 423 246 3400",
    "sg:postcode":"37660",
    "sg:province":"TN",
    "sg:tags":[
        "appraiser"
    ],
    "wof:name":"Real-Val",
    "wof:placetype":"venue"
},
  "geometry": {"coordinates":[-82.556229,36.542801],"type":"Point"}
}