{
  "type": "Feature",
  "properties": {
    "iso:country":"US",
    "sg:address":"430 E Emory Rd",
    "sg:city":"Powell",
    "sg:classifiers":[
        {
            "category":"Banks & Credit Unions",
            "subcategory":"Bank",
            "type":"Services"
        }
    ],
    "sg:phone":"+1 865 947 3443",
    "sg:postcode":"37849",
    "sg:province":"TN",
    "sg:tags":[
        "commercial"
    ],
    "wof:name":"Community Bank East Tenness",
    "wof:placetype":"venue"
},
  "geometry": {"coordinates":[-83.99723,36.049779],"type":"Point"}
}