{
  "type": "Feature",
  "properties": {
    "iso:country":"US",
    "sg:address":"3147 Frayser Raleigh Rd",
    "sg:city":"Memphis",
    "sg:classifiers":[
        {
            "category":"Retail",
            "subcategory":"Veterinary Services",
            "type":"Services"
        }
    ],
    "sg:phone":"+1 901 353 9452",
    "sg:postcode":"38128",
    "sg:province":"TN",
    "sg:tags":[
        "hospital",
        "animal"
    ],
    "wof:name":"Frayser Raleigh Animal Hosp",
    "wof:placetype":"venue"
},
  "geometry": {"coordinates":[-89.958192,35.221433],"type":"Point"}
}