{
  "type": "Feature",
  "properties": {
    "iso:country":"US",
    "sg:address":"226 Arendall St",
    "sg:city":"Henderson",
    "sg:classifiers":[
        {
            "category":"Retail",
            "subcategory":"Auto Repair",
            "type":"Services"
        }
    ],
    "sg:phone":"+1 731 989 5795",
    "sg:postcode":"38340",
    "sg:province":"TN",
    "sg:tags":[
        "body",
        "automobile",
        "painting"
    ],
    "wof:name":"Mitchell's Body Shop",
    "wof:placetype":"venue"
},
  "geometry": {"coordinates":[-88.629831,35.443174],"type":"Point"}
}