{
  "type": "Feature",
  "properties": {
    "iso:country":"US",
    "sg:address":"3210 Dayton Blvd",
    "sg:city":"Chattanooga",
    "sg:classifiers":[
        {
            "category":"Personal",
            "subcategory":"Beauty Salon",
            "type":"Services"
        }
    ],
    "sg:phone":"+1 423 876 8040",
    "sg:postcode":"37415",
    "sg:province":"TN",
    "sg:tags":[
        "school"
    ],
    "wof:name":"Innovative Institute-Csmtlgy",
    "wof:placetype":"venue"
},
  "geometry": {"coordinates":[-85.295621,35.108848],"type":"Point"}
}