{
  "type": "Feature",
  "properties": {
    "addr:full":"1829 11th Ave N Nashville TN 37208",
    "addr:housenumber":"1829",
    "addr:postcode":"37208",
    "addr:street":"11Th Ave N",
    "iso:country":"US",
    "sg:address":"1829 11th Ave N",
    "sg:city":"Nashville",
    "sg:classifiers":[
        {
            "category":"Building & Trades",
            "subcategory":"Construction",
            "type":"Services"
        }
    ],
    "sg:phone":"+1 615 259 1238",
    "sg:postcode":"37208",
    "sg:province":"TN",
    "sg:tags":[
        "house"
    ],
    "wof:name":"Lockett Improvements",
    "wof:placetype":"venue"
},
  "geometry": {"coordinates":[-86.805176,36.181807],"type":"Point"}
}