{
  "type": "Feature",
  "properties": {
    "iso:country":"US",
    "sg:address":"2934 Beulah Church Rd",
    "sg:city":"Arrington",
    "sg:classifiers":[
        {
            "category":"Freight",
            "type":"Transportation"
        }
    ],
    "sg:phone":"+1 615 395 0052",
    "sg:postcode":"37014",
    "sg:province":"TN",
    "wof:name":"Whitson Movers Services",
    "wof:placetype":"venue"
},
  "geometry": {"coordinates":[-86.621184,35.890121],"type":"Point"}
}