{
  "type": "Feature",
  "properties": {
    "iso:country":"US",
    "sg:address":"1033 Hickory Hollow Rd",
    "sg:city":"Nashville",
    "sg:classifiers":[
        {
            "category":"Communications",
            "subcategory":"Film & Video Production",
            "type":"Services"
        }
    ],
    "sg:phone":"+1 615 646 6600",
    "sg:postcode":"37221",
    "sg:province":"TN",
    "sg:tags":[
        "motion"
    ],
    "wof:name":"John E Coates Productions Inc",
    "wof:placetype":"venue"
},
  "geometry": {"coordinates":[-86.95692,36.089172],"type":"Point"}
}