{
  "type": "Feature",
  "properties": {
    "iso:country":"US",
    "sg:address":"2122 Winthorne Ln",
    "sg:city":"Murfreesboro",
    "sg:classifiers":[
        {
            "category":"Building & Trades",
            "subcategory":"Construction",
            "type":"Services"
        }
    ],
    "sg:phone":"+1 615 631 8308",
    "sg:postcode":"37129",
    "sg:province":"TN",
    "sg:tags":[
        "repairing",
        "remodeling",
        "contractor"
    ],
    "wof:name":"Millennium Painting & Rnvtns",
    "wof:placetype":"venue"
},
  "geometry": {"coordinates":[-86.39121299999999,35.882645],"type":"Point"}
}