{
  "type": "Feature",
  "properties": {
    "addr:full":"715 Mahler Ave Cookeville TN 38501",
    "addr:housenumber":"715",
    "addr:postcode":"38501",
    "addr:street":"Mahler Ave",
    "iso:country":"US",
    "sg:address":"715 Mahler Ave",
    "sg:city":"Cookeville",
    "sg:classifiers":[
        {
            "category":"Retail",
            "subcategory":"Auto Repair",
            "type":"Services"
        }
    ],
    "sg:phone":"+1 931 525 6699",
    "sg:postcode":"38501",
    "sg:province":"TN",
    "sg:tags":[
        "automotive",
        "exhaust"
    ],
    "wof:name":"AAA Muffler",
    "wof:placetype":"venue"
},
  "geometry": {"coordinates":[-85.50354,36.171656],"type":"Point"}
}