{
  "type": "Feature",
  "properties": {
    "addr:full":"3495 New Hope Rd Hendersonville TN 37075",
    "addr:housenumber":"3495",
    "addr:postcode":"37075",
    "addr:street":"New Hope Rd",
    "iso:country":"US",
    "sg:address":"3495 New Hope Rd",
    "sg:city":"Hendersonville",
    "sg:classifiers":[
        {
            "category":"Building & Trades",
            "subcategory":"Construction",
            "type":"Services"
        }
    ],
    "sg:phone":"+1 615 824 7797",
    "sg:postcode":"37075",
    "sg:province":"TN",
    "sg:tags":[
        "house",
        "nonresidential"
    ],
    "wof:name":"Dekock Agency",
    "wof:placetype":"venue"
},
  "geometry": {"coordinates":[-86.616078,36.419972],"type":"Point"}
}