{
  "type": "Feature",
  "properties": {
    "iso:country":"US",
    "sg:address":"8697 Grandbury Pl",
    "sg:city":"Cordova",
    "sg:classifiers":[
        {
            "category":"Banks & Credit Unions",
            "subcategory":"Bank",
            "type":"Services"
        }
    ],
    "sg:phone":"+1 901 485 6022",
    "sg:postcode":"38016",
    "sg:province":"TN",
    "sg:tags":[
        "broker",
        "mortgage"
    ],
    "wof:name":"Dellson Associates Enterprises",
    "wof:placetype":"venue"
},
  "geometry": {"coordinates":[-89.770938,35.184302],"type":"Point"}
}