{
  "type": "Feature",
  "properties": {
    "iso:country":"US",
    "sg:address":"241 Hannah Dr",
    "sg:city":"Oliver Springs",
    "sg:classifiers":[
        {
            "category":"Building & Trades",
            "subcategory":"Landscaping Services",
            "type":"Services"
        }
    ],
    "sg:phone":"+1 865 435 1892",
    "sg:postcode":"37840",
    "sg:province":"TN",
    "sg:tags":[
        "landscape",
        "contractor"
    ],
    "wof:name":"Unlimited Landscaping",
    "wof:placetype":"venue"
},
  "geometry": {"coordinates":[-84.330949,36.034589],"type":"Point"}
}