{
  "type": "Feature",
  "properties": {
    "addr:full":"7908 Wolftever Rd Ooltewah TN 37363",
    "addr:housenumber":"7908",
    "addr:postcode":"37363",
    "addr:street":"Wolftever Rd",
    "iso:country":"US",
    "sg:address":"7908 Wolftever Rd",
    "sg:city":"Ooltewah",
    "sg:classifiers":[
        {
            "category":"Professional",
            "subcategory":"Art Services",
            "type":"Services"
        }
    ],
    "sg:phone":"+1 423 238 4868",
    "sg:postcode":"37363",
    "sg:province":"TN",
    "sg:tags":[
        "commercial",
        "design"
    ],
    "wof:name":"Gourd Graphics",
    "wof:placetype":"venue"
},
  "geometry": {"coordinates":[-85.076821,35.132669],"type":"Point"}
}