{
  "type": "Feature",
  "properties": {
    "iso:country":"US",
    "sg:address":"5840 State Hwy 100",
    "sg:city":"Reagan",
    "sg:classifiers":[
        {
            "category":"Restaurant",
            "type":"Food & Drink"
        }
    ],
    "sg:phone":"+1 731 549 2881",
    "sg:postcode":"38368",
    "sg:province":"TN",
    "sg:tags":[
        "eating"
    ],
    "wof:name":"J & R Bbq",
    "wof:placetype":"venue"
},
  "geometry": {"coordinates":[-88.321759,35.509028],"type":"Point"}
}