{
  "type": "Feature",
  "properties": {
    "iso:country":"US",
    "sg:address":"2183 Nolensville Pike",
    "sg:city":"Nashville",
    "sg:classifiers":[
        {
            "category":"Retail",
            "subcategory":"Auto Repair",
            "type":"Services"
        }
    ],
    "sg:phone":"+1 615 259 3445",
    "sg:postcode":"37211",
    "sg:province":"TN",
    "sg:tags":[
        "repairing",
        "automobile"
    ],
    "wof:name":"Missouri Auto Repair",
    "wof:placetype":"venue"
},
  "geometry": {"coordinates":[-86.75342499999999,36.127294],"type":"Point"}
}