{
  "type": "Feature",
  "properties": {
    "addr:full":"1100 Kermit Dr Nashville TN 37217",
    "addr:housenumber":"1100",
    "addr:postcode":"37217",
    "addr:street":"Kermit Dr",
    "iso:country":"US",
    "sg:address":"1100 Kermit Dr",
    "sg:city":"Nashville",
    "sg:classifiers":[
        {
            "category":"Professional",
            "subcategory":"Business Services",
            "type":"Services"
        }
    ],
    "sg:phone":"+1 615 366 8822",
    "sg:postcode":"37217",
    "sg:province":"TN",
    "sg:tags":[
        "photography",
        "topographic",
        "aerial",
        "mapping",
        "form"
    ],
    "wof:name":"Photogrammetric Data Service",
    "wof:placetype":"venue"
},
  "geometry": {"coordinates":[-86.703839,36.123785],"type":"Point"}
}