{
  "type": "Feature",
  "properties": {
    "iso:country":"US",
    "sg:address":"1045 Galloway Ave",
    "sg:city":"Memphis",
    "sg:classifiers":[
        {
            "category":"Manufacturing",
            "subcategory":"Wood Products",
            "type":"Manufacturing & Wholesale Goods"
        }
    ],
    "sg:phone":"+1 901 525 9966",
    "sg:postcode":"38105",
    "sg:province":"TN",
    "sg:tags":[
        "millwork"
    ],
    "wof:name":"Memphis Millwork",
    "wof:placetype":"venue"
},
  "geometry": {"coordinates":[-90.024389,35.152814],"type":"Point"}
}