{
  "type": "Feature",
  "properties": {
    "iso:country":"US",
    "sg:address":"3612 State Hwy 107",
    "sg:city":"Chuckey",
    "sg:classifiers":[
        {
            "category":"Shopping",
            "subcategory":"Florist",
            "type":"Retail Goods"
        }
    ],
    "sg:phone":"+1 423 257 2637",
    "sg:postcode":"37641",
    "sg:province":"TN",
    "wof:name":"Blue Ridge Plant Farms",
    "wof:placetype":"venue"
},
  "geometry": {"coordinates":[-82.644732,36.159467],"type":"Point"}
}