{
  "type": "Feature",
  "properties": {
    "iso:country":"US",
    "sg:address":"1000 Apex St",
    "sg:city":"Nashville",
    "sg:classifiers":[
        {
            "category":"Home & Garden",
            "subcategory":"Building Materials",
            "type":"Retail Goods"
        }
    ],
    "sg:phone":"+1 615 248 5010",
    "sg:postcode":"37206",
    "sg:province":"TN",
    "sg:tags":[
        "lumber"
    ],
    "wof:name":"Us Lumber",
    "wof:placetype":"venue"
},
  "geometry": {"coordinates":[-86.75478099999999,36.188697],"type":"Point"}
}