{
  "type": "Feature",
  "properties": {
    "addr:full":"2613 Mcgavock Pike # C Nashville TN 37214",
    "addr:housenumber":"2613",
    "addr:postcode":"37214",
    "addr:street":"Mcgavock Pike # C",
    "iso:country":"US",
    "sg:address":"2613 Mcgavock Pike # C",
    "sg:city":"Nashville",
    "sg:classifiers":[
        {
            "category":"Shopping",
            "subcategory":"Gifts & Souvenirs",
            "type":"Retail Goods"
        }
    ],
    "sg:phone":"+1 615 872 8358",
    "sg:postcode":"37214",
    "sg:province":"TN",
    "sg:tags":[
        "shop"
    ],
    "wof:name":"Cooter's",
    "wof:placetype":"venue"
},
  "geometry": {"coordinates":[-86.697321,36.217124],"type":"Point"}
}