{
  "type": "Feature",
  "properties": {
    "iso:country":"US",
    "sg:address":"2324 Crestmoor Rd",
    "sg:city":"Nashville",
    "sg:classifiers":[
        {
            "category":"Restaurant",
            "type":"Food & Drink"
        }
    ],
    "sg:phone":"+1 615 386 9055",
    "sg:postcode":"37215",
    "sg:province":"TN",
    "sg:website":"www.cheesecakefactory.net",
    "wof:name":"Cheesecake Factory",
    "wof:placetype":"venue"
},
  "geometry": {"coordinates":[-86.816867,36.109591],"type":"Point"}
}