{
  "type": "Feature",
  "properties": {
    "addr:full":"2500 Shenandoah Dr Chattanooga TN 37421",
    "addr:housenumber":"2500",
    "addr:postcode":"37421",
    "addr:street":"Shenandoah Dr",
    "iso:country":"US",
    "sg:address":"2500 Shenandoah Dr",
    "sg:city":"Chattanooga",
    "sg:classifiers":[
        {
            "category":"Building & Trades",
            "subcategory":"Construction",
            "type":"Services"
        }
    ],
    "sg:phone":"+1 423 894 8779",
    "sg:postcode":"37421",
    "sg:province":"TN",
    "sg:tags":[
        "builder",
        "operative"
    ],
    "wof:name":"Akers Construction LLC",
    "wof:placetype":"venue"
},
  "geometry": {"coordinates":[-85.10167800000001,35.023654],"type":"Point"}
}