{
  "type": "Feature",
  "properties": {
    "iso:country":"US",
    "sg:address":"315 High St",
    "sg:city":"Huntingdon",
    "sg:classifiers":[
        {
            "category":"Shopping",
            "subcategory":"Computers & Home Electronics",
            "type":"Retail Goods"
        }
    ],
    "sg:phone":"+1 731 986 5503",
    "sg:postcode":"38344",
    "sg:province":"TN",
    "sg:tags":[
        "repair"
    ],
    "wof:name":"T V Mc Mackin Inc",
    "wof:placetype":"venue"
},
  "geometry": {"coordinates":[-88.41351,36.011847],"type":"Point"}
}