{
  "type": "Feature",
  "properties": {
    "iso:country":"US",
    "sg:address":"403 E Main St",
    "sg:city":"Rogersville",
    "sg:classifiers":[
        {
            "category":"Government",
            "subcategory":"Office",
            "type":"Public Place"
        }
    ],
    "sg:phone":"+1 423 272 7668",
    "sg:postcode":"37857",
    "sg:province":"TN",
    "sg:tags":[
        "development"
    ],
    "wof:name":"Industrial Development Board",
    "wof:placetype":"venue"
},
  "geometry": {"coordinates":[-83.003715,36.408136],"type":"Point"}
}