{
  "type": "Feature",
  "properties": {
    "iso:country":"US",
    "sg:address":"1066 W Outer Dr",
    "sg:city":"Oak Ridge",
    "sg:classifiers":[
        {
            "category":"Organizations",
            "subcategory":"Membership Organization",
            "type":"Services"
        }
    ],
    "sg:phone":"+1 865 482 3394",
    "sg:postcode":"37830",
    "sg:province":"TN",
    "wof:name":"Aid Assoc For Lutherans 4",
    "wof:placetype":"venue"
},
  "geometry": {"coordinates":[-84.339127,35.991432],"type":"Point"}
}