{
  "type": "Feature",
  "properties": {
    "iso:country":"US",
    "sg:address":"539 Winfield Dunn Pkwy",
    "sg:city":"Sevierville",
    "sg:classifiers":[
        {
            "category":"Shopping",
            "subcategory":"Bicycles & Sporting Goods",
            "type":"Retail Goods"
        }
    ],
    "sg:phone":"+1 865 453 5010",
    "sg:postcode":"37876",
    "sg:province":"TN",
    "sg:tags":[
        "equipment",
        "golf",
        "supply"
    ],
    "wof:name":"J Floyds Golf Works",
    "wof:placetype":"venue"
},
  "geometry": {"coordinates":[-83.572408,35.880732],"type":"Point"}
}