{
  "type": "Feature",
  "properties": {
    "addr:full":"2209 Crestmoor Rd Nashville TN 37215",
    "addr:housenumber":"2209",
    "addr:postcode":"37215",
    "addr:street":"Crestmoor Rd",
    "iso:country":"US",
    "sg:address":"2209 Crestmoor Rd",
    "sg:city":"Nashville",
    "sg:classifiers":[
        {
            "category":"Insurance",
            "subcategory":"Insurance Agent",
            "type":"Services"
        }
    ],
    "sg:phone":"+1 615 383 0449",
    "sg:postcode":"37215",
    "sg:province":"TN",
    "wof:name":"State Farm Insurance",
    "wof:placetype":"venue"
},
  "geometry": {"coordinates":[-86.81334200000001,36.10937],"type":"Point"}
}