{
  "type": "Feature",
  "properties": {
    "iso:country":"US",
    "sg:address":"420 Russfield Dr",
    "sg:city":"Knoxville",
    "sg:classifiers":[
        {
            "category":"Real Estate",
            "subcategory":"Real Estate Agent",
            "type":"Services"
        }
    ],
    "sg:phone":"+1 865 777 2175",
    "sg:postcode":"37934",
    "sg:province":"TN",
    "wof:name":"Boone Terena",
    "wof:placetype":"venue"
},
  "geometry": {"coordinates":[-84.169055,35.886947],"type":"Point"}
}