{
  "type": "Feature",
  "properties": {
    "iso:country":"US",
    "sg:address":"241 Mayberry St",
    "sg:city":"Sparta",
    "sg:classifiers":[
        {
            "category":"Manufacturing",
            "subcategory":"Tools & Machinery",
            "type":"Manufacturing & Wholesale Goods"
        }
    ],
    "sg:phone":"+1 931 837 8744",
    "sg:postcode":"38583",
    "sg:province":"TN",
    "sg:tags":[
        "machine",
        "shop"
    ],
    "wof:name":"Austin Machine Shop",
    "wof:placetype":"venue"
},
  "geometry": {"coordinates":[-85.480464,35.923838],"type":"Point"}
}