{
  "type": "Feature",
  "properties": {
    "iso:country":"US",
    "sg:address":"2432 Mitchell St",
    "sg:city":"Knoxville",
    "sg:classifiers":[
        {
            "category":"Building & Trades",
            "subcategory":"Construction",
            "type":"Services"
        }
    ],
    "sg:phone":"+1 865 522 2181",
    "sg:postcode":"37917",
    "sg:province":"TN",
    "sg:tags":[
        "concrete",
        "contractor"
    ],
    "wof:name":"Kline Building Group Inc",
    "wof:placetype":"venue"
},
  "geometry": {"coordinates":[-83.903137,35.992648],"type":"Point"}
}