{
  "type": "Feature",
  "properties": {
    "addr:full":"1945 NW Broad St Murfreesboro TN 37129",
    "addr:housenumber":"1945",
    "addr:postcode":"37129",
    "addr:street":"Nw Broad St",
    "iso:country":"US",
    "sg:address":"1945 NW Broad St",
    "sg:city":"Murfreesboro",
    "sg:classifiers":[
        {
            "category":"Shopping",
            "subcategory":"Used Merchandise",
            "type":"Retail Goods"
        }
    ],
    "sg:phone":"+1 615 895 6446",
    "sg:postcode":"37129",
    "sg:province":"TN",
    "wof:name":"A-1 Cash",
    "wof:placetype":"venue"
},
  "geometry": {"coordinates":[-86.403702,35.85591],"type":"Point"}
}