{
  "type": "Feature",
  "properties": {
    "iso:country":"US",
    "sg:address":"1029 Shelton Dr",
    "sg:city":"Henderson",
    "sg:classifiers":[
        {
            "category":"Professional",
            "subcategory":"Business Services",
            "type":"Services"
        }
    ],
    "sg:phone":"+1 731 989 7608",
    "sg:postcode":"38340",
    "sg:province":"TN",
    "wof:name":"Impressions",
    "wof:placetype":"venue"
},
  "geometry": {"coordinates":[-88.659525,35.458277],"type":"Point"}
}