{
  "type": "Feature",
  "properties": {
    "iso:country":"US",
    "sg:address":"142 Church St",
    "sg:city":"Madisonville",
    "sg:classifiers":[
        {
            "category":"Real Estate",
            "subcategory":"Real Estate Operator",
            "type":"Services"
        }
    ],
    "sg:phone":"+1 423 442 5917",
    "sg:postcode":"37354",
    "sg:province":"TN",
    "sg:tags":[
        "building",
        "apartment"
    ],
    "wof:name":"Mountain View Apartments",
    "wof:placetype":"venue"
},
  "geometry": {"coordinates":[-84.361341,35.518809],"type":"Point"}
}