{
  "type": "Feature",
  "properties": {
    "addr:full":"1134 Commerce Park Murfreesboro TN 37130",
    "addr:housenumber":"1134",
    "addr:postcode":"37130",
    "addr:street":"Commerce Park",
    "iso:country":"US",
    "sg:address":"1134 Commerce Park",
    "sg:city":"Murfreesboro",
    "sg:classifiers":[
        {
            "category":"Wholesale",
            "subcategory":"Durable Goods & Equipment",
            "type":"Manufacturing & Wholesale Goods"
        }
    ],
    "sg:phone":"+1 615 867 9989",
    "sg:postcode":"37130",
    "sg:province":"TN",
    "sg:tags":[
        "exporter"
    ],
    "wof:name":"Resilient Furniture Sales",
    "wof:placetype":"venue"
},
  "geometry": {"coordinates":[-86.392258,35.829867],"type":"Point"}
}