{
  "type": "Feature",
  "properties": {
    "addr:full":"8322 Chapman Hwy Knoxville TN 37920",
    "addr:housenumber":"8322",
    "addr:postcode":"37920",
    "addr:street":"Chapman Hwy",
    "iso:country":"US",
    "sg:address":"8322 Chapman Hwy",
    "sg:city":"Knoxville",
    "sg:classifiers":[
        {
            "category":"Autos & Motor Vehicles",
            "subcategory":"Automobile Sales",
            "type":"Retail Goods"
        }
    ],
    "sg:phone":"+1 865 577 1641",
    "sg:postcode":"37920",
    "sg:province":"TN",
    "sg:tags":[
        "used"
    ],
    "wof:name":"Car Depot",
    "wof:placetype":"venue"
},
  "geometry": {"coordinates":[-83.817628,35.900006],"type":"Point"}
}