{
  "type": "Feature",
  "properties": {
    "iso:country":"US",
    "sg:address":"330 Buffalo Valley Rd",
    "sg:city":"Cookeville",
    "sg:classifiers":[
        {
            "category":"Professional",
            "subcategory":"Advertising",
            "type":"Services"
        }
    ],
    "sg:phone":"+1 931 526 5766",
    "sg:postcode":"38501",
    "sg:province":"TN",
    "sg:tags":[
        "outdoor"
    ],
    "sg:website":"www.lamar.com",
    "wof:name":"Lamar Advertising Co",
    "wof:placetype":"venue"
},
  "geometry": {"coordinates":[-85.51402400000001,36.161024],"type":"Point"}
}