{
  "type": "Feature",
  "properties": {
    "iso:country":"US",
    "sg:address":"243 S Main St",
    "sg:city":"Jamestown",
    "sg:classifiers":[
        {
            "category":"Food & Beverages",
            "subcategory":"Fruits & Vegetables",
            "type":"Retail Goods"
        }
    ],
    "sg:phone":"+1 931 879 3578",
    "sg:postcode":"38556",
    "sg:province":"TN",
    "sg:tags":[
        "produce"
    ],
    "wof:name":"Penny's Garden Spot",
    "wof:placetype":"venue"
},
  "geometry": {"coordinates":[-84.932266,36.426302],"type":"Point"}
}