{
  "type": "Feature",
  "properties": {
    "addr:full":"735 S 1st St Pulaski TN 38478",
    "addr:housenumber":"735",
    "addr:postcode":"38478",
    "addr:street":"S 1St St",
    "iso:country":"US",
    "sg:address":"735 S 1st St",
    "sg:city":"Pulaski",
    "sg:classifiers":[
        {
            "category":"Personal",
            "subcategory":"Tattoo Parlor",
            "type":"Services"
        }
    ],
    "sg:phone":"+1 931 424 8765",
    "sg:postcode":"38478",
    "sg:province":"TN",
    "sg:tags":[
        "tattooing"
    ],
    "wof:name":"Mid Evil Ink Tattoos",
    "wof:placetype":"venue"
},
  "geometry": {"coordinates":[-87.034144,35.191385],"type":"Point"}
}