{
  "type": "Feature",
  "properties": {
    "iso:country":"US",
    "sg:address":"2255 Center St",
    "sg:city":"Chattanooga",
    "sg:classifiers":[
        {
            "category":"Professional",
            "type":"Services"
        }
    ],
    "sg:phone":"+1 423 899 3838",
    "sg:postcode":"37421",
    "sg:province":"TN",
    "wof:name":"Shae Foundation",
    "wof:placetype":"venue"
},
  "geometry": {"coordinates":[-85.161113,35.042555],"type":"Point"}
}