{
  "type": "Feature",
  "properties": {
    "addr:full":"630 Mississippi Ave Signal Mountain TN 37377",
    "addr:housenumber":"630",
    "addr:postcode":"37377",
    "addr:street":"Mississippi Ave",
    "iso:country":"US",
    "sg:address":"630 Mississippi Ave",
    "sg:city":"Signal Mountain",
    "sg:classifiers":[
        {
            "category":"Shopping",
            "subcategory":"Used Merchandise",
            "type":"Retail Goods"
        }
    ],
    "sg:phone":"+1 423 886 7411",
    "sg:postcode":"37377",
    "sg:province":"TN",
    "sg:tags":[
        "shop",
        "thrift"
    ],
    "wof:name":"St Timothy's Thrift Shop",
    "wof:placetype":"venue"
},
  "geometry": {"coordinates":[-85.346661,35.122549],"type":"Point"}
}