{
  "type": "Feature",
  "properties": {
    "iso:country":"US",
    "sg:address":"1196 Alpine Dr",
    "sg:city":"Sevierville",
    "sg:classifiers":[
        {
            "category":"Health Services",
            "subcategory":"Clinic",
            "type":"Services"
        },
        {
            "category":"Personal",
            "type":"Services"
        },
        {
            "category":"Health Services",
            "subcategory":"Health Practitioner",
            "type":"Services"
        }
    ],
    "sg:phone":"+1 865 428 4851",
    "sg:postcode":"37876",
    "sg:province":"TN",
    "sg:tags":[
        "information",
        "drug",
        "alcoholism",
        "abuse",
        "counselors-licensed",
        "professional",
        "addiction",
        "rehabilitation",
        "treatment"
    ],
    "sg:website":"http://emrecovery.org",
    "wof:name":"English Mountain Recovery",
    "wof:placetype":"venue"
},
  "geometry": {"coordinates":[-83.31113499999999,35.878339],"type":"Point"}
}