{
  "type": "Feature",
  "properties": {
    "addr:full":"2712 Ball Camp Byington Rd Knoxville TN 37931",
    "addr:housenumber":"2712",
    "addr:postcode":"37931",
    "addr:street":"Ball;Byington Rd",
    "iso:country":"US",
    "sg:address":"2712 Ball Camp Byington Rd",
    "sg:city":"Knoxville",
    "sg:classifiers":[
        {
            "category":"Building & Trades",
            "subcategory":"Construction",
            "type":"Services"
        }
    ],
    "sg:phone":"+1 865 693 6166",
    "sg:postcode":"37931",
    "sg:province":"TN",
    "sg:tags":[
        "maker",
        "cabinet"
    ],
    "wof:name":"LA Montagne Selected Wood",
    "wof:placetype":"venue"
},
  "geometry": {"coordinates":[-84.124427,35.963381],"type":"Point"}
}