{
  "type": "Feature",
  "properties": {
    "iso:country":"US",
    "sg:address":"316 N Main Ave",
    "sg:city":"Erwin",
    "sg:classifiers":[
        {
            "category":"Retail",
            "subcategory":"Repair Shop",
            "type":"Services"
        }
    ],
    "sg:phone":"+1 423 743 9590",
    "sg:postcode":"37650",
    "sg:province":"TN",
    "sg:tags":[
        "repairing",
        "lawn",
        "mower"
    ],
    "wof:name":"Lamb' S Small Engine",
    "wof:placetype":"venue"
},
  "geometry": {"coordinates":[-82.41446000000001,36.146985],"type":"Point"}
}