{
  "type": "Feature",
  "properties": {
    "iso:country":"US",
    "sg:address":"1227 Congress Pkwy N",
    "sg:city":"Athens",
    "sg:classifiers":[
        {
            "category":"Restaurant",
            "type":"Food & Drink"
        }
    ],
    "sg:menulink":"http://www.allmenus.com/tn/athens/200267-long-john-silvers/menu/",
    "sg:phone":"+1 423 745 3275",
    "sg:postcode":"37303",
    "sg:province":"TN",
    "sg:tags":[
        "seafood",
        "american"
    ],
    "wof:name":"Long John Silver's",
    "wof:placetype":"venue"
},
  "geometry": {"coordinates":[-84.57675,35.492234],"type":"Point"}
}