{
  "type": "Feature",
  "properties": {
    "addr:full":"8222 US Hwy 51 N Millington TN 38053",
    "addr:housenumber":"8222",
    "addr:postcode":"38053",
    "addr:street":"Us Hwy 51 N",
    "iso:country":"US",
    "sg:address":"8222 US Hwy 51 N",
    "sg:city":"Millington",
    "sg:classifiers":[
        {
            "category":"Social Services",
            "type":"Services"
        }
    ],
    "sg:phone":"+1 901 872 3525",
    "sg:postcode":"38053",
    "sg:province":"TN",
    "sg:tags":[
        "worker"
    ],
    "wof:name":"Douglas Gauss",
    "wof:placetype":"venue"
},
  "geometry": {"coordinates":[-89.90047800000001,35.350334],"type":"Point"}
}