{
  "type": "Feature",
  "properties": {
    "addr:full":"900 Ohio Ave Etowah TN 37331",
    "addr:housenumber":"900",
    "addr:postcode":"37331",
    "addr:street":"Ohio Ave",
    "iso:country":"US",
    "sg:address":"900 Ohio Ave",
    "sg:city":"Etowah",
    "sg:classifiers":[
        {
            "category":"Social Services",
            "type":"Services"
        }
    ],
    "sg:phone":"+1 423 263 0019",
    "sg:postcode":"37331",
    "sg:province":"TN",
    "sg:tags":[
        "counselor",
        "marriage",
        "family"
    ],
    "wof:name":"Smoky Mountain Counseling",
    "wof:placetype":"venue"
},
  "geometry": {"coordinates":[-84.527153,35.322711],"type":"Point"}
}