{
  "type": "Feature",
  "properties": {
    "iso:country":"US",
    "sg:address":"3651 Baxter Rd",
    "sg:city":"Joelton",
    "sg:classifiers":[
        {
            "category":"Professional",
            "type":"Services"
        }
    ],
    "sg:phone":"+1 615 876 1915",
    "sg:postcode":"37080",
    "sg:province":"TN",
    "wof:name":"Laymond Tackett",
    "wof:placetype":"venue"
},
  "geometry": {"coordinates":[-86.89063400000001,36.352082],"type":"Point"}
}