{
  "type": "Feature",
  "properties": {
    "iso:country":"US",
    "sg:address":"505 Dolly Parton Pkwy",
    "sg:city":"Sevierville",
    "sg:phone":"+1 865 428 4271",
    "sg:postcode":"37862",
    "sg:province":"TN",
    "sg:tags":[
        "gas"
    ],
    "wof:name":"Heritage Propane",
    "wof:placetype":"venue"
},
  "geometry": {"coordinates":[-83.55481,35.866391],"type":"Point"}
}