{
  "type": "Feature",
  "properties": {
    "iso:country":"US",
    "sg:address":"1555 Madison Ave",
    "sg:city":"Memphis",
    "sg:classifiers":[
        {
            "category":"Professional",
            "subcategory":"Printing & Photocopies",
            "type":"Services"
        }
    ],
    "sg:phone":"+1 901 761 5782",
    "sg:postcode":"38104",
    "sg:province":"TN",
    "sg:tags":[
        "photographers-commercial"
    ],
    "wof:name":"Terry Thompson Photography",
    "wof:placetype":"venue"
},
  "geometry": {"coordinates":[-90.009376,35.138252],"type":"Point"}
}