{
  "type": "Feature",
  "properties": {
    "addr:full":"8822 Production Ln Ooltewah TN 37363",
    "addr:housenumber":"8822",
    "addr:postcode":"37363",
    "addr:street":"Production Ln",
    "iso:country":"US",
    "sg:address":"8822 Production Ln",
    "sg:city":"Ooltewah",
    "sg:classifiers":[
        {
            "category":"Professional",
            "subcategory":"Lawyer & Legal Services",
            "type":"Services"
        }
    ],
    "sg:phone":"+1 423 842 5148",
    "sg:postcode":"37363",
    "sg:province":"TN",
    "sg:tags":[
        "attorney"
    ],
    "wof:name":"Kent R Moore",
    "wof:placetype":"venue"
},
  "geometry": {"coordinates":[-85.05596300000001,35.102557],"type":"Point"}
}