{
  "type": "Feature",
  "properties": {
    "iso:country":"US",
    "sg:address":"711 N Maney Ave",
    "sg:city":"Murfreesboro",
    "sg:classifiers":[
        {
            "category":"Organizations",
            "subcategory":"Religious Organization",
            "type":"Services"
        }
    ],
    "sg:phone":"+1 615 893 9901",
    "sg:postcode":"37130",
    "sg:province":"TN",
    "sg:tags":[
        "church"
    ],
    "wof:name":"Oakland Park Seventh-Day Adv",
    "wof:placetype":"venue"
},
  "geometry": {"coordinates":[-86.38562,35.852959],"type":"Point"}
}