{
  "type": "Feature",
  "properties": {
    "addr:full":"991 Ripley Island Rd Afton TN 37616",
    "addr:housenumber":"991",
    "addr:postcode":"37616",
    "addr:street":"Ripley Island Rd",
    "iso:country":"US",
    "sg:address":"991 Ripley Island Rd",
    "sg:city":"Afton",
    "sg:classifiers":[
        {
            "category":"Building & Trades",
            "subcategory":"Construction",
            "type":"Services"
        }
    ],
    "sg:phone":"+1 423 638 8225",
    "sg:postcode":"37616",
    "sg:province":"TN",
    "sg:tags":[
        "cabinet",
        "carpentry",
        "maker",
        "contractor"
    ],
    "wof:name":"Nelson & Sons Woodworking Shop",
    "wof:placetype":"venue"
},
  "geometry": {"coordinates":[-82.727164,36.177526],"type":"Point"}
}