{
  "type": "Feature",
  "properties": {
    "addr:full":"2809 Parkway Pigeon Forge TN 37863",
    "addr:housenumber":"2809",
    "addr:postcode":"37863",
    "addr:street":"Parkway",
    "iso:country":"US",
    "sg:address":"2809 Parkway",
    "sg:city":"Pigeon Forge",
    "sg:classifiers":[
        {
            "category":"Travel",
            "subcategory":"Hotels & Motels",
            "type":"Entertainment"
        }
    ],
    "sg:phone":"+1 865 453 4625",
    "sg:postcode":"37863",
    "sg:province":"TN",
    "sg:tags":[
        "operation"
    ],
    "wof:name":"Smoky Meadows Lodge",
    "wof:placetype":"venue"
},
  "geometry": {"coordinates":[-83.569008,35.799122],"type":"Point"}
}