{
  "type": "Feature",
  "properties": {
    "iso:country":"US",
    "sg:address":"401 East St",
    "sg:city":"Somerville",
    "sg:classifiers":[
        {
            "category":"Professional",
            "subcategory":"Art Services",
            "type":"Services"
        }
    ],
    "sg:phone":"+1 901 465 1317",
    "sg:postcode":"38068",
    "sg:province":"TN",
    "sg:tags":[
        "commercial",
        "design"
    ],
    "wof:name":"Snakekiller Prods",
    "wof:placetype":"venue"
},
  "geometry": {"coordinates":[-89.348922,35.239964],"type":"Point"}
}