{
  "type": "Feature",
  "properties": {
    "iso:country":"US",
    "sg:address":"320 Memorial Dr",
    "sg:city":"Paris",
    "sg:classifiers":[
        {
            "category":"Farming",
            "subcategory":"Nursery",
            "type":"Manufacturing & Wholesale Goods"
        },
        {
            "category":"Home & Garden",
            "subcategory":"Garden Supply",
            "type":"Retail Goods"
        }
    ],
    "sg:phone":"+1 731 642 2215",
    "sg:postcode":"38242",
    "sg:province":"TN",
    "sg:tags":[
        "nurseryman",
        "grows",
        "stock"
    ],
    "wof:name":"Wildwood Garden Center",
    "wof:placetype":"venue"
},
  "geometry": {"coordinates":[-88.296605,36.283407],"type":"Point"}
}