{
  "type": "Feature",
  "properties": {
    "iso:country":"US",
    "sg:address":"7502 Strawberry Plains Pike",
    "sg:city":"Knoxville",
    "sg:classifiers":[
        {
            "category":"Retail",
            "subcategory":"Auto Rental",
            "type":"Services"
        }
    ],
    "sg:phone":"+1 865 933 0455",
    "sg:postcode":"37924",
    "sg:province":"TN",
    "sg:tags":[
        "renting",
        "truck",
        "leasing"
    ],
    "wof:name":"U-Haul Co",
    "wof:placetype":"venue"
},
  "geometry": {"coordinates":[-83.77141899999999,36.006534],"type":"Point"}
}