{
  "type": "Feature",
  "properties": {
    "iso:country":"US",
    "sg:address":"248 S 4th St",
    "sg:city":"Nashville",
    "sg:classifiers":[
        {
            "category":"Building & Trades",
            "subcategory":"Construction",
            "type":"Services"
        }
    ],
    "sg:phone":"+1 615 259 7935",
    "sg:postcode":"37206",
    "sg:province":"TN",
    "sg:tags":[
        "contractor"
    ],
    "wof:name":"Houston Contractor",
    "wof:placetype":"venue"
},
  "geometry": {"coordinates":[-86.765355,36.169761],"type":"Point"}
}