{
  "type": "Feature",
  "properties": {
    "iso:country":"US",
    "sg:address":"10 Knolls Pl",
    "sg:city":"Nashville",
    "sg:classifiers":[
        {
            "category":"Social Services",
            "subcategory":"Child Care",
            "type":"Services"
        }
    ],
    "sg:phone":"+1 615 331 4110",
    "sg:postcode":"37211",
    "sg:province":"TN",
    "sg:website":"www.knowledgelearning.com",
    "wof:name":"Children's World Learning Ctr",
    "wof:placetype":"venue"
},
  "geometry": {"coordinates":[-86.71713699999999,36.045224],"type":"Point"}
}