{
  "type": "Feature",
  "properties": {
    "iso:country":"US",
    "sg:address":"4889 Old Bridge Rd",
    "sg:city":"Cookeville",
    "sg:classifiers":[
        {
            "category":"Professional",
            "subcategory":"Management & Consulting",
            "type":"Services"
        }
    ],
    "sg:phone":"+1 931 526 7554",
    "sg:postcode":"38506",
    "sg:province":"TN",
    "sg:tags":[
        "consultant",
        "business"
    ],
    "wof:name":"Bilbrey Brothers Livestock",
    "wof:placetype":"venue"
},
  "geometry": {"coordinates":[-85.48218199999999,36.097031],"type":"Point"}
}