{
  "type": "Feature",
  "properties": {
    "iso:country":"US",
    "sg:address":"5035 Hixson Pike",
    "sg:city":"Hixson",
    "sg:classifiers":[
        {
            "category":"Restaurant",
            "type":"Food & Drink"
        }
    ],
    "sg:menulink":"http://www.allmenus.com/tn/chattanooga/256677-super-suppers/menu/",
    "sg:phone":"+1 423 875 5485",
    "sg:postcode":"37343",
    "sg:province":"TN",
    "sg:tags":[
        "new",
        "american"
    ],
    "wof:name":"Super Suppers",
    "wof:placetype":"venue"
},
  "geometry": {"coordinates":[-85.24062000000001,35.135801],"type":"Point"}
}