{
  "type": "Feature",
  "properties": {
    "addr:full":"1004 Kensington Ln Kingsport TN 37664",
    "addr:housenumber":"1004",
    "addr:postcode":"37664",
    "addr:street":"Kensington Ln",
    "iso:country":"US",
    "sg:address":"1004 Kensington Ln",
    "sg:city":"Kingsport",
    "sg:classifiers":[
        {
            "category":"Professional",
            "subcategory":"Business Services",
            "type":"Services"
        }
    ],
    "sg:phone":"+1 423 288 2937",
    "sg:postcode":"37664",
    "sg:province":"TN",
    "sg:tags":[
        "interior",
        "consultant",
        "design",
        "decorator"
    ],
    "wof:name":"Jo Ann Bledsoe Interior Dec",
    "wof:placetype":"venue"
},
  "geometry": {"coordinates":[-82.49397500000001,36.518021],"type":"Point"}
}