{
  "type": "Feature",
  "properties": {
    "addr:full":"371 S White Station Rd Memphis TN 38117",
    "addr:housenumber":"371",
    "addr:postcode":"38117",
    "addr:street":"S White Station Rd",
    "iso:country":"US",
    "sg:address":"371 S White Station Rd",
    "sg:city":"Memphis",
    "sg:classifiers":[
        {
            "category":"Real Estate",
            "subcategory":"Developer",
            "type":"Services"
        }
    ],
    "sg:phone":"+1 901 763 3306",
    "sg:postcode":"38117",
    "sg:province":"TN",
    "sg:tags":[
        "cemetery"
    ],
    "wof:name":"Above Average Courier",
    "wof:placetype":"venue"
},
  "geometry": {"coordinates":[-89.887829,35.120658],"type":"Point"}
}