{
  "type": "Feature",
  "properties": {
    "iso:country":"US",
    "sg:address":"510 S Old Sevierville Pike",
    "sg:city":"Seymour",
    "sg:classifiers":[
        {
            "category":"Arts & Performance",
            "subcategory":"Theater",
            "type":"Entertainment"
        }
    ],
    "sg:phone":"+1 865 577 9527",
    "sg:postcode":"37865",
    "sg:province":"TN",
    "sg:tags":[
        "group"
    ],
    "wof:name":"Digital Entertainment Concepts",
    "wof:placetype":"venue"
},
  "geometry": {"coordinates":[-83.747394,35.88825],"type":"Point"}
}