{
  "type": "Feature",
  "properties": {
    "iso:country":"US",
    "sg:address":"260 Fort Sanders West Blvd",
    "sg:city":"Knoxville",
    "sg:classifiers":[
        {
            "category":"Professional",
            "type":"Services"
        }
    ],
    "sg:phone":"+1 865 769 4566",
    "sg:postcode":"37922",
    "sg:province":"TN",
    "sg:tags":[
        "establishment"
    ],
    "wof:name":"S E O's Second Look",
    "wof:placetype":"venue"
},
  "geometry": {"coordinates":[-84.12015700000001,35.900446],"type":"Point"}
}