{
  "type": "Feature",
  "properties": {
    "iso:country":"US",
    "sg:address":"941 Airport Service Rd",
    "sg:city":"Nashville",
    "sg:classifiers":[
        {
            "category":"Transit Center",
            "subcategory":"Freight",
            "type":"Transportation"
        }
    ],
    "sg:phone":"+1 615 275 0257",
    "sg:postcode":"37214",
    "sg:province":"TN",
    "sg:tags":[
        "air",
        "cargo",
        "express",
        "package"
    ],
    "wof:name":"Frontier Airlines Air Cargo",
    "wof:placetype":"venue"
},
  "geometry": {"coordinates":[-86.66555,36.12495],"type":"Point"}
}