{
  "type": "Feature",
  "properties": {
    "iso:country":"US",
    "sg:address":"6631 Imperial Oak Dr",
    "sg:city":"Memphis",
    "sg:classifiers":[
        {
            "category":"Autos & Motor Vehicles",
            "subcategory":"Auto Supplies",
            "type":"Retail Goods"
        }
    ],
    "sg:phone":"+1 901 949 4543",
    "sg:postcode":"38115",
    "sg:province":"TN",
    "wof:name":"Rodgers Tire Company",
    "wof:placetype":"venue"
},
  "geometry": {"coordinates":[-89.84410099999999,35.053294],"type":"Point"}
}