{
  "type": "Feature",
  "properties": {
    "addr:full":"1200 E Lakeview Dr Johnson City TN 37601",
    "addr:housenumber":"1200",
    "addr:postcode":"37601",
    "addr:street":"E Lakeview Dr",
    "iso:country":"US",
    "sg:address":"1200 E Lakeview Dr",
    "sg:city":"Johnson City",
    "sg:classifiers":[
        {
            "category":"Food & Beverages",
            "subcategory":"Groceries & Convenience Stores",
            "type":"Retail Goods"
        }
    ],
    "sg:phone":"+1 423 926 2134",
    "sg:postcode":"37601",
    "sg:province":"TN",
    "sg:tags":[
        "grocer"
    ],
    "wof:name":"Jim's Market & Deli",
    "wof:placetype":"venue"
},
  "geometry": {"coordinates":[-82.338144,36.350761],"type":"Point"}
}