{
  "type": "Feature",
  "properties": {
    "addr:full":"3443 Dickerson Pike Nashville TN 37207",
    "addr:housenumber":"3443",
    "addr:postcode":"37207",
    "addr:street":"Dickerson Pike",
    "iso:country":"US",
    "sg:address":"3443 Dickerson Pike",
    "sg:city":"Nashville",
    "sg:classifiers":[
        {
            "category":"Health Services",
            "subcategory":"Doctor",
            "type":"Services"
        }
    ],
    "sg:phone":"+1 615 860 1702",
    "sg:postcode":"37207",
    "sg:province":"TN",
    "sg:tags":[
        "medical"
    ],
    "sg:website":"www.uhc.com",
    "wof:name":"Urology Associates",
    "wof:placetype":"venue"
},
  "geometry": {"coordinates":[-86.75720800000001,36.241164],"type":"Point"}
}