{
  "type": "Feature",
  "properties": {
    "iso:country":"US",
    "sg:address":"8008 Powell Heights Rd",
    "sg:city":"Powell",
    "sg:classifiers":[
        {
            "category":"Government",
            "subcategory":"Court House",
            "type":"Public Place"
        }
    ],
    "sg:phone":"+1 561 625 1401",
    "sg:postcode":"37849",
    "sg:province":"TN",
    "wof:name":"SES Process Inc",
    "wof:placetype":"venue"
},
  "geometry": {"coordinates":[-84.03384200000001,36.039164],"type":"Point"}
}