{
  "type": "Feature",
  "properties": {
    "addr:full":"104 Martin St Kingston TN 37763",
    "addr:housenumber":"104",
    "addr:postcode":"37763",
    "addr:street":"Martin St",
    "iso:country":"US",
    "sg:address":"104 Martin St",
    "sg:city":"Kingston",
    "sg:classifiers":[
        {
            "category":"Restaurant",
            "type":"Food & Drink"
        }
    ],
    "sg:menulink":"http://www.allmenus.com/tn/kingston/73107-pizza-hut/menu/",
    "sg:phone":"+1 865 376 2300",
    "sg:postcode":"37763",
    "sg:province":"TN",
    "sg:tags":[
        "american",
        "pizza"
    ],
    "wof:name":"Pizza Hut",
    "wof:placetype":"venue"
},
  "geometry": {"coordinates":[-84.511872,35.87788],"type":"Point"}
}