{
  "type": "Feature",
  "properties": {
    "iso:country":"US",
    "sg:address":"1020 Riverfront Pkwy",
    "sg:city":"Chattanooga",
    "sg:classifiers":[
        {
            "category":"Banks & Credit Unions",
            "subcategory":"Bank",
            "type":"Services"
        }
    ],
    "sg:phone":"+1 423 756 3300",
    "sg:postcode":"37402",
    "sg:province":"TN",
    "sg:website":"www.comtrustfcu.com",
    "wof:name":"Comtrust Federal Credit Union",
    "wof:placetype":"venue"
},
  "geometry": {"coordinates":[-85.32230300000001,35.047232],"type":"Point"}
}