{
  "type": "Feature",
  "properties": {
    "addr:full":"448 N Cedar Bluff Rd Knoxville TN 37923",
    "addr:housenumber":"448",
    "addr:postcode":"37923",
    "addr:street":"N Cedar Bluff Rd",
    "iso:country":"US",
    "sg:address":"448 N Cedar Bluff Rd",
    "sg:city":"Knoxville",
    "sg:classifiers":[
        {
            "category":"Professional",
            "subcategory":"Advertising",
            "type":"Services"
        }
    ],
    "sg:phone":"+1 865 690 3459",
    "sg:postcode":"37923",
    "sg:province":"TN",
    "sg:tags":[
        "shipping",
        "mailing",
        "direct",
        "business",
        "mail"
    ],
    "wof:name":"UPS Store The",
    "wof:placetype":"venue"
},
  "geometry": {"coordinates":[-84.09383800000001,35.924281],"type":"Point"}
}