{
  "type": "Feature",
  "properties": {
    "iso:country":"US",
    "sg:address":"123 N Church Ave",
    "sg:city":"Henderson",
    "sg:classifiers":[
        {
            "category":"Shopping",
            "type":"Retail Goods"
        }
    ],
    "sg:phone":"+1 731 989 2631",
    "sg:postcode":"38340",
    "sg:province":"TN",
    "sg:tags":[
        "hardware",
        "merchandise"
    ],
    "wof:name":"Farmers Supply",
    "wof:placetype":"venue"
},
  "geometry": {"coordinates":[-88.64501,35.437546],"type":"Point"}
}