{
  "type": "Feature",
  "properties": {
    "addr:full":"10643 Lakecove Way Knoxville TN 37922",
    "addr:housenumber":"10643",
    "addr:postcode":"37922",
    "addr:street":"Lakecove Way",
    "iso:country":"US",
    "sg:address":"10643 Lakecove Way",
    "sg:city":"Knoxville",
    "sg:classifiers":[
        {
            "category":"Professional",
            "subcategory":"Business Services",
            "type":"Services"
        }
    ],
    "sg:phone":"+1 865 777 0033",
    "sg:postcode":"37922",
    "sg:province":"TN",
    "wof:name":"Cynthia Yeager",
    "wof:placetype":"venue"
},
  "geometry": {"coordinates":[-84.11705000000001,35.862538],"type":"Point"}
}