{
  "type": "Feature",
  "properties": {
    "iso:country":"US",
    "sg:address":"1401 E 50th St",
    "sg:city":"Chattanooga",
    "sg:classifiers":[
        {
            "category":"Freight",
            "type":"Transportation"
        }
    ],
    "sg:phone":"+1 423 827 0780",
    "sg:postcode":"37407",
    "sg:province":"TN",
    "sg:tags":[
        "trucking"
    ],
    "wof:name":"J Norton Transport",
    "wof:placetype":"venue"
},
  "geometry": {"coordinates":[-85.292923,34.985851],"type":"Point"}
}