{
  "type": "Feature",
  "properties": {
    "iso:country":"US",
    "sg:address":"2922 Sidco Dr",
    "sg:city":"Nashville",
    "sg:classifiers":[
        {
            "category":"Organizations",
            "subcategory":"Labor Organization",
            "type":"Services"
        }
    ],
    "sg:phone":"+1 615 255 6000",
    "sg:postcode":"37204",
    "sg:province":"TN",
    "wof:name":"Bricklayers Union",
    "wof:placetype":"venue"
},
  "geometry": {"coordinates":[-86.755467,36.10888],"type":"Point"}
}