{
  "type": "Feature",
  "properties": {
    "addr:full":"1032 Bales St Gallatin TN 37066",
    "addr:housenumber":"1032",
    "addr:postcode":"37066",
    "addr:street":"Bales St",
    "iso:country":"US",
    "sg:address":"1032 Bales St",
    "sg:city":"Gallatin",
    "sg:classifiers":[
        {
            "category":"Retail",
            "subcategory":"Auto Repair",
            "type":"Services"
        }
    ],
    "sg:phone":"+1 615 452 3317",
    "sg:postcode":"37066",
    "sg:province":"TN",
    "sg:tags":[
        "general"
    ],
    "wof:name":"Gallatin Radiator Service Inc",
    "wof:placetype":"venue"
},
  "geometry": {"coordinates":[-86.43668599999999,36.371281],"type":"Point"}
}