{
  "type": "Feature",
  "properties": {
    "addr:full":"600 N Holtzclaw Ave Chattanooga TN 37404",
    "addr:housenumber":"600",
    "addr:postcode":"37404",
    "addr:street":"N Holtzclaw Ave",
    "iso:country":"US",
    "sg:address":"600 N Holtzclaw Ave",
    "sg:city":"Chattanooga",
    "sg:classifiers":[
        {
            "category":"Organizations",
            "subcategory":"Non-profit Organization",
            "type":"Services"
        }
    ],
    "sg:phone":"+1 423 622 4397",
    "sg:postcode":"37404",
    "sg:province":"TN",
    "wof:name":"Community Connections",
    "wof:placetype":"venue"
},
  "geometry": {"coordinates":[-85.277551,35.048131],"type":"Point"}
}