{
  "type": "Feature",
  "properties": {
    "iso:country":"US",
    "sg:address":"3263 Sharpe Ave",
    "sg:city":"Memphis",
    "sg:classifiers":[
        {
            "category":"Home & Garden",
            "subcategory":"Carpets & Floor Coverings",
            "type":"Retail Goods"
        }
    ],
    "sg:phone":"+1 901 744 6465",
    "sg:postcode":"38111",
    "sg:province":"TN",
    "sg:website":"www.bpidecosurf.com",
    "wof:name":"Building Plastics",
    "wof:placetype":"venue"
},
  "geometry": {"coordinates":[-89.95349299999999,35.086587],"type":"Point"}
}