{
  "type": "Feature",
  "properties": {
    "iso:country":"US",
    "sg:address":"425 Peach St",
    "sg:city":"Selmer",
    "sg:classifiers":[
        {
            "category":"Shopping",
            "subcategory":"Used Merchandise",
            "type":"Retail Goods"
        }
    ],
    "sg:phone":"+1 731 645 4211",
    "sg:postcode":"38375",
    "sg:province":"TN",
    "sg:tags":[
        "pawnbroker"
    ],
    "wof:name":"Selmer Pawn Shop",
    "wof:placetype":"venue"
},
  "geometry": {"coordinates":[-88.599431,35.177139],"type":"Point"}
}