{
  "type": "Feature",
  "properties": {
    "iso:country":"US",
    "sg:address":"6214 Enterprise Dr",
    "sg:city":"Knoxville",
    "sg:classifiers":[
        {
            "category":"Wholesale",
            "subcategory":"Painting Supplies",
            "type":"Manufacturing & Wholesale Goods"
        }
    ],
    "sg:phone":"+1 865 558 8450",
    "sg:postcode":"37909",
    "sg:province":"TN",
    "sg:tags":[
        "paint",
        "varnish"
    ],
    "wof:name":"Bsm Associates Inc",
    "wof:placetype":"venue"
},
  "geometry": {"coordinates":[-84.02257899999999,35.956607],"type":"Point"}
}