{
  "type": "Feature",
  "properties": {
    "addr:full":"2542 Ridgeway Rd Ste 3 Memphis TN 38119",
    "addr:housenumber":"2542",
    "addr:postcode":"38119",
    "addr:street":"Ridgeway Rd Ste 3",
    "iso:country":"US",
    "sg:address":"2542 Ridgeway Rd Ste 3",
    "sg:city":"Memphis",
    "sg:phone":"+1 901 685 1284",
    "sg:postcode":"38119",
    "sg:province":"TN",
    "wof:name":"Mobile Ultrasound Services Inc",
    "wof:placetype":"venue"
},
  "geometry": {"coordinates":[-89.858971,35.079097],"type":"Point"}
}