{
  "type": "Feature",
  "properties": {
    "addr:full":"5122 Summer Ave Memphis TN 38122",
    "addr:housenumber":"5122",
    "addr:postcode":"38122",
    "addr:street":"Summer Ave",
    "iso:country":"US",
    "sg:address":"5122 Summer Ave",
    "sg:city":"Memphis",
    "sg:classifiers":[
        {
            "category":"Restaurant",
            "type":"Food & Drink"
        }
    ],
    "sg:phone":"+1 901 682 0256",
    "sg:postcode":"38122",
    "sg:province":"TN",
    "sg:tags":[
        "preparation",
        "eating",
        "mfg"
    ],
    "wof:name":"China Noodle",
    "wof:placetype":"venue"
},
  "geometry": {"coordinates":[-89.890704,35.15136],"type":"Point"}
}