{
  "type": "Feature",
  "properties": {
    "iso:country":"US",
    "sg:address":"435 Wyndham Hall Way",
    "sg:city":"Knoxville",
    "sg:classifiers":[
        {
            "category":"Professional",
            "subcategory":"Business Services",
            "type":"Services"
        }
    ],
    "sg:phone":"+1 865 671 8858",
    "sg:postcode":"37934",
    "sg:province":"TN",
    "sg:tags":[
        "auctioneer"
    ],
    "sg:website":"www.rbauction.com",
    "wof:name":"Ritchie Bros Auctioneers",
    "wof:placetype":"venue"
},
  "geometry": {"coordinates":[-84.176588,35.890553],"type":"Point"}
}