{
  "type": "Feature",
  "properties": {
    "iso:country":"US",
    "sg:address":"106 Vulco Dr",
    "sg:city":"Hendersonville",
    "sg:classifiers":[
        {
            "category":"Building & Trades",
            "subcategory":"Construction",
            "type":"Services"
        }
    ],
    "sg:phone":"+1 615 824 7058",
    "sg:postcode":"37075",
    "sg:province":"TN",
    "wof:name":"Boones Construction",
    "wof:placetype":"venue"
},
  "geometry": {"coordinates":[-86.62410199999999,36.271067],"type":"Point"}
}