{
  "type": "Feature",
  "properties": {
    "addr:full":"262 Lebanon Church Rd Dresden TN 38225",
    "addr:housenumber":"262",
    "addr:postcode":"38225",
    "addr:street":"Lebanon Church Rd",
    "iso:country":"US",
    "sg:address":"262 Lebanon Church Rd",
    "sg:city":"Dresden",
    "sg:classifiers":[
        {
            "category":"Wholesale",
            "subcategory":"Machinery & Supplies",
            "type":"Manufacturing & Wholesale Goods"
        }
    ],
    "sg:phone":"+1 731 364 9662",
    "sg:postcode":"38225",
    "sg:province":"TN",
    "sg:tags":[
        "equipment",
        "construction",
        "parts",
        "mfg"
    ],
    "wof:name":"Woodard Equipment Service",
    "wof:placetype":"venue"
},
  "geometry": {"coordinates":[-88.64537,36.319971],"type":"Point"}
}