{
  "type": "Feature",
  "properties": {
    "iso:country":"US",
    "sg:address":"17120 Central Pike",
    "sg:city":"Lebanon",
    "sg:classifiers":[
        {
            "category":"Professional",
            "subcategory":"Accounting & Tax Preparation",
            "type":"Services"
        }
    ],
    "sg:phone":"+1 615 403 8381",
    "sg:postcode":"37090",
    "sg:province":"TN",
    "wof:name":"Kaye Couch Enterprises In",
    "wof:placetype":"venue"
},
  "geometry": {"coordinates":[-86.36919399999999,36.122347],"type":"Point"}
}