{
  "type": "Feature",
  "properties": {
    "iso:country":"US",
    "sg:address":"5063 Fort Henry Dr",
    "sg:city":"Kingsport",
    "sg:classifiers":[
        {
            "category":"Retail",
            "subcategory":"Auto Repair",
            "type":"Services"
        }
    ],
    "sg:phone":"+1 423 239 1794",
    "sg:postcode":"37663",
    "sg:province":"TN",
    "sg:tags":[
        "transmission"
    ],
    "wof:name":"Blevins Auto Care",
    "wof:placetype":"venue"
},
  "geometry": {"coordinates":[-82.479078,36.464179],"type":"Point"}
}