{
  "type": "Feature",
  "properties": {
    "iso:country":"US",
    "sg:address":"357 River Bluff Dr W",
    "sg:city":"Manchester",
    "sg:classifiers":[
        {
            "category":"Professional",
            "type":"Services"
        }
    ],
    "sg:phone":"+1 931 723 2759",
    "sg:postcode":"37355",
    "sg:province":"TN",
    "wof:name":"Beth Ezell",
    "wof:placetype":"venue"
},
  "geometry": {"coordinates":[-86.132178,35.477385],"type":"Point"}
}