{
  "type": "Feature",
  "properties": {
    "addr:full":"2659 Newport Hwy Sevierville TN 37876",
    "addr:housenumber":"2659",
    "addr:postcode":"37876",
    "addr:street":"Newport Hwy",
    "iso:country":"US",
    "sg:address":"2659 Newport Hwy",
    "sg:city":"Sevierville",
    "sg:classifiers":[
        {
            "category":"Shopping",
            "subcategory":"Clothing, Apparel, & Fashions",
            "type":"Retail Goods"
        }
    ],
    "sg:phone":"+1 865 429 3311",
    "sg:postcode":"37876",
    "sg:province":"TN",
    "wof:name":"Triple C Dance Barn",
    "wof:placetype":"venue"
},
  "geometry": {"coordinates":[-83.444356,35.889642],"type":"Point"}
}