{
  "type": "Feature",
  "properties": {
    "addr:full":"608 Depot St Jonesborough TN 37659",
    "addr:housenumber":"608",
    "addr:postcode":"37659",
    "addr:street":"Depot St",
    "iso:country":"US",
    "sg:address":"608 Depot St",
    "sg:city":"Jonesborough",
    "sg:classifiers":[
        {
            "category":"Building & Trades",
            "subcategory":"Construction",
            "type":"Services"
        }
    ],
    "sg:phone":"+1 423 753 1714",
    "sg:postcode":"37659",
    "sg:province":"TN",
    "sg:tags":[
        "grading",
        "contractor"
    ],
    "wof:name":"Highway Dept",
    "wof:placetype":"venue"
},
  "geometry": {"coordinates":[-82.47862600000001,36.289272],"type":"Point"}
}