{
  "type": "Feature",
  "properties": {
    "addr:full":"40 N Cedar Ave Cookeville TN 38501",
    "addr:housenumber":"40",
    "addr:postcode":"38501",
    "addr:street":"N Cedar Ave",
    "iso:country":"US",
    "sg:address":"40 N Cedar Ave",
    "sg:city":"Cookeville",
    "sg:classifiers":[
        {
            "category":"Autos & Motor Vehicles",
            "subcategory":"Automobile Sales",
            "type":"Retail Goods"
        }
    ],
    "sg:phone":"+1 931 526 5506",
    "sg:postcode":"38501",
    "sg:province":"TN",
    "sg:tags":[
        "car",
        "used",
        "dealer"
    ],
    "wof:name":"Big Bud's Auto Sales",
    "wof:placetype":"venue"
},
  "geometry": {"coordinates":[-85.50783,36.165009],"type":"Point"}
}