{
  "type": "Feature",
  "properties": {
    "addr:full":"3845 Airport Hwy Louisville TN 37777",
    "addr:housenumber":"3845",
    "addr:postcode":"37777",
    "addr:street":"Airport Hwy",
    "iso:country":"US",
    "sg:address":"3845 Airport Hwy",
    "sg:city":"Louisville",
    "sg:classifiers":[
        {
            "category":"Home & Garden",
            "subcategory":"Mobile Homes",
            "type":"Retail Goods"
        }
    ],
    "sg:phone":"+1 865 982 9825",
    "sg:postcode":"37777",
    "sg:province":"TN",
    "wof:name":"Horton Homes Of Alcoa",
    "wof:placetype":"venue"
},
  "geometry": {"coordinates":[-83.966307,35.844865],"type":"Point"}
}