{
  "type": "Feature",
  "properties": {
    "addr:full":"237 Antioch Church Rd Halls TN 38040",
    "addr:housenumber":"237",
    "addr:postcode":"38040",
    "addr:street":"Antioch Church Rd",
    "iso:country":"US",
    "sg:address":"237 Antioch Church Rd",
    "sg:city":"Halls",
    "sg:classifiers":[
        {
            "category":"Shopping",
            "subcategory":"Florist",
            "type":"Retail Goods"
        }
    ],
    "sg:phone":"+1 731 836 5757",
    "sg:postcode":"38040",
    "sg:province":"TN",
    "wof:name":"Halls Flower & Bridal Shop",
    "wof:placetype":"venue"
},
  "geometry": {"coordinates":[-89.479974,35.907846],"type":"Point"}
}