{
  "type": "Feature",
  "properties": {
    "iso:country":"US",
    "sg:address":"10530 State Hwy 128",
    "sg:city":"Savannah",
    "sg:classifiers":[
        {
            "category":"Retail",
            "subcategory":"Veterinary Services",
            "type":"Services"
        }
    ],
    "sg:phone":"+1 731 925 8120",
    "sg:postcode":"38372",
    "sg:province":"TN",
    "sg:tags":[
        "veterinarian"
    ],
    "wof:name":"Animal Hospital",
    "wof:placetype":"venue"
},
  "geometry": {"coordinates":[-88.244562,35.199585],"type":"Point"}
}