{
  "type": "Feature",
  "properties": {
    "iso:country":"US",
    "sg:address":"10028 W Emory Rd",
    "sg:city":"Knoxville",
    "sg:classifiers":[
        {
            "category":"Professional",
            "subcategory":"Business Services",
            "type":"Services"
        }
    ],
    "sg:phone":"+1 865 539 4985",
    "sg:postcode":"37931",
    "sg:province":"TN",
    "wof:name":"Donald Green & Associates",
    "wof:placetype":"venue"
},
  "geometry": {"coordinates":[-84.164551,35.98154],"type":"Point"}
}