{
  "type": "Feature",
  "properties": {
    "iso:country":"US",
    "sg:address":"227 Sharon Dr",
    "sg:city":"Pigeon Forge",
    "sg:classifiers":[
        {
            "category":"Professional",
            "type":"Services"
        }
    ],
    "sg:phone":"+1 865 453 7448",
    "sg:postcode":"37863",
    "sg:province":"TN",
    "sg:tags":[
        "establishment"
    ],
    "wof:name":"Bohanon Ora",
    "wof:placetype":"venue"
},
  "geometry": {"coordinates":[-83.571716,35.797849],"type":"Point"}
}