{
  "type": "Feature",
  "properties": {
    "iso:country":"US",
    "sg:address":"133 Mathes Cir",
    "sg:city":"Chuckey",
    "sg:classifiers":[
        {
            "category":"Wholesale",
            "subcategory":"Machinery & Supplies",
            "type":"Manufacturing & Wholesale Goods"
        }
    ],
    "sg:phone":"+1 423 257 4587",
    "sg:postcode":"37641",
    "sg:province":"TN",
    "sg:tags":[
        "equipment",
        "industrial"
    ],
    "wof:name":"Maint-Plus",
    "wof:placetype":"venue"
},
  "geometry": {"coordinates":[-82.601444,36.151248],"type":"Point"}
}