{
  "type": "Feature",
  "properties": {
    "iso:country":"US",
    "sg:address":"3575 Southern Ave",
    "sg:city":"Memphis",
    "sg:classifiers":[
        {
            "category":"Retail",
            "subcategory":"Auto Repair",
            "type":"Services"
        }
    ],
    "sg:phone":"+1 901 327 3584",
    "sg:postcode":"38111",
    "sg:province":"TN",
    "wof:name":"Baker Auto Service Inc",
    "wof:placetype":"venue"
},
  "geometry": {"coordinates":[-89.944042,35.115563],"type":"Point"}
}