{
  "type": "Feature",
  "properties": {
    "addr:full":"9512 Stringtown Rd Strawberry Plns TN 37871",
    "addr:housenumber":"9512",
    "addr:postcode":"37871",
    "addr:street":"Stringtown Rd",
    "iso:country":"US",
    "sg:address":"9512 Stringtown Rd",
    "sg:city":"Strawberry Plns",
    "sg:classifiers":[
        {
            "category":"Retail",
            "subcategory":"Auto Repair",
            "type":"Services"
        }
    ],
    "sg:phone":"+1 865 933 2542",
    "sg:postcode":"37871",
    "sg:province":"TN",
    "sg:tags":[
        "shop",
        "body",
        "automobile",
        "general",
        "automotive",
        "painting"
    ],
    "wof:name":"Griffey's Body Shop",
    "wof:placetype":"venue"
},
  "geometry": {"coordinates":[-83.696639,36.025662],"type":"Point"}
}