{
  "type": "Feature",
  "properties": {
    "addr:full":"411 Bushnell St Nashville TN 37206",
    "addr:housenumber":"411",
    "addr:postcode":"37206",
    "addr:street":"Bushnell St",
    "iso:country":"US",
    "sg:address":"411 Bushnell St",
    "sg:city":"Nashville",
    "sg:classifiers":[
        {
            "category":"Manufacturing",
            "subcategory":"Signs",
            "type":"Manufacturing & Wholesale Goods"
        }
    ],
    "sg:phone":"+1 615 228 3522",
    "sg:postcode":"37206",
    "sg:province":"TN",
    "sg:tags":[
        "specialty",
        "mfg"
    ],
    "wof:name":"Artrageous Signs & Design",
    "wof:placetype":"venue"
},
  "geometry": {"coordinates":[-86.734695,36.180567],"type":"Point"}
}