{
  "type": "Feature",
  "properties": {
    "iso:country":"US",
    "sg:address":"808 Hatcher Ln",
    "sg:city":"Columbia",
    "sg:classifiers":[
        {
            "category":"Health Services",
            "subcategory":"Doctor",
            "type":"Services"
        }
    ],
    "sg:phone":"+1 931 381 3975",
    "sg:postcode":"38401",
    "sg:province":"TN",
    "sg:tags":[
        "physician",
        "surgeon"
    ],
    "wof:name":"Columbia Surgery Group",
    "wof:placetype":"venue"
},
  "geometry": {"coordinates":[-87.052216,35.602902],"type":"Point"}
}