{
  "type": "Feature",
  "properties": {
    "iso:country":"US",
    "sg:address":"2014 US Hwy 45W Byp",
    "sg:city":"Trenton",
    "sg:classifiers":[
        {
            "category":"Food & Beverages",
            "subcategory":"Liquor & Beverages",
            "type":"Retail Goods"
        },
        {
            "category":"Shopping",
            "subcategory":"Gifts & Souvenirs",
            "type":"Retail Goods"
        }
    ],
    "sg:phone":"+1 731 855 0339",
    "sg:postcode":"38382",
    "sg:province":"TN",
    "sg:tags":[
        "party",
        "alcoholic",
        "supply"
    ],
    "wof:name":"Peg & Tom's Party Shop",
    "wof:placetype":"venue"
},
  "geometry": {"coordinates":[-88.930498,35.96838],"type":"Point"}
}