{
  "type": "Feature",
  "properties": {
    "addr:full":"608 Madison St Shelbyville TN 37160",
    "addr:housenumber":"608",
    "addr:postcode":"37160",
    "addr:street":"Madison St",
    "iso:country":"US",
    "sg:address":"608 Madison St",
    "sg:city":"Shelbyville",
    "sg:classifiers":[
        {
            "category":"Professional",
            "type":"Services"
        },
        {
            "category":"Restaurant",
            "type":"Food & Drink"
        }
    ],
    "sg:phone":"+1 931 684 2345",
    "sg:postcode":"37160",
    "sg:province":"TN",
    "sg:tags":[
        "establishment"
    ],
    "wof:name":"Joe's Fine Dinning",
    "wof:placetype":"venue"
},
  "geometry": {"coordinates":[-86.450945,35.487932],"type":"Point"}
}