{
  "type": "Feature",
  "properties": {
    "iso:country":"US",
    "sg:address":"1201 Oak Ridge Tpke",
    "sg:city":"Oak Ridge",
    "sg:classifiers":[
        {
            "category":"Organizations",
            "subcategory":"Membership Organization",
            "type":"Services"
        },
        {
            "category":"Organizations",
            "subcategory":"Professional Association",
            "type":"Services"
        }
    ],
    "sg:phone":"+1 865 483 3047",
    "sg:postcode":"37830",
    "sg:province":"TN",
    "wof:name":"East TN Economic Council",
    "wof:placetype":"venue"
},
  "geometry": {"coordinates":[-84.249529,36.017721],"type":"Point"}
}