{
  "type": "Feature",
  "properties": {
    "addr:full":"170 N Ocoee St Cleveland TN 37311",
    "addr:housenumber":"170",
    "addr:postcode":"37311",
    "addr:street":"N Ocoee St",
    "iso:country":"US",
    "sg:address":"170 N Ocoee St",
    "sg:city":"Cleveland",
    "sg:classifiers":[
        {
            "category":"Restaurant",
            "type":"Food & Drink"
        }
    ],
    "sg:phone":"+1 423 479 6331",
    "sg:postcode":"37311",
    "sg:province":"TN",
    "sg:tags":[
        "eating"
    ],
    "wof:name":"Diamond Lil's Restaurant",
    "wof:placetype":"venue"
},
  "geometry": {"coordinates":[-84.875231,35.160312],"type":"Point"}
}