{
  "type": "Feature",
  "properties": {
    "iso:country":"US",
    "sg:address":"1648 Sunset Rd",
    "sg:city":"Brentwood",
    "sg:classifiers":[
        {
            "category":"Building & Trades",
            "subcategory":"Construction",
            "type":"Services"
        }
    ],
    "sg:phone":"+1 615 776 3415",
    "sg:postcode":"37027",
    "sg:province":"TN",
    "sg:tags":[
        "house"
    ],
    "wof:name":"Legacy Renovation LLC",
    "wof:placetype":"venue"
},
  "geometry": {"coordinates":[-86.689238,35.962545],"type":"Point"}
}