{
  "type": "Feature",
  "properties": {
    "iso:country":"US",
    "sg:address":"739 NW Broad St",
    "sg:city":"Murfreesboro",
    "sg:classifiers":[
        {
            "category":"Home & Garden",
            "subcategory":"Building Materials",
            "type":"Retail Goods"
        }
    ],
    "sg:phone":"+1 615 893 1515",
    "sg:postcode":"37129",
    "sg:province":"TN",
    "sg:website":"www.haynesbroslumber.com",
    "wof:name":"Haynes Brothers Lumber Co",
    "wof:placetype":"venue"
},
  "geometry": {"coordinates":[-86.392618,35.84256],"type":"Point"}
}