{
  "type": "Feature",
  "properties": {
    "iso:country":"US",
    "sg:address":"3112 Kendrick Rd",
    "sg:city":"Corinth",
    "sg:classifiers":[
        {
            "category":"Social Services",
            "subcategory":"Child Care",
            "type":"Services"
        }
    ],
    "sg:phone":"+1 662 286 8687",
    "sg:postcode":"38834",
    "sg:province":"TN",
    "sg:tags":[
        "school",
        "day"
    ],
    "wof:name":"ABC Learning Center Inc",
    "wof:placetype":"venue"
},
  "geometry": {"coordinates":[-88.489587,34.945235],"type":"Point"}
}