{
  "type": "Feature",
  "properties": {
    "addr:full":"1406 Aste St Memphis TN 38106",
    "addr:housenumber":"1406",
    "addr:postcode":"38106",
    "addr:street":"Aste St",
    "iso:country":"US",
    "sg:address":"1406 Aste St",
    "sg:city":"Memphis",
    "sg:classifiers":[
        {
            "category":"Organizations",
            "subcategory":"Religious Organization",
            "type":"Services"
        }
    ],
    "sg:phone":"+1 901 948 9863",
    "sg:postcode":"38106",
    "sg:province":"TN",
    "sg:tags":[
        "place",
        "worship",
        "church"
    ],
    "sg:website":"http://www.watchtower.org",
    "wof:name":"Jehovah's Witnesses",
    "wof:placetype":"venue"
},
  "geometry": {"coordinates":[-90.048351,35.108758],"type":"Point"}
}