{
  "type": "Feature",
  "properties": {
    "iso:country":"US",
    "sg:address":"955 S 4th St",
    "sg:city":"Memphis",
    "sg:classifiers":[
        {
            "category":"Organizations",
            "subcategory":"Religious Organization",
            "type":"Services"
        }
    ],
    "sg:phone":"+1 901 774 6992",
    "sg:postcode":"38126",
    "sg:province":"TN",
    "wof:name":"New Slem Mssnary Baptst Church",
    "wof:placetype":"venue"
},
  "geometry": {"coordinates":[-90.05114500000001,35.121026],"type":"Point"}
}