{
  "type": "Feature",
  "properties": {
    "iso:country":"US",
    "sg:address":"4210 Raven Dr",
    "sg:city":"Knoxville",
    "sg:classifiers":[
        {
            "category":"Organizations",
            "subcategory":"Community Association",
            "type":"Services"
        }
    ],
    "sg:phone":"+1 865 687 4691",
    "sg:postcode":"37918",
    "sg:province":"TN",
    "wof:name":"International Assoc of LI",
    "wof:placetype":"venue"
},
  "geometry": {"coordinates":[-83.90898,36.048929],"type":"Point"}
}