{
  "type": "Feature",
  "properties": {
    "addr:full":"4505 Cottonwood Rd Memphis TN 38118",
    "addr:housenumber":"4505",
    "addr:postcode":"38118",
    "addr:street":"Cottonwood Rd",
    "iso:country":"US",
    "sg:address":"4505 Cottonwood Rd",
    "sg:city":"Memphis",
    "sg:classifiers":[
        {
            "category":"Professional",
            "subcategory":"Business Services",
            "type":"Services"
        }
    ],
    "sg:phone":"+1 901 363 3945",
    "sg:postcode":"38118",
    "sg:province":"TN",
    "wof:name":"Blade Commercial Service",
    "wof:placetype":"venue"
},
  "geometry": {"coordinates":[-89.911784,35.069287],"type":"Point"}
}