{
  "type": "Feature",
  "properties": {
    "addr:full":"505 Horton St Decherd TN 37324",
    "addr:housenumber":"505",
    "addr:postcode":"37324",
    "addr:street":"Horton St",
    "iso:country":"US",
    "sg:address":"505 Horton St",
    "sg:city":"Decherd",
    "sg:classifiers":[
        {
            "category":"Organizations",
            "subcategory":"Religious Organization",
            "type":"Services"
        }
    ],
    "sg:phone":"+1 931 962 8596",
    "sg:postcode":"37324",
    "sg:province":"TN",
    "sg:tags":[
        "church"
    ],
    "wof:name":"First Seventh Day Adventist",
    "wof:placetype":"venue"
},
  "geometry": {"coordinates":[-86.078457,35.216036],"type":"Point"}
}