{
  "type": "Feature",
  "properties": {
    "iso:country":"US",
    "sg:address":"629 Glades Rd",
    "sg:city":"Gatlinburg",
    "sg:classifiers":[
        {
            "category":"Travel",
            "subcategory":"Hotels & Motels",
            "type":"Entertainment"
        }
    ],
    "sg:phone":"+1 865 436 8435",
    "sg:postcode":"37738",
    "sg:province":"TN",
    "sg:tags":[
        "operation",
        "chalet",
        "rental",
        "cabin"
    ],
    "wof:name":"Pine Mountain Rentals",
    "wof:placetype":"venue"
},
  "geometry": {"coordinates":[-83.45715199999999,35.743328],"type":"Point"}
}