{
  "type": "Feature",
  "properties": {
    "iso:country":"US",
    "sg:address":"1673 Hicks Hollow Rd",
    "sg:city":"Westmoreland",
    "sg:classifiers":[
        {
            "category":"Building & Trades",
            "subcategory":"Electrical",
            "type":"Services"
        }
    ],
    "sg:phone":"+1 615 644 5016",
    "sg:postcode":"37186",
    "sg:province":"TN",
    "sg:tags":[
        "electric",
        "contractor"
    ],
    "wof:name":"Westside Heat & Air",
    "wof:placetype":"venue"
},
  "geometry": {"coordinates":[-86.205662,36.511454],"type":"Point"}
}