{
  "type": "Feature",
  "properties": {
    "iso:country":"US",
    "sg:address":"625 W Main St",
    "sg:city":"Murfreesboro",
    "sg:classifiers":[
        {
            "category":"Health Services",
            "subcategory":"Medical Lab",
            "type":"Services"
        }
    ],
    "sg:phone":"+1 615 896 5223",
    "sg:postcode":"37129",
    "sg:province":"TN",
    "sg:tags":[
        "resonance",
        "magnetic",
        "imaging"
    ],
    "wof:name":"Doc Mart",
    "wof:placetype":"venue"
},
  "geometry": {"coordinates":[-86.400694,35.84682],"type":"Point"}
}