{
  "type": "Feature",
  "properties": {
    "addr:full":"719 Arbor Knoll Blvd Antioch TN 37013",
    "addr:housenumber":"719",
    "addr:postcode":"37013",
    "addr:street":"Arbor Knoll Blvd",
    "iso:country":"US",
    "sg:address":"719 Arbor Knoll Blvd",
    "sg:city":"Antioch",
    "sg:classifiers":[
        {
            "category":"Building & Trades",
            "subcategory":"Construction",
            "type":"Services"
        }
    ],
    "sg:phone":"+1 615 566 3153",
    "sg:postcode":"37013",
    "sg:province":"TN",
    "sg:tags":[
        "painter"
    ],
    "wof:name":"Jorge's Painting",
    "wof:placetype":"venue"
},
  "geometry": {"coordinates":[-86.667947,36.041718],"type":"Point"}
}