{
  "type": "Feature",
  "properties": {
    "addr:full":"4701 E Emory Rd Knoxville TN 37938",
    "addr:housenumber":"4701",
    "addr:postcode":"37938",
    "addr:street":"E Emory Rd",
    "iso:country":"US",
    "sg:address":"4701 E Emory Rd",
    "sg:city":"Knoxville",
    "sg:classifiers":[
        {
            "category":"Communications",
            "subcategory":"Film & Video Production",
            "type":"Services"
        }
    ],
    "sg:phone":"+1 865 922 4050",
    "sg:postcode":"37938",
    "sg:province":"TN",
    "sg:tags":[
        "taping"
    ],
    "wof:name":"Memory Graphics",
    "wof:placetype":"venue"
},
  "geometry": {"coordinates":[-83.91606,36.087538],"type":"Point"}
}