{
  "type": "Feature",
  "properties": {
    "addr:full":"301 Lake Dr Somerville TN 38068",
    "addr:housenumber":"301",
    "addr:postcode":"38068",
    "addr:street":"Lake Dr",
    "iso:country":"US",
    "sg:address":"301 Lake Dr",
    "sg:city":"Somerville",
    "sg:classifiers":[
        {
            "category":"Professional",
            "type":"Services"
        }
    ],
    "sg:phone":"+1 901 465 8332",
    "sg:postcode":"38068",
    "sg:province":"TN",
    "wof:name":"Willowbrook VNA",
    "wof:placetype":"venue"
},
  "geometry": {"coordinates":[-89.36366700000001,35.246247],"type":"Point"}
}