{
  "type": "Feature",
  "properties": {
    "iso:country":"US",
    "sg:address":"3321 Kinneys Rd",
    "sg:city":"Cedar Hill",
    "sg:classifiers":[
        {
            "category":"Building & Trades",
            "subcategory":"Construction",
            "type":"Services"
        }
    ],
    "sg:phone":"+1 615 696 2373",
    "sg:postcode":"37032",
    "sg:province":"TN",
    "sg:tags":[
        "general",
        "contractor"
    ],
    "wof:name":"Steve Powell Construction Co",
    "wof:placetype":"venue"
},
  "geometry": {"coordinates":[-86.97823200000001,36.533612],"type":"Point"}
}