{
  "type": "Feature",
  "properties": {
    "iso:country":"US",
    "sg:address":"5727 Lee Hwy",
    "sg:city":"Chattanooga",
    "sg:classifiers":[
        {
            "category":"Bars & Pubs",
            "type":"Food & Drink"
        }
    ],
    "sg:phone":"+1 423 855 1893",
    "sg:postcode":"37421",
    "sg:province":"TN",
    "sg:tags":[
        "lounge",
        "cocktail"
    ],
    "wof:name":"Cabaret Royale Supper Club",
    "wof:placetype":"venue"
},
  "geometry": {"coordinates":[-85.204047,35.018931],"type":"Point"}
}