{
  "type": "Feature",
  "properties": {
    "iso:country":"US",
    "sg:address":"24 White Bridge Pike",
    "sg:city":"Nashville",
    "sg:classifiers":[
        {
            "category":"Health Services",
            "subcategory":"Health Practitioner",
            "type":"Services"
        }
    ],
    "sg:phone":"+1 615 352 0011",
    "sg:postcode":"37205",
    "sg:province":"TN",
    "wof:name":"Aesthetic Center",
    "wof:placetype":"venue"
},
  "geometry": {"coordinates":[-86.854569,36.12945],"type":"Point"}
}