{
  "type": "Feature",
  "properties": {
    "addr:full":"180 Churchill Dr Sparta TN 38583",
    "addr:housenumber":"180",
    "addr:postcode":"38583",
    "addr:street":"Churchill Dr",
    "iso:country":"US",
    "sg:address":"180 Churchill Dr",
    "sg:city":"Sparta",
    "sg:classifiers":[
        {
            "category":"Home & Garden",
            "subcategory":"Building Materials",
            "type":"Retail Goods"
        }
    ],
    "sg:phone":"+1 931 836 2645",
    "sg:postcode":"38583",
    "sg:province":"TN",
    "wof:name":"Color Concepts",
    "wof:placetype":"venue"
},
  "geometry": {"coordinates":[-85.481559,35.938704],"type":"Point"}
}