{
  "type": "Feature",
  "properties": {
    "iso:country":"US",
    "sg:address":"1973 Lee Hwy",
    "sg:city":"Bristol",
    "sg:classifiers":[
        {
            "category":"Travel",
            "subcategory":"Hotels & Motels",
            "type":"Entertainment"
        }
    ],
    "sg:phone":"+1 276 669 2178",
    "sg:postcode":"24201",
    "sg:province":"TN",
    "sg:tags":[
        "operation"
    ],
    "wof:name":"Budget Inn",
    "wof:placetype":"venue"
},
  "geometry": {"coordinates":[-82.15855500000001,36.625217],"type":"Point"}
}