{
  "type": "Feature",
  "properties": {
    "addr:full":"927 Signal Rd Signal Mountain TN 37377",
    "addr:housenumber":"927",
    "addr:postcode":"37377",
    "addr:street":"Signal Rd",
    "iso:country":"US",
    "sg:address":"927 Signal Rd",
    "sg:city":"Signal Mountain",
    "sg:classifiers":[
        {
            "category":"Building & Trades",
            "subcategory":"Landscaping Services",
            "type":"Services"
        }
    ],
    "sg:phone":"+1 423 886 4439",
    "sg:postcode":"37377",
    "sg:province":"TN",
    "sg:tags":[
        "irrigation",
        "landscape"
    ],
    "wof:name":"Joshuas Ldscpg & Irrigation",
    "wof:placetype":"venue"
},
  "geometry": {"coordinates":[-85.33918300000001,35.122979],"type":"Point"}
}