{
  "type": "Feature",
  "properties": {
    "iso:country":"US",
    "sg:address":"322 N Front St",
    "sg:city":"Murfreesboro",
    "sg:classifiers":[
        {
            "category":"Education",
            "subcategory":"Special Training",
            "type":"Public Place"
        }
    ],
    "sg:phone":"+1 615 867 3928",
    "sg:postcode":"37130",
    "sg:province":"TN",
    "wof:name":"Boro School Of Martial Arts",
    "wof:placetype":"venue"
},
  "geometry": {"coordinates":[-86.394564,35.849203],"type":"Point"}
}