{
  "type": "Feature",
  "properties": {
    "iso:country":"US",
    "sg:address":"1713 N Hwy 92",
    "sg:city":"Jefferson City",
    "sg:classifiers":[
        {
            "category":"Personal",
            "type":"Services"
        }
    ],
    "sg:phone":"+1 865 471 0140",
    "sg:postcode":"37760",
    "sg:province":"TN",
    "wof:name":"Sunburst Tanning",
    "wof:placetype":"venue"
},
  "geometry": {"coordinates":[-83.506964,36.120258],"type":"Point"}
}