{
  "type": "Feature",
  "properties": {
    "iso:country":"US",
    "sg:address":"5291 Mendenhall Park Pl",
    "sg:city":"Memphis",
    "sg:classifiers":[
        {
            "category":"Building & Trades",
            "subcategory":"Cleaning & Sanitation",
            "type":"Services"
        }
    ],
    "sg:phone":"+1 901 685 9665",
    "sg:postcode":"38115",
    "sg:province":"TN",
    "sg:tags":[
        "janitor"
    ],
    "sg:website":"www.kimcocorp.com",
    "wof:name":"Kimco Corp",
    "wof:placetype":"venue"
},
  "geometry": {"coordinates":[-89.887608,35.043526],"type":"Point"}
}