{
  "type": "Feature",
  "properties": {
    "addr:full":"4245 Cherry Center Dr Memphis TN 38118",
    "addr:housenumber":"4245",
    "addr:postcode":"38118",
    "addr:street":"Cherry Center Dr",
    "iso:country":"US",
    "sg:address":"4245 Cherry Center Dr",
    "sg:city":"Memphis",
    "sg:classifiers":[
        {
            "category":"Insurance",
            "subcategory":"Insurance Agent",
            "type":"Services"
        }
    ],
    "sg:phone":"+1 901 565 0050",
    "sg:postcode":"38118",
    "sg:province":"TN",
    "wof:name":"Allstate Insurance Co",
    "wof:placetype":"venue"
},
  "geometry": {"coordinates":[-89.920456,35.073361],"type":"Point"}
}