{
  "type": "Feature",
  "properties": {
    "addr:full":"517 Sanbyrn Dr Murfreesboro TN 37130",
    "addr:housenumber":"517",
    "addr:postcode":"37130",
    "addr:street":"Sanbyrn Dr",
    "iso:country":"US",
    "sg:address":"517 Sanbyrn Dr",
    "sg:city":"Murfreesboro",
    "sg:classifiers":[
        {
            "category":"Organizations",
            "subcategory":"Religious Organization",
            "type":"Services"
        }
    ],
    "sg:phone":"+1 615 896 9272",
    "sg:postcode":"37130",
    "sg:province":"TN",
    "sg:website":"www.1st-church.com",
    "wof:name":"First Church Of God",
    "wof:placetype":"venue"
},
  "geometry": {"coordinates":[-86.382948,35.82861],"type":"Point"}
}