{
  "type": "Feature",
  "properties": {
    "addr:full":"250 Venture Cir Nashville TN 37228",
    "addr:housenumber":"250",
    "addr:postcode":"37228",
    "addr:street":"Venture Cir",
    "iso:country":"US",
    "sg:address":"250 Venture Cir",
    "sg:city":"Nashville",
    "sg:classifiers":[
        {
            "category":"Health Services",
            "subcategory":"Clinic",
            "type":"Services"
        }
    ],
    "sg:phone":"+1 615 780 2538",
    "sg:postcode":"37228",
    "sg:province":"TN",
    "wof:name":"Success By Six",
    "wof:placetype":"venue"
},
  "geometry": {"coordinates":[-86.795602,36.195912],"type":"Point"}
}