{
  "type": "Feature",
  "properties": {
    "iso:country":"US",
    "sg:address":"4608 Hixson Pike",
    "sg:city":"Hixson",
    "sg:classifiers":[
        {
            "category":"Shopping",
            "subcategory":"Computers & Home Electronics",
            "type":"Retail Goods"
        }
    ],
    "sg:phone":"+1 423 870 1073",
    "sg:postcode":"37343",
    "sg:province":"TN",
    "sg:tags":[
        "equipment",
        "dealer"
    ],
    "wof:name":"American Computer Dist",
    "wof:placetype":"venue"
},
  "geometry": {"coordinates":[-85.248198,35.122797],"type":"Point"}
}