{
  "type": "Feature",
  "properties": {
    "iso:country":"US",
    "sg:address":"2391 Lamar Ave",
    "sg:city":"Memphis",
    "sg:classifiers":[
        {
            "category":"Shopping",
            "subcategory":"Clothing, Apparel, & Fashions",
            "type":"Retail Goods"
        }
    ],
    "sg:phone":"+1 901 745 5437",
    "sg:postcode":"38114",
    "sg:province":"TN",
    "sg:tags":[
        "infant",
        "wear"
    ],
    "wof:name":"Discount Kids Wear",
    "wof:placetype":"venue"
},
  "geometry": {"coordinates":[-89.981618,35.102662],"type":"Point"}
}