{
  "type": "Feature",
  "properties": {
    "iso:country":"US",
    "sg:address":"323 Ridgeland Dr",
    "sg:city":"Clarksville",
    "sg:classifiers":[
        {
            "category":"Social Services",
            "subcategory":"Child Care",
            "type":"Services"
        }
    ],
    "sg:phone":"+1 931 552 7295",
    "sg:postcode":"37043",
    "sg:province":"TN",
    "sg:tags":[
        "day"
    ],
    "wof:name":"Ms Shamona's Home Daycare",
    "wof:placetype":"venue"
},
  "geometry": {"coordinates":[-87.319788,36.546392],"type":"Point"}
}