{
  "type": "Feature",
  "properties": {
    "iso:country":"US",
    "sg:address":"128 N Military St",
    "sg:city":"Loretto",
    "sg:classifiers":[
        {
            "category":"Insurance",
            "subcategory":"Insurance Agent",
            "type":"Services"
        }
    ],
    "sg:phone":"+1 931 853 7126",
    "sg:postcode":"38469",
    "sg:province":"TN",
    "wof:name":"Loretto Insurance Svc",
    "wof:placetype":"venue"
},
  "geometry": {"coordinates":[-87.433887,35.081015],"type":"Point"}
}