{
  "type": "Feature",
  "properties": {
    "addr:full":"555 Church St Nashville TN 37219",
    "addr:housenumber":"555",
    "addr:postcode":"37219",
    "addr:street":"Church St",
    "iso:country":"US",
    "sg:address":"555 Church St",
    "sg:city":"Nashville",
    "sg:classifiers":[
        {
            "category":"Retail",
            "subcategory":"Laundry & Dry Cleaning",
            "type":"Services"
        }
    ],
    "sg:phone":"+1 615 252 2273",
    "sg:postcode":"37219",
    "sg:province":"TN",
    "sg:tags":[
        "cleaner",
        "upholstery",
        "rug",
        "carpet"
    ],
    "wof:name":"Complete Carpet Care",
    "wof:placetype":"venue"
},
  "geometry": {"coordinates":[-86.781085,36.162756],"type":"Point"}
}