{
  "type": "Feature",
  "properties": {
    "iso:country":"US",
    "sg:address":"604 Pinecrest Dr",
    "sg:city":"Corinth",
    "sg:classifiers":[
        {
            "category":"Wholesale",
            "subcategory":"Groceries",
            "type":"Manufacturing & Wholesale Goods"
        }
    ],
    "sg:phone":"+1 662 287 1101",
    "sg:postcode":"38834",
    "sg:province":"TN",
    "sg:tags":[
        "baker"
    ],
    "wof:name":"Lewis Brothers Bakeries Inc",
    "wof:placetype":"venue"
},
  "geometry": {"coordinates":[-88.495425,34.947942],"type":"Point"}
}