{
  "type": "Feature",
  "properties": {
    "addr:full":"313 Maple St Athens TN 37303",
    "addr:housenumber":"313",
    "addr:postcode":"37303",
    "addr:street":"Maple St",
    "iso:country":"US",
    "sg:address":"313 Maple St",
    "sg:city":"Athens",
    "sg:classifiers":[
        {
            "category":"Shopping",
            "subcategory":"Computers & Home Electronics",
            "type":"Retail Goods"
        }
    ],
    "sg:phone":"+1 423 745 5756",
    "sg:postcode":"37303",
    "sg:province":"TN",
    "sg:tags":[
        "equipment",
        "dealer"
    ],
    "wof:name":"Compnet Internet & Computer",
    "wof:placetype":"venue"
},
  "geometry": {"coordinates":[-84.613218,35.44824],"type":"Point"}
}