{
  "type": "Feature",
  "properties": {
    "iso:country":"US",
    "sg:address":"3204 Clio Ave",
    "sg:city":"Chattanooga",
    "sg:classifiers":[
        {
            "category":"Organizations",
            "subcategory":"Religious Organization",
            "type":"Services"
        }
    ],
    "sg:phone":"+1 423 622 1913",
    "sg:postcode":"37407",
    "sg:province":"TN",
    "wof:name":"Temple Baptist Church",
    "wof:placetype":"venue"
},
  "geometry": {"coordinates":[-85.29181,35.006174],"type":"Point"}
}