{
  "type": "Feature",
  "properties": {
    "iso:country":"US",
    "sg:address":"3398 Thomas St",
    "sg:city":"Memphis",
    "sg:classifiers":[
        {
            "category":"Autos & Motor Vehicles",
            "subcategory":"Auto Supplies",
            "type":"Retail Goods"
        }
    ],
    "sg:phone":"+1 901 354 7737",
    "sg:postcode":"38127",
    "sg:province":"TN",
    "sg:tags":[
        "tire"
    ],
    "wof:name":"North Tire",
    "wof:placetype":"venue"
},
  "geometry": {"coordinates":[-90.030154,35.216908],"type":"Point"}
}