{
  "type": "Feature",
  "properties": {
    "iso:country":"US",
    "sg:address":"2101 Portland Ave",
    "sg:city":"Nashville",
    "sg:classifiers":[
        {
            "category":"Real Estate",
            "subcategory":"Real Estate Operator",
            "type":"Services"
        }
    ],
    "sg:phone":"+1 615 383 5453",
    "sg:postcode":"37212",
    "sg:province":"TN",
    "sg:tags":[
        "apartment"
    ],
    "sg:website":"www.trammelcrow.com",
    "wof:name":"Trammell Crow Co",
    "wof:placetype":"venue"
},
  "geometry": {"coordinates":[-86.80200499999999,36.133289],"type":"Point"}
}