{
  "type": "Feature",
  "properties": {
    "iso:country":"US",
    "sg:address":"1715 Cumberland Ave",
    "sg:city":"Knoxville",
    "sg:classifiers":[
        {
            "category":"Professional",
            "subcategory":"Advertising",
            "type":"Services"
        }
    ],
    "sg:phone":"+1 865 523 8213",
    "sg:postcode":"37916",
    "sg:province":"TN",
    "sg:tags":[
        "mailing",
        "shipping"
    ],
    "wof:name":"Fed Ex Kinko's Ofc & Print Ctr",
    "wof:placetype":"venue"
},
  "geometry": {"coordinates":[-83.933194,35.956363],"type":"Point"}
}