{
  "type": "Feature",
  "properties": {
    "addr:full":"760 E Main St Hendersonville TN 37075",
    "addr:housenumber":"760",
    "addr:postcode":"37075",
    "addr:street":"E Main St",
    "iso:country":"US",
    "sg:address":"760 E Main St",
    "sg:city":"Hendersonville",
    "sg:classifiers":[
        {
            "category":"Shopping",
            "type":"Retail Goods"
        }
    ],
    "sg:phone":"+1 615 826 9880",
    "sg:postcode":"37075",
    "sg:province":"TN",
    "sg:tags":[
        "art",
        "gallery",
        "merchandise",
        "dealer"
    ],
    "wof:name":"All About Art Gallery Frame Sp",
    "wof:placetype":"venue"
},
  "geometry": {"coordinates":[-86.559939,36.328002],"type":"Point"}
}