{
  "type": "Feature",
  "properties": {
    "iso:country":"US",
    "sg:address":"4641 Spencer Hale Rd",
    "sg:city":"Morristown",
    "sg:classifiers":[
        {
            "category":"Local Transit",
            "type":"Transportation"
        }
    ],
    "sg:phone":"+1 423 587 5710",
    "sg:postcode":"37813",
    "sg:province":"TN",
    "sg:tags":[
        "passenger"
    ],
    "wof:name":"Hale Trans",
    "wof:placetype":"venue"
},
  "geometry": {"coordinates":[-83.261447,36.156599],"type":"Point"}
}