{
  "type": "Feature",
  "properties": {
    "addr:full":"203 E Main St Woodbury TN 37190",
    "addr:housenumber":"203",
    "addr:postcode":"37190",
    "addr:street":"E Main St",
    "iso:country":"US",
    "sg:address":"203 E Main St",
    "sg:city":"Woodbury",
    "sg:classifiers":[
        {
            "category":"Autos & Motor Vehicles",
            "subcategory":"Auto Supplies",
            "type":"Retail Goods"
        }
    ],
    "sg:phone":"+1 615 563 5524",
    "sg:postcode":"37190",
    "sg:province":"TN",
    "sg:tags":[
        "tire"
    ],
    "wof:name":"Freedom Tires",
    "wof:placetype":"venue"
},
  "geometry": {"coordinates":[-86.067065,35.82735],"type":"Point"}
}