{
  "type": "Feature",
  "properties": {
    "iso:country":"US",
    "sg:address":"625 Walnut St",
    "sg:city":"Chattanooga",
    "sg:classifiers":[
        {
            "category":"Sports & Exercise",
            "subcategory":"Golf",
            "type":"Entertainment"
        }
    ],
    "sg:phone":"+1 423 266 7277",
    "sg:postcode":"37402",
    "sg:province":"TN",
    "sg:tags":[
        "course"
    ],
    "wof:name":"Chattanooga Classic Tournament",
    "wof:placetype":"venue"
},
  "geometry": {"coordinates":[-85.307496,35.048746],"type":"Point"}
}