{
  "type": "Feature",
  "properties": {
    "addr:full":"4361 Woodbury Hwy Manchester TN 37355",
    "addr:housenumber":"4361",
    "addr:postcode":"37355",
    "addr:street":"Woodbury Hwy",
    "iso:country":"US",
    "sg:address":"4361 Woodbury Hwy",
    "sg:city":"Manchester",
    "sg:classifiers":[
        {
            "category":"Organizations",
            "subcategory":"Religious Organization",
            "type":"Services"
        }
    ],
    "sg:phone":"+1 931 723 1003",
    "sg:postcode":"37355",
    "sg:province":"TN",
    "wof:name":"Hillcrest Baptist Church",
    "wof:placetype":"venue"
},
  "geometry": {"coordinates":[-86.08233799999999,35.549003],"type":"Point"}
}