{
  "type": "Feature",
  "properties": {
    "iso:country":"US",
    "sg:address":"6849 Charlotte Pike",
    "sg:city":"Nashville",
    "sg:classifiers":[
        {
            "category":"Organizations",
            "subcategory":"Religious Organization",
            "type":"Services"
        }
    ],
    "sg:phone":"+1 615 352 2800",
    "sg:postcode":"37209",
    "sg:province":"TN",
    "wof:name":"West Nashville Church",
    "wof:placetype":"venue"
},
  "geometry": {"coordinates":[-86.89544600000001,36.131915],"type":"Point"}
}