{
  "type": "Feature",
  "properties": {
    "iso:country":"US",
    "sg:address":"134 Timber Creek Dr",
    "sg:city":"Cordova",
    "sg:classifiers":[
        {
            "category":"Real Estate",
            "subcategory":"Real Estate Agent",
            "type":"Services"
        }
    ],
    "sg:phone":"+1 901 753 6300",
    "sg:postcode":"38018",
    "sg:province":"TN",
    "wof:name":"Pyramid Realtors",
    "wof:placetype":"venue"
},
  "geometry": {"coordinates":[-89.797353,35.126849],"type":"Point"}
}