{
  "type": "Feature",
  "properties": {
    "iso:country":"US",
    "sg:address":"218 Old Watauga Rd",
    "sg:city":"Elizabethton",
    "sg:classifiers":[
        {
            "category":"Professional",
            "type":"Services"
        }
    ],
    "sg:phone":"+1 423 543 1409",
    "sg:postcode":"37643",
    "sg:province":"TN",
    "wof:name":"Tri Cities Elevator Services",
    "wof:placetype":"venue"
},
  "geometry": {"coordinates":[-82.238772,36.360599],"type":"Point"}
}