{
  "type": "Feature",
  "properties": {
    "addr:full":"130 E Cumberland St Kingston TN 37763",
    "addr:housenumber":"130",
    "addr:postcode":"37763",
    "addr:street":"E Cumberland St",
    "iso:country":"US",
    "sg:address":"130 E Cumberland St",
    "sg:city":"Kingston",
    "sg:classifiers":[
        {
            "category":"Home & Garden",
            "subcategory":"Home Furnishings",
            "type":"Retail Goods"
        }
    ],
    "sg:phone":"+1 865 717 1060",
    "sg:postcode":"37763",
    "sg:province":"TN",
    "wof:name":"Dollar General",
    "wof:placetype":"venue"
},
  "geometry": {"coordinates":[-84.515652,35.872297],"type":"Point"}
}