{
  "type": "Feature",
  "properties": {
    "iso:country":"US",
    "sg:address":"406 Cooks Valley Rd",
    "sg:city":"Kingsport",
    "sg:classifiers":[
        {
            "category":"Organizations",
            "subcategory":"Religious Organization",
            "type":"Services"
        }
    ],
    "sg:phone":"+1 423 288 5081",
    "sg:postcode":"37664",
    "sg:province":"TN",
    "sg:tags":[
        "church"
    ],
    "wof:name":"Sunnyside Baptist Church Inc",
    "wof:placetype":"venue"
},
  "geometry": {"coordinates":[-82.459284,36.540207],"type":"Point"}
}