{
  "type": "Feature",
  "properties": {
    "iso:country":"US",
    "sg:address":"2155 N Highland Ave",
    "sg:city":"Jackson",
    "sg:classifiers":[
        {
            "category":"Utilities",
            "subcategory":"Mobile Phone",
            "type":"Services"
        }
    ],
    "sg:phone":"+1 731 427 9000",
    "sg:postcode":"38305",
    "sg:province":"TN",
    "sg:tags":[
        "communication",
        "radiotelephone",
        "merchandise"
    ],
    "wof:name":"Verizon",
    "wof:placetype":"venue"
},
  "geometry": {"coordinates":[-88.828397,35.661008],"type":"Point"}
}