{
  "type": "Feature",
  "properties": {
    "addr:full":"7408 Wood Rd Corryton TN 37721",
    "addr:housenumber":"7408",
    "addr:postcode":"37721",
    "addr:street":"Wood Rd",
    "iso:country":"US",
    "sg:address":"7408 Wood Rd",
    "sg:city":"Corryton",
    "sg:classifiers":[
        {
            "category":"Retail",
            "subcategory":"Auto Repair",
            "type":"Services"
        }
    ],
    "sg:phone":"+1 865 689 1029",
    "sg:postcode":"37721",
    "sg:province":"TN",
    "sg:tags":[
        "automotive"
    ],
    "wof:name":"Hotrods",
    "wof:placetype":"venue"
},
  "geometry": {"coordinates":[-83.88278699999999,36.14922],"type":"Point"}
}