{
  "type": "Feature",
  "properties": {
    "iso:country":"US",
    "sg:address":"3366 Bedford Ln",
    "sg:city":"Germantown",
    "sg:classifiers":[
        {
            "category":"Professional",
            "type":"Services"
        }
    ],
    "sg:phone":"+1 901 853 7787",
    "sg:postcode":"38139",
    "sg:province":"TN",
    "wof:name":"Jack",
    "wof:placetype":"venue"
},
  "geometry": {"coordinates":[-89.737881,35.057371],"type":"Point"}
}