{
  "type": "Feature",
  "properties": {
    "iso:country":"US",
    "sg:address":"1817 Oakwood Dr",
    "sg:city":"Kingsport",
    "sg:classifiers":[
        {
            "category":"Building & Trades",
            "subcategory":"Construction",
            "type":"Services"
        }
    ],
    "sg:phone":"+1 423 247 4868",
    "sg:postcode":"37664",
    "sg:province":"TN",
    "sg:tags":[
        "house"
    ],
    "wof:name":"Secur Hm Improvement",
    "wof:placetype":"venue"
},
  "geometry": {"coordinates":[-82.533829,36.525663],"type":"Point"}
}