{
  "type": "Feature",
  "properties": {
    "iso:country":"US",
    "sg:address":"749 W Snowden Cir",
    "sg:city":"Memphis",
    "sg:classifiers":[
        {
            "category":"Organizations",
            "subcategory":"Non-profit Organization",
            "type":"Services"
        }
    ],
    "sg:phone":"+1 901 272 7490",
    "sg:postcode":"38104",
    "sg:province":"TN",
    "sg:tags":[
        "social"
    ],
    "wof:name":"Annesdale Snowden Cmnty Dev",
    "wof:placetype":"venue"
},
  "geometry": {"coordinates":[-90.01860499999999,35.126009],"type":"Point"}
}