{
  "type": "Feature",
  "properties": {
    "iso:country":"US",
    "sg:address":"3812 Thrall Dr",
    "sg:city":"Knoxville",
    "sg:classifiers":[
        {
            "category":"Wholesale",
            "subcategory":"Durable Goods & Equipment",
            "type":"Manufacturing & Wholesale Goods"
        }
    ],
    "sg:phone":"+1 865 689 8141",
    "sg:postcode":"37918",
    "sg:province":"TN",
    "wof:name":"Avb Supply",
    "wof:placetype":"venue"
},
  "geometry": {"coordinates":[-83.921849,36.051472],"type":"Point"}
}