{
  "type": "Feature",
  "properties": {
    "addr:full":"161 Green St Nashville TN 37210",
    "addr:housenumber":"161",
    "addr:postcode":"37210",
    "addr:street":"Green St",
    "iso:country":"US",
    "sg:address":"161 Green St",
    "sg:city":"Nashville",
    "sg:classifiers":[
        {
            "category":"Building & Trades",
            "subcategory":"Electrical",
            "type":"Services"
        }
    ],
    "sg:phone":"+1 615 734 0788",
    "sg:postcode":"37210",
    "sg:province":"TN",
    "sg:tags":[
        "electric",
        "contractor"
    ],
    "wof:name":"R G Electrical Contractors LLC",
    "wof:placetype":"venue"
},
  "geometry": {"coordinates":[-86.752145,36.152392],"type":"Point"}
}