{
  "type": "Feature",
  "properties": {
    "iso:country":"US",
    "sg:address":"131 Tucker St",
    "sg:city":"Jackson",
    "sg:classifiers":[
        {
            "category":"Banks & Credit Unions",
            "subcategory":"Investment Brokerage",
            "type":"Services"
        }
    ],
    "sg:phone":"+1 731 424 4441",
    "sg:postcode":"38301",
    "sg:province":"TN",
    "sg:tags":[
        "liquor"
    ],
    "wof:name":"Lindsey & Lindsey",
    "wof:placetype":"venue"
},
  "geometry": {"coordinates":[-88.824394,35.636969],"type":"Point"}
}