{
  "type": "Feature",
  "properties": {
    "iso:country":"US",
    "sg:address":"5925 Ooltewah Ringgold Rd",
    "sg:city":"Ooltewah",
    "sg:classifiers":[
        {
            "category":"Banks & Credit Unions",
            "subcategory":"Bank",
            "type":"Services"
        }
    ],
    "sg:phone":"+1 423 238 5050",
    "sg:postcode":"37363",
    "sg:province":"TN",
    "sg:tags":[
        "loan",
        "real estate"
    ],
    "wof:name":"Executive Home Lending",
    "wof:placetype":"venue"
},
  "geometry": {"coordinates":[-85.05862500000001,35.082618],"type":"Point"}
}