{
  "type": "Feature",
  "properties": {
    "addr:full":"635 E Main St Hendersonville TN 37075",
    "addr:housenumber":"635",
    "addr:postcode":"37075",
    "addr:street":"E Main St",
    "iso:country":"US",
    "sg:address":"635 E Main St",
    "sg:city":"Hendersonville",
    "sg:classifiers":[
        {
            "category":"Health Services",
            "subcategory":"Medical Lab",
            "type":"Services"
        }
    ],
    "sg:phone":"+1 615 338 0003",
    "sg:postcode":"37075",
    "sg:province":"TN",
    "sg:tags":[
        "resonance",
        "magnetic",
        "imaging"
    ],
    "wof:name":"Imaging Solutions & Svc Inc",
    "wof:placetype":"venue"
},
  "geometry": {"coordinates":[-86.56525999999999,36.325188],"type":"Point"}
}