{
  "type": "Feature",
  "properties": {
    "iso:country":"US",
    "sg:address":"2105 McCallie Ave",
    "sg:city":"Chattanooga",
    "sg:classifiers":[
        {
            "category":"Professional",
            "type":"Services"
        }
    ],
    "sg:phone":"+1 423 624 9349",
    "sg:postcode":"37404",
    "sg:province":"TN",
    "wof:name":"Little Ds",
    "wof:placetype":"venue"
},
  "geometry": {"coordinates":[-85.270684,35.034502],"type":"Point"}
}