{
  "type": "Feature",
  "properties": {
    "iso:country":"US",
    "sg:address":"403 E Baltimore St",
    "sg:city":"Jackson",
    "sg:classifiers":[
        {
            "category":"Retail",
            "subcategory":"Funeral Services",
            "type":"Services"
        }
    ],
    "sg:phone":"+1 731 424 2424",
    "sg:postcode":"38301",
    "sg:province":"TN",
    "sg:tags":[
        "director"
    ],
    "wof:name":"Lawrence-Sorensen Funeral Home",
    "wof:placetype":"venue"
},
  "geometry": {"coordinates":[-88.81567200000001,35.613437],"type":"Point"}
}