{
  "type": "Feature",
  "properties": {
    "iso:country":"US",
    "sg:address":"7253 Green Meadows Ln",
    "sg:city":"Nashville",
    "sg:classifiers":[
        {
            "category":"Building & Trades",
            "subcategory":"Pest Control",
            "type":"Services"
        }
    ],
    "sg:phone":"+1 615 662 0262",
    "sg:postcode":"37221",
    "sg:province":"TN",
    "wof:name":"Anti-Pest",
    "wof:placetype":"venue"
},
  "geometry": {"coordinates":[-86.93760399999999,36.068067],"type":"Point"}
}