{
  "type": "Feature",
  "properties": {
    "iso:country":"US",
    "sg:address":"902 Murphy Dr",
    "sg:city":"Pleasant View",
    "sg:classifiers":[
        {
            "category":"Building & Trades",
            "subcategory":"Electrical",
            "type":"Services"
        }
    ],
    "sg:phone":"+1 615 746 6830",
    "sg:postcode":"37146",
    "sg:province":"TN",
    "sg:tags":[
        "electric",
        "contractor"
    ],
    "wof:name":"Taylor Electric Co",
    "wof:placetype":"venue"
},
  "geometry": {"coordinates":[-87.057298,36.368199],"type":"Point"}
}