{
  "type": "Feature",
  "properties": {
    "addr:full":"2237 Frisco Ave Memphis TN 38114",
    "addr:housenumber":"2237",
    "addr:postcode":"38114",
    "addr:street":"Frisco Ave",
    "iso:country":"US",
    "sg:address":"2237 Frisco Ave",
    "sg:city":"Memphis",
    "sg:classifiers":[
        {
            "category":"Building & Trades",
            "subcategory":"Construction",
            "type":"Services"
        }
    ],
    "sg:phone":"+1 901 744 5369",
    "sg:postcode":"38114",
    "sg:province":"TN",
    "sg:tags":[
        "contractor"
    ],
    "wof:name":"Dm and Demolition",
    "wof:placetype":"venue"
},
  "geometry": {"coordinates":[-89.98800300000001,35.092997],"type":"Point"}
}