{
  "type": "Feature",
  "properties": {
    "addr:full":"170 Hidden Springs Ln Cookeville TN 38501",
    "addr:housenumber":"170",
    "addr:postcode":"38501",
    "addr:street":"Hidden Springs Ln",
    "iso:country":"US",
    "sg:address":"170 Hidden Springs Ln",
    "sg:city":"Cookeville",
    "sg:classifiers":[
        {
            "category":"Home & Garden",
            "subcategory":"Garden Supply",
            "type":"Retail Goods"
        }
    ],
    "sg:phone":"+1 931 268 2592",
    "sg:postcode":"38501",
    "sg:province":"TN",
    "sg:tags":[
        "nurseryman"
    ],
    "wof:name":"Hidden Springs Nursery",
    "wof:placetype":"venue"
},
  "geometry": {"coordinates":[-85.51091099999999,36.320616],"type":"Point"}
}