{
  "type": "Feature",
  "properties": {
    "iso:country":"US",
    "sg:address":"4400 Lebanon Pike",
    "sg:city":"Hermitage",
    "sg:classifiers":[
        {
            "category":"Banks & Credit Unions",
            "subcategory":"Bank",
            "type":"Services"
        }
    ],
    "sg:phone":"+1 615 871 7050",
    "sg:postcode":"37076",
    "sg:province":"TN",
    "sg:tags":[
        "state",
        "commercial"
    ],
    "wof:name":"National Bank Of Commerce",
    "wof:placetype":"venue"
},
  "geometry": {"coordinates":[-86.607097,36.212582],"type":"Point"}
}