{
  "type": "Feature",
  "properties": {
    "addr:full":"835 Clifton Rd Savannah TN 38372",
    "addr:housenumber":"835",
    "addr:postcode":"38372",
    "addr:street":"Clifton Rd",
    "iso:country":"US",
    "sg:address":"835 Clifton Rd",
    "sg:city":"Savannah",
    "sg:classifiers":[
        {
            "category":"Organizations",
            "subcategory":"Religious Organization",
            "type":"Services"
        }
    ],
    "sg:phone":"+1 731 925 4852",
    "sg:postcode":"38372",
    "sg:province":"TN",
    "wof:name":"Our Lady of Lk Church Mission",
    "wof:placetype":"venue"
},
  "geometry": {"coordinates":[-88.23425400000001,35.233862],"type":"Point"}
}