{
  "type": "Feature",
  "properties": {
    "iso:country":"US",
    "sg:address":"216 S Maple St",
    "sg:city":"Lebanon",
    "sg:classifiers":[
        {
            "category":"Real Estate",
            "subcategory":"Real Estate Agent",
            "type":"Services"
        }
    ],
    "sg:phone":"+1 615 444 9273",
    "sg:postcode":"37087",
    "sg:province":"TN",
    "wof:name":"Cato Industrial Development",
    "wof:placetype":"venue"
},
  "geometry": {"coordinates":[-86.293009,36.204893],"type":"Point"}
}