{
  "type": "Feature",
  "properties": {
    "addr:full":"126 Kilby St Sevierville TN 37862",
    "addr:housenumber":"126",
    "addr:postcode":"37862",
    "addr:street":"Kilby St",
    "iso:country":"US",
    "sg:address":"126 Kilby St",
    "sg:city":"Sevierville",
    "sg:classifiers":[
        {
            "category":"Retail",
            "subcategory":"Auto Rental",
            "type":"Services"
        }
    ],
    "sg:phone":"+1 865 429 3389",
    "sg:postcode":"37862",
    "sg:province":"TN",
    "sg:tags":[
        "renting",
        "truck",
        "leasing"
    ],
    "wof:name":"U-Haul Co",
    "wof:placetype":"venue"
},
  "geometry": {"coordinates":[-83.572526,35.873165],"type":"Point"}
}