{
  "type": "Feature",
  "properties": {
    "iso:country":"US",
    "sg:address":"104 Hotel Rd",
    "sg:city":"Knoxville",
    "sg:classifiers":[
        {
            "category":"Restaurant",
            "type":"Food & Drink"
        }
    ],
    "sg:phone":"+1 865 357 6693",
    "sg:postcode":"37918",
    "sg:province":"TN",
    "sg:tags":[
        "shop",
        "coffee"
    ],
    "wof:name":"Coffee Shoppe",
    "wof:placetype":"venue"
},
  "geometry": {"coordinates":[-83.93441900000001,36.037181],"type":"Point"}
}