{
  "type": "Feature",
  "properties": {
    "iso:country":"US",
    "sg:address":"5456 Hayes Rd",
    "sg:city":"Arlington",
    "sg:classifiers":[
        {
            "category":"Shopping",
            "subcategory":"Beauty & Cosmetics",
            "type":"Retail Goods"
        }
    ],
    "sg:phone":"+1 901 867 7168",
    "sg:postcode":"38002",
    "sg:province":"TN",
    "sg:tags":[
        "merchandise"
    ],
    "wof:name":"Exclusive Beauty Supply",
    "wof:placetype":"venue"
},
  "geometry": {"coordinates":[-89.660617,35.27828],"type":"Point"}
}