{
  "type": "Feature",
  "properties": {
    "iso:country":"US",
    "sg:address":"3820 Wears Valley Rd",
    "sg:city":"Sevierville",
    "sg:classifiers":[
        {
            "category":"Real Estate",
            "subcategory":"Real Estate Agent",
            "type":"Services"
        }
    ],
    "sg:phone":"+1 865 429 1203",
    "sg:postcode":"37862",
    "sg:province":"TN",
    "wof:name":"Taylor Investments",
    "wof:placetype":"venue"
},
  "geometry": {"coordinates":[-83.660079,35.711734],"type":"Point"}
}