{
  "type": "Feature",
  "properties": {
    "addr:full":"3845 Saint Philip Dr Memphis TN 38133",
    "addr:housenumber":"3845",
    "addr:postcode":"38133",
    "addr:street":"Saint Philip Dr",
    "iso:country":"US",
    "sg:address":"3845 Saint Philip Dr",
    "sg:city":"Memphis",
    "sg:classifiers":[
        {
            "category":"Wholesale",
            "subcategory":"Vending Machines",
            "type":"Manufacturing & Wholesale Goods"
        }
    ],
    "sg:phone":"+1 901 377 5179",
    "sg:postcode":"38133",
    "sg:province":"TN",
    "sg:tags":[
        "operator"
    ],
    "wof:name":"Fab Enterprises Inc",
    "wof:placetype":"venue"
},
  "geometry": {"coordinates":[-89.755354,35.230496],"type":"Point"}
}