{
  "type": "Feature",
  "properties": {
    "iso:country":"US",
    "sg:address":"1631 Miller Farms Rd",
    "sg:city":"Germantown",
    "sg:classifiers":[
        {
            "category":"Professional",
            "subcategory":"Printing & Photocopies",
            "type":"Services"
        }
    ],
    "sg:phone":"+1 901 755 1933",
    "sg:postcode":"38138",
    "sg:province":"TN",
    "wof:name":"Printery The",
    "wof:placetype":"venue"
},
  "geometry": {"coordinates":[-89.813346,35.103965],"type":"Point"}
}