{
  "type": "Feature",
  "properties": {
    "iso:country":"US",
    "sg:address":"1309 Broad St",
    "sg:city":"Elizabethton",
    "sg:classifiers":[
        {
            "category":"Personal",
            "subcategory":"Beauty Salon",
            "type":"Services"
        }
    ],
    "sg:phone":"+1 423 543 5860",
    "sg:postcode":"37643",
    "sg:province":"TN",
    "sg:tags":[
        "shop"
    ],
    "wof:name":"Hair Shack",
    "wof:placetype":"venue"
},
  "geometry": {"coordinates":[-82.186245,36.355334],"type":"Point"}
}