{
  "type": "Feature",
  "properties": {
    "iso:country":"US",
    "sg:address":"2620 W Big Richland Rd",
    "sg:city":"Waverly",
    "sg:classifiers":[
        {
            "category":"Professional",
            "type":"Services"
        }
    ],
    "sg:phone":"+1 931 296 1313",
    "sg:postcode":"37185",
    "sg:province":"TN",
    "wof:name":"Damon L Brown",
    "wof:placetype":"venue"
},
  "geometry": {"coordinates":[-87.81504,36.160145],"type":"Point"}
}