{
  "type": "Feature",
  "properties": {
    "iso:country":"US",
    "sg:address":"205 W Jackson Blvd",
    "sg:city":"Jonesborough",
    "sg:classifiers":[
        {
            "category":"Restaurant",
            "type":"Food & Drink"
        }
    ],
    "sg:phone":"+1 423 753 7030",
    "sg:postcode":"37659",
    "sg:province":"TN",
    "sg:tags":[
        "shop",
        "coffee"
    ],
    "wof:name":"Joe To Go Espresso",
    "wof:placetype":"venue"
},
  "geometry": {"coordinates":[-82.475784,36.296874],"type":"Point"}
}