{
  "type": "Feature",
  "properties": {
    "addr:full":"616 Furlong Cove Collierville TN 38017",
    "addr:housenumber":"616",
    "addr:postcode":"38017",
    "addr:street":"Furlong Cove",
    "iso:country":"US",
    "sg:address":"616 Furlong Cove",
    "sg:city":"Collierville",
    "sg:classifiers":[
        {
            "category":"Building & Trades",
            "subcategory":"Construction",
            "type":"Services"
        }
    ],
    "sg:phone":"+1 901 861 1300",
    "sg:postcode":"38017",
    "sg:province":"TN",
    "sg:tags":[
        "control",
        "corrosion"
    ],
    "wof:name":"Southeast Compliance",
    "wof:placetype":"venue"
},
  "geometry": {"coordinates":[-89.648352,35.047651],"type":"Point"}
}