{
  "type": "Feature",
  "properties": {
    "addr:full":"1804 Linden Ave Nashville TN 37212",
    "addr:housenumber":"1804",
    "addr:postcode":"37212",
    "addr:street":"Linden Ave",
    "iso:country":"US",
    "sg:address":"1804 Linden Ave",
    "sg:city":"Nashville",
    "sg:classifiers":[
        {
            "category":"Manufacturing",
            "subcategory":"Tools & Machinery",
            "type":"Manufacturing & Wholesale Goods"
        }
    ],
    "sg:phone":"+1 615 298 1664",
    "sg:postcode":"37212",
    "sg:province":"TN",
    "sg:tags":[
        "equipment",
        "mfg"
    ],
    "wof:name":"Lieb Enterprises",
    "wof:placetype":"venue"
},
  "geometry": {"coordinates":[-86.800012,36.12787],"type":"Point"}
}