{
  "type": "Feature",
  "properties": {
    "addr:full":"135 Garden East Rd Carthage TN 37058",
    "addr:housenumber":"135",
    "addr:postcode":"37058",
    "addr:street":"Garden East Rd",
    "iso:country":"US",
    "sg:address":"135 Garden East Rd",
    "sg:city":"Carthage",
    "sg:classifiers":[
        {
            "category":"Government",
            "subcategory":"Office",
            "type":"Public Place"
        }
    ],
    "sg:phone":"+1 615 735 3005",
    "sg:postcode":"37058",
    "sg:province":"TN",
    "sg:tags":[
        "county"
    ],
    "wof:name":"Smith County Ofc Resource Ctr",
    "wof:placetype":"venue"
},
  "geometry": {"coordinates":[-87.78056100000001,36.414022],"type":"Point"}
}