{
  "type": "Feature",
  "properties": {
    "iso:country":"US",
    "sg:address":"1980 Buffalo Rd",
    "sg:city":"Lawrenceburg",
    "sg:classifiers":[
        {
            "category":"Professional",
            "subcategory":"Business Services",
            "type":"Services"
        }
    ],
    "sg:phone":"+1 931 766 5270",
    "sg:postcode":"38464",
    "sg:province":"TN",
    "wof:name":"G Force Enterprises",
    "wof:placetype":"venue"
},
  "geometry": {"coordinates":[-87.339736,35.266413],"type":"Point"}
}