{
  "type": "Feature",
  "properties": {
    "iso:country":"US",
    "sg:address":"225 Lewis Ln",
    "sg:city":"Kingsport",
    "sg:classifiers":[
        {
            "category":"Wholesale",
            "subcategory":"Vending Machines",
            "type":"Manufacturing & Wholesale Goods"
        },
        {
            "category":"Building & Trades",
            "subcategory":"Equipment Rental",
            "type":"Services"
        }
    ],
    "sg:phone":"+1 423 246 4012",
    "sg:postcode":"37660",
    "sg:province":"TN",
    "sg:website":"www.fivestar-food.com",
    "wof:name":"Five Star Food Service Inc",
    "wof:placetype":"venue"
},
  "geometry": {"coordinates":[-82.625587,36.55338],"type":"Point"}
}