{
  "type": "Feature",
  "properties": {
    "addr:full":"404 Downy Meade Dr Franklin TN 37064",
    "addr:housenumber":"404",
    "addr:postcode":"37064",
    "addr:street":"Downy Meade Dr",
    "iso:country":"US",
    "sg:address":"404 Downy Meade Dr",
    "sg:city":"Franklin",
    "sg:classifiers":[
        {
            "category":"Real Estate",
            "subcategory":"Developer",
            "type":"Services"
        }
    ],
    "sg:phone":"+1 615 595 9036",
    "sg:postcode":"37064",
    "sg:province":"TN",
    "wof:name":"GLOry&ron Exum",
    "wof:placetype":"venue"
},
  "geometry": {"coordinates":[-86.840631,35.854789],"type":"Point"}
}