{
  "type": "Feature",
  "properties": {
    "addr:full":"6820 Smithville Hwy Sparta TN 38583",
    "addr:housenumber":"6820",
    "addr:postcode":"38583",
    "addr:street":"Smithville Hwy",
    "iso:country":"US",
    "sg:address":"6820 Smithville Hwy",
    "sg:city":"Sparta",
    "sg:classifiers":[
        {
            "category":"Retail",
            "subcategory":"Auto Repair",
            "type":"Services"
        }
    ],
    "sg:phone":"+1 931 761 2241",
    "sg:postcode":"38583",
    "sg:province":"TN",
    "sg:tags":[
        "supply",
        "truck",
        "general"
    ],
    "wof:name":"Englands Diesel Repair",
    "wof:placetype":"venue"
},
  "geometry": {"coordinates":[-85.60083400000001,35.958643],"type":"Point"}
}