{
  "type": "Feature",
  "properties": {
    "iso:country":"US",
    "sg:address":"8928 E Glendale Ct",
    "sg:city":"Cordova",
    "sg:classifiers":[
        {
            "category":"Restaurant",
            "type":"Food & Drink"
        }
    ],
    "sg:phone":"+1 901 753 1059",
    "sg:postcode":"38018",
    "sg:province":"TN",
    "sg:tags":[
        "eating"
    ],
    "wof:name":"Cicis Pizza",
    "wof:placetype":"venue"
},
  "geometry": {"coordinates":[-89.764403,35.134009],"type":"Point"}
}