{
  "type": "Feature",
  "properties": {
    "iso:country":"US",
    "sg:address":"2321 Dawns Pass",
    "sg:city":"Knoxville",
    "sg:classifiers":[
        {
            "category":"Professional",
            "subcategory":"Management & Consulting",
            "type":"Services"
        }
    ],
    "sg:phone":"+1 865 539 0111",
    "sg:postcode":"37919",
    "sg:province":"TN",
    "wof:name":"Ann Bynum & Assoc Inc",
    "wof:placetype":"venue"
},
  "geometry": {"coordinates":[-84.011841,35.882614],"type":"Point"}
}