{
  "type": "Feature",
  "properties": {
    "iso:country":"US",
    "sg:address":"4210 Millbranch Rd",
    "sg:city":"Memphis",
    "sg:classifiers":[
        {
            "category":"Real Estate",
            "subcategory":"Real Estate Agent",
            "type":"Services"
        }
    ],
    "sg:phone":"+1 901 345 9400",
    "sg:postcode":"38116",
    "sg:province":"TN",
    "sg:tags":[
        "authorities",
        "housing"
    ],
    "wof:name":"Home Buying Consultant Svc",
    "wof:placetype":"venue"
},
  "geometry": {"coordinates":[-90.007446,35.032323],"type":"Point"}
}