{
  "type": "Feature",
  "properties": {
    "addr:full":"6120 S River Bend Dr Nashville TN 37221",
    "addr:housenumber":"6120",
    "addr:postcode":"37221",
    "addr:street":"S River Bend Dr",
    "iso:country":"US",
    "sg:address":"6120 S River Bend Dr",
    "sg:city":"Nashville",
    "sg:classifiers":[
        {
            "category":"Retail",
            "subcategory":"Repair Shop",
            "type":"Services"
        }
    ],
    "sg:phone":"+1 615 662 0695",
    "sg:postcode":"37221",
    "sg:province":"TN",
    "sg:tags":[
        "equipment",
        "video"
    ],
    "wof:name":"Hoffman Communications",
    "wof:placetype":"venue"
},
  "geometry": {"coordinates":[-86.95396100000001,36.050882],"type":"Point"}
}