{
  "type": "Feature",
  "properties": {
    "iso:country":"US",
    "sg:address":"225 E 8th St Ste 4",
    "sg:city":"Chattanooga",
    "sg:classifiers":[
        {
            "category":"Utilities",
            "subcategory":"Telephone",
            "type":"Services"
        }
    ],
    "sg:phone":"+1 423 648 9700",
    "sg:postcode":"37402",
    "sg:province":"TN",
    "sg:tags":[
        "communication"
    ],
    "wof:name":"Covista",
    "wof:placetype":"venue"
},
  "geometry": {"coordinates":[-85.30716099999999,35.047],"type":"Point"}
}