{
  "type": "Feature",
  "properties": {
    "iso:country":"US",
    "sg:address":"3592 Commerce Cir",
    "sg:city":"Memphis",
    "sg:classifiers":[
        {
            "category":"Organizations",
            "subcategory":"Religious Organization",
            "type":"Services"
        }
    ],
    "sg:phone":"+1 901 565 9497",
    "sg:postcode":"38118",
    "sg:province":"TN",
    "sg:tags":[
        "church"
    ],
    "wof:name":"Church Of Christ At Memphis",
    "wof:placetype":"venue"
},
  "geometry": {"coordinates":[-89.92104999999999,35.051514],"type":"Point"}
}