{
  "type": "Feature",
  "properties": {
    "iso:country":"US",
    "sg:address":"219 2nd Ave N",
    "sg:city":"Nashville",
    "sg:classifiers":[
        {
            "category":"Professional",
            "type":"Services"
        }
    ],
    "sg:phone":"+1 615 781 6606",
    "sg:postcode":"37201",
    "sg:province":"TN",
    "wof:name":"Tennessee Wldlife Resources Fo",
    "wof:placetype":"venue"
},
  "geometry": {"coordinates":[-86.77691799999999,36.164423],"type":"Point"}
}