{
  "type": "Feature",
  "properties": {
    "addr:full":"297 Plus Park Blvd Nashville TN 37217",
    "addr:housenumber":"297",
    "addr:postcode":"37217",
    "addr:street":"Plus Park Blvd",
    "iso:country":"US",
    "sg:address":"297 Plus Park Blvd",
    "sg:city":"Nashville",
    "sg:classifiers":[
        {
            "category":"Government",
            "subcategory":"Office",
            "type":"Public Place"
        }
    ],
    "sg:phone":"+1 615 781 5392",
    "sg:postcode":"37217",
    "sg:province":"TN",
    "sg:tags":[
        "food",
        "district",
        "administration",
        "for",
        "drug"
    ],
    "wof:name":"Food & Drug Administration",
    "wof:placetype":"venue"
},
  "geometry": {"coordinates":[-86.724799,36.124587],"type":"Point"}
}