{
  "type": "Feature",
  "properties": {
    "iso:country":"US",
    "sg:address":"1112 Yoakum St",
    "sg:city":"New Tazewell",
    "sg:classifiers":[
        {
            "category":"Government",
            "subcategory":"Office",
            "type":"Public Place"
        }
    ],
    "sg:phone":"+1 423 626 9617",
    "sg:postcode":"37825",
    "sg:province":"TN",
    "sg:tags":[
        "county",
        "safety",
        "order"
    ],
    "wof:name":"Claiborne Cnty Emergency Mgmt",
    "wof:placetype":"venue"
},
  "geometry": {"coordinates":[-83.628681,36.428166],"type":"Point"}
}