{
  "type": "Feature",
  "properties": {
    "addr:full":"2810 Ball Camp Byington Rd Knoxville TN 37931",
    "addr:housenumber":"2810",
    "addr:postcode":"37931",
    "addr:street":"Ball;Byington Rd",
    "iso:country":"US",
    "sg:address":"2810 Ball Camp Byington Rd",
    "sg:city":"Knoxville",
    "sg:classifiers":[
        {
            "category":"Recreation",
            "type":"Entertainment"
        }
    ],
    "sg:phone":"+1 865 670 7682",
    "sg:postcode":"37931",
    "sg:province":"TN",
    "sg:tags":[
        "tennis",
        "instruction"
    ],
    "sg:website":"www.smokytennis.com",
    "wof:name":"Smoky Mountain Tennis Academy",
    "wof:placetype":"venue"
},
  "geometry": {"coordinates":[-84.123137,35.966065],"type":"Point"}
}