{
  "type": "Feature",
  "properties": {
    "iso:country":"US",
    "sg:address":"507 S Gay St",
    "sg:city":"Knoxville",
    "sg:classifiers":[
        {
            "category":"Insurance",
            "subcategory":"Life Insurance",
            "type":"Services"
        }
    ],
    "sg:phone":"+1 865 637 2611",
    "sg:postcode":"37902",
    "sg:province":"TN",
    "sg:tags":[
        "security",
        "carrier"
    ],
    "wof:name":"Nationwide",
    "wof:placetype":"venue"
},
  "geometry": {"coordinates":[-83.917813,35.964295],"type":"Point"}
}