{
  "type": "Feature",
  "properties": {
    "iso:country":"US",
    "sg:address":"1501 E Main St",
    "sg:city":"Chattanooga",
    "sg:classifiers":[
        {
            "category":"Banks & Credit Unions",
            "subcategory":"Bank",
            "type":"Services"
        }
    ],
    "sg:phone":"+1 423 757 3063",
    "sg:postcode":"37404",
    "sg:province":"TN",
    "sg:tags":[
        "national"
    ],
    "wof:name":"SunTrust",
    "wof:placetype":"venue"
},
  "geometry": {"coordinates":[-85.285079,35.027837],"type":"Point"}
}