{
  "type": "Feature",
  "properties": {
    "iso:country":"US",
    "sg:address":"1990 Troyer Ave",
    "sg:city":"Memphis",
    "sg:classifiers":[
        {
            "category":"Manufacturing",
            "subcategory":"Soap",
            "type":"Manufacturing & Wholesale Goods"
        },
        {
            "category":"Professional",
            "subcategory":"Business Services",
            "type":"Services"
        }
    ],
    "sg:phone":"+1 901 946 7801",
    "sg:postcode":"38114",
    "sg:province":"TN",
    "sg:tags":[
        "packaging",
        "contract"
    ],
    "wof:name":"Premier Packaging Inc",
    "wof:placetype":"venue"
},
  "geometry": {"coordinates":[-89.997011,35.088301],"type":"Point"}
}