{
  "type": "Feature",
  "properties": {
    "addr:full":"210 Lethco Ln Newport TN 37821",
    "addr:housenumber":"210",
    "addr:postcode":"37821",
    "addr:street":"Lethco Ln",
    "iso:country":"US",
    "sg:address":"210 Lethco Ln",
    "sg:city":"Newport",
    "sg:classifiers":[
        {
            "category":"Food & Beverages",
            "subcategory":"Groceries & Convenience Stores",
            "type":"Retail Goods"
        }
    ],
    "sg:phone":"+1 423 623 9309",
    "sg:postcode":"37821",
    "sg:province":"TN",
    "wof:name":"High Oaks Grocery & Deli",
    "wof:placetype":"venue"
},
  "geometry": {"coordinates":[-83.171046,35.974052],"type":"Point"}
}