{
  "type": "Feature",
  "properties": {
    "addr:full":"171 Clinton Ave Spring City TN 37381",
    "addr:housenumber":"171",
    "addr:postcode":"37381",
    "addr:street":"Clinton Ave",
    "iso:country":"US",
    "sg:address":"171 Clinton Ave",
    "sg:city":"Spring City",
    "sg:classifiers":[
        {
            "category":"Restaurant",
            "type":"Food & Drink"
        }
    ],
    "sg:phone":"+1 423 365 2222",
    "sg:postcode":"37381",
    "sg:province":"TN",
    "wof:name":"Red Barn Restaurant & Grill",
    "wof:placetype":"venue"
},
  "geometry": {"coordinates":[-84.8635,35.691981],"type":"Point"}
}