{
  "type": "Feature",
  "properties": {
    "iso:country":"US",
    "sg:address":"2633 Bakertown Rd",
    "sg:city":"Knoxville",
    "sg:classifiers":[
        {
            "category":"Real Estate",
            "subcategory":"Real Estate Operator",
            "type":"Services"
        }
    ],
    "sg:phone":"+1 865 470 8686",
    "sg:postcode":"37931",
    "sg:province":"TN",
    "sg:tags":[
        "apartment"
    ],
    "wof:name":"Bradford View Apartments",
    "wof:placetype":"venue"
},
  "geometry": {"coordinates":[-84.06499599999999,35.958031],"type":"Point"}
}