{
  "type": "Feature",
  "properties": {
    "iso:country":"US",
    "sg:address":"930 E Emerald Ave",
    "sg:city":"Knoxville",
    "sg:classifiers":[
        {
            "category":"Personal",
            "type":"Services"
        }
    ],
    "sg:phone":"+1 865 524 2547",
    "sg:postcode":"37917",
    "sg:province":"TN",
    "sg:tags":[
        "electrologist"
    ],
    "wof:name":"Skin Care Ctr",
    "wof:placetype":"venue"
},
  "geometry": {"coordinates":[-83.927635,35.991073],"type":"Point"}
}