{
  "type": "Feature",
  "properties": {
    "iso:country":"US",
    "sg:address":"7733 Oak Ridge Hwy",
    "sg:city":"Knoxville",
    "sg:classifiers":[
        {
            "category":"Health Services",
            "subcategory":"Doctor",
            "type":"Services"
        }
    ],
    "sg:phone":"+1 865 470 2560",
    "sg:postcode":"37931",
    "sg:province":"TN",
    "sg:tags":[
        "medical"
    ],
    "wof:name":"Pediatric Clinic",
    "wof:placetype":"venue"
},
  "geometry": {"coordinates":[-84.112076,35.979355],"type":"Point"}
}