{
  "type": "Feature",
  "properties": {
    "addr:full":"330 W Lincoln St Tullahoma TN 37388",
    "addr:housenumber":"330",
    "addr:postcode":"37388",
    "addr:street":"W Lincoln St",
    "iso:country":"US",
    "sg:address":"330 W Lincoln St",
    "sg:city":"Tullahoma",
    "sg:classifiers":[
        {
            "category":"Wholesale",
            "subcategory":"Auto Parts",
            "type":"Manufacturing & Wholesale Goods"
        }
    ],
    "sg:phone":"+1 931 455 2586",
    "sg:postcode":"37388",
    "sg:province":"TN",
    "wof:name":"Speedliner Custom Applications",
    "wof:placetype":"venue"
},
  "geometry": {"coordinates":[-86.21440200000001,35.359823],"type":"Point"}
}