{
  "type": "Feature",
  "properties": {
    "iso:country":"US",
    "sg:address":"182 Chaffin Pl",
    "sg:city":"Murfreesboro",
    "sg:classifiers":[
        {
            "category":"Travel",
            "subcategory":"Hotels & Motels",
            "type":"Entertainment"
        }
    ],
    "sg:phone":"+1 615 893 8170",
    "sg:postcode":"37129",
    "sg:province":"TN",
    "wof:name":"Days Inn",
    "wof:placetype":"venue"
},
  "geometry": {"coordinates":[-86.430088,35.844282],"type":"Point"}
}