{
  "type": "Feature",
  "properties": {
    "iso:country":"US",
    "sg:address":"6470 Haley Rd",
    "sg:city":"Memphis",
    "sg:classifiers":[
        {
            "category":"Government",
            "subcategory":"Office",
            "type":"Public Place"
        }
    ],
    "sg:phone":"+1 901 432 4738",
    "sg:postcode":"38134",
    "sg:province":"TN",
    "sg:tags":[
        "parish",
        "government-county"
    ],
    "sg:website":"http://www.memphispolice.net",
    "wof:name":"County Of Shelby",
    "wof:placetype":"venue"
},
  "geometry": {"coordinates":[-89.84765299999999,35.150481],"type":"Point"}
}