{
  "type": "Feature",
  "properties": {
    "iso:country":"US",
    "sg:address":"2710 Crazy Horse Ct",
    "sg:city":"Murfreesboro",
    "sg:classifiers":[
        {
            "category":"Wholesale",
            "subcategory":"Home Furnishings",
            "type":"Manufacturing & Wholesale Goods"
        }
    ],
    "sg:phone":"+1 615 893 9347",
    "sg:postcode":"37127",
    "sg:province":"TN",
    "wof:name":"Accessories Unique",
    "wof:placetype":"venue"
},
  "geometry": {"coordinates":[-86.395304,35.791965],"type":"Point"}
}