{
  "type": "Feature",
  "properties": {
    "addr:full":"100 E Main St Dyersburg TN 38024",
    "addr:housenumber":"100",
    "addr:postcode":"38024",
    "addr:street":"E Main St",
    "iso:country":"US",
    "sg:address":"100 E Main St",
    "sg:city":"Dyersburg",
    "sg:classifiers":[
        {
            "category":"Restaurant",
            "type":"Food & Drink"
        }
    ],
    "sg:menulink":"http://www.allmenus.com/tn/fowlkes/139900-subway/menu/",
    "sg:phone":"+1 731 287 7135",
    "sg:postcode":"38024",
    "sg:province":"TN",
    "sg:tags":[
        "american",
        "sandwich"
    ],
    "wof:name":"Subway",
    "wof:placetype":"venue"
},
  "geometry": {"coordinates":[-89.38493699999999,35.96885],"type":"Point"}
}