{
  "type": "Feature",
  "properties": {
    "iso:country":"US",
    "sg:address":"832 Greenwood Ave",
    "sg:city":"Clarksville",
    "sg:classifiers":[
        {
            "category":"Social Services",
            "type":"Services"
        }
    ],
    "sg:phone":"+1 931 920 7360",
    "sg:postcode":"37040",
    "sg:province":"TN",
    "sg:tags":[
        "crisis",
        "intervention"
    ],
    "wof:name":"Regional Intervention Program",
    "wof:placetype":"venue"
},
  "geometry": {"coordinates":[-87.34724900000001,36.519119],"type":"Point"}
}