{
  "type": "Feature",
  "properties": {
    "addr:full":"3128 Watauga Rd Johnson City TN 37694",
    "addr:housenumber":"3128",
    "addr:postcode":"37694",
    "addr:street":"Watauga Rd",
    "iso:country":"US",
    "sg:address":"3128 Watauga Rd",
    "sg:city":"Johnson City",
    "sg:classifiers":[
        {
            "category":"Autos & Motor Vehicles",
            "subcategory":"Automobile Sales",
            "type":"Retail Goods"
        }
    ],
    "sg:phone":"+1 423 929 0473",
    "sg:postcode":"37694",
    "sg:province":"TN",
    "sg:tags":[
        "used"
    ],
    "wof:name":"P & J Auto Sales",
    "wof:placetype":"venue"
},
  "geometry": {"coordinates":[-82.309725,36.365844],"type":"Point"}
}