{
  "type": "Feature",
  "properties": {
    "iso:country":"US",
    "sg:address":"238 Samsonite Blvd",
    "sg:city":"Murfreesboro",
    "sg:classifiers":[
        {
            "category":"Building & Trades",
            "subcategory":"Cleaning & Sanitation",
            "type":"Services"
        }
    ],
    "sg:phone":"+1 615 217 2222",
    "sg:postcode":"37129",
    "sg:province":"TN",
    "sg:tags":[
        "janitor"
    ],
    "wof:name":"Jackson Commercial Svc",
    "wof:placetype":"venue"
},
  "geometry": {"coordinates":[-86.39545200000001,35.827791],"type":"Point"}
}