{
  "type": "Feature",
  "properties": {
    "addr:full":"1401 Lynn Garden Dr Kingsport TN 37665",
    "addr:housenumber":"1401",
    "addr:postcode":"37665",
    "addr:street":"Lynn Garden Dr",
    "iso:country":"US",
    "sg:address":"1401 Lynn Garden Dr",
    "sg:city":"Kingsport",
    "sg:classifiers":[
        {
            "category":"Wholesale",
            "subcategory":"Plants",
            "type":"Manufacturing & Wholesale Goods"
        },
        {
            "category":"Farming",
            "subcategory":"Nursery",
            "type":"Manufacturing & Wholesale Goods"
        }
    ],
    "sg:phone":"+1 423 247 2161",
    "sg:postcode":"37665",
    "sg:province":"TN",
    "sg:tags":[
        "potted",
        "greenhouse",
        "stock"
    ],
    "wof:name":"Norton Greenhouse Company Inc",
    "wof:placetype":"venue"
},
  "geometry": {"coordinates":[-82.567662,36.577872],"type":"Point"}
}