{
  "type": "Feature",
  "properties": {
    "iso:country":"US",
    "sg:address":"6636 Burnt Knob Rd",
    "sg:city":"Murfreesboro",
    "sg:classifiers":[
        {
            "category":"Freight",
            "type":"Transportation"
        }
    ],
    "sg:phone":"+1 615 896 6610",
    "sg:postcode":"37129",
    "sg:province":"TN",
    "sg:tags":[
        "operator",
        "trucking"
    ],
    "wof:name":"Tonne Transport Inc",
    "wof:placetype":"venue"
},
  "geometry": {"coordinates":[-86.53990400000001,35.876246],"type":"Point"}
}