{
  "type": "Feature",
  "properties": {
    "iso:country":"US",
    "sg:address":"1703 Lebanon Pike Cir",
    "sg:city":"Nashville",
    "sg:classifiers":[
        {
            "category":"Freight",
            "type":"Transportation"
        }
    ],
    "sg:phone":"+1 615 889 0640",
    "sg:postcode":"37210",
    "sg:province":"TN",
    "sg:tags":[
        "operator",
        "trucking"
    ],
    "wof:name":"Bud Transportation",
    "wof:placetype":"venue"
},
  "geometry": {"coordinates":[-86.716205,36.152593],"type":"Point"}
}