{
  "type": "Feature",
  "properties": {
    "iso:country":"US",
    "sg:address":"8045 Hillsboro Hwy",
    "sg:city":"Hillsboro",
    "sg:classifiers":[
        {
            "category":"Food & Beverages",
            "subcategory":"Groceries & Convenience Stores",
            "type":"Retail Goods"
        }
    ],
    "sg:phone":"+1 931 596 4839",
    "sg:postcode":"37342",
    "sg:province":"TN",
    "wof:name":"41 KWIK Stop",
    "wof:placetype":"venue"
},
  "geometry": {"coordinates":[-85.967697,35.408026],"type":"Point"}
}