{
  "type": "Feature",
  "properties": {
    "iso:country":"US",
    "sg:address":"1045 Lavergne Cir",
    "sg:city":"Hendersonville",
    "sg:classifiers":[
        {
            "category":"Autos & Motor Vehicles",
            "subcategory":"Fuel & Gas Station",
            "type":"Retail Goods"
        },
        {
            "category":"Manufacturing",
            "subcategory":"Chemicals & Compounds",
            "type":"Manufacturing & Wholesale Goods"
        }
    ],
    "sg:phone":"+1 615 826 8932",
    "sg:postcode":"37075",
    "sg:province":"TN",
    "sg:tags":[
        "active",
        "management",
        "surface",
        "agent",
        "mfg"
    ],
    "sg:website":"www.tacbond.com",
    "wof:name":"Tennessee Adhesives Company",
    "wof:placetype":"venue"
},
  "geometry": {"coordinates":[-86.55648100000001,36.333636],"type":"Point"}
}