{
  "type": "Feature",
  "properties": {
    "addr:full":"5105 Maryland Way Brentwood TN 37027",
    "addr:housenumber":"5105",
    "addr:postcode":"37027",
    "addr:street":"Maryland Way",
    "iso:country":"US",
    "sg:address":"5105 Maryland Way",
    "sg:city":"Brentwood",
    "sg:classifiers":[
        {
            "category":"Real Estate",
            "subcategory":"Real Estate Agent",
            "type":"Services"
        }
    ],
    "sg:phone":"+1 615 371 9007",
    "sg:postcode":"37027",
    "sg:province":"TN",
    "sg:tags":[
        "building",
        "opera",
        "nonresidential"
    ],
    "wof:name":"Viva Properties",
    "wof:placetype":"venue"
},
  "geometry": {"coordinates":[-86.799074,36.033217],"type":"Point"}
}