{
  "type": "Feature",
  "properties": {
    "iso:country":"US",
    "sg:address":"958 W Main St",
    "sg:city":"Byrdstown",
    "sg:classifiers":[
        {
            "category":"Wholesale",
            "subcategory":"Auto Parts",
            "type":"Manufacturing & Wholesale Goods"
        }
    ],
    "sg:phone":"+1 931 864 6271",
    "sg:postcode":"38549",
    "sg:province":"TN",
    "sg:tags":[
        "automobile"
    ],
    "wof:name":"Stories Automotive Warehouse",
    "wof:placetype":"venue"
},
  "geometry": {"coordinates":[-85.153445,36.571968],"type":"Point"}
}