{
  "type": "Feature",
  "properties": {
    "addr:full":"5080 Malone Rd Memphis TN 38118",
    "addr:housenumber":"5080",
    "addr:postcode":"38118",
    "addr:street":"Malone Rd",
    "iso:country":"US",
    "sg:address":"5080 Malone Rd",
    "sg:city":"Memphis",
    "sg:classifiers":[
        {
            "category":"Freight",
            "type":"Transportation"
        }
    ],
    "sg:phone":"+1 901 743 9909",
    "sg:postcode":"38118",
    "sg:province":"TN",
    "sg:tags":[
        "operator",
        "trucking"
    ],
    "wof:name":"USA Motor Express Inc",
    "wof:placetype":"venue"
},
  "geometry": {"coordinates":[-89.919021,35.016929],"type":"Point"}
}