{
  "type": "Feature",
  "properties": {
    "iso:country":"US",
    "sg:address":"790 Halfmoon Rd",
    "sg:city":"Winchester",
    "sg:classifiers":[
        {
            "category":"Social Services",
            "subcategory":"Child Care",
            "type":"Services"
        }
    ],
    "sg:phone":"+1 931 967 7936",
    "sg:postcode":"37398",
    "sg:province":"TN",
    "sg:tags":[
        "day"
    ],
    "wof:name":"Wilma Fuqua",
    "wof:placetype":"venue"
},
  "geometry": {"coordinates":[-86.07314100000001,35.182917],"type":"Point"}
}