{
  "type": "Feature",
  "properties": {
    "iso:country":"US",
    "sg:address":"2109 Thomas Rd",
    "sg:city":"Memphis",
    "sg:classifiers":[
        {
            "category":"Manufacturing",
            "subcategory":"Textiles",
            "type":"Manufacturing & Wholesale Goods"
        },
        {
            "category":"Home & Garden",
            "subcategory":"Carpets & Floor Coverings",
            "type":"Retail Goods"
        }
    ],
    "sg:phone":"+1 901 384 7337",
    "sg:postcode":"38134",
    "sg:province":"TN",
    "sg:tags":[
        "tile-wholesale",
        "material",
        "manufacturer"
    ],
    "sg:website":"http://www.greerco.net",
    "wof:name":"Greer Co",
    "wof:placetype":"venue"
},
  "geometry": {"coordinates":[-89.887587,35.183478],"type":"Point"}
}