{
  "type": "Feature",
  "properties": {
    "addr:full":"1441 12th Ave S Nashville TN 37203",
    "addr:housenumber":"1441",
    "addr:postcode":"37203",
    "addr:street":"12Th Ave S",
    "iso:country":"US",
    "sg:address":"1441 12th Ave S",
    "sg:city":"Nashville",
    "sg:classifiers":[
        {
            "category":"Shopping",
            "type":"Retail Goods"
        }
    ],
    "sg:phone":"+1 615 269 6339",
    "sg:postcode":"37203",
    "sg:province":"TN",
    "sg:tags":[
        "salons-equipment",
        "supply",
        "cosmetic",
        "beauty",
        "perfume"
    ],
    "wof:name":"Tennessee Hair Plus Beauty Supply",
    "wof:placetype":"venue"
},
  "geometry": {"coordinates":[-86.788205,36.137517],"type":"Point"}
}