{
  "type": "Feature",
  "properties": {
    "iso:country":"US",
    "sg:address":"2369 Elvis Presley Blvd",
    "sg:city":"Memphis",
    "sg:classifiers":[
        {
            "category":"Shopping",
            "subcategory":"Pharmacy",
            "type":"Retail Goods"
        }
    ],
    "sg:phone":"+1 901 948 6622",
    "sg:postcode":"38116",
    "sg:province":"TN",
    "wof:name":"Champions Pharmacy & Herb Str",
    "wof:placetype":"venue"
},
  "geometry": {"coordinates":[-90.019001,35.080639],"type":"Point"}
}