{
  "type": "Feature",
  "properties": {
    "addr:full":"4564 Whites Creek Pike Whites Creek TN 37189",
    "addr:housenumber":"4564",
    "addr:postcode":"37189",
    "addr:street":"Whites Creek Pike",
    "iso:country":"US",
    "sg:address":"4564 Whites Creek Pike",
    "sg:city":"Whites Creek",
    "sg:classifiers":[
        {
            "category":"Building & Trades",
            "subcategory":"Landscaping Services",
            "type":"Services"
        }
    ],
    "sg:phone":"+1 615 876 7362",
    "sg:postcode":"37189",
    "sg:province":"TN",
    "wof:name":"Ultimate Lawn Service",
    "wof:placetype":"venue"
},
  "geometry": {"coordinates":[-86.839907,36.28484],"type":"Point"}
}