{
  "type": "Feature",
  "properties": {
    "iso:country":"US",
    "sg:address":"502 S Main St",
    "sg:city":"Memphis",
    "sg:classifiers":[
        {
            "category":"Manufacturing",
            "subcategory":"Printing",
            "type":"Manufacturing & Wholesale Goods"
        }
    ],
    "sg:phone":"+1 901 577 3005",
    "sg:postcode":"38103",
    "sg:province":"TN",
    "sg:tags":[
        "multimedia"
    ],
    "wof:name":"BFT Media",
    "wof:placetype":"venue"
},
  "geometry": {"coordinates":[-90.058913,35.133168],"type":"Point"}
}