{
  "type": "Feature",
  "properties": {
    "addr:full":"324 Spring St Clinton TN 37716",
    "addr:housenumber":"324",
    "addr:postcode":"37716",
    "addr:street":"Spring St",
    "iso:country":"US",
    "sg:address":"324 Spring St",
    "sg:city":"Clinton",
    "sg:classifiers":[
        {
            "category":"Retail",
            "subcategory":"Repair Shop",
            "type":"Services"
        }
    ],
    "sg:phone":"+1 865 457 5991",
    "sg:postcode":"37716",
    "sg:province":"TN",
    "sg:tags":[
        "upholsterer"
    ],
    "wof:name":"Hammond Upholstery",
    "wof:placetype":"venue"
},
  "geometry": {"coordinates":[-84.13269200000001,36.108175],"type":"Point"}
}