{
  "type": "Feature",
  "properties": {
    "iso:country":"US",
    "sg:address":"1846 S Highland Ave",
    "sg:city":"Jackson",
    "sg:classifiers":[
        {
            "category":"Banks & Credit Unions",
            "subcategory":"Financial Services",
            "type":"Services"
        }
    ],
    "sg:phone":"+1 731 427 3584",
    "sg:postcode":"38301",
    "sg:province":"TN",
    "sg:tags":[
        "trust",
        "investment",
        "real estate"
    ],
    "wof:name":"Lewis Investment",
    "wof:placetype":"venue"
},
  "geometry": {"coordinates":[-88.813665,35.561829],"type":"Point"}
}