{
  "type": "Feature",
  "properties": {
    "iso:country":"US",
    "sg:address":"3340 Poplar Ave",
    "sg:city":"Memphis",
    "sg:classifiers":[
        {
            "category":"Organizations",
            "subcategory":"Membership Organization",
            "type":"Services"
        }
    ],
    "sg:phone":"+1 901 458 4800",
    "sg:postcode":"38111",
    "sg:province":"TN",
    "sg:website":"www.madd.org",
    "wof:name":"Mothers Against Drunk Driving",
    "wof:placetype":"venue"
},
  "geometry": {"coordinates":[-89.951759,35.129507],"type":"Point"}
}