{
  "type": "Feature",
  "properties": {
    "iso:country":"US",
    "sg:address":"35 Ski Club Rd",
    "sg:city":"Harrison",
    "sg:classifiers":[
        {
            "category":"Professional",
            "subcategory":"Management & Consulting",
            "type":"Services"
        }
    ],
    "sg:phone":"+1 423 987 6512",
    "sg:postcode":"37341",
    "sg:province":"TN",
    "sg:tags":[
        "marketing",
        "consultant"
    ],
    "wof:name":"David Asbury Co",
    "wof:placetype":"venue"
},
  "geometry": {"coordinates":[-85.073812,35.21597],"type":"Point"}
}