{
  "type": "Feature",
  "properties": {
    "iso:country":"US",
    "sg:address":"1203 Foxwood Dr",
    "sg:city":"Sevierville",
    "sg:classifiers":[
        {
            "category":"Banks & Credit Unions",
            "subcategory":"Bank",
            "type":"Services"
        }
    ],
    "sg:phone":"+1 865 604 1888",
    "sg:postcode":"37862",
    "sg:province":"TN",
    "sg:tags":[
        "mortgage"
    ],
    "wof:name":"Hill Trust Mortgage Co",
    "wof:placetype":"venue"
},
  "geometry": {"coordinates":[-83.531373,35.850204],"type":"Point"}
}