{
  "type": "Feature",
  "properties": {
    "addr:full":"3935 Old Tasso Rd NE Cleveland TN 37312",
    "addr:housenumber":"3935",
    "addr:postcode":"37312",
    "addr:street":"Old Tasso Rd Ne",
    "iso:country":"US",
    "sg:address":"3935 Old Tasso Rd NE",
    "sg:city":"Cleveland",
    "sg:classifiers":[
        {
            "category":"Real Estate",
            "subcategory":"Real Estate Agent",
            "type":"Services"
        }
    ],
    "sg:phone":"+1 423 479 3793",
    "sg:postcode":"37312",
    "sg:province":"TN",
    "wof:name":"Davis Real Estate Co",
    "wof:placetype":"venue"
},
  "geometry": {"coordinates":[-84.83104299999999,35.180073],"type":"Point"}
}