{
  "type": "Feature",
  "properties": {
    "iso:country":"US",
    "sg:address":"407 Decatur Pike",
    "sg:city":"Athens",
    "sg:classifiers":[
        {
            "category":"Retail",
            "subcategory":"Auto Repair",
            "type":"Services"
        }
    ],
    "sg:phone":"+1 423 744 9721",
    "sg:postcode":"37303",
    "sg:province":"TN",
    "sg:tags":[
        "muffler",
        "exhaust",
        "system"
    ],
    "wof:name":"Maxi-Muffler",
    "wof:placetype":"venue"
},
  "geometry": {"coordinates":[-84.603387,35.448345],"type":"Point"}
}