{
  "type": "Feature",
  "properties": {
    "iso:country":"US",
    "sg:address":"8611 Camp Columbus Rd",
    "sg:city":"Hixson",
    "sg:classifiers":[
        {
            "category":"Education",
            "subcategory":"Special Training",
            "type":"Public Place"
        }
    ],
    "sg:phone":"+1 423 843 4755",
    "sg:postcode":"37343",
    "sg:province":"TN",
    "sg:tags":[
        "center"
    ],
    "wof:name":"Loftis Middle Sch Physical Edu",
    "wof:placetype":"venue"
},
  "geometry": {"coordinates":[-85.156898,35.196169],"type":"Point"}
}