{
  "type": "Feature",
  "properties": {
    "addr:full":"709 W Walnut St Johnson City TN 37604",
    "addr:housenumber":"709",
    "addr:postcode":"37604",
    "addr:street":"W Walnut St",
    "iso:country":"US",
    "sg:address":"709 W Walnut St",
    "sg:city":"Johnson City",
    "sg:classifiers":[
        {
            "category":"Manufacturing",
            "subcategory":"Tools & Machinery",
            "type":"Manufacturing & Wholesale Goods"
        }
    ],
    "sg:phone":"+1 423 232 7000",
    "sg:postcode":"37604",
    "sg:province":"TN",
    "sg:tags":[
        "game",
        "mfg",
        "carnival",
        "blower"
    ],
    "wof:name":"Huffer Manufacturing Inc",
    "wof:placetype":"venue"
},
  "geometry": {"coordinates":[-82.36164100000001,36.308488],"type":"Point"}
}