{
  "type": "Feature",
  "properties": {
    "iso:country":"US",
    "sg:address":"146 Rippy Ridge Rd",
    "sg:city":"Normandy",
    "sg:classifiers":[
        {
            "category":"Retail",
            "subcategory":"Repair Shop",
            "type":"Services"
        },
        {
            "category":"Home & Garden",
            "subcategory":"Garden Supply",
            "type":"Retail Goods"
        }
    ],
    "sg:phone":"+1 931 857 3673",
    "sg:postcode":"37360",
    "sg:province":"TN",
    "sg:tags":[
        "lawn",
        "mower"
    ],
    "wof:name":"Bruce's Small Engine",
    "wof:placetype":"venue"
},
  "geometry": {"coordinates":[-86.28539600000001,35.430428],"type":"Point"}
}