{
  "type": "Feature",
  "properties": {
    "iso:country":"US",
    "sg:address":"745 Co Rd 135",
    "sg:city":"Riceville",
    "sg:classifiers":[
        {
            "category":"Organizations",
            "subcategory":"Religious Organization",
            "type":"Services"
        }
    ],
    "sg:phone":"+1 423 462 2732",
    "sg:postcode":"37370",
    "sg:province":"TN",
    "wof:name":"Full Gospel Lighthouse Church",
    "wof:placetype":"venue"
},
  "geometry": {"coordinates":[-84.694385,35.393615],"type":"Point"}
}