{
  "type": "Feature",
  "properties": {
    "addr:full":"207 Sterling Rd Hendersonville TN 37075",
    "addr:housenumber":"207",
    "addr:postcode":"37075",
    "addr:street":"Sterling Rd",
    "iso:country":"US",
    "sg:address":"207 Sterling Rd",
    "sg:city":"Hendersonville",
    "sg:classifiers":[
        {
            "category":"Professional",
            "subcategory":"Computer Services",
            "type":"Services"
        }
    ],
    "sg:phone":"+1 615 264 2952",
    "sg:postcode":"37075",
    "sg:province":"TN",
    "sg:tags":[
        "datum"
    ],
    "wof:name":"Ogan Enterprises",
    "wof:placetype":"venue"
},
  "geometry": {"coordinates":[-86.61303599999999,36.250712],"type":"Point"}
}