{
  "type": "Feature",
  "properties": {
    "iso:country":"US",
    "sg:address":"2364 Mynatt Rd",
    "sg:city":"Knoxville",
    "sg:classifiers":[
        {
            "category":"Retail",
            "subcategory":"Auto Repair",
            "type":"Services"
        }
    ],
    "sg:phone":"+1 865 689 3628",
    "sg:postcode":"37918",
    "sg:province":"TN",
    "sg:tags":[
        "general"
    ],
    "wof:name":"Karnes Garage",
    "wof:placetype":"venue"
},
  "geometry": {"coordinates":[-83.94667200000001,36.047361],"type":"Point"}
}