{
  "type": "Feature",
  "properties": {
    "addr:full":"10325 McMinnville Hwy Morrison TN 37357",
    "addr:housenumber":"10325",
    "addr:postcode":"37357",
    "addr:street":"Mcminnville Hwy",
    "iso:country":"US",
    "sg:address":"10325 McMinnville Hwy",
    "sg:city":"Morrison",
    "sg:classifiers":[
        {
            "category":"Wholesale",
            "subcategory":"Farm Supplies",
            "type":"Manufacturing & Wholesale Goods"
        }
    ],
    "sg:phone":"+1 931 635 2732",
    "sg:postcode":"37357",
    "sg:province":"TN",
    "sg:tags":[
        "livestock"
    ],
    "wof:name":"Bryan Livestock",
    "wof:placetype":"venue"
},
  "geometry": {"coordinates":[-85.95039199999999,35.574968],"type":"Point"}
}