{
  "type": "Feature",
  "properties": {
    "iso:country":"US",
    "sg:address":"2915 Windsong Ct",
    "sg:city":"Murfreesboro",
    "sg:classifiers":[
        {
            "category":"Building & Trades",
            "subcategory":"Landscaping Services",
            "type":"Services"
        }
    ],
    "sg:phone":"+1 615 890 0095",
    "sg:postcode":"37129",
    "sg:province":"TN",
    "sg:tags":[
        "designer",
        "landscape"
    ],
    "wof:name":"Terri S Taylor Landscape Dsgnr",
    "wof:placetype":"venue"
},
  "geometry": {"coordinates":[-86.444422,35.880128],"type":"Point"}
}