{
  "type": "Feature",
  "properties": {
    "iso:country":"US",
    "sg:address":"224 S Church Ave",
    "sg:city":"Henderson",
    "sg:classifiers":[
        {
            "category":"Manufacturing",
            "subcategory":"Printing",
            "type":"Manufacturing & Wholesale Goods"
        }
    ],
    "sg:phone":"+1 731 989 1039",
    "sg:postcode":"38340",
    "sg:province":"TN",
    "sg:tags":[
        "printer"
    ],
    "sg:website":"www.chestercountyindependent.com",
    "wof:name":"Independent Publishing Inc",
    "wof:placetype":"venue"
},
  "geometry": {"coordinates":[-88.64267599999999,35.43498],"type":"Point"}
}