{
  "type": "Feature",
  "properties": {
    "addr:full":"407 Wild Plum Ln Crossville TN 38572",
    "addr:housenumber":"407",
    "addr:postcode":"38572",
    "addr:street":"Wild Plum Ln",
    "iso:country":"US",
    "sg:address":"407 Wild Plum Ln",
    "sg:city":"Crossville",
    "sg:classifiers":[
        {
            "category":"Sports & Exercise",
            "subcategory":"Golf",
            "type":"Entertainment"
        }
    ],
    "sg:phone":"+1 931 707 1640",
    "sg:postcode":"38572",
    "sg:province":"TN",
    "sg:tags":[
        "course",
        "public"
    ],
    "wof:name":"Bear Trace Cumberland Mountain",
    "wof:placetype":"venue"
},
  "geometry": {"coordinates":[-85.00684099999999,35.890112],"type":"Point"}
}