{
  "type": "Feature",
  "properties": {
    "iso:country":"US",
    "sg:address":"9636 Dayton Pike",
    "sg:city":"Soddy Daisy",
    "sg:classifiers":[
        {
            "category":"Autos & Motor Vehicles",
            "subcategory":"Automobile Sales",
            "type":"Retail Goods"
        }
    ],
    "sg:phone":"+1 423 332 2229",
    "sg:postcode":"37379",
    "sg:province":"TN",
    "sg:tags":[
        "car",
        "dealer"
    ],
    "wof:name":"Mark's Toys",
    "wof:placetype":"venue"
},
  "geometry": {"coordinates":[-85.191153,35.243215],"type":"Point"}
}