{
  "type": "Feature",
  "properties": {
    "addr:full":"259 A J Armes Rd Lancing TN 37770",
    "addr:housenumber":"259",
    "addr:postcode":"37770",
    "addr:street":"A J Armes Rd",
    "iso:country":"US",
    "sg:address":"259 A J Armes Rd",
    "sg:city":"Lancing",
    "sg:classifiers":[
        {
            "category":"Freight",
            "type":"Transportation"
        }
    ],
    "sg:phone":"+1 423 965 3074",
    "sg:postcode":"37770",
    "sg:province":"TN",
    "sg:tags":[
        "trucking"
    ],
    "wof:name":"R & M Trucking",
    "wof:placetype":"venue"
},
  "geometry": {"coordinates":[-84.72966099999999,36.09791],"type":"Point"}
}