{
  "type": "Feature",
  "properties": {
    "addr:full":"1312 Memorial Blvd Murfreesboro TN 37129",
    "addr:housenumber":"1312",
    "addr:postcode":"37129",
    "addr:street":"Memorial Blvd",
    "iso:country":"US",
    "sg:address":"1312 Memorial Blvd",
    "sg:city":"Murfreesboro",
    "sg:classifiers":[
        {
            "category":"Personal",
            "subcategory":"Beauty Salon",
            "type":"Services"
        }
    ],
    "sg:phone":"+1 615 898 1848",
    "sg:postcode":"37129",
    "sg:province":"TN",
    "wof:name":"Heads Up Hair Cutting Ctr",
    "wof:placetype":"venue"
},
  "geometry": {"coordinates":[-86.39803499999999,35.850966],"type":"Point"}
}