{
  "type": "Feature",
  "properties": {
    "iso:country":"US",
    "sg:address":"5159 Wheelis Dr",
    "sg:city":"Memphis",
    "sg:classifiers":[
        {
            "category":"Real Estate",
            "subcategory":"Real Estate Agent",
            "type":"Services"
        }
    ],
    "sg:phone":"+1 901 767 7338",
    "sg:postcode":"38117",
    "sg:province":"TN",
    "wof:name":"John McRee Realty",
    "wof:placetype":"venue"
},
  "geometry": {"coordinates":[-89.888891,35.114566],"type":"Point"}
}