{
  "type": "Feature",
  "properties": {
    "addr:full":"1151 Parkbrook Dr Friendsville TN 37737",
    "addr:housenumber":"1151",
    "addr:postcode":"37737",
    "addr:street":"Parkbrook Dr",
    "iso:country":"US",
    "sg:address":"1151 Parkbrook Dr",
    "sg:city":"Friendsville",
    "sg:classifiers":[
        {
            "category":"Building & Trades",
            "subcategory":"Construction",
            "type":"Services"
        }
    ],
    "sg:phone":"+1 865 995 9617",
    "sg:postcode":"37737",
    "sg:province":"TN",
    "sg:tags":[
        "house"
    ],
    "wof:name":"M Scott Bell Contractor",
    "wof:placetype":"venue"
},
  "geometry": {"coordinates":[-84.171886,35.770812],"type":"Point"}
}