{
  "type": "Feature",
  "properties": {
    "iso:country":"US",
    "sg:address":"1000 Main St",
    "sg:city":"Nashville",
    "sg:classifiers":[
        {
            "category":"Shopping",
            "subcategory":"Used Merchandise",
            "type":"Retail Goods"
        }
    ],
    "sg:phone":"+1 615 226 1401",
    "sg:postcode":"37206",
    "sg:province":"TN",
    "sg:tags":[
        "clothing"
    ],
    "wof:name":"Womens Clothing",
    "wof:placetype":"venue"
},
  "geometry": {"coordinates":[-86.752469,36.177709],"type":"Point"}
}