{
  "type": "Feature",
  "properties": {
    "addr:full":"4016 Edwards Ave Nashville TN 37216",
    "addr:housenumber":"4016",
    "addr:postcode":"37216",
    "addr:street":"Edwards Ave",
    "iso:country":"US",
    "sg:address":"4016 Edwards Ave",
    "sg:city":"Nashville",
    "sg:classifiers":[
        {
            "category":"Wholesale",
            "subcategory":"Scrap",
            "type":"Manufacturing & Wholesale Goods"
        }
    ],
    "sg:phone":"+1 615 262 9044",
    "sg:postcode":"37216",
    "sg:province":"TN",
    "sg:tags":[
        "recycling",
        "center"
    ],
    "wof:name":"Resource Recovery",
    "wof:placetype":"venue"
},
  "geometry": {"coordinates":[-86.738806,36.218705],"type":"Point"}
}