{
  "type": "Feature",
  "properties": {
    "iso:country":"US",
    "sg:address":"104 Eveningside Dr",
    "sg:city":"Chattanooga",
    "sg:classifiers":[
        {
            "category":"Professional",
            "subcategory":"Art Services",
            "type":"Services"
        }
    ],
    "sg:phone":"+1 423 622 4911",
    "sg:postcode":"37404",
    "sg:province":"TN",
    "sg:tags":[
        "commercial",
        "design"
    ],
    "wof:name":"James Courtney Inc",
    "wof:placetype":"venue"
},
  "geometry": {"coordinates":[-85.28391499999999,35.026609],"type":"Point"}
}