{
  "type": "Feature",
  "properties": {
    "iso:country":"US",
    "sg:address":"2308 Congress Pkwy NW",
    "sg:city":"Athens",
    "sg:classifiers":[
        {
            "category":"Personal",
            "subcategory":"Beauty Salon",
            "type":"Services"
        }
    ],
    "sg:phone":"+1 423 744 8423",
    "sg:postcode":"37303",
    "sg:province":"TN",
    "sg:tags":[
        "shop"
    ],
    "wof:name":"Hair Force",
    "wof:placetype":"venue"
},
  "geometry": {"coordinates":[-84.63493699999999,35.442171],"type":"Point"}
}