{
  "type": "Feature",
  "properties": {
    "iso:country":"US",
    "sg:address":"205 Evans St",
    "sg:city":"Livingston",
    "sg:classifiers":[
        {
            "category":"Freight",
            "type":"Transportation"
        }
    ],
    "sg:phone":"+1 931 823 1776",
    "sg:postcode":"38570",
    "sg:province":"TN",
    "sg:tags":[
        "commercial",
        "storage"
    ],
    "wof:name":"Livingston Self Storage",
    "wof:placetype":"venue"
},
  "geometry": {"coordinates":[-85.323418,36.38105],"type":"Point"}
}