{
  "type": "Feature",
  "properties": {
    "iso:country":"US",
    "sg:address":"370 Wallace Rd",
    "sg:city":"Nashville",
    "sg:classifiers":[
        {
            "category":"Professional",
            "subcategory":"Computer Services",
            "type":"Services"
        }
    ],
    "sg:phone":"+1 615 202 3147",
    "sg:postcode":"37211",
    "sg:province":"TN",
    "wof:name":"JET Computer Svc",
    "wof:placetype":"venue"
},
  "geometry": {"coordinates":[-86.725227,36.077425],"type":"Point"}
}