{
  "type": "Feature",
  "properties": {
    "iso:country":"US",
    "sg:address":"33 E Main St",
    "sg:city":"Hohenwald",
    "sg:classifiers":[
        {
            "category":"Sports & Exercise",
            "subcategory":"Gym",
            "type":"Entertainment"
        }
    ],
    "sg:phone":"+1 931 796 7001",
    "sg:postcode":"38462",
    "sg:province":"TN",
    "sg:tags":[
        "club",
        "health",
        "studio",
        "gymnasium"
    ],
    "wof:name":"Body Pro Gym",
    "wof:placetype":"venue"
},
  "geometry": {"coordinates":[-87.55172399999999,35.547957],"type":"Point"}
}