{
  "type": "Feature",
  "properties": {
    "iso:country":"US",
    "sg:address":"310 Falcon St",
    "sg:city":"Greenfield",
    "sg:classifiers":[
        {
            "category":"Autos & Motor Vehicles",
            "subcategory":"Automobile Sales",
            "type":"Retail Goods"
        }
    ],
    "sg:phone":"+1 731 235 9000",
    "sg:postcode":"38230",
    "sg:province":"TN",
    "sg:tags":[
        "car",
        "dealer"
    ],
    "wof:name":"Yellowjacket Auto Sales",
    "wof:placetype":"venue"
},
  "geometry": {"coordinates":[-88.794737,36.158406],"type":"Point"}
}