{
  "type": "Feature",
  "properties": {
    "iso:country":"US",
    "sg:address":"612 Beersheba Hwy",
    "sg:city":"Mc Minnville",
    "sg:classifiers":[
        {
            "category":"Restaurant",
            "type":"Food & Drink"
        }
    ],
    "sg:phone":"+1 931 473 7342",
    "sg:postcode":"37110",
    "sg:province":"TN",
    "sg:tags":[
        "eating"
    ],
    "wof:name":"Dairy Hill",
    "wof:placetype":"venue"
},
  "geometry": {"coordinates":[-85.757496,35.671748],"type":"Point"}
}