{
  "type": "Feature",
  "properties": {
    "addr:full":"3131 N Highland Ave Jackson TN 38305",
    "addr:housenumber":"3131",
    "addr:postcode":"38305",
    "addr:street":"N Highland Ave",
    "iso:country":"US",
    "sg:address":"3131 N Highland Ave",
    "sg:city":"Jackson",
    "sg:classifiers":[
        {
            "category":"Social Services",
            "subcategory":"Job Training",
            "type":"Services"
        }
    ],
    "sg:phone":"+1 731 668 9299",
    "sg:postcode":"38305",
    "sg:province":"TN",
    "sg:tags":[
        "rehabilitation"
    ],
    "wof:name":"Alliance Care",
    "wof:placetype":"venue"
},
  "geometry": {"coordinates":[-88.829899,35.694877],"type":"Point"}
}