{
  "type": "Feature",
  "properties": {
    "addr:full":"702 Sparta St Mc Minnville TN 37110",
    "addr:housenumber":"702",
    "addr:postcode":"37110",
    "addr:street":"Sparta St",
    "iso:country":"US",
    "sg:address":"702 Sparta St",
    "sg:city":"Mc Minnville",
    "sg:classifiers":[
        {
            "category":"Taxi",
            "type":"Transportation"
        }
    ],
    "sg:phone":"+1 931 473 2451",
    "sg:postcode":"37110",
    "sg:province":"TN",
    "sg:tags":[
        "taxicab"
    ],
    "wof:name":"A A Cab",
    "wof:placetype":"venue"
},
  "geometry": {"coordinates":[-85.76382599999999,35.687271],"type":"Point"}
}