{
  "type": "Feature",
  "properties": {
    "addr:full":"6655 State Hwy 89 Palmersville TN 38241",
    "addr:housenumber":"6655",
    "addr:postcode":"38241",
    "addr:street":"State Hwy 89",
    "iso:country":"US",
    "sg:address":"6655 State Hwy 89",
    "sg:city":"Palmersville",
    "sg:classifiers":[
        {
            "category":"Wholesale",
            "subcategory":"Farm Supplies",
            "type":"Manufacturing & Wholesale Goods"
        }
    ],
    "sg:phone":"+1 731 822 5345",
    "sg:postcode":"38241",
    "sg:province":"TN",
    "sg:tags":[
        "fertilizer"
    ],
    "wof:name":"Royster-Clark Inc",
    "wof:placetype":"venue"
},
  "geometry": {"coordinates":[-88.586197,36.404878],"type":"Point"}
}