{
  "type": "Feature",
  "properties": {
    "iso:country":"US",
    "sg:address":"2115 Elm Hill Pike",
    "sg:city":"Nashville",
    "sg:classifiers":[
        {
            "category":"Professional",
            "subcategory":"Advertising",
            "type":"Services"
        }
    ],
    "sg:phone":"+1 615 361 5884",
    "sg:postcode":"37210",
    "sg:province":"TN",
    "sg:tags":[
        "product",
        "promotional"
    ],
    "sg:website":"www.dcagency.com",
    "wof:name":"Dalmatian Creative Agency",
    "wof:placetype":"venue"
},
  "geometry": {"coordinates":[-86.69265799999999,36.150912],"type":"Point"}
}