{
  "type": "Feature",
  "properties": {
    "iso:country":"US",
    "sg:address":"1991 Madison St",
    "sg:city":"Clarksville",
    "sg:classifiers":[
        {
            "category":"Travel",
            "subcategory":"Hotels & Motels",
            "type":"Entertainment"
        }
    ],
    "sg:phone":"+1 931 645 4573",
    "sg:postcode":"37043",
    "sg:province":"TN",
    "sg:tags":[
        "operation"
    ],
    "wof:name":"Meadows Motel",
    "wof:placetype":"venue"
},
  "geometry": {"coordinates":[-87.292964,36.513342],"type":"Point"}
}