{
  "type": "Feature",
  "properties": {
    "iso:country":"US",
    "sg:address":"4271 S 3rd St",
    "sg:city":"Memphis",
    "sg:classifiers":[
        {
            "category":"Shopping",
            "subcategory":"Bicycles & Sporting Goods",
            "type":"Retail Goods"
        }
    ],
    "sg:phone":"+1 901 785 0302",
    "sg:postcode":"38109",
    "sg:province":"TN",
    "sg:tags":[
        "tackle",
        "fishing"
    ],
    "wof:name":"J & H Bait Shop",
    "wof:placetype":"venue"
},
  "geometry": {"coordinates":[-90.07402399999999,35.034717],"type":"Point"}
}