{
  "type": "Feature",
  "properties": {
    "iso:country":"US",
    "sg:address":"101 Windrock View Ln",
    "sg:city":"Oliver Springs",
    "sg:classifiers":[
        {
            "category":"Professional",
            "subcategory":"Testing Lab",
            "type":"Services"
        }
    ],
    "sg:phone":"+1 865 435 5923",
    "sg:postcode":"37840",
    "sg:province":"TN",
    "sg:tags":[
        "laboratory"
    ],
    "wof:name":"Patron Analytical Services LLC",
    "wof:placetype":"venue"
},
  "geometry": {"coordinates":[-84.38650699999999,35.967561],"type":"Point"}
}