{
  "type": "Feature",
  "properties": {
    "iso:country":"US",
    "sg:address":"1104 Skyline Dr",
    "sg:city":"Johnson City",
    "sg:classifiers":[
        {
            "category":"Shopping",
            "subcategory":"Clothing, Apparel, & Fashions",
            "type":"Retail Goods"
        }
    ],
    "sg:phone":"+1 423 928 5198",
    "sg:postcode":"37604",
    "sg:province":"TN",
    "sg:tags":[
        "family"
    ],
    "wof:name":"Ambers Wilson Jr",
    "wof:placetype":"venue"
},
  "geometry": {"coordinates":[-82.383616,36.321414],"type":"Point"}
}