{
  "type": "Feature",
  "properties": {
    "iso:country":"US",
    "sg:address":"20330 E Main St",
    "sg:city":"Huntingdon",
    "sg:classifiers":[
        {
            "category":"Food & Beverages",
            "subcategory":"Groceries & Convenience Stores",
            "type":"Retail Goods"
        }
    ],
    "sg:phone":"+1 731 986 9043",
    "sg:postcode":"38344",
    "sg:province":"TN",
    "wof:name":"Sal 880",
    "wof:placetype":"venue"
},
  "geometry": {"coordinates":[-88.417196,36.003867],"type":"Point"}
}