{
  "type": "Feature",
  "properties": {
    "addr:full":"4824 Petersburg Rd Knoxville TN 37921",
    "addr:housenumber":"4824",
    "addr:postcode":"37921",
    "addr:street":"Petersburg Rd",
    "iso:country":"US",
    "sg:address":"4824 Petersburg Rd",
    "sg:city":"Knoxville",
    "sg:classifiers":[
        {
            "category":"Professional",
            "subcategory":"Business Services",
            "type":"Services"
        }
    ],
    "sg:phone":"+1 865 588 7145",
    "sg:postcode":"37921",
    "sg:province":"TN",
    "wof:name":"Quick Messenger Service Inc",
    "wof:placetype":"venue"
},
  "geometry": {"coordinates":[-83.999782,35.978242],"type":"Point"}
}