{
  "type": "Feature",
  "properties": {
    "addr:full":"41 Tusculum Rd Antioch TN 37013",
    "addr:housenumber":"41",
    "addr:postcode":"37013",
    "addr:street":"Tusculum Rd",
    "iso:country":"US",
    "sg:address":"41 Tusculum Rd",
    "sg:city":"Antioch",
    "sg:classifiers":[
        {
            "category":"Organizations",
            "subcategory":"Religious Organization",
            "type":"Services"
        }
    ],
    "sg:phone":"+1 615 832 6248",
    "sg:postcode":"37013",
    "sg:province":"TN",
    "wof:name":"Antioch United Methdst Church",
    "wof:placetype":"venue"
},
  "geometry": {"coordinates":[-86.675799,36.052937],"type":"Point"}
}