{
  "type": "Feature",
  "properties": {
    "addr:full":"815 S James Campbell Blvd Columbia TN 38401",
    "addr:housenumber":"815",
    "addr:postcode":"38401",
    "addr:street":"S James Campbell Blvd",
    "iso:country":"US",
    "sg:address":"815 S James Campbell Blvd",
    "sg:city":"Columbia",
    "sg:classifiers":[
        {
            "category":"Restaurant",
            "type":"Food & Drink"
        }
    ],
    "sg:phone":"+1 931 381 1233",
    "sg:postcode":"38401",
    "sg:province":"TN",
    "wof:name":"Blue Island Buffet",
    "wof:placetype":"venue"
},
  "geometry": {"coordinates":[-87.056939,35.596237],"type":"Point"}
}