{
  "type": "Feature",
  "properties": {
    "iso:country":"US",
    "sg:address":"607 W Main St",
    "sg:city":"Humboldt",
    "sg:classifiers":[
        {
            "category":"Restaurant",
            "type":"Food & Drink"
        }
    ],
    "sg:phone":"+1 731 784 9450",
    "sg:postcode":"38343",
    "sg:province":"TN",
    "wof:name":"Armour's Bar-B-Que",
    "wof:placetype":"venue"
},
  "geometry": {"coordinates":[-88.922506,35.82014],"type":"Point"}
}