{
  "type": "Feature",
  "properties": {
    "iso:country":"US",
    "sg:address":"2112 Hollywood Dr",
    "sg:city":"Jackson",
    "sg:classifiers":[
        {
            "category":"Building & Trades",
            "subcategory":"Construction",
            "type":"Services"
        }
    ],
    "sg:phone":"+1 731 427 4481",
    "sg:postcode":"38305",
    "sg:province":"TN",
    "sg:tags":[
        "contractor"
    ],
    "wof:name":"Johnson Roofing Company",
    "wof:placetype":"venue"
},
  "geometry": {"coordinates":[-88.87087200000001,35.653612],"type":"Point"}
}