{
  "type": "Feature",
  "properties": {
    "iso:country":"US",
    "sg:address":"1730 N Germantown Pkwy",
    "sg:city":"Cordova",
    "sg:classifiers":[
        {
            "category":"Real Estate",
            "subcategory":"Real Estate Agent",
            "type":"Services"
        }
    ],
    "sg:phone":"+1 901 755 4001",
    "sg:postcode":"38016",
    "sg:province":"TN",
    "wof:name":"Traditional Properties",
    "wof:placetype":"venue"
},
  "geometry": {"coordinates":[-89.792834,35.173079],"type":"Point"}
}