{
  "type": "Feature",
  "properties": {
    "iso:country":"US",
    "sg:address":"1121 Myrtle St",
    "sg:city":"Kingsport",
    "sg:classifiers":[
        {
            "category":"Organizations",
            "subcategory":"Religious Organization",
            "type":"Services"
        }
    ],
    "sg:phone":"+1 423 245 7994",
    "sg:postcode":"37660",
    "sg:province":"TN",
    "wof:name":"Victory Apostolic Church",
    "wof:placetype":"venue"
},
  "geometry": {"coordinates":[-82.54544,36.540154],"type":"Point"}
}