{
  "type": "Feature",
  "properties": {
    "iso:country":"US",
    "sg:address":"418 W Palestine Ave",
    "sg:city":"Obion",
    "sg:classifiers":[
        {
            "category":"Food & Beverages",
            "subcategory":"Groceries & Convenience Stores",
            "type":"Retail Goods"
        }
    ],
    "sg:phone":"+1 731 536 6472",
    "sg:postcode":"38240",
    "sg:province":"TN",
    "wof:name":"Obion Food Plz",
    "wof:placetype":"venue"
},
  "geometry": {"coordinates":[-89.19513000000001,36.260459],"type":"Point"}
}