{
  "type": "Feature",
  "properties": {
    "iso:country":"US",
    "sg:address":"717 Myers Rd",
    "sg:city":"Tracy City",
    "sg:classifiers":[
        {
            "category":"Organizations",
            "subcategory":"Religious Organization",
            "type":"Services"
        }
    ],
    "sg:phone":"+1 931 592 2671",
    "sg:postcode":"37398",
    "sg:province":"TN",
    "sg:tags":[
        "church"
    ],
    "wof:name":"Myers Hill First Congregation",
    "wof:placetype":"venue"
},
  "geometry": {"coordinates":[-86.14026800000001,35.212214],"type":"Point"}
}