{
  "type": "Feature",
  "properties": {
    "iso:country":"US",
    "sg:address":"2014 State Hwy 13 S",
    "sg:city":"Waverly",
    "sg:classifiers":[
        {
            "category":"Utilities",
            "subcategory":"Refuse",
            "type":"Services"
        }
    ],
    "sg:phone":"+1 931 296 4814",
    "sg:postcode":"37185",
    "sg:province":"TN",
    "sg:tags":[
        "garbage",
        "collection"
    ],
    "wof:name":"Jesse Turner Meml Convenience",
    "wof:placetype":"venue"
},
  "geometry": {"coordinates":[-87.78130899999999,36.065052],"type":"Point"}
}