{
  "type": "Feature",
  "properties": {
    "addr:full":"424 Heathermoor Dr Knoxville TN 37934",
    "addr:housenumber":"424",
    "addr:postcode":"37934",
    "addr:street":"Heathermoor Dr",
    "iso:country":"US",
    "sg:address":"424 Heathermoor Dr",
    "sg:city":"Knoxville",
    "sg:classifiers":[
        {
            "category":"Building & Trades",
            "subcategory":"Construction",
            "type":"Services"
        }
    ],
    "sg:phone":"+1 865 966 8645",
    "sg:postcode":"37934",
    "sg:province":"TN",
    "sg:tags":[
        "general",
        "contractor"
    ],
    "wof:name":"Markli Construction Co Inc",
    "wof:placetype":"venue"
},
  "geometry": {"coordinates":[-84.19100299999999,35.88293],"type":"Point"}
}