{
  "type": "Feature",
  "properties": {
    "iso:country":"US",
    "sg:address":"130 Donelson Pike",
    "sg:city":"Nashville",
    "sg:classifiers":[
        {
            "category":"Health Services",
            "subcategory":"Doctor",
            "type":"Services"
        }
    ],
    "sg:phone":"+1 615 889 7111",
    "sg:postcode":"37214",
    "sg:province":"TN",
    "sg:tags":[
        "dentist"
    ],
    "wof:name":"John A Gholson III DDS",
    "wof:placetype":"venue"
},
  "geometry": {"coordinates":[-86.66332,36.167667],"type":"Point"}
}