{
  "type": "Feature",
  "properties": {
    "iso:country":"US",
    "sg:address":"1642 J P Hennessy Dr",
    "sg:city":"La Vergne",
    "sg:classifiers":[
        {
            "category":"Manufacturing",
            "subcategory":"Chemicals & Compounds",
            "type":"Manufacturing & Wholesale Goods"
        }
    ],
    "sg:phone":"+1 615 641 3600",
    "sg:postcode":"37086",
    "sg:province":"TN",
    "sg:tags":[
        "composite"
    ],
    "wof:name":"Composites One",
    "wof:placetype":"venue"
},
  "geometry": {"coordinates":[-86.601792,36.012883],"type":"Point"}
}