{
  "type": "Feature",
  "properties": {
    "iso:country":"US",
    "sg:address":"7509 Chapman Hwy",
    "sg:city":"Knoxville",
    "sg:classifiers":[
        {
            "category":"Restaurant",
            "type":"Food & Drink"
        }
    ],
    "sg:phone":"+1 865 577 3333",
    "sg:postcode":"37920",
    "sg:province":"TN",
    "wof:name":"Pancho's Mexican Restaurant #2",
    "wof:placetype":"venue"
},
  "geometry": {"coordinates":[-83.84282,35.908058],"type":"Point"}
}