{
  "type": "Feature",
  "properties": {
    "iso:country":"US",
    "sg:address":"607 Teree Dr",
    "sg:city":"Gallatin",
    "sg:classifiers":[
        {
            "category":"Professional",
            "subcategory":"Lawyer & Legal Services",
            "type":"Services"
        }
    ],
    "sg:phone":"+1 615 452 8256",
    "sg:postcode":"37066",
    "sg:province":"TN",
    "wof:name":"Fox Ronnie C CPA",
    "wof:placetype":"venue"
},
  "geometry": {"coordinates":[-86.437014,36.400645],"type":"Point"}
}