{
  "type": "Feature",
  "properties": {
    "iso:country":"US",
    "sg:address":"711 Ohio Ave",
    "sg:city":"Etowah",
    "sg:classifiers":[
        {
            "category":"Home & Garden",
            "subcategory":"Furniture",
            "type":"Retail Goods"
        }
    ],
    "sg:phone":"+1 423 263 7265",
    "sg:postcode":"37331",
    "sg:province":"TN",
    "sg:tags":[
        "clot",
        "household",
        "appliance"
    ],
    "wof:name":"Rules Furniture & Appliances",
    "wof:placetype":"venue"
},
  "geometry": {"coordinates":[-84.52642400000001,35.323885],"type":"Point"}
}