{
  "type": "Feature",
  "properties": {
    "iso:country":"US",
    "sg:address":"911 Grievers Chapel Rd",
    "sg:city":"Rockwood",
    "sg:classifiers":[
        {
            "category":"Building & Trades",
            "subcategory":"Construction",
            "type":"Services"
        }
    ],
    "sg:phone":"+1 865 354 9532",
    "sg:postcode":"37854",
    "sg:province":"TN",
    "sg:tags":[
        "excavation",
        "contractor"
    ],
    "wof:name":"Triple C Excavating",
    "wof:placetype":"venue"
},
  "geometry": {"coordinates":[-84.782726,35.858275],"type":"Point"}
}