{
  "type": "Feature",
  "properties": {
    "iso:country":"US",
    "sg:address":"303 Jarnigan Ave",
    "sg:city":"Morristown",
    "sg:classifiers":[
        {
            "category":"Food & Beverages",
            "subcategory":"Groceries & Convenience Stores",
            "type":"Retail Goods"
        }
    ],
    "sg:phone":"+1 423 581 5717",
    "sg:postcode":"37813",
    "sg:province":"TN",
    "wof:name":"West Side Food Market",
    "wof:placetype":"venue"
},
  "geometry": {"coordinates":[-83.306331,36.203603],"type":"Point"}
}