{
  "type": "Feature",
  "properties": {
    "addr:full":"589 Jim McKenzie Rd Brighton TN 38011",
    "addr:housenumber":"589",
    "addr:postcode":"38011",
    "addr:street":"Jim Mckenzie Rd",
    "iso:country":"US",
    "sg:address":"589 Jim McKenzie Rd",
    "sg:city":"Brighton",
    "sg:classifiers":[
        {
            "category":"Farming",
            "subcategory":"Farm",
            "type":"Manufacturing & Wholesale Goods"
        }
    ],
    "sg:phone":"+1 901 476 6041",
    "sg:postcode":"38011",
    "sg:province":"TN",
    "sg:tags":[
        "crop",
        "general"
    ],
    "wof:name":"A Goforth",
    "wof:placetype":"venue"
},
  "geometry": {"coordinates":[-89.721051,35.543346],"type":"Point"}
}