{
  "type": "Feature",
  "properties": {
    "iso:country":"US",
    "sg:address":"1343 N Willett St",
    "sg:city":"Memphis",
    "sg:classifiers":[
        {
            "category":"Organizations",
            "subcategory":"Membership Organization",
            "type":"Services"
        }
    ],
    "sg:phone":"+1 901 725 0861",
    "sg:postcode":"38108",
    "sg:province":"TN",
    "wof:name":"New Chelsea Neighborhood Assn",
    "wof:placetype":"venue"
},
  "geometry": {"coordinates":[-90.005888,35.17467],"type":"Point"}
}