{
  "type": "Feature",
  "properties": {
    "iso:country":"US",
    "sg:address":"165 W Broad St",
    "sg:city":"Cookeville",
    "sg:classifiers":[
        {
            "category":"Retail",
            "subcategory":"Auto Repair",
            "type":"Services"
        }
    ],
    "sg:phone":"+1 931 520 7587",
    "sg:postcode":"38501",
    "sg:province":"TN",
    "sg:tags":[
        "body"
    ],
    "wof:name":"Restorations",
    "wof:placetype":"venue"
},
  "geometry": {"coordinates":[-85.509146,36.164677],"type":"Point"}
}