{
  "type": "Feature",
  "properties": {
    "addr:full":"3023 Sweetwater Vonore Rd Sweetwater TN 37874",
    "addr:housenumber":"3023",
    "addr:postcode":"37874",
    "addr:street":"Sweetwater Vonore Rd",
    "iso:country":"US",
    "sg:address":"3023 Sweetwater Vonore Rd",
    "sg:city":"Sweetwater",
    "sg:classifiers":[
        {
            "category":"Organizations",
            "subcategory":"Religious Organization",
            "type":"Services"
        }
    ],
    "sg:phone":"+1 423 337 9467",
    "sg:postcode":"37874",
    "sg:province":"TN",
    "wof:name":"Trinity Baptist Church",
    "wof:placetype":"venue"
},
  "geometry": {"coordinates":[-84.369888,35.600186],"type":"Point"}
}