{
  "type": "Feature",
  "properties": {
    "iso:country":"US",
    "sg:address":"1230 E Pkwy",
    "sg:city":"Gatlinburg",
    "sg:classifiers":[
        {
            "category":"Government",
            "subcategory":"Police Station",
            "type":"Public Place"
        }
    ],
    "sg:phone":"+1 865 436 5181",
    "sg:postcode":"37738",
    "sg:province":"TN",
    "sg:tags":[
        "department"
    ],
    "wof:name":"Gatlinburg Police Department",
    "wof:placetype":"venue"
},
  "geometry": {"coordinates":[-83.48358500000001,35.726087],"type":"Point"}
}