{
  "type": "Feature",
  "properties": {
    "iso:country":"US",
    "sg:address":"8606 Coppock Rd",
    "sg:city":"Corryton",
    "sg:classifiers":[
        {
            "category":"Professional",
            "type":"Services"
        }
    ],
    "sg:phone":"+1 865 922 7353",
    "sg:postcode":"37721",
    "sg:province":"TN",
    "wof:name":"88 Keys Piano Svc",
    "wof:placetype":"venue"
},
  "geometry": {"coordinates":[-83.887027,36.141857],"type":"Point"}
}