{
  "type": "Feature",
  "properties": {
    "iso:country":"US",
    "sg:address":"5184 Verosa Ave",
    "sg:city":"Memphis",
    "sg:classifiers":[
        {
            "category":"Professional",
            "subcategory":"Computer Services",
            "type":"Services"
        }
    ],
    "sg:phone":"+1 901 821 0203",
    "sg:postcode":"38117",
    "sg:province":"TN",
    "wof:name":"Bh Computer Services",
    "wof:placetype":"venue"
},
  "geometry": {"coordinates":[-89.89122500000001,35.143165],"type":"Point"}
}