{
  "type": "Feature",
  "properties": {
    "addr:full":"315 W College St Pulaski TN 38478",
    "addr:housenumber":"315",
    "addr:postcode":"38478",
    "addr:street":"W College St",
    "iso:country":"US",
    "sg:address":"315 W College St",
    "sg:city":"Pulaski",
    "sg:classifiers":[
        {
            "category":"Retail",
            "subcategory":"Laundry & Dry Cleaning",
            "type":"Services"
        }
    ],
    "sg:phone":"+1 931 363 3553",
    "sg:postcode":"38478",
    "sg:province":"TN",
    "sg:tags":[
        "drycleaning",
        "plant",
        "agent",
        "garment"
    ],
    "wof:name":"Young Cleaners",
    "wof:placetype":"venue"
},
  "geometry": {"coordinates":[-87.035509,35.19787],"type":"Point"}
}