{
  "type": "Feature",
  "properties": {
    "iso:country":"US",
    "sg:address":"3101 Washington Pike NE",
    "sg:city":"Knoxville",
    "sg:classifiers":[
        {
            "category":"Real Estate",
            "subcategory":"Real Estate Operator",
            "type":"Services"
        }
    ],
    "sg:phone":"+1 865 544 1754",
    "sg:postcode":"37917",
    "sg:province":"TN",
    "sg:tags":[
        "building",
        "apartment"
    ],
    "wof:name":"Washington Ridge APT Homes",
    "wof:placetype":"venue"
},
  "geometry": {"coordinates":[-83.902405,36.009327],"type":"Point"}
}