{
  "type": "Feature",
  "properties": {
    "iso:country":"US",
    "sg:address":"323 E James Campbell Blvd",
    "sg:city":"Columbia",
    "sg:classifiers":[
        {
            "category":"Insurance",
            "subcategory":"Insurance Agent",
            "type":"Services"
        }
    ],
    "sg:phone":"+1 931 388 2935",
    "sg:postcode":"38401",
    "sg:province":"TN",
    "wof:name":"State Farm Insurance",
    "wof:placetype":"venue"
},
  "geometry": {"coordinates":[-87.02851699999999,35.588787],"type":"Point"}
}