{
  "type": "Feature",
  "properties": {
    "addr:full":"1703 E Broadway Ave Maryville TN 37804",
    "addr:housenumber":"1703",
    "addr:postcode":"37804",
    "addr:street":"E Broadway Ave",
    "iso:country":"US",
    "sg:address":"1703 E Broadway Ave",
    "sg:city":"Maryville",
    "sg:classifiers":[
        {
            "category":"Home & Garden",
            "subcategory":"Building Materials",
            "type":"Retail Goods"
        }
    ],
    "sg:phone":"+1 865 970 2811",
    "sg:postcode":"37804",
    "sg:province":"TN",
    "sg:tags":[
        "glass",
        "window",
        "plate"
    ],
    "wof:name":"East Tennessee Glass & Supply",
    "wof:placetype":"venue"
},
  "geometry": {"coordinates":[-83.956461,35.772857],"type":"Point"}
}