{
  "type": "Feature",
  "properties": {
    "addr:full":"3014 S Perkins Rd Memphis TN 38118",
    "addr:housenumber":"3014",
    "addr:postcode":"38118",
    "addr:street":"S Perkins Rd",
    "iso:country":"US",
    "sg:address":"3014 S Perkins Rd",
    "sg:city":"Memphis",
    "sg:classifiers":[
        {
            "category":"Personal",
            "subcategory":"Beauty Salon",
            "type":"Services"
        }
    ],
    "sg:phone":"+1 901 794 0323",
    "sg:postcode":"38118",
    "sg:province":"TN",
    "wof:name":"Hart Of Hair Full Svc Salon",
    "wof:placetype":"venue"
},
  "geometry": {"coordinates":[-89.90560000000001,35.068519],"type":"Point"}
}