{
  "type": "Feature",
  "properties": {
    "addr:full":"2626 Old Lebanon Rd Nashville TN 37214",
    "addr:housenumber":"2626",
    "addr:postcode":"37214",
    "addr:street":"Old Lebanon Rd",
    "iso:country":"US",
    "sg:address":"2626 Old Lebanon Rd",
    "sg:city":"Nashville",
    "sg:classifiers":[
        {
            "category":"Manufacturing",
            "subcategory":"Metals",
            "type":"Manufacturing & Wholesale Goods"
        }
    ],
    "sg:phone":"+1 615 889 8341",
    "sg:postcode":"37214",
    "sg:province":"TN",
    "sg:tags":[
        "screw",
        "bolt",
        "mfg"
    ],
    "wof:name":"Nashville Bolt LLC",
    "wof:placetype":"venue"
},
  "geometry": {"coordinates":[-86.670956,36.169982],"type":"Point"}
}