{
  "type": "Feature",
  "properties": {
    "addr:full":"675 Back Valley Rd Dayton TN 37321",
    "addr:housenumber":"675",
    "addr:postcode":"37321",
    "addr:street":"Back Valley Rd",
    "iso:country":"US",
    "sg:address":"675 Back Valley Rd",
    "sg:city":"Dayton",
    "sg:classifiers":[
        {
            "category":"Organizations",
            "subcategory":"Religious Organization",
            "type":"Services"
        }
    ],
    "sg:phone":"+1 423 775 1466",
    "sg:postcode":"37321",
    "sg:province":"TN",
    "wof:name":"Shamah Christian Ctr",
    "wof:placetype":"venue"
},
  "geometry": {"coordinates":[-85.024218,35.506885],"type":"Point"}
}