{
  "type": "Feature",
  "properties": {
    "iso:country":"US",
    "sg:address":"119 E Race St",
    "sg:city":"Kingston",
    "sg:classifiers":[
        {
            "category":"Shopping",
            "subcategory":"Used Merchandise",
            "type":"Retail Goods"
        },
        {
            "category":"Shopping",
            "subcategory":"Clothing, Apparel, & Fashions",
            "type":"Retail Goods"
        }
    ],
    "sg:phone":"+1 865 376 3170",
    "sg:postcode":"37763",
    "sg:province":"TN",
    "sg:tags":[
        "family"
    ],
    "wof:name":"Consigning Women & Kids",
    "wof:placetype":"venue"
},
  "geometry": {"coordinates":[-84.516561,35.871383],"type":"Point"}
}