{
  "type": "Feature",
  "properties": {
    "iso:country":"US",
    "sg:address":"319 Hickory Pl",
    "sg:city":"Nashville",
    "sg:classifiers":[
        {
            "category":"Professional",
            "type":"Services"
        }
    ],
    "sg:phone":"+1 615 758 2122",
    "sg:postcode":"37214",
    "sg:province":"TN",
    "wof:name":"Gre LLC",
    "wof:placetype":"venue"
},
  "geometry": {"coordinates":[-86.642528,36.158784],"type":"Point"}
}