{
  "type": "Feature",
  "properties": {
    "iso:country":"US",
    "sg:address":"1414 Kyle St",
    "sg:city":"Memphis",
    "sg:classifiers":[
        {
            "category":"Retail",
            "subcategory":"Repair Shop",
            "type":"Services"
        }
    ],
    "sg:phone":"+1 901 725 6616",
    "sg:postcode":"38106",
    "sg:province":"TN",
    "wof:name":"Four Star Repair Service",
    "wof:placetype":"venue"
},
  "geometry": {"coordinates":[-90.004811,35.106883],"type":"Point"}
}