{
  "type": "Feature",
  "properties": {
    "iso:country":"US",
    "sg:address":"3100 Fontaine Rd",
    "sg:city":"Memphis",
    "sg:classifiers":[
        {
            "category":"Autos & Motor Vehicles",
            "subcategory":"Auto Supplies",
            "type":"Retail Goods"
        },
        {
            "category":"Retail",
            "subcategory":"Auto Repair",
            "type":"Services"
        }
    ],
    "sg:phone":"+1 901 396 4500",
    "sg:postcode":"38116",
    "sg:province":"TN",
    "sg:tags":[
        "body",
        "painting",
        "truck"
    ],
    "wof:name":"Fleet Body Works",
    "wof:placetype":"venue"
},
  "geometry": {"coordinates":[-90.00923,35.063205],"type":"Point"}
}