{
  "type": "Feature",
  "properties": {
    "iso:country":"US",
    "sg:address":"122 Mobley Rd",
    "sg:city":"Blountville",
    "sg:classifiers":[
        {
            "category":"Building & Trades",
            "subcategory":"Construction",
            "type":"Services"
        }
    ],
    "sg:phone":"+1 423 279 0255",
    "sg:postcode":"37617",
    "sg:province":"TN",
    "sg:tags":[
        "mobile",
        "home"
    ],
    "wof:name":"Jerry's Mobile Home Svc",
    "wof:placetype":"venue"
},
  "geometry": {"coordinates":[-82.31437699999999,36.530417],"type":"Point"}
}