{
  "type": "Feature",
  "properties": {
    "iso:country":"US",
    "sg:address":"2250 N Roan St",
    "sg:city":"Johnson City",
    "sg:classifiers":[
        {
            "category":"Professional",
            "type":"Services"
        },
        {
            "category":"Personal",
            "subcategory":"Tanning Parlor",
            "type":"Services"
        }
    ],
    "sg:phone":"+1 423 232 7866",
    "sg:postcode":"37601",
    "sg:province":"TN",
    "sg:tags":[
        "salon"
    ],
    "wof:name":"Under The Sun",
    "wof:placetype":"venue"
},
  "geometry": {"coordinates":[-82.376997,36.344674],"type":"Point"}
}