{
  "type": "Feature",
  "properties": {
    "iso:country":"US",
    "sg:address":"2933 Colt Dr NE",
    "sg:city":"Knoxville",
    "sg:classifiers":[
        {
            "category":"Building & Trades",
            "subcategory":"Construction",
            "type":"Services"
        }
    ],
    "sg:phone":"+1 865 686 9963",
    "sg:postcode":"37918",
    "sg:province":"TN",
    "sg:tags":[
        "hanging",
        "contractor"
    ],
    "wof:name":"Young Painting Service",
    "wof:placetype":"venue"
},
  "geometry": {"coordinates":[-83.93554399999999,36.054406],"type":"Point"}
}