{
  "type": "Feature",
  "properties": {
    "iso:country":"US",
    "sg:address":"10015 State Hwy 46",
    "sg:city":"Bon Aqua",
    "sg:classifiers":[
        {
            "category":"Restaurant",
            "type":"Food & Drink"
        }
    ],
    "sg:phone":"+1 931 670 6705",
    "sg:postcode":"37025",
    "sg:province":"TN",
    "wof:name":"Big Bill's Bar-B-Que",
    "wof:placetype":"venue"
},
  "geometry": {"coordinates":[-87.305488,35.953578],"type":"Point"}
}