{
  "type": "Feature",
  "properties": {
    "iso:country":"US",
    "sg:address":"9 Music Sq E",
    "sg:city":"Nashville",
    "sg:classifiers":[
        {
            "category":"Professional",
            "subcategory":"Business Services",
            "type":"Services"
        }
    ],
    "sg:phone":"+1 615 332 8641",
    "sg:postcode":"37203",
    "sg:province":"TN",
    "wof:name":"Backwoods Edge Music",
    "wof:placetype":"venue"
},
  "geometry": {"coordinates":[-86.79177300000001,36.151491],"type":"Point"}
}