{
  "type": "Feature",
  "properties": {
    "iso:country":"US",
    "sg:address":"26 Security Dr",
    "sg:city":"Jackson",
    "sg:classifiers":[
        {
            "category":"Professional",
            "subcategory":"Accounting & Tax Preparation",
            "type":"Services"
        }
    ],
    "sg:phone":"+1 731 668 7070",
    "sg:postcode":"38305",
    "sg:province":"TN",
    "sg:tags":[
        "accountant"
    ],
    "sg:website":"www.craincpa.com",
    "wof:name":"Crain & Co",
    "wof:placetype":"venue"
},
  "geometry": {"coordinates":[-88.85378,35.692171],"type":"Point"}
}