{
  "type": "Feature",
  "properties": {
    "iso:country":"US",
    "sg:address":"6136 Airways Blvd",
    "sg:city":"Chattanooga",
    "sg:classifiers":[
        {
            "category":"Organizations",
            "subcategory":"Non-profit Organization",
            "type":"Services"
        }
    ],
    "sg:phone":"+1 423 892 5282",
    "sg:postcode":"37421",
    "sg:province":"TN",
    "wof:name":"Tri-State CARPENTERS Jatc",
    "wof:placetype":"venue"
},
  "geometry": {"coordinates":[-85.188975,35.032022],"type":"Point"}
}