{
  "type": "Feature",
  "properties": {
    "addr:full":"2323 Hanestown Rd Westmoreland TN 37083",
    "addr:housenumber":"2323",
    "addr:postcode":"37083",
    "addr:street":"Hanestown Rd",
    "iso:country":"US",
    "sg:address":"2323 Hanestown Rd",
    "sg:city":"Westmoreland",
    "sg:classifiers":[
        {
            "category":"Building & Trades",
            "subcategory":"Electrical",
            "type":"Services"
        }
    ],
    "sg:phone":"+1 615 633 5501",
    "sg:postcode":"37083",
    "sg:province":"TN",
    "sg:tags":[
        "electric",
        "contractor"
    ],
    "wof:name":"Down Home Farm",
    "wof:placetype":"venue"
},
  "geometry": {"coordinates":[-86.120558,36.62199],"type":"Point"}
}