{
  "type": "Feature",
  "properties": {
    "iso:country":"US",
    "sg:address":"992 Davidson Dr",
    "sg:city":"Nashville",
    "sg:classifiers":[
        {
            "category":"Wholesale",
            "subcategory":"Medical Equipment & Supplies",
            "type":"Manufacturing & Wholesale Goods"
        }
    ],
    "sg:phone":"+1 615 353 0556",
    "sg:postcode":"37205",
    "sg:province":"TN",
    "sg:tags":[
        "physician",
        "surgeon"
    ],
    "wof:name":"Dignity Inc",
    "wof:placetype":"venue"
},
  "geometry": {"coordinates":[-86.901797,36.123637],"type":"Point"}
}