{
  "type": "Feature",
  "properties": {
    "addr:full":"2303 S Chancery St Mc Minnville TN 37110",
    "addr:housenumber":"2303",
    "addr:postcode":"37110",
    "addr:street":"S Chancery St",
    "iso:country":"US",
    "sg:address":"2303 S Chancery St",
    "sg:city":"Mc Minnville",
    "sg:classifiers":[
        {
            "category":"Sports & Exercise",
            "subcategory":"Gym",
            "type":"Entertainment"
        }
    ],
    "sg:phone":"+1 931 668 4505",
    "sg:postcode":"37110",
    "sg:province":"TN",
    "sg:tags":[
        "club",
        "health",
        "studio",
        "gymnasium"
    ],
    "wof:name":"Total Fitness Ctr",
    "wof:placetype":"venue"
},
  "geometry": {"coordinates":[-85.795368,35.654138],"type":"Point"}
}