{
  "type": "Feature",
  "properties": {
    "iso:country":"US",
    "sg:address":"933 Bell Ave",
    "sg:city":"Signal Mountain",
    "sg:classifiers":[
        {
            "category":"Building & Trades",
            "subcategory":"Construction",
            "type":"Services"
        }
    ],
    "sg:phone":"+1 423 886 2677",
    "sg:postcode":"37377",
    "sg:province":"TN",
    "sg:tags":[
        "floor",
        "laying",
        "contractor"
    ],
    "wof:name":"Otis Morgan Carpet",
    "wof:placetype":"venue"
},
  "geometry": {"coordinates":[-85.32393,35.152297],"type":"Point"}
}