{
  "type": "Feature",
  "properties": {
    "iso:country":"US",
    "sg:address":"1365 Maley Hollow Rd",
    "sg:city":"Dayton",
    "sg:classifiers":[
        {
            "category":"Shopping",
            "subcategory":"Used Merchandise",
            "type":"Retail Goods"
        }
    ],
    "sg:phone":"+1 423 775 8028",
    "sg:postcode":"37321",
    "sg:province":"TN",
    "wof:name":"Rhea County Pawn Shop",
    "wof:placetype":"venue"
},
  "geometry": {"coordinates":[-85.021778,35.481922],"type":"Point"}
}