{
  "type": "Feature",
  "properties": {
    "iso:country":"US",
    "sg:address":"7 Laplace Dr",
    "sg:city":"Jackson",
    "sg:classifiers":[
        {
            "category":"Building & Trades",
            "subcategory":"Construction",
            "type":"Services"
        }
    ],
    "sg:phone":"+1 731 695 8440",
    "sg:postcode":"38305",
    "sg:province":"TN",
    "sg:tags":[
        "house"
    ],
    "wof:name":"Eagle Contractors",
    "wof:placetype":"venue"
},
  "geometry": {"coordinates":[-88.84170399999999,35.697831],"type":"Point"}
}