{
  "type": "Feature",
  "properties": {
    "iso:country":"US",
    "sg:address":"516 Bell Rd",
    "sg:city":"Antioch",
    "sg:classifiers":[
        {
            "category":"Manufacturing",
            "subcategory":"Printing",
            "type":"Manufacturing & Wholesale Goods"
        }
    ],
    "sg:phone":"+1 615 399 3939",
    "sg:postcode":"37013",
    "sg:province":"TN",
    "sg:tags":[
        "newspaper"
    ],
    "wof:name":"Korea Center Daily",
    "wof:placetype":"venue"
},
  "geometry": {"coordinates":[-86.63672099999999,36.068051],"type":"Point"}
}