{
  "type": "Feature",
  "properties": {
    "addr:full":"401 Tyson Ave Paris TN 38242",
    "addr:housenumber":"401",
    "addr:postcode":"38242",
    "addr:street":"Tyson Ave",
    "iso:country":"US",
    "sg:address":"401 Tyson Ave",
    "sg:city":"Paris",
    "sg:classifiers":[
        {
            "category":"Insurance",
            "subcategory":"Insurance Agent",
            "type":"Services"
        }
    ],
    "sg:phone":"+1 731 642 2063",
    "sg:postcode":"38242",
    "sg:province":"TN",
    "sg:tags":[
        "agency"
    ],
    "wof:name":"Allstate",
    "wof:placetype":"venue"
},
  "geometry": {"coordinates":[-88.31373499999999,36.29409],"type":"Point"}
}