{
  "type": "Feature",
  "properties": {
    "addr:full":"1329 Madison Ave Memphis TN 38104",
    "addr:housenumber":"1329",
    "addr:postcode":"38104",
    "addr:street":"Madison Ave",
    "iso:country":"US",
    "sg:address":"1329 Madison Ave",
    "sg:city":"Memphis",
    "sg:classifiers":[
        {
            "category":"Manufacturing",
            "subcategory":"Food",
            "type":"Manufacturing & Wholesale Goods"
        }
    ],
    "sg:phone":"+1 901 278 0078",
    "sg:postcode":"38104",
    "sg:province":"TN",
    "sg:tags":[
        "macaroni",
        "noodle",
        "spaghetti"
    ],
    "wof:name":"Valenza Pasta",
    "wof:placetype":"venue"
},
  "geometry": {"coordinates":[-90.01694999999999,35.138899],"type":"Point"}
}