{
  "type": "Feature",
  "properties": {
    "addr:full":"8158 Old Springfield Pike Goodlettsville TN 37072",
    "addr:housenumber":"8158",
    "addr:postcode":"37072",
    "addr:street":"Old Springfield Pike",
    "iso:country":"US",
    "sg:address":"8158 Old Springfield Pike",
    "sg:city":"Goodlettsville",
    "sg:classifiers":[
        {
            "category":"Professional",
            "subcategory":"Business Services",
            "type":"Services"
        }
    ],
    "sg:phone":"+1 615 851 2955",
    "sg:postcode":"37072",
    "sg:province":"TN",
    "wof:name":"Your Love Remains LLC",
    "wof:placetype":"venue"
},
  "geometry": {"coordinates":[-86.745091,36.371453],"type":"Point"}
}