{
  "type": "Feature",
  "properties": {
    "addr:full":"1331 S Locust Ave Lawrenceburg TN 38464",
    "addr:housenumber":"1331",
    "addr:postcode":"38464",
    "addr:street":"S Locust Ave",
    "iso:country":"US",
    "sg:address":"1331 S Locust Ave",
    "sg:city":"Lawrenceburg",
    "sg:classifiers":[
        {
            "category":"Health Services",
            "subcategory":"Doctor",
            "type":"Services"
        }
    ],
    "sg:phone":"+1 931 766 0088",
    "sg:postcode":"38464",
    "sg:province":"TN",
    "sg:tags":[
        "physician",
        "surgeon"
    ],
    "wof:name":"Tennessee Oncology",
    "wof:placetype":"venue"
},
  "geometry": {"coordinates":[-87.33640800000001,35.223215],"type":"Point"}
}