{
  "type": "Feature",
  "properties": {
    "iso:country":"US",
    "sg:address":"1215 Perimeter Dr",
    "sg:city":"Jamestown",
    "sg:classifiers":[
        {
            "category":"Health Services",
            "subcategory":"Doctor",
            "type":"Services"
        }
    ],
    "sg:phone":"+1 931 879 6845",
    "sg:postcode":"38556",
    "sg:province":"TN",
    "sg:tags":[
        "medical"
    ],
    "wof:name":"Joseph A Payant",
    "wof:placetype":"venue"
},
  "geometry": {"coordinates":[-84.968259,36.478497],"type":"Point"}
}