{
  "type": "Feature",
  "properties": {
    "addr:full":"108 College St Mc Minnville TN 37110",
    "addr:housenumber":"108",
    "addr:postcode":"37110",
    "addr:street":"College St",
    "iso:country":"US",
    "sg:address":"108 College St",
    "sg:city":"Mc Minnville",
    "sg:classifiers":[
        {
            "category":"Professional",
            "subcategory":"Art Services",
            "type":"Services"
        }
    ],
    "sg:phone":"+1 931 473 6157",
    "sg:postcode":"37110",
    "sg:province":"TN",
    "sg:tags":[
        "commercial",
        "design"
    ],
    "wof:name":"Phifer Graphics",
    "wof:placetype":"venue"
},
  "geometry": {"coordinates":[-85.772571,35.683892],"type":"Point"}
}