{
  "type": "Feature",
  "properties": {
    "iso:country":"US",
    "sg:address":"1741 Willette Rd",
    "sg:city":"Red Boiling Springs",
    "sg:classifiers":[
        {
            "category":"Food & Beverages",
            "subcategory":"Groceries & Convenience Stores",
            "type":"Retail Goods"
        }
    ],
    "sg:phone":"+1 615 699 2715",
    "sg:postcode":"37150",
    "sg:province":"TN",
    "sg:tags":[
        "station",
        "gasoline"
    ],
    "wof:name":"Willette Grocery",
    "wof:placetype":"venue"
},
  "geometry": {"coordinates":[-85.84813800000001,36.440877],"type":"Point"}
}