{
  "type": "Feature",
  "properties": {
    "iso:country":"US",
    "sg:address":"860 Loretta Dr",
    "sg:city":"Goodlettsville",
    "sg:classifiers":[
        {
            "category":"Social Services",
            "subcategory":"Child Care",
            "type":"Services"
        }
    ],
    "sg:phone":"+1 615 868 2228",
    "sg:postcode":"37072",
    "sg:province":"TN",
    "sg:tags":[
        "day"
    ],
    "wof:name":"Lil Angels Child Care Ctr LLC",
    "wof:placetype":"venue"
},
  "geometry": {"coordinates":[-86.710522,36.339344],"type":"Point"}
}