{
  "type": "Feature",
  "properties": {
    "addr:full":"911 S 3rd St Memphis TN 38106",
    "addr:housenumber":"911",
    "addr:postcode":"38106",
    "addr:street":"S 3Rd St",
    "iso:country":"US",
    "sg:address":"911 S 3rd St",
    "sg:city":"Memphis",
    "sg:classifiers":[
        {
            "category":"Personal",
            "subcategory":"Beauty Salon",
            "type":"Services"
        }
    ],
    "sg:phone":"+1 901 942 5917",
    "sg:postcode":"38106",
    "sg:province":"TN",
    "sg:tags":[
        "shop"
    ],
    "wof:name":"Don's House Of Beauty",
    "wof:placetype":"venue"
},
  "geometry": {"coordinates":[-90.055071,35.122314],"type":"Point"}
}