{
  "type": "Feature",
  "properties": {
    "addr:full":"1128 4th Ave S Nashville TN 37210",
    "addr:housenumber":"1128",
    "addr:postcode":"37210",
    "addr:street":"4Th Ave S",
    "iso:country":"US",
    "sg:address":"1128 4th Ave S",
    "sg:city":"Nashville",
    "sg:classifiers":[
        {
            "category":"Retail",
            "subcategory":"Auto Repair",
            "type":"Services"
        }
    ],
    "sg:phone":"+1 615 742 0060",
    "sg:postcode":"37210",
    "sg:province":"TN",
    "sg:tags":[
        "body"
    ],
    "wof:name":"Minor Dent Repair & Custom Pnt",
    "wof:placetype":"venue"
},
  "geometry": {"coordinates":[-86.766886,36.145429],"type":"Point"}
}