{
  "type": "Feature",
  "properties": {
    "iso:country":"US",
    "sg:address":"7811 Dogwood Rd",
    "sg:city":"Germantown",
    "sg:classifiers":[
        {
            "category":"Wholesale",
            "subcategory":"Apparel",
            "type":"Manufacturing & Wholesale Goods"
        }
    ],
    "sg:phone":"+1 901 624 3250",
    "sg:postcode":"38138",
    "sg:province":"TN",
    "sg:tags":[
        "clothing"
    ],
    "wof:name":"Foot Fetish",
    "wof:placetype":"venue"
},
  "geometry": {"coordinates":[-89.797509,35.08688],"type":"Point"}
}