{
  "type": "Feature",
  "properties": {
    "iso:country":"US",
    "sg:address":"521 Oliver Smith Rd",
    "sg:city":"Flintville",
    "sg:classifiers":[
        {
            "category":"Personal",
            "subcategory":"Beauty Salon",
            "type":"Services"
        }
    ],
    "sg:phone":"+1 931 937 8233",
    "sg:postcode":"37335",
    "sg:province":"TN",
    "sg:tags":[
        "shop"
    ],
    "wof:name":"Lindas Beauty Salon",
    "wof:placetype":"venue"
},
  "geometry": {"coordinates":[-86.48184000000001,35.024543],"type":"Point"}
}