{
  "type": "Feature",
  "properties": {
    "iso:country":"US",
    "sg:address":"122 E 12th St",
    "sg:city":"Cookeville",
    "sg:classifiers":[
        {
            "category":"Social Services",
            "subcategory":"Child Care",
            "type":"Services"
        },
        {
            "category":"Education",
            "subcategory":"School",
            "type":"Public Place"
        }
    ],
    "sg:phone":"+1 931 528 5639",
    "sg:postcode":"38501",
    "sg:province":"TN",
    "sg:tags":[
        "kindergarten",
        "academic",
        "preschool"
    ],
    "wof:name":"Montessori Pre School",
    "wof:placetype":"venue"
},
  "geometry": {"coordinates":[-85.50435,36.17895],"type":"Point"}
}