{
  "type": "Feature",
  "properties": {
    "addr:full":"210 N Laurel Cir Knoxville TN 37912",
    "addr:housenumber":"210",
    "addr:postcode":"37912",
    "addr:street":"N Laurel Cir",
    "iso:country":"US",
    "sg:address":"210 N Laurel Cir",
    "sg:city":"Knoxville",
    "sg:classifiers":[
        {
            "category":"Building & Trades",
            "subcategory":"Construction",
            "type":"Services"
        }
    ],
    "sg:phone":"+1 865 687 2391",
    "sg:postcode":"37912",
    "sg:province":"TN",
    "sg:tags":[
        "resurfacing",
        "laying",
        "refinishing",
        "floor"
    ],
    "wof:name":"Innovative Floor Covering",
    "wof:placetype":"venue"
},
  "geometry": {"coordinates":[-83.964572,36.012367],"type":"Point"}
}