{
  "type": "Feature",
  "properties": {
    "iso:country":"US",
    "sg:address":"800 W Market St",
    "sg:city":"Bolivar",
    "sg:classifiers":[
        {
            "category":"Insurance",
            "subcategory":"Insurance Agent",
            "type":"Services"
        }
    ],
    "sg:phone":"+1 731 658 3011",
    "sg:postcode":"38008",
    "sg:province":"TN",
    "wof:name":"Bolivar Insurance & Real Est",
    "wof:placetype":"venue"
},
  "geometry": {"coordinates":[-88.998931,35.256457],"type":"Point"}
}