{
  "type": "Feature",
  "properties": {
    "addr:full":"11 Timber Ridge Rd Bristol TN 24201",
    "addr:housenumber":"11",
    "addr:postcode":"24201",
    "addr:street":"Timber Ridge Rd",
    "iso:country":"US",
    "sg:address":"11 Timber Ridge Rd",
    "sg:city":"Bristol",
    "sg:classifiers":[
        {
            "category":"Professional",
            "subcategory":"Business Services",
            "type":"Services"
        }
    ],
    "sg:phone":"+1 276 669 2213",
    "sg:postcode":"24201",
    "sg:province":"TN",
    "wof:name":"Southeastern Bonding Inc",
    "wof:placetype":"venue"
},
  "geometry": {"coordinates":[-82.141469,36.611296],"type":"Point"}
}