{
  "type": "Feature",
  "properties": {
    "addr:full":"1352 Carr Ave Memphis TN 38104",
    "addr:housenumber":"1352",
    "addr:postcode":"38104",
    "addr:street":"Carr Ave",
    "iso:country":"US",
    "sg:address":"1352 Carr Ave",
    "sg:city":"Memphis",
    "sg:classifiers":[
        {
            "category":"Professional",
            "subcategory":"Business Services",
            "type":"Services"
        }
    ],
    "sg:phone":"+1 901 276 1140",
    "sg:postcode":"38104",
    "sg:province":"TN",
    "sg:tags":[
        "translator"
    ],
    "wof:name":"German Technical Translator",
    "wof:placetype":"venue"
},
  "geometry": {"coordinates":[-90.013561,35.131576],"type":"Point"}
}