{
  "type": "Feature",
  "properties": {
    "iso:country":"US",
    "sg:address":"813 Rogers St",
    "sg:city":"Clinton",
    "sg:classifiers":[
        {
            "category":"Real Estate",
            "subcategory":"Real Estate Operator",
            "type":"Services"
        }
    ],
    "sg:phone":"+1 865 457 0808",
    "sg:postcode":"37716",
    "sg:province":"TN",
    "sg:tags":[
        "apartment"
    ],
    "wof:name":"Ridgetop Apartments Inc",
    "wof:placetype":"venue"
},
  "geometry": {"coordinates":[-84.130393,36.11431],"type":"Point"}
}