{
  "type": "Feature",
  "properties": {
    "iso:country":"US",
    "sg:address":"135 Hawthorne Ave SW",
    "sg:city":"Knoxville",
    "sg:classifiers":[
        {
            "category":"Retail",
            "subcategory":"Auto Repair",
            "type":"Services"
        }
    ],
    "sg:phone":"+1 865 577 8212",
    "sg:postcode":"37920",
    "sg:province":"TN",
    "sg:tags":[
        "wrecker"
    ],
    "wof:name":"Floyd's Wrecker Svc",
    "wof:placetype":"venue"
},
  "geometry": {"coordinates":[-83.915857,35.952707],"type":"Point"}
}