{
  "type": "Feature",
  "properties": {
    "iso:country":"US",
    "sg:address":"4620 Old Broadway NE",
    "sg:city":"Knoxville",
    "sg:classifiers":[
        {
            "category":"Health Services",
            "subcategory":"Doctor",
            "type":"Services"
        }
    ],
    "sg:phone":"+1 865 524 4665",
    "sg:postcode":"37918",
    "sg:province":"TN",
    "sg:tags":[
        "dentist"
    ],
    "wof:name":"Michael J Molloy DDS",
    "wof:placetype":"venue"
},
  "geometry": {"coordinates":[-83.92416,36.017894],"type":"Point"}
}