{
  "type": "Feature",
  "properties": {
    "iso:country":"US",
    "sg:address":"105 Katye Ct",
    "sg:city":"Ashland City",
    "sg:classifiers":[
        {
            "category":"Professional",
            "subcategory":"Computer Services",
            "type":"Services"
        }
    ],
    "sg:phone":"+1 615 792 5197",
    "sg:postcode":"37015",
    "sg:province":"TN",
    "sg:tags":[
        "datum"
    ],
    "wof:name":"Bscene",
    "wof:placetype":"venue"
},
  "geometry": {"coordinates":[-87.05538300000001,36.279013],"type":"Point"}
}