{
  "type": "Feature",
  "properties": {
    "iso:country":"US",
    "sg:address":"2603 Elm Hill Pike",
    "sg:city":"Nashville",
    "sg:classifiers":[
        {
            "category":"Banks & Credit Unions",
            "subcategory":"Bank",
            "type":"Services"
        }
    ],
    "sg:phone":"+1 615 871 9999",
    "sg:postcode":"37214",
    "sg:province":"TN",
    "sg:tags":[
        "mortgage"
    ],
    "wof:name":"Advance Financial Services",
    "wof:placetype":"venue"
},
  "geometry": {"coordinates":[-86.671235,36.15128],"type":"Point"}
}