{
  "type": "Feature",
  "properties": {
    "addr:full":"2700 Middlebrook Pike Knoxville TN 37921",
    "addr:housenumber":"2700",
    "addr:postcode":"37921",
    "addr:street":"Middlebrook Pike",
    "iso:country":"US",
    "sg:address":"2700 Middlebrook Pike",
    "sg:city":"Knoxville",
    "sg:classifiers":[
        {
            "category":"Government",
            "subcategory":"Office",
            "type":"Public Place"
        }
    ],
    "sg:phone":"+1 865 594 6203",
    "sg:postcode":"37921",
    "sg:province":"TN",
    "sg:tags":[
        "state"
    ],
    "wof:name":"Land Reclamation Div",
    "wof:placetype":"venue"
},
  "geometry": {"coordinates":[-83.957904,35.96405],"type":"Point"}
}