{
  "type": "Feature",
  "properties": {
    "iso:country":"US",
    "sg:address":"9637 Kroger Park Dr",
    "sg:city":"Knoxville",
    "sg:classifiers":[
        {
            "category":"Restaurant",
            "type":"Food & Drink"
        }
    ],
    "sg:menulink":"http://www.allmenus.com/tn/knoxville/103994-ruby-tuesdays/menu/",
    "sg:phone":"+1 865 692 0224",
    "sg:postcode":"37922",
    "sg:province":"TN",
    "sg:tags":[
        "burger",
        "american"
    ],
    "wof:name":"Ruby Tuesdays",
    "wof:placetype":"venue"
},
  "geometry": {"coordinates":[-84.069891,35.861499],"type":"Point"}
}