{
  "type": "Feature",
  "properties": {
    "addr:full":"401 Smoky View Rd SW Knoxville TN 37920",
    "addr:housenumber":"401",
    "addr:postcode":"37920",
    "addr:street":"Smoky View Rd Sw",
    "iso:country":"US",
    "sg:address":"401 Smoky View Rd SW",
    "sg:city":"Knoxville",
    "sg:phone":"+1 865 573 1284",
    "sg:postcode":"37920",
    "sg:province":"TN",
    "sg:tags":[
        "wholesale",
        "retail",
        "commercial",
        "equipment"
    ],
    "wof:name":"East Tennessee Sales & Service",
    "wof:placetype":"venue"
},
  "geometry": {"coordinates":[-83.860743,35.907018],"type":"Point"}
}