{
  "type": "Feature",
  "properties": {
    "iso:country":"US",
    "sg:address":"468 S Washington St",
    "sg:city":"Ripley",
    "sg:classifiers":[
        {
            "category":"Freight",
            "type":"Transportation"
        }
    ],
    "sg:phone":"+1 731 221 1993",
    "sg:postcode":"38063",
    "sg:province":"TN",
    "sg:tags":[
        "trucking"
    ],
    "wof:name":"BMB Of Ripley Freedom Frt",
    "wof:placetype":"venue"
},
  "geometry": {"coordinates":[-89.544634,35.728037],"type":"Point"}
}