{
  "type": "Feature",
  "properties": {
    "iso:country":"US",
    "sg:address":"411 W Walnut St",
    "sg:city":"Johnson City",
    "sg:classifiers":[
        {
            "category":"Shopping",
            "subcategory":"Used Merchandise",
            "type":"Retail Goods"
        }
    ],
    "sg:phone":"+1 423 232 5263",
    "sg:postcode":"37604",
    "sg:province":"TN",
    "sg:tags":[
        "clothing"
    ],
    "wof:name":"Bettye Jane's",
    "wof:placetype":"venue"
},
  "geometry": {"coordinates":[-82.35526400000001,36.311296],"type":"Point"}
}