{
  "type": "Feature",
  "properties": {
    "iso:country":"US",
    "sg:address":"254 George Akins Rd",
    "sg:city":"Westmoreland",
    "sg:classifiers":[
        {
            "category":"Manufacturing",
            "subcategory":"Metals",
            "type":"Manufacturing & Wholesale Goods"
        }
    ],
    "sg:phone":"+1 615 644 2926",
    "sg:postcode":"37186",
    "sg:province":"TN",
    "sg:tags":[
        "die",
        "tool"
    ],
    "wof:name":"OK Tool Engineering",
    "wof:placetype":"venue"
},
  "geometry": {"coordinates":[-86.223393,36.564142],"type":"Point"}
}