{
  "type": "Feature",
  "properties": {
    "iso:country":"US",
    "sg:address":"1266 Jackson Felts Rd",
    "sg:city":"Joelton",
    "sg:classifiers":[
        {
            "category":"Restaurant",
            "type":"Food & Drink"
        }
    ],
    "sg:phone":"+1 615 746 8100",
    "sg:postcode":"37080",
    "sg:province":"TN",
    "sg:tags":[
        "eating"
    ],
    "wof:name":"Party Time Pizza",
    "wof:placetype":"venue"
},
  "geometry": {"coordinates":[-86.935278,36.34545],"type":"Point"}
}