{
  "type": "Feature",
  "properties": {
    "iso:country":"US",
    "sg:address":"106 Pleasant St",
    "sg:city":"Mt Pleasant",
    "sg:classifiers":[
        {
            "category":"Personal",
            "subcategory":"Beauty Salon",
            "type":"Services"
        }
    ],
    "sg:phone":"+1 931 379 5633",
    "sg:postcode":"38474",
    "sg:province":"TN",
    "wof:name":"K & M Beauty Shop",
    "wof:placetype":"venue"
},
  "geometry": {"coordinates":[-87.21039399999999,35.535609],"type":"Point"}
}