{
  "type": "Feature",
  "properties": {
    "iso:country":"US",
    "sg:address":"4294 Swinnea Rd",
    "sg:city":"Memphis",
    "sg:classifiers":[
        {
            "category":"Professional",
            "subcategory":"Business Services",
            "type":"Services"
        }
    ],
    "sg:phone":"+1 901 795 2189",
    "sg:postcode":"38118",
    "sg:province":"TN",
    "sg:tags":[
        "holding"
    ],
    "wof:name":"The Mallory Group Incorporated",
    "wof:placetype":"venue"
},
  "geometry": {"coordinates":[-89.96369300000001,35.028511],"type":"Point"}
}