{
  "type": "Feature",
  "properties": {
    "iso:country":"US",
    "sg:address":"321 Angelus St",
    "sg:city":"Memphis",
    "sg:classifiers":[
        {
            "category":"Professional",
            "subcategory":"Engineering",
            "type":"Services"
        }
    ],
    "sg:phone":"+1 901 726 6770",
    "sg:postcode":"38112",
    "sg:province":"TN",
    "sg:tags":[
        "engineer"
    ],
    "wof:name":"Wyatt Systems & Consulting Inc",
    "wof:placetype":"venue"
},
  "geometry": {"coordinates":[-90.005348,35.147896],"type":"Point"}
}