{
  "type": "Feature",
  "properties": {
    "iso:country":"US",
    "sg:address":"10306 Yellow Pine Ln",
    "sg:city":"Knoxville",
    "sg:classifiers":[
        {
            "category":"Building & Trades",
            "subcategory":"Construction",
            "type":"Services"
        }
    ],
    "sg:phone":"+1 865 675 1818",
    "sg:postcode":"37932",
    "sg:province":"TN",
    "sg:tags":[
        "contractor"
    ],
    "sg:website":"www.pcg.com",
    "wof:name":"Performance Contracting Group",
    "wof:placetype":"venue"
},
  "geometry": {"coordinates":[-84.133443,35.916733],"type":"Point"}
}