{
  "type": "Feature",
  "properties": {
    "iso:country":"US",
    "sg:address":"1201 Maxwell Branch Rd",
    "sg:city":"Cottontown",
    "sg:classifiers":[
        {
            "category":"Building & Trades",
            "subcategory":"Construction",
            "type":"Services"
        }
    ],
    "sg:phone":"+1 615 325 2157",
    "sg:postcode":"37048",
    "sg:province":"TN",
    "sg:tags":[
        "carpentry",
        "contractor"
    ],
    "wof:name":"Petitt Cabinet Co",
    "wof:placetype":"venue"
},
  "geometry": {"coordinates":[-86.603869,36.532348],"type":"Point"}
}