{
  "type": "Feature",
  "properties": {
    "addr:full":"1107 Darbytown Dr Nashville TN 37207",
    "addr:housenumber":"1107",
    "addr:postcode":"37207",
    "addr:street":"Darbytown Dr",
    "iso:country":"US",
    "sg:address":"1107 Darbytown Dr",
    "sg:city":"Nashville",
    "sg:classifiers":[
        {
            "category":"Wholesale",
            "subcategory":"Machinery & Supplies",
            "type":"Manufacturing & Wholesale Goods"
        }
    ],
    "sg:phone":"+1 615 612 4492",
    "sg:postcode":"37207",
    "sg:province":"TN",
    "sg:tags":[
        "machine",
        "floor"
    ],
    "wof:name":"Wal-Star Supply & Svc Inc",
    "wof:placetype":"venue"
},
  "geometry": {"coordinates":[-86.758415,36.266994],"type":"Point"}
}