{
  "type": "Feature",
  "properties": {
    "addr:full":"1826 Mountain Top Ln Cookeville TN 38506",
    "addr:housenumber":"1826",
    "addr:postcode":"38506",
    "addr:street":"Mountain Top Ln",
    "iso:country":"US",
    "sg:address":"1826 Mountain Top Ln",
    "sg:city":"Cookeville",
    "sg:classifiers":[
        {
            "category":"Building & Trades",
            "subcategory":"Landscaping Services",
            "type":"Services"
        }
    ],
    "sg:phone":"+1 931 537 2400",
    "sg:postcode":"38506",
    "sg:province":"TN",
    "wof:name":"Quality Lawn Care & Landscape",
    "wof:placetype":"venue"
},
  "geometry": {"coordinates":[-85.43513900000001,36.147099],"type":"Point"}
}