{
  "type": "Feature",
  "properties": {
    "addr:full":"7105 Dice Lampley Rd Fairview TN 37062",
    "addr:postcode":"7105;37062",
    "addr:street":"Lampley Rd",
    "iso:country":"US",
    "sg:address":"7105 Dice Lampley Rd",
    "sg:city":"Fairview",
    "sg:classifiers":[
        {
            "category":"Retail",
            "subcategory":"Repair Shop",
            "type":"Services"
        }
    ],
    "sg:phone":"+1 615 799 0328",
    "sg:postcode":"37062",
    "sg:province":"TN",
    "sg:tags":[
        "furniture"
    ],
    "wof:name":"Back Acres Furniture",
    "wof:placetype":"venue"
},
  "geometry": {"coordinates":[-87.15832,35.97746],"type":"Point"}
}