{
  "type": "Feature",
  "properties": {
    "iso:country":"US",
    "sg:address":"191 W Industrial Ave",
    "sg:city":"Memphis",
    "sg:classifiers":[
        {
            "category":"Freight",
            "type":"Transportation"
        }
    ],
    "sg:phone":"+1 901 942 8001",
    "sg:postcode":"38109",
    "sg:province":"TN",
    "sg:tags":[
        "operator",
        "local",
        "trucking"
    ],
    "wof:name":"Carolina National Trnsp",
    "wof:placetype":"venue"
},
  "geometry": {"coordinates":[-90.066277,35.082322],"type":"Point"}
}