{
  "type": "Feature",
  "properties": {
    "iso:country":"US",
    "sg:address":"700 Judge Purser Hill Rd",
    "sg:city":"Mc Minnville",
    "sg:classifiers":[
        {
            "category":"Organizations",
            "subcategory":"Religious Organization",
            "type":"Services"
        }
    ],
    "sg:phone":"+1 615 563 4649",
    "sg:postcode":"37110",
    "sg:province":"TN",
    "sg:tags":[
        "church"
    ],
    "wof:name":"Blues Hill Church Of Christ",
    "wof:placetype":"venue"
},
  "geometry": {"coordinates":[-85.93535799999999,35.844676],"type":"Point"}
}