{
  "type": "Feature",
  "properties": {
    "addr:full":"9020 Westland Dr Knoxville TN 37922",
    "addr:housenumber":"9020",
    "addr:postcode":"37922",
    "addr:street":"Westland Dr",
    "iso:country":"US",
    "sg:address":"9020 Westland Dr",
    "sg:city":"Knoxville",
    "sg:classifiers":[
        {
            "category":"Organizations",
            "subcategory":"Religious Organization",
            "type":"Services"
        }
    ],
    "sg:phone":"+1 865 539 2296",
    "sg:postcode":"37922",
    "sg:province":"TN",
    "wof:name":"Shepherds Fellowship",
    "wof:placetype":"venue"
},
  "geometry": {"coordinates":[-84.071816,35.891242],"type":"Point"}
}