{
  "type": "Feature",
  "properties": {
    "iso:country":"US",
    "sg:address":"6541 Chapman Hwy",
    "sg:city":"Knoxville",
    "sg:classifiers":[
        {
            "category":"Shopping",
            "subcategory":"Bicycles & Sporting Goods",
            "type":"Retail Goods"
        }
    ],
    "sg:phone":"+1 865 577 3103",
    "sg:postcode":"37920",
    "sg:province":"TN",
    "sg:tags":[
        "equipment",
        "line",
        "skate",
        "repair",
        "hobby"
    ],
    "wof:name":"In Line Skate Center Knoxville",
    "wof:placetype":"venue"
},
  "geometry": {"coordinates":[-83.863893,35.921073],"type":"Point"}
}