{
  "type": "Feature",
  "properties": {
    "iso:country":"US",
    "sg:address":"2999 Smith Springs Rd",
    "sg:city":"Nashville",
    "sg:classifiers":[
        {
            "category":"Retail",
            "subcategory":"Repair Shop",
            "type":"Services"
        }
    ],
    "sg:phone":"+1 615 582 6022",
    "sg:postcode":"37217",
    "sg:province":"TN",
    "wof:name":"Dixi Custom Upholstery",
    "wof:placetype":"venue"
},
  "geometry": {"coordinates":[-86.60462099999999,36.087454],"type":"Point"}
}