{
  "type": "Feature",
  "properties": {
    "iso:country":"US",
    "sg:address":"119 4th St",
    "sg:city":"Lawrenceburg",
    "sg:classifiers":[
        {
            "category":"Home & Garden",
            "subcategory":"Carpets & Floor Coverings",
            "type":"Retail Goods"
        }
    ],
    "sg:phone":"+1 931 762 0075",
    "sg:postcode":"38464",
    "sg:province":"TN",
    "wof:name":"Staffords Quality Crpt & Vinyl",
    "wof:placetype":"venue"
},
  "geometry": {"coordinates":[-87.33125800000001,35.248281],"type":"Point"}
}