{
  "type": "Feature",
  "properties": {
    "iso:country":"US",
    "sg:address":"613 University St",
    "sg:city":"Memphis",
    "sg:classifiers":[
        {
            "category":"Organizations",
            "subcategory":"Religious Organization",
            "type":"Services"
        }
    ],
    "sg:phone":"+1 901 274 3740",
    "sg:postcode":"38107",
    "sg:province":"TN",
    "sg:tags":[
        "church"
    ],
    "sg:website":"www.evergreenmemphis.org",
    "wof:name":"Evergreen Presbyterian Church",
    "wof:placetype":"venue"
},
  "geometry": {"coordinates":[-89.99185799999999,35.153923],"type":"Point"}
}