{
  "type": "Feature",
  "properties": {
    "iso:country":"US",
    "sg:address":"7310 Polk Dr",
    "sg:city":"Murfreesboro",
    "sg:classifiers":[
        {
            "category":"Building & Trades",
            "subcategory":"Construction",
            "type":"Services"
        }
    ],
    "sg:phone":"+1 615 516 5260",
    "sg:postcode":"37129",
    "sg:province":"TN",
    "sg:tags":[
        "hanging",
        "contractor"
    ],
    "wof:name":"Jerry Wade",
    "wof:placetype":"venue"
},
  "geometry": {"coordinates":[-86.472752,35.922279],"type":"Point"}
}