{
  "type": "Feature",
  "properties": {
    "iso:country":"US",
    "sg:address":"409 Union Ave",
    "sg:city":"Memphis",
    "sg:classifiers":[
        {
            "category":"Autos & Motor Vehicles",
            "subcategory":"Automobile Sales",
            "type":"Retail Goods"
        }
    ],
    "sg:phone":"+1 901 525 2247",
    "sg:postcode":"38103",
    "sg:province":"TN",
    "sg:tags":[
        "used",
        "supply"
    ],
    "wof:name":"Auto Trends Inc",
    "wof:placetype":"venue"
},
  "geometry": {"coordinates":[-90.044203,35.140668],"type":"Point"}
}