{
  "type": "Feature",
  "properties": {
    "iso:country":"US",
    "sg:address":"3500 N Hawthorne St",
    "sg:city":"Chattanooga",
    "sg:classifiers":[
        {
            "category":"Freight",
            "type":"Transportation"
        }
    ],
    "sg:phone":"+1 423 698 3913",
    "sg:postcode":"37406",
    "sg:province":"TN",
    "sg:tags":[
        "trucking"
    ],
    "wof:name":"J Lynn Inc",
    "wof:placetype":"venue"
},
  "geometry": {"coordinates":[-85.25054900000001,35.081297],"type":"Point"}
}