{
  "type": "Feature",
  "properties": {
    "addr:full":"212 E Broadway Ave Maryville TN 37804",
    "addr:housenumber":"212",
    "addr:postcode":"37804",
    "addr:street":"E Broadway Ave",
    "iso:country":"US",
    "sg:address":"212 E Broadway Ave",
    "sg:city":"Maryville",
    "sg:classifiers":[
        {
            "category":"Government",
            "subcategory":"Office",
            "type":"Public Place"
        }
    ],
    "sg:phone":"+1 865 982 5896",
    "sg:postcode":"37804",
    "sg:province":"TN",
    "sg:tags":[
        "federal"
    ],
    "wof:name":"Natural Resources Conservation",
    "wof:placetype":"venue"
},
  "geometry": {"coordinates":[-83.970141,35.756947],"type":"Point"}
}