{
  "type": "Feature",
  "properties": {
    "iso:country":"US",
    "sg:address":"4804 Charlotte Pike",
    "sg:city":"Nashville",
    "sg:classifiers":[
        {
            "category":"Personal",
            "subcategory":"Beauty Salon",
            "type":"Services"
        }
    ],
    "sg:phone":"+1 615 385 5600",
    "sg:postcode":"37209",
    "sg:province":"TN",
    "wof:name":"Hollywood Hair Salon",
    "wof:placetype":"venue"
},
  "geometry": {"coordinates":[-86.845947,36.152145],"type":"Point"}
}