{
  "type": "Feature",
  "properties": {
    "addr:full":"14 E Jefferson St Brownsville TN 38012",
    "addr:housenumber":"14",
    "addr:postcode":"38012",
    "addr:street":"E Jefferson St",
    "iso:country":"US",
    "sg:address":"14 E Jefferson St",
    "sg:city":"Brownsville",
    "sg:classifiers":[
        {
            "category":"Personal",
            "subcategory":"Barber",
            "type":"Services"
        }
    ],
    "sg:phone":"+1 731 772 6553",
    "sg:postcode":"38012",
    "sg:province":"TN",
    "sg:tags":[
        "school"
    ],
    "wof:name":"Professional Career Barber",
    "wof:placetype":"venue"
},
  "geometry": {"coordinates":[-89.262078,35.592691],"type":"Point"}
}