{
  "type": "Feature",
  "properties": {
    "iso:country":"US",
    "sg:address":"2424 Whitfield Rd",
    "sg:city":"Clarksville",
    "sg:classifiers":[
        {
            "category":"Retail",
            "subcategory":"Auto Rental",
            "type":"Services"
        }
    ],
    "sg:phone":"+1 931 647 6245",
    "sg:postcode":"37040",
    "sg:province":"TN",
    "sg:tags":[
        "mobile",
        "home",
        "leasing"
    ],
    "wof:name":"Prewitts Mobile Home Park",
    "wof:placetype":"venue"
},
  "geometry": {"coordinates":[-87.33596300000001,36.573831],"type":"Point"}
}