{
  "type": "Feature",
  "properties": {
    "addr:full":"4044 Hillsboro Pike Nashville TN 37215",
    "addr:housenumber":"4044",
    "addr:postcode":"37215",
    "addr:street":"Hillsboro Pike",
    "iso:country":"US",
    "sg:address":"4044 Hillsboro Pike",
    "sg:city":"Nashville",
    "sg:classifiers":[
        {
            "category":"Retail",
            "subcategory":"Laundry & Dry Cleaning",
            "type":"Services"
        }
    ],
    "sg:phone":"+1 615 292 4659",
    "sg:postcode":"37215",
    "sg:province":"TN",
    "sg:tags":[
        "cleaners"
    ],
    "wof:name":"Town & Country Cleaners",
    "wof:placetype":"venue"
},
  "geometry": {"coordinates":[-86.817572,36.101961],"type":"Point"}
}