{
  "type": "Feature",
  "properties": {
    "addr:full":"1704 Wildwood Ave SE Cleveland TN 37311",
    "addr:housenumber":"1704",
    "addr:postcode":"37311",
    "addr:street":"Wildwood Ave Se",
    "iso:country":"US",
    "sg:address":"1704 Wildwood Ave SE",
    "sg:city":"Cleveland",
    "sg:classifiers":[
        {
            "category":"Autos & Motor Vehicles",
            "subcategory":"Fuel & Gas Station",
            "type":"Retail Goods"
        }
    ],
    "sg:phone":"+1 423 559 1915",
    "sg:postcode":"37311",
    "sg:province":"TN",
    "sg:tags":[
        "oil"
    ],
    "wof:name":"Shell",
    "wof:placetype":"venue"
},
  "geometry": {"coordinates":[-84.87120400000001,35.142609],"type":"Point"}
}