{
  "type": "Feature",
  "properties": {
    "iso:country":"US",
    "sg:address":"3549 Southern Ave",
    "sg:city":"Memphis",
    "sg:classifiers":[
        {
            "category":"Retail",
            "subcategory":"Auto Repair",
            "type":"Services"
        }
    ],
    "sg:phone":"+1 901 323 1973",
    "sg:postcode":"38111",
    "sg:province":"TN",
    "sg:tags":[
        "wrecker"
    ],
    "wof:name":"F & J Wrecker Svc",
    "wof:placetype":"venue"
},
  "geometry": {"coordinates":[-89.943022,35.115856],"type":"Point"}
}