{
  "type": "Feature",
  "properties": {
    "iso:country":"US",
    "sg:address":"463 Hazelwood Rd",
    "sg:city":"Memphis",
    "sg:classifiers":[
        {
            "category":"Retail",
            "subcategory":"Repair Shop",
            "type":"Services"
        }
    ],
    "sg:phone":"+1 901 789 9739",
    "sg:postcode":"38109",
    "sg:province":"TN",
    "wof:name":"Miller S Reupholstery",
    "wof:placetype":"venue"
},
  "geometry": {"coordinates":[-90.079829,35.05953],"type":"Point"}
}