{
  "type": "Feature",
  "properties": {
    "iso:country":"US",
    "sg:address":"8326 Beaver Ridge Rd",
    "sg:city":"Knoxville",
    "sg:classifiers":[
        {
            "category":"Professional",
            "type":"Services"
        }
    ],
    "sg:phone":"+1 865 531 2260",
    "sg:postcode":"37931",
    "sg:province":"TN",
    "wof:name":"Sue Griffith",
    "wof:placetype":"venue"
},
  "geometry": {"coordinates":[-84.11542300000001,35.98297],"type":"Point"}
}