{
  "type": "Feature",
  "properties": {
    "iso:country":"US",
    "sg:address":"402 W Market St",
    "sg:city":"Bolivar",
    "sg:classifiers":[
        {
            "category":"Building & Trades",
            "subcategory":"Equipment Rental",
            "type":"Services"
        }
    ],
    "sg:phone":"+1 731 658 1953",
    "sg:postcode":"38008",
    "sg:province":"TN",
    "sg:tags":[
        "yard"
    ],
    "wof:name":"Rent-A-Center",
    "wof:placetype":"venue"
},
  "geometry": {"coordinates":[-88.99357999999999,35.25651],"type":"Point"}
}