{
  "type": "Feature",
  "properties": {
    "iso:country":"US",
    "sg:address":"424 Creekmore Rd",
    "sg:city":"Cottontown",
    "sg:classifiers":[
        {
            "category":"Mining & Drilling",
            "type":"Manufacturing & Wholesale Goods"
        }
    ],
    "sg:phone":"+1 615 325 4187",
    "sg:postcode":"37048",
    "sg:province":"TN",
    "sg:tags":[
        "field"
    ],
    "wof:name":"Hometown Real Estate",
    "wof:placetype":"venue"
},
  "geometry": {"coordinates":[-86.58122400000001,36.498284],"type":"Point"}
}