{
  "type": "Feature",
  "properties": {
    "addr:full":"900 S Gay St Knoxville TN 37902",
    "addr:housenumber":"900",
    "addr:postcode":"37902",
    "addr:street":"S Gay St",
    "iso:country":"US",
    "sg:address":"900 S Gay St",
    "sg:city":"Knoxville",
    "sg:classifiers":[
        {
            "category":"Real Estate",
            "subcategory":"Real Estate Agent",
            "type":"Services"
        }
    ],
    "sg:phone":"+1 865 525 7500",
    "sg:postcode":"37902",
    "sg:province":"TN",
    "sg:tags":[
        "management"
    ],
    "wof:name":"American Apartment Management",
    "wof:placetype":"venue"
},
  "geometry": {"coordinates":[-83.91572600000001,35.960934],"type":"Point"}
}