{
  "type": "Feature",
  "properties": {
    "addr:full":"1615 Ketner Mill Rd Whitwell TN 37397",
    "addr:housenumber":"1615",
    "addr:postcode":"37397",
    "addr:street":"Ketner Mill Rd",
    "iso:country":"US",
    "sg:address":"1615 Ketner Mill Rd",
    "sg:city":"Whitwell",
    "sg:classifiers":[
        {
            "category":"Food & Beverages",
            "subcategory":"Groceries & Convenience Stores",
            "type":"Retail Goods"
        }
    ],
    "sg:phone":"+1 423 658 5932",
    "sg:postcode":"37397",
    "sg:province":"TN",
    "wof:name":"Laynes Grocery",
    "wof:placetype":"venue"
},
  "geometry": {"coordinates":[-85.53707,35.14946],"type":"Point"}
}