{
  "type": "Feature",
  "properties": {
    "iso:country":"US",
    "sg:address":"681 Chapel Point Ln",
    "sg:city":"Knoxville",
    "sg:classifiers":[
        {
            "category":"Home & Garden",
            "subcategory":"Hardware",
            "type":"Retail Goods"
        }
    ],
    "sg:phone":"+1 865 675 6894",
    "sg:postcode":"37934",
    "sg:province":"TN",
    "wof:name":"Superior Bolt & Screw",
    "wof:placetype":"venue"
},
  "geometry": {"coordinates":[-84.17837900000001,35.893499],"type":"Point"}
}