{
  "type": "Feature",
  "properties": {
    "iso:country":"US",
    "sg:address":"2068 Greenfield Ave NW",
    "sg:city":"Cleveland",
    "sg:classifiers":[
        {
            "category":"Building & Trades",
            "subcategory":"Construction",
            "type":"Services"
        }
    ],
    "sg:phone":"+1 423 478 2888",
    "sg:postcode":"37312",
    "sg:province":"TN",
    "wof:name":"Potts Sam Asphalt Pav Co LLC",
    "wof:placetype":"venue"
},
  "geometry": {"coordinates":[-84.89052700000001,35.207426],"type":"Point"}
}