{
  "type": "Feature",
  "properties": {
    "iso:country":"US",
    "sg:address":"36 Frazier Ave",
    "sg:city":"Chattanooga",
    "sg:classifiers":[
        {
            "category":"Shopping",
            "subcategory":"Books",
            "type":"Retail Goods"
        }
    ],
    "sg:phone":"+1 423 265 6321",
    "sg:postcode":"37405",
    "sg:province":"TN",
    "sg:tags":[
        "art",
        "jewelry"
    ],
    "wof:name":"New Moon Gallery",
    "wof:placetype":"venue"
},
  "geometry": {"coordinates":[-85.30662599999999,35.062388],"type":"Point"}
}