{
  "type": "Feature",
  "properties": {
    "iso:country":"US",
    "sg:address":"1815 Downtown West Blvd",
    "sg:city":"Knoxville",
    "sg:classifiers":[
        {
            "category":"Banks & Credit Unions",
            "subcategory":"Bank",
            "type":"Services"
        }
    ],
    "sg:phone":"+1 865 470 5410",
    "sg:postcode":"37919",
    "sg:province":"TN",
    "sg:tags":[
        "banking",
        "commercial",
        "saving"
    ],
    "sg:website":"http://ad.doubleclick.net/clk;223972431;41535373;d?https://www.firsttennessee.com/Banking/Main?nicamp=Brand&nichan=Directory&nisrc=yellowpages&niseg=Banks",
    "wof:name":"FIRST TENNESSEE BANK",
    "wof:placetype":"venue"
},
  "geometry": {"coordinates":[-84.050881,35.923371],"type":"Point"}
}