{
  "type": "Feature",
  "properties": {
    "addr:full":"105 Eatherly Dr Carthage TN 37087",
    "addr:housenumber":"105",
    "addr:postcode":"37087",
    "addr:street":"Eatherly Dr",
    "iso:country":"US",
    "sg:address":"105 Eatherly Dr",
    "sg:city":"Carthage",
    "sg:classifiers":[
        {
            "category":"Government",
            "subcategory":"Office",
            "type":"Public Place"
        }
    ],
    "sg:phone":"+1 615 735 9740",
    "sg:postcode":"37087",
    "sg:province":"TN",
    "sg:tags":[
        "state",
        "resource"
    ],
    "wof:name":"Human Service Dept",
    "wof:placetype":"venue"
},
  "geometry": {"coordinates":[-86.26014499999999,36.219499],"type":"Point"}
}