{
  "type": "Feature",
  "properties": {
    "iso:country":"US",
    "sg:address":"3 Cadillac Dr",
    "sg:city":"Brentwood",
    "sg:classifiers":[
        {
            "category":"Autos & Motor Vehicles",
            "subcategory":"Automobile Sales",
            "type":"Retail Goods"
        }
    ],
    "sg:phone":"+1 615 986 6000",
    "sg:postcode":"37027",
    "sg:province":"TN",
    "sg:tags":[
        "car",
        "dealer"
    ],
    "wof:name":"Land Rover Nashville",
    "wof:placetype":"venue"
},
  "geometry": {"coordinates":[-86.795096,36.036215],"type":"Point"}
}