{
  "type": "Feature",
  "properties": {
    "iso:country":"US",
    "sg:address":"511 Henslee Dr",
    "sg:city":"Dickson",
    "sg:classifiers":[
        {
            "category":"Professional",
            "subcategory":"Advertising",
            "type":"Services"
        }
    ],
    "sg:phone":"+1 615 740 1778",
    "sg:postcode":"37055",
    "sg:province":"TN",
    "sg:tags":[
        "distribution"
    ],
    "wof:name":"AMA Distributing Co",
    "wof:placetype":"venue"
},
  "geometry": {"coordinates":[-87.385226,36.084853],"type":"Point"}
}