{
  "type": "Feature",
  "properties": {
    "iso:country":"US",
    "sg:address":"106 Trellis Dr",
    "sg:city":"Luttrell",
    "sg:classifiers":[
        {
            "category":"Building & Trades",
            "subcategory":"Cleaning & Sanitation",
            "type":"Services"
        }
    ],
    "sg:phone":"+1 865 992 9477",
    "sg:postcode":"37779",
    "sg:province":"TN",
    "sg:tags":[
        "maintenance"
    ],
    "wof:name":"Lafollette Housing",
    "wof:placetype":"venue"
},
  "geometry": {"coordinates":[-83.755441,36.202751],"type":"Point"}
}