{
  "type": "Feature",
  "properties": {
    "iso:country":"US",
    "sg:address":"3634 Austin Peay Hwy",
    "sg:city":"Memphis",
    "sg:classifiers":[
        {
            "category":"Real Estate",
            "subcategory":"Developer",
            "type":"Services"
        }
    ],
    "sg:phone":"+1 901 377 7511",
    "sg:postcode":"38128",
    "sg:province":"TN",
    "wof:name":"Resources For Human Developmnt",
    "wof:placetype":"venue"
},
  "geometry": {"coordinates":[-89.90633699999999,35.224029],"type":"Point"}
}