{
  "type": "Feature",
  "properties": {
    "iso:country":"US",
    "sg:address":"1022 E Main St",
    "sg:city":"Henderson",
    "sg:classifiers":[
        {
            "category":"Government",
            "subcategory":"Office",
            "type":"Public Place"
        }
    ],
    "sg:phone":"+1 731 989 2542",
    "sg:postcode":"38340",
    "sg:province":"TN",
    "sg:tags":[
        "county"
    ],
    "wof:name":"Chester County CTRS/Swhra",
    "wof:placetype":"venue"
},
  "geometry": {"coordinates":[-88.610462,35.447085],"type":"Point"}
}