{
  "type": "Feature",
  "properties": {
    "iso:country":"US",
    "sg:address":"2895 Shortside Ln",
    "sg:city":"Memphis",
    "sg:classifiers":[
        {
            "category":"Freight",
            "type":"Transportation"
        }
    ],
    "sg:phone":"+1 901 362 6136",
    "sg:postcode":"38118",
    "sg:province":"TN",
    "sg:tags":[
        "general"
    ],
    "wof:name":"Furniture Service & Dlvry Co",
    "wof:placetype":"venue"
},
  "geometry": {"coordinates":[-89.94192,35.069444],"type":"Point"}
}