{
  "type": "Feature",
  "properties": {
    "addr:full":"808 Walker St Columbia TN 38401",
    "addr:housenumber":"808",
    "addr:postcode":"38401",
    "addr:street":"Walker St",
    "iso:country":"US",
    "sg:address":"808 Walker St",
    "sg:city":"Columbia",
    "sg:classifiers":[
        {
            "category":"Professional",
            "subcategory":"Lawyer & Legal Services",
            "type":"Services"
        }
    ],
    "sg:phone":"+1 931 388 6806",
    "sg:postcode":"38401",
    "sg:province":"TN",
    "sg:tags":[
        "attorney"
    ],
    "wof:name":"Clayton Environmental Svc Inc",
    "wof:placetype":"venue"
},
  "geometry": {"coordinates":[-87.03878899999999,35.614545],"type":"Point"}
}