{
  "type": "Feature",
  "properties": {
    "iso:country":"US",
    "sg:address":"4112 Hillsboro Pike",
    "sg:city":"Nashville",
    "sg:classifiers":[
        {
            "category":"Autos & Motor Vehicles",
            "subcategory":"Fuel & Gas Station",
            "type":"Retail Goods"
        }
    ],
    "sg:phone":"+1 615 383 5987",
    "sg:postcode":"37215",
    "sg:province":"TN",
    "sg:tags":[
        "oil"
    ],
    "wof:name":"Green Hills Exxon Convenience",
    "wof:placetype":"venue"
},
  "geometry": {"coordinates":[-86.818579,36.101008],"type":"Point"}
}