{
  "type": "Feature",
  "properties": {
    "addr:full":"1445 Elvis Presley Blvd Memphis TN 38106",
    "addr:housenumber":"1445",
    "addr:postcode":"38106",
    "addr:street":"Elvis Presley Blvd",
    "iso:country":"US",
    "sg:address":"1445 Elvis Presley Blvd",
    "sg:city":"Memphis",
    "sg:classifiers":[
        {
            "category":"Professional",
            "type":"Services"
        }
    ],
    "sg:phone":"+1 901 678 2581",
    "sg:postcode":"38106",
    "sg:province":"TN",
    "wof:name":"Rrg of Memphis Inc",
    "wof:placetype":"venue"
},
  "geometry": {"coordinates":[-90.02136900000001,35.107504],"type":"Point"}
}