{
  "type": "Feature",
  "properties": {
    "addr:full":"4340 N Cherry Creek Ln Memphis TN 38141",
    "addr:housenumber":"4340",
    "addr:postcode":"38141",
    "addr:street":"N Cherry Creek Ln",
    "iso:country":"US",
    "sg:address":"4340 N Cherry Creek Ln",
    "sg:city":"Memphis",
    "sg:classifiers":[
        {
            "category":"Retail",
            "subcategory":"Laundry & Dry Cleaning",
            "type":"Services"
        }
    ],
    "sg:phone":"+1 901 375 9719",
    "sg:postcode":"38141",
    "sg:province":"TN",
    "sg:tags":[
        "cleaners",
        "rug",
        "carpet"
    ],
    "wof:name":"Color Tex Systems Carpet",
    "wof:placetype":"venue"
},
  "geometry": {"coordinates":[-89.86367199999999,35.029886],"type":"Point"}
}