{
  "type": "Feature",
  "properties": {
    "addr:full":"6781 E Shelby Dr Memphis TN 38141",
    "addr:housenumber":"6781",
    "addr:postcode":"38141",
    "addr:street":"E Shelby Dr",
    "iso:country":"US",
    "sg:address":"6781 E Shelby Dr",
    "sg:city":"Memphis",
    "sg:classifiers":[
        {
            "category":"Fast Food",
            "type":"Food & Drink"
        },
        {
            "category":"Restaurant",
            "type":"Food & Drink"
        }
    ],
    "sg:phone":"+1 901 368 5909",
    "sg:postcode":"38141",
    "sg:province":"TN",
    "sg:tags":[
        "american",
        "hot",
        "hamburger",
        "dog"
    ],
    "sg:website":"http://www.wendys.com",
    "wof:name":"Wendy's",
    "wof:placetype":"venue"
},
  "geometry": {"coordinates":[-89.83713,35.02039],"type":"Point"}
}