{
  "type": "Feature",
  "properties": {
    "iso:country":"US",
    "sg:address":"3826 Vesta Rd",
    "sg:city":"Lebanon",
    "sg:classifiers":[
        {
            "category":"Government",
            "subcategory":"Office",
            "type":"Public Place"
        }
    ],
    "sg:phone":"+1 615 444 2869",
    "sg:postcode":"37090",
    "sg:province":"TN",
    "sg:tags":[
        "village"
    ],
    "wof:name":"Gladeville Water Plant",
    "wof:placetype":"venue"
},
  "geometry": {"coordinates":[-86.421041,36.066435],"type":"Point"}
}