{
  "type": "Feature",
  "properties": {
    "addr:full":"352 Lige Rd Crossville TN 38555",
    "addr:housenumber":"352",
    "addr:postcode":"38555",
    "addr:street":"Lige Rd",
    "iso:country":"US",
    "sg:address":"352 Lige Rd",
    "sg:city":"Crossville",
    "sg:classifiers":[
        {
            "category":"Building & Trades",
            "subcategory":"Landscaping Services",
            "type":"Services"
        }
    ],
    "sg:phone":"+1 931 456 1051",
    "sg:postcode":"38555",
    "sg:province":"TN",
    "sg:tags":[
        "landscape"
    ],
    "wof:name":"All Around Services",
    "wof:placetype":"venue"
},
  "geometry": {"coordinates":[-84.985981,35.857327],"type":"Point"}
}