{
  "type": "Feature",
  "properties": {
    "addr:full":"3804 Saint Elmo Ave Chattanooga TN 37409",
    "addr:housenumber":"3804",
    "addr:postcode":"37409",
    "addr:street":"Saint Elmo Ave",
    "iso:country":"US",
    "sg:address":"3804 Saint Elmo Ave",
    "sg:city":"Chattanooga",
    "sg:classifiers":[
        {
            "category":"Professional",
            "subcategory":"Computer Services",
            "type":"Services"
        }
    ],
    "sg:phone":"+1 423 821 6210",
    "sg:postcode":"37409",
    "sg:province":"TN",
    "sg:tags":[
        "consultant",
        "designer",
        "datum",
        "system"
    ],
    "wof:name":"Tubatomic Studio",
    "wof:placetype":"venue"
},
  "geometry": {"coordinates":[-85.328357,35.010557],"type":"Point"}
}