{
  "type": "Feature",
  "properties": {
    "iso:country":"US",
    "sg:address":"180 Old Hickory Blvd E",
    "sg:city":"Jackson",
    "sg:classifiers":[
        {
            "category":"Restaurant",
            "type":"Food & Drink"
        }
    ],
    "sg:phone":"+1 731 664 3121",
    "sg:postcode":"38305",
    "sg:province":"TN",
    "sg:tags":[
        "eating"
    ],
    "wof:name":"Jade Garden",
    "wof:placetype":"venue"
},
  "geometry": {"coordinates":[-88.826341,35.651025],"type":"Point"}
}