{
  "type": "Feature",
  "properties": {
    "iso:country":"US",
    "sg:address":"1606 N Tennessee Blvd",
    "sg:city":"Murfreesboro",
    "sg:classifiers":[
        {
            "category":"Real Estate",
            "subcategory":"Real Estate Operator",
            "type":"Services"
        }
    ],
    "sg:phone":"+1 615 890 3700",
    "sg:postcode":"37130",
    "sg:province":"TN",
    "sg:tags":[
        "apartment"
    ],
    "wof:name":"Rosewood Apartments",
    "wof:placetype":"venue"
},
  "geometry": {"coordinates":[-86.36887400000001,35.866779],"type":"Point"}
}