{
  "type": "Feature",
  "properties": {
    "addr:full":"6800 Poplar Ave Germantown TN 38138",
    "addr:housenumber":"6800",
    "addr:postcode":"38138",
    "addr:street":"Poplar Ave",
    "iso:country":"US",
    "sg:address":"6800 Poplar Ave",
    "sg:city":"Germantown",
    "sg:classifiers":[
        {
            "category":"Professional",
            "subcategory":"Lawyer & Legal Services",
            "type":"Services"
        }
    ],
    "sg:phone":"+1 901 737 5656",
    "sg:postcode":"38138",
    "sg:province":"TN",
    "sg:tags":[
        "attorney"
    ],
    "wof:name":"Baker & Whitt",
    "wof:placetype":"venue"
},
  "geometry": {"coordinates":[-89.836511,35.097995],"type":"Point"}
}