{
  "type": "Feature",
  "properties": {
    "iso:country":"US",
    "sg:address":"140 E Division Rd",
    "sg:city":"Oak Ridge",
    "sg:classifiers":[
        {
            "category":"Professional",
            "subcategory":"Management & Consulting",
            "type":"Services"
        }
    ],
    "sg:phone":"+1 865 220 8630",
    "sg:postcode":"37830",
    "sg:province":"TN",
    "wof:name":"Netgain Corporation",
    "wof:placetype":"venue"
},
  "geometry": {"coordinates":[-84.241433,36.020609],"type":"Point"}
}