{
  "type": "Feature",
  "properties": {
    "iso:country":"US",
    "sg:address":"910 N 1st St",
    "sg:city":"Pulaski",
    "sg:classifiers":[
        {
            "category":"Retail",
            "subcategory":"Funeral Services",
            "type":"Services"
        }
    ],
    "sg:phone":"+1 931 424 8010",
    "sg:postcode":"38478",
    "sg:province":"TN",
    "wof:name":"Rose of Sharon Funeral Service",
    "wof:placetype":"venue"
},
  "geometry": {"coordinates":[-87.026797,35.20947],"type":"Point"}
}