{
  "type": "Feature",
  "properties": {
    "iso:country":"US",
    "sg:address":"31 N Madison Dr",
    "sg:city":"Humboldt",
    "sg:classifiers":[
        {
            "category":"Wholesale",
            "subcategory":"Machinery & Supplies",
            "type":"Manufacturing & Wholesale Goods"
        }
    ],
    "sg:phone":"+1 731 784 4800",
    "sg:postcode":"38343",
    "sg:province":"TN",
    "sg:tags":[
        "equipment",
        "industrial"
    ],
    "wof:name":"Moore Machinery Sales",
    "wof:placetype":"venue"
},
  "geometry": {"coordinates":[-88.845046,35.753299],"type":"Point"}
}