{
  "type": "Feature",
  "properties": {
    "addr:full":"121 Spring St Johnson City TN 37604",
    "addr:housenumber":"121",
    "addr:postcode":"37604",
    "addr:street":"Spring St",
    "iso:country":"US",
    "sg:address":"121 Spring St",
    "sg:city":"Johnson City",
    "sg:classifiers":[
        {
            "category":"Organizations",
            "subcategory":"Political Organization",
            "type":"Services"
        }
    ],
    "sg:phone":"+1 423 926 1148",
    "sg:postcode":"37604",
    "sg:province":"TN",
    "wof:name":"Johnson City Democratic Club",
    "wof:placetype":"venue"
},
  "geometry": {"coordinates":[-82.351603,36.315485],"type":"Point"}
}