{
  "type": "Feature",
  "properties": {
    "iso:country":"US",
    "sg:address":"1465 N Mack Smith Rd",
    "sg:city":"Chattanooga",
    "sg:classifiers":[
        {
            "category":"Professional",
            "subcategory":"Business Services",
            "type":"Services"
        }
    ],
    "sg:phone":"+1 423 893 8181",
    "sg:postcode":"37412",
    "sg:province":"TN",
    "wof:name":"Easy Auction",
    "wof:placetype":"venue"
},
  "geometry": {"coordinates":[-85.21781900000001,34.999418],"type":"Point"}
}