{
  "type": "Feature",
  "properties": {
    "iso:country":"US",
    "sg:address":"3104 Broad St",
    "sg:city":"Chattanooga",
    "sg:classifiers":[
        {
            "category":"Restaurant",
            "type":"Food & Drink"
        }
    ],
    "sg:menulink":"http://www.allmenus.com/tn/chattanooga/173171-wendys/menu/",
    "sg:phone":"+1 423 267 0754",
    "sg:postcode":"37408",
    "sg:province":"TN",
    "sg:tags":[
        "burger",
        "american",
        "soup"
    ],
    "wof:name":"Wendy's",
    "wof:placetype":"venue"
},
  "geometry": {"coordinates":[-85.32049600000001,35.020802],"type":"Point"}
}