{
  "type": "Feature",
  "properties": {
    "addr:full":"4826 US Hwy 70 E Brownsville TN 38012",
    "addr:housenumber":"4826",
    "addr:postcode":"38012",
    "addr:street":"Us Hwy 70 E",
    "iso:country":"US",
    "sg:address":"4826 US Hwy 70 E",
    "sg:city":"Brownsville",
    "sg:classifiers":[
        {
            "category":"Shopping",
            "subcategory":"Discount & Variety Stores",
            "type":"Retail Goods"
        }
    ],
    "sg:phone":"+1 731 772 1694",
    "sg:postcode":"38012",
    "sg:province":"TN",
    "sg:tags":[
        "merchandise",
        "general"
    ],
    "wof:name":"Mulligan Store",
    "wof:placetype":"venue"
},
  "geometry": {"coordinates":[-89.1771,35.59128],"type":"Point"}
}