{
  "type": "Feature",
  "properties": {
    "iso:country":"US",
    "sg:address":"955 E McKinney Ave",
    "sg:city":"Rogersville",
    "sg:classifiers":[
        {
            "category":"Social Services",
            "subcategory":"Job Training",
            "type":"Services"
        }
    ],
    "sg:phone":"+1 423 272 2661",
    "sg:postcode":"37857",
    "sg:province":"TN",
    "sg:tags":[
        "rehab",
        "government"
    ],
    "wof:name":"Employment Security Dept",
    "wof:placetype":"venue"
},
  "geometry": {"coordinates":[-82.994714,36.411607],"type":"Point"}
}