{
  "type": "Feature",
  "properties": {
    "iso:country":"US",
    "sg:address":"11 Music Sq E",
    "sg:city":"Nashville",
    "sg:classifiers":[
        {
            "category":"Banks & Credit Unions",
            "subcategory":"Bank",
            "type":"Services"
        }
    ],
    "sg:phone":"+1 615 252 2522",
    "sg:postcode":"37203",
    "sg:province":"TN",
    "sg:tags":[
        "broker",
        "mortgage"
    ],
    "wof:name":"Advantage Funding LLC",
    "wof:placetype":"venue"
},
  "geometry": {"coordinates":[-86.791724,36.151672],"type":"Point"}
}