{
  "type": "Feature",
  "properties": {
    "addr:full":"1020 Jackson St Nashville TN 37208",
    "addr:housenumber":"1020",
    "addr:postcode":"37208",
    "addr:street":"Jackson St",
    "iso:country":"US",
    "sg:address":"1020 Jackson St",
    "sg:city":"Nashville",
    "sg:classifiers":[
        {
            "category":"Organizations",
            "subcategory":"Membership Organization",
            "type":"Services"
        }
    ],
    "sg:phone":"+1 615 251 1149",
    "sg:postcode":"37208",
    "sg:province":"TN",
    "wof:name":"Community Enhancement Orgnztn",
    "wof:placetype":"venue"
},
  "geometry": {"coordinates":[-86.795147,36.170145],"type":"Point"}
}