{
  "type": "Feature",
  "properties": {
    "addr:full":"528 W College St Murfreesboro TN 37130",
    "addr:housenumber":"528",
    "addr:postcode":"37130",
    "addr:street":"W College St",
    "iso:country":"US",
    "sg:address":"528 W College St",
    "sg:city":"Murfreesboro",
    "sg:classifiers":[
        {
            "category":"Restaurant",
            "type":"Food & Drink"
        }
    ],
    "sg:phone":"+1 615 893 1405",
    "sg:postcode":"37130",
    "sg:province":"TN",
    "sg:tags":[
        "eating"
    ],
    "sg:website":"www.redrosecoffee.com",
    "wof:name":"Red Rose Coffee House & Bistro",
    "wof:placetype":"venue"
},
  "geometry": {"coordinates":[-86.39670599999999,35.848436],"type":"Point"}
}