{
  "type": "Feature",
  "properties": {
    "iso:country":"US",
    "sg:address":"68 S Yates Rd",
    "sg:city":"Memphis",
    "sg:classifiers":[
        {
            "category":"Sports & Exercise",
            "subcategory":"Sports Center",
            "type":"Entertainment"
        }
    ],
    "sg:phone":"+1 901 251 0641",
    "sg:postcode":"38120",
    "sg:province":"TN",
    "sg:tags":[
        "manager",
        "promoter"
    ],
    "wof:name":"Memphis & Shelby County Sports Authority",
    "wof:placetype":"venue"
},
  "geometry": {"coordinates":[-89.87470999999999,35.129126],"type":"Point"}
}