{
  "type": "Feature",
  "properties": {
    "addr:full":"2233 Fairview Blvd Fairview TN 37062",
    "addr:housenumber":"2233",
    "addr:postcode":"37062",
    "addr:street":"Fairview Blvd",
    "iso:country":"US",
    "sg:address":"2233 Fairview Blvd",
    "sg:city":"Fairview",
    "sg:classifiers":[
        {
            "category":"Restaurant",
            "type":"Food & Drink"
        }
    ],
    "sg:menulink":"http://www.allmenus.com/tn/fairview/203431-mcdonalds/menu/",
    "sg:phone":"+1 615 799 2227",
    "sg:postcode":"37062",
    "sg:province":"TN",
    "sg:tags":[
        "burger",
        "american"
    ],
    "wof:name":"McDonald's",
    "wof:placetype":"venue"
},
  "geometry": {"coordinates":[-87.128428,35.972556],"type":"Point"}
}