{
  "type": "Feature",
  "properties": {
    "iso:country":"US",
    "sg:address":"7800 Chapel Ridge Dr",
    "sg:city":"Cordova",
    "sg:classifiers":[
        {
            "category":"Building & Trades",
            "subcategory":"Construction",
            "type":"Services"
        }
    ],
    "sg:phone":"+1 901 624 2755",
    "sg:postcode":"38016",
    "sg:province":"TN",
    "sg:tags":[
        "house"
    ],
    "wof:name":"Ross Johnson Homes",
    "wof:placetype":"venue"
},
  "geometry": {"coordinates":[-89.80345,35.174764],"type":"Point"}
}