{
  "type": "Feature",
  "properties": {
    "addr:full":"101 E Broyles St Greeneville TN 37745",
    "addr:housenumber":"101",
    "addr:postcode":"37745",
    "addr:street":"E Broyles St",
    "iso:country":"US",
    "sg:address":"101 E Broyles St",
    "sg:city":"Greeneville",
    "sg:classifiers":[
        {
            "category":"Building & Trades",
            "subcategory":"Electrical",
            "type":"Services"
        }
    ],
    "sg:phone":"+1 423 639 7846",
    "sg:postcode":"37745",
    "sg:province":"TN",
    "sg:tags":[
        "electrical",
        "contractor"
    ],
    "wof:name":"Electrical Services Unlimited",
    "wof:placetype":"venue"
},
  "geometry": {"coordinates":[-82.825406,36.176837],"type":"Point"}
}