{
  "type": "Feature",
  "properties": {
    "iso:country":"US",
    "sg:address":"3555 Keith St",
    "sg:city":"Cleveland",
    "sg:classifiers":[
        {
            "category":"Personal",
            "subcategory":"Beauty Salon",
            "type":"Services"
        }
    ],
    "sg:phone":"+1 423 476 4488",
    "sg:postcode":"37312",
    "sg:province":"TN",
    "sg:tags":[
        "shop"
    ],
    "wof:name":"RE Creations Salon",
    "wof:placetype":"venue"
},
  "geometry": {"coordinates":[-84.85647400000001,35.194697],"type":"Point"}
}