{
  "type": "Feature",
  "properties": {
    "iso:country":"US",
    "sg:address":"1714 Louisville Dr",
    "sg:city":"Knoxville",
    "sg:classifiers":[
        {
            "category":"Wholesale",
            "subcategory":"Construction Materials",
            "type":"Manufacturing & Wholesale Goods"
        },
        {
            "category":"Manufacturing",
            "subcategory":"Glass & Minerals",
            "type":"Manufacturing & Wholesale Goods"
        }
    ],
    "sg:phone":"+1 865 588 2155",
    "sg:postcode":"37921",
    "sg:province":"TN",
    "sg:tags":[
        "tile",
        "product",
        "ceramic",
        "marble"
    ],
    "wof:name":"Dal-Tile",
    "wof:placetype":"venue"
},
  "geometry": {"coordinates":[-84.011805,35.960507],"type":"Point"}
}