{
  "type": "Feature",
  "properties": {
    "iso:country":"US",
    "sg:address":"1028 Glastonbury Dr",
    "sg:city":"Franklin",
    "sg:classifiers":[
        {
            "category":"Freight",
            "type":"Transportation"
        }
    ],
    "sg:phone":"+1 615 591 0849",
    "sg:postcode":"37069",
    "sg:province":"TN",
    "wof:name":"C & P Transport Inc",
    "wof:placetype":"venue"
},
  "geometry": {"coordinates":[-86.894974,35.965553],"type":"Point"}
}