{
  "type": "Feature",
  "properties": {
    "iso:country":"US",
    "sg:address":"7322 Bennington Dr",
    "sg:city":"Knoxville",
    "sg:classifiers":[
        {
            "category":"Autos & Motor Vehicles",
            "subcategory":"Automobile Sales",
            "type":"Retail Goods"
        }
    ],
    "sg:phone":"+1 865 531 0069",
    "sg:postcode":"37909",
    "sg:province":"TN",
    "sg:tags":[
        "car",
        "dealer"
    ],
    "wof:name":"Rice Buick GMC Truck Inc",
    "wof:placetype":"venue"
},
  "geometry": {"coordinates":[-84.03575600000001,35.936946],"type":"Point"}
}