{
  "type": "Feature",
  "properties": {
    "iso:country":"US",
    "sg:address":"2753 Jarrell Ridge Rd",
    "sg:city":"Clarksville",
    "sg:classifiers":[
        {
            "category":"Building & Trades",
            "subcategory":"Construction",
            "type":"Services"
        }
    ],
    "sg:phone":"+1 931 362 2300",
    "sg:postcode":"37043",
    "sg:province":"TN",
    "sg:tags":[
        "house"
    ],
    "wof:name":"Thaxton Construction",
    "wof:placetype":"venue"
},
  "geometry": {"coordinates":[-87.210938,36.412375],"type":"Point"}
}