{
  "type": "Feature",
  "properties": {
    "iso:country":"US",
    "sg:address":"11500 N Monticello Dr",
    "sg:city":"Knoxville",
    "sg:classifiers":[
        {
            "category":"Organizations",
            "subcategory":"Professional Association",
            "type":"Services"
        }
    ],
    "sg:phone":"+1 865 531 3288",
    "sg:postcode":"37934",
    "sg:province":"TN",
    "sg:tags":[
        "firm"
    ],
    "wof:name":"King Cynthia G Cpa PC",
    "wof:placetype":"venue"
},
  "geometry": {"coordinates":[-84.173177,35.888107],"type":"Point"}
}