{
  "type": "Feature",
  "properties": {
    "iso:country":"US",
    "sg:address":"93 N Rufe Taylor Rd",
    "sg:city":"Greeneville",
    "sg:classifiers":[
        {
            "category":"Restaurant",
            "type":"Food & Drink"
        }
    ],
    "sg:phone":"+1 423 638 1000",
    "sg:postcode":"37745",
    "sg:province":"TN",
    "sg:tags":[
        "eating"
    ],
    "wof:name":"J & Es Italian Village Inc",
    "wof:placetype":"venue"
},
  "geometry": {"coordinates":[-82.771199,36.18289],"type":"Point"}
}