{
  "type": "Feature",
  "properties": {
    "addr:full":"1512 J P Hennessy Dr La Vergne TN 37086",
    "addr:housenumber":"1512",
    "addr:postcode":"37086",
    "addr:street":"J P Hennessy Dr",
    "iso:country":"US",
    "sg:address":"1512 J P Hennessy Dr",
    "sg:city":"La Vergne",
    "sg:classifiers":[
        {
            "category":"Manufacturing",
            "subcategory":"Tools & Machinery",
            "type":"Manufacturing & Wholesale Goods"
        }
    ],
    "sg:phone":"+1 615 641 6964",
    "sg:postcode":"37086",
    "sg:province":"TN",
    "sg:tags":[
        "equipment",
        "material",
        "handling",
        "mfg"
    ],
    "sg:website":"www.wolfeindustrial.com",
    "wof:name":"Wolfe Industrial Inc",
    "wof:placetype":"venue"
},
  "geometry": {"coordinates":[-86.60877600000001,36.01158],"type":"Point"}
}