{
  "type": "Feature",
  "properties": {
    "iso:country":"US",
    "sg:address":"1050 Ski View Dr",
    "sg:city":"Gatlinburg",
    "sg:classifiers":[
        {
            "category":"Real Estate",
            "subcategory":"Real Estate Agent",
            "type":"Services"
        }
    ],
    "sg:phone":"+1 865 436 5225",
    "sg:postcode":"37738",
    "sg:province":"TN",
    "wof:name":"Kile Mgmtment Co",
    "wof:placetype":"venue"
},
  "geometry": {"coordinates":[-83.55586700000001,35.710043],"type":"Point"}
}