{
  "type": "Feature",
  "properties": {
    "iso:country":"US",
    "sg:address":"107 Hill Rd",
    "sg:city":"Ardmore",
    "sg:classifiers":[
        {
            "category":"Shopping",
            "subcategory":"Used Merchandise",
            "type":"Retail Goods"
        }
    ],
    "sg:phone":"+1 615 494 1131",
    "sg:postcode":"38449",
    "sg:province":"AL",
    "sg:tags":[
        "pawnbroker"
    ],
    "wof:name":"Pawn Web Jones & Assoc",
    "wof:placetype":"venue"
},
  "geometry": {"coordinates":[-86.789142,35.081325],"type":"Point"}
}