{
  "type": "Feature",
  "properties": {
    "iso:country":"US",
    "sg:address":"7621 E Lamar Alexander Pkwy",
    "sg:city":"Townsend",
    "sg:classifiers":[
        {
            "category":"Restaurant",
            "type":"Food & Drink"
        }
    ],
    "sg:phone":"+1 865 448 2046",
    "sg:postcode":"37882",
    "sg:province":"TN",
    "sg:tags":[
        "eating"
    ],
    "wof:name":"Anns Pizza Haven",
    "wof:placetype":"venue"
},
  "geometry": {"coordinates":[-83.756421,35.676122],"type":"Point"}
}