{
  "type": "Feature",
  "properties": {
    "iso:country":"US",
    "sg:address":"252 River Rock Blvd",
    "sg:city":"Murfreesboro",
    "sg:classifiers":[
        {
            "category":"Shopping",
            "subcategory":"Clothing, Apparel, & Fashions",
            "type":"Retail Goods"
        }
    ],
    "sg:phone":"+1 615 895 0476",
    "sg:postcode":"37128",
    "sg:province":"TN",
    "sg:tags":[
        "infant",
        "wear"
    ],
    "wof:name":"Carter's Childrenswear",
    "wof:placetype":"venue"
},
  "geometry": {"coordinates":[-86.43626,35.845531],"type":"Point"}
}