{
  "type": "Feature",
  "properties": {
    "iso:country":"US",
    "sg:address":"1741 Upper River Rd NE",
    "sg:city":"Charleston",
    "sg:classifiers":[
        {
            "category":"Autos & Motor Vehicles",
            "subcategory":"Automobile Sales",
            "type":"Retail Goods"
        }
    ],
    "sg:phone":"+1 423 336 1617",
    "sg:postcode":"37310",
    "sg:province":"TN",
    "sg:tags":[
        "used"
    ],
    "wof:name":"Tennessee Motors",
    "wof:placetype":"venue"
},
  "geometry": {"coordinates":[-84.72594700000001,35.253359],"type":"Point"}
}