{
  "type": "Feature",
  "properties": {
    "addr:full":"2612 US Hwy 43 S Leoma TN 38468",
    "addr:housenumber":"2612",
    "addr:postcode":"38468",
    "addr:street":"Us Hwy 43 S",
    "iso:country":"US",
    "sg:address":"2612 US Hwy 43 S",
    "sg:city":"Leoma",
    "sg:classifiers":[
        {
            "category":"Education",
            "subcategory":"School",
            "type":"Public Place"
        }
    ],
    "sg:phone":"+1 931 852 2542",
    "sg:postcode":"38468",
    "sg:province":"TN",
    "wof:name":"Leoma Elementary School",
    "wof:placetype":"venue"
},
  "geometry": {"coordinates":[-87.35925899999999,35.148892],"type":"Point"}
}