{
  "type": "Feature",
  "properties": {
    "iso:country":"US",
    "sg:address":"1649 E Stone Dr",
    "sg:city":"Kingsport",
    "sg:classifiers":[
        {
            "category":"Autos & Motor Vehicles",
            "subcategory":"Auto Supplies",
            "type":"Retail Goods"
        }
    ],
    "sg:phone":"+1 423 392 1100",
    "sg:postcode":"37660",
    "sg:province":"TN",
    "sg:tags":[
        "automobile",
        "parts"
    ],
    "sg:website":"www.autozone.com",
    "wof:name":"Autozone",
    "wof:placetype":"venue"
},
  "geometry": {"coordinates":[-82.51836900000001,36.547679],"type":"Point"}
}