{
  "type": "Feature",
  "properties": {
    "addr:full":"5902 Kingston Pike Knoxville TN 37919",
    "addr:housenumber":"5902",
    "addr:postcode":"37919",
    "addr:street":"Kingston Pike",
    "iso:country":"US",
    "sg:address":"5902 Kingston Pike",
    "sg:city":"Knoxville",
    "sg:classifiers":[
        {
            "category":"Organizations",
            "subcategory":"Religious Organization",
            "type":"Services"
        }
    ],
    "sg:phone":"+1 865 558 6391",
    "sg:postcode":"37919",
    "sg:province":"TN",
    "sg:tags":[
        "church"
    ],
    "wof:name":"Knoxville Korean Christian",
    "wof:placetype":"venue"
},
  "geometry": {"coordinates":[-84.000933,35.933175],"type":"Point"}
}