{
  "type": "Feature",
  "properties": {
    "iso:country":"US",
    "sg:address":"3779 Tinker Hollow Rd",
    "sg:city":"Pigeon Forge",
    "sg:classifiers":[
        {
            "category":"Retail",
            "subcategory":"Animal Services",
            "type":"Services"
        }
    ],
    "sg:phone":"+1 865 453 2028",
    "sg:postcode":"37863",
    "sg:province":"TN",
    "wof:name":"Loving Care Kennels",
    "wof:placetype":"venue"
},
  "geometry": {"coordinates":[-83.56019999999999,35.773179],"type":"Point"}
}