{
  "type": "Feature",
  "properties": {
    "addr:full":"2963 Foster Creighton Dr Nashville TN 37204",
    "addr:housenumber":"2963",
    "addr:postcode":"37204",
    "addr:street":"Foster Creighton Dr",
    "iso:country":"US",
    "sg:address":"2963 Foster Creighton Dr",
    "sg:city":"Nashville",
    "sg:classifiers":[
        {
            "category":"Manufacturing",
            "subcategory":"Printing",
            "type":"Manufacturing & Wholesale Goods"
        },
        {
            "category":"Professional",
            "subcategory":"Computer Services",
            "type":"Services"
        }
    ],
    "sg:phone":"+1 615 259 3733",
    "sg:postcode":"37204",
    "sg:province":"TN",
    "sg:tags":[
        "publisher",
        "software",
        "developer"
    ],
    "sg:website":"www.littleplanet.com",
    "wof:name":"Little Planet Learning Inc",
    "wof:placetype":"venue"
},
  "geometry": {"coordinates":[-86.75424099999999,36.105779],"type":"Point"}
}