{
  "type": "Feature",
  "properties": {
    "iso:country":"US",
    "sg:address":"700 E McMurry Blvd",
    "sg:city":"Hartsville",
    "sg:classifiers":[
        {
            "category":"Health Services",
            "subcategory":"Nursing And Care Facility",
            "type":"Services"
        }
    ],
    "sg:phone":"+1 615 374 3689",
    "sg:postcode":"37074",
    "sg:province":"TN",
    "sg:tags":[
        "home",
        "retirement",
        "community"
    ],
    "wof:name":"Sun Valley Retirement Home",
    "wof:placetype":"venue"
},
  "geometry": {"coordinates":[-86.144947,36.389337],"type":"Point"}
}