{
  "type": "Feature",
  "properties": {
    "iso:country":"US",
    "sg:address":"10021 Bluegrass Rd",
    "sg:city":"Knoxville",
    "sg:classifiers":[
        {
            "category":"Restaurant",
            "type":"Food & Drink"
        }
    ],
    "sg:phone":"+1 865 675 8933",
    "sg:postcode":"37922",
    "sg:province":"TN",
    "sg:tags":[
        "eating"
    ],
    "wof:name":"Brewingdale Coffee",
    "wof:placetype":"venue"
},
  "geometry": {"coordinates":[-84.099221,35.864053],"type":"Point"}
}