{
  "type": "Feature",
  "properties": {
    "addr:full":"3939 S 3rd St Memphis TN 38109",
    "addr:housenumber":"3939",
    "addr:postcode":"38109",
    "addr:street":"S 3Rd St",
    "iso:country":"US",
    "sg:address":"3939 S 3rd St",
    "sg:city":"Memphis",
    "sg:classifiers":[
        {
            "category":"Education",
            "subcategory":"School",
            "type":"Public Place"
        }
    ],
    "sg:phone":"+1 901 785 5592",
    "sg:postcode":"38109",
    "sg:province":"TN",
    "wof:name":"Levi Elem Headstart",
    "wof:placetype":"venue"
},
  "geometry": {"coordinates":[-90.067729,35.04106],"type":"Point"}
}