{
  "type": "Feature",
  "properties": {
    "iso:country":"US",
    "sg:address":"604 S Royal St",
    "sg:city":"Jackson",
    "sg:classifiers":[
        {
            "category":"Communications",
            "type":"Services"
        }
    ],
    "sg:phone":"+1 731 423 3440",
    "sg:postcode":"38301",
    "sg:province":"TN",
    "wof:name":"KIS Communications Inc",
    "wof:placetype":"venue"
},
  "geometry": {"coordinates":[-88.813802,35.603927],"type":"Point"}
}