{
  "type": "Feature",
  "properties": {
    "iso:country":"US",
    "sg:address":"4025 Sawmill Rd",
    "sg:city":"Woodlawn",
    "sg:classifiers":[
        {
            "category":"Wholesale",
            "subcategory":"Machinery & Supplies",
            "type":"Manufacturing & Wholesale Goods"
        }
    ],
    "sg:phone":"+1 931 920 2557",
    "sg:postcode":"37191",
    "sg:province":"TN",
    "sg:tags":[
        "equipment",
        "industrial"
    ],
    "wof:name":"Mikes Small Engine",
    "wof:placetype":"venue"
},
  "geometry": {"coordinates":[-87.479405,36.462294],"type":"Point"}
}