{
  "type": "Feature",
  "properties": {
    "addr:full":"330 Cedar Glen Cir Chattanooga TN 37412",
    "addr:housenumber":"330",
    "addr:postcode":"37412",
    "addr:street":"Cedar Glen Cir",
    "iso:country":"US",
    "sg:address":"330 Cedar Glen Cir",
    "sg:city":"Chattanooga",
    "sg:classifiers":[
        {
            "category":"Building & Trades",
            "subcategory":"Cleaning & Sanitation",
            "type":"Services"
        },
        {
            "category":"Organizations",
            "subcategory":"Community Association",
            "type":"Services"
        }
    ],
    "sg:phone":"+1 423 510 9052",
    "sg:postcode":"37412",
    "sg:province":"TN",
    "sg:tags":[
        "blind",
        "maintenance"
    ],
    "wof:name":"Bright & Shiny Blind Cleaners",
    "wof:placetype":"venue"
},
  "geometry": {"coordinates":[-85.191423,34.998857],"type":"Point"}
}