{
  "type": "Feature",
  "properties": {
    "iso:country":"US",
    "sg:address":"536 Blockhouse Rd",
    "sg:city":"Maryville",
    "sg:classifiers":[
        {
            "category":"Organizations",
            "subcategory":"Religious Organization",
            "type":"Services"
        }
    ],
    "sg:phone":"+1 865 983 7777",
    "sg:postcode":"37803",
    "sg:province":"TN",
    "sg:tags":[
        "church"
    ],
    "wof:name":"Piney Grove Baptist Church",
    "wof:placetype":"venue"
},
  "geometry": {"coordinates":[-83.933037,35.704419],"type":"Point"}
}