{
  "type": "Feature",
  "properties": {
    "iso:country":"US",
    "sg:address":"922 W Main St",
    "sg:city":"Parsons",
    "sg:classifiers":[
        {
            "category":"Professional",
            "subcategory":"Business Services",
            "type":"Services"
        }
    ],
    "sg:phone":"+1 731 847 9900",
    "sg:postcode":"38363",
    "sg:province":"TN",
    "wof:name":"Building Concepts Co",
    "wof:placetype":"venue"
},
  "geometry": {"coordinates":[-88.14283,35.647912],"type":"Point"}
}