{
  "type": "Feature",
  "properties": {
    "addr:full":"2624 Nolensville Pike Nashville TN 37211",
    "addr:housenumber":"2624",
    "addr:postcode":"37211",
    "addr:street":"Nolensville Pike",
    "iso:country":"US",
    "sg:address":"2624 Nolensville Pike",
    "sg:city":"Nashville",
    "sg:classifiers":[
        {
            "category":"Autos & Motor Vehicles",
            "subcategory":"Automobile Sales",
            "type":"Retail Goods"
        }
    ],
    "sg:phone":"+1 615 242 1279",
    "sg:postcode":"37211",
    "sg:province":"TN",
    "sg:tags":[
        "used"
    ],
    "wof:name":"Auto Mart Used Cars",
    "wof:placetype":"venue"
},
  "geometry": {"coordinates":[-86.747767,36.116145],"type":"Point"}
}