{
  "type": "Feature",
  "properties": {
    "iso:country":"US",
    "sg:address":"3661 Brainerd Rd",
    "sg:city":"Chattanooga",
    "sg:classifiers":[
        {
            "category":"Social Services",
            "type":"Services"
        }
    ],
    "sg:phone":"+1 423 629 0840",
    "sg:postcode":"37411",
    "sg:province":"TN",
    "wof:name":"Correctional Cnslng & Prbtn",
    "wof:placetype":"venue"
},
  "geometry": {"coordinates":[-85.245339,35.023809],"type":"Point"}
}