{
  "type": "Feature",
  "properties": {
    "iso:country":"US",
    "sg:address":"298 Swallows Chapel Rd",
    "sg:city":"Rickman",
    "sg:classifiers":[
        {
            "category":"Retail",
            "subcategory":"Repair Shop",
            "type":"Services"
        }
    ],
    "sg:phone":"+1 931 498 4952",
    "sg:postcode":"38506",
    "sg:province":"TN",
    "sg:tags":[
        "related"
    ],
    "wof:name":"Roscoe's Small Eng Repair Eng",
    "wof:placetype":"venue"
},
  "geometry": {"coordinates":[-85.41470099999999,36.303725],"type":"Point"}
}