{
  "type": "Feature",
  "properties": {
    "iso:country":"US",
    "sg:address":"1478 US Hwy 51 Bus",
    "sg:city":"Dyersburg",
    "sg:classifiers":[
        {
            "category":"Shopping",
            "subcategory":"Used Merchandise",
            "type":"Retail Goods"
        }
    ],
    "sg:phone":"+1 731 285 6001",
    "sg:postcode":"38024",
    "sg:province":"TN",
    "sg:tags":[
        "shop",
        "thrift"
    ],
    "wof:name":"Goodwill Industries",
    "wof:placetype":"venue"
},
  "geometry": {"coordinates":[-89.372793,36.046191],"type":"Point"}
}