{
  "type": "Feature",
  "properties": {
    "iso:country":"US",
    "sg:address":"504 Maple St",
    "sg:city":"Athens",
    "sg:classifiers":[
        {
            "category":"Personal",
            "subcategory":"Barber",
            "type":"Services"
        }
    ],
    "sg:phone":"+1 423 746 2843",
    "sg:postcode":"37303",
    "sg:province":"TN",
    "sg:tags":[
        "shop"
    ],
    "wof:name":"T W C Barber Shop",
    "wof:placetype":"venue"
},
  "geometry": {"coordinates":[-84.615042,35.444286],"type":"Point"}
}