{
  "type": "Feature",
  "properties": {
    "iso:country":"US",
    "sg:address":"2117 Berry St",
    "sg:city":"Kingsport",
    "sg:classifiers":[
        {
            "category":"Retail",
            "subcategory":"Laundry & Dry Cleaning",
            "type":"Services"
        }
    ],
    "sg:phone":"+1 423 247 4101",
    "sg:postcode":"37664",
    "sg:province":"TN",
    "sg:tags":[
        "uniform",
        "supply"
    ],
    "sg:website":"www.gkservices.com",
    "wof:name":"G & K Svc",
    "wof:placetype":"venue"
},
  "geometry": {"coordinates":[-82.52343,36.533857],"type":"Point"}
}