{
  "type": "Feature",
  "properties": {
    "iso:country":"US",
    "sg:address":"4106 Sneed Rd",
    "sg:city":"Nashville",
    "sg:classifiers":[
        {
            "category":"Professional",
            "subcategory":"Advertising",
            "type":"Services"
        }
    ],
    "sg:phone":"+1 615 386 3838",
    "sg:postcode":"37215",
    "sg:province":"TN",
    "sg:tags":[
        "guide"
    ],
    "wof:name":"Key Magazine Nashville",
    "wof:placetype":"venue"
},
  "geometry": {"coordinates":[-86.83609,36.105535],"type":"Point"}
}