{
  "type": "Feature",
  "properties": {
    "iso:country":"US",
    "sg:address":"307 Church St",
    "sg:city":"Loretto",
    "sg:classifiers":[
        {
            "category":"Education",
            "subcategory":"School",
            "type":"Public Place"
        }
    ],
    "sg:phone":"+1 931 853 4388",
    "sg:postcode":"38469",
    "sg:province":"TN",
    "wof:name":"Sacred Heart School",
    "wof:placetype":"venue"
},
  "geometry": {"coordinates":[-87.443399,35.076715],"type":"Point"}
}