{
  "type": "Feature",
  "properties": {
    "iso:country":"US",
    "sg:address":"4730 Tchulahoma Rd",
    "sg:city":"Memphis",
    "sg:classifiers":[
        {
            "category":"Professional",
            "type":"Services"
        }
    ],
    "sg:phone":"+1 901 375 9432",
    "sg:postcode":"38118",
    "sg:province":"TN",
    "wof:name":"Alcor Inc",
    "wof:placetype":"venue"
},
  "geometry": {"coordinates":[-89.95448,35.019828],"type":"Point"}
}