{
  "type": "Feature",
  "properties": {
    "addr:full":"701 Broadway Nashville TN 37203",
    "addr:housenumber":"701",
    "addr:postcode":"37203",
    "addr:street":"Broadway",
    "iso:country":"US",
    "sg:address":"701 Broadway",
    "sg:city":"Nashville",
    "sg:classifiers":[
        {
            "category":"Utilities",
            "subcategory":"Telephone",
            "type":"Services"
        }
    ],
    "sg:phone":"+1 615 248 3421",
    "sg:postcode":"37203",
    "sg:province":"TN",
    "sg:tags":[
        "distance",
        "long",
        "communications"
    ],
    "wof:name":"MCI",
    "wof:placetype":"venue"
},
  "geometry": {"coordinates":[-86.78210799999999,36.158896],"type":"Point"}
}