{
  "type": "Feature",
  "properties": {
    "iso:country":"US",
    "sg:address":"202 Jacob Dr",
    "sg:city":"Halls",
    "sg:classifiers":[
        {
            "category":"Freight",
            "type":"Transportation"
        }
    ],
    "sg:phone":"+1 901 482 0506",
    "sg:postcode":"38040",
    "sg:province":"TN",
    "sg:tags":[
        "operator",
        "local",
        "trucking"
    ],
    "wof:name":"Turtle Trucking",
    "wof:placetype":"venue"
},
  "geometry": {"coordinates":[-89.39183,35.910781],"type":"Point"}
}