{
  "type": "Feature",
  "properties": {
    "iso:country":"US",
    "sg:address":"1022 Elm St",
    "sg:city":"Knoxville",
    "sg:classifiers":[
        {
            "category":"Professional",
            "subcategory":"Business Services",
            "type":"Services"
        }
    ],
    "sg:phone":"+1 865 546 3206",
    "sg:postcode":"37921",
    "sg:province":"TN",
    "sg:tags":[
        "real estate"
    ],
    "wof:name":"Archer George W",
    "wof:placetype":"venue"
},
  "geometry": {"coordinates":[-83.93490300000001,35.974739],"type":"Point"}
}