{
  "type": "Feature",
  "properties": {
    "iso:country":"US",
    "sg:address":"904 Fair St",
    "sg:city":"Dyersburg",
    "sg:classifiers":[
        {
            "category":"Professional",
            "type":"Services"
        }
    ],
    "sg:phone":"+1 731 285 5741",
    "sg:postcode":"38024",
    "sg:province":"TN",
    "sg:tags":[
        "establishment"
    ],
    "wof:name":"Linda S Enterprise",
    "wof:placetype":"venue"
},
  "geometry": {"coordinates":[-89.376463,36.026004],"type":"Point"}
}