{
  "type": "Feature",
  "properties": {
    "addr:full":"118 Fort Granger Dr Franklin TN 37064",
    "addr:housenumber":"118",
    "addr:postcode":"37064",
    "addr:street":"Fort Granger Dr",
    "iso:country":"US",
    "sg:address":"118 Fort Granger Dr",
    "sg:city":"Franklin",
    "sg:classifiers":[
        {
            "category":"Home & Garden",
            "subcategory":"Home Furnishings",
            "type":"Retail Goods"
        }
    ],
    "sg:phone":"+1 615 595 6800",
    "sg:postcode":"37064",
    "sg:province":"TN",
    "wof:name":"Old South Lamps",
    "wof:placetype":"venue"
},
  "geometry": {"coordinates":[-86.85671600000001,35.926366],"type":"Point"}
}