{
  "type": "Feature",
  "properties": {
    "iso:country":"US",
    "sg:address":"301 N Jackson St",
    "sg:city":"Tullahoma",
    "sg:classifiers":[
        {
            "category":"Real Estate",
            "subcategory":"Architect",
            "type":"Services"
        }
    ],
    "sg:phone":"+1 931 393 3958",
    "sg:postcode":"37388",
    "sg:province":"TN",
    "sg:tags":[
        "course",
        "golf"
    ],
    "wof:name":"Golf Development Svc",
    "wof:placetype":"venue"
},
  "geometry": {"coordinates":[-86.21413099999999,35.364739],"type":"Point"}
}