{
  "type": "Feature",
  "properties": {
    "iso:country":"US",
    "sg:address":"601 S Concord St",
    "sg:city":"Knoxville",
    "sg:classifiers":[
        {
            "category":"Professional",
            "subcategory":"Detective & Security Services",
            "type":"Services"
        }
    ],
    "sg:phone":"+1 865 329 0474",
    "sg:postcode":"37919",
    "sg:province":"TN",
    "sg:tags":[
        "car"
    ],
    "wof:name":"S E I Inc",
    "wof:placetype":"venue"
},
  "geometry": {"coordinates":[-83.947204,35.952546],"type":"Point"}
}