{
  "type": "Feature",
  "properties": {
    "addr:full":"2029 Southern Oaks Dr Maryville TN 37801",
    "addr:housenumber":"2029",
    "addr:postcode":"37801",
    "addr:street":"Southern Oaks Dr",
    "iso:country":"US",
    "sg:address":"2029 Southern Oaks Dr",
    "sg:city":"Maryville",
    "sg:classifiers":[
        {
            "category":"Building & Trades",
            "subcategory":"Cleaning & Sanitation",
            "type":"Services"
        }
    ],
    "sg:phone":"+1 865 681 6374",
    "sg:postcode":"37801",
    "sg:province":"TN",
    "sg:tags":[
        "maintenance"
    ],
    "wof:name":"Sure Shine Cleaning Service",
    "wof:placetype":"venue"
},
  "geometry": {"coordinates":[-84.029915,35.750006],"type":"Point"}
}