{
  "type": "Feature",
  "properties": {
    "iso:country":"US",
    "sg:address":"2034 US Hwy 45W Byp",
    "sg:city":"Trenton",
    "sg:classifiers":[
        {
            "category":"Shopping",
            "subcategory":"Jewelry",
            "type":"Retail Goods"
        }
    ],
    "sg:phone":"+1 731 855 4228",
    "sg:postcode":"38382",
    "sg:province":"TN",
    "sg:tags":[
        "jeweler"
    ],
    "wof:name":"Hickerson Jewelers",
    "wof:placetype":"venue"
},
  "geometry": {"coordinates":[-88.931028,35.966577],"type":"Point"}
}