{
  "type": "Feature",
  "properties": {
    "iso:country":"US",
    "sg:address":"1020 Dollywood Ln",
    "sg:city":"Pigeon Forge",
    "sg:classifiers":[
        {
            "category":"Organizations",
            "subcategory":"Professional Association",
            "type":"Services"
        }
    ],
    "sg:phone":"+1 865 908 4040",
    "sg:postcode":"37876",
    "sg:province":"TN",
    "sg:tags":[
        "business",
        "trade"
    ],
    "wof:name":"Southern Gospel Music Assn",
    "wof:placetype":"venue"
},
  "geometry": {"coordinates":[-83.53529399999999,35.794424],"type":"Point"}
}