{
  "type": "Feature",
  "properties": {
    "iso:country":"US",
    "sg:address":"4456 US Hwy 11W",
    "sg:city":"Blountville",
    "sg:classifiers":[
        {
            "category":"Retail",
            "subcategory":"Animal Services",
            "type":"Services"
        }
    ],
    "sg:phone":"+1 423 323 1511",
    "sg:postcode":"37617",
    "sg:province":"TN",
    "wof:name":"Holly Brook Farms",
    "wof:placetype":"venue"
},
  "geometry": {"coordinates":[-82.39058900000001,36.571689],"type":"Point"}
}