{
  "type": "Feature",
  "properties": {
    "addr:full":"1316 Knightsbridge Dr Knoxville TN 37922",
    "addr:housenumber":"1316",
    "addr:postcode":"37922",
    "addr:street":"Knightsbridge Dr",
    "iso:country":"US",
    "sg:address":"1316 Knightsbridge Dr",
    "sg:city":"Knoxville",
    "sg:classifiers":[
        {
            "category":"Building & Trades",
            "subcategory":"Construction",
            "type":"Services"
        }
    ],
    "sg:phone":"+1 865 691 6213",
    "sg:postcode":"37922",
    "sg:province":"TN",
    "sg:tags":[
        "tile",
        "contractor"
    ],
    "wof:name":"Palmer Tile",
    "wof:placetype":"venue"
},
  "geometry": {"coordinates":[-84.041659,35.891827],"type":"Point"}
}