{
  "type": "Feature",
  "properties": {
    "iso:country":"US",
    "sg:address":"1301 State Hwy 12 S",
    "sg:city":"Ashland City",
    "sg:classifiers":[
        {
            "category":"Wholesale",
            "subcategory":"Meat",
            "type":"Manufacturing & Wholesale Goods"
        }
    ],
    "sg:phone":"+1 615 792 5616",
    "sg:postcode":"37015",
    "sg:province":"TN",
    "sg:tags":[
        "packing",
        "repair",
        "plant",
        "datum",
        "s"
    ],
    "wof:name":"Azac Jrs Taxidermy Studio",
    "wof:placetype":"venue"
},
  "geometry": {"coordinates":[-87.04017899999999,36.256213],"type":"Point"}
}