{
  "type": "Feature",
  "properties": {
    "iso:country":"US",
    "sg:address":"4682 Spottswood Ave",
    "sg:city":"Memphis",
    "sg:classifiers":[
        {
            "category":"Personal",
            "subcategory":"Beauty Salon",
            "type":"Services"
        }
    ],
    "sg:phone":"+1 901 761 4445",
    "sg:postcode":"38117",
    "sg:province":"TN",
    "sg:tags":[
        "school",
        "cosmetology"
    ],
    "wof:name":"Plaza Beauty School Inc",
    "wof:placetype":"venue"
},
  "geometry": {"coordinates":[-89.906465,35.111319],"type":"Point"}
}