{
  "type": "Feature",
  "properties": {
    "iso:country":"US",
    "sg:address":"4621 Ellistown Rd",
    "sg:city":"Knoxville",
    "sg:classifiers":[
        {
            "category":"Building & Trades",
            "subcategory":"Plumbing",
            "type":"Services"
        }
    ],
    "sg:phone":"+1 865 689 3999",
    "sg:postcode":"37924",
    "sg:province":"TN",
    "sg:tags":[
        "plumbing",
        "contractor"
    ],
    "wof:name":"Fountain City Plumbing",
    "wof:placetype":"venue"
},
  "geometry": {"coordinates":[-83.823407,36.08216],"type":"Point"}
}