{
  "type": "Feature",
  "properties": {
    "iso:country":"US",
    "sg:address":"4049 Nolensville Pike",
    "sg:city":"Nashville",
    "sg:classifiers":[
        {
            "category":"Banks & Credit Unions",
            "subcategory":"Bank",
            "type":"Services"
        }
    ],
    "sg:phone":"+1 615 833 1242",
    "sg:postcode":"37211",
    "sg:province":"TN",
    "sg:tags":[
        "depository",
        "banking"
    ],
    "wof:name":"Casa De Cambio Suroeste",
    "wof:placetype":"venue"
},
  "geometry": {"coordinates":[-86.726759,36.080799],"type":"Point"}
}