{
  "type": "Feature",
  "properties": {
    "iso:country":"US",
    "sg:address":"1145 N Concord Rd",
    "sg:city":"Chattanooga",
    "sg:classifiers":[
        {
            "category":"Social Services",
            "type":"Services"
        }
    ],
    "sg:phone":"+1 423 894 8227",
    "sg:postcode":"37421",
    "sg:province":"TN",
    "wof:name":"Mountain Crest Psychlgical Ctr",
    "wof:placetype":"venue"
},
  "geometry": {"coordinates":[-85.17628999999999,35.009538],"type":"Point"}
}