{
  "type": "Feature",
  "properties": {
    "iso:country":"US",
    "sg:address":"8515 Middle Valley Rd",
    "sg:city":"Hixson",
    "sg:classifiers":[
        {
            "category":"Government",
            "subcategory":"Office",
            "type":"Public Place"
        }
    ],
    "sg:phone":"+1 423 842 6252",
    "sg:postcode":"37343",
    "sg:province":"TN",
    "sg:tags":[
        "medical"
    ],
    "wof:name":"Paramedic Station",
    "wof:placetype":"venue"
},
  "geometry": {"coordinates":[-85.184021,35.207878],"type":"Point"}
}