{
  "type": "Feature",
  "properties": {
    "iso:country":"US",
    "sg:address":"1029 Lynn Garden Dr",
    "sg:city":"Kingsport",
    "sg:classifiers":[
        {
            "category":"Personal",
            "type":"Services"
        }
    ],
    "sg:phone":"+1 423 378 4844",
    "sg:postcode":"37665",
    "sg:province":"TN",
    "wof:name":"Mr Tax Of America",
    "wof:placetype":"venue"
},
  "geometry": {"coordinates":[-82.56633600000001,36.572798],"type":"Point"}
}