{
  "type": "Feature",
  "properties": {
    "iso:country":"US",
    "sg:address":"2617 Gallatin Pike",
    "sg:city":"Nashville",
    "sg:classifiers":[
        {
            "category":"Restaurant",
            "type":"Food & Drink"
        }
    ],
    "sg:phone":"+1 615 227 8388",
    "sg:postcode":"37216",
    "sg:province":"TN",
    "wof:name":"East Side Fish",
    "wof:placetype":"venue"
},
  "geometry": {"coordinates":[-86.74096299999999,36.199062],"type":"Point"}
}