{
  "type": "Feature",
  "properties": {
    "iso:country":"US",
    "sg:address":"495 S Plantation Dr",
    "sg:city":"Cookeville",
    "sg:classifiers":[
        {
            "category":"Personal",
            "type":"Services"
        }
    ],
    "sg:phone":"+1 931 537 2840",
    "sg:postcode":"38506",
    "sg:province":"TN",
    "wof:name":"Party Planner",
    "wof:placetype":"venue"
},
  "geometry": {"coordinates":[-85.433616,36.179096],"type":"Point"}
}