{
  "type": "Feature",
  "properties": {
    "iso:country":"US",
    "sg:address":"109 Spence Ln",
    "sg:city":"Nashville",
    "sg:classifiers":[
        {
            "category":"Manufacturing",
            "subcategory":"Buildings",
            "type":"Manufacturing & Wholesale Goods"
        },
        {
            "category":"Building & Trades",
            "subcategory":"Construction",
            "type":"Services"
        }
    ],
    "sg:phone":"+1 615 889 9585",
    "sg:postcode":"37210",
    "sg:province":"TN",
    "sg:tags":[
        "builder",
        "system",
        "home",
        "contractor",
        "air conditioning"
    ],
    "wof:name":"Builders Heat and Air",
    "wof:placetype":"venue"
},
  "geometry": {"coordinates":[-86.72112799999999,36.161429],"type":"Point"}
}