{
  "type": "Feature",
  "properties": {
    "iso:country":"US",
    "sg:address":"216 19th Ave N",
    "sg:city":"Nashville",
    "sg:classifiers":[
        {
            "category":"Shopping",
            "subcategory":"Department Store",
            "type":"Retail Goods"
        }
    ],
    "sg:phone":"+1 615 269 4889",
    "sg:postcode":"37203",
    "sg:province":"TN",
    "sg:tags":[
        "shop"
    ],
    "wof:name":"Do All Traps",
    "wof:placetype":"venue"
},
  "geometry": {"coordinates":[-86.79915,36.1547],"type":"Point"}
}