{
  "type": "Feature",
  "properties": {
    "iso:country":"US",
    "sg:address":"1109 S Main St",
    "sg:city":"Springfield",
    "sg:classifiers":[
        {
            "category":"Organizations",
            "subcategory":"Professional Association",
            "type":"Services"
        }
    ],
    "sg:phone":"+1 615 384 4543",
    "sg:postcode":"37172",
    "sg:province":"TN",
    "wof:name":"Eastern Dark Fired Tobacco",
    "wof:placetype":"venue"
},
  "geometry": {"coordinates":[-86.886081,36.503245],"type":"Point"}
}