{
  "type": "Feature",
  "properties": {
    "addr:full":"757 Walker Cove Rd Sparta TN 38583",
    "addr:housenumber":"757",
    "addr:postcode":"38583",
    "addr:street":"Walker Cove Rd",
    "iso:country":"US",
    "sg:address":"757 Walker Cove Rd",
    "sg:city":"Sparta",
    "sg:classifiers":[
        {
            "category":"Personal",
            "subcategory":"Beauty Salon",
            "type":"Services"
        }
    ],
    "sg:phone":"+1 931 738 2500",
    "sg:postcode":"38583",
    "sg:province":"TN",
    "wof:name":"Scissor Shack",
    "wof:placetype":"venue"
},
  "geometry": {"coordinates":[-85.48323499999999,35.958307],"type":"Point"}
}