{
  "type": "Feature",
  "properties": {
    "addr:full":"9830 Clovercroft Rd Nolensville TN 37135",
    "addr:housenumber":"9830",
    "addr:postcode":"37135",
    "addr:street":"Clovercroft Rd",
    "iso:country":"US",
    "sg:address":"9830 Clovercroft Rd",
    "sg:city":"Nolensville",
    "sg:classifiers":[
        {
            "category":"Building & Trades",
            "subcategory":"Construction",
            "type":"Services"
        }
    ],
    "sg:phone":"+1 615 776 7895",
    "sg:postcode":"37135",
    "sg:province":"TN",
    "sg:tags":[
        "home",
        "builder"
    ],
    "wof:name":"West View Homes LLC",
    "wof:placetype":"venue"
},
  "geometry": {"coordinates":[-86.67470299999999,35.940921],"type":"Point"}
}