{
  "type": "Feature",
  "properties": {
    "iso:country":"US",
    "sg:address":"318 Nancy Lynn Ln",
    "sg:city":"Knoxville",
    "sg:classifiers":[
        {
            "category":"Professional",
            "subcategory":"Business Services",
            "type":"Services"
        }
    ],
    "sg:phone":"+1 865 602 2160",
    "sg:postcode":"37919",
    "sg:province":"TN",
    "sg:tags":[
        "paging",
        "signaling"
    ],
    "wof:name":"Alpha Paging",
    "wof:placetype":"venue"
},
  "geometry": {"coordinates":[-84.00944800000001,35.926408],"type":"Point"}
}