{
  "type": "Feature",
  "properties": {
    "iso:country":"US",
    "sg:address":"117 Porter St",
    "sg:city":"Soddy Daisy",
    "sg:classifiers":[
        {
            "category":"Building & Trades",
            "subcategory":"Construction",
            "type":"Services"
        }
    ],
    "sg:phone":"+1 423 332 5175",
    "sg:postcode":"37379",
    "sg:province":"TN",
    "sg:tags":[
        "painter"
    ],
    "wof:name":"Mr Painter",
    "wof:placetype":"venue"
},
  "geometry": {"coordinates":[-85.198545,35.240916],"type":"Point"}
}