{
  "type": "Feature",
  "properties": {
    "iso:country":"US",
    "sg:address":"2740 Old Elm Hill Pike",
    "sg:city":"Nashville",
    "sg:classifiers":[
        {
            "category":"Manufacturing",
            "subcategory":"Printing",
            "type":"Manufacturing & Wholesale Goods"
        }
    ],
    "sg:phone":"+1 615 889 1860",
    "sg:postcode":"37214",
    "sg:province":"TN",
    "sg:tags":[
        "newspaper"
    ],
    "wof:name":"News Herald",
    "wof:placetype":"venue"
},
  "geometry": {"coordinates":[-86.668966,36.151135],"type":"Point"}
}