{
  "type": "Feature",
  "properties": {
    "iso:country":"US",
    "sg:address":"7221 Winchester Rd",
    "sg:city":"Memphis",
    "sg:classifiers":[
        {
            "category":"Wholesale",
            "subcategory":"Jewelry",
            "type":"Manufacturing & Wholesale Goods"
        }
    ],
    "sg:phone":"+1 901 754 7501",
    "sg:postcode":"38125",
    "sg:province":"TN",
    "sg:tags":[
        "distributes",
        "mfg"
    ],
    "wof:name":"Gold & Diamond International",
    "wof:placetype":"venue"
},
  "geometry": {"coordinates":[-89.819481,35.049423],"type":"Point"}
}