{
  "type": "Feature",
  "properties": {
    "iso:country":"US",
    "sg:address":"1326 Hardwood Trl",
    "sg:city":"Cordova",
    "sg:classifiers":[
        {
            "category":"Building & Trades",
            "subcategory":"Construction",
            "type":"Services"
        }
    ],
    "sg:phone":"+1 901 737 2929",
    "sg:postcode":"38016",
    "sg:province":"TN",
    "sg:tags":[
        "general",
        "contractor"
    ],
    "wof:name":"T R Mills Contractors Inc",
    "wof:placetype":"venue"
},
  "geometry": {"coordinates":[-89.790616,35.161194],"type":"Point"}
}