{
  "type": "Feature",
  "properties": {
    "iso:country":"US",
    "sg:address":"2615 Chapman Hwy",
    "sg:city":"Knoxville",
    "sg:classifiers":[
        {
            "category":"Shopping",
            "subcategory":"Music",
            "type":"Retail Goods"
        }
    ],
    "sg:phone":"+1 865 573 5710",
    "sg:postcode":"37920",
    "sg:province":"TN",
    "sg:tags":[
        "compact",
        "record",
        "disc",
        "tape"
    ],
    "wof:name":"Disc Exchange",
    "wof:placetype":"venue"
},
  "geometry": {"coordinates":[-83.912806,35.9473],"type":"Point"}
}