{
  "type": "Feature",
  "properties": {
    "iso:country":"US",
    "sg:address":"311 S Washington St",
    "sg:city":"Tullahoma",
    "sg:classifiers":[
        {
            "category":"Building & Trades",
            "subcategory":"Landscaping Services",
            "type":"Services"
        }
    ],
    "sg:phone":"+1 931 455 4700",
    "sg:postcode":"37388",
    "sg:province":"TN",
    "sg:tags":[
        "tree"
    ],
    "wof:name":"Brown's Tree & Stump Svc",
    "wof:placetype":"venue"
},
  "geometry": {"coordinates":[-86.205786,35.361439],"type":"Point"}
}