{
  "type": "Feature",
  "properties": {
    "addr:full":"11 Cedar Dr Fayetteville TN 37334",
    "addr:housenumber":"11",
    "addr:postcode":"37334",
    "addr:street":"Cedar Dr",
    "iso:country":"US",
    "sg:address":"11 Cedar Dr",
    "sg:city":"Fayetteville",
    "sg:classifiers":[
        {
            "category":"Organizations",
            "subcategory":"Religious Organization",
            "type":"Services"
        }
    ],
    "sg:phone":"+1 931 438 0428",
    "sg:postcode":"37334",
    "sg:province":"TN",
    "sg:tags":[
        "church"
    ],
    "wof:name":"St John AME Church",
    "wof:placetype":"venue"
},
  "geometry": {"coordinates":[-86.56094400000001,35.074848],"type":"Point"}
}