{
  "type": "Feature",
  "properties": {
    "addr:full":"261 Bowman Ln Bradyville TN 37026",
    "addr:housenumber":"261",
    "addr:postcode":"37026",
    "addr:street":"Bowman Ln",
    "iso:country":"US",
    "sg:address":"261 Bowman Ln",
    "sg:city":"Bradyville",
    "sg:classifiers":[
        {
            "category":"Building & Trades",
            "subcategory":"Construction",
            "type":"Services"
        }
    ],
    "sg:phone":"+1 615 765 5758",
    "sg:postcode":"37026",
    "sg:province":"TN",
    "sg:tags":[
        "fence",
        "contractor"
    ],
    "sg:website":"www.dcspecialtiesllc.com",
    "wof:name":"Dc Specialties LLC",
    "wof:placetype":"venue"
},
  "geometry": {"coordinates":[-86.077257,35.70744],"type":"Point"}
}