{
  "type": "Feature",
  "properties": {
    "addr:full":"12618 State Hwy 88 Halls TN 38040",
    "addr:housenumber":"12618",
    "addr:postcode":"38040",
    "addr:street":"State Hwy 88 Halls",
    "iso:country":"US",
    "sg:address":"12618 State Hwy 88",
    "sg:city":"Halls",
    "sg:classifiers":[
        {
            "category":"Retail",
            "subcategory":"Auto Repair",
            "type":"Services"
        }
    ],
    "sg:phone":"+1 731 656 4137",
    "sg:postcode":"38040",
    "sg:province":"TN",
    "sg:tags":[
        "automobile",
        "used",
        "general"
    ],
    "wof:name":"Kee Glynn Motor Co",
    "wof:placetype":"venue"
},
  "geometry": {"coordinates":[-89.33719000000001,35.816782],"type":"Point"}
}