{
  "type": "Feature",
  "properties": {
    "iso:country":"US",
    "sg:address":"228 Boardman Ave",
    "sg:city":"Maryville",
    "sg:classifiers":[
        {
            "category":"Building & Trades",
            "subcategory":"Landscaping Services",
            "type":"Services"
        }
    ],
    "sg:phone":"+1 865 982 8980",
    "sg:postcode":"37803",
    "sg:province":"TN",
    "sg:tags":[
        "lawn",
        "maintenance",
        "grounds"
    ],
    "wof:name":"A-1 Ron's Lawn & Landscaping",
    "wof:placetype":"venue"
},
  "geometry": {"coordinates":[-83.964927,35.7451],"type":"Point"}
}