{
  "type": "Feature",
  "properties": {
    "iso:country":"US",
    "sg:address":"1055 Houston Levee Rd",
    "sg:city":"Cordova",
    "sg:classifiers":[
        {
            "category":"Professional",
            "type":"Services"
        }
    ],
    "sg:phone":"+1 901 680 9416",
    "sg:postcode":"38018",
    "sg:province":"TN",
    "sg:tags":[
        "establishment"
    ],
    "wof:name":"Physicians Advisory Co",
    "wof:placetype":"venue"
},
  "geometry": {"coordinates":[-89.72754999999999,35.157041],"type":"Point"}
}