{
  "type": "Feature",
  "properties": {
    "addr:full":"5250 Tulane Rd Memphis TN 38109",
    "addr:housenumber":"5250",
    "addr:postcode":"38109",
    "addr:street":"Tulane Rd",
    "iso:country":"US",
    "sg:address":"5250 Tulane Rd",
    "sg:city":"Memphis",
    "sg:classifiers":[
        {
            "category":"Education",
            "subcategory":"School",
            "type":"Public Place"
        },
        {
            "category":"Government",
            "subcategory":"Office",
            "type":"Public Place"
        }
    ],
    "sg:phone":"+1 901 416 3156",
    "sg:postcode":"38109",
    "sg:province":"TN",
    "sg:website":"http://www.whitehaven95.com",
    "wof:name":"J P Freeman School",
    "wof:placetype":"venue"
},
  "geometry": {"coordinates":[-90.04305600000001,35.00463],"type":"Point"}
}