{
  "type": "Feature",
  "properties": {
    "iso:country":"US",
    "sg:address":"358 Volena Pl SW",
    "sg:city":"Knoxville",
    "sg:classifiers":[
        {
            "category":"Building & Trades",
            "subcategory":"Construction",
            "type":"Services"
        }
    ],
    "sg:phone":"+1 865 573 9390",
    "sg:postcode":"37920",
    "sg:province":"TN",
    "sg:tags":[
        "painter"
    ],
    "wof:name":"SDV Paint Contracting",
    "wof:placetype":"venue"
},
  "geometry": {"coordinates":[-83.914531,35.939691],"type":"Point"}
}