{
  "type": "Feature",
  "properties": {
    "addr:full":"102 Bluegrass Cove Hendersonville TN 37075",
    "addr:housenumber":"102",
    "addr:postcode":"37075",
    "addr:street":"Bluegrass Cove",
    "iso:country":"US",
    "sg:address":"102 Bluegrass Cove",
    "sg:city":"Hendersonville",
    "sg:classifiers":[
        {
            "category":"Social Services",
            "type":"Services"
        }
    ],
    "sg:phone":"+1 615 826 9622",
    "sg:postcode":"37075",
    "sg:province":"TN",
    "sg:tags":[
        "organization",
        "welfare"
    ],
    "sg:website":"www.ymcamidtn.org",
    "wof:name":"YMCA",
    "wof:placetype":"venue"
},
  "geometry": {"coordinates":[-86.565287,36.309053],"type":"Point"}
}