{
  "type": "Feature",
  "properties": {
    "iso:country":"US",
    "sg:address":"6089 Apple Tree Dr",
    "sg:city":"Memphis",
    "sg:classifiers":[
        {
            "category":"Building & Trades",
            "subcategory":"Construction",
            "type":"Services"
        }
    ],
    "sg:phone":"+1 901 566 5150",
    "sg:postcode":"38115",
    "sg:province":"TN",
    "sg:tags":[
        "contractor"
    ],
    "wof:name":"Vantage Builders Inc",
    "wof:placetype":"venue"
},
  "geometry": {"coordinates":[-89.86116800000001,35.068916],"type":"Point"}
}