{
  "type": "Feature",
  "properties": {
    "iso:country":"US",
    "sg:address":"441 Claircrest Dr",
    "sg:city":"Antioch",
    "sg:classifiers":[
        {
            "category":"Insurance",
            "subcategory":"Insurance Agent",
            "type":"Services"
        }
    ],
    "sg:phone":"+1 615 331 2366",
    "sg:postcode":"37013",
    "sg:province":"TN",
    "wof:name":"R 2 Financial",
    "wof:placetype":"venue"
},
  "geometry": {"coordinates":[-86.702331,36.058267],"type":"Point"}
}