{
  "type": "Feature",
  "properties": {
    "iso:country":"US",
    "sg:address":"621 Rocky Ridge Cir",
    "sg:city":"La Vergne",
    "sg:classifiers":[
        {
            "category":"Retail",
            "subcategory":"Auto Repair",
            "type":"Services"
        }
    ],
    "sg:phone":"+1 615 793 5960",
    "sg:postcode":"37086",
    "sg:province":"TN",
    "sg:tags":[
        "automotive",
        "complete"
    ],
    "wof:name":"Carters Wheel Alignment",
    "wof:placetype":"venue"
},
  "geometry": {"coordinates":[-86.55041,36.051853],"type":"Point"}
}