{
  "type": "Feature",
  "properties": {
    "iso:country":"US",
    "sg:address":"3626 Ringgold Rd",
    "sg:city":"Chattanooga",
    "sg:classifiers":[
        {
            "category":"Professional",
            "subcategory":"Business Services",
            "type":"Services"
        },
        {
            "category":"Manufacturing",
            "subcategory":"Apparel",
            "type":"Manufacturing & Wholesale Goods"
        }
    ],
    "sg:phone":"+1 423 629 7780",
    "sg:postcode":"37412",
    "sg:province":"TN",
    "sg:tags":[
        "digitizing",
        "embroidery"
    ],
    "sg:website":"www.signaturedesigns.com",
    "wof:name":"Signature Designs Inc",
    "wof:placetype":"venue"
},
  "geometry": {"coordinates":[-85.258849,35.001911],"type":"Point"}
}