{
  "type": "Feature",
  "properties": {
    "addr:full":"540 Robertson Rd Chuckey TN 37641",
    "addr:housenumber":"540",
    "addr:postcode":"37641",
    "addr:street":"Robertson Rd",
    "iso:country":"US",
    "sg:address":"540 Robertson Rd",
    "sg:city":"Chuckey",
    "sg:classifiers":[
        {
            "category":"Retail",
            "subcategory":"Repair Shop",
            "type":"Services"
        }
    ],
    "sg:phone":"+1 423 638 6265",
    "sg:postcode":"37641",
    "sg:province":"TN",
    "wof:name":"Tennessee Cleaning",
    "wof:placetype":"venue"
},
  "geometry": {"coordinates":[-82.72401499999999,36.272861],"type":"Point"}
}