{
  "type": "Feature",
  "properties": {
    "iso:country":"US",
    "sg:address":"135 Co Rd 105",
    "sg:city":"Athens",
    "sg:classifiers":[
        {
            "category":"Retail",
            "subcategory":"Auto Repair",
            "type":"Services"
        }
    ],
    "sg:phone":"+1 423 745 5941",
    "sg:postcode":"37303",
    "sg:province":"TN",
    "sg:tags":[
        "body",
        "automobile",
        "painting"
    ],
    "wof:name":"Womac Body Shop",
    "wof:placetype":"venue"
},
  "geometry": {"coordinates":[-84.704663,35.479563],"type":"Point"}
}