{
  "type": "Feature",
  "properties": {
    "addr:full":"1241 Highway Dr Clarksville TN 37040",
    "addr:housenumber":"1241",
    "addr:postcode":"37040",
    "addr:street":"Highway Dr",
    "iso:country":"US",
    "sg:address":"1241 Highway Dr",
    "sg:city":"Clarksville",
    "sg:classifiers":[
        {
            "category":"Social Services",
            "subcategory":"Job Training",
            "type":"Services"
        }
    ],
    "sg:phone":"+1 931 648 5560",
    "sg:postcode":"37040",
    "sg:province":"TN",
    "sg:tags":[
        "rehab",
        "government"
    ],
    "wof:name":"Vocational Rehabilitation Div",
    "wof:placetype":"venue"
},
  "geometry": {"coordinates":[-87.336662,36.51539],"type":"Point"}
}