{
  "type": "Feature",
  "properties": {
    "addr:full":"1980 Carson Springs Rd Newport TN 37821",
    "addr:housenumber":"1980",
    "addr:postcode":"37821",
    "addr:street":"Carson Springs Rd",
    "iso:country":"US",
    "sg:address":"1980 Carson Springs Rd",
    "sg:city":"Newport",
    "sg:classifiers":[
        {
            "category":"Professional",
            "type":"Services"
        }
    ],
    "sg:phone":"+1 865 509 0000",
    "sg:postcode":"37821",
    "sg:province":"TN",
    "sg:tags":[
        "establishment"
    ],
    "wof:name":"Planet Systems Inc",
    "wof:placetype":"venue"
},
  "geometry": {"coordinates":[-83.296395,35.904496],"type":"Point"}
}