{
  "type": "Feature",
  "properties": {
    "iso:country":"US",
    "sg:address":"1204 Elmwood Ave",
    "sg:city":"Nashville",
    "sg:classifiers":[
        {
            "category":"Professional",
            "subcategory":"Research",
            "type":"Services"
        }
    ],
    "sg:phone":"+1 615 292 0616",
    "sg:postcode":"37212",
    "sg:province":"TN",
    "sg:tags":[
        "marketing"
    ],
    "wof:name":"John Hart Media Inc",
    "wof:placetype":"venue"
},
  "geometry": {"coordinates":[-86.790098,36.126579],"type":"Point"}
}