{
  "type": "Feature",
  "properties": {
    "iso:country":"US",
    "sg:address":"450 Lance Dr",
    "sg:city":"Baxter",
    "sg:classifiers":[
        {
            "category":"Wholesale",
            "subcategory":"Auto Parts",
            "type":"Manufacturing & Wholesale Goods"
        }
    ],
    "sg:phone":"+1 931 858 3525",
    "sg:postcode":"38544",
    "sg:province":"TN",
    "sg:tags":[
        "used"
    ],
    "wof:name":"A 1 Auto Sales & Parts",
    "wof:placetype":"venue"
},
  "geometry": {"coordinates":[-85.61559699999999,36.164096],"type":"Point"}
}