{
  "type": "Feature",
  "properties": {
    "addr:full":"1130 5th St Bristol TN 37620",
    "addr:housenumber":"1130",
    "addr:postcode":"37620",
    "addr:street":"5Th St",
    "iso:country":"US",
    "sg:address":"1130 5th St",
    "sg:city":"Bristol",
    "sg:classifiers":[
        {
            "category":"Manufacturing",
            "subcategory":"Printing",
            "type":"Manufacturing & Wholesale Goods"
        }
    ],
    "sg:phone":"+1 423 764 0041",
    "sg:postcode":"37620",
    "sg:province":"TN",
    "sg:tags":[
        "label"
    ],
    "wof:name":"Empire Label LLC",
    "wof:placetype":"venue"
},
  "geometry": {"coordinates":[-82.173766,36.582144],"type":"Point"}
}