{
  "type": "Feature",
  "properties": {
    "iso:country":"US",
    "sg:address":"294 Jen Rue Ln",
    "sg:city":"Ooltewah",
    "sg:classifiers":[
        {
            "category":"Professional",
            "subcategory":"Advertising",
            "type":"Services"
        }
    ],
    "sg:phone":"+1 423 396 4884",
    "sg:postcode":"37363",
    "sg:province":"TN",
    "sg:tags":[
        "agency"
    ],
    "wof:name":"Advanced Advertising",
    "wof:placetype":"venue"
},
  "geometry": {"coordinates":[-85.028713,35.06316],"type":"Point"}
}