{
  "type": "Feature",
  "properties": {
    "addr:full":"1204 Andrew Donelson Hermitage TN 37076",
    "addr:housenumber":"1204",
    "addr:postcode":"37076",
    "addr:street":"Andrew Donelson",
    "iso:country":"US",
    "sg:address":"1204 Andrew Donelson",
    "sg:city":"Hermitage",
    "sg:classifiers":[
        {
            "category":"Professional",
            "subcategory":"Business Services",
            "type":"Services"
        }
    ],
    "sg:phone":"+1 615 885 1772",
    "sg:postcode":"37076",
    "sg:province":"TN",
    "wof:name":"Sweet Sayings",
    "wof:placetype":"venue"
},
  "geometry": {"coordinates":[-86.606492,36.19957],"type":"Point"}
}