{
  "type": "Feature",
  "properties": {
    "iso:country":"US",
    "sg:address":"5074 Park Ave",
    "sg:city":"Memphis",
    "sg:classifiers":[
        {
            "category":"Retail",
            "subcategory":"Animal Services",
            "type":"Services"
        }
    ],
    "sg:phone":"+1 901 767 7490",
    "sg:postcode":"38117",
    "sg:province":"TN",
    "sg:tags":[
        "pet",
        "grooming",
        "washing"
    ],
    "wof:name":"Chris's Poodle Palace",
    "wof:placetype":"venue"
},
  "geometry": {"coordinates":[-89.894251,35.106637],"type":"Point"}
}