{
  "type": "Feature",
  "properties": {
    "iso:country":"US",
    "sg:address":"975 Culbertson Rd",
    "sg:city":"Greeneville",
    "sg:classifiers":[
        {
            "category":"Building & Trades",
            "subcategory":"Construction",
            "type":"Services"
        }
    ],
    "sg:phone":"+1 423 638 3432",
    "sg:postcode":"37743",
    "sg:province":"TN",
    "sg:tags":[
        "hanging",
        "contractor"
    ],
    "wof:name":"Thomas E Dier",
    "wof:placetype":"venue"
},
  "geometry": {"coordinates":[-82.987075,36.064097],"type":"Point"}
}