{
  "type": "Feature",
  "properties": {
    "addr:full":"1507 Lewis Ave Dyersburg TN 38024",
    "addr:housenumber":"1507",
    "addr:postcode":"38024",
    "addr:street":"Lewis Ave",
    "iso:country":"US",
    "sg:address":"1507 Lewis Ave",
    "sg:city":"Dyersburg",
    "sg:classifiers":[
        {
            "category":"Social Services",
            "subcategory":"Child Care",
            "type":"Services"
        },
        {
            "category":"Education",
            "subcategory":"School",
            "type":"Public Place"
        }
    ],
    "sg:phone":"+1 731 288 0058",
    "sg:postcode":"38024",
    "sg:province":"TN",
    "sg:tags":[
        "day"
    ],
    "wof:name":"Discoveryland Learning Center",
    "wof:placetype":"venue"
},
  "geometry": {"coordinates":[-89.36568800000001,36.048108],"type":"Point"}
}