{
  "type": "Feature",
  "properties": {
    "iso:country":"US",
    "sg:address":"4933 Walnut Grove Rd",
    "sg:city":"Memphis",
    "sg:classifiers":[
        {
            "category":"Professional",
            "subcategory":"Management & Consulting",
            "type":"Services"
        }
    ],
    "sg:phone":"+1 901 761 1370",
    "sg:postcode":"38117",
    "sg:province":"TN",
    "wof:name":"Global Marketing Group LLC",
    "wof:placetype":"venue"
},
  "geometry": {"coordinates":[-89.896173,35.130552],"type":"Point"}
}