{
  "type": "Feature",
  "properties": {
    "iso:country":"US",
    "sg:address":"3548 Brunswick Rd",
    "sg:city":"Memphis",
    "sg:classifiers":[
        {
            "category":"Organizations",
            "subcategory":"Religious Organization",
            "type":"Services"
        }
    ],
    "sg:phone":"+1 901 388 1381",
    "sg:postcode":"38133",
    "sg:province":"TN",
    "sg:tags":[
        "church"
    ],
    "wof:name":"Reorganized CHURCH-Jesus-Lds",
    "wof:placetype":"venue"
},
  "geometry": {"coordinates":[-89.768595,35.220061],"type":"Point"}
}