{
  "type": "Feature",
  "properties": {
    "iso:country":"US",
    "sg:address":"624 Snow St",
    "sg:city":"Chattanooga",
    "sg:classifiers":[
        {
            "category":"Professional",
            "subcategory":"Business Services",
            "type":"Services"
        }
    ],
    "sg:phone":"+1 423 265 3054",
    "sg:postcode":"37405",
    "sg:province":"TN",
    "sg:tags":[
        "barricade"
    ],
    "wof:name":"A & H Safety Supply",
    "wof:placetype":"venue"
},
  "geometry": {"coordinates":[-85.310799,35.070069],"type":"Point"}
}