{
  "type": "Feature",
  "properties": {
    "iso:country":"US",
    "sg:address":"3210 Rudy St",
    "sg:city":"Knoxville",
    "sg:classifiers":[
        {
            "category":"Food & Beverages",
            "subcategory":"Liquor & Beverages",
            "type":"Retail Goods"
        }
    ],
    "sg:phone":"+1 865 525 4031",
    "sg:postcode":"37921",
    "sg:province":"TN",
    "sg:tags":[
        "store"
    ],
    "wof:name":"Palace Liquor Store Inc",
    "wof:placetype":"venue"
},
  "geometry": {"coordinates":[-83.95361200000001,35.991086],"type":"Point"}
}