{
  "type": "Feature",
  "properties": {
    "iso:country":"US",
    "sg:address":"3150 Stage Post Dr # 110",
    "sg:city":"Memphis",
    "sg:classifiers":[
        {
            "category":"Retail",
            "subcategory":"Repair Shop",
            "type":"Services"
        }
    ],
    "sg:phone":"+1 901 386 2242",
    "sg:postcode":"38133",
    "sg:province":"TN",
    "sg:tags":[
        "equipment",
        "medical"
    ],
    "wof:name":"Iba Dosimetry America, Inc.",
    "wof:placetype":"venue"
},
  "geometry": {"coordinates":[-89.80219700000001,35.211661],"type":"Point"}
}