{
  "type": "Feature",
  "properties": {
    "iso:country":"US",
    "sg:address":"9032 Stone Walk Pl",
    "sg:city":"Germantown",
    "sg:classifiers":[
        {
            "category":"Professional",
            "subcategory":"Lawyer & Legal Services",
            "type":"Services"
        }
    ],
    "sg:phone":"+1 901 759 3489",
    "sg:postcode":"38138",
    "sg:province":"TN",
    "sg:tags":[
        "attorney"
    ],
    "sg:website":"www.holleywaldrop.com",
    "wof:name":"Holley Waldrop Mearn & Lazarov",
    "wof:placetype":"venue"
},
  "geometry": {"coordinates":[-89.76186800000001,35.064973],"type":"Point"}
}