{
  "type": "Feature",
  "properties": {
    "iso:country":"US",
    "sg:address":"7526 Hodges Ferry Rd",
    "sg:city":"Knoxville",
    "sg:classifiers":[
        {
            "category":"Restaurant",
            "type":"Food & Drink"
        }
    ],
    "sg:phone":"+1 865 579 7995",
    "sg:postcode":"37920",
    "sg:province":"TN",
    "sg:tags":[
        "eating"
    ],
    "wof:name":"Cafe Noir",
    "wof:placetype":"venue"
},
  "geometry": {"coordinates":[-83.75403900000001,35.936765],"type":"Point"}
}