{
  "type": "Feature",
  "properties": {
    "iso:country":"US",
    "sg:address":"923 Virginia Ave",
    "sg:city":"Knoxville",
    "sg:classifiers":[
        {
            "category":"Professional",
            "subcategory":"Business Services",
            "type":"Services"
        }
    ],
    "sg:phone":"+1 865 637 0008",
    "sg:postcode":"37921",
    "sg:province":"TN",
    "sg:tags":[
        "notary"
    ],
    "wof:name":"Dale Disney",
    "wof:placetype":"venue"
},
  "geometry": {"coordinates":[-83.941954,35.982379],"type":"Point"}
}