{
  "type": "Feature",
  "properties": {
    "iso:country":"US",
    "sg:address":"169 E Main St",
    "sg:city":"Hendersonville",
    "sg:classifiers":[
        {
            "category":"Banks & Credit Unions",
            "subcategory":"Bank",
            "type":"Services"
        }
    ],
    "sg:phone":"+1 615 824 7012",
    "sg:postcode":"37075",
    "sg:province":"TN",
    "sg:tags":[
        "national",
        "commercial"
    ],
    "sg:website":"www.usbank.com",
    "wof:name":"US Bank",
    "wof:placetype":"venue"
},
  "geometry": {"coordinates":[-86.60597799999999,36.307569],"type":"Point"}
}