{
  "type": "Feature",
  "properties": {
    "iso:country":"US",
    "sg:address":"620 Reliability Cir",
    "sg:city":"Knoxville",
    "sg:classifiers":[
        {
            "category":"Professional",
            "subcategory":"Business Services",
            "type":"Services"
        }
    ],
    "sg:phone":"+1 865 675 4822",
    "sg:postcode":"37932",
    "sg:province":"TN",
    "wof:name":"REA Service Inc",
    "wof:placetype":"venue"
},
  "geometry": {"coordinates":[-84.129615,35.917066],"type":"Point"}
}