{
  "type": "Feature",
  "properties": {
    "addr:full":"904 High Springs Rd Knoxville TN 37932",
    "addr:housenumber":"904",
    "addr:postcode":"37932",
    "addr:street":"High Springs Rd",
    "iso:country":"US",
    "sg:address":"904 High Springs Rd",
    "sg:city":"Knoxville",
    "sg:classifiers":[
        {
            "category":"Professional",
            "type":"Services"
        }
    ],
    "sg:phone":"+1 865 966 4867",
    "sg:postcode":"37932",
    "sg:province":"TN",
    "sg:tags":[
        "establishment"
    ],
    "wof:name":"Jortec Inc",
    "wof:placetype":"venue"
},
  "geometry": {"coordinates":[-84.161987,35.905291],"type":"Point"}
}