{
  "type": "Feature",
  "properties": {
    "addr:full":"8483 E Brainerd Rd Chattanooga TN 37421",
    "addr:housenumber":"8483",
    "addr:postcode":"37421",
    "addr:street":"E Brainerd Rd",
    "iso:country":"US",
    "sg:address":"8483 E Brainerd Rd",
    "sg:city":"Chattanooga",
    "sg:classifiers":[
        {
            "category":"Shopping",
            "subcategory":"Gifts & Souvenirs",
            "type":"Retail Goods"
        }
    ],
    "sg:phone":"+1 423 893 8334",
    "sg:postcode":"37421",
    "sg:province":"TN",
    "sg:tags":[
        "shop"
    ],
    "wof:name":"Dry Duck II",
    "wof:placetype":"venue"
},
  "geometry": {"coordinates":[-85.137643,35.00165],"type":"Point"}
}