{
  "type": "Feature",
  "properties": {
    "iso:country":"US",
    "sg:address":"1903 Capri Rd",
    "sg:city":"Memphis",
    "sg:classifiers":[
        {
            "category":"Professional",
            "type":"Services"
        }
    ],
    "sg:phone":"+1 901 767 8111",
    "sg:postcode":"38117",
    "sg:province":"TN",
    "wof:name":"Lg Leatherwood",
    "wof:placetype":"venue"
},
  "geometry": {"coordinates":[-89.912132,35.08079],"type":"Point"}
}