{
  "type": "Feature",
  "properties": {
    "addr:full":"8372 Rambling Rose Dr Ooltewah TN 37363",
    "addr:housenumber":"8372",
    "addr:postcode":"37363",
    "addr:street":"Rambling Rose Dr",
    "iso:country":"US",
    "sg:address":"8372 Rambling Rose Dr",
    "sg:city":"Ooltewah",
    "sg:classifiers":[
        {
            "category":"Retail",
            "subcategory":"Repair Shop",
            "type":"Services"
        }
    ],
    "sg:phone":"+1 423 238 3567",
    "sg:postcode":"37363",
    "sg:province":"TN",
    "wof:name":"Matador Compressor Services",
    "wof:placetype":"venue"
},
  "geometry": {"coordinates":[-85.064058,35.138853],"type":"Point"}
}