{
  "type": "Feature",
  "properties": {
    "iso:country":"US",
    "sg:address":"3825 Ringgold Rd",
    "sg:city":"Chattanooga",
    "sg:classifiers":[
        {
            "category":"Health Services",
            "subcategory":"Dentist",
            "type":"Services"
        }
    ],
    "sg:phone":"+1 423 629 6015",
    "sg:postcode":"37412",
    "sg:province":"TN",
    "wof:name":"Rader, Rex E Jr Dds",
    "wof:placetype":"venue"
},
  "geometry": {"coordinates":[-85.25639099999999,34.999426],"type":"Point"}
}