{
  "type": "Feature",
  "properties": {
    "iso:country":"US",
    "sg:address":"8220 Kingston Pike",
    "sg:city":"Knoxville",
    "sg:classifiers":[
        {
            "category":"Home & Garden",
            "subcategory":"Furniture",
            "type":"Retail Goods"
        }
    ],
    "sg:phone":"+1 865 694 0039",
    "sg:postcode":"37919",
    "sg:province":"TN",
    "wof:name":"Rooms To Go Tennessee Corp",
    "wof:placetype":"venue"
},
  "geometry": {"coordinates":[-84.05346299999999,35.924389],"type":"Point"}
}