{
  "type": "Feature",
  "properties": {
    "iso:country":"US",
    "sg:address":"32 Pebblecreek Cove",
    "sg:city":"Humboldt",
    "sg:classifiers":[
        {
            "category":"Professional",
            "subcategory":"Business Services",
            "type":"Services"
        }
    ],
    "sg:phone":"+1 731 784 8770",
    "sg:postcode":"38343",
    "sg:province":"TN",
    "wof:name":"Brady L Staggs",
    "wof:placetype":"venue"
},
  "geometry": {"coordinates":[-88.87217200000001,35.784227],"type":"Point"}
}