{
  "type": "Feature",
  "properties": {
    "iso:country":"US",
    "sg:address":"855 Old Stage Rd",
    "sg:city":"Dickson",
    "sg:classifiers":[
        {
            "category":"Building & Trades",
            "subcategory":"Construction",
            "type":"Services"
        }
    ],
    "sg:phone":"+1 615 789 5967",
    "sg:postcode":"37055",
    "sg:province":"TN",
    "sg:tags":[
        "house"
    ],
    "wof:name":"Westermans Construction",
    "wof:placetype":"venue"
},
  "geometry": {"coordinates":[-87.39877,36.154592],"type":"Point"}
}