{
  "type": "Feature",
  "properties": {
    "iso:country":"US",
    "sg:address":"6316 Pettus Rd",
    "sg:city":"Antioch",
    "sg:classifiers":[
        {
            "category":"Building & Trades",
            "subcategory":"Cleaning & Sanitation",
            "type":"Services"
        }
    ],
    "sg:phone":"+1 615 941 1415",
    "sg:postcode":"37013",
    "sg:province":"TN",
    "sg:tags":[
        "maintenance"
    ],
    "wof:name":"Dustbusters Cleaning Serv",
    "wof:placetype":"venue"
},
  "geometry": {"coordinates":[-86.677307,35.997677],"type":"Point"}
}