{
  "type": "Feature",
  "properties": {
    "iso:country":"US",
    "sg:address":"1482 Amherst Rd",
    "sg:city":"Knoxville",
    "sg:classifiers":[
        {
            "category":"Bars & Pubs",
            "type":"Food & Drink"
        }
    ],
    "sg:phone":"+1 865 330 0011",
    "sg:postcode":"37909",
    "sg:province":"TN",
    "sg:tags":[
        "drinking"
    ],
    "wof:name":"A J's Sports Bar",
    "wof:placetype":"venue"
},
  "geometry": {"coordinates":[-84.01349399999999,35.954311],"type":"Point"}
}