{
  "type": "Feature",
  "properties": {
    "addr:full":"2806 Schaad Rd Knoxville TN 37921",
    "addr:housenumber":"2806",
    "addr:postcode":"37921",
    "addr:street":"Schaad Rd",
    "iso:country":"US",
    "sg:address":"2806 Schaad Rd",
    "sg:city":"Knoxville",
    "sg:classifiers":[
        {
            "category":"Banks & Credit Unions",
            "subcategory":"Bank",
            "type":"Services"
        }
    ],
    "sg:phone":"+1 865 947 1003",
    "sg:postcode":"37921",
    "sg:province":"TN",
    "sg:tags":[
        "loan",
        "real estate"
    ],
    "wof:name":"Countrywide Home Loans",
    "wof:placetype":"venue"
},
  "geometry": {"coordinates":[-84.019784,36.005717],"type":"Point"}
}