{
  "type": "Feature",
  "properties": {
    "iso:country":"US",
    "sg:address":"512 6th Ave",
    "sg:city":"Columbia",
    "sg:classifiers":[
        {
            "category":"Personal",
            "subcategory":"Beauty Salon",
            "type":"Services"
        }
    ],
    "sg:phone":"+1 931 381 6990",
    "sg:postcode":"38401",
    "sg:province":"TN",
    "sg:tags":[
        "shop"
    ],
    "sg:website":"www.thenailgarden.com",
    "wof:name":"Nail Garden",
    "wof:placetype":"venue"
},
  "geometry": {"coordinates":[-87.022627,35.624794],"type":"Point"}
}