{
  "type": "Feature",
  "properties": {
    "iso:country":"US",
    "sg:address":"433 Mc Nally Dr",
    "sg:city":"Nashville",
    "sg:classifiers":[
        {
            "category":"Wholesale",
            "subcategory":"Office Equipment",
            "type":"Manufacturing & Wholesale Goods"
        }
    ],
    "sg:phone":"+1 615 333 8800",
    "sg:postcode":"37211",
    "sg:province":"TN",
    "sg:tags":[
        "supply"
    ],
    "wof:name":"Daisytek Office Products",
    "wof:placetype":"venue"
},
  "geometry": {"coordinates":[-86.74241499999999,36.092466],"type":"Point"}
}