{
  "type": "Feature",
  "properties": {
    "addr:full":"2298 Barfield Rd Murfreesboro TN 37128",
    "addr:housenumber":"2298",
    "addr:postcode":"37128",
    "addr:street":"Barfield Rd",
    "iso:country":"US",
    "sg:address":"2298 Barfield Rd",
    "sg:city":"Murfreesboro",
    "sg:classifiers":[
        {
            "category":"Education",
            "subcategory":"Dance Studio",
            "type":"Public Place"
        }
    ],
    "sg:phone":"+1 615 896 3118",
    "sg:postcode":"37128",
    "sg:province":"TN",
    "wof:name":"Barfield School Of Dance",
    "wof:placetype":"venue"
},
  "geometry": {"coordinates":[-86.429627,35.801354],"type":"Point"}
}