{
  "type": "Feature",
  "properties": {
    "addr:full":"119 S Walnut St Murfreesboro TN 37130",
    "addr:housenumber":"119",
    "addr:postcode":"37130",
    "addr:street":"S Walnut St",
    "iso:country":"US",
    "sg:address":"119 S Walnut St",
    "sg:city":"Murfreesboro",
    "sg:classifiers":[
        {
            "category":"Retail",
            "subcategory":"Laundry & Dry Cleaning",
            "type":"Services"
        },
        {
            "category":"Building & Trades",
            "subcategory":"Construction",
            "type":"Services"
        }
    ],
    "sg:phone":"+1 615 893 4999",
    "sg:postcode":"37130",
    "sg:province":"TN",
    "sg:tags":[
        "fire",
        "upholstery",
        "damage",
        "restoration",
        "carpet"
    ],
    "wof:name":"All Techni Clean",
    "wof:placetype":"venue"
},
  "geometry": {"coordinates":[-86.39381899999999,35.846019],"type":"Point"}
}