{
  "type": "Feature",
  "properties": {
    "addr:full":"347 Shady Oak Dr White Bluff TN 37187",
    "addr:housenumber":"347",
    "addr:postcode":"37187",
    "addr:street":"Shady Oak Dr White Bluff",
    "iso:country":"US",
    "sg:address":"347 Shady Oak Dr",
    "sg:city":"White Bluff",
    "sg:classifiers":[
        {
            "category":"Government",
            "subcategory":"Office",
            "type":"Public Place"
        }
    ],
    "sg:phone":"+1 615 797 3129",
    "sg:postcode":"37187",
    "sg:province":"TN",
    "sg:tags":[
        "village"
    ],
    "wof:name":"White Bluff Filter Plant",
    "wof:placetype":"venue"
},
  "geometry": {"coordinates":[-87.219162,36.112584],"type":"Point"}
}