{
  "type": "Feature",
  "properties": {
    "addr:full":"129 Co Rd 202 Athens TN 37303",
    "addr:housenumber":"129;202",
    "addr:postcode":"37303",
    "addr:street":"Co Rd",
    "iso:country":"US",
    "sg:address":"129 Co Rd 202",
    "sg:city":"Athens",
    "sg:classifiers":[
        {
            "category":"Professional",
            "subcategory":"Research",
            "type":"Services"
        }
    ],
    "sg:phone":"+1 423 507 8341",
    "sg:postcode":"37303",
    "sg:province":"TN",
    "sg:tags":[
        "nonphysical",
        "commercial"
    ],
    "wof:name":"Kings Keep",
    "wof:placetype":"venue"
},
  "geometry": {"coordinates":[-84.61127500000001,35.481989],"type":"Point"}
}