{
  "type": "Feature",
  "properties": {
    "iso:country":"US",
    "sg:address":"339 E Main St",
    "sg:city":"Adamsville",
    "sg:classifiers":[
        {
            "category":"Government",
            "subcategory":"Post Office",
            "type":"Public Place"
        }
    ],
    "sg:phone":"+1 731 632 4270",
    "sg:postcode":"38310",
    "sg:province":"TN",
    "wof:name":"US Post Office",
    "wof:placetype":"venue"
},
  "geometry": {"coordinates":[-88.385571,35.235435],"type":"Point"}
}