{
  "type": "Feature",
  "properties": {
    "addr:full":"302 W Vine St Murfreesboro TN 37130",
    "addr:housenumber":"302",
    "addr:postcode":"37130",
    "addr:street":"W Vine St",
    "iso:country":"US",
    "sg:address":"302 W Vine St",
    "sg:city":"Murfreesboro",
    "sg:classifiers":[
        {
            "category":"Shopping",
            "type":"Retail Goods"
        }
    ],
    "sg:phone":"+1 615 890 0732",
    "sg:postcode":"37130",
    "sg:province":"TN",
    "sg:tags":[
        "merchandise"
    ],
    "wof:name":"Burton Dye Prints",
    "wof:placetype":"venue"
},
  "geometry": {"coordinates":[-86.395056,35.845428],"type":"Point"}
}