{
  "type": "Feature",
  "properties": {
    "iso:country":"US",
    "sg:address":"2611 Gallatin Pike",
    "sg:city":"Nashville",
    "sg:classifiers":[
        {
            "category":"Utilities",
            "subcategory":"Refuse",
            "type":"Services"
        },
        {
            "category":"Wholesale",
            "subcategory":"Scrap",
            "type":"Manufacturing & Wholesale Goods"
        }
    ],
    "sg:phone":"+1 615 226 1464",
    "sg:postcode":"37216",
    "sg:province":"TN",
    "sg:tags":[
        "recycling",
        "center",
        "system"
    ],
    "wof:name":"Pocket Money Recycling Inc",
    "wof:placetype":"venue"
},
  "geometry": {"coordinates":[-86.74152599999999,36.198012],"type":"Point"}
}