{
  "type": "Feature",
  "properties": {
    "addr:full":"7105 Genoa Dr Chattanooga TN 37421",
    "addr:housenumber":"7105",
    "addr:postcode":"37421",
    "addr:street":"Genoa Dr",
    "iso:country":"US",
    "sg:address":"7105 Genoa Dr",
    "sg:city":"Chattanooga",
    "sg:classifiers":[
        {
            "category":"Wholesale",
            "subcategory":"Machinery & Supplies",
            "type":"Manufacturing & Wholesale Goods"
        }
    ],
    "sg:phone":"+1 423 892 1758",
    "sg:postcode":"37421",
    "sg:province":"TN",
    "sg:tags":[
        "machine",
        "distributor",
        "tool"
    ],
    "wof:name":"Ray Edens Co",
    "wof:placetype":"venue"
},
  "geometry": {"coordinates":[-85.16527499999999,35.028072],"type":"Point"}
}