{
  "type": "Feature",
  "properties": {
    "addr:full":"108 S Main Ave Dyersburg TN 38024",
    "addr:housenumber":"108",
    "addr:postcode":"38024",
    "addr:street":"S Main Ave",
    "iso:country":"US",
    "sg:address":"108 S Main Ave",
    "sg:city":"Dyersburg",
    "sg:classifiers":[
        {
            "category":"Professional",
            "subcategory":"Advertising",
            "type":"Services"
        }
    ],
    "sg:phone":"+1 731 285 0686",
    "sg:postcode":"38024",
    "sg:province":"TN",
    "sg:tags":[
        "guide"
    ],
    "wof:name":"Shopper's Guide",
    "wof:placetype":"venue"
},
  "geometry": {"coordinates":[-89.385741,36.032416],"type":"Point"}
}