{
  "type": "Feature",
  "properties": {
    "addr:full":"848 Dickerson Pike Nashville TN 37207",
    "addr:housenumber":"848",
    "addr:postcode":"37207",
    "addr:street":"Dickerson Pike",
    "iso:country":"US",
    "sg:address":"848 Dickerson Pike",
    "sg:city":"Nashville",
    "sg:classifiers":[
        {
            "category":"Banks & Credit Unions",
            "subcategory":"Bank",
            "type":"Services"
        }
    ],
    "sg:phone":"+1 615 226 8816",
    "sg:postcode":"37207",
    "sg:province":"TN",
    "sg:tags":[
        "loan"
    ],
    "wof:name":"Household Pawn",
    "wof:placetype":"venue"
},
  "geometry": {"coordinates":[-86.773627,36.18571],"type":"Point"}
}