{
  "type": "Feature",
  "properties": {
    "addr:full":"6701 Baum Dr SW Knoxville TN 37919",
    "addr:housenumber":"6701",
    "addr:postcode":"37919",
    "addr:street":"Baum Dr Sw",
    "iso:country":"US",
    "sg:address":"6701 Baum Dr SW",
    "sg:city":"Knoxville",
    "sg:classifiers":[
        {
            "category":"Travel",
            "subcategory":"Travel Agent",
            "type":"Entertainment"
        }
    ],
    "sg:phone":"+1 865 584 3611",
    "sg:postcode":"37919",
    "sg:province":"TN",
    "sg:tags":[
        "passenger",
        "agency",
        "transportation",
        "arrangement"
    ],
    "wof:name":"Carlson Wagonlit Travel",
    "wof:placetype":"venue"
},
  "geometry": {"coordinates":[-84.01166499999999,35.927383],"type":"Point"}
}