{
  "type": "Feature",
  "properties": {
    "iso:country":"US",
    "sg:address":"105 British Woods Dr",
    "sg:city":"Nashville",
    "sg:classifiers":[
        {
            "category":"Education",
            "subcategory":"Special Training",
            "type":"Public Place"
        }
    ],
    "sg:phone":"+1 615 361 0748",
    "sg:postcode":"37217",
    "sg:province":"TN",
    "wof:name":"Stray Air Inc",
    "wof:placetype":"venue"
},
  "geometry": {"coordinates":[-86.65260600000001,36.093461],"type":"Point"}
}