{
  "type": "Feature",
  "properties": {
    "iso:country":"US",
    "sg:address":"1001 N Highland Ave",
    "sg:city":"Murfreesboro",
    "sg:classifiers":[
        {
            "category":"Health Services",
            "subcategory":"Doctor",
            "type":"Services"
        }
    ],
    "sg:phone":"+1 615 849 8719",
    "sg:postcode":"37130",
    "sg:province":"TN",
    "sg:tags":[
        "laboratory",
        "medical"
    ],
    "sg:website":"www.theimagingcenterofmurfreesboro.com",
    "wof:name":"Imaging Center Inc",
    "wof:placetype":"venue"
},
  "geometry": {"coordinates":[-86.38252,35.854001],"type":"Point"}
}