{
  "type": "Feature",
  "properties": {
    "iso:country":"US",
    "sg:address":"2382 Crocker Springs Rd",
    "sg:city":"Goodlettsville",
    "sg:classifiers":[
        {
            "category":"Travel",
            "subcategory":"Hotels & Motels",
            "type":"Entertainment"
        }
    ],
    "sg:phone":"+1 615 876 8502",
    "sg:postcode":"37072",
    "sg:province":"TN",
    "sg:tags":[
        "breakfast",
        "accommodation",
        "bed"
    ],
    "wof:name":"Crocker Springs Bed & Brkfst",
    "wof:placetype":"venue"
},
  "geometry": {"coordinates":[-86.82396799999999,36.331145],"type":"Point"}
}