{
  "type": "Feature",
  "properties": {
    "addr:full":"114 College St E Fayetteville TN 37334",
    "addr:housenumber":"114",
    "addr:postcode":"37334",
    "addr:street":"College St E",
    "iso:country":"US",
    "sg:address":"114 College St E",
    "sg:city":"Fayetteville",
    "sg:classifiers":[
        {
            "category":"Shopping",
            "subcategory":"Gifts & Souvenirs",
            "type":"Retail Goods"
        }
    ],
    "sg:phone":"+1 931 438 0607",
    "sg:postcode":"37334",
    "sg:province":"TN",
    "wof:name":"Ivy Wreath",
    "wof:placetype":"venue"
},
  "geometry": {"coordinates":[-86.57042,35.152303],"type":"Point"}
}