{
  "type": "Feature",
  "properties": {
    "iso:country":"US",
    "sg:address":"940 Virginia Ave",
    "sg:city":"Knoxville",
    "sg:classifiers":[
        {
            "category":"Building & Trades",
            "subcategory":"Plumbing",
            "type":"Services"
        },
        {
            "category":"Building & Trades",
            "subcategory":"Construction",
            "type":"Services"
        },
        {
            "category":"Building & Trades",
            "subcategory":"Cleaning & Sanitation",
            "type":"Services"
        }
    ],
    "sg:phone":"+1 865 521 9196",
    "sg:postcode":"37921",
    "sg:province":"TN",
    "sg:tags":[
        "cleaner",
        "plumber",
        "industrial",
        "repairer",
        "specialty",
        "system",
        "heating",
        "plumbing-drain",
        "contractor",
        "air conditioning",
        "sewer",
        "contractors-commercial"
    ],
    "wof:name":"Volunteer Drain Service",
    "wof:placetype":"venue"
},
  "geometry": {"coordinates":[-83.943274,35.981548],"type":"Point"}
}