{
  "type": "Feature",
  "properties": {
    "iso:country":"US",
    "sg:address":"2597 McKnight Rd",
    "sg:city":"Culleoka",
    "sg:classifiers":[
        {
            "category":"Professional",
            "type":"Services"
        }
    ],
    "sg:phone":"+1 931 987 0507",
    "sg:postcode":"38451",
    "sg:province":"TN",
    "wof:name":"Beverly D Rogers",
    "wof:placetype":"venue"
},
  "geometry": {"coordinates":[-86.937302,35.485381],"type":"Point"}
}