{
  "type": "Feature",
  "properties": {
    "iso:country":"US",
    "sg:address":"2600 Colonial Towers Dr",
    "sg:city":"Cordova",
    "sg:classifiers":[
        {
            "category":"Organizations",
            "subcategory":"Membership Organization",
            "type":"Services"
        }
    ],
    "sg:phone":"+1 901 382 8852",
    "sg:postcode":"38016",
    "sg:province":"TN",
    "sg:tags":[
        "club",
        "private"
    ],
    "wof:name":"Colonial Estates",
    "wof:placetype":"venue"
},
  "geometry": {"coordinates":[-89.768867,35.199848],"type":"Point"}
}