{
  "type": "Feature",
  "properties": {
    "iso:country":"US",
    "sg:address":"1462 Piedmont Rd",
    "sg:city":"New Market",
    "sg:classifiers":[
        {
            "category":"Shopping",
            "subcategory":"Gifts & Souvenirs",
            "type":"Retail Goods"
        }
    ],
    "sg:phone":"+1 865 475 8128",
    "sg:postcode":"37820",
    "sg:province":"TN",
    "wof:name":"Banc Card of America Inc",
    "wof:placetype":"venue"
},
  "geometry": {"coordinates":[-83.545621,36.071344],"type":"Point"}
}