{
  "type": "Feature",
  "properties": {
    "addr:full":"42 Smith Rd Fayetteville TN 37334",
    "addr:housenumber":"42",
    "addr:postcode":"37334",
    "addr:street":"Smith Rd",
    "iso:country":"US",
    "sg:address":"42 Smith Rd",
    "sg:city":"Fayetteville",
    "sg:phone":"+1 931 433 6913",
    "sg:postcode":"37334",
    "sg:province":"TN",
    "sg:tags":[
        "farm",
        "field",
        "crop"
    ],
    "wof:name":"George Monks",
    "wof:placetype":"venue"
},
  "geometry": {"coordinates":[-86.557123,35.060151],"type":"Point"}
}