{
  "type": "Feature",
  "properties": {
    "iso:country":"US",
    "sg:address":"690 Fitzhugh Blvd",
    "sg:city":"Smyrna",
    "sg:classifiers":[
        {
            "category":"Wholesale",
            "subcategory":"Machinery & Supplies",
            "type":"Manufacturing & Wholesale Goods"
        }
    ],
    "sg:phone":"+1 615 220 4004",
    "sg:postcode":"37167",
    "sg:province":"TN",
    "sg:tags":[
        "aircraft",
        "broker"
    ],
    "wof:name":"Fractionair",
    "wof:placetype":"venue"
},
  "geometry": {"coordinates":[-86.51285799999999,36.01854],"type":"Point"}
}