{
  "type": "Feature",
  "properties": {
    "iso:country":"US",
    "sg:address":"6314 US Hwy 41 A",
    "sg:city":"Pleasant View",
    "sg:classifiers":[
        {
            "category":"Shopping",
            "subcategory":"Discount & Variety Stores",
            "type":"Retail Goods"
        }
    ],
    "sg:phone":"+1 615 746 3325",
    "sg:postcode":"37146",
    "sg:province":"TN",
    "wof:name":"Dollar General",
    "wof:placetype":"venue"
},
  "geometry": {"coordinates":[-87.022541,36.394409],"type":"Point"}
}