{
  "type": "Feature",
  "properties": {
    "addr:full":"400 Monroe Ave Memphis TN 38103",
    "addr:housenumber":"400",
    "addr:postcode":"38103",
    "addr:street":"Monroe Ave",
    "iso:country":"US",
    "sg:address":"400 Monroe Ave",
    "sg:city":"Memphis",
    "sg:classifiers":[
        {
            "category":"Manufacturing",
            "subcategory":"Food",
            "type":"Manufacturing & Wholesale Goods"
        }
    ],
    "sg:phone":"+1 901 525 8611",
    "sg:postcode":"38103",
    "sg:province":"TN",
    "sg:tags":[
        "product",
        "mfg"
    ],
    "wof:name":"Continental Baking Co",
    "wof:placetype":"venue"
},
  "geometry": {"coordinates":[-90.04266200000001,35.14138],"type":"Point"}
}