{
  "type": "Feature",
  "properties": {
    "iso:country":"US",
    "sg:address":"3818 W End Ave",
    "sg:city":"Nashville",
    "sg:classifiers":[
        {
            "category":"Real Estate",
            "subcategory":"Real Estate Agent",
            "type":"Services"
        }
    ],
    "sg:phone":"+1 615 255 8531",
    "sg:postcode":"37205",
    "sg:province":"TN",
    "sg:tags":[
        "condo",
        "assoc"
    ],
    "wof:name":"Montclair Condominium Assoc",
    "wof:placetype":"venue"
},
  "geometry": {"coordinates":[-86.832127,36.132218],"type":"Point"}
}