{
  "type": "Feature",
  "properties": {
    "addr:full":"3403 Mallard Dr Clarksville TN 37042",
    "addr:housenumber":"3403",
    "addr:postcode":"37042",
    "addr:street":"Mallard Dr",
    "iso:country":"US",
    "sg:address":"3403 Mallard Dr",
    "sg:city":"Clarksville",
    "sg:classifiers":[
        {
            "category":"Arts & Performance",
            "subcategory":"Theater",
            "type":"Entertainment"
        }
    ],
    "sg:phone":"+1 931 431 0946",
    "sg:postcode":"37042",
    "sg:province":"TN",
    "sg:tags":[
        "musician"
    ],
    "wof:name":"Raymond N Ruffin",
    "wof:placetype":"venue"
},
  "geometry": {"coordinates":[-87.411507,36.639889],"type":"Point"}
}