{
  "type": "Feature",
  "properties": {
    "iso:country":"US",
    "sg:address":"860 Ridge Lake Blvd",
    "sg:city":"Memphis",
    "sg:classifiers":[
        {
            "category":"Building & Trades",
            "subcategory":"Pest Control",
            "type":"Services"
        }
    ],
    "sg:phone":"+1 901 543 7634",
    "sg:postcode":"38120",
    "sg:province":"TN",
    "sg:tags":[
        "disinfecting"
    ],
    "wof:name":"Terminex Pest Control Systems",
    "wof:placetype":"venue"
},
  "geometry": {"coordinates":[-89.867896,35.105603],"type":"Point"}
}