{
  "type": "Feature",
  "properties": {
    "addr:full":"117 Peak Hill Cir Nashville TN 37211",
    "addr:housenumber":"117",
    "addr:postcode":"37211",
    "addr:street":"Peak Hill Cir",
    "iso:country":"US",
    "sg:address":"117 Peak Hill Cir",
    "sg:city":"Nashville",
    "sg:classifiers":[
        {
            "category":"Building & Trades",
            "subcategory":"Construction",
            "type":"Services"
        }
    ],
    "sg:phone":"+1 615 566 4899",
    "sg:postcode":"37211",
    "sg:province":"TN",
    "sg:tags":[
        "house"
    ],
    "wof:name":"Luehrsen Construction",
    "wof:placetype":"venue"
},
  "geometry": {"coordinates":[-86.71728400000001,36.026768],"type":"Point"}
}