{
  "type": "Feature",
  "properties": {
    "iso:country":"US",
    "sg:address":"4615 Poplar Ave Ste 17",
    "sg:city":"Memphis",
    "sg:classifiers":[
        {
            "category":"Shopping",
            "subcategory":"Stationery & Office Supplies",
            "type":"Retail Goods"
        },
        {
            "category":"Shopping",
            "subcategory":"Gifts & Souvenirs",
            "type":"Retail Goods"
        }
    ],
    "sg:phone":"+1 901 767 8808",
    "sg:postcode":"38117",
    "sg:province":"TN",
    "sg:tags":[
        "shop",
        "announcement",
        "store",
        "invitation"
    ],
    "wof:name":"Stovall Collection & Stationer",
    "wof:placetype":"venue"
},
  "geometry": {"coordinates":[-89.908142,35.116713],"type":"Point"}
}