{
  "type": "Feature",
  "properties": {
    "addr:full":"2015 8th Ave S Nashville TN 37204",
    "addr:housenumber":"2015",
    "addr:postcode":"37204",
    "addr:street":"8Th Ave S",
    "iso:country":"US",
    "sg:address":"2015 8th Ave S",
    "sg:city":"Nashville",
    "sg:classifiers":[
        {
            "category":"Shopping",
            "subcategory":"Used Merchandise",
            "type":"Retail Goods"
        }
    ],
    "sg:phone":"+1 615 279 9922",
    "sg:postcode":"37204",
    "sg:province":"TN",
    "sg:tags":[
        "antique"
    ],
    "wof:name":"Eighth Avenue Antique Mall",
    "wof:placetype":"venue"
},
  "geometry": {"coordinates":[-86.779324,36.132589],"type":"Point"}
}