{
  "type": "Feature",
  "properties": {
    "addr:full":"4911 State Hwy 58 Chattanooga TN 37416",
    "addr:housenumber":"4911",
    "addr:postcode":"37416",
    "addr:street":"State Hwy 58",
    "iso:country":"US",
    "sg:address":"4911 State Hwy 58",
    "sg:city":"Chattanooga",
    "sg:classifiers":[
        {
            "category":"Autos & Motor Vehicles",
            "subcategory":"Auto Supplies",
            "type":"Retail Goods"
        }
    ],
    "sg:phone":"+1 423 499 3576",
    "sg:postcode":"37416",
    "sg:province":"TN",
    "sg:tags":[
        "repair",
        "gen",
        "tire"
    ],
    "wof:name":"Express Tire & Auto Service",
    "wof:placetype":"venue"
},
  "geometry": {"coordinates":[-85.18652,35.089819],"type":"Point"}
}