{
  "type": "Feature",
  "properties": {
    "iso:country":"US",
    "sg:address":"145 Lawson Ln",
    "sg:city":"Waverly",
    "sg:classifiers":[
        {
            "category":"Retail",
            "subcategory":"Repair Shop",
            "type":"Services"
        }
    ],
    "sg:phone":"+1 931 296 2323",
    "sg:postcode":"37185",
    "sg:province":"TN",
    "sg:tags":[
        "plumbing",
        "drain",
        "cleaning",
        "sewer"
    ],
    "wof:name":"Merideth & Voorhees Plumbing",
    "wof:placetype":"venue"
},
  "geometry": {"coordinates":[-87.74590499999999,36.08504],"type":"Point"}
}