{
  "type": "Feature",
  "properties": {
    "iso:country":"US",
    "sg:address":"8419 Dayton Pike",
    "sg:city":"Soddy Daisy",
    "sg:classifiers":[
        {
            "category":"Building & Trades",
            "subcategory":"Cleaning & Sanitation",
            "type":"Services"
        }
    ],
    "sg:phone":"+1 423 842 6644",
    "sg:postcode":"37379",
    "sg:province":"TN",
    "sg:tags":[
        "maintenance"
    ],
    "wof:name":"M P W U H P Specialty Service",
    "wof:placetype":"venue"
},
  "geometry": {"coordinates":[-85.224523,35.219799],"type":"Point"}
}