{
  "type": "Feature",
  "properties": {
    "addr:full":"5118 Park Ave Memphis TN 38117",
    "addr:housenumber":"5118",
    "addr:postcode":"38117",
    "addr:street":"Park Ave",
    "iso:country":"US",
    "sg:address":"5118 Park Ave",
    "sg:city":"Memphis",
    "sg:classifiers":[
        {
            "category":"Government",
            "subcategory":"Court House",
            "type":"Public Place"
        }
    ],
    "sg:phone":"+1 901 761 5102",
    "sg:postcode":"38117",
    "sg:province":"TN",
    "sg:tags":[
        "county",
        "clerk"
    ],
    "wof:name":"Clerks Office",
    "wof:placetype":"venue"
},
  "geometry": {"coordinates":[-89.890809,35.106371],"type":"Point"}
}