{
  "type": "Feature",
  "properties": {
    "addr:full":"160 Imperial Blvd Hendersonville TN 37075",
    "addr:housenumber":"160",
    "addr:postcode":"37075",
    "addr:street":"Imperial Blvd",
    "iso:country":"US",
    "sg:address":"160 Imperial Blvd",
    "sg:city":"Hendersonville",
    "sg:classifiers":[
        {
            "category":"Shopping",
            "subcategory":"Used Merchandise",
            "type":"Retail Goods"
        }
    ],
    "sg:phone":"+1 615 824 9494",
    "sg:postcode":"37075",
    "sg:province":"TN",
    "wof:name":"Universal Computer Inc",
    "wof:placetype":"venue"
},
  "geometry": {"coordinates":[-86.631074,36.300597],"type":"Point"}
}