{
  "type": "Feature",
  "properties": {
    "iso:country":"US",
    "sg:address":"333 Old Middlesboro Hwy",
    "sg:city":"La Follette",
    "sg:classifiers":[
        {
            "category":"Real Estate",
            "subcategory":"Real Estate Agent",
            "type":"Services"
        },
        {
            "category":"Professional",
            "subcategory":"Business Services",
            "type":"Services"
        }
    ],
    "sg:phone":"+1 423 563 0194",
    "sg:postcode":"37766",
    "sg:province":"TN",
    "sg:tags":[
        "inspection"
    ],
    "wof:name":"Comprehensive Property Assessm",
    "wof:placetype":"venue"
},
  "geometry": {"coordinates":[-84.05670499999999,36.407901],"type":"Point"}
}