{
  "type": "Feature",
  "properties": {
    "iso:country":"US",
    "sg:address":"340 9th Ave N",
    "sg:city":"Franklin",
    "sg:classifiers":[
        {
            "category":"Wholesale",
            "subcategory":"Farm Supplies",
            "type":"Manufacturing & Wholesale Goods"
        }
    ],
    "sg:phone":"+1 615 794 4661",
    "sg:postcode":"37064",
    "sg:province":"TN",
    "sg:tags":[
        "preparation",
        "market",
        "crop",
        "for"
    ],
    "wof:name":"C R S",
    "wof:placetype":"venue"
},
  "geometry": {"coordinates":[-86.874825,35.922401],"type":"Point"}
}