{
  "type": "Feature",
  "properties": {
    "iso:country":"US",
    "sg:address":"6907 Kingston Pike",
    "sg:city":"Knoxville",
    "sg:classifiers":[
        {
            "category":"Personal",
            "subcategory":"Beauty Salon",
            "type":"Services"
        }
    ],
    "sg:phone":"+1 865 588 7007",
    "sg:postcode":"37919",
    "sg:province":"TN",
    "sg:tags":[
        "shop"
    ],
    "wof:name":"Hair Gallery",
    "wof:placetype":"venue"
},
  "geometry": {"coordinates":[-84.022127,35.932282],"type":"Point"}
}