{
  "type": "Feature",
  "properties": {
    "iso:country":"US",
    "sg:address":"218 Proffitt Ridge Rd",
    "sg:city":"Mooresburg",
    "sg:classifiers":[
        {
            "category":"Professional",
            "subcategory":"Management & Consulting",
            "type":"Services"
        }
    ],
    "sg:phone":"+1 423 272 3722",
    "sg:postcode":"37811",
    "sg:province":"TN",
    "wof:name":"First String Production",
    "wof:placetype":"venue"
},
  "geometry": {"coordinates":[-83.222019,36.328415],"type":"Point"}
}