{
  "type": "Feature",
  "properties": {
    "iso:country":"US",
    "sg:address":"975 Greeson Hollow Rd",
    "sg:city":"Waynesboro",
    "sg:classifiers":[
        {
            "category":"Professional",
            "type":"Services"
        }
    ],
    "sg:phone":"+1 931 722 5352",
    "sg:postcode":"38485",
    "sg:province":"TN",
    "wof:name":"Swinea Sr Raye",
    "wof:placetype":"venue"
},
  "geometry": {"coordinates":[-87.748428,35.298216],"type":"Point"}
}