{
  "type": "Feature",
  "properties": {
    "iso:country":"US",
    "sg:address":"5409 Maryland Way",
    "sg:city":"Brentwood",
    "sg:classifiers":[
        {
            "category":"Professional",
            "subcategory":"Lawyer & Legal Services",
            "type":"Services"
        }
    ],
    "sg:phone":"+1 615 370 8900",
    "sg:postcode":"37027",
    "sg:province":"TN",
    "wof:name":"Anderson & Blackard",
    "wof:placetype":"venue"
},
  "geometry": {"coordinates":[-86.814865,36.036792],"type":"Point"}
}