{
  "type": "Feature",
  "properties": {
    "iso:country":"US",
    "sg:address":"1049 N Cedar Bluff Rd",
    "sg:city":"Knoxville",
    "sg:classifiers":[
        {
            "category":"Restaurant",
            "type":"Food & Drink"
        }
    ],
    "sg:phone":"+1 865 769 1377",
    "sg:postcode":"37923",
    "sg:province":"TN",
    "wof:name":"Z Mex Grille",
    "wof:placetype":"venue"
},
  "geometry": {"coordinates":[-84.094649,35.940652],"type":"Point"}
}