{
  "type": "Feature",
  "properties": {
    "addr:full":"7216 Nolensville Rd Nolensville TN 37135",
    "addr:housenumber":"7216",
    "addr:postcode":"37135",
    "addr:street":"Nolensville Rd",
    "iso:country":"US",
    "sg:address":"7216 Nolensville Rd",
    "sg:city":"Nolensville",
    "sg:classifiers":[
        {
            "category":"Building & Trades",
            "subcategory":"Landscaping Services",
            "type":"Services"
        }
    ],
    "sg:phone":"+1 615 642 1316",
    "sg:postcode":"37135",
    "sg:province":"TN",
    "sg:tags":[
        "landscape"
    ],
    "wof:name":"Gc Landscaping",
    "wof:placetype":"venue"
},
  "geometry": {"coordinates":[-86.67513700000001,35.963793],"type":"Point"}
}