{
  "type": "Feature",
  "properties": {
    "iso:country":"US",
    "sg:address":"415 W Main St",
    "sg:city":"Rogersville",
    "sg:classifiers":[
        {
            "category":"Organizations",
            "subcategory":"Religious Organization",
            "type":"Services"
        }
    ],
    "sg:phone":"+1 423 272 4048",
    "sg:postcode":"37857",
    "sg:province":"TN",
    "sg:tags":[
        "church"
    ],
    "wof:name":"St Matthias Episcopal Church",
    "wof:placetype":"venue"
},
  "geometry": {"coordinates":[-83.01012,36.405642],"type":"Point"}
}