{
  "type": "Feature",
  "properties": {
    "iso:country":"US",
    "sg:address":"1081 McClure Rd",
    "sg:city":"Memphis",
    "sg:classifiers":[
        {
            "category":"Education",
            "subcategory":"Special Training",
            "type":"Public Place"
        }
    ],
    "sg:phone":"+1 901 332 6221",
    "sg:postcode":"38116",
    "sg:province":"TN",
    "wof:name":"Israel Of God",
    "wof:placetype":"venue"
},
  "geometry": {"coordinates":[-90.028705,35.014516],"type":"Point"}
}