{
  "type": "Feature",
  "properties": {
    "iso:country":"US",
    "sg:address":"945 Barnes Rd",
    "sg:city":"Antioch",
    "sg:classifiers":[
        {
            "category":"Shopping",
            "type":"Retail Goods"
        }
    ],
    "sg:phone":"+1 615 533 1933",
    "sg:postcode":"37013",
    "sg:province":"TN",
    "sg:tags":[
        "merchandise"
    ],
    "sg:website":"www.accessandmobilityonline.com",
    "wof:name":"Access & Mobility",
    "wof:placetype":"venue"
},
  "geometry": {"coordinates":[-86.68056300000001,36.022632],"type":"Point"}
}