{
  "type": "Feature",
  "properties": {
    "iso:country":"US",
    "sg:address":"5151 Saundersville Rd",
    "sg:city":"Old Hickory",
    "sg:classifiers":[
        {
            "category":"Professional",
            "subcategory":"Management & Consulting",
            "type":"Services"
        }
    ],
    "sg:phone":"+1 615 758 8220",
    "sg:postcode":"37138",
    "sg:province":"TN",
    "wof:name":"Csl Enterprises",
    "wof:placetype":"venue"
},
  "geometry": {"coordinates":[-86.576896,36.241951],"type":"Point"}
}