{
  "type": "Feature",
  "properties": {
    "addr:full":"912 Kelley Rd Memphis TN 38111",
    "addr:housenumber":"912",
    "addr:postcode":"38111",
    "addr:street":"Kelley Rd",
    "iso:country":"US",
    "sg:address":"912 Kelley Rd",
    "sg:city":"Memphis",
    "sg:classifiers":[
        {
            "category":"Recreation",
            "type":"Entertainment"
        },
        {
            "category":"Organizations",
            "subcategory":"Professional Association",
            "type":"Services"
        }
    ],
    "sg:phone":"+1 901 324 3889",
    "sg:postcode":"38111",
    "sg:province":"TN",
    "sg:tags":[
        "club",
        "membership"
    ],
    "wof:name":"Lightman M A Bridge Club",
    "wof:placetype":"venue"
},
  "geometry": {"coordinates":[-89.934361,35.106359],"type":"Point"}
}