{
  "type": "Feature",
  "properties": {
    "addr:full":"9 Pennsylvania Ave Bristol TN 37620",
    "addr:housenumber":"9",
    "addr:postcode":"37620",
    "addr:street":"Pennsylvania Ave",
    "iso:country":"US",
    "sg:address":"9 Pennsylvania Ave",
    "sg:city":"Bristol",
    "sg:classifiers":[
        {
            "category":"Restaurant",
            "type":"Food & Drink"
        }
    ],
    "sg:phone":"+1 423 844 0014",
    "sg:postcode":"37620",
    "sg:province":"TN",
    "sg:tags":[
        "parlor",
        "ice",
        "cream"
    ],
    "wof:name":"State Street Sweets & Eats",
    "wof:placetype":"venue"
},
  "geometry": {"coordinates":[-82.17728,36.594719],"type":"Point"}
}