{
  "type": "Feature",
  "properties": {
    "addr:full":"2896 S Rutherford Blvd Murfreesboro TN 37130",
    "addr:housenumber":"2896",
    "addr:postcode":"37130",
    "addr:street":"S Rutherford Blvd",
    "iso:country":"US",
    "sg:address":"2896 S Rutherford Blvd",
    "sg:city":"Murfreesboro",
    "sg:classifiers":[
        {
            "category":"Restaurant",
            "type":"Food & Drink"
        }
    ],
    "sg:phone":"+1 615 895 7777",
    "sg:postcode":"37130",
    "sg:province":"TN",
    "wof:name":"Applebee's Neighborhood Grill",
    "wof:placetype":"venue"
},
  "geometry": {"coordinates":[-86.395394,35.819073],"type":"Point"}
}