{
  "type": "Feature",
  "properties": {
    "addr:full":"103 24th St Old Hickory TN 37138",
    "addr:housenumber":"103",
    "addr:postcode":"37138",
    "addr:street":"24Th St",
    "iso:country":"US",
    "sg:address":"103 24th St",
    "sg:city":"Old Hickory",
    "sg:classifiers":[
        {
            "category":"Organizations",
            "subcategory":"Religious Organization",
            "type":"Services"
        }
    ],
    "sg:phone":"+1 615 847 5551",
    "sg:postcode":"37138",
    "sg:province":"TN",
    "sg:tags":[
        "church"
    ],
    "wof:name":"Cumberland Baptist Church",
    "wof:placetype":"venue"
},
  "geometry": {"coordinates":[-86.640344,36.248378],"type":"Point"}
}