{
  "type": "Feature",
  "properties": {
    "iso:country":"US",
    "sg:address":"337 Hill Ave",
    "sg:city":"Nashville",
    "sg:classifiers":[
        {
            "category":"Wholesale",
            "subcategory":"Hardware",
            "type":"Manufacturing & Wholesale Goods"
        }
    ],
    "sg:phone":"+1 615 242 2456",
    "sg:postcode":"37210",
    "sg:province":"TN",
    "sg:tags":[
        "plumbing",
        "rep",
        "mfg"
    ],
    "wof:name":"Southern Marketing Group",
    "wof:placetype":"venue"
},
  "geometry": {"coordinates":[-86.729539,36.136195],"type":"Point"}
}