{
  "type": "Feature",
  "properties": {
    "iso:country":"US",
    "sg:address":"1562 Gabay St",
    "sg:city":"Memphis",
    "sg:classifiers":[
        {
            "category":"Social Services",
            "subcategory":"Child Care",
            "type":"Services"
        }
    ],
    "sg:phone":"+1 901 774 9992",
    "sg:postcode":"38106",
    "sg:province":"TN",
    "sg:tags":[
        "day"
    ],
    "wof:name":"Kizzies Kottage",
    "wof:placetype":"venue"
},
  "geometry": {"coordinates":[-90.03971900000001,35.101906],"type":"Point"}
}