{
  "type": "Feature",
  "properties": {
    "iso:country":"US",
    "sg:address":"5803 Midland Rd",
    "sg:city":"Christiana",
    "sg:classifiers":[
        {
            "category":"Freight",
            "type":"Transportation"
        }
    ],
    "sg:phone":"+1 615 895 5948",
    "sg:postcode":"37037",
    "sg:province":"TN",
    "sg:tags":[
        "operator",
        "trucking"
    ],
    "wof:name":"Unkletrucks Inc",
    "wof:placetype":"venue"
},
  "geometry": {"coordinates":[-86.462847,35.721538],"type":"Point"}
}