{
  "type": "Feature",
  "properties": {
    "iso:country":"US",
    "sg:address":"4505 Summer Ave",
    "sg:city":"Memphis",
    "sg:classifiers":[
        {
            "category":"Home & Garden",
            "subcategory":"Building Materials",
            "type":"Retail Goods"
        }
    ],
    "sg:phone":"+1 901 682 7681",
    "sg:postcode":"38122",
    "sg:province":"TN",
    "sg:tags":[
        "paint"
    ],
    "wof:name":"Farrell-Calhoun Paint Inc",
    "wof:placetype":"venue"
},
  "geometry": {"coordinates":[-89.91078899999999,35.148702],"type":"Point"}
}