{
  "type": "Feature",
  "properties": {
    "iso:country":"US",
    "sg:address":"4227 Sparta Hwy",
    "sg:city":"Mc Minnville",
    "sg:classifiers":[
        {
            "category":"Wholesale",
            "subcategory":"Machinery & Supplies",
            "type":"Manufacturing & Wholesale Goods"
        }
    ],
    "sg:phone":"+1 931 668 7986",
    "sg:postcode":"37110",
    "sg:province":"TN",
    "wof:name":"Four Lane Feed & Equipment",
    "wof:placetype":"venue"
},
  "geometry": {"coordinates":[-85.71818399999999,35.715107],"type":"Point"}
}