{
  "type": "Feature",
  "properties": {
    "iso:country":"US",
    "sg:address":"30 Covington St",
    "sg:city":"Clarksville",
    "sg:classifiers":[
        {
            "category":"Real Estate",
            "subcategory":"Real Estate Agent",
            "type":"Services"
        }
    ],
    "sg:phone":"+1 931 648 9350",
    "sg:postcode":"37040",
    "sg:province":"TN",
    "wof:name":"Greentree Co",
    "wof:placetype":"venue"
},
  "geometry": {"coordinates":[-87.318881,36.56371],"type":"Point"}
}