{
  "type": "Feature",
  "properties": {
    "iso:country":"US",
    "sg:address":"113 E Broad St",
    "sg:city":"Livingston",
    "sg:classifiers":[
        {
            "category":"Recreation",
            "type":"Entertainment"
        }
    ],
    "sg:phone":"+1 931 823 2551",
    "sg:postcode":"38570",
    "sg:province":"TN",
    "wof:name":"Joe L Evins Community Center",
    "wof:placetype":"venue"
},
  "geometry": {"coordinates":[-85.32196,36.383933],"type":"Point"}
}