{
  "type": "Feature",
  "properties": {
    "iso:country":"US",
    "sg:address":"7013 Stanfort Ln",
    "sg:city":"Knoxville",
    "sg:classifiers":[
        {
            "category":"Professional",
            "subcategory":"Art Services",
            "type":"Services"
        }
    ],
    "sg:phone":"+1 865 947 3541",
    "sg:postcode":"37918",
    "sg:province":"TN",
    "sg:tags":[
        "graphic",
        "designer"
    ],
    "wof:name":"Graphic Productions",
    "wof:placetype":"venue"
},
  "geometry": {"coordinates":[-83.98971299999999,36.042948],"type":"Point"}
}