{
  "type": "Feature",
  "properties": {
    "addr:full":"10 S Jefferson St Winchester TN 37398",
    "addr:housenumber":"10",
    "addr:postcode":"37398",
    "addr:street":"S Jefferson St",
    "iso:country":"US",
    "sg:address":"10 S Jefferson St",
    "sg:city":"Winchester",
    "sg:classifiers":[
        {
            "category":"Professional",
            "subcategory":"Detective & Security Services",
            "type":"Services"
        }
    ],
    "sg:phone":"+1 931 967 1300",
    "sg:postcode":"37398",
    "sg:province":"TN",
    "sg:tags":[
        "agency"
    ],
    "wof:name":"A 1 Investigations",
    "wof:placetype":"venue"
},
  "geometry": {"coordinates":[-86.11239999999999,35.186282],"type":"Point"}
}