{
  "type": "Feature",
  "properties": {
    "iso:country":"US",
    "sg:address":"800 18th Ave S",
    "sg:city":"Nashville",
    "sg:classifiers":[
        {
            "category":"Professional",
            "subcategory":"Accounting & Tax Preparation",
            "type":"Services"
        }
    ],
    "sg:phone":"+1 615 320 5152",
    "sg:postcode":"37203",
    "sg:province":"TN",
    "sg:tags":[
        "accountant"
    ],
    "wof:name":"Cima Financial Management",
    "wof:placetype":"venue"
},
  "geometry": {"coordinates":[-86.794787,36.148631],"type":"Point"}
}