{
  "type": "Feature",
  "properties": {
    "iso:country":"US",
    "sg:address":"12610 Lexington St",
    "sg:city":"Huntingdon",
    "sg:classifiers":[
        {
            "category":"Building & Trades",
            "subcategory":"Construction",
            "type":"Services"
        }
    ],
    "sg:phone":"+1 731 986 9430",
    "sg:postcode":"38344",
    "sg:province":"TN",
    "sg:tags":[
        "general",
        "contractor"
    ],
    "wof:name":"Miller Contractors Inc",
    "wof:placetype":"venue"
},
  "geometry": {"coordinates":[-88.426225,35.998832],"type":"Point"}
}