{
  "type": "Feature",
  "properties": {
    "addr:full":"787 E Main St Hendersonville TN 37075",
    "addr:housenumber":"787",
    "addr:postcode":"37075",
    "addr:street":"E Main St",
    "iso:country":"US",
    "sg:address":"787 E Main St",
    "sg:city":"Hendersonville",
    "sg:classifiers":[
        {
            "category":"Building & Trades",
            "subcategory":"Construction",
            "type":"Services"
        }
    ],
    "sg:phone":"+1 615 824 2242",
    "sg:postcode":"37075",
    "sg:province":"TN",
    "sg:tags":[
        "roofing",
        "contractor"
    ],
    "wof:name":"Fairview Roofing",
    "wof:placetype":"venue"
},
  "geometry": {"coordinates":[-86.561032,36.327192],"type":"Point"}
}