{
  "type": "Feature",
  "properties": {
    "iso:country":"US",
    "sg:address":"1178A Glen Springs Rd",
    "sg:city":"Drummonds",
    "sg:classifiers":[
        {
            "category":"Insurance",
            "subcategory":"Hazard Insurance",
            "type":"Services"
        }
    ],
    "sg:phone":"+1 901 835 4513",
    "sg:postcode":"38023",
    "sg:province":"TN",
    "wof:name":"Sherry Bennard",
    "wof:placetype":"venue"
},
  "geometry": {"coordinates":[-89.891239,35.486301],"type":"Point"}
}