{
  "type": "Feature",
  "properties": {
    "addr:full":"1139 Brownlee Rd Memphis TN 38116",
    "addr:housenumber":"1139",
    "addr:postcode":"38116",
    "addr:street":"Brownlee Rd",
    "iso:country":"US",
    "sg:address":"1139 Brownlee Rd",
    "sg:city":"Memphis",
    "sg:classifiers":[
        {
            "category":"Personal",
            "subcategory":"Barber",
            "type":"Services"
        }
    ],
    "sg:phone":"+1 901 346 6591",
    "sg:postcode":"38116",
    "sg:province":"TN",
    "wof:name":"Midtown Barber Shop",
    "wof:placetype":"venue"
},
  "geometry": {"coordinates":[-90.03370200000001,35.032559],"type":"Point"}
}