{
  "type": "Feature",
  "properties": {
    "iso:country":"US",
    "sg:address":"3980 New Covington Pike",
    "sg:city":"Memphis",
    "sg:classifiers":[
        {
            "category":"Health Services",
            "subcategory":"Doctor",
            "type":"Services"
        }
    ],
    "sg:phone":"+1 901 382 2606",
    "sg:postcode":"38128",
    "sg:province":"TN",
    "sg:tags":[
        "physician",
        "surgeon"
    ],
    "wof:name":"Memphis Orthopaedic",
    "wof:placetype":"venue"
},
  "geometry": {"coordinates":[-89.894258,35.234108],"type":"Point"}
}