{
  "type": "Feature",
  "properties": {
    "iso:country":"US",
    "sg:address":"1641 Bartlett Rd",
    "sg:city":"Bartlett",
    "sg:classifiers":[
        {
            "category":"Wholesale",
            "subcategory":"Office Equipment",
            "type":"Manufacturing & Wholesale Goods"
        }
    ],
    "sg:phone":"+1 901 850 1195",
    "sg:postcode":"38134",
    "sg:province":"TN",
    "sg:tags":[
        "vault",
        "safe"
    ],
    "wof:name":"Heritage Safes",
    "wof:placetype":"venue"
},
  "geometry": {"coordinates":[-89.878997,35.167492],"type":"Point"}
}