{
  "type": "Feature",
  "properties": {
    "iso:country":"US",
    "sg:address":"306 Rogers Dr",
    "sg:city":"Manchester",
    "sg:classifiers":[
        {
            "category":"Wholesale",
            "subcategory":"Computers",
            "type":"Manufacturing & Wholesale Goods"
        }
    ],
    "sg:phone":"+1 931 728 3511",
    "sg:postcode":"37355",
    "sg:province":"TN",
    "wof:name":"Tom Jernigan",
    "wof:placetype":"venue"
},
  "geometry": {"coordinates":[-86.078999,35.452017],"type":"Point"}
}