{
  "type": "Feature",
  "properties": {
    "iso:country":"US",
    "sg:address":"670 N Germantown Pkwy",
    "sg:city":"Cordova",
    "sg:classifiers":[
        {
            "category":"Food & Beverages",
            "subcategory":"Liquor & Beverages",
            "type":"Retail Goods"
        }
    ],
    "sg:phone":"+1 901 753 4977",
    "sg:postcode":"38018",
    "sg:province":"TN",
    "sg:tags":[
        "alcoholic",
        "wine"
    ],
    "wof:name":"Trinity Wine & Liquors",
    "wof:placetype":"venue"
},
  "geometry": {"coordinates":[-89.79539,35.142587],"type":"Point"}
}