{
  "type": "Feature",
  "properties": {
    "addr:full":"1052 Brookfield Rd Memphis TN 38119",
    "addr:housenumber":"1052",
    "addr:postcode":"38119",
    "addr:street":"Brookfield Rd",
    "iso:country":"US",
    "sg:address":"1052 Brookfield Rd",
    "sg:city":"Memphis",
    "sg:classifiers":[
        {
            "category":"Professional",
            "subcategory":"Lawyer & Legal Services",
            "type":"Services"
        }
    ],
    "sg:phone":"+1 901 683 5993",
    "sg:postcode":"38119",
    "sg:province":"TN",
    "sg:tags":[
        "attorney"
    ],
    "wof:name":"Mathes Law Firm",
    "wof:placetype":"venue"
},
  "geometry": {"coordinates":[-89.873733,35.102294],"type":"Point"}
}