{
  "type": "Feature",
  "properties": {
    "iso:country":"US",
    "sg:address":"1800 Wayne Rd",
    "sg:city":"Savannah",
    "sg:classifiers":[
        {
            "category":"Building & Trades",
            "subcategory":"Equipment Rental",
            "type":"Services"
        }
    ],
    "sg:phone":"+1 731 925 8814",
    "sg:postcode":"38372",
    "sg:province":"TN",
    "sg:tags":[
        "leasing",
        "furniture"
    ],
    "sg:website":"www.rentway.com",
    "wof:name":"Rent Way",
    "wof:placetype":"venue"
},
  "geometry": {"coordinates":[-88.234133,35.227537],"type":"Point"}
}