{
  "type": "Feature",
  "properties": {
    "iso:country":"US",
    "sg:address":"200 Lincoln Ave",
    "sg:city":"Morristown",
    "sg:classifiers":[
        {
            "category":"Shopping",
            "subcategory":"Florist",
            "type":"Retail Goods"
        }
    ],
    "sg:phone":"+1 423 586 0946",
    "sg:postcode":"37813",
    "sg:province":"TN",
    "wof:name":"Flower's By Janice",
    "wof:placetype":"venue"
},
  "geometry": {"coordinates":[-83.285662,36.20327],"type":"Point"}
}