{
  "type": "Feature",
  "properties": {
    "addr:full":"2345 N Reed Hooker Rd Eads TN 38028",
    "addr:housenumber":"2345",
    "addr:postcode":"38028",
    "addr:street":"N Reed Hooker Rd",
    "iso:country":"US",
    "sg:address":"2345 N Reed Hooker Rd",
    "sg:city":"Eads",
    "sg:classifiers":[
        {
            "category":"Building & Trades",
            "subcategory":"Construction",
            "type":"Services"
        }
    ],
    "sg:phone":"+1 901 853 3449",
    "sg:postcode":"38028",
    "sg:province":"TN",
    "sg:tags":[
        "sewer"
    ],
    "wof:name":"Larry E Yancey Construction Co",
    "wof:placetype":"venue"
},
  "geometry": {"coordinates":[-89.68213799999999,35.190635],"type":"Point"}
}