{
  "type": "Feature",
  "properties": {
    "iso:country":"US",
    "sg:address":"3914 Saint Elmo Ave",
    "sg:city":"Chattanooga",
    "sg:classifiers":[
        {
            "category":"Organizations",
            "subcategory":"Professional Association",
            "type":"Services"
        }
    ],
    "sg:phone":"+1 423 822 1007",
    "sg:postcode":"37409",
    "sg:province":"TN",
    "wof:name":"National Christian Foundation",
    "wof:placetype":"venue"
},
  "geometry": {"coordinates":[-85.328366,35.010232],"type":"Point"}
}