{
  "type": "Feature",
  "properties": {
    "addr:full":"116 Broadway St Mt Pleasant TN 38474",
    "addr:housenumber":"116",
    "addr:postcode":"38474",
    "addr:street":"Broadway St",
    "iso:country":"US",
    "sg:address":"116 Broadway St",
    "sg:city":"Mt Pleasant",
    "sg:classifiers":[
        {
            "category":"Organizations",
            "subcategory":"Religious Organization",
            "type":"Services"
        }
    ],
    "sg:phone":"+1 931 379 3048",
    "sg:postcode":"38474",
    "sg:province":"TN",
    "sg:tags":[
        "church"
    ],
    "wof:name":"Mt Nebo Baptist Church",
    "wof:placetype":"venue"
},
  "geometry": {"coordinates":[-87.202994,35.534178],"type":"Point"}
}