{
  "type": "Feature",
  "properties": {
    "iso:country":"US",
    "sg:address":"1376 Squire Fox Rd",
    "sg:city":"Dandridge",
    "sg:classifiers":[
        {
            "category":"Building & Trades",
            "subcategory":"Construction",
            "type":"Services"
        }
    ],
    "sg:phone":"+1 865 397 3707",
    "sg:postcode":"37725",
    "sg:province":"TN",
    "sg:tags":[
        "excavating",
        "contractor"
    ],
    "wof:name":"Kings Excavating",
    "wof:placetype":"venue"
},
  "geometry": {"coordinates":[-83.46934400000001,36.007506],"type":"Point"}
}