{
  "type": "Feature",
  "properties": {
    "iso:country":"US",
    "sg:address":"222 S 3rd St",
    "sg:city":"Union City",
    "sg:classifiers":[
        {
            "category":"Manufacturing",
            "subcategory":"Tools & Machinery",
            "type":"Manufacturing & Wholesale Goods"
        }
    ],
    "sg:phone":"+1 731 885 5221",
    "sg:postcode":"38261",
    "sg:province":"TN",
    "wof:name":"Currey's Welding & Machine Shp",
    "wof:placetype":"venue"
},
  "geometry": {"coordinates":[-89.05897,36.42555],"type":"Point"}
}