{
  "type": "Feature",
  "properties": {
    "addr:full":"7350 Raleigh Lagrange Rd Cordova TN 38018",
    "addr:housenumber":"7350",
    "addr:postcode":"38018",
    "addr:street":"Raleigh Lagrange Rd",
    "iso:country":"US",
    "sg:address":"7350 Raleigh Lagrange Rd",
    "sg:city":"Cordova",
    "sg:classifiers":[
        {
            "category":"Organizations",
            "subcategory":"Religious Organization",
            "type":"Services"
        }
    ],
    "sg:phone":"+1 901 266 2626",
    "sg:postcode":"38018",
    "sg:province":"TN",
    "sg:tags":[
        "church"
    ],
    "sg:website":"www.neshobauu.org",
    "wof:name":"Neshoba Unitarian Unvrslst Chr",
    "wof:placetype":"venue"
},
  "geometry": {"coordinates":[-89.818378,35.148582],"type":"Point"}
}