{
  "type": "Feature",
  "properties": {
    "iso:country":"US",
    "sg:address":"2740 Florence Dr",
    "sg:city":"Pigeon Forge",
    "sg:classifiers":[
        {
            "category":"Travel",
            "subcategory":"Hotels & Motels",
            "type":"Entertainment"
        }
    ],
    "sg:phone":"+1 865 453 7640",
    "sg:postcode":"37863",
    "sg:province":"TN",
    "sg:tags":[
        "cottage",
        "cabin"
    ],
    "sg:website":"www.countryoaks.com",
    "wof:name":"Country Oaks Cottages",
    "wof:placetype":"venue"
},
  "geometry": {"coordinates":[-83.573397,35.800336],"type":"Point"}
}