{
  "type": "Feature",
  "properties": {
    "addr:full":"4005 Fountain Valley Dr Knoxville TN 37918",
    "addr:housenumber":"4005",
    "addr:postcode":"37918",
    "addr:street":"Fountain Valley Dr",
    "iso:country":"US",
    "sg:address":"4005 Fountain Valley Dr",
    "sg:city":"Knoxville",
    "sg:classifiers":[
        {
            "category":"Health Services",
            "subcategory":"Doctor",
            "type":"Services"
        }
    ],
    "sg:phone":"+1 865 925 9030",
    "sg:postcode":"37918",
    "sg:province":"TN",
    "sg:tags":[
        "dentist"
    ],
    "sg:website":"www.smileworks2.com",
    "wof:name":"Michael J Solly DDS",
    "wof:placetype":"venue"
},
  "geometry": {"coordinates":[-83.92558699999999,36.069531],"type":"Point"}
}