{
  "type": "Feature",
  "properties": {
    "addr:full":"3006 Gallatin Pike Nashville TN 37216",
    "addr:housenumber":"3006",
    "addr:postcode":"37216",
    "addr:street":"Gallatin Pike",
    "iso:country":"US",
    "sg:address":"3006 Gallatin Pike",
    "sg:city":"Nashville",
    "sg:classifiers":[
        {
            "category":"Shopping",
            "subcategory":"Discount & Variety Stores",
            "type":"Retail Goods"
        }
    ],
    "sg:phone":"+1 615 226 7711",
    "sg:postcode":"37216",
    "sg:province":"TN",
    "wof:name":"Dollar General",
    "wof:placetype":"venue"
},
  "geometry": {"coordinates":[-86.738606,36.20326],"type":"Point"}
}