{
  "type": "Feature",
  "properties": {
    "iso:country":"US",
    "sg:address":"694 Marshall Ave",
    "sg:city":"Memphis",
    "sg:classifiers":[
        {
            "category":"Retail",
            "subcategory":"Auto Repair",
            "type":"Services"
        },
        {
            "category":"Manufacturing",
            "subcategory":"Motor Vehicles & Parts",
            "type":"Manufacturing & Wholesale Goods"
        }
    ],
    "sg:phone":"+1 901 527 4605",
    "sg:postcode":"38103",
    "sg:province":"TN",
    "sg:tags":[
        "repairing",
        "radiator",
        "mfg",
        "automobile",
        "support",
        "automotive",
        "aviation",
        "ground"
    ],
    "wof:name":"Walker Radiator Works Inc",
    "wof:placetype":"venue"
},
  "geometry": {"coordinates":[-90.038573,35.139807],"type":"Point"}
}