{
  "type": "Feature",
  "properties": {
    "iso:country":"US",
    "sg:address":"3399 N Hawthorne St",
    "sg:city":"Chattanooga",
    "sg:classifiers":[
        {
            "category":"Manufacturing",
            "subcategory":"Printing",
            "type":"Manufacturing & Wholesale Goods"
        }
    ],
    "sg:phone":"+1 423 698 8653",
    "sg:postcode":"37406",
    "sg:province":"TN",
    "sg:tags":[
        "commercial"
    ],
    "wof:name":"Murray Printing & Office Supl",
    "wof:placetype":"venue"
},
  "geometry": {"coordinates":[-85.25241800000001,35.078319],"type":"Point"}
}