{
  "type": "Feature",
  "properties": {
    "addr:full":"1201 8th Ave S Nashville TN 37204",
    "addr:housenumber":"1201",
    "addr:postcode":"37204",
    "addr:street":"8Th Ave S",
    "iso:country":"US",
    "sg:address":"1201 8th Ave S",
    "sg:city":"Nashville",
    "sg:classifiers":[
        {
            "category":"Professional",
            "subcategory":"Management & Consulting",
            "type":"Services"
        }
    ],
    "sg:phone":"+1 615 320 3149",
    "sg:postcode":"37204",
    "sg:province":"TN",
    "sg:tags":[
        "consultant",
        "educational"
    ],
    "sg:website":"www.scholarshipadministrators.net",
    "wof:name":"Scholarship Program Admin Inc",
    "wof:placetype":"venue"
},
  "geometry": {"coordinates":[-86.77861300000001,36.141113],"type":"Point"}
}