{
  "type": "Feature",
  "properties": {
    "addr:full":"1066 Esplanade Pl Memphis TN 38106",
    "addr:housenumber":"1066",
    "addr:postcode":"38106",
    "addr:street":"Esplanade Pl",
    "iso:country":"US",
    "sg:address":"1066 Esplanade Pl",
    "sg:city":"Memphis",
    "sg:classifiers":[
        {
            "category":"Building & Trades",
            "subcategory":"Cleaning & Sanitation",
            "type":"Services"
        }
    ],
    "sg:phone":"+1 901 725 5261",
    "sg:postcode":"38106",
    "sg:province":"TN",
    "sg:tags":[
        "maintenance"
    ],
    "wof:name":"Saulsberry Janitorial Inc",
    "wof:placetype":"venue"
},
  "geometry": {"coordinates":[-90.070474,35.12152],"type":"Point"}
}