{
  "type": "Feature",
  "properties": {
    "iso:country":"US",
    "sg:address":"1214 Church St",
    "sg:city":"Nashville",
    "sg:classifiers":[
        {
            "category":"Banks & Credit Unions",
            "subcategory":"Bank",
            "type":"Services"
        }
    ],
    "sg:phone":"+1 615 747 3801",
    "sg:postcode":"37203",
    "sg:province":"TN",
    "sg:website":"www.escu.com",
    "wof:name":"Electric Service Credit Union",
    "wof:placetype":"venue"
},
  "geometry": {"coordinates":[-86.789513,36.158968],"type":"Point"}
}