{
  "type": "Feature",
  "properties": {
    "addr:full":"5900 Ringgold Rd Chattanooga TN 37412",
    "addr:housenumber":"5900",
    "addr:postcode":"37412",
    "addr:street":"Ringgold Rd",
    "iso:country":"US",
    "sg:address":"5900 Ringgold Rd",
    "sg:city":"Chattanooga",
    "sg:classifiers":[
        {
            "category":"Retail",
            "subcategory":"Auto Rental",
            "type":"Services"
        },
        {
            "category":"Building & Trades",
            "subcategory":"Equipment Rental",
            "type":"Services"
        },
        {
            "category":"Retail",
            "subcategory":"Storage",
            "type":"Services"
        }
    ],
    "sg:phone":"+1 423 899 3655",
    "sg:postcode":"37412",
    "sg:province":"TN",
    "sg:tags":[
        "renting",
        "moving-self",
        "leasing",
        "moving",
        "truck",
        "trailer"
    ],
    "sg:website":"http://www.pensketruckrental.com/",
    "wof:name":"Penske Truck Rental",
    "wof:placetype":"venue"
},
  "geometry": {"coordinates":[-85.21779600000001,34.990269],"type":"Point"}
}