{
  "type": "Feature",
  "properties": {
    "addr:full":"1727 Florida St Memphis TN 38109",
    "addr:housenumber":"1727",
    "addr:postcode":"38109",
    "addr:street":"Florida St",
    "iso:country":"US",
    "sg:address":"1727 Florida St",
    "sg:city":"Memphis",
    "sg:classifiers":[
        {
            "category":"Freight",
            "type":"Transportation"
        }
    ],
    "sg:phone":"+1 901 775 0809",
    "sg:postcode":"38109",
    "sg:province":"TN",
    "sg:tags":[
        "trucking"
    ],
    "wof:name":"Peacock Enterprises",
    "wof:placetype":"venue"
},
  "geometry": {"coordinates":[-90.062758,35.099198],"type":"Point"}
}