{
  "type": "Feature",
  "properties": {
    "addr:full":"200 W 19th St Chattanooga TN 37408",
    "addr:housenumber":"200",
    "addr:postcode":"37408",
    "addr:street":"W 19Th St",
    "iso:country":"US",
    "sg:address":"200 W 19th St",
    "sg:city":"Chattanooga",
    "sg:classifiers":[
        {
            "category":"Organizations",
            "subcategory":"Religious Organization",
            "type":"Services"
        }
    ],
    "sg:phone":"+1 423 265 8235",
    "sg:postcode":"37408",
    "sg:province":"TN",
    "sg:tags":[
        "church"
    ],
    "wof:name":"Church Of The Lord Jesus",
    "wof:placetype":"venue"
},
  "geometry": {"coordinates":[-85.31209,35.03388],"type":"Point"}
}