{
  "type": "Feature",
  "properties": {
    "iso:country":"US",
    "sg:address":"1988 Browns Mill Rd",
    "sg:city":"Cookeville",
    "sg:classifiers":[
        {
            "category":"Food & Beverages",
            "subcategory":"Bakery",
            "type":"Retail Goods"
        }
    ],
    "sg:phone":"+1 931 520 0388",
    "sg:postcode":"38506",
    "sg:province":"TN",
    "sg:tags":[
        "baker"
    ],
    "wof:name":"Kearns Earthgrain Baking Co",
    "wof:placetype":"venue"
},
  "geometry": {"coordinates":[-85.47342,36.123613],"type":"Point"}
}