{
  "type": "Feature",
  "properties": {
    "addr:full":"1674 Old Mill Rd Germantown TN 38138",
    "addr:housenumber":"1674",
    "addr:postcode":"38138",
    "addr:street":"Old Mill Rd",
    "iso:country":"US",
    "sg:address":"1674 Old Mill Rd",
    "sg:city":"Germantown",
    "sg:classifiers":[
        {
            "category":"Professional",
            "subcategory":"Employment Agencies",
            "type":"Services"
        }
    ],
    "sg:phone":"+1 901 751 3811",
    "sg:postcode":"38138",
    "sg:province":"TN",
    "wof:name":"Adstaff LLC",
    "wof:placetype":"venue"
},
  "geometry": {"coordinates":[-89.81214,35.104098],"type":"Point"}
}