{
  "type": "Feature",
  "properties": {
    "iso:country":"US",
    "sg:address":"508 National Ave",
    "sg:city":"Chattanooga",
    "sg:classifiers":[
        {
            "category":"Banks & Credit Unions",
            "subcategory":"Bank",
            "type":"Services"
        }
    ],
    "sg:phone":"+1 423 629 2578",
    "sg:postcode":"37404",
    "sg:province":"TN",
    "sg:website":"www.southerncu.com",
    "wof:name":"Southern Credit Union",
    "wof:placetype":"venue"
},
  "geometry": {"coordinates":[-85.28556500000001,35.038904],"type":"Point"}
}