{
  "type": "Feature",
  "properties": {
    "iso:country":"US",
    "sg:address":"99 Old Hickory Blvd",
    "sg:city":"Jackson",
    "sg:classifiers":[
        {
            "category":"Restaurant",
            "type":"Food & Drink"
        }
    ],
    "sg:menulink":"http://www.allmenus.com/tn/jackson/65597-cicis-pizza-buffet/menu/",
    "sg:phone":"+1 731 668 3333",
    "sg:postcode":"38305",
    "sg:province":"TN",
    "sg:tags":[
        "american",
        "pizza"
    ],
    "wof:name":"CiCi's Pizza Buffet",
    "wof:placetype":"venue"
},
  "geometry": {"coordinates":[-88.828202,35.654675],"type":"Point"}
}