{
  "type": "Feature",
  "properties": {
    "addr:full":"2525 W End Ave Nashville TN 37203",
    "addr:housenumber":"2525",
    "addr:postcode":"37203",
    "addr:street":"W End Ave",
    "iso:country":"US",
    "sg:address":"2525 W End Ave",
    "sg:city":"Nashville",
    "sg:classifiers":[
        {
            "category":"Coffee & Tea",
            "type":"Food & Drink"
        }
    ],
    "sg:menulink":"http://www.allmenus.com/tn/nashville/115237-starbucks-coffee/menu/",
    "sg:phone":"+1 615 341 0093",
    "sg:postcode":"37203",
    "sg:province":"TN",
    "sg:tags":[
        "american"
    ],
    "wof:name":"Starbucks Coffee",
    "wof:placetype":"venue"
},
  "geometry": {"coordinates":[-86.80846,36.145778],"type":"Point"}
}