{
  "type": "Feature",
  "properties": {
    "addr:full":"101 Frazier Ave Chattanooga TN 37411",
    "addr:housenumber":"101",
    "addr:postcode":"37411",
    "addr:street":"Frazier Ave",
    "iso:country":"US",
    "sg:address":"101 Frazier Ave",
    "sg:city":"Chattanooga",
    "sg:classifiers":[
        {
            "category":"Shopping",
            "type":"Retail Goods"
        }
    ],
    "sg:phone":"+1 423 267 0100",
    "sg:postcode":"37411",
    "sg:province":"TN",
    "sg:tags":[
        "picture",
        "frame"
    ],
    "wof:name":"Fireworks",
    "wof:placetype":"venue"
},
  "geometry": {"coordinates":[-85.30662599999999,35.062388],"type":"Point"}
}