{
  "type": "Feature",
  "properties": {
    "addr:full":"4001 Memorial Blvd Kingsport TN 37664",
    "addr:housenumber":"4001",
    "addr:postcode":"37664",
    "addr:street":"Memorial Blvd",
    "iso:country":"US",
    "sg:address":"4001 Memorial Blvd",
    "sg:city":"Kingsport",
    "sg:classifiers":[
        {
            "category":"Food & Beverages",
            "subcategory":"Groceries & Convenience Stores",
            "type":"Retail Goods"
        }
    ],
    "sg:phone":"+1 423 246 6746",
    "sg:postcode":"37664",
    "sg:province":"TN",
    "wof:name":"Sunoco",
    "wof:placetype":"venue"
},
  "geometry": {"coordinates":[-82.494293,36.531234],"type":"Point"}
}