{
  "type": "Feature",
  "properties": {
    "iso:country":"US",
    "sg:address":"468 Ellis Ave",
    "sg:city":"Maryville",
    "sg:classifiers":[
        {
            "category":"Personal",
            "subcategory":"Beauty Salon",
            "type":"Services"
        }
    ],
    "sg:phone":"+1 865 981 8859",
    "sg:postcode":"37804",
    "sg:province":"TN",
    "sg:tags":[
        "shop"
    ],
    "wof:name":"Irenes Creative Styles",
    "wof:placetype":"venue"
},
  "geometry": {"coordinates":[-83.966403,35.757136],"type":"Point"}
}