{
  "type": "Feature",
  "properties": {
    "iso:country":"US",
    "sg:address":"801 E Watauga Ave",
    "sg:city":"Johnson City",
    "sg:classifiers":[
        {
            "category":"Health Services",
            "subcategory":"Chiropractor",
            "type":"Services"
        }
    ],
    "sg:phone":"+1 423 929 7951",
    "sg:postcode":"37601",
    "sg:province":"TN",
    "sg:tags":[
        "clinic",
        "chiropractic"
    ],
    "wof:name":"Jones Chiropractic Clinic",
    "wof:placetype":"venue"
},
  "geometry": {"coordinates":[-82.347326,36.329999],"type":"Point"}
}