{
  "type": "Feature",
  "properties": {
    "iso:country":"US",
    "sg:address":"308 Orchard Valley Dr",
    "sg:city":"Harriman",
    "sg:classifiers":[
        {
            "category":"Manufacturing",
            "subcategory":"Paper Products",
            "type":"Manufacturing & Wholesale Goods"
        }
    ],
    "sg:phone":"+1 865 435 6100",
    "sg:postcode":"37748",
    "sg:province":"TN",
    "sg:tags":[
        "thermal",
        "coating",
        "spray"
    ],
    "wof:name":"Tennessee Metallizing",
    "wof:placetype":"venue"
},
  "geometry": {"coordinates":[-84.418978,35.967828],"type":"Point"}
}