{
  "type": "Feature",
  "properties": {
    "addr:full":"6239 Airpark Dr Chattanooga TN 37421",
    "addr:housenumber":"6239",
    "addr:postcode":"37421",
    "addr:street":"Airpark Dr",
    "iso:country":"US",
    "sg:address":"6239 Airpark Dr",
    "sg:city":"Chattanooga",
    "sg:classifiers":[
        {
            "category":"Health Services",
            "subcategory":"Clinic",
            "type":"Services"
        },
        {
            "category":"Sports & Exercise",
            "subcategory":"Gym",
            "type":"Entertainment"
        }
    ],
    "sg:phone":"+1 423 499 2250",
    "sg:postcode":"37421",
    "sg:province":"TN",
    "sg:tags":[
        "personal",
        "trainer"
    ],
    "wof:name":"Chattanooga Fitness & Ntrtn",
    "wof:placetype":"venue"
},
  "geometry": {"coordinates":[-85.185468,35.03522],"type":"Point"}
}