{
  "type": "Feature",
  "properties": {
    "iso:country":"US",
    "sg:address":"5050 S National Dr",
    "sg:city":"Knoxville",
    "sg:classifiers":[
        {
            "category":"Manufacturing",
            "subcategory":"Motor Vehicles & Parts",
            "type":"Manufacturing & Wholesale Goods"
        }
    ],
    "sg:phone":"+1 865 546 5920",
    "sg:postcode":"37914",
    "sg:province":"TN",
    "sg:tags":[
        "automobile",
        "supply"
    ],
    "sg:website":"www.modine.com",
    "wof:name":"Modine Manufacturing Co",
    "wof:placetype":"venue"
},
  "geometry": {"coordinates":[-83.83696999999999,35.942117],"type":"Point"}
}