{
  "type": "Feature",
  "properties": {
    "iso:country":"US",
    "sg:address":"416 S Sycamore St",
    "sg:city":"Elizabethton",
    "sg:classifiers":[
        {
            "category":"Education",
            "subcategory":"School",
            "type":"Public Place"
        }
    ],
    "sg:phone":"+1 423 547 8314",
    "sg:postcode":"37643",
    "sg:province":"TN",
    "wof:name":"Carter County Transition Schol",
    "wof:placetype":"venue"
},
  "geometry": {"coordinates":[-82.211472,36.344124],"type":"Point"}
}