{
  "type": "Feature",
  "properties": {
    "iso:country":"US",
    "sg:address":"4646 Poplar Ave",
    "sg:city":"Memphis",
    "sg:classifiers":[
        {
            "category":"Insurance",
            "subcategory":"Insurance Agent",
            "type":"Services"
        },
        {
            "category":"Insurance",
            "subcategory":"Hazard Insurance",
            "type":"Services"
        },
        {
            "category":"Insurance",
            "subcategory":"Title Insurance",
            "type":"Services"
        },
        {
            "category":"Insurance",
            "subcategory":"Life Insurance",
            "type":"Services"
        }
    ],
    "sg:phone":"+1 901 761 2783",
    "sg:postcode":"38117",
    "sg:province":"TN",
    "sg:tags":[
        "business",
        "auto",
        "commercial",
        "homeowner",
        "motorcycle",
        "renter"
    ],
    "wof:name":"Allstate Insurance Company - Janice Blakely",
    "wof:placetype":"venue"
},
  "geometry": {"coordinates":[-89.907065,35.116248],"type":"Point"}
}