{
  "type": "Feature",
  "properties": {
    "iso:country":"US",
    "sg:address":"195 N Bank St",
    "sg:city":"Oneida",
    "sg:classifiers":[
        {
            "category":"Education",
            "subcategory":"School",
            "type":"Public Place"
        }
    ],
    "sg:phone":"+1 423 569 8912",
    "sg:postcode":"37841",
    "sg:province":"TN",
    "wof:name":"Oneida Superintendents Office",
    "wof:placetype":"venue"
},
  "geometry": {"coordinates":[-84.51088799999999,36.50407],"type":"Point"}
}