{
  "type": "Feature",
  "properties": {
    "iso:country":"US",
    "sg:address":"516 W Main St",
    "sg:city":"Lebanon",
    "sg:classifiers":[
        {
            "category":"Banks & Credit Unions",
            "subcategory":"Investment Brokerage",
            "type":"Services"
        }
    ],
    "sg:phone":"+1 615 444 0303",
    "sg:postcode":"37087",
    "sg:province":"TN",
    "sg:tags":[
        "security"
    ],
    "wof:name":"Hilliard Lyons",
    "wof:placetype":"venue"
},
  "geometry": {"coordinates":[-86.30257899999999,36.209161],"type":"Point"}
}