{
  "type": "Feature",
  "properties": {
    "iso:country":"US",
    "sg:address":"286 Hermitage Ave",
    "sg:city":"Nashville",
    "sg:classifiers":[
        {
            "category":"Building & Trades",
            "subcategory":"Cleaning & Sanitation",
            "type":"Services"
        },
        {
            "category":"Manufacturing",
            "subcategory":"Chemicals & Compounds",
            "type":"Manufacturing & Wholesale Goods"
        }
    ],
    "sg:phone":"+1 615 242 6258",
    "sg:postcode":"37210",
    "sg:province":"TN",
    "sg:tags":[
        "industrial",
        "mfg"
    ],
    "wof:name":"Hickory Solutions LLC",
    "wof:placetype":"venue"
},
  "geometry": {"coordinates":[-86.752135,36.153559],"type":"Point"}
}