{
  "type": "Feature",
  "properties": {
    "iso:country":"US",
    "sg:address":"221 Manufacturer Rd",
    "sg:city":"Pikeville",
    "sg:classifiers":[
        {
            "category":"Organizations",
            "subcategory":"Religious Organization",
            "type":"Services"
        }
    ],
    "sg:phone":"+1 423 447 2075",
    "sg:postcode":"37367",
    "sg:province":"TN",
    "sg:tags":[
        "church"
    ],
    "wof:name":"Wheeler Addition Church Of God",
    "wof:placetype":"venue"
},
  "geometry": {"coordinates":[-85.191419,35.621784],"type":"Point"}
}