{
  "type": "Feature",
  "properties": {
    "iso:country":"US",
    "sg:address":"316 N Maple St",
    "sg:city":"Murfreesboro",
    "sg:classifiers":[
        {
            "category":"Shopping",
            "subcategory":"Florist",
            "type":"Retail Goods"
        }
    ],
    "sg:phone":"+1 615 893 5764",
    "sg:postcode":"37130",
    "sg:province":"TN",
    "sg:tags":[
        "plant"
    ],
    "wof:name":"Hudson's Flower & Gift Shop",
    "wof:placetype":"venue"
},
  "geometry": {"coordinates":[-86.392133,35.849019],"type":"Point"}
}