{
  "type": "Feature",
  "properties": {
    "iso:country":"US",
    "sg:address":"4385 Getwell Rd",
    "sg:city":"Memphis",
    "sg:classifiers":[
        {
            "category":"Manufacturing",
            "subcategory":"Printing",
            "type":"Manufacturing & Wholesale Goods"
        }
    ],
    "sg:phone":"+1 901 363 7600",
    "sg:postcode":"38118",
    "sg:province":"TN",
    "sg:tags":[
        "print",
        "lithographic"
    ],
    "wof:name":"Minuteman Press",
    "wof:placetype":"venue"
},
  "geometry": {"coordinates":[-89.93707000000001,35.028841],"type":"Point"}
}