{
  "type": "Feature",
  "properties": {
    "iso:country":"US",
    "sg:address":"1501 Scottsville Rd",
    "sg:city":"Lafayette",
    "sg:classifiers":[
        {
            "category":"Personal",
            "subcategory":"Beauty Salon",
            "type":"Services"
        }
    ],
    "sg:phone":"+1 615 666 5051",
    "sg:postcode":"37083",
    "sg:province":"TN",
    "sg:tags":[
        "shop"
    ],
    "wof:name":"Johnna's Style Shop",
    "wof:placetype":"venue"
},
  "geometry": {"coordinates":[-86.035741,36.540644],"type":"Point"}
}