{
  "type": "Feature",
  "properties": {
    "iso:country":"US",
    "sg:address":"4296 US Hwy 51 N",
    "sg:city":"Memphis",
    "sg:classifiers":[
        {
            "category":"Retail",
            "subcategory":"Auto Repair",
            "type":"Services"
        }
    ],
    "sg:phone":"+1 901 358 6333",
    "sg:postcode":"38127",
    "sg:province":"TN",
    "sg:tags":[
        "wrecker"
    ],
    "wof:name":"Boyd's Wrecker Svc",
    "wof:placetype":"venue"
},
  "geometry": {"coordinates":[-90.008049,35.243121],"type":"Point"}
}