{
  "type": "Feature",
  "properties": {
    "iso:country":"US",
    "sg:address":"698 S Water Ave",
    "sg:city":"Gallatin",
    "sg:classifiers":[
        {
            "category":"Restaurant",
            "type":"Food & Drink"
        }
    ],
    "sg:phone":"+1 615 451 4800",
    "sg:postcode":"37066",
    "sg:province":"TN",
    "sg:tags":[
        "eating"
    ],
    "wof:name":"Golden China Buffet Restaurant",
    "wof:placetype":"venue"
},
  "geometry": {"coordinates":[-86.44233699999999,36.377773],"type":"Point"}
}