{
  "type": "Feature",
  "properties": {
    "iso:country":"US",
    "sg:address":"7156 State Hwy 100",
    "sg:city":"Nashville",
    "sg:classifiers":[
        {
            "category":"Restaurant",
            "type":"Food & Drink"
        }
    ],
    "sg:phone":"+1 615 353 6314",
    "sg:postcode":"37221",
    "sg:province":"TN",
    "sg:tags":[
        "eating"
    ],
    "wof:name":"Home Run Enterprise",
    "wof:placetype":"venue"
},
  "geometry": {"coordinates":[-86.904631,36.062322],"type":"Point"}
}