{
  "type": "Feature",
  "properties": {
    "iso:country":"US",
    "sg:address":"3732 Masonwood Ln",
    "sg:city":"Memphis",
    "sg:classifiers":[
        {
            "category":"Real Estate",
            "subcategory":"Real Estate Agent",
            "type":"Services"
        }
    ],
    "sg:phone":"+1 901 396 5623",
    "sg:postcode":"38116",
    "sg:province":"TN",
    "wof:name":"J & J Real Estate Investments",
    "wof:placetype":"venue"
},
  "geometry": {"coordinates":[-90.031424,35.045086],"type":"Point"}
}