{
  "type": "Feature",
  "properties": {
    "iso:country":"US",
    "sg:address":"4160 S 3rd St",
    "sg:city":"Memphis",
    "sg:classifiers":[
        {
            "category":"Wholesale",
            "subcategory":"Home Furnishings",
            "type":"Manufacturing & Wholesale Goods"
        },
        {
            "category":"Shopping",
            "subcategory":"Gifts & Souvenirs",
            "type":"Retail Goods"
        }
    ],
    "sg:phone":"+1 901 785 1009",
    "sg:postcode":"38109",
    "sg:province":"TN",
    "sg:tags":[
        "pottery"
    ],
    "wof:name":"Johnson's Imports",
    "wof:placetype":"venue"
},
  "geometry": {"coordinates":[-90.073407,35.035161],"type":"Point"}
}