{
  "type": "Feature",
  "properties": {
    "iso:country":"US",
    "sg:address":"6960 Parkbrook Ln",
    "sg:city":"Cordova",
    "sg:classifiers":[
        {
            "category":"Home & Garden",
            "subcategory":"Building Materials",
            "type":"Retail Goods"
        }
    ],
    "sg:phone":"+1 901 315 8275",
    "sg:postcode":"38018",
    "sg:province":"TN",
    "sg:tags":[
        "door"
    ],
    "wof:name":"Mannas Garage Doors",
    "wof:placetype":"venue"
},
  "geometry": {"coordinates":[-89.831191,35.150747],"type":"Point"}
}