{
  "type": "Feature",
  "properties": {
    "iso:country":"US",
    "sg:address":"113 Goodson Ave",
    "sg:city":"Chattanooga",
    "sg:classifiers":[
        {
            "category":"Professional",
            "type":"Services"
        }
    ],
    "sg:phone":"+1 423 870 3159",
    "sg:postcode":"37405",
    "sg:province":"TN",
    "sg:tags":[
        "establishment"
    ],
    "wof:name":"Adawn's",
    "wof:placetype":"venue"
},
  "geometry": {"coordinates":[-85.316546,35.089359],"type":"Point"}
}