{
  "type": "Feature",
  "properties": {
    "iso:country":"US",
    "sg:address":"5410 Maryland Way Suite 300",
    "sg:city":"Brentwood",
    "sg:classifiers":[
        {
            "category":"Professional",
            "subcategory":"Research",
            "type":"Services"
        }
    ],
    "sg:phone":"+1 888 646 7763",
    "sg:postcode":"37027",
    "sg:province":"TN",
    "sg:website":"http://www.cogenthealthcare.com",
    "wof:name":"Cogent Healthcare",
    "wof:placetype":"venue"
},
  "geometry": {"coordinates":[-86.81491,36.036722],"type":"Point"}
}