{
  "type": "Feature",
  "properties": {
    "iso:country":"US",
    "sg:address":"1249 Ashwood Dr",
    "sg:city":"Jefferson City",
    "sg:classifiers":[
        {
            "category":"Professional",
            "subcategory":"Lawyer & Legal Services",
            "type":"Services"
        }
    ],
    "sg:phone":"+1 865 475 8348",
    "sg:postcode":"37760",
    "sg:province":"TN",
    "wof:name":"Wall Tom O Attorney At Law",
    "wof:placetype":"venue"
},
  "geometry": {"coordinates":[-83.516575,36.128046],"type":"Point"}
}