{
  "type": "Feature",
  "properties": {
    "iso:country":"US",
    "sg:address":"1635 Ramsay St",
    "sg:city":"Alcoa",
    "sg:classifiers":[
        {
            "category":"Professional",
            "subcategory":"Business Services",
            "type":"Services"
        }
    ],
    "sg:phone":"+1 865 681 0825",
    "sg:postcode":"37701",
    "sg:province":"TN",
    "wof:name":"Noah Artist Agency",
    "wof:placetype":"venue"
},
  "geometry": {"coordinates":[-83.98284099999999,35.797126],"type":"Point"}
}