{
  "type": "Feature",
  "properties": {
    "iso:country":"US",
    "sg:address":"416 Erin Dr",
    "sg:city":"Knoxville",
    "sg:classifiers":[
        {
            "category":"Wholesale",
            "subcategory":"Hardware",
            "type":"Manufacturing & Wholesale Goods"
        }
    ],
    "sg:phone":"+1 865 588 5703",
    "sg:postcode":"37919",
    "sg:province":"TN",
    "sg:tags":[
        "beverage",
        "dispensing"
    ],
    "wof:name":"Industrial Vendors Inc",
    "wof:placetype":"venue"
},
  "geometry": {"coordinates":[-84.00052700000001,35.92789],"type":"Point"}
}