{
  "type": "Feature",
  "properties": {
    "iso:country":"US",
    "sg:address":"3150 Lenox Park Blvd",
    "sg:city":"Memphis",
    "sg:classifiers":[
        {
            "category":"Professional",
            "subcategory":"Management & Consulting",
            "type":"Services"
        }
    ],
    "sg:phone":"+1 901 273 2575",
    "sg:postcode":"38115",
    "sg:province":"TN",
    "sg:tags":[
        "communications",
        "consultant"
    ],
    "wof:name":"Magowan Communications Group",
    "wof:placetype":"venue"
},
  "geometry": {"coordinates":[-89.841854,35.062604],"type":"Point"}
}