{
  "type": "Feature",
  "properties": {
    "iso:country":"US",
    "sg:address":"204 Chaffin Pl",
    "sg:city":"Murfreesboro",
    "sg:classifiers":[
        {
            "category":"Shopping",
            "subcategory":"Used Merchandise",
            "type":"Retail Goods"
        }
    ],
    "sg:phone":"+1 615 907 6066",
    "sg:postcode":"37129",
    "sg:province":"TN",
    "sg:tags":[
        "antique"
    ],
    "wof:name":"Hylabrook Antique Mall",
    "wof:placetype":"venue"
},
  "geometry": {"coordinates":[-86.429883,35.843991],"type":"Point"}
}