{
  "type": "Feature",
  "properties": {
    "addr:full":"7517 Callis Creek Dr Memphis TN 38119",
    "addr:housenumber":"7517",
    "addr:postcode":"38119",
    "addr:street":"Callis Creek Dr",
    "iso:country":"US",
    "sg:address":"7517 Callis Creek Dr",
    "sg:city":"Memphis",
    "sg:classifiers":[
        {
            "category":"Professional",
            "type":"Services"
        }
    ],
    "sg:phone":"+1 901 309 5926",
    "sg:postcode":"38119",
    "sg:province":"TN",
    "sg:tags":[
        "establishment"
    ],
    "wof:name":"Marie Lynn Group Inc",
    "wof:placetype":"venue"
},
  "geometry": {"coordinates":[-89.812045,35.061671],"type":"Point"}
}