{
  "type": "Feature",
  "properties": {
    "iso:country":"US",
    "sg:address":"6421 Kingsport Hwy",
    "sg:city":"Johnson City",
    "sg:classifiers":[
        {
            "category":"Professional",
            "type":"Services"
        }
    ],
    "sg:phone":"+1 423 477 7886",
    "sg:postcode":"37615",
    "sg:province":"TN",
    "wof:name":"Mike Moran",
    "wof:placetype":"venue"
},
  "geometry": {"coordinates":[-82.449991,36.437829],"type":"Point"}
}