{
  "type": "Feature",
  "properties": {
    "iso:country":"US",
    "sg:address":"37 Industrial Park Dr",
    "sg:city":"Hendersonville",
    "sg:classifiers":[
        {
            "category":"Manufacturing",
            "subcategory":"Tools & Machinery",
            "type":"Manufacturing & Wholesale Goods"
        }
    ],
    "sg:phone":"+1 615 822 1935",
    "sg:postcode":"37075",
    "sg:province":"TN",
    "sg:tags":[
        "mold",
        "special"
    ],
    "wof:name":"Micro Precision Inc",
    "wof:placetype":"venue"
},
  "geometry": {"coordinates":[-86.63516199999999,36.308233],"type":"Point"}
}