{
  "type": "Feature",
  "properties": {
    "iso:country":"US",
    "sg:address":"6002 Knight Arnold Rd Exd",
    "sg:city":"Memphis",
    "sg:classifiers":[
        {
            "category":"Banks & Credit Unions",
            "subcategory":"Bank",
            "type":"Services"
        }
    ],
    "sg:phone":"+1 901 797 8447",
    "sg:postcode":"38115",
    "sg:province":"TN",
    "sg:tags":[
        "loan",
        "mortgage",
        "real estate"
    ],
    "wof:name":"Lifetime Funding Company",
    "wof:placetype":"venue"
},
  "geometry": {"coordinates":[-89.86404899999999,35.060765],"type":"Point"}
}