{
  "type": "Feature",
  "properties": {
    "iso:country":"US",
    "sg:address":"609 Greenwood Dr",
    "sg:city":"Maryville",
    "sg:classifiers":[
        {
            "category":"Real Estate",
            "subcategory":"Surveying",
            "type":"Services"
        }
    ],
    "sg:phone":"+1 865 984 2684",
    "sg:postcode":"37803",
    "sg:province":"TN",
    "sg:tags":[
        "surveyor",
        "land"
    ],
    "wof:name":"Mc Clanahan Sony",
    "wof:placetype":"venue"
},
  "geometry": {"coordinates":[-84.013412,35.702706],"type":"Point"}
}