{
  "type": "Feature",
  "properties": {
    "iso:country":"US",
    "sg:address":"501 Great Circle Rd",
    "sg:city":"Nashville",
    "sg:classifiers":[
        {
            "category":"Professional",
            "subcategory":"Lawyer & Legal Services",
            "type":"Services"
        }
    ],
    "sg:phone":"+1 615 259 4535",
    "sg:postcode":"37228",
    "sg:province":"TN",
    "sg:tags":[
        "attorney"
    ],
    "wof:name":"Vaughan & Maxwell",
    "wof:placetype":"venue"
},
  "geometry": {"coordinates":[-86.804232,36.199001],"type":"Point"}
}