{
  "type": "Feature",
  "properties": {
    "addr:full":"1835 Buffalo Trl Morristown TN 37814",
    "addr:housenumber":"1835",
    "addr:postcode":"37814",
    "addr:street":"Buffalo Trl",
    "iso:country":"US",
    "sg:address":"1835 Buffalo Trl",
    "sg:city":"Morristown",
    "sg:classifiers":[
        {
            "category":"Health Services",
            "subcategory":"Clinic",
            "type":"Services"
        }
    ],
    "sg:phone":"+1 423 587 8771",
    "sg:postcode":"37814",
    "sg:province":"TN",
    "sg:tags":[
        "home"
    ],
    "wof:name":"Premier Support Svc Inc",
    "wof:placetype":"venue"
},
  "geometry": {"coordinates":[-83.284848,36.234704],"type":"Point"}
}