{
  "type": "Feature",
  "properties": {
    "iso:country":"US",
    "sg:address":"150 W Church Ave",
    "sg:city":"Maryville",
    "sg:classifiers":[
        {
            "category":"Restaurant",
            "type":"Food & Drink"
        }
    ],
    "sg:phone":"+1 865 379 5700",
    "sg:postcode":"37801",
    "sg:province":"TN",
    "sg:website":"www.rubytuesday.com",
    "wof:name":"Ruby Tuesday Inc",
    "wof:placetype":"venue"
},
  "geometry": {"coordinates":[-83.97097100000001,35.755134],"type":"Point"}
}