{
  "type": "Feature",
  "properties": {
    "iso:country":"US",
    "sg:address":"1819 Wilson Pkwy",
    "sg:city":"Fayetteville",
    "sg:classifiers":[
        {
            "category":"Freight",
            "type":"Transportation"
        }
    ],
    "sg:phone":"+1 931 993 9446",
    "sg:postcode":"37334",
    "sg:province":"TN",
    "sg:tags":[
        "commercial",
        "storage"
    ],
    "wof:name":"Park View Storage",
    "wof:placetype":"venue"
},
  "geometry": {"coordinates":[-86.580986,35.142148],"type":"Point"}
}