{
  "type": "Feature",
  "properties": {
    "iso:country":"US",
    "sg:address":"7105 Peach Ct",
    "sg:city":"Brentwood",
    "sg:classifiers":[
        {
            "category":"Wholesale",
            "subcategory":"Machinery & Supplies",
            "type":"Manufacturing & Wholesale Goods"
        }
    ],
    "sg:phone":"+1 615 376 8889",
    "sg:postcode":"37027",
    "sg:province":"TN",
    "sg:tags":[
        "carpet",
        "cleaning",
        "rug"
    ],
    "wof:name":"Eco Tech LLC",
    "wof:placetype":"venue"
},
  "geometry": {"coordinates":[-86.784986,36.027215],"type":"Point"}
}