{
  "type": "Feature",
  "properties": {
    "iso:country":"US",
    "sg:address":"80 Pete Sain Rd",
    "sg:city":"Manchester",
    "sg:classifiers":[
        {
            "category":"Autos & Motor Vehicles",
            "subcategory":"Auto Supplies",
            "type":"Retail Goods"
        }
    ],
    "sg:phone":"+1 931 723 7773",
    "sg:postcode":"37355",
    "sg:province":"TN",
    "wof:name":"J Tech LLC",
    "wof:placetype":"venue"
},
  "geometry": {"coordinates":[-85.999554,35.54954],"type":"Point"}
}