{
  "type": "Feature",
  "properties": {
    "iso:country":"US",
    "sg:address":"8104 Ainsworth Dr NW",
    "sg:city":"Knoxville",
    "sg:classifiers":[
        {
            "category":"Manufacturing",
            "subcategory":"Metals",
            "type":"Manufacturing & Wholesale Goods"
        }
    ],
    "sg:phone":"+1 865 531 9482",
    "sg:postcode":"37909",
    "sg:province":"TN",
    "sg:tags":[
        "steel",
        "mfg",
        "structural"
    ],
    "wof:name":"Allied Steel Corporation",
    "wof:placetype":"venue"
},
  "geometry": {"coordinates":[-84.052468,35.934326],"type":"Point"}
}