{
  "type": "Feature",
  "properties": {
    "iso:country":"US",
    "sg:address":"728 Daugherty Rd",
    "sg:city":"Oliver Springs",
    "sg:classifiers":[
        {
            "category":"Building & Trades",
            "subcategory":"Landscaping Services",
            "type":"Services"
        }
    ],
    "sg:phone":"+1 865 435 4452",
    "sg:postcode":"37840",
    "sg:province":"TN",
    "wof:name":"Yes Dear Lawn & Home Maint Co",
    "wof:placetype":"venue"
},
  "geometry": {"coordinates":[-84.358462,36.039893],"type":"Point"}
}