{
  "type": "Feature",
  "properties": {
    "iso:country":"US",
    "sg:address":"2741 Frayser Blvd",
    "sg:city":"Memphis",
    "sg:classifiers":[
        {
            "category":"Organizations",
            "subcategory":"Religious Organization",
            "type":"Services"
        }
    ],
    "sg:phone":"+1 901 357 5560",
    "sg:postcode":"38127",
    "sg:province":"TN",
    "wof:name":"Range Hills Baptist Church",
    "wof:placetype":"venue"
},
  "geometry": {"coordinates":[-89.970146,35.221237],"type":"Point"}
}