{
  "type": "Feature",
  "properties": {
    "iso:country":"US",
    "sg:address":"201 Ledford Mill Rd",
    "sg:city":"Tullahoma",
    "sg:classifiers":[
        {
            "category":"Professional",
            "type":"Services"
        }
    ],
    "sg:phone":"+1 931 393 0567",
    "sg:postcode":"37388",
    "sg:province":"TN",
    "sg:tags":[
        "establishment"
    ],
    "wof:name":"Clyde Carter & Sons",
    "wof:placetype":"venue"
},
  "geometry": {"coordinates":[-86.246798,35.387297],"type":"Point"}
}