{
  "type": "Feature",
  "properties": {
    "iso:country":"US",
    "sg:address":"7052 E Lamar Alexander Pkwy",
    "sg:city":"Townsend",
    "sg:classifiers":[
        {
            "category":"Travel",
            "subcategory":"Hotels & Motels",
            "type":"Entertainment"
        }
    ],
    "sg:phone":"+1 865 448 6639",
    "sg:postcode":"37882",
    "sg:province":"TN",
    "wof:name":"Big Valley Motel",
    "wof:placetype":"venue"
},
  "geometry": {"coordinates":[-83.789287,35.682173],"type":"Point"}
}