{
  "type": "Feature",
  "properties": {
    "iso:country":"US",
    "sg:address":"3630 Trousdale Dr",
    "sg:city":"Nashville",
    "sg:classifiers":[
        {
            "category":"Building & Trades",
            "subcategory":"Construction",
            "type":"Services"
        }
    ],
    "sg:phone":"+1 615 292 0004",
    "sg:postcode":"37204",
    "sg:province":"TN",
    "sg:tags":[
        "house",
        "remodeling",
        "general"
    ],
    "wof:name":"Mkf Construction",
    "wof:placetype":"venue"
},
  "geometry": {"coordinates":[-86.749454,36.095558],"type":"Point"}
}