{
  "type": "Feature",
  "properties": {
    "iso:country":"US",
    "sg:address":"112 Indian Ln",
    "sg:city":"Harriman",
    "sg:classifiers":[
        {
            "category":"Building & Trades",
            "subcategory":"Landscaping Services",
            "type":"Services"
        }
    ],
    "sg:phone":"+1 865 882 8263",
    "sg:postcode":"37748",
    "sg:province":"TN",
    "wof:name":"Timber Jacks",
    "wof:placetype":"venue"
},
  "geometry": {"coordinates":[-84.596349,35.911288],"type":"Point"}
}