{
  "type": "Feature",
  "properties": {
    "addr:full":"409 Sunset Ct Hermitage TN 37076",
    "addr:housenumber":"409",
    "addr:postcode":"37076",
    "addr:street":"Sunset Ct",
    "iso:country":"US",
    "sg:address":"409 Sunset Ct",
    "sg:city":"Hermitage",
    "sg:classifiers":[
        {
            "category":"Professional",
            "subcategory":"Art Services",
            "type":"Services"
        }
    ],
    "sg:phone":"+1 615 874 9933",
    "sg:postcode":"37076",
    "sg:province":"TN",
    "sg:tags":[
        "agent",
        "artist"
    ],
    "wof:name":"Maxwell Productions",
    "wof:placetype":"venue"
},
  "geometry": {"coordinates":[-86.591887,36.191147],"type":"Point"}
}