{
  "type": "Feature",
  "properties": {
    "iso:country":"US",
    "sg:address":"5935 Knight Arnold Rd Exd",
    "sg:city":"Memphis",
    "sg:classifiers":[
        {
            "category":"Autos & Motor Vehicles",
            "subcategory":"Fuel & Gas Station",
            "type":"Retail Goods"
        }
    ],
    "sg:phone":"+1 901 794 5944",
    "sg:postcode":"38115",
    "sg:province":"TN",
    "sg:tags":[
        "oil"
    ],
    "wof:name":"C J's Hickory Hills Amoco",
    "wof:placetype":"venue"
},
  "geometry": {"coordinates":[-89.86198,35.060542],"type":"Point"}
}