{
  "type": "Feature",
  "properties": {
    "iso:country":"US",
    "sg:address":"101 Noles St",
    "sg:city":"Decherd",
    "sg:classifiers":[
        {
            "category":"Banks & Credit Unions",
            "subcategory":"Bank",
            "type":"Services"
        }
    ],
    "sg:phone":"+1 931 962 1595",
    "sg:postcode":"37324",
    "sg:province":"TN",
    "sg:tags":[
        "cashing",
        "check"
    ],
    "wof:name":"Check Exchange",
    "wof:placetype":"venue"
},
  "geometry": {"coordinates":[-86.09384799999999,35.203504],"type":"Point"}
}