{
  "type": "Feature",
  "properties": {
    "addr:full":"108 Narrows Rd Shelbyville TN 37160",
    "addr:housenumber":"108",
    "addr:postcode":"37160",
    "addr:street":"Narrows Rd",
    "iso:country":"US",
    "sg:address":"108 Narrows Rd",
    "sg:city":"Shelbyville",
    "sg:classifiers":[
        {
            "category":"Organizations",
            "subcategory":"Religious Organization",
            "type":"Services"
        }
    ],
    "sg:phone":"+1 931 684 1805",
    "sg:postcode":"37160",
    "sg:province":"TN",
    "wof:name":"Southside Church Of Christ",
    "wof:placetype":"venue"
},
  "geometry": {"coordinates":[-86.469301,35.460886],"type":"Point"}
}