{
  "type": "Feature",
  "properties": {
    "iso:country":"US",
    "sg:address":"3081 Summer Ave",
    "sg:city":"Memphis",
    "sg:classifiers":[
        {
            "category":"Home & Garden",
            "subcategory":"Furniture",
            "type":"Retail Goods"
        }
    ],
    "sg:phone":"+1 901 452 8409",
    "sg:postcode":"38122",
    "sg:province":"TN",
    "wof:name":"Furniture For Less Inc",
    "wof:placetype":"venue"
},
  "geometry": {"coordinates":[-89.958679,35.149379],"type":"Point"}
}