{
  "type": "Feature",
  "properties": {
    "iso:country":"US",
    "sg:address":"617 Hudson Rd",
    "sg:city":"Chattanooga",
    "sg:classifiers":[
        {
            "category":"Utilities",
            "subcategory":"Refuse",
            "type":"Services"
        }
    ],
    "sg:phone":"+1 423 265 0132",
    "sg:postcode":"37405",
    "sg:province":"TN",
    "sg:tags":[
        "water",
        "industrial",
        "plant",
        "waste",
        "treatment"
    ],
    "wof:name":"AQUA Treat",
    "wof:placetype":"venue"
},
  "geometry": {"coordinates":[-85.334993,35.079186],"type":"Point"}
}