{
  "type": "Feature",
  "properties": {
    "iso:country":"US",
    "sg:address":"6522 Chapman Hwy",
    "sg:city":"Knoxville",
    "sg:classifiers":[
        {
            "category":"Shopping",
            "subcategory":"Department Store",
            "type":"Retail Goods"
        }
    ],
    "sg:phone":"+1 865 577 2596",
    "sg:postcode":"37920",
    "sg:province":"TN",
    "wof:name":"Wal-Mart",
    "wof:placetype":"venue"
},
  "geometry": {"coordinates":[-83.864768,35.921247],"type":"Point"}
}