{
  "type": "Feature",
  "properties": {
    "iso:country":"US",
    "sg:address":"7608 Moore Rd",
    "sg:city":"Memphis",
    "sg:classifiers":[
        {
            "category":"Wholesale",
            "subcategory":"Farm Supplies",
            "type":"Manufacturing & Wholesale Goods"
        }
    ],
    "sg:phone":"+1 901 624 1134",
    "sg:postcode":"38120",
    "sg:province":"TN",
    "sg:tags":[
        "bulb",
        "seed"
    ],
    "wof:name":"Stoneville Pedigree Seed",
    "wof:placetype":"venue"
},
  "geometry": {"coordinates":[-89.812967,35.126247],"type":"Point"}
}