{
  "type": "Feature",
  "properties": {
    "iso:country":"US",
    "sg:address":"3960 Bell Rd",
    "sg:city":"Hermitage",
    "sg:classifiers":[
        {
            "category":"Real Estate",
            "subcategory":"Real Estate Operator",
            "type":"Services"
        }
    ],
    "sg:phone":"+1 615 874 2400",
    "sg:postcode":"37076",
    "sg:province":"TN",
    "sg:tags":[
        "building",
        "apartment"
    ],
    "wof:name":"Coves At Priest Lake",
    "wof:placetype":"venue"
},
  "geometry": {"coordinates":[-86.611851,36.16484],"type":"Point"}
}