{
  "type": "Feature",
  "properties": {
    "iso:country":"US",
    "sg:address":"847 Whitney Ave",
    "sg:city":"Memphis",
    "sg:classifiers":[
        {
            "category":"Organizations",
            "subcategory":"Community Association",
            "type":"Services"
        }
    ],
    "sg:phone":"+1 901 353 2118",
    "sg:postcode":"38127",
    "sg:province":"TN",
    "wof:name":"VFW Post 4916",
    "wof:placetype":"venue"
},
  "geometry": {"coordinates":[-90.03584600000001,35.208222],"type":"Point"}
}