{
  "type": "Feature",
  "properties": {
    "addr:full":"8523 Providence Rd Ooltewah TN 37363",
    "addr:housenumber":"8523",
    "addr:postcode":"37363",
    "addr:street":"Providence Rd",
    "iso:country":"US",
    "sg:address":"8523 Providence Rd",
    "sg:city":"Ooltewah",
    "sg:classifiers":[
        {
            "category":"Organizations",
            "subcategory":"Religious Organization",
            "type":"Services"
        }
    ],
    "sg:phone":"+1 423 238 4363",
    "sg:postcode":"37363",
    "sg:province":"TN",
    "wof:name":"Providence Baptist Church",
    "wof:placetype":"venue"
},
  "geometry": {"coordinates":[-85.05006899999999,35.135431],"type":"Point"}
}