{
  "type": "Feature",
  "properties": {
    "iso:country":"US",
    "sg:address":"1430 Nottingham Dr",
    "sg:city":"Newport",
    "sg:classifiers":[
        {
            "category":"Real Estate",
            "subcategory":"Real Estate Operator",
            "type":"Services"
        }
    ],
    "sg:phone":"+1 423 623 4951",
    "sg:postcode":"37821",
    "sg:province":"TN",
    "sg:tags":[
        "building",
        "apartment"
    ],
    "wof:name":"Bicentennial Apartments Inc",
    "wof:placetype":"venue"
},
  "geometry": {"coordinates":[-83.193995,35.928428],"type":"Point"}
}