{
  "type": "Feature",
  "properties": {
    "addr:full":"7 S McLean Blvd Memphis TN 38104",
    "addr:housenumber":"7",
    "addr:postcode":"38104",
    "addr:street":"S Mclean Blvd",
    "iso:country":"US",
    "sg:address":"7 S McLean Blvd",
    "sg:city":"Memphis",
    "sg:classifiers":[
        {
            "category":"Retail",
            "subcategory":"Auto Rental",
            "type":"Services"
        }
    ],
    "sg:phone":"+1 901 272 8825",
    "sg:postcode":"38104",
    "sg:province":"TN",
    "sg:tags":[
        "renting",
        "truck",
        "leasing"
    ],
    "wof:name":"Budget Truck Rental",
    "wof:placetype":"venue"
},
  "geometry": {"coordinates":[-90.00013300000001,35.135338],"type":"Point"}
}