{
  "type": "Feature",
  "properties": {
    "addr:full":"1415 Union St Shelbyville TN 37160",
    "addr:housenumber":"1415",
    "addr:postcode":"37160",
    "addr:street":"Union St",
    "iso:country":"US",
    "sg:address":"1415 Union St",
    "sg:city":"Shelbyville",
    "sg:classifiers":[
        {
            "category":"Building & Trades",
            "subcategory":"Construction",
            "type":"Services"
        }
    ],
    "sg:phone":"+1 931 684 2818",
    "sg:postcode":"37160",
    "sg:province":"TN",
    "sg:tags":[
        "c"
    ],
    "wof:name":"Crowell Properties",
    "wof:placetype":"venue"
},
  "geometry": {"coordinates":[-86.48924700000001,35.50793],"type":"Point"}
}