{
  "type": "Feature",
  "properties": {
    "iso:country":"US",
    "sg:address":"6630 Charlotte Pike",
    "sg:city":"Nashville",
    "sg:classifiers":[
        {
            "category":"Food & Beverages",
            "subcategory":"Groceries & Convenience Stores",
            "type":"Retail Goods"
        }
    ],
    "sg:phone":"+1 615 356 3818",
    "sg:postcode":"37209",
    "sg:province":"TN",
    "wof:name":"Food Lion LLC",
    "wof:placetype":"venue"
},
  "geometry": {"coordinates":[-86.88329400000001,36.137058],"type":"Point"}
}