{
  "type": "Feature",
  "properties": {
    "iso:country":"US",
    "sg:address":"302 Sunset Dr",
    "sg:city":"Johnson City",
    "sg:classifiers":[
        {
            "category":"Health Services",
            "subcategory":"Doctor",
            "type":"Services"
        }
    ],
    "sg:phone":"+1 423 282 8869",
    "sg:postcode":"37604",
    "sg:province":"TN",
    "wof:name":"Hay Walker W DDS",
    "wof:placetype":"venue"
},
  "geometry": {"coordinates":[-82.37653,36.343591],"type":"Point"}
}