{
  "type": "Feature",
  "properties": {
    "addr:full":"1512 Dry Hollow Rd Monterey TN 38574",
    "addr:housenumber":"1512",
    "addr:postcode":"38574",
    "addr:street":"Dry Hollow Rd",
    "iso:country":"US",
    "sg:address":"1512 Dry Hollow Rd",
    "sg:city":"Monterey",
    "sg:classifiers":[
        {
            "category":"Freight",
            "type":"Transportation"
        }
    ],
    "sg:phone":"+1 931 445 3237",
    "sg:postcode":"38574",
    "sg:province":"TN",
    "sg:tags":[
        "operator",
        "local",
        "trucking"
    ],
    "wof:name":"Dry Hollow Trucking",
    "wof:placetype":"venue"
},
  "geometry": {"coordinates":[-85.22403,36.257982],"type":"Point"}
}