{
  "type": "Feature",
  "properties": {
    "iso:country":"US",
    "sg:address":"5421 Crestview Dr",
    "sg:city":"Memphis",
    "sg:classifiers":[
        {
            "category":"Retail",
            "subcategory":"Laundry & Dry Cleaning",
            "type":"Services"
        }
    ],
    "sg:phone":"+1 901 382 4411",
    "sg:postcode":"38134",
    "sg:province":"TN",
    "sg:tags":[
        "rental",
        "uniform"
    ],
    "wof:name":"Paramount Uniform Sales",
    "wof:placetype":"venue"
},
  "geometry": {"coordinates":[-89.886325,35.170876],"type":"Point"}
}