{
  "type": "Feature",
  "properties": {
    "iso:country":"US",
    "sg:address":"2305 Highland Ave",
    "sg:city":"Columbia",
    "sg:classifiers":[
        {
            "category":"Building & Trades",
            "subcategory":"Electrical",
            "type":"Services"
        }
    ],
    "sg:phone":"+1 931 381 8242",
    "sg:postcode":"38401",
    "sg:province":"TN",
    "sg:tags":[
        "electric",
        "contractor"
    ],
    "wof:name":"Mark Dawson Electric",
    "wof:placetype":"venue"
},
  "geometry": {"coordinates":[-87.045921,35.593246],"type":"Point"}
}