{
  "type": "Feature",
  "properties": {
    "iso:country":"US",
    "sg:address":"238 Heathersett Dr",
    "sg:city":"Franklin",
    "sg:classifiers":[
        {
            "category":"Professional",
            "subcategory":"Business Services",
            "type":"Services"
        },
        {
            "category":"Professional",
            "subcategory":"Computer Services",
            "type":"Services"
        }
    ],
    "sg:phone":"+1 615 790 8318",
    "sg:postcode":"37064",
    "sg:province":"TN",
    "sg:tags":[
        "bar",
        "coding"
    ],
    "wof:name":"Quest and Solutions",
    "wof:placetype":"venue"
},
  "geometry": {"coordinates":[-86.856466,35.894469],"type":"Point"}
}