{
  "type": "Feature",
  "properties": {
    "iso:country":"US",
    "sg:address":"3084 Southern Ave",
    "sg:city":"Memphis",
    "sg:classifiers":[
        {
            "category":"Organizations",
            "subcategory":"Religious Organization",
            "type":"Services"
        }
    ],
    "sg:phone":"+1 901 454 7777",
    "sg:postcode":"38111",
    "sg:province":"TN",
    "sg:website":"www.olivetbc.com",
    "wof:name":"Olivet Baptist Church",
    "wof:placetype":"venue"
},
  "geometry": {"coordinates":[-89.959107,35.115457],"type":"Point"}
}