{
  "type": "Feature",
  "properties": {
    "iso:country":"US",
    "sg:address":"255 Vance Ave",
    "sg:city":"Memphis",
    "sg:classifiers":[
        {
            "category":"Retail",
            "subcategory":"Auto Repair",
            "type":"Services"
        }
    ],
    "sg:phone":"+1 901 543 9207",
    "sg:postcode":"38126",
    "sg:province":"TN",
    "sg:tags":[
        "shop"
    ],
    "wof:name":"Complete Custom Auto",
    "wof:placetype":"venue"
},
  "geometry": {"coordinates":[-90.05323199999999,35.135506],"type":"Point"}
}