{
  "type": "Feature",
  "properties": {
    "addr:full":"1016 N 1st St Milan TN 38358",
    "addr:housenumber":"1016",
    "addr:postcode":"38358",
    "addr:street":"N 1St St",
    "iso:country":"US",
    "sg:address":"1016 N 1st St",
    "sg:city":"Milan",
    "sg:classifiers":[
        {
            "category":"Autos & Motor Vehicles",
            "subcategory":"Auto Supplies",
            "type":"Retail Goods"
        }
    ],
    "sg:phone":"+1 731 686 2477",
    "sg:postcode":"38358",
    "sg:province":"TN",
    "sg:tags":[
        "automobile",
        "parts"
    ],
    "wof:name":"Autozone",
    "wof:placetype":"venue"
},
  "geometry": {"coordinates":[-88.759135,35.921161],"type":"Point"}
}