{
  "type": "Feature",
  "properties": {
    "addr:full":"120 Commerce St Clarksville TN 37040",
    "addr:housenumber":"120",
    "addr:postcode":"37040",
    "addr:street":"Commerce St",
    "iso:country":"US",
    "sg:address":"120 Commerce St",
    "sg:city":"Clarksville",
    "sg:classifiers":[
        {
            "category":"Government",
            "subcategory":"Police Station",
            "type":"Public Place"
        }
    ],
    "sg:phone":"+1 931 648 5740",
    "sg:postcode":"37040",
    "sg:province":"TN",
    "sg:tags":[
        "protection"
    ],
    "wof:name":"Montgomery Cnty Sheriffs Dept",
    "wof:placetype":"venue"
},
  "geometry": {"coordinates":[-87.35861800000001,36.526207],"type":"Point"}
}