{
  "type": "Feature",
  "properties": {
    "iso:country":"US",
    "sg:address":"205 Roger Ave",
    "sg:city":"Bolivar",
    "sg:classifiers":[
        {
            "category":"Personal",
            "subcategory":"Beauty Salon",
            "type":"Services"
        }
    ],
    "sg:phone":"+1 731 658 2730",
    "sg:postcode":"38008",
    "sg:province":"TN",
    "sg:tags":[
        "shop"
    ],
    "wof:name":"T & J Family Hair Care",
    "wof:placetype":"venue"
},
  "geometry": {"coordinates":[-88.98623499999999,35.270416],"type":"Point"}
}