{
  "type": "Feature",
  "properties": {
    "iso:country":"US",
    "sg:address":"4806 Wales Ct",
    "sg:city":"Nashville",
    "sg:classifiers":[
        {
            "category":"Professional",
            "subcategory":"Computer Services",
            "type":"Services"
        }
    ],
    "sg:phone":"+1 615 834 9855",
    "sg:postcode":"37211",
    "sg:province":"TN",
    "sg:tags":[
        "programing",
        "custom"
    ],
    "wof:name":"Moore Consulting Services",
    "wof:placetype":"venue"
},
  "geometry": {"coordinates":[-86.71494199999999,36.07267],"type":"Point"}
}