{
  "type": "Feature",
  "properties": {
    "addr:full":"6607 Baird Cove Bartlett TN 38135",
    "addr:housenumber":"6607",
    "addr:postcode":"38135",
    "addr:street":"Baird Cove",
    "iso:country":"US",
    "sg:address":"6607 Baird Cove",
    "sg:city":"Bartlett",
    "sg:classifiers":[
        {
            "category":"Home & Garden",
            "subcategory":"Building Materials",
            "type":"Retail Goods"
        }
    ],
    "sg:phone":"+1 901 388 5058",
    "sg:postcode":"38135",
    "sg:province":"TN",
    "sg:tags":[
        "door"
    ],
    "wof:name":"Garage Doors & Openers",
    "wof:placetype":"venue"
},
  "geometry": {"coordinates":[-89.843774,35.219461],"type":"Point"}
}