{
  "type": "Feature",
  "properties": {
    "addr:full":"135 Glen Oaks Dr Johnson City TN 37615",
    "addr:housenumber":"135",
    "addr:postcode":"37615",
    "addr:street":"Glen Oaks Dr",
    "iso:country":"US",
    "sg:address":"135 Glen Oaks Dr",
    "sg:city":"Johnson City",
    "sg:classifiers":[
        {
            "category":"Building & Trades",
            "subcategory":"Electrical",
            "type":"Services"
        }
    ],
    "sg:phone":"+1 423 282 8652",
    "sg:postcode":"37615",
    "sg:province":"TN",
    "sg:tags":[
        "electrical",
        "contractor"
    ],
    "wof:name":"Burleson Electric Company",
    "wof:placetype":"venue"
},
  "geometry": {"coordinates":[-82.432273,36.397144],"type":"Point"}
}