{
  "type": "Feature",
  "properties": {
    "iso:country":"US",
    "sg:address":"1449 Hickory Point Rd",
    "sg:city":"Clarksville",
    "sg:classifiers":[
        {
            "category":"Professional",
            "subcategory":"Business Services",
            "type":"Services"
        }
    ],
    "sg:phone":"+1 931 362 9238",
    "sg:postcode":"37043",
    "sg:province":"TN",
    "wof:name":"Home Interior Decorating Inc",
    "wof:placetype":"venue"
},
  "geometry": {"coordinates":[-87.25624999999999,36.456748],"type":"Point"}
}