{
  "type": "Feature",
  "properties": {
    "addr:full":"1710 N Shelby Oaks Dr Memphis TN 38134",
    "addr:housenumber":"1710",
    "addr:postcode":"38134",
    "addr:street":"N Shelby Oaks Dr",
    "iso:country":"US",
    "sg:address":"1710 N Shelby Oaks Dr",
    "sg:city":"Memphis",
    "sg:classifiers":[
        {
            "category":"Professional",
            "subcategory":"Research",
            "type":"Services"
        }
    ],
    "sg:phone":"+1 901 507 4606",
    "sg:postcode":"38134",
    "sg:province":"TN",
    "sg:tags":[
        "laboratory"
    ],
    "wof:name":"Memphis Testing Laboratory",
    "wof:placetype":"venue"
},
  "geometry": {"coordinates":[-89.854969,35.170543],"type":"Point"}
}