{
  "type": "Feature",
  "properties": {
    "addr:full":"5124 Poplar Ave Memphis TN 38117",
    "addr:housenumber":"5124",
    "addr:postcode":"38117",
    "addr:street":"Poplar Ave",
    "iso:country":"US",
    "sg:address":"5124 Poplar Ave",
    "sg:city":"Memphis",
    "sg:classifiers":[
        {
            "category":"Travel",
            "subcategory":"Travel Agent",
            "type":"Entertainment"
        }
    ],
    "sg:phone":"+1 901 291 1400",
    "sg:postcode":"38117",
    "sg:province":"TN",
    "sg:tags":[
        "agency",
        "bureau"
    ],
    "sg:website":"www.aitvl.com",
    "wof:name":"A & I Travel Svc Inc",
    "wof:placetype":"venue"
},
  "geometry": {"coordinates":[-89.89164,35.110864],"type":"Point"}
}