{
  "type": "Feature",
  "properties": {
    "addr:full":"6848 Stage Rd Memphis TN 38134",
    "addr:housenumber":"6848",
    "addr:postcode":"38134",
    "addr:street":"Stage Rd",
    "iso:country":"US",
    "sg:address":"6848 Stage Rd",
    "sg:city":"Memphis",
    "sg:classifiers":[
        {
            "category":"Shopping",
            "subcategory":"Tobacco",
            "type":"Retail Goods"
        }
    ],
    "sg:phone":"+1 901 383 2447",
    "sg:postcode":"38134",
    "sg:province":"TN",
    "sg:tags":[
        "product"
    ],
    "wof:name":"Cheap Cigs Inc",
    "wof:placetype":"venue"
},
  "geometry": {"coordinates":[-89.83607499999999,35.205662],"type":"Point"}
}