{
  "type": "Feature",
  "properties": {
    "iso:country":"US",
    "sg:address":"620 N Blythe Ave",
    "sg:city":"Gallatin",
    "sg:classifiers":[
        {
            "category":"Retail",
            "subcategory":"Auto Repair",
            "type":"Services"
        }
    ],
    "sg:phone":"+1 615 451 0330",
    "sg:postcode":"37066",
    "sg:province":"TN",
    "sg:tags":[
        "repairing",
        "automobile"
    ],
    "wof:name":"D & B Auto Repair",
    "wof:placetype":"venue"
},
  "geometry": {"coordinates":[-86.451786,36.398452],"type":"Point"}
}