{
  "type": "Feature",
  "properties": {
    "iso:country":"US",
    "sg:address":"2227 Lake Rd",
    "sg:city":"Dyersburg",
    "sg:classifiers":[
        {
            "category":"Organizations",
            "subcategory":"Religious Organization",
            "type":"Services"
        }
    ],
    "sg:phone":"+1 731 285 1705",
    "sg:postcode":"38024",
    "sg:province":"TN",
    "sg:tags":[
        "church"
    ],
    "wof:name":"Church of Christ Lake Road",
    "wof:placetype":"venue"
},
  "geometry": {"coordinates":[-89.394552,36.055987],"type":"Point"}
}