{
  "type": "Feature",
  "properties": {
    "addr:full":"127 Main Ave N Fayetteville TN 37334",
    "addr:housenumber":"127",
    "addr:postcode":"37334",
    "addr:street":"Main Ave N",
    "iso:country":"US",
    "sg:address":"127 Main Ave N",
    "sg:city":"Fayetteville",
    "sg:classifiers":[
        {
            "category":"Manufacturing",
            "subcategory":"Metals",
            "type":"Manufacturing & Wholesale Goods"
        }
    ],
    "sg:phone":"+1 931 438 5464",
    "sg:postcode":"37334",
    "sg:province":"TN",
    "wof:name":"Main Avenue",
    "wof:placetype":"venue"
},
  "geometry": {"coordinates":[-86.57041599999999,35.152862],"type":"Point"}
}