{
  "type": "Feature",
  "properties": {
    "iso:country":"US",
    "sg:address":"808 N Locust Ave",
    "sg:city":"Lawrenceburg",
    "sg:classifiers":[
        {
            "category":"Personal",
            "type":"Services"
        }
    ],
    "sg:phone":"+1 931 766 5800",
    "sg:postcode":"38464",
    "sg:province":"TN",
    "wof:name":"Pro Tan Inc",
    "wof:placetype":"venue"
},
  "geometry": {"coordinates":[-87.327218,35.248136],"type":"Point"}
}