{
  "type": "Feature",
  "properties": {
    "addr:full":"6044 Hickory Ridge Trl Memphis TN 38115",
    "addr:housenumber":"6044",
    "addr:postcode":"38115",
    "addr:street":"Hickory Ridge Trl",
    "iso:country":"US",
    "sg:address":"6044 Hickory Ridge Trl",
    "sg:city":"Memphis",
    "sg:classifiers":[
        {
            "category":"Shopping",
            "subcategory":"Clothing, Apparel, & Fashions",
            "type":"Retail Goods"
        }
    ],
    "sg:phone":"+1 901 370 4996",
    "sg:postcode":"38115",
    "sg:province":"TN",
    "wof:name":"4 Ever Young",
    "wof:placetype":"venue"
},
  "geometry": {"coordinates":[-89.86263,35.057792],"type":"Point"}
}