{
  "type": "Feature",
  "properties": {
    "iso:country":"US",
    "sg:address":"9443 Gwynnbrook Cove",
    "sg:city":"Germantown",
    "sg:classifiers":[
        {
            "category":"Wholesale",
            "subcategory":"Scrap",
            "type":"Manufacturing & Wholesale Goods"
        }
    ],
    "sg:phone":"+1 901 756 2801",
    "sg:postcode":"38139",
    "sg:province":"TN",
    "sg:tags":[
        "whole",
        "plastic"
    ],
    "wof:name":"Burcham International Corp",
    "wof:placetype":"venue"
},
  "geometry": {"coordinates":[-89.744466,35.08091],"type":"Point"}
}