{
  "type": "Feature",
  "properties": {
    "iso:country":"US",
    "sg:address":"791 Fairbanks St",
    "sg:city":"Cookeville",
    "sg:classifiers":[
        {
            "category":"Manufacturing",
            "subcategory":"Chemicals & Compounds",
            "type":"Manufacturing & Wholesale Goods"
        }
    ],
    "sg:phone":"+1 931 528 3662",
    "sg:postcode":"38501",
    "sg:province":"TN",
    "sg:tags":[
        "preparation",
        "mfg"
    ],
    "wof:name":"Scott Insulation",
    "wof:placetype":"venue"
},
  "geometry": {"coordinates":[-85.51639,36.145188],"type":"Point"}
}