{
  "type": "Feature",
  "properties": {
    "iso:country":"US",
    "sg:address":"820 Hillview Hts",
    "sg:city":"Nashville",
    "sg:classifiers":[
        {
            "category":"Real Estate",
            "subcategory":"Real Estate Operator",
            "type":"Services"
        }
    ],
    "sg:phone":"+1 615 269 5551",
    "sg:postcode":"37204",
    "sg:province":"TN",
    "sg:tags":[
        "apartment",
        "complex"
    ],
    "wof:name":"Park At Melrose Aptartments",
    "wof:placetype":"venue"
},
  "geometry": {"coordinates":[-86.780807,36.126162],"type":"Point"}
}