{
  "type": "Feature",
  "properties": {
    "iso:country":"US",
    "sg:address":"7095 Ivy Leaf Cir",
    "sg:city":"Germantown",
    "sg:classifiers":[
        {
            "category":"Real Estate",
            "subcategory":"Real Estate Agent",
            "type":"Services"
        },
        {
            "category":"Real Estate",
            "subcategory":"Real Estate Operator",
            "type":"Services"
        }
    ],
    "sg:phone":"+1 901 755 8977",
    "sg:postcode":"38138",
    "sg:province":"TN",
    "sg:tags":[
        "apartment"
    ],
    "wof:name":"Sentinel Real Estate Corp",
    "wof:placetype":"venue"
},
  "geometry": {"coordinates":[-89.82593300000001,35.11488],"type":"Point"}
}