{
  "type": "Feature",
  "properties": {
    "iso:country":"US",
    "sg:address":"579 Lonesome Valley Rd",
    "sg:city":"Sevierville",
    "sg:classifiers":[
        {
            "category":"Building & Trades",
            "subcategory":"Plumbing",
            "type":"Services"
        }
    ],
    "sg:phone":"+1 865 453 3055",
    "sg:postcode":"37862",
    "sg:province":"TN",
    "sg:tags":[
        "conditioning",
        "air",
        "system",
        "contractor"
    ],
    "wof:name":"Marshalls Heating and Air",
    "wof:placetype":"venue"
},
  "geometry": {"coordinates":[-83.586946,35.822838],"type":"Point"}
}