{
  "type": "Feature",
  "properties": {
    "iso:country":"US",
    "sg:address":"530 Church St",
    "sg:city":"Nashville",
    "sg:classifiers":[
        {
            "category":"Professional",
            "subcategory":"Lawyer & Legal Services",
            "type":"Services"
        }
    ],
    "sg:phone":"+1 615 259 2404",
    "sg:postcode":"37203",
    "sg:province":"TN",
    "sg:tags":[
        "attorney"
    ],
    "wof:name":"Earl Roberts Law Offices",
    "wof:placetype":"venue"
},
  "geometry": {"coordinates":[-86.78045400000001,36.163144],"type":"Point"}
}