{
  "type": "Feature",
  "properties": {
    "iso:country":"US",
    "sg:address":"1189 Genesis Rd",
    "sg:city":"Crossville",
    "sg:classifiers":[
        {
            "category":"Home & Garden",
            "subcategory":"Building Materials",
            "type":"Retail Goods"
        }
    ],
    "sg:phone":"+1 931 484 9284",
    "sg:postcode":"38555",
    "sg:province":"TN",
    "sg:tags":[
        "glass",
        "window",
        "plate"
    ],
    "wof:name":"Whittenburg Glass Svc",
    "wof:placetype":"venue"
},
  "geometry": {"coordinates":[-85.018955,35.968561],"type":"Point"}
}