{
  "type": "Feature",
  "properties": {
    "iso:country":"US",
    "sg:address":"3223 Austin Peay Hwy",
    "sg:city":"Memphis",
    "sg:classifiers":[
        {
            "category":"Autos & Motor Vehicles",
            "subcategory":"Auto Supplies",
            "type":"Retail Goods"
        }
    ],
    "sg:phone":"+1 901 386 9780",
    "sg:postcode":"38135",
    "sg:province":"TN",
    "sg:tags":[
        "equipment",
        "parts",
        "electrical",
        "automobile"
    ],
    "sg:website":"www.advanceauto.com",
    "wof:name":"Advance Auto Parts Inc",
    "wof:placetype":"venue"
},
  "geometry": {"coordinates":[-89.91704300000001,35.213281],"type":"Point"}
}