{
  "type": "Feature",
  "properties": {
    "iso:country":"US",
    "sg:address":"553 Arlington Ave",
    "sg:city":"Chattanooga",
    "sg:classifiers":[
        {
            "category":"Shopping",
            "subcategory":"Clothing, Apparel, & Fashions",
            "type":"Retail Goods"
        }
    ],
    "sg:phone":"+1 423 622 4690",
    "sg:postcode":"37404",
    "sg:province":"TN",
    "wof:name":"Meco Siler Fashions",
    "wof:placetype":"venue"
},
  "geometry": {"coordinates":[-85.264387,35.041754],"type":"Point"}
}