{
  "type": "Feature",
  "properties": {
    "iso:country":"US",
    "sg:address":"7445 Travis Rd",
    "sg:city":"Morristown",
    "sg:classifiers":[
        {
            "category":"Building & Trades",
            "subcategory":"Landscaping Services",
            "type":"Services"
        }
    ],
    "sg:phone":"+1 423 586 6499",
    "sg:postcode":"37877",
    "sg:province":"TN",
    "sg:tags":[
        "landscape",
        "contractor"
    ],
    "wof:name":"Johnson's Landscaping",
    "wof:placetype":"venue"
},
  "geometry": {"coordinates":[-83.439531,36.176671],"type":"Point"}
}