{
  "type": "Feature",
  "properties": {
    "addr:full":"4761 Navy Rd Millington TN 38053",
    "addr:housenumber":"4761",
    "addr:postcode":"38053",
    "addr:street":"Navy Rd",
    "iso:country":"US",
    "sg:address":"4761 Navy Rd",
    "sg:city":"Millington",
    "sg:classifiers":[
        {
            "category":"Restaurant",
            "type":"Food & Drink"
        }
    ],
    "sg:menulink":"http://www.allmenus.com/tn/millington/173224-wendys/menu/",
    "sg:phone":"+1 901 872 8131",
    "sg:postcode":"38053",
    "sg:province":"TN",
    "sg:tags":[
        "burger",
        "american",
        "soup"
    ],
    "wof:name":"Wendy's",
    "wof:placetype":"venue"
},
  "geometry": {"coordinates":[-89.90469899999999,35.340966],"type":"Point"}
}