{
  "type": "Feature",
  "properties": {
    "iso:country":"US",
    "sg:address":"301 W Broad St",
    "sg:city":"Smithville",
    "sg:classifiers":[
        {
            "category":"Personal",
            "subcategory":"Beauty Salon",
            "type":"Services"
        }
    ],
    "sg:phone":"+1 615 597 2669",
    "sg:postcode":"37166",
    "sg:province":"TN",
    "sg:tags":[
        "shop"
    ],
    "wof:name":"A-1 Tanning & Hair Designs",
    "wof:placetype":"venue"
},
  "geometry": {"coordinates":[-85.817866,35.957656],"type":"Point"}
}