{
  "type": "Feature",
  "properties": {
    "iso:country":"US",
    "sg:address":"2008 N Locust Ave",
    "sg:city":"Lawrenceburg",
    "sg:classifiers":[
        {
            "category":"Shopping",
            "subcategory":"Department Store",
            "type":"Retail Goods"
        }
    ],
    "sg:phone":"+1 931 762 3507",
    "sg:postcode":"38464",
    "sg:province":"TN",
    "wof:name":"Peebles",
    "wof:placetype":"venue"
},
  "geometry": {"coordinates":[-87.321812,35.267323],"type":"Point"}
}