{
  "type": "Feature",
  "properties": {
    "iso:country":"US",
    "sg:address":"169 Bunch Ln",
    "sg:city":"Jacksboro",
    "sg:classifiers":[
        {
            "category":"Home & Garden",
            "subcategory":"Carpets & Floor Coverings",
            "type":"Retail Goods"
        }
    ],
    "sg:phone":"+1 423 566 1872",
    "sg:postcode":"37757",
    "sg:province":"TN",
    "sg:tags":[
        "laying",
        "contractor"
    ],
    "wof:name":"J & J Carpets",
    "wof:placetype":"venue"
},
  "geometry": {"coordinates":[-84.192718,36.317745],"type":"Point"}
}