{
  "type": "Feature",
  "properties": {
    "iso:country":"US",
    "sg:address":"7871 Holmes Creek Rd",
    "sg:city":"Smithville",
    "sg:classifiers":[
        {
            "category":"Freight",
            "type":"Transportation"
        }
    ],
    "sg:phone":"+1 615 597 8454",
    "sg:postcode":"37166",
    "sg:province":"TN",
    "sg:tags":[
        "operator",
        "local",
        "trucking"
    ],
    "wof:name":"Stout Springs Trucking Inc",
    "wof:placetype":"venue"
},
  "geometry": {"coordinates":[-85.82749699999999,35.997244],"type":"Point"}
}