{
  "type": "Feature",
  "properties": {
    "iso:country":"US",
    "sg:address":"4129 Cromwell Rd",
    "sg:city":"Chattanooga",
    "sg:classifiers":[
        {
            "category":"Building & Trades",
            "subcategory":"Construction",
            "type":"Services"
        }
    ],
    "sg:phone":"+1 423 855 2913",
    "sg:postcode":"37421",
    "sg:province":"TN",
    "sg:tags":[
        "gen",
        "contractor"
    ],
    "wof:name":"Future ERA Construction Inc",
    "wof:placetype":"venue"
},
  "geometry": {"coordinates":[-85.199732,35.066567],"type":"Point"}
}