{
  "type": "Feature",
  "properties": {
    "iso:country":"US",
    "sg:address":"150 Harris Hollow Rd",
    "sg:city":"Erwin",
    "sg:classifiers":[
        {
            "category":"Building & Trades",
            "subcategory":"Construction",
            "type":"Services"
        }
    ],
    "sg:phone":"+1 423 743 6406",
    "sg:postcode":"37650",
    "sg:province":"TN",
    "sg:tags":[
        "general",
        "contractor"
    ],
    "wof:name":"Higgins Construction & Masonry",
    "wof:placetype":"venue"
},
  "geometry": {"coordinates":[-82.402748,36.169255],"type":"Point"}
}