{
  "type": "Feature",
  "properties": {
    "iso:country":"US",
    "sg:address":"8050 Dexter Rd Ste 104",
    "sg:city":"Cordova",
    "sg:classifiers":[
        {
            "category":"Personal",
            "subcategory":"Nail Salon",
            "type":"Services"
        }
    ],
    "sg:phone":"+1 901 309 1399",
    "sg:postcode":"38016",
    "sg:province":"TN",
    "wof:name":"A Nail",
    "wof:placetype":"venue"
},
  "geometry": {"coordinates":[-89.79409,35.173279],"type":"Point"}
}