{
  "type": "Feature",
  "properties": {
    "iso:country":"US",
    "sg:address":"44 Laurelwood Cove",
    "sg:city":"Jackson",
    "sg:classifiers":[
        {
            "category":"Retail",
            "subcategory":"Portrait Studio",
            "type":"Services"
        }
    ],
    "sg:phone":"+1 731 660 4116",
    "sg:postcode":"38305",
    "sg:province":"TN",
    "sg:tags":[
        "photo"
    ],
    "wof:name":"Timothy Irby Photography",
    "wof:placetype":"venue"
},
  "geometry": {"coordinates":[-88.891671,35.69241],"type":"Point"}
}