{
  "type": "Feature",
  "properties": {
    "iso:country":"US",
    "sg:address":"913 Chicamauga Ave",
    "sg:city":"Nashville",
    "sg:classifiers":[
        {
            "category":"Social Services",
            "subcategory":"Adult Care",
            "type":"Services"
        }
    ],
    "sg:phone":"+1 615 228 4095",
    "sg:postcode":"37206",
    "sg:province":"TN",
    "sg:tags":[
        "home",
        "residential"
    ],
    "wof:name":"Johnson Residential Home",
    "wof:placetype":"venue"
},
  "geometry": {"coordinates":[-86.753001,36.185246],"type":"Point"}
}