{
  "type": "Feature",
  "properties": {
    "addr:full":"125 Church St Bradford TN 38316",
    "addr:housenumber":"125",
    "addr:postcode":"38316",
    "addr:street":"Church St",
    "iso:country":"US",
    "sg:address":"125 Church St",
    "sg:city":"Bradford",
    "sg:classifiers":[
        {
            "category":"Organizations",
            "subcategory":"Religious Organization",
            "type":"Services"
        }
    ],
    "sg:phone":"+1 731 742 3291",
    "sg:postcode":"38316",
    "sg:province":"TN",
    "wof:name":"First Baptist Parsonage",
    "wof:placetype":"venue"
},
  "geometry": {"coordinates":[-88.809245,36.075983],"type":"Point"}
}