{
  "type": "Feature",
  "properties": {
    "iso:country":"US",
    "sg:address":"2904 Montvale Rd",
    "sg:city":"Maryville",
    "sg:classifiers":[
        {
            "category":"Food & Beverages",
            "subcategory":"Groceries & Convenience Stores",
            "type":"Retail Goods"
        }
    ],
    "sg:phone":"+1 865 984 3646",
    "sg:postcode":"37803",
    "sg:province":"TN",
    "wof:name":"Foot Hill Market",
    "wof:placetype":"venue"
},
  "geometry": {"coordinates":[-83.965777,35.702639],"type":"Point"}
}