{
  "type": "Feature",
  "properties": {
    "iso:country":"US",
    "sg:address":"1393 N Hollywood St",
    "sg:city":"Memphis",
    "sg:classifiers":[
        {
            "category":"Restaurant",
            "type":"Food & Drink"
        }
    ],
    "sg:phone":"+1 901 327 2212",
    "sg:postcode":"38108",
    "sg:province":"TN",
    "sg:website":"www.fatburger.net",
    "wof:name":"Fatburger",
    "wof:placetype":"venue"
},
  "geometry": {"coordinates":[-89.975516,35.173769],"type":"Point"}
}