{
  "type": "Feature",
  "properties": {
    "iso:country":"US",
    "sg:address":"111 Main St",
    "sg:city":"Gordonsville",
    "sg:classifiers":[
        {
            "category":"Shopping",
            "subcategory":"Used Merchandise",
            "type":"Retail Goods"
        }
    ],
    "sg:phone":"+1 615 683 0961",
    "sg:postcode":"38563",
    "sg:province":"TN",
    "wof:name":"Cherry Pickers Antiques & Col",
    "wof:placetype":"venue"
},
  "geometry": {"coordinates":[-85.92717,36.172524],"type":"Point"}
}