{
  "type": "Feature",
  "properties": {
    "iso:country":"US",
    "sg:address":"5672 Walnut Grove Pl",
    "sg:city":"Memphis",
    "sg:classifiers":[
        {
            "category":"Communications",
            "subcategory":"Film & Video Production",
            "type":"Services"
        }
    ],
    "sg:phone":"+1 901 262 1551",
    "sg:postcode":"38120",
    "sg:province":"TN",
    "sg:tags":[
        "taping"
    ],
    "sg:website":"www.maximizemedia.com",
    "wof:name":"Maximize Media Inc",
    "wof:placetype":"venue"
},
  "geometry": {"coordinates":[-89.87307800000001,35.131589],"type":"Point"}
}