{
  "type": "Feature",
  "properties": {
    "iso:country":"US",
    "sg:address":"3340 Players Club Pkwy",
    "sg:city":"Memphis",
    "sg:classifiers":[
        {
            "category":"Professional",
            "subcategory":"Advertising",
            "type":"Services"
        },
        {
            "category":"Professional",
            "subcategory":"Computer Services",
            "type":"Services"
        }
    ],
    "sg:phone":"+1 901 748 8700",
    "sg:postcode":"38125",
    "sg:province":"TN",
    "sg:tags":[
        "directory",
        "web",
        "design",
        "site",
        "guide"
    ],
    "wof:name":"A T&T Real Yellow Pages",
    "wof:placetype":"venue"
},
  "geometry": {"coordinates":[-89.78480999999999,35.057174],"type":"Point"}
}