{
  "type": "Feature",
  "properties": {
    "addr:full":"1600 Willoughby Rd Knoxville TN 37920",
    "addr:housenumber":"1600",
    "addr:postcode":"37920",
    "addr:street":"Willoughby Rd",
    "iso:country":"US",
    "sg:address":"1600 Willoughby Rd",
    "sg:city":"Knoxville",
    "sg:classifiers":[
        {
            "category":"Social Services",
            "subcategory":"Child Care",
            "type":"Services"
        }
    ],
    "sg:phone":"+1 865 577 0123",
    "sg:postcode":"37920",
    "sg:province":"TN",
    "wof:name":"My Village Child Development",
    "wof:placetype":"venue"
},
  "geometry": {"coordinates":[-83.92855900000001,35.927081],"type":"Point"}
}