{
  "type": "Feature",
  "properties": {
    "addr:full":"607 Market St SW Knoxville TN 37902",
    "addr:housenumber":"607",
    "addr:postcode":"37902",
    "addr:street":"Market St Sw",
    "iso:country":"US",
    "sg:address":"607 Market St SW",
    "sg:city":"Knoxville",
    "sg:classifiers":[
        {
            "category":"Professional",
            "subcategory":"Lawyer & Legal Services",
            "type":"Services"
        }
    ],
    "sg:phone":"+1 865 546 7300",
    "sg:postcode":"37902",
    "sg:province":"TN",
    "sg:tags":[
        "attorney"
    ],
    "wof:name":"James L Milligan Jr & Assoc",
    "wof:placetype":"venue"
},
  "geometry": {"coordinates":[-83.91837,35.963067],"type":"Point"}
}