{
  "type": "Feature",
  "properties": {
    "iso:country":"US",
    "sg:address":"115 Eastpark Dr Ste 300",
    "sg:city":"Brentwood",
    "sg:classifiers":[
        {
            "category":"Health Services",
            "subcategory":"Hospital",
            "type":"Services"
        }
    ],
    "sg:phone":"+1 615 771 4400",
    "sg:postcode":"37027",
    "sg:province":"TN",
    "sg:tags":[
        "dialysis"
    ],
    "sg:website":"http://www.renaladvantage.com",
    "wof:name":"National Renal Alliance",
    "wof:placetype":"venue"
},
  "geometry": {"coordinates":[-86.791251,36.035253],"type":"Point"}
}