{
  "type": "Feature",
  "properties": {
    "addr:full":"521 Old Salem Hwy Murfreesboro TN 37129",
    "addr:housenumber":"521",
    "addr:postcode":"37129",
    "addr:street":"Old Salem Hwy",
    "iso:country":"US",
    "sg:address":"521 Old Salem Hwy",
    "sg:city":"Murfreesboro",
    "sg:classifiers":[
        {
            "category":"Home & Garden",
            "subcategory":"Building Materials",
            "type":"Retail Goods"
        }
    ],
    "sg:phone":"+1 615 867 1084",
    "sg:postcode":"37129",
    "sg:province":"TN",
    "wof:name":"Trim Sales",
    "wof:placetype":"venue"
},
  "geometry": {"coordinates":[-86.395273,35.841791],"type":"Point"}
}