{
  "type": "Feature",
  "properties": {
    "addr:full":"4070 Kingston Pike Knoxville TN 37919",
    "addr:housenumber":"4070",
    "addr:postcode":"37919",
    "addr:street":"Kingston Pike",
    "iso:country":"US",
    "sg:address":"4070 Kingston Pike",
    "sg:city":"Knoxville",
    "sg:classifiers":[
        {
            "category":"Organizations",
            "subcategory":"Religious Organization",
            "type":"Services"
        }
    ],
    "sg:phone":"+1 865 522 5043",
    "sg:postcode":"37919",
    "sg:province":"TN",
    "wof:name":"Saint Grge Greek Orthdox Chrch",
    "wof:placetype":"venue"
},
  "geometry": {"coordinates":[-83.973421,35.942651],"type":"Point"}
}