{
  "type": "Feature",
  "properties": {
    "iso:country":"US",
    "sg:address":"4055 State Hwy 22A",
    "sg:city":"Huron",
    "sg:classifiers":[
        {
            "category":"Professional",
            "subcategory":"Management & Consulting",
            "type":"Services"
        }
    ],
    "sg:phone":"+1 731 968 4879",
    "sg:postcode":"38345",
    "sg:province":"TN",
    "wof:name":"Gateley & Assoc",
    "wof:placetype":"venue"
},
  "geometry": {"coordinates":[-88.466297,35.563248],"type":"Point"}
}