{
  "type": "Feature",
  "properties": {
    "iso:country":"US",
    "sg:address":"319 Webb Rd E",
    "sg:city":"Bell Buckle",
    "sg:classifiers":[
        {
            "category":"Education",
            "subcategory":"School",
            "type":"Public Place"
        }
    ],
    "sg:phone":"+1 931 389 9322",
    "sg:postcode":"37020",
    "sg:province":"TN",
    "sg:website":"www.thewebbschool.com",
    "wof:name":"WEBB School",
    "wof:placetype":"venue"
},
  "geometry": {"coordinates":[-86.348877,35.58889],"type":"Point"}
}