{
  "type": "Feature",
  "properties": {
    "iso:country":"US",
    "sg:address":"783 Old Hickory Blvd",
    "sg:city":"Brentwood",
    "sg:classifiers":[
        {
            "category":"Health Services",
            "subcategory":"Clinic",
            "type":"Services"
        }
    ],
    "sg:phone":"+1 615 309 6001",
    "sg:postcode":"37027",
    "sg:province":"TN",
    "sg:tags":[
        "specialty",
        "outpatient"
    ],
    "wof:name":"Community Rehab Inc",
    "wof:placetype":"venue"
},
  "geometry": {"coordinates":[-86.78258099999999,36.038996],"type":"Point"}
}