{
  "type": "Feature",
  "properties": {
    "addr:full":"420 Railroad St W Elizabethton TN 37643",
    "addr:housenumber":"420",
    "addr:postcode":"37643",
    "addr:street":"Railroad St W",
    "iso:country":"US",
    "sg:address":"420 Railroad St W",
    "sg:city":"Elizabethton",
    "sg:classifiers":[
        {
            "category":"Personal",
            "type":"Services"
        }
    ],
    "sg:phone":"+1 423 542 6488",
    "sg:postcode":"37643",
    "sg:province":"TN",
    "sg:tags":[
        "control",
        "weight"
    ],
    "wof:name":"A New Image Weight Loss Clinic",
    "wof:placetype":"venue"
},
  "geometry": {"coordinates":[-82.232906,36.351038],"type":"Point"}
}