{
  "type": "Feature",
  "properties": {
    "iso:country":"US",
    "sg:address":"756 Contraband Ln",
    "sg:city":"Cookeville",
    "sg:classifiers":[
        {
            "category":"Arts & Performance",
            "subcategory":"Theater",
            "type":"Entertainment"
        }
    ],
    "sg:phone":"+1 931 525 3684",
    "sg:postcode":"38501",
    "sg:province":"TN",
    "sg:tags":[
        "clown"
    ],
    "wof:name":"Put On A Happy Face",
    "wof:placetype":"venue"
},
  "geometry": {"coordinates":[-85.52537599999999,36.148458],"type":"Point"}
}