{
  "type": "Feature",
  "properties": {
    "addr:full":"106 S Gay St Knoxville TN 37902",
    "addr:housenumber":"106",
    "addr:postcode":"37902",
    "addr:street":"S Gay St",
    "iso:country":"US",
    "sg:address":"106 S Gay St",
    "sg:city":"Knoxville",
    "sg:classifiers":[
        {
            "category":"Shopping",
            "type":"Retail Goods"
        }
    ],
    "sg:phone":"+1 865 673 0802",
    "sg:postcode":"37902",
    "sg:province":"TN",
    "sg:tags":[
        "art",
        "gallery",
        "dealer"
    ],
    "wof:name":"University Tennessee Art Galle",
    "wof:placetype":"venue"
},
  "geometry": {"coordinates":[-83.91983999999999,35.967985],"type":"Point"}
}