{
  "type": "Feature",
  "properties": {
    "addr:full":"8906 Rutledge Pike Mascot TN 37924",
    "addr:housenumber":"8906",
    "addr:postcode":"37924",
    "addr:street":"Rutledge Pike",
    "iso:country":"US",
    "sg:address":"8906 Rutledge Pike",
    "sg:city":"Mascot",
    "sg:classifiers":[
        {
            "category":"Autos & Motor Vehicles",
            "subcategory":"Automobile Sales",
            "type":"Retail Goods"
        }
    ],
    "sg:phone":"+1 865 933 8080",
    "sg:postcode":"37924",
    "sg:province":"TN",
    "sg:tags":[
        "car",
        "dealer"
    ],
    "wof:name":"Trading Post",
    "wof:placetype":"venue"
},
  "geometry": {"coordinates":[-83.768209,36.077975],"type":"Point"}
}