{
  "type": "Feature",
  "properties": {
    "addr:full":"870 Overton Plz Livingston TN 38570",
    "addr:housenumber":"870",
    "addr:postcode":"38570",
    "addr:street":"Overton Plz",
    "iso:country":"US",
    "sg:address":"870 Overton Plz",
    "sg:city":"Livingston",
    "sg:classifiers":[
        {
            "category":"Shopping",
            "subcategory":"Department Store",
            "type":"Retail Goods"
        }
    ],
    "sg:phone":"+1 931 823 7787",
    "sg:postcode":"38570",
    "sg:province":"TN",
    "sg:tags":[
        "shop"
    ],
    "wof:name":"Lots Of Stuff",
    "wof:placetype":"venue"
},
  "geometry": {"coordinates":[-85.33475799999999,36.380349],"type":"Point"}
}