{
  "type": "Feature",
  "properties": {
    "iso:country":"US",
    "sg:address":"2858 Chesney Rd",
    "sg:city":"Friendsville",
    "sg:classifiers":[
        {
            "category":"Wholesale",
            "subcategory":"Electrical",
            "type":"Manufacturing & Wholesale Goods"
        }
    ],
    "sg:phone":"+1 865 995 2472",
    "sg:postcode":"37737",
    "sg:province":"TN",
    "sg:tags":[
        "equipment"
    ],
    "wof:name":"Security Alarms Ltd Inc",
    "wof:placetype":"venue"
},
  "geometry": {"coordinates":[-84.08217500000001,35.756823],"type":"Point"}
}