{
  "type": "Feature",
  "properties": {
    "iso:country":"US",
    "sg:address":"516 Tennessee St",
    "sg:city":"Memphis",
    "sg:classifiers":[
        {
            "category":"Professional",
            "subcategory":"Research",
            "type":"Services"
        }
    ],
    "sg:phone":"+1 901 333 1384",
    "sg:postcode":"38103",
    "sg:province":"TN",
    "sg:tags":[
        "nonphysical",
        "commercial"
    ],
    "wof:name":"Next Researchcom Inc",
    "wof:placetype":"venue"
},
  "geometry": {"coordinates":[-90.062484,35.133417],"type":"Point"}
}