{
  "type": "Feature",
  "properties": {
    "iso:country":"US",
    "sg:address":"130 Hillcrest Dr",
    "sg:city":"Clarksville",
    "sg:classifiers":[
        {
            "category":"Insurance",
            "subcategory":"Insurance Agent",
            "type":"Services"
        }
    ],
    "sg:phone":"+1 931 648 0805",
    "sg:postcode":"37043",
    "sg:province":"TN",
    "wof:name":"Hadley Insurance Agency",
    "wof:placetype":"venue"
},
  "geometry": {"coordinates":[-87.30443200000001,36.515163],"type":"Point"}
}