{
  "type": "Feature",
  "properties": {
    "iso:country":"US",
    "sg:address":"9048 Fallswood Ln",
    "sg:city":"Brentwood",
    "sg:classifiers":[
        {
            "category":"Shopping",
            "subcategory":"Clothing, Apparel, & Fashions",
            "type":"Retail Goods"
        }
    ],
    "sg:phone":"+1 615 371 2489",
    "sg:postcode":"37027",
    "sg:province":"TN",
    "wof:name":"Music City Window Fashion",
    "wof:placetype":"venue"
},
  "geometry": {"coordinates":[-86.776678,35.994081],"type":"Point"}
}