{
  "type": "Feature",
  "properties": {
    "iso:country":"US",
    "sg:address":"3307 Park Ave",
    "sg:city":"Memphis",
    "sg:classifiers":[
        {
            "category":"Professional",
            "subcategory":"Engineering",
            "type":"Services"
        }
    ],
    "sg:phone":"+1 901 454 1115",
    "sg:postcode":"38111",
    "sg:province":"TN",
    "sg:tags":[
        "ventilating",
        "heating",
        "engineer"
    ],
    "wof:name":"ACS Heating & Air Conditiong",
    "wof:placetype":"venue"
},
  "geometry": {"coordinates":[-89.951452,35.107709],"type":"Point"}
}