{
  "type": "Feature",
  "properties": {
    "iso:country":"US",
    "sg:address":"1459 Railroad St",
    "sg:city":"Dayton",
    "sg:classifiers":[
        {
            "category":"Shopping",
            "subcategory":"Clothing, Apparel, & Fashions",
            "type":"Retail Goods"
        }
    ],
    "sg:phone":"+1 423 570 8180",
    "sg:postcode":"37321",
    "sg:province":"TN",
    "wof:name":"Jewelry Hut",
    "wof:placetype":"venue"
},
  "geometry": {"coordinates":[-85.012658,35.497568],"type":"Point"}
}