{
  "type": "Feature",
  "properties": {
    "addr:full":"1564 Cranford Rd Memphis TN 38117",
    "addr:housenumber":"1564",
    "addr:postcode":"38117",
    "addr:street":"Cranford Rd",
    "iso:country":"US",
    "sg:address":"1564 Cranford Rd",
    "sg:city":"Memphis",
    "sg:classifiers":[
        {
            "category":"Professional",
            "subcategory":"Management & Consulting",
            "type":"Services"
        }
    ],
    "sg:phone":"+1 901 682 2838",
    "sg:postcode":"38117",
    "sg:province":"TN",
    "sg:tags":[
        "public",
        "relations"
    ],
    "wof:name":"Lumbermens Eductl Foundation",
    "wof:placetype":"venue"
},
  "geometry": {"coordinates":[-89.898127,35.090346],"type":"Point"}
}