{
  "type": "Feature",
  "properties": {
    "iso:country":"US",
    "sg:address":"211 Mason St",
    "sg:city":"Woodbury",
    "sg:classifiers":[
        {
            "category":"Building & Trades",
            "subcategory":"Plumbing",
            "type":"Services"
        }
    ],
    "sg:phone":"+1 615 563 2924",
    "sg:postcode":"37190",
    "sg:province":"TN",
    "sg:tags":[
        "plumbing",
        "contractor"
    ],
    "wof:name":"Terry's Plumbing",
    "wof:placetype":"venue"
},
  "geometry": {"coordinates":[-86.06222699999999,35.825924],"type":"Point"}
}