{
  "type": "Feature",
  "properties": {
    "iso:country":"US",
    "sg:address":"2237 Carmack Rd",
    "sg:city":"Ripley",
    "sg:classifiers":[
        {
            "category":"Professional",
            "subcategory":"Business Services",
            "type":"Services"
        }
    ],
    "sg:phone":"+1 731 635 1106",
    "sg:postcode":"38063",
    "sg:province":"TN",
    "wof:name":"Always Bonding Co",
    "wof:placetype":"venue"
},
  "geometry": {"coordinates":[-89.48608299999999,35.780914],"type":"Point"}
}