{
  "type": "Feature",
  "properties": {
    "iso:country":"US",
    "sg:address":"101 Jackson Rd",
    "sg:city":"Maynardville",
    "sg:classifiers":[
        {
            "category":"Personal",
            "subcategory":"Beauty Salon",
            "type":"Services"
        }
    ],
    "sg:phone":"+1 865 992 0000",
    "sg:postcode":"37857",
    "sg:province":"TN",
    "wof:name":"Hair Efx",
    "wof:placetype":"venue"
},
  "geometry": {"coordinates":[-83.039361,36.391503],"type":"Point"}
}