{
  "type": "Feature",
  "properties": {
    "iso:country":"US",
    "sg:address":"4601 Fairwood Ln",
    "sg:city":"Chattanooga",
    "sg:classifiers":[
        {
            "category":"Communications",
            "subcategory":"Film & Video Production",
            "type":"Services"
        }
    ],
    "sg:phone":"+1 423 899 0050",
    "sg:postcode":"37416",
    "sg:province":"TN",
    "sg:tags":[
        "motion",
        "picture"
    ],
    "wof:name":"New Money Entertainment",
    "wof:placetype":"venue"
},
  "geometry": {"coordinates":[-85.19390199999999,35.083231],"type":"Point"}
}