{
  "type": "Feature",
  "properties": {
    "addr:full":"5115 Park Ave Memphis TN 38117",
    "addr:housenumber":"5115",
    "addr:postcode":"38117",
    "addr:street":"Park Ave",
    "iso:country":"US",
    "sg:address":"5115 Park Ave",
    "sg:city":"Memphis",
    "sg:classifiers":[
        {
            "category":"Retail",
            "subcategory":"Auto Repair",
            "type":"Services"
        }
    ],
    "sg:phone":"+1 901 767 9054",
    "sg:postcode":"38117",
    "sg:province":"TN",
    "sg:tags":[
        "shop",
        "tire"
    ],
    "wof:name":"Goodyear Mathis Tire Auto Ctr",
    "wof:placetype":"venue"
},
  "geometry": {"coordinates":[-89.89077899999999,35.106194],"type":"Point"}
}