{
  "type": "Feature",
  "properties": {
    "iso:country":"US",
    "sg:address":"3704 Dayton Blvd",
    "sg:city":"Chattanooga",
    "sg:classifiers":[
        {
            "category":"Organizations",
            "subcategory":"Community Association",
            "type":"Services"
        }
    ],
    "sg:phone":"+1 423 876 4411",
    "sg:postcode":"37415",
    "sg:province":"TN",
    "sg:tags":[
        "club"
    ],
    "wof:name":"Redbank Lions Club",
    "wof:placetype":"venue"
},
  "geometry": {"coordinates":[-85.29206000000001,35.115193],"type":"Point"}
}