{
  "type": "Feature",
  "properties": {
    "iso:country":"US",
    "sg:address":"5312 Rondo Rd NE",
    "sg:city":"Knoxville",
    "sg:classifiers":[
        {
            "category":"Professional",
            "subcategory":"Accounting & Tax Preparation",
            "type":"Services"
        }
    ],
    "sg:phone":"+1 865 687 2500",
    "sg:postcode":"37918",
    "sg:province":"TN",
    "sg:tags":[
        "bookkeeping",
        "general"
    ],
    "wof:name":"Small Business Bookkeeping",
    "wof:placetype":"venue"
},
  "geometry": {"coordinates":[-83.92250300000001,36.040731],"type":"Point"}
}