{
  "type": "Feature",
  "properties": {
    "iso:country":"US",
    "sg:address":"406 Avoca St",
    "sg:city":"Nashville",
    "sg:classifiers":[
        {
            "category":"Shopping",
            "subcategory":"Gifts & Souvenirs",
            "type":"Retail Goods"
        }
    ],
    "sg:phone":"+1 615 783 1873",
    "sg:postcode":"37203",
    "sg:province":"TN",
    "sg:tags":[
        "shop"
    ],
    "wof:name":"R N Jackson Jewlery & Gifts",
    "wof:placetype":"venue"
},
  "geometry": {"coordinates":[-86.818111,36.147467],"type":"Point"}
}