{
  "type": "Feature",
  "properties": {
    "iso:country":"US",
    "sg:address":"5437 Yale Rd",
    "sg:city":"Memphis",
    "sg:classifiers":[
        {
            "category":"Building & Trades",
            "subcategory":"Cleaning & Sanitation",
            "type":"Services"
        }
    ],
    "sg:phone":"+1 901 937 4144",
    "sg:postcode":"38134",
    "sg:province":"TN",
    "sg:tags":[
        "maintenance"
    ],
    "wof:name":"Home Towne Maintenance & RPS",
    "wof:placetype":"venue"
},
  "geometry": {"coordinates":[-89.881704,35.220544],"type":"Point"}
}