{
  "type": "Feature",
  "properties": {
    "iso:country":"US",
    "sg:address":"7545 Hodges Ferry Rd",
    "sg:city":"Knoxville",
    "sg:classifiers":[
        {
            "category":"Organizations",
            "subcategory":"Non-profit Organization",
            "type":"Services"
        }
    ],
    "sg:phone":"+1 865 577 9740",
    "sg:postcode":"37920",
    "sg:province":"TN",
    "wof:name":"Mission Services",
    "wof:placetype":"venue"
},
  "geometry": {"coordinates":[-83.762248,35.946084],"type":"Point"}
}