{
  "type": "Feature",
  "properties": {
    "iso:country":"US",
    "sg:address":"707 W Main St",
    "sg:city":"Hendersonville",
    "sg:classifiers":[
        {
            "category":"Shopping",
            "subcategory":"Gifts & Souvenirs",
            "type":"Retail Goods"
        }
    ],
    "sg:phone":"+1 615 826 2025",
    "sg:postcode":"37075",
    "sg:province":"TN",
    "wof:name":"Race Day Remembered",
    "wof:placetype":"venue"
},
  "geometry": {"coordinates":[-86.640817,36.303006],"type":"Point"}
}