{
  "type": "Feature",
  "properties": {
    "addr:full":"1150 US Hwy 51 Bus Dyersburg TN 38024",
    "addr:housenumber":"1150",
    "addr:postcode":"38024",
    "addr:street":"Us Hwy 51 Bus",
    "iso:country":"US",
    "sg:address":"1150 US Hwy 51 Bus",
    "sg:city":"Dyersburg",
    "sg:classifiers":[
        {
            "category":"Banks & Credit Unions",
            "subcategory":"Bank",
            "type":"Services"
        }
    ],
    "sg:phone":"+1 731 286 4474",
    "sg:postcode":"38024",
    "sg:province":"TN",
    "wof:name":"First State Bank",
    "wof:placetype":"venue"
},
  "geometry": {"coordinates":[-89.39501,36.012348],"type":"Point"}
}