{
  "type": "Feature",
  "properties": {
    "addr:full":"116 Wheeler Ave Nashville TN 37211",
    "addr:housenumber":"116",
    "addr:postcode":"37211",
    "addr:street":"Wheeler Ave",
    "iso:country":"US",
    "sg:address":"116 Wheeler Ave",
    "sg:city":"Nashville",
    "sg:classifiers":[
        {
            "category":"Shopping",
            "subcategory":"Florist",
            "type":"Retail Goods"
        }
    ],
    "sg:phone":"+1 931 879 6030",
    "sg:postcode":"37211",
    "sg:province":"TN",
    "wof:name":"Country Treasures & Florals",
    "wof:placetype":"venue"
},
  "geometry": {"coordinates":[-86.728272,36.095153],"type":"Point"}
}