{
  "type": "Feature",
  "properties": {
    "iso:country":"US",
    "sg:address":"712 N Manassas St",
    "sg:city":"Memphis",
    "sg:classifiers":[
        {
            "category":"Food & Beverages",
            "subcategory":"Groceries & Convenience Stores",
            "type":"Retail Goods"
        }
    ],
    "sg:phone":"+1 901 526 7714",
    "sg:postcode":"38107",
    "sg:province":"TN",
    "sg:tags":[
        "grocer"
    ],
    "wof:name":"Maxine's Grocery",
    "wof:placetype":"venue"
},
  "geometry": {"coordinates":[-90.032557,35.160972],"type":"Point"}
}