{
  "type": "Feature",
  "properties": {
    "iso:country":"US",
    "sg:address":"2820 Parkway",
    "sg:city":"Pigeon Forge",
    "sg:classifiers":[
        {
            "category":"Restaurant",
            "type":"Food & Drink"
        }
    ],
    "sg:phone":"+1 865 428 0652",
    "sg:postcode":"37863",
    "sg:province":"TN",
    "sg:tags":[
        "eating"
    ],
    "wof:name":"Hearthside Restaurant",
    "wof:placetype":"venue"
},
  "geometry": {"coordinates":[-83.568477,35.798905],"type":"Point"}
}