{
  "type": "Feature",
  "properties": {
    "iso:country":"US",
    "sg:address":"3597 Elwood Dr",
    "sg:city":"Morristown",
    "sg:classifiers":[
        {
            "category":"Building & Trades",
            "subcategory":"Landscaping Services",
            "type":"Services"
        }
    ],
    "sg:phone":"+1 423 585 5671",
    "sg:postcode":"37814",
    "sg:province":"TN",
    "sg:tags":[
        "landscape",
        "contractor"
    ],
    "wof:name":"Oakview Landscaping & Lawn",
    "wof:placetype":"venue"
},
  "geometry": {"coordinates":[-83.25167,36.235811],"type":"Point"}
}