{
  "type": "Feature",
  "properties": {
    "addr:full":"209 Austin St Greeneville TN 37745",
    "addr:housenumber":"209",
    "addr:postcode":"37745",
    "addr:street":"Austin St",
    "iso:country":"US",
    "sg:address":"209 Austin St",
    "sg:city":"Greeneville",
    "sg:classifiers":[
        {
            "category":"Building & Trades",
            "subcategory":"Construction",
            "type":"Services"
        }
    ],
    "sg:phone":"+1 423 639 9410",
    "sg:postcode":"37745",
    "sg:province":"TN",
    "sg:tags":[
        "contractor"
    ],
    "wof:name":"Isley Sheet Metal",
    "wof:placetype":"venue"
},
  "geometry": {"coordinates":[-82.820322,36.173272],"type":"Point"}
}