{
  "type": "Feature",
  "properties": {
    "iso:country":"US",
    "sg:address":"8623 Tullahoma Hwy",
    "sg:city":"Estill Springs",
    "sg:classifiers":[
        {
            "category":"Organizations",
            "subcategory":"Religious Organization",
            "type":"Services"
        }
    ],
    "sg:phone":"+1 931 649 2909",
    "sg:postcode":"37330",
    "sg:province":"TN",
    "sg:tags":[
        "church"
    ],
    "wof:name":"Liberty Outreach Church",
    "wof:placetype":"venue"
},
  "geometry": {"coordinates":[-86.14978600000001,35.295253],"type":"Point"}
}