{
  "type": "Feature",
  "properties": {
    "addr:full":"1044 Ashley Ln Dayton TN 37321",
    "addr:housenumber":"1044",
    "addr:postcode":"37321",
    "addr:street":"Ashley Ln",
    "iso:country":"US",
    "sg:address":"1044 Ashley Ln",
    "sg:city":"Dayton",
    "sg:classifiers":[
        {
            "category":"Food & Beverages",
            "subcategory":"Groceries & Convenience Stores",
            "type":"Retail Goods"
        }
    ],
    "sg:phone":"+1 423 570 0297",
    "sg:postcode":"37321",
    "sg:province":"TN",
    "wof:name":"Trackers",
    "wof:placetype":"venue"
},
  "geometry": {"coordinates":[-84.967055,35.537304],"type":"Point"}
}