{
  "type": "Feature",
  "properties": {
    "iso:country":"US",
    "sg:address":"513 W College St",
    "sg:city":"Brownsville",
    "sg:classifiers":[
        {
            "category":"Real Estate",
            "subcategory":"Real Estate Operator",
            "type":"Services"
        }
    ],
    "sg:phone":"+1 731 772 1265",
    "sg:postcode":"38012",
    "sg:province":"TN",
    "sg:tags":[
        "property",
        "lessor"
    ],
    "wof:name":"Burton W Sale & Roanne",
    "wof:placetype":"venue"
},
  "geometry": {"coordinates":[-89.270746,35.595991],"type":"Point"}
}