{
  "type": "Feature",
  "properties": {
    "iso:country":"US",
    "sg:address":"55 Bob Tollett Loop",
    "sg:city":"Crossville",
    "sg:classifiers":[
        {
            "category":"Retail",
            "subcategory":"Veterinary Services",
            "type":"Services"
        }
    ],
    "sg:phone":"+1 931 484 5521",
    "sg:postcode":"38555",
    "sg:province":"TN",
    "wof:name":"Animal Hospital",
    "wof:placetype":"venue"
},
  "geometry": {"coordinates":[-84.99429499999999,35.915577],"type":"Point"}
}