{
  "type": "Feature",
  "properties": {
    "iso:country":"US",
    "sg:address":"2960 Tchulahoma Rd",
    "sg:city":"Memphis",
    "sg:classifiers":[
        {
            "category":"Banks & Credit Unions",
            "subcategory":"Bank",
            "type":"Services"
        }
    ],
    "sg:phone":"+1 901 542 7400",
    "sg:postcode":"38118",
    "sg:province":"TN",
    "sg:tags":[
        "house",
        "nation",
        "check",
        "clearing",
        "wide"
    ],
    "wof:name":"First Tennessee",
    "wof:placetype":"venue"
},
  "geometry": {"coordinates":[-89.953992,35.066794],"type":"Point"}
}