{
  "type": "Feature",
  "properties": {
    "addr:full":"7625 US Hwy 64 Memphis TN 38133",
    "addr:housenumber":"7625",
    "addr:postcode":"38133",
    "addr:street":"Us Hwy 64",
    "iso:country":"US",
    "sg:address":"7625 US Hwy 64",
    "sg:city":"Memphis",
    "sg:classifiers":[
        {
            "category":"Shopping",
            "type":"Retail Goods"
        }
    ],
    "sg:phone":"+1 901 507 7821",
    "sg:postcode":"38133",
    "sg:province":"TN",
    "sg:tags":[
        "limb",
        "artificial"
    ],
    "wof:name":"Wolfchase Limb & Brace LLC",
    "wof:placetype":"venue"
},
  "geometry": {"coordinates":[-89.810388,35.204654],"type":"Point"}
}