{
  "type": "Feature",
  "properties": {
    "iso:country":"US",
    "sg:address":"3770 Homewood Rd",
    "sg:city":"Memphis",
    "sg:classifiers":[
        {
            "category":"Freight",
            "type":"Transportation"
        }
    ],
    "sg:phone":"+1 901 366 4788",
    "sg:postcode":"38118",
    "sg:province":"TN",
    "sg:tags":[
        "operator",
        "trucking"
    ],
    "wof:name":"Shipper's Express Inc",
    "wof:placetype":"venue"
},
  "geometry": {"coordinates":[-89.925831,35.041323],"type":"Point"}
}