{
  "type": "Feature",
  "properties": {
    "iso:country":"US",
    "sg:address":"1208 S Lowry St",
    "sg:city":"Smyrna",
    "sg:classifiers":[
        {
            "category":"Bars & Pubs",
            "type":"Food & Drink"
        }
    ],
    "sg:phone":"+1 615 355 1688",
    "sg:postcode":"37167",
    "sg:province":"TN",
    "wof:name":"Hangman",
    "wof:placetype":"venue"
},
  "geometry": {"coordinates":[-86.48695499999999,35.945995],"type":"Point"}
}