{
  "type": "Feature",
  "properties": {
    "iso:country":"US",
    "sg:address":"2755 Colony Park Dr",
    "sg:city":"Memphis",
    "sg:classifiers":[
        {
            "category":"Organizations",
            "subcategory":"Religious Organization",
            "type":"Services"
        }
    ],
    "sg:phone":"+1 901 541 6022",
    "sg:postcode":"38118",
    "sg:province":"TN",
    "sg:tags":[
        "place",
        "worship",
        "church"
    ],
    "sg:website":"http://www.gideons.org",
    "wof:name":"Gideons International",
    "wof:placetype":"venue"
},
  "geometry": {"coordinates":[-89.922539,35.073391],"type":"Point"}
}