{
  "type": "Feature",
  "properties": {
    "iso:country":"US",
    "sg:address":"208 Industrial Dr",
    "sg:city":"Mountain City",
    "sg:classifiers":[
        {
            "category":"Professional",
            "type":"Services"
        }
    ],
    "sg:phone":"+1 423 727 4464",
    "sg:postcode":"37683",
    "sg:province":"TN",
    "wof:name":"Picture Perfect",
    "wof:placetype":"venue"
},
  "geometry": {"coordinates":[-81.800411,36.439097],"type":"Point"}
}