{
  "type": "Feature",
  "properties": {
    "iso:country":"US",
    "sg:address":"4796 State Hwy 100",
    "sg:city":"Lyles",
    "sg:classifiers":[
        {
            "category":"Food & Beverages",
            "subcategory":"Groceries & Convenience Stores",
            "type":"Retail Goods"
        }
    ],
    "sg:phone":"+1 931 670 4472",
    "sg:postcode":"37098",
    "sg:province":"TN",
    "sg:tags":[
        "grocer"
    ],
    "wof:name":"Patton's Park Bi-Rite Market",
    "wof:placetype":"venue"
},
  "geometry": {"coordinates":[-87.335542,35.905422],"type":"Point"}
}