{
  "type": "Feature",
  "properties": {
    "iso:country":"US",
    "sg:address":"8515 Sawyer Brown Rd",
    "sg:city":"Nashville",
    "sg:classifiers":[
        {
            "category":"Building & Trades",
            "subcategory":"Construction",
            "type":"Services"
        }
    ],
    "sg:phone":"+1 615 646 2700",
    "sg:postcode":"37221",
    "sg:province":"TN",
    "sg:tags":[
        "house"
    ],
    "wof:name":"Caste Home Rehabers",
    "wof:placetype":"venue"
},
  "geometry": {"coordinates":[-86.948234,36.069908],"type":"Point"}
}