{
  "type": "Feature",
  "properties": {
    "iso:country":"US",
    "sg:address":"744 Stonetrace Dr",
    "sg:city":"Murfreesboro",
    "sg:classifiers":[
        {
            "category":"Professional",
            "subcategory":"Management & Consulting",
            "type":"Services"
        }
    ],
    "sg:phone":"+1 615 849 9674",
    "sg:postcode":"37128",
    "sg:province":"TN",
    "sg:tags":[
        "consultant",
        "business"
    ],
    "sg:website":"www.galestoner.com",
    "wof:name":"GALESTONER.COM",
    "wof:placetype":"venue"
},
  "geometry": {"coordinates":[-86.443726,35.838657],"type":"Point"}
}