{
  "type": "Feature",
  "properties": {
    "iso:country":"US",
    "sg:address":"123 Stonebrook Pl",
    "sg:city":"Jackson",
    "sg:classifiers":[
        {
            "category":"Restaurant",
            "type":"Food & Drink"
        }
    ],
    "sg:menulink":"http://www.allmenus.com/tn/jackson/127936-red-lobster/menu/",
    "sg:phone":"+1 731 664 8655",
    "sg:postcode":"38305",
    "sg:province":"TN",
    "sg:tags":[
        "seafood",
        "american"
    ],
    "wof:name":"Red Lobster",
    "wof:placetype":"venue"
},
  "geometry": {"coordinates":[-88.85652399999999,35.685787],"type":"Point"}
}