{
  "type": "Feature",
  "properties": {
    "iso:country":"US",
    "sg:address":"2000 Johnson Industrial Blvd",
    "sg:city":"Nolensville",
    "sg:classifiers":[
        {
            "category":"Utilities",
            "subcategory":"Water",
            "type":"Services"
        }
    ],
    "sg:phone":"+1 615 776 2511",
    "sg:postcode":"37135",
    "sg:province":"TN",
    "sg:tags":[
        "company",
        "sewage"
    ],
    "wof:name":"College Grove Water Utility",
    "wof:placetype":"venue"
},
  "geometry": {"coordinates":[-86.66606899999999,35.956901],"type":"Point"}
}