{
  "type": "Feature",
  "properties": {
    "iso:country":"US",
    "sg:address":"112 Masters Rd",
    "sg:city":"Hixson",
    "sg:classifiers":[
        {
            "category":"Wholesale",
            "subcategory":"Non-durable Goods",
            "type":"Manufacturing & Wholesale Goods"
        }
    ],
    "sg:phone":"+1 423 842 3065",
    "sg:postcode":"37343",
    "sg:province":"TN",
    "sg:tags":[
        "item",
        "representative",
        "promotional"
    ],
    "wof:name":"Gibson Advertising Specialties",
    "wof:placetype":"venue"
},
  "geometry": {"coordinates":[-85.214201,35.152518],"type":"Point"}
}