{
  "type": "Feature",
  "properties": {
    "addr:full":"40 Donelson St Nashville TN 37210",
    "addr:housenumber":"40",
    "addr:postcode":"37210",
    "addr:street":"Donelson St",
    "iso:country":"US",
    "sg:address":"40 Donelson St",
    "sg:city":"Nashville",
    "sg:classifiers":[
        {
            "category":"Restaurant",
            "type":"Food & Drink"
        }
    ],
    "sg:phone":"+1 615 885 9723",
    "sg:postcode":"37210",
    "sg:province":"TN",
    "sg:tags":[
        "eating"
    ],
    "wof:name":"Waffle House",
    "wof:placetype":"venue"
},
  "geometry": {"coordinates":[-86.75547899999999,36.148942],"type":"Point"}
}