{
  "type": "Feature",
  "properties": {
    "iso:country":"US",
    "sg:address":"2830 Stage Center Cove",
    "sg:city":"Memphis",
    "sg:classifiers":[
        {
            "category":"Shopping",
            "subcategory":"Gifts & Souvenirs",
            "type":"Retail Goods"
        }
    ],
    "sg:phone":"+1 901 382 9902",
    "sg:postcode":"38134",
    "sg:province":"TN",
    "wof:name":"Ldh Gift and Decorating",
    "wof:placetype":"venue"
},
  "geometry": {"coordinates":[-89.860094,35.20294],"type":"Point"}
}