{
  "type": "Feature",
  "properties": {
    "iso:country":"US",
    "sg:address":"1209 Sparta St",
    "sg:city":"Mc Minnville",
    "sg:classifiers":[
        {
            "category":"Personal",
            "subcategory":"Beauty Salon",
            "type":"Services"
        }
    ],
    "sg:phone":"+1 931 473 2589",
    "sg:postcode":"37110",
    "sg:province":"TN",
    "sg:tags":[
        "shop"
    ],
    "wof:name":"Be Lovely",
    "wof:placetype":"venue"
},
  "geometry": {"coordinates":[-85.755134,35.691004],"type":"Point"}
}