{
  "type": "Feature",
  "properties": {
    "iso:country":"US",
    "sg:address":"610 Highland Rd",
    "sg:city":"Westmoreland",
    "sg:classifiers":[
        {
            "category":"Organizations",
            "subcategory":"Religious Organization",
            "type":"Services"
        }
    ],
    "sg:phone":"+1 615 888 2700",
    "sg:postcode":"37186",
    "sg:province":"TN",
    "sg:tags":[
        "church"
    ],
    "wof:name":"Highland Church-The Nazarene",
    "wof:placetype":"venue"
},
  "geometry": {"coordinates":[-86.380928,36.607697],"type":"Point"}
}