{
  "type": "Feature",
  "properties": {
    "iso:country":"US",
    "sg:address":"130 Trousdale Ferry Pike",
    "sg:city":"Lebanon",
    "sg:classifiers":[
        {
            "category":"Retail",
            "subcategory":"Funeral Services",
            "type":"Services"
        }
    ],
    "sg:phone":"+1 615 444 9494",
    "sg:postcode":"37087",
    "sg:province":"TN",
    "wof:name":"Saddler Funeral Home",
    "wof:placetype":"venue"
},
  "geometry": {"coordinates":[-86.27343,36.208823],"type":"Point"}
}