{
  "type": "Feature",
  "properties": {
    "iso:country":"US",
    "sg:address":"3512 Old Lowes Ferry Rd",
    "sg:city":"Louisville",
    "sg:classifiers":[
        {
            "category":"Wholesale",
            "subcategory":"Vending Machines",
            "type":"Manufacturing & Wholesale Goods"
        }
    ],
    "sg:phone":"+1 865 983 3310",
    "sg:postcode":"37777",
    "sg:province":"TN",
    "wof:name":"Bowen Vending Co",
    "wof:placetype":"venue"
},
  "geometry": {"coordinates":[-84.096295,35.82342],"type":"Point"}
}