{
  "type": "Feature",
  "properties": {
    "addr:full":"3895 E Christine Gardens Memphis TN 38118",
    "addr:housenumber":"3895",
    "addr:postcode":"38118",
    "addr:street":"E Christine Gardens",
    "iso:country":"US",
    "sg:address":"3895 E Christine Gardens",
    "sg:city":"Memphis",
    "sg:classifiers":[
        {
            "category":"Professional",
            "subcategory":"Management & Consulting",
            "type":"Services"
        }
    ],
    "sg:phone":"+1 901 794 7199",
    "sg:postcode":"38118",
    "sg:province":"TN",
    "sg:tags":[
        "consultant",
        "business"
    ],
    "wof:name":"Eagle Enterprise Corp",
    "wof:placetype":"venue"
},
  "geometry": {"coordinates":[-89.952232,35.041685],"type":"Point"}
}