{
  "type": "Feature",
  "properties": {
    "addr:full":"6160 Shallowford Rd Chattanooga TN 37421",
    "addr:housenumber":"6160",
    "addr:postcode":"37421",
    "addr:street":"Shallowford Rd",
    "iso:country":"US",
    "sg:address":"6160 Shallowford Rd",
    "sg:city":"Chattanooga",
    "sg:classifiers":[
        {
            "category":"Banks & Credit Unions",
            "subcategory":"Bank",
            "type":"Services"
        }
    ],
    "sg:phone":"+1 423 499 9915",
    "sg:postcode":"37421",
    "sg:province":"TN",
    "sg:tags":[
        "loan",
        "real estate"
    ],
    "sg:website":"www.wellsfargo.com",
    "wof:name":"Wells Fargo Home Mortgage",
    "wof:placetype":"venue"
},
  "geometry": {"coordinates":[-85.182597,35.053137],"type":"Point"}
}