{
  "type": "Feature",
  "properties": {
    "addr:full":"128 Old Cosby Hwy Newport TN 37821",
    "addr:housenumber":"128",
    "addr:postcode":"37821",
    "addr:street":"Old Cosby Hwy",
    "iso:country":"US",
    "sg:address":"128 Old Cosby Hwy",
    "sg:city":"Newport",
    "sg:classifiers":[
        {
            "category":"Wholesale",
            "subcategory":"Groceries",
            "type":"Manufacturing & Wholesale Goods"
        }
    ],
    "sg:phone":"+1 423 623 1387",
    "sg:postcode":"37821",
    "sg:province":"TN",
    "sg:tags":[
        "food",
        "product"
    ],
    "wof:name":"Cocke County Wholesale Co",
    "wof:placetype":"venue"
},
  "geometry": {"coordinates":[-83.19458899999999,35.965685],"type":"Point"}
}