{
  "type": "Feature",
  "properties": {
    "addr:full":"8030 Dodson Rd Knoxville TN 37920",
    "addr:housenumber":"8030",
    "addr:postcode":"37920",
    "addr:street":"Dodson Rd",
    "iso:country":"US",
    "sg:address":"8030 Dodson Rd",
    "sg:city":"Knoxville",
    "sg:classifiers":[
        {
            "category":"Organizations",
            "subcategory":"Non-profit Organization",
            "type":"Services"
        }
    ],
    "sg:phone":"+1 865 577 0757",
    "sg:postcode":"37920",
    "sg:province":"TN",
    "wof:name":"Volunteer State Veterans Mmrl",
    "wof:placetype":"venue"
},
  "geometry": {"coordinates":[-83.773991,35.929564],"type":"Point"}
}