{
  "type": "Feature",
  "properties": {
    "iso:country":"US",
    "sg:address":"815 Gallatin Pike S",
    "sg:city":"Madison",
    "sg:classifiers":[
        {
            "category":"Freight",
            "type":"Transportation"
        }
    ],
    "sg:phone":"+1 615 865 7959",
    "sg:postcode":"37115",
    "sg:province":"TN",
    "sg:tags":[
        "commercial",
        "storage"
    ],
    "wof:name":"Madison Self Serve",
    "wof:placetype":"venue"
},
  "geometry": {"coordinates":[-86.71670899999999,36.25354],"type":"Point"}
}