{
  "type": "Feature",
  "properties": {
    "iso:country":"US",
    "sg:address":"269 Germantown Bend Cove",
    "sg:city":"Cordova",
    "sg:classifiers":[
        {
            "category":"Real Estate",
            "subcategory":"Real Estate Agent",
            "type":"Services"
        }
    ],
    "sg:phone":"+1 901 751 2122",
    "sg:postcode":"38018",
    "sg:province":"TN",
    "wof:name":"Bill King Co Realtor",
    "wof:placetype":"venue"
},
  "geometry": {"coordinates":[-89.79838100000001,35.123571],"type":"Point"}
}