{
  "type": "Feature",
  "properties": {
    "addr:full":"304 S Broadway Portland TN 37148",
    "addr:housenumber":"304",
    "addr:postcode":"37148",
    "addr:street":"S Broadway",
    "iso:country":"US",
    "sg:address":"304 S Broadway",
    "sg:city":"Portland",
    "sg:classifiers":[
        {
            "category":"Shopping",
            "subcategory":"Pharmacy",
            "type":"Retail Goods"
        }
    ],
    "sg:phone":"+1 615 323 0046",
    "sg:postcode":"37148",
    "sg:province":"TN",
    "sg:tags":[
        "drug",
        "store"
    ],
    "wof:name":"CVS",
    "wof:placetype":"venue"
},
  "geometry": {"coordinates":[-86.513161,36.573233],"type":"Point"}
}