{
  "type": "Feature",
  "properties": {
    "iso:country":"US",
    "sg:address":"108 Harding Pl",
    "sg:city":"Nashville",
    "sg:classifiers":[
        {
            "category":"Health Services",
            "subcategory":"Health Practitioner",
            "type":"Services"
        }
    ],
    "sg:phone":"+1 615 662 2427",
    "sg:postcode":"37205",
    "sg:province":"TN",
    "sg:tags":[
        "psychologist"
    ],
    "wof:name":"Daniel L Rock PHD",
    "wof:placetype":"venue"
},
  "geometry": {"coordinates":[-86.868031,36.101604],"type":"Point"}
}