{
  "type": "Feature",
  "properties": {
    "addr:full":"2901 Glencliff Rd Nashville TN 37211",
    "addr:housenumber":"2901",
    "addr:postcode":"37211",
    "addr:street":"Glencliff Rd",
    "iso:country":"US",
    "sg:address":"2901 Glencliff Rd",
    "sg:city":"Nashville",
    "sg:classifiers":[
        {
            "category":"Organizations",
            "subcategory":"Religious Organization",
            "type":"Services"
        }
    ],
    "sg:phone":"+1 615 833 5010",
    "sg:postcode":"37211",
    "sg:province":"TN",
    "sg:tags":[
        "church"
    ],
    "wof:name":"Glencliff United Methodist Chr",
    "wof:placetype":"venue"
},
  "geometry": {"coordinates":[-86.71996900000001,36.111917],"type":"Point"}
}