{
  "type": "Feature",
  "properties": {
    "iso:country":"US",
    "sg:address":"38 Dry Weakley Rd",
    "sg:city":"Ethridge",
    "sg:classifiers":[
        {
            "category":"Wholesale",
            "subcategory":"Machinery & Supplies",
            "type":"Manufacturing & Wholesale Goods"
        }
    ],
    "sg:phone":"+1 931 829 2603",
    "sg:postcode":"38456",
    "sg:province":"TN",
    "sg:tags":[
        "farm",
        "equipment"
    ],
    "wof:name":"Summertown Equipment Sales",
    "wof:placetype":"venue"
},
  "geometry": {"coordinates":[-87.29321299999999,35.320015],"type":"Point"}
}