{
  "type": "Feature",
  "properties": {
    "iso:country":"US",
    "sg:address":"101 Short St",
    "sg:city":"Lebanon",
    "sg:classifiers":[
        {
            "category":"Shopping",
            "subcategory":"Used Merchandise",
            "type":"Retail Goods"
        }
    ],
    "sg:phone":"+1 615 449 5954",
    "sg:postcode":"37087",
    "sg:province":"TN",
    "sg:tags":[
        "antique"
    ],
    "wof:name":"Lebanon Antique Mall",
    "wof:placetype":"venue"
},
  "geometry": {"coordinates":[-86.291541,36.20339],"type":"Point"}
}