{
  "type": "Feature",
  "properties": {
    "iso:country":"US",
    "sg:address":"2525 Park Green Ln",
    "sg:city":"Old Hickory",
    "sg:classifiers":[
        {
            "category":"Wholesale",
            "subcategory":"Machinery & Supplies",
            "type":"Manufacturing & Wholesale Goods"
        }
    ],
    "sg:phone":"+1 615 847 0689",
    "sg:postcode":"37138",
    "sg:province":"TN",
    "wof:name":"Deere & Company",
    "wof:placetype":"venue"
},
  "geometry": {"coordinates":[-86.657584,36.248174],"type":"Point"}
}