{
  "type": "Feature",
  "properties": {
    "addr:full":"4920 Ross Rd Memphis TN 38141",
    "addr:housenumber":"4920",
    "addr:postcode":"38141",
    "addr:street":"Ross Rd",
    "iso:country":"US",
    "sg:address":"4920 Ross Rd",
    "sg:city":"Memphis",
    "sg:classifiers":[
        {
            "category":"Place Of Worship",
            "subcategory":"Church",
            "type":"Public Place"
        },
        {
            "category":"Place Of Worship",
            "type":"Public Place"
        }
    ],
    "sg:phone":"+1 901 363 7439",
    "sg:postcode":"38141",
    "sg:province":"TN",
    "sg:tags":[
        "churches-church",
        "christ"
    ],
    "sg:website":"http://www.rossroadchurch.org",
    "wof:name":"Ross Road Church Of Christ",
    "wof:placetype":"venue"
},
  "geometry": {"coordinates":[-89.83980099999999,35.01436],"type":"Point"}
}