{
  "type": "Feature",
  "properties": {
    "iso:country":"US",
    "sg:address":"2825 New Center Dr",
    "sg:city":"Sevierville",
    "sg:classifiers":[
        {
            "category":"Personal",
            "subcategory":"Beauty Salon",
            "type":"Services"
        }
    ],
    "sg:phone":"+1 865 428 1986",
    "sg:postcode":"37876",
    "sg:province":"TN",
    "sg:tags":[
        "shop"
    ],
    "wof:name":"New Center Hair Salon",
    "wof:placetype":"venue"
},
  "geometry": {"coordinates":[-83.437572,35.882373],"type":"Point"}
}