{
  "type": "Feature",
  "properties": {
    "addr:full":"1982 N Highland Ave Jackson TN 38305",
    "addr:housenumber":"1982",
    "addr:postcode":"38305",
    "addr:street":"N Highland Ave",
    "iso:country":"US",
    "sg:address":"1982 N Highland Ave",
    "sg:city":"Jackson",
    "sg:classifiers":[
        {
            "category":"Autos & Motor Vehicles",
            "subcategory":"Auto Supplies",
            "type":"Retail Goods"
        }
    ],
    "sg:phone":"+1 731 668 8300",
    "sg:postcode":"38305",
    "sg:province":"TN",
    "sg:tags":[
        "tire"
    ],
    "wof:name":"Goodyear Auto Svc Ctr",
    "wof:placetype":"venue"
},
  "geometry": {"coordinates":[-88.828107,35.655116],"type":"Point"}
}