{
  "type": "Feature",
  "properties": {
    "iso:country":"US",
    "sg:address":"276 Mount Zion Rd NW",
    "sg:city":"Georgetown",
    "sg:classifiers":[
        {
            "category":"Retail",
            "subcategory":"Auto Repair",
            "type":"Services"
        }
    ],
    "sg:phone":"+1 423 478 5786",
    "sg:postcode":"37336",
    "sg:province":"TN",
    "sg:tags":[
        "shop",
        "industrial",
        "mfg",
        "automobile",
        "machine",
        "machinery",
        "automotive"
    ],
    "wof:name":"Rick's Automotive Machine Shop",
    "wof:placetype":"venue"
},
  "geometry": {"coordinates":[-84.92374700000001,35.27474],"type":"Point"}
}