{
  "type": "Feature",
  "properties": {
    "iso:country":"US",
    "sg:address":"6576 E Brainerd Rd",
    "sg:city":"Chattanooga",
    "sg:classifiers":[
        {
            "category":"Real Estate",
            "subcategory":"Real Estate Services",
            "type":"Services"
        }
    ],
    "sg:phone":"+1 423 855 1719",
    "sg:postcode":"37421",
    "sg:province":"TN",
    "sg:tags":[
        "company",
        "title"
    ],
    "wof:name":"Real Estate Loan Svc",
    "wof:placetype":"venue"
},
  "geometry": {"coordinates":[-85.185867,35.018165],"type":"Point"}
}