{
  "type": "Feature",
  "properties": {
    "iso:country":"US",
    "sg:address":"2774 Bartlett Rd",
    "sg:city":"Memphis",
    "sg:classifiers":[
        {
            "category":"Personal",
            "subcategory":"Beauty Salon",
            "type":"Services"
        }
    ],
    "sg:phone":"+1 901 372 2881",
    "sg:postcode":"38134",
    "sg:province":"TN",
    "wof:name":"Hair Garden",
    "wof:placetype":"venue"
},
  "geometry": {"coordinates":[-89.86846300000001,35.202642],"type":"Point"}
}