{
  "type": "Feature",
  "properties": {
    "iso:country":"US",
    "sg:address":"545 Mainstream Dr",
    "sg:city":"Nashville",
    "sg:classifiers":[
        {
            "category":"Utilities",
            "subcategory":"Cable",
            "type":"Services"
        }
    ],
    "sg:phone":"+1 931 645 8840",
    "sg:postcode":"37228",
    "sg:province":"TN",
    "sg:tags":[
        "television"
    ],
    "wof:name":"Charter Cmmnctons Holdings LLC",
    "wof:placetype":"venue"
},
  "geometry": {"coordinates":[-86.811386,36.200021],"type":"Point"}
}