{
  "type": "Feature",
  "properties": {
    "iso:country":"US",
    "sg:address":"2134 Hartland Rd",
    "sg:city":"Franklin",
    "sg:classifiers":[
        {
            "category":"Professional",
            "subcategory":"Business Services",
            "type":"Services"
        }
    ],
    "sg:phone":"+1 615 791 1034",
    "sg:postcode":"37069",
    "sg:province":"TN",
    "wof:name":"Qsp Inc",
    "wof:placetype":"venue"
},
  "geometry": {"coordinates":[-86.87179,35.984396],"type":"Point"}
}