{
  "type": "Feature",
  "properties": {
    "iso:country":"US",
    "sg:address":"2840 S Church St",
    "sg:city":"Murfreesboro",
    "sg:classifiers":[
        {
            "category":"Wholesale",
            "subcategory":"Machinery & Supplies",
            "type":"Manufacturing & Wholesale Goods"
        }
    ],
    "sg:phone":"+1 615 907 3355",
    "sg:postcode":"37127",
    "sg:province":"TN",
    "sg:tags":[
        "equipment",
        "hydraulic"
    ],
    "wof:name":"Taiyo America Inc",
    "wof:placetype":"venue"
},
  "geometry": {"coordinates":[-86.398366,35.801654],"type":"Point"}
}