{
  "type": "Feature",
  "properties": {
    "iso:country":"US",
    "sg:address":"6001 Old Hickory Blvd",
    "sg:city":"Hermitage",
    "sg:classifiers":[
        {
            "category":"Real Estate",
            "subcategory":"Real Estate Operator",
            "type":"Services"
        }
    ],
    "sg:phone":"+1 615 579 3153",
    "sg:postcode":"37076",
    "sg:province":"TN",
    "sg:tags":[
        "building",
        "nonresidential"
    ],
    "wof:name":"D&E Auditorium Seating",
    "wof:placetype":"venue"
},
  "geometry": {"coordinates":[-86.59760799999999,36.163948],"type":"Point"}
}