{
  "type": "Feature",
  "properties": {
    "iso:country":"US",
    "sg:address":"200 Crockett St",
    "sg:city":"Rogersville",
    "sg:classifiers":[
        {
            "category":"Recreation",
            "type":"Entertainment"
        }
    ],
    "sg:phone":"+1 423 272 1961",
    "sg:postcode":"37857",
    "sg:province":"TN",
    "sg:tags":[
        "attraction",
        "tourist"
    ],
    "wof:name":"Crockett Spring Park",
    "wof:placetype":"venue"
},
  "geometry": {"coordinates":[-83.008084,36.403666],"type":"Point"}
}