{
  "type": "Feature",
  "properties": {
    "addr:full":"600 Volunteer Pkwy Bristol TN 37620",
    "addr:housenumber":"600",
    "addr:postcode":"37620",
    "addr:street":"Volunteer Pkwy",
    "iso:country":"US",
    "sg:address":"600 Volunteer Pkwy",
    "sg:city":"Bristol",
    "sg:classifiers":[
        {
            "category":"Restaurant",
            "type":"Food & Drink"
        }
    ],
    "sg:menulink":"http://www.allmenus.com/tn/bristol/84307-papa-johns-pizza/menu/",
    "sg:phone":"+1 423 968 7272",
    "sg:postcode":"37620",
    "sg:province":"TN",
    "sg:tags":[
        "american",
        "pizza"
    ],
    "wof:name":"Papa John's Pizza",
    "wof:placetype":"venue"
},
  "geometry": {"coordinates":[-82.185715,36.585873],"type":"Point"}
}