{
  "type": "Feature",
  "properties": {
    "addr:full":"51 Depot St Friendship TN 38034",
    "addr:housenumber":"51",
    "addr:postcode":"38034",
    "addr:street":"Depot St",
    "iso:country":"US",
    "sg:address":"51 Depot St",
    "sg:city":"Friendship",
    "sg:classifiers":[
        {
            "category":"Retail",
            "subcategory":"Auto Repair",
            "type":"Services"
        }
    ],
    "sg:phone":"+1 731 677 2282",
    "sg:postcode":"38034",
    "sg:province":"TN",
    "sg:tags":[
        "body"
    ],
    "wof:name":"Crawford & Son Upholstery",
    "wof:placetype":"venue"
},
  "geometry": {"coordinates":[-89.240725,35.947748],"type":"Point"}
}