{
  "type": "Feature",
  "properties": {
    "addr:full":"7212 Kingston Pike Knoxville TN 37919",
    "addr:housenumber":"7212",
    "addr:postcode":"37919",
    "addr:street":"Kingston Pike",
    "iso:country":"US",
    "sg:address":"7212 Kingston Pike",
    "sg:city":"Knoxville",
    "sg:classifiers":[
        {
            "category":"Utilities",
            "subcategory":"Mobile Phone",
            "type":"Services"
        }
    ],
    "sg:phone":"+1 865 588 2355",
    "sg:postcode":"37919",
    "sg:province":"TN",
    "sg:tags":[
        "communication",
        "radiotelephone"
    ],
    "wof:name":"Cingular Wireless",
    "wof:placetype":"venue"
},
  "geometry": {"coordinates":[-84.029372,35.930378],"type":"Point"}
}