{
  "type": "Feature",
  "properties": {
    "iso:country":"US",
    "sg:address":"8088 Kingston Pike",
    "sg:city":"Knoxville",
    "sg:classifiers":[
        {
            "category":"Restaurant",
            "type":"Food & Drink"
        }
    ],
    "sg:phone":"+1 865 531 5616",
    "sg:postcode":"37919",
    "sg:province":"TN",
    "wof:name":"Roxy",
    "wof:placetype":"venue"
},
  "geometry": {"coordinates":[-84.056781,35.923679],"type":"Point"}
}