{
  "type": "Feature",
  "properties": {
    "iso:country":"US",
    "sg:address":"1203 Old Hwy 68",
    "sg:city":"Sweetwater",
    "sg:classifiers":[
        {
            "category":"Restaurant",
            "type":"Food & Drink"
        }
    ],
    "sg:phone":"+1 423 337 9600",
    "sg:postcode":"37874",
    "sg:province":"TN",
    "wof:name":"Stop-In",
    "wof:placetype":"venue"
},
  "geometry": {"coordinates":[-84.436758,35.592839],"type":"Point"}
}