{
  "type": "Feature",
  "properties": {
    "iso:country":"US",
    "sg:address":"372 Keel Hollow Rd",
    "sg:city":"Dover",
    "sg:classifiers":[
        {
            "category":"Building & Trades",
            "subcategory":"Construction",
            "type":"Services"
        }
    ],
    "sg:phone":"+1 931 232 2230",
    "sg:postcode":"37058",
    "sg:province":"TN",
    "sg:tags":[
        "house"
    ],
    "wof:name":"McElroy Construction",
    "wof:placetype":"venue"
},
  "geometry": {"coordinates":[-87.892093,36.464344],"type":"Point"}
}