{
  "type": "Feature",
  "properties": {
    "iso:country":"US",
    "sg:address":"4521 Aldersgate Rd",
    "sg:city":"Memphis",
    "sg:classifiers":[
        {
            "category":"Real Estate",
            "subcategory":"Real Estate Agent",
            "type":"Services"
        }
    ],
    "sg:phone":"+1 901 789 2787",
    "sg:postcode":"38117",
    "sg:province":"TN",
    "wof:name":"Nu-Way Equity",
    "wof:placetype":"venue"
},
  "geometry": {"coordinates":[-89.909947,35.121601],"type":"Point"}
}