{
  "type": "Feature",
  "properties": {
    "iso:country":"US",
    "sg:address":"116 Concord Rd",
    "sg:city":"Knoxville",
    "sg:classifiers":[
        {
            "category":"Health Services",
            "subcategory":"Doctor",
            "type":"Services"
        }
    ],
    "sg:phone":"+1 865 675 4342",
    "sg:postcode":"37934",
    "sg:province":"TN",
    "sg:tags":[
        "physician",
        "family",
        "practice",
        "surgeons",
        "medicine"
    ],
    "sg:website":"http://www.fhcpllc.com",
    "wof:name":"Family Health Center PLLC",
    "wof:placetype":"venue"
},
  "geometry": {"coordinates":[-84.15255000000001,35.883272],"type":"Point"}
}