{
  "type": "Feature",
  "properties": {
    "addr:full":"3869 Dovefield Ct Louisville TN 37777",
    "addr:housenumber":"3869",
    "addr:postcode":"37777",
    "addr:street":"Dovefield Ct",
    "iso:country":"US",
    "sg:address":"3869 Dovefield Ct",
    "sg:city":"Louisville",
    "sg:classifiers":[
        {
            "category":"Professional",
            "type":"Services"
        }
    ],
    "sg:phone":"+1 865 599 6379",
    "sg:postcode":"37777",
    "sg:province":"TN",
    "sg:tags":[
        "establishment"
    ],
    "wof:name":"Nu-Finish",
    "wof:placetype":"venue"
},
  "geometry": {"coordinates":[-83.992118,35.851354],"type":"Point"}
}