{
  "type": "Feature",
  "properties": {
    "iso:country":"US",
    "sg:address":"505 Webb Mill Bridge Rd",
    "sg:city":"Hornsby",
    "sg:classifiers":[
        {
            "category":"Freight",
            "type":"Transportation"
        }
    ],
    "sg:phone":"+1 731 658 5094",
    "sg:postcode":"38044",
    "sg:province":"TN",
    "sg:tags":[
        "operator",
        "local",
        "trucking"
    ],
    "wof:name":"Hodge Trucking",
    "wof:placetype":"venue"
},
  "geometry": {"coordinates":[-88.79405800000001,35.200901],"type":"Point"}
}