{
  "type": "Feature",
  "properties": {
    "iso:country":"US",
    "sg:address":"2682 Lamar Ave",
    "sg:city":"Memphis",
    "sg:classifiers":[
        {
            "category":"Manufacturing",
            "subcategory":"Food",
            "type":"Manufacturing & Wholesale Goods"
        }
    ],
    "sg:phone":"+1 800 464 3960",
    "sg:postcode":"38114",
    "sg:province":"TN",
    "sg:tags":[
        "product",
        "mfg"
    ],
    "wof:name":"Earthgrains Baking Co",
    "wof:placetype":"venue"
},
  "geometry": {"coordinates":[-89.973664,35.098567],"type":"Point"}
}