{
  "type": "Feature",
  "properties": {
    "iso:country":"US",
    "sg:address":"107 McFarlin Rd",
    "sg:city":"Murfreesboro",
    "sg:classifiers":[
        {
            "category":"Building & Trades",
            "subcategory":"Construction",
            "type":"Services"
        }
    ],
    "sg:phone":"+1 615 907 5792",
    "sg:postcode":"37130",
    "sg:province":"TN",
    "sg:tags":[
        "resurfacing",
        "laying",
        "refinishing",
        "floor"
    ],
    "wof:name":"J J's Hardwood Floors",
    "wof:placetype":"venue"
},
  "geometry": {"coordinates":[-86.349395,35.839162],"type":"Point"}
}