{
  "type": "Feature",
  "properties": {
    "iso:country":"US",
    "sg:address":"5621 Mouse Creek Rd NW",
    "sg:city":"Cleveland",
    "sg:classifiers":[
        {
            "category":"Retail",
            "subcategory":"Laundry & Dry Cleaning",
            "type":"Services"
        }
    ],
    "sg:phone":"+1 423 336 5769",
    "sg:postcode":"37312",
    "sg:province":"TN",
    "sg:tags":[
        "cleaners",
        "rug",
        "carpet"
    ],
    "wof:name":"Coleman Deep Steam",
    "wof:placetype":"venue"
},
  "geometry": {"coordinates":[-84.84956099999999,35.234509],"type":"Point"}
}