{
  "type": "Feature",
  "properties": {
    "iso:country":"US",
    "sg:address":"5921 New Hope Ct",
    "sg:city":"Hermitage",
    "sg:classifiers":[
        {
            "category":"Professional",
            "subcategory":"Computer Services",
            "type":"Services"
        }
    ],
    "sg:phone":"+1 615 902 9789",
    "sg:postcode":"37076",
    "sg:province":"TN",
    "sg:tags":[
        "datum"
    ],
    "wof:name":"Computer Data Services",
    "wof:placetype":"venue"
},
  "geometry": {"coordinates":[-86.587175,36.163664],"type":"Point"}
}