{
  "type": "Feature",
  "properties": {
    "addr:full":"321 Maple St Athens TN 37303",
    "addr:housenumber":"321",
    "addr:postcode":"37303",
    "addr:street":"Maple St",
    "iso:country":"US",
    "sg:address":"321 Maple St",
    "sg:city":"Athens",
    "sg:classifiers":[
        {
            "category":"Banks & Credit Unions",
            "subcategory":"Bank",
            "type":"Services"
        }
    ],
    "sg:phone":"+1 423 746 4890",
    "sg:postcode":"37303",
    "sg:province":"TN",
    "sg:tags":[
        "loan",
        "real estate"
    ],
    "sg:website":"www.heightsfinance.com",
    "wof:name":"Heights Finance Corp",
    "wof:placetype":"venue"
},
  "geometry": {"coordinates":[-84.613347,35.448208],"type":"Point"}
}