{
  "type": "Feature",
  "properties": {
    "iso:country":"US",
    "sg:address":"2004 American Way",
    "sg:city":"Kingsport",
    "sg:classifiers":[
        {
            "category":"Insurance",
            "subcategory":"Insurance Agent",
            "type":"Services"
        }
    ],
    "sg:phone":"+1 423 246 6125",
    "sg:postcode":"37660",
    "sg:province":"TN",
    "wof:name":"American General Life Ins Co",
    "wof:placetype":"venue"
},
  "geometry": {"coordinates":[-82.51078699999999,36.544467],"type":"Point"}
}