{
  "type": "Feature",
  "properties": {
    "iso:country":"US",
    "sg:address":"418 Frank Stanton Rd",
    "sg:city":"Limestone",
    "sg:classifiers":[
        {
            "category":"Farming",
            "subcategory":"Dairy Farm",
            "type":"Manufacturing & Wholesale Goods"
        }
    ],
    "sg:phone":"+1 423 257 6879",
    "sg:postcode":"37681",
    "sg:province":"TN",
    "wof:name":"Moore Dairy",
    "wof:placetype":"venue"
},
  "geometry": {"coordinates":[-82.598525,36.180663],"type":"Point"}
}