{
  "type": "Feature",
  "properties": {
    "iso:country":"US",
    "sg:address":"953 E Moody Ave",
    "sg:city":"Knoxville",
    "sg:classifiers":[
        {
            "category":"Recreation",
            "type":"Entertainment"
        }
    ],
    "sg:phone":"+1 865 577 0651",
    "sg:postcode":"37920",
    "sg:province":"TN",
    "sg:tags":[
        "center"
    ],
    "wof:name":"Cecil WEBB Recreation Ctr",
    "wof:placetype":"venue"
},
  "geometry": {"coordinates":[-83.89874,35.944016],"type":"Point"}
}