{
  "type": "Feature",
  "properties": {
    "iso:country":"US",
    "sg:address":"113 Barksdale Ct",
    "sg:city":"Memphis",
    "sg:classifiers":[
        {
            "category":"Organizations",
            "subcategory":"Community Association",
            "type":"Services"
        }
    ],
    "sg:phone":"+1 901 274 9963",
    "sg:postcode":"38104",
    "sg:province":"TN",
    "wof:name":"Noble Krewe of Hathor",
    "wof:placetype":"venue"
},
  "geometry": {"coordinates":[-89.998262,35.14069],"type":"Point"}
}