{
  "type": "Feature",
  "properties": {
    "iso:country":"US",
    "sg:address":"5502 Laurie Ln",
    "sg:city":"Memphis",
    "sg:classifiers":[
        {
            "category":"Banks & Credit Unions",
            "subcategory":"Investment Brokerage",
            "type":"Services"
        }
    ],
    "sg:phone":"+1 901 682 2949",
    "sg:postcode":"38120",
    "sg:province":"TN",
    "sg:tags":[
        "stock",
        "bond"
    ],
    "wof:name":"Schultz Investments",
    "wof:placetype":"venue"
},
  "geometry": {"coordinates":[-89.88365400000001,35.119693],"type":"Point"}
}