{
  "type": "Feature",
  "properties": {
    "iso:country":"US",
    "sg:address":"53 Century Blvd",
    "sg:city":"Nashville",
    "sg:classifiers":[
        {
            "category":"Wholesale",
            "subcategory":"Electrical",
            "type":"Manufacturing & Wholesale Goods"
        }
    ],
    "sg:phone":"+1 615 874 8701",
    "sg:postcode":"37214",
    "sg:province":"TN",
    "wof:name":"Clarion Corporation America",
    "wof:placetype":"venue"
},
  "geometry": {"coordinates":[-86.68251600000001,36.148165],"type":"Point"}
}