{
  "type": "Feature",
  "properties": {
    "iso:country":"US",
    "sg:address":"956 Summitville Rd",
    "sg:city":"Manchester",
    "sg:classifiers":[
        {
            "category":"Building & Trades",
            "subcategory":"Construction",
            "type":"Services"
        }
    ],
    "sg:phone":"+1 931 728 5317",
    "sg:postcode":"37355",
    "sg:province":"TN",
    "sg:tags":[
        "general",
        "contractor"
    ],
    "wof:name":"H & H Roofing & Construction",
    "wof:placetype":"venue"
},
  "geometry": {"coordinates":[-85.99090700000001,35.557933],"type":"Point"}
}