{
  "type": "Feature",
  "properties": {
    "iso:country":"US",
    "sg:address":"1216 Louisville Hwy",
    "sg:city":"Goodlettsville",
    "sg:classifiers":[
        {
            "category":"Building & Trades",
            "subcategory":"Construction",
            "type":"Services"
        }
    ],
    "sg:phone":"+1 615 859 4461",
    "sg:postcode":"37072",
    "sg:province":"TN",
    "sg:tags":[
        "fabricator",
        "metal"
    ],
    "wof:name":"Precision Metalwork Inc",
    "wof:placetype":"venue"
},
  "geometry": {"coordinates":[-86.709299,36.372433],"type":"Point"}
}