{
  "type": "Feature",
  "properties": {
    "addr:full":"1511 Chase Meadows Cir Hixson TN 37343",
    "addr:housenumber":"1511",
    "addr:postcode":"37343",
    "addr:street":"Chase Meadows Cir",
    "iso:country":"US",
    "sg:address":"1511 Chase Meadows Cir",
    "sg:city":"Hixson",
    "sg:classifiers":[
        {
            "category":"Communications",
            "subcategory":"Film & Video Production",
            "type":"Services"
        }
    ],
    "sg:phone":"+1 423 875 2646",
    "sg:postcode":"37343",
    "sg:province":"TN",
    "sg:tags":[
        "consultant",
        "audio"
    ],
    "wof:name":"H 2 Audio",
    "wof:placetype":"venue"
},
  "geometry": {"coordinates":[-85.23976500000001,35.148508],"type":"Point"}
}