{
  "type": "Feature",
  "properties": {
    "iso:country":"US",
    "sg:address":"14956 Lebanon Rd",
    "sg:city":"Old Hickory",
    "sg:classifiers":[
        {
            "category":"Retail",
            "subcategory":"Auto Repair",
            "type":"Services"
        }
    ],
    "sg:phone":"+1 615 773 1495",
    "sg:postcode":"37138",
    "sg:province":"TN",
    "sg:tags":[
        "general"
    ],
    "wof:name":"Mid Tenn Auto & Marine Service",
    "wof:placetype":"venue"
},
  "geometry": {"coordinates":[-86.576121,36.218162],"type":"Point"}
}