{
  "type": "Feature",
  "properties": {
    "iso:country":"US",
    "sg:address":"114 International Dr",
    "sg:city":"Lawrenceburg",
    "sg:classifiers":[
        {
            "category":"Retail",
            "subcategory":"Auto Repair",
            "type":"Services"
        }
    ],
    "sg:phone":"+1 931 762 1820",
    "sg:postcode":"38464",
    "sg:province":"TN",
    "sg:tags":[
        "body",
        "automobile",
        "painting"
    ],
    "wof:name":"Mashburn Collision Center",
    "wof:placetype":"venue"
},
  "geometry": {"coordinates":[-87.29583599999999,35.236533],"type":"Point"}
}