{
  "type": "Feature",
  "properties": {
    "iso:country":"US",
    "sg:address":"313 Draper Ln",
    "sg:city":"Gainesboro",
    "sg:classifiers":[
        {
            "category":"Building & Trades",
            "subcategory":"Electrical",
            "type":"Services"
        }
    ],
    "sg:phone":"+1 931 268 0261",
    "sg:postcode":"38562",
    "sg:province":"TN",
    "sg:tags":[
        "electric",
        "contractor"
    ],
    "sg:website":"www.montgomeryelectric.com",
    "wof:name":"Montgomery Electric",
    "wof:placetype":"venue"
},
  "geometry": {"coordinates":[-85.65549900000001,36.354523],"type":"Point"}
}