{
  "type": "Feature",
  "properties": {
    "addr:full":"14545 W Andrew Johnson Hwy Bulls Gap TN 37711",
    "addr:housenumber":"14545",
    "addr:postcode":"37711",
    "addr:street":"W Andrew Johnson Hwy;Gap",
    "iso:country":"US",
    "sg:address":"14545 W Andrew Johnson Hwy",
    "sg:city":"Bulls Gap",
    "sg:classifiers":[
        {
            "category":"Retail",
            "subcategory":"Auto Repair",
            "type":"Services"
        }
    ],
    "sg:phone":"+1 423 235 7923",
    "sg:postcode":"37711",
    "sg:province":"TN",
    "sg:tags":[
        "automotive",
        "wrecker"
    ],
    "wof:name":"Ace 24 Hr Towing & Recovery LL",
    "wof:placetype":"venue"
},
  "geometry": {"coordinates":[-83.048812,36.224893],"type":"Point"}
}