{
  "type": "Feature",
  "properties": {
    "iso:country":"US",
    "sg:address":"250 Hatcher Rd",
    "sg:city":"Mount Juliet",
    "sg:classifiers":[
        {
            "category":"Building & Trades",
            "subcategory":"Construction",
            "type":"Services"
        }
    ],
    "sg:phone":"+1 615 758 3659",
    "sg:postcode":"37122",
    "sg:province":"TN",
    "sg:tags":[
        "excavation",
        "contractor"
    ],
    "wof:name":"A1 Operators",
    "wof:placetype":"venue"
},
  "geometry": {"coordinates":[-86.53488900000001,36.190196],"type":"Point"}
}