{
  "type": "Feature",
  "properties": {
    "iso:country":"US",
    "sg:address":"496 Thompson Creek Rd",
    "sg:city":"Shelbyville",
    "sg:classifiers":[
        {
            "category":"Freight",
            "type":"Transportation"
        }
    ],
    "sg:phone":"+1 931 857 3227",
    "sg:postcode":"37160",
    "sg:province":"TN",
    "sg:tags":[
        "trucking"
    ],
    "wof:name":"J Brinkley Trucking",
    "wof:placetype":"venue"
},
  "geometry": {"coordinates":[-86.321613,35.446912],"type":"Point"}
}