{
  "type": "Feature",
  "properties": {
    "addr:full":"4030 Lebanon Pike Hermitage TN 37076",
    "addr:housenumber":"4030",
    "addr:postcode":"37076",
    "addr:street":"Lebanon Pike",
    "iso:country":"US",
    "sg:address":"4030 Lebanon Pike",
    "sg:city":"Hermitage",
    "sg:classifiers":[
        {
            "category":"Banks & Credit Unions",
            "subcategory":"Bank",
            "type":"Services"
        }
    ],
    "sg:phone":"+1 615 885 6595",
    "sg:postcode":"37076",
    "sg:province":"TN",
    "sg:tags":[
        "personal",
        "institution"
    ],
    "wof:name":"Advance America",
    "wof:placetype":"venue"
},
  "geometry": {"coordinates":[-86.621714,36.195586],"type":"Point"}
}