{
  "type": "Feature",
  "properties": {
    "addr:full":"610 W Burton St Murfreesboro TN 37130",
    "addr:housenumber":"610",
    "addr:postcode":"37130",
    "addr:street":"W Burton St",
    "iso:country":"US",
    "sg:address":"610 W Burton St",
    "sg:city":"Murfreesboro",
    "sg:classifiers":[
        {
            "category":"Building & Trades",
            "subcategory":"Construction",
            "type":"Services"
        }
    ],
    "sg:phone":"+1 615 713 2863",
    "sg:postcode":"37130",
    "sg:province":"TN",
    "sg:tags":[
        "home",
        "improvement",
        "contractor"
    ],
    "sg:website":"http://www.advantagehi.com",
    "wof:name":"Advantage Home Improvement Inc",
    "wof:placetype":"venue"
},
  "geometry": {"coordinates":[-86.39673999999999,35.849738],"type":"Point"}
}