{
  "type": "Feature",
  "properties": {
    "iso:country":"US",
    "sg:address":"3040 Monk House Rd",
    "sg:city":"Somerville",
    "sg:classifiers":[
        {
            "category":"Local Transit",
            "type":"Transportation"
        }
    ],
    "sg:phone":"+1 901 465 7521",
    "sg:postcode":"38068",
    "sg:province":"TN",
    "wof:name":"Scott Shuttle Svc",
    "wof:placetype":"venue"
},
  "geometry": {"coordinates":[-89.278423,35.159267],"type":"Point"}
}