{
  "type": "Feature",
  "properties": {
    "addr:full":"120 Nashville Hwy Columbia TN 38401",
    "addr:housenumber":"120",
    "addr:postcode":"38401",
    "addr:street":"Nashville Hwy",
    "iso:country":"US",
    "sg:address":"120 Nashville Hwy",
    "sg:city":"Columbia",
    "sg:classifiers":[
        {
            "category":"Food & Beverages",
            "subcategory":"Groceries & Convenience Stores",
            "type":"Retail Goods"
        }
    ],
    "sg:phone":"+1 931 381 7817",
    "sg:postcode":"38401",
    "sg:province":"TN",
    "wof:name":"Scot Market",
    "wof:placetype":"venue"
},
  "geometry": {"coordinates":[-87.029234,35.627168],"type":"Point"}
}