{
  "type": "Feature",
  "properties": {
    "iso:country":"US",
    "sg:address":"2943 Sycamore View Rd",
    "sg:city":"Memphis",
    "sg:classifiers":[
        {
            "category":"Home & Garden",
            "subcategory":"Building Materials",
            "type":"Retail Goods"
        },
        {
            "category":"Building & Trades",
            "subcategory":"Construction",
            "type":"Services"
        }
    ],
    "sg:phone":"+1 901 826 6402",
    "sg:postcode":"38134",
    "sg:province":"TN",
    "sg:tags":[
        "repair",
        "bathroom",
        "altering",
        "painting",
        "handyman",
        "contractor",
        "planning",
        "maintenance",
        "improvement",
        "remodeling",
        "kitchen"
    ],
    "sg:website":"http://www.bartletthomeimprovement.com",
    "wof:name":"Bartlett Home Improvement",
    "wof:placetype":"venue"
},
  "geometry": {"coordinates":[-89.86847,35.205917],"type":"Point"}
}