{
  "type": "Feature",
  "properties": {
    "iso:country":"US",
    "sg:address":"4633 Nebo Rd",
    "sg:city":"Walland",
    "sg:classifiers":[
        {
            "category":"Personal",
            "subcategory":"Beauty Salon",
            "type":"Services"
        }
    ],
    "sg:phone":"+1 865 681 9467",
    "sg:postcode":"37886",
    "sg:province":"TN",
    "sg:tags":[
        "shop"
    ],
    "wof:name":"Dawn Homme",
    "wof:placetype":"venue"
},
  "geometry": {"coordinates":[-83.841037,35.731109],"type":"Point"}
}