{
  "type": "Feature",
  "properties": {
    "addr:full":"440 Rankin Ave Dunlap TN 37327",
    "addr:housenumber":"440",
    "addr:postcode":"37327",
    "addr:street":"Rankin Ave",
    "iso:country":"US",
    "sg:address":"440 Rankin Ave",
    "sg:city":"Dunlap",
    "sg:classifiers":[
        {
            "category":"Organizations",
            "subcategory":"Religious Organization",
            "type":"Services"
        }
    ],
    "sg:phone":"+1 423 949 2814",
    "sg:postcode":"37327",
    "sg:province":"TN",
    "sg:tags":[
        "church"
    ],
    "wof:name":"Seventh-Day Adventist Church",
    "wof:placetype":"venue"
},
  "geometry": {"coordinates":[-85.395443,35.360531],"type":"Point"}
}