{
  "type": "Feature",
  "properties": {
    "addr:full":"432 Bell Rd Nashville TN 37217",
    "addr:housenumber":"432",
    "addr:postcode":"37217",
    "addr:street":"Bell Rd",
    "iso:country":"US",
    "sg:address":"432 Bell Rd",
    "sg:city":"Nashville",
    "sg:classifiers":[
        {
            "category":"Retail",
            "subcategory":"Veterinary Services",
            "type":"Services"
        }
    ],
    "sg:phone":"+1 615 361 1844",
    "sg:postcode":"37217",
    "sg:province":"TN",
    "sg:tags":[
        "veterinarian"
    ],
    "wof:name":"Nashville Cat Clinic",
    "wof:placetype":"venue"
},
  "geometry": {"coordinates":[-86.634923,36.075858],"type":"Point"}
}