{
  "type": "Feature",
  "properties": {
    "iso:country":"US",
    "sg:address":"1262 Getwell Rd",
    "sg:city":"Memphis",
    "sg:classifiers":[
        {
            "category":"Retail",
            "subcategory":"Veterinary Services",
            "type":"Services"
        },
        {
            "category":"Retail",
            "subcategory":"Animal Services",
            "type":"Services"
        }
    ],
    "sg:phone":"+1 901 743 6515",
    "sg:postcode":"38111",
    "sg:province":"TN",
    "sg:tags":[
        "pet",
        "grooming",
        "hospital",
        "veterinarian",
        "clinic"
    ],
    "wof:name":"GetWell Animal Hospital",
    "wof:placetype":"venue"
},
  "geometry": {"coordinates":[-89.930943,35.097179],"type":"Point"}
}