{
  "type": "Feature",
  "properties": {
    "addr:full":"109 Mount Pleasant Rd Andersonville TN 37743",
    "addr:housenumber":"109",
    "addr:postcode":"37743",
    "addr:street":"Mount Pleasant Rd",
    "iso:country":"US",
    "sg:address":"109 Mount Pleasant Rd",
    "sg:city":"Andersonville",
    "sg:classifiers":[
        {
            "category":"Building & Trades",
            "subcategory":"Plumbing",
            "type":"Services"
        }
    ],
    "sg:phone":"+1 865 494 7082",
    "sg:postcode":"37743",
    "sg:province":"TN",
    "sg:tags":[
        "plumbing",
        "contractor"
    ],
    "wof:name":"White Brothers Plumbing",
    "wof:placetype":"venue"
},
  "geometry": {"coordinates":[-82.899244,36.170866],"type":"Point"}
}