{
  "type": "Feature",
  "properties": {
    "addr:full":"1512 Watauga St Kingsport TN 37664",
    "addr:housenumber":"1512",
    "addr:postcode":"37664",
    "addr:street":"Watauga St",
    "iso:country":"US",
    "sg:address":"1512 Watauga St",
    "sg:city":"Kingsport",
    "sg:classifiers":[
        {
            "category":"Building & Trades",
            "subcategory":"Construction",
            "type":"Services"
        }
    ],
    "sg:phone":"+1 423 246 2459",
    "sg:postcode":"37664",
    "sg:province":"TN",
    "sg:tags":[
        "house"
    ],
    "wof:name":"Dennis R Smith Construction",
    "wof:placetype":"venue"
},
  "geometry": {"coordinates":[-82.533872,36.540384],"type":"Point"}
}