{
  "type": "Feature",
  "properties": {
    "addr:full":"2312 Guthrie Ave NW Cleveland TN 37311",
    "addr:housenumber":"2312",
    "addr:postcode":"37311",
    "addr:street":"Guthrie Ave Nw",
    "iso:country":"US",
    "sg:address":"2312 Guthrie Ave NW",
    "sg:city":"Cleveland",
    "sg:classifiers":[
        {
            "category":"Building & Trades",
            "subcategory":"Construction",
            "type":"Services"
        }
    ],
    "sg:phone":"+1 423 479 6844",
    "sg:postcode":"37311",
    "sg:province":"TN",
    "sg:tags":[
        "contractor",
        "fence-sales"
    ],
    "sg:website":"http://www.burnsiron.com/",
    "wof:name":"Burns Ornamental Iron And Fabricating",
    "wof:placetype":"venue"
},
  "geometry": {"coordinates":[-84.885599,35.184253],"type":"Point"}
}