{
  "type": "Feature",
  "properties": {
    "iso:country":"US",
    "sg:address":"2025 Wolfe Rd",
    "sg:city":"White Bluff",
    "sg:classifiers":[
        {
            "category":"Shopping",
            "subcategory":"Used Merchandise",
            "type":"Retail Goods"
        }
    ],
    "sg:phone":"+1 615 797 3123",
    "sg:postcode":"37187",
    "sg:province":"TN",
    "sg:tags":[
        "antique"
    ],
    "wof:name":"Elements Inc",
    "wof:placetype":"venue"
},
  "geometry": {"coordinates":[-87.21231899999999,36.090049],"type":"Point"}
}