{
  "type": "Feature",
  "properties": {
    "addr:full":"2100 W End Ave Nashville TN 37203",
    "addr:housenumber":"2100",
    "addr:postcode":"37203",
    "addr:street":"W End Ave",
    "iso:country":"US",
    "sg:address":"2100 W End Ave",
    "sg:city":"Nashville",
    "sg:classifiers":[
        {
            "category":"Professional",
            "subcategory":"Lawyer & Legal Services",
            "type":"Services"
        }
    ],
    "sg:phone":"+1 615 321 2256",
    "sg:postcode":"37203",
    "sg:province":"TN",
    "sg:tags":[
        "attorney"
    ],
    "sg:website":"www.roseimmigration.com",
    "wof:name":"Rose Immigration Law Firm",
    "wof:placetype":"venue"
},
  "geometry": {"coordinates":[-86.803471,36.149373],"type":"Point"}
}