{
  "type": "Feature",
  "properties": {
    "iso:country":"US",
    "sg:address":"106 N Church St",
    "sg:city":"Murfreesboro",
    "sg:classifiers":[
        {
            "category":"Shopping",
            "subcategory":"Clothing, Apparel, & Fashions",
            "type":"Retail Goods"
        }
    ],
    "sg:phone":"+1 615 893 4617",
    "sg:postcode":"37130",
    "sg:province":"TN",
    "sg:tags":[
        "ready"
    ],
    "wof:name":"Ruby's Dress Shop",
    "wof:placetype":"venue"
},
  "geometry": {"coordinates":[-86.391307,35.84631],"type":"Point"}
}