{
  "type": "Feature",
  "properties": {
    "iso:country":"US",
    "sg:address":"5946 State Hwy 150",
    "sg:city":"Sequatchie",
    "sg:classifiers":[
        {
            "category":"Government",
            "subcategory":"Fire Station",
            "type":"Public Place"
        }
    ],
    "sg:phone":"+1 423 942 2600",
    "sg:postcode":"37374",
    "sg:province":"TN",
    "sg:tags":[
        "department"
    ],
    "wof:name":"Foster Falls Volunteer Fire",
    "wof:placetype":"venue"
},
  "geometry": {"coordinates":[-85.66133600000001,35.140005],"type":"Point"}
}