{
  "type": "Feature",
  "properties": {
    "addr:full":"6281 Stage Rd Memphis TN 38134",
    "addr:housenumber":"6281",
    "addr:postcode":"38134",
    "addr:street":"Stage Rd",
    "iso:country":"US",
    "sg:address":"6281 Stage Rd",
    "sg:city":"Memphis",
    "sg:classifiers":[
        {
            "category":"Travel",
            "subcategory":"Travel Agent",
            "type":"Entertainment"
        },
        {
            "category":"Banks & Credit Unions",
            "subcategory":"Investment Brokerage",
            "type":"Services"
        },
        {
            "category":"Banks & Credit Unions",
            "subcategory":"Bank",
            "type":"Services"
        },
        {
            "category":"Banks & Credit Unions",
            "subcategory":"Financial Services",
            "type":"Services"
        }
    ],
    "sg:phone":"+1 901 382 6600",
    "sg:postcode":"38134",
    "sg:province":"TN",
    "sg:tags":[
        "loan",
        "agency",
        "mortgage"
    ],
    "sg:website":"http://www.bankofbartlett.com",
    "wof:name":"Bank Of Bartlett",
    "wof:placetype":"venue"
},
  "geometry": {"coordinates":[-89.85410299999999,35.204762],"type":"Point"}
}