{
  "type": "Feature",
  "properties": {
    "iso:country":"US",
    "sg:address":"225 Rolling Hills Ln",
    "sg:city":"Puryear",
    "sg:classifiers":[
        {
            "category":"Professional",
            "type":"Services"
        }
    ],
    "sg:phone":"+1 901 753 1725",
    "sg:postcode":"38251",
    "sg:province":"TN",
    "wof:name":"Rolling Hill Nursery",
    "wof:placetype":"venue"
},
  "geometry": {"coordinates":[-88.418091,36.473893],"type":"Point"}
}