{
  "type": "Feature",
  "properties": {
    "iso:country":"US",
    "sg:address":"4740 Nolensville Pike",
    "sg:city":"Nashville",
    "sg:classifiers":[
        {
            "category":"Manufacturing",
            "subcategory":"Metals",
            "type":"Manufacturing & Wholesale Goods"
        },
        {
            "category":"Shopping",
            "type":"Retail Goods"
        }
    ],
    "sg:phone":"+1 615 833 0200",
    "sg:postcode":"37211",
    "sg:province":"TN",
    "sg:tags":[
        "trophy",
        "product",
        "mfg",
        "fabricated",
        "award",
        "medal",
        "merchandise"
    ],
    "wof:name":"Award Center Inc",
    "wof:placetype":"venue"
},
  "geometry": {"coordinates":[-86.718289,36.067352],"type":"Point"}
}