{
  "type": "Feature",
  "properties": {
    "iso:country":"US",
    "sg:address":"10421 Chapman Hwy",
    "sg:city":"Seymour",
    "sg:classifiers":[
        {
            "category":"Retail",
            "subcategory":"Veterinary Services",
            "type":"Services"
        }
    ],
    "sg:phone":"+1 865 579 6738",
    "sg:postcode":"37865",
    "sg:province":"TN",
    "sg:tags":[
        "veterinarian"
    ],
    "wof:name":"Fix-A-Pet",
    "wof:placetype":"venue"
},
  "geometry": {"coordinates":[-83.78457899999999,35.881865],"type":"Point"}
}