{
  "type": "Feature",
  "properties": {
    "iso:country":"US",
    "sg:address":"3224 Joyce Ave",
    "sg:city":"Knoxville",
    "sg:classifiers":[
        {
            "category":"Organizations",
            "subcategory":"Religious Organization",
            "type":"Services"
        }
    ],
    "sg:phone":"+1 865 524 3937",
    "sg:postcode":"37921",
    "sg:province":"TN",
    "sg:tags":[
        "church"
    ],
    "sg:website":"www.westviewwesleyanchurch.org",
    "wof:name":"West View Wesleyan Church",
    "wof:placetype":"venue"
},
  "geometry": {"coordinates":[-83.96557900000001,35.965026],"type":"Point"}
}