{
  "type": "Feature",
  "properties": {
    "iso:country":"US",
    "sg:address":"201 Nelson St",
    "sg:city":"Corinth",
    "sg:classifiers":[
        {
            "category":"Shopping",
            "subcategory":"Clothing, Apparel, & Fashions",
            "type":"Retail Goods"
        }
    ],
    "sg:phone":"+1 662 286 2173",
    "sg:postcode":"38834",
    "sg:province":"TN",
    "wof:name":"Strawberry Fields",
    "wof:placetype":"venue"
},
  "geometry": {"coordinates":[-88.529505,34.939485],"type":"Point"}
}