{
  "type": "Feature",
  "properties": {
    "iso:country":"US",
    "sg:address":"4008 Sheddan Dr",
    "sg:city":"Columbia",
    "sg:classifiers":[
        {
            "category":"Building & Trades",
            "subcategory":"Construction",
            "type":"Services"
        }
    ],
    "sg:phone":"+1 931 381 0675",
    "sg:postcode":"38401",
    "sg:province":"TN",
    "sg:tags":[
        "excavation",
        "contractor"
    ],
    "wof:name":"Ra Backhoe Dozer Service",
    "wof:placetype":"venue"
},
  "geometry": {"coordinates":[-87.092249,35.594795],"type":"Point"}
}