{
  "type": "Feature",
  "properties": {
    "addr:full":"19 Beasley Hollow Ln Carthage TN 37030",
    "addr:housenumber":"19",
    "addr:postcode":"37030",
    "addr:street":"Beasley Hollow Ln",
    "iso:country":"US",
    "sg:address":"19 Beasley Hollow Ln",
    "sg:city":"Carthage",
    "sg:classifiers":[
        {
            "category":"Organizations",
            "subcategory":"Religious Organization",
            "type":"Services"
        }
    ],
    "sg:phone":"+1 615 735 9297",
    "sg:postcode":"37030",
    "sg:province":"TN",
    "wof:name":"Lily Hill Baptist Church",
    "wof:placetype":"venue"
},
  "geometry": {"coordinates":[-85.89185000000001,36.323818],"type":"Point"}
}