{
  "type": "Feature",
  "properties": {
    "addr:full":"7446 Shallowford Rd Chattanooga TN 37421",
    "addr:housenumber":"7446",
    "addr:postcode":"37421",
    "addr:street":"Shallowford Rd",
    "iso:country":"US",
    "sg:address":"7446 Shallowford Rd",
    "sg:city":"Chattanooga",
    "sg:classifiers":[
        {
            "category":"Health Services",
            "subcategory":"Doctor",
            "type":"Services"
        }
    ],
    "sg:phone":"+1 423 899 2800",
    "sg:postcode":"37421",
    "sg:province":"TN",
    "sg:tags":[
        "dentist"
    ],
    "wof:name":"Hamilton Family Dentistry",
    "wof:placetype":"venue"
},
  "geometry": {"coordinates":[-85.143659,35.038011],"type":"Point"}
}