{
  "type": "Feature",
  "properties": {
    "addr:full":"1090 Pulaski Hwy Lawrenceburg TN 38464",
    "addr:housenumber":"1090",
    "addr:postcode":"38464",
    "addr:street":"Pulaski Hwy",
    "iso:country":"US",
    "sg:address":"1090 Pulaski Hwy",
    "sg:city":"Lawrenceburg",
    "sg:classifiers":[
        {
            "category":"Organizations",
            "subcategory":"Religious Organization",
            "type":"Services"
        }
    ],
    "sg:phone":"+1 931 762 5104",
    "sg:postcode":"38464",
    "sg:province":"TN",
    "sg:website":"www.lawrenceburg.com/calvaryhill",
    "wof:name":"Calvary Hill Church Of God",
    "wof:placetype":"venue"
},
  "geometry": {"coordinates":[-87.308121,35.237588],"type":"Point"}
}