{
  "type": "Feature",
  "properties": {
    "iso:country":"US",
    "sg:address":"2802 Douglas Dam Rd",
    "sg:city":"Sevierville",
    "sg:classifiers":[
        {
            "category":"Organizations",
            "subcategory":"Professional Association",
            "type":"Services"
        }
    ],
    "sg:phone":"+1 865 980 9519",
    "sg:postcode":"37876",
    "sg:province":"TN",
    "wof:name":"Luttrell Reba Tenn Educatn",
    "wof:placetype":"venue"
},
  "geometry": {"coordinates":[-83.544572,35.950337],"type":"Point"}
}