{
  "type": "Feature",
  "properties": {
    "iso:country":"US",
    "sg:address":"2505 Dobbins Pike",
    "sg:city":"Portland",
    "sg:classifiers":[
        {
            "category":"Building & Trades",
            "subcategory":"Construction",
            "type":"Services"
        }
    ],
    "sg:phone":"+1 615 888 9917",
    "sg:postcode":"37148",
    "sg:province":"TN",
    "sg:tags":[
        "insulation",
        "heat",
        "contractor"
    ],
    "wof:name":"Ricky Brown's Insulation",
    "wof:placetype":"venue"
},
  "geometry": {"coordinates":[-86.423891,36.51241],"type":"Point"}
}