{
  "type": "Feature",
  "properties": {
    "iso:country":"US",
    "sg:address":"130 Butler Rd",
    "sg:city":"Jonesborough",
    "sg:classifiers":[
        {
            "category":"Autos & Motor Vehicles",
            "subcategory":"Automobile Sales",
            "type":"Retail Goods"
        }
    ],
    "sg:phone":"+1 423 753 2221",
    "sg:postcode":"37659",
    "sg:province":"TN",
    "sg:tags":[
        "used"
    ],
    "wof:name":"Drycreek Auto Sales",
    "wof:placetype":"venue"
},
  "geometry": {"coordinates":[-82.411997,36.213041],"type":"Point"}
}