{
  "type": "Feature",
  "properties": {
    "addr:full":"1715 Eagle Dr Hixson TN 37343",
    "addr:housenumber":"1715",
    "addr:postcode":"37343",
    "addr:street":"Eagle Dr",
    "iso:country":"US",
    "sg:address":"1715 Eagle Dr",
    "sg:city":"Hixson",
    "sg:classifiers":[
        {
            "category":"Wholesale",
            "subcategory":"Metals & Minerals",
            "type":"Manufacturing & Wholesale Goods"
        }
    ],
    "sg:phone":"+1 423 332 0460",
    "sg:postcode":"37343",
    "sg:province":"TN",
    "sg:tags":[
        "pipe"
    ],
    "wof:name":"Tennessee Valley Pipe",
    "wof:placetype":"venue"
},
  "geometry": {"coordinates":[-85.193467,35.161929],"type":"Point"}
}