{
  "type": "Feature",
  "properties": {
    "addr:full":"908 S Fulton Dr Corinth TN 38834",
    "addr:housenumber":"908",
    "addr:postcode":"38834",
    "addr:street":"S Fulton Dr",
    "iso:country":"US",
    "sg:address":"908 S Fulton Dr",
    "sg:city":"Corinth",
    "sg:classifiers":[
        {
            "category":"Farming",
            "subcategory":"Nursery",
            "type":"Manufacturing & Wholesale Goods"
        }
    ],
    "sg:phone":"+1 662 286 6301",
    "sg:postcode":"38834",
    "sg:province":"TN",
    "sg:tags":[
        "ornamental"
    ],
    "wof:name":"Just For You",
    "wof:placetype":"venue"
},
  "geometry": {"coordinates":[-88.52339600000001,34.92166],"type":"Point"}
}