{
  "type": "Feature",
  "properties": {
    "iso:country":"US",
    "sg:address":"1405 Riverport Rd",
    "sg:city":"Kingsport",
    "sg:classifiers":[
        {
            "category":"Manufacturing",
            "subcategory":"Printing",
            "type":"Manufacturing & Wholesale Goods"
        }
    ],
    "sg:phone":"+1 423 246 8066",
    "sg:postcode":"37660",
    "sg:province":"TN",
    "sg:tags":[
        "repair",
        "book"
    ],
    "wof:name":"Bookworks",
    "wof:placetype":"venue"
},
  "geometry": {"coordinates":[-82.58011500000001,36.54467],"type":"Point"}
}