{
  "type": "Feature",
  "properties": {
    "iso:country":"US",
    "sg:address":"2650 Nashville Hwy",
    "sg:city":"Mc Minnville",
    "sg:classifiers":[
        {
            "category":"Retail",
            "subcategory":"Auto Repair",
            "type":"Services"
        }
    ],
    "sg:phone":"+1 931 815 3988",
    "sg:postcode":"37110",
    "sg:province":"TN",
    "sg:tags":[
        "repairing",
        "automobile"
    ],
    "wof:name":"Keith's Auto Repair",
    "wof:placetype":"venue"
},
  "geometry": {"coordinates":[-85.815769,35.696096],"type":"Point"}
}