{
  "type": "Feature",
  "properties": {
    "iso:country":"US",
    "sg:address":"3196 Dickerson Pike",
    "sg:city":"Nashville",
    "sg:classifiers":[
        {
            "category":"Restaurant",
            "type":"Food & Drink"
        }
    ],
    "sg:menulink":"http://www.allmenus.com/tn/nashville/166335-arbys/menu/",
    "sg:phone":"+1 615 228 1160",
    "sg:postcode":"37207",
    "sg:province":"TN",
    "sg:tags":[
        "burger",
        "american"
    ],
    "wof:name":"Arby's",
    "wof:placetype":"venue"
},
  "geometry": {"coordinates":[-86.759004,36.23406],"type":"Point"}
}