{
  "type": "Feature",
  "properties": {
    "iso:country":"US",
    "sg:address":"822 S Main St",
    "sg:city":"Columbia",
    "sg:classifiers":[
        {
            "category":"Restaurant",
            "type":"Food & Drink"
        }
    ],
    "sg:phone":"+1 931 388 3005",
    "sg:postcode":"38401",
    "sg:province":"TN",
    "wof:name":"Lucille's Restaurant",
    "wof:placetype":"venue"
},
  "geometry": {"coordinates":[-87.034014,35.614326],"type":"Point"}
}