{
  "type": "Feature",
  "properties": {
    "addr:full":"5917 Thorngrove Pike Knoxville TN 37914",
    "addr:postcode":"5917;37914",
    "addr:street":"Thorngrove Pike",
    "iso:country":"US",
    "sg:address":"5917 Thorngrove Pike",
    "sg:city":"Knoxville",
    "sg:classifiers":[
        {
            "category":"Retail",
            "subcategory":"Repair Shop",
            "type":"Services"
        }
    ],
    "sg:phone":"+1 865 522 7925",
    "sg:postcode":"37914",
    "sg:province":"TN",
    "sg:tags":[
        "upholsterer"
    ],
    "wof:name":"Hancock's Upholstering Shop",
    "wof:placetype":"venue"
},
  "geometry": {"coordinates":[-83.79807599999999,35.964829],"type":"Point"}
}