{
  "type": "Feature",
  "properties": {
    "iso:country":"US",
    "sg:address":"4006 Sowell Hollow Rd",
    "sg:city":"Columbia",
    "sg:classifiers":[
        {
            "category":"Organizations",
            "subcategory":"Religious Organization",
            "type":"Services"
        }
    ],
    "sg:phone":"+1 931 388 8770",
    "sg:postcode":"38401",
    "sg:province":"TN",
    "wof:name":"Help Ministry 1st Family",
    "wof:placetype":"venue"
},
  "geometry": {"coordinates":[-87.09925800000001,35.538688],"type":"Point"}
}