{
  "type": "Feature",
  "properties": {
    "addr:full":"505 Market St SW Knoxville TN 37902",
    "addr:housenumber":"505",
    "addr:postcode":"37902",
    "addr:street":"Market St Sw",
    "iso:country":"US",
    "sg:address":"505 Market St SW",
    "sg:city":"Knoxville",
    "sg:classifiers":[
        {
            "category":"Professional",
            "subcategory":"Lawyer & Legal Services",
            "type":"Services"
        }
    ],
    "sg:phone":"+1 865 637 8281",
    "sg:postcode":"37902",
    "sg:province":"TN",
    "wof:name":"Adkins Gary",
    "wof:placetype":"venue"
},
  "geometry": {"coordinates":[-83.918852,35.96384],"type":"Point"}
}