{
  "type": "Feature",
  "properties": {
    "iso:country":"US",
    "sg:address":"3120 Chapman Hwy",
    "sg:city":"Knoxville",
    "sg:classifiers":[
        {
            "category":"Food & Beverages",
            "subcategory":"Groceries & Convenience Stores",
            "type":"Retail Goods"
        }
    ],
    "sg:phone":"+1 865 579 3652",
    "sg:postcode":"37920",
    "sg:province":"TN",
    "wof:name":"Kenjo Market",
    "wof:placetype":"venue"
},
  "geometry": {"coordinates":[-83.91162300000001,35.944822],"type":"Point"}
}