{
  "type": "Feature",
  "properties": {
    "iso:country":"US",
    "sg:address":"440 Talley Rd",
    "sg:city":"Parrottsville",
    "sg:classifiers":[
        {
            "category":"Professional",
            "subcategory":"Accounting & Tax Preparation",
            "type":"Services"
        }
    ],
    "sg:phone":"+1 423 625 9410",
    "sg:postcode":"37843",
    "sg:province":"TN",
    "sg:tags":[
        "bookkeeping",
        "general"
    ],
    "wof:name":"Professional Bookkeeping & Tax",
    "wof:placetype":"venue"
},
  "geometry": {"coordinates":[-83.108068,36.018989],"type":"Point"}
}