{
  "type": "Feature",
  "properties": {
    "iso:country":"US",
    "sg:address":"9235 Strawberry Plains Pike",
    "sg:city":"Strawberry Plns",
    "sg:classifiers":[
        {
            "category":"Organizations",
            "subcategory":"Religious Organization",
            "type":"Services"
        }
    ],
    "sg:phone":"+1 865 933 2388",
    "sg:postcode":"37871",
    "sg:province":"TN",
    "sg:tags":[
        "church"
    ],
    "sg:website":"www.lyonscreekbaptist.org",
    "wof:name":"Lyons Creek Baptist Church",
    "wof:placetype":"venue"
},
  "geometry": {"coordinates":[-83.718502,36.032448],"type":"Point"}
}