{
  "type": "Feature",
  "properties": {
    "iso:country":"US",
    "sg:address":"210 E Public Sq",
    "sg:city":"Smithville",
    "sg:classifiers":[
        {
            "category":"Social Services",
            "type":"Services"
        }
    ],
    "sg:phone":"+1 615 597 7692",
    "sg:postcode":"37166",
    "sg:province":"TN",
    "wof:name":"Tennessee Opprtnity Prgram Inc",
    "wof:placetype":"venue"
},
  "geometry": {"coordinates":[-85.812804,35.961127],"type":"Point"}
}