{
  "type": "Feature",
  "properties": {
    "iso:country":"US",
    "sg:address":"1781 S Prescott St",
    "sg:city":"Memphis",
    "sg:classifiers":[
        {
            "category":"Professional",
            "subcategory":"Accounting & Tax Preparation",
            "type":"Services"
        }
    ],
    "sg:phone":"+1 901 398 4100",
    "sg:postcode":"38111",
    "sg:province":"TN",
    "sg:tags":[
        "return",
        "filing"
    ],
    "wof:name":"Express Tax Svc",
    "wof:placetype":"venue"
},
  "geometry": {"coordinates":[-89.95522099999999,35.082694],"type":"Point"}
}