{
  "type": "Feature",
  "properties": {
    "addr:full":"2032 Artesian Dr Nolensville TN 37135",
    "addr:housenumber":"2032",
    "addr:postcode":"37135",
    "addr:street":"Artesian Dr",
    "iso:country":"US",
    "sg:address":"2032 Artesian Dr",
    "sg:city":"Nolensville",
    "sg:classifiers":[
        {
            "category":"Building & Trades",
            "subcategory":"Plumbing",
            "type":"Services"
        }
    ],
    "sg:phone":"+1 615 776 3366",
    "sg:postcode":"37135",
    "sg:province":"TN",
    "sg:tags":[
        "conditioning",
        "air",
        "system",
        "contractor"
    ],
    "wof:name":"Southern Comfort Heating/Cool",
    "wof:placetype":"venue"
},
  "geometry": {"coordinates":[-86.687124,35.936786],"type":"Point"}
}