{
  "type": "Feature",
  "properties": {
    "iso:country":"US",
    "sg:address":"2829 Rennoc Rd NE",
    "sg:city":"Knoxville",
    "sg:classifiers":[
        {
            "category":"Retail",
            "subcategory":"Funeral Services",
            "type":"Services"
        }
    ],
    "sg:phone":"+1 865 688 2331",
    "sg:postcode":"37918",
    "sg:province":"TN",
    "sg:tags":[
        "director"
    ],
    "wof:name":"Mynatt Funeral Home",
    "wof:placetype":"venue"
},
  "geometry": {"coordinates":[-83.92865500000001,36.03142],"type":"Point"}
}