{
  "type": "Feature",
  "properties": {
    "addr:full":"507 Short Bark Rd Madisonville TN 37354",
    "addr:housenumber":"507",
    "addr:postcode":"37354",
    "addr:street":"Short Bark Rd",
    "iso:country":"US",
    "sg:address":"507 Short Bark Rd",
    "sg:city":"Madisonville",
    "sg:phone":"+1 423 442 3129",
    "sg:postcode":"37354",
    "sg:province":"TN",
    "sg:tags":[
        "farm",
        "corn",
        "wheat",
        "soybean"
    ],
    "wof:name":"Leo Smith",
    "wof:placetype":"venue"
},
  "geometry": {"coordinates":[-84.345054,35.569894],"type":"Point"}
}