{
  "type": "Feature",
  "properties": {
    "addr:full":"1113 Persimmon Ridge Rd Jonesborough TN 37659",
    "addr:housenumber":"1113",
    "addr:postcode":"37659",
    "addr:street":"Persimmon Ridge Rd",
    "iso:country":"US",
    "sg:address":"1113 Persimmon Ridge Rd",
    "sg:city":"Jonesborough",
    "sg:classifiers":[
        {
            "category":"Real Estate",
            "subcategory":"Real Estate Operator",
            "type":"Services"
        }
    ],
    "sg:phone":"+1 423 753 7026",
    "sg:postcode":"37659",
    "sg:province":"TN",
    "sg:tags":[
        "apartment"
    ],
    "wof:name":"Bethel Housing",
    "wof:placetype":"venue"
},
  "geometry": {"coordinates":[-82.49203199999999,36.289901],"type":"Point"}
}