{
  "type": "Feature",
  "properties": {
    "iso:country":"US",
    "sg:address":"4134 Bull Run Rd",
    "sg:city":"Ashland City",
    "sg:classifiers":[
        {
            "category":"Building & Trades",
            "subcategory":"Construction",
            "type":"Services"
        }
    ],
    "sg:phone":"+1 615 254 8822",
    "sg:postcode":"37015",
    "sg:province":"TN",
    "sg:tags":[
        "floor",
        "laying",
        "contractor"
    ],
    "wof:name":"Vincent R Langley Contracting",
    "wof:placetype":"venue"
},
  "geometry": {"coordinates":[-86.960476,36.232084],"type":"Point"}
}