{
  "type": "Feature",
  "properties": {
    "iso:country":"US",
    "sg:address":"3918 Dickerson Pike",
    "sg:city":"Nashville",
    "sg:classifiers":[
        {
            "category":"Restaurant",
            "type":"Food & Drink"
        }
    ],
    "sg:phone":"+1 615 868 3900",
    "sg:postcode":"37207",
    "sg:province":"TN",
    "sg:tags":[
        "eating"
    ],
    "wof:name":"White Fish & Barbecue",
    "wof:placetype":"venue"
},
  "geometry": {"coordinates":[-86.75313800000001,36.274255],"type":"Point"}
}