{
  "type": "Feature",
  "properties": {
    "iso:country":"US",
    "sg:address":"1100 Smithville Hwy",
    "sg:city":"Mc Minnville",
    "sg:classifiers":[
        {
            "category":"Shopping",
            "subcategory":"Clothing, Apparel, & Fashions",
            "type":"Retail Goods"
        }
    ],
    "sg:phone":"+1 931 473 0801",
    "sg:postcode":"37110",
    "sg:province":"TN",
    "wof:name":"Roxie & Darla's Fashions",
    "wof:placetype":"venue"
},
  "geometry": {"coordinates":[-85.77970000000001,35.696182],"type":"Point"}
}