{
  "type": "Feature",
  "properties": {
    "iso:country":"US",
    "sg:address":"4335 Horn Lake Rd",
    "sg:city":"Memphis",
    "sg:classifiers":[
        {
            "category":"Organizations",
            "subcategory":"Religious Organization",
            "type":"Services"
        }
    ],
    "sg:phone":"+1 901 789 4403",
    "sg:postcode":"38109",
    "sg:province":"TN",
    "sg:tags":[
        "church"
    ],
    "wof:name":"New Covenant Seventh-Day Chr",
    "wof:placetype":"venue"
},
  "geometry": {"coordinates":[-90.070165,35.031198],"type":"Point"}
}