{
  "type": "Feature",
  "properties": {
    "addr:full":"204 Blue Hills Dr Nashville TN 37214",
    "addr:housenumber":"204",
    "addr:postcode":"37214",
    "addr:street":"Blue Hills Dr",
    "iso:country":"US",
    "sg:address":"204 Blue Hills Dr",
    "sg:city":"Nashville",
    "sg:classifiers":[
        {
            "category":"Professional",
            "subcategory":"Computer Services",
            "type":"Services"
        }
    ],
    "sg:phone":"+1 615 883 5000",
    "sg:postcode":"37214",
    "sg:province":"TN",
    "sg:tags":[
        "datum",
        "commercial",
        "desi"
    ],
    "wof:name":"Splat Productions LLC",
    "wof:placetype":"venue"
},
  "geometry": {"coordinates":[-86.68648399999999,36.165669],"type":"Point"}
}