{
  "type": "Feature",
  "properties": {
    "iso:country":"US",
    "sg:address":"2557 Verona Caney Rd",
    "sg:city":"Lewisburg",
    "sg:classifiers":[
        {
            "category":"Personal",
            "subcategory":"Beauty Salon",
            "type":"Services"
        }
    ],
    "sg:phone":"+1 931 359 3121",
    "sg:postcode":"37091",
    "sg:province":"TN",
    "sg:tags":[
        "shop"
    ],
    "wof:name":"Styles & Nails By Michelle",
    "wof:placetype":"venue"
},
  "geometry": {"coordinates":[-86.769278,35.531798],"type":"Point"}
}