{
  "type": "Feature",
  "properties": {
    "addr:full":"4423 State Hwy 58 Chattanooga TN 37416",
    "addr:housenumber":"4423",
    "addr:postcode":"37416",
    "addr:street":"State Hwy 58",
    "iso:country":"US",
    "sg:address":"4423 State Hwy 58",
    "sg:city":"Chattanooga",
    "sg:classifiers":[
        {
            "category":"Professional",
            "type":"Services"
        }
    ],
    "sg:phone":"+1 423 490 0104",
    "sg:postcode":"37416",
    "sg:province":"TN",
    "wof:name":"Distinctively Dees",
    "wof:placetype":"venue"
},
  "geometry": {"coordinates":[-85.198944,35.084775],"type":"Point"}
}