{
  "type": "Feature",
  "properties": {
    "iso:country":"US",
    "sg:address":"2657 N Hollywood St",
    "sg:city":"Memphis",
    "sg:classifiers":[
        {
            "category":"Retail",
            "subcategory":"Laundry & Dry Cleaning",
            "type":"Services"
        }
    ],
    "sg:phone":"+1 901 358 9031",
    "sg:postcode":"38108",
    "sg:province":"TN",
    "sg:tags":[
        "drycleaning",
        "plant",
        "cleaners"
    ],
    "wof:name":"Perry's Cleaners",
    "wof:placetype":"venue"
},
  "geometry": {"coordinates":[-89.97586099999999,35.197421],"type":"Point"}
}