{
  "type": "Feature",
  "properties": {
    "addr:full":"111 Shepherd Hills Dr Madison TN 37115",
    "addr:housenumber":"111",
    "addr:postcode":"37115",
    "addr:street":"Shepherd Hills Dr",
    "iso:country":"US",
    "sg:address":"111 Shepherd Hills Dr",
    "sg:city":"Madison",
    "sg:classifiers":[
        {
            "category":"Arts & Performance",
            "subcategory":"Theater",
            "type":"Entertainment"
        }
    ],
    "sg:phone":"+1 615 868 7171",
    "sg:postcode":"37115",
    "sg:province":"TN",
    "sg:tags":[
        "bureau"
    ],
    "wof:name":"L S Records",
    "wof:placetype":"venue"
},
  "geometry": {"coordinates":[-86.693033,36.299081],"type":"Point"}
}