{
  "type": "Feature",
  "properties": {
    "addr:full":"654 W Iris Dr Nashville TN 37204",
    "addr:housenumber":"654",
    "addr:postcode":"37204",
    "addr:street":"W Iris Dr",
    "iso:country":"US",
    "sg:address":"654 W Iris Dr",
    "sg:city":"Nashville",
    "sg:classifiers":[
        {
            "category":"Health Services",
            "subcategory":"Hospital",
            "type":"Services"
        }
    ],
    "sg:phone":"+1 615 269 5170",
    "sg:postcode":"37204",
    "sg:province":"TN",
    "sg:tags":[
        "mental"
    ],
    "wof:name":"Harbor House",
    "wof:placetype":"venue"
},
  "geometry": {"coordinates":[-86.769198,36.114532],"type":"Point"}
}