{
  "type": "Feature",
  "properties": {
    "iso:country":"US",
    "sg:address":"100 Hamm Rd",
    "sg:city":"Chattanooga",
    "sg:classifiers":[
        {
            "category":"Building & Trades",
            "subcategory":"Construction",
            "type":"Services"
        }
    ],
    "sg:phone":"+1 423 266 1855",
    "sg:postcode":"37405",
    "sg:province":"TN",
    "sg:tags":[
        "designer",
        "marine",
        "contractor"
    ],
    "wof:name":"Southern Marine Construction",
    "wof:placetype":"venue"
},
  "geometry": {"coordinates":[-85.333108,35.052929],"type":"Point"}
}