{
  "type": "Feature",
  "properties": {
    "iso:country":"US",
    "sg:address":"2260 Cambridge Dr",
    "sg:city":"Morristown",
    "sg:classifiers":[
        {
            "category":"Professional",
            "subcategory":"Computer Services",
            "type":"Services"
        }
    ],
    "sg:phone":"+1 423 587 6739",
    "sg:postcode":"37814",
    "sg:province":"TN",
    "sg:tags":[
        "related",
        "programing",
        "custom"
    ],
    "wof:name":"Computer Solutions Development",
    "wof:placetype":"venue"
},
  "geometry": {"coordinates":[-83.315763,36.226885],"type":"Point"}
}