{
  "type": "Feature",
  "properties": {
    "addr:full":"2879 Sprankle Ave Memphis TN 38118",
    "addr:housenumber":"2879",
    "addr:postcode":"38118",
    "addr:street":"Sprankle Ave",
    "iso:country":"US",
    "sg:address":"2879 Sprankle Ave",
    "sg:city":"Memphis",
    "sg:classifiers":[
        {
            "category":"Professional",
            "subcategory":"Engineering",
            "type":"Services"
        }
    ],
    "sg:phone":"+1 907 797 4783",
    "sg:postcode":"38118",
    "sg:province":"TN",
    "sg:tags":[
        "laboratory",
        "testing"
    ],
    "wof:name":"Litton Systems Inc",
    "wof:placetype":"venue"
},
  "geometry": {"coordinates":[-89.968986,35.064568],"type":"Point"}
}