{
  "type": "Feature",
  "properties": {
    "iso:country":"US",
    "sg:address":"2351 Sullivan Knowles Rd",
    "sg:city":"Sparta",
    "sg:classifiers":[
        {
            "category":"Government",
            "subcategory":"Fire Station",
            "type":"Public Place"
        }
    ],
    "sg:phone":"+1 931 738 2106",
    "sg:postcode":"38583",
    "sg:province":"TN",
    "sg:tags":[
        "department",
        "protection"
    ],
    "wof:name":"Mt Gilead Volunteer Fire Dept",
    "wof:placetype":"venue"
},
  "geometry": {"coordinates":[-85.502746,35.900288],"type":"Point"}
}