{
  "type": "Feature",
  "properties": {
    "iso:country":"US",
    "sg:address":"5181 Braden Dr",
    "sg:city":"Memphis",
    "sg:classifiers":[
        {
            "category":"Personal",
            "subcategory":"Beauty Salon",
            "type":"Services"
        }
    ],
    "sg:phone":"+1 901 357 8335",
    "sg:postcode":"38127",
    "sg:province":"TN",
    "wof:name":"Quita Touch",
    "wof:placetype":"venue"
},
  "geometry": {"coordinates":[-90.03994,35.267307],"type":"Point"}
}