{
  "type": "Feature",
  "properties": {
    "iso:country":"US",
    "sg:address":"3643 New Oak Ct",
    "sg:city":"Memphis",
    "sg:classifiers":[
        {
            "category":"Professional",
            "subcategory":"Business Services",
            "type":"Services"
        }
    ],
    "sg:phone":"+1 901 344 9407",
    "sg:postcode":"38116",
    "sg:province":"TN",
    "wof:name":"Abelsett Enterprises",
    "wof:placetype":"venue"
},
  "geometry": {"coordinates":[-90.024503,35.049564],"type":"Point"}
}