{
  "type": "Feature",
  "properties": {
    "iso:country":"US",
    "sg:address":"937 Voss Ln",
    "sg:city":"Decaturville",
    "sg:phone":"+1 731 852 3123",
    "sg:postcode":"38344",
    "sg:province":"TN",
    "sg:tags":[
        "farm",
        "corn"
    ],
    "wof:name":"Douglas Vise",
    "wof:placetype":"venue"
},
  "geometry": {"coordinates":[-88.47541,35.951967],"type":"Point"}
}