{
  "type": "Feature",
  "properties": {
    "iso:country":"US",
    "sg:address":"991 Cottonport Rd",
    "sg:city":"Decatur",
    "sg:classifiers":[
        {
            "category":"Organizations",
            "subcategory":"Religious Organization",
            "type":"Services"
        }
    ],
    "sg:phone":"+1 423 334 3640",
    "sg:postcode":"37321",
    "sg:province":"TN",
    "wof:name":"Cottonport Baptist Church",
    "wof:placetype":"venue"
},
  "geometry": {"coordinates":[-84.932733,35.503995],"type":"Point"}
}