{
  "type": "Feature",
  "properties": {
    "addr:full":"138 Chaffin Pl Murfreesboro TN 37129",
    "addr:housenumber":"138",
    "addr:postcode":"37129",
    "addr:street":"Chaffin Pl",
    "iso:country":"US",
    "sg:address":"138 Chaffin Pl",
    "sg:city":"Murfreesboro",
    "sg:classifiers":[
        {
            "category":"Bars & Pubs",
            "type":"Food & Drink"
        }
    ],
    "sg:menulink":"http://www.allmenus.com/tn/murfreesboro/34497-cracker-barrel-old-country-store/menu/",
    "sg:phone":"+1 615 893 4980",
    "sg:postcode":"37129",
    "sg:province":"TN",
    "sg:tags":[
        "american",
        "southern"
    ],
    "wof:name":"Cracker Barrel Old Country Store",
    "wof:placetype":"venue"
},
  "geometry": {"coordinates":[-86.430819,35.845558],"type":"Point"}
}