{
  "type": "Feature",
  "properties": {
    "iso:country":"US",
    "sg:address":"146 Glendale Dr",
    "sg:city":"Church Hill",
    "sg:classifiers":[
        {
            "category":"Building & Trades",
            "subcategory":"Construction",
            "type":"Services"
        }
    ],
    "sg:phone":"+1 423 357 3123",
    "sg:postcode":"37642",
    "sg:province":"TN",
    "sg:tags":[
        "contractor"
    ],
    "wof:name":"Pounders Masonry",
    "wof:placetype":"venue"
},
  "geometry": {"coordinates":[-82.706598,36.559928],"type":"Point"}
}