{
  "type": "Feature",
  "properties": {
    "addr:full":"110 Wells Rd Trade TN 37691",
    "addr:housenumber":"110",
    "addr:postcode":"37691",
    "addr:street":"Wells Rd",
    "iso:country":"US",
    "sg:address":"110 Wells Rd",
    "sg:city":"Trade",
    "sg:classifiers":[
        {
            "category":"Building & Trades",
            "subcategory":"Construction",
            "type":"Services"
        }
    ],
    "sg:phone":"+1 423 727 7065",
    "sg:postcode":"37691",
    "sg:province":"TN",
    "sg:tags":[
        "general",
        "contractor"
    ],
    "wof:name":"Stone Mountain Construction",
    "wof:placetype":"venue"
},
  "geometry": {"coordinates":[-81.762086,36.376631],"type":"Point"}
}