{
  "type": "Feature",
  "properties": {
    "iso:country":"US",
    "sg:address":"2397 Memorial Blvd",
    "sg:city":"Murfreesboro",
    "sg:classifiers":[
        {
            "category":"Restaurant",
            "type":"Food & Drink"
        }
    ],
    "sg:menulink":"http://www.allmenus.com/tn/murfreesboro/177836-jack-in-the-box/menu/",
    "sg:phone":"+1 615 849 1234",
    "sg:postcode":"37129",
    "sg:province":"TN",
    "sg:tags":[
        "burger",
        "american"
    ],
    "wof:name":"Jack in the Box",
    "wof:placetype":"venue"
},
  "geometry": {"coordinates":[-86.382932,35.886956],"type":"Point"}
}