{
  "type": "Feature",
  "properties": {
    "iso:country":"US",
    "sg:address":"245 E Market St",
    "sg:city":"Kingsport",
    "sg:classifiers":[
        {
            "category":"Food & Beverages",
            "subcategory":"Groceries & Convenience Stores",
            "type":"Retail Goods"
        }
    ],
    "sg:phone":"+1 423 245 0045",
    "sg:postcode":"37660",
    "sg:province":"TN",
    "wof:name":"Kattys Korner",
    "wof:placetype":"venue"
},
  "geometry": {"coordinates":[-82.558779,36.545243],"type":"Point"}
}