{
  "type": "Feature",
  "properties": {
    "iso:country":"US",
    "sg:address":"210 Sixteenth Model Rd",
    "sg:city":"Manchester",
    "sg:classifiers":[
        {
            "category":"Building & Trades",
            "subcategory":"Landscaping Services",
            "type":"Services"
        }
    ],
    "sg:phone":"+1 931 723 1470",
    "sg:postcode":"37355",
    "sg:province":"TN",
    "wof:name":"Yard Works",
    "wof:placetype":"venue"
},
  "geometry": {"coordinates":[-86.161447,35.528509],"type":"Point"}
}