{
  "type": "Feature",
  "properties": {
    "iso:country":"US",
    "sg:address":"1808 Tucson Ln",
    "sg:city":"Knoxville",
    "sg:classifiers":[
        {
            "category":"Professional",
            "subcategory":"Art Services",
            "type":"Services"
        }
    ],
    "sg:phone":"+1 865 692 5259",
    "sg:postcode":"37922",
    "sg:province":"TN",
    "sg:tags":[
        "commercial",
        "design"
    ],
    "wof:name":"Tribal Tuna Graphix",
    "wof:placetype":"venue"
},
  "geometry": {"coordinates":[-84.087305,35.86451],"type":"Point"}
}