{
  "type": "Feature",
  "properties": {
    "iso:country":"US",
    "sg:address":"620 Cherokee Blvd",
    "sg:city":"Chattanooga",
    "sg:classifiers":[
        {
            "category":"Insurance",
            "subcategory":"Insurance Agent",
            "type":"Services"
        }
    ],
    "sg:phone":"+1 423 752 1734",
    "sg:postcode":"37405",
    "sg:province":"TN",
    "wof:name":"Security Group The",
    "wof:placetype":"venue"
},
  "geometry": {"coordinates":[-85.317752,35.069215],"type":"Point"}
}