{
  "type": "Feature",
  "properties": {
    "iso:country":"US",
    "sg:address":"4510 Hixson Pike",
    "sg:city":"Hixson",
    "sg:classifiers":[
        {
            "category":"Professional",
            "subcategory":"Accounting & Tax Preparation",
            "type":"Services"
        }
    ],
    "sg:phone":"+1 423 875 6565",
    "sg:postcode":"37343",
    "sg:province":"TN",
    "sg:tags":[
        "bookkeeping",
        "general"
    ],
    "wof:name":"Perry T Sherrell CPA",
    "wof:placetype":"venue"
},
  "geometry": {"coordinates":[-85.249104,35.119868],"type":"Point"}
}