{
  "type": "Feature",
  "properties": {
    "iso:country":"US",
    "sg:address":"100 Florence St",
    "sg:city":"Greeneville",
    "sg:classifiers":[
        {
            "category":"Building & Trades",
            "subcategory":"Construction",
            "type":"Services"
        }
    ],
    "sg:phone":"+1 423 639 8588",
    "sg:postcode":"37745",
    "sg:province":"TN",
    "sg:tags":[
        "painter"
    ],
    "wof:name":"Have Brush Will Travel",
    "wof:placetype":"venue"
},
  "geometry": {"coordinates":[-82.737849,36.167552],"type":"Point"}
}