{
  "type": "Feature",
  "properties": {
    "iso:country":"US",
    "sg:address":"1171 Nashville Hwy",
    "sg:city":"Lewisburg",
    "sg:classifiers":[
        {
            "category":"Government",
            "subcategory":"Office",
            "type":"Public Place"
        }
    ],
    "sg:phone":"+1 931 359 8021",
    "sg:postcode":"37091",
    "sg:province":"TN",
    "sg:tags":[
        "federal"
    ],
    "wof:name":"Natural Resources Conservation",
    "wof:placetype":"venue"
},
  "geometry": {"coordinates":[-86.77571500000001,35.465559],"type":"Point"}
}