{
  "type": "Feature",
  "properties": {
    "addr:full":"31 Northgate Mall Chattanooga TN 37415",
    "addr:housenumber":"31",
    "addr:postcode":"37415",
    "addr:street":"Northgate Mall",
    "iso:country":"US",
    "sg:address":"31 Northgate Mall",
    "sg:city":"Chattanooga",
    "sg:classifiers":[
        {
            "category":"Shopping",
            "subcategory":"Gifts & Souvenirs",
            "type":"Retail Goods"
        }
    ],
    "sg:phone":"+1 423 877 5025",
    "sg:postcode":"37415",
    "sg:province":"TN",
    "sg:tags":[
        "shop"
    ],
    "wof:name":"Hallmark",
    "wof:placetype":"venue"
},
  "geometry": {"coordinates":[-85.24433000000001,35.136703],"type":"Point"}
}