{
  "type": "Feature",
  "properties": {
    "iso:country":"US",
    "sg:address":"2047 W Elk Ave",
    "sg:city":"Elizabethton",
    "sg:classifiers":[
        {
            "category":"Autos & Motor Vehicles",
            "subcategory":"Automobile Sales",
            "type":"Retail Goods"
        }
    ],
    "sg:phone":"+1 423 543 8388",
    "sg:postcode":"37643",
    "sg:province":"TN",
    "sg:tags":[
        "car",
        "used",
        "dealer"
    ],
    "wof:name":"Stouts Riverside Auto Center",
    "wof:placetype":"venue"
},
  "geometry": {"coordinates":[-82.261698,36.336405],"type":"Point"}
}