{
  "type": "Feature",
  "properties": {
    "addr:full":"4462 Clarksville Pike Nashville TN 37218",
    "addr:housenumber":"4462",
    "addr:postcode":"37218",
    "addr:street":"Clarksville Pike",
    "iso:country":"US",
    "sg:address":"4462 Clarksville Pike",
    "sg:city":"Nashville",
    "sg:classifiers":[
        {
            "category":"Shopping",
            "subcategory":"Clothing, Apparel, & Fashions",
            "type":"Retail Goods"
        }
    ],
    "sg:phone":"+1 615 299 9715",
    "sg:postcode":"37218",
    "sg:province":"TN",
    "sg:tags":[
        "handbag"
    ],
    "wof:name":"Diva's Handbags",
    "wof:placetype":"venue"
},
  "geometry": {"coordinates":[-86.83812,36.223453],"type":"Point"}
}