{
  "type": "Feature",
  "properties": {
    "iso:country":"US",
    "sg:address":"165 Madison Ave",
    "sg:city":"Memphis",
    "sg:classifiers":[
        {
            "category":"Professional",
            "subcategory":"Lawyer & Legal Services",
            "type":"Services"
        }
    ],
    "sg:phone":"+1 901 526 2000",
    "sg:postcode":"38103",
    "sg:province":"TN",
    "sg:tags":[
        "attorney",
        "law",
        "administrative",
        "governmental",
        "business"
    ],
    "wof:name":"Flock , Adam C. - Baker, Donelson, Bearm",
    "wof:placetype":"venue"
},
  "geometry": {"coordinates":[-90.05064,35.144623],"type":"Point"}
}