{
  "type": "Feature",
  "properties": {
    "iso:country":"US",
    "sg:address":"5523 State Hwy 153",
    "sg:city":"Hixson",
    "sg:classifiers":[
        {
            "category":"Shopping",
            "subcategory":"Clothing, Apparel, & Fashions",
            "type":"Retail Goods"
        }
    ],
    "sg:phone":"+1 423 875 8860",
    "sg:postcode":"37343",
    "sg:province":"TN",
    "wof:name":"Rue 21",
    "wof:placetype":"venue"
},
  "geometry": {"coordinates":[-85.24911400000001,35.144301],"type":"Point"}
}