{
  "type": "Feature",
  "properties": {
    "addr:full":"2509 Cruzen St Nashville TN 37211",
    "addr:housenumber":"2509",
    "addr:postcode":"37211",
    "addr:street":"Cruzen St",
    "iso:country":"US",
    "sg:address":"2509 Cruzen St",
    "sg:city":"Nashville",
    "sg:classifiers":[
        {
            "category":"Building & Trades",
            "subcategory":"Plumbing",
            "type":"Services"
        }
    ],
    "sg:phone":"+1 615 256 4444",
    "sg:postcode":"37211",
    "sg:province":"TN",
    "sg:tags":[
        "sheet",
        "work",
        "metal",
        "contractor"
    ],
    "sg:website":"www.leaderindustries.com",
    "wof:name":"United Air",
    "wof:placetype":"venue"
},
  "geometry": {"coordinates":[-86.751766,36.115824],"type":"Point"}
}