{
  "type": "Feature",
  "properties": {
    "iso:country":"US",
    "sg:address":"4384 Stage Rd",
    "sg:city":"Memphis",
    "sg:classifiers":[
        {
            "category":"Personal",
            "subcategory":"Beauty Salon",
            "type":"Services"
        }
    ],
    "sg:phone":"+1 901 380 1180",
    "sg:postcode":"38128",
    "sg:province":"TN",
    "wof:name":"Growing Hands",
    "wof:placetype":"venue"
},
  "geometry": {"coordinates":[-89.91955799999999,35.205362],"type":"Point"}
}