{
  "type": "Feature",
  "properties": {
    "iso:country":"US",
    "sg:address":"5791 Summer Trees Dr",
    "sg:city":"Memphis",
    "sg:classifiers":[
        {
            "category":"Health Services",
            "subcategory":"Doctor",
            "type":"Services"
        }
    ],
    "sg:phone":"+1 901 383 8548",
    "sg:postcode":"38134",
    "sg:province":"TN",
    "sg:tags":[
        "physician",
        "surgeon"
    ],
    "wof:name":"Michael B Brady MD",
    "wof:placetype":"venue"
},
  "geometry": {"coordinates":[-89.874105,35.165547],"type":"Point"}
}