{
  "type": "Feature",
  "properties": {
    "addr:full":"337 W Mount Rd Kodak TN 37764",
    "addr:housenumber":"337",
    "addr:postcode":"37764",
    "addr:street":"W Mount Rd",
    "iso:country":"US",
    "sg:address":"337 W Mount Rd",
    "sg:city":"Kodak",
    "sg:classifiers":[
        {
            "category":"Organizations",
            "subcategory":"Religious Organization",
            "type":"Services"
        }
    ],
    "sg:phone":"+1 865 933 0692",
    "sg:postcode":"37764",
    "sg:province":"TN",
    "wof:name":"Beech Springs Baptist Church",
    "wof:placetype":"venue"
},
  "geometry": {"coordinates":[-83.615909,35.967648],"type":"Point"}
}