{
  "type": "Feature",
  "properties": {
    "iso:country":"US",
    "sg:address":"2101 Fort Henry Dr",
    "sg:city":"Kingsport",
    "sg:classifiers":[
        {
            "category":"Shopping",
            "type":"Retail Goods"
        }
    ],
    "sg:phone":"+1 423 247 9366",
    "sg:postcode":"37664",
    "sg:province":"TN",
    "sg:tags":[
        "merchandise"
    ],
    "wof:name":"Tennessee Communications",
    "wof:placetype":"venue"
},
  "geometry": {"coordinates":[-82.522086,36.527122],"type":"Point"}
}