{
  "type": "Feature",
  "properties": {
    "iso:country":"US",
    "sg:address":"7008 Penbrook Dr",
    "sg:city":"Franklin",
    "sg:classifiers":[
        {
            "category":"Manufacturing",
            "subcategory":"Tools & Machinery",
            "type":"Manufacturing & Wholesale Goods"
        }
    ],
    "sg:phone":"+1 615 369 0787",
    "sg:postcode":"37069",
    "sg:province":"TN",
    "sg:tags":[
        "terminal",
        "computer",
        "employment",
        "agency",
        "mfg"
    ],
    "wof:name":"Technically Right LLC",
    "wof:placetype":"venue"
},
  "geometry": {"coordinates":[-86.892027,35.96084],"type":"Point"}
}