{
  "type": "Feature",
  "properties": {
    "iso:country":"US",
    "sg:address":"1906 Columbia Ave",
    "sg:city":"Franklin",
    "sg:classifiers":[
        {
            "category":"Retail",
            "subcategory":"Auto Repair",
            "type":"Services"
        }
    ],
    "sg:phone":"+1 615 790 7216",
    "sg:postcode":"37064",
    "sg:province":"TN",
    "sg:tags":[
        "repairing",
        "automobile",
        "automotive",
        "general"
    ],
    "wof:name":"Crutcher's Auto Repair",
    "wof:placetype":"venue"
},
  "geometry": {"coordinates":[-86.876341,35.898117],"type":"Point"}
}