{
  "type": "Feature",
  "properties": {
    "iso:country":"US",
    "sg:address":"681 Carson Creek Rd",
    "sg:city":"Limestone",
    "sg:classifiers":[
        {
            "category":"Professional",
            "subcategory":"Business Services",
            "type":"Services"
        }
    ],
    "sg:phone":"+1 423 257 3903",
    "sg:postcode":"37681",
    "sg:province":"TN",
    "wof:name":"Home Inspection",
    "wof:placetype":"venue"
},
  "geometry": {"coordinates":[-82.629631,36.26825],"type":"Point"}
}