{
  "type": "Feature",
  "properties": {
    "iso:country":"US",
    "sg:address":"747 W Elk Ave",
    "sg:city":"Elizabethton",
    "sg:classifiers":[
        {
            "category":"Banks & Credit Unions",
            "subcategory":"Bank",
            "type":"Services"
        }
    ],
    "sg:phone":"+1 423 543 6817",
    "sg:postcode":"37643",
    "sg:province":"TN",
    "sg:tags":[
        "cashing",
        "personal",
        "check",
        "institution"
    ],
    "wof:name":"Advance America",
    "wof:placetype":"venue"
},
  "geometry": {"coordinates":[-82.232984,36.35147],"type":"Point"}
}