{
  "type": "Feature",
  "properties": {
    "iso:country":"US",
    "sg:address":"1134 N Broadway St",
    "sg:city":"Knoxville",
    "sg:classifiers":[
        {
            "category":"Home & Garden",
            "subcategory":"Carpets & Floor Coverings",
            "type":"Retail Goods"
        }
    ],
    "sg:phone":"+1 865 523 0731",
    "sg:postcode":"37917",
    "sg:province":"TN",
    "sg:tags":[
        "dealer",
        "rug"
    ],
    "wof:name":"Davis Carpets LLC",
    "wof:placetype":"venue"
},
  "geometry": {"coordinates":[-83.922703,35.982682],"type":"Point"}
}