{
  "type": "Feature",
  "properties": {
    "iso:country":"US",
    "sg:address":"145 Pickwick St S",
    "sg:city":"Savannah",
    "sg:classifiers":[
        {
            "category":"Health Services",
            "subcategory":"Doctor",
            "type":"Services"
        }
    ],
    "sg:phone":"+1 731 925 9277",
    "sg:postcode":"38372",
    "sg:province":"TN",
    "sg:tags":[
        "physician",
        "surgeon"
    ],
    "wof:name":"James H Thomas MD",
    "wof:placetype":"venue"
},
  "geometry": {"coordinates":[-88.246602,35.224154],"type":"Point"}
}