{
  "type": "Feature",
  "properties": {
    "iso:country":"US",
    "sg:address":"207 Commerce Dr",
    "sg:city":"Smyrna",
    "sg:classifiers":[
        {
            "category":"Social Services",
            "subcategory":"Adult Care",
            "type":"Services"
        }
    ],
    "sg:phone":"+1 615 355 9900",
    "sg:postcode":"37167",
    "sg:province":"TN",
    "sg:tags":[
        "residential"
    ],
    "wof:name":"Smyrna Residential Care Center",
    "wof:placetype":"venue"
},
  "geometry": {"coordinates":[-86.510822,35.975314],"type":"Point"}
}