{
  "type": "Feature",
  "properties": {
    "iso:country":"US",
    "sg:address":"201 Forks of the River Pkwy",
    "sg:city":"Sevierville",
    "sg:classifiers":[
        {
            "category":"Food & Beverages",
            "subcategory":"Groceries & Convenience Stores",
            "type":"Retail Goods"
        }
    ],
    "sg:phone":"+1 865 428 1544",
    "sg:postcode":"37862",
    "sg:province":"TN",
    "wof:name":"Kroger",
    "wof:placetype":"venue"
},
  "geometry": {"coordinates":[-83.567707,35.867269],"type":"Point"}
}