{
  "type": "Feature",
  "properties": {
    "addr:full":"1999 E Stone Dr Kingsport TN 37660",
    "addr:housenumber":"1999",
    "addr:postcode":"37660",
    "addr:street":"E Stone Dr",
    "iso:country":"US",
    "sg:address":"1999 E Stone Dr",
    "sg:city":"Kingsport",
    "sg:classifiers":[
        {
            "category":"Professional",
            "subcategory":"Lawyer & Legal Services",
            "type":"Services"
        }
    ],
    "sg:phone":"+1 423 230 2045",
    "sg:postcode":"37660",
    "sg:province":"TN",
    "sg:tags":[
        "attorney"
    ],
    "wof:name":"Arrington Schelin & Herrell PC",
    "wof:placetype":"venue"
},
  "geometry": {"coordinates":[-82.511538,36.545232],"type":"Point"}
}