{
  "type": "Feature",
  "properties": {
    "iso:country":"US",
    "sg:address":"714 N Germantown Pkwy",
    "sg:city":"Cordova",
    "sg:classifiers":[
        {
            "category":"Personal",
            "type":"Services"
        },
        {
            "category":"Sports & Exercise",
            "subcategory":"Gym",
            "type":"Entertainment"
        }
    ],
    "sg:phone":"+1 901 881 3078",
    "sg:postcode":"38018",
    "sg:province":"TN",
    "sg:tags":[
        "trainer",
        "consultant",
        "program",
        "physical",
        "fitness"
    ],
    "sg:website":"http://memphis.citysearch.com/profile/external/606936190/cordova_tn/jazzercise_cordova_fitness_center.html?publisher=yellowpages&reference_id=1&placement=ypwebsitemip",
    "wof:name":"Jazzercise Cordova Fitness Center",
    "wof:placetype":"venue"
},
  "geometry": {"coordinates":[-89.795427,35.144249],"type":"Point"}
}