{
  "type": "Feature",
  "properties": {
    "addr:full":"214 Dyllis Rd Harriman TN 37748",
    "addr:housenumber":"214",
    "addr:postcode":"37748",
    "addr:street":"Dyllis Rd",
    "iso:country":"US",
    "sg:address":"214 Dyllis Rd",
    "sg:city":"Harriman",
    "sg:classifiers":[
        {
            "category":"Shopping",
            "type":"Retail Goods"
        }
    ],
    "sg:phone":"+1 865 435 6053",
    "sg:postcode":"37748",
    "sg:province":"TN",
    "sg:tags":[
        "merchandise"
    ],
    "wof:name":"Deborah M Sylvia Dstrbtr",
    "wof:placetype":"venue"
},
  "geometry": {"coordinates":[-84.40880300000001,35.97331],"type":"Point"}
}