{
  "type": "Feature",
  "properties": {
    "addr:full":"1027 Mineral Wells Ave Paris TN 38242",
    "addr:housenumber":"1027",
    "addr:postcode":"38242",
    "addr:street":"Mineral Wells Ave",
    "iso:country":"US",
    "sg:address":"1027 Mineral Wells Ave",
    "sg:city":"Paris",
    "sg:classifiers":[
        {
            "category":"Professional",
            "subcategory":"Accounting & Tax Preparation",
            "type":"Services"
        }
    ],
    "sg:phone":"+1 731 642 2940",
    "sg:postcode":"38242",
    "sg:province":"TN",
    "sg:tags":[
        "return",
        "filing"
    ],
    "wof:name":"Business Dynamics LLC",
    "wof:placetype":"venue"
},
  "geometry": {"coordinates":[-88.31381,36.28947],"type":"Point"}
}