{
  "type": "Feature",
  "properties": {
    "addr:full":"708 W Forest Ave Jackson TN 38301",
    "addr:housenumber":"708",
    "addr:postcode":"38301",
    "addr:street":"W Forest Ave",
    "iso:country":"US",
    "sg:address":"708 W Forest Ave",
    "sg:city":"Jackson",
    "sg:classifiers":[
        {
            "category":"Restaurant",
            "type":"Food & Drink"
        }
    ],
    "sg:menulink":"http://www.allmenus.com/tn/jackson/140276-subway/menu/",
    "sg:phone":"+1 731 425 5699",
    "sg:postcode":"38301",
    "sg:province":"TN",
    "sg:tags":[
        "american",
        "sandwich"
    ],
    "wof:name":"Subway",
    "wof:placetype":"venue"
},
  "geometry": {"coordinates":[-88.83179699999999,35.637012],"type":"Point"}
}