{
  "type": "Feature",
  "properties": {
    "iso:country":"US",
    "sg:address":"2505 E Lamar Alexander Pkwy",
    "sg:city":"Maryville",
    "sg:classifiers":[
        {
            "category":"Food & Beverages",
            "subcategory":"Fruits & Vegetables",
            "type":"Retail Goods"
        },
        {
            "category":"Home & Garden",
            "subcategory":"Garden Supply",
            "type":"Retail Goods"
        }
    ],
    "sg:phone":"+1 865 984 9664",
    "sg:postcode":"37804",
    "sg:province":"TN",
    "sg:tags":[
        "center"
    ],
    "wof:name":"Mc Mahans Produce",
    "wof:placetype":"venue"
},
  "geometry": {"coordinates":[-83.931889,35.756043],"type":"Point"}
}