{
  "type": "Feature",
  "properties": {
    "iso:country":"US",
    "sg:address":"4820 Washington Pike",
    "sg:city":"Knoxville",
    "sg:classifiers":[
        {
            "category":"Freight",
            "type":"Transportation"
        }
    ],
    "sg:phone":"+1 865 637 6300",
    "sg:postcode":"37917",
    "sg:province":"TN",
    "sg:tags":[
        "special",
        "general"
    ],
    "wof:name":"East Town Self Storage",
    "wof:placetype":"venue"
},
  "geometry": {"coordinates":[-83.883172,36.026579],"type":"Point"}
}