{
  "type": "Feature",
  "properties": {
    "addr:full":"30 Grassland Rd Crossville TN 38572",
    "addr:housenumber":"30",
    "addr:postcode":"38572",
    "addr:street":"Grassland Rd",
    "iso:country":"US",
    "sg:address":"30 Grassland Rd",
    "sg:city":"Crossville",
    "sg:classifiers":[
        {
            "category":"Real Estate",
            "subcategory":"Developer",
            "type":"Services"
        }
    ],
    "sg:phone":"+1 931 788 6371",
    "sg:postcode":"38572",
    "sg:province":"TN",
    "sg:tags":[
        "association"
    ],
    "wof:name":"Grassland Subdivision Property",
    "wof:placetype":"venue"
},
  "geometry": {"coordinates":[-85.073044,35.841915],"type":"Point"}
}