{
  "type": "Feature",
  "properties": {
    "iso:country":"US",
    "sg:address":"3340 Poplar Ave",
    "sg:city":"Memphis",
    "sg:classifiers":[
        {
            "category":"Health Services",
            "subcategory":"Clinic",
            "type":"Services"
        }
    ],
    "sg:phone":"+1 901 324 3049",
    "sg:postcode":"38111",
    "sg:province":"TN",
    "sg:tags":[
        "home"
    ],
    "wof:name":"Caring Angels Health Care",
    "wof:placetype":"venue"
},
  "geometry": {"coordinates":[-89.951759,35.129507],"type":"Point"}
}