{
  "type": "Feature",
  "properties": {
    "addr:full":"4279 Benton Ave Chattanooga TN 37406",
    "addr:housenumber":"4279",
    "addr:postcode":"37406",
    "addr:street":"Benton Ave",
    "iso:country":"US",
    "sg:address":"4279 Benton Ave",
    "sg:city":"Chattanooga",
    "sg:classifiers":[
        {
            "category":"Communications",
            "subcategory":"Television Station",
            "type":"Services"
        }
    ],
    "sg:phone":"+1 423 756 5500",
    "sg:postcode":"37406",
    "sg:province":"TN",
    "sg:tags":[
        "broadcasting",
        "co"
    ],
    "sg:website":"www.newschannel9.com",
    "wof:name":"News Channel 9",
    "wof:placetype":"venue"
},
  "geometry": {"coordinates":[-85.210082,35.082928],"type":"Point"}
}