{
  "type": "Feature",
  "properties": {
    "addr:full":"456 W Valley Dr Lot 5 Kingsport TN 37664",
    "addr:housenumber":"456;5",
    "addr:postcode":"37664",
    "addr:street":"W Valley Dr Lot",
    "iso:country":"US",
    "sg:address":"456 W Valley Dr Lot 5",
    "sg:city":"Kingsport",
    "sg:classifiers":[
        {
            "category":"Retail",
            "subcategory":"Repair Shop",
            "type":"Services"
        }
    ],
    "sg:phone":"+1 423 677 5576",
    "sg:postcode":"37664",
    "sg:province":"TN",
    "sg:tags":[
        "dishwasher",
        "refinishing",
        "appliance",
        "major",
        "dryer",
        "small",
        "washer",
        "freezers-repair",
        "refrigerator"
    ],
    "wof:name":"Ottie's Appliance Repair",
    "wof:placetype":"venue"
},
  "geometry": {"coordinates":[-82.57658000000001,36.4438],"type":"Point"}
}