{
  "type": "Feature",
  "properties": {
    "iso:country":"US",
    "sg:address":"5850 Scott Hwy",
    "sg:city":"Robbins",
    "sg:classifiers":[
        {
            "category":"Insurance",
            "subcategory":"Insurance Agent",
            "type":"Services"
        }
    ],
    "sg:phone":"+1 423 627 2122",
    "sg:postcode":"37852",
    "sg:province":"TN",
    "wof:name":"Keeton's Insurance & Monument",
    "wof:placetype":"venue"
},
  "geometry": {"coordinates":[-84.588455,36.357201],"type":"Point"}
}