{
  "type": "Feature",
  "properties": {
    "iso:country":"US",
    "sg:address":"211 Sherway Rd",
    "sg:city":"Knoxville",
    "sg:classifiers":[
        {
            "category":"Manufacturing",
            "subcategory":"Printing",
            "type":"Manufacturing & Wholesale Goods"
        }
    ],
    "sg:phone":"+1 865 690 0288",
    "sg:postcode":"37922",
    "sg:province":"TN",
    "sg:tags":[
        "commercial",
        "printer",
        "lithographic"
    ],
    "sg:website":"www.blytheprinting.com",
    "wof:name":"Blythe Printing Inc",
    "wof:placetype":"venue"
},
  "geometry": {"coordinates":[-84.110035,35.908929],"type":"Point"}
}