{
  "type": "Feature",
  "properties": {
    "iso:country":"US",
    "sg:address":"6515 Scenic Dr",
    "sg:city":"Murfreesboro",
    "sg:classifiers":[
        {
            "category":"Organizations",
            "subcategory":"Religious Organization",
            "type":"Services"
        }
    ],
    "sg:phone":"+1 615 459 0025",
    "sg:postcode":"37129",
    "sg:province":"TN",
    "sg:tags":[
        "church"
    ],
    "wof:name":"Scenic Drive Baptist Church",
    "wof:placetype":"venue"
},
  "geometry": {"coordinates":[-86.488197,35.932721],"type":"Point"}
}