{
  "type": "Feature",
  "properties": {
    "addr:full":"576 Oak Ridge Tpke Oak Ridge TN 37830",
    "addr:housenumber":"576",
    "addr:postcode":"37830",
    "addr:street":"Oak Ridge Tpke",
    "iso:country":"US",
    "sg:address":"576 Oak Ridge Tpke",
    "sg:city":"Oak Ridge",
    "sg:classifiers":[
        {
            "category":"Professional",
            "subcategory":"Management & Consulting",
            "type":"Services"
        }
    ],
    "sg:phone":"+1 865 483 3726",
    "sg:postcode":"37830",
    "sg:province":"TN",
    "sg:tags":[
        "consultant",
        "business"
    ],
    "wof:name":"RAM-Vitec Inc",
    "wof:placetype":"venue"
},
  "geometry": {"coordinates":[-84.227925,36.032045],"type":"Point"}
}