{
  "type": "Feature",
  "properties": {
    "addr:full":"2020 US Hwy 11 E Jonesborough TN 37659",
    "addr:housenumber":"2020",
    "addr:postcode":"37659",
    "addr:street":"Us Hwy 11 E Jonesborough",
    "iso:country":"US",
    "sg:address":"2020 US Hwy 11 E",
    "sg:city":"Jonesborough",
    "sg:classifiers":[
        {
            "category":"Manufacturing",
            "subcategory":"Tools & Machinery",
            "type":"Manufacturing & Wholesale Goods"
        }
    ],
    "sg:phone":"+1 423 913 0515",
    "sg:postcode":"37659",
    "sg:province":"TN",
    "sg:tags":[
        "manufacture",
        "furnace",
        "burning",
        "retail",
        "wood",
        "distributes"
    ],
    "sg:website":"www.freeheatmachine.com",
    "wof:name":"Timber Ridge Inc",
    "wof:placetype":"venue"
},
  "geometry": {"coordinates":[-82.51503599999999,36.283397],"type":"Point"}
}