{
  "type": "Feature",
  "properties": {
    "addr:full":"620 W Mountainview Rd Johnson City TN 37604",
    "addr:housenumber":"620",
    "addr:postcode":"37604",
    "addr:street":"W Mountainview Rd",
    "iso:country":"US",
    "sg:address":"620 W Mountainview Rd",
    "sg:city":"Johnson City",
    "sg:classifiers":[
        {
            "category":"Government",
            "subcategory":"Office",
            "type":"Public Place"
        }
    ],
    "sg:phone":"+1 423 283 0982",
    "sg:postcode":"37604",
    "sg:province":"TN",
    "sg:tags":[
        "village"
    ],
    "wof:name":"Roundtree Pump Station",
    "wof:placetype":"venue"
},
  "geometry": {"coordinates":[-82.409705,36.351265],"type":"Point"}
}