{
  "type": "Feature",
  "properties": {
    "iso:country":"US",
    "sg:address":"6030 Bresslyn Rd",
    "sg:city":"Nashville",
    "sg:classifiers":[
        {
            "category":"Professional",
            "type":"Services"
        }
    ],
    "sg:phone":"+1 615 353 0569",
    "sg:postcode":"37205",
    "sg:province":"TN",
    "wof:name":"Hematotypes Inc",
    "wof:placetype":"venue"
},
  "geometry": {"coordinates":[-86.877708,36.116554],"type":"Point"}
}