{
  "type": "Feature",
  "properties": {
    "addr:full":"183 Mesa Trl Sparta TN 38583",
    "addr:housenumber":"183",
    "addr:postcode":"38583",
    "addr:street":"Mesa Trl",
    "iso:country":"US",
    "sg:address":"183 Mesa Trl",
    "sg:city":"Sparta",
    "sg:classifiers":[
        {
            "category":"Banks & Credit Unions",
            "subcategory":"Bank",
            "type":"Services"
        }
    ],
    "sg:phone":"+1 931 738 3187",
    "sg:postcode":"38583",
    "sg:province":"TN",
    "sg:tags":[
        "personal",
        "loan",
        "real estate",
        "institution"
    ],
    "wof:name":"Citi Financial",
    "wof:placetype":"venue"
},
  "geometry": {"coordinates":[-85.377138,35.936714],"type":"Point"}
}