{
  "type": "Feature",
  "properties": {
    "iso:country":"US",
    "sg:address":"313 Wilhagan Rd",
    "sg:city":"Nashville",
    "sg:classifiers":[
        {
            "category":"Manufacturing",
            "subcategory":"Metals",
            "type":"Manufacturing & Wholesale Goods"
        }
    ],
    "sg:phone":"+1 615 367 2030",
    "sg:postcode":"37217",
    "sg:province":"TN",
    "sg:tags":[
        "coating",
        "powder"
    ],
    "wof:name":"Woodbury Corp",
    "wof:placetype":"venue"
},
  "geometry": {"coordinates":[-86.71866,36.133555],"type":"Point"}
}