{
  "type": "Feature",
  "properties": {
    "iso:country":"US",
    "sg:address":"102 Double Springs Rd",
    "sg:city":"Murfreesboro",
    "sg:classifiers":[
        {
            "category":"Retail",
            "subcategory":"Auto Repair",
            "type":"Services"
        }
    ],
    "sg:phone":"+1 615 893 5704",
    "sg:postcode":"37127",
    "sg:province":"TN",
    "sg:tags":[
        "general"
    ],
    "wof:name":"Auto Maintenance Inc",
    "wof:placetype":"venue"
},
  "geometry": {"coordinates":[-86.337017,35.836179],"type":"Point"}
}