{
  "type": "Feature",
  "properties": {
    "addr:full":"1436 Robinson Rd Old Hickory TN 37138",
    "addr:housenumber":"1436",
    "addr:postcode":"37138",
    "addr:street":"Robinson Rd",
    "iso:country":"US",
    "sg:address":"1436 Robinson Rd",
    "sg:city":"Old Hickory",
    "sg:classifiers":[
        {
            "category":"Restaurant",
            "type":"Food & Drink"
        }
    ],
    "sg:menulink":"http://www.allmenus.com/tn/nashville/154983-hardees/menu/",
    "sg:phone":"+1 615 847 8854",
    "sg:postcode":"37138",
    "sg:province":"TN",
    "sg:tags":[
        "burger",
        "american"
    ],
    "wof:name":"Hardee's",
    "wof:placetype":"venue"
},
  "geometry": {"coordinates":[-86.655129,36.256175],"type":"Point"}
}