{
  "type": "Feature",
  "properties": {
    "addr:full":"5025 Rockport McIllwain Rd Holladay TN 38341",
    "addr:housenumber":"5025",
    "addr:postcode":"38341",
    "addr:street":"Rockport Mcillwain Rd",
    "iso:country":"US",
    "sg:address":"5025 Rockport McIllwain Rd",
    "sg:city":"Holladay",
    "sg:classifiers":[
        {
            "category":"Professional",
            "subcategory":"Business Services",
            "type":"Services"
        }
    ],
    "sg:phone":"+1 731 584 9084",
    "sg:postcode":"38341",
    "sg:province":"TN",
    "sg:tags":[
        "automobile",
        "appraiser"
    ],
    "wof:name":"Property Damage Appraisers Inc",
    "wof:placetype":"venue"
},
  "geometry": {"coordinates":[-88.074247,35.8827],"type":"Point"}
}