{
  "type": "Feature",
  "properties": {
    "iso:country":"US",
    "sg:address":"200 W Church St",
    "sg:city":"Lexington",
    "sg:classifiers":[
        {
            "category":"Health Services",
            "subcategory":"Clinic",
            "type":"Services"
        }
    ],
    "sg:phone":"+1 731 968 1860",
    "sg:postcode":"38351",
    "sg:province":"TN",
    "sg:tags":[
        "home",
        "care"
    ],
    "wof:name":"Community Home Health",
    "wof:placetype":"venue"
},
  "geometry": {"coordinates":[-88.398684,35.654231],"type":"Point"}
}