{
  "type": "Feature",
  "properties": {
    "iso:country":"US",
    "sg:address":"9 Pennsylvania Ave",
    "sg:city":"Bristol",
    "sg:classifiers":[
        {
            "category":"Personal",
            "subcategory":"Tattoo Parlor",
            "type":"Services"
        }
    ],
    "sg:phone":"+1 423 968 3939",
    "sg:postcode":"37620",
    "sg:province":"TN",
    "sg:tags":[
        "tattooing"
    ],
    "wof:name":"Billy Jack's Tattoos",
    "wof:placetype":"venue"
},
  "geometry": {"coordinates":[-82.17728,36.594719],"type":"Point"}
}