{
  "type": "Feature",
  "properties": {
    "iso:country":"US",
    "sg:address":"713 E Emory Rd",
    "sg:city":"Knoxville",
    "sg:classifiers":[
        {
            "category":"Insurance",
            "subcategory":"Insurance Agent",
            "type":"Services"
        }
    ],
    "sg:phone":"+1 865 938 3824",
    "sg:postcode":"37938",
    "sg:province":"TN",
    "wof:name":"J & S Insurance",
    "wof:placetype":"venue"
},
  "geometry": {"coordinates":[-83.98904400000001,36.053211],"type":"Point"}
}