{
  "type": "Feature",
  "properties": {
    "iso:country":"US",
    "sg:address":"295 S Bellevue Blvd",
    "sg:city":"Memphis",
    "sg:classifiers":[
        {
            "category":"Health Services",
            "subcategory":"Doctor",
            "type":"Services"
        }
    ],
    "sg:phone":"+1 901 272 3070",
    "sg:postcode":"38104",
    "sg:province":"TN",
    "sg:tags":[
        "medical"
    ],
    "wof:name":"Rudorfer Bennett L MD",
    "wof:placetype":"venue"
},
  "geometry": {"coordinates":[-90.02086,35.133934],"type":"Point"}
}