{
  "type": "Feature",
  "properties": {
    "iso:country":"US",
    "sg:address":"142 Churchill Dr",
    "sg:city":"Sparta",
    "sg:classifiers":[
        {
            "category":"Shopping",
            "subcategory":"Computers & Home Electronics",
            "type":"Retail Goods"
        }
    ],
    "sg:phone":"+1 931 836 2600",
    "sg:postcode":"38583",
    "sg:province":"TN",
    "sg:tags":[
        "equipment",
        "satellite",
        "system"
    ],
    "wof:name":"National Communications Inc",
    "wof:placetype":"venue"
},
  "geometry": {"coordinates":[-85.481948,35.937277],"type":"Point"}
}