{
  "type": "Feature",
  "properties": {
    "iso:country":"US",
    "sg:address":"5357 McMinnville Hwy",
    "sg:city":"Manchester",
    "sg:classifiers":[
        {
            "category":"Building & Trades",
            "subcategory":"Landscaping Services",
            "type":"Services"
        }
    ],
    "sg:phone":"+1 931 723 5000",
    "sg:postcode":"37355",
    "sg:province":"TN",
    "wof:name":"Pebbles & Ponds",
    "wof:placetype":"venue"
},
  "geometry": {"coordinates":[-86.01356699999999,35.528539],"type":"Point"}
}