{
  "type": "Feature",
  "properties": {
    "addr:full":"4617 Central Avenue Pike Knoxville TN 37912",
    "addr:housenumber":"4617",
    "addr:postcode":"37912",
    "addr:street":"Central Avenue Pike",
    "iso:country":"US",
    "sg:address":"4617 Central Avenue Pike",
    "sg:city":"Knoxville",
    "sg:classifiers":[
        {
            "category":"Shopping",
            "subcategory":"Crafts & Fabrics",
            "type":"Retail Goods"
        }
    ],
    "sg:phone":"+1 865 577 7785",
    "sg:postcode":"37912",
    "sg:province":"TN",
    "sg:tags":[
        "sewing"
    ],
    "wof:name":"TNT Custom Embroidery",
    "wof:placetype":"venue"
},
  "geometry": {"coordinates":[-83.96584199999999,36.00742],"type":"Point"}
}