{
  "type": "Feature",
  "properties": {
    "iso:country":"US",
    "sg:address":"55 Jones Bend Rd",
    "sg:city":"Paris",
    "sg:classifiers":[
        {
            "category":"Social Services",
            "subcategory":"Child Care",
            "type":"Services"
        }
    ],
    "sg:phone":"+1 731 642 6444",
    "sg:postcode":"38242",
    "sg:province":"TN",
    "wof:name":"Tennessee Early Childhood Ctr",
    "wof:placetype":"venue"
},
  "geometry": {"coordinates":[-88.343783,36.31002],"type":"Point"}
}