{
  "type": "Feature",
  "properties": {
    "iso:country":"US",
    "sg:address":"210 Marvin Terry Ln",
    "sg:city":"Henderson",
    "sg:classifiers":[
        {
            "category":"Building & Trades",
            "subcategory":"Construction",
            "type":"Services"
        }
    ],
    "sg:phone":"+1 731 989 3947",
    "sg:postcode":"38340",
    "sg:province":"TN",
    "sg:tags":[
        "framing",
        "contractor"
    ],
    "wof:name":"Bobby Evans Construction",
    "wof:placetype":"venue"
},
  "geometry": {"coordinates":[-88.592271,35.418029],"type":"Point"}
}