{
  "type": "Feature",
  "properties": {
    "addr:full":"3112 Rollingstone Dr Antioch TN 37013",
    "addr:housenumber":"3112",
    "addr:postcode":"37013",
    "addr:street":"Rollingstone Dr",
    "iso:country":"US",
    "sg:address":"3112 Rollingstone Dr",
    "sg:city":"Antioch",
    "sg:classifiers":[
        {
            "category":"Professional",
            "subcategory":"Management & Consulting",
            "type":"Services"
        }
    ],
    "sg:phone":"+1 615 579 1230",
    "sg:postcode":"37013",
    "sg:province":"TN",
    "sg:tags":[
        "fuel"
    ],
    "wof:name":"A M Management Group",
    "wof:placetype":"venue"
},
  "geometry": {"coordinates":[-86.61633999999999,36.072348],"type":"Point"}
}