{
  "type": "Feature",
  "properties": {
    "iso:country":"US",
    "sg:address":"131 Fergus Rd",
    "sg:city":"Carthage",
    "sg:classifiers":[
        {
            "category":"Manufacturing",
            "subcategory":"Metals",
            "type":"Manufacturing & Wholesale Goods"
        }
    ],
    "sg:phone":"+1 615 735 3201",
    "sg:postcode":"37086",
    "sg:province":"TN",
    "sg:tags":[
        "tube",
        "fabricating"
    ],
    "sg:website":"www.overstreet-hughes.com",
    "wof:name":"Overstreet-Hughes Co",
    "wof:placetype":"venue"
},
  "geometry": {"coordinates":[-86.544123,36.010725],"type":"Point"}
}