{
  "type": "Feature",
  "properties": {
    "addr:full":"201 N Fulton Dr Corinth TN 38834",
    "addr:housenumber":"201",
    "addr:postcode":"38834",
    "addr:street":"N Fulton Dr",
    "iso:country":"US",
    "sg:address":"201 N Fulton Dr",
    "sg:city":"Corinth",
    "sg:classifiers":[
        {
            "category":"Wholesale",
            "subcategory":"Groceries",
            "type":"Manufacturing & Wholesale Goods"
        }
    ],
    "sg:phone":"+1 662 287 6689",
    "sg:postcode":"38834",
    "sg:province":"TN",
    "sg:tags":[
        "grocer"
    ],
    "wof:name":"Long Wholesale Distributors",
    "wof:placetype":"venue"
},
  "geometry": {"coordinates":[-88.52627099999999,34.937006],"type":"Point"}
}