{
  "type": "Feature",
  "properties": {
    "iso:country":"US",
    "sg:address":"7120 Maynardville Pike",
    "sg:city":"Knoxville",
    "sg:classifiers":[
        {
            "category":"Utilities",
            "subcategory":"Mobile Phone",
            "type":"Services"
        }
    ],
    "sg:phone":"+1 865 925 0200",
    "sg:postcode":"37918",
    "sg:province":"TN",
    "sg:tags":[
        "telephone",
        "cellular"
    ],
    "wof:name":"Aircom Cellular & Paging",
    "wof:placetype":"venue"
},
  "geometry": {"coordinates":[-83.92711799999999,36.078576],"type":"Point"}
}