{
  "type": "Feature",
  "properties": {
    "addr:full":"454 N Willett St Memphis TN 38112",
    "addr:housenumber":"454",
    "addr:postcode":"38112",
    "addr:street":"N Willett St",
    "iso:country":"US",
    "sg:address":"454 N Willett St",
    "sg:city":"Memphis",
    "sg:classifiers":[
        {
            "category":"Organizations",
            "subcategory":"Membership Organization",
            "type":"Services"
        }
    ],
    "sg:phone":"+1 901 274 4944",
    "sg:postcode":"38112",
    "sg:province":"TN",
    "wof:name":"Friends Of Tyson Pratcher Hq",
    "wof:placetype":"venue"
},
  "geometry": {"coordinates":[-90.007975,35.149979],"type":"Point"}
}