{
  "type": "Feature",
  "properties": {
    "addr:full":"1238 Pine St Kingsport TN 37664",
    "addr:housenumber":"1238",
    "addr:postcode":"37664",
    "addr:street":"Pine St",
    "iso:country":"US",
    "sg:address":"1238 Pine St",
    "sg:city":"Kingsport",
    "sg:classifiers":[
        {
            "category":"Organizations",
            "subcategory":"Religious Organization",
            "type":"Services"
        }
    ],
    "sg:phone":"+1 423 245 9157",
    "sg:postcode":"37664",
    "sg:province":"TN",
    "sg:tags":[
        "church"
    ],
    "wof:name":"Calvary Baptist Church Inc",
    "wof:placetype":"venue"
},
  "geometry": {"coordinates":[-82.545728,36.537254],"type":"Point"}
}