{
  "type": "Feature",
  "properties": {
    "addr:full":"3017 Rossville Blvd Chattanooga TN 37407",
    "addr:housenumber":"3017",
    "addr:postcode":"37407",
    "addr:street":"Rossville Blvd",
    "iso:country":"US",
    "sg:address":"3017 Rossville Blvd",
    "sg:city":"Chattanooga",
    "sg:classifiers":[
        {
            "category":"Autos & Motor Vehicles",
            "subcategory":"Auto Supplies",
            "type":"Retail Goods"
        }
    ],
    "sg:phone":"+1 423 624 9090",
    "sg:postcode":"37407",
    "sg:province":"TN",
    "sg:tags":[
        "tire"
    ],
    "wof:name":"Nu 2U Tires",
    "wof:placetype":"venue"
},
  "geometry": {"coordinates":[-85.293745,35.009031],"type":"Point"}
}