{
  "type": "Feature",
  "properties": {
    "addr:full":"5770 Old Hwy 48 Cunningham TN 37052",
    "addr:housenumber":"5770",
    "addr:postcode":"37052",
    "addr:street":"Old Hwy 48 Cunningham",
    "iso:country":"US",
    "sg:address":"5770 Old Hwy 48",
    "sg:city":"Cunningham",
    "sg:classifiers":[
        {
            "category":"Freight",
            "type":"Transportation"
        }
    ],
    "sg:phone":"+1 931 387 3630",
    "sg:postcode":"37052",
    "sg:province":"TN",
    "sg:tags":[
        "mobile",
        "home"
    ],
    "wof:name":"Wall Contractors & Supply",
    "wof:placetype":"venue"
},
  "geometry": {"coordinates":[-87.3458,36.334894],"type":"Point"}
}