{
  "type": "Feature",
  "properties": {
    "addr:full":"131 Clay Little Rd Elizabethton TN 37643",
    "addr:housenumber":"131",
    "addr:postcode":"37643",
    "addr:street":"Clay Little Rd",
    "iso:country":"US",
    "sg:address":"131 Clay Little Rd",
    "sg:city":"Elizabethton",
    "sg:classifiers":[
        {
            "category":"Retail",
            "subcategory":"Auto Repair",
            "type":"Services"
        }
    ],
    "sg:phone":"+1 423 542 5427",
    "sg:postcode":"37643",
    "sg:province":"TN",
    "sg:tags":[
        "general"
    ],
    "wof:name":"Mobile Mechanic",
    "wof:placetype":"venue"
},
  "geometry": {"coordinates":[-82.202124,36.312509],"type":"Point"}
}