{
  "type": "Feature",
  "properties": {
    "addr:full":"2165 Bruton Branch Rd Savannah TN 38372",
    "addr:housenumber":"2165",
    "addr:postcode":"38372",
    "addr:street":"Bruton Branch Rd",
    "iso:country":"US",
    "sg:address":"2165 Bruton Branch Rd",
    "sg:city":"Savannah",
    "sg:classifiers":[
        {
            "category":"Professional",
            "subcategory":"Business Services",
            "type":"Services"
        }
    ],
    "sg:phone":"+1 731 926 3972",
    "sg:postcode":"38372",
    "sg:province":"TN",
    "wof:name":"Reeves Property Group",
    "wof:placetype":"venue"
},
  "geometry": {"coordinates":[-88.18108599999999,35.063096],"type":"Point"}
}