{
  "type": "Feature",
  "properties": {
    "addr:full":"1802 Williamson Ct Brentwood TN 37027",
    "addr:housenumber":"1802",
    "addr:postcode":"37027",
    "addr:street":"Williamson Ct",
    "iso:country":"US",
    "sg:address":"1802 Williamson Ct",
    "sg:city":"Brentwood",
    "sg:classifiers":[
        {
            "category":"Insurance",
            "subcategory":"Insurance Agent",
            "type":"Services"
        }
    ],
    "sg:phone":"+1 615 372 0389",
    "sg:postcode":"37027",
    "sg:province":"TN",
    "sg:website":"www.aflac.com",
    "wof:name":"AFLAC",
    "wof:placetype":"venue"
},
  "geometry": {"coordinates":[-86.818577,35.958308],"type":"Point"}
}