{
  "type": "Feature",
  "properties": {
    "addr:full":"112 Thomaswood Chase Tullahoma TN 37388",
    "addr:housenumber":"112",
    "addr:postcode":"37388",
    "addr:street":"Thomaswood Chase",
    "iso:country":"US",
    "sg:address":"112 Thomaswood Chase",
    "sg:city":"Tullahoma",
    "sg:classifiers":[
        {
            "category":"Professional",
            "subcategory":"Research",
            "type":"Services"
        }
    ],
    "sg:phone":"+1 931 393 5167",
    "sg:postcode":"37388",
    "sg:province":"TN",
    "sg:tags":[
        "environmental",
        "ecological"
    ],
    "wof:name":"Sandlin Environmental Cnsltng",
    "wof:placetype":"venue"
},
  "geometry": {"coordinates":[-86.18922999999999,35.390863],"type":"Point"}
}