{
  "type": "Feature",
  "properties": {
    "iso:country":"US",
    "sg:address":"3676 Baxter Ave",
    "sg:city":"Nashville",
    "sg:classifiers":[
        {
            "category":"Retail",
            "subcategory":"Repair Shop",
            "type":"Services"
        }
    ],
    "sg:phone":"+1 615 299 8057",
    "sg:postcode":"37216",
    "sg:province":"TN",
    "wof:name":"Pinnacle Awning Cleaning Speci",
    "wof:placetype":"venue"
},
  "geometry": {"coordinates":[-86.73317900000001,36.213787],"type":"Point"}
}