{
  "type": "Feature",
  "properties": {
    "addr:full":"2044 Charjean Rd Memphis TN 38114",
    "addr:housenumber":"2044",
    "addr:postcode":"38114",
    "addr:street":"Charjean Rd",
    "iso:country":"US",
    "sg:address":"2044 Charjean Rd",
    "sg:city":"Memphis",
    "sg:classifiers":[
        {
            "category":"Professional",
            "subcategory":"Business Services",
            "type":"Services"
        }
    ],
    "sg:phone":"+1 901 744 9880",
    "sg:postcode":"38114",
    "sg:province":"TN",
    "sg:tags":[
        "recording",
        "studio"
    ],
    "wof:name":"Stone Records",
    "wof:placetype":"venue"
},
  "geometry": {"coordinates":[-89.983171,35.088784],"type":"Point"}
}