{
  "type": "Feature",
  "properties": {
    "iso:country":"US",
    "sg:address":"616 Munford-Atoka Ave",
    "sg:city":"Munford",
    "sg:classifiers":[
        {
            "category":"Building & Trades",
            "subcategory":"Construction",
            "type":"Services"
        }
    ],
    "sg:phone":"+1 901 837 4281",
    "sg:postcode":"38058",
    "sg:province":"TN",
    "sg:tags":[
        "tile",
        "dealer"
    ],
    "wof:name":"Classic Marble & Tile",
    "wof:placetype":"venue"
},
  "geometry": {"coordinates":[-89.798472,35.446553],"type":"Point"}
}