{
  "type": "Feature",
  "properties": {
    "iso:country":"US",
    "sg:address":"111 Jenkins Rd",
    "sg:city":"Gordonsville",
    "sg:classifiers":[
        {
            "category":"Professional",
            "subcategory":"Business Services",
            "type":"Services"
        }
    ],
    "sg:phone":"+1 615 683 6475",
    "sg:postcode":"37030",
    "sg:province":"TN",
    "wof:name":"Eric Ingram Business",
    "wof:placetype":"venue"
},
  "geometry": {"coordinates":[-86.05692000000001,36.253061],"type":"Point"}
}