{
  "type": "Feature",
  "properties": {
    "iso:country":"US",
    "sg:address":"1509 Neelys Bend Rd",
    "sg:city":"Madison",
    "sg:classifiers":[
        {
            "category":"Professional",
            "subcategory":"Business Services",
            "type":"Services"
        }
    ],
    "sg:phone":"+1 615 612 2600",
    "sg:postcode":"37115",
    "sg:province":"TN",
    "sg:tags":[
        "lecture",
        "bureau",
        "seminar"
    ],
    "wof:name":"Educare",
    "wof:placetype":"venue"
},
  "geometry": {"coordinates":[-86.668694,36.22909],"type":"Point"}
}