{
  "type": "Feature",
  "properties": {
    "iso:country":"US",
    "sg:address":"574 Trousdale Ferry Pike",
    "sg:city":"Lebanon",
    "sg:classifiers":[
        {
            "category":"Real Estate",
            "subcategory":"Real Estate Operator",
            "type":"Services"
        }
    ],
    "sg:phone":"+1 615 453 0700",
    "sg:postcode":"37087",
    "sg:province":"TN",
    "sg:tags":[
        "building",
        "apartment"
    ],
    "wof:name":"Spring Hill Townhomes",
    "wof:placetype":"venue"
},
  "geometry": {"coordinates":[-86.268716,36.209163],"type":"Point"}
}