{
  "type": "Feature",
  "properties": {
    "iso:country":"US",
    "sg:address":"809 Bradyville Rd",
    "sg:city":"Woodbury",
    "sg:classifiers":[
        {
            "category":"Food & Beverages",
            "subcategory":"Groceries & Convenience Stores",
            "type":"Retail Goods"
        }
    ],
    "sg:phone":"+1 615 563 1402",
    "sg:postcode":"37190",
    "sg:province":"TN",
    "wof:name":"Parsley's Market & Deli",
    "wof:placetype":"venue"
},
  "geometry": {"coordinates":[-86.150756,35.806737],"type":"Point"}
}