{
  "type": "Feature",
  "properties": {
    "addr:full":"463 Parkway Gatlinburg TN 37738",
    "addr:housenumber":"463",
    "addr:postcode":"37738",
    "addr:street":"Parkway",
    "iso:country":"US",
    "sg:address":"463 Parkway",
    "sg:city":"Gatlinburg",
    "sg:classifiers":[
        {
            "category":"Shopping",
            "subcategory":"Clothing, Apparel, & Fashions",
            "type":"Retail Goods"
        }
    ],
    "sg:phone":"+1 865 430 3152",
    "sg:postcode":"37738",
    "sg:province":"TN",
    "sg:tags":[
        "sportswear"
    ],
    "wof:name":"Maggie's Sportswear",
    "wof:placetype":"venue"
},
  "geometry": {"coordinates":[-83.51072600000001,35.715442],"type":"Point"}
}