{
  "type": "Feature",
  "properties": {
    "iso:country":"US",
    "sg:address":"601 Asheville Hwy",
    "sg:city":"Greeneville",
    "sg:classifiers":[
        {
            "category":"Food & Beverages",
            "subcategory":"Groceries & Convenience Stores",
            "type":"Retail Goods"
        }
    ],
    "sg:phone":"+1 423 787 1691",
    "sg:postcode":"37743",
    "sg:province":"TN",
    "wof:name":"Quick Stop Market",
    "wof:placetype":"venue"
},
  "geometry": {"coordinates":[-82.84751799999999,36.146389],"type":"Point"}
}