{
  "type": "Feature",
  "properties": {
    "iso:country":"US",
    "sg:address":"2422 Thorngrove Pike",
    "sg:city":"Knoxville",
    "sg:classifiers":[
        {
            "category":"Building & Trades",
            "subcategory":"Construction",
            "type":"Services"
        }
    ],
    "sg:phone":"+1 865 673 0422",
    "sg:postcode":"37914",
    "sg:province":"TN",
    "sg:tags":[
        "excavation",
        "contractor"
    ],
    "wof:name":"Dans Bobcat Excavating",
    "wof:placetype":"venue"
},
  "geometry": {"coordinates":[-83.83090900000001,35.969188],"type":"Point"}
}