{
  "type": "Feature",
  "properties": {
    "addr:full":"120 S Jefferson Ave Cookeville TN 38501",
    "addr:housenumber":"120",
    "addr:postcode":"38501",
    "addr:street":"S Jefferson Ave",
    "iso:country":"US",
    "sg:address":"120 S Jefferson Ave",
    "sg:city":"Cookeville",
    "sg:classifiers":[
        {
            "category":"Banks & Credit Unions",
            "subcategory":"Bank",
            "type":"Services"
        }
    ],
    "sg:phone":"+1 931 526 9496",
    "sg:postcode":"38501",
    "sg:province":"TN",
    "sg:tags":[
        "loan",
        "real estate"
    ],
    "wof:name":"Mortgage Investors Group",
    "wof:placetype":"venue"
},
  "geometry": {"coordinates":[-85.50023400000001,36.161025],"type":"Point"}
}