{
  "type": "Feature",
  "properties": {
    "iso:country":"US",
    "sg:address":"507 W High St",
    "sg:city":"Manchester",
    "sg:classifiers":[
        {
            "category":"Professional",
            "subcategory":"Computer Services",
            "type":"Services"
        }
    ],
    "sg:phone":"+1 931 723 4054",
    "sg:postcode":"37355",
    "sg:province":"TN",
    "sg:tags":[
        "development",
        "software"
    ],
    "wof:name":"Novanet Inc",
    "wof:placetype":"venue"
},
  "geometry": {"coordinates":[-86.093406,35.484923],"type":"Point"}
}