{
  "type": "Feature",
  "properties": {
    "addr:full":"103 Industrial Dr Ripley TN 38063",
    "addr:housenumber":"103",
    "addr:postcode":"38063",
    "addr:street":"Industrial Dr",
    "iso:country":"US",
    "sg:address":"103 Industrial Dr",
    "sg:city":"Ripley",
    "sg:classifiers":[
        {
            "category":"Government",
            "subcategory":"Office",
            "type":"Public Place"
        }
    ],
    "sg:phone":"+1 731 635 1621",
    "sg:postcode":"38063",
    "sg:province":"TN",
    "sg:tags":[
        "village"
    ],
    "wof:name":"Ripley City Street Supt",
    "wof:placetype":"venue"
},
  "geometry": {"coordinates":[-89.516882,35.777223],"type":"Point"}
}