{
  "type": "Feature",
  "properties": {
    "iso:country":"US",
    "sg:address":"5510 Stage Rd",
    "sg:city":"Bartlett",
    "sg:classifiers":[
        {
            "category":"Food & Beverages",
            "subcategory":"Groceries & Convenience Stores",
            "type":"Retail Goods"
        }
    ],
    "sg:phone":"+1 901 387 0880",
    "sg:postcode":"38134",
    "sg:province":"TN",
    "wof:name":"Friendly Quick Stop",
    "wof:placetype":"venue"
},
  "geometry": {"coordinates":[-89.880548,35.205194],"type":"Point"}
}