{
  "type": "Feature",
  "properties": {
    "addr:full":"3683 Roy Messer Hwy White Pine TN 37890",
    "addr:housenumber":"3683",
    "addr:postcode":"37890",
    "addr:street":"Roy Messer Hwy",
    "iso:country":"US",
    "sg:address":"3683 Roy Messer Hwy",
    "sg:city":"White Pine",
    "sg:classifiers":[
        {
            "category":"Travel",
            "subcategory":"Hotels & Motels",
            "type":"Entertainment"
        }
    ],
    "sg:phone":"+1 865 674 8656",
    "sg:postcode":"37890",
    "sg:province":"TN",
    "wof:name":"Hillcrest Inn",
    "wof:placetype":"venue"
},
  "geometry": {"coordinates":[-83.339521,36.110127],"type":"Point"}
}