{
  "type": "Feature",
  "properties": {
    "addr:full":"7202 Eureka Rd NW Cleveland TN 37312",
    "addr:housenumber":"7202",
    "addr:postcode":"37312",
    "addr:street":"Eureka Rd Nw",
    "iso:country":"US",
    "sg:address":"7202 Eureka Rd NW",
    "sg:city":"Cleveland",
    "sg:classifiers":[
        {
            "category":"Manufacturing",
            "subcategory":"Chemicals & Compounds",
            "type":"Manufacturing & Wholesale Goods"
        }
    ],
    "sg:phone":"+1 423 614 7439",
    "sg:postcode":"37312",
    "sg:province":"TN",
    "sg:tags":[
        "product",
        "mfg"
    ],
    "wof:name":"Partners For Health",
    "wof:placetype":"venue"
},
  "geometry": {"coordinates":[-84.876499,35.254329],"type":"Point"}
}