{
  "type": "Feature",
  "properties": {
    "iso:country":"US",
    "sg:address":"149 W Court Ave",
    "sg:city":"Selmer",
    "sg:classifiers":[
        {
            "category":"Shopping",
            "subcategory":"Florist",
            "type":"Retail Goods"
        }
    ],
    "sg:phone":"+1 731 645 4389",
    "sg:postcode":"38375",
    "sg:province":"TN",
    "wof:name":"Fannie's Florist",
    "wof:placetype":"venue"
},
  "geometry": {"coordinates":[-88.59421500000001,35.171606],"type":"Point"}
}