{
  "type": "Feature",
  "properties": {
    "iso:country":"US",
    "sg:address":"709 Bruce Rd",
    "sg:city":"Dickson",
    "sg:classifiers":[
        {
            "category":"Organizations",
            "subcategory":"Religious Organization",
            "type":"Services"
        }
    ],
    "sg:phone":"+1 615 441 1006",
    "sg:postcode":"37055",
    "sg:province":"TN",
    "sg:tags":[
        "church"
    ],
    "wof:name":"Church Of Jesus Christ Of Lds",
    "wof:placetype":"venue"
},
  "geometry": {"coordinates":[-87.453172,36.032144],"type":"Point"}
}