{
  "type": "Feature",
  "properties": {
    "addr:full":"528 W Main St Lebanon TN 37087",
    "addr:housenumber":"528",
    "addr:postcode":"37087",
    "addr:street":"W Main St",
    "iso:country":"US",
    "sg:address":"528 W Main St",
    "sg:city":"Lebanon",
    "sg:classifiers":[
        {
            "category":"Restaurant",
            "type":"Food & Drink"
        }
    ],
    "sg:phone":"+1 615 547 7985",
    "sg:postcode":"37087",
    "sg:province":"TN",
    "sg:tags":[
        "eating"
    ],
    "wof:name":"Spotted Dog Corp",
    "wof:placetype":"venue"
},
  "geometry": {"coordinates":[-86.304422,36.209266],"type":"Point"}
}