{
  "type": "Feature",
  "properties": {
    "addr:full":"2 Northgate Park Chattanooga TN 37415",
    "addr:housenumber":"2",
    "addr:postcode":"37415",
    "addr:street":"Northgate",
    "iso:country":"US",
    "sg:address":"2 Northgate Park",
    "sg:city":"Chattanooga",
    "sg:classifiers":[
        {
            "category":"Professional",
            "subcategory":"Business Services",
            "type":"Services"
        }
    ],
    "sg:phone":"+1 423 876 7201",
    "sg:postcode":"37415",
    "sg:province":"TN",
    "wof:name":"Rha Health Services",
    "wof:placetype":"venue"
},
  "geometry": {"coordinates":[-85.237217,35.133289],"type":"Point"}
}