{
  "type": "Feature",
  "properties": {
    "iso:country":"US",
    "sg:address":"1718 Madison Ave",
    "sg:city":"Memphis",
    "sg:classifiers":[
        {
            "category":"Fast Food",
            "type":"Food & Drink"
        },
        {
            "category":"Restaurant",
            "type":"Food & Drink"
        },
        {
            "category":"Professional",
            "type":"Services"
        }
    ],
    "sg:phone":"+1 901 274 7101",
    "sg:postcode":"38104",
    "sg:province":"TN",
    "sg:tags":[
        "caterer"
    ],
    "wof:name":"Zinnie's",
    "wof:placetype":"venue"
},
  "geometry": {"coordinates":[-90.003894,35.138149],"type":"Point"}
}