{
  "type": "Feature",
  "properties": {
    "addr:full":"2540 Nashville Hwy Columbia TN 38401",
    "addr:housenumber":"2540",
    "addr:postcode":"38401",
    "addr:street":"Nashville Hwy",
    "iso:country":"US",
    "sg:address":"2540 Nashville Hwy",
    "sg:city":"Columbia",
    "sg:classifiers":[
        {
            "category":"Restaurant",
            "type":"Food & Drink"
        }
    ],
    "sg:menulink":"http://www.allmenus.com/tn/spring-hill/214911-burger-king/menu/",
    "sg:phone":"+1 931 486 1941",
    "sg:postcode":"38401",
    "sg:province":"TN",
    "sg:tags":[
        "burger",
        "american"
    ],
    "wof:name":"Burger King",
    "wof:placetype":"venue"
},
  "geometry": {"coordinates":[-86.97373899999999,35.709589],"type":"Point"}
}