{
  "type": "Feature",
  "properties": {
    "iso:country":"US",
    "sg:address":"836 NW Rutland Rd",
    "sg:city":"Mount Juliet",
    "sg:classifiers":[
        {
            "category":"Professional",
            "subcategory":"Art Services",
            "type":"Services"
        }
    ],
    "sg:phone":"+1 615 754 0700",
    "sg:postcode":"37122",
    "sg:province":"TN",
    "sg:tags":[
        "photography",
        "commercial",
        "medical"
    ],
    "wof:name":"Wharton Paul Photography",
    "wof:placetype":"venue"
},
  "geometry": {"coordinates":[-86.50550699999999,36.17977],"type":"Point"}
}