{
  "type": "Feature",
  "properties": {
    "addr:full":"344 S Bells St Alamo TN 38001",
    "addr:housenumber":"344",
    "addr:postcode":"38001",
    "addr:street":"S Bells St",
    "iso:country":"US",
    "sg:address":"344 S Bells St",
    "sg:city":"Alamo",
    "sg:classifiers":[
        {
            "category":"Government",
            "subcategory":"Office",
            "type":"Public Place"
        }
    ],
    "sg:phone":"+1 731 696 5539",
    "sg:postcode":"38001",
    "sg:province":"TN",
    "wof:name":"Crockett County Soil Cnsrvtn",
    "wof:placetype":"venue"
},
  "geometry": {"coordinates":[-89.117324,35.780244],"type":"Point"}
}