{
  "type": "Feature",
  "properties": {
    "iso:country":"US",
    "sg:address":"1005 Jackson Love Hwy",
    "sg:city":"Erwin",
    "sg:classifiers":[
        {
            "category":"Insurance",
            "subcategory":"Insurance Agent",
            "type":"Services"
        }
    ],
    "sg:phone":"+1 423 743 9136",
    "sg:postcode":"37650",
    "sg:province":"TN",
    "wof:name":"Farm Bureau Insurance",
    "wof:placetype":"venue"
},
  "geometry": {"coordinates":[-82.419517,36.130423],"type":"Point"}
}