{
  "type": "Feature",
  "properties": {
    "iso:country":"US",
    "sg:address":"3956 Brainerd Rd",
    "sg:city":"Chattanooga",
    "sg:classifiers":[
        {
            "category":"Home & Garden",
            "subcategory":"Building Materials",
            "type":"Retail Goods"
        }
    ],
    "sg:phone":"+1 423 624 6520",
    "sg:postcode":"37411",
    "sg:province":"TN",
    "sg:tags":[
        "wallpaper"
    ],
    "sg:website":"www.wallpaperwholesaler.com",
    "wof:name":"Wholesale Wallpaper",
    "wof:placetype":"venue"
},
  "geometry": {"coordinates":[-85.240011,35.01907],"type":"Point"}
}