{
  "type": "Feature",
  "properties": {
    "iso:country":"US",
    "sg:address":"4204 Fizer Ave",
    "sg:city":"Memphis",
    "sg:classifiers":[
        {
            "category":"Shopping",
            "subcategory":"Shoes",
            "type":"Retail Goods"
        }
    ],
    "sg:phone":"+1 901 744 8872",
    "sg:postcode":"38111",
    "sg:province":"TN",
    "wof:name":"Green Eye",
    "wof:placetype":"venue"
},
  "geometry": {"coordinates":[-89.920637,35.094606],"type":"Point"}
}