{
  "type": "Feature",
  "properties": {
    "iso:country":"US",
    "sg:address":"1916 Hwy 31 W",
    "sg:city":"White House",
    "sg:classifiers":[
        {
            "category":"Health Services",
            "subcategory":"Clinic",
            "type":"Services"
        }
    ],
    "sg:phone":"+1 615 672 7855",
    "sg:postcode":"37188",
    "sg:province":"TN",
    "wof:name":"Sumner County Emrgncy Med Svc",
    "wof:placetype":"venue"
},
  "geometry": {"coordinates":[-86.68973699999999,36.430971],"type":"Point"}
}