{
  "type": "Feature",
  "properties": {
    "iso:country":"US",
    "sg:address":"1105 E Bell St",
    "sg:city":"Murfreesboro",
    "sg:classifiers":[
        {
            "category":"Organizations",
            "subcategory":"Religious Organization",
            "type":"Services"
        }
    ],
    "sg:phone":"+1 615 896 1529",
    "sg:postcode":"37130",
    "sg:province":"TN",
    "wof:name":"Raiders For Christ",
    "wof:placetype":"venue"
},
  "geometry": {"coordinates":[-86.3729,35.848303],"type":"Point"}
}