{
  "type": "Feature",
  "properties": {
    "addr:full":"2911 Essary Dr Knoxville TN 37918",
    "addr:housenumber":"2911",
    "addr:postcode":"37918",
    "addr:street":"Essary Dr",
    "iso:country":"US",
    "sg:address":"2911 Essary Dr",
    "sg:city":"Knoxville",
    "sg:classifiers":[
        {
            "category":"Health Services",
            "subcategory":"Doctor",
            "type":"Services"
        }
    ],
    "sg:phone":"+1 865 687 0760",
    "sg:postcode":"37918",
    "sg:province":"TN",
    "sg:tags":[
        "physician",
        "surgeon"
    ],
    "wof:name":"Premiere Medical Assoc",
    "wof:placetype":"venue"
},
  "geometry": {"coordinates":[-83.927615,36.03609],"type":"Point"}
}