{
  "type": "Feature",
  "properties": {
    "iso:country":"US",
    "sg:address":"1619 E Lamar Alexander Pkwy",
    "sg:city":"Maryville",
    "sg:classifiers":[
        {
            "category":"Banks & Credit Unions",
            "subcategory":"Bank",
            "type":"Services"
        }
    ],
    "sg:phone":"+1 865 380 0001",
    "sg:postcode":"37804",
    "sg:province":"TN",
    "sg:tags":[
        "depository",
        "banking",
        "check",
        "cashing"
    ],
    "wof:name":"Cash Now",
    "wof:placetype":"venue"
},
  "geometry": {"coordinates":[-83.948393,35.755368],"type":"Point"}
}