{
  "type": "Feature",
  "properties": {
    "iso:country":"US",
    "sg:address":"5895 Winchester Rd",
    "sg:city":"Memphis",
    "sg:classifiers":[
        {
            "category":"Autos & Motor Vehicles",
            "subcategory":"Fuel & Gas Station",
            "type":"Retail Goods"
        }
    ],
    "sg:phone":"+1 901 363 5741",
    "sg:postcode":"38115",
    "sg:province":"TN",
    "sg:tags":[
        "oil"
    ],
    "wof:name":"Hickory Hill 76",
    "wof:placetype":"venue"
},
  "geometry": {"coordinates":[-89.86869799999999,35.050046],"type":"Point"}
}