{
  "type": "Feature",
  "properties": {
    "iso:country":"US",
    "sg:address":"1 Terminal Dr",
    "sg:city":"Nashville",
    "sg:classifiers":[
        {
            "category":"Local Transit",
            "type":"Transportation"
        }
    ],
    "sg:phone":"+1 615 275 1180",
    "sg:postcode":"37214",
    "sg:province":"TN",
    "sg:tags":[
        "airport"
    ],
    "sg:website":"www.graylinenashville.com",
    "wof:name":"Downtown Airport Express",
    "wof:placetype":"venue"
},
  "geometry": {"coordinates":[-86.667547,36.136164],"type":"Point"}
}