{
  "type": "Feature",
  "properties": {
    "iso:country":"US",
    "sg:address":"1943 Berryhill Rd",
    "sg:city":"Cordova",
    "sg:classifiers":[
        {
            "category":"Shopping",
            "subcategory":"Pharmacy",
            "type":"Retail Goods"
        }
    ],
    "sg:phone":"+1 901 757 0414",
    "sg:postcode":"38016",
    "sg:province":"TN",
    "wof:name":"Walgreens",
    "wof:placetype":"venue"
},
  "geometry": {"coordinates":[-89.75623400000001,35.182731],"type":"Point"}
}