{
  "type": "Feature",
  "properties": {
    "addr:full":"31 Hunter Hill Dr Jackson TN 38305",
    "addr:housenumber":"31",
    "addr:postcode":"38305",
    "addr:street":"Hunter Hill Dr",
    "iso:country":"US",
    "sg:address":"31 Hunter Hill Dr",
    "sg:city":"Jackson",
    "sg:classifiers":[
        {
            "category":"Professional",
            "subcategory":"Accounting & Tax Preparation",
            "type":"Services"
        }
    ],
    "sg:phone":"+1 731 660 4207",
    "sg:postcode":"38305",
    "sg:province":"TN",
    "sg:tags":[
        "accountant"
    ],
    "wof:name":"Padgett Business Svc",
    "wof:placetype":"venue"
},
  "geometry": {"coordinates":[-88.926266,35.686644],"type":"Point"}
}