{
  "type": "Feature",
  "properties": {
    "iso:country":"US",
    "sg:address":"4737 Spottswood Ave",
    "sg:city":"Memphis",
    "sg:classifiers":[
        {
            "category":"Shopping",
            "type":"Retail Goods"
        },
        {
            "category":"Organizations",
            "subcategory":"Non-profit Organization",
            "type":"Services"
        }
    ],
    "sg:phone":"+1 901 763 3235",
    "sg:postcode":"38117",
    "sg:province":"TN",
    "sg:tags":[
        "fund",
        "games",
        "raising",
        "merchandise",
        "supply"
    ],
    "wof:name":"NCS Inc",
    "wof:placetype":"venue"
},
  "geometry": {"coordinates":[-89.903531,35.11213],"type":"Point"}
}