{
  "type": "Feature",
  "properties": {
    "addr:full":"1135 E Shelby Dr Memphis TN 38116",
    "addr:housenumber":"1135",
    "addr:postcode":"38116",
    "addr:street":"E Shelby Dr",
    "iso:country":"US",
    "sg:address":"1135 E Shelby Dr",
    "sg:city":"Memphis",
    "sg:classifiers":[
        {
            "category":"Retail",
            "subcategory":"Auto Repair",
            "type":"Services"
        }
    ],
    "sg:phone":"+1 901 398 8510",
    "sg:postcode":"38116",
    "sg:province":"TN",
    "sg:tags":[
        "automotive",
        "general"
    ],
    "sg:website":"www.jiffylube.com",
    "wof:name":"Jiffy Lube",
    "wof:placetype":"venue"
},
  "geometry": {"coordinates":[-90.02635100000001,35.020876],"type":"Point"}
}