{
  "type": "Feature",
  "properties": {
    "iso:country":"US",
    "sg:address":"2141 William Switch Rd",
    "sg:city":"Ripley",
    "sg:phone":"+1 731 635 8191",
    "sg:postcode":"38063",
    "sg:province":"TN",
    "sg:tags":[
        "farm",
        "cotton"
    ],
    "wof:name":"Sumrow John",
    "wof:placetype":"venue"
},
  "geometry": {"coordinates":[-89.589378,35.715654],"type":"Point"}
}