{
  "type": "Feature",
  "properties": {
    "iso:country":"US",
    "sg:address":"960 Restbrook Ave",
    "sg:city":"Memphis",
    "sg:classifiers":[
        {
            "category":"Building & Trades",
            "subcategory":"Construction",
            "type":"Services"
        }
    ],
    "sg:phone":"+1 901 358 2322",
    "sg:postcode":"38127",
    "sg:province":"TN",
    "sg:tags":[
        "general",
        "contractor"
    ],
    "sg:website":"www.popwellscontracting.com",
    "wof:name":"Popwell's Contracting",
    "wof:placetype":"venue"
},
  "geometry": {"coordinates":[-90.03006600000001,35.224397],"type":"Point"}
}