{
  "type": "Feature",
  "properties": {
    "iso:country":"US",
    "sg:address":"113 Piney Flats Rd",
    "sg:city":"Piney Flats",
    "sg:classifiers":[
        {
            "category":"Personal",
            "subcategory":"Beauty Salon",
            "type":"Services"
        }
    ],
    "sg:phone":"+1 423 538 5369",
    "sg:postcode":"37686",
    "sg:province":"TN",
    "sg:tags":[
        "shop"
    ],
    "wof:name":"Barbara's Hair Fashions",
    "wof:placetype":"venue"
},
  "geometry": {"coordinates":[-82.31579600000001,36.426493],"type":"Point"}
}