{
  "type": "Feature",
  "properties": {
    "iso:country":"US",
    "sg:address":"320 E College St",
    "sg:city":"Dickson",
    "sg:classifiers":[
        {
            "category":"Professional",
            "subcategory":"Lawyer & Legal Services",
            "type":"Services"
        }
    ],
    "sg:phone":"+1 615 740 5700",
    "sg:postcode":"37055",
    "sg:province":"TN",
    "wof:name":"Ramsey & Thorton",
    "wof:placetype":"venue"
},
  "geometry": {"coordinates":[-87.38504399999999,36.074459],"type":"Point"}
}