{
  "type": "Feature",
  "properties": {
    "addr:full":"1430 Madison Ave Memphis TN 38104",
    "addr:housenumber":"1430",
    "addr:postcode":"38104",
    "addr:street":"Madison Ave",
    "iso:country":"US",
    "sg:address":"1430 Madison Ave",
    "sg:city":"Memphis",
    "sg:classifiers":[
        {
            "category":"Freight",
            "type":"Transportation"
        }
    ],
    "sg:phone":"+1 901 726 9461",
    "sg:postcode":"38104",
    "sg:province":"TN",
    "sg:tags":[
        "mover"
    ],
    "wof:name":"Wehaulit",
    "wof:placetype":"venue"
},
  "geometry": {"coordinates":[-90.013774,35.138749],"type":"Point"}
}