{
  "type": "Feature",
  "properties": {
    "addr:full":"1025 State Hwy 111 Cookeville TN 38570",
    "addr:housenumber":"1025",
    "addr:postcode":"38570",
    "addr:street":"State Hwy 111",
    "iso:country":"US",
    "sg:address":"1025 State Hwy 111",
    "sg:city":"Cookeville",
    "sg:classifiers":[
        {
            "category":"Education",
            "subcategory":"Vocational School",
            "type":"Public Place"
        }
    ],
    "sg:phone":"+1 931 526 3660",
    "sg:postcode":"38570",
    "sg:province":"TN",
    "wof:name":"Medvance Institute",
    "wof:placetype":"venue"
},
  "geometry": {"coordinates":[-85.334453,36.378129],"type":"Point"}
}