{
  "type": "Feature",
  "properties": {
    "iso:country":"US",
    "sg:address":"906 S Cooper St",
    "sg:city":"Memphis",
    "sg:classifiers":[
        {
            "category":"Shopping",
            "subcategory":"Clothing, Apparel, & Fashions",
            "type":"Retail Goods"
        }
    ],
    "sg:phone":"+1 901 726 6600",
    "sg:postcode":"38104",
    "sg:province":"TN",
    "sg:tags":[
        "furnishing"
    ],
    "wof:name":"Lux",
    "wof:placetype":"venue"
},
  "geometry": {"coordinates":[-89.99087299999999,35.121661],"type":"Point"}
}