{
  "type": "Feature",
  "properties": {
    "iso:country":"US",
    "sg:address":"225 Charles St",
    "sg:city":"Newport",
    "sg:classifiers":[
        {
            "category":"Organizations",
            "subcategory":"Religious Organization",
            "type":"Services"
        }
    ],
    "sg:phone":"+1 423 623 9190",
    "sg:postcode":"37821",
    "sg:province":"TN",
    "wof:name":"Abba Father Inc",
    "wof:placetype":"venue"
},
  "geometry": {"coordinates":[-83.20395600000001,35.954945],"type":"Point"}
}