{
  "type": "Feature",
  "properties": {
    "iso:country":"US",
    "sg:address":"1061 State Hwy 93",
    "sg:city":"Fall Branch",
    "sg:classifiers":[
        {
            "category":"Education",
            "subcategory":"School",
            "type":"Public Place"
        }
    ],
    "sg:phone":"+1 423 348 1200",
    "sg:postcode":"37656",
    "sg:province":"TN",
    "sg:tags":[
        "elementary"
    ],
    "wof:name":"Fall Branch Elementary School",
    "wof:placetype":"venue"
},
  "geometry": {"coordinates":[-82.62,36.410257],"type":"Point"}
}