{
  "type": "Feature",
  "properties": {
    "iso:country":"US",
    "sg:address":"10629 Bob Gray Rd",
    "sg:city":"Knoxville",
    "sg:classifiers":[
        {
            "category":"Building & Trades",
            "subcategory":"Electrical",
            "type":"Services"
        }
    ],
    "sg:phone":"+1 865 675 4353",
    "sg:postcode":"37932",
    "sg:province":"TN",
    "sg:tags":[
        "electrical",
        "contractor"
    ],
    "wof:name":"Electrical Electronic Educator",
    "wof:placetype":"venue"
},
  "geometry": {"coordinates":[-84.143944,35.931022],"type":"Point"}
}