{
  "type": "Feature",
  "properties": {
    "addr:full":"1175 Pineville Rd Chattanooga TN 37405",
    "addr:housenumber":"1175",
    "addr:postcode":"37405",
    "addr:street":"Pineville Rd",
    "iso:country":"US",
    "sg:address":"1175 Pineville Rd",
    "sg:city":"Chattanooga",
    "sg:classifiers":[
        {
            "category":"Real Estate",
            "subcategory":"Real Estate Operator",
            "type":"Services"
        }
    ],
    "sg:phone":"+1 423 265 7696",
    "sg:postcode":"37405",
    "sg:province":"TN",
    "sg:tags":[
        "building",
        "apartment"
    ],
    "wof:name":"Windridge Apartments",
    "wof:placetype":"venue"
},
  "geometry": {"coordinates":[-85.32654100000001,35.084861],"type":"Point"}
}