{
  "type": "Feature",
  "properties": {
    "iso:country":"US",
    "sg:address":"4469 Lebanon Pike",
    "sg:city":"Hermitage",
    "sg:classifiers":[
        {
            "category":"Shopping",
            "subcategory":"Computers & Home Electronics",
            "type":"Retail Goods"
        }
    ],
    "sg:phone":"+1 615 885 2660",
    "sg:postcode":"37076",
    "sg:province":"TN",
    "sg:tags":[
        "game",
        "video"
    ],
    "wof:name":"Game Stop Corp",
    "wof:placetype":"venue"
},
  "geometry": {"coordinates":[-86.60987,36.209257],"type":"Point"}
}