{
  "type": "Feature",
  "properties": {
    "iso:country":"US",
    "sg:address":"12020 Olympic Dr",
    "sg:city":"Knoxville",
    "sg:classifiers":[
        {
            "category":"Building & Trades",
            "subcategory":"Construction",
            "type":"Services"
        }
    ],
    "sg:phone":"+1 865 671 2060",
    "sg:postcode":"37934",
    "sg:province":"TN",
    "sg:tags":[
        "contracting",
        "consulting",
        "general"
    ],
    "wof:name":"Image Construction Inc",
    "wof:placetype":"venue"
},
  "geometry": {"coordinates":[-84.186283,35.872472],"type":"Point"}
}