{
  "type": "Feature",
  "properties": {
    "iso:country":"US",
    "sg:address":"697 S Yates Rd",
    "sg:city":"Memphis",
    "sg:classifiers":[
        {
            "category":"Arts & Performance",
            "subcategory":"Theater",
            "type":"Entertainment"
        }
    ],
    "sg:phone":"+1 901 767 8320",
    "sg:postcode":"38120",
    "sg:province":"TN",
    "sg:tags":[
        "personal",
        "magician"
    ],
    "wof:name":"Tinker Tunes and Balloons",
    "wof:placetype":"venue"
},
  "geometry": {"coordinates":[-89.877088,35.111288],"type":"Point"}
}