{
  "type": "Feature",
  "properties": {
    "iso:country":"US",
    "sg:address":"6216 Perimeter Dr",
    "sg:city":"Chattanooga",
    "sg:classifiers":[
        {
            "category":"Organizations",
            "subcategory":"Professional Association",
            "type":"Services"
        }
    ],
    "sg:phone":"+1 423 899 4990",
    "sg:postcode":"37421",
    "sg:province":"TN",
    "wof:name":"Chattanooga Local",
    "wof:placetype":"venue"
},
  "geometry": {"coordinates":[-85.185287,35.030203],"type":"Point"}
}