{
  "type": "Feature",
  "properties": {
    "iso:country":"US",
    "sg:address":"3472 Brainerd Rd",
    "sg:city":"Chattanooga",
    "sg:classifiers":[
        {
            "category":"Manufacturing",
            "subcategory":"Printing",
            "type":"Manufacturing & Wholesale Goods"
        },
        {
            "category":"Manufacturing",
            "subcategory":"Motor Vehicles & Parts",
            "type":"Manufacturing & Wholesale Goods"
        }
    ],
    "sg:phone":"+1 423 697 1856",
    "sg:postcode":"37411",
    "sg:province":"TN",
    "sg:tags":[
        "screen",
        "mfg",
        "trimming"
    ],
    "sg:website":"www.quicktees.com",
    "wof:name":"Quick Tee's",
    "wof:placetype":"venue"
},
  "geometry": {"coordinates":[-85.248886,35.025637],"type":"Point"}
}