{
  "type": "Feature",
  "properties": {
    "iso:country":"US",
    "sg:address":"120 N 2nd St",
    "sg:city":"Pulaski",
    "sg:classifiers":[
        {
            "category":"Real Estate",
            "subcategory":"Real Estate Agent",
            "type":"Services"
        }
    ],
    "sg:phone":"+1 931 363 3366",
    "sg:postcode":"38478",
    "sg:province":"TN",
    "wof:name":"Harwell Partners Real Estate",
    "wof:placetype":"venue"
},
  "geometry": {"coordinates":[-87.031443,35.200149],"type":"Point"}
}