{
  "type": "Feature",
  "properties": {
    "iso:country":"US",
    "sg:address":"590 W Church St",
    "sg:city":"Lexington",
    "sg:classifiers":[
        {
            "category":"Social Services",
            "subcategory":"Child Care",
            "type":"Services"
        }
    ],
    "sg:phone":"+1 731 968 1661",
    "sg:postcode":"38351",
    "sg:province":"TN",
    "wof:name":"Country Munchkin Childcare",
    "wof:placetype":"venue"
},
  "geometry": {"coordinates":[-88.40738,35.656422],"type":"Point"}
}