{
  "type": "Feature",
  "properties": {
    "iso:country":"US",
    "sg:address":"4716 Trenton Dr",
    "sg:city":"Hermitage",
    "sg:classifiers":[
        {
            "category":"Building & Trades",
            "subcategory":"Construction",
            "type":"Services"
        }
    ],
    "sg:phone":"+1 615 874 8231",
    "sg:postcode":"37076",
    "sg:province":"TN",
    "sg:tags":[
        "maintenance",
        "contractor"
    ],
    "wof:name":"Crl Enterprises",
    "wof:placetype":"venue"
},
  "geometry": {"coordinates":[-86.59603199999999,36.213542],"type":"Point"}
}