{
  "type": "Feature",
  "properties": {
    "addr:full":"300 N Main St Goodlettsville TN 37072",
    "addr:housenumber":"300",
    "addr:postcode":"37072",
    "addr:street":"N Main St",
    "iso:country":"US",
    "sg:address":"300 N Main St",
    "sg:city":"Goodlettsville",
    "sg:classifiers":[
        {
            "category":"Education",
            "subcategory":"School",
            "type":"Public Place"
        }
    ],
    "sg:phone":"+1 615 859 8956",
    "sg:postcode":"37072",
    "sg:province":"TN",
    "wof:name":"Goodlettsville Middle School",
    "wof:placetype":"venue"
},
  "geometry": {"coordinates":[-86.71382699999999,36.325221],"type":"Point"}
}