{
  "type": "Feature",
  "properties": {
    "iso:country":"US",
    "sg:address":"104 N Locust Ave",
    "sg:city":"Lawrenceburg",
    "sg:classifiers":[
        {
            "category":"Health Services",
            "subcategory":"Doctor",
            "type":"Services"
        }
    ],
    "sg:phone":"+1 931 762 6476",
    "sg:postcode":"38464",
    "sg:province":"TN",
    "sg:tags":[
        "medical"
    ],
    "wof:name":"Staley Homer L MD",
    "wof:placetype":"venue"
},
  "geometry": {"coordinates":[-87.330119,35.241355],"type":"Point"}
}