{
  "type": "Feature",
  "properties": {
    "addr:full":"8140 US Hwy 64 Bartlett TN 38133",
    "addr:housenumber":"8140",
    "addr:postcode":"38133",
    "addr:street":"Us Hwy 64",
    "iso:country":"US",
    "sg:address":"8140 US Hwy 64",
    "sg:city":"Bartlett",
    "sg:classifiers":[
        {
            "category":"Autos & Motor Vehicles",
            "subcategory":"Fuel & Gas Station",
            "type":"Retail Goods"
        }
    ],
    "sg:phone":"+1 901 937 5300",
    "sg:postcode":"38133",
    "sg:province":"TN",
    "sg:tags":[
        "station",
        "gasoline",
        "oil"
    ],
    "wof:name":"Shell",
    "wof:placetype":"venue"
},
  "geometry": {"coordinates":[-89.78905,35.204577],"type":"Point"}
}