{
  "type": "Feature",
  "properties": {
    "iso:country":"US",
    "sg:address":"424 Church St",
    "sg:city":"Nashville",
    "sg:classifiers":[
        {
            "category":"Professional",
            "subcategory":"Business Services",
            "type":"Services"
        }
    ],
    "sg:phone":"+1 615 467 3090",
    "sg:postcode":"37203",
    "sg:province":"TN",
    "wof:name":"Augusta Capital",
    "wof:placetype":"venue"
},
  "geometry": {"coordinates":[-86.779298,36.163635],"type":"Point"}
}