{
  "type": "Feature",
  "properties": {
    "iso:country":"US",
    "sg:address":"601 S Peters Rd",
    "sg:city":"Knoxville",
    "sg:classifiers":[
        {
            "category":"Building & Trades",
            "subcategory":"Construction",
            "type":"Services"
        }
    ],
    "sg:phone":"+1 865 556 2771",
    "sg:postcode":"37922",
    "sg:province":"TN",
    "sg:tags":[
        "house"
    ],
    "wof:name":"Ajax Builders",
    "wof:placetype":"venue"
},
  "geometry": {"coordinates":[-84.074203,35.901655],"type":"Point"}
}