{
  "type": "Feature",
  "properties": {
    "iso:country":"US",
    "sg:address":"103 Sequoia Dr",
    "sg:city":"Chattanooga",
    "sg:classifiers":[
        {
            "category":"Wholesale",
            "subcategory":"Auto Parts",
            "type":"Manufacturing & Wholesale Goods"
        }
    ],
    "sg:phone":"+1 423 624 9206",
    "sg:postcode":"37411",
    "sg:province":"TN",
    "wof:name":"Prestige Key Trak",
    "wof:placetype":"venue"
},
  "geometry": {"coordinates":[-85.232069,35.018783],"type":"Point"}
}