{
  "type": "Feature",
  "properties": {
    "addr:full":"1293 Heil Quaker Blvd La Vergne TN 37086",
    "addr:housenumber":"1293",
    "addr:postcode":"37086",
    "addr:street":"Heil Quaker Blvd",
    "iso:country":"US",
    "sg:address":"1293 Heil Quaker Blvd",
    "sg:city":"La Vergne",
    "sg:classifiers":[
        {
            "category":"Wholesale",
            "subcategory":"Stationery",
            "type":"Manufacturing & Wholesale Goods"
        }
    ],
    "sg:phone":"+1 615 287 0615",
    "sg:postcode":"37086",
    "sg:province":"TN",
    "sg:tags":[
        "product",
        "paper"
    ],
    "wof:name":"International Paper",
    "wof:placetype":"venue"
},
  "geometry": {"coordinates":[-86.60729600000001,36.006124],"type":"Point"}
}