{
  "type": "Feature",
  "properties": {
    "iso:country":"US",
    "sg:address":"2811 Mount Vernon Rd",
    "sg:city":"Chapel Hill",
    "sg:classifiers":[
        {
            "category":"Organizations",
            "subcategory":"Religious Organization",
            "type":"Services"
        }
    ],
    "sg:phone":"+1 931 364 7711",
    "sg:postcode":"37034",
    "sg:province":"TN",
    "sg:tags":[
        "church"
    ],
    "wof:name":"Mount Vernon Missionary Baptst",
    "wof:placetype":"venue"
},
  "geometry": {"coordinates":[-86.666712,35.66522],"type":"Point"}
}