{
  "type": "Feature",
  "properties": {
    "iso:country":"US",
    "sg:address":"707 Morrison St",
    "sg:city":"Mc Minnville",
    "sg:phone":"+1 931 473 6521",
    "sg:postcode":"37110",
    "sg:province":"TN",
    "sg:tags":[
        "oil"
    ],
    "wof:name":"Central Oil Co",
    "wof:placetype":"venue"
},
  "geometry": {"coordinates":[-85.794009,35.669666],"type":"Point"}
}