{
  "type": "Feature",
  "properties": {
    "addr:full":"751 Pineville Rd Chattanooga TN 37405",
    "addr:housenumber":"751",
    "addr:postcode":"37405",
    "addr:street":"Pineville Rd",
    "iso:country":"US",
    "sg:address":"751 Pineville Rd",
    "sg:city":"Chattanooga",
    "sg:classifiers":[
        {
            "category":"Wholesale",
            "subcategory":"Chemicals & Plastics",
            "type":"Manufacturing & Wholesale Goods"
        }
    ],
    "sg:phone":"+1 423 267 1646",
    "sg:postcode":"37405",
    "sg:province":"TN",
    "sg:tags":[
        "based",
        "aluminum",
        "mfg"
    ],
    "wof:name":"Cytec Industries",
    "wof:placetype":"venue"
},
  "geometry": {"coordinates":[-85.330325,35.06614],"type":"Point"}
}