{
  "type": "Feature",
  "properties": {
    "iso:country":"US",
    "sg:address":"51 Germantown Ct",
    "sg:city":"Cordova",
    "sg:classifiers":[
        {
            "category":"Professional",
            "subcategory":"Computer Services",
            "type":"Services"
        }
    ],
    "sg:phone":"+1 901 309 1415",
    "sg:postcode":"38018",
    "sg:province":"TN",
    "sg:tags":[
        "programing",
        "custom"
    ],
    "wof:name":"Global Data Systems Inc",
    "wof:placetype":"venue"
},
  "geometry": {"coordinates":[-89.795137,35.129974],"type":"Point"}
}