{
  "type": "Feature",
  "properties": {
    "iso:country":"US",
    "sg:address":"4646 Poplar Ave",
    "sg:city":"Memphis",
    "sg:classifiers":[
        {
            "category":"Banks & Credit Unions",
            "subcategory":"Bank",
            "type":"Services"
        }
    ],
    "sg:phone":"+1 901 680 0673",
    "sg:postcode":"38117",
    "sg:province":"TN",
    "sg:tags":[
        "loan"
    ],
    "wof:name":"Neuropathy Research Foundation",
    "wof:placetype":"venue"
},
  "geometry": {"coordinates":[-89.90776099999999,35.116714],"type":"Point"}
}