{
  "type": "Feature",
  "properties": {
    "iso:country":"US",
    "sg:address":"1055 Cosby Hwy",
    "sg:city":"Newport",
    "sg:classifiers":[
        {
            "category":"Shopping",
            "subcategory":"Clothing, Apparel, & Fashions",
            "type":"Retail Goods"
        }
    ],
    "sg:phone":"+1 423 623 6906",
    "sg:postcode":"37821",
    "sg:province":"TN",
    "sg:website":"www.catofashions.com",
    "wof:name":"Cato",
    "wof:placetype":"venue"
},
  "geometry": {"coordinates":[-83.207421,35.944197],"type":"Point"}
}