{
  "type": "Feature",
  "properties": {
    "addr:full":"2501 Turpins Glen Dr Germantown TN 38138",
    "addr:housenumber":"2501",
    "addr:postcode":"38138",
    "addr:street":"Turpins Glen Dr",
    "iso:country":"US",
    "sg:address":"2501 Turpins Glen Dr",
    "sg:city":"Germantown",
    "sg:classifiers":[
        {
            "category":"Building & Trades",
            "subcategory":"Cleaning & Sanitation",
            "type":"Services"
        }
    ],
    "sg:phone":"+1 901 754 9475",
    "sg:postcode":"38138",
    "sg:province":"TN",
    "sg:tags":[
        "janitor"
    ],
    "wof:name":"Nu Life Carpet Cleaners",
    "wof:placetype":"venue"
},
  "geometry": {"coordinates":[-89.817678,35.079785],"type":"Point"}
}