{
  "type": "Feature",
  "properties": {
    "iso:country":"US",
    "sg:address":"121 Clifftop Dr",
    "sg:city":"Hendersonville",
    "sg:classifiers":[
        {
            "category":"Professional",
            "type":"Services"
        }
    ],
    "sg:phone":"+1 615 822 6374",
    "sg:postcode":"37075",
    "sg:province":"TN",
    "wof:name":"Melanie A Hicks",
    "wof:placetype":"venue"
},
  "geometry": {"coordinates":[-86.574466,36.295385],"type":"Point"}
}