{
  "type": "Feature",
  "properties": {
    "addr:full":"2400 Poplar Ave Memphis TN 38104",
    "addr:housenumber":"2400",
    "addr:postcode":"38104",
    "addr:street":"Poplar Ave",
    "iso:country":"US",
    "sg:address":"2400 Poplar Ave",
    "sg:city":"Memphis",
    "sg:classifiers":[
        {
            "category":"Insurance",
            "subcategory":"Insurance Agent",
            "type":"Services"
        }
    ],
    "sg:phone":"+1 901 452 0082",
    "sg:postcode":"38104",
    "sg:province":"TN",
    "wof:name":"Allstate",
    "wof:placetype":"venue"
},
  "geometry": {"coordinates":[-89.98057799999999,35.139728],"type":"Point"}
}