{
  "type": "Feature",
  "properties": {
    "addr:full":"5326 Otter Creek Ct Brentwood TN 37027",
    "addr:housenumber":"5326",
    "addr:postcode":"37027",
    "addr:street":"Otter Creek Ct",
    "iso:country":"US",
    "sg:address":"5326 Otter Creek Ct",
    "sg:city":"Brentwood",
    "sg:classifiers":[
        {
            "category":"Professional",
            "subcategory":"Business Services",
            "type":"Services"
        }
    ],
    "sg:phone":"+1 615 373 5250",
    "sg:postcode":"37027",
    "sg:province":"TN",
    "sg:tags":[
        "interior",
        "design"
    ],
    "wof:name":"Gaylord Brenda Interiors",
    "wof:placetype":"venue"
},
  "geometry": {"coordinates":[-86.81322900000001,36.064356],"type":"Point"}
}