{
  "type": "Feature",
  "properties": {
    "iso:country":"US",
    "sg:address":"204 Dunlap St",
    "sg:city":"Paris",
    "sg:classifiers":[
        {
            "category":"Shopping",
            "subcategory":"Gifts & Souvenirs",
            "type":"Retail Goods"
        }
    ],
    "sg:phone":"+1 731 641 6577",
    "sg:postcode":"38242",
    "sg:province":"TN",
    "sg:tags":[
        "shop"
    ],
    "wof:name":"Sharon's Gift & KWIK Mart",
    "wof:placetype":"venue"
},
  "geometry": {"coordinates":[-88.323427,36.300977],"type":"Point"}
}