{
  "type": "Feature",
  "properties": {
    "iso:country":"US",
    "sg:address":"331 E Broadway St",
    "sg:city":"Newport",
    "sg:classifiers":[
        {
            "category":"Professional",
            "subcategory":"Lawyer & Legal Services",
            "type":"Services"
        }
    ],
    "sg:phone":"+1 423 623 3091",
    "sg:postcode":"37821",
    "sg:province":"TN",
    "sg:tags":[
        "attorney"
    ],
    "wof:name":"Myers Jr/Myers & Bell",
    "wof:placetype":"venue"
},
  "geometry": {"coordinates":[-83.184978,35.96675],"type":"Point"}
}