{
  "type": "Feature",
  "properties": {
    "iso:country":"US",
    "sg:address":"1318 Karnes Ave NE",
    "sg:city":"Knoxville",
    "sg:classifiers":[
        {
            "category":"Retail",
            "subcategory":"Repair Shop",
            "type":"Services"
        }
    ],
    "sg:phone":"+1 865 689 8096",
    "sg:postcode":"37917",
    "sg:province":"TN",
    "sg:tags":[
        "welding"
    ],
    "wof:name":"Alamo Welding & Steel Co Inc",
    "wof:placetype":"venue"
},
  "geometry": {"coordinates":[-83.925668,36.008958],"type":"Point"}
}