{
  "type": "Feature",
  "properties": {
    "addr:full":"3900 Alcoa Hwy Knoxville TN 37920",
    "addr:housenumber":"3900",
    "addr:postcode":"37920",
    "addr:street":"Alcoa Hwy",
    "iso:country":"US",
    "sg:address":"3900 Alcoa Hwy",
    "sg:city":"Knoxville",
    "sg:classifiers":[
        {
            "category":"Food & Beverages",
            "subcategory":"Bakery",
            "type":"Retail Goods"
        }
    ],
    "sg:phone":"+1 865 254 4551",
    "sg:postcode":"37920",
    "sg:province":"TN",
    "wof:name":"Turnbull Bakeries",
    "wof:placetype":"venue"
},
  "geometry": {"coordinates":[-83.95965200000001,35.874921],"type":"Point"}
}