{
  "type": "Feature",
  "properties": {
    "iso:country":"US",
    "sg:address":"409 E Warren St",
    "sg:city":"Tullahoma",
    "sg:classifiers":[
        {
            "category":"Manufacturing",
            "subcategory":"Lumber",
            "type":"Manufacturing & Wholesale Goods"
        }
    ],
    "sg:phone":"+1 931 455 3004",
    "sg:postcode":"37388",
    "sg:province":"TN",
    "sg:tags":[
        "company",
        "logging"
    ],
    "wof:name":"Lynch Logging",
    "wof:placetype":"venue"
},
  "geometry": {"coordinates":[-86.202557,35.363628],"type":"Point"}
}