{
  "type": "Feature",
  "properties": {
    "addr:full":"200 Stonebridge Blvd Jackson TN 38305",
    "addr:housenumber":"200",
    "addr:postcode":"38305",
    "addr:street":"Stonebridge Blvd",
    "iso:country":"US",
    "sg:address":"200 Stonebridge Blvd",
    "sg:city":"Jackson",
    "sg:classifiers":[
        {
            "category":"Wholesale",
            "subcategory":"Machinery & Supplies",
            "type":"Manufacturing & Wholesale Goods"
        }
    ],
    "sg:phone":"+1 731 668 0034",
    "sg:postcode":"38305",
    "sg:province":"TN",
    "sg:tags":[
        "industrial"
    ],
    "wof:name":"Sundown Tint",
    "wof:placetype":"venue"
},
  "geometry": {"coordinates":[-88.853014,35.679274],"type":"Point"}
}