{
  "type": "Feature",
  "properties": {
    "iso:country":"US",
    "sg:address":"7104 Patten Ln",
    "sg:city":"Nashville",
    "sg:classifiers":[
        {
            "category":"Building & Trades",
            "subcategory":"Construction",
            "type":"Services"
        }
    ],
    "sg:phone":"+1 615 646 8552",
    "sg:postcode":"37221",
    "sg:province":"TN",
    "sg:tags":[
        "general",
        "contractor"
    ],
    "wof:name":"Hearn Contracting Inc",
    "wof:placetype":"venue"
},
  "geometry": {"coordinates":[-86.92630699999999,36.067537],"type":"Point"}
}