{
  "type": "Feature",
  "properties": {
    "iso:country":"US",
    "sg:address":"9237 Shadymill Ln",
    "sg:city":"Knoxville",
    "sg:classifiers":[
        {
            "category":"Education",
            "subcategory":"Special Training",
            "type":"Public Place"
        }
    ],
    "sg:phone":"+1 865 690 3992",
    "sg:postcode":"37922",
    "sg:province":"TN",
    "sg:tags":[
        "personal",
        "development",
        "school"
    ],
    "wof:name":"Pretty As A Picture",
    "wof:placetype":"venue"
},
  "geometry": {"coordinates":[-84.086028,35.899453],"type":"Point"}
}