{
  "type": "Feature",
  "properties": {
    "iso:country":"US",
    "sg:address":"2010 Sevier Ave",
    "sg:city":"Knoxville",
    "sg:classifiers":[
        {
            "category":"Building & Trades",
            "subcategory":"Construction",
            "type":"Services"
        }
    ],
    "sg:phone":"+1 865 573 2148",
    "sg:postcode":"37920",
    "sg:province":"TN",
    "sg:tags":[
        "siding",
        "contractor"
    ],
    "sg:website":"www.goddardwarrior.com",
    "wof:name":"Goddard Continuous Guttering",
    "wof:placetype":"venue"
},
  "geometry": {"coordinates":[-83.90033,35.959],"type":"Point"}
}