{
  "type": "Feature",
  "properties": {
    "iso:country":"US",
    "sg:address":"1650 N Shelby Oaks Dr",
    "sg:city":"Memphis",
    "sg:classifiers":[
        {
            "category":"Building & Trades",
            "subcategory":"Construction",
            "type":"Services"
        }
    ],
    "sg:phone":"+1 901 684 7507",
    "sg:postcode":"38134",
    "sg:province":"TN",
    "sg:tags":[
        "new",
        "remodeling",
        "renovation"
    ],
    "wof:name":"ServiceMaster",
    "wof:placetype":"venue"
},
  "geometry": {"coordinates":[-89.85508900000001,35.169869],"type":"Point"}
}