{
  "type": "Feature",
  "properties": {
    "iso:country":"US",
    "sg:address":"217 S Old Sevierville Pike",
    "sg:city":"Seymour",
    "sg:classifiers":[
        {
            "category":"Banks & Credit Unions",
            "subcategory":"Investment Brokerage",
            "type":"Services"
        }
    ],
    "sg:phone":"+1 865 609 8192",
    "sg:postcode":"37865",
    "sg:province":"TN",
    "sg:tags":[
        "trade",
        "barter",
        "exchange"
    ],
    "wof:name":"ITEX",
    "wof:placetype":"venue"
},
  "geometry": {"coordinates":[-83.739133,35.887001],"type":"Point"}
}