{
  "type": "Feature",
  "properties": {
    "addr:full":"1217 Park Glen Rd SW Knoxville TN 37919",
    "addr:housenumber":"1217",
    "addr:postcode":"37919",
    "addr:street":"Park Glen Rd Sw",
    "iso:country":"US",
    "sg:address":"1217 Park Glen Rd SW",
    "sg:city":"Knoxville",
    "sg:classifiers":[
        {
            "category":"Building & Trades",
            "subcategory":"Landscaping Services",
            "type":"Services"
        }
    ],
    "sg:phone":"+1 865 584 7345",
    "sg:postcode":"37919",
    "sg:province":"TN",
    "wof:name":"Greer & Associates",
    "wof:placetype":"venue"
},
  "geometry": {"coordinates":[-84.00309900000001,35.914866],"type":"Point"}
}