{
  "type": "Feature",
  "properties": {
    "iso:country":"US",
    "sg:address":"3000 Commerce Dr NE",
    "sg:city":"Cleveland",
    "sg:classifiers":[
        {
            "category":"Retail",
            "subcategory":"Funeral Services",
            "type":"Services"
        }
    ],
    "sg:phone":"+1 423 472 1152",
    "sg:postcode":"37311",
    "sg:province":"TN",
    "sg:tags":[
        "director"
    ],
    "wof:name":"Ralph Buckner Funeral Home",
    "wof:placetype":"venue"
},
  "geometry": {"coordinates":[-84.852502,35.166827],"type":"Point"}
}