{
  "type": "Feature",
  "properties": {
    "iso:country":"US",
    "sg:address":"4304 Harding Pike",
    "sg:city":"Nashville",
    "sg:classifiers":[
        {
            "category":"Banks & Credit Unions",
            "subcategory":"Bank",
            "type":"Services"
        }
    ],
    "sg:phone":"+1 615 463 9000",
    "sg:postcode":"37205",
    "sg:province":"TN",
    "wof:name":"Suntrust Bank Inc",
    "wof:placetype":"venue"
},
  "geometry": {"coordinates":[-86.84498600000001,36.127088],"type":"Point"}
}