{
  "type": "Feature",
  "properties": {
    "iso:country":"US",
    "sg:address":"128 Blaine Dr",
    "sg:city":"Dandridge",
    "sg:classifiers":[
        {
            "category":"Professional",
            "subcategory":"Management & Consulting",
            "type":"Services"
        }
    ],
    "sg:phone":"+1 865 397 6118",
    "sg:postcode":"37709",
    "sg:province":"TN",
    "sg:tags":[
        "employee",
        "consultant",
        "benefit"
    ],
    "sg:website":"www.bencominc.com",
    "wof:name":"Benefit Compliance Inc",
    "wof:placetype":"venue"
},
  "geometry": {"coordinates":[-83.70706199999999,36.154031],"type":"Point"}
}