{
  "type": "Feature",
  "properties": {
    "iso:country":"US",
    "sg:address":"710 S 2nd St",
    "sg:city":"Nashville",
    "sg:classifiers":[
        {
            "category":"Wholesale",
            "subcategory":"Metals & Minerals",
            "type":"Manufacturing & Wholesale Goods"
        }
    ],
    "sg:phone":"+1 615 256 2900",
    "sg:postcode":"37213",
    "sg:province":"TN",
    "sg:tags":[
        "steel",
        "warehouse"
    ],
    "sg:website":"www.onealsteel.com",
    "wof:name":"O'Neal Steel Inc",
    "wof:placetype":"venue"
},
  "geometry": {"coordinates":[-86.766385,36.162],"type":"Point"}
}