{
  "type": "Feature",
  "properties": {
    "addr:full":"416 W Court St Dyersburg TN 38024",
    "addr:housenumber":"416",
    "addr:postcode":"38024",
    "addr:street":"W Court St",
    "iso:country":"US",
    "sg:address":"416 W Court St",
    "sg:city":"Dyersburg",
    "sg:classifiers":[
        {
            "category":"Professional",
            "subcategory":"Advertising",
            "type":"Services"
        }
    ],
    "sg:phone":"+1 731 287 9868",
    "sg:postcode":"38024",
    "sg:province":"TN",
    "wof:name":"Ad Sales",
    "wof:placetype":"venue"
},
  "geometry": {"coordinates":[-89.390552,36.033353],"type":"Point"}
}