{
  "type": "Feature",
  "properties": {
    "iso:country":"US",
    "sg:address":"3431 Alton Park Blvd",
    "sg:city":"Chattanooga",
    "sg:classifiers":[
        {
            "category":"Restaurant",
            "type":"Food & Drink"
        }
    ],
    "sg:phone":"+1 423 756 4975",
    "sg:postcode":"37410",
    "sg:province":"TN",
    "wof:name":"Momas Diner",
    "wof:placetype":"venue"
},
  "geometry": {"coordinates":[-85.31558699999999,35.012605],"type":"Point"}
}