{
  "type": "Feature",
  "properties": {
    "iso:country":"US",
    "sg:address":"108 Robin Hood Ln",
    "sg:city":"Church Hill",
    "sg:classifiers":[
        {
            "category":"Farming",
            "subcategory":"Livestock Farm",
            "type":"Manufacturing & Wholesale Goods"
        }
    ],
    "sg:phone":"+1 423 357 6609",
    "sg:postcode":"37642",
    "sg:province":"TN",
    "sg:tags":[
        "animal",
        "general"
    ],
    "wof:name":"Cornwell",
    "wof:placetype":"venue"
},
  "geometry": {"coordinates":[-82.765822,36.510265],"type":"Point"}
}