{
  "type": "Feature",
  "properties": {
    "iso:country":"US",
    "sg:address":"11817 Kingston Pike",
    "sg:city":"Knoxville",
    "sg:classifiers":[
        {
            "category":"Food & Beverages",
            "subcategory":"Groceries & Convenience Stores",
            "type":"Retail Goods"
        }
    ],
    "sg:phone":"+1 865 966 4360",
    "sg:postcode":"37934",
    "sg:province":"TN",
    "sg:tags":[
        "grocer"
    ],
    "wof:name":"Ingles Market",
    "wof:placetype":"venue"
},
  "geometry": {"coordinates":[-84.175257,35.874644],"type":"Point"}
}