{
  "type": "Feature",
  "properties": {
    "iso:country":"US",
    "sg:address":"710 N Broad St",
    "sg:city":"New Tazewell",
    "sg:classifiers":[
        {
            "category":"Home & Garden",
            "subcategory":"Building Materials",
            "type":"Retail Goods"
        }
    ],
    "sg:phone":"+1 423 626 3743",
    "sg:postcode":"37825",
    "sg:province":"TN",
    "sg:tags":[
        "door"
    ],
    "wof:name":"S & S Doors Inc",
    "wof:placetype":"venue"
},
  "geometry": {"coordinates":[-83.593374,36.445963],"type":"Point"}
}