{
  "type": "Feature",
  "properties": {
    "addr:full":"1680 Century Center Pkwy Memphis TN 38134",
    "addr:housenumber":"1680",
    "addr:postcode":"38134",
    "addr:street":"Century Center Pkwy",
    "iso:country":"US",
    "sg:address":"1680 Century Center Pkwy",
    "sg:city":"Memphis",
    "sg:classifiers":[
        {
            "category":"Wholesale",
            "subcategory":"Medical Equipment & Supplies",
            "type":"Manufacturing & Wholesale Goods"
        },
        {
            "category":"Social Services",
            "type":"Services"
        },
        {
            "category":"Shopping",
            "subcategory":"Pharmacy",
            "type":"Retail Goods"
        }
    ],
    "sg:phone":"+1 901 794 7755",
    "sg:postcode":"38134",
    "sg:province":"TN",
    "sg:tags":[
        "product",
        "developmentally",
        "disabled",
        "health",
        "need",
        "home",
        "special",
        "care"
    ],
    "wof:name":"Omnivisions",
    "wof:placetype":"venue"
},
  "geometry": {"coordinates":[-89.84369700000001,35.167789],"type":"Point"}
}