{
  "type": "Feature",
  "properties": {
    "iso:country":"US",
    "sg:address":"3056 Harrison Pike",
    "sg:city":"Cleveland",
    "sg:classifiers":[
        {
            "category":"Retail",
            "subcategory":"Repair Shop",
            "type":"Services"
        }
    ],
    "sg:phone":"+1 423 472 0600",
    "sg:postcode":"37311",
    "sg:province":"TN",
    "sg:tags":[
        "welding"
    ],
    "wof:name":"Harden Welding & Machine",
    "wof:placetype":"venue"
},
  "geometry": {"coordinates":[-84.93181800000001,35.183955],"type":"Point"}
}