{
  "type": "Feature",
  "properties": {
    "iso:country":"US",
    "sg:address":"151 River Rd",
    "sg:city":"Erwin",
    "sg:classifiers":[
        {
            "category":"Travel",
            "subcategory":"Hotels & Motels",
            "type":"Entertainment"
        }
    ],
    "sg:phone":"+1 423 735 0548",
    "sg:postcode":"37650",
    "sg:province":"TN",
    "sg:tags":[
        "chalet",
        "rental",
        "cabin"
    ],
    "wof:name":"Nolichucky Hostel Cabins Etc",
    "wof:placetype":"venue"
},
  "geometry": {"coordinates":[-82.448554,36.108122],"type":"Point"}
}