{
  "type": "Feature",
  "properties": {
    "iso:country":"US",
    "sg:address":"880 E 10th St",
    "sg:city":"Cookeville",
    "sg:classifiers":[
        {
            "category":"Health Services",
            "subcategory":"Health Practitioner",
            "type":"Services"
        }
    ],
    "sg:phone":"+1 931 520 7750",
    "sg:postcode":"38501",
    "sg:province":"TN",
    "sg:tags":[
        "specialty",
        "outpatient"
    ],
    "wof:name":"Physical Thrapy Rhbltation Ctr",
    "wof:placetype":"venue"
},
  "geometry": {"coordinates":[-85.48598800000001,36.175746],"type":"Point"}
}