{
  "type": "Feature",
  "properties": {
    "addr:full":"5610 Brainerd Rd Chattanooga TN 37411",
    "addr:housenumber":"5610",
    "addr:postcode":"37411",
    "addr:street":"Brainerd Rd",
    "iso:country":"US",
    "sg:address":"5610 Brainerd Rd",
    "sg:city":"Chattanooga",
    "sg:classifiers":[
        {
            "category":"Coffee & Tea",
            "type":"Food & Drink"
        }
    ],
    "sg:menulink":"http://www.allmenus.com/tn/chattanooga/115352-starbucks-coffee/menu/",
    "sg:phone":"+1 423 499 9042",
    "sg:postcode":"37411",
    "sg:province":"TN",
    "sg:tags":[
        "american"
    ],
    "wof:name":"Starbucks Coffee",
    "wof:placetype":"venue"
},
  "geometry": {"coordinates":[-85.21530199999999,35.010768],"type":"Point"}
}