{
  "type": "Feature",
  "properties": {
    "iso:country":"US",
    "sg:address":"207 Gallatin Pike S",
    "sg:city":"Madison",
    "sg:classifiers":[
        {
            "category":"Personal",
            "subcategory":"Shoe Repair & Shine",
            "type":"Services"
        }
    ],
    "sg:phone":"+1 615 612 4003",
    "sg:postcode":"37115",
    "sg:province":"TN",
    "sg:tags":[
        "repairing",
        "parlor",
        "boot"
    ],
    "wof:name":"One Stop Shoe Repair",
    "wof:placetype":"venue"
},
  "geometry": {"coordinates":[-86.71292099999999,36.260444],"type":"Point"}
}