{
  "type": "Feature",
  "properties": {
    "addr:full":"414 Chester St Athens TN 37303",
    "addr:housenumber":"414",
    "addr:postcode":"37303",
    "addr:street":"Chester St",
    "iso:country":"US",
    "sg:address":"414 Chester St",
    "sg:city":"Athens",
    "sg:classifiers":[
        {
            "category":"Organizations",
            "subcategory":"Religious Organization",
            "type":"Services"
        }
    ],
    "sg:phone":"+1 423 745 6510",
    "sg:postcode":"37303",
    "sg:province":"TN",
    "sg:tags":[
        "church"
    ],
    "wof:name":"Mount Pleasant Baptist Church",
    "wof:placetype":"venue"
},
  "geometry": {"coordinates":[-84.597393,35.445897],"type":"Point"}
}