{
  "type": "Feature",
  "properties": {
    "addr:full":"104 E Washington Ave Athens TN 37303",
    "addr:housenumber":"104",
    "addr:postcode":"37303",
    "addr:street":"E Washington Ave",
    "iso:country":"US",
    "sg:address":"104 E Washington Ave",
    "sg:city":"Athens",
    "sg:classifiers":[
        {
            "category":"Real Estate",
            "subcategory":"Real Estate Agent",
            "type":"Services"
        }
    ],
    "sg:phone":"+1 423 507 9080",
    "sg:postcode":"37303",
    "sg:province":"TN",
    "wof:name":"Wright Group L-A",
    "wof:placetype":"venue"
},
  "geometry": {"coordinates":[-84.591928,35.443262],"type":"Point"}
}