{
  "type": "Feature",
  "properties": {
    "iso:country":"US",
    "sg:address":"611 E Monroe St",
    "sg:city":"Tullahoma",
    "sg:classifiers":[
        {
            "category":"Wholesale",
            "subcategory":"Groceries",
            "type":"Manufacturing & Wholesale Goods"
        }
    ],
    "sg:phone":"+1 931 454 9917",
    "sg:postcode":"37388",
    "sg:province":"TN",
    "sg:tags":[
        "canned",
        "mfg"
    ],
    "wof:name":"Pepper Patch",
    "wof:placetype":"venue"
},
  "geometry": {"coordinates":[-86.193527,35.360707],"type":"Point"}
}