{
  "type": "Feature",
  "properties": {
    "addr:full":"5737 S Commerce Rd Watertown TN 37184",
    "addr:housenumber":"5737",
    "addr:postcode":"37184",
    "addr:street":"S Commerce Rd",
    "iso:country":"US",
    "sg:address":"5737 S Commerce Rd",
    "sg:city":"Watertown",
    "sg:classifiers":[
        {
            "category":"Building & Trades",
            "subcategory":"Cleaning & Sanitation",
            "type":"Services"
        }
    ],
    "sg:phone":"+1 615 449 1332",
    "sg:postcode":"37184",
    "sg:province":"TN",
    "sg:tags":[
        "butler",
        "maid"
    ],
    "wof:name":"Kay's Kleaning Svc",
    "wof:placetype":"venue"
},
  "geometry": {"coordinates":[-86.106549,36.160882],"type":"Point"}
}