{
  "type": "Feature",
  "properties": {
    "addr:full":"1420 W Church St Alamo TN 38001",
    "addr:housenumber":"1420",
    "addr:postcode":"38001",
    "addr:street":"W Church St",
    "iso:country":"US",
    "sg:address":"1420 W Church St",
    "sg:city":"Alamo",
    "sg:classifiers":[
        {
            "category":"Insurance",
            "subcategory":"Insurance Agent",
            "type":"Services"
        }
    ],
    "sg:phone":"+1 731 696 3170",
    "sg:postcode":"38001",
    "sg:province":"TN",
    "wof:name":"Craig Cochran Insurance",
    "wof:placetype":"venue"
},
  "geometry": {"coordinates":[-89.13849399999999,35.790524],"type":"Point"}
}