{
  "type": "Feature",
  "properties": {
    "addr:full":"127 E Northfield Blvd Murfreesboro TN 37130",
    "addr:housenumber":"127",
    "addr:postcode":"37130",
    "addr:street":"E Northfield Blvd",
    "iso:country":"US",
    "sg:address":"127 E Northfield Blvd",
    "sg:city":"Murfreesboro",
    "sg:classifiers":[
        {
            "category":"Social Services",
            "type":"Services"
        }
    ],
    "sg:phone":"+1 615 896 2946",
    "sg:postcode":"37130",
    "sg:province":"TN",
    "wof:name":"Jerry Redditt",
    "wof:placetype":"venue"
},
  "geometry": {"coordinates":[-86.38674,35.867805],"type":"Point"}
}