{
  "type": "Feature",
  "properties": {
    "iso:country":"US",
    "sg:address":"2894 Huntsville Hwy",
    "sg:city":"Fayetteville",
    "sg:classifiers":[
        {
            "category":"Wholesale",
            "subcategory":"Machinery & Supplies",
            "type":"Manufacturing & Wholesale Goods"
        }
    ],
    "sg:phone":"+1 931 433 5620",
    "sg:postcode":"37334",
    "sg:province":"TN",
    "sg:tags":[
        "tractor"
    ],
    "wof:name":"Hedden Tractor Co",
    "wof:placetype":"venue"
},
  "geometry": {"coordinates":[-86.573171,35.05695],"type":"Point"}
}