{
  "type": "Feature",
  "properties": {
    "iso:country":"US",
    "sg:address":"1652 E Stone Dr",
    "sg:city":"Kingsport",
    "sg:classifiers":[
        {
            "category":"Restaurant",
            "type":"Food & Drink"
        }
    ],
    "sg:phone":"+1 423 245 8211",
    "sg:postcode":"37660",
    "sg:province":"TN",
    "sg:tags":[
        "eating"
    ],
    "wof:name":"Mrs Winners Chicken & Biscuits",
    "wof:placetype":"venue"
},
  "geometry": {"coordinates":[-82.51785,36.547749],"type":"Point"}
}