{
  "type": "Feature",
  "properties": {
    "iso:country":"US",
    "sg:address":"100 US Hwy 51 N",
    "sg:city":"Covington",
    "sg:classifiers":[
        {
            "category":"Insurance",
            "subcategory":"Insurance Agent",
            "type":"Services"
        }
    ],
    "sg:phone":"+1 901 475 6467",
    "sg:postcode":"38019",
    "sg:province":"TN",
    "wof:name":"Able Agency LLC",
    "wof:placetype":"venue"
},
  "geometry": {"coordinates":[-89.64859800000001,35.565531],"type":"Point"}
}