{
  "type": "Feature",
  "properties": {
    "addr:full":"744 Reddoch St Memphis TN 38120",
    "addr:housenumber":"744",
    "addr:postcode":"38120",
    "addr:street":"Reddoch St",
    "iso:country":"US",
    "sg:address":"744 Reddoch St",
    "sg:city":"Memphis",
    "sg:classifiers":[
        {
            "category":"Manufacturing",
            "subcategory":"Signs",
            "type":"Manufacturing & Wholesale Goods"
        }
    ],
    "sg:phone":"+1 901 432 9098",
    "sg:postcode":"38120",
    "sg:province":"TN",
    "sg:tags":[
        "advertising"
    ],
    "sg:website":"www.nextresearch.com",
    "wof:name":"NEXTRESEARCH.COM",
    "wof:placetype":"venue"
},
  "geometry": {"coordinates":[-89.87915,35.110629],"type":"Point"}
}