{
  "type": "Feature",
  "properties": {
    "iso:country":"US",
    "sg:address":"1823 Lombardy Ave",
    "sg:city":"Nashville",
    "sg:classifiers":[
        {
            "category":"Manufacturing",
            "subcategory":"Chemicals & Compounds",
            "type":"Manufacturing & Wholesale Goods"
        }
    ],
    "sg:phone":"+1 615 297 7945",
    "sg:postcode":"37215",
    "sg:province":"TN",
    "sg:tags":[
        "inorganic",
        "industrial",
        "mfg"
    ],
    "wof:name":"Mercy Alumnae Assoc",
    "wof:placetype":"venue"
},
  "geometry": {"coordinates":[-86.801688,36.118015],"type":"Point"}
}