{
  "type": "Feature",
  "properties": {
    "iso:country":"US",
    "sg:address":"408 Broadway",
    "sg:city":"Nashville",
    "sg:classifiers":[
        {
            "category":"Bars & Pubs",
            "type":"Food & Drink"
        }
    ],
    "sg:menulink":"http://www.allmenus.com/tn/nashville/16964-baileys-pub--grille/menu/",
    "sg:phone":"+1 615 254 5452",
    "sg:postcode":"37203",
    "sg:province":"TN",
    "sg:tags":[
        "american"
    ],
    "wof:name":"Bailey's Pub & Grille",
    "wof:placetype":"venue"
},
  "geometry": {"coordinates":[-86.799317,36.147521],"type":"Point"}
}