{
  "type": "Feature",
  "properties": {
    "iso:country":"US",
    "sg:address":"555 Monteagle Dr",
    "sg:city":"Memphis",
    "sg:classifiers":[
        {
            "category":"Building & Trades",
            "subcategory":"Construction",
            "type":"Services"
        }
    ],
    "sg:phone":"+1 901 644 3199",
    "sg:postcode":"38109",
    "sg:province":"TN",
    "sg:tags":[
        "contractor"
    ],
    "wof:name":"Coleman Landscaping & Fencing",
    "wof:placetype":"venue"
},
  "geometry": {"coordinates":[-90.08390199999999,35.043894],"type":"Point"}
}