{
  "type": "Feature",
  "properties": {
    "iso:country":"US",
    "sg:address":"806 NW Broad St",
    "sg:city":"Murfreesboro",
    "sg:classifiers":[
        {
            "category":"Shopping",
            "subcategory":"Used Merchandise",
            "type":"Retail Goods"
        }
    ],
    "sg:phone":"+1 615 848 1247",
    "sg:postcode":"37129",
    "sg:province":"TN",
    "wof:name":"Tennessee Title Loan",
    "wof:placetype":"venue"
},
  "geometry": {"coordinates":[-86.398725,35.84921],"type":"Point"}
}