{
  "type": "Feature",
  "properties": {
    "iso:country":"US",
    "sg:address":"105 W Main St",
    "sg:city":"Manchester",
    "sg:classifiers":[
        {
            "category":"Banks & Credit Unions",
            "subcategory":"Bank",
            "type":"Services"
        }
    ],
    "sg:phone":"+1 931 723 8893",
    "sg:postcode":"37355",
    "sg:province":"TN",
    "sg:tags":[
        "loan",
        "mortgage",
        "real estate"
    ],
    "wof:name":"L C B Home Loans Inc",
    "wof:placetype":"venue"
},
  "geometry": {"coordinates":[-86.089204,35.482848],"type":"Point"}
}