{
  "type": "Feature",
  "properties": {
    "addr:full":"785 Brethren Church Rd Jonesborough TN 37659",
    "addr:housenumber":"785",
    "addr:postcode":"37659",
    "addr:street":"Church Rd",
    "iso:country":"US",
    "sg:address":"785 Brethren Church Rd",
    "sg:city":"Jonesborough",
    "sg:classifiers":[
        {
            "category":"Organizations",
            "subcategory":"Religious Organization",
            "type":"Services"
        }
    ],
    "sg:phone":"+1 423 753 8496",
    "sg:postcode":"37659",
    "sg:province":"TN",
    "wof:name":"Rev Don Hilton",
    "wof:placetype":"venue"
},
  "geometry": {"coordinates":[-82.51195300000001,36.347813],"type":"Point"}
}