{
  "type": "Feature",
  "properties": {
    "iso:country":"US",
    "sg:address":"232 McClellan Rd",
    "sg:city":"Jackson",
    "sg:classifiers":[
        {
            "category":"Education",
            "subcategory":"School",
            "type":"Public Place"
        }
    ],
    "sg:phone":"+1 731 664 0812",
    "sg:postcode":"38305",
    "sg:province":"TN",
    "sg:tags":[
        "private"
    ],
    "sg:website":"www.usj.tn.org",
    "wof:name":"University School of Jackson",
    "wof:placetype":"venue"
},
  "geometry": {"coordinates":[-88.88941800000001,35.70135],"type":"Point"}
}