{
  "type": "Feature",
  "properties": {
    "iso:country":"US",
    "sg:address":"5269 White Diamond St",
    "sg:city":"Memphis",
    "sg:classifiers":[
        {
            "category":"Professional",
            "subcategory":"Engineering",
            "type":"Services"
        }
    ],
    "sg:phone":"+1 901 785 1031",
    "sg:postcode":"38109",
    "sg:province":"TN",
    "sg:tags":[
        "consulting",
        "engineer"
    ],
    "wof:name":"Foreman Engineering Services",
    "wof:placetype":"venue"
},
  "geometry": {"coordinates":[-90.089476,35.004689],"type":"Point"}
}