{
  "type": "Feature",
  "properties": {
    "iso:country":"US",
    "sg:address":"2765 Cosby Hwy",
    "sg:city":"Cosby",
    "sg:classifiers":[
        {
            "category":"Building & Trades",
            "subcategory":"Construction",
            "type":"Services"
        }
    ],
    "sg:phone":"+1 423 625 3833",
    "sg:postcode":"37722",
    "sg:province":"TN",
    "sg:tags":[
        "builder",
        "operative"
    ],
    "wof:name":"Superior Home Builders",
    "wof:placetype":"venue"
},
  "geometry": {"coordinates":[-83.223251,35.870861],"type":"Point"}
}