{
  "type": "Feature",
  "properties": {
    "addr:full":"157 Shipley St Cookeville TN 38501",
    "addr:housenumber":"157",
    "addr:postcode":"38501",
    "addr:street":"Shipley St",
    "iso:country":"US",
    "sg:address":"157 Shipley St",
    "sg:city":"Cookeville",
    "sg:classifiers":[
        {
            "category":"Health Services",
            "subcategory":"Nursing And Care Facility",
            "type":"Services"
        }
    ],
    "sg:phone":"+1 931 520 1930",
    "sg:postcode":"38501",
    "sg:province":"TN",
    "sg:tags":[
        "intermediate"
    ],
    "wof:name":"Phillips Assisted Living Svcs",
    "wof:placetype":"venue"
},
  "geometry": {"coordinates":[-85.50323400000001,36.158033],"type":"Point"}
}