{
  "type": "Feature",
  "properties": {
    "iso:country":"US",
    "sg:address":"371 Ellis Ave",
    "sg:city":"Maryville",
    "sg:classifiers":[
        {
            "category":"Professional",
            "subcategory":"Management & Consulting",
            "type":"Services"
        }
    ],
    "sg:phone":"+1 865 681 7558",
    "sg:postcode":"37804",
    "sg:province":"TN",
    "wof:name":"Ewing Group",
    "wof:placetype":"venue"
},
  "geometry": {"coordinates":[-83.968062,35.756117],"type":"Point"}
}