{
  "type": "Feature",
  "properties": {
    "iso:country":"US",
    "sg:address":"707 Rector Dr",
    "sg:city":"Kingsport",
    "sg:classifiers":[
        {
            "category":"Building & Trades",
            "subcategory":"Construction",
            "type":"Services"
        }
    ],
    "sg:phone":"+1 423 578 3072",
    "sg:postcode":"37665",
    "sg:province":"TN",
    "sg:tags":[
        "carpentry",
        "contractor"
    ],
    "wof:name":"Dennis Howington",
    "wof:placetype":"venue"
},
  "geometry": {"coordinates":[-82.58681199999999,36.587504],"type":"Point"}
}