{
  "type": "Feature",
  "properties": {
    "addr:full":"5840 State Rte 100 Reagan TN 38368",
    "addr:housenumber":"5840",
    "addr:postcode":"38368",
    "addr:street":"State Rte 100",
    "iso:country":"US",
    "sg:address":"5840 State Rte 100",
    "sg:city":"Reagan",
    "sg:classifiers":[
        {
            "category":"Professional",
            "type":"Services"
        }
    ],
    "sg:phone":"+1 731 549 8800",
    "sg:postcode":"38368",
    "sg:province":"TN",
    "sg:tags":[
        "establishment"
    ],
    "wof:name":"R & B Market",
    "wof:placetype":"venue"
},
  "geometry": {"coordinates":[-88.321759,35.509028],"type":"Point"}
}