{
  "type": "Feature",
  "properties": {
    "addr:full":"455 Neville Rd Collierville TN 38017",
    "addr:housenumber":"455",
    "addr:postcode":"38017",
    "addr:street":"Neville Rd",
    "iso:country":"US",
    "sg:address":"455 Neville Rd",
    "sg:city":"Collierville",
    "sg:classifiers":[
        {
            "category":"Wholesale",
            "subcategory":"Machinery & Supplies",
            "type":"Manufacturing & Wholesale Goods"
        }
    ],
    "sg:phone":"+1 901 854 6787",
    "sg:postcode":"38017",
    "sg:province":"TN",
    "sg:tags":[
        "repair",
        "industrial",
        "structural"
    ],
    "wof:name":"Champion Industries",
    "wof:placetype":"venue"
},
  "geometry": {"coordinates":[-89.57498,35.040269],"type":"Point"}
}