{
  "type": "Feature",
  "properties": {
    "iso:country":"US",
    "sg:address":"240 W Gaines St",
    "sg:city":"Lawrenceburg",
    "sg:classifiers":[
        {
            "category":"Government",
            "subcategory":"Office",
            "type":"Public Place"
        }
    ],
    "sg:phone":"+1 931 766 4177",
    "sg:postcode":"38464",
    "sg:province":"TN",
    "wof:name":"Lawrence Cnty Circuit Ct Clerk",
    "wof:placetype":"venue"
},
  "geometry": {"coordinates":[-87.336474,35.242547],"type":"Point"}
}