{
  "type": "Feature",
  "properties": {
    "addr:full":"5738 Hwy 77 Newbern TN 38059",
    "addr:housenumber":"5738",
    "addr:postcode":"38059",
    "addr:street":"Hwy 77",
    "iso:country":"US",
    "sg:address":"5738 Hwy 77",
    "sg:city":"Newbern",
    "sg:classifiers":[
        {
            "category":"Organizations",
            "subcategory":"Religious Organization",
            "type":"Services"
        }
    ],
    "sg:phone":"+1 731 643 6816",
    "sg:postcode":"38059",
    "sg:province":"TN",
    "sg:tags":[
        "church"
    ],
    "wof:name":"Lemalsamac Church Of Christ",
    "wof:placetype":"venue"
},
  "geometry": {"coordinates":[-89.15716399999999,36.111901],"type":"Point"}
}