{
  "type": "Feature",
  "properties": {
    "addr:full":"586 Woodcrest Dr La Vergne TN 37086",
    "addr:housenumber":"586",
    "addr:postcode":"37086",
    "addr:street":"Woodcrest Dr",
    "iso:country":"US",
    "sg:address":"586 Woodcrest Dr",
    "sg:city":"La Vergne",
    "sg:classifiers":[
        {
            "category":"Building & Trades",
            "subcategory":"Construction",
            "type":"Services"
        }
    ],
    "sg:phone":"+1 615 793 6499",
    "sg:postcode":"37086",
    "sg:province":"TN",
    "sg:tags":[
        "contractor"
    ],
    "wof:name":"O'Riley Builders",
    "wof:placetype":"venue"
},
  "geometry": {"coordinates":[-86.609228,35.989425],"type":"Point"}
}