{
  "type": "Feature",
  "properties": {
    "iso:country":"US",
    "sg:address":"101 N Main St",
    "sg:city":"Lexington",
    "sg:classifiers":[
        {
            "category":"Professional",
            "type":"Services"
        }
    ],
    "sg:phone":"+1 731 967 4999",
    "sg:postcode":"38351",
    "sg:province":"TN",
    "sg:tags":[
        "establishment"
    ],
    "wof:name":"Home Place",
    "wof:placetype":"venue"
},
  "geometry": {"coordinates":[-88.396021,35.651599],"type":"Point"}
}