{
  "type": "Feature",
  "properties": {
    "addr:full":"10516 State Hwy 58 Ooltewah TN 37363",
    "addr:housenumber":"10516",
    "addr:postcode":"37363",
    "addr:street":"State Hwy 58",
    "iso:country":"US",
    "sg:address":"10516 State Hwy 58",
    "sg:city":"Ooltewah",
    "sg:classifiers":[
        {
            "category":"Home & Garden",
            "subcategory":"Garden Supply",
            "type":"Retail Goods"
        }
    ],
    "sg:phone":"+1 423 344 2099",
    "sg:postcode":"37363",
    "sg:province":"TN",
    "sg:tags":[
        "lawn"
    ],
    "wof:name":"Goodners Equipment",
    "wof:placetype":"venue"
},
  "geometry": {"coordinates":[-85.020026,35.229131],"type":"Point"}
}