{
  "type": "Feature",
  "properties": {
    "iso:country":"US",
    "sg:address":"4476 Millbranch Rd",
    "sg:city":"Memphis",
    "sg:classifiers":[
        {
            "category":"Personal",
            "subcategory":"Beauty Salon",
            "type":"Services"
        }
    ],
    "sg:phone":"+1 901 344 9187",
    "sg:postcode":"38116",
    "sg:province":"TN",
    "sg:tags":[
        "shop"
    ],
    "wof:name":"Before & After Hair Salon",
    "wof:placetype":"venue"
},
  "geometry": {"coordinates":[-90.00745499999999,35.026917],"type":"Point"}
}