{
  "type": "Feature",
  "properties": {
    "addr:full":"4429 Bluff City Hwy Bluff City TN 37618",
    "addr:housenumber":"4429",
    "addr:postcode":"37618",
    "addr:street":"Bluff City Hwy Bluff",
    "iso:country":"US",
    "sg:address":"4429 Bluff City Hwy",
    "sg:city":"Bluff City",
    "sg:classifiers":[
        {
            "category":"Professional",
            "type":"Services"
        }
    ],
    "sg:phone":"+1 423 538 4401",
    "sg:postcode":"37618",
    "sg:province":"TN",
    "sg:tags":[
        "establishment"
    ],
    "wof:name":"Airko",
    "wof:placetype":"venue"
},
  "geometry": {"coordinates":[-82.271755,36.47054],"type":"Point"}
}