{
  "type": "Feature",
  "properties": {
    "iso:country":"US",
    "sg:address":"3030 Gassaway Rd",
    "sg:city":"Woodbury",
    "sg:classifiers":[
        {
            "category":"Retail",
            "subcategory":"Auto Repair",
            "type":"Services"
        }
    ],
    "sg:phone":"+1 615 563 5171",
    "sg:postcode":"37190",
    "sg:province":"TN",
    "sg:tags":[
        "general"
    ],
    "wof:name":"Boyds Garage",
    "wof:placetype":"venue"
},
  "geometry": {"coordinates":[-86.028519,35.851172],"type":"Point"}
}