{
  "type": "Feature",
  "properties": {
    "iso:country":"US",
    "sg:address":"3504 Wears Valley Rd",
    "sg:city":"Sevierville",
    "sg:classifiers":[
        {
            "category":"Organizations",
            "subcategory":"Religious Organization",
            "type":"Services"
        }
    ],
    "sg:phone":"+1 865 453 1929",
    "sg:postcode":"37862",
    "sg:province":"TN",
    "wof:name":"First Baptist Church Wears Vly",
    "wof:placetype":"venue"
},
  "geometry": {"coordinates":[-83.649125,35.71841],"type":"Point"}
}