{
  "type": "Feature",
  "properties": {
    "iso:country":"US",
    "sg:address":"819 Buck Creek Rd",
    "sg:city":"Kingston",
    "sg:classifiers":[
        {
            "category":"Professional",
            "subcategory":"Business Services",
            "type":"Services"
        }
    ],
    "sg:phone":"+1 865 376 3144",
    "sg:postcode":"37763",
    "sg:province":"TN",
    "sg:tags":[
        "auctioneer"
    ],
    "wof:name":"Glen Wayne Evans Contractor",
    "wof:placetype":"venue"
},
  "geometry": {"coordinates":[-84.454981,35.834344],"type":"Point"}
}