{
  "type": "Feature",
  "properties": {
    "addr:full":"4943 Fulton Rd Brownsville TN 38012",
    "addr:housenumber":"4943",
    "addr:postcode":"38012",
    "addr:street":"Fulton Rd",
    "iso:country":"US",
    "sg:address":"4943 Fulton Rd",
    "sg:city":"Brownsville",
    "sg:classifiers":[
        {
            "category":"Freight",
            "type":"Transportation"
        }
    ],
    "sg:phone":"+1 731 772 4147",
    "sg:postcode":"38012",
    "sg:province":"TN",
    "sg:tags":[
        "operator",
        "local",
        "trucking"
    ],
    "wof:name":"Fulton Road Trucking Inc",
    "wof:placetype":"venue"
},
  "geometry": {"coordinates":[-89.377641,35.615201],"type":"Point"}
}