{
  "type": "Feature",
  "properties": {
    "iso:country":"US",
    "sg:address":"450 W Main St",
    "sg:city":"Gallatin",
    "sg:classifiers":[
        {
            "category":"Shopping",
            "subcategory":"Beauty & Cosmetics",
            "type":"Retail Goods"
        }
    ],
    "sg:phone":"+1 615 452 4198",
    "sg:postcode":"37066",
    "sg:province":"TN",
    "sg:tags":[
        "merchandise"
    ],
    "wof:name":"Custom Permanent Makeup",
    "wof:placetype":"venue"
},
  "geometry": {"coordinates":[-86.45244,36.386798],"type":"Point"}
}