{
  "type": "Feature",
  "properties": {
    "addr:full":"89 Fox Pond Cove Jackson TN 38305",
    "addr:housenumber":"89",
    "addr:postcode":"38305",
    "addr:street":"Fox Pond Cove",
    "iso:country":"US",
    "sg:address":"89 Fox Pond Cove",
    "sg:city":"Jackson",
    "sg:classifiers":[
        {
            "category":"Building & Trades",
            "subcategory":"Plumbing",
            "type":"Services"
        }
    ],
    "sg:phone":"+1 731 467 1471",
    "sg:postcode":"38305",
    "sg:province":"TN",
    "sg:tags":[
        "contractor"
    ],
    "wof:name":"G & H Services LLC",
    "wof:placetype":"venue"
},
  "geometry": {"coordinates":[-88.72711099999999,35.681523],"type":"Point"}
}