{
  "type": "Feature",
  "properties": {
    "iso:country":"US",
    "sg:address":"117 S Church St",
    "sg:city":"Mountain City",
    "sg:classifiers":[
        {
            "category":"Building & Trades",
            "subcategory":"Construction",
            "type":"Services"
        }
    ],
    "sg:phone":"+1 423 727 0717",
    "sg:postcode":"37683",
    "sg:province":"TN",
    "sg:tags":[
        "contractor"
    ],
    "wof:name":"Cabin Store",
    "wof:placetype":"venue"
},
  "geometry": {"coordinates":[-81.804444,36.473785],"type":"Point"}
}