{
  "type": "Feature",
  "properties": {
    "addr:full":"200 Outlet Village Blvd Lebanon TN 37090",
    "addr:housenumber":"200",
    "addr:postcode":"37090",
    "addr:street":"Outlet Village Blvd",
    "iso:country":"US",
    "sg:address":"200 Outlet Village Blvd",
    "sg:city":"Lebanon",
    "sg:classifiers":[
        {
            "category":"Shopping",
            "type":"Retail Goods"
        }
    ],
    "sg:phone":"+1 615 444 0215",
    "sg:postcode":"37090",
    "sg:province":"TN",
    "sg:tags":[
        "factory",
        "outlet"
    ],
    "wof:name":"Polo Ralph Lauren Store",
    "wof:placetype":"venue"
},
  "geometry": {"coordinates":[-86.304232,36.178541],"type":"Point"}
}