{
  "type": "Feature",
  "properties": {
    "iso:country":"US",
    "sg:address":"1488 Blackberry Ridge Rd",
    "sg:city":"Lenoir City",
    "sg:classifiers":[
        {
            "category":"Professional",
            "type":"Services"
        }
    ],
    "sg:phone":"+1 865 986 4586",
    "sg:postcode":"37772",
    "sg:province":"TN",
    "wof:name":"Mountain Melody Inc",
    "wof:placetype":"venue"
},
  "geometry": {"coordinates":[-84.21798,35.78824],"type":"Point"}
}