{
  "type": "Feature",
  "properties": {
    "iso:country":"US",
    "sg:address":"5410 Marion Ave",
    "sg:city":"Chattanooga",
    "sg:classifiers":[
        {
            "category":"Building & Trades",
            "subcategory":"Plumbing",
            "type":"Services"
        }
    ],
    "sg:phone":"+1 423 892 2535",
    "sg:postcode":"37412",
    "sg:province":"TN",
    "sg:tags":[
        "plumber"
    ],
    "wof:name":"Central Plumbing And Heating",
    "wof:placetype":"venue"
},
  "geometry": {"coordinates":[-85.230181,34.995938],"type":"Point"}
}