{
  "type": "Feature",
  "properties": {
    "iso:country":"US",
    "sg:address":"309 US Hwy 641 N",
    "sg:city":"Camden",
    "sg:classifiers":[
        {
            "category":"Personal",
            "subcategory":"Beauty Salon",
            "type":"Services"
        }
    ],
    "sg:phone":"+1 731 584 0309",
    "sg:postcode":"38320",
    "sg:province":"TN",
    "sg:tags":[
        "shop"
    ],
    "wof:name":"House Of Style",
    "wof:placetype":"venue"
},
  "geometry": {"coordinates":[-88.11191700000001,36.077507],"type":"Point"}
}