{
  "type": "Feature",
  "properties": {
    "iso:country":"US",
    "sg:address":"120 Trott Rd",
    "sg:city":"Bell Buckle",
    "sg:classifiers":[
        {
            "category":"Recreation",
            "type":"Entertainment"
        }
    ],
    "sg:phone":"+1 931 437 3083",
    "sg:postcode":"37020",
    "sg:province":"TN",
    "sg:tags":[
        "leather",
        "mfg",
        "good",
        "stable"
    ],
    "wof:name":"Midland Equestrian Center LLC",
    "wof:placetype":"venue"
},
  "geometry": {"coordinates":[-86.499308,35.622375],"type":"Point"}
}