{
  "type": "Feature",
  "properties": {
    "addr:full":"3405 Pearson Rd Memphis TN 38118",
    "addr:housenumber":"3405",
    "addr:postcode":"38118",
    "addr:street":"Pearson Rd",
    "iso:country":"US",
    "sg:address":"3405 Pearson Rd",
    "sg:city":"Memphis",
    "sg:classifiers":[
        {
            "category":"Building & Trades",
            "subcategory":"Electrical",
            "type":"Services"
        }
    ],
    "sg:phone":"+1 901 743 4839",
    "sg:postcode":"38118",
    "sg:province":"TN",
    "sg:tags":[
        "electrical",
        "electric",
        "contractor"
    ],
    "wof:name":"American Electrical Contrs",
    "wof:placetype":"venue"
},
  "geometry": {"coordinates":[-89.95085,35.072623],"type":"Point"}
}