{
  "type": "Feature",
  "properties": {
    "iso:country":"US",
    "sg:address":"3 Shamrock Ln",
    "sg:city":"Fayetteville",
    "sg:classifiers":[
        {
            "category":"Professional",
            "subcategory":"Management & Consulting",
            "type":"Services"
        }
    ],
    "sg:phone":"+1 931 937 8740",
    "sg:postcode":"37334",
    "sg:province":"TN",
    "sg:tags":[
        "consultant",
        "business"
    ],
    "wof:name":"Government Contracting Svc",
    "wof:placetype":"venue"
},
  "geometry": {"coordinates":[-86.487494,35.041316],"type":"Point"}
}