{
  "type": "Feature",
  "properties": {
    "iso:country":"US",
    "sg:address":"408 Ebenezer Rd",
    "sg:city":"Knoxville",
    "sg:classifiers":[
        {
            "category":"Professional",
            "subcategory":"Management & Consulting",
            "type":"Services"
        }
    ],
    "sg:phone":"+1 865 690 9190",
    "sg:postcode":"37923",
    "sg:province":"TN",
    "sg:tags":[
        "advisory",
        "investment"
    ],
    "wof:name":"Senior Advisors",
    "wof:placetype":"venue"
},
  "geometry": {"coordinates":[-84.07275199999999,35.904557],"type":"Point"}
}