{
  "type": "Feature",
  "properties": {
    "iso:country":"US",
    "sg:address":"192 S Main St",
    "sg:city":"Collierville",
    "sg:classifiers":[
        {
            "category":"Building & Trades",
            "subcategory":"Construction",
            "type":"Services"
        }
    ],
    "sg:phone":"+1 901 854 2276",
    "sg:postcode":"38017",
    "sg:province":"TN",
    "wof:name":"All American Yard Barns Inc",
    "wof:placetype":"venue"
},
  "geometry": {"coordinates":[-89.664186,35.039093],"type":"Point"}
}