{
  "type": "Feature",
  "properties": {
    "addr:full":"117 W Liberty Ave Covington TN 38019",
    "addr:housenumber":"117",
    "addr:postcode":"38019",
    "addr:street":"W Liberty Ave",
    "iso:country":"US",
    "sg:address":"117 W Liberty Ave",
    "sg:city":"Covington",
    "sg:classifiers":[
        {
            "category":"Personal",
            "subcategory":"Beauty Salon",
            "type":"Services"
        }
    ],
    "sg:phone":"+1 901 476 6334",
    "sg:postcode":"38019",
    "sg:province":"TN",
    "sg:tags":[
        "shop"
    ],
    "wof:name":"Sandra's Hair Shop",
    "wof:placetype":"venue"
},
  "geometry": {"coordinates":[-89.64773700000001,35.564521],"type":"Point"}
}