{
  "type": "Feature",
  "properties": {
    "iso:country":"US",
    "sg:address":"161 Three Way Ln",
    "sg:city":"Humboldt",
    "sg:classifiers":[
        {
            "category":"Real Estate",
            "subcategory":"Real Estate Operator",
            "type":"Services"
        }
    ],
    "sg:phone":"+1 731 784 3199",
    "sg:postcode":"38343",
    "sg:province":"TN",
    "sg:tags":[
        "property",
        "lessor"
    ],
    "wof:name":"Lahays Partnership",
    "wof:placetype":"venue"
},
  "geometry": {"coordinates":[-88.845519,35.767273],"type":"Point"}
}