{
  "type": "Feature",
  "properties": {
    "addr:full":"3424 Old Niles Ferry Rd Maryville TN 37803",
    "addr:housenumber":"3424",
    "addr:postcode":"37803",
    "addr:street":"Old Niles Ferry Rd",
    "iso:country":"US",
    "sg:address":"3424 Old Niles Ferry Rd",
    "sg:city":"Maryville",
    "sg:classifiers":[
        {
            "category":"Professional",
            "type":"Services"
        }
    ],
    "sg:phone":"+1 865 984 2793",
    "sg:postcode":"37803",
    "sg:province":"TN",
    "wof:name":"Wheels Inc",
    "wof:placetype":"venue"
},
  "geometry": {"coordinates":[-84.037207,35.691918],"type":"Point"}
}