{
  "type": "Feature",
  "properties": {
    "iso:country":"US",
    "sg:address":"611 E Governor John Sevier Hwy",
    "sg:city":"Knoxville",
    "sg:classifiers":[
        {
            "category":"Autos & Motor Vehicles",
            "subcategory":"Automobile Sales",
            "type":"Retail Goods"
        }
    ],
    "sg:phone":"+1 865 573 0730",
    "sg:postcode":"37920",
    "sg:province":"TN",
    "sg:tags":[
        "car",
        "dealer"
    ],
    "wof:name":"Polo Motor Co LLC",
    "wof:placetype":"venue"
},
  "geometry": {"coordinates":[-83.82933,35.91719],"type":"Point"}
}