{
  "type": "Feature",
  "properties": {
    "addr:full":"1680 N Tennessee Blvd Murfreesboro TN 37130",
    "addr:housenumber":"1680",
    "addr:postcode":"37130",
    "addr:street":"N Tennessee Blvd",
    "iso:country":"US",
    "sg:address":"1680 N Tennessee Blvd",
    "sg:city":"Murfreesboro",
    "sg:classifiers":[
        {
            "category":"Banks & Credit Unions",
            "subcategory":"Bank",
            "type":"Services"
        }
    ],
    "sg:phone":"+1 615 890 4940",
    "sg:postcode":"37130",
    "sg:province":"TN",
    "sg:website":"www.bankofamerica.com",
    "wof:name":"Bank Of America",
    "wof:placetype":"venue"
},
  "geometry": {"coordinates":[-86.369136,35.864257],"type":"Point"}
}