{
  "type": "Feature",
  "properties": {
    "iso:country":"US",
    "sg:address":"7233 Oak Ridge Hwy",
    "sg:city":"Knoxville",
    "sg:classifiers":[
        {
            "category":"Building & Trades",
            "subcategory":"Electrical",
            "type":"Services"
        }
    ],
    "sg:phone":"+1 865 692 6700",
    "sg:postcode":"37931",
    "sg:province":"TN",
    "sg:tags":[
        "electric",
        "contractor"
    ],
    "sg:website":"www.lloydselectric.org",
    "wof:name":"Lloyd's Electric Svc",
    "wof:placetype":"venue"
},
  "geometry": {"coordinates":[-84.080475,35.987599],"type":"Point"}
}