{
  "type": "Feature",
  "properties": {
    "addr:full":"3256 Oswego Rd Crossville TN 38572",
    "addr:housenumber":"3256",
    "addr:postcode":"38572",
    "addr:street":"Oswego Rd",
    "iso:country":"US",
    "sg:address":"3256 Oswego Rd",
    "sg:city":"Crossville",
    "sg:classifiers":[
        {
            "category":"Retail",
            "subcategory":"Repair Shop",
            "type":"Services"
        }
    ],
    "sg:phone":"+1 931 788 1653",
    "sg:postcode":"38572",
    "sg:province":"TN",
    "wof:name":"Outboards Unlimited",
    "wof:placetype":"venue"
},
  "geometry": {"coordinates":[-85.08466199999999,35.857828],"type":"Point"}
}