{
  "type": "Feature",
  "properties": {
    "addr:full":"408 James Robertson Pkwy Nashville TN 37219",
    "addr:housenumber":"408",
    "addr:postcode":"37219",
    "addr:street":"James Robertson Pkwy",
    "iso:country":"US",
    "sg:address":"408 James Robertson Pkwy",
    "sg:city":"Nashville",
    "sg:classifiers":[
        {
            "category":"Restaurant",
            "type":"Food & Drink"
        }
    ],
    "sg:phone":"+1 615 352 4410",
    "sg:postcode":"37219",
    "sg:province":"TN",
    "sg:tags":[
        "eating"
    ],
    "wof:name":"Waffle House",
    "wof:placetype":"venue"
},
  "geometry": {"coordinates":[-86.78200099999999,36.168213],"type":"Point"}
}