{
  "type": "Feature",
  "properties": {
    "iso:country":"US",
    "sg:address":"706 S Illinois Ave",
    "sg:city":"Oak Ridge",
    "sg:classifiers":[
        {
            "category":"Organizations",
            "subcategory":"Religious Organization",
            "type":"Services"
        }
    ],
    "sg:phone":"+1 865 482 3209",
    "sg:postcode":"37830",
    "sg:province":"TN",
    "wof:name":"United Methodist District Ofc",
    "wof:placetype":"venue"
},
  "geometry": {"coordinates":[-84.241388,36.001681],"type":"Point"}
}