{
  "type": "Feature",
  "properties": {
    "iso:country":"US",
    "sg:address":"1279 4th St",
    "sg:city":"Crossville",
    "sg:classifiers":[
        {
            "category":"Freight",
            "type":"Transportation"
        }
    ],
    "sg:phone":"+1 931 456 1032",
    "sg:postcode":"38555",
    "sg:province":"TN",
    "sg:tags":[
        "operator",
        "trucking"
    ],
    "wof:name":"Ed Lee Trucking",
    "wof:placetype":"venue"
},
  "geometry": {"coordinates":[-85.045457,35.939059],"type":"Point"}
}