{
  "type": "Feature",
  "properties": {
    "iso:country":"US",
    "sg:address":"4207 Brush Hill Rd",
    "sg:city":"Nashville",
    "sg:classifiers":[
        {
            "category":"Personal",
            "subcategory":"Beauty Salon",
            "type":"Services"
        }
    ],
    "sg:phone":"+1 615 228 4001",
    "sg:postcode":"37216",
    "sg:province":"TN",
    "wof:name":"All About Hair",
    "wof:placetype":"venue"
},
  "geometry": {"coordinates":[-86.71361400000001,36.229904],"type":"Point"}
}