{
  "type": "Feature",
  "properties": {
    "iso:country":"US",
    "sg:address":"5104 Dakota Ave",
    "sg:city":"Nashville",
    "sg:classifiers":[
        {
            "category":"Building & Trades",
            "subcategory":"Plumbing",
            "type":"Services"
        }
    ],
    "sg:phone":"+1 615 254 5025",
    "sg:postcode":"37209",
    "sg:province":"TN",
    "sg:tags":[
        "plumbing",
        "contractor"
    ],
    "wof:name":"Radnor Plumbing Co",
    "wof:placetype":"venue"
},
  "geometry": {"coordinates":[-86.84961,36.147443],"type":"Point"}
}