{
  "type": "Feature",
  "properties": {
    "addr:full":"111 28th Ave S Nashville TN 37212",
    "addr:housenumber":"111",
    "addr:postcode":"37212",
    "addr:street":"28Th Ave S",
    "iso:country":"US",
    "sg:address":"111 28th Ave S",
    "sg:city":"Nashville",
    "sg:classifiers":[
        {
            "category":"Insurance",
            "subcategory":"Insurance Agent",
            "type":"Services"
        }
    ],
    "sg:phone":"+1 615 327 0903",
    "sg:postcode":"37212",
    "sg:province":"TN",
    "sg:website":"www.turnerwilliams.com",
    "wof:name":"Turner P Williams & Assoc",
    "wof:placetype":"venue"
},
  "geometry": {"coordinates":[-86.81058299999999,36.143409],"type":"Point"}
}