{
  "type": "Feature",
  "properties": {
    "addr:full":"505 W Mountainview Rd Johnson City TN 37604",
    "addr:housenumber":"505",
    "addr:postcode":"37604",
    "addr:street":"W Mountainview Rd",
    "iso:country":"US",
    "sg:address":"505 W Mountainview Rd",
    "sg:city":"Johnson City",
    "sg:classifiers":[
        {
            "category":"Wholesale",
            "subcategory":"Construction Materials",
            "type":"Manufacturing & Wholesale Goods"
        }
    ],
    "sg:phone":"+1 423 282 4527",
    "sg:postcode":"37604",
    "sg:province":"TN",
    "sg:tags":[
        "glass"
    ],
    "wof:name":"Pilkington North America",
    "wof:placetype":"venue"
},
  "geometry": {"coordinates":[-82.408624,36.352967],"type":"Point"}
}