{
  "type": "Feature",
  "properties": {
    "iso:country":"US",
    "sg:address":"2009 Belmont Blvd",
    "sg:city":"Nashville",
    "sg:classifiers":[
        {
            "category":"Shopping",
            "subcategory":"Used Merchandise",
            "type":"Retail Goods"
        }
    ],
    "sg:phone":"+1 615 383 4321",
    "sg:postcode":"37212",
    "sg:province":"TN",
    "sg:tags":[
        "shop",
        "consignment"
    ],
    "wof:name":"Classic Consigment",
    "wof:placetype":"venue"
},
  "geometry": {"coordinates":[-86.795681,36.132728],"type":"Point"}
}