{
  "type": "Feature",
  "properties": {
    "iso:country":"US",
    "sg:address":"4105 Hickory Hill Rd",
    "sg:city":"Memphis",
    "sg:classifiers":[
        {
            "category":"Wholesale",
            "subcategory":"Medical Equipment & Supplies",
            "type":"Manufacturing & Wholesale Goods"
        }
    ],
    "sg:phone":"+1 901 360 0029",
    "sg:postcode":"38115",
    "sg:province":"TN",
    "sg:tags":[
        "physician",
        "surgeon"
    ],
    "wof:name":"Omni Healthcare",
    "wof:placetype":"venue"
},
  "geometry": {"coordinates":[-89.866508,35.035769],"type":"Point"}
}