{
  "type": "Feature",
  "properties": {
    "iso:country":"US",
    "sg:address":"7161 E Andrew Johnson Hwy",
    "sg:city":"Whitesburg",
    "sg:classifiers":[
        {
            "category":"Retail",
            "subcategory":"Repair Shop",
            "type":"Services"
        }
    ],
    "sg:phone":"+1 423 581 5557",
    "sg:postcode":"37891",
    "sg:province":"TN",
    "sg:tags":[
        "auto",
        "machinery",
        "general"
    ],
    "wof:name":"Wolfe Garage",
    "wof:placetype":"venue"
},
  "geometry": {"coordinates":[-83.144098,36.271087],"type":"Point"}
}