{
  "type": "Feature",
  "properties": {
    "addr:full":"3610 Oak Hollow Cir Memphis TN 38116",
    "addr:housenumber":"3610",
    "addr:postcode":"38116",
    "addr:street":"Oak Hollow Cir",
    "iso:country":"US",
    "sg:address":"3610 Oak Hollow Cir",
    "sg:city":"Memphis",
    "sg:classifiers":[
        {
            "category":"Professional",
            "subcategory":"Detective & Security Services",
            "type":"Services"
        }
    ],
    "sg:phone":"+1 901 348 4111",
    "sg:postcode":"38116",
    "sg:province":"TN",
    "sg:tags":[
        "car"
    ],
    "wof:name":"Middlebrook Investigative Bure",
    "wof:placetype":"venue"
},
  "geometry": {"coordinates":[-90.022903,35.05012],"type":"Point"}
}