{
  "type": "Feature",
  "properties": {
    "iso:country":"US",
    "sg:address":"266 S Cleveland St",
    "sg:city":"Memphis",
    "sg:classifiers":[
        {
            "category":"Health Services",
            "subcategory":"Doctor",
            "type":"Services"
        }
    ],
    "sg:phone":"+1 901 725 1425",
    "sg:postcode":"38104",
    "sg:province":"TN",
    "sg:tags":[
        "dental",
        "practice"
    ],
    "wof:name":"Kemp Greg DDS",
    "wof:placetype":"venue"
},
  "geometry": {"coordinates":[-90.016676,35.135079],"type":"Point"}
}