{
  "type": "Feature",
  "properties": {
    "iso:country":"US",
    "sg:address":"620 Cherokee Blvd",
    "sg:city":"Chattanooga",
    "sg:classifiers":[
        {
            "category":"Health Services",
            "subcategory":"Doctor",
            "type":"Services"
        }
    ],
    "sg:phone":"+1 423 266 9000",
    "sg:postcode":"37405",
    "sg:province":"TN",
    "sg:tags":[
        "physician",
        "surgeon"
    ],
    "wof:name":"Gulshan Sultan MD",
    "wof:placetype":"venue"
},
  "geometry": {"coordinates":[-85.317752,35.069215],"type":"Point"}
}