{
  "type": "Feature",
  "properties": {
    "iso:country":"US",
    "sg:address":"6920 Sylar Rd",
    "sg:city":"Ooltewah",
    "sg:classifiers":[
        {
            "category":"Banks & Credit Unions",
            "subcategory":"Financial Services",
            "type":"Services"
        }
    ],
    "sg:phone":"+1 423 238 9507",
    "sg:postcode":"37363",
    "sg:province":"TN",
    "sg:tags":[
        "company",
        "holding"
    ],
    "wof:name":"Rogers Enterprises",
    "wof:placetype":"venue"
},
  "geometry": {"coordinates":[-85.045366,35.109767],"type":"Point"}
}