{
  "type": "Feature",
  "properties": {
    "addr:full":"4814 Jones Chapel Rd Cedar Hill TN 37032",
    "addr:housenumber":"4814",
    "addr:postcode":"37032",
    "addr:street":"Jones Chapel Rd",
    "iso:country":"US",
    "sg:address":"4814 Jones Chapel Rd",
    "sg:city":"Cedar Hill",
    "sg:classifiers":[
        {
            "category":"Real Estate",
            "subcategory":"Real Estate Agent",
            "type":"Services"
        }
    ],
    "sg:phone":"+1 615 642 0694",
    "sg:postcode":"37032",
    "sg:province":"TN",
    "wof:name":"Justin Head",
    "wof:placetype":"venue"
},
  "geometry": {"coordinates":[-86.955336,36.557218],"type":"Point"}
}