{
  "type": "Feature",
  "properties": {
    "addr:full":"250 25th Ave N Nashville TN 37203",
    "addr:housenumber":"250",
    "addr:postcode":"37203",
    "addr:street":"25Th Ave N",
    "iso:country":"US",
    "sg:address":"250 25th Ave N",
    "sg:city":"Nashville",
    "sg:classifiers":[
        {
            "category":"Professional",
            "type":"Services"
        }
    ],
    "sg:phone":"+1 615 342 5626",
    "sg:postcode":"37203",
    "sg:province":"TN",
    "sg:tags":[
        "establishment"
    ],
    "wof:name":"Nashville Transplant Assoc",
    "wof:placetype":"venue"
},
  "geometry": {"coordinates":[-86.81067,36.150507],"type":"Point"}
}