{
  "type": "Feature",
  "properties": {
    "iso:country":"US",
    "sg:address":"6600 Stage Rd",
    "sg:city":"Memphis",
    "sg:classifiers":[
        {
            "category":"Banks & Credit Unions",
            "subcategory":"Bank",
            "type":"Services"
        }
    ],
    "sg:phone":"+1 901 372 7354",
    "sg:postcode":"38134",
    "sg:province":"TN",
    "wof:name":"First Tennessee Bank",
    "wof:placetype":"venue"
},
  "geometry": {"coordinates":[-89.843588,35.20481],"type":"Point"}
}