{
  "type": "Feature",
  "properties": {
    "iso:country":"US",
    "sg:address":"1618 Melody Ln",
    "sg:city":"Chattanooga",
    "sg:classifiers":[
        {
            "category":"Building & Trades",
            "subcategory":"Plumbing",
            "type":"Services"
        }
    ],
    "sg:phone":"+1 423 867 5737",
    "sg:postcode":"37412",
    "sg:province":"TN",
    "sg:tags":[
        "contractor"
    ],
    "wof:name":"Covenant Plumbing Solutions",
    "wof:placetype":"venue"
},
  "geometry": {"coordinates":[-85.26951099999999,34.99059],"type":"Point"}
}