{
  "type": "Feature",
  "properties": {
    "iso:country":"US",
    "sg:address":"5184 Cordell Cove",
    "sg:city":"Memphis",
    "sg:classifiers":[
        {
            "category":"Shopping",
            "subcategory":"Clothing, Apparel, & Fashions",
            "type":"Retail Goods"
        }
    ],
    "sg:phone":"+1 901 566 9243",
    "sg:postcode":"38118",
    "sg:province":"TN",
    "wof:name":"Capriels Closet",
    "wof:placetype":"venue"
},
  "geometry": {"coordinates":[-89.889978,35.070938],"type":"Point"}
}