{
  "type": "Feature",
  "properties": {
    "iso:country":"US",
    "sg:address":"2565 Crocker Springs Rd",
    "sg:city":"Goodlettsville",
    "sg:classifiers":[
        {
            "category":"Professional",
            "subcategory":"Computer Services",
            "type":"Services"
        }
    ],
    "sg:phone":"+1 615 299 9044",
    "sg:postcode":"37072",
    "sg:province":"TN",
    "sg:tags":[
        "processing",
        "datum"
    ],
    "wof:name":"Nashville Information Tech",
    "wof:placetype":"venue"
},
  "geometry": {"coordinates":[-86.822417,36.327484],"type":"Point"}
}