{
  "type": "Feature",
  "properties": {
    "iso:country":"US",
    "sg:address":"720 N 5th Ave",
    "sg:city":"Knoxville",
    "sg:classifiers":[
        {
            "category":"Education",
            "subcategory":"Junior College",
            "type":"Public Place"
        }
    ],
    "sg:phone":"+1 865 524 3043",
    "sg:postcode":"37917",
    "sg:province":"TN",
    "sg:tags":[
        "university"
    ],
    "wof:name":"Knoxville Business College",
    "wof:placetype":"venue"
},
  "geometry": {"coordinates":[-83.916561,35.978904],"type":"Point"}
}