{
  "type": "Feature",
  "properties": {
    "addr:full":"381 W Main St Hendersonville TN 37075",
    "addr:housenumber":"381",
    "addr:postcode":"37075",
    "addr:street":"W Main St",
    "iso:country":"US",
    "sg:address":"381 W Main St",
    "sg:city":"Hendersonville",
    "sg:classifiers":[
        {
            "category":"Organizations",
            "subcategory":"Religious Organization",
            "type":"Services"
        }
    ],
    "sg:phone":"+1 615 826 0042",
    "sg:postcode":"37075",
    "sg:province":"TN",
    "sg:tags":[
        "church"
    ],
    "sg:website":"www.communitychurchhendersonville.org",
    "wof:name":"Community Church-Christ Youth",
    "wof:placetype":"venue"
},
  "geometry": {"coordinates":[-86.629751,36.302628],"type":"Point"}
}