{
  "type": "Feature",
  "properties": {
    "addr:full":"218 Linda Ln Madison TN 37115",
    "addr:housenumber":"218",
    "addr:postcode":"37115",
    "addr:street":"Linda Ln",
    "iso:country":"US",
    "sg:address":"218 Linda Ln",
    "sg:city":"Madison",
    "sg:classifiers":[
        {
            "category":"Shopping",
            "subcategory":"Clothing, Apparel, & Fashions",
            "type":"Retail Goods"
        }
    ],
    "sg:phone":"+1 615 865 6537",
    "sg:postcode":"37115",
    "sg:province":"TN",
    "wof:name":"Pennyrich Bras",
    "wof:placetype":"venue"
},
  "geometry": {"coordinates":[-86.72569,36.257931],"type":"Point"}
}