{
  "type": "Feature",
  "properties": {
    "addr:full":"2022 Rosemark Rd Atoka TN 38004",
    "addr:housenumber":"2022",
    "addr:postcode":"38004",
    "addr:street":"Rosemark Rd",
    "iso:country":"US",
    "sg:address":"2022 Rosemark Rd",
    "sg:city":"Atoka",
    "sg:classifiers":[
        {
            "category":"Restaurant",
            "type":"Food & Drink"
        }
    ],
    "sg:menulink":"http://www.allmenus.com/tn/munford-atoka/66848-pizza-pro/menu/",
    "sg:phone":"+1 901 837 3407",
    "sg:postcode":"38004",
    "sg:province":"TN",
    "sg:tags":[
        "american",
        "pizza"
    ],
    "wof:name":"Pizza Pro",
    "wof:placetype":"venue"
},
  "geometry": {"coordinates":[-89.76622399999999,35.404517],"type":"Point"}
}