{
  "type": "Feature",
  "properties": {
    "addr:full":"625 Hilltop Dr Athens TN 37303",
    "addr:housenumber":"625",
    "addr:postcode":"37303",
    "addr:street":"Hilltop Dr",
    "iso:country":"US",
    "sg:address":"625 Hilltop Dr",
    "sg:city":"Athens",
    "sg:classifiers":[
        {
            "category":"Building & Trades",
            "subcategory":"Pest Control",
            "type":"Services"
        }
    ],
    "sg:phone":"+1 423 744 7257",
    "sg:postcode":"37303",
    "sg:province":"TN",
    "wof:name":"McMinn Termite & Pest Control",
    "wof:placetype":"venue"
},
  "geometry": {"coordinates":[-84.616837,35.463839],"type":"Point"}
}