{
  "type": "Feature",
  "properties": {
    "iso:country":"US",
    "sg:address":"233 E Gaines St",
    "sg:city":"Lawrenceburg",
    "sg:classifiers":[
        {
            "category":"Health Services",
            "subcategory":"Doctor",
            "type":"Services"
        }
    ],
    "sg:phone":"+1 931 762 1144",
    "sg:postcode":"38464",
    "sg:province":"TN",
    "sg:tags":[
        "physician",
        "surgeon"
    ],
    "wof:name":"Frances A Berry-Brown MD",
    "wof:placetype":"venue"
},
  "geometry": {"coordinates":[-87.33199999999999,35.241079],"type":"Point"}
}