{
  "type": "Feature",
  "properties": {
    "iso:country":"US",
    "sg:address":"155 Petro Rd",
    "sg:city":"Kingston Springs",
    "sg:classifiers":[
        {
            "category":"Shopping",
            "subcategory":"Clothing, Apparel, & Fashions",
            "type":"Retail Goods"
        }
    ],
    "sg:phone":"+1 615 952 9199",
    "sg:postcode":"37190",
    "sg:province":"TN",
    "sg:tags":[
        "saddlery",
        "supply",
        "west",
        "horse",
        "equipment",
        "trailer"
    ],
    "sg:website":"www.sundownertrailercenters.com",
    "wof:name":"Sundowner Of Nashville",
    "wof:placetype":"venue"
},
  "geometry": {"coordinates":[-86.022898,35.872936],"type":"Point"}
}