{
  "type": "Feature",
  "properties": {
    "iso:country":"US",
    "sg:address":"3075 Lamar Ave",
    "sg:city":"Memphis",
    "sg:classifiers":[
        {
            "category":"Travel",
            "subcategory":"Hotels & Motels",
            "type":"Entertainment"
        }
    ],
    "sg:phone":"+1 901 744 9898",
    "sg:postcode":"38114",
    "sg:province":"TN",
    "sg:tags":[
        "operation",
        "lodging"
    ],
    "wof:name":"Liberty Inn",
    "wof:placetype":"venue"
},
  "geometry": {"coordinates":[-89.959774,35.083769],"type":"Point"}
}