{
  "type": "Feature",
  "properties": {
    "addr:full":"595 E Tickle St Dyersburg TN 38024",
    "addr:housenumber":"595",
    "addr:postcode":"38024",
    "addr:street":"E Tickle St",
    "iso:country":"US",
    "sg:address":"595 E Tickle St",
    "sg:city":"Dyersburg",
    "sg:classifiers":[
        {
            "category":"Health Services",
            "subcategory":"Doctor",
            "type":"Services"
        }
    ],
    "sg:phone":"+1 731 285 9938",
    "sg:postcode":"38024",
    "sg:province":"TN",
    "sg:tags":[
        "physician",
        "surgeon"
    ],
    "wof:name":"Dyersburg Internal Medicine",
    "wof:placetype":"venue"
},
  "geometry": {"coordinates":[-89.37864999999999,36.047258],"type":"Point"}
}