{
  "type": "Feature",
  "properties": {
    "iso:country":"US",
    "sg:address":"105 Heady Dr",
    "sg:city":"Nashville",
    "sg:classifiers":[
        {
            "category":"Shopping",
            "subcategory":"Used Merchandise",
            "type":"Retail Goods"
        }
    ],
    "sg:phone":"+1 615 354 1267",
    "sg:postcode":"37205",
    "sg:province":"TN",
    "wof:name":"Artifacts",
    "wof:placetype":"venue"
},
  "geometry": {"coordinates":[-86.871887,36.098888],"type":"Point"}
}