{
  "type": "Feature",
  "properties": {
    "addr:full":"1306 Arrowhead Dr Brentwood TN 37027",
    "addr:housenumber":"1306",
    "addr:postcode":"37027",
    "addr:street":"Arrowhead Dr",
    "iso:country":"US",
    "sg:address":"1306 Arrowhead Dr",
    "sg:city":"Brentwood",
    "sg:classifiers":[
        {
            "category":"Insurance",
            "subcategory":"Insurance Agent",
            "type":"Services"
        }
    ],
    "sg:phone":"+1 615 370 5151",
    "sg:postcode":"37027",
    "sg:province":"TN",
    "wof:name":"International Fidelity Insuran",
    "wof:placetype":"venue"
},
  "geometry": {"coordinates":[-86.763611,35.984691],"type":"Point"}
}