{
  "type": "Feature",
  "properties": {
    "iso:country":"US",
    "sg:address":"2210 Buchanan St",
    "sg:city":"Nashville",
    "sg:classifiers":[
        {
            "category":"Organizations",
            "subcategory":"Religious Organization",
            "type":"Services"
        }
    ],
    "sg:phone":"+1 615 242 1140",
    "sg:postcode":"37208",
    "sg:province":"TN",
    "sg:tags":[
        "church"
    ],
    "wof:name":"Ransom Temple Presbyterian Chr",
    "wof:placetype":"venue"
},
  "geometry": {"coordinates":[-86.81435,36.180282],"type":"Point"}
}