{
  "type": "Feature",
  "properties": {
    "iso:country":"US",
    "sg:address":"302 W Main St",
    "sg:city":"Murfreesboro",
    "sg:classifiers":[
        {
            "category":"Professional",
            "type":"Services"
        }
    ],
    "sg:phone":"+1 615 893 4363",
    "sg:postcode":"37130",
    "sg:province":"TN",
    "sg:tags":[
        "establishment"
    ],
    "wof:name":"Robins Nest",
    "wof:placetype":"venue"
},
  "geometry": {"coordinates":[-86.3951,35.846427],"type":"Point"}
}