{
  "type": "Feature",
  "properties": {
    "addr:full":"2836 Logan St Nashville TN 37211",
    "addr:housenumber":"2836",
    "addr:postcode":"37211",
    "addr:street":"Logan St",
    "iso:country":"US",
    "sg:address":"2836 Logan St",
    "sg:city":"Nashville",
    "sg:classifiers":[
        {
            "category":"Building & Trades",
            "subcategory":"Pest Control",
            "type":"Services"
        }
    ],
    "sg:phone":"+1 615 834 0531",
    "sg:postcode":"37211",
    "sg:province":"TN",
    "wof:name":"Arrow Snyder Exterminators",
    "wof:placetype":"venue"
},
  "geometry": {"coordinates":[-86.741854,36.111718],"type":"Point"}
}