{
  "type": "Feature",
  "properties": {
    "addr:full":"275 Bitter Creek Hwy Harriman TN 37748",
    "addr:housenumber":"275",
    "addr:postcode":"37748",
    "addr:street":"Bitter Creek Hwy",
    "iso:country":"US",
    "sg:address":"275 Bitter Creek Hwy",
    "sg:city":"Harriman",
    "sg:classifiers":[
        {
            "category":"Freight",
            "type":"Transportation"
        }
    ],
    "sg:phone":"+1 865 590 0303",
    "sg:postcode":"37748",
    "sg:province":"TN",
    "sg:tags":[
        "arrangement",
        "broker",
        "trucking"
    ],
    "wof:name":"Hilltop Transportation Inc",
    "wof:placetype":"venue"
},
  "geometry": {"coordinates":[-84.501445,35.970459],"type":"Point"}
}