{
  "type": "Feature",
  "properties": {
    "iso:country":"US",
    "sg:address":"909 E Wood St",
    "sg:city":"Paris",
    "sg:classifiers":[
        {
            "category":"Home & Garden",
            "subcategory":"Building Materials",
            "type":"Retail Goods"
        }
    ],
    "sg:phone":"+1 731 642 3233",
    "sg:postcode":"38242",
    "sg:province":"TN",
    "sg:tags":[
        "wallpaper"
    ],
    "wof:name":"Wallpaper For Less",
    "wof:placetype":"venue"
},
  "geometry": {"coordinates":[-88.310782,36.30213],"type":"Point"}
}