{
  "type": "Feature",
  "properties": {
    "iso:country":"US",
    "sg:address":"111 Center Park Dr",
    "sg:city":"Knoxville",
    "sg:classifiers":[
        {
            "category":"Health Services",
            "subcategory":"Health Practitioner",
            "type":"Services"
        }
    ],
    "sg:phone":"+1 865 693 9997",
    "sg:postcode":"37922",
    "sg:province":"TN",
    "wof:name":"Christopher Hebb PHD",
    "wof:placetype":"venue"
},
  "geometry": {"coordinates":[-84.12173,35.902832],"type":"Point"}
}