{
  "type": "Feature",
  "properties": {
    "addr:full":"1710 Fairview Blvd Fairview TN 37062",
    "addr:housenumber":"1710",
    "addr:postcode":"37062",
    "addr:street":"Fairview Blvd",
    "iso:country":"US",
    "sg:address":"1710 Fairview Blvd",
    "sg:city":"Fairview",
    "sg:classifiers":[
        {
            "category":"Restaurant",
            "type":"Food & Drink"
        }
    ],
    "sg:phone":"+1 615 799 0215",
    "sg:postcode":"37062",
    "sg:province":"TN",
    "wof:name":"Country Cafe",
    "wof:placetype":"venue"
},
  "geometry": {"coordinates":[-87.144896,35.947459],"type":"Point"}
}