{
  "type": "Feature",
  "properties": {
    "addr:full":"102 Vermont Ave Oak Ridge TN 37830",
    "addr:housenumber":"102",
    "addr:postcode":"37830",
    "addr:street":"Vermont Ave",
    "iso:country":"US",
    "sg:address":"102 Vermont Ave",
    "sg:city":"Oak Ridge",
    "sg:classifiers":[
        {
            "category":"Health Services",
            "subcategory":"Doctor",
            "type":"Services"
        }
    ],
    "sg:phone":"+1 865 483 3377",
    "sg:postcode":"37830",
    "sg:province":"TN",
    "sg:tags":[
        "physician",
        "surgeon",
        "medical"
    ],
    "wof:name":"Cumberland Oncology & Hmtlgy",
    "wof:placetype":"venue"
},
  "geometry": {"coordinates":[-84.248327,36.020613],"type":"Point"}
}