{
  "type": "Feature",
  "properties": {
    "iso:country":"US",
    "sg:address":"2900 Home Dr",
    "sg:city":"Chattanooga",
    "sg:classifiers":[
        {
            "category":"Utilities",
            "subcategory":"Refuse",
            "type":"Services"
        },
        {
            "category":"Wholesale",
            "subcategory":"Scrap",
            "type":"Manufacturing & Wholesale Goods"
        }
    ],
    "sg:phone":"+1 423 267 0097",
    "sg:postcode":"37410",
    "sg:province":"TN",
    "sg:tags":[
        "recycling",
        "waste",
        "paper",
        "center",
        "recycles"
    ],
    "sg:website":"www.rockteen.com",
    "wof:name":"Chattanooga Recycled Fiber",
    "wof:placetype":"venue"
},
  "geometry": {"coordinates":[-85.309843,35.018465],"type":"Point"}
}