{
  "type": "Feature",
  "properties": {
    "iso:country":"US",
    "sg:address":"930 N Jackson St",
    "sg:city":"Tullahoma",
    "sg:classifiers":[
        {
            "category":"Personal",
            "subcategory":"Beauty Salon",
            "type":"Services"
        }
    ],
    "sg:phone":"+1 931 455 8899",
    "sg:postcode":"37388",
    "sg:province":"TN",
    "sg:tags":[
        "shop",
        "barber"
    ],
    "wof:name":"Hair Fantasy",
    "wof:placetype":"venue"
},
  "geometry": {"coordinates":[-86.22235499999999,35.373964],"type":"Point"}
}