{
  "type": "Feature",
  "properties": {
    "iso:country":"US",
    "sg:address":"117 Huxley Rd",
    "sg:city":"Knoxville",
    "sg:classifiers":[
        {
            "category":"Health Services",
            "subcategory":"Clinic",
            "type":"Services"
        }
    ],
    "sg:phone":"+1 865 531 7730",
    "sg:postcode":"37922",
    "sg:province":"TN",
    "sg:tags":[
        "medical",
        "examination"
    ],
    "sg:website":"www.firstchoiceexam.com",
    "wof:name":"First Choice Paramedicals",
    "wof:placetype":"venue"
},
  "geometry": {"coordinates":[-84.13323099999999,35.896682],"type":"Point"}
}