{
  "type": "Feature",
  "properties": {
    "iso:country":"US",
    "sg:address":"2806 Newburn Dr",
    "sg:city":"Johnson City",
    "sg:classifiers":[
        {
            "category":"Education",
            "subcategory":"School",
            "type":"Public Place"
        }
    ],
    "sg:phone":"+1 423 928 3647",
    "sg:postcode":"37604",
    "sg:province":"TN",
    "wof:name":"Cool School For Dogs",
    "wof:placetype":"venue"
},
  "geometry": {"coordinates":[-82.39361599999999,36.288011],"type":"Point"}
}