{
  "type": "Feature",
  "properties": {
    "iso:country":"US",
    "sg:address":"137 7th Ave N",
    "sg:city":"Nashville",
    "sg:classifiers":[
        {
            "category":"Restaurant",
            "type":"Food & Drink"
        }
    ],
    "sg:phone":"+1 615 255 8122",
    "sg:postcode":"37203",
    "sg:province":"TN",
    "sg:tags":[
        "eating"
    ],
    "wof:name":"KOTO Sushi Bar",
    "wof:placetype":"venue"
},
  "geometry": {"coordinates":[-86.78157400000001,36.16028],"type":"Point"}
}