{
  "type": "Feature",
  "properties": {
    "iso:country":"US",
    "sg:address":"551 Old Hwy 46 S",
    "sg:city":"Dickson",
    "sg:classifiers":[
        {
            "category":"Wholesale",
            "subcategory":"Groceries",
            "type":"Manufacturing & Wholesale Goods"
        }
    ],
    "sg:phone":"+1 615 441 1494",
    "sg:postcode":"37055",
    "sg:province":"TN",
    "sg:tags":[
        "baker"
    ],
    "wof:name":"Colonial Baking Co",
    "wof:placetype":"venue"
},
  "geometry": {"coordinates":[-87.330399,36.002942],"type":"Point"}
}