{
  "type": "Feature",
  "properties": {
    "addr:full":"2106 Ravenwood Dr Murfreesboro TN 37129",
    "addr:housenumber":"2106",
    "addr:postcode":"37129",
    "addr:street":"Ravenwood Dr",
    "iso:country":"US",
    "sg:address":"2106 Ravenwood Dr",
    "sg:city":"Murfreesboro",
    "sg:classifiers":[
        {
            "category":"Arts & Performance",
            "subcategory":"Theater",
            "type":"Entertainment"
        }
    ],
    "sg:phone":"+1 615 895 0370",
    "sg:postcode":"37129",
    "sg:province":"TN",
    "sg:tags":[
        "group",
        "merchandise"
    ],
    "wof:name":"Mad Striper",
    "wof:placetype":"venue"
},
  "geometry": {"coordinates":[-86.398083,35.884389],"type":"Point"}
}