{
  "type": "Feature",
  "properties": {
    "iso:country":"US",
    "sg:address":"3416 Macon Rd",
    "sg:city":"Memphis",
    "sg:classifiers":[
        {
            "category":"Retail",
            "subcategory":"Self-service Laundry",
            "type":"Services"
        }
    ],
    "sg:phone":"+1 901 323 8267",
    "sg:postcode":"38122",
    "sg:province":"TN",
    "sg:tags":[
        "coin"
    ],
    "wof:name":"Quarter Coin Laundry",
    "wof:placetype":"venue"
},
  "geometry": {"coordinates":[-89.945747,35.162197],"type":"Point"}
}