{
  "type": "Feature",
  "properties": {
    "iso:country":"US",
    "sg:address":"405 S Ruth St",
    "sg:city":"Maryville",
    "sg:classifiers":[
        {
            "category":"Real Estate",
            "subcategory":"Architect",
            "type":"Services"
        }
    ],
    "sg:phone":"+1 865 977 0598",
    "sg:postcode":"37803",
    "sg:province":"TN",
    "sg:tags":[
        "illustrator",
        "architectural"
    ],
    "wof:name":"Christopher Illustrations",
    "wof:placetype":"venue"
},
  "geometry": {"coordinates":[-83.978905,35.742831],"type":"Point"}
}