{
  "type": "Feature",
  "properties": {
    "addr:full":"1027 17th Ave S Nashville TN 37212",
    "addr:housenumber":"1027",
    "addr:postcode":"37212",
    "addr:street":"17Th Ave S",
    "iso:country":"US",
    "sg:address":"1027 17th Ave S",
    "sg:city":"Nashville",
    "sg:classifiers":[
        {
            "category":"Professional",
            "subcategory":"Advertising",
            "type":"Services"
        }
    ],
    "sg:phone":"+1 615 385 4646",
    "sg:postcode":"37212",
    "sg:province":"TN",
    "sg:tags":[
        "publicity"
    ],
    "wof:name":"Force Inc",
    "wof:placetype":"venue"
},
  "geometry": {"coordinates":[-86.794422,36.143959],"type":"Point"}
}