{
  "type": "Feature",
  "properties": {
    "addr:full":"1040 W Main St Waverly TN 37185",
    "addr:housenumber":"1040",
    "addr:postcode":"37185",
    "addr:street":"W Main St",
    "iso:country":"US",
    "sg:address":"1040 W Main St",
    "sg:city":"Waverly",
    "sg:classifiers":[
        {
            "category":"Professional",
            "subcategory":"Accounting & Tax Preparation",
            "type":"Services"
        }
    ],
    "sg:phone":"+1 931 296 3107",
    "sg:postcode":"37185",
    "sg:province":"TN",
    "sg:tags":[
        "accountant"
    ],
    "wof:name":"Durham Nunnery & Brooks",
    "wof:placetype":"venue"
},
  "geometry": {"coordinates":[-87.83165200000001,36.078902],"type":"Point"}
}