{
  "type": "Feature",
  "properties": {
    "addr:full":"2400 Crestmoor Rd Nashville TN 37215",
    "addr:housenumber":"2400",
    "addr:postcode":"37215",
    "addr:street":"Crestmoor Rd",
    "iso:country":"US",
    "sg:address":"2400 Crestmoor Rd",
    "sg:city":"Nashville",
    "sg:classifiers":[
        {
            "category":"Professional",
            "subcategory":"Management & Consulting",
            "type":"Services"
        }
    ],
    "sg:phone":"+1 615 386 7003",
    "sg:postcode":"37215",
    "sg:province":"TN",
    "wof:name":"Law Offices of John S Gannon",
    "wof:placetype":"venue"
},
  "geometry": {"coordinates":[-86.819481,36.109943],"type":"Point"}
}