{
  "type": "Feature",
  "properties": {
    "iso:country":"US",
    "sg:address":"1522 W G St",
    "sg:city":"Elizabethton",
    "sg:classifiers":[
        {
            "category":"Building & Trades",
            "subcategory":"Equipment Rental",
            "type":"Services"
        }
    ],
    "sg:phone":"+1 423 543 5918",
    "sg:postcode":"37643",
    "sg:province":"TN",
    "sg:tags":[
        "yard"
    ],
    "wof:name":"A To Z Rental Inc",
    "wof:placetype":"venue"
},
  "geometry": {"coordinates":[-82.247575,36.340579],"type":"Point"}
}