{
  "type": "Feature",
  "properties": {
    "iso:country":"US",
    "sg:address":"1127 Johnny Stone Ct",
    "sg:city":"Columbia",
    "sg:classifiers":[
        {
            "category":"Organizations",
            "subcategory":"Community Association",
            "type":"Services"
        }
    ],
    "sg:phone":"+1 931 381 9957",
    "sg:postcode":"38401",
    "sg:province":"TN",
    "sg:tags":[
        "club"
    ],
    "wof:name":"Godfathers Motorcycle Club",
    "wof:placetype":"venue"
},
  "geometry": {"coordinates":[-87.014819,35.617136],"type":"Point"}
}