{
  "type": "Feature",
  "properties": {
    "iso:country":"US",
    "sg:address":"360 Kingsport Hwy",
    "sg:city":"Greeneville",
    "sg:classifiers":[
        {
            "category":"Recreation",
            "subcategory":"Arcade",
            "type":"Entertainment"
        }
    ],
    "sg:phone":"+1 423 639 3060",
    "sg:postcode":"37745",
    "sg:province":"TN",
    "sg:tags":[
        "video"
    ],
    "wof:name":"Fun City Amusement II",
    "wof:placetype":"venue"
},
  "geometry": {"coordinates":[-82.813958,36.183275],"type":"Point"}
}