{
  "type": "Feature",
  "properties": {
    "addr:full":"3245 Starsdale St Memphis TN 38118",
    "addr:housenumber":"3245",
    "addr:postcode":"38118",
    "addr:street":"Starsdale St",
    "iso:country":"US",
    "sg:address":"3245 Starsdale St",
    "sg:city":"Memphis",
    "sg:classifiers":[
        {
            "category":"Building & Trades",
            "subcategory":"Cleaning & Sanitation",
            "type":"Services"
        }
    ],
    "sg:phone":"+1 901 368 4618",
    "sg:postcode":"38118",
    "sg:province":"TN",
    "sg:tags":[
        "janitor"
    ],
    "wof:name":"Heart To Heart Cleaning Svc",
    "wof:placetype":"venue"
},
  "geometry": {"coordinates":[-89.89984,35.060776],"type":"Point"}
}