{
  "type": "Feature",
  "properties": {
    "addr:full":"3917 Alderwood Dr Kingsport TN 37664",
    "addr:housenumber":"3917",
    "addr:postcode":"37664",
    "addr:street":"Alderwood Dr",
    "iso:country":"US",
    "sg:address":"3917 Alderwood Dr",
    "sg:city":"Kingsport",
    "sg:classifiers":[
        {
            "category":"Banks & Credit Unions",
            "subcategory":"Investment Brokerage",
            "type":"Services"
        }
    ],
    "sg:phone":"+1 423 245 3450",
    "sg:postcode":"37664",
    "sg:province":"TN",
    "wof:name":"AJS Investments LLC",
    "wof:placetype":"venue"
},
  "geometry": {"coordinates":[-82.511832,36.520583],"type":"Point"}
}