{
  "type": "Feature",
  "properties": {
    "iso:country":"US",
    "sg:address":"284 Winchester Hwy",
    "sg:city":"Hillsboro",
    "sg:classifiers":[
        {
            "category":"Education",
            "subcategory":"School",
            "type":"Public Place"
        }
    ],
    "sg:phone":"+1 931 596 2968",
    "sg:postcode":"37342",
    "sg:province":"TN",
    "wof:name":"Hillsboro School Family Rsrc",
    "wof:placetype":"venue"
},
  "geometry": {"coordinates":[-85.97339700000001,35.408326],"type":"Point"}
}