{
  "type": "Feature",
  "properties": {
    "addr:full":"865 Bellevue Rd Apt F12 Nashville TN 37221",
    "addr:housenumber":"865",
    "addr:postcode":"37221",
    "addr:street":"Bellevue Rd Apt F12",
    "iso:country":"US",
    "sg:address":"865 Bellevue Rd Apt F12",
    "sg:city":"Nashville",
    "sg:classifiers":[
        {
            "category":"Building & Trades",
            "subcategory":"Construction",
            "type":"Services"
        }
    ],
    "sg:phone":"+1 615 457 0508",
    "sg:postcode":"37221",
    "sg:province":"TN",
    "sg:tags":[
        "carpenter"
    ],
    "wof:name":"Groundup Restorations",
    "wof:placetype":"venue"
},
  "geometry": {"coordinates":[-86.940625,36.074099],"type":"Point"}
}