{
  "type": "Feature",
  "properties": {
    "iso:country":"US",
    "sg:address":"2523 Wilma Rudolph Blvd",
    "sg:city":"Clarksville",
    "sg:classifiers":[
        {
            "category":"Building & Trades",
            "subcategory":"Construction",
            "type":"Services"
        }
    ],
    "sg:phone":"+1 931 552 9726",
    "sg:postcode":"37040",
    "sg:province":"TN",
    "sg:tags":[
        "residential",
        "contractor"
    ],
    "wof:name":"ACI Development",
    "wof:placetype":"venue"
},
  "geometry": {"coordinates":[-87.299769,36.578713],"type":"Point"}
}