{
  "type": "Feature",
  "properties": {
    "addr:full":"147 Featherstone Dr Franklin TN 37069",
    "addr:housenumber":"147",
    "addr:postcode":"37069",
    "addr:street":"Featherstone Dr",
    "iso:country":"US",
    "sg:address":"147 Featherstone Dr",
    "sg:city":"Franklin",
    "sg:classifiers":[
        {
            "category":"Professional",
            "subcategory":"Business Services",
            "type":"Services"
        }
    ],
    "sg:phone":"+1 615 791 1470",
    "sg:postcode":"37069",
    "sg:province":"TN",
    "wof:name":"Pease Enterprises Inc",
    "wof:placetype":"venue"
},
  "geometry": {"coordinates":[-86.88502200000001,35.991198],"type":"Point"}
}