{
  "type": "Feature",
  "properties": {
    "addr:full":"4945 American Way Memphis TN 38118",
    "addr:housenumber":"4945",
    "addr:postcode":"38118",
    "addr:street":"American Way",
    "iso:country":"US",
    "sg:address":"4945 American Way",
    "sg:city":"Memphis",
    "sg:classifiers":[
        {
            "category":"Professional",
            "subcategory":"Employment Agencies",
            "type":"Services"
        }
    ],
    "sg:phone":"+1 901 365 6993",
    "sg:postcode":"38118",
    "sg:province":"TN",
    "sg:tags":[
        "help",
        "contractor"
    ],
    "wof:name":"Spherion",
    "wof:placetype":"venue"
},
  "geometry": {"coordinates":[-89.89802299999999,35.075125],"type":"Point"}
}