{
  "type": "Feature",
  "properties": {
    "addr:full":"105 Anderson Ln Gainesboro TN 38562",
    "addr:housenumber":"105",
    "addr:postcode":"38562",
    "addr:street":"Anderson Ln",
    "iso:country":"US",
    "sg:address":"105 Anderson Ln",
    "sg:city":"Gainesboro",
    "sg:classifiers":[
        {
            "category":"Food & Beverages",
            "subcategory":"Liquor & Beverages",
            "type":"Retail Goods"
        }
    ],
    "sg:phone":"+1 931 268 2471",
    "sg:postcode":"38562",
    "sg:province":"TN",
    "wof:name":"Lakefront Liquors & Wines",
    "wof:placetype":"venue"
},
  "geometry": {"coordinates":[-85.636876,36.372073],"type":"Point"}
}