{
  "type": "Feature",
  "properties": {
    "iso:country":"US",
    "sg:address":"900 Forrest Dr",
    "sg:city":"Tullahoma",
    "sg:classifiers":[
        {
            "category":"Real Estate",
            "subcategory":"Real Estate Operator",
            "type":"Services"
        }
    ],
    "sg:phone":"+1 931 455 8191",
    "sg:postcode":"37388",
    "sg:province":"TN",
    "sg:tags":[
        "building",
        "nonresidential"
    ],
    "wof:name":"Bch Properties",
    "wof:placetype":"venue"
},
  "geometry": {"coordinates":[-86.208292,35.375144],"type":"Point"}
}