{
  "type": "Feature",
  "properties": {
    "addr:full":"1619 E Main St Chattanooga TN 37404",
    "addr:housenumber":"1619",
    "addr:postcode":"37404",
    "addr:street":"E Main St",
    "iso:country":"US",
    "sg:address":"1619 E Main St",
    "sg:city":"Chattanooga",
    "sg:classifiers":[
        {
            "category":"Organizations",
            "subcategory":"Religious Organization",
            "type":"Services"
        }
    ],
    "sg:phone":"+1 423 629 6039",
    "sg:postcode":"37404",
    "sg:province":"TN",
    "wof:name":"Second Bptst Chrch Chattanooga",
    "wof:placetype":"venue"
},
  "geometry": {"coordinates":[-85.28315499999999,35.027246],"type":"Point"}
}