{
  "type": "Feature",
  "properties": {
    "iso:country":"US",
    "sg:address":"246 W Main St",
    "sg:city":"Jackson",
    "sg:classifiers":[
        {
            "category":"Building & Trades",
            "subcategory":"Construction",
            "type":"Services"
        }
    ],
    "sg:phone":"+1 731 427 9022",
    "sg:postcode":"38301",
    "sg:province":"TN",
    "sg:tags":[
        "house"
    ],
    "wof:name":"Madison Realty",
    "wof:placetype":"venue"
},
  "geometry": {"coordinates":[-88.82205999999999,35.614342],"type":"Point"}
}