{
  "type": "Feature",
  "properties": {
    "iso:country":"US",
    "sg:address":"197 Beasley Dr",
    "sg:city":"Dickson",
    "sg:classifiers":[
        {
            "category":"Restaurant",
            "type":"Food & Drink"
        }
    ],
    "sg:phone":"+1 615 441 8800",
    "sg:postcode":"37055",
    "sg:province":"TN",
    "wof:name":"Pizza Galaxy LLC",
    "wof:placetype":"venue"
},
  "geometry": {"coordinates":[-87.37846399999999,36.061814],"type":"Point"}
}