{
  "type": "Feature",
  "properties": {
    "addr:full":"1201 W 5th Ave Springfield TN 37172",
    "addr:housenumber":"1201",
    "addr:postcode":"37172",
    "addr:street":"W 5Th Ave",
    "iso:country":"US",
    "sg:address":"1201 W 5th Ave",
    "sg:city":"Springfield",
    "sg:classifiers":[
        {
            "category":"Building & Trades",
            "subcategory":"Electrical",
            "type":"Services"
        }
    ],
    "sg:phone":"+1 615 384 2780",
    "sg:postcode":"37172",
    "sg:province":"TN",
    "sg:tags":[
        "electric",
        "contractor"
    ],
    "wof:name":"Charles Jennette Electrical",
    "wof:placetype":"venue"
},
  "geometry": {"coordinates":[-86.901313,36.503645],"type":"Point"}
}