{
  "type": "Feature",
  "properties": {
    "addr:full":"2701 Vermont Ave Chattanooga TN 37404",
    "addr:housenumber":"2701",
    "addr:postcode":"37404",
    "addr:street":"Vermont Ave",
    "iso:country":"US",
    "sg:address":"2701 Vermont Ave",
    "sg:city":"Chattanooga",
    "sg:classifiers":[
        {
            "category":"Professional",
            "subcategory":"Management & Consulting",
            "type":"Services"
        }
    ],
    "sg:phone":"+1 423 629 4316",
    "sg:postcode":"37404",
    "sg:province":"TN",
    "sg:tags":[
        "food"
    ],
    "wof:name":"Sodexho",
    "wof:placetype":"venue"
},
  "geometry": {"coordinates":[-85.258228,35.036825],"type":"Point"}
}