{
  "type": "Feature",
  "properties": {
    "iso:country":"US",
    "sg:address":"8475 Tullahoma Hwy",
    "sg:city":"Estill Springs",
    "sg:classifiers":[
        {
            "category":"Food & Beverages",
            "subcategory":"Groceries & Convenience Stores",
            "type":"Retail Goods"
        }
    ],
    "sg:phone":"+1 931 649 5675",
    "sg:postcode":"37330",
    "sg:province":"TN",
    "wof:name":"Brahman Inc",
    "wof:placetype":"venue"
},
  "geometry": {"coordinates":[-86.151236,35.29698],"type":"Point"}
}