{
  "type": "Feature",
  "properties": {
    "iso:country":"US",
    "sg:address":"317 Main St",
    "sg:city":"Franklin",
    "sg:classifiers":[
        {
            "category":"Organizations",
            "subcategory":"Non-profit Organization",
            "type":"Services"
        }
    ],
    "sg:phone":"+1 615 376 5357",
    "sg:postcode":"37064",
    "sg:province":"TN",
    "sg:tags":[
        "human"
    ],
    "wof:name":"Covenant Marriage",
    "wof:placetype":"venue"
},
  "geometry": {"coordinates":[-86.86924999999999,35.924951],"type":"Point"}
}