{
  "type": "Feature",
  "properties": {
    "addr:full":"874 Springfield Hwy Goodlettsville TN 37072",
    "addr:housenumber":"874",
    "addr:postcode":"37072",
    "addr:street":"Springfield Hwy",
    "iso:country":"US",
    "sg:address":"874 Springfield Hwy",
    "sg:city":"Goodlettsville",
    "sg:classifiers":[
        {
            "category":"Building & Trades",
            "subcategory":"Plumbing",
            "type":"Services"
        }
    ],
    "sg:phone":"+1 615 859 0870",
    "sg:postcode":"37072",
    "sg:province":"TN",
    "sg:tags":[
        "conditioning",
        "air",
        "heating",
        "contractor"
    ],
    "wof:name":"Kimbro Electric Service Inc",
    "wof:placetype":"venue"
},
  "geometry": {"coordinates":[-86.72531600000001,36.358533],"type":"Point"}
}