{
  "type": "Feature",
  "properties": {
    "addr:full":"281 10th St Crossville TN 38555",
    "addr:housenumber":"281",
    "addr:postcode":"38555",
    "addr:street":"10Th St",
    "iso:country":"US",
    "sg:address":"281 10th St",
    "sg:city":"Crossville",
    "sg:classifiers":[
        {
            "category":"Social Services",
            "type":"Services"
        }
    ],
    "sg:phone":"+1 931 484 3225",
    "sg:postcode":"38555",
    "sg:province":"TN",
    "sg:tags":[
        "organization",
        "welfare"
    ],
    "wof:name":"Good Samaritans",
    "wof:placetype":"venue"
},
  "geometry": {"coordinates":[-85.03471,35.949896],"type":"Point"}
}