{
  "type": "Feature",
  "properties": {
    "addr:full":"1198 Rock Church Rd Dickson TN 37055",
    "addr:housenumber":"1198",
    "addr:postcode":"37055",
    "addr:street":"Rock Church Rd",
    "iso:country":"US",
    "sg:address":"1198 Rock Church Rd",
    "sg:city":"Dickson",
    "sg:classifiers":[
        {
            "category":"Utilities",
            "subcategory":"Sewage",
            "type":"Services"
        }
    ],
    "sg:phone":"+1 615 446 8662",
    "sg:postcode":"37055",
    "sg:province":"TN",
    "sg:tags":[
        "disposal",
        "system"
    ],
    "wof:name":"Dickson City Sewage Plant",
    "wof:placetype":"venue"
},
  "geometry": {"coordinates":[-87.314263,36.09492],"type":"Point"}
}