{
  "type": "Feature",
  "properties": {
    "addr:full":"513 Westbrook Rd Knoxville TN 37919",
    "addr:housenumber":"513",
    "addr:postcode":"37919",
    "addr:street":"Westbrook Rd",
    "iso:country":"US",
    "sg:address":"513 Westbrook Rd",
    "sg:city":"Knoxville",
    "sg:classifiers":[
        {
            "category":"Social Services",
            "subcategory":"Job Training",
            "type":"Services"
        }
    ],
    "sg:phone":"+1 865 560 5533",
    "sg:postcode":"37919",
    "sg:province":"TN",
    "wof:name":"Trainers Edge",
    "wof:placetype":"venue"
},
  "geometry": {"coordinates":[-84.05502,35.91077],"type":"Point"}
}