{
  "type": "Feature",
  "properties": {
    "iso:country":"US",
    "sg:address":"2164 US Hwy 11",
    "sg:city":"Niota",
    "sg:classifiers":[
        {
            "category":"Recreation",
            "type":"Entertainment"
        }
    ],
    "sg:phone":"+1 423 568 3038",
    "sg:postcode":"37826",
    "sg:province":"TN",
    "wof:name":"M & M Ponies",
    "wof:placetype":"venue"
},
  "geometry": {"coordinates":[-84.52401500000001,35.535256],"type":"Point"}
}