{
  "type": "Feature",
  "properties": {
    "iso:country":"US",
    "sg:address":"1805 Haley Ave",
    "sg:city":"Nashville",
    "sg:classifiers":[
        {
            "category":"Professional",
            "type":"Services"
        }
    ],
    "sg:phone":"+1 615 742 9966",
    "sg:postcode":"37218",
    "sg:province":"TN",
    "sg:tags":[
        "establishment"
    ],
    "wof:name":"Opportunity House",
    "wof:placetype":"venue"
},
  "geometry": {"coordinates":[-86.832498,36.189596],"type":"Point"}
}