{
  "type": "Feature",
  "properties": {
    "addr:full":"5885 Ridgeway Center Pkwy Suite 108 Memphis TN 38120",
    "addr:housenumber":"5885",
    "addr:postcode":"38120",
    "addr:street":"Ridgeway Center Pkwy Suite 108",
    "iso:country":"US",
    "sg:address":"5885 Ridgeway Center Pkwy Suite 108",
    "sg:city":"Memphis",
    "sg:classifiers":[
        {
            "category":"Insurance",
            "subcategory":"Hazard Insurance",
            "type":"Services"
        },
        {
            "category":"Insurance",
            "subcategory":"Insurance Agent",
            "type":"Services"
        },
        {
            "category":"Insurance",
            "subcategory":"Life Insurance",
            "type":"Services"
        }
    ],
    "sg:phone":"+1 901 236 0307",
    "sg:postcode":"38120",
    "sg:province":"TN",
    "sg:tags":[
        "auto"
    ],
    "sg:website":"http://allstateagencies.com/STEPHANIESOTO/Welcome/?cid=OTC-Southern-Club-Blue-iYP048468yp&att=STEPHANIESOTO",
    "wof:name":"Stephanie Soto - Allstate Insurance Company",
    "wof:placetype":"venue"
},
  "geometry": {"coordinates":[-89.86583299999999,35.104853],"type":"Point"}
}