{
  "type": "Feature",
  "properties": {
    "addr:full":"311 S Fair St Morrison TN 37357",
    "addr:housenumber":"311",
    "addr:postcode":"37357",
    "addr:street":"S Fair St",
    "iso:country":"US",
    "sg:address":"311 S Fair St",
    "sg:city":"Morrison",
    "sg:classifiers":[
        {
            "category":"Retail",
            "subcategory":"Auto Repair",
            "type":"Services"
        }
    ],
    "sg:phone":"+1 931 635 2868",
    "sg:postcode":"37357",
    "sg:province":"TN",
    "sg:tags":[
        "repairing",
        "automobile"
    ],
    "wof:name":"Greg Hullett Automotive",
    "wof:placetype":"venue"
},
  "geometry": {"coordinates":[-85.9145,35.601698],"type":"Point"}
}