{
  "type": "Feature",
  "properties": {
    "iso:country":"US",
    "sg:address":"1555 W Main St",
    "sg:city":"Livingston",
    "sg:classifiers":[
        {
            "category":"Freight",
            "type":"Transportation"
        }
    ],
    "sg:phone":"+1 931 403 1055",
    "sg:postcode":"38570",
    "sg:province":"TN",
    "sg:tags":[
        "commercial",
        "storage"
    ],
    "wof:name":"Riden Around Car Wash",
    "wof:placetype":"venue"
},
  "geometry": {"coordinates":[-85.34093300000001,36.36842],"type":"Point"}
}