{
  "type": "Feature",
  "properties": {
    "iso:country":"US",
    "sg:address":"188 Thompson Rd",
    "sg:city":"Covington",
    "sg:classifiers":[
        {
            "category":"Food & Beverages",
            "subcategory":"Groceries & Convenience Stores",
            "type":"Retail Goods"
        }
    ],
    "sg:phone":"+1 901 476 7713",
    "sg:postcode":"38019",
    "sg:province":"TN",
    "wof:name":"Bucksnort Grocery",
    "wof:placetype":"venue"
},
  "geometry": {"coordinates":[-89.714473,35.561566],"type":"Point"}
}