{
  "type": "Feature",
  "properties": {
    "addr:full":"2182 Old Russellville Pike Clarksville TN 37043",
    "addr:housenumber":"2182",
    "addr:postcode":"37043",
    "addr:street":"Old Russellville Pike",
    "iso:country":"US",
    "sg:address":"2182 Old Russellville Pike",
    "sg:city":"Clarksville",
    "sg:classifiers":[
        {
            "category":"Organizations",
            "subcategory":"Religious Organization",
            "type":"Services"
        }
    ],
    "sg:phone":"+1 931 645 9927",
    "sg:postcode":"37043",
    "sg:province":"TN",
    "sg:tags":[
        "church"
    ],
    "sg:website":"www.clarksvillevcf.org",
    "wof:name":"Vineyard Christian Fellowship",
    "wof:placetype":"venue"
},
  "geometry": {"coordinates":[-87.30282,36.563919],"type":"Point"}
}