{
  "type": "Feature",
  "properties": {
    "iso:country":"US",
    "sg:address":"61 Seaboard Ln",
    "sg:city":"Brentwood",
    "sg:classifiers":[
        {
            "category":"Wholesale",
            "subcategory":"Construction Materials",
            "type":"Manufacturing & Wholesale Goods"
        }
    ],
    "sg:phone":"+1 615 221 9014",
    "sg:postcode":"37027",
    "sg:province":"TN",
    "sg:tags":[
        "building"
    ],
    "wof:name":"Parksite Plunkett-Webster",
    "wof:placetype":"venue"
},
  "geometry": {"coordinates":[-86.819603,35.962696],"type":"Point"}
}