{
  "type": "Feature",
  "properties": {
    "iso:country":"US",
    "sg:address":"72 Herron Grove Rd",
    "sg:city":"Jackson",
    "sg:classifiers":[
        {
            "category":"Shopping",
            "type":"Retail Goods"
        },
        {
            "category":"Shopping",
            "subcategory":"Gifts & Souvenirs",
            "type":"Retail Goods"
        }
    ],
    "sg:phone":"+1 731 424 7577",
    "sg:postcode":"38301",
    "sg:province":"TN",
    "sg:tags":[
        "picture",
        "frame"
    ],
    "wof:name":"Frame N Hang",
    "wof:placetype":"venue"
},
  "geometry": {"coordinates":[-88.81127600000001,35.574784],"type":"Point"}
}