{
  "type": "Feature",
  "properties": {
    "addr:full":"10011 State Hwy 58 Ooltewah TN 37363",
    "addr:housenumber":"10011",
    "addr:postcode":"37363",
    "addr:street":"State Hwy 58",
    "iso:country":"US",
    "sg:address":"10011 State Hwy 58",
    "sg:city":"Ooltewah",
    "sg:classifiers":[
        {
            "category":"Autos & Motor Vehicles",
            "subcategory":"Fuel & Gas Station",
            "type":"Retail Goods"
        }
    ],
    "sg:phone":"+1 423 344 0433",
    "sg:postcode":"37363",
    "sg:province":"TN",
    "sg:tags":[
        "grocery",
        "station",
        "gasoline"
    ],
    "wof:name":"Trudys",
    "wof:placetype":"venue"
},
  "geometry": {"coordinates":[-85.02746500000001,35.219613],"type":"Point"}
}