{
  "type": "Feature",
  "properties": {
    "addr:full":"1504 Virginia St Johnson City TN 37604",
    "addr:housenumber":"1504",
    "addr:postcode":"37604",
    "addr:street":"Virginia St",
    "iso:country":"US",
    "sg:address":"1504 Virginia St",
    "sg:city":"Johnson City",
    "sg:classifiers":[
        {
            "category":"Organizations",
            "subcategory":"Religious Organization",
            "type":"Services"
        }
    ],
    "sg:phone":"+1 423 929 9080",
    "sg:postcode":"37604",
    "sg:province":"TN",
    "wof:name":"Morning Light Community Free",
    "wof:placetype":"venue"
},
  "geometry": {"coordinates":[-82.354145,36.301809],"type":"Point"}
}