{
  "type": "Feature",
  "properties": {
    "iso:country":"US",
    "sg:address":"217 2nd Ave S",
    "sg:city":"Franklin",
    "sg:classifiers":[
        {
            "category":"Professional",
            "subcategory":"Lawyer & Legal Services",
            "type":"Services"
        }
    ],
    "sg:phone":"+1 615 791 1031",
    "sg:postcode":"37064",
    "sg:province":"TN",
    "sg:tags":[
        "attorney"
    ],
    "sg:website":"www.sutter-law.com",
    "wof:name":"Sutter O'Connell Mannion",
    "wof:placetype":"venue"
},
  "geometry": {"coordinates":[-86.86609199999999,35.923853],"type":"Point"}
}