{
  "type": "Feature",
  "properties": {
    "iso:country":"US",
    "sg:address":"757 Walnut Knoll Ln",
    "sg:city":"Cordova",
    "sg:classifiers":[
        {
            "category":"Wholesale",
            "subcategory":"Electrical",
            "type":"Manufacturing & Wholesale Goods"
        }
    ],
    "sg:phone":"+1 901 755 1800",
    "sg:postcode":"38018",
    "sg:province":"TN",
    "sg:tags":[
        "control",
        "burglar",
        "alarm",
        "system",
        "monitoring",
        "security"
    ],
    "sg:website":"http://www.fraseprotection.com",
    "wof:name":"Frase Protection Inc",
    "wof:placetype":"venue"
},
  "geometry": {"coordinates":[-89.793674,35.145866],"type":"Point"}
}