{
  "type": "Feature",
  "properties": {
    "addr:full":"121 Suburban Rd SW Knoxville TN 37923",
    "addr:housenumber":"121",
    "addr:postcode":"37923",
    "addr:street":"Suburban Rd Sw",
    "iso:country":"US",
    "sg:address":"121 Suburban Rd SW",
    "sg:city":"Knoxville",
    "sg:classifiers":[
        {
            "category":"Health Services",
            "subcategory":"Doctor",
            "type":"Services"
        }
    ],
    "sg:phone":"+1 865 690 8890",
    "sg:postcode":"37923",
    "sg:province":"TN",
    "sg:tags":[
        "dentist"
    ],
    "wof:name":"Steve Jones DDS",
    "wof:placetype":"venue"
},
  "geometry": {"coordinates":[-84.066935,35.920556],"type":"Point"}
}