{
  "type": "Feature",
  "properties": {
    "iso:country":"US",
    "sg:address":"471 Old Hickory Blvd",
    "sg:city":"Brentwood",
    "sg:classifiers":[
        {
            "category":"Restaurant",
            "type":"Food & Drink"
        }
    ],
    "sg:menulink":"http://www.allmenus.com/tn/nashville/177824-jack-in-the-box/menu/",
    "sg:phone":"+1 615 331 1760",
    "sg:postcode":"37027",
    "sg:province":"TN",
    "sg:tags":[
        "burger",
        "american"
    ],
    "wof:name":"Jack in the Box",
    "wof:placetype":"venue"
},
  "geometry": {"coordinates":[-86.745659,36.040221],"type":"Point"}
}