{
  "type": "Feature",
  "properties": {
    "addr:full":"1401 E Riverwood Dr Nashville TN 37216",
    "addr:housenumber":"1401",
    "addr:postcode":"37216",
    "addr:street":"E Riverwood Dr",
    "iso:country":"US",
    "sg:address":"1401 E Riverwood Dr",
    "sg:city":"Nashville",
    "sg:classifiers":[
        {
            "category":"Professional",
            "type":"Services"
        }
    ],
    "sg:phone":"+1 615 227 3933",
    "sg:postcode":"37216",
    "sg:province":"TN",
    "wof:name":"Willie Ben Carter Music Inc",
    "wof:placetype":"venue"
},
  "geometry": {"coordinates":[-86.710807,36.219172],"type":"Point"}
}