{
  "type": "Feature",
  "properties": {
    "iso:country":"US",
    "sg:address":"350 S Lowry St",
    "sg:city":"Smyrna",
    "sg:classifiers":[
        {
            "category":"Restaurant",
            "type":"Food & Drink"
        }
    ],
    "sg:phone":"+1 615 223 8898",
    "sg:postcode":"37167",
    "sg:province":"TN",
    "sg:tags":[
        "eating"
    ],
    "wof:name":"Famous Chinese Restaurant",
    "wof:placetype":"venue"
},
  "geometry": {"coordinates":[-86.49619,35.957323],"type":"Point"}
}