{
  "type": "Feature",
  "properties": {
    "iso:country":"US",
    "sg:address":"345 N Ericson Dr",
    "sg:city":"Cordova",
    "sg:classifiers":[
        {
            "category":"Professional",
            "subcategory":"Art Services",
            "type":"Services"
        }
    ],
    "sg:phone":"+1 901 757 4563",
    "sg:postcode":"38018",
    "sg:province":"TN",
    "sg:tags":[
        "commercial",
        "design"
    ],
    "wof:name":"Shara Danziger",
    "wof:placetype":"venue"
},
  "geometry": {"coordinates":[-89.775858,35.134393],"type":"Point"}
}