{
  "type": "Feature",
  "properties": {
    "iso:country":"US",
    "sg:address":"1333 W Main St",
    "sg:city":"Lebanon",
    "sg:classifiers":[
        {
            "category":"Professional",
            "subcategory":"Accounting & Tax Preparation",
            "type":"Services"
        }
    ],
    "sg:phone":"+1 615 444 7545",
    "sg:postcode":"37087",
    "sg:province":"TN",
    "sg:tags":[
        "accountant"
    ],
    "wof:name":"Denny & Denny PC",
    "wof:placetype":"venue"
},
  "geometry": {"coordinates":[-86.326903,36.215071],"type":"Point"}
}