{
  "type": "Feature",
  "properties": {
    "iso:country":"US",
    "sg:address":"1407 N Locust Ave",
    "sg:city":"Lawrenceburg",
    "sg:classifiers":[
        {
            "category":"Health Services",
            "subcategory":"Doctor",
            "type":"Services"
        }
    ],
    "sg:phone":"+1 931 766 2110",
    "sg:postcode":"38464",
    "sg:province":"TN",
    "sg:tags":[
        "physician",
        "surgeon"
    ],
    "wof:name":"Frank J Chuck MD",
    "wof:placetype":"venue"
},
  "geometry": {"coordinates":[-87.32534800000001,35.25633],"type":"Point"}
}