{
  "type": "Feature",
  "properties": {
    "iso:country":"US",
    "sg:address":"215 Lynn Garden Dr",
    "sg:city":"Kingsport",
    "sg:classifiers":[
        {
            "category":"Building & Trades",
            "subcategory":"Equipment Rental",
            "type":"Services"
        }
    ],
    "sg:phone":"+1 423 245 6139",
    "sg:postcode":"37660",
    "sg:province":"TN",
    "sg:tags":[
        "general"
    ],
    "wof:name":"Kingsport Rental Center",
    "wof:placetype":"venue"
},
  "geometry": {"coordinates":[-82.57005700000001,36.552851],"type":"Point"}
}