{
  "type": "Feature",
  "properties": {
    "iso:country":"US",
    "sg:address":"303 Washington St",
    "sg:city":"Newbern",
    "sg:classifiers":[
        {
            "category":"Shopping",
            "subcategory":"Gifts & Souvenirs",
            "type":"Retail Goods"
        }
    ],
    "sg:phone":"+1 731 627 9823",
    "sg:postcode":"38059",
    "sg:province":"TN",
    "wof:name":"Southern Elegance",
    "wof:placetype":"venue"
},
  "geometry": {"coordinates":[-89.261538,36.117965],"type":"Point"}
}