{
  "type": "Feature",
  "properties": {
    "iso:country":"US",
    "sg:address":"1354 Sparta St",
    "sg:city":"Mc Minnville",
    "sg:classifiers":[
        {
            "category":"Restaurant",
            "type":"Food & Drink"
        }
    ],
    "sg:phone":"+1 931 473 4854",
    "sg:postcode":"37110",
    "sg:province":"TN",
    "sg:tags":[
        "eating"
    ],
    "wof:name":"Wendys",
    "wof:placetype":"venue"
},
  "geometry": {"coordinates":[-85.750899,35.693811],"type":"Point"}
}