{
  "type": "Feature",
  "properties": {
    "iso:country":"US",
    "sg:address":"2837 Farrisview Blvd",
    "sg:city":"Memphis",
    "sg:classifiers":[
        {
            "category":"Professional",
            "subcategory":"Detective & Security Services",
            "type":"Services"
        }
    ],
    "sg:phone":"+1 901 542 0068",
    "sg:postcode":"38118",
    "sg:province":"TN",
    "sg:tags":[
        "car"
    ],
    "wof:name":"Madison Armored Car",
    "wof:placetype":"venue"
},
  "geometry": {"coordinates":[-89.970195,35.076581],"type":"Point"}
}