{
  "type": "Feature",
  "properties": {
    "addr:full":"3455 US Hwy 45 N Henderson TN 38340",
    "addr:housenumber":"3455",
    "addr:postcode":"38340",
    "addr:street":"Us Hwy 45 N",
    "iso:country":"US",
    "sg:address":"3455 US Hwy 45 N",
    "sg:city":"Henderson",
    "sg:classifiers":[
        {
            "category":"Shopping",
            "subcategory":"Gifts & Souvenirs",
            "type":"Retail Goods"
        }
    ],
    "sg:phone":"+1 731 989 2643",
    "sg:postcode":"38340",
    "sg:province":"TN",
    "wof:name":"Ducks Market",
    "wof:placetype":"venue"
},
  "geometry": {"coordinates":[-88.68947,35.469537],"type":"Point"}
}