{
  "type": "Feature",
  "properties": {
    "iso:country":"US",
    "sg:address":"2191 Zion Rd",
    "sg:city":"Columbia",
    "sg:classifiers":[
        {
            "category":"Retail",
            "subcategory":"Animal Services",
            "type":"Services"
        }
    ],
    "sg:phone":"+1 931 388 8166",
    "sg:postcode":"38401",
    "sg:province":"TN",
    "wof:name":"Rummage Stables",
    "wof:placetype":"venue"
},
  "geometry": {"coordinates":[-87.14209,35.607909],"type":"Point"}
}