{
  "type": "Feature",
  "properties": {
    "iso:country":"US",
    "sg:address":"1423 Corinth Rd",
    "sg:city":"Mount Juliet",
    "sg:classifiers":[
        {
            "category":"Farming",
            "subcategory":"Farm",
            "type":"Manufacturing & Wholesale Goods"
        }
    ],
    "sg:phone":"+1 615 444 3847",
    "sg:postcode":"37122",
    "sg:province":"TN",
    "sg:tags":[
        "crop",
        "general"
    ],
    "wof:name":"Harvey Lackey",
    "wof:placetype":"venue"
},
  "geometry": {"coordinates":[-86.496938,36.100474],"type":"Point"}
}