{
  "type": "Feature",
  "properties": {
    "addr:full":"7463 Hickory Ridge Rd Mount Juliet TN 37122",
    "addr:housenumber":"7463",
    "addr:postcode":"37122",
    "addr:street":"Hickory Ridge Rd",
    "iso:country":"US",
    "sg:address":"7463 Hickory Ridge Rd",
    "sg:city":"Mount Juliet",
    "sg:classifiers":[
        {
            "category":"Organizations",
            "subcategory":"Religious Organization",
            "type":"Services"
        }
    ],
    "sg:phone":"+1 615 444 2390",
    "sg:postcode":"37122",
    "sg:province":"TN",
    "wof:name":"Mount Olive Baptist Church",
    "wof:placetype":"venue"
},
  "geometry": {"coordinates":[-86.425545,36.193047],"type":"Point"}
}