{
  "type": "Feature",
  "properties": {
    "addr:full":"2020 Hickory Hill Ln Hermitage TN 37076",
    "addr:housenumber":"2020",
    "addr:postcode":"37076",
    "addr:street":"Hickory Hill Ln",
    "iso:country":"US",
    "sg:address":"2020 Hickory Hill Ln",
    "sg:city":"Hermitage",
    "sg:classifiers":[
        {
            "category":"Food & Beverages",
            "subcategory":"Bakery",
            "type":"Retail Goods"
        }
    ],
    "sg:phone":"+1 615 871 9294",
    "sg:postcode":"37076",
    "sg:province":"TN",
    "wof:name":"Artistic Sweets",
    "wof:placetype":"venue"
},
  "geometry": {"coordinates":[-86.634142,36.193219],"type":"Point"}
}