{
  "type": "Feature",
  "properties": {
    "iso:country":"US",
    "sg:address":"262 N Church Ave",
    "sg:city":"Henderson",
    "sg:classifiers":[
        {
            "category":"Restaurant",
            "type":"Food & Drink"
        }
    ],
    "sg:phone":"+1 731 989 1975",
    "sg:postcode":"38340",
    "sg:province":"TN",
    "wof:name":"Gus's Fried Chicken",
    "wof:placetype":"venue"
},
  "geometry": {"coordinates":[-88.647648,35.440563],"type":"Point"}
}