{
  "type": "Feature",
  "properties": {
    "iso:country":"US",
    "sg:address":"6861 Standifer Gap Rd",
    "sg:city":"Chattanooga",
    "sg:classifiers":[
        {
            "category":"Retail",
            "subcategory":"Car Wash",
            "type":"Services"
        }
    ],
    "sg:phone":"+1 423 855 0420",
    "sg:postcode":"37421",
    "sg:province":"TN",
    "sg:tags":[
        "polishing",
        "washing"
    ],
    "wof:name":"Thompson's Auto Clean-Up",
    "wof:placetype":"venue"
},
  "geometry": {"coordinates":[-85.15427099999999,35.053858],"type":"Point"}
}