{
  "type": "Feature",
  "properties": {
    "iso:country":"US",
    "sg:address":"2354 US Hwy 41 S",
    "sg:city":"Greenbrier",
    "sg:classifiers":[
        {
            "category":"Retail",
            "subcategory":"Laundry & Dry Cleaning",
            "type":"Services"
        }
    ],
    "sg:phone":"+1 615 643 7730",
    "sg:postcode":"37073",
    "sg:province":"TN",
    "sg:tags":[
        "power"
    ],
    "wof:name":"Wash Tub",
    "wof:placetype":"venue"
},
  "geometry": {"coordinates":[-86.804154,36.425463],"type":"Point"}
}