{
  "type": "Feature",
  "properties": {
    "iso:country":"US",
    "sg:address":"590 S Barksdale St",
    "sg:city":"Memphis",
    "sg:classifiers":[
        {
            "category":"Professional",
            "subcategory":"Art Services",
            "type":"Services"
        }
    ],
    "sg:phone":"+1 901 274 6966",
    "sg:postcode":"38104",
    "sg:province":"TN",
    "sg:tags":[
        "photography",
        "commercial"
    ],
    "wof:name":"Steve Jones Photography",
    "wof:placetype":"venue"
},
  "geometry": {"coordinates":[-89.998091,35.12967],"type":"Point"}
}