{
  "type": "Feature",
  "properties": {
    "addr:full":"4232 Chesney Glen Dr Hermitage TN 37076",
    "addr:housenumber":"4232",
    "addr:postcode":"37076",
    "addr:street":"Chesney Glen Dr",
    "iso:country":"US",
    "sg:address":"4232 Chesney Glen Dr",
    "sg:city":"Hermitage",
    "sg:classifiers":[
        {
            "category":"Manufacturing",
            "subcategory":"Printing",
            "type":"Manufacturing & Wholesale Goods"
        }
    ],
    "sg:phone":"+1 615 885 2208",
    "sg:postcode":"37076",
    "sg:province":"TN",
    "sg:tags":[
        "multimedia"
    ],
    "wof:name":"Nvil Design Group",
    "wof:placetype":"venue"
},
  "geometry": {"coordinates":[-86.585441,36.188997],"type":"Point"}
}