{
  "type": "Feature",
  "properties": {
    "iso:country":"US",
    "sg:address":"2009 Lamar Ave",
    "sg:city":"Memphis",
    "sg:classifiers":[
        {
            "category":"Health Services",
            "subcategory":"Hospital",
            "type":"Services"
        }
    ],
    "sg:phone":"+1 901 726 6053",
    "sg:postcode":"38114",
    "sg:province":"TN",
    "sg:tags":[
        "mental"
    ],
    "wof:name":"Foundations Associates",
    "wof:placetype":"venue"
},
  "geometry": {"coordinates":[-89.995124,35.112672],"type":"Point"}
}