{
  "type": "Feature",
  "properties": {
    "iso:country":"US",
    "sg:address":"161 Summers Rd",
    "sg:city":"Maynardville",
    "sg:classifiers":[
        {
            "category":"Building & Trades",
            "subcategory":"Construction",
            "type":"Services"
        }
    ],
    "sg:phone":"+1 865 898 9267",
    "sg:postcode":"37807",
    "sg:province":"TN",
    "sg:tags":[
        "roofing",
        "contractor"
    ],
    "sg:website":"www.allensroofing.com",
    "wof:name":"Allen's Roofing",
    "wof:placetype":"venue"
},
  "geometry": {"coordinates":[-83.88422799999999,36.26054],"type":"Point"}
}