{
  "type": "Feature",
  "properties": {
    "addr:full":"6405 Hixson Pike Hixson TN 37343",
    "addr:housenumber":"6405",
    "addr:postcode":"37343",
    "addr:street":"Hixson Pike",
    "iso:country":"US",
    "sg:address":"6405 Hixson Pike",
    "sg:city":"Hixson",
    "sg:classifiers":[
        {
            "category":"Autos & Motor Vehicles",
            "subcategory":"Fuel & Gas Station",
            "type":"Retail Goods"
        }
    ],
    "sg:phone":"+1 423 843 9688",
    "sg:postcode":"37343",
    "sg:province":"TN",
    "sg:tags":[
        "convenience",
        "station"
    ],
    "wof:name":"Mr Zip",
    "wof:placetype":"venue"
},
  "geometry": {"coordinates":[-85.196242,35.157243],"type":"Point"}
}