{
  "type": "Feature",
  "properties": {
    "iso:country":"US",
    "sg:address":"3898 McCain Rd",
    "sg:city":"Memphis",
    "sg:classifiers":[
        {
            "category":"Organizations",
            "subcategory":"Religious Organization",
            "type":"Services"
        }
    ],
    "sg:phone":"+1 901 785 6363",
    "sg:postcode":"38109",
    "sg:province":"TN",
    "wof:name":"Unity Church Of God In Christ",
    "wof:placetype":"venue"
},
  "geometry": {"coordinates":[-90.07825,35.041152],"type":"Point"}
}