{
  "type": "Feature",
  "properties": {
    "iso:country":"US",
    "sg:address":"550 N Grundy Quarles Hwy",
    "sg:city":"Gainesboro",
    "sg:classifiers":[
        {
            "category":"Building & Trades",
            "subcategory":"Construction",
            "type":"Services"
        }
    ],
    "sg:phone":"+1 931 268 0773",
    "sg:postcode":"38562",
    "sg:province":"TN",
    "sg:tags":[
        "general",
        "contractor"
    ],
    "wof:name":"Carwile Enterprises Inc",
    "wof:placetype":"venue"
},
  "geometry": {"coordinates":[-85.651459,36.365703],"type":"Point"}
}