{
  "type": "Feature",
  "properties": {
    "iso:country":"US",
    "sg:address":"1409 Jones Ave",
    "sg:city":"Nashville",
    "sg:classifiers":[
        {
            "category":"Place Of Worship",
            "subcategory":"Church",
            "type":"Public Place"
        },
        {
            "category":"Place Of Worship",
            "type":"Public Place"
        }
    ],
    "sg:phone":"+1 615 226 3339",
    "sg:postcode":"37207",
    "sg:province":"TN",
    "sg:tags":[
        "churches-baptist-general",
        "churches-baptist-missionary",
        "churches-baptist"
    ],
    "wof:name":"Zion Springs Missionary Baptist Church",
    "wof:placetype":"venue"
},
  "geometry": {"coordinates":[-86.759111,36.196354],"type":"Point"}
}