{
  "type": "Feature",
  "properties": {
    "addr:full":"2078 Shrum Cemetery Rd Westmoreland TN 37186",
    "addr:housenumber":"2078",
    "addr:postcode":"37186",
    "addr:street":"Shrum Cemetery Rd",
    "iso:country":"US",
    "sg:address":"2078 Shrum Cemetery Rd",
    "sg:city":"Westmoreland",
    "sg:classifiers":[
        {
            "category":"Building & Trades",
            "subcategory":"Landscaping Services",
            "type":"Services"
        }
    ],
    "sg:phone":"+1 615 666 7688",
    "sg:postcode":"37186",
    "sg:province":"TN",
    "sg:tags":[
        "tree"
    ],
    "wof:name":"Terry Lee Rollin Tree Svc",
    "wof:placetype":"venue"
},
  "geometry": {"coordinates":[-86.160996,36.553045],"type":"Point"}
}