{
  "type": "Feature",
  "properties": {
    "iso:country":"US",
    "sg:address":"6955 Westerly Winds Rd",
    "sg:city":"Knoxville",
    "sg:classifiers":[
        {
            "category":"Building & Trades",
            "subcategory":"Landscaping Services",
            "type":"Services"
        }
    ],
    "sg:phone":"+1 865 938 0264",
    "sg:postcode":"37931",
    "sg:province":"TN",
    "sg:tags":[
        "landscape"
    ],
    "wof:name":"Kennedy Lawnscapes LLC",
    "wof:placetype":"venue"
},
  "geometry": {"coordinates":[-84.104271,35.987689],"type":"Point"}
}