{
  "type": "Feature",
  "properties": {
    "addr:full":"613 E Meeting St Dandridge TN 37725",
    "addr:housenumber":"613",
    "addr:postcode":"37725",
    "addr:street":"E Meeting St",
    "iso:country":"US",
    "sg:address":"613 E Meeting St",
    "sg:city":"Dandridge",
    "sg:classifiers":[
        {
            "category":"Building & Trades",
            "subcategory":"Construction",
            "type":"Services"
        }
    ],
    "sg:phone":"+1 865 397 3822",
    "sg:postcode":"37725",
    "sg:province":"TN",
    "sg:tags":[
        "general",
        "contractor"
    ],
    "wof:name":"Mc Spadden Inc",
    "wof:placetype":"venue"
},
  "geometry": {"coordinates":[-83.395977,36.028725],"type":"Point"}
}