{
  "type": "Feature",
  "properties": {
    "iso:country":"US",
    "sg:address":"5319 Nolensville Pike",
    "sg:city":"Nashville",
    "sg:classifiers":[
        {
            "category":"Real Estate",
            "subcategory":"Real Estate Operator",
            "type":"Services"
        }
    ],
    "sg:phone":"+1 615 832 9430",
    "sg:postcode":"37211",
    "sg:province":"TN",
    "sg:tags":[
        "building",
        "apartment"
    ],
    "wof:name":"Hickory Woods Apartments",
    "wof:placetype":"venue"
},
  "geometry": {"coordinates":[-86.714466,36.051644],"type":"Point"}
}