{
  "type": "Feature",
  "properties": {
    "addr:full":"2169 Hurricane Creek Rd Mc Ewen TN 37101",
    "addr:housenumber":"2169",
    "addr:postcode":"37101",
    "addr:street":"Hurricane Creek Rd",
    "iso:country":"US",
    "sg:address":"2169 Hurricane Creek Rd",
    "sg:city":"Mc Ewen",
    "sg:classifiers":[
        {
            "category":"Building & Trades",
            "subcategory":"Construction",
            "type":"Services"
        }
    ],
    "sg:phone":"+1 931 296 1989",
    "sg:postcode":"37101",
    "sg:province":"TN",
    "sg:tags":[
        "contractor"
    ],
    "wof:name":"Patterson Siding & Trim",
    "wof:placetype":"venue"
},
  "geometry": {"coordinates":[-87.708404,36.020301],"type":"Point"}
}