{
  "type": "Feature",
  "properties": {
    "addr:full":"516 Tennessee St Memphis TN 38103",
    "addr:housenumber":"516",
    "addr:postcode":"38103",
    "addr:street":"Tennessee St",
    "iso:country":"US",
    "sg:address":"516 Tennessee St",
    "sg:city":"Memphis",
    "sg:classifiers":[
        {
            "category":"Professional",
            "subcategory":"Computer Services",
            "type":"Services"
        }
    ],
    "sg:phone":"+1 901 312 7705",
    "sg:postcode":"38103",
    "sg:province":"TN",
    "sg:tags":[
        "consulting",
        "management",
        "design",
        "system"
    ],
    "wof:name":"Extra Large Media",
    "wof:placetype":"venue"
},
  "geometry": {"coordinates":[-90.062484,35.133417],"type":"Point"}
}