{
  "type": "Feature",
  "properties": {
    "iso:country":"US",
    "sg:address":"759 Vixen Run",
    "sg:city":"Gatlinburg",
    "sg:classifiers":[
        {
            "category":"Professional",
            "subcategory":"Engineering",
            "type":"Services"
        }
    ],
    "sg:phone":"+1 865 436 0302",
    "sg:postcode":"37738",
    "sg:province":"TN",
    "wof:name":"Seres Group Pllc",
    "wof:placetype":"venue"
},
  "geometry": {"coordinates":[-83.342297,35.770018],"type":"Point"}
}