{
  "type": "Feature",
  "properties": {
    "iso:country":"US",
    "sg:address":"9517 Continental Dr",
    "sg:city":"Knoxville",
    "sg:classifiers":[
        {
            "category":"Building & Trades",
            "subcategory":"Construction",
            "type":"Services"
        }
    ],
    "sg:phone":"+1 865 531 0986",
    "sg:postcode":"37922",
    "sg:province":"TN",
    "sg:tags":[
        "residential",
        "house"
    ],
    "wof:name":"Tabor Construction Inc",
    "wof:placetype":"venue"
},
  "geometry": {"coordinates":[-84.09381500000001,35.897741],"type":"Point"}
}