{
  "type": "Feature",
  "properties": {
    "iso:country":"US",
    "sg:address":"2572 Memorial Blvd",
    "sg:city":"Springfield",
    "sg:classifiers":[
        {
            "category":"Personal",
            "subcategory":"Beauty Salon",
            "type":"Services"
        }
    ],
    "sg:phone":"+1 615 382 9188",
    "sg:postcode":"37172",
    "sg:province":"TN",
    "sg:tags":[
        "shop"
    ],
    "sg:website":"www.greatclips.com",
    "wof:name":"Great Clips",
    "wof:placetype":"venue"
},
  "geometry": {"coordinates":[-86.865809,36.488033],"type":"Point"}
}