{
  "type": "Feature",
  "properties": {
    "iso:country":"US",
    "sg:address":"4502 McCahill Rd",
    "sg:city":"Chattanooga",
    "sg:classifiers":[
        {
            "category":"Professional",
            "type":"Services"
        }
    ],
    "sg:phone":"+1 423 875 2975",
    "sg:postcode":"37415",
    "sg:province":"TN",
    "wof:name":"Shipleys Home Improvments",
    "wof:placetype":"venue"
},
  "geometry": {"coordinates":[-85.286974,35.134093],"type":"Point"}
}