{
  "type": "Feature",
  "properties": {
    "addr:full":"210 Cedar Ln NE Knoxville TN 37912",
    "addr:housenumber":"210",
    "addr:postcode":"37912",
    "addr:street":"Cedar Ln Ne",
    "iso:country":"US",
    "sg:address":"210 Cedar Ln NE",
    "sg:city":"Knoxville",
    "sg:classifiers":[
        {
            "category":"Real Estate",
            "subcategory":"Real Estate Agent",
            "type":"Services"
        }
    ],
    "sg:phone":"+1 865 688 7400",
    "sg:postcode":"37912",
    "sg:province":"TN",
    "wof:name":"Curtis Ward Properties",
    "wof:placetype":"venue"
},
  "geometry": {"coordinates":[-83.96702999999999,36.01521],"type":"Point"}
}