{
  "type": "Feature",
  "properties": {
    "addr:full":"901 W Walnut St Johnson City TN 37604",
    "addr:housenumber":"901",
    "addr:postcode":"37604",
    "addr:street":"W Walnut St",
    "iso:country":"US",
    "sg:address":"901 W Walnut St",
    "sg:city":"Johnson City",
    "sg:classifiers":[
        {
            "category":"Food & Beverages",
            "subcategory":"Groceries & Convenience Stores",
            "type":"Retail Goods"
        }
    ],
    "sg:phone":"+1 423 929 1061",
    "sg:postcode":"37604",
    "sg:province":"TN",
    "wof:name":"Mountain Imperial",
    "wof:placetype":"venue"
},
  "geometry": {"coordinates":[-82.367313,36.306035],"type":"Point"}
}