{
  "type": "Feature",
  "properties": {
    "iso:country":"US",
    "sg:address":"631 US Hwy 25-70",
    "sg:city":"Newport",
    "sg:classifiers":[
        {
            "category":"Banks & Credit Unions",
            "subcategory":"Bank",
            "type":"Services"
        }
    ],
    "sg:phone":"+1 423 625 2077",
    "sg:postcode":"37821",
    "sg:province":"TN",
    "sg:tags":[
        "loan"
    ],
    "wof:name":"Newport Pawn Shop",
    "wof:placetype":"venue"
},
  "geometry": {"coordinates":[-83.212086,35.972106],"type":"Point"}
}