{
  "type": "Feature",
  "properties": {
    "iso:country":"US",
    "sg:address":"23 Weatherford Sq",
    "sg:city":"Jackson",
    "sg:classifiers":[
        {
            "category":"Manufacturing",
            "subcategory":"Tools & Machinery",
            "type":"Manufacturing & Wholesale Goods"
        }
    ],
    "sg:phone":"+1 731 234 1383",
    "sg:postcode":"38305",
    "sg:province":"TN",
    "sg:tags":[
        "textile",
        "mfg"
    ],
    "wof:name":"Busy Bees",
    "wof:placetype":"venue"
},
  "geometry": {"coordinates":[-88.840126,35.667031],"type":"Point"}
}