{
  "type": "Feature",
  "properties": {
    "iso:country":"US",
    "sg:address":"6472 Winchester Rd",
    "sg:city":"Memphis",
    "sg:classifiers":[
        {
            "category":"Utilities",
            "subcategory":"Mobile Phone",
            "type":"Services"
        }
    ],
    "sg:phone":"+1 901 370 6200",
    "sg:postcode":"38115",
    "sg:province":"TN",
    "sg:tags":[
        "equipment",
        "paging",
        "signaling",
        "cellular",
        "telephone"
    ],
    "sg:website":"http://www.t-mobile.com",
    "wof:name":"T-Mobile",
    "wof:placetype":"venue"
},
  "geometry": {"coordinates":[-89.846802,35.049568],"type":"Point"}
}