{
  "type": "Feature",
  "properties": {
    "iso:country":"US",
    "sg:address":"385 W Lincoln St",
    "sg:city":"Tullahoma",
    "sg:classifiers":[
        {
            "category":"Professional",
            "type":"Services"
        }
    ],
    "sg:phone":"+1 931 455 5784",
    "sg:postcode":"37388",
    "sg:province":"TN",
    "sg:tags":[
        "establishment"
    ],
    "wof:name":"Cybergnostic Group",
    "wof:placetype":"venue"
},
  "geometry": {"coordinates":[-86.215321,35.359088],"type":"Point"}
}