{
  "type": "Feature",
  "properties": {
    "iso:country":"US",
    "sg:address":"1728 Covey Rise Trl",
    "sg:city":"Concord Farragut",
    "sg:classifiers":[
        {
            "category":"Retail",
            "subcategory":"Portrait Studio",
            "type":"Services"
        }
    ],
    "sg:phone":"+1 865 671 1880",
    "sg:postcode":"37922",
    "sg:province":"TN",
    "sg:tags":[
        "personal",
        "photographer",
        "photo"
    ],
    "sg:website":"www.joansmithphotography.com",
    "wof:name":"Joan Smith Photography",
    "wof:placetype":"venue"
},
  "geometry": {"coordinates":[-84.108558,35.863213],"type":"Point"}
}