{
  "type": "Feature",
  "properties": {
    "iso:country":"US",
    "sg:address":"173 Luna Ln",
    "sg:city":"Hendersonville",
    "sg:classifiers":[
        {
            "category":"Government",
            "subcategory":"Fire Station",
            "type":"Public Place"
        }
    ],
    "sg:phone":"+1 615 264 5350",
    "sg:postcode":"37075",
    "sg:province":"TN",
    "sg:tags":[
        "department"
    ],
    "wof:name":"Hendersonville Fire Station",
    "wof:placetype":"venue"
},
  "geometry": {"coordinates":[-86.618723,36.279801],"type":"Point"}
}