{
  "type": "Feature",
  "properties": {
    "iso:country":"US",
    "sg:address":"6399 Shelby View Dr",
    "sg:city":"Memphis",
    "sg:classifiers":[
        {
            "category":"Real Estate",
            "subcategory":"Real Estate Services",
            "type":"Services"
        },
        {
            "category":"Building & Trades",
            "subcategory":"Cleaning & Sanitation",
            "type":"Services"
        }
    ],
    "sg:phone":"+1 901 385 8989",
    "sg:postcode":"38134",
    "sg:province":"TN",
    "sg:tags":[
        "janitorial",
        "maintenance"
    ],
    "sg:website":"http://www.servicemasterclean.com/",
    "wof:name":"Service Master Clean",
    "wof:placetype":"venue"
},
  "geometry": {"coordinates":[-89.850661,35.176772],"type":"Point"}
}