{
  "type": "Feature",
  "properties": {
    "iso:country":"US",
    "sg:address":"2006 Wayne Rd",
    "sg:city":"Savannah",
    "sg:classifiers":[
        {
            "category":"Health Services",
            "subcategory":"Hospital",
            "type":"Services"
        }
    ],
    "sg:phone":"+1 731 925 4954",
    "sg:postcode":"38372",
    "sg:province":"TN",
    "wof:name":"Hardin County Hospital",
    "wof:placetype":"venue"
},
  "geometry": {"coordinates":[-88.230459,35.227209],"type":"Point"}
}