{
  "type": "Feature",
  "properties": {
    "iso:country":"US",
    "sg:address":"7620 Crestland Rd",
    "sg:city":"Knoxville",
    "sg:classifiers":[
        {
            "category":"Shopping",
            "subcategory":"Hobbies, Toys, & Games",
            "type":"Retail Goods"
        }
    ],
    "sg:phone":"+1 865 938 2852",
    "sg:postcode":"37938",
    "sg:province":"TN",
    "wof:name":"Sergent Engineering",
    "wof:placetype":"venue"
},
  "geometry": {"coordinates":[-83.980431,36.063662],"type":"Point"}
}