{
  "type": "Feature",
  "properties": {
    "addr:full":"235 Buffalo Valley Rd Cookeville TN 38501",
    "addr:housenumber":"235",
    "addr:postcode":"38501",
    "addr:street":"Buffalo Valley Rd",
    "iso:country":"US",
    "sg:address":"235 Buffalo Valley Rd",
    "sg:city":"Cookeville",
    "sg:classifiers":[
        {
            "category":"Building & Trades",
            "subcategory":"Electrical",
            "type":"Services"
        }
    ],
    "sg:phone":"+1 931 526 0274",
    "sg:postcode":"38501",
    "sg:province":"TN",
    "sg:tags":[
        "contractor"
    ],
    "wof:name":"B & C Plumbing & Electrical Co",
    "wof:placetype":"venue"
},
  "geometry": {"coordinates":[-85.511719,36.161173],"type":"Point"}
}