{
  "type": "Feature",
  "properties": {
    "iso:country":"US",
    "sg:address":"6985 Rose Trail Dr",
    "sg:city":"Memphis",
    "sg:classifiers":[
        {
            "category":"Professional",
            "type":"Services"
        }
    ],
    "sg:phone":"+1 901 373 6243",
    "sg:postcode":"38133",
    "sg:province":"TN",
    "sg:tags":[
        "residential",
        "commercial",
        "painting"
    ],
    "wof:name":"Point of Vue",
    "wof:placetype":"venue"
},
  "geometry": {"coordinates":[-89.828763,35.183806],"type":"Point"}
}