{
  "type": "Feature",
  "properties": {
    "iso:country":"US",
    "sg:address":"600 S Perkins Rd",
    "sg:city":"Memphis",
    "sg:classifiers":[
        {
            "category":"Professional",
            "subcategory":"Management & Consulting",
            "type":"Services"
        },
        {
            "category":"Health Services",
            "subcategory":"Nursing And Care Facility",
            "type":"Services"
        },
        {
            "category":"Banks & Credit Unions",
            "subcategory":"Financial Services",
            "type":"Services"
        },
        {
            "category":"Social Services",
            "subcategory":"Adult Care",
            "type":"Services"
        }
    ],
    "sg:phone":"+1 901 766 0905",
    "sg:postcode":"38117",
    "sg:province":"TN",
    "sg:tags":[
        "living",
        "financing",
        "planner",
        "consultant",
        "assisted",
        "rest",
        "elder",
        "planning",
        "home"
    ],
    "wof:name":"Delta Estate & Retirement Planning Group Inc",
    "wof:placetype":"venue"
},
  "geometry": {"coordinates":[-89.907471,35.114941],"type":"Point"}
}