{
  "type": "Feature",
  "properties": {
    "addr:full":"176 Roberta Dr Hendersonville TN 37075",
    "addr:housenumber":"176",
    "addr:postcode":"37075",
    "addr:street":"Roberta Dr",
    "iso:country":"US",
    "sg:address":"176 Roberta Dr",
    "sg:city":"Hendersonville",
    "sg:classifiers":[
        {
            "category":"Building & Trades",
            "subcategory":"Landscaping Services",
            "type":"Services"
        }
    ],
    "sg:phone":"+1 615 826 3866",
    "sg:postcode":"37075",
    "sg:province":"TN",
    "sg:tags":[
        "lawn",
        "maintenance",
        "grounds"
    ],
    "wof:name":"Craig's Lawn Svc",
    "wof:placetype":"venue"
},
  "geometry": {"coordinates":[-86.624923,36.254366],"type":"Point"}
}