{
  "type": "Feature",
  "properties": {
    "iso:country":"US",
    "sg:address":"4448 Weaver Rd",
    "sg:city":"Memphis",
    "sg:classifiers":[
        {
            "category":"Organizations",
            "subcategory":"Religious Organization",
            "type":"Services"
        }
    ],
    "sg:phone":"+1 901 789 4160",
    "sg:postcode":"38109",
    "sg:province":"TN",
    "sg:tags":[
        "church"
    ],
    "wof:name":"New Hope Pentecostal Holiness",
    "wof:placetype":"venue"
},
  "geometry": {"coordinates":[-90.09676399999999,35.025304],"type":"Point"}
}