{
  "type": "Feature",
  "properties": {
    "iso:country":"US",
    "sg:address":"262 Peachtree Cir",
    "sg:city":"Cleveland",
    "sg:classifiers":[
        {
            "category":"Food & Beverages",
            "subcategory":"Specialty",
            "type":"Retail Goods"
        }
    ],
    "sg:phone":"+1 423 478 5418",
    "sg:postcode":"37323",
    "sg:province":"TN",
    "sg:tags":[
        "water",
        "bulk",
        "company"
    ],
    "wof:name":"Appalachian Springs Water Svc",
    "wof:placetype":"venue"
},
  "geometry": {"coordinates":[-84.80649,35.168334],"type":"Point"}
}