{
  "type": "Feature",
  "properties": {
    "addr:full":"1527 22nd Ave N Nashville TN 37208",
    "addr:housenumber":"1527",
    "addr:postcode":"37208",
    "addr:street":"22Nd Ave N",
    "iso:country":"US",
    "sg:address":"1527 22nd Ave N",
    "sg:city":"Nashville",
    "sg:classifiers":[
        {
            "category":"Professional",
            "subcategory":"Business Services",
            "type":"Services"
        }
    ],
    "sg:phone":"+1 615 596 1229",
    "sg:postcode":"37208",
    "sg:province":"TN",
    "sg:tags":[
        "recording",
        "studio"
    ],
    "wof:name":"Murder Face Records",
    "wof:placetype":"venue"
},
  "geometry": {"coordinates":[-86.811959,36.174039],"type":"Point"}
}