{
  "type": "Feature",
  "properties": {
    "iso:country":"US",
    "sg:address":"3391 US Hwy 41A S",
    "sg:city":"Clarksville",
    "sg:classifiers":[
        {
            "category":"Real Estate",
            "subcategory":"Real Estate Agent",
            "type":"Services"
        }
    ],
    "sg:phone":"+1 931 358 0500",
    "sg:postcode":"37043",
    "sg:province":"TN",
    "wof:name":"Century 21 Real Estate Corpora",
    "wof:placetype":"venue"
},
  "geometry": {"coordinates":[-87.22201099999999,36.496619],"type":"Point"}
}