{
  "type": "Feature",
  "properties": {
    "addr:full":"330 Rockland Rd Hendersonville TN 37075",
    "addr:housenumber":"330",
    "addr:postcode":"37075",
    "addr:street":"Rockland Rd",
    "iso:country":"US",
    "sg:address":"330 Rockland Rd",
    "sg:city":"Hendersonville",
    "sg:classifiers":[
        {
            "category":"Professional",
            "type":"Services"
        }
    ],
    "sg:phone":"+1 615 826 8755",
    "sg:postcode":"37075",
    "sg:province":"TN",
    "wof:name":"Prime Tyme Athletics",
    "wof:placetype":"venue"
},
  "geometry": {"coordinates":[-86.650943,36.302738],"type":"Point"}
}