{
  "type": "Feature",
  "properties": {
    "iso:country":"US",
    "sg:address":"6209 Old Rutledge Pike",
    "sg:city":"Knoxville",
    "sg:classifiers":[
        {
            "category":"Manufacturing",
            "subcategory":"Glass & Minerals",
            "type":"Manufacturing & Wholesale Goods"
        }
    ],
    "sg:phone":"+1 865 546 0870",
    "sg:postcode":"37924",
    "sg:province":"TN",
    "sg:tags":[
        "concrete",
        "product",
        "metal",
        "s",
        "mfg"
    ],
    "sg:website":"www.shermandixie.com",
    "wof:name":"Sherman-Dixie Concrete Inds",
    "wof:placetype":"venue"
},
  "geometry": {"coordinates":[-83.837278,36.028154],"type":"Point"}
}