{
  "type": "Feature",
  "properties": {
    "iso:country":"US",
    "sg:address":"3071 McDaris Cir",
    "sg:city":"Cleveland",
    "sg:classifiers":[
        {
            "category":"Freight",
            "type":"Transportation"
        }
    ],
    "sg:phone":"+1 423 559 8313",
    "sg:postcode":"37323",
    "sg:province":"TN",
    "sg:tags":[
        "trucking"
    ],
    "wof:name":"Service Trucking Co",
    "wof:placetype":"venue"
},
  "geometry": {"coordinates":[-84.869365,35.120826],"type":"Point"}
}