{
  "type": "Feature",
  "properties": {
    "iso:country":"US",
    "sg:address":"415 Lillard Rd",
    "sg:city":"Murfreesboro",
    "sg:classifiers":[
        {
            "category":"Education",
            "subcategory":"Special Training",
            "type":"Public Place"
        }
    ],
    "sg:phone":"+1 615 895 3400",
    "sg:postcode":"37130",
    "sg:province":"TN",
    "sg:tags":[
        "educational"
    ],
    "wof:name":"Jubilee Educational Services",
    "wof:placetype":"venue"
},
  "geometry": {"coordinates":[-86.346327,35.848429],"type":"Point"}
}