{
  "type": "Feature",
  "properties": {
    "addr:full":"822 Riverside Cir Celina TN 38551",
    "addr:housenumber":"822",
    "addr:postcode":"38551",
    "addr:street":"Riverside Cir",
    "iso:country":"US",
    "sg:address":"822 Riverside Cir",
    "sg:city":"Celina",
    "sg:classifiers":[
        {
            "category":"Wholesale",
            "subcategory":"Non-durable Goods",
            "type":"Manufacturing & Wholesale Goods"
        }
    ],
    "sg:phone":"+1 931 243 2872",
    "sg:postcode":"38551",
    "sg:province":"TN",
    "wof:name":"Grammy's Gifts",
    "wof:placetype":"venue"
},
  "geometry": {"coordinates":[-85.491556,36.545977],"type":"Point"}
}