{
  "type": "Feature",
  "properties": {
    "iso:country":"US",
    "sg:address":"2029 Cookeville Hwy",
    "sg:city":"Livingston",
    "sg:classifiers":[
        {
            "category":"Government",
            "subcategory":"Office",
            "type":"Public Place"
        }
    ],
    "sg:phone":"+1 931 823 5333",
    "sg:postcode":"38570",
    "sg:province":"TN",
    "sg:tags":[
        "federal",
        "security"
    ],
    "wof:name":"US Army National Guard",
    "wof:placetype":"venue"
},
  "geometry": {"coordinates":[-85.344759,36.350442],"type":"Point"}
}