{
  "type": "Feature",
  "properties": {
    "iso:country":"US",
    "sg:address":"4021 Dorcas Ct",
    "sg:city":"Nashville",
    "sg:classifiers":[
        {
            "category":"Wholesale",
            "subcategory":"Apparel",
            "type":"Manufacturing & Wholesale Goods"
        }
    ],
    "sg:phone":"+1 615 269 9728",
    "sg:postcode":"37215",
    "sg:province":"TN",
    "sg:tags":[
        "clothing"
    ],
    "wof:name":"S T B Designs",
    "wof:placetype":"venue"
},
  "geometry": {"coordinates":[-86.841762,36.104984],"type":"Point"}
}