{
  "type": "Feature",
  "properties": {
    "addr:full":"8631 Cedar Farms Dr Cordova TN 38016",
    "addr:housenumber":"8631",
    "addr:postcode":"38016",
    "addr:street":"Cedar Farms Dr",
    "iso:country":"US",
    "sg:address":"8631 Cedar Farms Dr",
    "sg:city":"Cordova",
    "sg:classifiers":[
        {
            "category":"Professional",
            "subcategory":"Management & Consulting",
            "type":"Services"
        }
    ],
    "sg:phone":"+1 901 757 4123",
    "sg:postcode":"38016",
    "sg:province":"TN",
    "wof:name":"Five Star Htl Management Co",
    "wof:placetype":"venue"
},
  "geometry": {"coordinates":[-89.776061,35.168089],"type":"Point"}
}