{
  "type": "Feature",
  "properties": {
    "iso:country":"US",
    "sg:address":"3183 Thomas St",
    "sg:city":"Memphis",
    "sg:classifiers":[
        {
            "category":"Autos & Motor Vehicles",
            "subcategory":"Automobile Sales",
            "type":"Retail Goods"
        }
    ],
    "sg:phone":"+1 901 357 2800",
    "sg:postcode":"38127",
    "sg:province":"TN",
    "sg:tags":[
        "car",
        "used",
        "dealer"
    ],
    "wof:name":"J & D Quality Cars Inc",
    "wof:placetype":"venue"
},
  "geometry": {"coordinates":[-90.032264,35.212218],"type":"Point"}
}