{
  "type": "Feature",
  "properties": {
    "iso:country":"US",
    "sg:address":"647 Madison Ave",
    "sg:city":"Memphis",
    "sg:classifiers":[
        {
            "category":"Retail",
            "subcategory":"Repair Shop",
            "type":"Services"
        },
        {
            "category":"Wholesale",
            "subcategory":"Electrical",
            "type":"Manufacturing & Wholesale Goods"
        }
    ],
    "sg:phone":"+1 901 527 7543",
    "sg:postcode":"38103",
    "sg:province":"TN",
    "sg:tags":[
        "supply",
        "rep",
        "restaurant",
        "commercial",
        "equipment",
        "equipment-repair"
    ],
    "wof:name":"Camp Electric Company Inc",
    "wof:placetype":"venue"
},
  "geometry": {"coordinates":[-90.03927400000001,35.141574],"type":"Point"}
}