{
  "type": "Feature",
  "properties": {
    "addr:full":"1664 Elderberry Ln Cordova TN 38016",
    "addr:housenumber":"1664",
    "addr:postcode":"38016",
    "addr:street":"Elderberry Ln",
    "iso:country":"US",
    "sg:address":"1664 Elderberry Ln",
    "sg:city":"Cordova",
    "sg:classifiers":[
        {
            "category":"Personal",
            "subcategory":"Beauty Salon",
            "type":"Services"
        }
    ],
    "sg:phone":"+1 901 751 5304",
    "sg:postcode":"38016",
    "sg:province":"TN",
    "sg:tags":[
        "hair"
    ],
    "wof:name":"Yanceys Full Svc Hair Salon",
    "wof:placetype":"venue"
},
  "geometry": {"coordinates":[-89.762766,35.170824],"type":"Point"}
}