{
  "type": "Feature",
  "properties": {
    "iso:country":"US",
    "sg:address":"4343 Taylors Valley Rd",
    "sg:city":"Laurel Bloomery",
    "sg:classifiers":[
        {
            "category":"Building & Trades",
            "subcategory":"Construction",
            "type":"Services"
        }
    ],
    "sg:phone":"+1 423 727 7791",
    "sg:postcode":"37680",
    "sg:province":"TN",
    "sg:tags":[
        "house"
    ],
    "wof:name":"Sugar Creek Construction",
    "wof:placetype":"venue"
},
  "geometry": {"coordinates":[-81.71931499999999,36.603721],"type":"Point"}
}