{
  "type": "Feature",
  "properties": {
    "addr:full":"9701 Kingston Pike Knoxville TN 37922",
    "addr:housenumber":"9701",
    "addr:postcode":"37922",
    "addr:street":"Kingston Pike",
    "iso:country":"US",
    "sg:address":"9701 Kingston Pike",
    "sg:city":"Knoxville",
    "sg:classifiers":[
        {
            "category":"Professional",
            "subcategory":"Lawyer & Legal Services",
            "type":"Services"
        }
    ],
    "sg:phone":"+1 865 531 6440",
    "sg:postcode":"37922",
    "sg:province":"TN",
    "sg:tags":[
        "attorney"
    ],
    "wof:name":"Terry G Adams Jr Atty At Law",
    "wof:placetype":"venue"
},
  "geometry": {"coordinates":[-84.10946800000001,35.906282],"type":"Point"}
}