{
  "type": "Feature",
  "properties": {
    "addr:full":"1626 Downtown West Blvd Knoxville TN 37919",
    "addr:postcode":"37919",
    "addr:street":"Downtown West Blvd",
    "iso:country":"US",
    "sg:address":"1626 Downtown West Blvd",
    "sg:city":"Knoxville",
    "sg:classifiers":[
        {
            "category":"Professional",
            "subcategory":"Computer Services",
            "type":"Services"
        }
    ],
    "sg:phone":"+1 865 691 7859",
    "sg:postcode":"37919",
    "sg:province":"TN",
    "sg:tags":[
        "resellers",
        "added",
        "system",
        "value",
        "integration"
    ],
    "wof:name":"Moderntech Si",
    "wof:placetype":"venue"
},
  "geometry": {"coordinates":[-84.051018,35.920935],"type":"Point"}
}