{
  "type": "Feature",
  "properties": {
    "iso:country":"US",
    "sg:address":"5098 Rugby Hwy",
    "sg:city":"Robbins",
    "sg:classifiers":[
        {
            "category":"Organizations",
            "subcategory":"Community Association",
            "type":"Services"
        }
    ],
    "sg:phone":"+1 423 627 2941",
    "sg:postcode":"37852",
    "sg:province":"TN",
    "wof:name":"Big South Fork Amateur Radio C",
    "wof:placetype":"venue"
},
  "geometry": {"coordinates":[-84.679717,36.347501],"type":"Point"}
}