{
  "type": "Feature",
  "properties": {
    "addr:full":"2667 Clayton Arnold Rd Thompsons Station TN 37179",
    "addr:housenumber":"2667",
    "addr:postcode":"37179",
    "addr:street":"Clayton Arnold Rd",
    "iso:country":"US",
    "sg:address":"2667 Clayton Arnold Rd",
    "sg:city":"Thompsons Station",
    "sg:classifiers":[
        {
            "category":"Professional",
            "type":"Services"
        }
    ],
    "sg:phone":"+1 615 790 1970",
    "sg:postcode":"37179",
    "sg:province":"TN",
    "wof:name":"Terry L Poteet Jr",
    "wof:placetype":"venue"
},
  "geometry": {"coordinates":[-86.878355,35.804525],"type":"Point"}
}