{
  "type": "Feature",
  "properties": {
    "iso:country":"US",
    "sg:address":"225 N Lindell St",
    "sg:city":"Martin",
    "sg:classifiers":[
        {
            "category":"Personal",
            "subcategory":"Beauty Salon",
            "type":"Services"
        }
    ],
    "sg:phone":"+1 731 588 2694",
    "sg:postcode":"38237",
    "sg:province":"TN",
    "wof:name":"Mane Attractions",
    "wof:placetype":"venue"
},
  "geometry": {"coordinates":[-88.849144,36.350798],"type":"Point"}
}