{
  "type": "Feature",
  "properties": {
    "addr:full":"5740 Uptain Rd Chattanooga TN 37411",
    "addr:housenumber":"5740",
    "addr:postcode":"37411",
    "addr:street":"Uptain Rd",
    "iso:country":"US",
    "sg:address":"5740 Uptain Rd",
    "sg:city":"Chattanooga",
    "sg:classifiers":[
        {
            "category":"Health Services",
            "subcategory":"Health Practitioner",
            "type":"Services"
        },
        {
            "category":"Health Services",
            "subcategory":"Hospice",
            "type":"Services"
        }
    ],
    "sg:phone":"+1 423 855 5797",
    "sg:postcode":"37411",
    "sg:province":"TN",
    "sg:tags":[
        "home"
    ],
    "wof:name":"Home Health Care Of East Tennessee",
    "wof:placetype":"venue"
},
  "geometry": {"coordinates":[-85.211338,35.009522],"type":"Point"}
}