{
  "type": "Feature",
  "properties": {
    "addr:full":"5603 Carters Valley Rd Church Hill TN 37642",
    "addr:housenumber":"5603",
    "addr:postcode":"37642",
    "addr:street":"Carters Valley Rd",
    "iso:country":"US",
    "sg:address":"5603 Carters Valley Rd",
    "sg:city":"Church Hill",
    "sg:classifiers":[
        {
            "category":"Building & Trades",
            "subcategory":"Landscaping Services",
            "type":"Services"
        }
    ],
    "sg:phone":"+1 423 357 7332",
    "sg:postcode":"37642",
    "sg:province":"TN",
    "wof:name":"Barrett Tree Service",
    "wof:placetype":"venue"
},
  "geometry": {"coordinates":[-82.659434,36.583004],"type":"Point"}
}