{
  "type": "Feature",
  "properties": {
    "iso:country":"US",
    "sg:address":"400 Rocky Knob St",
    "sg:city":"Fayetteville",
    "sg:classifiers":[
        {
            "category":"Education",
            "subcategory":"Library",
            "type":"Public Place"
        }
    ],
    "sg:phone":"+1 931 433 3286",
    "sg:postcode":"37334",
    "sg:province":"TN",
    "wof:name":"Fayettvll-Lncoln Cnty Pub Lbra",
    "wof:placetype":"venue"
},
  "geometry": {"coordinates":[-86.56938700000001,35.15526],"type":"Point"}
}