{
  "type": "Feature",
  "properties": {
    "addr:full":"2010 N Locust Ave Lawrenceburg TN 38464",
    "addr:housenumber":"2010",
    "addr:postcode":"38464",
    "addr:street":"N Locust Ave",
    "iso:country":"US",
    "sg:address":"2010 N Locust Ave",
    "sg:city":"Lawrenceburg",
    "sg:classifiers":[
        {
            "category":"Shopping",
            "subcategory":"Clothing, Apparel, & Fashions",
            "type":"Retail Goods"
        }
    ],
    "sg:phone":"+1 931 762 7976",
    "sg:postcode":"38464",
    "sg:province":"TN",
    "wof:name":"Cato",
    "wof:placetype":"venue"
},
  "geometry": {"coordinates":[-87.321819,35.267307],"type":"Point"}
}