{
  "type": "Feature",
  "properties": {
    "iso:country":"US",
    "sg:address":"103 W Jackson Ave",
    "sg:city":"Knoxville",
    "sg:classifiers":[
        {
            "category":"Shopping",
            "subcategory":"Gifts & Souvenirs",
            "type":"Retail Goods"
        }
    ],
    "sg:phone":"+1 865 637 1311",
    "sg:postcode":"37902",
    "sg:province":"TN",
    "wof:name":"The Complex Inc",
    "wof:placetype":"venue"
},
  "geometry": {"coordinates":[-83.919543,35.969791],"type":"Point"}
}