{
  "type": "Feature",
  "properties": {
    "iso:country":"US",
    "sg:address":"423 Majors Blvd",
    "sg:city":"Lynchburg",
    "sg:classifiers":[
        {
            "category":"Travel",
            "subcategory":"Hotels & Motels",
            "type":"Entertainment"
        }
    ],
    "sg:phone":"+1 931 759 5995",
    "sg:postcode":"37352",
    "sg:province":"TN",
    "wof:name":"Lynchburg Country Inn",
    "wof:placetype":"venue"
},
  "geometry": {"coordinates":[-86.379943,35.280591],"type":"Point"}
}