{
  "type": "Feature",
  "properties": {
    "iso:country":"US",
    "sg:address":"1404 Autumn Knoll Rd",
    "sg:city":"Hermitage",
    "sg:classifiers":[
        {
            "category":"Professional",
            "subcategory":"Business Services",
            "type":"Services"
        }
    ],
    "sg:phone":"+1 615 902 0012",
    "sg:postcode":"37076",
    "sg:province":"TN",
    "wof:name":"Michael J Media Group",
    "wof:placetype":"venue"
},
  "geometry": {"coordinates":[-86.597309,36.187],"type":"Point"}
}