{
  "type": "Feature",
  "properties": {
    "iso:country":"US",
    "sg:address":"1921 Wheeler St",
    "sg:city":"Johnson City",
    "sg:classifiers":[
        {
            "category":"Organizations",
            "subcategory":"Religious Organization",
            "type":"Services"
        }
    ],
    "sg:phone":"+1 423 928 5901",
    "sg:postcode":"37604",
    "sg:province":"TN",
    "wof:name":"Leonard Nave Rev",
    "wof:placetype":"venue"
},
  "geometry": {"coordinates":[-82.38147600000001,36.300072],"type":"Point"}
}