{
  "type": "Feature",
  "properties": {
    "iso:country":"US",
    "sg:address":"107 1st Ave NW",
    "sg:city":"Winchester",
    "sg:classifiers":[
        {
            "category":"Shopping",
            "subcategory":"Pharmacy",
            "type":"Retail Goods"
        }
    ],
    "sg:phone":"+1 931 967 2251",
    "sg:postcode":"37398",
    "sg:province":"TN",
    "wof:name":"Blue Front Drug Stores",
    "wof:placetype":"venue"
},
  "geometry": {"coordinates":[-86.112364,35.186273],"type":"Point"}
}