{
  "type": "Feature",
  "properties": {
    "iso:country":"US",
    "sg:address":"1789 New Hope Rd",
    "sg:city":"Guys",
    "sg:classifiers":[
        {
            "category":"Farming",
            "subcategory":"Farm",
            "type":"Manufacturing & Wholesale Goods"
        }
    ],
    "sg:phone":"+1 731 645 7398",
    "sg:postcode":"38339",
    "sg:province":"TN",
    "wof:name":"Austin Farms",
    "wof:placetype":"venue"
},
  "geometry": {"coordinates":[-88.51227,35.067151],"type":"Point"}
}