{
  "type": "Feature",
  "properties": {
    "iso:country":"US",
    "sg:address":"1605 Harding Pl",
    "sg:city":"Nashville",
    "sg:classifiers":[
        {
            "category":"Professional",
            "subcategory":"Management & Consulting",
            "type":"Services"
        }
    ],
    "sg:phone":"+1 615 665 5988",
    "sg:postcode":"37215",
    "sg:province":"TN",
    "sg:tags":[
        "performance",
        "evaluation",
        "for",
        "foreign"
    ],
    "wof:name":"Britton Cheerie Dean",
    "wof:placetype":"venue"
},
  "geometry": {"coordinates":[-86.828411,36.091283],"type":"Point"}
}