{
  "type": "Feature",
  "properties": {
    "iso:country":"US",
    "sg:address":"510 Wedgewood Ave",
    "sg:city":"Nashville",
    "sg:classifiers":[
        {
            "category":"Education",
            "subcategory":"School",
            "type":"Public Place"
        }
    ],
    "sg:phone":"+1 615 291 6380",
    "sg:postcode":"37203",
    "sg:province":"TN",
    "wof:name":"Fallhamilton Elementary Schl",
    "wof:placetype":"venue"
},
  "geometry": {"coordinates":[-86.76646700000001,36.133128],"type":"Point"}
}