{
  "type": "Feature",
  "properties": {
    "addr:full":"1814 Meharry Blvd Nashville TN 37208",
    "addr:postcode":"1814;37208",
    "addr:street":"Meharry Blvd",
    "iso:country":"US",
    "sg:address":"1814 Meharry Blvd",
    "sg:city":"Nashville",
    "sg:classifiers":[
        {
            "category":"Building & Trades",
            "subcategory":"Landscaping Services",
            "type":"Services"
        }
    ],
    "sg:phone":"+1 615 327 0012",
    "sg:postcode":"37208",
    "sg:province":"TN",
    "sg:tags":[
        "lawn",
        "maintenance",
        "grounds"
    ],
    "wof:name":"Weldon's Lawn Svc",
    "wof:placetype":"venue"
},
  "geometry": {"coordinates":[-86.80677300000001,36.168324],"type":"Point"}
}