{
  "type": "Feature",
  "properties": {
    "iso:country":"US",
    "sg:address":"2310 Maysville Rd",
    "sg:city":"Dickson",
    "sg:classifiers":[
        {
            "category":"Building & Trades",
            "subcategory":"Construction",
            "type":"Services"
        }
    ],
    "sg:phone":"+1 615 763 2894",
    "sg:postcode":"37055",
    "sg:province":"TN",
    "sg:tags":[
        "house"
    ],
    "wof:name":"Larry Morgan Construction",
    "wof:placetype":"venue"
},
  "geometry": {"coordinates":[-87.463151,36.184102],"type":"Point"}
}