{
  "type": "Feature",
  "properties": {
    "iso:country":"US",
    "sg:address":"5068 Park Ave",
    "sg:city":"Memphis",
    "sg:classifiers":[
        {
            "category":"Food & Beverages",
            "subcategory":"Bakery",
            "type":"Retail Goods"
        }
    ],
    "sg:phone":"+1 901 866 2447",
    "sg:postcode":"38117",
    "sg:province":"TN",
    "sg:tags":[
        "cookie",
        "cracker"
    ],
    "wof:name":"Ricki's Cookie Corner",
    "wof:placetype":"venue"
},
  "geometry": {"coordinates":[-89.894081,35.106631],"type":"Point"}
}