{
  "type": "Feature",
  "properties": {
    "iso:country":"US",
    "sg:address":"3933 Deerfield Rd",
    "sg:city":"Knoxville",
    "sg:classifiers":[
        {
            "category":"Retail",
            "subcategory":"Laundry & Dry Cleaning",
            "type":"Services"
        }
    ],
    "sg:phone":"+1 865 588 8505",
    "sg:postcode":"37921",
    "sg:province":"TN",
    "sg:tags":[
        "cleaners",
        "rug",
        "carpet"
    ],
    "wof:name":"Perfection Plus Carpet Clean",
    "wof:placetype":"venue"
},
  "geometry": {"coordinates":[-84.005813,35.978692],"type":"Point"}
}