{
  "type": "Feature",
  "properties": {
    "iso:country":"US",
    "sg:address":"521 Oak Park Dr",
    "sg:city":"Sugar Tree",
    "sg:classifiers":[
        {
            "category":"Government",
            "subcategory":"Fire Station",
            "type":"Public Place"
        }
    ],
    "sg:phone":"+1 731 847 3377",
    "sg:postcode":"38380",
    "sg:province":"TN",
    "sg:tags":[
        "department",
        "volunteer"
    ],
    "wof:name":"Woodlawn Shres Vlntr Fire Dept",
    "wof:placetype":"venue"
},
  "geometry": {"coordinates":[-88.02943399999999,35.736541],"type":"Point"}
}