{
  "type": "Feature",
  "properties": {
    "iso:country":"US",
    "sg:address":"9605 US Hwy 64",
    "sg:city":"Somerville",
    "sg:classifiers":[
        {
            "category":"Wholesale",
            "subcategory":"Machinery & Supplies",
            "type":"Manufacturing & Wholesale Goods"
        },
        {
            "category":"Retail",
            "subcategory":"Repair Shop",
            "type":"Services"
        }
    ],
    "sg:phone":"+1 901 465 2345",
    "sg:postcode":"38068",
    "sg:province":"TN",
    "sg:tags":[
        "equipment",
        "establishment",
        "taxidermist"
    ],
    "wof:name":"Dixie Land Taxidermy & Supply",
    "wof:placetype":"venue"
},
  "geometry": {"coordinates":[-89.47828800000001,35.231542],"type":"Point"}
}