{
  "type": "Feature",
  "properties": {
    "addr:full":"1084 Murfreesboro Pike Nashville TN 37217",
    "addr:housenumber":"1084",
    "addr:postcode":"37217",
    "addr:street":"Murfreesboro Pike",
    "iso:country":"US",
    "sg:address":"1084 Murfreesboro Pike",
    "sg:city":"Nashville",
    "sg:classifiers":[
        {
            "category":"Restaurant",
            "type":"Food & Drink"
        }
    ],
    "sg:menulink":"http://www.allmenus.com/tn/nashville/177844-jack-in-the-box/menu/",
    "sg:phone":"+1 615 365 4600",
    "sg:postcode":"37217",
    "sg:province":"TN",
    "sg:tags":[
        "burger",
        "american"
    ],
    "wof:name":"Jack in the Box",
    "wof:placetype":"venue"
},
  "geometry": {"coordinates":[-86.711213,36.127371],"type":"Point"}
}