{
  "type": "Feature",
  "properties": {
    "addr:full":"5831 Washington Pike Knoxville TN 37918",
    "addr:housenumber":"5831",
    "addr:postcode":"37918",
    "addr:street":"Washington Pike",
    "iso:country":"US",
    "sg:address":"5831 Washington Pike",
    "sg:city":"Knoxville",
    "sg:classifiers":[
        {
            "category":"Professional",
            "subcategory":"Accounting & Tax Preparation",
            "type":"Services"
        }
    ],
    "sg:phone":"+1 865 688 1883",
    "sg:postcode":"37918",
    "sg:province":"TN",
    "wof:name":"Jerry L Tipton CPA",
    "wof:placetype":"venue"
},
  "geometry": {"coordinates":[-83.874977,36.05221],"type":"Point"}
}