{
  "type": "Feature",
  "properties": {
    "iso:country":"US",
    "sg:address":"1211 Oakdale Trl",
    "sg:city":"Knoxville",
    "sg:classifiers":[
        {
            "category":"Education",
            "subcategory":"Special Training",
            "type":"Public Place"
        }
    ],
    "sg:phone":"+1 865 689 9575",
    "sg:postcode":"37914",
    "sg:province":"TN",
    "wof:name":"Turtle Cove Retreat Inc",
    "wof:placetype":"venue"
},
  "geometry": {"coordinates":[-83.853875,35.993307],"type":"Point"}
}