{
  "type": "Feature",
  "properties": {
    "iso:country":"US",
    "sg:address":"111 Three Way Ln",
    "sg:city":"Humboldt",
    "sg:classifiers":[
        {
            "category":"Wholesale",
            "subcategory":"Meat",
            "type":"Manufacturing & Wholesale Goods"
        }
    ],
    "sg:phone":"+1 731 824 3337",
    "sg:postcode":"38343",
    "sg:province":"TN",
    "sg:tags":[
        "plant",
        "packing"
    ],
    "wof:name":"Three Way Processing",
    "wof:placetype":"venue"
},
  "geometry": {"coordinates":[-88.841869,35.763207],"type":"Point"}
}