{
  "type": "Feature",
  "properties": {
    "addr:full":"8345 Championship Dr Memphis TN 38125",
    "addr:housenumber":"8345",
    "addr:postcode":"38125",
    "addr:street":"Championship Dr",
    "iso:country":"US",
    "sg:address":"8345 Championship Dr",
    "sg:city":"Memphis",
    "sg:classifiers":[
        {
            "category":"Real Estate",
            "subcategory":"Real Estate Operator",
            "type":"Services"
        }
    ],
    "sg:phone":"+1 901 748 0002",
    "sg:postcode":"38125",
    "sg:province":"TN",
    "sg:tags":[
        "building",
        "apartment"
    ],
    "sg:website":"www.maac.net",
    "wof:name":"Lincoln On Green At Southwind",
    "wof:placetype":"venue"
},
  "geometry": {"coordinates":[-89.78504599999999,35.052675],"type":"Point"}
}