{
  "type": "Feature",
  "properties": {
    "iso:country":"US",
    "sg:address":"400 McAmoore Dr",
    "sg:city":"Smyrna",
    "sg:classifiers":[
        {
            "category":"Shopping",
            "subcategory":"Hobbies, Toys, & Games",
            "type":"Retail Goods"
        }
    ],
    "sg:phone":"+1 615 355 6785",
    "sg:postcode":"37167",
    "sg:province":"TN",
    "sg:tags":[
        "model",
        "supply"
    ],
    "wof:name":"Anderson's Unlimited",
    "wof:placetype":"venue"
},
  "geometry": {"coordinates":[-86.529242,35.923352],"type":"Point"}
}