{
  "type": "Feature",
  "properties": {
    "iso:country":"US",
    "sg:address":"1124 N Gateway Ave",
    "sg:city":"Rockwood",
    "sg:classifiers":[
        {
            "category":"Restaurant",
            "type":"Food & Drink"
        }
    ],
    "sg:phone":"+1 865 354 8288",
    "sg:postcode":"37854",
    "sg:province":"TN",
    "wof:name":"China King",
    "wof:placetype":"venue"
},
  "geometry": {"coordinates":[-84.66839,35.878814],"type":"Point"}
}