{
  "type": "Feature",
  "properties": {
    "iso:country":"US",
    "sg:address":"1660 Wells Station Rd",
    "sg:city":"Memphis",
    "sg:classifiers":[
        {
            "category":"Food & Beverages",
            "subcategory":"Groceries & Convenience Stores",
            "type":"Retail Goods"
        }
    ],
    "sg:phone":"+1 901 767 0306",
    "sg:postcode":"38108",
    "sg:province":"TN",
    "wof:name":"Wells Station Grocery Store",
    "wof:placetype":"venue"
},
  "geometry": {"coordinates":[-89.91666600000001,35.176283],"type":"Point"}
}