{
  "type": "Feature",
  "properties": {
    "iso:country":"US",
    "sg:address":"5636 Tulip Tree Dr",
    "sg:city":"Memphis",
    "sg:classifiers":[
        {
            "category":"Building & Trades",
            "subcategory":"Cleaning & Sanitation",
            "type":"Services"
        }
    ],
    "sg:phone":"+1 901 794 0187",
    "sg:postcode":"38115",
    "sg:province":"TN",
    "sg:tags":[
        "maintenance"
    ],
    "wof:name":"Jani-King",
    "wof:placetype":"venue"
},
  "geometry": {"coordinates":[-89.875398,35.048335],"type":"Point"}
}