{
  "type": "Feature",
  "properties": {
    "iso:country":"US",
    "sg:address":"1129 N 6th Ave",
    "sg:city":"Knoxville",
    "sg:classifiers":[
        {
            "category":"Organizations",
            "subcategory":"Religious Organization",
            "type":"Services"
        }
    ],
    "sg:phone":"+1 865 524 8680",
    "sg:postcode":"37917",
    "sg:province":"TN",
    "sg:tags":[
        "church"
    ],
    "wof:name":"Sixth Ave Baptist Church Inc",
    "wof:placetype":"venue"
},
  "geometry": {"coordinates":[-83.91468,35.983372],"type":"Point"}
}