{
  "type": "Feature",
  "properties": {
    "iso:country":"US",
    "sg:address":"514 W Summer St",
    "sg:city":"Greeneville",
    "sg:classifiers":[
        {
            "category":"Manufacturing",
            "subcategory":"Tools & Machinery",
            "type":"Manufacturing & Wholesale Goods"
        }
    ],
    "sg:phone":"+1 423 638 3451",
    "sg:postcode":"37743",
    "sg:province":"TN",
    "sg:tags":[
        "engine",
        "repair",
        "mfg",
        "equipment",
        "electrical",
        "boat"
    ],
    "wof:name":"Holly Creek Enterprises",
    "wof:placetype":"venue"
},
  "geometry": {"coordinates":[-82.83956000000001,36.1647],"type":"Point"}
}