{
  "type": "Feature",
  "properties": {
    "iso:country":"US",
    "sg:address":"600 S Perkins Rd",
    "sg:city":"Memphis",
    "sg:classifiers":[
        {
            "category":"Personal",
            "type":"Services"
        }
    ],
    "sg:phone":"+1 901 761 3283",
    "sg:postcode":"38117",
    "sg:province":"TN",
    "sg:tags":[
        "dating"
    ],
    "wof:name":"Private Lines Of Memphis",
    "wof:placetype":"venue"
},
  "geometry": {"coordinates":[-89.907524,35.113191],"type":"Point"}
}