{
  "type": "Feature",
  "properties": {
    "iso:country":"US",
    "sg:address":"118 N 3rd St",
    "sg:city":"Pulaski",
    "sg:classifiers":[
        {
            "category":"Health Services",
            "subcategory":"Optometrist",
            "type":"Services"
        }
    ],
    "sg:phone":"+1 931 363 4557",
    "sg:postcode":"38478",
    "sg:province":"TN",
    "wof:name":"Wadley Family Eye Care",
    "wof:placetype":"venue"
},
  "geometry": {"coordinates":[-87.032743,35.200583],"type":"Point"}
}