{
  "type": "Feature",
  "properties": {
    "addr:full":"86 N Rufe Taylor Rd Greeneville TN 37745",
    "addr:housenumber":"86",
    "addr:postcode":"37745",
    "addr:street":"N Rufe Taylor Rd",
    "iso:country":"US",
    "sg:address":"86 N Rufe Taylor Rd",
    "sg:city":"Greeneville",
    "sg:classifiers":[
        {
            "category":"Retail",
            "subcategory":"Auto Repair",
            "type":"Services"
        }
    ],
    "sg:phone":"+1 423 639 8420",
    "sg:postcode":"37745",
    "sg:province":"TN",
    "sg:tags":[
        "body",
        "automobile",
        "painting"
    ],
    "wof:name":"Shipley's Auto Body & Frame",
    "wof:placetype":"venue"
},
  "geometry": {"coordinates":[-82.771114,36.183015],"type":"Point"}
}