{
  "type": "Feature",
  "properties": {
    "iso:country":"US",
    "sg:address":"191 Forks River Rd",
    "sg:city":"Waverly",
    "sg:classifiers":[
        {
            "category":"Building & Trades",
            "subcategory":"Construction",
            "type":"Services"
        }
    ],
    "sg:phone":"+1 931 296 4785",
    "sg:postcode":"37185",
    "sg:province":"TN",
    "sg:tags":[
        "general",
        "contractor"
    ],
    "wof:name":"Kent Parker Construction",
    "wof:placetype":"venue"
},
  "geometry": {"coordinates":[-87.826519,36.056209],"type":"Point"}
}