{
  "type": "Feature",
  "properties": {
    "addr:full":"2104 Grenada Blvd Knoxville TN 37922",
    "addr:housenumber":"2104",
    "addr:postcode":"37922",
    "addr:street":"Grenada Blvd",
    "iso:country":"US",
    "sg:address":"2104 Grenada Blvd",
    "sg:city":"Knoxville",
    "sg:classifiers":[
        {
            "category":"Organizations",
            "subcategory":"Religious Organization",
            "type":"Services"
        }
    ],
    "sg:phone":"+1 865 769 2741",
    "sg:postcode":"37922",
    "sg:province":"TN",
    "wof:name":"Trinity Systems Incorporated",
    "wof:placetype":"venue"
},
  "geometry": {"coordinates":[-84.062685,35.872253],"type":"Point"}
}