{
  "type": "Feature",
  "properties": {
    "iso:country":"US",
    "sg:address":"432 E Commerce St",
    "sg:city":"Lewisburg",
    "sg:classifiers":[
        {
            "category":"Professional",
            "subcategory":"Computer Services",
            "type":"Services"
        }
    ],
    "sg:phone":"+1 931 359 7960",
    "sg:postcode":"37091",
    "sg:province":"TN",
    "sg:tags":[
        "telephone",
        "information",
        "retrieval",
        "communications"
    ],
    "wof:name":"TN Web",
    "wof:placetype":"venue"
},
  "geometry": {"coordinates":[-86.78230600000001,35.447729],"type":"Point"}
}