{
  "type": "Feature",
  "properties": {
    "addr:full":"711 N Broad St New Tazewell TN 37825",
    "addr:housenumber":"711",
    "addr:postcode":"37825",
    "addr:street":"N Broad St",
    "iso:country":"US",
    "sg:address":"711 N Broad St",
    "sg:city":"New Tazewell",
    "sg:classifiers":[
        {
            "category":"Personal",
            "subcategory":"Beauty Salon",
            "type":"Services"
        }
    ],
    "sg:phone":"+1 423 626 1252",
    "sg:postcode":"37825",
    "sg:province":"TN",
    "wof:name":"Tammy & Co Hairstyling",
    "wof:placetype":"venue"
},
  "geometry": {"coordinates":[-83.593312,36.445826],"type":"Point"}
}