{
  "type": "Feature",
  "properties": {
    "iso:country":"US",
    "sg:address":"4460 Brunswick Rd",
    "sg:city":"Arlington",
    "sg:classifiers":[
        {
            "category":"Organizations",
            "subcategory":"Religious Organization",
            "type":"Services"
        }
    ],
    "sg:phone":"+1 901 381 1753",
    "sg:postcode":"38002",
    "sg:province":"TN",
    "wof:name":"New Mt Zion MB Church",
    "wof:placetype":"venue"
},
  "geometry": {"coordinates":[-89.771694,35.247054],"type":"Point"}
}