{
  "type": "Feature",
  "properties": {
    "iso:country":"US",
    "sg:address":"4273 Cherry Center Dr",
    "sg:city":"Memphis",
    "sg:classifiers":[
        {
            "category":"Insurance",
            "subcategory":"Insurance Agent",
            "type":"Services"
        }
    ],
    "sg:phone":"+1 901 795 6872",
    "sg:postcode":"38118",
    "sg:province":"TN",
    "wof:name":"Kansas City Life Insurance Co",
    "wof:placetype":"venue"
},
  "geometry": {"coordinates":[-89.921741,35.074457],"type":"Point"}
}