{
  "type": "Feature",
  "properties": {
    "iso:country":"US",
    "sg:address":"3311 4th Ave",
    "sg:city":"Chattanooga",
    "sg:classifiers":[
        {
            "category":"Retail",
            "subcategory":"Laundry & Dry Cleaning",
            "type":"Services"
        }
    ],
    "sg:phone":"+1 423 698 4829",
    "sg:postcode":"37407",
    "sg:province":"TN",
    "sg:tags":[
        "cleaners"
    ],
    "wof:name":"East Lake Cleaners",
    "wof:placetype":"venue"
},
  "geometry": {"coordinates":[-85.28675200000001,35.004749],"type":"Point"}
}