{
  "type": "Feature",
  "properties": {
    "addr:full":"7541 Emory Rd NE Corryton TN 37721",
    "addr:housenumber":"7541",
    "addr:postcode":"37721",
    "addr:street":"Emory Rd Ne",
    "iso:country":"US",
    "sg:address":"7541 Emory Rd NE",
    "sg:city":"Corryton",
    "sg:classifiers":[
        {
            "category":"Organizations",
            "subcategory":"Non-profit Organization",
            "type":"Services"
        }
    ],
    "sg:phone":"+1 865 689 8106",
    "sg:postcode":"37721",
    "sg:province":"TN",
    "sg:tags":[
        "social"
    ],
    "wof:name":"Gibbs Center LLC",
    "wof:placetype":"venue"
},
  "geometry": {"coordinates":[-83.850353,36.12217],"type":"Point"}
}