{
  "type": "Feature",
  "properties": {
    "iso:country":"US",
    "sg:address":"3115 Yukon Dr",
    "sg:city":"Arlington",
    "sg:classifiers":[
        {
            "category":"Banks & Credit Unions",
            "subcategory":"Financial Services",
            "type":"Services"
        }
    ],
    "sg:phone":"+1 901 937 4032",
    "sg:postcode":"38002",
    "sg:province":"TN",
    "sg:tags":[
        "investor"
    ],
    "wof:name":"D&P Investment Co",
    "wof:placetype":"venue"
},
  "geometry": {"coordinates":[-89.735979,35.210558],"type":"Point"}
}