{
  "type": "Feature",
  "properties": {
    "iso:country":"US",
    "sg:address":"1001 N Military Ave",
    "sg:city":"Lawrenceburg",
    "sg:classifiers":[
        {
            "category":"Restaurant",
            "type":"Food & Drink"
        }
    ],
    "sg:phone":"+1 931 762 2030",
    "sg:postcode":"38464",
    "sg:province":"TN",
    "wof:name":"Rick's Barbecue",
    "wof:placetype":"venue"
},
  "geometry": {"coordinates":[-87.327168,35.25696],"type":"Point"}
}