{
  "type": "Feature",
  "properties": {
    "iso:country":"US",
    "sg:address":"5390 Virginia Way",
    "sg:city":"Brentwood",
    "sg:classifiers":[
        {
            "category":"Organizations",
            "subcategory":"Community Association",
            "type":"Services"
        }
    ],
    "sg:phone":"+1 615 370 0920",
    "sg:postcode":"37027",
    "sg:province":"TN",
    "sg:tags":[
        "h",
        "fraternity",
        "international"
    ],
    "wof:name":"Alpha Omicron PI Fraternity",
    "wof:placetype":"venue"
},
  "geometry": {"coordinates":[-86.81248600000001,36.03361],"type":"Point"}
}