{
  "type": "Feature",
  "properties": {
    "addr:full":"308 E Mitchell St Trimble TN 38259",
    "addr:housenumber":"308",
    "addr:postcode":"38259",
    "addr:street":"E Mitchell St",
    "iso:country":"US",
    "sg:address":"308 E Mitchell St",
    "sg:city":"Trimble",
    "sg:classifiers":[
        {
            "category":"Organizations",
            "subcategory":"Religious Organization",
            "type":"Services"
        }
    ],
    "sg:phone":"+1 731 297 5691",
    "sg:postcode":"38259",
    "sg:province":"TN",
    "sg:tags":[
        "church"
    ],
    "wof:name":"Methodist Church",
    "wof:placetype":"venue"
},
  "geometry": {"coordinates":[-89.186052,36.202998],"type":"Point"}
}