{
  "type": "Feature",
  "properties": {
    "addr:full":"119 E Main St Jackson TN 38301",
    "addr:housenumber":"119",
    "addr:postcode":"38301",
    "addr:street":"E Main St",
    "iso:country":"US",
    "sg:address":"119 E Main St",
    "sg:city":"Jackson",
    "sg:classifiers":[
        {
            "category":"Government",
            "subcategory":"Office",
            "type":"Public Place"
        }
    ],
    "sg:phone":"+1 731 425 8262",
    "sg:postcode":"38301",
    "sg:province":"TN",
    "sg:tags":[
        "village"
    ],
    "wof:name":"Jackson Building Inspector",
    "wof:placetype":"venue"
},
  "geometry": {"coordinates":[-88.818275,35.614384],"type":"Point"}
}