{
  "type": "Feature",
  "properties": {
    "iso:country":"US",
    "sg:address":"4876 Nolensville Pike",
    "sg:city":"Nashville",
    "sg:classifiers":[
        {
            "category":"Shopping",
            "subcategory":"Musical Instruments",
            "type":"Retail Goods"
        }
    ],
    "sg:phone":"+1 615 832 7450",
    "sg:postcode":"37211",
    "sg:province":"TN",
    "wof:name":"Nashville Used Music",
    "wof:placetype":"venue"
},
  "geometry": {"coordinates":[-86.717513,36.065877],"type":"Point"}
}