{
  "type": "Feature",
  "properties": {
    "addr:full":"286 Beacon Rd Darden TN 38363",
    "addr:housenumber":"286",
    "addr:postcode":"38363",
    "addr:street":"Beacon Rd",
    "iso:country":"US",
    "sg:address":"286 Beacon Rd",
    "sg:city":"Darden",
    "sg:classifiers":[
        {
            "category":"Organizations",
            "subcategory":"Religious Organization",
            "type":"Services"
        }
    ],
    "sg:phone":"+1 731 847 6718",
    "sg:postcode":"38363",
    "sg:province":"TN",
    "sg:tags":[
        "clergy"
    ],
    "wof:name":"Vaughn Hamm",
    "wof:placetype":"venue"
},
  "geometry": {"coordinates":[-88.184169,35.634836],"type":"Point"}
}