{
  "type": "Feature",
  "properties": {
    "iso:country":"US",
    "sg:address":"1085 Natchez Pt",
    "sg:city":"Memphis",
    "sg:classifiers":[
        {
            "category":"Real Estate",
            "subcategory":"Real Estate Operator",
            "type":"Services"
        }
    ],
    "sg:phone":"+1 901 522 8855",
    "sg:postcode":"38103",
    "sg:province":"TN",
    "sg:tags":[
        "apartment"
    ],
    "wof:name":"Riverset Luxury Apartments",
    "wof:placetype":"venue"
},
  "geometry": {"coordinates":[-90.054315,35.173324],"type":"Point"}
}