{
  "type": "Feature",
  "properties": {
    "addr:full":"231 Linda Vista St Bolivar TN 38008",
    "addr:housenumber":"231",
    "addr:postcode":"38008",
    "addr:street":"Linda Vista St",
    "iso:country":"US",
    "sg:address":"231 Linda Vista St",
    "sg:city":"Bolivar",
    "sg:classifiers":[
        {
            "category":"Utilities",
            "subcategory":"Telephone",
            "type":"Services"
        }
    ],
    "sg:phone":"+1 731 658 9480",
    "sg:postcode":"38008",
    "sg:province":"TN",
    "sg:tags":[
        "communications"
    ],
    "wof:name":"Wap Communications",
    "wof:placetype":"venue"
},
  "geometry": {"coordinates":[-88.997426,35.264266],"type":"Point"}
}