{
  "type": "Feature",
  "properties": {
    "iso:country":"US",
    "sg:address":"1277 N Bellevue Blvd",
    "sg:city":"Memphis",
    "sg:classifiers":[
        {
            "category":"Bars & Pubs",
            "type":"Food & Drink"
        }
    ],
    "sg:phone":"+1 901 278 5891",
    "sg:postcode":"38107",
    "sg:province":"TN",
    "sg:tags":[
        "drinking"
    ],
    "wof:name":"Bean Sports Bar and Grill",
    "wof:placetype":"venue"
},
  "geometry": {"coordinates":[-90.017651,35.174398],"type":"Point"}
}