{
  "type": "Feature",
  "properties": {
    "iso:country":"US",
    "sg:address":"3626 Cherry Rd",
    "sg:city":"Memphis",
    "sg:classifiers":[
        {
            "category":"Wholesale",
            "subcategory":"Machinery & Supplies",
            "type":"Manufacturing & Wholesale Goods"
        },
        {
            "category":"Manufacturing",
            "subcategory":"Chemicals & Compounds",
            "type":"Manufacturing & Wholesale Goods"
        }
    ],
    "sg:phone":"+1 901 368 5001",
    "sg:postcode":"38118",
    "sg:province":"TN",
    "sg:tags":[
        "detergent",
        "gd",
        "janitor",
        "mfg"
    ],
    "sg:website":"www.buckeyeinternational.com",
    "wof:name":"Buckeye Cleaning Center",
    "wof:placetype":"venue"
},
  "geometry": {"coordinates":[-89.917169,35.050619],"type":"Point"}
}