{
  "type": "Feature",
  "properties": {
    "addr:full":"149 Baypath Dr Oak Ridge TN 37830",
    "addr:housenumber":"149",
    "addr:postcode":"37830",
    "addr:street":"Baypath Dr",
    "iso:country":"US",
    "sg:address":"149 Baypath Dr",
    "sg:city":"Oak Ridge",
    "sg:classifiers":[
        {
            "category":"Banks & Credit Unions",
            "subcategory":"Investment Brokerage",
            "type":"Services"
        }
    ],
    "sg:phone":"+1 865 483 5992",
    "sg:postcode":"37830",
    "sg:province":"TN",
    "sg:tags":[
        "advisory",
        "financial"
    ],
    "wof:name":"United Financial Network",
    "wof:placetype":"venue"
},
  "geometry": {"coordinates":[-84.19989,36.024591],"type":"Point"}
}