{
  "type": "Feature",
  "properties": {
    "iso:country":"US",
    "sg:address":"1075 West Ave",
    "sg:city":"Crossville",
    "sg:classifiers":[
        {
            "category":"Autos & Motor Vehicles",
            "subcategory":"Auto Supplies",
            "type":"Retail Goods"
        }
    ],
    "sg:phone":"+1 931 456 4545",
    "sg:postcode":"38555",
    "sg:province":"TN",
    "sg:website":"www.autozone.com",
    "wof:name":"Autozone",
    "wof:placetype":"venue"
},
  "geometry": {"coordinates":[-85.039067,35.954641],"type":"Point"}
}