{
  "type": "Feature",
  "properties": {
    "addr:full":"1701 Galleria Blvd Franklin TN 37067",
    "addr:housenumber":"1701",
    "addr:postcode":"37067",
    "addr:street":"Galleria Blvd",
    "iso:country":"US",
    "sg:address":"1701 Galleria Blvd",
    "sg:city":"Franklin",
    "sg:classifiers":[
        {
            "category":"Shopping",
            "subcategory":"Department Store",
            "type":"Retail Goods"
        }
    ],
    "sg:phone":"+1 615 771 2093",
    "sg:postcode":"37067",
    "sg:province":"TN",
    "sg:website":"www.target.com",
    "wof:name":"Target",
    "wof:placetype":"venue"
},
  "geometry": {"coordinates":[-86.810636,35.96411],"type":"Point"}
}