{
  "type": "Feature",
  "properties": {
    "iso:country":"US",
    "sg:address":"2840 Knob Creek Ln",
    "sg:city":"Knoxville",
    "sg:classifiers":[
        {
            "category":"Sports & Exercise",
            "subcategory":"Gym",
            "type":"Entertainment"
        }
    ],
    "sg:phone":"+1 865 637 7468",
    "sg:postcode":"37912",
    "sg:province":"TN",
    "sg:tags":[
        "fitness",
        "physical",
        "facility"
    ],
    "wof:name":"Stretch N Grow",
    "wof:placetype":"venue"
},
  "geometry": {"coordinates":[-84.00447800000001,35.993565],"type":"Point"}
}