{
  "type": "Feature",
  "properties": {
    "iso:country":"US",
    "sg:address":"5555 Coles Ferry Pike",
    "sg:city":"Lebanon",
    "sg:classifiers":[
        {
            "category":"Organizations",
            "subcategory":"Religious Organization",
            "type":"Services"
        }
    ],
    "sg:phone":"+1 615 443 2232",
    "sg:postcode":"37087",
    "sg:province":"TN",
    "wof:name":"Berea Church Of Christ",
    "wof:placetype":"venue"
},
  "geometry": {"coordinates":[-86.344775,36.271517],"type":"Point"}
}