{
  "type": "Feature",
  "properties": {
    "iso:country":"US",
    "sg:address":"136 W Bernard Ave",
    "sg:city":"Greeneville",
    "sg:classifiers":[
        {
            "category":"Retail",
            "subcategory":"Animal Services",
            "type":"Services"
        }
    ],
    "sg:phone":"+1 423 639 4487",
    "sg:postcode":"37743",
    "sg:province":"TN",
    "wof:name":"Waggin Tails",
    "wof:placetype":"venue"
},
  "geometry": {"coordinates":[-82.821855,36.16033],"type":"Point"}
}