{
  "type": "Feature",
  "properties": {
    "iso:country":"US",
    "sg:address":"402 Foxglove Pl",
    "sg:city":"Mount Juliet",
    "sg:classifiers":[
        {
            "category":"Shopping",
            "subcategory":"Beauty & Cosmetics",
            "type":"Retail Goods"
        }
    ],
    "sg:phone":"+1 615 754 2025",
    "sg:postcode":"37122",
    "sg:province":"TN",
    "sg:tags":[
        "merchandise"
    ],
    "wof:name":"Mary Kay",
    "wof:placetype":"venue"
},
  "geometry": {"coordinates":[-86.485467,36.244146],"type":"Point"}
}