{
  "type": "Feature",
  "properties": {
    "iso:country":"US",
    "sg:address":"133 N 3rd St",
    "sg:city":"Selmer",
    "sg:classifiers":[
        {
            "category":"Organizations",
            "subcategory":"Religious Organization",
            "type":"Services"
        }
    ],
    "sg:phone":"+1 731 645 5316",
    "sg:postcode":"38375",
    "sg:province":"TN",
    "sg:tags":[
        "church"
    ],
    "wof:name":"First Christian Church",
    "wof:placetype":"venue"
},
  "geometry": {"coordinates":[-88.59266,35.170752],"type":"Point"}
}