{
  "type": "Feature",
  "properties": {
    "iso:country":"US",
    "sg:address":"2917 Best Rd",
    "sg:city":"Maryville",
    "sg:classifiers":[
        {
            "category":"Building & Trades",
            "subcategory":"Construction",
            "type":"Services"
        }
    ],
    "sg:phone":"+1 865 379 0436",
    "sg:postcode":"37803",
    "sg:province":"TN",
    "sg:tags":[
        "house"
    ],
    "wof:name":"Zesut Inc",
    "wof:placetype":"venue"
},
  "geometry": {"coordinates":[-83.987802,35.690078],"type":"Point"}
}