{
  "type": "Feature",
  "properties": {
    "iso:country":"US",
    "sg:address":"813 Ridge Lake Blvd",
    "sg:city":"Memphis",
    "sg:classifiers":[
        {
            "category":"Real Estate",
            "subcategory":"Real Estate Operator",
            "type":"Services"
        }
    ],
    "sg:phone":"+1 901 763 0172",
    "sg:postcode":"38120",
    "sg:province":"TN",
    "sg:tags":[
        "property",
        "lessor"
    ],
    "wof:name":"Shannon Brothers Enterprises",
    "wof:placetype":"venue"
},
  "geometry": {"coordinates":[-89.86775400000001,35.110434],"type":"Point"}
}