{
  "type": "Feature",
  "properties": {
    "addr:full":"2328 Old Hwy 46 S Dickson TN 37055",
    "addr:housenumber":"2328",
    "addr:postcode":"37055",
    "addr:street":"Old Hwy 46 S",
    "iso:country":"US",
    "sg:address":"2328 Old Hwy 46 S",
    "sg:city":"Dickson",
    "sg:classifiers":[
        {
            "category":"Travel",
            "subcategory":"Hotels & Motels",
            "type":"Entertainment"
        }
    ],
    "sg:phone":"+1 615 446 3766",
    "sg:postcode":"37055",
    "sg:province":"TN",
    "wof:name":"South Aire Inn",
    "wof:placetype":"venue"
},
  "geometry": {"coordinates":[-87.321406,35.978409],"type":"Point"}
}