{
  "type": "Feature",
  "properties": {
    "iso:country":"US",
    "sg:address":"7592 W Farmington Blvd",
    "sg:city":"Germantown",
    "sg:classifiers":[
        {
            "category":"Shopping",
            "subcategory":"Stationery & Office Supplies",
            "type":"Retail Goods"
        }
    ],
    "sg:phone":"+1 901 762 0300",
    "sg:postcode":"38138",
    "sg:province":"TN",
    "wof:name":"Trueform LLC",
    "wof:placetype":"venue"
},
  "geometry": {"coordinates":[-89.81019499999999,35.095626],"type":"Point"}
}