{
  "type": "Feature",
  "properties": {
    "addr:full":"955 Pine Dr Dandridge TN 37725",
    "addr:housenumber":"955",
    "addr:postcode":"37725",
    "addr:street":"Pine Dr",
    "iso:country":"US",
    "sg:address":"955 Pine Dr",
    "sg:city":"Dandridge",
    "sg:classifiers":[
        {
            "category":"Manufacturing",
            "subcategory":"Electronics",
            "type":"Manufacturing & Wholesale Goods"
        }
    ],
    "sg:phone":"+1 865 397 4700",
    "sg:postcode":"37725",
    "sg:province":"TN",
    "sg:tags":[
        "repair",
        "electrical",
        "component",
        "electronic",
        "mfg"
    ],
    "wof:name":"Challenger Inc",
    "wof:placetype":"venue"
},
  "geometry": {"coordinates":[-83.423248,36.034208],"type":"Point"}
}