{
  "type": "Feature",
  "properties": {
    "iso:country":"US",
    "sg:address":"2560 Sunny Glade Cove",
    "sg:city":"Memphis",
    "sg:classifiers":[
        {
            "category":"Shopping",
            "subcategory":"Beauty & Cosmetics",
            "type":"Retail Goods"
        }
    ],
    "sg:phone":"+1 901 377 1995",
    "sg:postcode":"38133",
    "sg:province":"TN",
    "sg:tags":[
        "shop",
        "merchandise"
    ],
    "sg:website":"www.aloettecosmetics.com",
    "wof:name":"Aloette Cosmetics",
    "wof:placetype":"venue"
},
  "geometry": {"coordinates":[-89.823652,35.195851],"type":"Point"}
}