{
  "type": "Feature",
  "properties": {
    "iso:country":"US",
    "sg:address":"2552 Poplar Ave",
    "sg:city":"Memphis",
    "sg:classifiers":[
        {
            "category":"Personal",
            "subcategory":"Barber",
            "type":"Services"
        }
    ],
    "sg:phone":"+1 901 454 1879",
    "sg:postcode":"38104",
    "sg:province":"TN",
    "wof:name":"Carrie's Cutts",
    "wof:placetype":"venue"
},
  "geometry": {"coordinates":[-89.975165,35.137799],"type":"Point"}
}