{
  "type": "Feature",
  "properties": {
    "iso:country":"US",
    "sg:address":"5784 Sparta Hwy",
    "sg:city":"Crossville",
    "sg:classifiers":[
        {
            "category":"Building & Trades",
            "subcategory":"Plumbing",
            "type":"Services"
        }
    ],
    "sg:phone":"+1 931 484 1693",
    "sg:postcode":"38572",
    "sg:province":"TN",
    "sg:tags":[
        "contractor"
    ],
    "wof:name":"Cumberland Climate Control",
    "wof:placetype":"venue"
},
  "geometry": {"coordinates":[-85.126312,35.958296],"type":"Point"}
}