{
  "type": "Feature",
  "properties": {
    "iso:country":"US",
    "sg:address":"225 Ayers Dr",
    "sg:city":"Cleveland",
    "sg:classifiers":[
        {
            "category":"Building & Trades",
            "subcategory":"Landscaping Services",
            "type":"Services"
        }
    ],
    "sg:phone":"+1 423 472 3748",
    "sg:postcode":"37323",
    "sg:province":"TN",
    "wof:name":"Landscape By Design",
    "wof:placetype":"venue"
},
  "geometry": {"coordinates":[-84.841863,35.150152],"type":"Point"}
}