{
  "type": "Feature",
  "properties": {
    "addr:full":"6025 Stage Rd Memphis TN 38134",
    "addr:housenumber":"6025",
    "addr:postcode":"38134",
    "addr:street":"Stage Rd",
    "iso:country":"US",
    "sg:address":"6025 Stage Rd",
    "sg:city":"Memphis",
    "sg:classifiers":[
        {
            "category":"Professional",
            "subcategory":"Computer Services",
            "type":"Services"
        }
    ],
    "sg:phone":"+1 901 379 9780",
    "sg:postcode":"38134",
    "sg:province":"TN",
    "sg:tags":[
        "consulting",
        "internet"
    ],
    "wof:name":"Iom",
    "wof:placetype":"venue"
},
  "geometry": {"coordinates":[-89.862537,35.204682],"type":"Point"}
}