{
  "type": "Feature",
  "properties": {
    "addr:full":"591 S Mendenhall Rd Memphis TN 38117",
    "addr:housenumber":"591",
    "addr:postcode":"38117",
    "addr:street":"S Mendenhall Rd",
    "iso:country":"US",
    "sg:address":"591 S Mendenhall Rd",
    "sg:city":"Memphis",
    "sg:classifiers":[
        {
            "category":"Banks & Credit Unions",
            "subcategory":"Bank",
            "type":"Services"
        }
    ],
    "sg:phone":"+1 901 312 4636",
    "sg:postcode":"38117",
    "sg:province":"TN",
    "sg:tags":[
        "saving",
        "commercial"
    ],
    "wof:name":"Cadence Bank Na",
    "wof:placetype":"venue"
},
  "geometry": {"coordinates":[-89.895927,35.114976],"type":"Point"}
}