{
  "type": "Feature",
  "properties": {
    "iso:country":"US",
    "sg:address":"5653 Frist Blvd",
    "sg:city":"Hermitage",
    "sg:classifiers":[
        {
            "category":"Health Services",
            "subcategory":"Health Practitioner",
            "type":"Services"
        }
    ],
    "sg:phone":"+1 615 885 9591",
    "sg:postcode":"37076",
    "sg:province":"TN",
    "sg:tags":[
        "therapist",
        "physical"
    ],
    "wof:name":"Star Physical Therapy",
    "wof:placetype":"venue"
},
  "geometry": {"coordinates":[-86.606565,36.179871],"type":"Point"}
}