{
  "type": "Feature",
  "properties": {
    "iso:country":"US",
    "sg:address":"387 Pine Laurel Cir",
    "sg:city":"Bluff City",
    "sg:classifiers":[
        {
            "category":"Education",
            "subcategory":"Vocational School",
            "type":"Public Place"
        }
    ],
    "sg:phone":"+1 423 538 5780",
    "sg:postcode":"37618",
    "sg:province":"TN",
    "sg:tags":[
        "processing",
        "datum"
    ],
    "wof:name":"Milhorn Tommy J Jr",
    "wof:placetype":"venue"
},
  "geometry": {"coordinates":[-82.24646199999999,36.505935],"type":"Point"}
}