{
  "type": "Feature",
  "properties": {
    "addr:full":"1243 US Hwy 51 N Scn Ripley TN 38063",
    "addr:housenumber":"1243",
    "addr:postcode":"38063",
    "addr:street":"Us Hwy 51 N Scn",
    "iso:country":"US",
    "sg:address":"1243 US Hwy 51 N Scn",
    "sg:city":"Ripley",
    "sg:classifiers":[
        {
            "category":"Banks & Credit Unions",
            "subcategory":"Bank",
            "type":"Services"
        }
    ],
    "sg:phone":"+1 731 635 9077",
    "sg:postcode":"38063",
    "sg:province":"TN",
    "sg:tags":[
        "financing"
    ],
    "wof:name":"Personal Finance Corp",
    "wof:placetype":"venue"
},
  "geometry": {"coordinates":[-89.530036,35.773383],"type":"Point"}
}