{
  "type": "Feature",
  "properties": {
    "addr:full":"2500 Franklin Hayes Rd Pulaski TN 38478",
    "addr:housenumber":"2500",
    "addr:postcode":"38478",
    "addr:street":"Franklin Hayes Rd",
    "iso:country":"US",
    "sg:address":"2500 Franklin Hayes Rd",
    "sg:city":"Pulaski",
    "sg:classifiers":[
        {
            "category":"Manufacturing",
            "subcategory":"Metals",
            "type":"Manufacturing & Wholesale Goods"
        }
    ],
    "sg:phone":"+1 931 363 8045",
    "sg:postcode":"38478",
    "sg:province":"TN",
    "sg:tags":[
        "blast",
        "furnace",
        "works"
    ],
    "wof:name":"Southeastern Tooling",
    "wof:placetype":"venue"
},
  "geometry": {"coordinates":[-86.914469,35.159369],"type":"Point"}
}