{
  "type": "Feature",
  "properties": {
    "addr:full":"2923 Sutherland Ave Knoxville TN 37919",
    "addr:housenumber":"2923",
    "addr:postcode":"37919",
    "addr:street":"Sutherland Ave",
    "iso:country":"US",
    "sg:address":"2923 Sutherland Ave",
    "sg:city":"Knoxville",
    "sg:classifiers":[
        {
            "category":"Building & Trades",
            "subcategory":"Construction",
            "type":"Services"
        }
    ],
    "sg:phone":"+1 865 524 3024",
    "sg:postcode":"37919",
    "sg:province":"TN",
    "sg:tags":[
        "general",
        "contractor"
    ],
    "wof:name":"Charles Hobson Co Inc",
    "wof:placetype":"venue"
},
  "geometry": {"coordinates":[-83.96484,35.952872],"type":"Point"}
}