{
  "type": "Feature",
  "properties": {
    "addr:full":"4007 Copeland Dr Nashville TN 37215",
    "addr:housenumber":"4007",
    "addr:postcode":"37215",
    "addr:street":"Copeland Dr",
    "iso:country":"US",
    "sg:address":"4007 Copeland Dr",
    "sg:city":"Nashville",
    "sg:classifiers":[
        {
            "category":"Real Estate",
            "subcategory":"Real Estate Agent",
            "type":"Services"
        }
    ],
    "sg:phone":"+1 615 463 3100",
    "sg:postcode":"37215",
    "sg:province":"TN",
    "sg:tags":[
        "management"
    ],
    "wof:name":"Vivant",
    "wof:placetype":"venue"
},
  "geometry": {"coordinates":[-86.840418,36.105237],"type":"Point"}
}