{
  "type": "Feature",
  "properties": {
    "iso:country":"US",
    "sg:address":"2745 E Stone Dr",
    "sg:city":"Kingsport",
    "sg:classifiers":[
        {
            "category":"Shopping",
            "subcategory":"Used Merchandise",
            "type":"Retail Goods"
        }
    ],
    "sg:phone":"+1 423 245 1200",
    "sg:postcode":"37660",
    "sg:province":"TN",
    "sg:tags":[
        "antique"
    ],
    "wof:name":"Hole In The Wall",
    "wof:placetype":"venue"
},
  "geometry": {"coordinates":[-82.48572799999999,36.554122],"type":"Point"}
}