{
  "type": "Feature",
  "properties": {
    "addr:full":"512 Grand Lagoon Madison TN 37115",
    "addr:housenumber":"512",
    "addr:postcode":"37115",
    "addr:street":"Grand Lagoon",
    "iso:country":"US",
    "sg:address":"512 Grand Lagoon",
    "sg:city":"Madison",
    "sg:classifiers":[
        {
            "category":"Retail",
            "subcategory":"Car Wash",
            "type":"Services"
        }
    ],
    "sg:phone":"+1 615 860 7517",
    "sg:postcode":"37115",
    "sg:province":"TN",
    "sg:tags":[
        "carwash"
    ],
    "wof:name":"Johnson & Johnson Auto Detail",
    "wof:placetype":"venue"
},
  "geometry": {"coordinates":[-86.675168,36.250286],"type":"Point"}
}