{
  "type": "Feature",
  "properties": {
    "iso:country":"US",
    "sg:address":"1031 17th Ave S",
    "sg:city":"Nashville",
    "sg:classifiers":[
        {
            "category":"Manufacturing",
            "subcategory":"Apparel",
            "type":"Manufacturing & Wholesale Goods"
        }
    ],
    "sg:phone":"+1 615 320 1715",
    "sg:postcode":"37212",
    "sg:province":"TN",
    "sg:tags":[
        "flag",
        "banner"
    ],
    "wof:name":"Confederate Gray",
    "wof:placetype":"venue"
},
  "geometry": {"coordinates":[-86.79441199999999,36.144027],"type":"Point"}
}