{
  "type": "Feature",
  "properties": {
    "iso:country":"US",
    "sg:address":"1307 Greenfield Ave",
    "sg:city":"Nashville",
    "sg:classifiers":[
        {
            "category":"Utilities",
            "subcategory":"Telephone",
            "type":"Services"
        }
    ],
    "sg:phone":"+1 615 227 9125",
    "sg:postcode":"37216",
    "sg:province":"TN",
    "sg:tags":[
        "communications"
    ],
    "wof:name":"Moxie Publishing",
    "wof:placetype":"venue"
},
  "geometry": {"coordinates":[-86.72397100000001,36.209146],"type":"Point"}
}