{
  "type": "Feature",
  "properties": {
    "iso:country":"US",
    "sg:address":"121 S Forrest Ave",
    "sg:city":"Camden",
    "sg:classifiers":[
        {
            "category":"Government",
            "subcategory":"Office",
            "type":"Public Place"
        }
    ],
    "sg:phone":"+1 731 584 0778",
    "sg:postcode":"38320",
    "sg:province":"TN",
    "wof:name":"Benton County Archives",
    "wof:placetype":"venue"
},
  "geometry": {"coordinates":[-88.097338,36.056373],"type":"Point"}
}