{
  "type": "Feature",
  "properties": {
    "addr:full":"704 N Jefferson St Shelbyville TN 37160",
    "addr:housenumber":"704",
    "addr:postcode":"37160",
    "addr:street":"N Jefferson St",
    "iso:country":"US",
    "sg:address":"704 N Jefferson St",
    "sg:city":"Shelbyville",
    "sg:classifiers":[
        {
            "category":"Professional",
            "subcategory":"Research",
            "type":"Services"
        }
    ],
    "sg:phone":"+1 931 680 5700",
    "sg:postcode":"37160",
    "sg:province":"TN",
    "sg:tags":[
        "market",
        "analysis"
    ],
    "wof:name":"Research Net Inc",
    "wof:placetype":"venue"
},
  "geometry": {"coordinates":[-86.457205,35.488697],"type":"Point"}
}