{
  "type": "Feature",
  "properties": {
    "addr:full":"3040 Austin Peay Hwy Memphis TN 38128",
    "addr:housenumber":"3040",
    "addr:postcode":"38128",
    "addr:street":"Austin Peay Hwy",
    "iso:country":"US",
    "sg:address":"3040 Austin Peay Hwy",
    "sg:city":"Memphis",
    "sg:classifiers":[
        {
            "category":"Retail",
            "subcategory":"Storage",
            "type":"Services"
        },
        {
            "category":"Manufacturing",
            "subcategory":"Paper Products",
            "type":"Manufacturing & Wholesale Goods"
        }
    ],
    "sg:phone":"+1 901 266 3377",
    "sg:postcode":"38128",
    "sg:province":"TN",
    "sg:tags":[
        "fiber",
        "automobile",
        "household",
        "commercial",
        "boxes-corrugated",
        "self",
        "boat"
    ],
    "sg:website":"http://www.ustoreit.com/?utm_source=yellowpages&utm_medium=premium&utm_campaign=yp2010&phid=0327",
    "wof:name":"U-Store-It",
    "wof:placetype":"venue"
},
  "geometry": {"coordinates":[-89.92152400000001,35.206883],"type":"Point"}
}