{
  "type": "Feature",
  "properties": {
    "addr:full":"1548 Oakley Allons Rd Allons TN 38541",
    "addr:housenumber":"1548",
    "addr:postcode":"38541",
    "addr:street":"Oakley Allons Rd",
    "iso:country":"US",
    "sg:address":"1548 Oakley Allons Rd",
    "sg:city":"Allons",
    "sg:classifiers":[
        {
            "category":"Professional",
            "subcategory":"Business Services",
            "type":"Services"
        }
    ],
    "sg:phone":"+1 931 823 8987",
    "sg:postcode":"38541",
    "sg:province":"TN",
    "wof:name":"Christy Lee",
    "wof:placetype":"venue"
},
  "geometry": {"coordinates":[-85.313419,36.485086],"type":"Point"}
}