{
  "type": "Feature",
  "properties": {
    "addr:full":"5069 Berta Rd Memphis TN 38109",
    "addr:housenumber":"5069",
    "addr:postcode":"38109",
    "addr:street":"Berta Rd",
    "iso:country":"US",
    "sg:address":"5069 Berta Rd",
    "sg:city":"Memphis",
    "sg:classifiers":[
        {
            "category":"Building & Trades",
            "subcategory":"Landscaping Services",
            "type":"Services"
        }
    ],
    "sg:phone":"+1 901 789 9272",
    "sg:postcode":"38109",
    "sg:province":"TN",
    "sg:tags":[
        "lawn",
        "maintenance",
        "grounds"
    ],
    "wof:name":"Lee's Pro Lawn Svc Inc",
    "wof:placetype":"venue"
},
  "geometry": {"coordinates":[-90.04680500000001,35.010415],"type":"Point"}
}