{
  "type": "Feature",
  "properties": {
    "addr:full":"537 Cold Stream Pl Nashville TN 37221",
    "addr:housenumber":"537",
    "addr:postcode":"37221",
    "addr:street":"Cold Stream Pl",
    "iso:country":"US",
    "sg:address":"537 Cold Stream Pl",
    "sg:city":"Nashville",
    "sg:classifiers":[
        {
            "category":"Wholesale",
            "subcategory":"Scrap",
            "type":"Manufacturing & Wholesale Goods"
        }
    ],
    "sg:phone":"+1 615 646 0185",
    "sg:postcode":"37221",
    "sg:province":"TN",
    "sg:tags":[
        "recycling",
        "center"
    ],
    "wof:name":"Boworld Recycling Resources",
    "wof:placetype":"venue"
},
  "geometry": {"coordinates":[-86.966718,36.054959],"type":"Point"}
}