{
  "type": "Feature",
  "properties": {
    "addr:full":"660 Trussell Rd Monteagle TN 37356",
    "addr:housenumber":"660",
    "addr:postcode":"37356",
    "addr:street":"Trussell Rd",
    "iso:country":"US",
    "sg:address":"660 Trussell Rd",
    "sg:city":"Monteagle",
    "sg:classifiers":[
        {
            "category":"Wholesale",
            "subcategory":"Construction Materials",
            "type":"Manufacturing & Wholesale Goods"
        }
    ],
    "sg:phone":"+1 931 924 7263",
    "sg:postcode":"37356",
    "sg:province":"TN",
    "sg:tags":[
        "sand",
        "gravel"
    ],
    "wof:name":"Monteagle Sand LLC",
    "wof:placetype":"venue"
},
  "geometry": {"coordinates":[-85.821609,35.230577],"type":"Point"}
}