{
  "type": "Feature",
  "properties": {
    "iso:country":"US",
    "sg:address":"110 Garwood Ln",
    "sg:city":"Sevierville",
    "sg:classifiers":[
        {
            "category":"Organizations",
            "subcategory":"Professional Association",
            "type":"Services"
        }
    ],
    "sg:phone":"+1 865 453 6411",
    "sg:postcode":"37803",
    "sg:province":"TN",
    "sg:tags":[
        "chambers",
        "business",
        "commerce"
    ],
    "sg:website":"www.seviervillechamber.org",
    "wof:name":"Sevierville Chamber Commerce",
    "wof:placetype":"venue"
},
  "geometry": {"coordinates":[-84.00369999999999,35.721939],"type":"Point"}
}