{
  "type": "Feature",
  "properties": {
    "addr:full":"113 Eau Clair St Kingsport TN 37664",
    "addr:housenumber":"113",
    "addr:postcode":"37664",
    "addr:street":"Eau Clair St",
    "iso:country":"US",
    "sg:address":"113 Eau Clair St",
    "sg:city":"Kingsport",
    "sg:classifiers":[
        {
            "category":"Building & Trades",
            "subcategory":"Construction",
            "type":"Services"
        }
    ],
    "sg:phone":"+1 423 288 8850",
    "sg:postcode":"37664",
    "sg:province":"TN",
    "sg:tags":[
        "house"
    ],
    "wof:name":"Liberty Construction",
    "wof:placetype":"venue"
},
  "geometry": {"coordinates":[-82.47052499999999,36.539183],"type":"Point"}
}