{
  "type": "Feature",
  "properties": {
    "iso:country":"US",
    "sg:address":"209 10th Ave S",
    "sg:city":"Nashville",
    "sg:classifiers":[
        {
            "category":"Professional",
            "subcategory":"Accounting & Tax Preparation",
            "type":"Services"
        }
    ],
    "sg:phone":"+1 615 322 9900",
    "sg:postcode":"37203",
    "sg:province":"TN",
    "sg:tags":[
        "accountant"
    ],
    "sg:website":"www.collinsworthbright.com",
    "wof:name":"Collinsworth Bright & Co PC",
    "wof:placetype":"venue"
},
  "geometry": {"coordinates":[-86.782178,36.155001],"type":"Point"}
}