{
  "type": "Feature",
  "properties": {
    "iso:country":"US",
    "sg:address":"1117 Buffalo Trl",
    "sg:city":"Morristown",
    "sg:classifiers":[
        {
            "category":"Retail",
            "subcategory":"Car Wash",
            "type":"Services"
        }
    ],
    "sg:phone":"+1 423 587 2220",
    "sg:postcode":"37814",
    "sg:province":"TN",
    "sg:tags":[
        "automobile",
        "detail",
        "clean"
    ],
    "wof:name":"Bryant's Auto Detailing",
    "wof:placetype":"venue"
},
  "geometry": {"coordinates":[-83.295963,36.225681],"type":"Point"}
}