{
  "type": "Feature",
  "properties": {
    "iso:country":"US",
    "sg:address":"299 S Walnut Bend Rd",
    "sg:city":"Cordova",
    "sg:classifiers":[
        {
            "category":"Building & Trades",
            "subcategory":"Construction",
            "type":"Services"
        }
    ],
    "sg:phone":"+1 901 757 2383",
    "sg:postcode":"38018",
    "sg:province":"TN",
    "sg:tags":[
        "commercial",
        "contractor"
    ],
    "wof:name":"Maler Construction Assoc Inc",
    "wof:placetype":"venue"
},
  "geometry": {"coordinates":[-89.798069,35.121979],"type":"Point"}
}