{
  "type": "Feature",
  "properties": {
    "iso:country":"US",
    "sg:address":"160 Lakeview Ferry Ln",
    "sg:city":"Clinton",
    "sg:classifiers":[
        {
            "category":"Building & Trades",
            "subcategory":"Construction",
            "type":"Services"
        }
    ],
    "sg:phone":"+1 865 945 1118",
    "sg:postcode":"37716",
    "sg:province":"TN",
    "sg:tags":[
        "house",
        "construct",
        "contractor"
    ],
    "wof:name":"Lomanex",
    "wof:placetype":"venue"
},
  "geometry": {"coordinates":[-84.146006,36.016255],"type":"Point"}
}