{
  "type": "Feature",
  "properties": {
    "iso:country":"US",
    "sg:address":"109 Public Sq",
    "sg:city":"Mt Pleasant",
    "sg:classifiers":[
        {
            "category":"Personal",
            "subcategory":"Barber",
            "type":"Services"
        }
    ],
    "sg:phone":"+1 931 379 3587",
    "sg:postcode":"38474",
    "sg:province":"TN",
    "sg:tags":[
        "shop"
    ],
    "wof:name":"Lightning's Barber Shop",
    "wof:placetype":"venue"
},
  "geometry": {"coordinates":[-87.207239,35.534084],"type":"Point"}
}