{
  "type": "Feature",
  "properties": {
    "iso:country":"US",
    "sg:address":"42 N Washington Ave",
    "sg:city":"Brownsville",
    "sg:classifiers":[
        {
            "category":"Personal",
            "subcategory":"Beauty Salon",
            "type":"Services"
        }
    ],
    "sg:phone":"+1 731 772 1519",
    "sg:postcode":"38012",
    "sg:province":"TN",
    "sg:tags":[
        "shop"
    ],
    "wof:name":"L & M Beauty Salon",
    "wof:placetype":"venue"
},
  "geometry": {"coordinates":[-89.262237,35.594733],"type":"Point"}
}