{
  "type": "Feature",
  "properties": {
    "addr:full":"1348 Wenlock Rd Knoxville TN 37922",
    "addr:housenumber":"1348",
    "addr:postcode":"37922",
    "addr:street":"Wenlock Rd",
    "iso:country":"US",
    "sg:address":"1348 Wenlock Rd",
    "sg:city":"Knoxville",
    "sg:classifiers":[
        {
            "category":"Building & Trades",
            "subcategory":"Construction",
            "type":"Services"
        }
    ],
    "sg:phone":"+1 865 691 0929",
    "sg:postcode":"37922",
    "sg:province":"TN",
    "sg:tags":[
        "home",
        "nonresidential",
        "improvement"
    ],
    "wof:name":"Repair Maintenance & Constr",
    "wof:placetype":"venue"
},
  "geometry": {"coordinates":[-84.069469,35.885963],"type":"Point"}
}