{
  "type": "Feature",
  "properties": {
    "addr:full":"3758 Summer Ave Memphis TN 38122",
    "addr:housenumber":"3758",
    "addr:postcode":"38122",
    "addr:street":"Summer Ave",
    "iso:country":"US",
    "sg:address":"3758 Summer Ave",
    "sg:city":"Memphis",
    "sg:classifiers":[
        {
            "category":"Recreation",
            "type":"Entertainment"
        }
    ],
    "sg:phone":"+1 901 454 9696",
    "sg:postcode":"38122",
    "sg:province":"TN",
    "sg:tags":[
        "martial",
        "arts",
        "instruction"
    ],
    "wof:name":"Bei Shaolin Kung Fu Institute",
    "wof:placetype":"venue"
},
  "geometry": {"coordinates":[-89.936516,35.149373],"type":"Point"}
}