{
  "type": "Feature",
  "properties": {
    "iso:country":"US",
    "sg:address":"405 Loganberry Ln",
    "sg:city":"Knoxville",
    "sg:classifiers":[
        {
            "category":"Education",
            "subcategory":"Special Training",
            "type":"Public Place"
        }
    ],
    "sg:phone":"+1 865 300 3932",
    "sg:postcode":"37934",
    "sg:province":"TN",
    "wof:name":"Yoga Education Services Inc",
    "wof:placetype":"venue"
},
  "geometry": {"coordinates":[-84.18270200000001,35.862371],"type":"Point"}
}