{
  "type": "Feature",
  "properties": {
    "addr:full":"2233 Winford Ave Nashville TN 37211",
    "addr:housenumber":"2233",
    "addr:postcode":"37211",
    "addr:street":"Winford Ave",
    "iso:country":"US",
    "sg:address":"2233 Winford Ave",
    "sg:city":"Nashville",
    "sg:classifiers":[
        {
            "category":"Education",
            "subcategory":"School",
            "type":"Public Place"
        }
    ],
    "sg:phone":"+1 615 862 8911",
    "sg:postcode":"37211",
    "sg:province":"TN",
    "wof:name":"Berry Head Start",
    "wof:placetype":"venue"
},
  "geometry": {"coordinates":[-86.756299,36.122812],"type":"Point"}
}