{
  "type": "Feature",
  "properties": {
    "addr:full":"4000 Pleasant Ridge Rd Knoxville TN 37912",
    "addr:housenumber":"4000",
    "addr:postcode":"37912",
    "addr:street":"Pleasant Ridge Rd",
    "iso:country":"US",
    "sg:address":"4000 Pleasant Ridge Rd",
    "sg:city":"Knoxville",
    "sg:classifiers":[
        {
            "category":"Real Estate",
            "subcategory":"Real Estate Agent",
            "type":"Services"
        }
    ],
    "sg:phone":"+1 865 329 0009",
    "sg:postcode":"37912",
    "sg:province":"TN",
    "sg:tags":[
        "personal"
    ],
    "wof:name":"Baco Realty",
    "wof:placetype":"venue"
},
  "geometry": {"coordinates":[-83.975105,35.980843],"type":"Point"}
}