{
  "type": "Feature",
  "properties": {
    "iso:country":"US",
    "sg:address":"1488 Old Lake City Hwy",
    "sg:city":"Clinton",
    "sg:classifiers":[
        {
            "category":"Professional",
            "type":"Services"
        }
    ],
    "sg:phone":"+1 865 463 9039",
    "sg:postcode":"37716",
    "sg:province":"TN",
    "wof:name":"Vivian Carroll",
    "wof:placetype":"venue"
},
  "geometry": {"coordinates":[-84.15486199999999,36.155613],"type":"Point"}
}