{
  "type": "Feature",
  "properties": {
    "iso:country":"US",
    "sg:address":"217 S Anderson St",
    "sg:city":"Tullahoma",
    "sg:classifiers":[
        {
            "category":"Home & Garden",
            "subcategory":"Furniture",
            "type":"Retail Goods"
        }
    ],
    "sg:phone":"+1 931 461 9111",
    "sg:postcode":"37388",
    "sg:province":"TN",
    "sg:tags":[
        "equipment",
        "kitchen",
        "cabinet"
    ],
    "wof:name":"Kitchen Co",
    "wof:placetype":"venue"
},
  "geometry": {"coordinates":[-86.204037,35.364312],"type":"Point"}
}