{
  "type": "Feature",
  "properties": {
    "addr:full":"744 Gentry Rd Chattanooga TN 37421",
    "addr:housenumber":"744",
    "addr:postcode":"37421",
    "addr:street":"Gentry Rd",
    "iso:country":"US",
    "sg:address":"744 Gentry Rd",
    "sg:city":"Chattanooga",
    "sg:classifiers":[
        {
            "category":"Building & Trades",
            "subcategory":"Construction",
            "type":"Services"
        }
    ],
    "sg:phone":"+1 423 892 0316",
    "sg:postcode":"37421",
    "sg:province":"TN",
    "sg:tags":[
        "hanging",
        "contractor"
    ],
    "wof:name":"James Willis PTG",
    "wof:placetype":"venue"
},
  "geometry": {"coordinates":[-85.141564,34.991122],"type":"Point"}
}