{
  "type": "Feature",
  "properties": {
    "addr:full":"4326 Jersey Pike Chattanooga TN 37416",
    "addr:housenumber":"4326",
    "addr:postcode":"37416",
    "addr:street":"Jersey Pike",
    "iso:country":"US",
    "sg:address":"4326 Jersey Pike",
    "sg:city":"Chattanooga",
    "sg:phone":"+1 423 892 5717",
    "sg:postcode":"37416",
    "sg:province":"TN",
    "sg:tags":[
        "product",
        "petroleum"
    ],
    "wof:name":"Magellan Midstream Partners LL",
    "wof:placetype":"venue"
},
  "geometry": {"coordinates":[-85.19179800000001,35.070618],"type":"Point"}
}