{
  "type": "Feature",
  "properties": {
    "addr:full":"8582 US Hwy 51 N Millington TN 38053",
    "addr:housenumber":"8582",
    "addr:postcode":"38053",
    "addr:street":"Us Hwy 51 N",
    "iso:country":"US",
    "sg:address":"8582 US Hwy 51 N",
    "sg:city":"Millington",
    "sg:classifiers":[
        {
            "category":"Professional",
            "subcategory":"Lawyer & Legal Services",
            "type":"Services"
        }
    ],
    "sg:phone":"+1 901 872 4229",
    "sg:postcode":"38053",
    "sg:province":"TN",
    "sg:tags":[
        "attorney"
    ],
    "wof:name":"Cole & Peel",
    "wof:placetype":"venue"
},
  "geometry": {"coordinates":[-89.891428,35.361297],"type":"Point"}
}