{
  "type": "Feature",
  "properties": {
    "iso:country":"US",
    "sg:address":"30 E Chickasaw Cove",
    "sg:city":"Memphis",
    "sg:classifiers":[
        {
            "category":"Health Services",
            "subcategory":"Health Practitioner",
            "type":"Services"
        }
    ],
    "sg:phone":"+1 901 323 1928",
    "sg:postcode":"38111",
    "sg:province":"TN",
    "sg:tags":[
        "psychologist"
    ],
    "wof:name":"Bailey J Riley Phd Clinical",
    "wof:placetype":"venue"
},
  "geometry": {"coordinates":[-89.959515,35.130867],"type":"Point"}
}