{
  "type": "Feature",
  "properties": {
    "iso:country":"US",
    "sg:address":"121 New Hope Rd",
    "sg:city":"Dyer",
    "sg:classifiers":[
        {
            "category":"Building & Trades",
            "subcategory":"Construction",
            "type":"Services"
        }
    ],
    "sg:phone":"+1 731 692 2747",
    "sg:postcode":"38330",
    "sg:province":"TN",
    "sg:tags":[
        "contractor"
    ],
    "wof:name":"Elliott & Swink Masonry Contr",
    "wof:placetype":"venue"
},
  "geometry": {"coordinates":[-88.97439,36.092807],"type":"Point"}
}