{
  "type": "Feature",
  "properties": {
    "iso:country":"US",
    "sg:address":"359 Shepherd Hills Rd",
    "sg:city":"Cookeville",
    "sg:classifiers":[
        {
            "category":"Retail",
            "subcategory":"Laundry & Dry Cleaning",
            "type":"Services"
        }
    ],
    "sg:phone":"+1 931 526 5315",
    "sg:postcode":"38501",
    "sg:province":"TN",
    "sg:tags":[
        "cleaners",
        "rug",
        "carpet"
    ],
    "wof:name":"Clean World",
    "wof:placetype":"venue"
},
  "geometry": {"coordinates":[-85.513499,36.192811],"type":"Point"}
}