{
  "type": "Feature",
  "properties": {
    "iso:country":"US",
    "sg:address":"515 W College St",
    "sg:city":"Murfreesboro",
    "sg:classifiers":[
        {
            "category":"Home & Garden",
            "subcategory":"Garden Supply",
            "type":"Retail Goods"
        }
    ],
    "sg:phone":"+1 615 890 0556",
    "sg:postcode":"37130",
    "sg:province":"TN",
    "sg:tags":[
        "merchandise"
    ],
    "wof:name":"Howse Small Engine Repair",
    "wof:placetype":"venue"
},
  "geometry": {"coordinates":[-86.396997,35.848477],"type":"Point"}
}