{
  "type": "Feature",
  "properties": {
    "iso:country":"US",
    "sg:address":"1802 Apple Valley Cir",
    "sg:city":"Nashville",
    "sg:classifiers":[
        {
            "category":"Professional",
            "subcategory":"Lawyer & Legal Services",
            "type":"Services"
        }
    ],
    "sg:phone":"+1 615 860 9774",
    "sg:postcode":"37207",
    "sg:province":"TN",
    "sg:tags":[
        "attorney"
    ],
    "wof:name":"Kathy A Leslie",
    "wof:placetype":"venue"
},
  "geometry": {"coordinates":[-86.769504,36.253084],"type":"Point"}
}