{
  "type": "Feature",
  "properties": {
    "iso:country":"US",
    "sg:address":"4429 Stewarts Ferry Pike",
    "sg:city":"Mount Juliet",
    "sg:classifiers":[
        {
            "category":"Food & Beverages",
            "subcategory":"Groceries & Convenience Stores",
            "type":"Retail Goods"
        }
    ],
    "sg:phone":"+1 615 444 4495",
    "sg:postcode":"37122",
    "sg:province":"TN",
    "wof:name":"Suggs Creek General Store",
    "wof:placetype":"venue"
},
  "geometry": {"coordinates":[-86.495453,36.118671],"type":"Point"}
}