{
  "type": "Feature",
  "properties": {
    "iso:country":"US",
    "sg:address":"737 Melrose Ave",
    "sg:city":"Nashville",
    "sg:classifiers":[
        {
            "category":"Wholesale",
            "subcategory":"Hardware",
            "type":"Manufacturing & Wholesale Goods"
        }
    ],
    "sg:phone":"+1 615 252 8801",
    "sg:postcode":"37211",
    "sg:province":"TN",
    "sg:tags":[
        "nut",
        "bolt"
    ],
    "wof:name":"Brighton-Best Socket Screw Mfg",
    "wof:placetype":"venue"
},
  "geometry": {"coordinates":[-86.76302699999999,36.120476],"type":"Point"}
}