{
  "type": "Feature",
  "properties": {
    "iso:country":"US",
    "sg:address":"828 Loretta Dr",
    "sg:city":"Goodlettsville",
    "sg:classifiers":[
        {
            "category":"Professional",
            "subcategory":"Advertising",
            "type":"Services"
        }
    ],
    "sg:phone":"+1 615 851 8767",
    "sg:postcode":"37072",
    "sg:province":"TN",
    "sg:tags":[
        "agency"
    ],
    "wof:name":"Milemarker Advertising Inc",
    "wof:placetype":"venue"
},
  "geometry": {"coordinates":[-86.710244,36.339197],"type":"Point"}
}