{
  "type": "Feature",
  "properties": {
    "addr:full":"835 Windsor St Cookeville TN 38501",
    "addr:housenumber":"835",
    "addr:postcode":"38501",
    "addr:street":"Windsor St",
    "iso:country":"US",
    "sg:address":"835 Windsor St",
    "sg:city":"Cookeville",
    "sg:classifiers":[
        {
            "category":"Freight",
            "type":"Transportation"
        }
    ],
    "sg:phone":"+1 931 372 0454",
    "sg:postcode":"38501",
    "sg:province":"TN",
    "sg:tags":[
        "operator",
        "trucking"
    ],
    "wof:name":"Johnson Trucking",
    "wof:placetype":"venue"
},
  "geometry": {"coordinates":[-85.518207,36.143203],"type":"Point"}
}