{
  "type": "Feature",
  "properties": {
    "iso:country":"US",
    "sg:address":"713 Dover Glen Dr",
    "sg:city":"Antioch",
    "sg:classifiers":[
        {
            "category":"Arts & Performance",
            "subcategory":"Theater",
            "type":"Entertainment"
        }
    ],
    "sg:phone":"+1 615 485 1867",
    "sg:postcode":"37013",
    "sg:province":"TN",
    "sg:tags":[
        "bureau"
    ],
    "wof:name":"Beat House Entertainment",
    "wof:placetype":"venue"
},
  "geometry": {"coordinates":[-86.650645,36.074557],"type":"Point"}
}