{
  "type": "Feature",
  "properties": {
    "iso:country":"US",
    "sg:address":"416 21st Ave S",
    "sg:city":"Nashville",
    "sg:classifiers":[
        {
            "category":"Ice Cream",
            "type":"Food & Drink"
        }
    ],
    "sg:menulink":"http://www.allmenus.com/tn/nashville/217408-ben--jerrys/menu/",
    "sg:postcode":"37203",
    "sg:province":"TN",
    "sg:tags":[
        "american"
    ],
    "wof:name":"Ben & Jerry's",
    "wof:placetype":"venue"
},
  "geometry": {"coordinates":[-86.79913999999999,36.146153],"type":"Point"}
}