{
  "type": "Feature",
  "properties": {
    "iso:country":"US",
    "sg:address":"768 Trimble Hwy",
    "sg:city":"Kenton",
    "sg:phone":"+1 731 643 6596",
    "sg:postcode":"38233",
    "sg:province":"TN",
    "sg:tags":[
        "farm",
        "grain",
        "cash",
        "cotton"
    ],
    "wof:name":"Robert Minton",
    "wof:placetype":"venue"
},
  "geometry": {"coordinates":[-89.13636700000001,36.156502],"type":"Point"}
}