{
  "type": "Feature",
  "properties": {
    "iso:country":"US",
    "sg:address":"309 E Walnut St",
    "sg:city":"Sweetwater",
    "sg:classifiers":[
        {
            "category":"Local Transit",
            "type":"Transportation"
        }
    ],
    "sg:phone":"+1 423 337 3668",
    "sg:postcode":"37874",
    "sg:province":"TN",
    "sg:tags":[
        "ambulance"
    ],
    "wof:name":"Monroe County Emergency Svc",
    "wof:placetype":"venue"
},
  "geometry": {"coordinates":[-84.461189,35.598859],"type":"Point"}
}