{
  "type": "Feature",
  "properties": {
    "iso:country":"US",
    "sg:address":"326 E Park St",
    "sg:city":"Alamo",
    "sg:classifiers":[
        {
            "category":"Education",
            "subcategory":"School",
            "type":"Public Place"
        }
    ],
    "sg:phone":"+1 731 696 2764",
    "sg:postcode":"38001",
    "sg:province":"TN",
    "sg:website":"www.alamoschool.org",
    "wof:name":"Alamo School Special Ed Dept",
    "wof:placetype":"venue"
},
  "geometry": {"coordinates":[-89.111963,35.783516],"type":"Point"}
}