{
  "type": "Feature",
  "properties": {
    "iso:country":"US",
    "sg:address":"5720 Stage Rd",
    "sg:city":"Bartlett",
    "sg:classifiers":[
        {
            "category":"Education",
            "subcategory":"Dance Studio",
            "type":"Public Place"
        }
    ],
    "sg:phone":"+1 901 379 2600",
    "sg:postcode":"38134",
    "sg:province":"TN",
    "sg:tags":[
        "instruction",
        "dancing"
    ],
    "wof:name":"Essentials Dance Co",
    "wof:placetype":"venue"
},
  "geometry": {"coordinates":[-89.87191,35.204292],"type":"Point"}
}