{
  "type": "Feature",
  "properties": {
    "addr:full":"1894 Thompsons Station Rd W Thompsons Station TN 37179",
    "addr:housenumber":"1894",
    "addr:postcode":"37179",
    "addr:street":"Thompsons Station Rd W",
    "iso:country":"US",
    "sg:address":"1894 Thompsons Station Rd W",
    "sg:city":"Thompsons Station",
    "sg:classifiers":[
        {
            "category":"Farming",
            "subcategory":"Farm",
            "type":"Manufacturing & Wholesale Goods"
        }
    ],
    "sg:phone":"+1 615 794 1256",
    "sg:postcode":"37179",
    "sg:province":"TN",
    "sg:tags":[
        "crop",
        "general"
    ],
    "wof:name":"Spring Valley Farms",
    "wof:placetype":"venue"
},
  "geometry": {"coordinates":[-86.95777,35.821642],"type":"Point"}
}