{
  "type": "Feature",
  "properties": {
    "iso:country":"US",
    "sg:address":"1712 Fairfield Pike",
    "sg:city":"Shelbyville",
    "sg:classifiers":[
        {
            "category":"Building & Trades",
            "subcategory":"Construction",
            "type":"Services"
        }
    ],
    "sg:phone":"+1 931 684 2162",
    "sg:postcode":"37160",
    "sg:province":"TN",
    "sg:tags":[
        "house"
    ],
    "wof:name":"Finis Arnold Bldg Co",
    "wof:placetype":"venue"
},
  "geometry": {"coordinates":[-86.442106,35.51751],"type":"Point"}
}