{
  "type": "Feature",
  "properties": {
    "iso:country":"US",
    "sg:address":"5734 US Hwy 51 N",
    "sg:city":"Memphis",
    "sg:classifiers":[
        {
            "category":"Autos & Motor Vehicles",
            "subcategory":"Automobile Sales",
            "type":"Retail Goods"
        }
    ],
    "sg:phone":"+1 901 358 2600",
    "sg:postcode":"38127",
    "sg:province":"TN",
    "wof:name":"Chucks Autoplex",
    "wof:placetype":"venue"
},
  "geometry": {"coordinates":[-89.97271499999999,35.28265],"type":"Point"}
}