{
  "type": "Feature",
  "properties": {
    "iso:country":"US",
    "sg:address":"1225 Willowbrook Dr",
    "sg:city":"Clarksville",
    "sg:classifiers":[
        {
            "category":"Building & Trades",
            "subcategory":"Plumbing",
            "type":"Services"
        }
    ],
    "sg:phone":"+1 931 920 2392",
    "sg:postcode":"37043",
    "sg:province":"TN",
    "sg:tags":[
        "contractor"
    ],
    "wof:name":"Tim Jurisin Plumbing",
    "wof:placetype":"venue"
},
  "geometry": {"coordinates":[-87.243725,36.467655],"type":"Point"}
}