{
  "type": "Feature",
  "properties": {
    "addr:full":"2159 N Thompson Ln Murfreesboro TN 37129",
    "addr:housenumber":"2159",
    "addr:postcode":"37129",
    "addr:street":"N Thompson Ln",
    "iso:country":"US",
    "sg:address":"2159 N Thompson Ln",
    "sg:city":"Murfreesboro",
    "sg:classifiers":[
        {
            "category":"Recreation",
            "type":"Entertainment"
        }
    ],
    "sg:phone":"+1 615 207 9806",
    "sg:postcode":"37129",
    "sg:province":"TN",
    "sg:tags":[
        "martial",
        "arts",
        "instruction"
    ],
    "wof:name":"Hayes Martial Arts",
    "wof:placetype":"venue"
},
  "geometry": {"coordinates":[-86.420271,35.899874],"type":"Point"}
}