{
  "type": "Feature",
  "properties": {
    "iso:country":"US",
    "sg:address":"4650 Applestone St",
    "sg:city":"Memphis",
    "sg:classifiers":[
        {
            "category":"Building & Trades",
            "subcategory":"Construction",
            "type":"Services"
        }
    ],
    "sg:phone":"+1 901 289 5170",
    "sg:postcode":"38109",
    "sg:province":"TN",
    "sg:tags":[
        "painter"
    ],
    "wof:name":"T & T Maintenance",
    "wof:placetype":"venue"
},
  "geometry": {"coordinates":[-90.05899700000001,35.021117],"type":"Point"}
}