{
  "type": "Feature",
  "properties": {
    "iso:country":"US",
    "sg:address":"1000 Maddox-Simpson Pkwy",
    "sg:city":"Lebanon",
    "sg:classifiers":[
        {
            "category":"Building & Trades",
            "subcategory":"Construction",
            "type":"Services"
        }
    ],
    "sg:phone":"+1 615 443 7838",
    "sg:postcode":"37090",
    "sg:province":"TN",
    "sg:tags":[
        "home",
        "builder"
    ],
    "wof:name":"Carlton Homes",
    "wof:placetype":"venue"
},
  "geometry": {"coordinates":[-86.290993,36.172784],"type":"Point"}
}