{
  "type": "Feature",
  "properties": {
    "iso:country":"US",
    "sg:address":"931 Industrial Park Rd",
    "sg:city":"Dandridge",
    "sg:classifiers":[
        {
            "category":"Government",
            "subcategory":"Office",
            "type":"Public Place"
        }
    ],
    "sg:phone":"+1 865 397 7824",
    "sg:postcode":"37725",
    "sg:province":"TN",
    "sg:tags":[
        "county",
        "affairs",
        "admin"
    ],
    "wof:name":"Veterans Affairs Ofc",
    "wof:placetype":"venue"
},
  "geometry": {"coordinates":[-83.425049,36.030023],"type":"Point"}
}