{
  "type": "Feature",
  "properties": {
    "iso:country":"US",
    "sg:address":"352 Pippin Rd",
    "sg:city":"Cookeville",
    "sg:classifiers":[
        {
            "category":"Building & Trades",
            "subcategory":"Construction",
            "type":"Services"
        }
    ],
    "sg:phone":"+1 931 528 9784",
    "sg:postcode":"38501",
    "sg:province":"TN",
    "sg:tags":[
        "house"
    ],
    "wof:name":"Will Fix Call Phill Wicks",
    "wof:placetype":"venue"
},
  "geometry": {"coordinates":[-85.549485,36.179354],"type":"Point"}
}