{
  "type": "Feature",
  "properties": {
    "addr:full":"299 Hill Rd Vanleer TN 37181",
    "addr:housenumber":"299",
    "addr:postcode":"37181",
    "addr:street":"Hill Rd",
    "iso:country":"US",
    "sg:address":"299 Hill Rd",
    "sg:city":"Vanleer",
    "sg:classifiers":[
        {
            "category":"Autos & Motor Vehicles",
            "subcategory":"Automobile Sales",
            "type":"Retail Goods"
        },
        {
            "category":"Manufacturing",
            "subcategory":"Retail Goods",
            "type":"Manufacturing & Wholesale Goods"
        }
    ],
    "sg:phone":"+1 615 763 2018",
    "sg:postcode":"37181",
    "sg:province":"TN",
    "sg:tags":[
        "supply",
        "mfg",
        "fastener",
        "equipment",
        "aircraft",
        "parts",
        "aerospace"
    ],
    "wof:name":"Sapco Inc",
    "wof:placetype":"venue"
},
  "geometry": {"coordinates":[-87.49995199999999,36.221585],"type":"Point"}
}