{
  "type": "Feature",
  "properties": {
    "addr:full":"1002 E Walthal Cir Memphis TN 38111",
    "addr:housenumber":"1002",
    "addr:postcode":"38111",
    "addr:street":"E Walthal Cir",
    "iso:country":"US",
    "sg:address":"1002 E Walthal Cir",
    "sg:city":"Memphis",
    "sg:classifiers":[
        {
            "category":"Retail",
            "subcategory":"Repair Shop",
            "type":"Services"
        }
    ],
    "sg:phone":"+1 901 323 3676",
    "sg:postcode":"38111",
    "sg:province":"TN",
    "sg:tags":[
        "small",
        "major",
        "appliance",
        "refinishing"
    ],
    "wof:name":"Memphis Appliance Service",
    "wof:placetype":"venue"
},
  "geometry": {"coordinates":[-89.948025,35.102295],"type":"Point"}
}