{
  "type": "Feature",
  "properties": {
    "iso:country":"US",
    "sg:address":"121 Executive Dr",
    "sg:city":"Jackson",
    "sg:classifiers":[
        {
            "category":"Government",
            "subcategory":"Police Station",
            "type":"Public Place"
        }
    ],
    "sg:phone":"+1 731 984 6600",
    "sg:postcode":"38305",
    "sg:province":"TN",
    "sg:tags":[
        "state"
    ],
    "sg:website":"www.tbi.state.tn.us",
    "wof:name":"Investigation Bureau",
    "wof:placetype":"venue"
},
  "geometry": {"coordinates":[-88.823696,35.670773],"type":"Point"}
}