{
  "type": "Feature",
  "properties": {
    "addr:full":"6135 Cedar Grove Rd Arlington TN 38002",
    "addr:housenumber":"6135",
    "addr:postcode":"38002",
    "addr:street":"Cedar Grove Rd",
    "iso:country":"US",
    "sg:address":"6135 Cedar Grove Rd",
    "sg:city":"Arlington",
    "sg:classifiers":[
        {
            "category":"Professional",
            "subcategory":"Business Services",
            "type":"Services"
        }
    ],
    "sg:phone":"+1 901 829 3060",
    "sg:postcode":"38002",
    "sg:province":"TN",
    "wof:name":"Triple R Enterprises LLC",
    "wof:placetype":"venue"
},
  "geometry": {"coordinates":[-89.78957200000001,35.287159],"type":"Point"}
}