{
  "type": "Feature",
  "properties": {
    "iso:country":"US",
    "sg:address":"703 W Main St",
    "sg:city":"Jefferson City",
    "sg:classifiers":[
        {
            "category":"Shopping",
            "subcategory":"Computers & Home Electronics",
            "type":"Retail Goods"
        }
    ],
    "sg:phone":"+1 865 475 7070",
    "sg:postcode":"37760",
    "sg:province":"TN",
    "sg:tags":[
        "distributor",
        "equipment",
        "parts",
        "dealer"
    ],
    "wof:name":"Chips Xp",
    "wof:placetype":"venue"
},
  "geometry": {"coordinates":[-83.49243,36.126225],"type":"Point"}
}