{
  "type": "Feature",
  "properties": {
    "iso:country":"US",
    "sg:address":"3570 Cosby Hwy",
    "sg:city":"Cosby",
    "sg:classifiers":[
        {
            "category":"Building & Trades",
            "subcategory":"Plumbing",
            "type":"Services"
        }
    ],
    "sg:phone":"+1 423 487 2654",
    "sg:postcode":"37722",
    "sg:province":"TN",
    "sg:tags":[
        "contractor"
    ],
    "wof:name":"Mathis Plumbing",
    "wof:placetype":"venue"
},
  "geometry": {"coordinates":[-83.238293,35.831692],"type":"Point"}
}