{
  "type": "Feature",
  "properties": {
    "addr:full":"2414 Lamar Ave Memphis TN 38114",
    "addr:housenumber":"2414",
    "addr:postcode":"38114",
    "addr:street":"Lamar Ave",
    "iso:country":"US",
    "sg:address":"2414 Lamar Ave",
    "sg:city":"Memphis",
    "sg:classifiers":[
        {
            "category":"Social Services",
            "subcategory":"Child Care",
            "type":"Services"
        }
    ],
    "sg:phone":"+1 901 743 0096",
    "sg:postcode":"38114",
    "sg:province":"TN",
    "wof:name":"Cherokee Children & Family Svc",
    "wof:placetype":"venue"
},
  "geometry": {"coordinates":[-89.983952,35.104369],"type":"Point"}
}