{
  "type": "Feature",
  "properties": {
    "iso:country":"US",
    "sg:address":"2274 Crisp Springs Rd",
    "sg:city":"Mc Minnville",
    "sg:classifiers":[
        {
            "category":"Home & Garden",
            "subcategory":"Building Materials",
            "type":"Retail Goods"
        }
    ],
    "sg:phone":"+1 931 939 0379",
    "sg:postcode":"37110",
    "sg:province":"TN",
    "wof:name":"Sealcraft",
    "wof:placetype":"venue"
},
  "geometry": {"coordinates":[-85.873823,35.702776],"type":"Point"}
}