{
  "type": "Feature",
  "properties": {
    "iso:country":"US",
    "sg:address":"25 Hillendale Rd",
    "sg:city":"Crossville",
    "sg:classifiers":[
        {
            "category":"Building & Trades",
            "subcategory":"Cleaning & Sanitation",
            "type":"Services"
        }
    ],
    "sg:phone":"+1 931 788 1452",
    "sg:postcode":"38572",
    "sg:province":"TN",
    "sg:tags":[
        "repair",
        "maintenance"
    ],
    "wof:name":"Commercial Clean",
    "wof:placetype":"venue"
},
  "geometry": {"coordinates":[-85.04340500000001,35.841671],"type":"Point"}
}