{
  "type": "Feature",
  "properties": {
    "addr:full":"125 2nd Ave N Nashville TN 37201",
    "addr:housenumber":"125",
    "addr:postcode":"37201",
    "addr:street":"2Nd Ave N",
    "iso:country":"US",
    "sg:address":"125 2nd Ave N",
    "sg:city":"Nashville",
    "sg:classifiers":[
        {
            "category":"Real Estate",
            "subcategory":"Real Estate Services",
            "type":"Services"
        },
        {
            "category":"Real Estate",
            "subcategory":"Developer",
            "type":"Services"
        },
        {
            "category":"Real Estate",
            "subcategory":"Real Estate Agent",
            "type":"Services"
        }
    ],
    "sg:phone":"+1 615 242 1122",
    "sg:postcode":"37201",
    "sg:province":"TN",
    "sg:tags":[
        "investing",
        "management",
        "commercial"
    ],
    "wof:name":"Robin Realty Co",
    "wof:placetype":"venue"
},
  "geometry": {"coordinates":[-86.77558500000001,36.162575],"type":"Point"}
}