{
  "type": "Feature",
  "properties": {
    "iso:country":"US",
    "sg:address":"3819 Dickerson Pike",
    "sg:city":"Nashville",
    "sg:classifiers":[
        {
            "category":"Professional",
            "subcategory":"Business Services",
            "type":"Services"
        }
    ],
    "sg:phone":"+1 615 366 1607",
    "sg:postcode":"37207",
    "sg:province":"TN",
    "sg:tags":[
        "repossessing"
    ],
    "wof:name":"Blessed Towing & Recovery",
    "wof:placetype":"venue"
},
  "geometry": {"coordinates":[-86.75689300000001,36.265285],"type":"Point"}
}