{
  "type": "Feature",
  "properties": {
    "iso:country":"US",
    "sg:address":"6161 Poplar Ave",
    "sg:city":"Memphis",
    "sg:classifiers":[
        {
            "category":"Coffee & Tea",
            "type":"Food & Drink"
        }
    ],
    "sg:menulink":"http://www.allmenus.com/tn/memphis/115362-starbucks-coffee/menu/",
    "sg:phone":"+1 901 818 9136",
    "sg:postcode":"38119",
    "sg:province":"TN",
    "sg:tags":[
        "american"
    ],
    "wof:name":"Starbucks Coffee",
    "wof:placetype":"venue"
},
  "geometry": {"coordinates":[-89.85761599999999,35.101552],"type":"Point"}
}