{
  "type": "Feature",
  "properties": {
    "addr:full":"3935 Ostella Rd Cornersville TN 37047",
    "addr:housenumber":"3935",
    "addr:postcode":"37047",
    "addr:street":"Ostella Rd",
    "iso:country":"US",
    "sg:address":"3935 Ostella Rd",
    "sg:city":"Cornersville",
    "sg:classifiers":[
        {
            "category":"Restaurant",
            "type":"Food & Drink"
        }
    ],
    "sg:phone":"+1 931 270 1591",
    "sg:postcode":"37047",
    "sg:province":"TN",
    "sg:tags":[
        "eating"
    ],
    "wof:name":"Highway 50 Drive In Theater",
    "wof:placetype":"venue"
},
  "geometry": {"coordinates":[-86.794853,35.322893],"type":"Point"}
}