{
  "type": "Feature",
  "properties": {
    "iso:country":"US",
    "sg:address":"2126 Abbott Martin Rd",
    "sg:city":"Nashville",
    "sg:classifiers":[
        {
            "category":"Shopping",
            "subcategory":"Optical Goods",
            "type":"Retail Goods"
        }
    ],
    "sg:phone":"+1 615 383 6629",
    "sg:postcode":"37215",
    "sg:province":"TN",
    "sg:tags":[
        "sun",
        "goggles",
        "sunglasses"
    ],
    "wof:name":"Cool Shades",
    "wof:placetype":"venue"
},
  "geometry": {"coordinates":[-86.81619499999999,36.106229],"type":"Point"}
}