{
  "type": "Feature",
  "properties": {
    "iso:country":"US",
    "sg:address":"339 Mahala Rd",
    "sg:city":"Sweetwater",
    "sg:classifiers":[
        {
            "category":"Retail",
            "subcategory":"Repair Shop",
            "type":"Services"
        }
    ],
    "sg:phone":"+1 423 337 6884",
    "sg:postcode":"37874",
    "sg:province":"TN",
    "sg:tags":[
        "electrical"
    ],
    "wof:name":"Waynes Appliance Service",
    "wof:placetype":"venue"
},
  "geometry": {"coordinates":[-84.446893,35.595703],"type":"Point"}
}