{
  "type": "Feature",
  "properties": {
    "iso:country":"US",
    "sg:address":"2018 Crencor Dr",
    "sg:city":"Goodlettsville",
    "sg:classifiers":[
        {
            "category":"Professional",
            "subcategory":"Management & Consulting",
            "type":"Services"
        }
    ],
    "sg:phone":"+1 615 851 6548",
    "sg:postcode":"37072",
    "sg:province":"TN",
    "sg:tags":[
        "aviation",
        "consultant"
    ],
    "wof:name":"Aviation Group Inc",
    "wof:placetype":"venue"
},
  "geometry": {"coordinates":[-86.691078,36.342286],"type":"Point"}
}