{
  "type": "Feature",
  "properties": {
    "iso:country":"US",
    "sg:address":"403 Bridgeway Ave",
    "sg:city":"Old Hickory",
    "sg:classifiers":[
        {
            "category":"Food & Beverages",
            "subcategory":"Groceries & Convenience Stores",
            "type":"Retail Goods"
        }
    ],
    "sg:phone":"+1 615 847 8481",
    "sg:postcode":"37138",
    "sg:province":"TN",
    "wof:name":"J & B Market",
    "wof:placetype":"venue"
},
  "geometry": {"coordinates":[-86.666409,36.26947],"type":"Point"}
}