{
  "type": "Feature",
  "properties": {
    "addr:full":"175 Beasley Dr Dickson TN 37055",
    "addr:housenumber":"175",
    "addr:postcode":"37055",
    "addr:street":"Beasley Dr",
    "iso:country":"US",
    "sg:address":"175 Beasley Dr",
    "sg:city":"Dickson",
    "sg:classifiers":[
        {
            "category":"Retail",
            "subcategory":"Portrait Studio",
            "type":"Services"
        }
    ],
    "sg:phone":"+1 615 446 9391",
    "sg:postcode":"37055",
    "sg:province":"TN",
    "sg:tags":[
        "photo"
    ],
    "wof:name":"Wal-Mart Portrait Studio",
    "wof:placetype":"venue"
},
  "geometry": {"coordinates":[-87.380134,36.062359],"type":"Point"}
}