{
  "type": "Feature",
  "properties": {
    "addr:full":"8526 Beersheba Hwy Mc Minnville TN 37110",
    "addr:housenumber":"8526",
    "addr:postcode":"37110",
    "addr:street":"Beersheba Hwy Mc Minnville",
    "iso:country":"US",
    "sg:address":"8526 Beersheba Hwy",
    "sg:city":"Mc Minnville",
    "sg:classifiers":[
        {
            "category":"Wholesale",
            "subcategory":"Plants",
            "type":"Manufacturing & Wholesale Goods"
        }
    ],
    "sg:phone":"+1 931 668 8022",
    "sg:postcode":"37110",
    "sg:province":"TN",
    "sg:tags":[
        "nursery",
        "grows",
        "stock"
    ],
    "wof:name":"Triangle Nursery Inc",
    "wof:placetype":"venue"
},
  "geometry": {"coordinates":[-85.712855,35.584574],"type":"Point"}
}