{
  "type": "Feature",
  "properties": {
    "iso:country":"US",
    "sg:address":"934 Looney Ave",
    "sg:city":"Memphis",
    "sg:classifiers":[
        {
            "category":"Organizations",
            "subcategory":"Religious Organization",
            "type":"Services"
        }
    ],
    "sg:phone":"+1 901 527 4188",
    "sg:postcode":"38107",
    "sg:province":"TN",
    "sg:tags":[
        "church"
    ],
    "wof:name":"Bethlehem Baptist Church",
    "wof:placetype":"venue"
},
  "geometry": {"coordinates":[-90.02655900000001,35.160583],"type":"Point"}
}