{
  "type": "Feature",
  "properties": {
    "iso:country":"US",
    "sg:address":"304 Carver Ln",
    "sg:city":"Lebanon",
    "sg:classifiers":[
        {
            "category":"Autos & Motor Vehicles",
            "subcategory":"Recreational Vehicle Sales",
            "type":"Retail Goods"
        }
    ],
    "sg:phone":"+1 615 444 3435",
    "sg:postcode":"37087",
    "sg:province":"TN",
    "wof:name":"Charlie Tatum Campers",
    "wof:placetype":"venue"
},
  "geometry": {"coordinates":[-86.332633,36.233217],"type":"Point"}
}