{
  "type": "Feature",
  "properties": {
    "iso:country":"US",
    "sg:address":"4039 Hillsboro Pike",
    "sg:city":"Nashville",
    "sg:classifiers":[
        {
            "category":"Food & Beverages",
            "subcategory":"Groceries & Convenience Stores",
            "type":"Retail Goods"
        }
    ],
    "sg:phone":"+1 615 292 5519",
    "sg:postcode":"37215",
    "sg:province":"TN",
    "sg:tags":[
        "grocer"
    ],
    "wof:name":"H G Hill Food Store",
    "wof:placetype":"venue"
},
  "geometry": {"coordinates":[-86.81776600000001,36.10197],"type":"Point"}
}