{
  "type": "Feature",
  "properties": {
    "addr:full":"3532 Calvert St Rockford TN 37853",
    "addr:housenumber":"3532",
    "addr:postcode":"37853",
    "addr:street":"Calvert St",
    "iso:country":"US",
    "sg:address":"3532 Calvert St",
    "sg:city":"Rockford",
    "sg:classifiers":[
        {
            "category":"Retail",
            "subcategory":"Car Wash",
            "type":"Services"
        }
    ],
    "sg:phone":"+1 865 983 4167",
    "sg:postcode":"37853",
    "sg:province":"TN",
    "sg:tags":[
        "carwash"
    ],
    "wof:name":"TS Detail",
    "wof:placetype":"venue"
},
  "geometry": {"coordinates":[-83.948751,35.819437],"type":"Point"}
}