{
  "type": "Feature",
  "properties": {
    "iso:country":"US",
    "sg:address":"4015 Travis Dr",
    "sg:city":"Nashville",
    "sg:classifiers":[
        {
            "category":"Professional",
            "subcategory":"Employment Agencies",
            "type":"Services"
        }
    ],
    "sg:phone":"+1 615 831 0300",
    "sg:postcode":"37211",
    "sg:province":"TN",
    "sg:tags":[
        "help",
        "contractor"
    ],
    "wof:name":"Alternative Staffing Concepts",
    "wof:placetype":"venue"
},
  "geometry": {"coordinates":[-86.725646,36.083626],"type":"Point"}
}