{
  "type": "Feature",
  "properties": {
    "addr:full":"101 Ringgold Rd Clarksville TN 37042",
    "addr:housenumber":"101",
    "addr:postcode":"37042",
    "addr:street":"Ringgold Rd",
    "iso:country":"US",
    "sg:address":"101 Ringgold Rd",
    "sg:city":"Clarksville",
    "sg:classifiers":[
        {
            "category":"Real Estate",
            "subcategory":"Real Estate Agent",
            "type":"Services"
        }
    ],
    "sg:phone":"+1 931 503 8000",
    "sg:postcode":"37042",
    "sg:province":"TN",
    "wof:name":"Prudential",
    "wof:placetype":"venue"
},
  "geometry": {"coordinates":[-87.417748,36.593944],"type":"Point"}
}