{
  "type": "Feature",
  "properties": {
    "iso:country":"US",
    "sg:address":"4800 Morgan Dr",
    "sg:city":"Old Hickory",
    "sg:classifiers":[
        {
            "category":"Wholesale",
            "subcategory":"Home Furnishings",
            "type":"Manufacturing & Wholesale Goods"
        }
    ],
    "sg:phone":"+1 615 758 5998",
    "sg:postcode":"37138",
    "sg:province":"TN",
    "wof:name":"M&M Crafts Co",
    "wof:placetype":"venue"
},
  "geometry": {"coordinates":[-86.580117,36.233226],"type":"Point"}
}