{
  "type": "Feature",
  "properties": {
    "iso:country":"US",
    "sg:address":"530 Grey Ln",
    "sg:city":"Greeneville",
    "sg:classifiers":[
        {
            "category":"Building & Trades",
            "subcategory":"Cleaning & Sanitation",
            "type":"Services"
        }
    ],
    "sg:phone":"+1 423 639 1410",
    "sg:postcode":"37743",
    "sg:province":"TN",
    "sg:tags":[
        "maintenance"
    ],
    "wof:name":"Appalachian Cleaning",
    "wof:placetype":"venue"
},
  "geometry": {"coordinates":[-82.80212299999999,36.108459],"type":"Point"}
}