{
  "type": "Feature",
  "properties": {
    "addr:full":"127 Franklin St Clarksville TN 37040",
    "addr:housenumber":"127",
    "addr:postcode":"37040",
    "addr:street":"Franklin St",
    "iso:country":"US",
    "sg:address":"127 Franklin St",
    "sg:city":"Clarksville",
    "sg:classifiers":[
        {
            "category":"Home & Garden",
            "subcategory":"Home Furnishings",
            "type":"Retail Goods"
        }
    ],
    "sg:phone":"+1 931 551 9800",
    "sg:postcode":"37040",
    "sg:province":"TN",
    "sg:tags":[
        "interior",
        "gift"
    ],
    "wof:name":"Traditions",
    "wof:placetype":"venue"
},
  "geometry": {"coordinates":[-87.359149,36.527597],"type":"Point"}
}