{
  "type": "Feature",
  "properties": {
    "iso:country":"US",
    "sg:address":"130 N Main St",
    "sg:city":"Clinton",
    "sg:classifiers":[
        {
            "category":"Education",
            "subcategory":"Library",
            "type":"Public Place"
        },
        {
            "category":"Government",
            "subcategory":"Office",
            "type":"Public Place"
        }
    ],
    "sg:phone":"+1 865 457 0931",
    "sg:postcode":"37716",
    "sg:province":"TN",
    "wof:name":"Clinch-Powell Regional Library",
    "wof:placetype":"venue"
},
  "geometry": {"coordinates":[-84.133081,36.10091],"type":"Point"}
}