{
  "type": "Feature",
  "properties": {
    "iso:country":"US",
    "sg:address":"2670 Memorial Blvd",
    "sg:city":"Murfreesboro",
    "sg:classifiers":[
        {
            "category":"Real Estate",
            "subcategory":"Real Estate Agent",
            "type":"Services"
        }
    ],
    "sg:phone":"+1 615 890 0750",
    "sg:postcode":"37129",
    "sg:province":"TN",
    "wof:name":"Fritzco Properties",
    "wof:placetype":"venue"
},
  "geometry": {"coordinates":[-86.39451200000001,35.855874],"type":"Point"}
}