{
  "type": "Feature",
  "properties": {
    "iso:country":"US",
    "sg:address":"3507 7th Ave",
    "sg:city":"Chattanooga",
    "sg:classifiers":[
        {
            "category":"Freight",
            "type":"Transportation"
        }
    ],
    "sg:phone":"+1 423 867 3554",
    "sg:postcode":"37407",
    "sg:province":"TN",
    "sg:tags":[
        "warehouse"
    ],
    "wof:name":"J D Helton Roofing Co",
    "wof:placetype":"venue"
},
  "geometry": {"coordinates":[-85.28466,35.001023],"type":"Point"}
}