{
  "type": "Feature",
  "properties": {
    "addr:full":"1135 Bell Rd Antioch TN 37013",
    "addr:housenumber":"1135",
    "addr:postcode":"37013",
    "addr:street":"Bell Rd",
    "iso:country":"US",
    "sg:address":"1135 Bell Rd",
    "sg:city":"Antioch",
    "sg:classifiers":[
        {
            "category":"Banks & Credit Unions",
            "subcategory":"Bank",
            "type":"Services"
        }
    ],
    "sg:phone":"+1 615 731 7787",
    "sg:postcode":"37013",
    "sg:province":"TN",
    "sg:tags":[
        "financing",
        "mortgage"
    ],
    "wof:name":"Citi Financial",
    "wof:placetype":"venue"
},
  "geometry": {"coordinates":[-86.66517899999999,36.045045],"type":"Point"}
}