{
  "type": "Feature",
  "properties": {
    "addr:full":"639 W Main St Hendersonville TN 37075",
    "addr:housenumber":"639",
    "addr:postcode":"37075",
    "addr:street":"W Main St",
    "iso:country":"US",
    "sg:address":"639 W Main St",
    "sg:city":"Hendersonville",
    "sg:classifiers":[
        {
            "category":"Autos & Motor Vehicles",
            "subcategory":"Auto Supplies",
            "type":"Retail Goods"
        }
    ],
    "sg:phone":"+1 615 264 4734",
    "sg:postcode":"37075",
    "sg:province":"TN",
    "sg:tags":[
        "automobile",
        "parts"
    ],
    "wof:name":"O'REILLY Auto Parts",
    "wof:placetype":"venue"
},
  "geometry": {"coordinates":[-86.639199,36.302851],"type":"Point"}
}