{
  "type": "Feature",
  "properties": {
    "iso:country":"US",
    "sg:address":"4560 Double Tree Rd",
    "sg:city":"Memphis",
    "sg:classifiers":[
        {
            "category":"Education",
            "subcategory":"School",
            "type":"Public Place"
        },
        {
            "category":"Government",
            "subcategory":"Office",
            "type":"Public Place"
        }
    ],
    "sg:phone":"+1 901 416 8144",
    "sg:postcode":"38109",
    "sg:province":"TN",
    "sg:website":"http://www.whitehaven95.com",
    "wof:name":"Double Tree School",
    "wof:placetype":"venue"
},
  "geometry": {"coordinates":[-90.10373300000001,35.023472],"type":"Point"}
}