{
  "type": "Feature",
  "properties": {
    "iso:country":"US",
    "sg:address":"25 Airport Rd",
    "sg:city":"Lexington",
    "sg:classifiers":[
        {
            "category":"Airport",
            "type":"Transportation"
        }
    ],
    "sg:phone":"+1 731 968 3666",
    "sg:postcode":"38351",
    "sg:province":"TN",
    "wof:name":"Franklins-Wilkins Airport",
    "wof:placetype":"venue"
},
  "geometry": {"coordinates":[-88.38232000000001,35.654496],"type":"Point"}
}