{
  "type": "Feature",
  "properties": {
    "addr:full":"2905 Cinder Ln Knoxville TN 37914",
    "addr:housenumber":"2905",
    "addr:postcode":"37914",
    "addr:street":"Cinder Ln",
    "iso:country":"US",
    "sg:address":"2905 Cinder Ln",
    "sg:city":"Knoxville",
    "sg:classifiers":[
        {
            "category":"Freight",
            "type":"Transportation"
        }
    ],
    "sg:phone":"+1 865 521 6161",
    "sg:postcode":"37914",
    "sg:province":"TN",
    "sg:tags":[
        "operator",
        "trucking"
    ],
    "sg:website":"www.watkins.com",
    "wof:name":"Watkins Motor Lines Inc",
    "wof:placetype":"venue"
},
  "geometry": {"coordinates":[-83.819506,35.961439],"type":"Point"}
}