{
  "type": "Feature",
  "properties": {
    "iso:country":"US",
    "sg:address":"1027 Whitney Ave",
    "sg:city":"Memphis",
    "sg:classifiers":[
        {
            "category":"Personal",
            "subcategory":"Beauty Salon",
            "type":"Services"
        }
    ],
    "sg:phone":"+1 901 357 4600",
    "sg:postcode":"38127",
    "sg:province":"TN",
    "sg:tags":[
        "shop"
    ],
    "wof:name":"Unique Touch of Style Salon",
    "wof:placetype":"venue"
},
  "geometry": {"coordinates":[-90.032028,35.209615],"type":"Point"}
}