{
  "type": "Feature",
  "properties": {
    "iso:country":"US",
    "sg:address":"1977 Kostka Ln",
    "sg:city":"Germantown",
    "sg:classifiers":[
        {
            "category":"Real Estate",
            "subcategory":"Real Estate Agent",
            "type":"Services"
        }
    ],
    "sg:phone":"+1 901 751 0590",
    "sg:postcode":"38139",
    "sg:province":"TN",
    "wof:name":"Rl Roberts and Associates LLC",
    "wof:placetype":"venue"
},
  "geometry": {"coordinates":[-89.759944,35.094517],"type":"Point"}
}