{
  "type": "Feature",
  "properties": {
    "iso:country":"US",
    "sg:address":"1009 Ruskin Dr",
    "sg:city":"Knoxville",
    "sg:classifiers":[
        {
            "category":"Organizations",
            "subcategory":"Membership Organization",
            "type":"Services"
        }
    ],
    "sg:phone":"+1 865 694 8223",
    "sg:postcode":"37923",
    "sg:province":"TN",
    "wof:name":"Servant Ministries",
    "wof:placetype":"venue"
},
  "geometry": {"coordinates":[-84.066474,35.936602],"type":"Point"}
}