{
  "type": "Feature",
  "properties": {
    "addr:full":"6400 Worchester Dr Nashville TN 37221",
    "addr:postcode":"6400;37221",
    "addr:street":"Worchester Dr",
    "iso:country":"US",
    "sg:address":"6400 Worchester Dr",
    "sg:city":"Nashville",
    "sg:classifiers":[
        {
            "category":"Building & Trades",
            "subcategory":"Construction",
            "type":"Services"
        }
    ],
    "sg:phone":"+1 615 373 4407",
    "sg:postcode":"37221",
    "sg:province":"TN",
    "sg:tags":[
        "contractor"
    ],
    "wof:name":"Patterson Contractors Inc",
    "wof:placetype":"venue"
},
  "geometry": {"coordinates":[-86.885606,36.049841],"type":"Point"}
}