{
  "type": "Feature",
  "properties": {
    "iso:country":"US",
    "sg:address":"3095 Lamar Ave",
    "sg:city":"Memphis",
    "sg:classifiers":[
        {
            "category":"Autos & Motor Vehicles",
            "subcategory":"Fuel & Gas Station",
            "type":"Retail Goods"
        }
    ],
    "sg:phone":"+1 901 743 9952",
    "sg:postcode":"38114",
    "sg:province":"TN",
    "sg:tags":[
        "oil"
    ],
    "wof:name":"Lucky's Citgo",
    "wof:placetype":"venue"
},
  "geometry": {"coordinates":[-89.959868,35.083783],"type":"Point"}
}