{
  "type": "Feature",
  "properties": {
    "addr:full":"36 Old Huntsville Rd Fayetteville TN 37334",
    "addr:housenumber":"36",
    "addr:postcode":"37334",
    "addr:street":"Old Huntsville Rd",
    "iso:country":"US",
    "sg:address":"36 Old Huntsville Rd",
    "sg:city":"Fayetteville",
    "sg:classifiers":[
        {
            "category":"Social Services",
            "subcategory":"Child Care",
            "type":"Services"
        }
    ],
    "sg:phone":"+1 931 433 1770",
    "sg:postcode":"37334",
    "sg:province":"TN",
    "sg:tags":[
        "day"
    ],
    "wof:name":"Miss Jans Day Care",
    "wof:placetype":"venue"
},
  "geometry": {"coordinates":[-86.590085,35.085628],"type":"Point"}
}