{
  "type": "Feature",
  "properties": {
    "addr:full":"1 Chadsworth Pl Tullahoma TN 37388",
    "addr:housenumber":"1",
    "addr:postcode":"37388",
    "addr:street":"Chadsworth Pl",
    "iso:country":"US",
    "sg:address":"1 Chadsworth Pl",
    "sg:city":"Tullahoma",
    "sg:classifiers":[
        {
            "category":"Shopping",
            "subcategory":"Used Merchandise",
            "type":"Retail Goods"
        }
    ],
    "sg:phone":"+1 931 455 2049",
    "sg:postcode":"37388",
    "sg:province":"TN",
    "wof:name":"Rose Cottage Antiques & Gifts",
    "wof:placetype":"venue"
},
  "geometry": {"coordinates":[-86.212946,35.394121],"type":"Point"}
}