{
  "type": "Feature",
  "properties": {
    "iso:country":"US",
    "sg:address":"3210 Thomas St",
    "sg:city":"Memphis",
    "sg:classifiers":[
        {
            "category":"Shopping",
            "subcategory":"Clothing, Apparel, & Fashions",
            "type":"Retail Goods"
        },
        {
            "category":"Shopping",
            "subcategory":"Beauty & Cosmetics",
            "type":"Retail Goods"
        },
        {
            "category":"Personal",
            "subcategory":"Barber",
            "type":"Services"
        },
        {
            "category":"Personal",
            "subcategory":"Beauty Salon",
            "type":"Services"
        }
    ],
    "sg:phone":"+1 901 353 6930",
    "sg:postcode":"38127",
    "sg:province":"TN",
    "sg:tags":[
        "supply",
        "women's",
        "hair",
        "equipment",
        "salons-equipment",
        "accessory",
        "apparel",
        "perfume"
    ],
    "wof:name":"Omni Fashions",
    "wof:placetype":"venue"
},
  "geometry": {"coordinates":[-90.03187200000001,35.213274],"type":"Point"}
}