{
  "type": "Feature",
  "properties": {
    "iso:country":"US",
    "sg:address":"1575 E McLemore Ave",
    "sg:city":"Memphis",
    "sg:classifiers":[
        {
            "category":"Communications",
            "subcategory":"Film & Video Production",
            "type":"Services"
        }
    ],
    "sg:phone":"+1 901 278 8771",
    "sg:postcode":"38106",
    "sg:province":"TN",
    "sg:tags":[
        "motion"
    ],
    "wof:name":"Digit Productions Inc",
    "wof:placetype":"venue"
},
  "geometry": {"coordinates":[-90.007267,35.115287],"type":"Point"}
}