{
  "type": "Feature",
  "properties": {
    "addr:full":"4664 Horn Lake Rd Memphis TN 38109",
    "addr:housenumber":"4664",
    "addr:postcode":"38109",
    "addr:street":"Horn Lake Rd",
    "iso:country":"US",
    "sg:address":"4664 Horn Lake Rd",
    "sg:city":"Memphis",
    "sg:classifiers":[
        {
            "category":"Personal",
            "subcategory":"Barber",
            "type":"Services"
        }
    ],
    "sg:phone":"+1 901 785 5912",
    "sg:postcode":"38109",
    "sg:province":"TN",
    "sg:tags":[
        "shop"
    ],
    "wof:name":"Thomas Barber Shop",
    "wof:placetype":"venue"
},
  "geometry": {"coordinates":[-90.068151,35.021089],"type":"Point"}
}