{
  "type": "Feature",
  "properties": {
    "iso:country":"US",
    "sg:address":"1221 Bedfordshire Ct",
    "sg:city":"Nashville",
    "sg:classifiers":[
        {
            "category":"Professional",
            "subcategory":"Art Services",
            "type":"Services"
        }
    ],
    "sg:phone":"+1 615 662 5465",
    "sg:postcode":"37221",
    "sg:province":"TN",
    "sg:tags":[
        "commercial",
        "photography",
        "datum"
    ],
    "sg:website":"www.vision3.com",
    "wof:name":"Vision 3",
    "wof:placetype":"venue"
},
  "geometry": {"coordinates":[-86.922752,36.060313],"type":"Point"}
}