{
  "type": "Feature",
  "properties": {
    "iso:country":"US",
    "sg:address":"80 Munford-Atoka Ave",
    "sg:city":"Munford",
    "sg:classifiers":[
        {
            "category":"Freight",
            "type":"Transportation"
        }
    ],
    "sg:phone":"+1 901 837 0076",
    "sg:postcode":"38058",
    "sg:province":"TN",
    "sg:tags":[
        "storage"
    ],
    "wof:name":"Munford Mini Storage",
    "wof:placetype":"venue"
},
  "geometry": {"coordinates":[-89.79353500000001,35.445533],"type":"Point"}
}