{
  "type": "Feature",
  "properties": {
    "iso:country":"US",
    "sg:address":"1593 Old Columbia Rd",
    "sg:city":"Lewisburg",
    "sg:classifiers":[
        {
            "category":"Government",
            "subcategory":"Office",
            "type":"Public Place"
        }
    ],
    "sg:phone":"+1 931 359 4866",
    "sg:postcode":"37091",
    "sg:province":"TN",
    "sg:tags":[
        "county"
    ],
    "wof:name":"Marshall County Sch Garage",
    "wof:placetype":"venue"
},
  "geometry": {"coordinates":[-86.81357,35.46026],"type":"Point"}
}