{
  "type": "Feature",
  "properties": {
    "iso:country":"US",
    "sg:address":"1583 N Hollywood St",
    "sg:city":"Memphis",
    "sg:classifiers":[
        {
            "category":"Real Estate",
            "subcategory":"Developer",
            "type":"Services"
        }
    ],
    "sg:phone":"+1 901 454 7041",
    "sg:postcode":"38108",
    "sg:province":"TN",
    "wof:name":"Nevets Comm Housing Dev Org",
    "wof:placetype":"venue"
},
  "geometry": {"coordinates":[-89.975251,35.179274],"type":"Point"}
}