{
  "type": "Feature",
  "properties": {
    "iso:country":"US",
    "sg:address":"676 Huron Ave",
    "sg:city":"Memphis",
    "sg:classifiers":[
        {
            "category":"Food & Beverages",
            "subcategory":"Specialty",
            "type":"Retail Goods"
        },
        {
            "category":"Manufacturing",
            "subcategory":"Food",
            "type":"Manufacturing & Wholesale Goods"
        }
    ],
    "sg:phone":"+1 901 525 4422",
    "sg:postcode":"38107",
    "sg:province":"TN",
    "sg:tags":[
        "product",
        "manufacturer",
        "spice"
    ],
    "wof:name":"Ingredients Corp Of America",
    "wof:placetype":"venue"
},
  "geometry": {"coordinates":[-90.035758,35.177611],"type":"Point"}
}