{
  "type": "Feature",
  "properties": {
    "iso:country":"US",
    "sg:address":"1005 Red Oak Dr",
    "sg:city":"Greenbrier",
    "sg:classifiers":[
        {
            "category":"Building & Trades",
            "subcategory":"Construction",
            "type":"Services"
        }
    ],
    "sg:phone":"+1 615 859 0278",
    "sg:postcode":"37073",
    "sg:province":"TN",
    "sg:tags":[
        "home",
        "builder"
    ],
    "wof:name":"John Carpenter Homes Inc",
    "wof:placetype":"venue"
},
  "geometry": {"coordinates":[-86.774812,36.407303],"type":"Point"}
}