{
  "type": "Feature",
  "properties": {
    "iso:country":"US",
    "sg:address":"1509 N Main St",
    "sg:city":"Shelbyville",
    "sg:classifiers":[
        {
            "category":"Health Services",
            "subcategory":"Chiropractor",
            "type":"Services"
        }
    ],
    "sg:phone":"+1 931 685 0040",
    "sg:postcode":"37160",
    "sg:province":"TN",
    "wof:name":"Bedford County Chiropractic",
    "wof:placetype":"venue"
},
  "geometry": {"coordinates":[-86.45711300000001,35.505085],"type":"Point"}
}