{
  "type": "Feature",
  "properties": {
    "iso:country":"US",
    "sg:address":"3615 Ringgold Rd",
    "sg:city":"Chattanooga",
    "sg:classifiers":[
        {
            "category":"Banks & Credit Unions",
            "subcategory":"Bank",
            "type":"Services"
        }
    ],
    "sg:phone":"+1 423 698 4407",
    "sg:postcode":"37412",
    "sg:province":"TN",
    "sg:tags":[
        "loan",
        "real estate"
    ],
    "wof:name":"Citizens Savings & Loan",
    "wof:placetype":"venue"
},
  "geometry": {"coordinates":[-85.25855199999999,35.001696],"type":"Point"}
}