{
  "type": "Feature",
  "properties": {
    "iso:country":"US",
    "sg:address":"695 Emory Valley Rd",
    "sg:city":"Oak Ridge",
    "sg:classifiers":[
        {
            "category":"Personal",
            "type":"Services"
        }
    ],
    "sg:phone":"+1 865 483 2826",
    "sg:postcode":"37830",
    "sg:province":"TN",
    "wof:name":"Tropical Tans",
    "wof:placetype":"venue"
},
  "geometry": {"coordinates":[-84.22775300000001,36.020994],"type":"Point"}
}