{
  "type": "Feature",
  "properties": {
    "addr:full":"2771 Clarke Rd Memphis TN 38115",
    "addr:housenumber":"2771",
    "addr:postcode":"38115",
    "addr:street":"Clarke Rd",
    "iso:country":"US",
    "sg:address":"2771 Clarke Rd",
    "sg:city":"Memphis",
    "sg:classifiers":[
        {
            "category":"Recreation",
            "type":"Entertainment"
        }
    ],
    "sg:phone":"+1 901 362 5612",
    "sg:postcode":"38115",
    "sg:province":"TN",
    "sg:tags":[
        "martial",
        "arts",
        "instruction"
    ],
    "wof:name":"Midsouth Martial Arts",
    "wof:placetype":"venue"
},
  "geometry": {"coordinates":[-89.87553200000001,35.072375],"type":"Point"}
}