{
  "type": "Feature",
  "properties": {
    "addr:full":"1755 Hwy 48 Clarksville TN 37040",
    "addr:housenumber":"1755",
    "addr:postcode":"37040",
    "addr:street":"Hwy 48",
    "iso:country":"US",
    "sg:address":"1755 Hwy 48",
    "sg:city":"Clarksville",
    "sg:classifiers":[
        {
            "category":"Restaurant",
            "type":"Food & Drink"
        }
    ],
    "sg:phone":"+1 931 552 0660",
    "sg:postcode":"37040",
    "sg:province":"TN",
    "sg:tags":[
        "eating"
    ],
    "wof:name":"Central Pizza",
    "wof:placetype":"venue"
},
  "geometry": {"coordinates":[-87.377049,36.473155],"type":"Point"}
}