{
  "type": "Feature",
  "properties": {
    "iso:country":"US",
    "sg:address":"1730 Sunshine Rd",
    "sg:city":"Henderson",
    "sg:classifiers":[
        {
            "category":"Wholesale",
            "subcategory":"Construction Materials",
            "type":"Manufacturing & Wholesale Goods"
        }
    ],
    "sg:phone":"+1 731 989 4141",
    "sg:postcode":"38340",
    "sg:province":"TN",
    "sg:tags":[
        "sand",
        "gravel"
    ],
    "wof:name":"Tri State Express",
    "wof:placetype":"venue"
},
  "geometry": {"coordinates":[-88.688936,35.370769],"type":"Point"}
}