{
  "type": "Feature",
  "properties": {
    "iso:country":"US",
    "sg:address":"741 Old Hwy 79",
    "sg:city":"Dover",
    "sg:classifiers":[
        {
            "category":"Personal",
            "type":"Services"
        }
    ],
    "sg:phone":"+1 931 232 8306",
    "sg:postcode":"37058",
    "sg:province":"TN",
    "sg:tags":[
        "general"
    ],
    "wof:name":"Regional Contracting",
    "wof:placetype":"venue"
},
  "geometry": {"coordinates":[-87.80167899999999,36.512565],"type":"Point"}
}