{
  "type": "Feature",
  "properties": {
    "iso:country":"US",
    "sg:address":"930 Hairetown Rd",
    "sg:city":"Jonesborough",
    "sg:classifiers":[
        {
            "category":"Retail",
            "subcategory":"Auto Repair",
            "type":"Services"
        }
    ],
    "sg:phone":"+1 423 753 8237",
    "sg:postcode":"37659",
    "sg:province":"TN",
    "sg:tags":[
        "wrecker"
    ],
    "wof:name":"Jerry's Towing Svc",
    "wof:placetype":"venue"
},
  "geometry": {"coordinates":[-82.483467,36.336783],"type":"Point"}
}