{
  "type": "Feature",
  "properties": {
    "iso:country":"US",
    "sg:address":"815 N Broadway St",
    "sg:city":"Knoxville",
    "sg:classifiers":[
        {
            "category":"Social Services",
            "subcategory":"Child Care",
            "type":"Services"
        }
    ],
    "sg:phone":"+1 865 523 5442",
    "sg:postcode":"37917",
    "sg:province":"TN",
    "sg:tags":[
        "organization",
        "religious",
        "day"
    ],
    "wof:name":"Broadway Baptist Church",
    "wof:placetype":"venue"
},
  "geometry": {"coordinates":[-83.923546,35.979457],"type":"Point"}
}