{
  "type": "Feature",
  "properties": {
    "iso:country":"US",
    "sg:address":"2835 Jimtown Rd",
    "sg:city":"Lafayette",
    "sg:classifiers":[
        {
            "category":"Retail",
            "subcategory":"Repair Shop",
            "type":"Services"
        }
    ],
    "sg:phone":"+1 615 688 5544",
    "sg:postcode":"37083",
    "sg:province":"TN",
    "sg:tags":[
        "taxidermist"
    ],
    "wof:name":"Terry's Taxidermy",
    "wof:placetype":"venue"
},
  "geometry": {"coordinates":[-85.90344399999999,36.548879],"type":"Point"}
}