{
  "type": "Feature",
  "properties": {
    "addr:full":"1517 Derby Trce Nashville TN 37211",
    "addr:housenumber":"1517",
    "addr:postcode":"37211",
    "addr:street":"Derby Trce",
    "iso:country":"US",
    "sg:address":"1517 Derby Trce",
    "sg:city":"Nashville",
    "sg:classifiers":[
        {
            "category":"Organizations",
            "subcategory":"Non-profit Organization",
            "type":"Services"
        }
    ],
    "sg:phone":"+1 615 833 4244",
    "sg:postcode":"37211",
    "sg:province":"TN",
    "wof:name":"Compassion International Inc",
    "wof:placetype":"venue"
},
  "geometry": {"coordinates":[-86.74378299999999,36.046203],"type":"Point"}
}