{
  "type": "Feature",
  "properties": {
    "iso:country":"US",
    "sg:address":"171 S Tennessee Ave",
    "sg:city":"La Follette",
    "sg:classifiers":[
        {
            "category":"Banks & Credit Unions",
            "subcategory":"Bank",
            "type":"Services"
        }
    ],
    "sg:phone":"+1 423 566 6864",
    "sg:postcode":"37766",
    "sg:province":"TN",
    "sg:tags":[
        "personal",
        "institution"
    ],
    "wof:name":"Beacon Finance Corp",
    "wof:placetype":"venue"
},
  "geometry": {"coordinates":[-84.121976,36.380051],"type":"Point"}
}