{
  "type": "Feature",
  "properties": {
    "iso:country":"US",
    "sg:address":"105 Lincoln Ave N",
    "sg:city":"Fayetteville",
    "sg:classifiers":[
        {
            "category":"Wholesale",
            "subcategory":"Auto Parts",
            "type":"Manufacturing & Wholesale Goods"
        }
    ],
    "sg:phone":"+1 931 433 6191",
    "sg:postcode":"37334",
    "sg:province":"TN",
    "wof:name":"Shrader Auto Parts & Supply Co",
    "wof:placetype":"venue"
},
  "geometry": {"coordinates":[-86.571715,35.153183],"type":"Point"}
}