{
  "type": "Feature",
  "properties": {
    "iso:country":"US",
    "sg:address":"6375 Old Mount Helen Rd",
    "sg:city":"Allardt",
    "sg:classifiers":[
        {
            "category":"Farming",
            "subcategory":"Fish & Marine Products",
            "type":"Manufacturing & Wholesale Goods"
        }
    ],
    "sg:phone":"+1 931 879 9796",
    "sg:postcode":"38504",
    "sg:province":"TN",
    "sg:tags":[
        "management"
    ],
    "wof:name":"Honey Creek Hunting Preserve",
    "wof:placetype":"venue"
},
  "geometry": {"coordinates":[-84.714725,36.418099],"type":"Point"}
}