{
  "type": "Feature",
  "properties": {
    "iso:country":"US",
    "sg:address":"6580 Austin Peay Hwy",
    "sg:city":"Arlington",
    "sg:classifiers":[
        {
            "category":"Building & Trades",
            "subcategory":"Landscaping Services",
            "type":"Services"
        }
    ],
    "sg:phone":"+1 901 872 4189",
    "sg:postcode":"38002",
    "sg:province":"TN",
    "wof:name":"Bryants Tree Sewrvices Company",
    "wof:placetype":"venue"
},
  "geometry": {"coordinates":[-89.824354,35.306149],"type":"Point"}
}