{
  "type": "Feature",
  "properties": {
    "iso:country":"US",
    "sg:address":"1615 Old Niles Ferry Rd",
    "sg:city":"Maryville",
    "sg:classifiers":[
        {
            "category":"Personal",
            "subcategory":"Beauty Salon",
            "type":"Services"
        }
    ],
    "sg:phone":"+1 865 984 7115",
    "sg:postcode":"37803",
    "sg:province":"TN",
    "sg:tags":[
        "shop"
    ],
    "wof:name":"Nail Cottage",
    "wof:placetype":"venue"
},
  "geometry": {"coordinates":[-83.98827,35.737509],"type":"Point"}
}