{
  "type": "Feature",
  "properties": {
    "addr:full":"1015 Jefferson St Nashville TN 37208",
    "addr:housenumber":"1015",
    "addr:postcode":"37208",
    "addr:street":"Jefferson St",
    "iso:country":"US",
    "sg:address":"1015 Jefferson St",
    "sg:city":"Nashville",
    "sg:classifiers":[
        {
            "category":"Shopping",
            "subcategory":"Discount & Variety Stores",
            "type":"Retail Goods"
        },
        {
            "category":"Shopping",
            "subcategory":"Department Store",
            "type":"Retail Goods"
        }
    ],
    "sg:phone":"+1 615 244 2312",
    "sg:postcode":"37208",
    "sg:province":"TN",
    "wof:name":"Family Dollar Stores",
    "wof:placetype":"venue"
},
  "geometry": {"coordinates":[-86.795305,36.172245],"type":"Point"}
}