{
  "type": "Feature",
  "properties": {
    "iso:country":"US",
    "sg:address":"512 Hogan Rd",
    "sg:city":"Nashville",
    "sg:classifiers":[
        {
            "category":"Retail",
            "subcategory":"Repair Shop",
            "type":"Services"
        },
        {
            "category":"Manufacturing",
            "subcategory":"Furniture",
            "type":"Manufacturing & Wholesale Goods"
        }
    ],
    "sg:phone":"+1 615 333 3124",
    "sg:postcode":"37220",
    "sg:province":"TN",
    "sg:tags":[
        "upholstered",
        "household",
        "upholsterer",
        "mfg"
    ],
    "wof:name":"Tate's Upholstery",
    "wof:placetype":"venue"
},
  "geometry": {"coordinates":[-86.760171,36.065333],"type":"Point"}
}