{
  "type": "Feature",
  "properties": {
    "iso:country":"US",
    "sg:address":"7740 Trinity Rd",
    "sg:city":"Cordova",
    "sg:classifiers":[
        {
            "category":"Professional",
            "subcategory":"Art Services",
            "type":"Services"
        }
    ],
    "sg:phone":"+1 901 755 3619",
    "sg:postcode":"38018",
    "sg:province":"TN",
    "sg:tags":[
        "photography",
        "commercial"
    ],
    "wof:name":"Megapixil Photography",
    "wof:placetype":"venue"
},
  "geometry": {"coordinates":[-89.80545600000001,35.13938],"type":"Point"}
}