{
  "type": "Feature",
  "properties": {
    "iso:country":"US",
    "sg:address":"321 Woods Rd",
    "sg:city":"Portland",
    "sg:classifiers":[
        {
            "category":"Manufacturing",
            "subcategory":"Furniture",
            "type":"Manufacturing & Wholesale Goods"
        }
    ],
    "sg:phone":"+1 615 325 9873",
    "sg:postcode":"37148",
    "sg:province":"TN",
    "sg:tags":[
        "household",
        "wood",
        "mfg"
    ],
    "wof:name":"Groovenutcasecocom",
    "wof:placetype":"venue"
},
  "geometry": {"coordinates":[-86.541411,36.621685],"type":"Point"}
}