{
  "type": "Feature",
  "properties": {
    "iso:country":"US",
    "sg:address":"1458 W Poplar Ave",
    "sg:city":"Collierville",
    "sg:classifiers":[
        {
            "category":"Health Services",
            "subcategory":"Doctor",
            "type":"Services"
        }
    ],
    "sg:phone":"+1 901 850 1150",
    "sg:postcode":"38017",
    "sg:province":"TN",
    "sg:tags":[
        "medical"
    ],
    "wof:name":"Collirville Orthpd Spt Medicne",
    "wof:placetype":"venue"
},
  "geometry": {"coordinates":[-89.710358,35.047135],"type":"Point"}
}