{
  "type": "Feature",
  "properties": {
    "iso:country":"US",
    "sg:address":"10000 Parkside Dr",
    "sg:city":"Knoxville",
    "sg:classifiers":[
        {
            "category":"Real Estate",
            "subcategory":"Real Estate Agent",
            "type":"Services"
        }
    ],
    "sg:phone":"+1 865 691 4933",
    "sg:postcode":"37922",
    "sg:province":"TN",
    "sg:tags":[
        "agency",
        "rental"
    ],
    "wof:name":"MSP Rents",
    "wof:placetype":"venue"
},
  "geometry": {"coordinates":[-84.11672900000001,35.909528],"type":"Point"}
}