{
  "type": "Feature",
  "properties": {
    "iso:country":"US",
    "sg:address":"7856 Deer Lake Dr",
    "sg:city":"Millington",
    "sg:classifiers":[
        {
            "category":"Manufacturing",
            "subcategory":"Signs",
            "type":"Manufacturing & Wholesale Goods"
        }
    ],
    "sg:phone":"+1 901 876 5742",
    "sg:postcode":"38053",
    "sg:province":"TN",
    "sg:tags":[
        "specialty",
        "mfg"
    ],
    "wof:name":"Signs First LLC",
    "wof:placetype":"venue"
},
  "geometry": {"coordinates":[-89.99777,35.341157],"type":"Point"}
}