{
  "type": "Feature",
  "properties": {
    "addr:full":"101 N Maple Ave Ethridge TN 38456",
    "addr:housenumber":"101",
    "addr:postcode":"38456",
    "addr:street":"N Maple Ave",
    "iso:country":"US",
    "sg:address":"101 N Maple Ave",
    "sg:city":"Ethridge",
    "sg:classifiers":[
        {
            "category":"Farming",
            "subcategory":"Farm",
            "type":"Manufacturing & Wholesale Goods"
        }
    ],
    "sg:phone":"+1 931 829 2582",
    "sg:postcode":"38456",
    "sg:province":"TN",
    "sg:tags":[
        "crop",
        "general"
    ],
    "wof:name":"Tom Hudson",
    "wof:placetype":"venue"
},
  "geometry": {"coordinates":[-87.307076,35.324684],"type":"Point"}
}