{
  "type": "Feature",
  "properties": {
    "iso:country":"US",
    "sg:address":"2396 Hwy 70 E",
    "sg:city":"Cookeville",
    "sg:classifiers":[
        {
            "category":"Building & Trades",
            "subcategory":"Landscaping Services",
            "type":"Services"
        }
    ],
    "sg:phone":"+1 931 520 0529",
    "sg:postcode":"38506",
    "sg:province":"TN",
    "wof:name":"Little Boys Lawn Service LLC",
    "wof:placetype":"venue"
},
  "geometry": {"coordinates":[-85.450711,36.118272],"type":"Point"}
}