{
  "type": "Feature",
  "properties": {
    "addr:full":"224 S Maple St Adamsville TN 38310",
    "addr:housenumber":"224",
    "addr:postcode":"38310",
    "addr:street":"S Maple St",
    "iso:country":"US",
    "sg:address":"224 S Maple St",
    "sg:city":"Adamsville",
    "sg:classifiers":[
        {
            "category":"Personal",
            "subcategory":"Tanning Parlor",
            "type":"Services"
        }
    ],
    "sg:phone":"+1 731 632 4243",
    "sg:postcode":"38310",
    "sg:province":"TN",
    "sg:tags":[
        "salon"
    ],
    "wof:name":"Tan World",
    "wof:placetype":"venue"
},
  "geometry": {"coordinates":[-88.39087600000001,35.23403],"type":"Point"}
}