{
  "type": "Feature",
  "properties": {
    "iso:country":"US",
    "sg:address":"3110 S Perkins Rd",
    "sg:city":"Memphis",
    "sg:classifiers":[
        {
            "category":"Shopping",
            "subcategory":"Discount & Variety Stores",
            "type":"Retail Goods"
        }
    ],
    "sg:phone":"+1 901 565 9798",
    "sg:postcode":"38118",
    "sg:province":"TN",
    "sg:tags":[
        "oriental"
    ],
    "wof:name":"Chi's Oriental Food Vinh",
    "wof:placetype":"venue"
},
  "geometry": {"coordinates":[-89.905737,35.06337],"type":"Point"}
}