{
  "type": "Feature",
  "properties": {
    "iso:country":"US",
    "sg:address":"2907 Lone Oak Dr",
    "sg:city":"Murfreesboro",
    "sg:classifiers":[
        {
            "category":"Professional",
            "type":"Services"
        }
    ],
    "sg:phone":"+1 615 893 4205",
    "sg:postcode":"37128",
    "sg:province":"TN",
    "wof:name":"Rithm Rite Inc",
    "wof:placetype":"venue"
},
  "geometry": {"coordinates":[-86.41893399999999,35.7897],"type":"Point"}
}