{
  "type": "Feature",
  "properties": {
    "iso:country":"US",
    "sg:address":"4333 Sparta Hwy",
    "sg:city":"Mc Minnville",
    "sg:classifiers":[
        {
            "category":"Retail",
            "subcategory":"Auto Repair",
            "type":"Services"
        }
    ],
    "sg:phone":"+1 931 668 4566",
    "sg:postcode":"37110",
    "sg:province":"TN",
    "sg:tags":[
        "body"
    ],
    "wof:name":"Option Moto",
    "wof:placetype":"venue"
},
  "geometry": {"coordinates":[-85.716514,35.714634],"type":"Point"}
}