{
  "type": "Feature",
  "properties": {
    "addr:full":"2308 Sycamore Dr Knoxville TN 37921",
    "addr:housenumber":"2308",
    "addr:postcode":"37921",
    "addr:street":"Sycamore Dr",
    "iso:country":"US",
    "sg:address":"2308 Sycamore Dr",
    "sg:city":"Knoxville",
    "sg:classifiers":[
        {
            "category":"Building & Trades",
            "subcategory":"Plumbing",
            "type":"Services"
        }
    ],
    "sg:phone":"+1 865 584 3367",
    "sg:postcode":"37921",
    "sg:province":"TN",
    "sg:tags":[
        "plumbing",
        "contractor"
    ],
    "wof:name":"Cureton Hodges Contractors LLC",
    "wof:placetype":"venue"
},
  "geometry": {"coordinates":[-83.970451,35.979798],"type":"Point"}
}