{
  "type": "Feature",
  "properties": {
    "iso:country":"US",
    "sg:address":"457 Clinch Valley Rd",
    "sg:city":"Luttrell",
    "sg:classifiers":[
        {
            "category":"Social Services",
            "type":"Services"
        }
    ],
    "sg:phone":"+1 865 992 9886",
    "sg:postcode":"37779",
    "sg:province":"TN",
    "sg:tags":[
        "senior",
        "citizen"
    ],
    "wof:name":"Senior Citizens Home Assistanc",
    "wof:placetype":"venue"
},
  "geometry": {"coordinates":[-83.72147200000001,36.227034],"type":"Point"}
}