{
  "type": "Feature",
  "properties": {
    "iso:country":"US",
    "sg:address":"8912 Town and Country Cir",
    "sg:city":"Knoxville",
    "sg:classifiers":[
        {
            "category":"Health Services",
            "subcategory":"Doctor",
            "type":"Services"
        }
    ],
    "sg:phone":"+1 865 531 4633",
    "sg:postcode":"37923",
    "sg:province":"TN",
    "wof:name":"Kilgord Ronald L DDS",
    "wof:placetype":"venue"
},
  "geometry": {"coordinates":[-84.084333,35.9171],"type":"Point"}
}