{
  "type": "Feature",
  "properties": {
    "iso:country":"US",
    "sg:address":"1834 Breckenridge Dr",
    "sg:city":"Murfreesboro",
    "sg:classifiers":[
        {
            "category":"Building & Trades",
            "subcategory":"Construction",
            "type":"Services"
        }
    ],
    "sg:phone":"+1 615 217 9743",
    "sg:postcode":"37129",
    "sg:province":"TN",
    "sg:tags":[
        "house"
    ],
    "wof:name":"Watts Construction Inc",
    "wof:placetype":"venue"
},
  "geometry": {"coordinates":[-86.41728000000001,35.900424],"type":"Point"}
}