{
  "type": "Feature",
  "properties": {
    "iso:country":"US",
    "sg:address":"625 S Jackson St",
    "sg:city":"Morristown",
    "sg:classifiers":[
        {
            "category":"Government",
            "subcategory":"Fire Station",
            "type":"Public Place"
        }
    ],
    "sg:phone":"+1 423 586 5072",
    "sg:postcode":"37813",
    "sg:province":"TN",
    "sg:tags":[
        "department"
    ],
    "wof:name":"Morristown City Fire Dept",
    "wof:placetype":"venue"
},
  "geometry": {"coordinates":[-83.293395,36.206163],"type":"Point"}
}