{
  "type": "Feature",
  "properties": {
    "addr:full":"1655 Lowland Pike Morristown TN 37813",
    "addr:housenumber":"1655",
    "addr:postcode":"37813",
    "addr:street":"Lowland Pike",
    "iso:country":"US",
    "sg:address":"1655 Lowland Pike",
    "sg:city":"Morristown",
    "sg:classifiers":[
        {
            "category":"Professional",
            "subcategory":"Management & Consulting",
            "type":"Services"
        }
    ],
    "sg:phone":"+1 423 587 4254",
    "sg:postcode":"37813",
    "sg:province":"TN",
    "wof:name":"Virtual Humn Rsource Solutions",
    "wof:placetype":"venue"
},
  "geometry": {"coordinates":[-83.243756,36.178877],"type":"Point"}
}