{
  "type": "Feature",
  "properties": {
    "addr:full":"5360 Edmondson Pike Nashville TN 37211",
    "addr:housenumber":"5360",
    "addr:postcode":"37211",
    "addr:street":"Edmondson Pike",
    "iso:country":"US",
    "sg:address":"5360 Edmondson Pike",
    "sg:city":"Nashville",
    "sg:classifiers":[
        {
            "category":"Professional",
            "type":"Services"
        }
    ],
    "sg:phone":"+1 615 332 3112",
    "sg:postcode":"37211",
    "sg:province":"TN",
    "sg:tags":[
        "establishment"
    ],
    "wof:name":"Jonah Reed Productions",
    "wof:placetype":"venue"
},
  "geometry": {"coordinates":[-86.74338,36.050512],"type":"Point"}
}