{
  "type": "Feature",
  "properties": {
    "addr:full":"211 Fawn Wood Ct Nashville TN 37207",
    "addr:housenumber":"211",
    "addr:postcode":"37207",
    "addr:street":"Fawn Wood Ct",
    "iso:country":"US",
    "sg:address":"211 Fawn Wood Ct",
    "sg:city":"Nashville",
    "sg:classifiers":[
        {
            "category":"Building & Trades",
            "subcategory":"Cleaning & Sanitation",
            "type":"Services"
        }
    ],
    "sg:phone":"+1 615 650 5447",
    "sg:postcode":"37207",
    "sg:province":"TN",
    "sg:tags":[
        "maintenance"
    ],
    "wof:name":"Davidson Janitorial LLC",
    "wof:placetype":"venue"
},
  "geometry": {"coordinates":[-86.774366,36.244241],"type":"Point"}
}