{
  "type": "Feature",
  "properties": {
    "iso:country":"US",
    "sg:address":"900 Conference Dr",
    "sg:city":"Goodlettsville",
    "sg:classifiers":[
        {
            "category":"Home & Garden",
            "subcategory":"Carpets & Floor Coverings",
            "type":"Retail Goods"
        }
    ],
    "sg:phone":"+1 615 859 4334",
    "sg:postcode":"37072",
    "sg:province":"TN",
    "wof:name":"Flooring Solutions",
    "wof:placetype":"venue"
},
  "geometry": {"coordinates":[-86.701082,36.323522],"type":"Point"}
}