{
  "type": "Feature",
  "properties": {
    "iso:country":"US",
    "sg:address":"5543 Edmondson Pike",
    "sg:city":"Nashville",
    "sg:classifiers":[
        {
            "category":"Arts & Performance",
            "subcategory":"Theater",
            "type":"Entertainment"
        }
    ],
    "sg:phone":"+1 615 717 6262",
    "sg:postcode":"37211",
    "sg:province":"TN",
    "sg:tags":[
        "talent",
        "agency",
        "casting"
    ],
    "wof:name":"Us Talent Showcase",
    "wof:placetype":"venue"
},
  "geometry": {"coordinates":[-86.743776,36.040976],"type":"Point"}
}