{
  "type": "Feature",
  "properties": {
    "iso:country":"US",
    "sg:address":"706 S Highland St",
    "sg:city":"Memphis",
    "sg:classifiers":[
        {
            "category":"Place Of Worship",
            "subcategory":"Church",
            "type":"Public Place"
        }
    ],
    "sg:phone":"+1 901 323 3817",
    "sg:postcode":"38111",
    "sg:province":"TN",
    "sg:tags":[
        "churches-catholic"
    ],
    "wof:name":"St Anne Church",
    "wof:placetype":"venue"
},
  "geometry": {"coordinates":[-89.94586200000001,35.112511],"type":"Point"}
}