{
  "type": "Feature",
  "properties": {
    "iso:country":"US",
    "sg:address":"905 Pickwick St S",
    "sg:city":"Savannah",
    "sg:classifiers":[
        {
            "category":"Home & Garden",
            "subcategory":"Carpets & Floor Coverings",
            "type":"Retail Goods"
        }
    ],
    "sg:phone":"+1 731 925 5242",
    "sg:postcode":"38372",
    "sg:province":"TN",
    "sg:tags":[
        "dealer",
        "rug"
    ],
    "wof:name":"Home Decor Floors & Wallpaper",
    "wof:placetype":"venue"
},
  "geometry": {"coordinates":[-88.24508899999999,35.211236],"type":"Point"}
}