{
  "type": "Feature",
  "properties": {
    "addr:full":"2903 Memorial Blvd Springfield TN 37172",
    "addr:housenumber":"2903",
    "addr:postcode":"37172",
    "addr:street":"Memorial Blvd",
    "iso:country":"US",
    "sg:address":"2903 Memorial Blvd",
    "sg:city":"Springfield",
    "sg:classifiers":[
        {
            "category":"Shopping",
            "subcategory":"Stationery & Office Supplies",
            "type":"Retail Goods"
        }
    ],
    "sg:phone":"+1 615 384 4044",
    "sg:postcode":"37172",
    "sg:province":"TN",
    "wof:name":"Officeworks",
    "wof:placetype":"venue"
},
  "geometry": {"coordinates":[-86.864698,36.487035],"type":"Point"}
}