{
  "type": "Feature",
  "properties": {
    "iso:country":"US",
    "sg:address":"2485 Lake Rd",
    "sg:city":"Dyersburg",
    "sg:classifiers":[
        {
            "category":"Restaurant",
            "type":"Food & Drink"
        }
    ],
    "sg:phone":"+1 731 285 0361",
    "sg:postcode":"38024",
    "sg:province":"TN",
    "sg:tags":[
        "fast"
    ],
    "wof:name":"Wendys",
    "wof:placetype":"venue"
},
  "geometry": {"coordinates":[-89.395538,36.061935],"type":"Point"}
}