{
  "type": "Feature",
  "properties": {
    "addr:full":"405 Fairfax Ave Nashville TN 37212",
    "addr:housenumber":"405",
    "addr:postcode":"37212",
    "addr:street":"Fairfax Ave",
    "iso:country":"US",
    "sg:address":"405 Fairfax Ave",
    "sg:city":"Nashville",
    "sg:classifiers":[
        {
            "category":"Real Estate",
            "subcategory":"Architect",
            "type":"Services"
        }
    ],
    "sg:phone":"+1 615 297 1919",
    "sg:postcode":"37212",
    "sg:province":"TN",
    "sg:tags":[
        "architectural"
    ],
    "sg:website":"www.jt-architecture.com",
    "wof:name":"John Teselle Architecture PC",
    "wof:placetype":"venue"
},
  "geometry": {"coordinates":[-86.817064,36.13577],"type":"Point"}
}