{
  "type": "Feature",
  "properties": {
    "iso:country":"US",
    "sg:address":"1081 Oak Drive Cir",
    "sg:city":"Kingsport",
    "sg:classifiers":[
        {
            "category":"Building & Trades",
            "subcategory":"Construction",
            "type":"Services"
        }
    ],
    "sg:phone":"+1 423 245 5440",
    "sg:postcode":"37665",
    "sg:province":"TN",
    "sg:tags":[
        "house"
    ],
    "wof:name":"Structural Effects",
    "wof:placetype":"venue"
},
  "geometry": {"coordinates":[-82.558527,36.571266],"type":"Point"}
}