{
  "type": "Feature",
  "properties": {
    "iso:country":"US",
    "sg:address":"2703 Glenwood Pkwy",
    "sg:city":"Chattanooga",
    "sg:classifiers":[
        {
            "category":"Shopping",
            "subcategory":"Used Merchandise",
            "type":"Retail Goods"
        }
    ],
    "sg:phone":"+1 423 495 1032",
    "sg:postcode":"37404",
    "sg:province":"TN",
    "sg:tags":[
        "shop",
        "consignment"
    ],
    "wof:name":"Let's Do It Again",
    "wof:placetype":"venue"
},
  "geometry": {"coordinates":[-85.258343,35.036758],"type":"Point"}
}