{
  "type": "Feature",
  "properties": {
    "iso:country":"US",
    "sg:address":"1723 Clift Eldridge Rd",
    "sg:city":"Soddy Daisy",
    "sg:classifiers":[
        {
            "category":"Building & Trades",
            "subcategory":"Construction",
            "type":"Services"
        }
    ],
    "sg:phone":"+1 423 332 4784",
    "sg:postcode":"37379",
    "sg:province":"TN",
    "sg:tags":[
        "gas",
        "line",
        "installation",
        "repair"
    ],
    "wof:name":"B & B Gas Piping Svc Inc",
    "wof:placetype":"venue"
},
  "geometry": {"coordinates":[-85.11802299999999,35.265281],"type":"Point"}
}