{
  "type": "Feature",
  "properties": {
    "addr:full":"3750 Big Ridge Rd Oneida TN 37841",
    "addr:housenumber":"3750",
    "addr:postcode":"37841",
    "addr:street":"Big Ridge Rd",
    "iso:country":"US",
    "sg:address":"3750 Big Ridge Rd",
    "sg:city":"Oneida",
    "sg:classifiers":[
        {
            "category":"Manufacturing",
            "subcategory":"Lumber",
            "type":"Manufacturing & Wholesale Goods"
        }
    ],
    "sg:phone":"+1 423 569 5090",
    "sg:postcode":"37841",
    "sg:province":"TN",
    "sg:tags":[
        "logging"
    ],
    "wof:name":"Babbs Logging",
    "wof:placetype":"venue"
},
  "geometry": {"coordinates":[-84.541589,36.546903],"type":"Point"}
}