{
  "type": "Feature",
  "properties": {
    "iso:country":"US",
    "sg:address":"133 Ellen Dr",
    "sg:city":"Atoka",
    "sg:classifiers":[
        {
            "category":"Education",
            "subcategory":"School",
            "type":"Public Place"
        }
    ],
    "sg:phone":"+1 901 837 4184",
    "sg:postcode":"38004",
    "sg:province":"TN",
    "wof:name":"William Golding",
    "wof:placetype":"venue"
},
  "geometry": {"coordinates":[-89.77350199999999,35.430642],"type":"Point"}
}