{
  "type": "Feature",
  "properties": {
    "iso:country":"US",
    "sg:address":"2565 E Broadway Ave",
    "sg:city":"Maryville",
    "sg:classifiers":[
        {
            "category":"Government",
            "subcategory":"Fire Station",
            "type":"Public Place"
        }
    ],
    "sg:phone":"+1 865 983 2133",
    "sg:postcode":"37804",
    "sg:province":"TN",
    "sg:tags":[
        "department"
    ],
    "wof:name":"Blount County Fire Dept",
    "wof:placetype":"venue"
},
  "geometry": {"coordinates":[-83.946697,35.790097],"type":"Point"}
}