{
  "type": "Feature",
  "properties": {
    "iso:country":"US",
    "sg:address":"2206 Wilkinson Pike",
    "sg:city":"Maryville",
    "sg:classifiers":[
        {
            "category":"Building & Trades",
            "subcategory":"Landscaping Services",
            "type":"Services"
        }
    ],
    "sg:phone":"+1 865 977 7541",
    "sg:postcode":"37803",
    "sg:province":"TN",
    "sg:tags":[
        "lawn",
        "care"
    ],
    "wof:name":"Quality Lawn Care",
    "wof:placetype":"venue"
},
  "geometry": {"coordinates":[-83.942179,35.738883],"type":"Point"}
}