{
  "type": "Feature",
  "properties": {
    "addr:full":"93 Isham St Crossville TN 38555",
    "addr:housenumber":"93",
    "addr:postcode":"38555",
    "addr:street":"Isham St",
    "iso:country":"US",
    "sg:address":"93 Isham St",
    "sg:city":"Crossville",
    "sg:classifiers":[
        {
            "category":"Shopping",
            "type":"Retail Goods"
        }
    ],
    "sg:phone":"+1 931 456 4144",
    "sg:postcode":"38555",
    "sg:province":"TN",
    "sg:tags":[
        "tropical",
        "fish",
        "merchandise"
    ],
    "wof:name":"Wick's Water World",
    "wof:placetype":"venue"
},
  "geometry": {"coordinates":[-85.01041499999999,35.952653],"type":"Point"}
}