{
  "type": "Feature",
  "properties": {
    "iso:country":"US",
    "sg:address":"133 Apple Valley Rd",
    "sg:city":"Townsend",
    "sg:classifiers":[
        {
            "category":"Restaurant",
            "type":"Food & Drink"
        }
    ],
    "sg:phone":"+1 865 448 0250",
    "sg:postcode":"37862",
    "sg:province":"TN",
    "sg:tags":[
        "eating"
    ],
    "wof:name":"Cades Cove Galley",
    "wof:placetype":"venue"
},
  "geometry": {"coordinates":[-83.576279,35.827332],"type":"Point"}
}