{
  "type": "Feature",
  "properties": {
    "iso:country":"US",
    "sg:address":"912 County Line Rd",
    "sg:city":"Mooresburg",
    "sg:classifiers":[
        {
            "category":"Building & Trades",
            "subcategory":"Construction",
            "type":"Services"
        }
    ],
    "sg:phone":"+1 423 272 5237",
    "sg:postcode":"37811",
    "sg:province":"TN",
    "sg:tags":[
        "wallpaper"
    ],
    "wof:name":"Dowell Roger Pro Paper Hangers",
    "wof:placetype":"venue"
},
  "geometry": {"coordinates":[-83.257578,36.31733],"type":"Point"}
}