{
  "type": "Feature",
  "properties": {
    "iso:country":"US",
    "sg:address":"111 Wildflower Way",
    "sg:city":"Murfreesboro",
    "sg:classifiers":[
        {
            "category":"Professional",
            "type":"Services"
        }
    ],
    "sg:phone":"+1 615 848 0494",
    "sg:postcode":"37129",
    "sg:province":"TN",
    "wof:name":"Dragon Fly Designs",
    "wof:placetype":"venue"
},
  "geometry": {"coordinates":[-86.38460499999999,35.966331],"type":"Point"}
}