{
  "type": "Feature",
  "properties": {
    "addr:full":"1291 Walter Webb Dr Sevierville TN 37862",
    "addr:housenumber":"1291",
    "addr:postcode":"37862",
    "addr:street":"Walter Webb Dr",
    "iso:country":"US",
    "sg:address":"1291 Walter Webb Dr",
    "sg:city":"Sevierville",
    "sg:classifiers":[
        {
            "category":"Real Estate",
            "subcategory":"Real Estate Operator",
            "type":"Services"
        }
    ],
    "sg:phone":"+1 865 428 5227",
    "sg:postcode":"37862",
    "sg:province":"TN",
    "sg:tags":[
        "building",
        "apartment"
    ],
    "wof:name":"Meadows",
    "wof:placetype":"venue"
},
  "geometry": {"coordinates":[-83.524855,35.866653],"type":"Point"}
}