{
  "type": "Feature",
  "properties": {
    "iso:country":"US",
    "sg:address":"194 Spence Ln",
    "sg:city":"Nashville",
    "sg:classifiers":[
        {
            "category":"Building & Trades",
            "subcategory":"Construction",
            "type":"Services"
        }
    ],
    "sg:phone":"+1 615 316 9337",
    "sg:postcode":"37210",
    "sg:province":"TN",
    "sg:tags":[
        "house"
    ],
    "wof:name":"Buddy Dunn Contractors",
    "wof:placetype":"venue"
},
  "geometry": {"coordinates":[-86.72155600000001,36.159515],"type":"Point"}
}