{
  "type": "Feature",
  "properties": {
    "iso:country":"US",
    "sg:address":"3501 Hermitage Industrial Dr",
    "sg:city":"Hermitage",
    "sg:classifiers":[
        {
            "category":"Retail",
            "subcategory":"Repair Shop",
            "type":"Services"
        }
    ],
    "sg:phone":"+1 615 889 1850",
    "sg:postcode":"37076",
    "sg:province":"TN",
    "sg:tags":[
        "upholsterer"
    ],
    "wof:name":"Autumn Group",
    "wof:placetype":"venue"
},
  "geometry": {"coordinates":[-86.62263,36.186513],"type":"Point"}
}