{
  "type": "Feature",
  "properties": {
    "addr:full":"700 E Depot St Shelbyville TN 37160",
    "addr:housenumber":"700",
    "addr:postcode":"37160",
    "addr:street":"E Depot St",
    "iso:country":"US",
    "sg:address":"700 E Depot St",
    "sg:city":"Shelbyville",
    "sg:classifiers":[
        {
            "category":"Food & Beverages",
            "subcategory":"Groceries & Convenience Stores",
            "type":"Retail Goods"
        }
    ],
    "sg:phone":"+1 931 680 1722",
    "sg:postcode":"37160",
    "sg:province":"TN",
    "sg:tags":[
        "market"
    ],
    "wof:name":"Depot Street Market",
    "wof:placetype":"venue"
},
  "geometry": {"coordinates":[-86.448122,35.480411],"type":"Point"}
}