{
  "type": "Feature",
  "properties": {
    "addr:full":"879 Tracy Rd Millington TN 38053",
    "addr:housenumber":"879",
    "addr:postcode":"38053",
    "addr:street":"Tracy Rd",
    "iso:country":"US",
    "sg:address":"879 Tracy Rd",
    "sg:city":"Millington",
    "sg:classifiers":[
        {
            "category":"Professional",
            "type":"Services"
        }
    ],
    "sg:phone":"+1 901 837 6528",
    "sg:postcode":"38053",
    "sg:province":"TN",
    "wof:name":"Christopher Franklin",
    "wof:placetype":"venue"
},
  "geometry": {"coordinates":[-89.837743,35.39001],"type":"Point"}
}