{
  "type": "Feature",
  "properties": {
    "iso:country":"US",
    "sg:address":"837 Circle Dr",
    "sg:city":"Manchester",
    "sg:classifiers":[
        {
            "category":"Professional",
            "type":"Services"
        }
    ],
    "sg:phone":"+1 931 728 1734",
    "sg:postcode":"37355",
    "sg:province":"TN",
    "wof:name":"Mktjimmys",
    "wof:placetype":"venue"
},
  "geometry": {"coordinates":[-86.031098,35.533279],"type":"Point"}
}