{
  "type": "Feature",
  "properties": {
    "iso:country":"US",
    "sg:address":"4435 Summer Ave",
    "sg:city":"Memphis",
    "sg:classifiers":[
        {
            "category":"Professional",
            "subcategory":"Business Services",
            "type":"Services"
        }
    ],
    "sg:phone":"+1 901 818 5575",
    "sg:postcode":"38122",
    "sg:province":"TN",
    "sg:tags":[
        "import",
        "importer",
        "representative"
    ],
    "wof:name":"O K Trading",
    "wof:placetype":"venue"
},
  "geometry": {"coordinates":[-89.912857,35.14883],"type":"Point"}
}