{
  "type": "Feature",
  "properties": {
    "addr:full":"245 Church St Spring City TN 37381",
    "addr:housenumber":"245",
    "addr:postcode":"37381",
    "addr:street":"Church St",
    "iso:country":"US",
    "sg:address":"245 Church St",
    "sg:city":"Spring City",
    "sg:classifiers":[
        {
            "category":"Organizations",
            "subcategory":"Religious Organization",
            "type":"Services"
        }
    ],
    "sg:phone":"+1 423 365 6324",
    "sg:postcode":"37381",
    "sg:province":"TN",
    "sg:tags":[
        "church"
    ],
    "wof:name":"Spring City United Methodist",
    "wof:placetype":"venue"
},
  "geometry": {"coordinates":[-84.86239999999999,35.693886],"type":"Point"}
}