{
  "type": "Feature",
  "properties": {
    "iso:country":"US",
    "sg:address":"1809 Clift Eldridge Rd",
    "sg:city":"Soddy Daisy",
    "sg:classifiers":[
        {
            "category":"Recreation",
            "subcategory":"Marina",
            "type":"Entertainment"
        }
    ],
    "sg:phone":"+1 423 332 2202",
    "sg:postcode":"37379",
    "sg:province":"TN",
    "sg:tags":[
        "operation"
    ],
    "wof:name":"Forrest Cove Marina",
    "wof:placetype":"venue"
},
  "geometry": {"coordinates":[-85.117232,35.263636],"type":"Point"}
}