{
  "type": "Feature",
  "properties": {
    "addr:full":"3920 Highland Ln Crossville TN 38555",
    "addr:housenumber":"3920",
    "addr:postcode":"38555",
    "addr:street":"Highland Ln",
    "iso:country":"US",
    "sg:address":"3920 Highland Ln",
    "sg:city":"Crossville",
    "sg:classifiers":[
        {
            "category":"Communications",
            "subcategory":"Radio Station",
            "type":"Services"
        }
    ],
    "sg:phone":"+1 931 484 5168",
    "sg:postcode":"38555",
    "sg:province":"TN",
    "sg:tags":[
        "broadcast"
    ],
    "wof:name":"Adam Reagan",
    "wof:placetype":"venue"
},
  "geometry": {"coordinates":[-84.955415,35.946515],"type":"Point"}
}