{
  "type": "Feature",
  "properties": {
    "iso:country":"US",
    "sg:address":"3621 E Pkwy",
    "sg:city":"Gatlinburg",
    "sg:classifiers":[
        {
            "category":"Building & Trades",
            "subcategory":"Landscaping Services",
            "type":"Services"
        }
    ],
    "sg:phone":"+1 865 436 3014",
    "sg:postcode":"37738",
    "sg:province":"TN",
    "sg:tags":[
        "landscape",
        "contractor"
    ],
    "wof:name":"Bell's Nursery & Landscaping",
    "wof:placetype":"venue"
},
  "geometry": {"coordinates":[-83.36155599999999,35.75793],"type":"Point"}
}