{
  "type": "Feature",
  "properties": {
    "addr:full":"3039 Lamar Ave Memphis TN 38114",
    "addr:housenumber":"3039",
    "addr:postcode":"38114",
    "addr:street":"Lamar Ave",
    "iso:country":"US",
    "sg:address":"3039 Lamar Ave",
    "sg:city":"Memphis",
    "sg:classifiers":[
        {
            "category":"Local Transit",
            "type":"Transportation"
        }
    ],
    "sg:phone":"+1 901 745 8700",
    "sg:postcode":"38114",
    "sg:province":"TN",
    "sg:tags":[
        "passenger"
    ],
    "wof:name":"Diamond Transportation Svc",
    "wof:placetype":"venue"
},
  "geometry": {"coordinates":[-89.961012,35.084735],"type":"Point"}
}