{
  "type": "Feature",
  "properties": {
    "iso:country":"US",
    "sg:address":"820 W College St",
    "sg:city":"Murfreesboro",
    "sg:classifiers":[
        {
            "category":"Building & Trades",
            "subcategory":"Cleaning & Sanitation",
            "type":"Services"
        }
    ],
    "sg:phone":"+1 615 867 4040",
    "sg:postcode":"37129",
    "sg:province":"TN",
    "sg:tags":[
        "janitor"
    ],
    "wof:name":"Jani-Clean",
    "wof:placetype":"venue"
},
  "geometry": {"coordinates":[-86.402905,35.853851],"type":"Point"}
}