{
  "type": "Feature",
  "properties": {
    "addr:full":"2565 Scottsway Rd Memphis TN 38115",
    "addr:housenumber":"2565",
    "addr:postcode":"38115",
    "addr:street":"Scottsway Rd",
    "iso:country":"US",
    "sg:address":"2565 Scottsway Rd",
    "sg:city":"Memphis",
    "sg:classifiers":[
        {
            "category":"Wholesale",
            "subcategory":"Motor Vehicles",
            "type":"Manufacturing & Wholesale Goods"
        }
    ],
    "sg:phone":"+1 901 795 7704",
    "sg:postcode":"38115",
    "sg:province":"TN",
    "wof:name":"Auto X",
    "wof:placetype":"venue"
},
  "geometry": {"coordinates":[-89.887293,35.077065],"type":"Point"}
}