{
  "type": "Feature",
  "properties": {
    "iso:country":"US",
    "sg:address":"5914 Charlotte Pike",
    "sg:city":"Nashville",
    "sg:classifiers":[
        {
            "category":"Utilities",
            "subcategory":"Mobile Phone",
            "type":"Services"
        }
    ],
    "sg:phone":"+1 615 356 4366",
    "sg:postcode":"37209",
    "sg:province":"TN",
    "sg:tags":[
        "telephone",
        "cellular"
    ],
    "wof:name":"United Cellular",
    "wof:placetype":"venue"
},
  "geometry": {"coordinates":[-86.86156200000001,36.149416],"type":"Point"}
}