{
  "type": "Feature",
  "properties": {
    "iso:country":"US",
    "sg:address":"908 Hunters Lake Dr",
    "sg:city":"Johnson City",
    "sg:classifiers":[
        {
            "category":"Professional",
            "type":"Services"
        }
    ],
    "sg:phone":"+1 423 610 1392",
    "sg:postcode":"37604",
    "sg:province":"TN",
    "sg:tags":[
        "establishment"
    ],
    "wof:name":"Hunter's Lake Community Assoc",
    "wof:placetype":"venue"
},
  "geometry": {"coordinates":[-82.387682,36.327596],"type":"Point"}
}