{
  "type": "Feature",
  "properties": {
    "iso:country":"US",
    "sg:address":"815 W Main St",
    "sg:city":"Livingston",
    "sg:classifiers":[
        {
            "category":"Autos & Motor Vehicles",
            "subcategory":"Fuel & Gas Station",
            "type":"Retail Goods"
        }
    ],
    "sg:phone":"+1 931 823 7662",
    "sg:postcode":"38570",
    "sg:province":"TN",
    "sg:tags":[
        "station",
        "gasoline"
    ],
    "wof:name":"Chevron",
    "wof:placetype":"venue"
},
  "geometry": {"coordinates":[-85.331824,36.379353],"type":"Point"}
}