{
  "type": "Feature",
  "properties": {
    "iso:country":"US",
    "sg:address":"650 Milligan Rd",
    "sg:city":"Afton",
    "sg:classifiers":[
        {
            "category":"Freight",
            "type":"Transportation"
        }
    ],
    "sg:phone":"+1 423 638 2497",
    "sg:postcode":"37616",
    "sg:province":"TN",
    "sg:tags":[
        "operator",
        "trucking"
    ],
    "wof:name":"Coffey Truck Lines",
    "wof:placetype":"venue"
},
  "geometry": {"coordinates":[-82.740146,36.217068],"type":"Point"}
}