{
  "type": "Feature",
  "properties": {
    "iso:country":"US",
    "sg:address":"461 21st Ave S",
    "sg:city":"Nashville",
    "sg:classifiers":[
        {
            "category":"Building & Trades",
            "subcategory":"Construction",
            "type":"Services"
        }
    ],
    "sg:phone":"+1 615 321 0814",
    "sg:postcode":"37240",
    "sg:province":"TN",
    "sg:tags":[
        "general",
        "contractor"
    ],
    "wof:name":"Wieck Construction",
    "wof:placetype":"venue"
},
  "geometry": {"coordinates":[-86.799396,36.147867],"type":"Point"}
}