{
  "type": "Feature",
  "properties": {
    "addr:full":"3312 Harris Rd Knoxville TN 37924",
    "addr:housenumber":"3312",
    "addr:postcode":"37924",
    "addr:street":"Harris Rd",
    "iso:country":"US",
    "sg:address":"3312 Harris Rd",
    "sg:city":"Knoxville",
    "sg:classifiers":[
        {
            "category":"Building & Trades",
            "subcategory":"Construction",
            "type":"Services"
        }
    ],
    "sg:phone":"+1 865 525 6064",
    "sg:postcode":"37924",
    "sg:province":"TN",
    "sg:tags":[
        "house",
        "nonresidential"
    ],
    "wof:name":"Tallie Lynn Bush",
    "wof:placetype":"venue"
},
  "geometry": {"coordinates":[-83.84697799999999,36.053075],"type":"Point"}
}