{
  "type": "Feature",
  "properties": {
    "iso:country":"US",
    "sg:address":"2320 Cookeville Hwy",
    "sg:city":"Livingston",
    "sg:classifiers":[
        {
            "category":"Wholesale",
            "subcategory":"Electrical",
            "type":"Manufacturing & Wholesale Goods"
        }
    ],
    "sg:phone":"+1 931 823 2319",
    "sg:postcode":"38570",
    "sg:province":"TN",
    "sg:tags":[
        "operated",
        "telephone",
        "card"
    ],
    "wof:name":"BBI",
    "wof:placetype":"venue"
},
  "geometry": {"coordinates":[-85.35451,36.332783],"type":"Point"}
}