{
  "type": "Feature",
  "properties": {
    "iso:country":"US",
    "sg:address":"2700 Boones Creek Rd",
    "sg:city":"Johnson City",
    "sg:classifiers":[
        {
            "category":"Restaurant",
            "type":"Food & Drink"
        }
    ],
    "sg:phone":"+1 423 283 7605",
    "sg:postcode":"37615",
    "sg:province":"TN",
    "sg:tags":[
        "eating"
    ],
    "wof:name":"Wendys",
    "wof:placetype":"venue"
},
  "geometry": {"coordinates":[-82.427582,36.375122],"type":"Point"}
}