{
  "type": "Feature",
  "properties": {
    "addr:full":"7620 Shallowford Rd Chattanooga TN 37421",
    "addr:housenumber":"7620",
    "addr:postcode":"37421",
    "addr:street":"Shallowford Rd",
    "iso:country":"US",
    "sg:address":"7620 Shallowford Rd",
    "sg:city":"Chattanooga",
    "sg:classifiers":[
        {
            "category":"Health Services",
            "subcategory":"Nursing And Care Facility",
            "type":"Services"
        }
    ],
    "sg:phone":"+1 423 296 0097",
    "sg:postcode":"37421",
    "sg:province":"TN",
    "wof:name":"Morning Pointe Of Chattanooga",
    "wof:placetype":"venue"
},
  "geometry": {"coordinates":[-85.139822,35.036534],"type":"Point"}
}