{
  "type": "Feature",
  "properties": {
    "iso:country":"US",
    "sg:address":"4883 N Broadway St",
    "sg:city":"Knoxville",
    "sg:classifiers":[
        {
            "category":"Banks & Credit Unions",
            "subcategory":"Bank",
            "type":"Services"
        }
    ],
    "sg:phone":"+1 865 281 7994",
    "sg:postcode":"37918",
    "sg:province":"TN",
    "sg:tags":[
        "cashing",
        "check"
    ],
    "wof:name":"Check Cash USA",
    "wof:placetype":"venue"
},
  "geometry": {"coordinates":[-83.92820500000001,36.028075],"type":"Point"}
}