{
  "type": "Feature",
  "properties": {
    "iso:country":"US",
    "sg:address":"6347 Hartsville Rd",
    "sg:city":"Dixon Springs",
    "sg:classifiers":[
        {
            "category":"Manufacturing",
            "subcategory":"Metals",
            "type":"Manufacturing & Wholesale Goods"
        }
    ],
    "sg:phone":"+1 615 735 9278",
    "sg:postcode":"37057",
    "sg:province":"TN",
    "sg:tags":[
        "duct",
        "fitting"
    ],
    "wof:name":"Mc Call's Duct Work",
    "wof:placetype":"venue"
},
  "geometry": {"coordinates":[-86.057833,36.446079],"type":"Point"}
}