{
  "type": "Feature",
  "properties": {
    "addr:full":"112 W Main St Whiteville TN 38075",
    "addr:housenumber":"112",
    "addr:postcode":"38075",
    "addr:street":"W Main St",
    "iso:country":"US",
    "sg:address":"112 W Main St",
    "sg:city":"Whiteville",
    "sg:classifiers":[
        {
            "category":"Government",
            "subcategory":"Post Office",
            "type":"Public Place"
        }
    ],
    "sg:phone":"+1 731 254 8671",
    "sg:postcode":"38075",
    "sg:province":"TN",
    "sg:tags":[
        "postal",
        "us"
    ],
    "wof:name":"Whiteville Post Office",
    "wof:placetype":"venue"
},
  "geometry": {"coordinates":[-89.157504,35.322308],"type":"Point"}
}