{
  "type": "Feature",
  "properties": {
    "addr:full":"1711 Linda Ln Maryville TN 37803",
    "addr:housenumber":"1711",
    "addr:postcode":"37803",
    "addr:street":"Linda Ln",
    "iso:country":"US",
    "sg:address":"1711 Linda Ln",
    "sg:city":"Maryville",
    "sg:classifiers":[
        {
            "category":"Arts & Performance",
            "subcategory":"Theater",
            "type":"Entertainment"
        }
    ],
    "sg:phone":"+1 865 984 6643",
    "sg:postcode":"37803",
    "sg:province":"TN",
    "sg:tags":[
        "group"
    ],
    "wof:name":"Fuller Light N Sound",
    "wof:placetype":"venue"
},
  "geometry": {"coordinates":[-83.98923000000001,35.73453],"type":"Point"}
}