{
  "type": "Feature",
  "properties": {
    "iso:country":"US",
    "sg:address":"6415 Deane Hill Dr",
    "sg:city":"Knoxville",
    "sg:classifiers":[
        {
            "category":"Professional",
            "subcategory":"Employment Agencies",
            "type":"Services"
        }
    ],
    "sg:phone":"+1 865 254 6626",
    "sg:postcode":"37919",
    "sg:province":"TN",
    "sg:tags":[
        "help",
        "supply"
    ],
    "wof:name":"Orofacial Myology Assoc Tenn",
    "wof:placetype":"venue"
},
  "geometry": {"coordinates":[-84.012597,35.928801],"type":"Point"}
}