{
  "type": "Feature",
  "properties": {
    "iso:country":"US",
    "sg:address":"11109 Hwy 19 W",
    "sg:city":"Ripley",
    "sg:classifiers":[
        {
            "category":"Professional",
            "type":"Services"
        }
    ],
    "sg:phone":"+1 731 635 5392",
    "sg:postcode":"38063",
    "sg:province":"TN",
    "wof:name":"Micheles Carousel",
    "wof:placetype":"venue"
},
  "geometry": {"coordinates":[-89.715673,35.772295],"type":"Point"}
}