{
  "type": "Feature",
  "properties": {
    "iso:country":"US",
    "sg:address":"620 Stage Coach Loop",
    "sg:city":"Mountain City",
    "sg:classifiers":[
        {
            "category":"Home & Garden",
            "subcategory":"Building Materials",
            "type":"Retail Goods"
        }
    ],
    "sg:phone":"+1 423 727 6070",
    "sg:postcode":"37683",
    "sg:province":"TN",
    "wof:name":"Foggy Mountain Stain Glass",
    "wof:placetype":"venue"
},
  "geometry": {"coordinates":[-81.91548400000001,36.433628],"type":"Point"}
}