{
  "type": "Feature",
  "properties": {
    "iso:country":"US",
    "sg:address":"37 Old Jackson Hwy S",
    "sg:city":"Saint Joseph",
    "sg:classifiers":[
        {
            "category":"Communications",
            "subcategory":"Radio Station",
            "type":"Services"
        }
    ],
    "sg:phone":"+1 931 845 4172",
    "sg:postcode":"38481",
    "sg:province":"TN",
    "sg:tags":[
        "broadcast"
    ],
    "wof:name":"Wjor",
    "wof:placetype":"venue"
},
  "geometry": {"coordinates":[-87.511493,35.014391],"type":"Point"}
}