{
  "type": "Feature",
  "properties": {
    "addr:full":"3921 American Way Memphis TN 38118",
    "addr:housenumber":"3921",
    "addr:postcode":"38118",
    "addr:street":"American Way",
    "iso:country":"US",
    "sg:address":"3921 American Way",
    "sg:city":"Memphis",
    "sg:classifiers":[
        {
            "category":"Local Transit",
            "type":"Transportation"
        }
    ],
    "sg:phone":"+1 901 722 0322",
    "sg:postcode":"38118",
    "sg:province":"TN",
    "sg:tags":[
        "bus",
        "line"
    ],
    "wof:name":"Memphis Area Transit Authority",
    "wof:placetype":"venue"
},
  "geometry": {"coordinates":[-89.940224,35.076723],"type":"Point"}
}