{
  "type": "Feature",
  "properties": {
    "iso:country":"US",
    "sg:address":"4040 Mountain Creek Rd",
    "sg:city":"Chattanooga",
    "sg:classifiers":[
        {
            "category":"Real Estate",
            "subcategory":"Real Estate Operator",
            "type":"Services"
        }
    ],
    "sg:phone":"+1 423 875 3121",
    "sg:postcode":"37415",
    "sg:province":"TN",
    "sg:tags":[
        "townhouses"
    ],
    "wof:name":"Alpine Villas Apartments LTD",
    "wof:placetype":"venue"
},
  "geometry": {"coordinates":[-85.30794,35.13259],"type":"Point"}
}