{
  "type": "Feature",
  "properties": {
    "addr:full":"330 Hardin Ln Sevierville TN 37862",
    "addr:housenumber":"330",
    "addr:postcode":"37862",
    "addr:street":"Hardin Ln",
    "iso:country":"US",
    "sg:address":"330 Hardin Ln",
    "sg:city":"Sevierville",
    "sg:classifiers":[
        {
            "category":"Real Estate",
            "subcategory":"Real Estate Operator",
            "type":"Services"
        }
    ],
    "sg:phone":"+1 865 428 0248",
    "sg:postcode":"37862",
    "sg:province":"TN",
    "sg:tags":[
        "building",
        "apartment"
    ],
    "wof:name":"Mountain View Apartments",
    "wof:placetype":"venue"
},
  "geometry": {"coordinates":[-83.575694,35.866697],"type":"Point"}
}