{
  "type": "Feature",
  "properties": {
    "iso:country":"US",
    "sg:address":"117 E Commerce St",
    "sg:city":"Loretto",
    "sg:classifiers":[
        {
            "category":"Personal",
            "type":"Services"
        }
    ],
    "sg:phone":"+1 931 853 4645",
    "sg:postcode":"38469",
    "sg:province":"TN",
    "sg:tags":[
        "therapist",
        "massage"
    ],
    "wof:name":"Ramona Pedersen Lmt",
    "wof:placetype":"venue"
},
  "geometry": {"coordinates":[-87.436072,35.078697],"type":"Point"}
}