{
  "type": "Feature",
  "properties": {
    "iso:country":"US",
    "sg:address":"6924 Mackin Ln",
    "sg:city":"Knoxville",
    "sg:classifiers":[
        {
            "category":"Professional",
            "subcategory":"Business Services",
            "type":"Services"
        }
    ],
    "sg:phone":"+1 865 693 5493",
    "sg:postcode":"37931",
    "sg:province":"TN",
    "wof:name":"Hickman Family Partnership LP",
    "wof:placetype":"venue"
},
  "geometry": {"coordinates":[-84.08546800000001,35.987715],"type":"Point"}
}