{
  "type": "Feature",
  "properties": {
    "iso:country":"US",
    "sg:address":"140 N Main St",
    "sg:city":"Eagleville",
    "sg:classifiers":[
        {
            "category":"Home & Garden",
            "subcategory":"Building Materials",
            "type":"Retail Goods"
        }
    ],
    "sg:phone":"+1 615 274 6237",
    "sg:postcode":"37060",
    "sg:province":"TN",
    "wof:name":"Crosslin Supply Co Inc",
    "wof:placetype":"venue"
},
  "geometry": {"coordinates":[-86.65034799999999,35.751388],"type":"Point"}
}