{
  "type": "Feature",
  "properties": {
    "iso:country":"US",
    "sg:address":"3872 Kerwin Dr",
    "sg:city":"Memphis",
    "sg:classifiers":[
        {
            "category":"Freight",
            "type":"Transportation"
        }
    ],
    "sg:phone":"+1 901 372 1583",
    "sg:postcode":"38128",
    "sg:province":"TN",
    "sg:tags":[
        "operator",
        "local",
        "trucking"
    ],
    "wof:name":"S L Jones Trucking Co",
    "wof:placetype":"venue"
},
  "geometry": {"coordinates":[-89.932682,35.232919],"type":"Point"}
}