{
  "type": "Feature",
  "properties": {
    "addr:full":"2702 W Broad St Cookeville TN 38501",
    "addr:housenumber":"2702",
    "addr:postcode":"38501",
    "addr:street":"W Broad St",
    "iso:country":"US",
    "sg:address":"2702 W Broad St",
    "sg:city":"Cookeville",
    "sg:classifiers":[
        {
            "category":"Retail",
            "subcategory":"Auto Repair",
            "type":"Services"
        }
    ],
    "sg:phone":"+1 931 528 0080",
    "sg:postcode":"38501",
    "sg:province":"TN",
    "sg:tags":[
        "repairing",
        "automobile"
    ],
    "wof:name":"Affordable Used Cars & Trucks",
    "wof:placetype":"venue"
},
  "geometry": {"coordinates":[-85.582565,36.173537],"type":"Point"}
}