{
  "type": "Feature",
  "properties": {
    "iso:country":"US",
    "sg:address":"159 Cumberland Dr",
    "sg:city":"Hendersonville",
    "sg:classifiers":[
        {
            "category":"Professional",
            "subcategory":"Art Services",
            "type":"Services"
        }
    ],
    "sg:phone":"+1 615 264 1135",
    "sg:postcode":"37075",
    "sg:province":"TN",
    "sg:tags":[
        "graphic",
        "design"
    ],
    "sg:website":"www.stricklingraphics.com",
    "wof:name":"Stricklin Graphics",
    "wof:placetype":"venue"
},
  "geometry": {"coordinates":[-86.61918900000001,36.252796],"type":"Point"}
}