{
  "type": "Feature",
  "properties": {
    "iso:country":"US",
    "sg:address":"143 W Bernard Ave",
    "sg:city":"Greeneville",
    "sg:classifiers":[
        {
            "category":"Wholesale",
            "subcategory":"Auto Parts",
            "type":"Manufacturing & Wholesale Goods"
        }
    ],
    "sg:phone":"+1 423 639 1121",
    "sg:postcode":"37743",
    "sg:province":"TN",
    "sg:tags":[
        "automobile",
        "rebuilt"
    ],
    "wof:name":"AAA Used Cars LLC",
    "wof:placetype":"venue"
},
  "geometry": {"coordinates":[-82.822118,36.16004],"type":"Point"}
}