{
  "type": "Feature",
  "properties": {
    "addr:full":"291 Saturn Dr Memphis TN 38109",
    "addr:housenumber":"291",
    "addr:postcode":"38109",
    "addr:street":"Saturn Dr",
    "iso:country":"US",
    "sg:address":"291 Saturn Dr",
    "sg:city":"Memphis",
    "sg:classifiers":[
        {
            "category":"Freight",
            "type":"Transportation"
        }
    ],
    "sg:phone":"+1 901 346 2214",
    "sg:postcode":"38109",
    "sg:province":"TN",
    "sg:tags":[
        "trucking"
    ],
    "wof:name":"MLG Trucking",
    "wof:placetype":"venue"
},
  "geometry": {"coordinates":[-90.05381199999999,35.061556],"type":"Point"}
}