{
  "type": "Feature",
  "properties": {
    "iso:country":"US",
    "sg:address":"5596 Boy Scout Rd",
    "sg:city":"Franklin",
    "sg:classifiers":[
        {
            "category":"Food & Beverages",
            "subcategory":"Groceries & Convenience Stores",
            "type":"Retail Goods"
        }
    ],
    "sg:phone":"+1 615 791 6484",
    "sg:postcode":"37064",
    "sg:province":"TN",
    "sg:tags":[
        "grocer"
    ],
    "wof:name":"Puckett's Grocery",
    "wof:placetype":"venue"
},
  "geometry": {"coordinates":[-87.05653599999999,35.912784],"type":"Point"}
}