{
  "type": "Feature",
  "properties": {
    "iso:country":"US",
    "sg:address":"600 Mimosa Dr",
    "sg:city":"Cleveland",
    "sg:classifiers":[
        {
            "category":"Building & Trades",
            "subcategory":"Construction",
            "type":"Services"
        }
    ],
    "sg:phone":"+1 423 479 1188",
    "sg:postcode":"37312",
    "sg:province":"TN",
    "sg:tags":[
        "builder",
        "stair"
    ],
    "sg:website":"www.southeasternstair.com",
    "wof:name":"Southeastern Stair & Millwork",
    "wof:placetype":"venue"
},
  "geometry": {"coordinates":[-84.857005,35.202501],"type":"Point"}
}