{
  "type": "Feature",
  "properties": {
    "iso:country":"US",
    "sg:address":"2638 Allen Ferry Rd",
    "sg:city":"Smithville",
    "sg:classifiers":[
        {
            "category":"Building & Trades",
            "subcategory":"Construction",
            "type":"Services"
        }
    ],
    "sg:phone":"+1 615 597 1402",
    "sg:postcode":"37166",
    "sg:province":"TN",
    "sg:tags":[
        "heavy"
    ],
    "wof:name":"David H Pack Company",
    "wof:placetype":"venue"
},
  "geometry": {"coordinates":[-85.81503499999999,35.976567],"type":"Point"}
}