{
  "type": "Feature",
  "properties": {
    "addr:full":"7708 Fernvale Rd Fairview TN 37062",
    "addr:housenumber":"7708",
    "addr:postcode":"37062",
    "addr:street":"Fernvale Rd",
    "iso:country":"US",
    "sg:address":"7708 Fernvale Rd",
    "sg:city":"Fairview",
    "sg:classifiers":[
        {
            "category":"Building & Trades",
            "subcategory":"Construction",
            "type":"Services"
        }
    ],
    "sg:phone":"+1 615 799 9200",
    "sg:postcode":"37062",
    "sg:province":"TN",
    "sg:tags":[
        "floor",
        "installation",
        "contractor"
    ],
    "wof:name":"M B R Floor Installation",
    "wof:placetype":"venue"
},
  "geometry": {"coordinates":[-87.102886,35.962178],"type":"Point"}
}