{
  "type": "Feature",
  "properties": {
    "iso:country":"US",
    "sg:address":"1265 Simms Heights Rd",
    "sg:city":"Kingston Springs",
    "sg:classifiers":[
        {
            "category":"Retail",
            "subcategory":"Repair Shop",
            "type":"Services"
        }
    ],
    "sg:phone":"+1 615 952 2990",
    "sg:postcode":"37082",
    "sg:province":"TN",
    "sg:tags":[
        "professional",
        "instrument"
    ],
    "wof:name":"Paramunt Precision Calibration",
    "wof:placetype":"venue"
},
  "geometry": {"coordinates":[-87.13583,36.088407],"type":"Point"}
}