{
  "type": "Feature",
  "properties": {
    "addr:full":"305 W 20th St Chattanooga TN 37408",
    "addr:housenumber":"305",
    "addr:postcode":"37408",
    "addr:street":"W 20Th St",
    "iso:country":"US",
    "sg:address":"305 W 20th St",
    "sg:city":"Chattanooga",
    "sg:classifiers":[
        {
            "category":"Retail",
            "subcategory":"Auto Rental",
            "type":"Services"
        }
    ],
    "sg:phone":"+1 423 267 9500",
    "sg:postcode":"37408",
    "sg:province":"TN",
    "sg:tags":[
        "renting",
        "automobile"
    ],
    "wof:name":"Enterprise Rent A Car",
    "wof:placetype":"venue"
},
  "geometry": {"coordinates":[-85.31362,35.033208],"type":"Point"}
}