{
  "type": "Feature",
  "properties": {
    "iso:country":"US",
    "sg:address":"1401 Railroad Ave",
    "sg:city":"Athens",
    "sg:classifiers":[
        {
            "category":"Autos & Motor Vehicles",
            "subcategory":"Auto Supplies",
            "type":"Retail Goods"
        }
    ],
    "sg:phone":"+1 423 745 7249",
    "sg:postcode":"37303",
    "sg:province":"TN",
    "sg:tags":[
        "alternator",
        "generator",
        "merchandise"
    ],
    "wof:name":"Wayne's Batteries",
    "wof:placetype":"venue"
},
  "geometry": {"coordinates":[-84.60525199999999,35.457449],"type":"Point"}
}