{
  "type": "Feature",
  "properties": {
    "iso:country":"US",
    "sg:address":"60 Tusculum Rd",
    "sg:city":"Antioch",
    "sg:classifiers":[
        {
            "category":"Restaurant",
            "type":"Food & Drink"
        }
    ],
    "sg:phone":"+1 615 533 0290",
    "sg:postcode":"37013",
    "sg:province":"TN",
    "sg:tags":[
        "caterer"
    ],
    "wof:name":"Catering By Tony",
    "wof:placetype":"venue"
},
  "geometry": {"coordinates":[-86.678431,36.052897],"type":"Point"}
}