{
  "type": "Feature",
  "properties": {
    "addr:full":"236 Price Rd Elizabethton TN 37643",
    "addr:housenumber":"236",
    "addr:postcode":"37643",
    "addr:street":"Price Rd",
    "iso:country":"US",
    "sg:address":"236 Price Rd",
    "sg:city":"Elizabethton",
    "sg:classifiers":[
        {
            "category":"Wholesale",
            "subcategory":"Construction Materials",
            "type":"Manufacturing & Wholesale Goods"
        }
    ],
    "sg:phone":"+1 423 474 3233",
    "sg:postcode":"37643",
    "sg:province":"TN",
    "sg:tags":[
        "insulation"
    ],
    "wof:name":"R Quality Insulation",
    "wof:placetype":"venue"
},
  "geometry": {"coordinates":[-82.13235899999999,36.382466],"type":"Point"}
}