{
  "type": "Feature",
  "properties": {
    "addr:full":"556 Metroplex Dr Nashville TN 37211",
    "addr:housenumber":"556",
    "addr:postcode":"37211",
    "addr:street":"Metroplex Dr",
    "iso:country":"US",
    "sg:address":"556 Metroplex Dr",
    "sg:city":"Nashville",
    "sg:classifiers":[
        {
            "category":"Wholesale",
            "subcategory":"Drugs",
            "type":"Manufacturing & Wholesale Goods"
        }
    ],
    "sg:phone":"+1 615 833 7530",
    "sg:postcode":"37211",
    "sg:province":"TN",
    "wof:name":"Cardinal Health",
    "wof:placetype":"venue"
},
  "geometry": {"coordinates":[-86.70267699999999,36.092946],"type":"Point"}
}