{
  "type": "Feature",
  "properties": {
    "addr:full":"4901 Section Line Rd Union City TN 38261",
    "addr:housenumber":"4901",
    "addr:postcode":"38261",
    "addr:street":"Section Line Rd",
    "iso:country":"US",
    "sg:address":"4901 Section Line Rd",
    "sg:city":"Union City",
    "sg:classifiers":[
        {
            "category":"Building & Trades",
            "subcategory":"Plumbing",
            "type":"Services"
        }
    ],
    "sg:phone":"+1 731 431 8525",
    "sg:postcode":"38261",
    "sg:province":"TN",
    "sg:tags":[
        "contractor"
    ],
    "wof:name":"ML Plumbing",
    "wof:placetype":"venue"
},
  "geometry": {"coordinates":[-89.00975,36.475704],"type":"Point"}
}