{
  "type": "Feature",
  "properties": {
    "addr:full":"1585 Brown Ave Cookeville TN 38501",
    "addr:housenumber":"1585",
    "addr:postcode":"38501",
    "addr:street":"Brown Ave",
    "iso:country":"US",
    "sg:address":"1585 Brown Ave",
    "sg:city":"Cookeville",
    "sg:classifiers":[
        {
            "category":"Wholesale",
            "subcategory":"Auto Parts",
            "type":"Manufacturing & Wholesale Goods"
        }
    ],
    "sg:phone":"+1 931 526 7787",
    "sg:postcode":"38501",
    "sg:province":"TN",
    "sg:tags":[
        "repair",
        "automotive"
    ],
    "wof:name":"Truckpro",
    "wof:placetype":"venue"
},
  "geometry": {"coordinates":[-85.48828,36.184885],"type":"Point"}
}