{
  "type": "Feature",
  "properties": {
    "iso:country":"US",
    "sg:address":"4830 Summer Ave",
    "sg:city":"Memphis",
    "sg:classifiers":[
        {
            "category":"Wholesale",
            "subcategory":"Machinery & Supplies",
            "type":"Manufacturing & Wholesale Goods"
        }
    ],
    "sg:phone":"+1 901 682 6223",
    "sg:postcode":"38122",
    "sg:province":"TN",
    "sg:tags":[
        "equipment",
        "salon",
        "establishment",
        "beauty"
    ],
    "wof:name":"Heil Beauty Supply Inc",
    "wof:placetype":"venue"
},
  "geometry": {"coordinates":[-89.89999400000001,35.148622],"type":"Point"}
}