{
  "type": "Feature",
  "properties": {
    "iso:country":"US",
    "sg:address":"829 W Main St",
    "sg:city":"Hendersonville",
    "sg:classifiers":[
        {
            "category":"Autos & Motor Vehicles",
            "subcategory":"Automobile Sales",
            "type":"Retail Goods"
        }
    ],
    "sg:phone":"+1 615 822 4444",
    "sg:postcode":"37075",
    "sg:province":"TN",
    "sg:tags":[
        "car",
        "dealer"
    ],
    "wof:name":"Maple Motors",
    "wof:placetype":"venue"
},
  "geometry": {"coordinates":[-86.64621,36.303531],"type":"Point"}
}