{
  "type": "Feature",
  "properties": {
    "iso:country":"US",
    "sg:address":"4724 Hickory Hill Rd",
    "sg:city":"Memphis",
    "sg:classifiers":[
        {
            "category":"Professional",
            "subcategory":"Computer Services",
            "type":"Services"
        }
    ],
    "sg:phone":"+1 901 362 5008",
    "sg:postcode":"38141",
    "sg:province":"TN",
    "sg:tags":[
        "internet"
    ],
    "sg:website":"www.justmy.net",
    "wof:name":"JUSTMY.COM",
    "wof:placetype":"venue"
},
  "geometry": {"coordinates":[-89.866157,35.019086],"type":"Point"}
}