{
  "type": "Feature",
  "properties": {
    "iso:country":"US",
    "sg:address":"130 S 1st St",
    "sg:city":"Clarksville",
    "sg:classifiers":[
        {
            "category":"Government",
            "subcategory":"Office",
            "type":"Public Place"
        }
    ],
    "sg:phone":"+1 931 648 5702",
    "sg:postcode":"37040",
    "sg:province":"TN",
    "sg:tags":[
        "county",
        "safety",
        "order"
    ],
    "wof:name":"Montgomery Emergency Mgmt",
    "wof:placetype":"venue"
},
  "geometry": {"coordinates":[-87.360094,36.526376],"type":"Point"}
}