{
  "type": "Feature",
  "properties": {
    "addr:full":"122 Madison Ave Memphis TN 38103",
    "addr:housenumber":"122",
    "addr:postcode":"38103",
    "addr:street":"Madison Ave",
    "iso:country":"US",
    "sg:address":"122 Madison Ave",
    "sg:city":"Memphis",
    "sg:classifiers":[
        {
            "category":"Banks & Credit Unions",
            "subcategory":"Bank",
            "type":"Services"
        }
    ],
    "sg:phone":"+1 901 528 0245",
    "sg:postcode":"38103",
    "sg:province":"TN",
    "sg:tags":[
        "loan"
    ],
    "wof:name":"Bluffcity Finance",
    "wof:placetype":"venue"
},
  "geometry": {"coordinates":[-90.051708,35.145002],"type":"Point"}
}