{
  "type": "Feature",
  "properties": {
    "addr:full":"4285 E Morris Blvd Morristown TN 37813",
    "addr:housenumber":"4285",
    "addr:postcode":"37813",
    "addr:street":"E Morris Blvd",
    "iso:country":"US",
    "sg:address":"4285 E Morris Blvd",
    "sg:city":"Morristown",
    "sg:classifiers":[
        {
            "category":"Retail",
            "subcategory":"Veterinary Services",
            "type":"Services"
        }
    ],
    "sg:phone":"+1 423 587 4393",
    "sg:postcode":"37813",
    "sg:province":"TN",
    "wof:name":"Appalachian Animal Hospital",
    "wof:placetype":"venue"
},
  "geometry": {"coordinates":[-83.239063,36.234676],"type":"Point"}
}