{
  "type": "Feature",
  "properties": {
    "iso:country":"US",
    "sg:address":"1412 Eagle Bend Dr",
    "sg:city":"Clinton",
    "sg:classifiers":[
        {
            "category":"Professional",
            "subcategory":"Computer Services",
            "type":"Services"
        }
    ],
    "sg:phone":"+1 865 457 3634",
    "sg:postcode":"37716",
    "sg:province":"TN",
    "sg:tags":[
        "programing",
        "custom"
    ],
    "wof:name":"DRLNDRL Inc",
    "wof:placetype":"venue"
},
  "geometry": {"coordinates":[-84.11370100000001,36.093118],"type":"Point"}
}