{
  "type": "Feature",
  "properties": {
    "iso:country":"US",
    "sg:address":"413 E Elk Ave",
    "sg:city":"Elizabethton",
    "sg:classifiers":[
        {
            "category":"Health Services",
            "subcategory":"Health Practitioner",
            "type":"Services"
        }
    ],
    "sg:phone":"+1 423 542 8011",
    "sg:postcode":"37643",
    "sg:province":"TN",
    "sg:tags":[
        "gambling",
        "addiction-information",
        "treatment"
    ],
    "wof:name":"Crossroads Area Alcohol Drug Rehabilitation Association",
    "wof:placetype":"venue"
},
  "geometry": {"coordinates":[-82.217888,36.347469],"type":"Point"}
}