{
  "type": "Feature",
  "properties": {
    "iso:country":"US",
    "sg:address":"1924 Wilson Pkwy",
    "sg:city":"Fayetteville",
    "sg:classifiers":[
        {
            "category":"Autos & Motor Vehicles",
            "subcategory":"Automobile Sales",
            "type":"Retail Goods"
        }
    ],
    "sg:phone":"+1 931 433 4620",
    "sg:postcode":"37334",
    "sg:province":"TN",
    "wof:name":"Patrick Trailer Sales",
    "wof:placetype":"venue"
},
  "geometry": {"coordinates":[-86.576764,35.140847],"type":"Point"}
}