{
  "type": "Feature",
  "properties": {
    "iso:country":"US",
    "sg:address":"388 Co Rd 313",
    "sg:city":"Sweetwater",
    "sg:classifiers":[
        {
            "category":"Real Estate",
            "subcategory":"Real Estate Operator",
            "type":"Services"
        }
    ],
    "sg:phone":"+1 423 337 5602",
    "sg:postcode":"37874",
    "sg:province":"TN",
    "sg:tags":[
        "property",
        "lessor"
    ],
    "wof:name":"Jack Hanley",
    "wof:placetype":"venue"
},
  "geometry": {"coordinates":[-84.556861,35.586278],"type":"Point"}
}