{
  "type": "Feature",
  "properties": {
    "addr:full":"3645 Sunnyside St Memphis TN 38135",
    "addr:housenumber":"3645",
    "addr:postcode":"38135",
    "addr:street":"Sunnyside St",
    "iso:country":"US",
    "sg:address":"3645 Sunnyside St",
    "sg:city":"Memphis",
    "sg:classifiers":[
        {
            "category":"Wholesale",
            "subcategory":"Electrical",
            "type":"Manufacturing & Wholesale Goods"
        }
    ],
    "sg:phone":"+1 901 380 9383",
    "sg:postcode":"38135",
    "sg:province":"TN",
    "sg:tags":[
        "alarm",
        "burglar",
        "system"
    ],
    "wof:name":"Chipster Alarms",
    "wof:placetype":"venue"
},
  "geometry": {"coordinates":[-89.887085,35.225369],"type":"Point"}
}