{
  "type": "Feature",
  "properties": {
    "iso:country":"US",
    "sg:address":"6340 Waterlevel Hwy",
    "sg:city":"Cleveland",
    "sg:classifiers":[
        {
            "category":"Shopping",
            "subcategory":"Department Store",
            "type":"Retail Goods"
        }
    ],
    "sg:phone":"+1 423 472 1861",
    "sg:postcode":"37323",
    "sg:province":"TN",
    "sg:tags":[
        "shop"
    ],
    "wof:name":"Bargain Place",
    "wof:placetype":"venue"
},
  "geometry": {"coordinates":[-84.75077,35.133086],"type":"Point"}
}