{
  "type": "Feature",
  "properties": {
    "iso:country":"US",
    "sg:address":"325 E Broadway St",
    "sg:city":"Newport",
    "sg:classifiers":[
        {
            "category":"Banks & Credit Unions",
            "subcategory":"Bank",
            "type":"Services"
        }
    ],
    "sg:phone":"+1 423 623 4011",
    "sg:postcode":"37821",
    "sg:province":"TN",
    "sg:tags":[
        "loan",
        "real estate"
    ],
    "wof:name":"Closing Place",
    "wof:placetype":"venue"
},
  "geometry": {"coordinates":[-83.185158,35.966613],"type":"Point"}
}