{
  "type": "Feature",
  "properties": {
    "iso:country":"US",
    "sg:address":"429 Bakertown Rd",
    "sg:city":"Antioch",
    "sg:classifiers":[
        {
            "category":"Professional",
            "type":"Services"
        }
    ],
    "sg:phone":"+1 615 333 2341",
    "sg:postcode":"37013",
    "sg:province":"TN",
    "wof:name":"Corey L Blake Services",
    "wof:placetype":"venue"
},
  "geometry": {"coordinates":[-86.68788600000001,36.071674],"type":"Point"}
}