{
  "type": "Feature",
  "properties": {
    "iso:country":"US",
    "sg:address":"9413 Apison Pike",
    "sg:city":"Ooltewah",
    "sg:classifiers":[
        {
            "category":"Health Services",
            "subcategory":"Doctor",
            "type":"Services"
        }
    ],
    "sg:phone":"+1 423 396 4020",
    "sg:postcode":"37363",
    "sg:province":"TN",
    "sg:tags":[
        "dentist"
    ],
    "wof:name":"Family & Cosmetic Dentistry",
    "wof:placetype":"venue"
},
  "geometry": {"coordinates":[-85.069745,35.060844],"type":"Point"}
}