{
  "type": "Feature",
  "properties": {
    "iso:country":"US",
    "sg:address":"3715 Timberlake Dr SW",
    "sg:city":"Knoxville",
    "sg:classifiers":[
        {
            "category":"Building & Trades",
            "subcategory":"Landscaping Services",
            "type":"Services"
        }
    ],
    "sg:phone":"+1 865 577 6356",
    "sg:postcode":"37920",
    "sg:province":"TN",
    "wof:name":"Natural Designs",
    "wof:placetype":"venue"
},
  "geometry": {"coordinates":[-83.962637,35.91729],"type":"Point"}
}