{
  "type": "Feature",
  "properties": {
    "iso:country":"US",
    "sg:address":"1815 Tuskegee Blvd",
    "sg:city":"Chattanooga",
    "sg:classifiers":[
        {
            "category":"Building & Trades",
            "subcategory":"Construction",
            "type":"Services"
        }
    ],
    "sg:phone":"+1 423 892 4516",
    "sg:postcode":"37421",
    "sg:province":"TN",
    "sg:tags":[
        "product",
        "asphalt"
    ],
    "wof:name":"James Smith Construction Inc",
    "wof:placetype":"venue"
},
  "geometry": {"coordinates":[-85.187971,35.040363],"type":"Point"}
}