{
  "type": "Feature",
  "properties": {
    "iso:country":"US",
    "sg:address":"248 N Military Ave",
    "sg:city":"Lawrenceburg",
    "sg:classifiers":[
        {
            "category":"Banks & Credit Unions",
            "subcategory":"Bank",
            "type":"Services"
        }
    ],
    "sg:phone":"+1 931 766 0056",
    "sg:postcode":"38464",
    "sg:province":"TN",
    "sg:tags":[
        "depository",
        "banking"
    ],
    "wof:name":"O K Check Cashing",
    "wof:placetype":"venue"
},
  "geometry": {"coordinates":[-87.33433100000001,35.24212],"type":"Point"}
}