{
  "type": "Feature",
  "properties": {
    "iso:country":"US",
    "sg:address":"124 12th Ave S",
    "sg:city":"Nashville",
    "sg:classifiers":[
        {
            "category":"Professional",
            "subcategory":"Management & Consulting",
            "type":"Services"
        }
    ],
    "sg:phone":"+1 615 254 1875",
    "sg:postcode":"37203",
    "sg:province":"TN",
    "wof:name":"Armistead Barkley",
    "wof:placetype":"venue"
},
  "geometry": {"coordinates":[-86.787195,36.156324],"type":"Point"}
}