{
  "type": "Feature",
  "properties": {
    "iso:country":"US",
    "sg:address":"7428 Rolling River Pkwy",
    "sg:city":"Nashville",
    "sg:classifiers":[
        {
            "category":"Insurance",
            "subcategory":"Insurance Agent",
            "type":"Services"
        }
    ],
    "sg:phone":"+1 615 646 5501",
    "sg:postcode":"37221",
    "sg:province":"TN",
    "wof:name":"Scot H Crawford & Associates",
    "wof:placetype":"venue"
},
  "geometry": {"coordinates":[-86.96691800000001,36.062757],"type":"Point"}
}