{
  "type": "Feature",
  "properties": {
    "addr:full":"14402 Dayton Pike Sale Creek TN 37373",
    "addr:housenumber":"14402",
    "addr:postcode":"37373",
    "addr:street":"Dayton Pike",
    "iso:country":"US",
    "sg:address":"14402 Dayton Pike",
    "sg:city":"Sale Creek",
    "sg:classifiers":[
        {
            "category":"Shopping",
            "subcategory":"Clothing, Apparel, & Fashions",
            "type":"Retail Goods"
        }
    ],
    "sg:phone":"+1 423 451 0070",
    "sg:postcode":"37373",
    "sg:province":"TN",
    "sg:tags":[
        "uniform"
    ],
    "wof:name":"Uniform Shoppe",
    "wof:placetype":"venue"
},
  "geometry": {"coordinates":[-85.121779,35.356414],"type":"Point"}
}