{
  "type": "Feature",
  "properties": {
    "addr:full":"260 Brown Dr Jacksboro TN 37757",
    "addr:housenumber":"260",
    "addr:postcode":"37757",
    "addr:street":"Brown Dr",
    "iso:country":"US",
    "sg:address":"260 Brown Dr",
    "sg:city":"Jacksboro",
    "sg:classifiers":[
        {
            "category":"Health Services",
            "subcategory":"Chiropractor",
            "type":"Services"
        }
    ],
    "sg:phone":"+1 423 562 0017",
    "sg:postcode":"37757",
    "sg:province":"TN",
    "wof:name":"Lindon Owens DC",
    "wof:placetype":"venue"
},
  "geometry": {"coordinates":[-84.13965399999999,36.321671],"type":"Point"}
}