{
  "type": "Feature",
  "properties": {
    "iso:country":"US",
    "sg:address":"70 N 4th St",
    "sg:city":"Memphis",
    "sg:classifiers":[
        {
            "category":"Real Estate",
            "subcategory":"Real Estate Operator",
            "type":"Services"
        }
    ],
    "sg:phone":"+1 901 543 8700",
    "sg:postcode":"38103",
    "sg:province":"TN",
    "sg:tags":[
        "apartment"
    ],
    "wof:name":"Fielder Square Downtown",
    "wof:placetype":"venue"
},
  "geometry": {"coordinates":[-90.04701900000001,35.144806],"type":"Point"}
}