{
  "type": "Feature",
  "properties": {
    "iso:country":"US",
    "sg:address":"8000 E Brainerd Rd",
    "sg:city":"Chattanooga",
    "sg:classifiers":[
        {
            "category":"Shopping",
            "type":"Retail Goods"
        }
    ],
    "sg:phone":"+1 423 855 2051",
    "sg:postcode":"37421",
    "sg:province":"TN",
    "sg:tags":[
        "cake",
        "equipment",
        "decorating",
        "merchandise",
        "supply"
    ],
    "sg:website":"www.sugarshoppe.com",
    "wof:name":"Sugar Shoppe",
    "wof:placetype":"venue"
},
  "geometry": {"coordinates":[-85.150173,35.004214],"type":"Point"}
}