{
  "type": "Feature",
  "properties": {
    "iso:country":"US",
    "sg:address":"910 Greenwich Dr",
    "sg:city":"Maryville",
    "sg:classifiers":[
        {
            "category":"Professional",
            "subcategory":"Management & Consulting",
            "type":"Services"
        }
    ],
    "sg:phone":"+1 865 982 5058",
    "sg:postcode":"37803",
    "sg:province":"TN",
    "wof:name":"Mueller Consulting & Service",
    "wof:placetype":"venue"
},
  "geometry": {"coordinates":[-84.01217,35.699043],"type":"Point"}
}