{
  "type": "Feature",
  "properties": {
    "iso:country":"US",
    "sg:address":"2911 Old Knoxville Hwy",
    "sg:city":"Maryville",
    "sg:classifiers":[
        {
            "category":"Banks & Credit Unions",
            "subcategory":"Bank",
            "type":"Services"
        }
    ],
    "sg:phone":"+1 865 681 9848",
    "sg:postcode":"37804",
    "sg:province":"TN",
    "sg:tags":[
        "depository",
        "banking"
    ],
    "wof:name":"Check In Cash Out Inc",
    "wof:placetype":"venue"
},
  "geometry": {"coordinates":[-83.94318699999999,35.801518],"type":"Point"}
}