{
  "type": "Feature",
  "properties": {
    "iso:country":"US",
    "sg:address":"114 N Cedar Ave",
    "sg:city":"Cookeville",
    "sg:classifiers":[
        {
            "category":"Personal",
            "subcategory":"Beauty Salon",
            "type":"Services"
        }
    ],
    "sg:phone":"+1 931 372 1648",
    "sg:postcode":"38501",
    "sg:province":"TN",
    "sg:tags":[
        "shop"
    ],
    "wof:name":"Cedar Street Salon",
    "wof:placetype":"venue"
},
  "geometry": {"coordinates":[-85.50768600000001,36.16613],"type":"Point"}
}