{
  "type": "Feature",
  "properties": {
    "addr:full":"5205 Catalina Rd Knoxville TN 37918",
    "addr:housenumber":"5205",
    "addr:postcode":"37918",
    "addr:street":"Catalina Rd",
    "iso:country":"US",
    "sg:address":"5205 Catalina Rd",
    "sg:city":"Knoxville",
    "sg:classifiers":[
        {
            "category":"Wholesale",
            "subcategory":"Machinery & Supplies",
            "type":"Manufacturing & Wholesale Goods"
        }
    ],
    "sg:phone":"+1 865 281 7997",
    "sg:postcode":"37918",
    "sg:province":"TN",
    "sg:tags":[
        "equipment",
        "industrial"
    ],
    "wof:name":"Perkinson Company Inc",
    "wof:placetype":"venue"
},
  "geometry": {"coordinates":[-83.901743,36.059075],"type":"Point"}
}