{
  "type": "Feature",
  "properties": {
    "addr:full":"901 Idlewild Dr Madison TN 37115",
    "addr:housenumber":"901",
    "addr:postcode":"37115",
    "addr:street":"Idlewild Dr",
    "iso:country":"US",
    "sg:address":"901 Idlewild Dr",
    "sg:city":"Madison",
    "sg:classifiers":[
        {
            "category":"Organizations",
            "subcategory":"Religious Organization",
            "type":"Services"
        }
    ],
    "sg:phone":"+1 615 868 6975",
    "sg:postcode":"37115",
    "sg:province":"TN",
    "sg:tags":[
        "church"
    ],
    "wof:name":"Bible Holiness Church Inc",
    "wof:placetype":"venue"
},
  "geometry": {"coordinates":[-86.70171499999999,36.251278],"type":"Point"}
}