{
  "type": "Feature",
  "properties": {
    "iso:country":"US",
    "sg:address":"1680 Century Center Pkwy",
    "sg:city":"Bartlett",
    "sg:classifiers":[
        {
            "category":"Education",
            "subcategory":"Special Training",
            "type":"Public Place"
        }
    ],
    "sg:phone":"+1 901 377 7234",
    "sg:postcode":"38134",
    "sg:province":"TN",
    "sg:tags":[
        "program"
    ],
    "wof:name":"Chrysler Service Training",
    "wof:placetype":"venue"
},
  "geometry": {"coordinates":[-89.843503,35.168061],"type":"Point"}
}