{
  "type": "Feature",
  "properties": {
    "iso:country":"US",
    "sg:address":"1196 US Hwy 51 Bus",
    "sg:city":"Dyersburg",
    "sg:classifiers":[
        {
            "category":"Autos & Motor Vehicles",
            "subcategory":"Automobile Sales",
            "type":"Retail Goods"
        }
    ],
    "sg:phone":"+1 731 286 0055",
    "sg:postcode":"38024",
    "sg:province":"TN",
    "sg:tags":[
        "car",
        "dealer"
    ],
    "wof:name":"Twitty City Auto Sales",
    "wof:placetype":"venue"
},
  "geometry": {"coordinates":[-89.39540700000001,36.011563],"type":"Point"}
}