{
  "type": "Feature",
  "properties": {
    "addr:full":"4955 US Hwy 43 N Mt Pleasant TN 38483",
    "addr:housenumber":"4955",
    "addr:postcode":"38483",
    "addr:street":"Us Hwy 43 N",
    "iso:country":"US",
    "sg:address":"4955 US Hwy 43 N",
    "sg:city":"Mt Pleasant",
    "sg:classifiers":[
        {
            "category":"Food & Beverages",
            "subcategory":"Groceries & Convenience Stores",
            "type":"Retail Goods"
        }
    ],
    "sg:phone":"+1 931 964 0228",
    "sg:postcode":"38483",
    "sg:province":"TN",
    "sg:tags":[
        "product"
    ],
    "wof:name":"Tie Tgens Super Rama Foods",
    "wof:placetype":"venue"
},
  "geometry": {"coordinates":[-87.28075699999999,35.432297],"type":"Point"}
}