{
  "type": "Feature",
  "properties": {
    "iso:country":"US",
    "sg:address":"151 Gray Station Rd",
    "sg:city":"Johnson City",
    "sg:classifiers":[
        {
            "category":"Retail",
            "subcategory":"Portrait Studio",
            "type":"Services"
        }
    ],
    "sg:phone":"+1 423 477 8747",
    "sg:postcode":"37615",
    "sg:province":"TN",
    "sg:tags":[
        "photographer"
    ],
    "wof:name":"S & S Photography",
    "wof:placetype":"venue"
},
  "geometry": {"coordinates":[-82.45517599999999,36.437762],"type":"Point"}
}