{
  "type": "Feature",
  "properties": {
    "addr:full":"8563 Fay Rd Cordova TN 38018",
    "addr:housenumber":"8563",
    "addr:postcode":"38018",
    "addr:street":"Fay Rd",
    "iso:country":"US",
    "sg:address":"8563 Fay Rd",
    "sg:city":"Cordova",
    "sg:classifiers":[
        {
            "category":"Education",
            "subcategory":"School",
            "type":"Public Place"
        }
    ],
    "sg:phone":"+1 901 751 2000",
    "sg:postcode":"38018",
    "sg:province":"TN",
    "sg:tags":[
        "k-",
        "private"
    ],
    "sg:website":"http://www.lamplighterschool.org",
    "wof:name":"Lamplighter Montessori School",
    "wof:placetype":"venue"
},
  "geometry": {"coordinates":[-89.776161,35.154852],"type":"Point"}
}