{
  "type": "Feature",
  "properties": {
    "iso:country":"US",
    "sg:address":"229 Whitsett Rd",
    "sg:city":"Nashville",
    "sg:classifiers":[
        {
            "category":"Manufacturing",
            "subcategory":"Tools & Machinery",
            "type":"Manufacturing & Wholesale Goods"
        }
    ],
    "sg:phone":"+1 615 333 1496",
    "sg:postcode":"37210",
    "sg:province":"TN",
    "sg:tags":[
        "cleaning",
        "system"
    ],
    "sg:website":"www.safety-kleen.com",
    "wof:name":"Safety-Kleen Corp",
    "wof:placetype":"venue"
},
  "geometry": {"coordinates":[-86.74385700000001,36.115119],"type":"Point"}
}