{
  "type": "Feature",
  "properties": {
    "iso:country":"US",
    "sg:address":"279 George Anderson Rd",
    "sg:city":"Medina",
    "sg:classifiers":[
        {
            "category":"Utilities",
            "subcategory":"Refuse",
            "type":"Services"
        }
    ],
    "sg:phone":"+1 731 427 8819",
    "sg:postcode":"38355",
    "sg:province":"TN",
    "sg:tags":[
        "garbage",
        "collection"
    ],
    "wof:name":"Brady Smith Sanitation Svc",
    "wof:placetype":"venue"
},
  "geometry": {"coordinates":[-88.71194300000001,35.751719],"type":"Point"}
}