{
  "type": "Feature",
  "properties": {
    "addr:full":"231 S 10th St Clarksville TN 37040",
    "addr:housenumber":"231",
    "addr:postcode":"37040",
    "addr:street":"S 10Th St",
    "iso:country":"US",
    "sg:address":"231 S 10th St",
    "sg:city":"Clarksville",
    "sg:classifiers":[
        {
            "category":"Banks & Credit Unions",
            "subcategory":"Bank",
            "type":"Services"
        }
    ],
    "sg:phone":"+1 931 648 2555",
    "sg:postcode":"37040",
    "sg:province":"TN",
    "sg:tags":[
        "cashing",
        "check"
    ],
    "wof:name":"Tenth Street Money Store",
    "wof:placetype":"venue"
},
  "geometry": {"coordinates":[-87.346357,36.52674],"type":"Point"}
}