{
  "type": "Feature",
  "properties": {
    "iso:country":"US",
    "sg:address":"2604 Fort Henry Dr",
    "sg:city":"Kingsport",
    "sg:classifiers":[
        {
            "category":"Autos & Motor Vehicles",
            "subcategory":"Auto Supplies",
            "type":"Retail Goods"
        }
    ],
    "sg:phone":"+1 423 247 2271",
    "sg:postcode":"37664",
    "sg:province":"TN",
    "sg:tags":[
        "equipment",
        "racing",
        "car",
        "automobile"
    ],
    "wof:name":"Gulley Performance Ctr",
    "wof:placetype":"venue"
},
  "geometry": {"coordinates":[-82.517951,36.521879],"type":"Point"}
}