{
  "type": "Feature",
  "properties": {
    "iso:country":"US",
    "sg:address":"201 Willis Knight Dr",
    "sg:city":"Red Boiling Spgs",
    "sg:classifiers":[
        {
            "category":"Real Estate",
            "subcategory":"Real Estate Agent",
            "type":"Services"
        }
    ],
    "sg:phone":"+1 615 699 2107",
    "sg:postcode":"37150",
    "sg:province":"TN",
    "sg:tags":[
        "authorities",
        "housing"
    ],
    "wof:name":"Portland Housing Authority",
    "wof:placetype":"venue"
},
  "geometry": {"coordinates":[-85.841134,36.532658],"type":"Point"}
}