{
  "type": "Feature",
  "properties": {
    "iso:country":"US",
    "sg:address":"206 E Division St",
    "sg:city":"Mount Juliet",
    "sg:classifiers":[
        {
            "category":"Wholesale",
            "subcategory":"Stationery",
            "type":"Manufacturing & Wholesale Goods"
        }
    ],
    "sg:phone":"+1 615 754 9797",
    "sg:postcode":"37122",
    "sg:province":"TN",
    "sg:tags":[
        "sensitive",
        "industrial",
        "tape",
        "pressure"
    ],
    "wof:name":"Jdc Inc",
    "wof:placetype":"venue"
},
  "geometry": {"coordinates":[-86.51425999999999,36.197201],"type":"Point"}
}