{
  "type": "Feature",
  "properties": {
    "iso:country":"US",
    "sg:address":"200 Tennessee Dr",
    "sg:city":"Livingston",
    "sg:classifiers":[
        {
            "category":"Manufacturing",
            "subcategory":"Building Materials",
            "type":"Manufacturing & Wholesale Goods"
        }
    ],
    "sg:phone":"+1 931 823 0660",
    "sg:postcode":"38570",
    "sg:province":"TN",
    "sg:tags":[
        "manufacture",
        "wooden",
        "fireplace",
        "mantel"
    ],
    "wof:name":"American Classic Mantel Co",
    "wof:placetype":"venue"
},
  "geometry": {"coordinates":[-85.349914,36.374304],"type":"Point"}
}