{
  "type": "Feature",
  "properties": {
    "iso:country":"US",
    "sg:address":"110 W High St",
    "sg:city":"Woodbury",
    "sg:classifiers":[
        {
            "category":"Manufacturing",
            "subcategory":"Printing",
            "type":"Manufacturing & Wholesale Goods"
        }
    ],
    "sg:phone":"+1 615 563 5555",
    "sg:postcode":"37190",
    "sg:province":"TN",
    "sg:tags":[
        "commercial"
    ],
    "wof:name":"Stewart Printing",
    "wof:placetype":"venue"
},
  "geometry": {"coordinates":[-86.070059,35.826707],"type":"Point"}
}