{
  "type": "Feature",
  "properties": {
    "iso:country":"US",
    "sg:address":"136 Cumberland St",
    "sg:city":"Memphis",
    "sg:classifiers":[
        {
            "category":"Wholesale",
            "subcategory":"Stationery",
            "type":"Manufacturing & Wholesale Goods"
        }
    ],
    "sg:phone":"+1 901 454 4801",
    "sg:postcode":"38112",
    "sg:province":"TN",
    "sg:tags":[
        "packaging",
        "material"
    ],
    "wof:name":"ASA Industries",
    "wof:placetype":"venue"
},
  "geometry": {"coordinates":[-89.969105,35.146079],"type":"Point"}
}