{
  "type": "Feature",
  "properties": {
    "addr:full":"2609 Highview Dr Nashville TN 37206",
    "addr:housenumber":"2609",
    "addr:postcode":"37206",
    "addr:street":"Highview Dr",
    "iso:country":"US",
    "sg:address":"2609 Highview Dr",
    "sg:city":"Nashville",
    "sg:classifiers":[
        {
            "category":"Building & Trades",
            "subcategory":"Electrical",
            "type":"Services"
        }
    ],
    "sg:phone":"+1 615 589 0135",
    "sg:postcode":"37206",
    "sg:province":"TN",
    "sg:tags":[
        "electric",
        "contractor"
    ],
    "wof:name":"ABC Electric Inc",
    "wof:placetype":"venue"
},
  "geometry": {"coordinates":[-86.706845,36.193009],"type":"Point"}
}