{
  "type": "Feature",
  "properties": {
    "iso:country":"US",
    "sg:address":"2617 Twisted Oak Cv S",
    "sg:city":"Cordova",
    "sg:classifiers":[
        {
            "category":"Autos & Motor Vehicles",
            "subcategory":"Automobile Sales",
            "type":"Retail Goods"
        }
    ],
    "sg:phone":"+1 901 384 7938",
    "sg:postcode":"38016",
    "sg:province":"TN",
    "sg:tags":[
        "new",
        "car"
    ],
    "wof:name":"Mercedes Benz Club Of America, Inc., Memphis Section",
    "wof:placetype":"venue"
},
  "geometry": {"coordinates":[-89.76296600000001,35.196923],"type":"Point"}
}