{
  "type": "Feature",
  "properties": {
    "iso:country":"US",
    "sg:address":"201 Broad St",
    "sg:city":"Chattanooga",
    "sg:classifiers":[
        {
            "category":"Restaurant",
            "type":"Food & Drink"
        },
        {
            "category":"Ice Cream",
            "type":"Food & Drink"
        }
    ],
    "sg:menulink":"http://www.allmenus.com/tn/chattanooga/217401-ben--jerrys/menu/",
    "sg:postcode":"37402",
    "sg:province":"TN",
    "sg:tags":[
        "american",
        "ice",
        "cream"
    ],
    "wof:name":"Ben & Jerry's",
    "wof:placetype":"venue"
},
  "geometry": {"coordinates":[-85.311173,35.054437],"type":"Point"}
}