{
  "type": "Feature",
  "properties": {
    "iso:country":"US",
    "sg:address":"1489 Hayne Rd",
    "sg:city":"Memphis",
    "sg:classifiers":[
        {
            "category":"Food & Beverages",
            "subcategory":"Specialty",
            "type":"Retail Goods"
        },
        {
            "category":"Professional",
            "subcategory":"Management & Consulting",
            "type":"Services"
        }
    ],
    "sg:phone":"+1 901 761 5338",
    "sg:postcode":"38119",
    "sg:province":"TN",
    "sg:tags":[
        "selling",
        "establishment",
        "direct"
    ],
    "wof:name":"Shaklee Products Distributors",
    "wof:placetype":"venue"
},
  "geometry": {"coordinates":[-89.881884,35.091185],"type":"Point"}
}