{
  "type": "Feature",
  "properties": {
    "iso:country":"US",
    "sg:address":"1755 Huskey Dr",
    "sg:city":"Clarksville",
    "sg:classifiers":[
        {
            "category":"Home & Garden",
            "subcategory":"Carpets & Floor Coverings",
            "type":"Retail Goods"
        }
    ],
    "sg:phone":"+1 931 645 0153",
    "sg:postcode":"37040",
    "sg:province":"TN",
    "sg:tags":[
        "material"
    ],
    "wof:name":"Custom Floors",
    "wof:placetype":"venue"
},
  "geometry": {"coordinates":[-87.329334,36.555919],"type":"Point"}
}