{
  "type": "Feature",
  "properties": {
    "iso:country":"US",
    "sg:address":"4924 Kaye Rd",
    "sg:city":"Memphis",
    "sg:classifiers":[
        {
            "category":"Professional",
            "subcategory":"Art Services",
            "type":"Services"
        }
    ],
    "sg:phone":"+1 901 289 0222",
    "sg:postcode":"38117",
    "sg:province":"TN",
    "sg:tags":[
        "commercial",
        "design"
    ],
    "wof:name":"John Vergos Art & Design",
    "wof:placetype":"venue"
},
  "geometry": {"coordinates":[-89.897267,35.104356],"type":"Point"}
}