{
  "type": "Feature",
  "properties": {
    "iso:country":"US",
    "sg:address":"1805 Alpine Dr",
    "sg:city":"Clarksville",
    "sg:classifiers":[
        {
            "category":"Real Estate",
            "subcategory":"Surveying",
            "type":"Services"
        }
    ],
    "sg:phone":"+1 931 920 1750",
    "sg:postcode":"37040",
    "sg:province":"TN",
    "sg:tags":[
        "surveyor"
    ],
    "wof:name":"Suiter Surveying & Land Plnnng",
    "wof:placetype":"venue"
},
  "geometry": {"coordinates":[-87.33119499999999,36.554821],"type":"Point"}
}