{
  "type": "Feature",
  "properties": {
    "iso:country":"US",
    "sg:address":"101 W Bockman Way",
    "sg:city":"Sparta",
    "sg:classifiers":[
        {
            "category":"Insurance",
            "subcategory":"Insurance Agent",
            "type":"Services"
        }
    ],
    "sg:phone":"+1 931 836 2459",
    "sg:postcode":"38583",
    "sg:province":"TN",
    "wof:name":"Woodmen Of The World Insurance",
    "wof:placetype":"venue"
},
  "geometry": {"coordinates":[-85.46735200000001,35.926787],"type":"Point"}
}