{
  "type": "Feature",
  "properties": {
    "addr:full":"625 Dry Creek Rd Smithville TN 37166",
    "addr:housenumber":"625",
    "addr:postcode":"37166",
    "addr:street":"Dry Creek Rd",
    "iso:country":"US",
    "sg:address":"625 Dry Creek Rd",
    "sg:city":"Smithville",
    "sg:classifiers":[
        {
            "category":"Personal",
            "subcategory":"Beauty Salon",
            "type":"Services"
        },
        {
            "category":"Personal",
            "subcategory":"Barber",
            "type":"Services"
        }
    ],
    "sg:phone":"+1 615 597 9998",
    "sg:postcode":"37166",
    "sg:province":"TN",
    "sg:tags":[
        "shop"
    ],
    "wof:name":"It's All About Looks",
    "wof:placetype":"venue"
},
  "geometry": {"coordinates":[-85.837982,35.956637],"type":"Point"}
}