{
  "type": "Feature",
  "properties": {
    "addr:full":"3945 Forestview Dr Cleveland TN 37312",
    "addr:housenumber":"3945",
    "addr:postcode":"37312",
    "addr:street":"Forestview Dr",
    "iso:country":"US",
    "sg:address":"3945 Forestview Dr",
    "sg:city":"Cleveland",
    "sg:classifiers":[
        {
            "category":"Retail",
            "subcategory":"Photofinishing",
            "type":"Services"
        }
    ],
    "sg:phone":"+1 423 339 2632",
    "sg:postcode":"37312",
    "sg:province":"TN",
    "sg:tags":[
        "laboratory"
    ],
    "wof:name":"Pierce Digital Imaging",
    "wof:placetype":"venue"
},
  "geometry": {"coordinates":[-84.864395,35.204602],"type":"Point"}
}