{
  "type": "Feature",
  "properties": {
    "iso:country":"US",
    "sg:address":"5710 Brainerd Rd",
    "sg:city":"Chattanooga",
    "sg:classifiers":[
        {
            "category":"Travel",
            "subcategory":"Travel Agent",
            "type":"Entertainment"
        }
    ],
    "sg:phone":"+1 423 842 3550",
    "sg:postcode":"37411",
    "sg:province":"TN",
    "sg:tags":[
        "agency",
        "bureau"
    ],
    "wof:name":"Great American Travel Agency",
    "wof:placetype":"venue"
},
  "geometry": {"coordinates":[-85.214145,35.011559],"type":"Point"}
}