{
  "type": "Feature",
  "properties": {
    "iso:country":"US",
    "sg:address":"5490 Ragsdale Rd",
    "sg:city":"Manchester",
    "sg:classifiers":[
        {
            "category":"Organizations",
            "subcategory":"Community Association",
            "type":"Services"
        }
    ],
    "sg:phone":"+1 931 728 4466",
    "sg:postcode":"37355",
    "sg:province":"TN",
    "wof:name":"Fabulous Fords Forever In",
    "wof:placetype":"venue"
},
  "geometry": {"coordinates":[-85.98518199999999,35.513103],"type":"Point"}
}