{
  "type": "Feature",
  "properties": {
    "iso:country":"US",
    "sg:address":"5348 State Hwy 153",
    "sg:city":"Hixson",
    "sg:classifiers":[
        {
            "category":"Autos & Motor Vehicles",
            "subcategory":"Automobile Sales",
            "type":"Retail Goods"
        }
    ],
    "sg:phone":"+1 423 875 2023",
    "sg:postcode":"37343",
    "sg:province":"TN",
    "sg:tags":[
        "dealer",
        "passenger",
        "leasing",
        "truck",
        "car"
    ],
    "sg:website":"www.marshallmizeford.com",
    "wof:name":"Marshal Mize Ford Inc",
    "wof:placetype":"venue"
},
  "geometry": {"coordinates":[-85.247607,35.138091],"type":"Point"}
}