{
  "type": "Feature",
  "properties": {
    "addr:full":"216 W Brooks Rd Memphis TN 38109",
    "addr:housenumber":"216",
    "addr:postcode":"38109",
    "addr:street":"W Brooks Rd",
    "iso:country":"US",
    "sg:address":"216 W Brooks Rd",
    "sg:city":"Memphis",
    "sg:classifiers":[
        {
            "category":"Bars & Pubs",
            "type":"Food & Drink"
        }
    ],
    "sg:phone":"+1 901 785 9360",
    "sg:postcode":"38109",
    "sg:province":"TN",
    "sg:tags":[
        "drinking"
    ],
    "wof:name":"Kojacks",
    "wof:placetype":"venue"
},
  "geometry": {"coordinates":[-90.072213,35.063378],"type":"Point"}
}