{
  "type": "Feature",
  "properties": {
    "iso:country":"US",
    "sg:address":"211 Commerce St",
    "sg:city":"Nashville",
    "sg:classifiers":[
        {
            "category":"Professional",
            "subcategory":"Lawyer & Legal Services",
            "type":"Services"
        }
    ],
    "sg:phone":"+1 615 726 5693",
    "sg:postcode":"37201",
    "sg:province":"TN",
    "sg:tags":[
        "attorney"
    ],
    "wof:name":"Nichole Francis",
    "wof:placetype":"venue"
},
  "geometry": {"coordinates":[-86.776338,36.163057],"type":"Point"}
}