{
  "type": "Feature",
  "properties": {
    "iso:country":"US",
    "sg:address":"228 Jackson Meadows Dr",
    "sg:city":"Hermitage",
    "sg:classifiers":[
        {
            "category":"Banks & Credit Unions",
            "subcategory":"Bank",
            "type":"Services"
        }
    ],
    "sg:phone":"+1 615 902 0229",
    "sg:postcode":"37076",
    "sg:province":"TN",
    "sg:tags":[
        "mortgage"
    ],
    "sg:website":"www.anchormortgage.com",
    "wof:name":"Anchor Mortgage",
    "wof:placetype":"venue"
},
  "geometry": {"coordinates":[-86.599723,36.217938],"type":"Point"}
}