{
  "type": "Feature",
  "properties": {
    "addr:full":"2405 Fly Rd Nolensville TN 37135",
    "addr:housenumber":"2405",
    "addr:postcode":"37135",
    "addr:street":"Fly Rd",
    "iso:country":"US",
    "sg:address":"2405 Fly Rd",
    "sg:city":"Nolensville",
    "sg:classifiers":[
        {
            "category":"Building & Trades",
            "subcategory":"Construction",
            "type":"Services"
        }
    ],
    "sg:phone":"+1 615 776 7670",
    "sg:postcode":"37135",
    "sg:province":"TN",
    "sg:tags":[
        "house"
    ],
    "wof:name":"Scott Home Improvement",
    "wof:placetype":"venue"
},
  "geometry": {"coordinates":[-86.633955,35.961611],"type":"Point"}
}