{
  "type": "Feature",
  "properties": {
    "iso:country":"US",
    "sg:address":"8101 Dayton Blvd",
    "sg:city":"Hixson",
    "sg:classifiers":[
        {
            "category":"Shopping",
            "subcategory":"Used Merchandise",
            "type":"Retail Goods"
        }
    ],
    "sg:phone":"+1 423 842 3039",
    "sg:postcode":"37343",
    "sg:province":"TN",
    "sg:tags":[
        "store"
    ],
    "wof:name":"Country Boy Store",
    "wof:placetype":"venue"
},
  "geometry": {"coordinates":[-85.234235,35.206159],"type":"Point"}
}