{
  "type": "Feature",
  "properties": {
    "iso:country":"US",
    "sg:address":"1789 Kirby Pkwy",
    "sg:city":"Germantown",
    "sg:classifiers":[
        {
            "category":"Real Estate",
            "subcategory":"Real Estate Services",
            "type":"Services"
        }
    ],
    "sg:phone":"+1 901 754 7056",
    "sg:postcode":"38120",
    "sg:province":"TN",
    "sg:tags":[
        "company",
        "title"
    ],
    "wof:name":"Allied Title",
    "wof:placetype":"venue"
},
  "geometry": {"coordinates":[-89.839349,35.101043],"type":"Point"}
}