{
  "type": "Feature",
  "properties": {
    "iso:country":"US",
    "sg:address":"105 Gieger Rd NE",
    "sg:city":"Cleveland",
    "sg:classifiers":[
        {
            "category":"Building & Trades",
            "subcategory":"Construction",
            "type":"Services"
        }
    ],
    "sg:phone":"+1 423 336 5838",
    "sg:postcode":"37312",
    "sg:province":"TN",
    "sg:tags":[
        "hanging",
        "contractor"
    ],
    "wof:name":"Jones Painting & Home Repair",
    "wof:placetype":"venue"
},
  "geometry": {"coordinates":[-84.798637,35.242045],"type":"Point"}
}