{
  "type": "Feature",
  "properties": {
    "addr:full":"4363 Hawkeye St Memphis TN 38109",
    "addr:housenumber":"4363",
    "addr:postcode":"38109",
    "addr:street":"Hawkeye St",
    "iso:country":"US",
    "sg:address":"4363 Hawkeye St",
    "sg:city":"Memphis",
    "sg:classifiers":[
        {
            "category":"Professional",
            "subcategory":"Lawyer & Legal Services",
            "type":"Services"
        }
    ],
    "sg:phone":"+1 901 650 8279",
    "sg:postcode":"38109",
    "sg:province":"TN",
    "wof:name":"Peete Legal Services",
    "wof:placetype":"venue"
},
  "geometry": {"coordinates":[-90.090422,35.030296],"type":"Point"}
}