{
  "type": "Feature",
  "properties": {
    "addr:full":"491 S Fishing Ford Rd Petersburg TN 37144",
    "addr:housenumber":"491",
    "addr:postcode":"37144",
    "addr:street":"S Fishing Ford Rd",
    "iso:country":"US",
    "sg:address":"491 S Fishing Ford Rd",
    "sg:city":"Petersburg",
    "sg:classifiers":[
        {
            "category":"Organizations",
            "subcategory":"Religious Organization",
            "type":"Services"
        }
    ],
    "sg:phone":"+1 931 433 7018",
    "sg:postcode":"37144",
    "sg:province":"TN",
    "sg:tags":[
        "church"
    ],
    "wof:name":"Howell First Baptist Church",
    "wof:placetype":"venue"
},
  "geometry": {"coordinates":[-86.613648,35.23333],"type":"Point"}
}