{
  "type": "Feature",
  "properties": {
    "addr:full":"4160 Clarksville Pike Nashville TN 37218",
    "addr:housenumber":"4160",
    "addr:postcode":"37218",
    "addr:street":"Clarksville Pike",
    "iso:country":"US",
    "sg:address":"4160 Clarksville Pike",
    "sg:city":"Nashville",
    "sg:classifiers":[
        {
            "category":"Autos & Motor Vehicles",
            "subcategory":"Fuel & Gas Station",
            "type":"Retail Goods"
        }
    ],
    "sg:phone":"+1 615 299 0616",
    "sg:postcode":"37218",
    "sg:province":"TN",
    "sg:tags":[
        "grocery",
        "station",
        "gasoline"
    ],
    "wof:name":"Speedway 8426",
    "wof:placetype":"venue"
},
  "geometry": {"coordinates":[-86.83727500000001,36.217269],"type":"Point"}
}