{
  "type": "Feature",
  "properties": {
    "addr:full":"2172 Mansfield Gap Rd Talbott TN 37877",
    "addr:housenumber":"2172",
    "addr:postcode":"37877",
    "addr:street":"Mansfield Gap Rd",
    "iso:country":"US",
    "sg:address":"2172 Mansfield Gap Rd",
    "sg:city":"Talbott",
    "sg:classifiers":[
        {
            "category":"Professional",
            "type":"Services"
        }
    ],
    "sg:phone":"+1 865 674 0957",
    "sg:postcode":"37877",
    "sg:province":"TN",
    "wof:name":"L R Stansberry",
    "wof:placetype":"venue"
},
  "geometry": {"coordinates":[-83.35239,36.133606],"type":"Point"}
}