{
  "type": "Feature",
  "properties": {
    "addr:full":"2527 Lebanon Pike Nashville TN 37214",
    "addr:housenumber":"2527",
    "addr:postcode":"37214",
    "addr:street":"Lebanon Pike",
    "iso:country":"US",
    "sg:address":"2527 Lebanon Pike",
    "sg:city":"Nashville",
    "sg:classifiers":[
        {
            "category":"Restaurant",
            "type":"Food & Drink"
        }
    ],
    "sg:menulink":"http://www.allmenus.com/tn/nashville/246266-krystal/menu/",
    "sg:phone":"+1 615 883 0968",
    "sg:postcode":"37214",
    "sg:province":"TN",
    "sg:tags":[
        "burger",
        "american"
    ],
    "wof:name":"Krystal",
    "wof:placetype":"venue"
},
  "geometry": {"coordinates":[-86.67697699999999,36.169274],"type":"Point"}
}