{
  "type": "Feature",
  "properties": {
    "iso:country":"US",
    "sg:address":"4304 Charlotte Ave",
    "sg:city":"Nashville",
    "sg:classifiers":[
        {
            "category":"Health Services",
            "subcategory":"Doctor",
            "type":"Services"
        }
    ],
    "sg:phone":"+1 615 298 3384",
    "sg:postcode":"37209",
    "sg:province":"TN",
    "sg:tags":[
        "physician",
        "surgeon"
    ],
    "wof:name":"Helping Hands Surgical Assoc",
    "wof:placetype":"venue"
},
  "geometry": {"coordinates":[-86.839539,36.152356],"type":"Point"}
}