{
  "type": "Feature",
  "properties": {
    "iso:country":"US",
    "sg:address":"416 Church St",
    "sg:city":"Clarksville",
    "sg:classifiers":[
        {
            "category":"Organizations",
            "subcategory":"Religious Organization",
            "type":"Services"
        }
    ],
    "sg:phone":"+1 931 645 9587",
    "sg:postcode":"37040",
    "sg:province":"TN",
    "sg:tags":[
        "church"
    ],
    "wof:name":"Forest Street United Methodist",
    "wof:placetype":"venue"
},
  "geometry": {"coordinates":[-87.353712,36.51786],"type":"Point"}
}