{
  "type": "Feature",
  "properties": {
    "addr:full":"1201 E Main St Chattanooga TN 37408",
    "addr:housenumber":"1201",
    "addr:postcode":"37408",
    "addr:street":"E Main St",
    "iso:country":"US",
    "sg:address":"1201 E Main St",
    "sg:city":"Chattanooga",
    "sg:classifiers":[
        {
            "category":"Organizations",
            "subcategory":"Professional Association",
            "type":"Services"
        }
    ],
    "sg:phone":"+1 423 756 0507",
    "sg:postcode":"37408",
    "sg:province":"TN",
    "sg:website":"www.habitat.com",
    "wof:name":"Habitat For Humanity Home",
    "wof:placetype":"venue"
},
  "geometry": {"coordinates":[-85.288483,35.029095],"type":"Point"}
}