{
  "type": "Feature",
  "properties": {
    "addr:full":"4028 Papermill Dr Knoxville TN 37909",
    "addr:postcode":"4028;37909",
    "addr:street":"Papermill Dr",
    "iso:country":"US",
    "sg:address":"4028 Papermill Dr",
    "sg:city":"Knoxville",
    "sg:classifiers":[
        {
            "category":"Professional",
            "subcategory":"Management & Consulting",
            "type":"Services"
        }
    ],
    "sg:phone":"+1 865 558 0511",
    "sg:postcode":"37909",
    "sg:province":"TN",
    "sg:tags":[
        "food"
    ],
    "wof:name":"Tennessee Valley Food Svc",
    "wof:placetype":"venue"
},
  "geometry": {"coordinates":[-83.981595,35.953434],"type":"Point"}
}