{
  "type": "Feature",
  "properties": {
    "iso:country":"US",
    "sg:address":"517 W Madison Ave",
    "sg:city":"Athens",
    "sg:classifiers":[
        {
            "category":"Building & Trades",
            "subcategory":"Plumbing",
            "type":"Services"
        }
    ],
    "sg:phone":"+1 423 744 0256",
    "sg:postcode":"37303",
    "sg:province":"TN",
    "sg:tags":[
        "contractor"
    ],
    "wof:name":"D/B/A Advanced Mechanical",
    "wof:placetype":"venue"
},
  "geometry": {"coordinates":[-84.59986000000001,35.440059],"type":"Point"}
}