{
  "type": "Feature",
  "properties": {
    "iso:country":"US",
    "sg:address":"1720 Hwy 25 70 E",
    "sg:city":"Del Rio",
    "sg:classifiers":[
        {
            "category":"Travel",
            "subcategory":"Hotels & Motels",
            "type":"Entertainment"
        }
    ],
    "sg:phone":"+1 423 613 8424",
    "sg:postcode":"37727",
    "sg:province":"TN",
    "sg:tags":[
        "breakfast",
        "operation",
        "bed",
        "accommodation"
    ],
    "wof:name":"Cady's Farmhouse Inn",
    "wof:placetype":"venue"
},
  "geometry": {"coordinates":[-83.104292,35.953133],"type":"Point"}
}