{
  "type": "Feature",
  "properties": {
    "iso:country":"US",
    "sg:address":"103 E College St",
    "sg:city":"Dickson",
    "sg:classifiers":[
        {
            "category":"Retail",
            "subcategory":"Portrait Studio",
            "type":"Services"
        }
    ],
    "sg:phone":"+1 615 446 2722",
    "sg:postcode":"37055",
    "sg:province":"TN",
    "sg:tags":[
        "photo"
    ],
    "wof:name":"Hooper Photography",
    "wof:placetype":"venue"
},
  "geometry": {"coordinates":[-87.38697500000001,36.076157],"type":"Point"}
}