{
  "type": "Feature",
  "properties": {
    "addr:full":"5419 Hixson Pike Hixson TN 37343",
    "addr:housenumber":"5419",
    "addr:postcode":"37343",
    "addr:street":"Hixson Pike",
    "iso:country":"US",
    "sg:address":"5419 Hixson Pike",
    "sg:city":"Hixson",
    "sg:classifiers":[
        {
            "category":"Retail",
            "subcategory":"Animal Services",
            "type":"Services"
        }
    ],
    "sg:phone":"+1 423 842 1109",
    "sg:postcode":"37343",
    "sg:province":"TN",
    "sg:tags":[
        "pet",
        "grooming",
        "washing"
    ],
    "wof:name":"Dirty Dog",
    "wof:placetype":"venue"
},
  "geometry": {"coordinates":[-85.230895,35.141628],"type":"Point"}
}