{
  "type": "Feature",
  "properties": {
    "iso:country":"US",
    "sg:address":"200 S Headden Dr",
    "sg:city":"Ridgely",
    "sg:classifiers":[
        {
            "category":"Wholesale",
            "subcategory":"Machinery & Supplies",
            "type":"Manufacturing & Wholesale Goods"
        },
        {
            "category":"Shopping",
            "type":"Retail Goods"
        }
    ],
    "sg:phone":"+1 731 264 5561",
    "sg:postcode":"38080",
    "sg:province":"TN",
    "sg:tags":[
        "farm",
        "equipment",
        "merchandise"
    ],
    "wof:name":"Shaw Truck & Tractor Co Inc",
    "wof:placetype":"venue"
},
  "geometry": {"coordinates":[-89.47816899999999,36.262789],"type":"Point"}
}