{
  "type": "Feature",
  "properties": {
    "iso:country":"US",
    "sg:address":"900 Crown Point Rd W",
    "sg:city":"Signal Mountain",
    "sg:classifiers":[
        {
            "category":"Health Services",
            "subcategory":"Doctor",
            "type":"Services"
        }
    ],
    "sg:phone":"+1 423 886 2511",
    "sg:postcode":"37377",
    "sg:province":"TN",
    "sg:tags":[
        "medical"
    ],
    "wof:name":"James K Metcalfe MD",
    "wof:placetype":"venue"
},
  "geometry": {"coordinates":[-85.34075199999999,35.137287],"type":"Point"}
}