{
  "type": "Feature",
  "properties": {
    "addr:full":"10325 Richardson Landing Rd Drummonds TN 38023",
    "addr:housenumber":"10325",
    "addr:postcode":"38023",
    "addr:street":"Richardson Landing Rd",
    "iso:country":"US",
    "sg:address":"10325 Richardson Landing Rd",
    "sg:city":"Drummonds",
    "sg:classifiers":[
        {
            "category":"Professional",
            "subcategory":"Engineering",
            "type":"Services"
        }
    ],
    "sg:phone":"+1 901 835 3662",
    "sg:postcode":"38023",
    "sg:province":"TN",
    "sg:tags":[
        "consulting",
        "engineer"
    ],
    "wof:name":"Corps Of Engineer",
    "wof:placetype":"venue"
},
  "geometry": {"coordinates":[-89.942446,35.507994],"type":"Point"}
}