{
  "type": "Feature",
  "properties": {
    "iso:country":"US",
    "sg:address":"7063 Cutter Mill Rd",
    "sg:city":"Memphis",
    "sg:classifiers":[
        {
            "category":"Building & Trades",
            "subcategory":"Construction",
            "type":"Services"
        }
    ],
    "sg:phone":"+1 901 755 6357",
    "sg:postcode":"38141",
    "sg:province":"TN",
    "sg:tags":[
        "system",
        "specialty",
        "heating",
        "contractor",
        "air conditioning"
    ],
    "wof:name":"Absolute Heating & Air Conditioning",
    "wof:placetype":"venue"
},
  "geometry": {"coordinates":[-89.829492,35.016078],"type":"Point"}
}