{
  "type": "Feature",
  "properties": {
    "iso:country":"US",
    "sg:address":"105 N Monroe St",
    "sg:city":"Newbern",
    "sg:classifiers":[
        {
            "category":"Health Services",
            "subcategory":"Clinic",
            "type":"Services"
        }
    ],
    "sg:phone":"+1 731 627 0734",
    "sg:postcode":"38059",
    "sg:province":"TN",
    "sg:tags":[
        "home",
        "care"
    ],
    "wof:name":"Newbern Medical Clinic PC",
    "wof:placetype":"venue"
},
  "geometry": {"coordinates":[-89.264404,36.113905],"type":"Point"}
}