{
  "type": "Feature",
  "properties": {
    "iso:country":"US",
    "sg:address":"2008 E 3rd St",
    "sg:city":"Chattanooga",
    "sg:classifiers":[
        {
            "category":"Organizations",
            "subcategory":"Religious Organization",
            "type":"Services"
        }
    ],
    "sg:phone":"+1 423 622 7263",
    "sg:postcode":"37404",
    "sg:province":"TN",
    "wof:name":"East Third St Church Christ",
    "wof:placetype":"venue"
},
  "geometry": {"coordinates":[-85.26935,35.039846],"type":"Point"}
}