{
  "type": "Feature",
  "properties": {
    "addr:full":"510 W Main St Lebanon TN 37087",
    "addr:housenumber":"510",
    "addr:postcode":"37087",
    "addr:street":"W Main St",
    "iso:country":"US",
    "sg:address":"510 W Main St",
    "sg:city":"Lebanon",
    "sg:classifiers":[
        {
            "category":"Restaurant",
            "type":"Food & Drink"
        }
    ],
    "sg:phone":"+1 615 443 4697",
    "sg:postcode":"37087",
    "sg:province":"TN",
    "wof:name":"Los Compadres Mexican",
    "wof:placetype":"venue"
},
  "geometry": {"coordinates":[-86.30188200000001,36.209091],"type":"Point"}
}