{
  "type": "Feature",
  "properties": {
    "addr:full":"6000 Carriage Dr Memphis TN 38134",
    "addr:housenumber":"6000",
    "addr:postcode":"38134",
    "addr:street":"Carriage Dr",
    "iso:country":"US",
    "sg:address":"6000 Carriage Dr",
    "sg:city":"Memphis",
    "sg:classifiers":[
        {
            "category":"Professional",
            "subcategory":"Computer Services",
            "type":"Services"
        }
    ],
    "sg:phone":"+1 901 372 6426",
    "sg:postcode":"38134",
    "sg:province":"TN",
    "sg:tags":[
        "programing",
        "custom"
    ],
    "wof:name":"Computer Warmware Inc",
    "wof:placetype":"venue"
},
  "geometry": {"coordinates":[-89.864057,35.19689],"type":"Point"}
}