{
  "type": "Feature",
  "properties": {
    "iso:country":"US",
    "sg:address":"48 White Bridge Rd",
    "sg:city":"Nashville",
    "sg:phone":"+1 615 356 1556",
    "sg:postcode":"37205",
    "sg:province":"TN",
    "wof:name":"Anatolia Turkish Restaurant",
    "wof:placetype":"venue"
},
  "geometry": {"coordinates":[-86.853233,36.128719],"type":"Point"}
}