{
  "type": "Feature",
  "properties": {
    "iso:country":"US",
    "sg:address":"4651 Peppertree Ln",
    "sg:city":"Memphis",
    "sg:classifiers":[
        {
            "category":"Banks & Credit Unions",
            "subcategory":"Financial Services",
            "type":"Services"
        }
    ],
    "sg:phone":"+1 901 683 3336",
    "sg:postcode":"38117",
    "sg:province":"TN",
    "sg:tags":[
        "investment",
        "closed"
    ],
    "wof:name":"B C P Family Ltd Partnership",
    "wof:placetype":"venue"
},
  "geometry": {"coordinates":[-89.90802600000001,35.121309],"type":"Point"}
}