{
  "type": "Feature",
  "properties": {
    "iso:country":"US",
    "sg:address":"518 S Moore Rd",
    "sg:city":"Chattanooga",
    "sg:classifiers":[
        {
            "category":"Personal",
            "subcategory":"Beauty Salon",
            "type":"Services"
        }
    ],
    "sg:phone":"+1 423 892 5054",
    "sg:postcode":"37412",
    "sg:province":"TN",
    "wof:name":"House Spouse Chattanooga Style",
    "wof:placetype":"venue"
},
  "geometry": {"coordinates":[-85.23307,35.004028],"type":"Point"}
}