{
  "type": "Feature",
  "properties": {
    "addr:full":"100 Hemlock St Bruceton TN 38317",
    "addr:housenumber":"100",
    "addr:postcode":"38317",
    "addr:street":"Hemlock St",
    "iso:country":"US",
    "sg:address":"100 Hemlock St",
    "sg:city":"Bruceton",
    "sg:classifiers":[
        {
            "category":"Manufacturing",
            "subcategory":"Furniture",
            "type":"Manufacturing & Wholesale Goods"
        }
    ],
    "sg:phone":"+1 731 586 7902",
    "sg:postcode":"38317",
    "sg:province":"TN",
    "sg:tags":[
        "mfg",
        "contractor",
        "wood",
        "carpentry"
    ],
    "wof:name":"Jacks Cabinet Shop",
    "wof:placetype":"venue"
},
  "geometry": {"coordinates":[-88.241074,36.04405],"type":"Point"}
}