{
  "type": "Feature",
  "properties": {
    "iso:country":"US",
    "sg:address":"495 Creek Pt",
    "sg:city":"Mount Juliet",
    "sg:classifiers":[
        {
            "category":"Freight",
            "type":"Transportation"
        }
    ],
    "sg:phone":"+1 615 294 7160",
    "sg:postcode":"37122",
    "sg:province":"TN",
    "sg:tags":[
        "arrangement"
    ],
    "wof:name":"Brady Express",
    "wof:placetype":"venue"
},
  "geometry": {"coordinates":[-86.504623,36.226955],"type":"Point"}
}