{
  "type": "Feature",
  "properties": {
    "addr:full":"326 Shatolan Ct Blountville TN 37617",
    "addr:housenumber":"326",
    "addr:postcode":"37617",
    "addr:street":"Shatolan Ct",
    "iso:country":"US",
    "sg:address":"326 Shatolan Ct",
    "sg:city":"Blountville",
    "sg:classifiers":[
        {
            "category":"Professional",
            "subcategory":"Computer Services",
            "type":"Services"
        }
    ],
    "sg:phone":"+1 423 323 0921",
    "sg:postcode":"37617",
    "sg:province":"TN",
    "sg:tags":[
        "design",
        "system"
    ],
    "wof:name":"Puritan Computer Concepts",
    "wof:placetype":"venue"
},
  "geometry": {"coordinates":[-82.36798400000001,36.500078],"type":"Point"}
}