{
  "type": "Feature",
  "properties": {
    "addr:full":"1015 Highland Rd Collinwood TN 38450",
    "addr:housenumber":"1015",
    "addr:postcode":"38450",
    "addr:street":"Highland Rd",
    "iso:country":"US",
    "sg:address":"1015 Highland Rd",
    "sg:city":"Collinwood",
    "sg:classifiers":[
        {
            "category":"Manufacturing",
            "subcategory":"Building Materials",
            "type":"Manufacturing & Wholesale Goods"
        }
    ],
    "sg:phone":"+1 931 724 5161",
    "sg:postcode":"38450",
    "sg:province":"TN",
    "sg:tags":[
        "member",
        "mfg",
        "wood",
        "structural"
    ],
    "wof:name":"Eagle Truss LLC",
    "wof:placetype":"venue"
},
  "geometry": {"coordinates":[-87.75438800000001,35.221797],"type":"Point"}
}