{
  "type": "Feature",
  "properties": {
    "iso:country":"US",
    "sg:address":"264 Mallory Station Rd",
    "sg:city":"Franklin",
    "sg:classifiers":[
        {
            "category":"Utilities",
            "subcategory":"Telephone",
            "type":"Services"
        }
    ],
    "sg:phone":"+1 615 599 3728",
    "sg:postcode":"37067",
    "sg:province":"TN",
    "sg:tags":[
        "communications",
        "computer",
        "programing",
        "custom"
    ],
    "wof:name":"Christcentralcom",
    "wof:placetype":"venue"
},
  "geometry": {"coordinates":[-86.831616,35.955883],"type":"Point"}
}