{
  "type": "Feature",
  "properties": {
    "iso:country":"US",
    "sg:address":"880 Strayleaf Rd",
    "sg:city":"Wildersville",
    "sg:classifiers":[
        {
            "category":"Farming",
            "subcategory":"Livestock Farm",
            "type":"Manufacturing & Wholesale Goods"
        }
    ],
    "sg:phone":"+1 731 968 3975",
    "sg:postcode":"38388",
    "sg:province":"TN",
    "sg:tags":[
        "beef",
        "feedlot",
        "cattle"
    ],
    "wof:name":"Sammy Barker",
    "wof:placetype":"venue"
},
  "geometry": {"coordinates":[-88.40984,35.750582],"type":"Point"}
}