{
  "type": "Feature",
  "properties": {
    "iso:country":"US",
    "sg:address":"550 Ford Rd",
    "sg:city":"Lenoir City",
    "sg:classifiers":[
        {
            "category":"Health Services",
            "subcategory":"Doctor",
            "type":"Services"
        }
    ],
    "sg:phone":"+1 865 271 6000",
    "sg:postcode":"37772",
    "sg:province":"TN",
    "sg:tags":[
        "physician",
        "surgeon"
    ],
    "wof:name":"Ft Sanders Loudon Medical Ctr",
    "wof:placetype":"venue"
},
  "geometry": {"coordinates":[-84.251604,35.840275],"type":"Point"}
}