{
  "type": "Feature",
  "properties": {
    "addr:full":"2643 Sunbury Cir Memphis TN 38133",
    "addr:housenumber":"2643",
    "addr:postcode":"38133",
    "addr:street":"Sunbury Cir",
    "iso:country":"US",
    "sg:address":"2643 Sunbury Cir",
    "sg:city":"Memphis",
    "sg:classifiers":[
        {
            "category":"Shopping",
            "subcategory":"Stationery & Office Supplies",
            "type":"Retail Goods"
        }
    ],
    "sg:phone":"+1 901 277 7903",
    "sg:postcode":"38133",
    "sg:province":"TN",
    "sg:tags":[
        "business"
    ],
    "wof:name":"Allied Office Products",
    "wof:placetype":"venue"
},
  "geometry": {"coordinates":[-89.809113,35.195625],"type":"Point"}
}