{
  "type": "Feature",
  "properties": {
    "iso:country":"US",
    "sg:address":"483 Horseshoe Bend Rd",
    "sg:city":"Jonesborough",
    "sg:classifiers":[
        {
            "category":"Farming",
            "subcategory":"Orchard",
            "type":"Manufacturing & Wholesale Goods"
        }
    ],
    "sg:phone":"+1 423 913 1128",
    "sg:postcode":"37659",
    "sg:province":"TN",
    "sg:tags":[
        "grove",
        "management"
    ],
    "wof:name":"Orchard Jan C",
    "wof:placetype":"venue"
},
  "geometry": {"coordinates":[-82.542934,36.320017],"type":"Point"}
}