{
  "type": "Feature",
  "properties": {
    "iso:country":"US",
    "sg:address":"529 Tuscarora Dr",
    "sg:city":"Antioch",
    "sg:classifiers":[
        {
            "category":"Building & Trades",
            "subcategory":"Construction",
            "type":"Services"
        }
    ],
    "sg:phone":"+1 615 331 8403",
    "sg:postcode":"37013",
    "sg:province":"TN",
    "sg:tags":[
        "hanging",
        "contractor"
    ],
    "wof:name":"Fleenor Painting Service",
    "wof:placetype":"venue"
},
  "geometry": {"coordinates":[-86.681123,36.05908],"type":"Point"}
}