{
  "type": "Feature",
  "properties": {
    "iso:country":"US",
    "sg:address":"103 Elza Dr",
    "sg:city":"Oak Ridge",
    "sg:classifiers":[
        {
            "category":"Retail",
            "subcategory":"Car Wash",
            "type":"Services"
        }
    ],
    "sg:phone":"+1 865 483 7720",
    "sg:postcode":"37830",
    "sg:province":"TN",
    "sg:tags":[
        "automobile",
        "detail",
        "clean"
    ],
    "wof:name":"Superior Systems Detail Shop",
    "wof:placetype":"venue"
},
  "geometry": {"coordinates":[-84.20314,36.051924],"type":"Point"}
}