{
  "type": "Feature",
  "properties": {
    "iso:country":"US",
    "sg:address":"4160 Jersey Pike",
    "sg:city":"Chattanooga",
    "sg:classifiers":[
        {
            "category":"Shopping",
            "subcategory":"Computers & Home Electronics",
            "type":"Retail Goods"
        }
    ],
    "sg:phone":"+1 423 624 0071",
    "sg:postcode":"37416",
    "sg:province":"TN",
    "sg:tags":[
        "parts",
        "supply"
    ],
    "wof:name":"Shields Electronics",
    "wof:placetype":"venue"
},
  "geometry": {"coordinates":[-85.19631099999999,35.063136],"type":"Point"}
}