{
  "type": "Feature",
  "properties": {
    "iso:country":"US",
    "sg:address":"612 Fulton Rd",
    "sg:city":"Brownsville",
    "sg:classifiers":[
        {
            "category":"Organizations",
            "subcategory":"Religious Organization",
            "type":"Services"
        }
    ],
    "sg:phone":"+1 731 772 2663",
    "sg:postcode":"38012",
    "sg:province":"TN",
    "sg:tags":[
        "church"
    ],
    "wof:name":"New Vision Community Church",
    "wof:placetype":"venue"
},
  "geometry": {"coordinates":[-89.301633,35.601171],"type":"Point"}
}