{
  "type": "Feature",
  "properties": {
    "iso:country":"US",
    "sg:address":"2911 Tazewell Pike",
    "sg:city":"Knoxville",
    "sg:classifiers":[
        {
            "category":"Professional",
            "subcategory":"Business Services",
            "type":"Services"
        }
    ],
    "sg:phone":"+1 865 919 2755",
    "sg:postcode":"37918",
    "sg:province":"TN",
    "sg:tags":[
        "info",
        "broker"
    ],
    "wof:name":"Data Find Solutions",
    "wof:placetype":"venue"
},
  "geometry": {"coordinates":[-83.923379,36.025304],"type":"Point"}
}