{
  "type": "Feature",
  "properties": {
    "iso:country":"US",
    "sg:address":"6151 Shallowford Rd",
    "sg:city":"Chattanooga",
    "sg:classifiers":[
        {
            "category":"Health Services",
            "subcategory":"Doctor",
            "type":"Services"
        }
    ],
    "sg:phone":"+1 423 870 3223",
    "sg:postcode":"37421",
    "sg:province":"TN",
    "sg:tags":[
        "physician",
        "surgeon"
    ],
    "wof:name":"Shire Facial Plastic Surgery",
    "wof:placetype":"venue"
},
  "geometry": {"coordinates":[-85.18257699999999,35.053285],"type":"Point"}
}