{
  "type": "Feature",
  "properties": {
    "iso:country":"US",
    "sg:address":"77 Carriage House Dr",
    "sg:city":"Jackson",
    "sg:classifiers":[
        {
            "category":"Shopping",
            "subcategory":"Clothing, Apparel, & Fashions",
            "type":"Retail Goods"
        }
    ],
    "sg:phone":"+1 731 668 6900",
    "sg:postcode":"38305",
    "sg:province":"TN",
    "sg:tags":[
        "sport",
        "shoes",
        "clothes"
    ],
    "wof:name":"Looking Good",
    "wof:placetype":"venue"
},
  "geometry": {"coordinates":[-88.829877,35.667564],"type":"Point"}
}