{
  "type": "Feature",
  "properties": {
    "iso:country":"US",
    "sg:address":"8218 Tyne Ridge Rd",
    "sg:city":"Chattanooga",
    "sg:classifiers":[
        {
            "category":"Communications",
            "subcategory":"Film & Video Production",
            "type":"Services"
        }
    ],
    "sg:phone":"+1 423 490 3491",
    "sg:postcode":"37421",
    "sg:province":"TN",
    "sg:tags":[
        "motion"
    ],
    "wof:name":"Buccaneer Broadcast Production",
    "wof:placetype":"venue"
},
  "geometry": {"coordinates":[-85.122585,35.047273],"type":"Point"}
}