{
  "type": "Feature",
  "properties": {
    "addr:full":"148 Riverpark Way Sevierville TN 37862",
    "addr:housenumber":"148",
    "addr:postcode":"37862",
    "addr:street":"Riverpark Way",
    "iso:country":"US",
    "sg:address":"148 Riverpark Way",
    "sg:city":"Sevierville",
    "sg:classifiers":[
        {
            "category":"Real Estate",
            "subcategory":"Real Estate Operator",
            "type":"Services"
        }
    ],
    "sg:phone":"+1 865 428 1373",
    "sg:postcode":"37862",
    "sg:province":"TN",
    "sg:tags":[
        "apartment"
    ],
    "wof:name":"Riverpark Apartments",
    "wof:placetype":"venue"
},
  "geometry": {"coordinates":[-83.58059900000001,35.88399],"type":"Point"}
}