{
  "type": "Feature",
  "properties": {
    "iso:country":"US",
    "sg:address":"1023 Waters Edge Cir",
    "sg:city":"Mount Juliet",
    "sg:classifiers":[
        {
            "category":"Building & Trades",
            "subcategory":"Landscaping Services",
            "type":"Services"
        }
    ],
    "sg:phone":"+1 615 773 8935",
    "sg:postcode":"37122",
    "sg:province":"TN",
    "sg:tags":[
        "landscape"
    ],
    "wof:name":"Ash Landscape & Lawn Maint",
    "wof:placetype":"venue"
},
  "geometry": {"coordinates":[-86.52080100000001,36.258104],"type":"Point"}
}