{
  "type": "Feature",
  "properties": {
    "iso:country":"US",
    "sg:address":"300 Court Ave",
    "sg:city":"Sevierville",
    "sg:classifiers":[
        {
            "category":"Organizations",
            "subcategory":"Non-profit Organization",
            "type":"Services"
        }
    ],
    "sg:phone":"+1 865 453 9046",
    "sg:postcode":"37862",
    "sg:province":"TN",
    "sg:tags":[
        "life",
        "carrier",
        "insurance",
        "social"
    ],
    "wof:name":"Sevier County Farm Bureau",
    "wof:placetype":"venue"
},
  "geometry": {"coordinates":[-83.56622900000001,35.865969],"type":"Point"}
}