{
  "type": "Feature",
  "properties": {
    "addr:full":"105 Walnut St Collierville TN 38017",
    "addr:housenumber":"105",
    "addr:postcode":"38017",
    "addr:street":"Walnut St",
    "iso:country":"US",
    "sg:address":"105 Walnut St",
    "sg:city":"Collierville",
    "sg:classifiers":[
        {
            "category":"Restaurant",
            "type":"Food & Drink"
        }
    ],
    "sg:phone":"+1 901 853 3072",
    "sg:postcode":"38017",
    "sg:province":"TN",
    "wof:name":"Quiznos Sub",
    "wof:placetype":"venue"
},
  "geometry": {"coordinates":[-89.666713,35.042261],"type":"Point"}
}