{
  "type": "Feature",
  "properties": {
    "iso:country":"US",
    "sg:address":"2947 Lower Walkers Creek Rd",
    "sg:city":"Goodlettsville",
    "sg:classifiers":[
        {
            "category":"Organizations",
            "subcategory":"Religious Organization",
            "type":"Services"
        }
    ],
    "sg:phone":"+1 615 859 7644",
    "sg:postcode":"37072",
    "sg:province":"TN",
    "sg:tags":[
        "church"
    ],
    "wof:name":"Walkers' United Methodist Chr",
    "wof:placetype":"venue"
},
  "geometry": {"coordinates":[-86.75703900000001,36.342515],"type":"Point"}
}