{
  "type": "Feature",
  "properties": {
    "iso:country":"US",
    "sg:address":"1584 Getwell Rd",
    "sg:city":"Memphis",
    "sg:classifiers":[
        {
            "category":"Retail",
            "subcategory":"Repair Shop",
            "type":"Services"
        }
    ],
    "sg:phone":"+1 901 452 7321",
    "sg:postcode":"38111",
    "sg:province":"TN",
    "sg:tags":[
        "television",
        "set",
        "radio",
        "lease"
    ],
    "wof:name":"Teletronics T V Sales and Svc",
    "wof:placetype":"venue"
},
  "geometry": {"coordinates":[-89.93105300000001,35.088756],"type":"Point"}
}