{
  "type": "Feature",
  "properties": {
    "iso:country":"US",
    "sg:address":"108 Honest St",
    "sg:city":"Chattanooga",
    "sg:classifiers":[
        {
            "category":"Retail",
            "subcategory":"Auto Repair",
            "type":"Services"
        }
    ],
    "sg:phone":"+1 423 490 0216",
    "sg:postcode":"37421",
    "sg:province":"TN",
    "sg:tags":[
        "body",
        "automobile",
        "painting"
    ],
    "wof:name":"Capital Toyota Body Shop",
    "wof:placetype":"venue"
},
  "geometry": {"coordinates":[-85.204117,35.022664],"type":"Point"}
}