{
  "type": "Feature",
  "properties": {
    "iso:country":"US",
    "sg:address":"6941 Climping Rd",
    "sg:city":"Memphis",
    "sg:classifiers":[
        {
            "category":"Shopping",
            "subcategory":"Clothing, Apparel, & Fashions",
            "type":"Retail Goods"
        }
    ],
    "sg:phone":"+1 901 754 3387",
    "sg:postcode":"38119",
    "sg:province":"TN",
    "sg:tags":[
        "wear"
    ],
    "wof:name":"Grands Closet",
    "wof:placetype":"venue"
},
  "geometry": {"coordinates":[-89.832007,35.092888],"type":"Point"}
}