{
  "type": "Feature",
  "properties": {
    "iso:country":"US",
    "sg:address":"493 Cave Rd",
    "sg:city":"Nashville",
    "sg:classifiers":[
        {
            "category":"Manufacturing",
            "subcategory":"Printing",
            "type":"Manufacturing & Wholesale Goods"
        }
    ],
    "sg:phone":"+1 615 883 7190",
    "sg:postcode":"37210",
    "sg:province":"TN",
    "sg:tags":[
        "photography",
        "commercial"
    ],
    "wof:name":"Color Systems Inc",
    "wof:placetype":"venue"
},
  "geometry": {"coordinates":[-86.720769,36.161891],"type":"Point"}
}