{
  "type": "Feature",
  "properties": {
    "iso:country":"US",
    "sg:address":"2584 Milton Ln",
    "sg:city":"Thompsons Station",
    "sg:classifiers":[
        {
            "category":"Professional",
            "subcategory":"Management & Consulting",
            "type":"Services"
        }
    ],
    "sg:phone":"+1 615 599 2937",
    "sg:postcode":"37179",
    "sg:province":"TN",
    "wof:name":"B & A",
    "wof:placetype":"venue"
},
  "geometry": {"coordinates":[-86.884253,35.787664],"type":"Point"}
}