{
  "type": "Feature",
  "properties": {
    "addr:full":"103 W Main St Morristown TN 37814",
    "addr:housenumber":"103",
    "addr:postcode":"37814",
    "addr:street":"W Main St",
    "iso:country":"US",
    "sg:address":"103 W Main St",
    "sg:city":"Morristown",
    "sg:classifiers":[
        {
            "category":"Restaurant",
            "type":"Food & Drink"
        }
    ],
    "sg:phone":"+1 423 318 1100",
    "sg:postcode":"37814",
    "sg:province":"TN",
    "sg:tags":[
        "shop",
        "coffee"
    ],
    "wof:name":"Higher Grounds",
    "wof:placetype":"venue"
},
  "geometry": {"coordinates":[-83.292337,36.213898],"type":"Point"}
}