{
  "type": "Feature",
  "properties": {
    "iso:country":"US",
    "sg:address":"513 Summerfield Dr",
    "sg:city":"Smyrna",
    "sg:classifiers":[
        {
            "category":"Building & Trades",
            "subcategory":"Landscaping Services",
            "type":"Services"
        }
    ],
    "sg:phone":"+1 615 223 1225",
    "sg:postcode":"37167",
    "sg:province":"TN",
    "sg:tags":[
        "landscape"
    ],
    "wof:name":"A Time To Plant",
    "wof:placetype":"venue"
},
  "geometry": {"coordinates":[-86.530736,35.947632],"type":"Point"}
}