{
  "type": "Feature",
  "properties": {
    "addr:full":"4266 Carters Valley Rd Church Hill TN 37642",
    "addr:housenumber":"4266",
    "addr:postcode":"37642",
    "addr:street":"Carters Valley Rd",
    "iso:country":"US",
    "sg:address":"4266 Carters Valley Rd",
    "sg:city":"Church Hill",
    "sg:classifiers":[
        {
            "category":"Government",
            "subcategory":"Office",
            "type":"Public Place"
        }
    ],
    "sg:phone":"+1 423 357 8901",
    "sg:postcode":"37642",
    "sg:province":"TN",
    "wof:name":"Carters Valley Convenience Ctr",
    "wof:placetype":"venue"
},
  "geometry": {"coordinates":[-82.71202700000001,36.557517],"type":"Point"}
}