{
  "type": "Feature",
  "properties": {
    "iso:country":"US",
    "sg:address":"3309 Mutton Hollow Rd",
    "sg:city":"Kodak",
    "sg:classifiers":[
        {
            "category":"Local Transit",
            "type":"Transportation"
        }
    ],
    "sg:phone":"+1 865 397 5466",
    "sg:postcode":"37764",
    "sg:province":"TN",
    "sg:tags":[
        "limousine"
    ],
    "wof:name":"Sweetheart's Limo",
    "wof:placetype":"venue"
},
  "geometry": {"coordinates":[-83.566005,35.989656],"type":"Point"}
}