{
  "type": "Feature",
  "properties": {
    "iso:country":"US",
    "sg:address":"1202 Wilkinson Rd",
    "sg:city":"Knoxville",
    "sg:phone":"+1 865 690 4234",
    "sg:postcode":"37923",
    "sg:province":"TN",
    "sg:tags":[
        "communications",
        "telegraph"
    ],
    "wof:name":"Knoxville Repeater Group",
    "wof:placetype":"venue"
},
  "geometry": {"coordinates":[-84.110505,35.941592],"type":"Point"}
}