{
  "type": "Feature",
  "properties": {
    "iso:country":"US",
    "sg:address":"2710 Hillsboro Rd",
    "sg:city":"Brentwood",
    "sg:classifiers":[
        {
            "category":"Organizations",
            "subcategory":"Religious Organization",
            "type":"Services"
        }
    ],
    "sg:phone":"+1 615 373 8219",
    "sg:postcode":"37027",
    "sg:province":"TN",
    "wof:name":"Pleasant View",
    "wof:placetype":"venue"
},
  "geometry": {"coordinates":[-86.88825199999999,36.017154],"type":"Point"}
}