{
  "type": "Feature",
  "properties": {
    "addr:full":"146 W Knight St Portland TN 37148",
    "addr:housenumber":"146",
    "addr:postcode":"37148",
    "addr:street":"W Knight St",
    "iso:country":"US",
    "sg:address":"146 W Knight St",
    "sg:city":"Portland",
    "sg:classifiers":[
        {
            "category":"Personal",
            "type":"Services"
        }
    ],
    "sg:phone":"+1 615 325 2430",
    "sg:postcode":"37148",
    "sg:province":"TN",
    "wof:name":"Inches-A-Weigh",
    "wof:placetype":"venue"
},
  "geometry": {"coordinates":[-86.51545400000001,36.575541],"type":"Point"}
}