{
  "type": "Feature",
  "properties": {
    "iso:country":"US",
    "sg:address":"5600 Leipers Creek Rd",
    "sg:city":"Franklin",
    "sg:classifiers":[
        {
            "category":"Shopping",
            "subcategory":"Discount & Variety Stores",
            "type":"Retail Goods"
        }
    ],
    "sg:phone":"+1 615 794 1066",
    "sg:postcode":"37064",
    "sg:province":"TN",
    "sg:tags":[
        "merchandise",
        "general"
    ],
    "wof:name":"Davis General Merchandise",
    "wof:placetype":"venue"
},
  "geometry": {"coordinates":[-87.037232,35.841429],"type":"Point"}
}