{
  "type": "Feature",
  "properties": {
    "iso:country":"US",
    "sg:address":"1204 Carthage Hwy",
    "sg:city":"Lebanon",
    "sg:classifiers":[
        {
            "category":"Wholesale",
            "subcategory":"Machinery & Supplies",
            "type":"Manufacturing & Wholesale Goods"
        }
    ],
    "sg:phone":"+1 615 444 0423",
    "sg:postcode":"37087",
    "sg:province":"TN",
    "sg:tags":[
        "boring",
        "drilling"
    ],
    "wof:name":"Mid South Drillers Supply Inc",
    "wof:placetype":"venue"
},
  "geometry": {"coordinates":[-86.257318,36.215545],"type":"Point"}
}