{
  "type": "Feature",
  "properties": {
    "addr:full":"934 N Weisgarber Rd Knoxville TN 37909",
    "addr:housenumber":"934",
    "addr:postcode":"37909",
    "addr:street":"N Weisgarber Rd",
    "iso:country":"US",
    "sg:address":"934 N Weisgarber Rd",
    "sg:city":"Knoxville",
    "sg:classifiers":[
        {
            "category":"Organizations",
            "subcategory":"Religious Organization",
            "type":"Services"
        }
    ],
    "sg:phone":"+1 865 584 7531",
    "sg:postcode":"37909",
    "sg:province":"TN",
    "sg:tags":[
        "church"
    ],
    "wof:name":"Church Of The Saviour",
    "wof:placetype":"venue"
},
  "geometry": {"coordinates":[-84.010147,35.93971],"type":"Point"}
}