{
  "type": "Feature",
  "properties": {
    "addr:full":"3731 Summer Ave Memphis TN 38122",
    "addr:housenumber":"3731",
    "addr:postcode":"38122",
    "addr:street":"Summer Ave",
    "iso:country":"US",
    "sg:address":"3731 Summer Ave",
    "sg:city":"Memphis",
    "sg:classifiers":[
        {
            "category":"Restaurant",
            "type":"Food & Drink"
        }
    ],
    "sg:menulink":"http://www.allmenus.com/tn/memphis/173206-wendys/menu/",
    "sg:phone":"+1 901 452 8821",
    "sg:postcode":"38122",
    "sg:province":"TN",
    "sg:tags":[
        "burger",
        "american",
        "soup"
    ],
    "wof:name":"Wendy's",
    "wof:placetype":"venue"
},
  "geometry": {"coordinates":[-89.93656,35.149298],"type":"Point"}
}