{
  "type": "Feature",
  "properties": {
    "iso:country":"US",
    "sg:address":"605 W Due West Ave",
    "sg:city":"Madison",
    "sg:classifiers":[
        {
            "category":"Health Services",
            "subcategory":"Hospital",
            "type":"Services"
        }
    ],
    "sg:phone":"+1 615 865 7310",
    "sg:postcode":"37115",
    "sg:province":"TN",
    "sg:tags":[
        "dialysis"
    ],
    "sg:website":"http://www.khgreensboro.com",
    "wof:name":"Dci",
    "wof:placetype":"venue"
},
  "geometry": {"coordinates":[-86.735527,36.24929],"type":"Point"}
}