{
  "type": "Feature",
  "properties": {
    "iso:country":"US",
    "sg:address":"308 Coleman St",
    "sg:city":"Smyrna",
    "sg:classifiers":[
        {
            "category":"Shopping",
            "subcategory":"Computers & Home Electronics",
            "type":"Retail Goods"
        }
    ],
    "sg:phone":"+1 615 355 9289",
    "sg:postcode":"37167",
    "sg:province":"TN",
    "sg:tags":[
        "audio"
    ],
    "wof:name":"Audio Monk",
    "wof:placetype":"venue"
},
  "geometry": {"coordinates":[-86.52505600000001,35.980475],"type":"Point"}
}