{
  "type": "Feature",
  "properties": {
    "addr:full":"240 Great Circle Rd Nashville TN 37228",
    "addr:housenumber":"240",
    "addr:postcode":"37228",
    "addr:street":"Great Circle Rd",
    "iso:country":"US",
    "sg:address":"240 Great Circle Rd",
    "sg:city":"Nashville",
    "sg:classifiers":[
        {
            "category":"Building & Trades",
            "subcategory":"Electrical",
            "type":"Services"
        }
    ],
    "sg:phone":"+1 615 291 9926",
    "sg:postcode":"37228",
    "sg:province":"TN",
    "sg:tags":[
        "electric",
        "contractor"
    ],
    "wof:name":"Lincoln Electric Automaion Div",
    "wof:placetype":"venue"
},
  "geometry": {"coordinates":[-86.79323599999999,36.197422],"type":"Point"}
}