{
  "type": "Feature",
  "properties": {
    "iso:country":"US",
    "sg:address":"337 Goff Rd",
    "sg:city":"Sparta",
    "sg:classifiers":[
        {
            "category":"Food & Beverages",
            "subcategory":"Meat & Fish",
            "type":"Retail Goods"
        },
        {
            "category":"Wholesale",
            "subcategory":"Meat",
            "type":"Manufacturing & Wholesale Goods"
        }
    ],
    "sg:phone":"+1 931 935 8180",
    "sg:postcode":"38583",
    "sg:province":"TN",
    "sg:tags":[
        "personal",
        "plant",
        "product",
        "packing"
    ],
    "wof:name":"Cope Custom Slaughtering",
    "wof:placetype":"venue"
},
  "geometry": {"coordinates":[-85.36291900000001,35.930398],"type":"Point"}
}