{
  "type": "Feature",
  "properties": {
    "addr:full":"125 Campbell Pl La Vergne TN 37086",
    "addr:housenumber":"125",
    "addr:postcode":"37086",
    "addr:street":"Campbell Pl",
    "iso:country":"US",
    "sg:address":"125 Campbell Pl",
    "sg:city":"La Vergne",
    "sg:classifiers":[
        {
            "category":"Manufacturing",
            "subcategory":"Building Materials",
            "type":"Manufacturing & Wholesale Goods"
        }
    ],
    "sg:phone":"+1 615 793 2031",
    "sg:postcode":"37086",
    "sg:province":"TN",
    "sg:tags":[
        "mfg",
        "wood",
        "kitchen",
        "cabinet"
    ],
    "wof:name":"Ganns Cabinets & Tops In",
    "wof:placetype":"venue"
},
  "geometry": {"coordinates":[-86.556533,36.006266],"type":"Point"}
}