{
  "type": "Feature",
  "properties": {
    "iso:country":"US",
    "sg:address":"610 Boscobel St",
    "sg:city":"Nashville",
    "sg:classifiers":[
        {
            "category":"Organizations",
            "subcategory":"Religious Organization",
            "type":"Services"
        }
    ],
    "sg:phone":"+1 615 255 8963",
    "sg:postcode":"37206",
    "sg:province":"TN",
    "sg:tags":[
        "clergy"
    ],
    "wof:name":"Schade Edward Reverend",
    "wof:placetype":"venue"
},
  "geometry": {"coordinates":[-86.76011,36.169716],"type":"Point"}
}