{
  "type": "Feature",
  "properties": {
    "iso:country":"US",
    "sg:address":"4005 Brush Hill Rd",
    "sg:city":"Nashville",
    "sg:classifiers":[
        {
            "category":"Professional",
            "type":"Services"
        }
    ],
    "sg:phone":"+1 615 227 2204",
    "sg:postcode":"37216",
    "sg:province":"TN",
    "wof:name":"Troxler Cornerstone Inc",
    "wof:placetype":"venue"
},
  "geometry": {"coordinates":[-86.71159,36.226493],"type":"Point"}
}