{
  "type": "Feature",
  "properties": {
    "iso:country":"US",
    "sg:address":"206 Dalewood Dr",
    "sg:city":"Johnson City",
    "sg:classifiers":[
        {
            "category":"Building & Trades",
            "subcategory":"Construction",
            "type":"Services"
        }
    ],
    "sg:phone":"+1 423 926 9251",
    "sg:postcode":"37601",
    "sg:province":"TN",
    "sg:tags":[
        "water",
        "restoration",
        "damage"
    ],
    "sg:website":"www.spotlessrestoration.com",
    "wof:name":"Spotless Carpet Cleaners",
    "wof:placetype":"venue"
},
  "geometry": {"coordinates":[-82.30295599999999,36.350981],"type":"Point"}
}