{
  "type": "Feature",
  "properties": {
    "iso:country":"US",
    "sg:address":"218 Scenic View Dr",
    "sg:city":"Clinton",
    "sg:classifiers":[
        {
            "category":"Retail",
            "subcategory":"Car Wash",
            "type":"Services"
        }
    ],
    "sg:phone":"+1 865 457 2764",
    "sg:postcode":"37716",
    "sg:province":"TN",
    "sg:tags":[
        "automobile",
        "detail",
        "clean"
    ],
    "wof:name":"Ultimate Off Road Product",
    "wof:placetype":"venue"
},
  "geometry": {"coordinates":[-84.11457799999999,36.055794],"type":"Point"}
}