{
  "type": "Feature",
  "properties": {
    "addr:full":"201 Poplar Ave Memphis TN 38103",
    "addr:housenumber":"201",
    "addr:postcode":"38103",
    "addr:street":"Poplar Ave",
    "iso:country":"US",
    "sg:address":"201 Poplar Ave",
    "sg:city":"Memphis",
    "sg:classifiers":[
        {
            "category":"Social Services",
            "type":"Services"
        }
    ],
    "sg:phone":"+1 901 576 2500",
    "sg:postcode":"38103",
    "sg:province":"TN",
    "wof:name":"Probation Dept",
    "wof:placetype":"venue"
},
  "geometry": {"coordinates":[-90.046341,35.148886],"type":"Point"}
}