{
  "type": "Feature",
  "properties": {
    "iso:country":"US",
    "sg:address":"2192 Filmore Ave",
    "sg:city":"Memphis",
    "sg:classifiers":[
        {
            "category":"Home & Garden",
            "subcategory":"Household Appliances",
            "type":"Retail Goods"
        },
        {
            "category":"Building & Trades",
            "subcategory":"Construction",
            "type":"Services"
        }
    ],
    "sg:phone":"+1 901 744 8900",
    "sg:postcode":"38114",
    "sg:province":"TN",
    "sg:tags":[
        "dishwashing",
        "system",
        "machine",
        "mechanical",
        "contractor",
        "air conditioning"
    ],
    "wof:name":"Hartsfield J C Co Inc",
    "wof:placetype":"venue"
},
  "geometry": {"coordinates":[-89.989105,35.093554],"type":"Point"}
}