{
  "type": "Feature",
  "properties": {
    "iso:country":"US",
    "sg:address":"141 Little Senator Cir",
    "sg:city":"Clinton",
    "sg:classifiers":[
        {
            "category":"Personal",
            "subcategory":"Barber",
            "type":"Services"
        }
    ],
    "sg:phone":"+1 865 494 8099",
    "sg:postcode":"37828",
    "sg:province":"TN",
    "wof:name":"Shear Cuts Barber Shop",
    "wof:placetype":"venue"
},
  "geometry": {"coordinates":[-84.066799,36.182203],"type":"Point"}
}