{
  "type": "Feature",
  "properties": {
    "iso:country":"US",
    "sg:address":"5807 Clover St",
    "sg:city":"Chattanooga",
    "sg:classifiers":[
        {
            "category":"Shopping",
            "subcategory":"Clothing, Apparel, & Fashions",
            "type":"Retail Goods"
        }
    ],
    "sg:phone":"+1 423 893 0165",
    "sg:postcode":"37412",
    "sg:province":"TN",
    "sg:tags":[
        "wear"
    ],
    "wof:name":"Diapers For Less",
    "wof:placetype":"venue"
},
  "geometry": {"coordinates":[-85.223241,34.995534],"type":"Point"}
}