{
  "type": "Feature",
  "properties": {
    "iso:country":"US",
    "sg:address":"2418 Russell Rd",
    "sg:city":"Kodak",
    "sg:classifiers":[
        {
            "category":"Building & Trades",
            "subcategory":"Plumbing",
            "type":"Services"
        }
    ],
    "sg:phone":"+1 865 933 2050",
    "sg:postcode":"37764",
    "sg:province":"TN",
    "sg:tags":[
        "contractor"
    ],
    "wof:name":"Roberts Jerry Heating & AC",
    "wof:placetype":"venue"
},
  "geometry": {"coordinates":[-83.67053799999999,35.966115],"type":"Point"}
}