{
  "type": "Feature",
  "properties": {
    "iso:country":"US",
    "sg:address":"2807 Rossville Blvd",
    "sg:city":"Chattanooga",
    "sg:classifiers":[
        {
            "category":"Wholesale",
            "subcategory":"Auto Parts",
            "type":"Manufacturing & Wholesale Goods"
        }
    ],
    "sg:phone":"+1 423 629 7328",
    "sg:postcode":"37407",
    "sg:province":"TN",
    "sg:tags":[
        "us",
        "supply"
    ],
    "wof:name":"Hub Cap Willies",
    "wof:placetype":"venue"
},
  "geometry": {"coordinates":[-85.29410900000001,35.01419],"type":"Point"}
}