{
  "type": "Feature",
  "properties": {
    "addr:full":"810 Seven Oaks Dr Mt Carmel TN 37645",
    "addr:housenumber":"810",
    "addr:postcode":"37645",
    "addr:street":"Seven Oaks Dr Mt",
    "iso:country":"US",
    "sg:address":"810 Seven Oaks Dr",
    "sg:city":"Mt Carmel",
    "sg:classifiers":[
        {
            "category":"Building & Trades",
            "subcategory":"Electrical",
            "type":"Services"
        }
    ],
    "sg:phone":"+1 423 357 7865",
    "sg:postcode":"37645",
    "sg:province":"TN",
    "sg:tags":[
        "electrical",
        "electric",
        "contractor"
    ],
    "wof:name":"Appalachian Control Systems",
    "wof:placetype":"venue"
},
  "geometry": {"coordinates":[-82.65662399999999,36.559613],"type":"Point"}
}