{
  "type": "Feature",
  "properties": {
    "iso:country":"US",
    "sg:address":"1679 Peach Ave",
    "sg:city":"Memphis",
    "sg:classifiers":[
        {
            "category":"Manufacturing",
            "subcategory":"Tools & Machinery",
            "type":"Manufacturing & Wholesale Goods"
        }
    ],
    "sg:phone":"+1 901 278 1659",
    "sg:postcode":"38112",
    "sg:province":"TN",
    "sg:tags":[
        "computer",
        "electronic",
        "mfg"
    ],
    "wof:name":"Inisoft Corp",
    "wof:placetype":"venue"
},
  "geometry": {"coordinates":[-90.003526,35.147307],"type":"Point"}
}