{
  "type": "Feature",
  "properties": {
    "iso:country":"US",
    "sg:address":"230 Pedigo Rd",
    "sg:city":"Madisonville",
    "sg:classifiers":[
        {
            "category":"Building & Trades",
            "subcategory":"Construction",
            "type":"Services"
        }
    ],
    "sg:phone":"+1 423 442 7154",
    "sg:postcode":"37354",
    "sg:province":"TN",
    "sg:tags":[
        "contractor"
    ],
    "wof:name":"Giles Masonry",
    "wof:placetype":"venue"
},
  "geometry": {"coordinates":[-84.33966100000001,35.535492],"type":"Point"}
}