{
  "type": "Feature",
  "properties": {
    "iso:country":"US",
    "sg:address":"5004 Clarksville Hwy",
    "sg:city":"Whites Creek",
    "sg:classifiers":[
        {
            "category":"Building & Trades",
            "subcategory":"Construction",
            "type":"Services"
        }
    ],
    "sg:phone":"+1 615 876 4874",
    "sg:postcode":"37189",
    "sg:province":"TN",
    "wof:name":"Elliott Paving Co",
    "wof:placetype":"venue"
},
  "geometry": {"coordinates":[-86.848074,36.25639],"type":"Point"}
}