{
  "type": "Feature",
  "properties": {
    "iso:country":"US",
    "sg:address":"315 Ash St",
    "sg:city":"Nashville",
    "sg:classifiers":[
        {
            "category":"Organizations",
            "subcategory":"Professional Association",
            "type":"Services"
        }
    ],
    "sg:phone":"+1 615 255 6444",
    "sg:postcode":"37210",
    "sg:province":"TN",
    "wof:name":"Nashville Advertising Fdrtn",
    "wof:placetype":"venue"
},
  "geometry": {"coordinates":[-86.770922,36.152559],"type":"Point"}
}