{
  "type": "Feature",
  "properties": {
    "addr:full":"5 W Maple St Sparta TN 38583",
    "addr:housenumber":"5",
    "addr:postcode":"38583",
    "addr:street":"W Maple St",
    "iso:country":"US",
    "sg:address":"5 W Maple St",
    "sg:city":"Sparta",
    "sg:classifiers":[
        {
            "category":"Social Services",
            "type":"Services"
        }
    ],
    "sg:phone":"+1 931 836 3340",
    "sg:postcode":"38583",
    "sg:province":"TN",
    "wof:name":"Red Cross",
    "wof:placetype":"venue"
},
  "geometry": {"coordinates":[-85.464322,35.925235],"type":"Point"}
}