{
  "type": "Feature",
  "properties": {
    "iso:country":"US",
    "sg:address":"215 Maple St",
    "sg:city":"Harriman",
    "sg:classifiers":[
        {
            "category":"Restaurant",
            "type":"Food & Drink"
        }
    ],
    "sg:phone":"+1 865 882 9101",
    "sg:postcode":"37748",
    "sg:province":"TN",
    "wof:name":"Harriman City Sch Cafeteria",
    "wof:placetype":"venue"
},
  "geometry": {"coordinates":[-84.53859199999999,35.946177],"type":"Point"}
}