{
  "type": "Feature",
  "properties": {
    "addr:full":"102 Natcor Dr Dover TN 37058",
    "addr:housenumber":"102",
    "addr:postcode":"37058",
    "addr:street":"Natcor Dr",
    "iso:country":"US",
    "sg:address":"102 Natcor Dr",
    "sg:city":"Dover",
    "sg:classifiers":[
        {
            "category":"Education",
            "subcategory":"Library",
            "type":"Public Place"
        }
    ],
    "sg:phone":"+1 931 232 3127",
    "sg:postcode":"37058",
    "sg:province":"TN",
    "wof:name":"Stewart Public Library",
    "wof:placetype":"venue"
},
  "geometry": {"coordinates":[-87.831041,36.485962],"type":"Point"}
}