{
  "type": "Feature",
  "properties": {
    "iso:country":"US",
    "sg:address":"756 East St",
    "sg:city":"Covington",
    "sg:classifiers":[
        {
            "category":"Shopping",
            "subcategory":"Department Store",
            "type":"Retail Goods"
        }
    ],
    "sg:phone":"+1 901 476 9343",
    "sg:postcode":"38019",
    "sg:province":"TN",
    "sg:tags":[
        "shop"
    ],
    "wof:name":"Bargain Outlet",
    "wof:placetype":"venue"
},
  "geometry": {"coordinates":[-89.64025700000001,35.556684],"type":"Point"}
}