{
  "type": "Feature",
  "properties": {
    "iso:country":"US",
    "sg:address":"7 Morning Side Pl",
    "sg:city":"Memphis",
    "sg:classifiers":[
        {
            "category":"Banks & Credit Unions",
            "subcategory":"Financial Services",
            "type":"Services"
        }
    ],
    "sg:phone":"+1 901 324 1468",
    "sg:postcode":"38104",
    "sg:province":"TN",
    "sg:tags":[
        "investment",
        "closed"
    ],
    "wof:name":"Greenleaf Asset Management LLC",
    "wof:placetype":"venue"
},
  "geometry": {"coordinates":[-89.983672,35.136553],"type":"Point"}
}