{
  "type": "Feature",
  "properties": {
    "iso:country":"US",
    "sg:address":"235 New Lake Rd",
    "sg:city":"Spring City",
    "sg:classifiers":[
        {
            "category":"Real Estate",
            "subcategory":"Surveying",
            "type":"Services"
        }
    ],
    "sg:phone":"+1 423 365 5425",
    "sg:postcode":"37381",
    "sg:province":"TN",
    "sg:tags":[
        "surveyor"
    ],
    "wof:name":"Bill Roberts Land Surveyor",
    "wof:placetype":"venue"
},
  "geometry": {"coordinates":[-84.859042,35.691366],"type":"Point"}
}