{
  "type": "Feature",
  "properties": {
    "addr:full":"425 Conkinnon Dr Lenoir City TN 37772",
    "addr:housenumber":"425",
    "addr:postcode":"37772",
    "addr:street":"Conkinnon Dr",
    "iso:country":"US",
    "sg:address":"425 Conkinnon Dr",
    "sg:city":"Lenoir City",
    "sg:classifiers":[
        {
            "category":"Building & Trades",
            "subcategory":"Construction",
            "type":"Services"
        }
    ],
    "sg:phone":"+1 865 986 4801",
    "sg:postcode":"37772",
    "sg:province":"TN",
    "sg:tags":[
        "residential"
    ],
    "wof:name":"Kirkland Construction",
    "wof:placetype":"venue"
},
  "geometry": {"coordinates":[-84.20070800000001,35.7845],"type":"Point"}
}