{
  "type": "Feature",
  "properties": {
    "iso:country":"US",
    "sg:address":"202 Ann St",
    "sg:city":"Halls",
    "sg:classifiers":[
        {
            "category":"Social Services",
            "subcategory":"Child Care",
            "type":"Services"
        }
    ],
    "sg:phone":"+1 731 836 5377",
    "sg:postcode":"38040",
    "sg:province":"TN",
    "sg:tags":[
        "day"
    ],
    "wof:name":"A B Cees Learning",
    "wof:placetype":"venue"
},
  "geometry": {"coordinates":[-89.400588,35.878679],"type":"Point"}
}