{
  "type": "Feature",
  "properties": {
    "iso:country":"US",
    "sg:address":"118 E Commercial Ave",
    "sg:city":"Monterey",
    "sg:classifiers":[
        {
            "category":"Restaurant",
            "type":"Food & Drink"
        }
    ],
    "sg:phone":"+1 931 839 6149",
    "sg:postcode":"38574",
    "sg:province":"TN",
    "sg:tags":[
        "eating"
    ],
    "wof:name":"Cup & Saucer Restaurant",
    "wof:placetype":"venue"
},
  "geometry": {"coordinates":[-85.26783500000001,36.147707],"type":"Point"}
}