{
  "type": "Feature",
  "properties": {
    "iso:country":"US",
    "sg:address":"112 Edwards Dr",
    "sg:city":"Jackson",
    "sg:classifiers":[
        {
            "category":"Freight",
            "type":"Transportation"
        }
    ],
    "sg:phone":"+1 731 424 4709",
    "sg:postcode":"38301",
    "sg:province":"TN",
    "sg:tags":[
        "trucking"
    ],
    "sg:website":"www.swifttrans.com",
    "wof:name":"Swift Transportation Co",
    "wof:placetype":"venue"
},
  "geometry": {"coordinates":[-88.81880099999999,35.55735],"type":"Point"}
}