{
  "type": "Feature",
  "properties": {
    "addr:full":"1105 E Jackson Blvd Jonesborough TN 37659",
    "addr:housenumber":"1105",
    "addr:postcode":"37659",
    "addr:street":"E Jackson Blvd",
    "iso:country":"US",
    "sg:address":"1105 E Jackson Blvd",
    "sg:city":"Jonesborough",
    "sg:classifiers":[
        {
            "category":"Government",
            "subcategory":"Office",
            "type":"Public Place"
        }
    ],
    "sg:phone":"+1 423 753 2191",
    "sg:postcode":"37659",
    "sg:province":"TN",
    "sg:tags":[
        "federal",
        "planning",
        "dev"
    ],
    "wof:name":"USDA Rural Development",
    "wof:placetype":"venue"
},
  "geometry": {"coordinates":[-82.462689,36.300859],"type":"Point"}
}