{
  "type": "Feature",
  "properties": {
    "addr:full":"3535 Saint Elmo Ave Chattanooga TN 37409",
    "addr:housenumber":"3535",
    "addr:postcode":"37409",
    "addr:street":"Saint Elmo Ave",
    "iso:country":"US",
    "sg:address":"3535 Saint Elmo Ave",
    "sg:city":"Chattanooga",
    "sg:classifiers":[
        {
            "category":"Building & Trades",
            "subcategory":"Construction",
            "type":"Services"
        }
    ],
    "sg:phone":"+1 423 266 4231",
    "sg:postcode":"37409",
    "sg:province":"TN",
    "sg:tags":[
        "warehouse",
        "industrial",
        "contractor"
    ],
    "sg:website":"www.ledco-inc.com",
    "wof:name":"Ledco Inc",
    "wof:placetype":"venue"
},
  "geometry": {"coordinates":[-85.32704200000001,35.014314],"type":"Point"}
}