{
  "type": "Feature",
  "properties": {
    "addr:full":"3750 Hacks Cross Rd Memphis TN 38125",
    "addr:housenumber":"3750",
    "addr:postcode":"38125",
    "addr:street":"Hacks Cross Rd",
    "iso:country":"US",
    "sg:address":"3750 Hacks Cross Rd",
    "sg:city":"Memphis",
    "sg:classifiers":[
        {
            "category":"Restaurant",
            "type":"Food & Drink"
        }
    ],
    "sg:menulink":"http://www.allmenus.com/tn/collierville/57925-mi-pueblo/menu/",
    "sg:phone":"+1 901 751 8896",
    "sg:postcode":"38125",
    "sg:province":"TN",
    "sg:tags":[
        "mexican"
    ],
    "wof:name":"Mi Pueblo",
    "wof:placetype":"venue"
},
  "geometry": {"coordinates":[-89.79505399999999,35.046392],"type":"Point"}
}