{
  "type": "Feature",
  "properties": {
    "addr:full":"211 Robert Ave Murfreesboro TN 37188",
    "addr:housenumber":"211",
    "addr:postcode":"37188",
    "addr:street":"Robert Ave",
    "iso:country":"US",
    "sg:address":"211 Robert Ave",
    "sg:city":"Murfreesboro",
    "sg:classifiers":[
        {
            "category":"Wholesale",
            "subcategory":"Medical Equipment & Supplies",
            "type":"Manufacturing & Wholesale Goods"
        }
    ],
    "sg:phone":"+1 615 895 5224",
    "sg:postcode":"37188",
    "sg:province":"TN",
    "sg:tags":[
        "physician",
        "surgeon"
    ],
    "wof:name":"Medical Mobility Inc",
    "wof:placetype":"venue"
},
  "geometry": {"coordinates":[-86.642053,36.470119],"type":"Point"}
}