{
  "type": "Feature",
  "properties": {
    "addr:full":"120 Forest St Trenton TN 38382",
    "addr:housenumber":"120",
    "addr:postcode":"38382",
    "addr:street":"Forest St",
    "iso:country":"US",
    "sg:address":"120 Forest St",
    "sg:city":"Trenton",
    "sg:classifiers":[
        {
            "category":"Museum",
            "type":"Entertainment"
        }
    ],
    "sg:phone":"+1 731 855 9979",
    "sg:postcode":"38382",
    "sg:province":"TN",
    "sg:tags":[
        "organization",
        "arts",
        "information"
    ],
    "wof:name":"Gibson County Visual Arts Assn",
    "wof:placetype":"venue"
},
  "geometry": {"coordinates":[-88.947851,35.966892],"type":"Point"}
}