{
  "type": "Feature",
  "properties": {
    "iso:country":"US",
    "sg:address":"3199 Long Hollow Pike",
    "sg:city":"Hendersonville",
    "sg:classifiers":[
        {
            "category":"Government",
            "subcategory":"Fire Station",
            "type":"Public Place"
        }
    ],
    "sg:phone":"+1 615 824 4300",
    "sg:postcode":"37075",
    "sg:province":"TN",
    "sg:tags":[
        "protection"
    ],
    "wof:name":"Shackle Island Fire & Rescue",
    "wof:placetype":"venue"
},
  "geometry": {"coordinates":[-86.603925,36.369636],"type":"Point"}
}