{
  "type": "Feature",
  "properties": {
    "iso:country":"US",
    "sg:address":"105 Short Ln",
    "sg:city":"Gallatin",
    "sg:classifiers":[
        {
            "category":"Building & Trades",
            "subcategory":"Plumbing",
            "type":"Services"
        }
    ],
    "sg:phone":"+1 615 735 2600",
    "sg:postcode":"37066",
    "sg:province":"TN",
    "sg:tags":[
        "conditioning",
        "air",
        "system",
        "contractor"
    ],
    "sg:website":"www.bradleylankford.com",
    "wof:name":"Lankford Heat & Air Cond LLC",
    "wof:placetype":"venue"
},
  "geometry": {"coordinates":[-86.384615,36.361108],"type":"Point"}
}