{
  "type": "Feature",
  "properties": {
    "addr:full":"511 Algie Neely Rd Denmark TN 38391",
    "addr:housenumber":"511",
    "addr:postcode":"38391",
    "addr:street":"Algie Neely Rd",
    "iso:country":"US",
    "sg:address":"511 Algie Neely Rd",
    "sg:city":"Denmark",
    "sg:classifiers":[
        {
            "category":"Professional",
            "subcategory":"Lawyer & Legal Services",
            "type":"Services"
        }
    ],
    "sg:phone":"+1 731 422 6895",
    "sg:postcode":"38391",
    "sg:province":"TN",
    "sg:tags":[
        "attorney"
    ],
    "wof:name":"Hewitt Chatman",
    "wof:placetype":"venue"
},
  "geometry": {"coordinates":[-88.99342300000001,35.594404],"type":"Point"}
}