{
  "type": "Feature",
  "properties": {
    "addr:full":"5305 Confederate Dr Nashville TN 37215",
    "addr:housenumber":"5305",
    "addr:postcode":"37215",
    "addr:street":"Confederate Dr",
    "iso:country":"US",
    "sg:address":"5305 Confederate Dr",
    "sg:city":"Nashville",
    "sg:classifiers":[
        {
            "category":"Building & Trades",
            "subcategory":"Construction",
            "type":"Services"
        }
    ],
    "sg:phone":"+1 615 373 0719",
    "sg:postcode":"37215",
    "sg:province":"TN",
    "sg:tags":[
        "carpenter"
    ],
    "wof:name":"John A Carpenter",
    "wof:placetype":"venue"
},
  "geometry": {"coordinates":[-86.81610999999999,36.063663],"type":"Point"}
}