{
  "type": "Feature",
  "properties": {
    "iso:country":"US",
    "sg:address":"347 Saint Francis Ave",
    "sg:city":"Smyrna",
    "sg:classifiers":[
        {
            "category":"Building & Trades",
            "subcategory":"Construction",
            "type":"Services"
        }
    ],
    "sg:phone":"+1 615 355 8322",
    "sg:postcode":"37167",
    "sg:province":"TN",
    "sg:tags":[
        "contractor"
    ],
    "wof:name":"Intorcia Construction",
    "wof:placetype":"venue"
},
  "geometry": {"coordinates":[-86.543153,35.976431],"type":"Point"}
}