{
  "type": "Feature",
  "properties": {
    "iso:country":"US",
    "sg:address":"312 Vine St",
    "sg:city":"Chattanooga",
    "sg:classifiers":[
        {
            "category":"Professional",
            "subcategory":"Lawyer & Legal Services",
            "type":"Services"
        }
    ],
    "sg:phone":"+1 423 266 7555",
    "sg:postcode":"37403",
    "sg:province":"TN",
    "sg:tags":[
        "attorney",
        "criminal",
        "law"
    ],
    "sg:website":"http://www.levittandlevitt.com/",
    "wof:name":"Levitt & Levitt",
    "wof:placetype":"venue"
},
  "geometry": {"coordinates":[-85.305672,35.049965],"type":"Point"}
}