{
  "type": "Feature",
  "properties": {
    "iso:country":"US",
    "sg:address":"7230 Banther Rd",
    "sg:city":"Harrison",
    "sg:classifiers":[
        {
            "category":"Freight",
            "type":"Transportation"
        }
    ],
    "sg:phone":"+1 423 344 4470",
    "sg:postcode":"37341",
    "sg:province":"TN",
    "sg:tags":[
        "operator",
        "local",
        "trucking"
    ],
    "wof:name":"Blakes Deliveries Inc",
    "wof:placetype":"venue"
},
  "geometry": {"coordinates":[-85.066847,35.179913],"type":"Point"}
}