{
  "type": "Feature",
  "properties": {
    "iso:country":"US",
    "sg:address":"1964 Fayetteville Hwy",
    "sg:city":"Belfast",
    "sg:classifiers":[
        {
            "category":"Building & Trades",
            "subcategory":"Construction",
            "type":"Services"
        }
    ],
    "sg:phone":"+1 931 276 2429",
    "sg:postcode":"37091",
    "sg:province":"TN",
    "sg:tags":[
        "street",
        "paving",
        "hwy",
        "contractor"
    ],
    "wof:name":"Wright Paving Contractors Inc",
    "wof:placetype":"venue"
},
  "geometry": {"coordinates":[-86.717393,35.428607],"type":"Point"}
}