{
  "type": "Feature",
  "properties": {
    "addr:full":"5525 Chester St Arlington TN 38002",
    "addr:housenumber":"5525",
    "addr:postcode":"38002",
    "addr:street":"Chester St",
    "iso:country":"US",
    "sg:address":"5525 Chester St",
    "sg:city":"Arlington",
    "sg:classifiers":[
        {
            "category":"Restaurant",
            "type":"Food & Drink"
        }
    ],
    "sg:phone":"+1 901 867 3843",
    "sg:postcode":"38002",
    "sg:province":"TN",
    "sg:tags":[
        "eating"
    ],
    "wof:name":"Shephard Haven",
    "wof:placetype":"venue"
},
  "geometry": {"coordinates":[-89.648836,35.276989],"type":"Point"}
}