{
  "type": "Feature",
  "properties": {
    "addr:full":"1949 Redbud Way Sevierville TN 37876",
    "addr:housenumber":"1949",
    "addr:postcode":"37876",
    "addr:street":"Redbud Way",
    "iso:country":"US",
    "sg:address":"1949 Redbud Way",
    "sg:city":"Sevierville",
    "sg:classifiers":[
        {
            "category":"Building & Trades",
            "subcategory":"Construction",
            "type":"Services"
        }
    ],
    "sg:phone":"+1 865 429 1301",
    "sg:postcode":"37876",
    "sg:province":"TN",
    "sg:tags":[
        "contractor"
    ],
    "wof:name":"Cardwell Insulation",
    "wof:placetype":"venue"
},
  "geometry": {"coordinates":[-83.503698,35.919044],"type":"Point"}
}