{
  "type": "Feature",
  "properties": {
    "iso:country":"US",
    "sg:address":"7685 Farmington Blvd",
    "sg:city":"Germantown",
    "sg:classifiers":[
        {
            "category":"Sports & Exercise",
            "subcategory":"Gym",
            "type":"Entertainment"
        }
    ],
    "sg:phone":"+1 901 755 5535",
    "sg:postcode":"38138",
    "sg:province":"TN",
    "sg:tags":[
        "club",
        "health",
        "studio",
        "gymnasium"
    ],
    "wof:name":"Fitness Together",
    "wof:placetype":"venue"
},
  "geometry": {"coordinates":[-89.807225,35.095406],"type":"Point"}
}