{
  "type": "Feature",
  "properties": {
    "iso:country":"US",
    "sg:address":"3258 Stage Run Dr",
    "sg:city":"Hixson",
    "sg:classifiers":[
        {
            "category":"Insurance",
            "subcategory":"Insurance Agent",
            "type":"Services"
        }
    ],
    "sg:phone":"+1 423 843 3251",
    "sg:postcode":"37343",
    "sg:province":"TN",
    "wof:name":"Choo Choo Financial",
    "wof:placetype":"venue"
},
  "geometry": {"coordinates":[-85.21159,35.135628],"type":"Point"}
}