{
  "type": "Feature",
  "properties": {
    "iso:country":"US",
    "sg:address":"501 Evergreen St",
    "sg:city":"Harriman",
    "sg:classifiers":[
        {
            "category":"Manufacturing",
            "subcategory":"Printing",
            "type":"Manufacturing & Wholesale Goods"
        }
    ],
    "sg:phone":"+1 865 882 9340",
    "sg:postcode":"37748",
    "sg:province":"TN",
    "sg:tags":[
        "newspaper"
    ],
    "wof:name":"Roane Reader",
    "wof:placetype":"venue"
},
  "geometry": {"coordinates":[-84.53466299999999,35.959655],"type":"Point"}
}