{
  "type": "Feature",
  "properties": {
    "iso:country":"US",
    "sg:address":"1321 Murfreesboro Pike",
    "sg:city":"Nashville",
    "sg:classifiers":[
        {
            "category":"Government",
            "subcategory":"Office",
            "type":"Public Place"
        }
    ],
    "sg:phone":"+1 615 781 5318",
    "sg:postcode":"37217",
    "sg:province":"TN",
    "sg:tags":[
        "administration",
        "training",
        "employment",
        "for"
    ],
    "wof:name":"Apprenticeship and Training",
    "wof:placetype":"venue"
},
  "geometry": {"coordinates":[-86.697508,36.116422],"type":"Point"}
}