{
  "type": "Feature",
  "properties": {
    "iso:country":"US",
    "sg:address":"136 Overhill Rd",
    "sg:city":"Newport",
    "sg:classifiers":[
        {
            "category":"Freight",
            "type":"Transportation"
        }
    ],
    "sg:phone":"+1 423 623 1134",
    "sg:postcode":"37821",
    "sg:province":"TN",
    "sg:tags":[
        "company",
        "trucking"
    ],
    "wof:name":"C & A Trucking",
    "wof:placetype":"venue"
},
  "geometry": {"coordinates":[-83.218682,35.906663],"type":"Point"}
}