{
  "type": "Feature",
  "properties": {
    "iso:country":"US",
    "sg:address":"1904 Lawrence St",
    "sg:city":"Columbia",
    "sg:classifiers":[
        {
            "category":"Social Services",
            "type":"Services"
        }
    ],
    "sg:phone":"+1 931 840 0522",
    "sg:postcode":"38401",
    "sg:province":"TN",
    "sg:tags":[
        "organization",
        "welfare"
    ],
    "wof:name":"Employment Enabling Svc",
    "wof:placetype":"venue"
},
  "geometry": {"coordinates":[-87.05270299999999,35.598918],"type":"Point"}
}