{
  "type": "Feature",
  "properties": {
    "iso:country":"US",
    "sg:address":"1428 Hopewell Rd",
    "sg:city":"Knoxville",
    "sg:classifiers":[
        {
            "category":"Professional",
            "subcategory":"Business Services",
            "type":"Services"
        }
    ],
    "sg:phone":"+1 865 522 1776",
    "sg:postcode":"37920",
    "sg:province":"TN",
    "wof:name":"Tennessee Bonding Co",
    "wof:placetype":"venue"
},
  "geometry": {"coordinates":[-83.79651,35.932186],"type":"Point"}
}