{
  "type": "Feature",
  "properties": {
    "addr:full":"252 Carroll Creek Rd Johnson City TN 37601",
    "addr:housenumber":"252",
    "addr:postcode":"37601",
    "addr:street":"Carroll Creek Rd",
    "iso:country":"US",
    "sg:address":"252 Carroll Creek Rd",
    "sg:city":"Johnson City",
    "sg:classifiers":[
        {
            "category":"Wholesale",
            "subcategory":"Computers",
            "type":"Manufacturing & Wholesale Goods"
        }
    ],
    "sg:phone":"+1 877 819 0276",
    "sg:postcode":"37601",
    "sg:province":"TN",
    "sg:tags":[
        "home",
        "networking",
        "automation"
    ],
    "wof:name":"Linkedhouse",
    "wof:placetype":"venue"
},
  "geometry": {"coordinates":[-82.36499999999999,36.393223],"type":"Point"}
}