{
  "type": "Feature",
  "properties": {
    "addr:full":"1515 Elm Hill Pike Nashville TN 37210",
    "addr:housenumber":"1515",
    "addr:postcode":"37210",
    "addr:street":"Elm Hill Pike",
    "iso:country":"US",
    "sg:address":"1515 Elm Hill Pike",
    "sg:city":"Nashville",
    "sg:classifiers":[
        {
            "category":"Building & Trades",
            "subcategory":"Electrical",
            "type":"Services"
        }
    ],
    "sg:phone":"+1 615 361 8100",
    "sg:postcode":"37210",
    "sg:province":"TN",
    "sg:tags":[
        "electrical",
        "contractor"
    ],
    "wof:name":"Logan Media Services LLC",
    "wof:placetype":"venue"
},
  "geometry": {"coordinates":[-86.71506100000001,36.144291],"type":"Point"}
}