{
  "type": "Feature",
  "properties": {
    "iso:country":"US",
    "sg:address":"3691 Austin Peay Hwy",
    "sg:city":"Memphis",
    "sg:classifiers":[
        {
            "category":"Banks & Credit Unions",
            "subcategory":"Bank",
            "type":"Services"
        }
    ],
    "sg:phone":"+1 901 382 6622",
    "sg:postcode":"38135",
    "sg:province":"TN",
    "sg:tags":[
        "state"
    ],
    "sg:website":"www.bankofbartlett.com",
    "wof:name":"Bank Of Bartlett",
    "wof:placetype":"venue"
},
  "geometry": {"coordinates":[-89.90532399999999,35.224737],"type":"Point"}
}