{
  "type": "Feature",
  "properties": {
    "iso:country":"US",
    "sg:address":"1218 W Main St",
    "sg:city":"Lebanon",
    "sg:classifiers":[
        {
            "category":"Banks & Credit Unions",
            "subcategory":"Bank",
            "type":"Services"
        }
    ],
    "sg:phone":"+1 615 444 1976",
    "sg:postcode":"37087",
    "sg:province":"TN",
    "sg:tags":[
        "cashing",
        "check"
    ],
    "wof:name":"Capitol Cash",
    "wof:placetype":"venue"
},
  "geometry": {"coordinates":[-86.31998299999999,36.212696],"type":"Point"}
}