{
  "type": "Feature",
  "properties": {
    "iso:country":"US",
    "sg:address":"502 N Garden St",
    "sg:city":"Columbia",
    "sg:classifiers":[
        {
            "category":"Real Estate",
            "subcategory":"Real Estate Agent",
            "type":"Services"
        }
    ],
    "sg:phone":"+1 931 388 0041",
    "sg:postcode":"38401",
    "sg:province":"TN",
    "wof:name":"Progressive Realty",
    "wof:placetype":"venue"
},
  "geometry": {"coordinates":[-87.034879,35.619028],"type":"Point"}
}