{
  "type": "Feature",
  "properties": {
    "iso:country":"US",
    "sg:address":"1905 N Jackson St",
    "sg:city":"Tullahoma",
    "sg:classifiers":[
        {
            "category":"Recreation",
            "type":"Entertainment"
        },
        {
            "category":"Sports & Exercise",
            "subcategory":"Gym",
            "type":"Entertainment"
        }
    ],
    "sg:phone":"+1 931 455 2790",
    "sg:postcode":"37388",
    "sg:province":"TN",
    "sg:tags":[
        "club",
        "health",
        "studio",
        "gymnasium"
    ],
    "wof:name":"Contours Express",
    "wof:placetype":"venue"
},
  "geometry": {"coordinates":[-86.232747,35.385248],"type":"Point"}
}