{
  "type": "Feature",
  "properties": {
    "addr:full":"3942 Park Ave Memphis TN 38111",
    "addr:housenumber":"3942",
    "addr:postcode":"38111",
    "addr:street":"Park Ave",
    "iso:country":"US",
    "sg:address":"3942 Park Ave",
    "sg:city":"Memphis",
    "sg:classifiers":[
        {
            "category":"Insurance",
            "subcategory":"Insurance Agent",
            "type":"Services"
        },
        {
            "category":"Insurance",
            "subcategory":"Hazard Insurance",
            "type":"Services"
        },
        {
            "category":"Insurance",
            "subcategory":"Title Insurance",
            "type":"Services"
        }
    ],
    "sg:phone":"+1 901 458 2633",
    "sg:postcode":"38111",
    "sg:province":"TN",
    "sg:tags":[
        "auto",
        "commercial",
        "business",
        "homeowner"
    ],
    "sg:website":"http://www.realpagessites.com/moratinsurance",
    "wof:name":"Morat Insurance Services Incorporated",
    "wof:placetype":"venue"
},
  "geometry": {"coordinates":[-89.93122200000001,35.10752],"type":"Point"}
}