{
  "type": "Feature",
  "properties": {
    "iso:country":"US",
    "sg:address":"2600 Old Murfreesboro Rd W",
    "sg:city":"Lebanon",
    "sg:classifiers":[
        {
            "category":"Organizations",
            "subcategory":"Religious Organization",
            "type":"Services"
        }
    ],
    "sg:phone":"+1 615 444 6529",
    "sg:postcode":"37090",
    "sg:province":"TN",
    "sg:tags":[
        "church"
    ],
    "wof:name":"Jehovah's Witnesses",
    "wof:placetype":"venue"
},
  "geometry": {"coordinates":[-86.311598,36.168804],"type":"Point"}
}