{
  "type": "Feature",
  "properties": {
    "addr:full":"828 N Military Ave Lawrenceburg TN 38464",
    "addr:housenumber":"828",
    "addr:postcode":"38464",
    "addr:street":"N Military Ave",
    "iso:country":"US",
    "sg:address":"828 N Military Ave",
    "sg:city":"Lawrenceburg",
    "sg:classifiers":[
        {
            "category":"Social Services",
            "type":"Services"
        }
    ],
    "sg:phone":"+1 931 766 1420",
    "sg:postcode":"38464",
    "sg:province":"TN",
    "sg:tags":[
        "probation"
    ],
    "wof:name":"Adult Probation Ofc",
    "wof:placetype":"venue"
},
  "geometry": {"coordinates":[-87.33028899999999,35.251009],"type":"Point"}
}