{
  "type": "Feature",
  "properties": {
    "addr:full":"3003 Rossville Blvd Chattanooga TN 37407",
    "addr:housenumber":"3003",
    "addr:postcode":"37407",
    "addr:street":"Rossville Blvd",
    "iso:country":"US",
    "sg:address":"3003 Rossville Blvd",
    "sg:city":"Chattanooga",
    "sg:classifiers":[
        {
            "category":"Building & Trades",
            "subcategory":"Electrical",
            "type":"Services"
        }
    ],
    "sg:phone":"+1 423 593 1309",
    "sg:postcode":"37407",
    "sg:province":"TN",
    "sg:tags":[
        "industrial",
        "electrician",
        "contractors-commercial",
        "electric"
    ],
    "sg:website":"http://www.metro-electricinc.com",
    "wof:name":"Metro Electric Inc.",
    "wof:placetype":"venue"
},
  "geometry": {"coordinates":[-85.29389399999999,35.010172],"type":"Point"}
}