{
  "type": "Feature",
  "properties": {
    "iso:country":"US",
    "sg:address":"251 Old Gray Station Rd",
    "sg:city":"Johnson City",
    "sg:classifiers":[
        {
            "category":"Home & Garden",
            "subcategory":"Garden Supply",
            "type":"Retail Goods"
        }
    ],
    "sg:phone":"+1 423 467 2300",
    "sg:postcode":"37615",
    "sg:province":"TN",
    "wof:name":"Mize Farm & Garden Supply Inc",
    "wof:placetype":"venue"
},
  "geometry": {"coordinates":[-82.470118,36.408287],"type":"Point"}
}