{
  "type": "Feature",
  "properties": {
    "addr:full":"1615 Lisalynn Dr Hixson TN 37343",
    "addr:housenumber":"1615",
    "addr:postcode":"37343",
    "addr:street":"Lisalynn Dr",
    "iso:country":"US",
    "sg:address":"1615 Lisalynn Dr",
    "sg:city":"Hixson",
    "sg:classifiers":[
        {
            "category":"Professional",
            "subcategory":"Detective & Security Services",
            "type":"Services"
        }
    ],
    "sg:phone":"+1 423 842 7135",
    "sg:postcode":"37343",
    "sg:province":"TN",
    "sg:tags":[
        "car"
    ],
    "wof:name":"VIP Research",
    "wof:placetype":"venue"
},
  "geometry": {"coordinates":[-85.189083,35.198922],"type":"Point"}
}