{
  "type": "Feature",
  "properties": {
    "iso:country":"US",
    "sg:address":"901 Morrison Springs Rd",
    "sg:city":"Whitwell",
    "sg:classifiers":[
        {
            "category":"Farming",
            "subcategory":"Livestock Farm",
            "type":"Manufacturing & Wholesale Goods"
        }
    ],
    "sg:phone":"+1 423 658 5854",
    "sg:postcode":"37397",
    "sg:province":"TN",
    "sg:tags":[
        "hog",
        "beef",
        "f",
        "corn",
        "soybean",
        "cattle",
        "feedlot"
    ],
    "wof:name":"Dan Prigmore",
    "wof:placetype":"venue"
},
  "geometry": {"coordinates":[-85.53527699999999,35.165175],"type":"Point"}
}