{
  "type": "Feature",
  "properties": {
    "iso:country":"US",
    "sg:address":"392 Warfield Blvd Ct",
    "sg:city":"Clarksville",
    "sg:classifiers":[
        {
            "category":"Retail",
            "subcategory":"Auto Repair",
            "type":"Services"
        }
    ],
    "sg:phone":"+1 931 553 0055",
    "sg:postcode":"37043",
    "sg:province":"TN",
    "sg:tags":[
        "automotive",
        "exhaust",
        "sup"
    ],
    "wof:name":"Riverside Muffler & Alignment",
    "wof:placetype":"venue"
},
  "geometry": {"coordinates":[-87.284823,36.566919],"type":"Point"}
}