{
  "type": "Feature",
  "properties": {
    "iso:country":"US",
    "sg:address":"2416 Music Valley Dr",
    "sg:city":"Nashville",
    "sg:classifiers":[
        {
            "category":"Organizations",
            "subcategory":"Religious Organization",
            "type":"Services"
        }
    ],
    "sg:phone":"+1 615 577 1708",
    "sg:postcode":"37214",
    "sg:province":"TN",
    "sg:tags":[
        "church"
    ],
    "wof:name":"Nashville Church",
    "wof:placetype":"venue"
},
  "geometry": {"coordinates":[-86.69425699999999,36.219159],"type":"Point"}
}