{
  "type": "Feature",
  "properties": {
    "iso:country":"US",
    "sg:address":"639 E Main St",
    "sg:city":"Hendersonville",
    "sg:classifiers":[
        {
            "category":"Wholesale",
            "subcategory":"Painting Supplies",
            "type":"Manufacturing & Wholesale Goods"
        },
        {
            "category":"Manufacturing",
            "subcategory":"Chemicals & Compounds",
            "type":"Manufacturing & Wholesale Goods"
        }
    ],
    "sg:phone":"+1 615 826 1800",
    "sg:postcode":"37075",
    "sg:province":"TN",
    "sg:tags":[
        "mfg",
        "colors",
        "cyclic",
        "pigment"
    ],
    "wof:name":"Decorative Color & Chemical",
    "wof:placetype":"venue"
},
  "geometry": {"coordinates":[-86.565441,36.325091],"type":"Point"}
}