{
  "type": "Feature",
  "properties": {
    "iso:country":"US",
    "sg:address":"1174 Little Valley Rd",
    "sg:city":"Maynardville",
    "sg:classifiers":[
        {
            "category":"Professional",
            "type":"Services"
        }
    ],
    "sg:phone":"+1 865 992 5088",
    "sg:postcode":"37807",
    "sg:province":"TN",
    "wof:name":"Steven K Hamner",
    "wof:placetype":"venue"
},
  "geometry": {"coordinates":[-83.810998,36.265975],"type":"Point"}
}