{
  "type": "Feature",
  "properties": {
    "iso:country":"US",
    "sg:address":"3 Rock Crest Dr",
    "sg:city":"Signal Mountain",
    "sg:classifiers":[
        {
            "category":"Social Services",
            "subcategory":"Child Care",
            "type":"Services"
        }
    ],
    "sg:phone":"+1 423 886 7330",
    "sg:postcode":"37377",
    "sg:province":"TN",
    "sg:tags":[
        "day"
    ],
    "wof:name":"Turner Learning Systems LLC",
    "wof:placetype":"venue"
},
  "geometry": {"coordinates":[-85.350802,35.114641],"type":"Point"}
}