{
  "type": "Feature",
  "properties": {
    "iso:country":"US",
    "sg:address":"1024 S Yates Rd",
    "sg:city":"Memphis",
    "sg:classifiers":[
        {
            "category":"Personal",
            "subcategory":"Beauty Salon",
            "type":"Services"
        }
    ],
    "sg:phone":"+1 901 682 1609",
    "sg:postcode":"38120",
    "sg:province":"TN",
    "sg:tags":[
        "shop"
    ],
    "wof:name":"Fashion Flair",
    "wof:placetype":"venue"
},
  "geometry": {"coordinates":[-89.877274,35.105382],"type":"Point"}
}