{
  "type": "Feature",
  "properties": {
    "iso:country":"US",
    "sg:address":"225 Anderson Ave",
    "sg:city":"Brownsville",
    "sg:classifiers":[
        {
            "category":"Wholesale",
            "subcategory":"Tobacco Products",
            "type":"Manufacturing & Wholesale Goods"
        }
    ],
    "sg:phone":"+1 731 772 0243",
    "sg:postcode":"38012",
    "sg:province":"TN",
    "sg:tags":[
        "cigarette",
        "cigar",
        "dealer"
    ],
    "wof:name":"Discount Tobacco",
    "wof:placetype":"venue"
},
  "geometry": {"coordinates":[-89.25129800000001,35.590213],"type":"Point"}
}