{
  "type": "Feature",
  "properties": {
    "iso:country":"US",
    "sg:address":"6616 Deane Hill Dr",
    "sg:city":"Knoxville",
    "sg:classifiers":[
        {
            "category":"Freight",
            "type":"Transportation"
        }
    ],
    "sg:phone":"+1 865 691 5713",
    "sg:postcode":"37919",
    "sg:province":"TN",
    "sg:tags":[
        "general"
    ],
    "wof:name":"Oak Factory Outl of Knoxville",
    "wof:placetype":"venue"
},
  "geometry": {"coordinates":[-84.015067,35.927716],"type":"Point"}
}