{
  "type": "Feature",
  "properties": {
    "addr:full":"1720 Getwell Rd Memphis TN 38111",
    "addr:housenumber":"1720",
    "addr:postcode":"38111",
    "addr:street":"Getwell Rd",
    "iso:country":"US",
    "sg:address":"1720 Getwell Rd",
    "sg:city":"Memphis",
    "sg:classifiers":[
        {
            "category":"Education",
            "subcategory":"School",
            "type":"Public Place"
        }
    ],
    "sg:phone":"+1 901 744 5024",
    "sg:postcode":"38111",
    "sg:province":"TN",
    "sg:tags":[
        "executive"
    ],
    "wof:name":"South Park Elementary School",
    "wof:placetype":"venue"
},
  "geometry": {"coordinates":[-89.93115,35.084678],"type":"Point"}
}