{
  "type": "Feature",
  "properties": {
    "addr:full":"4108 Hunting Dr Hermitage TN 37076",
    "addr:housenumber":"4108",
    "addr:postcode":"37076",
    "addr:street":"Hunting Dr",
    "iso:country":"US",
    "sg:address":"4108 Hunting Dr",
    "sg:city":"Hermitage",
    "sg:classifiers":[
        {
            "category":"Professional",
            "subcategory":"Management & Consulting",
            "type":"Services"
        }
    ],
    "sg:phone":"+1 615 578 4723",
    "sg:postcode":"37076",
    "sg:province":"TN",
    "sg:tags":[
        "counselor",
        "public",
        "relations"
    ],
    "wof:name":"Details Unlimited!",
    "wof:placetype":"venue"
},
  "geometry": {"coordinates":[-86.61116699999999,36.180125],"type":"Point"}
}