{
  "type": "Feature",
  "properties": {
    "iso:country":"US",
    "sg:address":"2531 Nunnelee Ave",
    "sg:city":"Memphis",
    "sg:classifiers":[
        {
            "category":"Professional",
            "subcategory":"Business Services",
            "type":"Services"
        }
    ],
    "sg:phone":"+1 901 358 7002",
    "sg:postcode":"38127",
    "sg:province":"TN",
    "sg:tags":[
        "contractor"
    ],
    "wof:name":"R C Shannon Roofing",
    "wof:placetype":"venue"
},
  "geometry": {"coordinates":[-89.979035,35.214419],"type":"Point"}
}