{
  "type": "Feature",
  "properties": {
    "iso:country":"US",
    "sg:address":"6724 David Crockett Hwy",
    "sg:city":"Belvidere",
    "sg:classifiers":[
        {
            "category":"Utilities",
            "subcategory":"Water",
            "type":"Services"
        }
    ],
    "sg:phone":"+1 931 962 0208",
    "sg:postcode":"37306",
    "sg:province":"TN",
    "sg:tags":[
        "company",
        "sewage"
    ],
    "wof:name":"Belvidere Rural Utility Dist",
    "wof:placetype":"venue"
},
  "geometry": {"coordinates":[-86.196789,35.121467],"type":"Point"}
}