{
  "type": "Feature",
  "properties": {
    "addr:full":"156 Ivanhoe Ln Crossville TN 38555",
    "addr:housenumber":"156",
    "addr:postcode":"38555",
    "addr:street":"Ivanhoe Ln",
    "iso:country":"US",
    "sg:address":"156 Ivanhoe Ln",
    "sg:city":"Crossville",
    "sg:classifiers":[
        {
            "category":"Building & Trades",
            "subcategory":"Construction",
            "type":"Services"
        }
    ],
    "sg:phone":"+1 931 335 4530",
    "sg:postcode":"38555",
    "sg:province":"TN",
    "sg:tags":[
        "concrete",
        "contractor"
    ],
    "wof:name":"Dion Concrete",
    "wof:placetype":"venue"
},
  "geometry": {"coordinates":[-85.03998,35.948073],"type":"Point"}
}