{
  "type": "Feature",
  "properties": {
    "addr:full":"650 W Broadway St Rogersville TN 37857",
    "addr:housenumber":"650",
    "addr:postcode":"37857",
    "addr:street":"W Broadway St",
    "iso:country":"US",
    "sg:address":"650 W Broadway St",
    "sg:city":"Rogersville",
    "sg:classifiers":[
        {
            "category":"Retail",
            "subcategory":"Veterinary Services",
            "type":"Services"
        }
    ],
    "sg:phone":"+1 423 272 7320",
    "sg:postcode":"37857",
    "sg:province":"TN",
    "wof:name":"Slaughter Veterinarian Clinic",
    "wof:placetype":"venue"
},
  "geometry": {"coordinates":[-83.01033099999999,36.400549],"type":"Point"}
}