{
  "type": "Feature",
  "properties": {
    "addr:full":"713 W Main St Hendersonville TN 37075",
    "addr:housenumber":"713",
    "addr:postcode":"37075",
    "addr:street":"W Main St",
    "iso:country":"US",
    "sg:address":"713 W Main St",
    "sg:city":"Hendersonville",
    "sg:classifiers":[
        {
            "category":"Health Services",
            "subcategory":"Health Practitioner",
            "type":"Services"
        }
    ],
    "sg:phone":"+1 615 310 8595",
    "sg:postcode":"37075",
    "sg:province":"TN",
    "wof:name":"R & R Massage",
    "wof:placetype":"venue"
},
  "geometry": {"coordinates":[-86.641065,36.303036],"type":"Point"}
}