{
  "type": "Feature",
  "properties": {
    "iso:country":"US",
    "sg:address":"2746 E Center St",
    "sg:city":"Kingsport",
    "sg:classifiers":[
        {
            "category":"Wholesale",
            "subcategory":"Electrical",
            "type":"Manufacturing & Wholesale Goods"
        }
    ],
    "sg:phone":"+1 423 392 4801",
    "sg:postcode":"37664",
    "sg:province":"TN",
    "sg:tags":[
        "equipment",
        "electric",
        "supply"
    ],
    "wof:name":"Wholesale Supply Group Inc",
    "wof:placetype":"venue"
},
  "geometry": {"coordinates":[-82.51583100000001,36.53411],"type":"Point"}
}