{
  "type": "Feature",
  "properties": {
    "addr:full":"2667 Dayton Mountain Hwy Dayton TN 37321",
    "addr:housenumber":"2667",
    "addr:postcode":"37321",
    "addr:street":"Dayton Mountain Hwy",
    "iso:country":"US",
    "sg:address":"2667 Dayton Mountain Hwy",
    "sg:city":"Dayton",
    "sg:classifiers":[
        {
            "category":"Organizations",
            "subcategory":"Religious Organization",
            "type":"Services"
        }
    ],
    "sg:phone":"+1 423 570 9300",
    "sg:postcode":"37321",
    "sg:province":"TN",
    "sg:tags":[
        "church"
    ],
    "wof:name":"Cranmore Cove Baptist Church",
    "wof:placetype":"venue"
},
  "geometry": {"coordinates":[-85.03754000000001,35.513867],"type":"Point"}
}