{
  "type": "Feature",
  "properties": {
    "iso:country":"US",
    "sg:address":"2821 Dogwood Pl",
    "sg:city":"Nashville",
    "sg:classifiers":[
        {
            "category":"Professional",
            "subcategory":"Management & Consulting",
            "type":"Services"
        }
    ],
    "sg:phone":"+1 615 292 0604",
    "sg:postcode":"37204",
    "sg:province":"TN",
    "wof:name":"August Group",
    "wof:placetype":"venue"
},
  "geometry": {"coordinates":[-86.764819,36.113572],"type":"Point"}
}