{
  "type": "Feature",
  "properties": {
    "addr:full":"801 S James Campbell Blvd Columbia TN 38401",
    "addr:housenumber":"801",
    "addr:postcode":"38401",
    "addr:street":"S James Campbell Blvd",
    "iso:country":"US",
    "sg:address":"801 S James Campbell Blvd",
    "sg:city":"Columbia",
    "sg:classifiers":[
        {
            "category":"Retail",
            "subcategory":"Portrait Studio",
            "type":"Services"
        }
    ],
    "sg:phone":"+1 931 490 9747",
    "sg:postcode":"38401",
    "sg:province":"TN",
    "sg:tags":[
        "photo"
    ],
    "wof:name":"Olan Mills Portrait Studios",
    "wof:placetype":"venue"
},
  "geometry": {"coordinates":[-87.056567,35.595994],"type":"Point"}
}