{
  "type": "Feature",
  "properties": {
    "iso:country":"US",
    "sg:address":"229 Dale Ave",
    "sg:city":"Knoxville",
    "sg:classifiers":[
        {
            "category":"Building & Trades",
            "subcategory":"Construction",
            "type":"Services"
        }
    ],
    "sg:phone":"+1 865 546 0093",
    "sg:postcode":"37921",
    "sg:province":"TN",
    "sg:tags":[
        "merchandise",
        "contractor"
    ],
    "wof:name":"Granite & Tile Works Co",
    "wof:placetype":"venue"
},
  "geometry": {"coordinates":[-83.933567,35.96388],"type":"Point"}
}