{
  "type": "Feature",
  "properties": {
    "iso:country":"US",
    "sg:address":"1820 Madison St",
    "sg:city":"Clarksville",
    "sg:classifiers":[
        {
            "category":"Ice Cream",
            "type":"Food & Drink"
        }
    ],
    "sg:menulink":"http://www.allmenus.com/tn/clarksville/209312-tcby/menu/",
    "sg:phone":"+1 931 645 8229",
    "sg:postcode":"37043",
    "sg:province":"TN",
    "sg:tags":[
        "smoothy",
        "juice",
        "american"
    ],
    "wof:name":"TCBY",
    "wof:placetype":"venue"
},
  "geometry": {"coordinates":[-87.309665,36.513582],"type":"Point"}
}