{
  "type": "Feature",
  "properties": {
    "addr:full":"304 E College St Dickson TN 37055",
    "addr:housenumber":"304",
    "addr:postcode":"37055",
    "addr:street":"E College St",
    "iso:country":"US",
    "sg:address":"304 E College St",
    "sg:city":"Dickson",
    "sg:classifiers":[
        {
            "category":"Health Services",
            "subcategory":"Doctor",
            "type":"Services"
        }
    ],
    "sg:phone":"+1 615 446 4967",
    "sg:postcode":"37055",
    "sg:province":"TN",
    "wof:name":"J D Baggett DDS",
    "wof:placetype":"venue"
},
  "geometry": {"coordinates":[-87.385426,36.074677],"type":"Point"}
}