{
  "type": "Feature",
  "properties": {
    "iso:country":"US",
    "sg:address":"102 W Main St",
    "sg:city":"Lebanon",
    "sg:classifiers":[
        {
            "category":"Professional",
            "subcategory":"Lawyer & Legal Services",
            "type":"Services"
        }
    ],
    "sg:phone":"+1 615 443 7274",
    "sg:postcode":"37087",
    "sg:province":"TN",
    "sg:tags":[
        "attorney"
    ],
    "wof:name":"James H Kinnard",
    "wof:placetype":"venue"
},
  "geometry": {"coordinates":[-86.291738,36.207961],"type":"Point"}
}