{
  "type": "Feature",
  "properties": {
    "iso:country":"US",
    "sg:address":"5778 Brenners Pl",
    "sg:city":"Memphis",
    "sg:classifiers":[
        {
            "category":"Professional",
            "type":"Services"
        }
    ],
    "sg:phone":"+1 901 381 4487",
    "sg:postcode":"38134",
    "sg:province":"TN",
    "wof:name":"Kfh Incorporated",
    "wof:placetype":"venue"
},
  "geometry": {"coordinates":[-89.871278,35.193962],"type":"Point"}
}