{
  "type": "Feature",
  "properties": {
    "iso:country":"US",
    "sg:address":"40 Parker Dr",
    "sg:city":"Jackson",
    "sg:classifiers":[
        {
            "category":"Building & Trades",
            "subcategory":"Plumbing",
            "type":"Services"
        }
    ],
    "sg:phone":"+1 731 660 6803",
    "sg:postcode":"38305",
    "sg:province":"TN",
    "sg:tags":[
        "conditioning",
        "air",
        "system",
        "contractor"
    ],
    "wof:name":"M & A Supply Co",
    "wof:placetype":"venue"
},
  "geometry": {"coordinates":[-88.835814,35.715017],"type":"Point"}
}