{
  "type": "Feature",
  "properties": {
    "iso:country":"US",
    "sg:address":"1001 Reynolds St",
    "sg:city":"Paris",
    "sg:classifiers":[
        {
            "category":"Social Services",
            "subcategory":"Child Care",
            "type":"Services"
        }
    ],
    "sg:phone":"+1 731 644 7195",
    "sg:postcode":"38242",
    "sg:province":"TN",
    "sg:tags":[
        "kindergarten",
        "academic",
        "school"
    ],
    "wof:name":"Tennessee CARES",
    "wof:placetype":"venue"
},
  "geometry": {"coordinates":[-88.337791,36.292381],"type":"Point"}
}