{
  "type": "Feature",
  "properties": {
    "iso:country":"US",
    "sg:address":"4235 Sykes Rd",
    "sg:city":"Millington",
    "sg:classifiers":[
        {
            "category":"Shopping",
            "subcategory":"Music",
            "type":"Retail Goods"
        }
    ],
    "sg:phone":"+1 901 872 7081",
    "sg:postcode":"38053",
    "sg:province":"TN",
    "wof:name":"By Faith Records Inc",
    "wof:placetype":"venue"
},
  "geometry": {"coordinates":[-89.92235599999999,35.308993],"type":"Point"}
}