{
  "type": "Feature",
  "properties": {
    "iso:country":"US",
    "sg:address":"518 Congress Pkwy NW",
    "sg:city":"Athens",
    "sg:classifiers":[
        {
            "category":"Professional",
            "subcategory":"Accounting & Tax Preparation",
            "type":"Services"
        }
    ],
    "sg:phone":"+1 423 745 2722",
    "sg:postcode":"37303",
    "sg:province":"TN",
    "sg:tags":[
        "accountant"
    ],
    "wof:name":"Gerry Borstelmann CPA",
    "wof:placetype":"venue"
},
  "geometry": {"coordinates":[-84.61206799999999,35.46186],"type":"Point"}
}