{
  "type": "Feature",
  "properties": {
    "iso:country":"US",
    "sg:address":"762 Amos Gamble Rd",
    "sg:city":"Shelbyville",
    "sg:classifiers":[
        {
            "category":"Restaurant",
            "type":"Food & Drink"
        }
    ],
    "sg:phone":"+1 931 684 7642",
    "sg:postcode":"37160",
    "sg:province":"TN",
    "wof:name":"Dinner Table",
    "wof:placetype":"venue"
},
  "geometry": {"coordinates":[-86.443417,35.400617],"type":"Point"}
}