{
  "type": "Feature",
  "properties": {
    "iso:country":"US",
    "sg:address":"3061 Milkyway Dr",
    "sg:city":"Memphis",
    "sg:classifiers":[
        {
            "category":"Shopping",
            "subcategory":"Gifts & Souvenirs",
            "type":"Retail Goods"
        }
    ],
    "sg:phone":"+1 901 372 1632",
    "sg:postcode":"38134",
    "sg:province":"TN",
    "wof:name":"Desert Bloomed",
    "wof:placetype":"venue"
},
  "geometry": {"coordinates":[-89.84402300000001,35.209949],"type":"Point"}
}