{
  "type": "Feature",
  "properties": {
    "iso:country":"US",
    "sg:address":"5124 Stage Rd",
    "sg:city":"Memphis",
    "sg:classifiers":[
        {
            "category":"Banks & Credit Unions",
            "subcategory":"Investment Brokerage",
            "type":"Services"
        },
        {
            "category":"Insurance",
            "subcategory":"Insurance Agent",
            "type":"Services"
        }
    ],
    "sg:phone":"+1 901 382 6478",
    "sg:postcode":"38134",
    "sg:province":"TN",
    "sg:tags":[
        "security"
    ],
    "wof:name":"Preferred Services",
    "wof:placetype":"venue"
},
  "geometry": {"coordinates":[-89.89164,35.206862],"type":"Point"}
}