{
  "type": "Feature",
  "properties": {
    "iso:country":"US",
    "sg:address":"321 S Mill St",
    "sg:city":"Morrison",
    "sg:classifiers":[
        {
            "category":"Retail",
            "subcategory":"Portrait Studio",
            "type":"Services"
        },
        {
            "category":"Professional",
            "subcategory":"Art Services",
            "type":"Services"
        }
    ],
    "sg:phone":"+1 931 635 5555",
    "sg:postcode":"37357",
    "sg:province":"TN",
    "sg:tags":[
        "photographer",
        "photography",
        "commercial"
    ],
    "wof:name":"Mc Afee Photography",
    "wof:placetype":"venue"
},
  "geometry": {"coordinates":[-85.921384,35.597312],"type":"Point"}
}