{
  "type": "Feature",
  "properties": {
    "addr:full":"1720 E Northfield Blvd Murfreesboro TN 37130",
    "addr:housenumber":"1720",
    "addr:postcode":"37130",
    "addr:street":"E Northfield Blvd",
    "iso:country":"US",
    "sg:address":"1720 E Northfield Blvd",
    "sg:city":"Murfreesboro",
    "sg:classifiers":[
        {
            "category":"Organizations",
            "subcategory":"Religious Organization",
            "type":"Services"
        }
    ],
    "sg:phone":"+1 615 890 4656",
    "sg:postcode":"37130",
    "sg:province":"TN",
    "sg:tags":[
        "religion",
        "church"
    ],
    "wof:name":"Jehovah's Witnesses",
    "wof:placetype":"venue"
},
  "geometry": {"coordinates":[-86.355802,35.871976],"type":"Point"}
}