{
  "type": "Feature",
  "properties": {
    "iso:country":"US",
    "sg:address":"330 S Parkway W",
    "sg:city":"Memphis",
    "sg:classifiers":[
        {
            "category":"Autos & Motor Vehicles",
            "subcategory":"Auto Supplies",
            "type":"Retail Goods"
        },
        {
            "category":"Wholesale",
            "subcategory":"Machinery & Supplies",
            "type":"Manufacturing & Wholesale Goods"
        }
    ],
    "sg:phone":"+1 901 948 6624",
    "sg:postcode":"38109",
    "sg:province":"TN",
    "sg:tags":[
        "industrial",
        "glass",
        "coating",
        "tinting",
        "equipment",
        "window"
    ],
    "wof:name":"Midsouth Distributors",
    "wof:placetype":"venue"
},
  "geometry": {"coordinates":[-90.073486,35.107971],"type":"Point"}
}