{
  "type": "Feature",
  "properties": {
    "addr:full":"10149 2nd St Gates TN 38037",
    "addr:housenumber":"10149",
    "addr:postcode":"38037",
    "addr:street":"2Nd St",
    "iso:country":"US",
    "sg:address":"10149 2nd St",
    "sg:city":"Gates",
    "sg:classifiers":[
        {
            "category":"Sports & Exercise",
            "subcategory":"Gym",
            "type":"Entertainment"
        }
    ],
    "sg:phone":"+1 731 836 0368",
    "sg:postcode":"38037",
    "sg:province":"TN",
    "sg:tags":[
        "club",
        "health",
        "studio",
        "gymnasium"
    ],
    "wof:name":"L & E Fitness",
    "wof:placetype":"venue"
},
  "geometry": {"coordinates":[-89.406052,35.838764],"type":"Point"}
}