{
  "type": "Feature",
  "properties": {
    "iso:country":"US",
    "sg:address":"111 Peachtree Pl",
    "sg:city":"Jonesborough",
    "sg:classifiers":[
        {
            "category":"Building & Trades",
            "subcategory":"Construction",
            "type":"Services"
        }
    ],
    "sg:phone":"+1 423 753 8448",
    "sg:postcode":"37659",
    "sg:province":"TN",
    "sg:tags":[
        "house"
    ],
    "wof:name":"Chapman Home Builders",
    "wof:placetype":"venue"
},
  "geometry": {"coordinates":[-82.427688,36.297278],"type":"Point"}
}