{
  "type": "Feature",
  "properties": {
    "iso:country":"US",
    "sg:address":"6025 Stage Rd",
    "sg:city":"Bartlett",
    "sg:classifiers":[
        {
            "category":"Shopping",
            "subcategory":"Books",
            "type":"Retail Goods"
        }
    ],
    "sg:phone":"+1 901 388 8062",
    "sg:postcode":"38134",
    "sg:province":"TN",
    "sg:tags":[
        "dealer"
    ],
    "sg:website":"www.familychristian.com",
    "wof:name":"Family Christian Book Store",
    "wof:placetype":"venue"
},
  "geometry": {"coordinates":[-89.862537,35.204682],"type":"Point"}
}