{
  "type": "Feature",
  "properties": {
    "addr:full":"2956 Industrial Pkwy Knoxville TN 37921",
    "addr:housenumber":"2956",
    "addr:postcode":"37921",
    "addr:street":"Industrial Pkwy",
    "iso:country":"US",
    "sg:address":"2956 Industrial Pkwy",
    "sg:city":"Knoxville",
    "sg:classifiers":[
        {
            "category":"Wholesale",
            "subcategory":"Machinery & Supplies",
            "type":"Manufacturing & Wholesale Goods"
        }
    ],
    "sg:phone":"+1 865 546 1704",
    "sg:postcode":"37921",
    "sg:province":"TN",
    "sg:tags":[
        "bearing"
    ],
    "sg:website":"www.motionindustries.com",
    "wof:name":"Motion Industries Inc",
    "wof:placetype":"venue"
},
  "geometry": {"coordinates":[-83.968101,35.976089],"type":"Point"}
}