{
  "type": "Feature",
  "properties": {
    "iso:country":"US",
    "sg:address":"100 Palace St",
    "sg:city":"Martin",
    "sg:classifiers":[
        {
            "category":"Organizations",
            "subcategory":"Religious Organization",
            "type":"Services"
        }
    ],
    "sg:phone":"+1 731 587 9848",
    "sg:postcode":"38237",
    "sg:province":"TN",
    "wof:name":"Progrssive Mssnary Bptst Chrch",
    "wof:placetype":"venue"
},
  "geometry": {"coordinates":[-88.84901499999999,36.351071],"type":"Point"}
}