{
  "type": "Feature",
  "properties": {
    "addr:full":"213 Pebble Glen Dr Franklin TN 37064",
    "addr:housenumber":"213",
    "addr:postcode":"37064",
    "addr:street":"Pebble Glen Dr",
    "iso:country":"US",
    "sg:address":"213 Pebble Glen Dr",
    "sg:city":"Franklin",
    "sg:classifiers":[
        {
            "category":"Wholesale",
            "subcategory":"Construction Materials",
            "type":"Manufacturing & Wholesale Goods"
        }
    ],
    "sg:phone":"+1 615 794 6568",
    "sg:postcode":"37064",
    "sg:province":"TN",
    "sg:tags":[
        "building",
        "selling",
        "representative",
        "mfg"
    ],
    "wof:name":"Tennessee Architectural Pdts",
    "wof:placetype":"venue"
},
  "geometry": {"coordinates":[-86.85350800000001,35.921852],"type":"Point"}
}