{
  "type": "Feature",
  "properties": {
    "iso:country":"US",
    "sg:address":"13195 State Hwy 196",
    "sg:city":"Eads",
    "sg:classifiers":[
        {
            "category":"Retail",
            "subcategory":"Car Wash",
            "type":"Services"
        }
    ],
    "sg:phone":"+1 901 854 6009",
    "sg:postcode":"38028",
    "sg:province":"TN",
    "sg:tags":[
        "carwash",
        "automobile",
        "detail",
        "clean"
    ],
    "wof:name":"D J-C Shop",
    "wof:placetype":"venue"
},
  "geometry": {"coordinates":[-89.59284,35.17587],"type":"Point"}
}