{
  "type": "Feature",
  "properties": {
    "addr:full":"100 N Main St Memphis TN 38103",
    "addr:housenumber":"100",
    "addr:postcode":"38103",
    "addr:street":"N Main St",
    "iso:country":"US",
    "sg:address":"100 N Main St",
    "sg:city":"Memphis",
    "sg:classifiers":[
        {
            "category":"Professional",
            "subcategory":"Lawyer & Legal Services",
            "type":"Services"
        }
    ],
    "sg:phone":"+1 901 336 5269",
    "sg:postcode":"38103",
    "sg:province":"TN",
    "sg:tags":[
        "attorney"
    ],
    "wof:name":"C Todd Mason",
    "wof:placetype":"venue"
},
  "geometry": {"coordinates":[-90.051801,35.147461],"type":"Point"}
}