{
  "type": "Feature",
  "properties": {
    "iso:country":"US",
    "sg:address":"3315 12th Ave",
    "sg:city":"Chattanooga",
    "sg:classifiers":[
        {
            "category":"Organizations",
            "subcategory":"Religious Organization",
            "type":"Services"
        }
    ],
    "sg:phone":"+1 423 624 4013",
    "sg:postcode":"37407",
    "sg:province":"TN",
    "sg:tags":[
        "church"
    ],
    "wof:name":"Friendship East Community Chr",
    "wof:placetype":"venue"
},
  "geometry": {"coordinates":[-85.279715,35.002102],"type":"Point"}
}