{
  "type": "Feature",
  "properties": {
    "iso:country":"US",
    "sg:address":"3120 New Union Rd",
    "sg:city":"Dayton",
    "sg:classifiers":[
        {
            "category":"Farming",
            "subcategory":"Livestock Farm",
            "type":"Manufacturing & Wholesale Goods"
        }
    ],
    "sg:phone":"+1 423 775 1365",
    "sg:postcode":"37321",
    "sg:province":"TN",
    "sg:tags":[
        "vegetable",
        "live",
        "stock"
    ],
    "wof:name":"Harris Colonel",
    "wof:placetype":"venue"
},
  "geometry": {"coordinates":[-84.948368,35.463727],"type":"Point"}
}