{
  "type": "Feature",
  "properties": {
    "iso:country":"US",
    "sg:address":"415 S Depot St",
    "sg:city":"Rogersville",
    "sg:classifiers":[
        {
            "category":"Travel",
            "subcategory":"Hotels & Motels",
            "type":"Entertainment"
        }
    ],
    "sg:phone":"+1 423 272 5171",
    "sg:postcode":"37857",
    "sg:province":"TN",
    "wof:name":"Hale Rings Inn",
    "wof:placetype":"venue"
},
  "geometry": {"coordinates":[-83.00545200000001,36.404481],"type":"Point"}
}