{
  "type": "Feature",
  "properties": {
    "addr:full":"125 Mountain Perkins Ln Jacksboro TN 37757",
    "addr:housenumber":"125",
    "addr:postcode":"37757",
    "addr:street":"Mountain Perkins Ln",
    "iso:country":"US",
    "sg:address":"125 Mountain Perkins Ln",
    "sg:city":"Jacksboro",
    "sg:classifiers":[
        {
            "category":"Restaurant",
            "type":"Food & Drink"
        }
    ],
    "sg:menulink":"http://www.allmenus.com/tn/la-follette/153825-zaxbys/menu/",
    "sg:phone":"+1 423 566 4777",
    "sg:postcode":"37757",
    "sg:province":"TN",
    "sg:tags":[
        "american",
        "wing"
    ],
    "wof:name":"Zaxby's",
    "wof:placetype":"venue"
},
  "geometry": {"coordinates":[-84.18218400000001,36.334752],"type":"Point"}
}