{
  "type": "Feature",
  "properties": {
    "iso:country":"US",
    "sg:address":"1701 Louisville Dr",
    "sg:city":"Knoxville",
    "sg:classifiers":[
        {
            "category":"Wholesale",
            "subcategory":"Electrical",
            "type":"Manufacturing & Wholesale Goods"
        }
    ],
    "sg:phone":"+1 423 584 2831",
    "sg:postcode":"37921",
    "sg:province":"TN",
    "sg:tags":[
        "equipment"
    ],
    "wof:name":"ADT Security Services Inc",
    "wof:placetype":"venue"
},
  "geometry": {"coordinates":[-84.01268899999999,35.960049],"type":"Point"}
}