{
  "type": "Feature",
  "properties": {
    "iso:country":"US",
    "sg:address":"9520 Grove Rd",
    "sg:city":"Cordova",
    "sg:classifiers":[
        {
            "category":"Banks & Credit Unions",
            "subcategory":"Bank",
            "type":"Services"
        }
    ],
    "sg:phone":"+1 901 372 9566",
    "sg:postcode":"38016",
    "sg:province":"TN",
    "sg:tags":[
        "loan",
        "mortgage"
    ],
    "wof:name":"Mortgages & More Inc",
    "wof:placetype":"venue"
},
  "geometry": {"coordinates":[-89.743197,35.1967],"type":"Point"}
}