{
  "type": "Feature",
  "properties": {
    "addr:full":"100 Schools Dr Camden TN 38320",
    "addr:postcode":"38320",
    "addr:street":"Schools Dr",
    "iso:country":"US",
    "sg:address":"100 Schools Dr",
    "sg:city":"Camden",
    "sg:classifiers":[
        {
            "category":"Real Estate",
            "subcategory":"Real Estate Operator",
            "type":"Services"
        }
    ],
    "sg:phone":"+1 731 584 2008",
    "sg:postcode":"38320",
    "sg:province":"TN",
    "sg:tags":[
        "building",
        "apartment"
    ],
    "wof:name":"Red Oak Apartments",
    "wof:placetype":"venue"
},
  "geometry": {"coordinates":[-88.106269,36.072873],"type":"Point"}
}