{
  "type": "Feature",
  "properties": {
    "iso:country":"US",
    "sg:address":"1957 Sutherland Ave",
    "sg:city":"Knoxville",
    "sg:classifiers":[
        {
            "category":"Autos & Motor Vehicles",
            "subcategory":"Automobile Sales",
            "type":"Retail Goods"
        }
    ],
    "sg:phone":"+1 865 523 2222",
    "sg:postcode":"37919",
    "sg:province":"TN",
    "sg:tags":[
        "car",
        "dealer"
    ],
    "wof:name":"Motor Cars Of Knoxville",
    "wof:placetype":"venue"
},
  "geometry": {"coordinates":[-83.946972,35.96072],"type":"Point"}
}