{
  "type": "Feature",
  "properties": {
    "iso:country":"US",
    "sg:address":"119 O'Conner St",
    "sg:city":"Jackson",
    "sg:classifiers":[
        {
            "category":"Wholesale",
            "subcategory":"Plants",
            "type":"Manufacturing & Wholesale Goods"
        }
    ],
    "sg:phone":"+1 731 422 1180",
    "sg:postcode":"38301",
    "sg:province":"TN",
    "sg:tags":[
        "florist"
    ],
    "wof:name":"Metro Wholesales Florist Inc",
    "wof:placetype":"venue"
},
  "geometry": {"coordinates":[-88.54043299999999,35.358616],"type":"Point"}
}