{
  "type": "Feature",
  "properties": {
    "iso:country":"US",
    "sg:address":"3056 Miser Station Rd",
    "sg:city":"Louisville",
    "sg:classifiers":[
        {
            "category":"Professional",
            "type":"Services"
        },
        {
            "category":"Real Estate",
            "subcategory":"Real Estate Agent",
            "type":"Services"
        }
    ],
    "sg:phone":"+1 865 984 0085",
    "sg:postcode":"37777",
    "sg:province":"TN",
    "wof:name":"Outerbanks Limited LLC",
    "wof:placetype":"venue"
},
  "geometry": {"coordinates":[-84.034675,35.803396],"type":"Point"}
}