{
  "type": "Feature",
  "properties": {
    "addr:full":"2408 Vine St Chattanooga TN 37404",
    "addr:housenumber":"2408",
    "addr:postcode":"37404",
    "addr:street":"Vine St",
    "iso:country":"US",
    "sg:address":"2408 Vine St",
    "sg:city":"Chattanooga",
    "sg:classifiers":[
        {
            "category":"Professional",
            "type":"Services"
        }
    ],
    "sg:phone":"+1 423 622 3885",
    "sg:postcode":"37404",
    "sg:province":"TN",
    "wof:name":"Embrace Writers",
    "wof:placetype":"venue"
},
  "geometry": {"coordinates":[-85.264685,35.034101],"type":"Point"}
}