{
  "type": "Feature",
  "properties": {
    "iso:country":"US",
    "sg:address":"2108 Blue Springs Rd SE",
    "sg:city":"Cleveland",
    "sg:classifiers":[
        {
            "category":"Retail",
            "subcategory":"Self-service Laundry",
            "type":"Services"
        }
    ],
    "sg:phone":"+1 423 479 5163",
    "sg:postcode":"37311",
    "sg:province":"TN",
    "sg:tags":[
        "coin"
    ],
    "wof:name":"Blue Springs Laundry",
    "wof:placetype":"venue"
},
  "geometry": {"coordinates":[-84.88895100000001,35.134232],"type":"Point"}
}