{
  "type": "Feature",
  "properties": {
    "iso:country":"US",
    "sg:address":"3549 Decatur Hwy",
    "sg:city":"Kingston",
    "sg:classifiers":[
        {
            "category":"Autos & Motor Vehicles",
            "subcategory":"Fuel & Gas Station",
            "type":"Retail Goods"
        }
    ],
    "sg:phone":"+1 865 376 5087",
    "sg:postcode":"37763",
    "sg:province":"TN",
    "sg:tags":[
        "oil"
    ],
    "wof:name":"Allen's Coastal",
    "wof:placetype":"venue"
},
  "geometry": {"coordinates":[-84.562816,35.803274],"type":"Point"}
}