{
  "type": "Feature",
  "properties": {
    "addr:full":"2239 Whitten Rd Memphis TN 38133",
    "addr:housenumber":"2239",
    "addr:postcode":"38133",
    "addr:street":"Whitten Rd",
    "iso:country":"US",
    "sg:address":"2239 Whitten Rd",
    "sg:city":"Memphis",
    "sg:classifiers":[
        {
            "category":"Professional",
            "subcategory":"Art Services",
            "type":"Services"
        }
    ],
    "sg:phone":"+1 901 937 1155",
    "sg:postcode":"38133",
    "sg:province":"TN",
    "sg:tags":[
        "photographer"
    ],
    "wof:name":"Lifetouch National Schl Studio",
    "wof:placetype":"venue"
},
  "geometry": {"coordinates":[-89.835987,35.18644],"type":"Point"}
}