{
  "type": "Feature",
  "properties": {
    "addr:full":"454 S Lowry St Smyrna TN 37167",
    "addr:housenumber":"454",
    "addr:postcode":"37167",
    "addr:street":"S Lowry St",
    "iso:country":"US",
    "sg:address":"454 S Lowry St",
    "sg:city":"Smyrna",
    "sg:classifiers":[
        {
            "category":"Autos & Motor Vehicles",
            "subcategory":"Automobile Sales",
            "type":"Retail Goods"
        }
    ],
    "sg:phone":"+1 615 355 5290",
    "sg:postcode":"37167",
    "sg:province":"TN",
    "sg:tags":[
        "car",
        "dealer"
    ],
    "wof:name":"B & G Auto Sales",
    "wof:placetype":"venue"
},
  "geometry": {"coordinates":[-86.494338,35.954727],"type":"Point"}
}