{
  "type": "Feature",
  "properties": {
    "iso:country":"US",
    "sg:address":"1701 Louisville Dr",
    "sg:city":"Knoxville",
    "sg:classifiers":[
        {
            "category":"Wholesale",
            "subcategory":"Machinery & Supplies",
            "type":"Manufacturing & Wholesale Goods"
        },
        {
            "category":"Home & Garden",
            "subcategory":"Building Materials",
            "type":"Retail Goods"
        }
    ],
    "sg:phone":"+1 865 212 9945",
    "sg:postcode":"37921",
    "sg:province":"TN",
    "sg:tags":[
        "house",
        "industrial"
    ],
    "wof:name":"Kryton Marketing Division",
    "wof:placetype":"venue"
},
  "geometry": {"coordinates":[-84.01268899999999,35.960049],"type":"Point"}
}