{
  "type": "Feature",
  "properties": {
    "iso:country":"US",
    "sg:address":"5742 Brainerd Rd",
    "sg:city":"Chattanooga",
    "sg:classifiers":[
        {
            "category":"Shopping",
            "subcategory":"Clothing, Apparel, & Fashions",
            "type":"Retail Goods"
        }
    ],
    "sg:phone":"+1 423 296 1101",
    "sg:postcode":"37411",
    "sg:province":"TN",
    "sg:tags":[
        "uniform"
    ],
    "wof:name":"Uniform Shop",
    "wof:placetype":"venue"
},
  "geometry": {"coordinates":[-85.213415,35.011872],"type":"Point"}
}