{
  "type": "Feature",
  "properties": {
    "iso:country":"US",
    "sg:address":"5909 Shelby Oaks Dr",
    "sg:city":"Memphis",
    "sg:classifiers":[
        {
            "category":"Professional",
            "subcategory":"Advertising",
            "type":"Services"
        }
    ],
    "sg:phone":"+1 901 383 8315",
    "sg:postcode":"38134",
    "sg:province":"TN",
    "sg:tags":[
        "representative"
    ],
    "wof:name":"NCR Systemedia Group Inc",
    "wof:placetype":"venue"
},
  "geometry": {"coordinates":[-89.866238,35.166052],"type":"Point"}
}