{
  "type": "Feature",
  "properties": {
    "addr:full":"8707 Fay Rd Cordova TN 38018",
    "addr:housenumber":"8707",
    "addr:postcode":"38018",
    "addr:street":"Fay Rd",
    "iso:country":"US",
    "sg:address":"8707 Fay Rd",
    "sg:city":"Cordova",
    "sg:classifiers":[
        {
            "category":"Social Services",
            "subcategory":"Child Care",
            "type":"Services"
        }
    ],
    "sg:phone":"+1 901 756 9859",
    "sg:postcode":"38018",
    "sg:province":"TN",
    "sg:tags":[
        "kindergarten",
        "academic",
        "school"
    ],
    "wof:name":"Early Childhood Learning Ctr",
    "wof:placetype":"venue"
},
  "geometry": {"coordinates":[-89.774231,35.154734],"type":"Point"}
}