{
  "type": "Feature",
  "properties": {
    "iso:country":"US",
    "sg:address":"401 Doe Ridge",
    "sg:city":"Franklin",
    "sg:classifiers":[
        {
            "category":"Professional",
            "subcategory":"Computer Services",
            "type":"Services"
        }
    ],
    "sg:phone":"+1 615 595 1085",
    "sg:postcode":"37067",
    "sg:province":"TN",
    "sg:tags":[
        "it"
    ],
    "wof:name":"Nexus Solutions",
    "wof:placetype":"venue"
},
  "geometry": {"coordinates":[-86.79392199999999,35.911744],"type":"Point"}
}