{
  "type": "Feature",
  "properties": {
    "addr:full":"1749 N 9th Ave Humboldt TN 38343",
    "addr:housenumber":"1749",
    "addr:postcode":"38343",
    "addr:street":"N 9Th Ave",
    "iso:country":"US",
    "sg:address":"1749 N 9th Ave",
    "sg:city":"Humboldt",
    "sg:classifiers":[
        {
            "category":"Wholesale",
            "subcategory":"Chemicals & Plastics",
            "type":"Manufacturing & Wholesale Goods"
        }
    ],
    "sg:phone":"+1 731 784 9492",
    "sg:postcode":"38343",
    "sg:province":"TN",
    "wof:name":"Helena Chemical Co",
    "wof:placetype":"venue"
},
  "geometry": {"coordinates":[-88.92200099999999,35.833132],"type":"Point"}
}