{
  "type": "Feature",
  "properties": {
    "iso:country":"US",
    "sg:address":"585 S Cooper St",
    "sg:city":"Memphis",
    "sg:classifiers":[
        {
            "category":"Restaurant",
            "type":"Food & Drink"
        }
    ],
    "sg:phone":"+1 901 272 0940",
    "sg:postcode":"38104",
    "sg:province":"TN",
    "sg:tags":[
        "house",
        "steak",
        "barbecue"
    ],
    "wof:name":"Neelys Barbeque Corporate Offices",
    "wof:placetype":"venue"
},
  "geometry": {"coordinates":[-89.99053600000001,35.12973],"type":"Point"}
}