{
  "type": "Feature",
  "properties": {
    "addr:full":"7824 Ewing Rd Powell TN 37849",
    "addr:housenumber":"7824",
    "addr:postcode":"37849",
    "addr:street":"Ewing Rd",
    "iso:country":"US",
    "sg:address":"7824 Ewing Rd",
    "sg:city":"Powell",
    "sg:phone":"+1 865 938 1123",
    "sg:postcode":"37849",
    "sg:province":"TN",
    "sg:tags":[
        "scale"
    ],
    "wof:name":"Absolute Weighing Inc",
    "wof:placetype":"venue"
},
  "geometry": {"coordinates":[-84.02955300000001,36.035811],"type":"Point"}
}