{
  "type": "Feature",
  "properties": {
    "iso:country":"US",
    "sg:address":"10412 Lexington Dr",
    "sg:city":"Knoxville",
    "sg:classifiers":[
        {
            "category":"Organizations",
            "subcategory":"Labor Organization",
            "type":"Services"
        }
    ],
    "sg:phone":"+1 865 966 2009",
    "sg:postcode":"37932",
    "sg:province":"TN",
    "wof:name":"Laborers Local",
    "wof:placetype":"venue"
},
  "geometry": {"coordinates":[-84.135293,35.910952],"type":"Point"}
}