{
  "type": "Feature",
  "properties": {
    "iso:country":"US",
    "sg:address":"1 Murfreesboro Rd",
    "sg:city":"Lebanon",
    "sg:classifiers":[
        {
            "category":"Organizations",
            "subcategory":"Religious Organization",
            "type":"Services"
        }
    ],
    "sg:phone":"+1 615 443 1248",
    "sg:postcode":"37090",
    "sg:province":"TN",
    "sg:tags":[
        "church"
    ],
    "wof:name":"Lebanon Family Worship Church",
    "wof:placetype":"venue"
},
  "geometry": {"coordinates":[-86.300084,36.180001],"type":"Point"}
}