{
  "type": "Feature",
  "properties": {
    "iso:country":"US",
    "sg:address":"150 E Park Cir",
    "sg:city":"Dickson",
    "sg:classifiers":[
        {
            "category":"Real Estate",
            "subcategory":"Real Estate Operator",
            "type":"Services"
        }
    ],
    "sg:phone":"+1 615 446 1771",
    "sg:postcode":"37055",
    "sg:province":"TN",
    "sg:tags":[
        "building",
        "apartment"
    ],
    "wof:name":"East Forest Park Apartments",
    "wof:placetype":"venue"
},
  "geometry": {"coordinates":[-87.365364,36.072706],"type":"Point"}
}