{
  "type": "Feature",
  "properties": {
    "iso:country":"US",
    "sg:address":"844 Parkrose Rd",
    "sg:city":"Memphis",
    "sg:classifiers":[
        {
            "category":"Professional",
            "type":"Services"
        }
    ],
    "sg:phone":"+1 901 378 7427",
    "sg:postcode":"38109",
    "sg:province":"TN",
    "wof:name":"Buckley Communications",
    "wof:placetype":"venue"
},
  "geometry": {"coordinates":[-90.093018,35.023622],"type":"Point"}
}