{
  "type": "Feature",
  "properties": {
    "addr:full":"175 Lafayette St Nashville TN 37210",
    "addr:housenumber":"175",
    "addr:postcode":"37210",
    "addr:street":"Lafayette St",
    "iso:country":"US",
    "sg:address":"175 Lafayette St",
    "sg:city":"Nashville",
    "sg:classifiers":[
        {
            "category":"Food & Beverages",
            "subcategory":"Groceries & Convenience Stores",
            "type":"Retail Goods"
        }
    ],
    "sg:phone":"+1 615 726 1660",
    "sg:postcode":"37210",
    "sg:province":"TN",
    "sg:tags":[
        "grocer"
    ],
    "wof:name":"Fast Service Plus",
    "wof:placetype":"venue"
},
  "geometry": {"coordinates":[-86.7572,36.14699],"type":"Point"}
}