{
  "type": "Feature",
  "properties": {
    "addr:full":"1124 E Weisgarber Rd Knoxville TN 37909",
    "addr:housenumber":"1124",
    "addr:postcode":"37909",
    "addr:street":"E Weisgarber Rd",
    "iso:country":"US",
    "sg:address":"1124 E Weisgarber Rd",
    "sg:city":"Knoxville",
    "sg:classifiers":[
        {
            "category":"Health Services",
            "subcategory":"Doctor",
            "type":"Services"
        }
    ],
    "sg:phone":"+1 865 588 1037",
    "sg:postcode":"37909",
    "sg:province":"TN",
    "sg:tags":[
        "medical"
    ],
    "wof:name":"Eye Surgery Center East Tenn",
    "wof:placetype":"venue"
},
  "geometry": {"coordinates":[-84.011764,35.944123],"type":"Point"}
}