{
  "type": "Feature",
  "properties": {
    "addr:full":"1901 Murfreesboro Pike Nashville TN 37217",
    "addr:housenumber":"1901",
    "addr:postcode":"37217",
    "addr:street":"Murfreesboro Pike",
    "iso:country":"US",
    "sg:address":"1901 Murfreesboro Pike",
    "sg:city":"Nashville",
    "sg:classifiers":[
        {
            "category":"Recreation",
            "subcategory":"Arcade",
            "type":"Entertainment"
        }
    ],
    "sg:phone":"+1 615 758 8848",
    "sg:postcode":"37217",
    "sg:province":"TN",
    "sg:tags":[
        "amusement",
        "devices"
    ],
    "wof:name":"Nashville Vintage Pinball Co",
    "wof:placetype":"venue"
},
  "geometry": {"coordinates":[-86.656345,36.096573],"type":"Point"}
}