{
  "type": "Feature",
  "properties": {
    "iso:country":"US",
    "sg:address":"1230 West Ave",
    "sg:city":"Crossville",
    "sg:classifiers":[
        {
            "category":"Shopping",
            "subcategory":"Clothing, Apparel, & Fashions",
            "type":"Retail Goods"
        }
    ],
    "sg:phone":"+1 931 456 6842",
    "sg:postcode":"38555",
    "sg:province":"TN",
    "wof:name":"Priscillas The Lingerie Shop",
    "wof:placetype":"venue"
},
  "geometry": {"coordinates":[-85.040359,35.957432],"type":"Point"}
}