{
  "type": "Feature",
  "properties": {
    "addr:full":"8705 Unicorn Dr Knoxville TN 37923",
    "addr:housenumber":"8705",
    "addr:postcode":"37923",
    "addr:street":"Unicorn Dr",
    "iso:country":"US",
    "sg:address":"8705 Unicorn Dr",
    "sg:city":"Knoxville",
    "sg:classifiers":[
        {
            "category":"Professional",
            "type":"Services"
        }
    ],
    "sg:phone":"+1 865 769 6573",
    "sg:postcode":"37923",
    "sg:province":"TN",
    "sg:tags":[
        "establishment"
    ],
    "wof:name":"Q A Systems Corp",
    "wof:placetype":"venue"
},
  "geometry": {"coordinates":[-84.075472,35.919681],"type":"Point"}
}