{
  "type": "Feature",
  "properties": {
    "iso:country":"US",
    "sg:address":"416 Old Pencil Mill Rd",
    "sg:city":"Chapel Hill",
    "sg:classifiers":[
        {
            "category":"Building & Trades",
            "subcategory":"Construction",
            "type":"Services"
        }
    ],
    "sg:phone":"+1 931 294 2532",
    "sg:postcode":"37034",
    "sg:province":"TN",
    "sg:tags":[
        "paving",
        "contractor"
    ],
    "wof:name":"Mcclintock Paving",
    "wof:placetype":"venue"
},
  "geometry": {"coordinates":[-86.592108,35.608191],"type":"Point"}
}