{
  "type": "Feature",
  "properties": {
    "iso:country":"US",
    "sg:address":"115 Rileys Path",
    "sg:city":"Cookeville",
    "sg:classifiers":[
        {
            "category":"Professional",
            "type":"Services"
        },
        {
            "category":"Building & Trades",
            "subcategory":"Landscaping Services",
            "type":"Services"
        }
    ],
    "sg:phone":"+1 931 537 6777",
    "sg:postcode":"38506",
    "sg:province":"TN",
    "sg:tags":[
        "establishment"
    ],
    "wof:name":"New Day Service & Supplies",
    "wof:placetype":"venue"
},
  "geometry": {"coordinates":[-85.45400600000001,36.189286],"type":"Point"}
}