{
  "type": "Feature",
  "properties": {
    "iso:country":"US",
    "sg:address":"22 N Front St",
    "sg:city":"Memphis",
    "sg:classifiers":[
        {
            "category":"Professional",
            "subcategory":"Lawyer & Legal Services",
            "type":"Services"
        }
    ],
    "sg:phone":"+1 901 525 3450",
    "sg:postcode":"38103",
    "sg:province":"TN",
    "sg:tags":[
        "attorney"
    ],
    "wof:name":"Archibald & Halmon",
    "wof:placetype":"venue"
},
  "geometry": {"coordinates":[-90.05371599999999,35.14656],"type":"Point"}
}