{
  "type": "Feature",
  "properties": {
    "iso:country":"US",
    "sg:address":"2000 Oak Ridge Tpke",
    "sg:city":"Oak Ridge",
    "sg:classifiers":[
        {
            "category":"Organizations",
            "subcategory":"Religious Organization",
            "type":"Services"
        }
    ],
    "sg:phone":"+1 865 483 7153",
    "sg:postcode":"37830",
    "sg:province":"TN",
    "wof:name":"First Assembly Of God",
    "wof:placetype":"venue"
},
  "geometry": {"coordinates":[-84.28990899999999,36.002338],"type":"Point"}
}