{
  "type": "Feature",
  "properties": {
    "iso:country":"US",
    "sg:address":"1726 Poplar Ave",
    "sg:city":"Memphis",
    "sg:classifiers":[
        {
            "category":"Health Services",
            "subcategory":"Doctor",
            "type":"Services"
        }
    ],
    "sg:phone":"+1 901 278 7139",
    "sg:postcode":"38104",
    "sg:province":"TN",
    "sg:tags":[
        "physician",
        "geriatrics",
        "surgeons"
    ],
    "wof:name":"Burns, Robert MD",
    "wof:placetype":"venue"
},
  "geometry": {"coordinates":[-90.002977,35.142848],"type":"Point"}
}