{
  "type": "Feature",
  "properties": {
    "addr:full":"95 McDougal Rd Fayetteville TN 37334",
    "addr:housenumber":"95",
    "addr:postcode":"37334",
    "addr:street":"Mcdougal Rd",
    "iso:country":"US",
    "sg:address":"95 McDougal Rd",
    "sg:city":"Fayetteville",
    "sg:classifiers":[
        {
            "category":"Freight",
            "type":"Transportation"
        }
    ],
    "sg:phone":"+1 931 438 7197",
    "sg:postcode":"37334",
    "sg:province":"TN",
    "sg:tags":[
        "trucking"
    ],
    "wof:name":"Five K Trucking",
    "wof:placetype":"venue"
},
  "geometry": {"coordinates":[-86.56441,35.076007],"type":"Point"}
}