{
  "type": "Feature",
  "properties": {
    "iso:country":"US",
    "sg:address":"1584 E Alcy Rd",
    "sg:city":"Memphis",
    "sg:classifiers":[
        {
            "category":"Restaurant",
            "type":"Food & Drink"
        }
    ],
    "sg:phone":"+1 901 946 4131",
    "sg:postcode":"38114",
    "sg:province":"TN",
    "sg:tags":[
        "eating"
    ],
    "wof:name":"Day Diner",
    "wof:placetype":"venue"
},
  "geometry": {"coordinates":[-90.010563,35.077965],"type":"Point"}
}