{
  "type": "Feature",
  "properties": {
    "iso:country":"US",
    "sg:address":"2212 Elliston Pl",
    "sg:city":"Nashville",
    "sg:classifiers":[
        {
            "category":"Professional",
            "type":"Services"
        }
    ],
    "sg:phone":"+1 615 340 0787",
    "sg:postcode":"37203",
    "sg:province":"TN",
    "wof:name":"Fiesta Azteca",
    "wof:placetype":"venue"
},
  "geometry": {"coordinates":[-86.80416700000001,36.151265],"type":"Point"}
}