{
  "type": "Feature",
  "properties": {
    "addr:full":"3279 Mount Carmel Rd Covington TN 38019",
    "addr:housenumber":"3279",
    "addr:postcode":"38019",
    "addr:street":"Mount Carmel Rd",
    "iso:country":"US",
    "sg:address":"3279 Mount Carmel Rd",
    "sg:city":"Covington",
    "sg:phone":"+1 901 476 2958",
    "sg:postcode":"38019",
    "sg:province":"TN",
    "sg:tags":[
        "farm",
        "soybean"
    ],
    "wof:name":"Catherine McCalla",
    "wof:placetype":"venue"
},
  "geometry": {"coordinates":[-89.648703,35.5159],"type":"Point"}
}