{
  "type": "Feature",
  "properties": {
    "iso:country":"US",
    "sg:address":"2460 State Hwy 149",
    "sg:city":"Palmyra",
    "sg:classifiers":[
        {
            "category":"Food & Beverages",
            "subcategory":"Groceries & Convenience Stores",
            "type":"Retail Goods"
        }
    ],
    "sg:phone":"+1 931 326 5205",
    "sg:postcode":"37142",
    "sg:province":"TN",
    "sg:tags":[
        "grocer"
    ],
    "wof:name":"Palmyra 149 Market",
    "wof:placetype":"venue"
},
  "geometry": {"coordinates":[-87.474835,36.437431],"type":"Point"}
}