{
  "type": "Feature",
  "properties": {
    "addr:full":"3222 Peoples St Johnson City TN 37604",
    "addr:housenumber":"3222",
    "addr:postcode":"37604",
    "addr:street":"Peoples St",
    "iso:country":"US",
    "sg:address":"3222 Peoples St",
    "sg:city":"Johnson City",
    "sg:classifiers":[
        {
            "category":"Shopping",
            "subcategory":"Computers & Home Electronics",
            "type":"Retail Goods"
        }
    ],
    "sg:phone":"+1 423 262 0329",
    "sg:postcode":"37604",
    "sg:province":"TN",
    "sg:tags":[
        "equipment",
        "electronic",
        "supply"
    ],
    "wof:name":"Best Buy",
    "wof:placetype":"venue"
},
  "geometry": {"coordinates":[-82.40177300000001,36.346209],"type":"Point"}
}