{
  "type": "Feature",
  "properties": {
    "iso:country":"US",
    "sg:address":"911 Timberside Dr",
    "sg:city":"Nolensville",
    "sg:classifiers":[
        {
            "category":"Building & Trades",
            "subcategory":"Construction",
            "type":"Services"
        }
    ],
    "sg:phone":"+1 615 776 3020",
    "sg:postcode":"37135",
    "sg:province":"TN",
    "sg:tags":[
        "residential"
    ],
    "wof:name":"Forney Construction",
    "wof:placetype":"venue"
},
  "geometry": {"coordinates":[-86.66495399999999,35.962241],"type":"Point"}
}