{
  "type": "Feature",
  "properties": {
    "iso:country":"US",
    "sg:address":"3337 Earhart Rd",
    "sg:city":"Mount Juliet",
    "sg:classifiers":[
        {
            "category":"Wholesale",
            "subcategory":"Plants",
            "type":"Manufacturing & Wholesale Goods"
        }
    ],
    "sg:phone":"+1 615 885 1126",
    "sg:postcode":"37076",
    "sg:province":"TN",
    "sg:tags":[
        "florist"
    ],
    "wof:name":"Sutton Wholesale Enterprises",
    "wof:placetype":"venue"
},
  "geometry": {"coordinates":[-86.57058600000001,36.147549],"type":"Point"}
}