{
  "type": "Feature",
  "properties": {
    "iso:country":"US",
    "sg:address":"283 Rainbow Rd",
    "sg:city":"Mountain City",
    "sg:classifiers":[
        {
            "category":"Professional",
            "type":"Services"
        }
    ],
    "sg:phone":"+1 615 727 8868",
    "sg:postcode":"37683",
    "sg:province":"TN",
    "wof:name":"421 Greenhouse",
    "wof:placetype":"venue"
},
  "geometry": {"coordinates":[-81.799986,36.445192],"type":"Point"}
}