{
  "type": "Feature",
  "properties": {
    "iso:country":"US",
    "sg:address":"2603 Jefferson St",
    "sg:city":"Nashville",
    "sg:classifiers":[
        {
            "category":"Professional",
            "subcategory":"Engineering",
            "type":"Services"
        }
    ],
    "sg:phone":"+1 615 320 5667",
    "sg:postcode":"37208",
    "sg:province":"TN",
    "sg:tags":[
        "engineer"
    ],
    "wof:name":"Engineering Consultants Svc",
    "wof:placetype":"venue"
},
  "geometry": {"coordinates":[-86.816883,36.168053],"type":"Point"}
}