{
  "type": "Feature",
  "properties": {
    "addr:full":"1493 Sneed Rd W Franklin TN 37069",
    "addr:housenumber":"1493",
    "addr:postcode":"37069",
    "addr:street":"Sneed Rd W",
    "iso:country":"US",
    "sg:address":"1493 Sneed Rd W",
    "sg:city":"Franklin",
    "sg:classifiers":[
        {
            "category":"Utilities",
            "subcategory":"Refuse",
            "type":"Services"
        }
    ],
    "sg:phone":"+1 615 371 1697",
    "sg:postcode":"37069",
    "sg:province":"TN",
    "sg:tags":[
        "system"
    ],
    "wof:name":"County of Williamson",
    "wof:placetype":"venue"
},
  "geometry": {"coordinates":[-86.891194,36.024707],"type":"Point"}
}