{
  "type": "Feature",
  "properties": {
    "iso:country":"US",
    "sg:address":"2176 West St",
    "sg:city":"Germantown",
    "sg:classifiers":[
        {
            "category":"Banks & Credit Unions",
            "subcategory":"Bank",
            "type":"Services"
        }
    ],
    "sg:phone":"+1 901 312 4025",
    "sg:postcode":"38138",
    "sg:province":"TN",
    "wof:name":"Renasant Bank",
    "wof:placetype":"venue"
},
  "geometry": {"coordinates":[-89.811474,35.089741],"type":"Point"}
}