{
  "type": "Feature",
  "properties": {
    "iso:country":"US",
    "sg:address":"822 E Commerce St",
    "sg:city":"Lewisburg",
    "sg:classifiers":[
        {
            "category":"Government",
            "subcategory":"Office",
            "type":"Public Place"
        }
    ],
    "sg:phone":"+1 931 270 2228",
    "sg:postcode":"37091",
    "sg:province":"TN",
    "sg:tags":[
        "state",
        "security"
    ],
    "wof:name":"National Guard Armory",
    "wof:placetype":"venue"
},
  "geometry": {"coordinates":[-86.772678,35.444883],"type":"Point"}
}