{
  "type": "Feature",
  "properties": {
    "addr:full":"607 Blevins Ave Elizabethton TN 37643",
    "addr:housenumber":"607",
    "addr:postcode":"37643",
    "addr:street":"Blevins Ave",
    "iso:country":"US",
    "sg:address":"607 Blevins Ave",
    "sg:city":"Elizabethton",
    "sg:classifiers":[
        {
            "category":"Shopping",
            "subcategory":"Discount & Variety Stores",
            "type":"Retail Goods"
        }
    ],
    "sg:phone":"+1 423 547 3224",
    "sg:postcode":"37643",
    "sg:province":"TN",
    "sg:tags":[
        "merchandise",
        "general"
    ],
    "wof:name":"D&D General Store",
    "wof:placetype":"venue"
},
  "geometry": {"coordinates":[-82.22358199999999,36.341162],"type":"Point"}
}