{
  "type": "Feature",
  "properties": {
    "addr:full":"5984 W Andrew Johnson Hwy Morristown TN 37814",
    "addr:housenumber":"5984",
    "addr:postcode":"37814",
    "addr:street":"W Andrew Johnson Hwy",
    "iso:country":"US",
    "sg:address":"5984 W Andrew Johnson Hwy",
    "sg:city":"Morristown",
    "sg:classifiers":[
        {
            "category":"Travel",
            "subcategory":"Hotels & Motels",
            "type":"Entertainment"
        }
    ],
    "sg:phone":"+1 423 586 4666",
    "sg:postcode":"37814",
    "sg:province":"TN",
    "sg:tags":[
        "operation"
    ],
    "wof:name":"Motel 6",
    "wof:placetype":"venue"
},
  "geometry": {"coordinates":[-83.392989,36.178699],"type":"Point"}
}