{
  "type": "Feature",
  "properties": {
    "iso:country":"US",
    "sg:address":"5532 Old Hickory Blvd",
    "sg:city":"Hermitage",
    "sg:classifiers":[
        {
            "category":"Restaurant",
            "type":"Food & Drink"
        }
    ],
    "sg:phone":"+1 615 885 2363",
    "sg:postcode":"37076",
    "sg:province":"TN",
    "sg:tags":[
        "eating"
    ],
    "wof:name":"Royal Thai Restaurant",
    "wof:placetype":"venue"
},
  "geometry": {"coordinates":[-86.60609599999999,36.179867],"type":"Point"}
}