{
  "type": "Feature",
  "properties": {
    "addr:full":"20479 Alberta St Oneida TN 37841",
    "addr:housenumber":"20479",
    "addr:postcode":"37841",
    "addr:street":"Alberta St",
    "iso:country":"US",
    "sg:address":"20479 Alberta St",
    "sg:city":"Oneida",
    "sg:classifiers":[
        {
            "category":"Autos & Motor Vehicles",
            "subcategory":"Auto Supplies",
            "type":"Retail Goods"
        }
    ],
    "sg:phone":"+1 423 569 2228",
    "sg:postcode":"37841",
    "sg:province":"TN",
    "sg:tags":[
        "parts",
        "accessory"
    ],
    "wof:name":"Autozone",
    "wof:placetype":"venue"
},
  "geometry": {"coordinates":[-84.496993,36.524495],"type":"Point"}
}