{
  "type": "Feature",
  "properties": {
    "iso:country":"US",
    "sg:address":"303 W Main St",
    "sg:city":"Mountain City",
    "sg:classifiers":[
        {
            "category":"Professional",
            "subcategory":"Lawyer & Legal Services",
            "type":"Services"
        }
    ],
    "sg:phone":"+1 423 727 7691",
    "sg:postcode":"37683",
    "sg:province":"TN",
    "wof:name":"Johnson K D Attorney At Law",
    "wof:placetype":"venue"
},
  "geometry": {"coordinates":[-81.807845,36.475466],"type":"Point"}
}