{
  "type": "Feature",
  "properties": {
    "iso:country":"US",
    "sg:address":"2213 NW Broad St",
    "sg:city":"Murfreesboro",
    "sg:classifiers":[
        {
            "category":"Building & Trades",
            "subcategory":"Construction",
            "type":"Services"
        }
    ],
    "sg:phone":"+1 615 217 8838",
    "sg:postcode":"37129",
    "sg:province":"TN",
    "sg:tags":[
        "roofing",
        "contractor"
    ],
    "wof:name":"Garner's General Contracting",
    "wof:placetype":"venue"
},
  "geometry": {"coordinates":[-86.40869499999999,35.863056],"type":"Point"}
}