{
  "type": "Feature",
  "properties": {
    "addr:full":"4776 Bowfield Dr Antioch TN 37013",
    "addr:housenumber":"4776",
    "addr:postcode":"37013",
    "addr:street":"Bowfield Dr",
    "iso:country":"US",
    "sg:address":"4776 Bowfield Dr",
    "sg:city":"Antioch",
    "sg:classifiers":[
        {
            "category":"Shopping",
            "subcategory":"Florist",
            "type":"Retail Goods"
        }
    ],
    "sg:phone":"+1 615 243 0992",
    "sg:postcode":"37013",
    "sg:province":"TN",
    "wof:name":"Designs By Logos",
    "wof:placetype":"venue"
},
  "geometry": {"coordinates":[-86.66689,36.063471],"type":"Point"}
}