{
  "type": "Feature",
  "properties": {
    "addr:full":"1975 Bobbitt Rd Williston TN 38076",
    "addr:housenumber":"1975",
    "addr:postcode":"38076",
    "addr:street":"Bobbitt Rd",
    "iso:country":"US",
    "sg:address":"1975 Bobbitt Rd",
    "sg:city":"Williston",
    "sg:classifiers":[
        {
            "category":"Building & Trades",
            "subcategory":"Construction",
            "type":"Services"
        }
    ],
    "sg:phone":"+1 901 465 3982",
    "sg:postcode":"38076",
    "sg:province":"TN",
    "sg:tags":[
        "general",
        "commercial",
        "contractor"
    ],
    "wof:name":"Colonial Painting Renovations",
    "wof:placetype":"venue"
},
  "geometry": {"coordinates":[-89.482889,35.145015],"type":"Point"}
}