{
  "type": "Feature",
  "properties": {
    "iso:country":"US",
    "sg:address":"206 Zelmer Ln",
    "sg:city":"Maryville",
    "sg:classifiers":[
        {
            "category":"Professional",
            "subcategory":"Research",
            "type":"Services"
        }
    ],
    "sg:phone":"+1 865 981 9787",
    "sg:postcode":"37801",
    "sg:province":"TN",
    "wof:name":"Julian Research",
    "wof:placetype":"venue"
},
  "geometry": {"coordinates":[-84.088306,35.69694],"type":"Point"}
}