{
  "type": "Feature",
  "properties": {
    "iso:country":"US",
    "sg:address":"1803 Madison St",
    "sg:city":"Shelbyville",
    "sg:classifiers":[
        {
            "category":"Organizations",
            "subcategory":"Religious Organization",
            "type":"Services"
        }
    ],
    "sg:phone":"+1 931 684 8521",
    "sg:postcode":"37160",
    "sg:province":"TN",
    "sg:tags":[
        "church"
    ],
    "wof:name":"Church Of Christ East Side",
    "wof:placetype":"venue"
},
  "geometry": {"coordinates":[-86.41257400000001,35.482947],"type":"Point"}
}