{
  "type": "Feature",
  "properties": {
    "iso:country":"US",
    "sg:address":"240 Old Dresden Hwy",
    "sg:city":"Paris",
    "sg:classifiers":[
        {
            "category":"Manufacturing",
            "subcategory":"Lumber",
            "type":"Manufacturing & Wholesale Goods"
        }
    ],
    "sg:phone":"+1 731 642 4181",
    "sg:postcode":"38242",
    "sg:province":"TN",
    "wof:name":"Henry County Hardwoods",
    "wof:placetype":"venue"
},
  "geometry": {"coordinates":[-88.37649399999999,36.300727],"type":"Point"}
}