{
  "type": "Feature",
  "properties": {
    "addr:full":"210 W McMurry Blvd Hartsville TN 37074",
    "addr:housenumber":"210",
    "addr:postcode":"37074",
    "addr:street":"W Mcmurry Blvd",
    "iso:country":"US",
    "sg:address":"210 W McMurry Blvd",
    "sg:city":"Hartsville",
    "sg:classifiers":[
        {
            "category":"Shopping",
            "subcategory":"Pharmacy",
            "type":"Retail Goods"
        }
    ],
    "sg:phone":"+1 615 374 2438",
    "sg:postcode":"37074",
    "sg:province":"TN",
    "wof:name":"Rite Aid",
    "wof:placetype":"venue"
},
  "geometry": {"coordinates":[-86.174898,36.402381],"type":"Point"}
}