{
  "type": "Feature",
  "properties": {
    "iso:country":"US",
    "sg:address":"4588 Shell Lane Pl",
    "sg:city":"Memphis",
    "sg:classifiers":[
        {
            "category":"Professional",
            "subcategory":"Accounting & Tax Preparation",
            "type":"Services"
        }
    ],
    "sg:phone":"+1 901 789 0738",
    "sg:postcode":"38109",
    "sg:province":"TN",
    "wof:name":"Miller Booker Miller Acct",
    "wof:placetype":"venue"
},
  "geometry": {"coordinates":[-90.041065,35.02292],"type":"Point"}
}