{
  "type": "Feature",
  "properties": {
    "addr:full":"314 Campbell Ave Tullahoma TN 37388",
    "addr:housenumber":"314",
    "addr:postcode":"37388",
    "addr:street":"Campbell Ave",
    "iso:country":"US",
    "sg:address":"314 Campbell Ave",
    "sg:city":"Tullahoma",
    "sg:classifiers":[
        {
            "category":"Retail",
            "subcategory":"Portrait Studio",
            "type":"Services"
        }
    ],
    "sg:phone":"+1 931 455 6783",
    "sg:postcode":"37388",
    "sg:province":"TN",
    "sg:tags":[
        "photographer"
    ],
    "wof:name":"Ray Cobb Photography",
    "wof:placetype":"venue"
},
  "geometry": {"coordinates":[-86.215165,35.363913],"type":"Point"}
}