{
  "type": "Feature",
  "properties": {
    "iso:country":"US",
    "sg:address":"3242 Players Club Cir",
    "sg:city":"Memphis",
    "sg:classifiers":[
        {
            "category":"Banks & Credit Unions",
            "subcategory":"Bank",
            "type":"Services"
        }
    ],
    "sg:phone":"+1 901 259 9002",
    "sg:postcode":"38125",
    "sg:province":"TN",
    "sg:tags":[
        "loan",
        "real estate"
    ],
    "sg:website":"www.americanhm.com",
    "wof:name":"American Home Mortgage Corp",
    "wof:placetype":"venue"
},
  "geometry": {"coordinates":[-89.790702,35.062976],"type":"Point"}
}