{
  "type": "Feature",
  "properties": {
    "addr:full":"2302 12th Ave S Nashville TN 37204",
    "addr:housenumber":"2302",
    "addr:postcode":"37204",
    "addr:street":"12Th Ave S",
    "iso:country":"US",
    "sg:address":"2302 12th Ave S",
    "sg:city":"Nashville",
    "sg:classifiers":[
        {
            "category":"Professional",
            "type":"Services"
        }
    ],
    "sg:phone":"+1 615 385 0856",
    "sg:postcode":"37204",
    "sg:province":"TN",
    "wof:name":"Savant Vintage Couture",
    "wof:placetype":"venue"
},
  "geometry": {"coordinates":[-86.78913300000001,36.126949],"type":"Point"}
}