{
  "type": "Feature",
  "properties": {
    "addr:full":"1125 West Ave Crossville TN 38555",
    "addr:housenumber":"1125",
    "addr:postcode":"38555",
    "addr:street":"West Ave",
    "iso:country":"US",
    "sg:address":"1125 West Ave",
    "sg:city":"Crossville",
    "sg:classifiers":[
        {
            "category":"Retail",
            "subcategory":"Auto Rental",
            "type":"Services"
        }
    ],
    "sg:phone":"+1 931 484 3411",
    "sg:postcode":"38555",
    "sg:province":"TN",
    "sg:tags":[
        "truck"
    ],
    "wof:name":"Ryder",
    "wof:placetype":"venue"
},
  "geometry": {"coordinates":[-85.040156,35.956814],"type":"Point"}
}