{
  "type": "Feature",
  "properties": {
    "iso:country":"US",
    "sg:address":"135 Starrett St",
    "sg:city":"Sweetwater",
    "sg:classifiers":[
        {
            "category":"Education",
            "subcategory":"School",
            "type":"Public Place"
        }
    ],
    "sg:phone":"+1 423 337 5905",
    "sg:postcode":"37874",
    "sg:province":"TN",
    "wof:name":"Brown Elementary School",
    "wof:placetype":"venue"
},
  "geometry": {"coordinates":[-84.453952,35.597995],"type":"Point"}
}