{
  "type": "Feature",
  "properties": {
    "addr:full":"933 Brushy Valley Rd Heiskell TN 37754",
    "addr:housenumber":"933",
    "addr:postcode":"37754",
    "addr:street":"Brushy Valley Rd",
    "iso:country":"US",
    "sg:address":"933 Brushy Valley Rd",
    "sg:city":"Heiskell",
    "sg:classifiers":[
        {
            "category":"Building & Trades",
            "subcategory":"Landscaping Services",
            "type":"Services"
        }
    ],
    "sg:phone":"+1 865 457 2247",
    "sg:postcode":"37754",
    "sg:province":"TN",
    "sg:tags":[
        "tree"
    ],
    "wof:name":"J R Poore's Tree Svc",
    "wof:placetype":"venue"
},
  "geometry": {"coordinates":[-84.067474,36.124533],"type":"Point"}
}