{
  "type": "Feature",
  "properties": {
    "iso:country":"US",
    "sg:address":"802 Loretta Dr",
    "sg:city":"Goodlettsville",
    "sg:classifiers":[
        {
            "category":"Building & Trades",
            "subcategory":"Construction",
            "type":"Services"
        }
    ],
    "sg:phone":"+1 615 855 3355",
    "sg:postcode":"37072",
    "sg:province":"TN",
    "sg:tags":[
        "contractor"
    ],
    "wof:name":"Extreme Pressure Washing",
    "wof:placetype":"venue"
},
  "geometry": {"coordinates":[-86.709976,36.338948],"type":"Point"}
}