{
  "type": "Feature",
  "properties": {
    "iso:country":"US",
    "sg:address":"114 Warrior Ln",
    "sg:city":"Johnson City",
    "sg:classifiers":[
        {
            "category":"Building & Trades",
            "subcategory":"Construction",
            "type":"Services"
        }
    ],
    "sg:phone":"+1 423 543 3737",
    "sg:postcode":"37601",
    "sg:province":"TN",
    "sg:tags":[
        "brick",
        "stone",
        "block"
    ],
    "wof:name":"J & T Contractors",
    "wof:placetype":"venue"
},
  "geometry": {"coordinates":[-82.288504,36.313164],"type":"Point"}
}