{
  "type": "Feature",
  "properties": {
    "iso:country":"US",
    "sg:address":"118 College St W",
    "sg:city":"Fayetteville",
    "sg:classifiers":[
        {
            "category":"Insurance",
            "subcategory":"Insurance Agent",
            "type":"Services"
        }
    ],
    "sg:phone":"+1 931 433 3059",
    "sg:postcode":"37334",
    "sg:province":"TN",
    "wof:name":"Askew Insurance",
    "wof:placetype":"venue"
},
  "geometry": {"coordinates":[-86.571743,35.152292],"type":"Point"}
}