{
  "type": "Feature",
  "properties": {
    "addr:full":"408 E Cedar St Dickson TN 37055",
    "addr:housenumber":"408",
    "addr:postcode":"37055",
    "addr:street":"E Cedar St",
    "iso:country":"US",
    "sg:address":"408 E Cedar St",
    "sg:city":"Dickson",
    "sg:classifiers":[
        {
            "category":"Professional",
            "type":"Services"
        }
    ],
    "sg:phone":"+1 615 441 2999",
    "sg:postcode":"37055",
    "sg:province":"TN",
    "wof:name":"Bradley Miller",
    "wof:placetype":"venue"
},
  "geometry": {"coordinates":[-87.38155999999999,36.078797],"type":"Point"}
}