{
  "type": "Feature",
  "properties": {
    "iso:country":"US",
    "sg:address":"5535 Murff Ave",
    "sg:city":"Memphis",
    "sg:classifiers":[
        {
            "category":"Transit Center",
            "subcategory":"Freight",
            "type":"Transportation"
        }
    ],
    "sg:phone":"+1 901 682 5361",
    "sg:postcode":"38119",
    "sg:province":"TN",
    "sg:tags":[
        "forwarding"
    ],
    "wof:name":"Bnb International",
    "wof:placetype":"venue"
},
  "geometry": {"coordinates":[-89.877771,35.08665],"type":"Point"}
}