{
  "type": "Feature",
  "properties": {
    "addr:full":"210 Shake Rag Rd Greeneville TN 37743",
    "addr:housenumber":"210",
    "addr:postcode":"37743",
    "addr:street":"Shake Rag Rd",
    "iso:country":"US",
    "sg:address":"210 Shake Rag Rd",
    "sg:city":"Greeneville",
    "sg:classifiers":[
        {
            "category":"Building & Trades",
            "subcategory":"Pest Control",
            "type":"Services"
        }
    ],
    "sg:phone":"+1 423 783 9989",
    "sg:postcode":"37743",
    "sg:province":"TN",
    "wof:name":"Rick's Exterminating Co",
    "wof:placetype":"venue"
},
  "geometry": {"coordinates":[-82.77126,36.090653],"type":"Point"}
}