{
  "type": "Feature",
  "properties": {
    "iso:country":"US",
    "sg:address":"211 Church St",
    "sg:city":"Dickson",
    "sg:classifiers":[
        {
            "category":"Restaurant",
            "type":"Food & Drink"
        }
    ],
    "sg:phone":"+1 615 446 3838",
    "sg:postcode":"37055",
    "sg:province":"TN",
    "sg:tags":[
        "eating"
    ],
    "wof:name":"Cabin Cafe",
    "wof:placetype":"venue"
},
  "geometry": {"coordinates":[-87.38482500000001,36.077655],"type":"Point"}
}