{
  "type": "Feature",
  "properties": {
    "iso:country":"US",
    "sg:address":"29418 8th Ave E",
    "sg:city":"Ardmore",
    "sg:classifiers":[
        {
            "category":"Organizations",
            "subcategory":"Religious Organization",
            "type":"Services"
        }
    ],
    "sg:phone":"+1 256 423 2367",
    "sg:postcode":"35739",
    "sg:province":"AL",
    "wof:name":"Parkview Baptist Church",
    "wof:placetype":"venue"
},
  "geometry": {"coordinates":[-86.83612,34.983413],"type":"Point"}
}