{
  "type": "Feature",
  "properties": {
    "iso:country":"US",
    "sg:address":"585 S Highland St",
    "sg:city":"Memphis",
    "sg:classifiers":[
        {
            "category":"Food & Beverages",
            "subcategory":"Groceries & Convenience Stores",
            "type":"Retail Goods"
        }
    ],
    "sg:phone":"+1 901 327 1883",
    "sg:postcode":"38111",
    "sg:province":"TN",
    "sg:tags":[
        "station",
        "gasoline"
    ],
    "wof:name":"Circle K",
    "wof:placetype":"venue"
},
  "geometry": {"coordinates":[-89.945779,35.116397],"type":"Point"}
}