{
  "type": "Feature",
  "properties": {
    "iso:country":"US",
    "sg:address":"255 Gifford Ln",
    "sg:city":"Hohenwald",
    "sg:classifiers":[
        {
            "category":"Banks & Credit Unions",
            "subcategory":"Financial Services",
            "type":"Services"
        }
    ],
    "sg:phone":"+1 931 796 4222",
    "sg:postcode":"38462",
    "sg:province":"TN",
    "sg:tags":[
        "investor"
    ],
    "wof:name":"LLC Gifford Brothers",
    "wof:placetype":"venue"
},
  "geometry": {"coordinates":[-87.50849700000001,35.499667],"type":"Point"}
}