{
  "type": "Feature",
  "properties": {
    "iso:country":"US",
    "sg:address":"2000 Church St",
    "sg:city":"Nashville",
    "sg:classifiers":[
        {
            "category":"Health Services",
            "subcategory":"Hospital",
            "type":"Services"
        }
    ],
    "sg:phone":"+1 615 284 2229",
    "sg:postcode":"37203",
    "sg:province":"TN",
    "sg:tags":[
        "center",
        "birth"
    ],
    "wof:name":"Baptist Childbirth Ctr",
    "wof:placetype":"venue"
},
  "geometry": {"coordinates":[-86.802683,36.152429],"type":"Point"}
}