{
  "type": "Feature",
  "properties": {
    "addr:full":"3401 W End Ave Nashville TN 37203",
    "addr:housenumber":"3401",
    "addr:postcode":"37203",
    "addr:street":"W End Ave",
    "iso:country":"US",
    "sg:address":"3401 W End Ave",
    "sg:city":"Nashville",
    "sg:classifiers":[
        {
            "category":"Social Services",
            "type":"Services"
        }
    ],
    "sg:phone":"+1 615 292 4327",
    "sg:postcode":"37203",
    "sg:province":"TN",
    "sg:tags":[
        "employee",
        "assistance",
        "program"
    ],
    "sg:website":"www.ohca-eap.com",
    "wof:name":"Horizon Behavioral Svc",
    "wof:placetype":"venue"
},
  "geometry": {"coordinates":[-86.820881,36.137624],"type":"Point"}
}