{
  "type": "Feature",
  "properties": {
    "addr:full":"3109 Midland Fosterville Rd Bell Buckle TN 37020",
    "addr:housenumber":"3109",
    "addr:postcode":"37020",
    "addr:street":"Midland Fosterville Rd",
    "iso:country":"US",
    "sg:address":"3109 Midland Fosterville Rd",
    "sg:city":"Bell Buckle",
    "sg:classifiers":[
        {
            "category":"Organizations",
            "subcategory":"Religious Organization",
            "type":"Services"
        }
    ],
    "sg:phone":"+1 615 233 5424",
    "sg:postcode":"37020",
    "sg:province":"TN",
    "sg:tags":[
        "church"
    ],
    "wof:name":"Midland Baptist Church",
    "wof:placetype":"venue"
},
  "geometry": {"coordinates":[-86.479128,35.669786],"type":"Point"}
}