{
  "type": "Feature",
  "properties": {
    "iso:country":"US",
    "sg:address":"2435 S Bellah Ct",
    "sg:city":"Murfreesboro",
    "sg:classifiers":[
        {
            "category":"Autos & Motor Vehicles",
            "subcategory":"Fuel & Gas Station",
            "type":"Retail Goods"
        }
    ],
    "sg:phone":"+1 615 849 8657",
    "sg:postcode":"37127",
    "sg:province":"TN",
    "sg:tags":[
        "oil"
    ],
    "wof:name":"Murphy Oil USA Inc",
    "wof:placetype":"venue"
},
  "geometry": {"coordinates":[-86.352177,35.802441],"type":"Point"}
}