{
  "type": "Feature",
  "properties": {
    "addr:full":"1224 Columbia Ave Franklin TN 37064",
    "addr:housenumber":"1224",
    "addr:postcode":"37064",
    "addr:street":"Columbia Ave",
    "iso:country":"US",
    "sg:address":"1224 Columbia Ave",
    "sg:city":"Franklin",
    "sg:classifiers":[
        {
            "category":"Professional",
            "subcategory":"Lawyer & Legal Services",
            "type":"Services"
        }
    ],
    "sg:phone":"+1 615 599 6000",
    "sg:postcode":"37064",
    "sg:province":"TN",
    "wof:name":"Judy A Oxford Attorney At Law",
    "wof:placetype":"venue"
},
  "geometry": {"coordinates":[-86.87353899999999,35.91549],"type":"Point"}
}