{
  "type": "Feature",
  "properties": {
    "addr:full":"306 Briar Hollow Rd Hohenwald TN 38462",
    "addr:housenumber":"306",
    "addr:postcode":"38462",
    "addr:street":"Briar Hollow Rd",
    "iso:country":"US",
    "sg:address":"306 Briar Hollow Rd",
    "sg:city":"Hohenwald",
    "sg:classifiers":[
        {
            "category":"Manufacturing",
            "subcategory":"Chemicals & Compounds",
            "type":"Manufacturing & Wholesale Goods"
        }
    ],
    "sg:phone":"+1 931 796 7436",
    "sg:postcode":"38462",
    "sg:province":"TN",
    "sg:tags":[
        "adhesive",
        "only",
        "mfg",
        "for",
        "plastic"
    ],
    "wof:name":"Hebco",
    "wof:placetype":"venue"
},
  "geometry": {"coordinates":[-87.48807600000001,35.569],"type":"Point"}
}