{
  "type": "Feature",
  "properties": {
    "iso:country":"US",
    "sg:address":"3036 Old McKenzie Hwy",
    "sg:city":"Henry",
    "sg:classifiers":[
        {
            "category":"Building & Trades",
            "subcategory":"Construction",
            "type":"Services"
        }
    ],
    "sg:phone":"+1 731 642 8600",
    "sg:postcode":"38231",
    "sg:province":"TN",
    "sg:tags":[
        "clearing",
        "land",
        "contractor"
    ],
    "wof:name":"Pages Dozer & Trackhoe",
    "wof:placetype":"venue"
},
  "geometry": {"coordinates":[-88.345945,36.247225],"type":"Point"}
}