{
  "type": "Feature",
  "properties": {
    "iso:country":"US",
    "sg:address":"4500 Post Rd",
    "sg:city":"Nashville",
    "sg:classifiers":[
        {
            "category":"Health Services",
            "subcategory":"Doctor",
            "type":"Services"
        }
    ],
    "sg:phone":"+1 615 356 4040",
    "sg:postcode":"37205",
    "sg:province":"TN",
    "wof:name":"Dr Robert F Goodrich DDS",
    "wof:placetype":"venue"
},
  "geometry": {"coordinates":[-86.85300599999999,36.126744],"type":"Point"}
}