{
  "type": "Feature",
  "properties": {
    "iso:country":"US",
    "sg:address":"179 Stewarts Ln",
    "sg:city":"Mc Minnville",
    "sg:classifiers":[
        {
            "category":"Manufacturing",
            "subcategory":"Lumber",
            "type":"Manufacturing & Wholesale Goods"
        }
    ],
    "sg:phone":"+1 931 934 2534",
    "sg:postcode":"37110",
    "sg:province":"TN",
    "sg:tags":[
        "farm",
        "nursery",
        "tree"
    ],
    "wof:name":"Stewarts Nursery",
    "wof:placetype":"venue"
},
  "geometry": {"coordinates":[-85.817644,35.78178],"type":"Point"}
}