{
  "type": "Feature",
  "properties": {
    "iso:country":"US",
    "sg:address":"3770 E Shelby Dr",
    "sg:city":"Memphis",
    "sg:classifiers":[
        {
            "category":"Restaurant",
            "type":"Food & Drink"
        }
    ],
    "sg:phone":"+1 901 375 0670",
    "sg:postcode":"38118",
    "sg:province":"TN",
    "sg:tags":[
        "eating"
    ],
    "wof:name":"Mrs Winners Chicken & Biscuits",
    "wof:placetype":"venue"
},
  "geometry": {"coordinates":[-89.938908,35.020664],"type":"Point"}
}