{
  "type": "Feature",
  "properties": {
    "iso:country":"US",
    "sg:address":"3305 Fontaine Rd",
    "sg:city":"Memphis",
    "sg:classifiers":[
        {
            "category":"Professional",
            "subcategory":"Management & Consulting",
            "type":"Services"
        }
    ],
    "sg:phone":"+1 901 396 8883",
    "sg:postcode":"38116",
    "sg:province":"TN",
    "sg:tags":[
        "break",
        "coffee",
        "supply"
    ],
    "wof:name":"S & D Coffee Inc",
    "wof:placetype":"venue"
},
  "geometry": {"coordinates":[-90.01021799999999,35.057307],"type":"Point"}
}