{
  "type": "Feature",
  "properties": {
    "iso:country":"US",
    "sg:address":"1 Park Plz",
    "sg:city":"Nashville",
    "sg:classifiers":[
        {
            "category":"Insurance",
            "subcategory":"Health Insurance",
            "type":"Services"
        }
    ],
    "sg:phone":"+1 615 327 9551",
    "sg:postcode":"37203",
    "sg:province":"TN",
    "wof:name":"Healthcare Tech Assssment Corp",
    "wof:placetype":"venue"
},
  "geometry": {"coordinates":[-86.812145,36.154443],"type":"Point"}
}