{
  "type": "Feature",
  "properties": {
    "addr:full":"221 Fairy Trl Lookout Mountain TN 37350",
    "addr:housenumber":"221",
    "addr:postcode":"37350",
    "addr:street":"Fairy Trl",
    "iso:country":"US",
    "sg:address":"221 Fairy Trl",
    "sg:city":"Lookout Mountain",
    "sg:classifiers":[
        {
            "category":"Professional",
            "subcategory":"Business Services",
            "type":"Services"
        }
    ],
    "sg:phone":"+1 423 821 7260",
    "sg:postcode":"37350",
    "sg:province":"TN",
    "sg:tags":[
        "consulting",
        "management"
    ],
    "wof:name":"Rchard H Lindeman Rsidence Off",
    "wof:placetype":"venue"
},
  "geometry": {"coordinates":[-85.347742,34.984527],"type":"Point"}
}