{
  "type": "Feature",
  "properties": {
    "iso:country":"US",
    "sg:address":"1907 N Roan St",
    "sg:city":"Johnson City",
    "sg:classifiers":[
        {
            "category":"Banks & Credit Unions",
            "subcategory":"Bank",
            "type":"Services"
        }
    ],
    "sg:phone":"+1 423 926 3300",
    "sg:postcode":"37601",
    "sg:province":"TN",
    "sg:website":"www.stateoffranklin.com",
    "wof:name":"State Of Franklin Savings Bank",
    "wof:placetype":"venue"
},
  "geometry": {"coordinates":[-82.374561,36.33976],"type":"Point"}
}