{
  "type": "Feature",
  "properties": {
    "iso:country":"US",
    "sg:address":"8608 Eagle Pointe Dr",
    "sg:city":"Knoxville",
    "sg:classifiers":[
        {
            "category":"Real Estate",
            "subcategory":"Real Estate Operator",
            "type":"Services"
        }
    ],
    "sg:phone":"+1 865 691 1407",
    "sg:postcode":"37931",
    "sg:province":"TN",
    "sg:tags":[
        "apartment"
    ],
    "sg:website":"www.knoxvilleapartments.com",
    "wof:name":"Courtyards",
    "wof:placetype":"venue"
},
  "geometry": {"coordinates":[-84.068726,35.946899],"type":"Point"}
}