{
  "type": "Feature",
  "properties": {
    "iso:country":"US",
    "sg:address":"1299 S Lauderdale St",
    "sg:city":"Memphis",
    "sg:classifiers":[
        {
            "category":"Real Estate",
            "subcategory":"Real Estate Operator",
            "type":"Services"
        }
    ],
    "sg:phone":"+1 901 948 0333",
    "sg:postcode":"38106",
    "sg:province":"TN",
    "sg:tags":[
        "apartment"
    ],
    "wof:name":"Lauderdale Oaks Apartments",
    "wof:placetype":"venue"
},
  "geometry": {"coordinates":[-90.043656,35.111777],"type":"Point"}
}