{
  "type": "Feature",
  "properties": {
    "iso:country":"US",
    "sg:address":"5655 Normandy Pl",
    "sg:city":"Memphis",
    "sg:classifiers":[
        {
            "category":"Professional",
            "subcategory":"Management & Consulting",
            "type":"Services"
        }
    ],
    "sg:phone":"+1 901 683 0214",
    "sg:postcode":"38120",
    "sg:province":"TN",
    "sg:tags":[
        "public",
        "relations"
    ],
    "wof:name":"Good Choice Productions",
    "wof:placetype":"venue"
},
  "geometry": {"coordinates":[-89.87362899999999,35.132944],"type":"Point"}
}