{
  "type": "Feature",
  "properties": {
    "iso:country":"US",
    "sg:address":"2555 Delmead Cove",
    "sg:city":"Germantown",
    "sg:classifiers":[
        {
            "category":"Real Estate",
            "subcategory":"Real Estate Operator",
            "type":"Services"
        }
    ],
    "sg:phone":"+1 901 758 2475",
    "sg:postcode":"38139",
    "sg:province":"TN",
    "sg:tags":[
        "property",
        "lessor"
    ],
    "wof:name":"Shelby Properties",
    "wof:placetype":"venue"
},
  "geometry": {"coordinates":[-89.74734599999999,35.079045],"type":"Point"}
}