{
  "type": "Feature",
  "properties": {
    "iso:country":"US",
    "sg:address":"1245 Dickerson Rd",
    "sg:city":"Goodlettsville",
    "sg:classifiers":[
        {
            "category":"Social Services",
            "type":"Services"
        }
    ],
    "sg:phone":"+1 615 851 6935",
    "sg:postcode":"37072",
    "sg:province":"TN",
    "sg:tags":[
        "organization",
        "welfare"
    ],
    "wof:name":"YMCA",
    "wof:placetype":"venue"
},
  "geometry": {"coordinates":[-86.734165,36.292252],"type":"Point"}
}