{
  "type": "Feature",
  "properties": {
    "addr:full":"1410 S Lee Hwy Cleveland TN 37311",
    "addr:housenumber":"1410",
    "addr:postcode":"37311",
    "addr:street":"S Lee Hwy",
    "iso:country":"US",
    "sg:address":"1410 S Lee Hwy",
    "sg:city":"Cleveland",
    "sg:classifiers":[
        {
            "category":"Food & Beverages",
            "subcategory":"Groceries & Convenience Stores",
            "type":"Retail Goods"
        }
    ],
    "sg:phone":"+1 423 472 8962",
    "sg:postcode":"37311",
    "sg:province":"TN",
    "sg:tags":[
        "gasoline"
    ],
    "wof:name":"Texaco",
    "wof:placetype":"venue"
},
  "geometry": {"coordinates":[-84.894943,35.15338],"type":"Point"}
}