{
  "type": "Feature",
  "properties": {
    "iso:country":"US",
    "sg:address":"1704 E Stone Dr",
    "sg:city":"Kingsport",
    "sg:classifiers":[
        {
            "category":"Travel",
            "subcategory":"Hotels & Motels",
            "type":"Entertainment"
        }
    ],
    "sg:phone":"+1 423 245 0286",
    "sg:postcode":"37660",
    "sg:province":"TN",
    "wof:name":"Econo Lodge",
    "wof:placetype":"venue"
},
  "geometry": {"coordinates":[-82.51707399999999,36.54737],"type":"Point"}
}