{
  "type": "Feature",
  "properties": {
    "addr:full":"216 Market St E Fayetteville TN 37334",
    "addr:housenumber":"216",
    "addr:postcode":"37334",
    "addr:street":"Market St E",
    "iso:country":"US",
    "sg:address":"216 Market St E",
    "sg:city":"Fayetteville",
    "sg:classifiers":[
        {
            "category":"Banks & Credit Unions",
            "subcategory":"Bank",
            "type":"Services"
        }
    ],
    "sg:phone":"+1 931 433 8766",
    "sg:postcode":"37334",
    "sg:province":"TN",
    "wof:name":"Bank Of Lincoln County",
    "wof:placetype":"venue"
},
  "geometry": {"coordinates":[-86.569197,35.151214],"type":"Point"}
}