{
  "type": "Feature",
  "properties": {
    "addr:full":"5796 Shelby Oaks Dr Memphis TN 38134",
    "addr:housenumber":"5796",
    "addr:postcode":"38134",
    "addr:street":"Shelby Oaks Dr",
    "iso:country":"US",
    "sg:address":"5796 Shelby Oaks Dr",
    "sg:city":"Memphis",
    "sg:classifiers":[
        {
            "category":"Organizations",
            "subcategory":"Non-profit Organization",
            "type":"Services"
        }
    ],
    "sg:phone":"+1 901 382 7300",
    "sg:postcode":"38134",
    "sg:province":"TN",
    "sg:tags":[
        "fund",
        "counselor",
        "raising"
    ],
    "sg:website":"www.uptildawn.org",
    "wof:name":"St Jude Children's Hospital",
    "wof:placetype":"venue"
},
  "geometry": {"coordinates":[-89.874279,35.162421],"type":"Point"}
}