{
  "type": "Feature",
  "properties": {
    "iso:country":"US",
    "sg:address":"3021 Kinwood Dr",
    "sg:city":"Antioch",
    "sg:classifiers":[
        {
            "category":"Building & Trades",
            "subcategory":"Cleaning & Sanitation",
            "type":"Services"
        }
    ],
    "sg:phone":"+1 615 361 6918",
    "sg:postcode":"37013",
    "sg:province":"TN",
    "sg:tags":[
        "maintenance"
    ],
    "wof:name":"Bros Cleaning Svc",
    "wof:placetype":"venue"
},
  "geometry": {"coordinates":[-86.625776,36.0696],"type":"Point"}
}