{
  "type": "Feature",
  "properties": {
    "iso:country":"US",
    "sg:address":"1820 N Eastman Rd",
    "sg:city":"Kingsport",
    "sg:classifiers":[
        {
            "category":"Professional",
            "subcategory":"Management & Consulting",
            "type":"Services"
        }
    ],
    "sg:phone":"+1 423 247 9181",
    "sg:postcode":"37664",
    "sg:province":"TN",
    "sg:tags":[
        "break",
        "coffee",
        "supply"
    ],
    "wof:name":"Palace Vending & Coffee Svc",
    "wof:placetype":"venue"
},
  "geometry": {"coordinates":[-82.52030600000001,36.541998],"type":"Point"}
}