{
  "type": "Feature",
  "properties": {
    "iso:country":"US",
    "sg:address":"4056 Elizabeth Dr",
    "sg:city":"Hermitage",
    "sg:classifiers":[
        {
            "category":"Professional",
            "type":"Services"
        }
    ],
    "sg:phone":"+1 615 414 5928",
    "sg:postcode":"37076",
    "sg:province":"TN",
    "wof:name":"Advanced Surgical Specialist",
    "wof:placetype":"venue"
},
  "geometry": {"coordinates":[-86.516384,36.115065],"type":"Point"}
}