{
  "type": "Feature",
  "properties": {
    "iso:country":"US",
    "sg:address":"3818 S Grundy Quarles Hwy",
    "sg:city":"Gainesboro",
    "sg:classifiers":[
        {
            "category":"Home & Garden",
            "subcategory":"Furniture",
            "type":"Retail Goods"
        }
    ],
    "sg:phone":"+1 931 268 2136",
    "sg:postcode":"38562",
    "sg:province":"TN",
    "sg:tags":[
        "household",
        "appliance"
    ],
    "wof:name":"Quality Furniture",
    "wof:placetype":"venue"
},
  "geometry": {"coordinates":[-85.612684,36.264268],"type":"Point"}
}