{
  "type": "Feature",
  "properties": {
    "iso:country":"US",
    "sg:address":"1913 Poplar Ave",
    "sg:city":"Memphis",
    "sg:classifiers":[
        {
            "category":"Organizations",
            "subcategory":"Community Association",
            "type":"Services"
        }
    ],
    "sg:phone":"+1 901 278 8663",
    "sg:postcode":"38104",
    "sg:province":"TN",
    "sg:tags":[
        "drinking"
    ],
    "wof:name":"HI Tone Cafe",
    "wof:placetype":"venue"
},
  "geometry": {"coordinates":[-89.99696900000001,35.142313],"type":"Point"}
}