{
  "type": "Feature",
  "properties": {
    "addr:full":"201 S Illinois Ave Oak Ridge TN 37830",
    "addr:housenumber":"201",
    "addr:postcode":"37830",
    "addr:street":"S Illinois Ave",
    "iso:country":"US",
    "sg:address":"201 S Illinois Ave",
    "sg:city":"Oak Ridge",
    "sg:classifiers":[
        {
            "category":"Banks & Credit Unions",
            "subcategory":"Bank",
            "type":"Services"
        }
    ],
    "sg:phone":"+1 865 482 0045",
    "sg:postcode":"37830",
    "sg:province":"TN",
    "sg:website":"www.k25fcu.org",
    "wof:name":"K-25 Federal Credit Union",
    "wof:placetype":"venue"
},
  "geometry": {"coordinates":[-84.263739,36.007985],"type":"Point"}
}