{
  "type": "Feature",
  "properties": {
    "addr:full":"298 W Broad St Dyer TN 38330",
    "addr:housenumber":"298",
    "addr:postcode":"38330",
    "addr:street":"W Broad St",
    "iso:country":"US",
    "sg:address":"298 W Broad St",
    "sg:city":"Dyer",
    "sg:classifiers":[
        {
            "category":"Food & Beverages",
            "subcategory":"Meat & Fish",
            "type":"Retail Goods"
        }
    ],
    "sg:phone":"+1 731 692 3049",
    "sg:postcode":"38330",
    "sg:province":"TN",
    "wof:name":"Choice Cut Meats & Deli",
    "wof:placetype":"venue"
},
  "geometry": {"coordinates":[-89.001859,36.067792],"type":"Point"}
}