{
  "type": "Feature",
  "properties": {
    "iso:country":"US",
    "sg:address":"122 Browns Ln",
    "sg:city":"Loretto",
    "sg:classifiers":[
        {
            "category":"Professional",
            "subcategory":"Business Services",
            "type":"Services"
        }
    ],
    "sg:phone":"+1 931 853 4344",
    "sg:postcode":"38469",
    "sg:province":"TN",
    "wof:name":"Data-Med Services",
    "wof:placetype":"venue"
},
  "geometry": {"coordinates":[-87.422596,35.078351],"type":"Point"}
}