{
  "type": "Feature",
  "properties": {
    "addr:full":"6631 Poplar Pike Memphis TN 38119",
    "addr:housenumber":"6631",
    "addr:postcode":"38119",
    "addr:street":"Poplar Pike",
    "iso:country":"US",
    "sg:address":"6631 Poplar Pike",
    "sg:city":"Memphis",
    "sg:classifiers":[
        {
            "category":"Shopping",
            "type":"Retail Goods"
        }
    ],
    "sg:phone":"+1 901 755 9348",
    "sg:postcode":"38119",
    "sg:province":"TN",
    "sg:tags":[
        "merchandise"
    ],
    "wof:name":"Realworld A/V Sales",
    "wof:placetype":"venue"
},
  "geometry": {"coordinates":[-89.84093900000001,35.095937],"type":"Point"}
}