{
  "type": "Feature",
  "properties": {
    "iso:country":"US",
    "sg:address":"1517 Braebury Cir",
    "sg:city":"Nashville",
    "sg:classifiers":[
        {
            "category":"Professional",
            "type":"Services"
        }
    ],
    "sg:phone":"+1 615 445 8885",
    "sg:postcode":"37211",
    "sg:province":"TN",
    "sg:tags":[
        "establishment"
    ],
    "wof:name":"Donald King Perkins Eastman",
    "wof:placetype":"venue"
},
  "geometry": {"coordinates":[-86.739591,36.018518],"type":"Point"}
}