{
  "type": "Feature",
  "properties": {
    "iso:country":"US",
    "sg:address":"733 Georgetown Dr",
    "sg:city":"Nashville",
    "sg:classifiers":[
        {
            "category":"Professional",
            "subcategory":"Business Services",
            "type":"Services"
        }
    ],
    "sg:phone":"+1 615 356 4407",
    "sg:postcode":"37205",
    "sg:province":"TN",
    "sg:tags":[
        "interior",
        "design"
    ],
    "wof:name":"Starbuck Designers Inc",
    "wof:placetype":"venue"
},
  "geometry": {"coordinates":[-86.888768,36.119781],"type":"Point"}
}