{
  "type": "Feature",
  "properties": {
    "addr:full":"1692 Eva Rd Camden TN 38320",
    "addr:housenumber":"1692",
    "addr:postcode":"38320",
    "addr:street":"Eva Rd",
    "iso:country":"US",
    "sg:address":"1692 Eva Rd",
    "sg:city":"Camden",
    "sg:classifiers":[
        {
            "category":"Utilities",
            "subcategory":"Cable",
            "type":"Services"
        }
    ],
    "sg:phone":"+1 731 584 2941",
    "sg:postcode":"38320",
    "sg:province":"TN",
    "sg:tags":[
        "television"
    ],
    "wof:name":"Benton County Cablevision",
    "wof:placetype":"venue"
},
  "geometry": {"coordinates":[-88.06501900000001,36.057678],"type":"Point"}
}