{
  "type": "Feature",
  "properties": {
    "addr:full":"211 S College St Trenton TN 38382",
    "addr:housenumber":"211",
    "addr:postcode":"38382",
    "addr:street":"S College St",
    "iso:country":"US",
    "sg:address":"211 S College St",
    "sg:city":"Trenton",
    "sg:classifiers":[
        {
            "category":"Banks & Credit Unions",
            "subcategory":"Bank",
            "type":"Services"
        }
    ],
    "sg:phone":"+1 731 855 2011",
    "sg:postcode":"38382",
    "sg:province":"TN",
    "wof:name":"Security Bank",
    "wof:placetype":"venue"
},
  "geometry": {"coordinates":[-88.941639,35.979692],"type":"Point"}
}