{
  "type": "Feature",
  "properties": {
    "iso:country":"US",
    "sg:address":"256 Seaboard Ln",
    "sg:city":"Franklin",
    "sg:classifiers":[
        {
            "category":"Banks & Credit Unions",
            "subcategory":"Bank",
            "type":"Services"
        }
    ],
    "sg:phone":"+1 615 591 2248",
    "sg:postcode":"37067",
    "sg:province":"TN",
    "sg:website":"www.cfbk.com",
    "wof:name":"Community First Bank & Trust",
    "wof:placetype":"venue"
},
  "geometry": {"coordinates":[-86.82586999999999,35.955236],"type":"Point"}
}