{
  "type": "Feature",
  "properties": {
    "addr:full":"713 Pine Valley Rd Knoxville TN 37923",
    "addr:housenumber":"713",
    "addr:postcode":"37923",
    "addr:street":"Pine Valley Rd",
    "iso:country":"US",
    "sg:address":"713 Pine Valley Rd",
    "sg:city":"Knoxville",
    "sg:classifiers":[
        {
            "category":"Professional",
            "subcategory":"Research",
            "type":"Services"
        }
    ],
    "sg:phone":"+1 865 694 8677",
    "sg:postcode":"37923",
    "sg:province":"TN",
    "sg:tags":[
        "nonphysical",
        "commercial"
    ],
    "wof:name":"Amick Research",
    "wof:placetype":"venue"
},
  "geometry": {"coordinates":[-84.059364,35.90189],"type":"Point"}
}