{
  "type": "Feature",
  "properties": {
    "iso:country":"US",
    "sg:address":"222 3rd Ave N",
    "sg:city":"Nashville",
    "sg:classifiers":[
        {
            "category":"Government",
            "subcategory":"Office",
            "type":"Public Place"
        }
    ],
    "sg:phone":"+1 615 862 6380",
    "sg:postcode":"37201",
    "sg:province":"TN",
    "sg:website":"www.nashville.org",
    "wof:name":"Metro Law Dept",
    "wof:placetype":"venue"
},
  "geometry": {"coordinates":[-86.777051,36.16326],"type":"Point"}
}