{
  "type": "Feature",
  "properties": {
    "addr:full":"3174 Wears Valley Rd Sevierville TN 37862",
    "addr:housenumber":"3174",
    "addr:postcode":"37862",
    "addr:street":"Wears Valley Rd",
    "iso:country":"US",
    "sg:address":"3174 Wears Valley Rd",
    "sg:city":"Sevierville",
    "sg:classifiers":[
        {
            "category":"Real Estate",
            "subcategory":"Real Estate Agent",
            "type":"Services"
        }
    ],
    "sg:phone":"+1 865 428 0345",
    "sg:postcode":"37862",
    "sg:province":"TN",
    "wof:name":"Charles A McGinnis",
    "wof:placetype":"venue"
},
  "geometry": {"coordinates":[-83.63611899999999,35.726407],"type":"Point"}
}