{
  "type": "Feature",
  "properties": {
    "iso:country":"US",
    "sg:address":"1130 US Hwy 51 Bus",
    "sg:city":"Dyersburg",
    "sg:classifiers":[
        {
            "category":"Banks & Credit Unions",
            "subcategory":"Bank",
            "type":"Services"
        }
    ],
    "sg:phone":"+1 731 287 7646",
    "sg:postcode":"38024",
    "sg:province":"TN",
    "sg:tags":[
        "loan"
    ],
    "wof:name":"Finance & Mortgage Acceptance",
    "wof:placetype":"venue"
},
  "geometry": {"coordinates":[-89.394834,36.012664],"type":"Point"}
}