{
  "type": "Feature",
  "properties": {
    "iso:country":"US",
    "sg:address":"5421 Cedar Heights Dr",
    "sg:city":"Knoxville",
    "sg:classifiers":[
        {
            "category":"Retail",
            "subcategory":"Auto Repair",
            "type":"Services"
        }
    ],
    "sg:phone":"+1 865 689 3455",
    "sg:postcode":"37912",
    "sg:province":"TN",
    "sg:tags":[
        "body"
    ],
    "wof:name":"Airbag Service",
    "wof:placetype":"venue"
},
  "geometry": {"coordinates":[-83.963628,36.025203],"type":"Point"}
}