{
  "type": "Feature",
  "properties": {
    "iso:country":"US",
    "sg:address":"7425 Commons Blvd",
    "sg:city":"Chattanooga",
    "sg:classifiers":[
        {
            "category":"Personal",
            "subcategory":"Beauty Salon",
            "type":"Services"
        }
    ],
    "sg:phone":"+1 423 648 4888",
    "sg:postcode":"37421",
    "sg:province":"TN",
    "sg:website":"www.sportclips.com",
    "wof:name":"Sport Clips",
    "wof:placetype":"venue"
},
  "geometry": {"coordinates":[-85.15025300000001,35.036298],"type":"Point"}
}