{
  "type": "Feature",
  "properties": {
    "iso:country":"US",
    "sg:address":"246 W Main St",
    "sg:city":"Johnson City",
    "sg:classifiers":[
        {
            "category":"Organizations",
            "subcategory":"Religious Organization",
            "type":"Services"
        }
    ],
    "sg:phone":"+1 423 929 0905",
    "sg:postcode":"37604",
    "sg:province":"TN",
    "wof:name":"Loaves & Fishes Ministries",
    "wof:placetype":"venue"
},
  "geometry": {"coordinates":[-82.359664,36.316556],"type":"Point"}
}