{
  "type": "Feature",
  "properties": {
    "iso:country":"US",
    "sg:address":"1496 Coleman Rd",
    "sg:city":"Franklin",
    "sg:classifiers":[
        {
            "category":"Wholesale",
            "subcategory":"Home Furnishings",
            "type":"Manufacturing & Wholesale Goods"
        }
    ],
    "sg:phone":"+1 615 207 5597",
    "sg:postcode":"37064",
    "sg:province":"TN",
    "wof:name":"Jch & Associates",
    "wof:placetype":"venue"
},
  "geometry": {"coordinates":[-86.927215,35.875834],"type":"Point"}
}