{
  "type": "Feature",
  "properties": {
    "iso:country":"US",
    "sg:address":"4396 Shadowline Cv",
    "sg:city":"Memphis",
    "sg:classifiers":[
        {
            "category":"Social Services",
            "subcategory":"Job Training",
            "type":"Services"
        },
        {
            "category":"Education",
            "subcategory":"Vocational School",
            "type":"Public Place"
        },
        {
            "category":"Professional",
            "subcategory":"Computer Services",
            "type":"Services"
        }
    ],
    "sg:phone":"+1 901 789 1272",
    "sg:postcode":"38109",
    "sg:province":"TN",
    "sg:tags":[
        "consultant",
        "designer",
        "employment",
        "system",
        "business"
    ],
    "wof:name":"Wanda J Cole",
    "wof:placetype":"venue"
},
  "geometry": {"coordinates":[-90.10496000000001,35.028811],"type":"Point"}
}