{
  "type": "Feature",
  "properties": {
    "iso:country":"US",
    "sg:address":"2413 Washington Ave",
    "sg:city":"Knoxville",
    "sg:classifiers":[
        {
            "category":"Professional",
            "subcategory":"Art Services",
            "type":"Services"
        }
    ],
    "sg:phone":"+1 865 974 9269",
    "sg:postcode":"37917",
    "sg:province":"TN",
    "sg:tags":[
        "commercial",
        "design"
    ],
    "wof:name":"Chas Law Designs",
    "wof:placetype":"venue"
},
  "geometry": {"coordinates":[-83.900773,35.987079],"type":"Point"}
}