{
  "type": "Feature",
  "properties": {
    "iso:country":"US",
    "sg:address":"3520 Afton Rd",
    "sg:city":"Afton",
    "sg:classifiers":[
        {
            "category":"Building & Trades",
            "subcategory":"Construction",
            "type":"Services"
        }
    ],
    "sg:phone":"+1 423 638 1957",
    "sg:postcode":"37616",
    "sg:province":"TN",
    "sg:tags":[
        "contractor"
    ],
    "wof:name":"S&R Holdings Inc",
    "wof:placetype":"venue"
},
  "geometry": {"coordinates":[-82.745908,36.219576],"type":"Point"}
}