{
  "type": "Feature",
  "properties": {
    "iso:country":"US",
    "sg:address":"4102 Cherryton Dr",
    "sg:city":"Chattanooga",
    "sg:classifiers":[
        {
            "category":"Home & Garden",
            "subcategory":"Building Materials",
            "type":"Retail Goods"
        }
    ],
    "sg:phone":"+1 423 624 4771",
    "sg:postcode":"37411",
    "sg:province":"TN",
    "wof:name":"Glass Of Distinction",
    "wof:placetype":"venue"
},
  "geometry": {"coordinates":[-85.235072,35.019196],"type":"Point"}
}