{
  "type": "Feature",
  "properties": {
    "addr:full":"299 Marie Ln Lynnville TN 38472",
    "addr:housenumber":"299",
    "addr:postcode":"38472",
    "addr:street":"Marie Ln",
    "iso:country":"US",
    "sg:address":"299 Marie Ln",
    "sg:city":"Lynnville",
    "sg:classifiers":[
        {
            "category":"Home & Garden",
            "subcategory":"Furniture",
            "type":"Retail Goods"
        }
    ],
    "sg:phone":"+1 931 527 9899",
    "sg:postcode":"38472",
    "sg:province":"TN",
    "sg:tags":[
        "making",
        "custom",
        "cabinet"
    ],
    "wof:name":"Coblentz Kitchen & Bath",
    "wof:placetype":"venue"
},
  "geometry": {"coordinates":[-86.932149,35.382909],"type":"Point"}
}