{
  "type": "Feature",
  "properties": {
    "iso:country":"US",
    "sg:address":"1485 Guthrie Rd",
    "sg:city":"Paris",
    "sg:classifiers":[
        {
            "category":"Professional",
            "type":"Services"
        }
    ],
    "sg:phone":"+1 731 644 0152",
    "sg:postcode":"38242",
    "sg:province":"TN",
    "wof:name":"William T Kibbler",
    "wof:placetype":"venue"
},
  "geometry": {"coordinates":[-88.30585600000001,36.330231],"type":"Point"}
}