{
  "type": "Feature",
  "properties": {
    "addr:full":"100 Netherland Ln Kingsport TN 37660",
    "addr:housenumber":"100",
    "addr:postcode":"37660",
    "addr:street":"Netherland Ln",
    "iso:country":"US",
    "sg:address":"100 Netherland Ln",
    "sg:city":"Kingsport",
    "sg:classifiers":[
        {
            "category":"Health Services",
            "subcategory":"Clinic",
            "type":"Services"
        }
    ],
    "sg:phone":"+1 423 230 0008",
    "sg:postcode":"37660",
    "sg:province":"TN",
    "sg:tags":[
        "specialty",
        "outpatient"
    ],
    "wof:name":"Functional Pathways",
    "wof:placetype":"venue"
},
  "geometry": {"coordinates":[-82.61707800000001,36.55367],"type":"Point"}
}