{
  "type": "Feature",
  "properties": {
    "iso:country":"US",
    "sg:address":"217 Pineway Dr",
    "sg:city":"Nashville",
    "sg:classifiers":[
        {
            "category":"Real Estate",
            "subcategory":"Real Estate Agent",
            "type":"Services"
        }
    ],
    "sg:phone":"+1 615 360 8870",
    "sg:postcode":"37217",
    "sg:province":"TN",
    "sg:tags":[
        "loan",
        "broker"
    ],
    "wof:name":"Metropolitan Escrow Inc",
    "wof:placetype":"venue"
},
  "geometry": {"coordinates":[-86.694508,36.114876],"type":"Point"}
}