{
  "type": "Feature",
  "properties": {
    "iso:country":"US",
    "sg:address":"583 S Riverside Dr",
    "sg:city":"Clarksville",
    "sg:classifiers":[
        {
            "category":"Banks & Credit Unions",
            "subcategory":"Bank",
            "type":"Services"
        }
    ],
    "sg:phone":"+1 931 648 3388",
    "sg:postcode":"37040",
    "sg:province":"TN",
    "sg:tags":[
        "loan"
    ],
    "wof:name":"World Acceptance Corp Cllctns",
    "wof:placetype":"venue"
},
  "geometry": {"coordinates":[-87.363243,36.521497],"type":"Point"}
}