{
  "type": "Feature",
  "properties": {
    "iso:country":"US",
    "sg:address":"62 Jackson Hwy",
    "sg:city":"Medina",
    "sg:classifiers":[
        {
            "category":"Wholesale",
            "subcategory":"Machinery & Supplies",
            "type":"Manufacturing & Wholesale Goods"
        }
    ],
    "sg:phone":"+1 731 783 0037",
    "sg:postcode":"38343",
    "sg:province":"TN",
    "sg:tags":[
        "equipment",
        "contractor"
    ],
    "wof:name":"Epperson and Epperson Equipmen",
    "wof:placetype":"venue"
},
  "geometry": {"coordinates":[-88.787606,35.794347],"type":"Point"}
}