{
  "type": "Feature",
  "properties": {
    "iso:country":"US",
    "sg:address":"5361 Trousdale Dr",
    "sg:city":"Nashville",
    "sg:classifiers":[
        {
            "category":"Building & Trades",
            "subcategory":"Cleaning & Sanitation",
            "type":"Services"
        }
    ],
    "sg:phone":"+1 615 371 5355",
    "sg:postcode":"37220",
    "sg:province":"TN",
    "sg:tags":[
        "ventilating",
        "system"
    ],
    "wof:name":"Hvaclean",
    "wof:placetype":"venue"
},
  "geometry": {"coordinates":[-86.75964500000001,36.054645],"type":"Point"}
}