{
  "type": "Feature",
  "properties": {
    "iso:country":"US",
    "sg:address":"201 Cameron Ct",
    "sg:city":"Hermitage",
    "sg:classifiers":[
        {
            "category":"Personal",
            "subcategory":"Beauty Salon",
            "type":"Services"
        }
    ],
    "sg:phone":"+1 615 889 6661",
    "sg:postcode":"37076",
    "sg:province":"TN",
    "wof:name":"Alex's VIP Hair Lounge",
    "wof:placetype":"venue"
},
  "geometry": {"coordinates":[-86.60177299999999,36.225685],"type":"Point"}
}