{
  "type": "Feature",
  "properties": {
    "iso:country":"US",
    "sg:address":"17 Market Sq SW",
    "sg:city":"Knoxville",
    "sg:classifiers":[
        {
            "category":"Government",
            "subcategory":"Office",
            "type":"Public Place"
        }
    ],
    "sg:phone":"+1 865 545 4637",
    "sg:postcode":"37902",
    "sg:province":"TN",
    "sg:tags":[
        "federal",
        "program",
        "adm"
    ],
    "wof:name":"US Commerce Dept",
    "wof:placetype":"venue"
},
  "geometry": {"coordinates":[-83.92037999999999,35.965509],"type":"Point"}
}