{
  "type": "Feature",
  "properties": {
    "iso:country":"US",
    "sg:address":"361 Sweeney Dr",
    "sg:city":"Crossville",
    "sg:classifiers":[
        {
            "category":"Shopping",
            "subcategory":"Clothing, Apparel, & Fashions",
            "type":"Retail Goods"
        }
    ],
    "sg:phone":"+1 931 707 7080",
    "sg:postcode":"38555",
    "sg:province":"TN",
    "sg:tags":[
        "sportswear"
    ],
    "wof:name":"Big Dog Sportswear",
    "wof:placetype":"venue"
},
  "geometry": {"coordinates":[-85.01999,35.984452],"type":"Point"}
}