{
  "type": "Feature",
  "properties": {
    "iso:country":"US",
    "sg:address":"457 Rolen Rd",
    "sg:city":"Sevierville",
    "sg:classifiers":[
        {
            "category":"Professional",
            "subcategory":"Business Services",
            "type":"Services"
        }
    ],
    "sg:phone":"+1 865 453 9220",
    "sg:postcode":"37876",
    "sg:province":"TN",
    "wof:name":"All Phase Sign Co",
    "wof:placetype":"venue"
},
  "geometry": {"coordinates":[-83.46118199999999,35.870504],"type":"Point"}
}