{
  "type": "Feature",
  "properties": {
    "iso:country":"US",
    "sg:address":"1833 Harrisburg Mill Rd",
    "sg:city":"Sevierville",
    "sg:classifiers":[
        {
            "category":"Real Estate",
            "subcategory":"Real Estate Operator",
            "type":"Services"
        }
    ],
    "sg:phone":"+1 865 774 5487",
    "sg:postcode":"37876",
    "sg:province":"TN",
    "sg:tags":[
        "building",
        "nonresidential"
    ],
    "wof:name":"Wf Properties LLC",
    "wof:placetype":"venue"
},
  "geometry": {"coordinates":[-83.487313,35.8599],"type":"Point"}
}