{
  "type": "Feature",
  "properties": {
    "iso:country":"US",
    "sg:address":"2742 Schaad Rd",
    "sg:city":"Knoxville",
    "sg:classifiers":[
        {
            "category":"Restaurant",
            "type":"Food & Drink"
        }
    ],
    "sg:menulink":"http://www.allmenus.com/tn/knoxville/191642-sonic/menu/",
    "sg:phone":"+1 865 947 2845",
    "sg:postcode":"37921",
    "sg:province":"TN",
    "sg:tags":[
        "burger",
        "american"
    ],
    "wof:name":"Sonic",
    "wof:placetype":"venue"
},
  "geometry": {"coordinates":[-84.01927000000001,36.006164],"type":"Point"}
}