{
  "type": "Feature",
  "properties": {
    "iso:country":"US",
    "sg:address":"1708 Sheila Ann Dr",
    "sg:city":"Mount Juliet",
    "sg:classifiers":[
        {
            "category":"Professional",
            "type":"Services"
        }
    ],
    "sg:phone":"+1 615 754 0184",
    "sg:postcode":"37122",
    "sg:province":"TN",
    "wof:name":"Nelson Poplar Music Group",
    "wof:placetype":"venue"
},
  "geometry": {"coordinates":[-86.55161200000001,36.206424],"type":"Point"}
}