{
  "type": "Feature",
  "properties": {
    "iso:country":"US",
    "sg:address":"109 Hazel Path",
    "sg:city":"Hendersonville",
    "sg:classifiers":[
        {
            "category":"Real Estate",
            "subcategory":"Architect",
            "type":"Services"
        }
    ],
    "sg:phone":"+1 615 265 2005",
    "sg:postcode":"37075",
    "sg:province":"TN",
    "wof:name":"TAG Design Svc",
    "wof:placetype":"venue"
},
  "geometry": {"coordinates":[-86.607922,36.306083],"type":"Point"}
}