{
  "type": "Feature",
  "properties": {
    "addr:full":"6960 Lee Hwy Chattanooga TN 37421",
    "addr:housenumber":"6960",
    "addr:postcode":"37421",
    "addr:street":"Lee Hwy",
    "iso:country":"US",
    "sg:address":"6960 Lee Hwy",
    "sg:city":"Chattanooga",
    "sg:classifiers":[
        {
            "category":"Food & Beverages",
            "subcategory":"Groceries & Convenience Stores",
            "type":"Retail Goods"
        }
    ],
    "sg:phone":"+1 423 899 9566",
    "sg:postcode":"37421",
    "sg:province":"TN",
    "sg:tags":[
        "station",
        "gas"
    ],
    "wof:name":"Golden Gallon 82",
    "wof:placetype":"venue"
},
  "geometry": {"coordinates":[-85.16303600000001,35.044397],"type":"Point"}
}