{
  "type": "Feature",
  "properties": {
    "iso:country":"US",
    "sg:address":"1876 Darks Mill Rd",
    "sg:city":"Columbia",
    "sg:classifiers":[
        {
            "category":"Insurance",
            "subcategory":"Hazard Insurance",
            "type":"Services"
        },
        {
            "category":"Professional",
            "subcategory":"Business Services",
            "type":"Services"
        }
    ],
    "sg:phone":"+1 931 490 9799",
    "sg:postcode":"38401",
    "sg:province":"TN",
    "sg:tags":[
        "bond"
    ],
    "wof:name":"ABC Bonding Company Inc",
    "wof:placetype":"venue"
},
  "geometry": {"coordinates":[-87.06211,35.683746],"type":"Point"}
}