{
  "type": "Feature",
  "properties": {
    "iso:country":"US",
    "sg:address":"3012 Eagle Dr",
    "sg:city":"Westmoreland",
    "sg:classifiers":[
        {
            "category":"Professional",
            "subcategory":"Art Services",
            "type":"Services"
        }
    ],
    "sg:phone":"+1 615 644 4433",
    "sg:postcode":"37186",
    "sg:province":"TN",
    "sg:tags":[
        "commercial",
        "design"
    ],
    "wof:name":"Arrowsmith Graphics",
    "wof:placetype":"venue"
},
  "geometry": {"coordinates":[-86.25867,36.564882],"type":"Point"}
}