{
  "type": "Feature",
  "properties": {
    "addr:full":"2409 Oasis Rd Bulls Gap TN 37711",
    "addr:housenumber":"2409",
    "addr:postcode":"37711",
    "addr:street":"Oasis Rd",
    "iso:country":"US",
    "sg:address":"2409 Oasis Rd",
    "sg:city":"Bulls Gap",
    "sg:classifiers":[
        {
            "category":"Shopping",
            "subcategory":"Bicycles & Sporting Goods",
            "type":"Retail Goods"
        }
    ],
    "sg:phone":"+1 423 235 4544",
    "sg:postcode":"37711",
    "sg:province":"TN",
    "wof:name":"Jeffs Sporting Goods",
    "wof:placetype":"venue"
},
  "geometry": {"coordinates":[-83.028229,36.244364],"type":"Point"}
}