{
  "type": "Feature",
  "properties": {
    "iso:country":"US",
    "sg:address":"312 McMaster Pl",
    "sg:city":"Maryville",
    "sg:classifiers":[
        {
            "category":"Social Services",
            "subcategory":"Adult Care",
            "type":"Services"
        }
    ],
    "sg:phone":"+1 865 977 9157",
    "sg:postcode":"37801",
    "sg:province":"TN",
    "sg:tags":[
        "home",
        "residential"
    ],
    "wof:name":"Home Away From Home Inc",
    "wof:placetype":"venue"
},
  "geometry": {"coordinates":[-83.976372,35.75404],"type":"Point"}
}