{
  "type": "Feature",
  "properties": {
    "iso:country":"US",
    "sg:address":"1407 N Locust Ave",
    "sg:city":"Lawrenceburg",
    "sg:classifiers":[
        {
            "category":"Shopping",
            "type":"Retail Goods"
        }
    ],
    "sg:phone":"+1 931 762 3710",
    "sg:postcode":"38464",
    "sg:province":"TN",
    "sg:tags":[
        "hearing",
        "equipment",
        "supply",
        "impaired"
    ],
    "wof:name":"Beltone Hearing Aid Ctr",
    "wof:placetype":"venue"
},
  "geometry": {"coordinates":[-87.32534800000001,35.25633],"type":"Point"}
}