{
  "type": "Feature",
  "properties": {
    "iso:country":"US",
    "sg:address":"312 Franklin St",
    "sg:city":"Clarksville",
    "sg:classifiers":[
        {
            "category":"Professional",
            "subcategory":"Lawyer & Legal Services",
            "type":"Services"
        }
    ],
    "sg:phone":"+1 931 906 0000",
    "sg:postcode":"37040",
    "sg:province":"TN",
    "sg:tags":[
        "attorney"
    ],
    "wof:name":"B Lynn Morton Law Offices",
    "wof:placetype":"venue"
},
  "geometry": {"coordinates":[-87.356711,36.527966],"type":"Point"}
}