{
  "type": "Feature",
  "properties": {
    "addr:full":"118 Public Sq Lebanon TN 37087",
    "addr:housenumber":"118",
    "addr:postcode":"37087",
    "addr:street":"Public Sq",
    "iso:country":"US",
    "sg:address":"118 Public Sq",
    "sg:city":"Lebanon",
    "sg:classifiers":[
        {
            "category":"Professional",
            "subcategory":"Computer Services",
            "type":"Services"
        }
    ],
    "sg:phone":"+1 615 443 3876",
    "sg:postcode":"37087",
    "sg:province":"TN",
    "wof:name":"Dillon It",
    "wof:placetype":"venue"
},
  "geometry": {"coordinates":[-86.29144599999999,36.208009],"type":"Point"}
}