{
  "type": "Feature",
  "properties": {
    "iso:country":"US",
    "sg:address":"2814 W End Ave",
    "sg:city":"Nashville",
    "sg:classifiers":[
        {
            "category":"Banks & Credit Unions",
            "subcategory":"Bank",
            "type":"Services"
        },
        {
            "category":"Banks & Credit Unions",
            "subcategory":"Financial Services",
            "type":"Services"
        }
    ],
    "sg:phone":"+1 615 871 7033",
    "sg:postcode":"37203",
    "sg:province":"TN",
    "sg:tags":[
        "financing",
        "loan"
    ],
    "sg:website":"http://www.SunTrust.com",
    "wof:name":"SunTrust Bank - Centennial Park",
    "wof:placetype":"venue"
},
  "geometry": {"coordinates":[-86.81236199999999,36.145047],"type":"Point"}
}