{
  "type": "Feature",
  "properties": {
    "iso:country":"US",
    "sg:address":"7703 Clapps Chapel Rd",
    "sg:city":"Corryton",
    "sg:classifiers":[
        {
            "category":"Education",
            "subcategory":"Special Training",
            "type":"Public Place"
        }
    ],
    "sg:phone":"+1 865 688 2074",
    "sg:postcode":"37721",
    "sg:province":"TN",
    "sg:tags":[
        "center"
    ],
    "wof:name":"Windy Hill Learning Ctr",
    "wof:placetype":"venue"
},
  "geometry": {"coordinates":[-83.838263,36.13352],"type":"Point"}
}