{
  "type": "Feature",
  "properties": {
    "addr:full":"27 W 19th St Chattanooga TN 37408",
    "addr:housenumber":"27",
    "addr:postcode":"37408",
    "addr:street":"W 19Th St",
    "iso:country":"US",
    "sg:address":"27 W 19th St",
    "sg:city":"Chattanooga",
    "sg:classifiers":[
        {
            "category":"Bars & Pubs",
            "type":"Food & Drink"
        }
    ],
    "sg:phone":"+1 423 634 0480",
    "sg:postcode":"37408",
    "sg:province":"TN",
    "sg:tags":[
        "lounge",
        "cocktail"
    ],
    "wof:name":"Marco's Lounge",
    "wof:placetype":"venue"
},
  "geometry": {"coordinates":[-85.30978899999999,35.033089],"type":"Point"}
}