{
  "type": "Feature",
  "properties": {
    "iso:country":"US",
    "sg:address":"6032 Hollow Springs Rd",
    "sg:city":"Bradyville",
    "sg:classifiers":[
        {
            "category":"Retail",
            "subcategory":"Auto Repair",
            "type":"Services"
        }
    ],
    "sg:phone":"+1 615 765 7736",
    "sg:postcode":"37026",
    "sg:province":"TN",
    "sg:tags":[
        "general"
    ],
    "wof:name":"Mid Tenn R V Service",
    "wof:placetype":"venue"
},
  "geometry": {"coordinates":[-86.112607,35.688334],"type":"Point"}
}