{
  "type": "Feature",
  "properties": {
    "iso:country":"US",
    "sg:address":"716 Lewisburg Hwy",
    "sg:city":"Fayetteville",
    "sg:classifiers":[
        {
            "category":"Personal",
            "type":"Services"
        },
        {
            "category":"Personal",
            "subcategory":"Beauty Salon",
            "type":"Services"
        }
    ],
    "sg:phone":"+1 931 433 8056",
    "sg:postcode":"37334",
    "sg:province":"TN",
    "sg:tags":[
        "shop"
    ],
    "wof:name":"Karmen's Touch Of Beauty",
    "wof:placetype":"venue"
},
  "geometry": {"coordinates":[-86.57705199999999,35.162781],"type":"Point"}
}