{
  "type": "Feature",
  "properties": {
    "addr:full":"319 N Highland Ave Jackson TN 38301",
    "addr:housenumber":"319",
    "addr:postcode":"38301",
    "addr:street":"N Highland Ave",
    "iso:country":"US",
    "sg:address":"319 N Highland Ave",
    "sg:city":"Jackson",
    "sg:classifiers":[
        {
            "category":"Retail",
            "subcategory":"Car Wash",
            "type":"Services"
        }
    ],
    "sg:phone":"+1 731 427 9044",
    "sg:postcode":"38301",
    "sg:province":"TN",
    "sg:tags":[
        "carwash"
    ],
    "wof:name":"J & A Hand Car Wash",
    "wof:placetype":"venue"
},
  "geometry": {"coordinates":[-88.819327,35.620066],"type":"Point"}
}