{
  "type": "Feature",
  "properties": {
    "iso:country":"US",
    "sg:address":"118 Southwood Dr",
    "sg:city":"Dickson",
    "sg:classifiers":[
        {
            "category":"Building & Trades",
            "subcategory":"Cleaning & Sanitation",
            "type":"Services"
        }
    ],
    "sg:phone":"+1 615 446 0644",
    "sg:postcode":"37055",
    "sg:province":"TN",
    "sg:tags":[
        "janitor"
    ],
    "wof:name":"Premier Cleaning Svc",
    "wof:placetype":"venue"
},
  "geometry": {"coordinates":[-87.35418300000001,36.031571],"type":"Point"}
}