{
  "type": "Feature",
  "properties": {
    "iso:country":"US",
    "sg:address":"731 Watkins Rd",
    "sg:city":"Maryville",
    "sg:classifiers":[
        {
            "category":"Professional",
            "type":"Services"
        }
    ],
    "sg:phone":"+1 865 981 9488",
    "sg:postcode":"37801",
    "sg:province":"TN",
    "wof:name":"Gum Drop",
    "wof:placetype":"venue"
},
  "geometry": {"coordinates":[-83.99157200000001,35.750418],"type":"Point"}
}