{
  "type": "Feature",
  "properties": {
    "iso:country":"US",
    "sg:address":"1633 Kimbrough Park Pl",
    "sg:city":"Germantown",
    "sg:classifiers":[
        {
            "category":"Professional",
            "subcategory":"Management & Consulting",
            "type":"Services"
        }
    ],
    "sg:phone":"+1 901 757 4447",
    "sg:postcode":"38138",
    "sg:province":"TN",
    "wof:name":"Berry Financial Services",
    "wof:placetype":"venue"
},
  "geometry": {"coordinates":[-89.79346,35.104402],"type":"Point"}
}