{
  "type": "Feature",
  "properties": {
    "iso:country":"US",
    "sg:address":"1035 1st Ave S",
    "sg:city":"Nashville",
    "sg:classifiers":[
        {
            "category":"Building & Trades",
            "subcategory":"Landscaping Services",
            "type":"Services"
        }
    ],
    "sg:phone":"+1 615 259 8928",
    "sg:postcode":"37210",
    "sg:province":"TN",
    "sg:tags":[
        "lawn",
        "maintenance",
        "grounds"
    ],
    "wof:name":"MTA Lawn Care",
    "wof:placetype":"venue"
},
  "geometry": {"coordinates":[-86.764301,36.147682],"type":"Point"}
}