{
  "type": "Feature",
  "properties": {
    "addr:full":"6939 Dusty Trail Ln Memphis TN 38133",
    "addr:housenumber":"6939",
    "addr:postcode":"38133",
    "addr:street":"Dusty Trail Ln",
    "iso:country":"US",
    "sg:address":"6939 Dusty Trail Ln",
    "sg:city":"Memphis",
    "sg:classifiers":[
        {
            "category":"Real Estate",
            "subcategory":"Real Estate Agent",
            "type":"Services"
        },
        {
            "category":"Real Estate",
            "subcategory":"Real Estate Operator",
            "type":"Services"
        }
    ],
    "sg:phone":"+1 901 382 5723",
    "sg:postcode":"38133",
    "sg:province":"TN",
    "sg:tags":[
        "apartment",
        "management"
    ],
    "wof:name":"The Birches At Countryside",
    "wof:placetype":"venue"
},
  "geometry": {"coordinates":[-89.832094,35.193886],"type":"Point"}
}