{
  "type": "Feature",
  "properties": {
    "iso:country":"US",
    "sg:address":"587 Peterson Lake Rd",
    "sg:city":"Collierville",
    "sg:classifiers":[
        {
            "category":"Professional",
            "subcategory":"Management & Consulting",
            "type":"Services"
        }
    ],
    "sg:phone":"+1 901 854 2015",
    "sg:postcode":"38017",
    "sg:province":"TN",
    "sg:tags":[
        "business"
    ],
    "wof:name":"Ben Doddridge",
    "wof:placetype":"venue"
},
  "geometry": {"coordinates":[-89.66838199999999,35.055398],"type":"Point"}
}