{
  "type": "Feature",
  "properties": {
    "addr:full":"4107 Gallatin Pike Nashville TN 37216",
    "addr:housenumber":"4107",
    "addr:postcode":"37216",
    "addr:street":"Gallatin Pike",
    "iso:country":"US",
    "sg:address":"4107 Gallatin Pike",
    "sg:city":"Nashville",
    "sg:classifiers":[
        {
            "category":"Health Services",
            "subcategory":"Nursing And Care Facility",
            "type":"Services"
        }
    ],
    "sg:phone":"+1 615 228 0356",
    "sg:postcode":"37216",
    "sg:province":"TN",
    "sg:tags":[
        "home",
        "convalescent",
        "centers-adult",
        "day"
    ],
    "sg:website":"www.jacksonparkchristianhome.com",
    "wof:name":"Jackson Park Christian Home",
    "wof:placetype":"venue"
},
  "geometry": {"coordinates":[-86.726601,36.22118],"type":"Point"}
}