{
  "type": "Feature",
  "properties": {
    "addr:full":"216 9th St Clarksville TN 37040",
    "addr:housenumber":"216",
    "addr:postcode":"37040",
    "addr:street":"9Th St",
    "iso:country":"US",
    "sg:address":"216 9th St",
    "sg:city":"Clarksville",
    "sg:classifiers":[
        {
            "category":"Retail",
            "subcategory":"Auto Repair",
            "type":"Services"
        }
    ],
    "sg:phone":"+1 931 648 0145",
    "sg:postcode":"37040",
    "sg:province":"TN",
    "sg:tags":[
        "repairing",
        "automobile",
        "radiator"
    ],
    "wof:name":"D & D Radiator & Air Cond Svc",
    "wof:placetype":"venue"
},
  "geometry": {"coordinates":[-87.347737,36.532439],"type":"Point"}
}