{
  "type": "Feature",
  "properties": {
    "iso:country":"US",
    "sg:address":"7284 Cedar Rd",
    "sg:city":"Memphis",
    "sg:classifiers":[
        {
            "category":"Wholesale",
            "subcategory":"Machinery & Supplies",
            "type":"Manufacturing & Wholesale Goods"
        }
    ],
    "sg:phone":"+1 901 388 0278",
    "sg:postcode":"38135",
    "sg:province":"TN",
    "sg:tags":[
        "equipment",
        "beauty"
    ],
    "wof:name":"Thrifty Beauty Supply",
    "wof:placetype":"venue"
},
  "geometry": {"coordinates":[-89.821907,35.227718],"type":"Point"}
}