{
  "type": "Feature",
  "properties": {
    "addr:full":"1595 Lamar Ave Memphis TN 38114",
    "addr:housenumber":"1595",
    "addr:postcode":"38114",
    "addr:street":"Lamar Ave",
    "iso:country":"US",
    "sg:address":"1595 Lamar Ave",
    "sg:city":"Memphis",
    "sg:classifiers":[
        {
            "category":"Organizations",
            "subcategory":"Religious Organization",
            "type":"Services"
        }
    ],
    "sg:phone":"+1 901 725 9630",
    "sg:postcode":"38114",
    "sg:province":"TN",
    "wof:name":"Eureka Mssionary Baptst Church",
    "wof:placetype":"venue"
},
  "geometry": {"coordinates":[-90.009826,35.122252],"type":"Point"}
}