{
  "type": "Feature",
  "properties": {
    "iso:country":"US",
    "sg:address":"710 S Anderson St",
    "sg:city":"Tullahoma",
    "sg:classifiers":[
        {
            "category":"Shopping",
            "subcategory":"Bicycles & Sporting Goods",
            "type":"Retail Goods"
        }
    ],
    "sg:phone":"+1 931 455 0354",
    "sg:postcode":"37388",
    "sg:province":"TN",
    "wof:name":"Sportsman Store",
    "wof:placetype":"venue"
},
  "geometry": {"coordinates":[-86.199113,35.358637],"type":"Point"}
}