{
  "type": "Feature",
  "properties": {
    "iso:country":"US",
    "sg:address":"3600 Keith St",
    "sg:city":"Cleveland",
    "sg:classifiers":[
        {
            "category":"Professional",
            "type":"Services"
        }
    ],
    "sg:phone":"+1 423 472 9250",
    "sg:postcode":"37312",
    "sg:province":"TN",
    "sg:tags":[
        "establishment"
    ],
    "wof:name":"Aleeco LLC",
    "wof:placetype":"venue"
},
  "geometry": {"coordinates":[-84.863247,35.191337],"type":"Point"}
}