{
  "type": "Feature",
  "properties": {
    "iso:country":"US",
    "sg:address":"123 McIntosh Dr",
    "sg:city":"Jackson",
    "sg:classifiers":[
        {
            "category":"Building & Trades",
            "subcategory":"Construction",
            "type":"Services"
        }
    ],
    "sg:phone":"+1 731 928 9227",
    "sg:postcode":"38305",
    "sg:province":"TN",
    "sg:tags":[
        "hanging",
        "contractor"
    ],
    "wof:name":"Marshall Lancaster",
    "wof:placetype":"venue"
},
  "geometry": {"coordinates":[-88.81965,35.691273],"type":"Point"}
}