{
  "type": "Feature",
  "properties": {
    "iso:country":"US",
    "sg:address":"583 Dejarnett Ln",
    "sg:city":"Murfreesboro",
    "sg:classifiers":[
        {
            "category":"Organizations",
            "subcategory":"Membership Organization",
            "type":"Services"
        }
    ],
    "sg:phone":"+1 615 907 2811",
    "sg:postcode":"37130",
    "sg:province":"TN",
    "wof:name":"All Gods Children Ministries",
    "wof:placetype":"venue"
},
  "geometry": {"coordinates":[-86.36380699999999,35.886851],"type":"Point"}
}