{
  "type": "Feature",
  "properties": {
    "iso:country":"US",
    "sg:address":"5710 Lee Hwy",
    "sg:city":"Chattanooga",
    "sg:classifiers":[
        {
            "category":"Wholesale",
            "subcategory":"Medical Equipment & Supplies",
            "type":"Manufacturing & Wholesale Goods"
        }
    ],
    "sg:phone":"+1 423 894 6418",
    "sg:postcode":"37421",
    "sg:province":"TN",
    "sg:tags":[
        "physician",
        "surgeon",
        "wheelchairs-rental"
    ],
    "wof:name":"Genesis Home Care Corp",
    "wof:placetype":"venue"
},
  "geometry": {"coordinates":[-85.20523300000001,35.01813],"type":"Point"}
}