{
  "type": "Feature",
  "properties": {
    "iso:country":"US",
    "sg:address":"3509 Bloomingdale Rd",
    "sg:city":"Kingsport",
    "sg:classifiers":[
        {
            "category":"Farming",
            "subcategory":"Livestock Farm",
            "type":"Manufacturing & Wholesale Goods"
        }
    ],
    "sg:phone":"+1 423 288 3657",
    "sg:postcode":"37660",
    "sg:province":"TN",
    "sg:tags":[
        "feeding"
    ],
    "wof:name":"Donald B Christian",
    "wof:placetype":"venue"
},
  "geometry": {"coordinates":[-82.47815199999999,36.586144],"type":"Point"}
}