{
  "type": "Feature",
  "properties": {
    "iso:country":"US",
    "sg:address":"3934 Kings Ln",
    "sg:city":"Nashville",
    "sg:classifiers":[
        {
            "category":"Organizations",
            "subcategory":"Professional Association",
            "type":"Services"
        }
    ],
    "sg:phone":"+1 615 573 4110",
    "sg:postcode":"37218",
    "sg:province":"TN",
    "sg:tags":[
        "business"
    ],
    "wof:name":"Pattons Residential & Coml",
    "wof:placetype":"venue"
},
  "geometry": {"coordinates":[-86.84827799999999,36.217443],"type":"Point"}
}