{
  "type": "Feature",
  "properties": {
    "iso:country":"US",
    "sg:address":"401 Union St",
    "sg:city":"Nashville",
    "sg:classifiers":[
        {
            "category":"Banks & Credit Unions",
            "subcategory":"Investment Brokerage",
            "type":"Services"
        }
    ],
    "sg:phone":"+1 615 255 3199",
    "sg:postcode":"37201",
    "sg:province":"TN",
    "sg:tags":[
        "merchant",
        "banking"
    ],
    "wof:name":"Jarratt Associates",
    "wof:placetype":"venue"
},
  "geometry": {"coordinates":[-86.780462,36.164778],"type":"Point"}
}