{
  "type": "Feature",
  "properties": {
    "iso:country":"US",
    "sg:address":"630 Skyview Dr",
    "sg:city":"Nashville",
    "sg:classifiers":[
        {
            "category":"Real Estate",
            "subcategory":"Real Estate Services",
            "type":"Services"
        }
    ],
    "sg:phone":"+1 615 228 7089",
    "sg:postcode":"37206",
    "sg:province":"TN",
    "sg:tags":[
        "company",
        "title"
    ],
    "wof:name":"Jackston Title Svc",
    "wof:placetype":"venue"
},
  "geometry": {"coordinates":[-86.730918,36.177758],"type":"Point"}
}