{
  "type": "Feature",
  "properties": {
    "iso:country":"US",
    "sg:address":"750 Old Hickory Blvd",
    "sg:city":"Brentwood",
    "sg:classifiers":[
        {
            "category":"Personal",
            "type":"Services"
        }
    ],
    "sg:phone":"+1 615 371 6116",
    "sg:postcode":"37027",
    "sg:province":"TN",
    "sg:tags":[
        "credit",
        "debt",
        "counseling"
    ],
    "wof:name":"Loyalty Group LLC",
    "wof:placetype":"venue"
},
  "geometry": {"coordinates":[-86.778505,36.041311],"type":"Point"}
}