{
  "type": "Feature",
  "properties": {
    "addr:full":"331 Highland Ave Cookeville TN 38501",
    "addr:housenumber":"331",
    "addr:postcode":"38501",
    "addr:street":"Highland Ave",
    "iso:country":"US",
    "sg:address":"331 Highland Ave",
    "sg:city":"Cookeville",
    "sg:classifiers":[
        {
            "category":"Professional",
            "type":"Services"
        }
    ],
    "sg:phone":"+1 931 473 1345",
    "sg:postcode":"38501",
    "sg:province":"TN",
    "wof:name":"Talent Zone",
    "wof:placetype":"venue"
},
  "geometry": {"coordinates":[-85.50416,36.156701],"type":"Point"}
}