{
  "type": "Feature",
  "properties": {
    "addr:full":"2098 Woodvale St Cleveland TN 37311",
    "addr:housenumber":"2098",
    "addr:postcode":"37311",
    "addr:street":"Woodvale St",
    "iso:country":"US",
    "sg:address":"2098 Woodvale St",
    "sg:city":"Cleveland",
    "sg:classifiers":[
        {
            "category":"Building & Trades",
            "subcategory":"Construction",
            "type":"Services"
        }
    ],
    "sg:phone":"+1 423 472 0095",
    "sg:postcode":"37311",
    "sg:province":"TN",
    "sg:tags":[
        "residential"
    ],
    "wof:name":"Edge Construction Gary C Sulzb",
    "wof:placetype":"venue"
},
  "geometry": {"coordinates":[-84.89336900000001,35.189494],"type":"Point"}
}