{
  "type": "Feature",
  "properties": {
    "iso:country":"US",
    "sg:address":"20805 Seminary St",
    "sg:city":"Hollow Rock",
    "sg:classifiers":[
        {
            "category":"Restaurant",
            "type":"Food & Drink"
        }
    ],
    "sg:phone":"+1 731 586 7735",
    "sg:postcode":"38342",
    "sg:province":"TN",
    "wof:name":"Iron Kettle",
    "wof:placetype":"venue"
},
  "geometry": {"coordinates":[-88.274143,36.035616],"type":"Point"}
}