{
  "type": "Feature",
  "properties": {
    "iso:country":"US",
    "sg:address":"2260 Elvis Presley Blvd",
    "sg:city":"Memphis",
    "sg:classifiers":[
        {
            "category":"Autos & Motor Vehicles",
            "subcategory":"Auto Supplies",
            "type":"Retail Goods"
        }
    ],
    "sg:phone":"+1 901 942 6100",
    "sg:postcode":"38106",
    "sg:province":"TN",
    "sg:tags":[
        "engine",
        "gasoline"
    ],
    "wof:name":"Fill N Go",
    "wof:placetype":"venue"
},
  "geometry": {"coordinates":[-90.01857200000001,35.083385],"type":"Point"}
}