{
  "type": "Feature",
  "properties": {
    "addr:full":"9041 Executive Park Dr Knoxville TN 37923",
    "addr:housenumber":"9041",
    "addr:postcode":"37923",
    "addr:street":"Executive Park Dr",
    "iso:country":"US",
    "sg:address":"9041 Executive Park Dr",
    "sg:city":"Knoxville",
    "sg:classifiers":[
        {
            "category":"Insurance",
            "subcategory":"Insurance Agent",
            "type":"Services"
        }
    ],
    "sg:phone":"+1 865 470 4162",
    "sg:postcode":"37923",
    "sg:province":"TN",
    "wof:name":"National Care Insurance",
    "wof:placetype":"venue"
},
  "geometry": {"coordinates":[-84.080641,35.922256],"type":"Point"}
}