{
  "type": "Feature",
  "properties": {
    "iso:country":"US",
    "sg:address":"200 Cumberland Hills Dr",
    "sg:city":"Madison",
    "sg:classifiers":[
        {
            "category":"Manufacturing",
            "subcategory":"Signs",
            "type":"Manufacturing & Wholesale Goods"
        }
    ],
    "sg:phone":"+1 615 859 5531",
    "sg:postcode":"37115",
    "sg:province":"TN",
    "wof:name":"Glen's Graphics",
    "wof:placetype":"venue"
},
  "geometry": {"coordinates":[-86.673833,36.303658],"type":"Point"}
}