{
  "type": "Feature",
  "properties": {
    "iso:country":"US",
    "sg:address":"5951 Rust Rd",
    "sg:city":"Memphis",
    "sg:classifiers":[
        {
            "category":"Professional",
            "subcategory":"Detective & Security Services",
            "type":"Services"
        }
    ],
    "sg:phone":"+1 901 353 7936",
    "sg:postcode":"38127",
    "sg:province":"TN",
    "sg:tags":[
        "information",
        "bureau"
    ],
    "wof:name":"Baptist Memorial Health Serv",
    "wof:placetype":"venue"
},
  "geometry": {"coordinates":[-89.980187,35.287794],"type":"Point"}
}