{
  "type": "Feature",
  "properties": {
    "addr:full":"6508 Winchester Rd Memphis TN 38115",
    "addr:housenumber":"6508",
    "addr:postcode":"38115",
    "addr:street":"Winchester Rd",
    "iso:country":"US",
    "sg:address":"6508 Winchester Rd",
    "sg:city":"Memphis",
    "sg:classifiers":[
        {
            "category":"Food & Beverages",
            "subcategory":"Groceries & Convenience Stores",
            "type":"Retail Goods"
        }
    ],
    "sg:phone":"+1 901 795 1848",
    "sg:postcode":"38115",
    "sg:province":"TN",
    "sg:tags":[
        "infant",
        "wear",
        "child"
    ],
    "wof:name":"Kids For Less",
    "wof:placetype":"venue"
},
  "geometry": {"coordinates":[-89.848028,35.049673],"type":"Point"}
}