{
  "type": "Feature",
  "properties": {
    "iso:country":"US",
    "sg:address":"1819 Galen Dr",
    "sg:city":"Johnson City",
    "sg:classifiers":[
        {
            "category":"Professional",
            "subcategory":"Computer Services",
            "type":"Services"
        }
    ],
    "sg:phone":"+1 423 434 9725",
    "sg:postcode":"37604",
    "sg:province":"TN",
    "sg:tags":[
        "datum"
    ],
    "wof:name":"Century Data Corp",
    "wof:placetype":"venue"
},
  "geometry": {"coordinates":[-82.360235,36.293697],"type":"Point"}
}