{
  "type": "Feature",
  "properties": {
    "iso:country":"US",
    "sg:address":"285 Birdwell Mill Rd",
    "sg:city":"Greeneville",
    "sg:classifiers":[
        {
            "category":"Health Services",
            "subcategory":"Medical Lab",
            "type":"Services"
        }
    ],
    "sg:phone":"+1 423 638 5592",
    "sg:postcode":"37743",
    "sg:province":"TN",
    "sg:tags":[
        "laboratory",
        "dental"
    ],
    "wof:name":"City Dental Laboratory",
    "wof:placetype":"venue"
},
  "geometry": {"coordinates":[-82.90818,36.052293],"type":"Point"}
}