{
  "type": "Feature",
  "properties": {
    "iso:country":"US",
    "sg:address":"2830 W Old Top Side Rd",
    "sg:city":"Louisville",
    "sg:classifiers":[
        {
            "category":"Retail",
            "subcategory":"Repair Shop",
            "type":"Services"
        }
    ],
    "sg:phone":"+1 865 983 7102",
    "sg:postcode":"37777",
    "sg:province":"TN",
    "wof:name":"T and T Upholstery",
    "wof:placetype":"venue"
},
  "geometry": {"coordinates":[-84.027294,35.824075],"type":"Point"}
}