{
  "type": "Feature",
  "properties": {
    "addr:full":"586 Campground Rd Manchester TN 37355",
    "addr:housenumber":"586",
    "addr:postcode":"37355",
    "addr:street":"Campground Rd",
    "iso:country":"US",
    "sg:address":"586 Campground Rd",
    "sg:city":"Manchester",
    "sg:classifiers":[
        {
            "category":"Retail",
            "subcategory":"Laundry & Dry Cleaning",
            "type":"Services"
        }
    ],
    "sg:phone":"+1 931 728 1747",
    "sg:postcode":"37355",
    "sg:province":"TN",
    "wof:name":"Crystal Clean Carpets",
    "wof:placetype":"venue"
},
  "geometry": {"coordinates":[-86.05002899999999,35.457971],"type":"Point"}
}