{
  "type": "Feature",
  "properties": {
    "iso:country":"US",
    "sg:address":"1513 E Main St",
    "sg:city":"Humboldt",
    "sg:classifiers":[
        {
            "category":"Freight",
            "type":"Transportation"
        }
    ],
    "sg:phone":"+1 731 784 3495",
    "sg:postcode":"38343",
    "sg:province":"TN",
    "sg:tags":[
        "operator",
        "local",
        "trucking"
    ],
    "wof:name":"Quality Moving Co",
    "wof:placetype":"venue"
},
  "geometry": {"coordinates":[-88.915076,35.819805],"type":"Point"}
}