{
  "type": "Feature",
  "properties": {
    "iso:country":"US",
    "sg:address":"5411 Burton Church Cove",
    "sg:city":"Memphis",
    "sg:classifiers":[
        {
            "category":"Building & Trades",
            "subcategory":"Construction",
            "type":"Services"
        }
    ],
    "sg:phone":"+1 901 386 1732",
    "sg:postcode":"38134",
    "sg:province":"TN",
    "sg:tags":[
        "flooring",
        "contractor"
    ],
    "wof:name":"Barthalow Flooring Co",
    "wof:placetype":"venue"
},
  "geometry": {"coordinates":[-89.882501,35.21775],"type":"Point"}
}