{
  "type": "Feature",
  "properties": {
    "iso:country":"US",
    "sg:address":"2309 Grandview Ave",
    "sg:city":"Nashville",
    "sg:classifiers":[
        {
            "category":"Professional",
            "type":"Services"
        },
        {
            "category":"Building & Trades",
            "subcategory":"Pest Control",
            "type":"Services"
        }
    ],
    "sg:phone":"+1 615 259 4939",
    "sg:postcode":"37211",
    "sg:province":"TN",
    "wof:name":"Nosquito Automatic Misting Sys",
    "wof:placetype":"venue"
},
  "geometry": {"coordinates":[-86.75137700000001,36.120363],"type":"Point"}
}