{
  "type": "Feature",
  "properties": {
    "addr:full":"100 Public Sq Ashland City TN 37015",
    "addr:housenumber":"100",
    "addr:postcode":"37015",
    "addr:street":"Public Sq",
    "iso:country":"US",
    "sg:address":"100 Public Sq",
    "sg:city":"Ashland City",
    "sg:classifiers":[
        {
            "category":"Government",
            "subcategory":"Office",
            "type":"Public Place"
        }
    ],
    "sg:phone":"+1 615 792 4316",
    "sg:postcode":"37015",
    "sg:province":"TN",
    "sg:tags":[
        "executive"
    ],
    "wof:name":"County of Cheatham",
    "wof:placetype":"venue"
},
  "geometry": {"coordinates":[-87.063424,36.274848],"type":"Point"}
}