{
  "type": "Feature",
  "properties": {
    "iso:country":"US",
    "sg:address":"2000 Knox Rd",
    "sg:city":"Collierville",
    "sg:classifiers":[
        {
            "category":"Professional",
            "subcategory":"Advertising",
            "type":"Services"
        }
    ],
    "sg:phone":"+1 901 853 7014",
    "sg:postcode":"38017",
    "sg:province":"TN",
    "sg:tags":[
        "counselor"
    ],
    "wof:name":"Hollis & Assoc",
    "wof:placetype":"venue"
},
  "geometry": {"coordinates":[-89.562911,35.024215],"type":"Point"}
}