{
  "type": "Feature",
  "properties": {
    "iso:country":"US",
    "sg:address":"3018 E Lamar Alexander Pkwy",
    "sg:city":"Maryville",
    "sg:classifiers":[
        {
            "category":"Personal",
            "subcategory":"Beauty Salon",
            "type":"Services"
        }
    ],
    "sg:phone":"+1 865 983 7450",
    "sg:postcode":"37804",
    "sg:province":"TN",
    "wof:name":"Tam-Ron Beauty Shop",
    "wof:placetype":"venue"
},
  "geometry": {"coordinates":[-83.917029,35.756609],"type":"Point"}
}