{
  "type": "Feature",
  "properties": {
    "iso:country":"US",
    "sg:address":"4645 Navy Rd",
    "sg:city":"Millington",
    "sg:classifiers":[
        {
            "category":"Shopping",
            "subcategory":"Used Merchandise",
            "type":"Retail Goods"
        }
    ],
    "sg:phone":"+1 901 872 4870",
    "sg:postcode":"38053",
    "sg:province":"TN",
    "sg:tags":[
        "book",
        "rare",
        "dealer"
    ],
    "wof:name":"T's Used Books",
    "wof:placetype":"venue"
},
  "geometry": {"coordinates":[-89.90779999999999,35.341311],"type":"Point"}
}