{
  "type": "Feature",
  "properties": {
    "iso:country":"US",
    "sg:address":"1960 Memorial Dr",
    "sg:city":"Clarksville",
    "sg:classifiers":[
        {
            "category":"Freight",
            "type":"Transportation"
        }
    ],
    "sg:phone":"+1 931 551 8080",
    "sg:postcode":"37043",
    "sg:province":"TN",
    "sg:tags":[
        "special",
        "general"
    ],
    "wof:name":"TLC Mini Storage",
    "wof:placetype":"venue"
},
  "geometry": {"coordinates":[-87.297122,36.52211],"type":"Point"}
}