{
  "type": "Feature",
  "properties": {
    "iso:country":"US",
    "sg:address":"503 W Parkview St",
    "sg:city":"Dyersburg",
    "sg:classifiers":[
        {
            "category":"Banks & Credit Unions",
            "subcategory":"Bank",
            "type":"Services"
        }
    ],
    "sg:phone":"+1 731 285 4757",
    "sg:postcode":"38024",
    "sg:province":"TN",
    "sg:tags":[
        "state",
        "commercial"
    ],
    "wof:name":"Stallings Lipford",
    "wof:placetype":"venue"
},
  "geometry": {"coordinates":[-89.38978400000001,36.04658],"type":"Point"}
}