{
  "type": "Feature",
  "properties": {
    "addr:full":"1400 County Hospital Rd Nashville TN 37218",
    "addr:housenumber":"1400",
    "addr:postcode":"37218",
    "addr:street":"County Hospital Rd",
    "iso:country":"US",
    "sg:address":"1400 County Hospital Rd",
    "sg:city":"Nashville",
    "sg:classifiers":[
        {
            "category":"Home & Garden",
            "subcategory":"Garden Supply",
            "type":"Retail Goods"
        }
    ],
    "sg:phone":"+1 615 259 2234",
    "sg:postcode":"37218",
    "sg:province":"TN",
    "wof:name":"Simply Mulch",
    "wof:placetype":"venue"
},
  "geometry": {"coordinates":[-86.851724,36.183587],"type":"Point"}
}