{
  "type": "Feature",
  "properties": {
    "addr:full":"4909 E Shelby Dr Memphis TN 38118",
    "addr:housenumber":"4909",
    "addr:postcode":"38118",
    "addr:street":"E Shelby Dr",
    "iso:country":"US",
    "sg:address":"4909 E Shelby Dr",
    "sg:city":"Memphis",
    "sg:classifiers":[
        {
            "category":"Wholesale",
            "subcategory":"Machinery & Supplies",
            "type":"Manufacturing & Wholesale Goods"
        }
    ],
    "sg:phone":"+1 901 365 1180",
    "sg:postcode":"38118",
    "sg:province":"TN",
    "sg:tags":[
        "contractor"
    ],
    "wof:name":"MMS Equipment Sales",
    "wof:placetype":"venue"
},
  "geometry": {"coordinates":[-89.900148,35.0204],"type":"Point"}
}