{
  "type": "Feature",
  "properties": {
    "iso:country":"US",
    "sg:address":"1314 5th Ave N",
    "sg:city":"Nashville",
    "sg:classifiers":[
        {
            "category":"Manufacturing",
            "subcategory":"Printing",
            "type":"Manufacturing & Wholesale Goods"
        }
    ],
    "sg:phone":"+1 615 726 1044",
    "sg:postcode":"37208",
    "sg:province":"TN",
    "sg:tags":[
        "commercial"
    ],
    "wof:name":"Business Card Express",
    "wof:placetype":"venue"
},
  "geometry": {"coordinates":[-86.78978499999999,36.178037],"type":"Point"}
}