{
  "type": "Feature",
  "properties": {
    "iso:country":"US",
    "sg:address":"1607 E Lamar Alexander Pkwy",
    "sg:city":"Maryville",
    "sg:classifiers":[
        {
            "category":"Professional",
            "type":"Services"
        }
    ],
    "sg:phone":"+1 865 982 9979",
    "sg:postcode":"37804",
    "sg:province":"TN",
    "sg:tags":[
        "establishment"
    ],
    "wof:name":"Sugar Plums",
    "wof:placetype":"venue"
},
  "geometry": {"coordinates":[-83.948171,35.755379],"type":"Point"}
}