{
  "type": "Feature",
  "properties": {
    "iso:country":"US",
    "sg:address":"501 Mahler Ave",
    "sg:city":"Cookeville",
    "sg:classifiers":[
        {
            "category":"Utilities",
            "subcategory":"Fuel Oil & Lpg",
            "type":"Services"
        }
    ],
    "sg:phone":"+1 931 526 7305",
    "sg:postcode":"38501",
    "sg:province":"TN",
    "sg:tags":[
        "liquefied",
        "gas",
        "petroleum"
    ],
    "wof:name":"Suburban Propane",
    "wof:placetype":"venue"
},
  "geometry": {"coordinates":[-85.50402,36.170234],"type":"Point"}
}