{
  "type": "Feature",
  "properties": {
    "iso:country":"US",
    "sg:address":"5 Stoneleigh Pl",
    "sg:city":"Brownsville",
    "sg:classifiers":[
        {
            "category":"Professional",
            "subcategory":"Management & Consulting",
            "type":"Services"
        }
    ],
    "sg:phone":"+1 731 772 7170",
    "sg:postcode":"38012",
    "sg:province":"TN",
    "sg:tags":[
        "marketing",
        "program"
    ],
    "wof:name":"Peter Mascolo",
    "wof:placetype":"venue"
},
  "geometry": {"coordinates":[-89.28377,35.604209],"type":"Point"}
}