{
  "type": "Feature",
  "properties": {
    "addr:full":"1943 Big Springs Rd Maryville TN 37801",
    "addr:housenumber":"1943",
    "addr:postcode":"37801",
    "addr:street":"Big Springs Rd",
    "iso:country":"US",
    "sg:address":"1943 Big Springs Rd",
    "sg:city":"Maryville",
    "sg:classifiers":[
        {
            "category":"Manufacturing",
            "subcategory":"Textiles",
            "type":"Manufacturing & Wholesale Goods"
        }
    ],
    "sg:phone":"+1 865 977 6668",
    "sg:postcode":"37801",
    "sg:province":"TN",
    "sg:tags":[
        "finishing",
        "printing",
        "commercial",
        "plant",
        "cotton"
    ],
    "sg:website":"www.e-commonthread.com",
    "wof:name":"Common Thread Inc",
    "wof:placetype":"venue"
},
  "geometry": {"coordinates":[-84.023715,35.751856],"type":"Point"}
}