{
  "type": "Feature",
  "properties": {
    "iso:country":"US",
    "sg:address":"2010 Bynum Rd",
    "sg:city":"Dresden",
    "sg:phone":"+1 731 648 5734",
    "sg:postcode":"38225",
    "sg:province":"TN",
    "sg:tags":[
        "farm",
        "grain",
        "cash"
    ],
    "wof:name":"Bates Farm",
    "wof:placetype":"venue"
},
  "geometry": {"coordinates":[-88.65165,36.239687],"type":"Point"}
}