{
  "type": "Feature",
  "properties": {
    "iso:country":"US",
    "sg:address":"505 Grand Lagoon",
    "sg:city":"Madison",
    "sg:classifiers":[
        {
            "category":"Professional",
            "type":"Services"
        }
    ],
    "sg:phone":"+1 615 319 3538",
    "sg:postcode":"37115",
    "sg:province":"TN",
    "wof:name":"Herod's Home Improvement",
    "wof:placetype":"venue"
},
  "geometry": {"coordinates":[-86.675161,36.25013],"type":"Point"}
}