{
  "type": "Feature",
  "properties": {
    "iso:country":"US",
    "sg:address":"8541 Baron Dr",
    "sg:city":"Knoxville",
    "sg:classifiers":[
        {
            "category":"Building & Trades",
            "subcategory":"Construction",
            "type":"Services"
        }
    ],
    "sg:phone":"+1 865 455 8294",
    "sg:postcode":"37923",
    "sg:province":"TN",
    "sg:tags":[
        "painter"
    ],
    "wof:name":"Callihan Painting",
    "wof:placetype":"venue"
},
  "geometry": {"coordinates":[-84.06825000000001,35.941497],"type":"Point"}
}