{
  "type": "Feature",
  "properties": {
    "iso:country":"US",
    "sg:address":"80 Nance Ln",
    "sg:city":"Nashville",
    "sg:classifiers":[
        {
            "category":"Building & Trades",
            "subcategory":"Plumbing",
            "type":"Services"
        }
    ],
    "sg:phone":"+1 615 742 3002",
    "sg:postcode":"37210",
    "sg:province":"TN",
    "sg:tags":[
        "contractor"
    ],
    "wof:name":"Patriot Irrigation & Lighting",
    "wof:placetype":"venue"
},
  "geometry": {"coordinates":[-86.749585,36.141479],"type":"Point"}
}