{
  "type": "Feature",
  "properties": {
    "iso:country":"US",
    "sg:address":"6901 Lake Breeze Dr",
    "sg:city":"Harrison",
    "sg:classifiers":[
        {
            "category":"Shopping",
            "subcategory":"Bicycles & Sporting Goods",
            "type":"Retail Goods"
        }
    ],
    "sg:phone":"+1 423 344 0665",
    "sg:postcode":"37341",
    "sg:province":"TN",
    "wof:name":"C & C Outdoors",
    "wof:placetype":"venue"
},
  "geometry": {"coordinates":[-85.108994,35.140236],"type":"Point"}
}