{
  "type": "Feature",
  "properties": {
    "iso:country":"US",
    "sg:address":"2825 Farrisview Blvd",
    "sg:city":"Memphis",
    "sg:classifiers":[
        {
            "category":"Food & Beverages",
            "subcategory":"Supermarket",
            "type":"Retail Goods"
        }
    ],
    "sg:phone":"+1 901 365 8361",
    "sg:postcode":"38118",
    "sg:province":"TN",
    "sg:tags":[
        "super",
        "store"
    ],
    "wof:name":"Memphis Foods",
    "wof:placetype":"venue"
},
  "geometry": {"coordinates":[-89.963902,35.07736],"type":"Point"}
}