{
  "type": "Feature",
  "properties": {
    "iso:country":"US",
    "sg:address":"7155 Lee Hwy",
    "sg:city":"Chattanooga",
    "sg:classifiers":[
        {
            "category":"Banks & Credit Unions",
            "subcategory":"Bank",
            "type":"Services"
        }
    ],
    "sg:phone":"+1 423 892 7914",
    "sg:postcode":"37421",
    "sg:province":"TN",
    "sg:tags":[
        "escrow"
    ],
    "wof:name":"Title Guaranty & Trust Co",
    "wof:placetype":"venue"
},
  "geometry": {"coordinates":[-85.15456500000001,35.049883],"type":"Point"}
}