{
  "type": "Feature",
  "properties": {
    "iso:country":"US",
    "sg:address":"1816 Huntsville Hwy",
    "sg:city":"Fayetteville",
    "sg:classifiers":[
        {
            "category":"Building & Trades",
            "subcategory":"Construction",
            "type":"Services"
        }
    ],
    "sg:phone":"+1 931 438 8940",
    "sg:postcode":"37334",
    "sg:province":"TN",
    "sg:tags":[
        "general",
        "contractor"
    ],
    "wof:name":"Mullins Construction Co",
    "wof:placetype":"venue"
},
  "geometry": {"coordinates":[-86.565896,35.125938],"type":"Point"}
}