{
  "type": "Feature",
  "properties": {
    "addr:full":"2030 Warren St Memphis TN 38106",
    "addr:housenumber":"2030",
    "addr:postcode":"38106",
    "addr:street":"Warren St",
    "iso:country":"US",
    "sg:address":"2030 Warren St",
    "sg:city":"Memphis",
    "sg:classifiers":[
        {
            "category":"Education",
            "subcategory":"Special Training",
            "type":"Public Place"
        }
    ],
    "sg:phone":"+1 901 774 0699",
    "sg:postcode":"38106",
    "sg:province":"TN",
    "sg:tags":[
        "tutoring"
    ],
    "wof:name":"Dellas' Tutoring Svc",
    "wof:placetype":"venue"
},
  "geometry": {"coordinates":[-90.01464799999999,35.090521],"type":"Point"}
}