{
  "type": "Feature",
  "properties": {
    "addr:full":"349 Gill St Alcoa TN 37701",
    "addr:housenumber":"349",
    "addr:postcode":"37701",
    "addr:street":"Gill St",
    "iso:country":"US",
    "sg:address":"349 Gill St",
    "sg:city":"Alcoa",
    "sg:classifiers":[
        {
            "category":"Personal",
            "subcategory":"Beauty Salon",
            "type":"Services"
        }
    ],
    "sg:phone":"+1 865 984 2330",
    "sg:postcode":"37701",
    "sg:province":"TN",
    "sg:tags":[
        "shop"
    ],
    "wof:name":"Raymour Hair Design",
    "wof:placetype":"venue"
},
  "geometry": {"coordinates":[-83.97430900000001,35.76035],"type":"Point"}
}