{
  "type": "Feature",
  "properties": {
    "iso:country":"US",
    "sg:address":"715 Georgia Ave",
    "sg:city":"Etowah",
    "sg:classifiers":[
        {
            "category":"Professional",
            "subcategory":"Business Services",
            "type":"Services"
        }
    ],
    "sg:phone":"+1 423 263 9230",
    "sg:postcode":"37331",
    "sg:province":"TN",
    "wof:name":"Cart Wilson Sales",
    "wof:placetype":"venue"
},
  "geometry": {"coordinates":[-84.529449,35.325891],"type":"Point"}
}