{
  "type": "Feature",
  "properties": {
    "iso:country":"US",
    "sg:address":"1614 Memorial Blvd",
    "sg:city":"Murfreesboro",
    "sg:classifiers":[
        {
            "category":"Banks & Credit Unions",
            "subcategory":"Bank",
            "type":"Services"
        }
    ],
    "sg:phone":"+1 615 217 2799",
    "sg:postcode":"37129",
    "sg:province":"TN",
    "sg:tags":[
        "cashing",
        "check"
    ],
    "wof:name":"Cash Express",
    "wof:placetype":"venue"
},
  "geometry": {"coordinates":[-86.396905,35.852529],"type":"Point"}
}