{
  "type": "Feature",
  "properties": {
    "addr:full":"9515 Apison Pike Ooltewah TN 37363",
    "addr:postcode":"9515;37363",
    "addr:street":"Apison Pike",
    "iso:country":"US",
    "sg:address":"9515 Apison Pike",
    "sg:city":"Ooltewah",
    "sg:classifiers":[
        {
            "category":"Food & Beverages",
            "subcategory":"Groceries & Convenience Stores",
            "type":"Retail Goods"
        }
    ],
    "sg:phone":"+1 423 396 2941",
    "sg:postcode":"37363",
    "sg:province":"TN",
    "sg:tags":[
        "product"
    ],
    "wof:name":"Mc Kee Foods",
    "wof:placetype":"venue"
},
  "geometry": {"coordinates":[-85.065521,35.059176],"type":"Point"}
}