{
  "type": "Feature",
  "properties": {
    "iso:country":"US",
    "sg:address":"813 18th Ave S",
    "sg:city":"Nashville",
    "sg:classifiers":[
        {
            "category":"Communications",
            "subcategory":"Film & Video Production",
            "type":"Services"
        }
    ],
    "sg:phone":"+1 615 587 2227",
    "sg:postcode":"37203",
    "sg:province":"TN",
    "sg:tags":[
        "motion"
    ],
    "wof:name":"My Friend Babs Enterprises",
    "wof:placetype":"venue"
},
  "geometry": {"coordinates":[-86.79442899999999,36.151112],"type":"Point"}
}