{
  "type": "Feature",
  "properties": {
    "iso:country":"US",
    "sg:address":"1856 Clara Mathis Rd",
    "sg:city":"Spring Hill",
    "sg:classifiers":[
        {
            "category":"Personal",
            "subcategory":"Barber",
            "type":"Services"
        }
    ],
    "sg:phone":"+1 931 388 5187",
    "sg:postcode":"37174",
    "sg:province":"TN",
    "sg:tags":[
        "shop"
    ],
    "wof:name":"Dee Barber",
    "wof:placetype":"venue"
},
  "geometry": {"coordinates":[-86.910106,35.666069],"type":"Point"}
}