{
  "type": "Feature",
  "properties": {
    "iso:country":"US",
    "sg:address":"5700 Brainerd Rd",
    "sg:city":"Chattanooga",
    "sg:classifiers":[
        {
            "category":"Professional",
            "subcategory":"Employment Agencies",
            "type":"Services"
        }
    ],
    "sg:phone":"+1 423 899 0941",
    "sg:postcode":"37411",
    "sg:province":"TN",
    "wof:name":"Holmes Personnel Consultants",
    "wof:placetype":"venue"
},
  "geometry": {"coordinates":[-85.213959,35.011708],"type":"Point"}
}