{
  "type": "Feature",
  "properties": {
    "addr:full":"159 Vantrease Ln Gallatin TN 37066",
    "addr:housenumber":"159",
    "addr:postcode":"37066",
    "addr:street":"Vantrease Ln",
    "iso:country":"US",
    "sg:address":"159 Vantrease Ln",
    "sg:city":"Gallatin",
    "sg:classifiers":[
        {
            "category":"Farming",
            "subcategory":"Livestock Farm",
            "type":"Manufacturing & Wholesale Goods"
        }
    ],
    "sg:phone":"+1 615 451 2041",
    "sg:postcode":"37066",
    "sg:province":"TN",
    "sg:tags":[
        "beef",
        "feedlot",
        "cattle"
    ],
    "wof:name":"Charles Vantrease",
    "wof:placetype":"venue"
},
  "geometry": {"coordinates":[-86.52927,36.430922],"type":"Point"}
}