{
  "type": "Feature",
  "properties": {
    "iso:country":"US",
    "sg:address":"1978 Loney Dr",
    "sg:city":"Nashville",
    "sg:classifiers":[
        {
            "category":"Building & Trades",
            "subcategory":"Construction",
            "type":"Services"
        }
    ],
    "sg:phone":"+1 615 742 7413",
    "sg:postcode":"37210",
    "sg:province":"TN",
    "sg:tags":[
        "contractor"
    ],
    "wof:name":"V T Drywall",
    "wof:placetype":"venue"
},
  "geometry": {"coordinates":[-86.734274,36.128514],"type":"Point"}
}