{
  "type": "Feature",
  "properties": {
    "iso:country":"US",
    "sg:address":"11017 Flotilla Dr",
    "sg:city":"Knoxville",
    "sg:classifiers":[
        {
            "category":"Professional",
            "subcategory":"Business Services",
            "type":"Services"
        }
    ],
    "sg:phone":"+1 865 966 7275",
    "sg:postcode":"37934",
    "sg:province":"TN",
    "wof:name":"Med-Voc Solutions",
    "wof:placetype":"venue"
},
  "geometry": {"coordinates":[-84.13511099999999,35.880407],"type":"Point"}
}