{
  "type": "Feature",
  "properties": {
    "addr:full":"919 Harpeth Valley Pl Nashville TN 37221",
    "addr:housenumber":"919",
    "addr:postcode":"37221",
    "addr:street":"Harpeth Valley Pl",
    "iso:country":"US",
    "sg:address":"919 Harpeth Valley Pl",
    "sg:city":"Nashville",
    "sg:classifiers":[
        {
            "category":"Banks & Credit Unions",
            "subcategory":"Bank",
            "type":"Services"
        }
    ],
    "sg:phone":"+1 615 662 0096",
    "sg:postcode":"37221",
    "sg:province":"TN",
    "sg:tags":[
        "loan",
        "mortgage",
        "real estate"
    ],
    "wof:name":"First Tennessee Home Loans",
    "wof:placetype":"venue"
},
  "geometry": {"coordinates":[-86.956917,36.083219],"type":"Point"}
}