{
  "type": "Feature",
  "properties": {
    "addr:full":"3072 Ingleside Dr Memphis TN 38134",
    "addr:housenumber":"3072",
    "addr:postcode":"38134",
    "addr:street":"Ingleside Dr",
    "iso:country":"US",
    "sg:address":"3072 Ingleside Dr",
    "sg:city":"Memphis",
    "sg:classifiers":[
        {
            "category":"Food & Beverages",
            "subcategory":"Candy",
            "type":"Retail Goods"
        }
    ],
    "sg:phone":"+1 901 377 3947",
    "sg:postcode":"38134",
    "sg:province":"TN",
    "wof:name":"Fannie Blackmon",
    "wof:placetype":"venue"
},
  "geometry": {"coordinates":[-89.853831,35.209022],"type":"Point"}
}