{
  "type": "Feature",
  "properties": {
    "iso:country":"US",
    "sg:address":"943 6th St NE",
    "sg:city":"Cleveland",
    "sg:classifiers":[
        {
            "category":"Organizations",
            "subcategory":"Religious Organization",
            "type":"Services"
        }
    ],
    "sg:phone":"+1 423 728 5010",
    "sg:postcode":"37311",
    "sg:province":"TN",
    "wof:name":"Rivers Of Living Water Church",
    "wof:placetype":"venue"
},
  "geometry": {"coordinates":[-84.860299,35.156866],"type":"Point"}
}