{
  "type": "Feature",
  "properties": {
    "iso:country":"US",
    "sg:address":"80 Monroe Ave",
    "sg:city":"Memphis",
    "sg:classifiers":[
        {
            "category":"Real Estate",
            "subcategory":"Real Estate Agent",
            "type":"Services"
        }
    ],
    "sg:phone":"+1 901 525 0712",
    "sg:postcode":"38103",
    "sg:province":"TN",
    "sg:tags":[
        "management"
    ],
    "wof:name":"Sanderlin Place GP & Brinkley",
    "wof:placetype":"venue"
},
  "geometry": {"coordinates":[-90.053349,35.144311],"type":"Point"}
}