{
  "type": "Feature",
  "properties": {
    "addr:full":"937 Herman St Nashville TN 37208",
    "addr:housenumber":"937",
    "addr:postcode":"37208",
    "addr:street":"Herman St",
    "iso:country":"US",
    "sg:address":"937 Herman St",
    "sg:city":"Nashville",
    "sg:classifiers":[
        {
            "category":"Social Services",
            "type":"Services"
        },
        {
            "category":"Education",
            "subcategory":"Special Training",
            "type":"Public Place"
        },
        {
            "category":"Shopping",
            "subcategory":"Used Merchandise",
            "type":"Retail Goods"
        },
        {
            "category":"Banks & Credit Unions",
            "subcategory":"Bank",
            "type":"Services"
        },
        {
            "category":"Organizations",
            "subcategory":"Non-profit Organization",
            "type":"Services"
        }
    ],
    "sg:phone":"+1 615 255 7808",
    "sg:postcode":"37208",
    "sg:province":"TN",
    "sg:tags":[
        "shop",
        "foundations-educational",
        "philanthropic",
        "career",
        "vocational",
        "research",
        "resale",
        "second",
        "counseling",
        "hand",
        "charity"
    ],
    "sg:website":"http://www.goodwill.org/",
    "wof:name":"Goodwill Industries Career Solutions",
    "wof:placetype":"venue"
},
  "geometry": {"coordinates":[-86.79033699999999,36.169759],"type":"Point"}
}