{
  "type": "Feature",
  "properties": {
    "iso:country":"US",
    "sg:address":"242 Rock House Rd",
    "sg:city":"Johnson City",
    "sg:classifiers":[
        {
            "category":"Freight",
            "type":"Transportation"
        }
    ],
    "sg:phone":"+1 423 926 5273",
    "sg:postcode":"37601",
    "sg:province":"TN",
    "sg:tags":[
        "operator",
        "local",
        "trucking"
    ],
    "wof:name":"Freds Delivery Service",
    "wof:placetype":"venue"
},
  "geometry": {"coordinates":[-82.301061,36.276559],"type":"Point"}
}