{
  "type": "Feature",
  "properties": {
    "iso:country":"US",
    "sg:address":"6425 Stage Rd",
    "sg:city":"Memphis",
    "sg:classifiers":[
        {
            "category":"Health Services",
            "subcategory":"Doctor",
            "type":"Services"
        }
    ],
    "sg:phone":"+1 901 755 3354",
    "sg:postcode":"38134",
    "sg:province":"TN",
    "sg:tags":[
        "medical"
    ],
    "wof:name":"Benbo Co",
    "wof:placetype":"venue"
},
  "geometry": {"coordinates":[-89.84887000000001,35.204672],"type":"Point"}
}