{
  "type": "Feature",
  "properties": {
    "iso:country":"US",
    "sg:address":"1420 Dodds Ave",
    "sg:city":"Chattanooga",
    "sg:classifiers":[
        {
            "category":"Retail",
            "subcategory":"Repair Shop",
            "type":"Services"
        }
    ],
    "sg:phone":"+1 423 698 0073",
    "sg:postcode":"37404",
    "sg:province":"TN",
    "sg:tags":[
        "refinishing",
        "furniture"
    ],
    "wof:name":"Mc Cracken Brothers",
    "wof:placetype":"venue"
},
  "geometry": {"coordinates":[-85.269317,35.022311],"type":"Point"}
}