{
  "type": "Feature",
  "properties": {
    "iso:country":"US",
    "sg:address":"728 Rankin Ave",
    "sg:city":"Dunlap",
    "sg:classifiers":[
        {
            "category":"Banks & Credit Unions",
            "subcategory":"Bank",
            "type":"Services"
        }
    ],
    "sg:phone":"+1 423 949 2238",
    "sg:postcode":"37327",
    "sg:province":"TN",
    "sg:tags":[
        "mortgage"
    ],
    "wof:name":"Valley Mortgage Co",
    "wof:placetype":"venue"
},
  "geometry": {"coordinates":[-85.378805,35.386681],"type":"Point"}
}