{
  "type": "Feature",
  "properties": {
    "iso:country":"US",
    "sg:address":"408 Municipal Dr",
    "sg:city":"Jefferson City",
    "sg:classifiers":[
        {
            "category":"Manufacturing",
            "subcategory":"Metals",
            "type":"Manufacturing & Wholesale Goods"
        }
    ],
    "sg:phone":"+1 865 475 9085",
    "sg:postcode":"37760",
    "sg:province":"TN",
    "sg:tags":[
        "steel",
        "e",
        "mfg",
        "spring",
        "automotive",
        "stampings"
    ],
    "sg:website":"www.matsuousa.com",
    "wof:name":"Matsuo Industries USA Inc",
    "wof:placetype":"venue"
},
  "geometry": {"coordinates":[-83.48064599999999,36.133504],"type":"Point"}
}