{
  "type": "Feature",
  "properties": {
    "addr:full":"2089 N Highland Ave Jackson TN 38305",
    "addr:housenumber":"2089",
    "addr:postcode":"38305",
    "addr:street":"N Highland Ave",
    "iso:country":"US",
    "sg:address":"2089 N Highland Ave",
    "sg:city":"Jackson",
    "sg:classifiers":[
        {
            "category":"Restaurant",
            "type":"Food & Drink"
        },
        {
            "category":"Ice Cream",
            "type":"Food & Drink"
        }
    ],
    "sg:menulink":"http://www.allmenus.com/tn/jackson/243737-baskin-robbins/menu/",
    "sg:phone":"+1 731 668 9255",
    "sg:postcode":"38305",
    "sg:province":"TN",
    "sg:tags":[
        "american",
        "ice",
        "cream"
    ],
    "wof:name":"Baskin-Robbins",
    "wof:placetype":"venue"
},
  "geometry": {"coordinates":[-88.82805399999999,35.658942],"type":"Point"}
}