{
  "type": "Feature",
  "properties": {
    "iso:country":"US",
    "sg:address":"546 Sumpter Rd",
    "sg:city":"Kingsport",
    "sg:classifiers":[
        {
            "category":"Building & Trades",
            "subcategory":"Landscaping Services",
            "type":"Services"
        }
    ],
    "sg:phone":"+1 423 349 7785",
    "sg:postcode":"37663",
    "sg:province":"TN",
    "wof:name":"Native Stock Nursery & Ldscpg",
    "wof:placetype":"venue"
},
  "geometry": {"coordinates":[-82.551621,36.452456],"type":"Point"}
}