{
  "type": "Feature",
  "properties": {
    "iso:country":"US",
    "sg:address":"3409 Sugar Creek Rd",
    "sg:city":"Laurel Bloomery",
    "sg:classifiers":[
        {
            "category":"Organizations",
            "subcategory":"Religious Organization",
            "type":"Services"
        }
    ],
    "sg:phone":"+1 423 727 0298",
    "sg:postcode":"37680",
    "sg:province":"TN",
    "wof:name":"State Line Baptist Church",
    "wof:placetype":"venue"
},
  "geometry": {"coordinates":[-81.728351,36.598133],"type":"Point"}
}