{
  "type": "Feature",
  "properties": {
    "addr:full":"1231 NW Broad St Murfreesboro TN 37129",
    "addr:housenumber":"1231",
    "addr:postcode":"37129",
    "addr:street":"Nw Broad St",
    "iso:country":"US",
    "sg:address":"1231 NW Broad St",
    "sg:city":"Murfreesboro",
    "sg:classifiers":[
        {
            "category":"Retail",
            "subcategory":"Repair Shop",
            "type":"Services"
        }
    ],
    "sg:phone":"+1 615 896 9080",
    "sg:postcode":"37129",
    "sg:province":"TN",
    "sg:tags":[
        "upholsterer"
    ],
    "wof:name":"Bilt-Rite Upholstery",
    "wof:placetype":"venue"
},
  "geometry": {"coordinates":[-86.39809099999999,35.848116],"type":"Point"}
}