{
  "type": "Feature",
  "properties": {
    "iso:country":"US",
    "sg:address":"265 White Bridge Pike",
    "sg:city":"Nashville",
    "sg:classifiers":[
        {
            "category":"Banks & Credit Unions",
            "subcategory":"Bank",
            "type":"Services"
        }
    ],
    "sg:phone":"+1 615 320 1550",
    "sg:postcode":"37209",
    "sg:province":"TN",
    "sg:tags":[
        "loan",
        "consumer",
        "company"
    ],
    "wof:name":"Avco Financial",
    "wof:placetype":"venue"
},
  "geometry": {"coordinates":[-86.857901,36.144501],"type":"Point"}
}