{
  "type": "Feature",
  "properties": {
    "iso:country":"US",
    "sg:address":"59 Pine Dr",
    "sg:city":"Spencer",
    "sg:classifiers":[
        {
            "category":"Food & Beverages",
            "subcategory":"Groceries & Convenience Stores",
            "type":"Retail Goods"
        }
    ],
    "sg:phone":"+1 931 946 8224",
    "sg:postcode":"38574",
    "sg:province":"TN",
    "wof:name":"Parkway Southside",
    "wof:placetype":"venue"
},
  "geometry": {"coordinates":[-85.23005499999999,36.088743],"type":"Point"}
}