{
  "type": "Feature",
  "properties": {
    "iso:country":"US",
    "sg:address":"3556 Tom Austin Hwy",
    "sg:city":"Springfield",
    "sg:classifiers":[
        {
            "category":"Shopping",
            "type":"Retail Goods"
        }
    ],
    "sg:phone":"+1 615 384 2367",
    "sg:postcode":"37172",
    "sg:province":"TN",
    "sg:tags":[
        "pet",
        "food",
        "supply"
    ],
    "sg:website":"www.tsc.com",
    "wof:name":"Tractor Supply Co",
    "wof:placetype":"venue"
},
  "geometry": {"coordinates":[-86.87809799999999,36.490777],"type":"Point"}
}