{
  "type": "Feature",
  "properties": {
    "iso:country":"US",
    "sg:address":"1 Franke Blvd",
    "sg:city":"Fayetteville",
    "sg:classifiers":[
        {
            "category":"Manufacturing",
            "subcategory":"Metals",
            "type":"Manufacturing & Wholesale Goods"
        }
    ],
    "sg:phone":"+1 931 433 7455",
    "sg:postcode":"37334",
    "sg:province":"TN",
    "sg:tags":[
        "sanitary",
        "ware",
        "mfg"
    ],
    "wof:name":"Franke Contract Group",
    "wof:placetype":"venue"
},
  "geometry": {"coordinates":[-86.516071,35.162812],"type":"Point"}
}