{
  "type": "Feature",
  "properties": {
    "iso:country":"US",
    "sg:address":"644 Fitzhugh Blvd",
    "sg:city":"Smyrna",
    "sg:classifiers":[
        {
            "category":"Airport",
            "type":"Transportation"
        }
    ],
    "sg:phone":"+1 615 220 8841",
    "sg:postcode":"37167",
    "sg:province":"TN",
    "wof:name":"Symrna Airport Public Safety",
    "wof:placetype":"venue"
},
  "geometry": {"coordinates":[-86.510707,36.016525],"type":"Point"}
}