{
  "type": "Feature",
  "properties": {
    "addr:full":"1908 Schofield St Knoxville TN 37921",
    "addr:housenumber":"1908",
    "addr:postcode":"37921",
    "addr:street":"Schofield St",
    "iso:country":"US",
    "sg:address":"1908 Schofield St",
    "sg:city":"Knoxville",
    "sg:classifiers":[
        {
            "category":"Restaurant",
            "type":"Food & Drink"
        }
    ],
    "sg:phone":"+1 865 637 7537",
    "sg:postcode":"37921",
    "sg:province":"TN",
    "sg:tags":[
        "eating"
    ],
    "wof:name":"Bourbon Street Cafe",
    "wof:placetype":"venue"
},
  "geometry": {"coordinates":[-83.95550900000001,35.971668],"type":"Point"}
}