{
  "type": "Feature",
  "properties": {
    "addr:full":"2231 Smith Springs Rd Nashville TN 37217",
    "addr:housenumber":"2231",
    "addr:postcode":"37217",
    "addr:street":"Smith Springs Rd",
    "iso:country":"US",
    "sg:address":"2231 Smith Springs Rd",
    "sg:city":"Nashville",
    "sg:classifiers":[
        {
            "category":"Building & Trades",
            "subcategory":"Landscaping Services",
            "type":"Services"
        }
    ],
    "sg:phone":"+1 615 481 1228",
    "sg:postcode":"37217",
    "sg:province":"TN",
    "sg:tags":[
        "lawn",
        "maintenance",
        "grounds"
    ],
    "wof:name":"Jayspray Lawncare",
    "wof:placetype":"venue"
},
  "geometry": {"coordinates":[-86.64497799999999,36.096709],"type":"Point"}
}