{
  "type": "Feature",
  "properties": {
    "iso:country":"US",
    "sg:address":"102 Keene St",
    "sg:city":"Loudon",
    "sg:classifiers":[
        {
            "category":"Retail",
            "subcategory":"Auto Repair",
            "type":"Services"
        }
    ],
    "sg:phone":"+1 865 408 9113",
    "sg:postcode":"37774",
    "sg:province":"TN",
    "sg:tags":[
        "repairing",
        "automobile"
    ],
    "wof:name":"Keene Street Motor",
    "wof:placetype":"venue"
},
  "geometry": {"coordinates":[-84.34885,35.731304],"type":"Point"}
}