{
  "type": "Feature",
  "properties": {
    "iso:country":"US",
    "sg:address":"1289 Bridgestone Blvd",
    "sg:city":"La Vergne",
    "sg:classifiers":[
        {
            "category":"Manufacturing",
            "subcategory":"Chemicals & Compounds",
            "type":"Manufacturing & Wholesale Goods"
        }
    ],
    "sg:phone":"+1 615 793 1990",
    "sg:postcode":"37086",
    "sg:province":"TN",
    "sg:tags":[
        "ch",
        "nickel",
        "liquid",
        "mfg",
        "sulfate",
        "industrial",
        "chloride"
    ],
    "wof:name":"Palm Commodities Intl Inc",
    "wof:placetype":"venue"
},
  "geometry": {"coordinates":[-86.605956,36.007272],"type":"Point"}
}