{
  "type": "Feature",
  "properties": {
    "addr:full":"14 S Washington Ave Brownsville TN 38012",
    "addr:housenumber":"14",
    "addr:postcode":"38012",
    "addr:street":"S Washington Ave",
    "iso:country":"US",
    "sg:address":"14 S Washington Ave",
    "sg:city":"Brownsville",
    "sg:classifiers":[
        {
            "category":"Shopping",
            "subcategory":"Florist",
            "type":"Retail Goods"
        }
    ],
    "sg:phone":"+1 731 772 2856",
    "sg:postcode":"38012",
    "sg:province":"TN",
    "wof:name":"Brownsville Flower Shop",
    "wof:placetype":"venue"
},
  "geometry": {"coordinates":[-89.26207700000001,35.593584],"type":"Point"}
}