{
  "type": "Feature",
  "properties": {
    "addr:full":"10970 Veterans Memorial Dr Decherd TN 37324",
    "addr:housenumber":"10970",
    "addr:postcode":"37324",
    "addr:street":"Veterans Memorial Dr",
    "iso:country":"US",
    "sg:address":"10970 Veterans Memorial Dr",
    "sg:city":"Decherd",
    "sg:classifiers":[
        {
            "category":"Farming",
            "subcategory":"Livestock Farm",
            "type":"Manufacturing & Wholesale Goods"
        }
    ],
    "sg:phone":"+1 931 967 6305",
    "sg:postcode":"37324",
    "sg:province":"TN",
    "sg:tags":[
        "beef",
        "feedlot",
        "cattle"
    ],
    "wof:name":"Randy Buckner",
    "wof:placetype":"venue"
},
  "geometry": {"coordinates":[-85.95479,35.276024],"type":"Point"}
}