{
  "type": "Feature",
  "properties": {
    "addr:full":"2 W 2nd St Chattanooga TN 37402",
    "addr:housenumber":"2",
    "addr:postcode":"37402",
    "addr:street":"W 2Nd St",
    "iso:country":"US",
    "sg:address":"2 W 2nd St",
    "sg:city":"Chattanooga",
    "sg:classifiers":[
        {
            "category":"Professional",
            "subcategory":"Computer Services",
            "type":"Services"
        }
    ],
    "sg:phone":"+1 423 267 7733",
    "sg:postcode":"37402",
    "sg:province":"TN",
    "sg:tags":[
        "consultant",
        "designer"
    ],
    "wof:name":"FREELIANT.COM",
    "wof:placetype":"venue"
},
  "geometry": {"coordinates":[-85.31065599999999,35.054748],"type":"Point"}
}