{
  "type": "Feature",
  "properties": {
    "iso:country":"US",
    "sg:address":"1257 Roberson Spring Rd",
    "sg:city":"Loudon",
    "sg:classifiers":[
        {
            "category":"Freight",
            "type":"Transportation"
        }
    ],
    "sg:phone":"+1 865 458 3835",
    "sg:postcode":"37774",
    "sg:province":"TN",
    "sg:tags":[
        "general"
    ],
    "wof:name":"McBride Company of TN",
    "wof:placetype":"venue"
},
  "geometry": {"coordinates":[-84.360788,35.723453],"type":"Point"}
}