{
  "type": "Feature",
  "properties": {
    "iso:country":"US",
    "sg:address":"38 Country Square Rd",
    "sg:city":"Milan",
    "sg:classifiers":[
        {
            "category":"Retail",
            "subcategory":"Repair Shop",
            "type":"Services"
        }
    ],
    "sg:phone":"+1 731 686 9290",
    "sg:postcode":"38358",
    "sg:province":"TN",
    "sg:tags":[
        "welding"
    ],
    "wof:name":"JD Welding",
    "wof:placetype":"venue"
},
  "geometry": {"coordinates":[-88.793071,35.851317],"type":"Point"}
}