{
  "type": "Feature",
  "properties": {
    "iso:country":"US",
    "sg:address":"1225 E Stone Dr",
    "sg:city":"Kingsport",
    "sg:classifiers":[
        {
            "category":"Bars & Pubs",
            "type":"Food & Drink"
        }
    ],
    "sg:menulink":"http://www.allmenus.com/tn/kingsport/280532-pratts-barbque--honey-glazed/menu/",
    "sg:phone":"+1 423 246 5749",
    "sg:postcode":"37660",
    "sg:province":"TN",
    "sg:tags":[
        "barbecue",
        "american"
    ],
    "wof:name":"Pratt's Barbque & Honey Glazed",
    "wof:placetype":"venue"
},
  "geometry": {"coordinates":[-82.527845,36.551064],"type":"Point"}
}