{
  "type": "Feature",
  "properties": {
    "iso:country":"US",
    "sg:address":"1645 Bell Rd",
    "sg:city":"Nashville",
    "sg:classifiers":[
        {
            "category":"Personal",
            "subcategory":"Beauty Salon",
            "type":"Services"
        }
    ],
    "sg:phone":"+1 615 331 2855",
    "sg:postcode":"37211",
    "sg:province":"TN",
    "sg:tags":[
        "shop"
    ],
    "wof:name":"Before 9 Salon",
    "wof:placetype":"venue"
},
  "geometry": {"coordinates":[-86.70262200000001,36.045436],"type":"Point"}
}