{
  "type": "Feature",
  "properties": {
    "addr:full":"197 Cheyenne Dr Jackson TN 38305",
    "addr:housenumber":"197",
    "addr:postcode":"38305",
    "addr:street":"Cheyenne Dr",
    "iso:country":"US",
    "sg:address":"197 Cheyenne Dr",
    "sg:city":"Jackson",
    "sg:classifiers":[
        {
            "category":"Social Services",
            "subcategory":"Child Care",
            "type":"Services"
        }
    ],
    "sg:phone":"+1 731 668 6722",
    "sg:postcode":"38305",
    "sg:province":"TN",
    "sg:tags":[
        "day"
    ],
    "wof:name":"Kids First Child Devmnt Ctr",
    "wof:placetype":"venue"
},
  "geometry": {"coordinates":[-88.83413899999999,35.695775],"type":"Point"}
}