{
  "type": "Feature",
  "properties": {
    "iso:country":"US",
    "sg:address":"4105 Bennett Rd",
    "sg:city":"Chattanooga",
    "sg:classifiers":[
        {
            "category":"Organizations",
            "subcategory":"Community Association",
            "type":"Services"
        }
    ],
    "sg:phone":"+1 423 867 6413",
    "sg:postcode":"37412",
    "sg:province":"TN",
    "wof:name":"Woodmen of Wld Ldg 6 & 876",
    "wof:placetype":"venue"
},
  "geometry": {"coordinates":[-85.25229,34.991447],"type":"Point"}
}