{
  "type": "Feature",
  "properties": {
    "iso:country":"US",
    "sg:address":"2211 Oakwood Dr E",
    "sg:city":"Franklin",
    "sg:classifiers":[
        {
            "category":"Banks & Credit Unions",
            "subcategory":"Financial Services",
            "type":"Services"
        }
    ],
    "sg:phone":"+1 615 790 2383",
    "sg:postcode":"37064",
    "sg:province":"TN",
    "sg:tags":[
        "company",
        "holding"
    ],
    "wof:name":"Evans & Co Inc",
    "wof:placetype":"venue"
},
  "geometry": {"coordinates":[-86.857277,35.882708],"type":"Point"}
}