{
  "type": "Feature",
  "properties": {
    "iso:country":"US",
    "sg:address":"1741 Lower Sharon Rd",
    "sg:city":"Dresden",
    "sg:phone":"+1 731 364 2435",
    "sg:postcode":"38225",
    "sg:province":"TN",
    "sg:tags":[
        "farm",
        "field",
        "crop"
    ],
    "wof:name":"Crews Joe and W H",
    "wof:placetype":"venue"
},
  "geometry": {"coordinates":[-88.734067,36.2497],"type":"Point"}
}