{
  "type": "Feature",
  "properties": {
    "addr:full":"203 Downs Blvd Franklin TN 37064",
    "addr:housenumber":"203",
    "addr:postcode":"37064",
    "addr:street":"Downs Blvd",
    "iso:country":"US",
    "sg:address":"203 Downs Blvd",
    "sg:city":"Franklin",
    "sg:classifiers":[
        {
            "category":"Home & Garden",
            "subcategory":"Hardware",
            "type":"Retail Goods"
        }
    ],
    "sg:phone":"+1 615 794 3641",
    "sg:postcode":"37064",
    "sg:province":"TN",
    "sg:website":"www.harpethtruevalue.com",
    "wof:name":"True Value Hardware",
    "wof:placetype":"venue"
},
  "geometry": {"coordinates":[-86.880483,35.908175],"type":"Point"}
}