{
  "type": "Feature",
  "properties": {
    "iso:country":"US",
    "sg:address":"5301 Hickory Hollow Pkwy",
    "sg:city":"Antioch",
    "sg:classifiers":[
        {
            "category":"Professional",
            "type":"Services"
        }
    ],
    "sg:phone":"+1 615 731 2495",
    "sg:postcode":"37013",
    "sg:province":"TN",
    "wof:name":"Service Merchandise Co Hickory",
    "wof:placetype":"venue"
},
  "geometry": {"coordinates":[-86.654701,36.046435],"type":"Point"}
}