{
  "type": "Feature",
  "properties": {
    "addr:full":"6803 Blackberry Ct Harrison TN 37341",
    "addr:housenumber":"6803",
    "addr:postcode":"37341",
    "addr:street":"Blackberry Ct",
    "iso:country":"US",
    "sg:address":"6803 Blackberry Ct",
    "sg:city":"Harrison",
    "sg:classifiers":[
        {
            "category":"Building & Trades",
            "subcategory":"Landscaping Services",
            "type":"Services"
        }
    ],
    "sg:phone":"+1 423 344 2289",
    "sg:postcode":"37341",
    "sg:province":"TN",
    "wof:name":"Great Scapes",
    "wof:placetype":"venue"
},
  "geometry": {"coordinates":[-85.13213,35.119878],"type":"Point"}
}