{
  "type": "Feature",
  "properties": {
    "iso:country":"US",
    "sg:address":"2581 Scottsway Rd",
    "sg:city":"Memphis",
    "sg:classifiers":[
        {
            "category":"Retail",
            "subcategory":"Repair Shop",
            "type":"Services"
        }
    ],
    "sg:phone":"+1 901 365 0249",
    "sg:postcode":"38115",
    "sg:province":"TN",
    "sg:tags":[
        "armature",
        "used",
        "rewinding",
        "automobile"
    ],
    "wof:name":"Liles Motor Company",
    "wof:placetype":"venue"
},
  "geometry": {"coordinates":[-89.88725100000001,35.07753],"type":"Point"}
}