{
  "type": "Feature",
  "properties": {
    "iso:country":"US",
    "sg:address":"1108 N 5th St",
    "sg:city":"Nashville",
    "sg:classifiers":[
        {
            "category":"Shopping",
            "type":"Retail Goods"
        }
    ],
    "sg:phone":"+1 615 227 0617",
    "sg:postcode":"37207",
    "sg:province":"TN",
    "sg:tags":[
        "merchandise"
    ],
    "wof:name":"Shop Ovadanet Inc",
    "wof:placetype":"venue"
},
  "geometry": {"coordinates":[-86.76220499999999,36.192307],"type":"Point"}
}