{
  "type": "Feature",
  "properties": {
    "addr:full":"6718 Texas Valley Rd Knoxville TN 37938",
    "addr:housenumber":"6718",
    "addr:postcode":"37938",
    "addr:street":"Texas Valley Rd",
    "iso:country":"US",
    "sg:address":"6718 Texas Valley Rd",
    "sg:city":"Knoxville",
    "sg:classifiers":[
        {
            "category":"Professional",
            "subcategory":"Research",
            "type":"Services"
        }
    ],
    "sg:phone":"+1 865 925 4520",
    "sg:postcode":"37938",
    "sg:province":"TN",
    "sg:tags":[
        "environmental",
        "ecological"
    ],
    "wof:name":"International Compliance Svc",
    "wof:placetype":"venue"
},
  "geometry": {"coordinates":[-83.91331700000001,36.145957],"type":"Point"}
}