{
  "type": "Feature",
  "properties": {
    "iso:country":"US",
    "sg:address":"208 W Commerce St",
    "sg:city":"Lewisburg",
    "sg:classifiers":[
        {
            "category":"Manufacturing",
            "subcategory":"Jewelry",
            "type":"Manufacturing & Wholesale Goods"
        }
    ],
    "sg:phone":"+1 931 359 4653",
    "sg:postcode":"37091",
    "sg:province":"TN",
    "sg:tags":[
        "precious",
        "metal",
        "mfg"
    ],
    "wof:name":"Goldsmith Shop Inc",
    "wof:placetype":"venue"
},
  "geometry": {"coordinates":[-86.789221,35.4492],"type":"Point"}
}