{
  "type": "Feature",
  "properties": {
    "iso:country":"US",
    "sg:address":"5012 Old Rome Pike",
    "sg:city":"Lebanon",
    "sg:classifiers":[
        {
            "category":"Freight",
            "type":"Transportation"
        }
    ],
    "sg:phone":"+1 615 443 0198",
    "sg:postcode":"37087",
    "sg:province":"TN",
    "sg:tags":[
        "mover"
    ],
    "wof:name":"Phil's Moving Svc",
    "wof:placetype":"venue"
},
  "geometry": {"coordinates":[-86.131248,36.25204],"type":"Point"}
}