{
  "type": "Feature",
  "properties": {
    "addr:full":"6540 Dayton Mountain Hwy Dayton TN 37321",
    "addr:housenumber":"6540",
    "addr:postcode":"37321",
    "addr:street":"Dayton Mountain Hwy",
    "iso:country":"US",
    "sg:address":"6540 Dayton Mountain Hwy",
    "sg:city":"Dayton",
    "sg:classifiers":[
        {
            "category":"Professional",
            "type":"Services"
        }
    ],
    "sg:phone":"+1 423 775 9607",
    "sg:postcode":"37321",
    "sg:province":"TN",
    "wof:name":"Thomas Henschen",
    "wof:placetype":"venue"
},
  "geometry": {"coordinates":[-85.072844,35.548759],"type":"Point"}
}