{
  "type": "Feature",
  "properties": {
    "iso:country":"US",
    "sg:address":"177 Burley Dr",
    "sg:city":"Cleveland",
    "sg:classifiers":[
        {
            "category":"Retail",
            "subcategory":"Funeral Services",
            "type":"Services"
        }
    ],
    "sg:phone":"+1 423 472 6930",
    "sg:postcode":"37312",
    "sg:province":"TN",
    "wof:name":"Parker Home Building",
    "wof:placetype":"venue"
},
  "geometry": {"coordinates":[-84.93853300000001,35.191607],"type":"Point"}
}