{
  "type": "Feature",
  "properties": {
    "iso:country":"US",
    "sg:address":"1267 5th St",
    "sg:city":"Jellico",
    "sg:classifiers":[
        {
            "category":"Restaurant",
            "type":"Food & Drink"
        }
    ],
    "sg:menulink":"http://www.allmenus.com/tn/elk-valley/154929-hardees/menu/",
    "sg:phone":"+1 423 784 7975",
    "sg:postcode":"37762",
    "sg:province":"TN",
    "sg:tags":[
        "burger",
        "american"
    ],
    "wof:name":"Hardee's",
    "wof:placetype":"venue"
},
  "geometry": {"coordinates":[-84.115785,36.582135],"type":"Point"}
}