{
  "type": "Feature",
  "properties": {
    "addr:full":"907 E Lamar Alexander Pkwy Maryville TN 37804",
    "addr:housenumber":"907",
    "addr:postcode":"37804",
    "addr:street":"E Lamar Alexander Pkwy",
    "iso:country":"US",
    "sg:address":"907 E Lamar Alexander Pkwy",
    "sg:city":"Maryville",
    "sg:classifiers":[
        {
            "category":"Health Services",
            "subcategory":"Doctor",
            "type":"Services"
        }
    ],
    "sg:phone":"+1 865 977 5590",
    "sg:postcode":"37804",
    "sg:province":"TN",
    "sg:tags":[
        "physician",
        "surgeon"
    ],
    "wof:name":"Blount Memorial Breast Health",
    "wof:placetype":"venue"
},
  "geometry": {"coordinates":[-83.959025,35.755039],"type":"Point"}
}