{
  "type": "Feature",
  "properties": {
    "iso:country":"US",
    "sg:address":"1966 Edgar Dillard Rd",
    "sg:city":"Greenbrier",
    "sg:classifiers":[
        {
            "category":"Building & Trades",
            "subcategory":"Cleaning & Sanitation",
            "type":"Services"
        }
    ],
    "sg:phone":"+1 615 643 6890",
    "sg:postcode":"37073",
    "sg:province":"TN",
    "sg:tags":[
        "janitor"
    ],
    "wof:name":"HGG Cleaners",
    "wof:placetype":"venue"
},
  "geometry": {"coordinates":[-86.85315199999999,36.395586],"type":"Point"}
}