{
  "type": "Feature",
  "properties": {
    "iso:country":"US",
    "sg:address":"7700 Gleason Dr",
    "sg:city":"Knoxville",
    "sg:classifiers":[
        {
            "category":"Taxi",
            "type":"Transportation"
        }
    ],
    "sg:phone":"+1 865 693 0777",
    "sg:postcode":"37919",
    "sg:province":"TN",
    "wof:name":"A & A Taxi",
    "wof:placetype":"venue"
},
  "geometry": {"coordinates":[-84.035431,35.922291],"type":"Point"}
}