{
  "type": "Feature",
  "properties": {
    "iso:country":"US",
    "sg:address":"725 W Broad St",
    "sg:city":"Smithville",
    "sg:classifiers":[
        {
            "category":"Wholesale",
            "subcategory":"Farm Supplies",
            "type":"Manufacturing & Wholesale Goods"
        }
    ],
    "sg:phone":"+1 615 597 4134",
    "sg:postcode":"37166",
    "sg:province":"TN",
    "wof:name":"De Kalb's Farmers Co-Op",
    "wof:placetype":"venue"
},
  "geometry": {"coordinates":[-85.842305,35.961953],"type":"Point"}
}