{
  "type": "Feature",
  "properties": {
    "addr:full":"3888 Macon Rd Memphis TN 38122",
    "addr:housenumber":"3888",
    "addr:postcode":"38122",
    "addr:street":"Macon Rd",
    "iso:country":"US",
    "sg:address":"3888 Macon Rd",
    "sg:city":"Memphis",
    "sg:classifiers":[
        {
            "category":"Autos & Motor Vehicles",
            "subcategory":"Fuel & Gas Station",
            "type":"Retail Goods"
        }
    ],
    "sg:phone":"+1 901 454 5800",
    "sg:postcode":"38122",
    "sg:province":"TN",
    "sg:tags":[
        "oil"
    ],
    "wof:name":"Z Best Market",
    "wof:placetype":"venue"
},
  "geometry": {"coordinates":[-89.928736,35.162293],"type":"Point"}
}