{
  "type": "Feature",
  "properties": {
    "addr:full":"109 Holiday Ct Franklin TN 37067",
    "addr:housenumber":"109",
    "addr:postcode":"37067",
    "addr:street":"Holiday Ct",
    "iso:country":"US",
    "sg:address":"109 Holiday Ct",
    "sg:city":"Franklin",
    "sg:classifiers":[
        {
            "category":"Professional",
            "subcategory":"Employment Agencies",
            "type":"Services"
        }
    ],
    "sg:phone":"+1 615 599 8888",
    "sg:postcode":"37067",
    "sg:province":"TN",
    "sg:tags":[
        "consultant",
        "search",
        "executive",
        "recruiting"
    ],
    "wof:name":"Gemstone Recruiting Inc",
    "wof:placetype":"venue"
},
  "geometry": {"coordinates":[-86.828003,35.917202],"type":"Point"}
}