{
  "type": "Feature",
  "properties": {
    "iso:country":"US",
    "sg:address":"1727 Ghost Creek Cove",
    "sg:city":"Collierville",
    "sg:classifiers":[
        {
            "category":"Building & Trades",
            "subcategory":"Landscaping Services",
            "type":"Services"
        }
    ],
    "sg:phone":"+1 901 850 8661",
    "sg:postcode":"38017",
    "sg:province":"TN",
    "sg:tags":[
        "lawn",
        "maintenance",
        "grounds"
    ],
    "wof:name":"Mid South Lawn Svc",
    "wof:placetype":"venue"
},
  "geometry": {"coordinates":[-89.697723,35.090421],"type":"Point"}
}