{
  "type": "Feature",
  "properties": {
    "iso:country":"US",
    "sg:address":"227 W Depot St",
    "sg:city":"Greeneville",
    "sg:classifiers":[
        {
            "category":"Retail",
            "subcategory":"Laundry & Dry Cleaning",
            "type":"Services"
        }
    ],
    "sg:phone":"+1 423 638 8141",
    "sg:postcode":"37743",
    "sg:province":"TN",
    "sg:tags":[
        "drycleaning",
        "plant",
        "pres",
        "garment"
    ],
    "wof:name":"Vogue Cleaners & Tailors",
    "wof:placetype":"venue"
},
  "geometry": {"coordinates":[-82.834687,36.164537],"type":"Point"}
}