{
  "type": "Feature",
  "properties": {
    "iso:country":"US",
    "sg:address":"1210 Tate Rd",
    "sg:city":"Bolivar",
    "sg:classifiers":[
        {
            "category":"Organizations",
            "subcategory":"Religious Organization",
            "type":"Services"
        }
    ],
    "sg:phone":"+1 731 658 3432",
    "sg:postcode":"38008",
    "sg:province":"TN",
    "sg:tags":[
        "church"
    ],
    "wof:name":"Trinity Baptist Church",
    "wof:placetype":"venue"
},
  "geometry": {"coordinates":[-89.007176,35.266078],"type":"Point"}
}