{
  "type": "Feature",
  "properties": {
    "iso:country":"US",
    "sg:address":"298 Main St",
    "sg:city":"Maynardville",
    "sg:classifiers":[
        {
            "category":"Government",
            "subcategory":"Office",
            "type":"Public Place"
        }
    ],
    "sg:phone":"+1 865 992 3292",
    "sg:postcode":"37807",
    "sg:province":"TN",
    "sg:tags":[
        "county",
        "resource"
    ],
    "wof:name":"Union County Office-The Aging",
    "wof:placetype":"venue"
},
  "geometry": {"coordinates":[-83.811807,36.242923],"type":"Point"}
}