{
  "type": "Feature",
  "properties": {
    "iso:country":"US",
    "sg:address":"3154 N Watkins St",
    "sg:city":"Memphis",
    "sg:classifiers":[
        {
            "category":"Autos & Motor Vehicles",
            "subcategory":"Auto Supplies",
            "type":"Retail Goods"
        },
        {
            "category":"Retail",
            "subcategory":"Auto Repair",
            "type":"Services"
        }
    ],
    "sg:phone":"+1 901 358 3579",
    "sg:postcode":"38127",
    "sg:province":"TN",
    "sg:tags":[
        "transmission",
        "brake",
        "transmissions-other"
    ],
    "wof:name":"Caldwell Auto Repair",
    "wof:placetype":"venue"
},
  "geometry": {"coordinates":[-90.00367199999999,35.211989],"type":"Point"}
}