{
  "type": "Feature",
  "properties": {
    "iso:country":"US",
    "sg:address":"2688 Pine Valley Rd",
    "sg:city":"Cookeville",
    "sg:classifiers":[
        {
            "category":"Building & Trades",
            "subcategory":"Construction",
            "type":"Services"
        }
    ],
    "sg:phone":"+1 931 537 3493",
    "sg:postcode":"38506",
    "sg:province":"TN",
    "sg:tags":[
        "house"
    ],
    "wof:name":"Sound Construction",
    "wof:placetype":"venue"
},
  "geometry": {"coordinates":[-85.449066,36.209902],"type":"Point"}
}