{
  "type": "Feature",
  "properties": {
    "iso:country":"US",
    "sg:address":"3507 Kellys Ferry Rd",
    "sg:city":"Chattanooga",
    "sg:classifiers":[
        {
            "category":"Shopping",
            "subcategory":"Used Merchandise",
            "type":"Retail Goods"
        }
    ],
    "sg:phone":"+1 423 821 6099",
    "sg:postcode":"37419",
    "sg:province":"TN",
    "wof:name":"Tone Club",
    "wof:placetype":"venue"
},
  "geometry": {"coordinates":[-85.373335,35.024016],"type":"Point"}
}