{
  "type": "Feature",
  "properties": {
    "addr:full":"808 W 6th St Columbia TN 38401",
    "addr:housenumber":"808",
    "addr:postcode":"38401",
    "addr:street":"W 6Th St",
    "iso:country":"US",
    "sg:address":"808 W 6th St",
    "sg:city":"Columbia",
    "sg:classifiers":[
        {
            "category":"Organizations",
            "subcategory":"Religious Organization",
            "type":"Services"
        }
    ],
    "sg:phone":"+1 931 388 6934",
    "sg:postcode":"38401",
    "sg:province":"TN",
    "sg:tags":[
        "church"
    ],
    "wof:name":"Mount Vernon Baptist Church",
    "wof:placetype":"venue"
},
  "geometry": {"coordinates":[-87.049401,35.618367],"type":"Point"}
}