{
  "type": "Feature",
  "properties": {
    "addr:full":"355 N Blythe Ave Gallatin TN 37066",
    "addr:housenumber":"355",
    "addr:postcode":"37066",
    "addr:street":"N Blythe Ave",
    "iso:country":"US",
    "sg:address":"355 N Blythe Ave",
    "sg:city":"Gallatin",
    "sg:classifiers":[
        {
            "category":"Organizations",
            "subcategory":"Religious Organization",
            "type":"Services"
        }
    ],
    "sg:phone":"+1 615 452 3137",
    "sg:postcode":"37066",
    "sg:province":"TN",
    "wof:name":"Saint Luke Africn Methdst Epis",
    "wof:placetype":"venue"
},
  "geometry": {"coordinates":[-86.452918,36.391926],"type":"Point"}
}