{
  "type": "Feature",
  "properties": {
    "addr:full":"3571 Parkway Pigeon Forge TN 37863",
    "addr:housenumber":"3571",
    "addr:postcode":"37863",
    "addr:street":"Parkway",
    "iso:country":"US",
    "sg:address":"3571 Parkway",
    "sg:city":"Pigeon Forge",
    "sg:classifiers":[
        {
            "category":"Travel",
            "subcategory":"Hotels & Motels",
            "type":"Entertainment"
        }
    ],
    "sg:phone":"+1 865 453 4784",
    "sg:postcode":"37863",
    "sg:province":"TN",
    "wof:name":"Tennessee Mountain Lodge",
    "wof:placetype":"venue"
},
  "geometry": {"coordinates":[-83.552556,35.784624],"type":"Point"}
}