{
  "type": "Feature",
  "properties": {
    "iso:country":"US",
    "sg:address":"1416 Lebanon Pike",
    "sg:city":"Nashville",
    "sg:classifiers":[
        {
            "category":"Wholesale",
            "subcategory":"Machinery & Supplies",
            "type":"Manufacturing & Wholesale Goods"
        }
    ],
    "sg:phone":"+1 615 242 7260",
    "sg:postcode":"37210",
    "sg:province":"TN",
    "sg:tags":[
        "equipment"
    ],
    "wof:name":"Rigging Gear Sales-Tennessee",
    "wof:placetype":"venue"
},
  "geometry": {"coordinates":[-86.736873,36.154433],"type":"Point"}
}