{
  "type": "Feature",
  "properties": {
    "addr:full":"765 Florence Rd Savannah TN 38372",
    "addr:housenumber":"765",
    "addr:postcode":"38372",
    "addr:street":"Florence Rd",
    "iso:country":"US",
    "sg:address":"765 Florence Rd",
    "sg:city":"Savannah",
    "sg:classifiers":[
        {
            "category":"Shopping",
            "subcategory":"Pharmacy",
            "type":"Retail Goods"
        }
    ],
    "sg:phone":"+1 731 925 3956",
    "sg:postcode":"38372",
    "sg:province":"TN",
    "wof:name":"Prescription Shop",
    "wof:placetype":"venue"
},
  "geometry": {"coordinates":[-88.239369,35.212321],"type":"Point"}
}