{
  "type": "Feature",
  "properties": {
    "addr:full":"918 Tennessee Blvd Lebanon TN 37087",
    "addr:housenumber":"918",
    "addr:postcode":"37087",
    "addr:street":"Tennessee Blvd",
    "iso:country":"US",
    "sg:address":"918 Tennessee Blvd",
    "sg:city":"Lebanon",
    "sg:classifiers":[
        {
            "category":"Retail",
            "subcategory":"Auto Repair",
            "type":"Services"
        }
    ],
    "sg:phone":"+1 615 443 3502",
    "sg:postcode":"37087",
    "sg:province":"TN",
    "sg:tags":[
        "repairing",
        "automobile"
    ],
    "wof:name":"Cedar City Diesel",
    "wof:placetype":"venue"
},
  "geometry": {"coordinates":[-86.271548,36.202978],"type":"Point"}
}