{
  "type": "Feature",
  "properties": {
    "iso:country":"US",
    "sg:address":"1120 Davidson Rd",
    "sg:city":"Nashville",
    "sg:classifiers":[
        {
            "category":"Professional",
            "type":"Services"
        }
    ],
    "sg:phone":"+1 615 356 6620",
    "sg:postcode":"37205",
    "sg:province":"TN",
    "wof:name":"Mike Miller Yards",
    "wof:placetype":"venue"
},
  "geometry": {"coordinates":[-86.89600299999999,36.122181],"type":"Point"}
}