{
  "type": "Feature",
  "properties": {
    "addr:full":"1093 N Maple St Adamsville TN 38310",
    "addr:housenumber":"1093",
    "addr:postcode":"38310",
    "addr:street":"N Maple St",
    "iso:country":"US",
    "sg:address":"1093 N Maple St",
    "sg:city":"Adamsville",
    "sg:classifiers":[
        {
            "category":"Wholesale",
            "subcategory":"Machinery & Supplies",
            "type":"Manufacturing & Wholesale Goods"
        }
    ],
    "sg:phone":"+1 731 645 6044",
    "sg:postcode":"38310",
    "sg:province":"TN",
    "sg:tags":[
        "janitor"
    ],
    "wof:name":"Better Source Supply",
    "wof:placetype":"venue"
},
  "geometry": {"coordinates":[-88.391086,35.277364],"type":"Point"}
}