{
  "type": "Feature",
  "properties": {
    "iso:country":"US",
    "sg:address":"1113 Tusculum Blvd",
    "sg:city":"Greeneville",
    "sg:classifiers":[
        {
            "category":"Professional",
            "subcategory":"Advertising",
            "type":"Services"
        }
    ],
    "sg:phone":"+1 423 798 9992",
    "sg:postcode":"37745",
    "sg:province":"TN",
    "sg:tags":[
        "mailing",
        "shipping"
    ],
    "wof:name":"UPS Store",
    "wof:placetype":"venue"
},
  "geometry": {"coordinates":[-82.806579,36.169485],"type":"Point"}
}