{
  "type": "Feature",
  "properties": {
    "iso:country":"US",
    "sg:address":"601 Kraft St",
    "sg:city":"Clarksville",
    "sg:classifiers":[
        {
            "category":"Wholesale",
            "subcategory":"Medical Equipment & Supplies",
            "type":"Manufacturing & Wholesale Goods"
        }
    ],
    "sg:phone":"+1 931 645 7866",
    "sg:postcode":"37040",
    "sg:province":"TN",
    "sg:tags":[
        "physician",
        "surgeon"
    ],
    "wof:name":"Hopewell Medical Center",
    "wof:placetype":"venue"
},
  "geometry": {"coordinates":[-87.359246,36.541655],"type":"Point"}
}