{
  "type": "Feature",
  "properties": {
    "iso:country":"US",
    "sg:address":"320 N Susong St",
    "sg:city":"Newport",
    "sg:classifiers":[
        {
            "category":"Shopping",
            "type":"Retail Goods"
        },
        {
            "category":"Communications",
            "type":"Services"
        }
    ],
    "sg:phone":"+1 423 625 2096",
    "sg:postcode":"37821",
    "sg:province":"TN",
    "sg:tags":[
        "carrier",
        "merchandise"
    ],
    "wof:name":"C & C Communications",
    "wof:placetype":"venue"
},
  "geometry": {"coordinates":[-83.19090199999999,35.980669],"type":"Point"}
}