{
  "type": "Feature",
  "properties": {
    "iso:country":"US",
    "sg:address":"6677 Red Birch Dr",
    "sg:city":"Memphis",
    "sg:classifiers":[
        {
            "category":"Professional",
            "type":"Services"
        }
    ],
    "sg:phone":"+1 901 795 5275",
    "sg:postcode":"38115",
    "sg:province":"TN",
    "wof:name":"Stillpoint Life Center",
    "wof:placetype":"venue"
},
  "geometry": {"coordinates":[-89.842127,35.040185],"type":"Point"}
}