{
  "type": "Feature",
  "properties": {
    "iso:country":"US",
    "sg:address":"3443 Dickerson Pike",
    "sg:city":"Nashville",
    "sg:classifiers":[
        {
            "category":"Health Services",
            "subcategory":"Podiatrist",
            "type":"Services"
        }
    ],
    "sg:phone":"+1 615 312 4219",
    "sg:postcode":"37207",
    "sg:province":"TN",
    "sg:website":"www.trennerpodiatry.com",
    "wof:name":"Skyline Foot & Ankle Ctr",
    "wof:placetype":"venue"
},
  "geometry": {"coordinates":[-86.75720800000001,36.241164],"type":"Point"}
}