{
  "type": "Feature",
  "properties": {
    "addr:full":"4330 Harding Pl Nashville TN 37205",
    "addr:housenumber":"4330",
    "addr:postcode":"37205",
    "addr:street":"Harding Pl",
    "iso:country":"US",
    "sg:address":"4330 Harding Pl",
    "sg:city":"Nashville",
    "sg:classifiers":[
        {
            "category":"Home & Garden",
            "subcategory":"Hardware",
            "type":"Retail Goods"
        }
    ],
    "sg:phone":"+1 615 292 1532",
    "sg:postcode":"37205",
    "sg:province":"TN",
    "wof:name":"Belle Meade-Hart Hardware",
    "wof:placetype":"venue"
},
  "geometry": {"coordinates":[-86.85021999999999,36.093315],"type":"Point"}
}