{
  "type": "Feature",
  "properties": {
    "iso:country":"US",
    "sg:address":"1811 Winding Way Dr",
    "sg:city":"White House",
    "sg:classifiers":[
        {
            "category":"Building & Trades",
            "subcategory":"Construction",
            "type":"Services"
        }
    ],
    "sg:phone":"+1 615 672 5868",
    "sg:postcode":"37188",
    "sg:province":"TN",
    "sg:tags":[
        "concrete",
        "contractor"
    ],
    "wof:name":"Mc Koin's Concrete",
    "wof:placetype":"venue"
},
  "geometry": {"coordinates":[-86.66055900000001,36.418867],"type":"Point"}
}