{
  "type": "Feature",
  "properties": {
    "addr:full":"1246 Louisville Hwy Goodlettsville TN 37072",
    "addr:housenumber":"1246",
    "addr:postcode":"37072",
    "addr:street":"Louisville Hwy",
    "iso:country":"US",
    "sg:address":"1246 Louisville Hwy",
    "sg:city":"Goodlettsville",
    "sg:classifiers":[
        {
            "category":"Government",
            "subcategory":"Office",
            "type":"Public Place"
        },
        {
            "category":"Government",
            "subcategory":"Police Station",
            "type":"Public Place"
        }
    ],
    "sg:phone":"+1 615 859 0880",
    "sg:postcode":"37072",
    "sg:province":"TN",
    "sg:tags":[
        "city",
        "protection"
    ],
    "sg:website":"www.cityofmillersville.com",
    "wof:name":"Millersville City Hall",
    "wof:placetype":"venue"
},
  "geometry": {"coordinates":[-86.69760599999999,36.386647],"type":"Point"}
}