{
  "type": "Feature",
  "properties": {
    "iso:country":"US",
    "sg:address":"535 Maddox-Simpson Pkwy",
    "sg:city":"Lebanon",
    "sg:classifiers":[
        {
            "category":"Manufacturing",
            "subcategory":"Printing",
            "type":"Manufacturing & Wholesale Goods"
        }
    ],
    "sg:phone":"+1 615 251 2311",
    "sg:postcode":"37090",
    "sg:province":"TN",
    "sg:tags":[
        "periodical"
    ],
    "wof:name":"Christian Resources",
    "wof:placetype":"venue"
},
  "geometry": {"coordinates":[-86.285347,36.176327],"type":"Point"}
}