{
  "type": "Feature",
  "properties": {
    "iso:country":"US",
    "sg:address":"929 Spring Creek Rd",
    "sg:city":"Chattanooga",
    "sg:classifiers":[
        {
            "category":"Utilities",
            "subcategory":"Water",
            "type":"Services"
        }
    ],
    "sg:phone":"+1 423 855 4044",
    "sg:postcode":"37412",
    "sg:province":"TN",
    "sg:tags":[
        "bulk",
        "companies-bottled"
    ],
    "wof:name":"Waters & Whitaker MD",
    "wof:placetype":"venue"
},
  "geometry": {"coordinates":[-85.21807099999999,35.000019],"type":"Point"}
}