{
  "type": "Feature",
  "properties": {
    "iso:country":"US",
    "sg:address":"165 Wears Valley Rd",
    "sg:city":"Pigeon Forge",
    "sg:classifiers":[
        {
            "category":"Home & Garden",
            "subcategory":"Home Furnishings",
            "type":"Retail Goods"
        }
    ],
    "sg:phone":"+1 865 453 1323",
    "sg:postcode":"37863",
    "sg:province":"TN",
    "sg:tags":[
        "housewares"
    ],
    "wof:name":"Farberware Outlet Store",
    "wof:placetype":"venue"
},
  "geometry": {"coordinates":[-83.577389,35.803705],"type":"Point"}
}