{
  "type": "Feature",
  "properties": {
    "iso:country":"US",
    "sg:address":"311 Bob Ford Rd",
    "sg:city":"Jonesborough",
    "sg:classifiers":[
        {
            "category":"Cinema",
            "subcategory":"Movie Rental",
            "type":"Entertainment"
        }
    ],
    "sg:phone":"+1 423 753 2013",
    "sg:postcode":"37659",
    "sg:province":"TN",
    "sg:tags":[
        "motion",
        "picture",
        "distributor",
        "film",
        "exchange"
    ],
    "wof:name":"Rey Lo",
    "wof:placetype":"venue"
},
  "geometry": {"coordinates":[-82.518569,36.403216],"type":"Point"}
}