{
  "type": "Feature",
  "properties": {
    "iso:country":"US",
    "sg:address":"19175 Alberta St",
    "sg:city":"Oneida",
    "sg:classifiers":[
        {
            "category":"Government",
            "subcategory":"Office",
            "type":"Public Place"
        }
    ],
    "sg:phone":"+1 423 569 4680",
    "sg:postcode":"37841",
    "sg:province":"TN",
    "sg:tags":[
        "executive"
    ],
    "wof:name":"Veterans Service Officer",
    "wof:placetype":"venue"
},
  "geometry": {"coordinates":[-84.49633,36.525276],"type":"Point"}
}