{
  "type": "Feature",
  "properties": {
    "addr:full":"3983 Homewood Rd Memphis TN 38118",
    "addr:housenumber":"3983",
    "addr:postcode":"38118",
    "addr:street":"Homewood Rd",
    "iso:country":"US",
    "sg:address":"3983 Homewood Rd",
    "sg:city":"Memphis",
    "sg:classifiers":[
        {
            "category":"Wholesale",
            "subcategory":"Machinery & Supplies",
            "type":"Manufacturing & Wholesale Goods"
        }
    ],
    "sg:phone":"+1 901 368 0741",
    "sg:postcode":"38118",
    "sg:province":"TN",
    "sg:tags":[
        "compressor",
        "gas"
    ],
    "wof:name":"Rotary Screw Sales & Svc Co",
    "wof:placetype":"venue"
},
  "geometry": {"coordinates":[-89.925746,35.039305],"type":"Point"}
}