{
  "type": "Feature",
  "properties": {
    "iso:country":"US",
    "sg:address":"1149 W Point Rd",
    "sg:city":"Lawrenceburg",
    "sg:classifiers":[
        {
            "category":"Retail",
            "subcategory":"Auto Repair",
            "type":"Services"
        }
    ],
    "sg:phone":"+1 931 762 0078",
    "sg:postcode":"38464",
    "sg:province":"TN",
    "sg:tags":[
        "automotive",
        "part",
        "supply"
    ],
    "wof:name":"J & G Tire Center Inc",
    "wof:placetype":"venue"
},
  "geometry": {"coordinates":[-87.42659,35.200378],"type":"Point"}
}