{
  "type": "Feature",
  "properties": {
    "addr:full":"5310 Hungerford Rd Memphis TN 38118",
    "addr:housenumber":"5310",
    "addr:postcode":"38118",
    "addr:street":"Hungerford Rd",
    "iso:country":"US",
    "sg:address":"5310 Hungerford Rd",
    "sg:city":"Memphis",
    "sg:classifiers":[
        {
            "category":"Building & Trades",
            "subcategory":"Construction",
            "type":"Services"
        }
    ],
    "sg:phone":"+1 901 367 9184",
    "sg:postcode":"38118",
    "sg:province":"TN",
    "sg:tags":[
        "contractor"
    ],
    "wof:name":"Mitchell's Contracting Svc",
    "wof:placetype":"venue"
},
  "geometry": {"coordinates":[-89.885643,35.024344],"type":"Point"}
}