{
  "type": "Feature",
  "properties": {
    "iso:country":"US",
    "sg:address":"232 Sky-Wa-Mo Rd",
    "sg:city":"Bluff City",
    "sg:classifiers":[
        {
            "category":"Professional",
            "type":"Services"
        }
    ],
    "sg:phone":"+1 423 538 3489",
    "sg:postcode":"37618",
    "sg:province":"TN",
    "wof:name":"Keith D Glover",
    "wof:placetype":"venue"
},
  "geometry": {"coordinates":[-82.209825,36.440028],"type":"Point"}
}