{
  "type": "Feature",
  "properties": {
    "iso:country":"US",
    "sg:address":"442 Metroplex Dr",
    "sg:city":"Nashville",
    "sg:classifiers":[
        {
            "category":"Social Services",
            "type":"Services"
        }
    ],
    "sg:phone":"+1 615 833 7735",
    "sg:postcode":"37211",
    "sg:province":"TN",
    "sg:tags":[
        "individual",
        "family"
    ],
    "wof:name":"World Relief",
    "wof:placetype":"venue"
},
  "geometry": {"coordinates":[-86.69638,36.089337],"type":"Point"}
}