{
  "type": "Feature",
  "properties": {
    "addr:full":"1617 N Broad St Tazewell TN 37879",
    "addr:housenumber":"1617",
    "addr:postcode":"37879",
    "addr:street":"N Broad St",
    "iso:country":"US",
    "sg:address":"1617 N Broad St",
    "sg:city":"Tazewell",
    "sg:classifiers":[
        {
            "category":"Restaurant",
            "type":"Food & Drink"
        }
    ],
    "sg:phone":"+1 423 626 3521",
    "sg:postcode":"37879",
    "sg:province":"TN",
    "wof:name":"Frostee Freeze Drive-In",
    "wof:placetype":"venue"
},
  "geometry": {"coordinates":[-83.56967,36.45081],"type":"Point"}
}