{
  "type": "Feature",
  "properties": {
    "iso:country":"US",
    "sg:address":"353 Johnny Cash Pkwy",
    "sg:city":"Hendersonville",
    "sg:classifiers":[
        {
            "category":"Retail",
            "subcategory":"Funeral Services",
            "type":"Services"
        }
    ],
    "sg:phone":"+1 615 824 3855",
    "sg:postcode":"37075",
    "sg:province":"TN",
    "sg:tags":[
        "director"
    ],
    "wof:name":"Harpeth Hills Memory Gardens",
    "wof:placetype":"venue"
},
  "geometry": {"coordinates":[-86.595315,36.312451],"type":"Point"}
}