{
  "type": "Feature",
  "properties": {
    "addr:full":"11531 Gulf Stream Rd Arlington TN 38002",
    "addr:housenumber":"11531",
    "addr:postcode":"38002",
    "addr:street":"Gulf Stream Rd",
    "iso:country":"US",
    "sg:address":"11531 Gulf Stream Rd",
    "sg:city":"Arlington",
    "sg:classifiers":[
        {
            "category":"Wholesale",
            "subcategory":"Machinery & Supplies",
            "type":"Manufacturing & Wholesale Goods"
        }
    ],
    "sg:phone":"+1 901 867 3400",
    "sg:postcode":"38002",
    "sg:province":"TN",
    "sg:tags":[
        "equipment",
        "lawn",
        "garden"
    ],
    "wof:name":"Dixie Sales Co",
    "wof:placetype":"venue"
},
  "geometry": {"coordinates":[-89.679795,35.287663],"type":"Point"}
}