{
  "type": "Feature",
  "properties": {
    "iso:country":"US",
    "sg:address":"503 E Hill St",
    "sg:city":"La Follette",
    "sg:classifiers":[
        {
            "category":"Building & Trades",
            "subcategory":"Landscaping Services",
            "type":"Services"
        }
    ],
    "sg:phone":"+1 423 563 0277",
    "sg:postcode":"37766",
    "sg:province":"TN",
    "sg:tags":[
        "tree"
    ],
    "wof:name":"Marty Jackson's Specialized",
    "wof:placetype":"venue"
},
  "geometry": {"coordinates":[-84.107633,36.377219],"type":"Point"}
}