{
  "type": "Feature",
  "properties": {
    "iso:country":"US",
    "sg:address":"296 S Main St",
    "sg:city":"Middleton",
    "sg:classifiers":[
        {
            "category":"Government",
            "subcategory":"Post Office",
            "type":"Public Place"
        }
    ],
    "sg:phone":"+1 731 376 0175",
    "sg:postcode":"38052",
    "sg:province":"TN",
    "sg:tags":[
        "postal",
        "us"
    ],
    "wof:name":"Middleton Post Office",
    "wof:placetype":"venue"
},
  "geometry": {"coordinates":[-88.892701,35.058652],"type":"Point"}
}