{
  "type": "Feature",
  "properties": {
    "iso:country":"US",
    "sg:address":"641 E Commerce St",
    "sg:city":"Lewisburg",
    "sg:classifiers":[
        {
            "category":"Cinema",
            "subcategory":"Movie Rental",
            "type":"Entertainment"
        }
    ],
    "sg:phone":"+1 931 359 4387",
    "sg:postcode":"37091",
    "sg:province":"TN",
    "sg:tags":[
        "video",
        "tape"
    ],
    "wof:name":"Video Mania",
    "wof:placetype":"venue"
},
  "geometry": {"coordinates":[-86.777579,35.446136],"type":"Point"}
}