{
  "type": "Feature",
  "properties": {
    "iso:country":"US",
    "sg:address":"6209 Lee Hwy",
    "sg:city":"Chattanooga",
    "sg:classifiers":[
        {
            "category":"Shopping",
            "subcategory":"Musical Instruments",
            "type":"Retail Goods"
        }
    ],
    "sg:phone":"+1 423 499 0600",
    "sg:postcode":"37421",
    "sg:province":"TN",
    "wof:name":"Summitt Baldwin Pianos Organs",
    "wof:placetype":"venue"
},
  "geometry": {"coordinates":[-85.185507,35.030456],"type":"Point"}
}