{
  "type": "Feature",
  "properties": {
    "addr:full":"522 Madison St Shelbyville TN 37160",
    "addr:housenumber":"522",
    "addr:postcode":"37160",
    "addr:street":"Madison St",
    "iso:country":"US",
    "sg:address":"522 Madison St",
    "sg:city":"Shelbyville",
    "sg:classifiers":[
        {
            "category":"Autos & Motor Vehicles",
            "subcategory":"Automobile Sales",
            "type":"Retail Goods"
        }
    ],
    "sg:phone":"+1 931 680 9522",
    "sg:postcode":"37160",
    "sg:province":"TN",
    "sg:tags":[
        "used"
    ],
    "wof:name":"Ruby Auto Sales",
    "wof:placetype":"venue"
},
  "geometry": {"coordinates":[-86.452698,35.488156],"type":"Point"}
}