{
  "type": "Feature",
  "properties": {
    "iso:country":"US",
    "sg:address":"2668 Charles Bryan Rd",
    "sg:city":"Memphis",
    "sg:classifiers":[
        {
            "category":"Building & Trades",
            "subcategory":"Landscaping Services",
            "type":"Services"
        }
    ],
    "sg:phone":"+1 901 388 2229",
    "sg:postcode":"38134",
    "sg:province":"TN",
    "wof:name":"Lawn Service",
    "wof:placetype":"venue"
},
  "geometry": {"coordinates":[-89.844989,35.197851],"type":"Point"}
}