{
  "type": "Feature",
  "properties": {
    "addr:full":"5853 Mount View Rd Antioch TN 37013",
    "addr:housenumber":"5853",
    "addr:postcode":"37013",
    "addr:street":"Mount View Rd",
    "iso:country":"US",
    "sg:address":"5853 Mount View Rd",
    "sg:city":"Antioch",
    "sg:classifiers":[
        {
            "category":"Building & Trades",
            "subcategory":"Landscaping Services",
            "type":"Services"
        }
    ],
    "sg:phone":"+1 615 641 7235",
    "sg:postcode":"37013",
    "sg:province":"TN",
    "sg:tags":[
        "lawn",
        "maintenance",
        "grounds"
    ],
    "wof:name":"Ground F X",
    "wof:placetype":"venue"
},
  "geometry": {"coordinates":[-86.622359,36.051782],"type":"Point"}
}