{
  "type": "Feature",
  "properties": {
    "addr:full":"1991 Gainesboro Grade Cookeville TN 38501",
    "addr:housenumber":"1991",
    "addr:postcode":"38501",
    "addr:street":"Gainesboro Grade",
    "iso:country":"US",
    "sg:address":"1991 Gainesboro Grade",
    "sg:city":"Cookeville",
    "sg:classifiers":[
        {
            "category":"Shopping",
            "type":"Retail Goods"
        }
    ],
    "sg:phone":"+1 931 528 5307",
    "sg:postcode":"38501",
    "sg:province":"TN",
    "sg:tags":[
        "picture",
        "frame"
    ],
    "wof:name":"Universal Arts & Frames",
    "wof:placetype":"venue"
},
  "geometry": {"coordinates":[-85.534049,36.191121],"type":"Point"}
}