{
  "type": "Feature",
  "properties": {
    "addr:full":"669 Whitney Ave Memphis TN 38127",
    "addr:housenumber":"669",
    "addr:postcode":"38127",
    "addr:street":"Whitney Ave",
    "iso:country":"US",
    "sg:address":"669 Whitney Ave",
    "sg:city":"Memphis",
    "sg:classifiers":[
        {
            "category":"Parking",
            "type":"Transportation"
        }
    ],
    "sg:phone":"+1 901 377 5920",
    "sg:postcode":"38127",
    "sg:province":"TN",
    "sg:tags":[
        "automobile"
    ],
    "wof:name":"Sonny Berryhill",
    "wof:placetype":"venue"
},
  "geometry": {"coordinates":[-90.04120500000001,35.206354],"type":"Point"}
}