{
  "type": "Feature",
  "properties": {
    "addr:full":"167 N Main St Ste B214 Memphis TN 38103",
    "addr:housenumber":"167",
    "addr:postcode":"38103",
    "addr:street":"N Main St Ste B214",
    "iso:country":"US",
    "sg:address":"167 N Main St Ste B214",
    "sg:city":"Memphis",
    "sg:classifiers":[
        {
            "category":"Government",
            "subcategory":"Office",
            "type":"Public Place"
        }
    ],
    "sg:phone":"+1 901 544 3972",
    "sg:postcode":"38103",
    "sg:province":"TN",
    "sg:tags":[
        "government-united",
        "state"
    ],
    "wof:name":"Federal Railroad Administration",
    "wof:placetype":"venue"
},
  "geometry": {"coordinates":[-90.05094800000001,35.149802],"type":"Point"}
}