{
  "type": "Feature",
  "properties": {
    "iso:country":"US",
    "sg:address":"80 Stagg Rd",
    "sg:city":"Oakland",
    "sg:classifiers":[
        {
            "category":"Retail",
            "subcategory":"Laundry & Dry Cleaning",
            "type":"Services"
        }
    ],
    "sg:phone":"+1 901 465 8844",
    "sg:postcode":"38060",
    "sg:province":"TN",
    "sg:tags":[
        "cleaners",
        "rug",
        "carpet"
    ],
    "wof:name":"Towne & Country Carpet Cleaner",
    "wof:placetype":"venue"
},
  "geometry": {"coordinates":[-89.50288500000001,35.213088],"type":"Point"}
}