{
  "type": "Feature",
  "properties": {
    "iso:country":"US",
    "sg:address":"603 Troupe Rd",
    "sg:city":"Shelbyville",
    "sg:classifiers":[
        {
            "category":"Retail",
            "subcategory":"Repair Shop",
            "type":"Services"
        }
    ],
    "sg:phone":"+1 931 680 1119",
    "sg:postcode":"37160",
    "sg:province":"TN",
    "sg:tags":[
        "product",
        "taxidermist",
        "mfg"
    ],
    "wof:name":"Alford's Taxidermy",
    "wof:placetype":"venue"
},
  "geometry": {"coordinates":[-86.50710599999999,35.518172],"type":"Point"}
}