{
  "type": "Feature",
  "properties": {
    "addr:full":"112 Oak Ridge Tpke Oak Ridge TN 37830",
    "addr:housenumber":"112",
    "addr:postcode":"37830",
    "addr:street":"Oak Ridge Tpke",
    "iso:country":"US",
    "sg:address":"112 Oak Ridge Tpke",
    "sg:city":"Oak Ridge",
    "sg:classifiers":[
        {
            "category":"Food & Beverages",
            "subcategory":"Groceries & Convenience Stores",
            "type":"Retail Goods"
        }
    ],
    "sg:phone":"+1 865 481 8110",
    "sg:postcode":"37830",
    "sg:province":"TN",
    "wof:name":"Gas N Go",
    "wof:placetype":"venue"
},
  "geometry": {"coordinates":[-84.208229,36.046312],"type":"Point"}
}