{
  "type": "Feature",
  "properties": {
    "iso:country":"US",
    "sg:address":"100 S Gay St",
    "sg:city":"Knoxville",
    "sg:classifiers":[
        {
            "category":"Museum",
            "type":"Entertainment"
        }
    ],
    "sg:phone":"+1 865 546 9705",
    "sg:postcode":"37902",
    "sg:province":"TN",
    "sg:tags":[
        "organization",
        "arts",
        "information"
    ],
    "wof:name":"African American Appalachian",
    "wof:placetype":"venue"
},
  "geometry": {"coordinates":[-83.919865,35.967884],"type":"Point"}
}