{
  "type": "Feature",
  "properties": {
    "iso:country":"US",
    "sg:address":"2003 Wilcox Blvd",
    "sg:city":"Chattanooga",
    "sg:classifiers":[
        {
            "category":"Organizations",
            "subcategory":"Religious Organization",
            "type":"Services"
        }
    ],
    "sg:phone":"+1 423 629 1442",
    "sg:postcode":"37406",
    "sg:province":"TN",
    "sg:tags":[
        "church"
    ],
    "wof:name":"Cathedral Praise/Urban Ministr",
    "wof:placetype":"venue"
},
  "geometry": {"coordinates":[-85.26334799999999,35.053655],"type":"Point"}
}