{
  "type": "Feature",
  "properties": {
    "addr:full":"3574 Glyn Carroll Cove Memphis TN 38133",
    "addr:housenumber":"3574",
    "addr:postcode":"38133",
    "addr:street":"Glyn Carroll Cove",
    "iso:country":"US",
    "sg:address":"3574 Glyn Carroll Cove",
    "sg:city":"Memphis",
    "sg:classifiers":[
        {
            "category":"Professional",
            "type":"Services"
        }
    ],
    "sg:phone":"+1 901 383 8031",
    "sg:postcode":"38133",
    "sg:province":"TN",
    "wof:name":"Mike Beavers",
    "wof:placetype":"venue"
},
  "geometry": {"coordinates":[-89.764509,35.222172],"type":"Point"}
}