{
  "type": "Feature",
  "properties": {
    "addr:full":"742 Bazel Rd Harriman TN 37748",
    "addr:housenumber":"742",
    "addr:postcode":"37748",
    "addr:street":"Bazel Rd",
    "iso:country":"US",
    "sg:address":"742 Bazel Rd",
    "sg:city":"Harriman",
    "sg:classifiers":[
        {
            "category":"Building & Trades",
            "subcategory":"Construction",
            "type":"Services"
        }
    ],
    "sg:phone":"+1 865 882 2637",
    "sg:postcode":"37748",
    "sg:province":"TN",
    "sg:tags":[
        "house"
    ],
    "wof:name":"Hackworth Construction",
    "wof:placetype":"venue"
},
  "geometry": {"coordinates":[-84.528964,35.966359],"type":"Point"}
}