{
  "type": "Feature",
  "properties": {
    "addr:full":"3983 Geraldus Ave Memphis TN 38111",
    "addr:housenumber":"3983",
    "addr:postcode":"38111",
    "addr:street":"Geraldus Ave",
    "iso:country":"US",
    "sg:address":"3983 Geraldus Ave",
    "sg:city":"Memphis",
    "sg:classifiers":[
        {
            "category":"Organizations",
            "subcategory":"Religious Organization",
            "type":"Services"
        }
    ],
    "sg:phone":"+1 901 745 3700",
    "sg:postcode":"38111",
    "sg:province":"TN",
    "wof:name":"Cross Temple Church Of God",
    "wof:placetype":"venue"
},
  "geometry": {"coordinates":[-89.927603,35.088794],"type":"Point"}
}