{
  "type": "Feature",
  "properties": {
    "iso:country":"US",
    "sg:address":"3873 Northbrook Dr",
    "sg:city":"Nashville",
    "sg:classifiers":[
        {
            "category":"Building & Trades",
            "subcategory":"Cleaning & Sanitation",
            "type":"Services"
        }
    ],
    "sg:phone":"+1 615 262 3185",
    "sg:postcode":"37207",
    "sg:province":"TN",
    "sg:tags":[
        "maintenance"
    ],
    "wof:name":"Thompsons Janitor Services",
    "wof:placetype":"venue"
},
  "geometry": {"coordinates":[-86.77605,36.249546],"type":"Point"}
}