{
  "type": "Feature",
  "properties": {
    "iso:country":"US",
    "sg:address":"7439 US Hwy 70 S",
    "sg:city":"Nashville",
    "sg:classifiers":[
        {
            "category":"Building & Trades",
            "subcategory":"Cleaning & Sanitation",
            "type":"Services"
        }
    ],
    "sg:phone":"+1 615 646 1094",
    "sg:postcode":"37221",
    "sg:province":"TN",
    "sg:tags":[
        "maintenance"
    ],
    "wof:name":"Lees Maintance",
    "wof:placetype":"venue"
},
  "geometry": {"coordinates":[-86.93748600000001,36.074632],"type":"Point"}
}