{
  "type": "Feature",
  "properties": {
    "iso:country":"US",
    "sg:address":"390 Mallory Station Rd",
    "sg:city":"Franklin",
    "sg:classifiers":[
        {
            "category":"Professional",
            "subcategory":"Employment Agencies",
            "type":"Services"
        }
    ],
    "sg:phone":"+1 615 771 1117",
    "sg:postcode":"37067",
    "sg:province":"TN",
    "sg:tags":[
        "opportunity"
    ],
    "wof:name":"Wood Personnel Svc",
    "wof:placetype":"venue"
},
  "geometry": {"coordinates":[-86.81853700000001,35.952282],"type":"Point"}
}