{
  "type": "Feature",
  "properties": {
    "iso:country":"US",
    "sg:address":"2330 E Andrew Johnson Hwy",
    "sg:city":"Morristown",
    "sg:classifiers":[
        {
            "category":"Retail",
            "subcategory":"Laundry & Dry Cleaning",
            "type":"Services"
        }
    ],
    "sg:phone":"+1 423 581 3381",
    "sg:postcode":"37814",
    "sg:province":"TN",
    "sg:tags":[
        "cleaners"
    ],
    "sg:website":"www.concordcustomcleaners.com",
    "wof:name":"Concord Custom Cleaners",
    "wof:placetype":"venue"
},
  "geometry": {"coordinates":[-83.26456,36.226771],"type":"Point"}
}