{
  "type": "Feature",
  "properties": {
    "iso:country":"US",
    "sg:address":"5388 Crestview Dr",
    "sg:city":"Memphis",
    "sg:classifiers":[
        {
            "category":"Autos & Motor Vehicles",
            "subcategory":"Auto Supplies",
            "type":"Retail Goods"
        }
    ],
    "sg:phone":"+1 901 373 5551",
    "sg:postcode":"38134",
    "sg:province":"TN",
    "sg:tags":[
        "wheel",
        "cover"
    ],
    "wof:name":"American Racing",
    "wof:placetype":"venue"
},
  "geometry": {"coordinates":[-89.885237,35.170996],"type":"Point"}
}