{
  "type": "Feature",
  "properties": {
    "iso:country":"US",
    "sg:address":"2795 Jockey Rd",
    "sg:city":"Limestone",
    "sg:classifiers":[
        {
            "category":"Building & Trades",
            "subcategory":"Construction",
            "type":"Services"
        }
    ],
    "sg:phone":"+1 423 257 2156",
    "sg:postcode":"37681",
    "sg:province":"TN",
    "sg:tags":[
        "contractor"
    ],
    "wof:name":"Roberts Drywall & Construction",
    "wof:placetype":"venue"
},
  "geometry": {"coordinates":[-82.67344900000001,36.273249],"type":"Point"}
}