{
  "type": "Feature",
  "properties": {
    "addr:full":"5871 Poplar Ave Memphis TN 38119",
    "addr:housenumber":"5871",
    "addr:postcode":"38119",
    "addr:street":"Poplar Ave",
    "iso:country":"US",
    "sg:address":"5871 Poplar Ave",
    "sg:city":"Memphis",
    "sg:classifiers":[
        {
            "category":"Restaurant",
            "type":"Food & Drink"
        }
    ],
    "sg:menulink":"http://www.allmenus.com/tn/memphis/33631-river-oaks-restaurant/menu/",
    "sg:phone":"+1 901 683 9305",
    "sg:postcode":"38119",
    "sg:province":"TN",
    "sg:tags":[
        "american"
    ],
    "wof:name":"River Oaks Restaurant",
    "wof:placetype":"venue"
},
  "geometry": {"coordinates":[-89.86708,35.103447],"type":"Point"}
}