{
  "type": "Feature",
  "properties": {
    "addr:full":"3503 Belmont Blvd Nashville TN 37215",
    "addr:housenumber":"3503",
    "addr:postcode":"37215",
    "addr:street":"Belmont Blvd",
    "iso:country":"US",
    "sg:address":"3503 Belmont Blvd",
    "sg:city":"Nashville",
    "sg:classifiers":[
        {
            "category":"Banks & Credit Unions",
            "subcategory":"Financial Services",
            "type":"Services"
        }
    ],
    "sg:phone":"+1 615 297 1854",
    "sg:postcode":"37215",
    "sg:province":"TN",
    "sg:tags":[
        "company",
        "bank",
        "holding"
    ],
    "wof:name":"Zoe Healthcare Inc",
    "wof:placetype":"venue"
},
  "geometry": {"coordinates":[-86.80002399999999,36.113112],"type":"Point"}
}