{
  "type": "Feature",
  "properties": {
    "iso:country":"US",
    "sg:address":"2440 Chelsea Ave",
    "sg:city":"Memphis",
    "sg:classifiers":[
        {
            "category":"Shopping",
            "subcategory":"Gifts & Souvenirs",
            "type":"Retail Goods"
        }
    ],
    "sg:phone":"+1 901 458 5820",
    "sg:postcode":"38108",
    "sg:province":"TN",
    "sg:tags":[
        "novelty"
    ],
    "wof:name":"Daryls Gifts & Novelties",
    "wof:placetype":"venue"
},
  "geometry": {"coordinates":[-89.97619400000001,35.174713],"type":"Point"}
}