{
  "type": "Feature",
  "properties": {
    "addr:full":"813 N Cumberland St Lebanon TN 37087",
    "addr:housenumber":"813",
    "addr:postcode":"37087",
    "addr:street":"N Cumberland St",
    "iso:country":"US",
    "sg:address":"813 N Cumberland St",
    "sg:city":"Lebanon",
    "sg:classifiers":[
        {
            "category":"Retail",
            "subcategory":"Auto Repair",
            "type":"Services"
        }
    ],
    "sg:phone":"+1 615 444 8322",
    "sg:postcode":"37087",
    "sg:province":"TN",
    "sg:tags":[
        "shop",
        "body",
        "painting",
        "automobile",
        "collision"
    ],
    "wof:name":"Shippers Auto Collision Repair",
    "wof:placetype":"venue"
},
  "geometry": {"coordinates":[-86.290436,36.222412],"type":"Point"}
}