{
  "type": "Feature",
  "properties": {
    "iso:country":"US",
    "sg:address":"5067 US Hwy 64",
    "sg:city":"Copperhill",
    "sg:classifiers":[
        {
            "category":"Home & Garden",
            "subcategory":"Furniture",
            "type":"Retail Goods"
        }
    ],
    "sg:phone":"+1 423 496 4233",
    "sg:postcode":"37317",
    "sg:province":"NC",
    "wof:name":"Logcraft Mountain Homes",
    "wof:placetype":"venue"
},
  "geometry": {"coordinates":[-84.38623699999999,35.029878],"type":"Point"}
}