{
  "type": "Feature",
  "properties": {
    "addr:full":"838 Belvoir Hills Dr Chattanooga TN 37412",
    "addr:housenumber":"838",
    "addr:postcode":"37412",
    "addr:street":"Belvoir Hills Dr",
    "iso:country":"US",
    "sg:address":"838 Belvoir Hills Dr",
    "sg:city":"Chattanooga",
    "sg:classifiers":[
        {
            "category":"Education",
            "subcategory":"Special Training",
            "type":"Public Place"
        }
    ],
    "sg:phone":"+1 423 629 6094",
    "sg:postcode":"37412",
    "sg:province":"TN",
    "wof:name":"Barnard Astronomical Society",
    "wof:placetype":"venue"
},
  "geometry": {"coordinates":[-85.248332,35.003916],"type":"Point"}
}