{
  "type": "Feature",
  "properties": {
    "iso:country":"US",
    "sg:address":"804 N Water Ave",
    "sg:city":"Gallatin",
    "sg:classifiers":[
        {
            "category":"Restaurant",
            "type":"Food & Drink"
        }
    ],
    "sg:phone":"+1 615 452 0535",
    "sg:postcode":"37066",
    "sg:province":"TN",
    "sg:tags":[
        "eating"
    ],
    "wof:name":"Gertie's Diner",
    "wof:placetype":"venue"
},
  "geometry": {"coordinates":[-86.445257,36.403415],"type":"Point"}
}