{
  "type": "Feature",
  "properties": {
    "addr:full":"435 S Pkwy W Memphis TN 38109",
    "addr:housenumber":"435",
    "addr:postcode":"38109",
    "addr:street":"S Pkwy W",
    "iso:country":"US",
    "sg:address":"435 S Pkwy W",
    "sg:city":"Memphis",
    "sg:classifiers":[
        {
            "category":"Sports & Exercise",
            "subcategory":"Golf",
            "type":"Entertainment"
        }
    ],
    "sg:phone":"+1 901 774 4340",
    "sg:postcode":"38109",
    "sg:province":"TN",
    "sg:tags":[
        "course",
        "executive",
        "public"
    ],
    "wof:name":"Parks Commission",
    "wof:placetype":"venue"
},
  "geometry": {"coordinates":[-90.075836,35.107965],"type":"Point"}
}