{
  "type": "Feature",
  "properties": {
    "iso:country":"US",
    "sg:address":"1160 Peach Orchard Rd",
    "sg:city":"Cookeville",
    "sg:classifiers":[
        {
            "category":"Building & Trades",
            "subcategory":"Plumbing",
            "type":"Services"
        }
    ],
    "sg:phone":"+1 931 526 5821",
    "sg:postcode":"38501",
    "sg:province":"TN",
    "sg:tags":[
        "plumbing",
        "contractor"
    ],
    "wof:name":"Wheeler Plumbing Co",
    "wof:placetype":"venue"
},
  "geometry": {"coordinates":[-85.569142,36.189779],"type":"Point"}
}