{
  "type": "Feature",
  "properties": {
    "iso:country":"US",
    "sg:address":"3034 Argyle Ave",
    "sg:city":"Murfreesboro",
    "sg:classifiers":[
        {
            "category":"Building & Trades",
            "subcategory":"Landscaping Services",
            "type":"Services"
        }
    ],
    "sg:phone":"+1 615 896 1454",
    "sg:postcode":"37127",
    "sg:province":"TN",
    "sg:tags":[
        "landscape"
    ],
    "wof:name":"Earthly Designs Landscaping",
    "wof:placetype":"venue"
},
  "geometry": {"coordinates":[-86.394407,35.783255],"type":"Point"}
}