{
  "type": "Feature",
  "properties": {
    "addr:full":"3492 Suzanne Dr Memphis TN 38127",
    "addr:housenumber":"3492",
    "addr:postcode":"38127",
    "addr:street":"Suzanne Dr",
    "iso:country":"US",
    "sg:address":"3492 Suzanne Dr",
    "sg:city":"Memphis",
    "sg:classifiers":[
        {
            "category":"Professional",
            "type":"Services"
        }
    ],
    "sg:phone":"+1 901 357 2234",
    "sg:postcode":"38127",
    "sg:province":"TN",
    "wof:name":"Address America Memphis Corp",
    "wof:placetype":"venue"
},
  "geometry": {"coordinates":[-89.983138,35.220469],"type":"Point"}
}