{
  "type": "Feature",
  "properties": {
    "addr:full":"2648 Broad Ave Memphis TN 38112",
    "addr:housenumber":"2648",
    "addr:postcode":"38112",
    "addr:street":"Broad Ave",
    "iso:country":"US",
    "sg:address":"2648 Broad Ave",
    "sg:city":"Memphis",
    "sg:classifiers":[
        {
            "category":"Retail",
            "subcategory":"Veterinary Services",
            "type":"Services"
        }
    ],
    "sg:phone":"+1 901 362 2393",
    "sg:postcode":"38112",
    "sg:province":"TN",
    "sg:tags":[
        "clinic",
        "veterinarian"
    ],
    "sg:website":"www.petvax.com",
    "wof:name":"Petvax",
    "wof:placetype":"venue"
},
  "geometry": {"coordinates":[-89.97144900000001,35.147719],"type":"Point"}
}