{
  "type": "Feature",
  "properties": {
    "addr:full":"472 Lasco St Somerville TN 38012",
    "addr:housenumber":"472",
    "addr:postcode":"38012",
    "addr:street":"Lasco St",
    "iso:country":"US",
    "sg:address":"472 Lasco St",
    "sg:city":"Somerville",
    "sg:classifiers":[
        {
            "category":"Building & Trades",
            "subcategory":"Construction",
            "type":"Services"
        }
    ],
    "sg:phone":"+1 901 465 2251",
    "sg:postcode":"38012",
    "sg:province":"TN",
    "sg:tags":[
        "house"
    ],
    "wof:name":"LL & Construction",
    "wof:placetype":"venue"
},
  "geometry": {"coordinates":[-89.270208,35.587637],"type":"Point"}
}