{
  "type": "Feature",
  "properties": {
    "addr:full":"1126 Mississippi Blvd Memphis TN 38126",
    "addr:housenumber":"1126",
    "addr:postcode":"38126",
    "addr:street":"Mississippi Blvd",
    "iso:country":"US",
    "sg:address":"1126 Mississippi Blvd",
    "sg:city":"Memphis",
    "sg:classifiers":[
        {
            "category":"Personal",
            "subcategory":"Beauty Salon",
            "type":"Services"
        }
    ],
    "sg:phone":"+1 901 948 6706",
    "sg:postcode":"38126",
    "sg:province":"TN",
    "sg:tags":[
        "shop"
    ],
    "wof:name":"Gentry's Barber & Beauty Shop",
    "wof:placetype":"venue"
},
  "geometry": {"coordinates":[-90.037301,35.116411],"type":"Point"}
}