{
  "type": "Feature",
  "properties": {
    "iso:country":"US",
    "sg:address":"4408 Dayton Blvd",
    "sg:city":"Chattanooga",
    "sg:classifiers":[
        {
            "category":"Restaurant",
            "type":"Food & Drink"
        }
    ],
    "sg:phone":"+1 423 875 3151",
    "sg:postcode":"37415",
    "sg:province":"TN",
    "sg:tags":[
        "eating"
    ],
    "wof:name":"Dub's Place",
    "wof:placetype":"venue"
},
  "geometry": {"coordinates":[-85.28350500000001,35.129042],"type":"Point"}
}