{
  "type": "Feature",
  "properties": {
    "addr:full":"1810 Stewart Pl Nashville TN 37203",
    "addr:housenumber":"1810",
    "addr:postcode":"37203",
    "addr:street":"Stewart Pl",
    "iso:country":"US",
    "sg:address":"1810 Stewart Pl",
    "sg:city":"Nashville",
    "sg:classifiers":[
        {
            "category":"Travel",
            "subcategory":"Campground",
            "type":"Entertainment"
        }
    ],
    "sg:phone":"+1 615 889 5198",
    "sg:postcode":"37203",
    "sg:province":"TN",
    "sg:tags":[
        "trailer"
    ],
    "wof:name":"Seven Points Campground",
    "wof:placetype":"venue"
},
  "geometry": {"coordinates":[-86.77135199999999,36.135232],"type":"Point"}
}