{
  "type": "Feature",
  "properties": {
    "iso:country":"US",
    "sg:address":"16192 Highland Dr",
    "sg:city":"Mc Kenzie",
    "sg:classifiers":[
        {
            "category":"Banks & Credit Unions",
            "subcategory":"Bank",
            "type":"Services"
        }
    ],
    "sg:phone":"+1 731 352 0100",
    "sg:postcode":"38201",
    "sg:province":"TN",
    "sg:tags":[
        "loan",
        "real estate"
    ],
    "wof:name":"H & H Mortgage Co",
    "wof:placetype":"venue"
},
  "geometry": {"coordinates":[-88.501377,36.134204],"type":"Point"}
}