{
  "type": "Feature",
  "properties": {
    "iso:country":"US",
    "sg:address":"2129 S Germantown Rd",
    "sg:city":"Germantown",
    "sg:classifiers":[
        {
            "category":"Wholesale",
            "subcategory":"Non-durable Goods",
            "type":"Manufacturing & Wholesale Goods"
        }
    ],
    "sg:phone":"+1 901 755 6096",
    "sg:postcode":"38138",
    "sg:province":"TN",
    "sg:tags":[
        "advertising"
    ],
    "wof:name":"Class Act",
    "wof:placetype":"venue"
},
  "geometry": {"coordinates":[-89.810153,35.089935],"type":"Point"}
}