{
  "type": "Feature",
  "properties": {
    "iso:country":"US",
    "sg:address":"143 4th Ave N",
    "sg:city":"Franklin",
    "sg:classifiers":[
        {
            "category":"Professional",
            "type":"Services"
        }
    ],
    "sg:phone":"+1 615 591 2112",
    "sg:postcode":"37064",
    "sg:province":"TN",
    "wof:name":"Musiccitycom Inc",
    "wof:placetype":"venue"
},
  "geometry": {"coordinates":[-86.87124300000001,35.925742],"type":"Point"}
}