{
  "type": "Feature",
  "properties": {
    "iso:country":"US",
    "sg:address":"3916 Nolensville Pike",
    "sg:city":"Nashville",
    "sg:classifiers":[
        {
            "category":"Real Estate",
            "subcategory":"Real Estate Agent",
            "type":"Services"
        },
        {
            "category":"Shopping",
            "subcategory":"Tobacco",
            "type":"Retail Goods"
        }
    ],
    "sg:phone":"+1 615 832 1214",
    "sg:postcode":"37211",
    "sg:province":"TN",
    "sg:tags":[
        "cigarette",
        "cigar",
        "dealer"
    ],
    "wof:name":"Real Discount Tobacco & Beer",
    "wof:placetype":"venue"
},
  "geometry": {"coordinates":[-86.728191,36.084971],"type":"Point"}
}