{
  "type": "Feature",
  "properties": {
    "addr:full":"5138 Old Summer Rd Memphis TN 38122",
    "addr:housenumber":"5138",
    "addr:postcode":"38122",
    "addr:street":"Old Summer Rd",
    "iso:country":"US",
    "sg:address":"5138 Old Summer Rd",
    "sg:city":"Memphis",
    "sg:classifiers":[
        {
            "category":"Shopping",
            "subcategory":"Crafts & Fabrics",
            "type":"Retail Goods"
        }
    ],
    "sg:phone":"+1 901 683 2424",
    "sg:postcode":"38122",
    "sg:province":"TN",
    "sg:tags":[
        "sewing",
        "piece"
    ],
    "wof:name":"Hancock Fabrics",
    "wof:placetype":"venue"
},
  "geometry": {"coordinates":[-89.890064,35.149846],"type":"Point"}
}