{
  "type": "Feature",
  "properties": {
    "addr:full":"3248 Fairbanks St Memphis TN 38128",
    "addr:housenumber":"3248",
    "addr:postcode":"38128",
    "addr:street":"Fairbanks St",
    "iso:country":"US",
    "sg:address":"3248 Fairbanks St",
    "sg:city":"Memphis",
    "sg:classifiers":[
        {
            "category":"Professional",
            "subcategory":"Computer Services",
            "type":"Services"
        }
    ],
    "sg:phone":"+1 901 381 9296",
    "sg:postcode":"38128",
    "sg:province":"TN",
    "wof:name":"Tennessee On-Site Professional",
    "wof:placetype":"venue"
},
  "geometry": {"coordinates":[-89.92268,35.214487],"type":"Point"}
}