{
  "type": "Feature",
  "properties": {
    "addr:full":"3294 Poplar Ave Memphis TN 38111",
    "addr:housenumber":"3294",
    "addr:postcode":"38111",
    "addr:street":"Poplar Ave",
    "iso:country":"US",
    "sg:address":"3294 Poplar Ave",
    "sg:city":"Memphis",
    "sg:classifiers":[
        {
            "category":"Health Services",
            "subcategory":"Doctor",
            "type":"Services"
        }
    ],
    "sg:phone":"+1 901 362 8671",
    "sg:postcode":"38111",
    "sg:province":"TN",
    "sg:tags":[
        "physician",
        "surgeon"
    ],
    "wof:name":"Ali Mahmood MD",
    "wof:placetype":"venue"
},
  "geometry": {"coordinates":[-89.95252499999999,35.129844],"type":"Point"}
}