{
  "type": "Feature",
  "properties": {
    "addr:full":"2308 Dickerson Pike Nashville TN 37207",
    "addr:housenumber":"2308",
    "addr:postcode":"37207",
    "addr:street":"Dickerson Pike",
    "iso:country":"US",
    "sg:address":"2308 Dickerson Pike",
    "sg:city":"Nashville",
    "sg:classifiers":[
        {
            "category":"Autos & Motor Vehicles",
            "subcategory":"Automobile Sales",
            "type":"Retail Goods"
        }
    ],
    "sg:phone":"+1 615 226 7045",
    "sg:postcode":"37207",
    "sg:province":"TN",
    "sg:tags":[
        "used"
    ],
    "wof:name":"R B Auto Sales",
    "wof:placetype":"venue"
},
  "geometry": {"coordinates":[-86.767403,36.20824],"type":"Point"}
}