{
  "type": "Feature",
  "properties": {
    "iso:country":"US",
    "sg:address":"395 Interstate Dr",
    "sg:city":"Manchester",
    "sg:classifiers":[
        {
            "category":"Health Services",
            "subcategory":"Clinic",
            "type":"Services"
        },
        {
            "category":"Social Services",
            "type":"Services"
        }
    ],
    "sg:phone":"+1 931 723 8744",
    "sg:postcode":"37355",
    "sg:province":"TN",
    "sg:tags":[
        "nursing",
        "skilled",
        "outpatient",
        "specialty",
        "citizen",
        "senior",
        "care"
    ],
    "wof:name":"Manchester Health Care Center",
    "wof:placetype":"venue"
},
  "geometry": {"coordinates":[-86.074381,35.496412],"type":"Point"}
}