{
  "type": "Feature",
  "properties": {
    "iso:country":"US",
    "sg:address":"2576 Bearwallow Rd",
    "sg:city":"Ashland City",
    "sg:classifiers":[
        {
            "category":"Building & Trades",
            "subcategory":"Construction",
            "type":"Services"
        }
    ],
    "sg:phone":"+1 615 792 5019",
    "sg:postcode":"37015",
    "sg:province":"TN",
    "sg:tags":[
        "general",
        "contractor"
    ],
    "wof:name":"Binkley Raybon Dozier & Backho",
    "wof:placetype":"venue"
},
  "geometry": {"coordinates":[-86.975741,36.311103],"type":"Point"}
}