{
  "type": "Feature",
  "properties": {
    "iso:country":"US",
    "sg:address":"136 S Illinois Ave",
    "sg:city":"Oak Ridge",
    "sg:classifiers":[
        {
            "category":"Building & Trades",
            "subcategory":"Electrical",
            "type":"Services"
        }
    ],
    "sg:phone":"+1 865 425 0749",
    "sg:postcode":"37830",
    "sg:province":"TN",
    "sg:tags":[
        "electric",
        "contractor"
    ],
    "wof:name":"Edison Electric",
    "wof:placetype":"venue"
},
  "geometry": {"coordinates":[-84.26477800000001,36.008282],"type":"Point"}
}