{
  "type": "Feature",
  "properties": {
    "addr:full":"573 S Lowry St Smyrna TN 37167",
    "addr:housenumber":"573",
    "addr:postcode":"37167",
    "addr:street":"S Lowry St",
    "iso:country":"US",
    "sg:address":"573 S Lowry St",
    "sg:city":"Smyrna",
    "sg:classifiers":[
        {
            "category":"Food & Beverages",
            "subcategory":"Specialty",
            "type":"Retail Goods"
        }
    ],
    "sg:phone":"+1 615 459 0807",
    "sg:postcode":"37167",
    "sg:province":"TN",
    "wof:name":"GNC",
    "wof:placetype":"venue"
},
  "geometry": {"coordinates":[-86.494872,35.955373],"type":"Point"}
}