{
  "type": "Feature",
  "properties": {
    "addr:full":"2800 Autumn Ave Memphis TN 38112",
    "addr:housenumber":"2800",
    "addr:postcode":"38112",
    "addr:street":"Autumn Ave",
    "iso:country":"US",
    "sg:address":"2800 Autumn Ave",
    "sg:city":"Memphis",
    "sg:classifiers":[
        {
            "category":"Wholesale",
            "subcategory":"Furniture",
            "type":"Manufacturing & Wholesale Goods"
        }
    ],
    "sg:phone":"+1 901 327 7488",
    "sg:postcode":"38112",
    "sg:province":"TN",
    "wof:name":"Global Church Service",
    "wof:placetype":"venue"
},
  "geometry": {"coordinates":[-89.967726,35.146779],"type":"Point"}
}