{
  "type": "Feature",
  "properties": {
    "addr:full":"758 Upper Cove Loop Rd Dayton TN 37321",
    "addr:housenumber":"758",
    "addr:postcode":"37321",
    "addr:street":"Upper Cove Loop Rd",
    "iso:country":"US",
    "sg:address":"758 Upper Cove Loop Rd",
    "sg:city":"Dayton",
    "sg:classifiers":[
        {
            "category":"Home & Garden",
            "subcategory":"Furniture",
            "type":"Retail Goods"
        },
        {
            "category":"Home & Garden",
            "subcategory":"Garden Supply",
            "type":"Retail Goods"
        }
    ],
    "sg:phone":"+1 423 775 5731",
    "sg:postcode":"37321",
    "sg:province":"TN",
    "sg:tags":[
        "lawn",
        "mower"
    ],
    "wof:name":"Gatto Enterprises",
    "wof:placetype":"venue"
},
  "geometry": {"coordinates":[-85.040643,35.503496],"type":"Point"}
}