{
  "type": "Feature",
  "properties": {
    "addr:full":"107 N Porter St Winchester TN 37398",
    "addr:housenumber":"107",
    "addr:postcode":"37398",
    "addr:street":"N Porter St",
    "iso:country":"US",
    "sg:address":"107 N Porter St",
    "sg:city":"Winchester",
    "sg:classifiers":[
        {
            "category":"Government",
            "subcategory":"Office",
            "type":"Public Place"
        }
    ],
    "sg:phone":"+1 931 962 1151",
    "sg:postcode":"37398",
    "sg:province":"TN",
    "sg:tags":[
        "state",
        "resource"
    ],
    "wof:name":"Food Stamps",
    "wof:placetype":"venue"
},
  "geometry": {"coordinates":[-86.111557,35.188201],"type":"Point"}
}