{
  "type": "Feature",
  "properties": {
    "iso:country":"US",
    "sg:address":"10977 Vonore Hwy",
    "sg:city":"Loudon",
    "sg:classifiers":[
        {
            "category":"Freight",
            "type":"Transportation"
        }
    ],
    "sg:phone":"+1 865 458 3363",
    "sg:postcode":"37774",
    "sg:province":"TN",
    "sg:tags":[
        "special",
        "general"
    ],
    "wof:name":"Vonore Road Storage Units",
    "wof:placetype":"venue"
},
  "geometry": {"coordinates":[-84.304179,35.713682],"type":"Point"}
}