{
  "type": "Feature",
  "properties": {
    "iso:country":"US",
    "sg:address":"9272 Hunterboro Dr",
    "sg:city":"Brentwood",
    "sg:classifiers":[
        {
            "category":"Professional",
            "subcategory":"Business Services",
            "type":"Services"
        }
    ],
    "sg:phone":"+1 615 371 9772",
    "sg:postcode":"37027",
    "sg:province":"TN",
    "wof:name":"Mike Kraski Enterprises Inc",
    "wof:placetype":"venue"
},
  "geometry": {"coordinates":[-86.765959,36.011325],"type":"Point"}
}