{
  "type": "Feature",
  "properties": {
    "iso:country":"US",
    "sg:address":"324 Tamworth Dr",
    "sg:city":"Nashville",
    "sg:classifiers":[
        {
            "category":"Food & Beverages",
            "subcategory":"Bakery",
            "type":"Retail Goods"
        }
    ],
    "sg:phone":"+1 615 883 3988",
    "sg:postcode":"37214",
    "sg:province":"TN",
    "sg:tags":[
        "cake",
        "decorating"
    ],
    "wof:name":"Cakes & Things",
    "wof:placetype":"venue"
},
  "geometry": {"coordinates":[-86.678431,36.1634],"type":"Point"}
}