{
  "type": "Feature",
  "properties": {
    "iso:country":"US",
    "sg:address":"2900 Lebanon Pike",
    "sg:city":"Nashville",
    "sg:classifiers":[
        {
            "category":"Professional",
            "subcategory":"Employment Agencies",
            "type":"Services"
        }
    ],
    "sg:phone":"+1 615 232 5119",
    "sg:postcode":"37214",
    "sg:province":"TN",
    "sg:tags":[
        "opportunity"
    ],
    "wof:name":"Chase Staffing Svc",
    "wof:placetype":"venue"
},
  "geometry": {"coordinates":[-86.656857,36.168352],"type":"Point"}
}