{
  "type": "Feature",
  "properties": {
    "iso:country":"US",
    "sg:address":"751 Circle Dr",
    "sg:city":"Dyersburg",
    "sg:classifiers":[
        {
            "category":"Retail",
            "subcategory":"Repair Shop",
            "type":"Services"
        }
    ],
    "sg:phone":"+1 731 285 8162",
    "sg:postcode":"38024",
    "sg:province":"TN",
    "sg:tags":[
        "lock",
        "locksmith"
    ],
    "wof:name":"Certified Locksmith",
    "wof:placetype":"venue"
},
  "geometry": {"coordinates":[-89.39743799999999,36.01788],"type":"Point"}
}