{
  "type": "Feature",
  "properties": {
    "iso:country":"US",
    "sg:address":"2330 Elvis Presley Blvd",
    "sg:city":"Memphis",
    "sg:classifiers":[
        {
            "category":"Retail",
            "subcategory":"Laundry & Dry Cleaning",
            "type":"Services"
        }
    ],
    "sg:phone":"+1 901 774 1837",
    "sg:postcode":"38106",
    "sg:province":"TN",
    "wof:name":"Neighborhood Laundry",
    "wof:placetype":"venue"
},
  "geometry": {"coordinates":[-90.018525,35.082938],"type":"Point"}
}