{
  "type": "Feature",
  "properties": {
    "iso:country":"US",
    "sg:address":"869 Oakwood Terrace Dr",
    "sg:city":"Antioch",
    "sg:classifiers":[
        {
            "category":"Professional",
            "subcategory":"Business Services",
            "type":"Services"
        }
    ],
    "sg:phone":"+1 615 333 1693",
    "sg:postcode":"37013",
    "sg:province":"TN",
    "wof:name":"Colemine Studio",
    "wof:placetype":"venue"
},
  "geometry": {"coordinates":[-86.673534,36.072755],"type":"Point"}
}