{
  "type": "Feature",
  "properties": {
    "addr:full":"1213 Montpier Dr Franklin TN 37069",
    "addr:housenumber":"1213",
    "addr:postcode":"37069",
    "addr:street":"Montpier Dr",
    "iso:country":"US",
    "sg:address":"1213 Montpier Dr",
    "sg:city":"Franklin",
    "sg:classifiers":[
        {
            "category":"Professional",
            "subcategory":"Employment Agencies",
            "type":"Services"
        }
    ],
    "sg:phone":"+1 615 790 3302",
    "sg:postcode":"37069",
    "sg:province":"TN",
    "wof:name":"Dawson Group",
    "wof:placetype":"venue"
},
  "geometry": {"coordinates":[-86.944225,35.983354],"type":"Point"}
}