{
  "type": "Feature",
  "properties": {
    "iso:country":"US",
    "sg:address":"2425 N Jackson St",
    "sg:city":"Normandy",
    "sg:classifiers":[
        {
            "category":"Retail",
            "subcategory":"Auto Repair",
            "type":"Services"
        }
    ],
    "sg:phone":"+1 931 455 1953",
    "sg:postcode":"37360",
    "sg:province":"TN",
    "sg:tags":[
        "repairing",
        "automobile"
    ],
    "wof:name":"Richard's Automotive",
    "wof:placetype":"venue"
},
  "geometry": {"coordinates":[-86.25508000000001,35.402576],"type":"Point"}
}