{
  "type": "Feature",
  "properties": {
    "iso:country":"US",
    "sg:address":"2722 S Roan St",
    "sg:city":"Johnson City",
    "sg:classifiers":[
        {
            "category":"Retail",
            "subcategory":"Auto Rental",
            "type":"Services"
        }
    ],
    "sg:phone":"+1 423 434 2661",
    "sg:postcode":"37601",
    "sg:province":"TN",
    "sg:tags":[
        "renting",
        "truck",
        "leasing"
    ],
    "wof:name":"MCI Ryder Truck",
    "wof:placetype":"venue"
},
  "geometry": {"coordinates":[-82.32827899999999,36.291142],"type":"Point"}
}