{
  "type": "Feature",
  "properties": {
    "iso:country":"US",
    "sg:address":"7914 Mahan Gap Rd",
    "sg:city":"Ooltewah",
    "sg:classifiers":[
        {
            "category":"Manufacturing",
            "subcategory":"Tools & Machinery",
            "type":"Manufacturing & Wholesale Goods"
        }
    ],
    "sg:phone":"+1 423 326 2942",
    "sg:postcode":"37363",
    "sg:province":"TN",
    "sg:tags":[
        "measuring",
        "instrument",
        "electrical",
        "mfg"
    ],
    "wof:name":"Scenic City Technology LLC",
    "wof:placetype":"venue"
},
  "geometry": {"coordinates":[-85.043987,35.177874],"type":"Point"}
}