{
  "type": "Feature",
  "properties": {
    "addr:full":"221 Beersheba Hwy Mc Minnville TN 37110",
    "addr:housenumber":"221",
    "addr:postcode":"37110",
    "addr:street":"Beersheba Hwy Mc Minnville",
    "iso:country":"US",
    "sg:address":"221 Beersheba Hwy",
    "sg:city":"Mc Minnville",
    "sg:classifiers":[
        {
            "category":"Autos & Motor Vehicles",
            "subcategory":"Automobile Sales",
            "type":"Retail Goods"
        }
    ],
    "sg:phone":"+1 931 473 6061",
    "sg:postcode":"37110",
    "sg:province":"TN",
    "sg:tags":[
        "used"
    ],
    "wof:name":"Jimmys Auto Sales",
    "wof:placetype":"venue"
},
  "geometry": {"coordinates":[-85.765533,35.679983],"type":"Point"}
}