{
  "type": "Feature",
  "properties": {
    "addr:full":"8014 Club Center Dr Cordova TN 38016",
    "addr:housenumber":"8014",
    "addr:postcode":"38016",
    "addr:street":"Club Center Dr",
    "iso:country":"US",
    "sg:address":"8014 Club Center Dr",
    "sg:city":"Cordova",
    "sg:classifiers":[
        {
            "category":"Manufacturing",
            "subcategory":"Printing",
            "type":"Manufacturing & Wholesale Goods"
        }
    ],
    "sg:phone":"+1 901 753 7588",
    "sg:postcode":"38016",
    "sg:province":"TN",
    "sg:tags":[
        "publisher"
    ],
    "wof:name":"Increase Media",
    "wof:placetype":"venue"
},
  "geometry": {"coordinates":[-89.795571,35.16401],"type":"Point"}
}