{
  "type": "Feature",
  "properties": {
    "addr:full":"3715 E Shelby Dr Memphis TN 38118",
    "addr:housenumber":"3715",
    "addr:postcode":"38118",
    "addr:street":"E Shelby Dr",
    "iso:country":"US",
    "sg:address":"3715 E Shelby Dr",
    "sg:city":"Memphis",
    "sg:classifiers":[
        {
            "category":"Organizations",
            "subcategory":"Religious Organization",
            "type":"Services"
        }
    ],
    "sg:phone":"+1 901 365 1650",
    "sg:postcode":"38118",
    "sg:province":"TN",
    "sg:tags":[
        "church"
    ],
    "wof:name":"Center Chapel Missionary Bapt",
    "wof:placetype":"venue"
},
  "geometry": {"coordinates":[-89.93719400000001,35.020505],"type":"Point"}
}