{
  "type": "Feature",
  "properties": {
    "iso:country":"US",
    "sg:address":"9700 Westland Dr",
    "sg:city":"Knoxville",
    "sg:classifiers":[
        {
            "category":"Professional",
            "subcategory":"Lawyer & Legal Services",
            "type":"Services"
        }
    ],
    "sg:phone":"+1 865 691 2777",
    "sg:postcode":"37922",
    "sg:province":"TN",
    "sg:tags":[
        "attorney"
    ],
    "sg:website":"http://www.rbrownlawyers.com",
    "wof:name":"Brown, Ralph",
    "wof:placetype":"venue"
},
  "geometry": {"coordinates":[-84.095192,35.875801],"type":"Point"}
}