{
  "type": "Feature",
  "properties": {
    "iso:country":"US",
    "sg:address":"1214 Woodvale Dr",
    "sg:city":"Mount Juliet",
    "sg:classifiers":[
        {
            "category":"Restaurant",
            "type":"Food & Drink"
        }
    ],
    "sg:phone":"+1 615 754 4160",
    "sg:postcode":"37122",
    "sg:province":"TN",
    "sg:tags":[
        "eating"
    ],
    "wof:name":"Arlie Que Inc",
    "wof:placetype":"venue"
},
  "geometry": {"coordinates":[-86.50511299999999,36.21789],"type":"Point"}
}