{
  "type": "Feature",
  "properties": {
    "addr:full":"2531 Park Dr Nashville TN 37214",
    "addr:housenumber":"2531",
    "addr:postcode":"37214",
    "addr:street":"Park Dr",
    "iso:country":"US",
    "sg:address":"2531 Park Dr",
    "sg:city":"Nashville",
    "sg:classifiers":[
        {
            "category":"Home & Garden",
            "subcategory":"Building Materials",
            "type":"Retail Goods"
        }
    ],
    "sg:phone":"+1 615 884 4935",
    "sg:postcode":"37214",
    "sg:province":"TN",
    "sg:tags":[
        "mixed",
        "concrete"
    ],
    "sg:website":"www.irvmat.com",
    "wof:name":"IMI/Irving Materials Inc",
    "wof:placetype":"venue"
},
  "geometry": {"coordinates":[-86.676045,36.170115],"type":"Point"}
}