{
  "type": "Feature",
  "properties": {
    "iso:country":"US",
    "sg:address":"4403 Elvis Presley Blvd",
    "sg:city":"Memphis",
    "sg:classifiers":[
        {
            "category":"Food & Beverages",
            "subcategory":"Bakery",
            "type":"Retail Goods"
        }
    ],
    "sg:phone":"+1 901 346 2530",
    "sg:postcode":"38116",
    "sg:province":"TN",
    "wof:name":"Wondder Bread",
    "wof:placetype":"venue"
},
  "geometry": {"coordinates":[-90.025256,35.027803],"type":"Point"}
}