{
  "type": "Feature",
  "properties": {
    "iso:country":"US",
    "sg:address":"988 State Hwy 210",
    "sg:city":"Dyersburg",
    "sg:classifiers":[
        {
            "category":"Education",
            "subcategory":"School",
            "type":"Public Place"
        }
    ],
    "sg:phone":"+1 731 285 1994",
    "sg:postcode":"38024",
    "sg:province":"TN",
    "wof:name":"Dyer County Holice Powell Schl",
    "wof:placetype":"venue"
},
  "geometry": {"coordinates":[-89.389476,35.970841],"type":"Point"}
}