{
  "type": "Feature",
  "properties": {
    "iso:country":"US",
    "sg:address":"1000 Center Ridge Rd",
    "sg:city":"Collierville",
    "sg:classifiers":[
        {
            "category":"Wholesale",
            "subcategory":"Electrical",
            "type":"Manufacturing & Wholesale Goods"
        }
    ],
    "sg:phone":"+1 901 861 3718",
    "sg:postcode":"38017",
    "sg:province":"TN",
    "sg:tags":[
        "electronic"
    ],
    "wof:name":"Security Mine",
    "wof:placetype":"venue"
},
  "geometry": {"coordinates":[-89.691278,35.01717],"type":"Point"}
}