{
  "type": "Feature",
  "properties": {
    "iso:country":"US",
    "sg:address":"4078 US Hwy 45 S",
    "sg:city":"Pinson",
    "sg:classifiers":[
        {
            "category":"Restaurant",
            "type":"Food & Drink"
        }
    ],
    "sg:phone":"+1 731 423 8288",
    "sg:postcode":"38366",
    "sg:province":"TN",
    "sg:tags":[
        "out"
    ],
    "wof:name":"Old Pinson Store",
    "wof:placetype":"venue"
},
  "geometry": {"coordinates":[-88.716302,35.487552],"type":"Point"}
}