{
  "type": "Feature",
  "properties": {
    "addr:full":"131 Lucille St Nashville TN 37207",
    "addr:housenumber":"131",
    "addr:postcode":"37207",
    "addr:street":"Lucille St",
    "iso:country":"US",
    "sg:address":"131 Lucille St",
    "sg:city":"Nashville",
    "sg:classifiers":[
        {
            "category":"Social Services",
            "subcategory":"Child Care",
            "type":"Services"
        }
    ],
    "sg:phone":"+1 615 650 2319",
    "sg:postcode":"37207",
    "sg:province":"TN",
    "sg:tags":[
        "day"
    ],
    "wof:name":"Joy Day Care",
    "wof:placetype":"venue"
},
  "geometry": {"coordinates":[-86.77006,36.196324],"type":"Point"}
}