{
  "type": "Feature",
  "properties": {
    "iso:country":"US",
    "sg:address":"401 S Castle St",
    "sg:city":"Knoxville",
    "sg:classifiers":[
        {
            "category":"Banks & Credit Unions",
            "subcategory":"Investment Brokerage",
            "type":"Services"
        }
    ],
    "sg:phone":"+1 865 637 9063",
    "sg:postcode":"37914",
    "sg:province":"TN",
    "sg:tags":[
        "consultant",
        "planning",
        "financial"
    ],
    "wof:name":"NIA Financial Svc",
    "wof:placetype":"venue"
},
  "geometry": {"coordinates":[-83.880746,35.988877],"type":"Point"}
}