{
  "type": "Feature",
  "properties": {
    "iso:country":"US",
    "sg:address":"502 Wilson Pike",
    "sg:city":"Brentwood",
    "sg:classifiers":[
        {
            "category":"Recreation",
            "type":"Entertainment"
        }
    ],
    "sg:phone":"+1 615 371 8109",
    "sg:postcode":"37027",
    "sg:province":"TN",
    "sg:tags":[
        "pool",
        "swimming"
    ],
    "sg:website":"www.thedolphinclub.com",
    "wof:name":"Brentwood Dolphin Club",
    "wof:placetype":"venue"
},
  "geometry": {"coordinates":[-86.78193899999999,36.017465],"type":"Point"}
}