{
  "type": "Feature",
  "properties": {
    "addr:full":"103 S Front St Selmer TN 38375",
    "addr:housenumber":"103",
    "addr:postcode":"38375",
    "addr:street":"S Front St",
    "iso:country":"US",
    "sg:address":"103 S Front St",
    "sg:city":"Selmer",
    "sg:classifiers":[
        {
            "category":"Restaurant",
            "type":"Food & Drink"
        }
    ],
    "sg:phone":"+1 731 645 7724",
    "sg:postcode":"38375",
    "sg:province":"TN",
    "wof:name":"Aunt B's",
    "wof:placetype":"venue"
},
  "geometry": {"coordinates":[-88.591577,35.16955],"type":"Point"}
}