{
  "type": "Feature",
  "properties": {
    "iso:country":"US",
    "sg:address":"715 W Cherokee Dr",
    "sg:city":"Jefferson City",
    "sg:classifiers":[
        {
            "category":"Retail",
            "subcategory":"Auto Repair",
            "type":"Services"
        }
    ],
    "sg:phone":"+1 865 475 4539",
    "sg:postcode":"37760",
    "sg:province":"TN",
    "sg:tags":[
        "repairing",
        "automobile",
        "general"
    ],
    "wof:name":"Brady's Garage",
    "wof:placetype":"venue"
},
  "geometry": {"coordinates":[-83.49355199999999,36.126408],"type":"Point"}
}