{
  "type": "Feature",
  "properties": {
    "iso:country":"US",
    "sg:address":"1059 Quarry Rd",
    "sg:city":"Mt Juliet",
    "sg:classifiers":[
        {
            "category":"Arts & Performance",
            "subcategory":"Theater",
            "type":"Entertainment"
        },
        {
            "category":"Professional",
            "subcategory":"Business Services",
            "type":"Services"
        }
    ],
    "sg:phone":"+1 615 453 0757",
    "sg:postcode":"37122",
    "sg:province":"TN",
    "sg:tags":[
        "group",
        "event"
    ],
    "sg:website":"www.activeentertain.com",
    "wof:name":"Active Entertainment",
    "wof:placetype":"venue"
},
  "geometry": {"coordinates":[-86.437226,36.217314],"type":"Point"}
}