{
  "type": "Feature",
  "properties": {
    "iso:country":"US",
    "sg:address":"113 Edgewater Pl",
    "sg:city":"Hendersonville",
    "sg:classifiers":[
        {
            "category":"Organizations",
            "subcategory":"Religious Organization",
            "type":"Services"
        }
    ],
    "sg:phone":"+1 615 826 1552",
    "sg:postcode":"37075",
    "sg:province":"TN",
    "sg:tags":[
        "church"
    ],
    "wof:name":"Victory Assembly Of God",
    "wof:placetype":"venue"
},
  "geometry": {"coordinates":[-86.579289,36.303273],"type":"Point"}
}