{
  "type": "Feature",
  "properties": {
    "iso:country":"US",
    "sg:address":"3702 Henderson Rd",
    "sg:city":"Knoxville",
    "sg:classifiers":[
        {
            "category":"Building & Trades",
            "subcategory":"Construction",
            "type":"Services"
        }
    ],
    "sg:phone":"+1 865 693 4107",
    "sg:postcode":"37931",
    "sg:province":"TN",
    "sg:tags":[
        "general",
        "contractor"
    ],
    "wof:name":"Kenneth R West Construction Co",
    "wof:placetype":"venue"
},
  "geometry": {"coordinates":[-84.132544,35.992826],"type":"Point"}
}