{
  "type": "Feature",
  "properties": {
    "iso:country":"US",
    "sg:address":"127 Woodmont Blvd",
    "sg:city":"Nashville",
    "sg:classifiers":[
        {
            "category":"Professional",
            "subcategory":"Lawyer & Legal Services",
            "type":"Services"
        }
    ],
    "sg:phone":"+1 615 669 5907",
    "sg:postcode":"37205",
    "sg:province":"TN",
    "sg:tags":[
        "personal",
        "attorney",
        "injury",
        "law"
    ],
    "sg:website":"http://www.kinnardclaytonandbeveridge.com",
    "wof:name":"Kinnard, Clayton And Beveridge",
    "wof:placetype":"venue"
},
  "geometry": {"coordinates":[-86.845037,36.122191],"type":"Point"}
}