{
  "type": "Feature",
  "properties": {
    "iso:country":"US",
    "sg:address":"6447 Grubb Rd",
    "sg:city":"Hixson",
    "sg:classifiers":[
        {
            "category":"Building & Trades",
            "subcategory":"Plumbing",
            "type":"Services"
        }
    ],
    "sg:phone":"+1 423 870 3556",
    "sg:postcode":"37343",
    "sg:province":"TN",
    "sg:tags":[
        "contractor"
    ],
    "wof:name":"Michael S Richards",
    "wof:placetype":"venue"
},
  "geometry": {"coordinates":[-85.251159,35.165912],"type":"Point"}
}