{
  "type": "Feature",
  "properties": {
    "iso:country":"US",
    "sg:address":"1115 Hill Rd",
    "sg:city":"Cookeville",
    "sg:classifiers":[
        {
            "category":"Personal",
            "subcategory":"Beauty Salon",
            "type":"Services"
        }
    ],
    "sg:phone":"+1 931 372 1727",
    "sg:postcode":"38501",
    "sg:province":"TN",
    "sg:tags":[
        "shop"
    ],
    "wof:name":"Lisa Gunning",
    "wof:placetype":"venue"
},
  "geometry": {"coordinates":[-85.514482,36.238898],"type":"Point"}
}