{
  "type": "Feature",
  "properties": {
    "addr:full":"1277 Getwell Rd Memphis TN 38111",
    "addr:housenumber":"1277",
    "addr:postcode":"38111",
    "addr:street":"Getwell Rd",
    "iso:country":"US",
    "sg:address":"1277 Getwell Rd",
    "sg:city":"Memphis",
    "sg:classifiers":[
        {
            "category":"Bars & Pubs",
            "type":"Food & Drink"
        }
    ],
    "sg:phone":"+1 901 454 0007",
    "sg:postcode":"38111",
    "sg:province":"TN",
    "sg:tags":[
        "drinking"
    ],
    "wof:name":"Castaways",
    "wof:placetype":"venue"
},
  "geometry": {"coordinates":[-89.93101299999999,35.096769],"type":"Point"}
}