{
  "type": "Feature",
  "properties": {
    "iso:country":"US",
    "sg:address":"13 Cherry St",
    "sg:city":"Dunlap",
    "sg:classifiers":[
        {
            "category":"Shopping",
            "subcategory":"Clothing, Apparel, & Fashions",
            "type":"Retail Goods"
        }
    ],
    "sg:phone":"+1 423 949 2524",
    "sg:postcode":"37327",
    "sg:province":"TN",
    "wof:name":"Claudia's Dress Shoppe",
    "wof:placetype":"venue"
},
  "geometry": {"coordinates":[-85.38782500000001,35.370715],"type":"Point"}
}