{
  "type": "Feature",
  "properties": {
    "iso:country":"US",
    "sg:address":"310 Dodds Ave",
    "sg:city":"Chattanooga",
    "sg:classifiers":[
        {
            "category":"Wholesale",
            "subcategory":"Computers",
            "type":"Manufacturing & Wholesale Goods"
        }
    ],
    "sg:phone":"+1 423 622 2113",
    "sg:postcode":"37404",
    "sg:province":"TN",
    "sg:tags":[
        "information",
        "retrieval"
    ],
    "wof:name":"Paperless Co",
    "wof:placetype":"venue"
},
  "geometry": {"coordinates":[-85.264194,35.031062],"type":"Point"}
}