{
  "type": "Feature",
  "properties": {
    "iso:country":"US",
    "sg:address":"8 Mistletoe Ct",
    "sg:city":"Johnson City",
    "sg:classifiers":[
        {
            "category":"Retail",
            "subcategory":"Animal Services",
            "type":"Services"
        }
    ],
    "sg:phone":"+1 423 952 0794",
    "sg:postcode":"37604",
    "sg:province":"TN",
    "sg:tags":[
        "pet",
        "grooming",
        "washing"
    ],
    "wof:name":"Tail Chasers Pet Salon",
    "wof:placetype":"venue"
},
  "geometry": {"coordinates":[-82.399075,36.265772],"type":"Point"}
}