{
  "type": "Feature",
  "properties": {
    "iso:country":"US",
    "sg:address":"5144 Old Summer Rd",
    "sg:city":"Memphis",
    "sg:classifiers":[
        {
            "category":"Wholesale",
            "subcategory":"Machinery & Supplies",
            "type":"Manufacturing & Wholesale Goods"
        }
    ],
    "sg:phone":"+1 901 763 1050",
    "sg:postcode":"38122",
    "sg:province":"TN",
    "sg:tags":[
        "salon",
        "beauty"
    ],
    "wof:name":"Heil Beauty Supply",
    "wof:placetype":"venue"
},
  "geometry": {"coordinates":[-89.890175,35.149968],"type":"Point"}
}