{
  "type": "Feature",
  "properties": {
    "iso:country":"US",
    "sg:address":"104 Trey Cir",
    "sg:city":"Bristol",
    "sg:classifiers":[
        {
            "category":"Building & Trades",
            "subcategory":"Construction",
            "type":"Services"
        }
    ],
    "sg:phone":"+1 423 764 9324",
    "sg:postcode":"37620",
    "sg:province":"TN",
    "sg:tags":[
        "general",
        "contractor"
    ],
    "wof:name":"Hal Overbey General Contractor",
    "wof:placetype":"venue"
},
  "geometry": {"coordinates":[-82.14595799999999,36.59129],"type":"Point"}
}