{
  "type": "Feature",
  "properties": {
    "iso:country":"US",
    "sg:address":"4208 E Andrew Johnson Hwy",
    "sg:city":"Morristown",
    "sg:classifiers":[
        {
            "category":"Autos & Motor Vehicles",
            "subcategory":"Automobile Sales",
            "type":"Retail Goods"
        }
    ],
    "sg:phone":"+1 423 585 5400",
    "sg:postcode":"37814",
    "sg:province":"TN",
    "sg:tags":[
        "car",
        "dealer"
    ],
    "wof:name":"Mike's Auto Sales",
    "wof:placetype":"venue"
},
  "geometry": {"coordinates":[-83.23773300000001,36.236868],"type":"Point"}
}