{
  "type": "Feature",
  "properties": {
    "iso:country":"US",
    "sg:address":"3013 Johnson Ave",
    "sg:city":"Memphis",
    "sg:classifiers":[
        {
            "category":"Personal",
            "subcategory":"Beauty Salon",
            "type":"Services"
        }
    ],
    "sg:phone":"+1 901 452 5330",
    "sg:postcode":"38112",
    "sg:province":"TN",
    "sg:tags":[
        "shop"
    ],
    "wof:name":"Keyta's Cutting Up",
    "wof:placetype":"venue"
},
  "geometry": {"coordinates":[-89.959847,35.141714],"type":"Point"}
}