{
  "type": "Feature",
  "properties": {
    "iso:country":"US",
    "sg:address":"7106 Sawyer Rd",
    "sg:city":"Signal Mountain",
    "sg:classifiers":[
        {
            "category":"Building & Trades",
            "subcategory":"Construction",
            "type":"Services"
        }
    ],
    "sg:phone":"+1 423 886 3941",
    "sg:postcode":"37377",
    "sg:province":"TN",
    "sg:tags":[
        "excavation",
        "contractor"
    ],
    "wof:name":"N & K Construction Company",
    "wof:placetype":"venue"
},
  "geometry": {"coordinates":[-85.298512,35.20751],"type":"Point"}
}