{
  "type": "Feature",
  "properties": {
    "addr:full":"5702 Spring Place Rd SE Cleveland TN 37323",
    "addr:housenumber":"5702",
    "addr:postcode":"37323",
    "addr:street":"Spring Place Rd Se",
    "iso:country":"US",
    "sg:address":"5702 Spring Place Rd SE",
    "sg:city":"Cleveland",
    "sg:classifiers":[
        {
            "category":"Farming",
            "subcategory":"Farm",
            "type":"Manufacturing & Wholesale Goods"
        }
    ],
    "sg:phone":"+1 423 472 1795",
    "sg:postcode":"37323",
    "sg:province":"TN",
    "sg:tags":[
        "crop",
        "general"
    ],
    "wof:name":"Jordan Poultry Farm",
    "wof:placetype":"venue"
},
  "geometry": {"coordinates":[-84.806073,35.044482],"type":"Point"}
}