{
  "type": "Feature",
  "properties": {
    "iso:country":"US",
    "sg:address":"115 Scarbrough Ln",
    "sg:city":"Buchanan",
    "sg:classifiers":[
        {
            "category":"Organizations",
            "subcategory":"Religious Organization",
            "type":"Services"
        }
    ],
    "sg:phone":"+1 731 642 3774",
    "sg:postcode":"38222",
    "sg:province":"TN",
    "wof:name":"Christ Family Worship Center",
    "wof:placetype":"venue"
},
  "geometry": {"coordinates":[-88.200096,36.368754],"type":"Point"}
}