{
  "type": "Feature",
  "properties": {
    "addr:full":"2850 White Oak Ridge Rd Mc Ewen TN 37101",
    "addr:housenumber":"2850",
    "addr:postcode":"37101",
    "addr:street":"White Oak Ridge Rd",
    "iso:country":"US",
    "sg:address":"2850 White Oak Ridge Rd",
    "sg:city":"Mc Ewen",
    "sg:classifiers":[
        {
            "category":"Building & Trades",
            "subcategory":"Construction",
            "type":"Services"
        }
    ],
    "sg:phone":"+1 865 908 4323",
    "sg:postcode":"37101",
    "sg:province":"TN",
    "sg:tags":[
        "home",
        "builder"
    ],
    "wof:name":"Legacy Homes LLC",
    "wof:placetype":"venue"
},
  "geometry": {"coordinates":[-87.69932900000001,36.195833],"type":"Point"}
}