{
  "type": "Feature",
  "properties": {
    "addr:full":"2524 Dickerson Pike Nashville TN 37207",
    "addr:housenumber":"2524",
    "addr:postcode":"37207",
    "addr:street":"Dickerson Pike",
    "iso:country":"US",
    "sg:address":"2524 Dickerson Pike",
    "sg:city":"Nashville",
    "sg:classifiers":[
        {
            "category":"Organizations",
            "subcategory":"Labor Organization",
            "type":"Services"
        }
    ],
    "sg:phone":"+1 615 227 9032",
    "sg:postcode":"37207",
    "sg:province":"TN",
    "wof:name":"Ironworker Shopmens Local Un",
    "wof:placetype":"venue"
},
  "geometry": {"coordinates":[-86.764397,36.213954],"type":"Point"}
}