{
  "type": "Feature",
  "properties": {
    "iso:country":"US",
    "sg:address":"360 Roseland Pl",
    "sg:city":"Memphis",
    "sg:classifiers":[
        {
            "category":"Building & Trades",
            "subcategory":"Construction",
            "type":"Services"
        }
    ],
    "sg:phone":"+1 901 327 0030",
    "sg:postcode":"38111",
    "sg:province":"TN",
    "sg:tags":[
        "general",
        "contractor"
    ],
    "wof:name":"Ben Duke Builder LLC",
    "wof:placetype":"venue"
},
  "geometry": {"coordinates":[-89.92854800000001,35.121832],"type":"Point"}
}