{
  "type": "Feature",
  "properties": {
    "addr:full":"3350 State Hwy 100 Lyles TN 37033",
    "addr:housenumber":"3350",
    "addr:postcode":"37033",
    "addr:street":"State Hwy 100",
    "iso:country":"US",
    "sg:address":"3350 State Hwy 100",
    "sg:city":"Lyles",
    "sg:classifiers":[
        {
            "category":"Food & Beverages",
            "subcategory":"Groceries & Convenience Stores",
            "type":"Retail Goods"
        }
    ],
    "sg:phone":"+1 931 670 0700",
    "sg:postcode":"37033",
    "sg:province":"TN",
    "sg:tags":[
        "grocer"
    ],
    "wof:name":"David's Corner Market",
    "wof:placetype":"venue"
},
  "geometry": {"coordinates":[-87.359527,35.85975],"type":"Point"}
}