{
  "type": "Feature",
  "properties": {
    "iso:country":"US",
    "sg:address":"3714 Nolensville Pike",
    "sg:city":"Nashville",
    "sg:classifiers":[
        {
            "category":"Real Estate",
            "subcategory":"Real Estate Agent",
            "type":"Services"
        }
    ],
    "sg:phone":"+1 615 837 1131",
    "sg:postcode":"37211",
    "sg:province":"TN",
    "wof:name":"Valdez Realty LLC",
    "wof:placetype":"venue"
},
  "geometry": {"coordinates":[-86.73661,36.094337],"type":"Point"}
}