{
  "type": "Feature",
  "properties": {
    "iso:country":"US",
    "sg:address":"8800 Fox River Way",
    "sg:city":"Knoxville",
    "sg:classifiers":[
        {
            "category":"Communications",
            "subcategory":"Film & Video Production",
            "type":"Services"
        }
    ],
    "sg:phone":"+1 865 470 2001",
    "sg:postcode":"37923",
    "sg:province":"TN",
    "sg:tags":[
        "motion"
    ],
    "wof:name":"Clark Video Productions",
    "wof:placetype":"venue"
},
  "geometry": {"coordinates":[-84.080663,35.930662],"type":"Point"}
}