{
  "type": "Feature",
  "properties": {
    "iso:country":"US",
    "sg:address":"6195 Bunker Hill Rd",
    "sg:city":"Cookeville",
    "sg:classifiers":[
        {
            "category":"Education",
            "subcategory":"College",
            "type":"Public Place"
        }
    ],
    "sg:phone":"+1 931 432 5486",
    "sg:postcode":"38506",
    "sg:province":"TN",
    "sg:tags":[
        "school",
        "theological"
    ],
    "wof:name":"Taylor Seminary Freewill",
    "wof:placetype":"venue"
},
  "geometry": {"coordinates":[-85.535932,36.082448],"type":"Point"}
}