{
  "type": "Feature",
  "properties": {
    "iso:country":"US",
    "sg:address":"314 S Polk St",
    "sg:city":"Tullahoma",
    "sg:classifiers":[
        {
            "category":"Manufacturing",
            "subcategory":"Signs",
            "type":"Manufacturing & Wholesale Goods"
        }
    ],
    "sg:phone":"+1 931 455 1041",
    "sg:postcode":"37388",
    "sg:province":"TN",
    "sg:tags":[
        "advertising",
        "specialty"
    ],
    "wof:name":"A & M Signs",
    "wof:placetype":"venue"
},
  "geometry": {"coordinates":[-86.204407,35.362114],"type":"Point"}
}