{
  "type": "Feature",
  "properties": {
    "iso:country":"US",
    "sg:address":"7474 Benjestown Rd",
    "sg:city":"Millington",
    "sg:classifiers":[
        {
            "category":"Freight",
            "type":"Transportation"
        }
    ],
    "sg:phone":"+1 901 876 5444",
    "sg:postcode":"38053",
    "sg:province":"TN",
    "sg:tags":[
        "distance",
        "long",
        "trucking"
    ],
    "wof:name":"Holt Trucking",
    "wof:placetype":"venue"
},
  "geometry": {"coordinates":[-90.030535,35.332007],"type":"Point"}
}