{
  "type": "Feature",
  "properties": {
    "addr:full":"8035 Club Pkwy Cordova TN 38016",
    "addr:housenumber":"8035",
    "addr:postcode":"38016",
    "addr:street":"Club Pkwy",
    "iso:country":"US",
    "sg:address":"8035 Club Pkwy",
    "sg:city":"Cordova",
    "sg:classifiers":[
        {
            "category":"Health Services",
            "subcategory":"Doctor",
            "type":"Services"
        }
    ],
    "sg:phone":"+1 901 759 0854",
    "sg:postcode":"38016",
    "sg:province":"TN",
    "sg:tags":[
        "physician",
        "surgeon"
    ],
    "wof:name":"Behavioral Pediatrics",
    "wof:placetype":"venue"
},
  "geometry": {"coordinates":[-89.794421,35.162316],"type":"Point"}
}