{
  "type": "Feature",
  "properties": {
    "iso:country":"US",
    "sg:address":"6988 Tagen Ct",
    "sg:city":"Memphis",
    "sg:classifiers":[
        {
            "category":"Shopping",
            "subcategory":"Bicycles & Sporting Goods",
            "type":"Retail Goods"
        }
    ],
    "sg:phone":"+1 901 384 0760",
    "sg:postcode":"38133",
    "sg:province":"TN",
    "wof:name":"Fishing For Guns",
    "wof:placetype":"venue"
},
  "geometry": {"coordinates":[-89.829398,35.19814],"type":"Point"}
}