{
  "type": "Feature",
  "properties": {
    "iso:country":"US",
    "sg:address":"2225 Industrial Rd",
    "sg:city":"Dyersburg",
    "sg:classifiers":[
        {
            "category":"Wholesale",
            "subcategory":"Electrical",
            "type":"Manufacturing & Wholesale Goods"
        }
    ],
    "sg:phone":"+1 731 285 9121",
    "sg:postcode":"38024",
    "sg:province":"TN",
    "sg:tags":[
        "distribution",
        "component",
        "transformer"
    ],
    "wof:name":"Ermco Components Inc",
    "wof:placetype":"venue"
},
  "geometry": {"coordinates":[-89.35027700000001,36.054873],"type":"Point"}
}