{
  "type": "Feature",
  "properties": {
    "addr:full":"315 N Weisgarber Rd Knoxville TN 37919",
    "addr:housenumber":"315",
    "addr:postcode":"37919",
    "addr:street":"N Weisgarber Rd",
    "iso:country":"US",
    "sg:address":"315 N Weisgarber Rd",
    "sg:city":"Knoxville",
    "sg:classifiers":[
        {
            "category":"Health Services",
            "subcategory":"Health Practitioner",
            "type":"Services"
        }
    ],
    "sg:phone":"+1 865 588 8586",
    "sg:postcode":"37919",
    "sg:province":"TN",
    "wof:name":"Patricia A Ridgeway PHD",
    "wof:placetype":"venue"
},
  "geometry": {"coordinates":[-84.007414,35.935763],"type":"Point"}
}