{
  "type": "Feature",
  "properties": {
    "iso:country":"US",
    "sg:address":"5134 Elmore Rd",
    "sg:city":"Bartlett",
    "sg:classifiers":[
        {
            "category":"Wholesale",
            "subcategory":"Vending Machines",
            "type":"Manufacturing & Wholesale Goods"
        }
    ],
    "sg:phone":"+1 901 372 5475",
    "sg:postcode":"38134",
    "sg:province":"TN",
    "wof:name":"Custom Vending Svc",
    "wof:placetype":"venue"
},
  "geometry": {"coordinates":[-89.892494,35.185368],"type":"Point"}
}