{
  "type": "Feature",
  "properties": {
    "iso:country":"US",
    "sg:address":"6000 Cortez Ct",
    "sg:city":"Hermitage",
    "sg:classifiers":[
        {
            "category":"Real Estate",
            "subcategory":"Real Estate Agent",
            "type":"Services"
        }
    ],
    "sg:phone":"+1 615 391 4000",
    "sg:postcode":"37076",
    "sg:province":"TN",
    "sg:tags":[
        "management"
    ],
    "wof:name":"J Property Management Group",
    "wof:placetype":"venue"
},
  "geometry": {"coordinates":[-86.61778700000001,36.189962],"type":"Point"}
}