{
  "type": "Feature",
  "properties": {
    "iso:country":"US",
    "sg:address":"8316 Beech Valley Rd",
    "sg:city":"Primm Springs",
    "sg:classifiers":[
        {
            "category":"Manufacturing",
            "subcategory":"Printing",
            "type":"Manufacturing & Wholesale Goods"
        }
    ],
    "sg:phone":"+1 931 729 9658",
    "sg:postcode":"38476",
    "sg:province":"TN",
    "sg:tags":[
        "newspaper"
    ],
    "wof:name":"Mc Graw-Hill Companies Inc",
    "wof:placetype":"venue"
},
  "geometry": {"coordinates":[-87.271027,35.828702],"type":"Point"}
}