{
  "type": "Feature",
  "properties": {
    "addr:full":"3313 Smith Place Rd Clarksville TN 37040",
    "addr:housenumber":"3313",
    "addr:postcode":"37040",
    "addr:street":"Smith Place Rd",
    "iso:country":"US",
    "sg:address":"3313 Smith Place Rd",
    "sg:city":"Clarksville",
    "sg:classifiers":[
        {
            "category":"Manufacturing",
            "subcategory":"Printing",
            "type":"Manufacturing & Wholesale Goods"
        }
    ],
    "sg:phone":"+1 931 387 2992",
    "sg:postcode":"37040",
    "sg:province":"TN",
    "sg:tags":[
        "newspaper"
    ],
    "wof:name":"Long Herald & Son",
    "wof:placetype":"venue"
},
  "geometry": {"coordinates":[-87.409145,36.422169],"type":"Point"}
}