{
  "type": "Feature",
  "properties": {
    "addr:full":"65 Germantown Ct Cordova TN 38018",
    "addr:housenumber":"65",
    "addr:postcode":"38018",
    "addr:street":"Germantown Ct",
    "iso:country":"US",
    "sg:address":"65 Germantown Ct",
    "sg:city":"Cordova",
    "sg:classifiers":[
        {
            "category":"Utilities",
            "subcategory":"Mobile Phone",
            "type":"Services"
        }
    ],
    "sg:phone":"+1 901 433 3300",
    "sg:postcode":"38018",
    "sg:province":"TN",
    "sg:tags":[
        "telephone",
        "cellular"
    ],
    "wof:name":"Cricket Communications",
    "wof:placetype":"venue"
},
  "geometry": {"coordinates":[-89.795649,35.129621],"type":"Point"}
}