{
  "type": "Feature",
  "properties": {
    "iso:country":"US",
    "sg:address":"8070 Breezy Creek Rd",
    "sg:city":"Germantown",
    "sg:classifiers":[
        {
            "category":"Insurance",
            "subcategory":"Insurance Agent",
            "type":"Services"
        }
    ],
    "sg:phone":"+1 901 754 2667",
    "sg:postcode":"38138",
    "sg:province":"TN",
    "wof:name":"Nationwide Insurance",
    "wof:placetype":"venue"
},
  "geometry": {"coordinates":[-89.793443,35.102005],"type":"Point"}
}