{
  "type": "Feature",
  "properties": {
    "addr:full":"2159 S Highland Ave Jackson TN 38301",
    "addr:housenumber":"2159",
    "addr:postcode":"38301",
    "addr:street":"S Highland Ave",
    "iso:country":"US",
    "sg:address":"2159 S Highland Ave",
    "sg:city":"Jackson",
    "sg:classifiers":[
        {
            "category":"Autos & Motor Vehicles",
            "subcategory":"Fuel & Gas Station",
            "type":"Retail Goods"
        }
    ],
    "sg:phone":"+1 731 424 7979",
    "sg:postcode":"38301",
    "sg:province":"TN",
    "sg:tags":[
        "oil"
    ],
    "wof:name":"Murphy Oil USA Inc",
    "wof:placetype":"venue"
},
  "geometry": {"coordinates":[-88.80678399999999,35.550067],"type":"Point"}
}