{
  "type": "Feature",
  "properties": {
    "addr:full":"122 Burton Rd Rogersville TN 37857",
    "addr:housenumber":"122",
    "addr:postcode":"37857",
    "addr:street":"Burton Rd",
    "iso:country":"US",
    "sg:address":"122 Burton Rd",
    "sg:city":"Rogersville",
    "sg:classifiers":[
        {
            "category":"Real Estate",
            "subcategory":"Real Estate Operator",
            "type":"Services"
        }
    ],
    "sg:phone":"+1 423 272 4804",
    "sg:postcode":"37857",
    "sg:province":"TN",
    "sg:tags":[
        "building",
        "apartment"
    ],
    "wof:name":"Burton Plaza",
    "wof:placetype":"venue"
},
  "geometry": {"coordinates":[-82.98955100000001,36.419713],"type":"Point"}
}