{
  "type": "Feature",
  "properties": {
    "iso:country":"US",
    "sg:address":"136 Kilby St",
    "sg:city":"Sevierville",
    "sg:classifiers":[
        {
            "category":"Retail",
            "subcategory":"Auto Repair",
            "type":"Services"
        }
    ],
    "sg:phone":"+1 865 453 9203",
    "sg:postcode":"37862",
    "sg:province":"TN",
    "sg:tags":[
        "wrecker"
    ],
    "wof:name":"Baker's Wrecker Svc",
    "wof:placetype":"venue"
},
  "geometry": {"coordinates":[-83.572355,35.873013],"type":"Point"}
}