{
  "type": "Feature",
  "properties": {
    "iso:country":"US",
    "sg:address":"524 Westwood Ave",
    "sg:city":"Jackson",
    "sg:classifiers":[
        {
            "category":"Personal",
            "subcategory":"Beauty Salon",
            "type":"Services"
        }
    ],
    "sg:phone":"+1 731 427 5815",
    "sg:postcode":"38301",
    "sg:province":"TN",
    "sg:tags":[
        "shop"
    ],
    "wof:name":"Coiffures Beauty Salons",
    "wof:placetype":"venue"
},
  "geometry": {"coordinates":[-88.827735,35.631789],"type":"Point"}
}