{
  "type": "Feature",
  "properties": {
    "iso:country":"US",
    "sg:address":"1434 Greenland Ave",
    "sg:city":"Nashville",
    "sg:classifiers":[
        {
            "category":"Professional",
            "subcategory":"Art Services",
            "type":"Services"
        }
    ],
    "sg:phone":"+1 615 227 9410",
    "sg:postcode":"37216",
    "sg:province":"TN",
    "sg:tags":[
        "photography",
        "commercial"
    ],
    "wof:name":"OConner Martin",
    "wof:placetype":"venue"
},
  "geometry": {"coordinates":[-86.712199,36.214085],"type":"Point"}
}