{
  "type": "Feature",
  "properties": {
    "iso:country":"US",
    "sg:address":"585 Rocktown Rd",
    "sg:city":"Jefferson City",
    "sg:classifiers":[
        {
            "category":"Freight",
            "type":"Transportation"
        }
    ],
    "sg:phone":"+1 865 475 3633",
    "sg:postcode":"37760",
    "sg:province":"TN",
    "sg:tags":[
        "operator",
        "local",
        "trucking"
    ],
    "wof:name":"Tripple R Trucking",
    "wof:placetype":"venue"
},
  "geometry": {"coordinates":[-83.433244,36.139361],"type":"Point"}
}