{
  "type": "Feature",
  "properties": {
    "addr:full":"1200 S Mount Juliet Rd Mount Juliet TN 37122",
    "addr:housenumber":"1200",
    "addr:postcode":"37122",
    "addr:street":"S Mount Juliet Rd",
    "iso:country":"US",
    "sg:address":"1200 S Mount Juliet Rd",
    "sg:city":"Mount Juliet",
    "sg:classifiers":[
        {
            "category":"Real Estate",
            "subcategory":"Real Estate Operator",
            "type":"Services"
        }
    ],
    "sg:phone":"+1 615 758 2488",
    "sg:postcode":"37122",
    "sg:province":"TN",
    "sg:tags":[
        "building",
        "apartment"
    ],
    "wof:name":"Thomas King Properties LLC",
    "wof:placetype":"venue"
},
  "geometry": {"coordinates":[-86.516262,36.153731],"type":"Point"}
}