{
  "type": "Feature",
  "properties": {
    "iso:country":"US",
    "sg:address":"1123 Dellwood Ave",
    "sg:city":"Memphis",
    "sg:classifiers":[
        {
            "category":"Food & Beverages",
            "subcategory":"Groceries & Convenience Stores",
            "type":"Retail Goods"
        }
    ],
    "sg:phone":"+1 901 357 7060",
    "sg:postcode":"38127",
    "sg:province":"TN",
    "sg:tags":[
        "grocer"
    ],
    "wof:name":"2-Star",
    "wof:placetype":"venue"
},
  "geometry": {"coordinates":[-90.02670000000001,35.210484],"type":"Point"}
}