{
  "type": "Feature",
  "properties": {
    "addr:full":"6324 Heritage Ridge Dr Hixson TN 37343",
    "addr:housenumber":"6324",
    "addr:postcode":"37343",
    "addr:street":"Heritage Ridge Dr",
    "iso:country":"US",
    "sg:address":"6324 Heritage Ridge Dr",
    "sg:city":"Hixson",
    "sg:classifiers":[
        {
            "category":"Banks & Credit Unions",
            "subcategory":"Financial Services",
            "type":"Services"
        }
    ],
    "sg:phone":"+1 423 495 9596",
    "sg:postcode":"37343",
    "sg:province":"TN",
    "sg:tags":[
        "company",
        "holding"
    ],
    "wof:name":"Mitchco",
    "wof:placetype":"venue"
},
  "geometry": {"coordinates":[-85.205017,35.145378],"type":"Point"}
}