{
  "type": "Feature",
  "properties": {
    "iso:country":"US",
    "sg:address":"800 Chestnut Stump Rd",
    "sg:city":"La Follette",
    "sg:classifiers":[
        {
            "category":"Education",
            "subcategory":"School",
            "type":"Public Place"
        }
    ],
    "sg:phone":"+1 423 562 0156",
    "sg:postcode":"37766",
    "sg:province":"TN",
    "wof:name":"Campbell County Preschool Prog",
    "wof:placetype":"venue"
},
  "geometry": {"coordinates":[-84.07891100000001,36.313177],"type":"Point"}
}