{
  "type": "Feature",
  "properties": {
    "iso:country":"US",
    "sg:address":"187 Hidden Lake Rd",
    "sg:city":"Hendersonville",
    "sg:classifiers":[
        {
            "category":"Arts & Performance",
            "subcategory":"Theater",
            "type":"Entertainment"
        }
    ],
    "sg:phone":"+1 615 264 3809",
    "sg:postcode":"37075",
    "sg:province":"TN",
    "sg:tags":[
        "group"
    ],
    "wof:name":"Leon Medica Musicians",
    "wof:placetype":"venue"
},
  "geometry": {"coordinates":[-86.588972,36.262448],"type":"Point"}
}