{
  "type": "Feature",
  "properties": {
    "iso:country":"US",
    "sg:address":"200 W Fort St",
    "sg:city":"Manchester",
    "sg:classifiers":[
        {
            "category":"Building & Trades",
            "subcategory":"Construction",
            "type":"Services"
        }
    ],
    "sg:phone":"+1 931 728 6903",
    "sg:postcode":"37355",
    "sg:province":"TN",
    "sg:tags":[
        "marking",
        "maintenance",
        "parking"
    ],
    "wof:name":"Manchester Public Works Dept",
    "wof:placetype":"venue"
},
  "geometry": {"coordinates":[-86.08985199999999,35.483719],"type":"Point"}
}