{
  "type": "Feature",
  "properties": {
    "iso:country":"US",
    "sg:address":"411 Jim Ct",
    "sg:city":"Clarksville",
    "sg:classifiers":[
        {
            "category":"Professional",
            "subcategory":"Business Services",
            "type":"Services"
        }
    ],
    "sg:phone":"+1 931 358 9818",
    "sg:postcode":"37043",
    "sg:province":"TN",
    "wof:name":"Kmp Healthcare Solutions Inc",
    "wof:placetype":"venue"
},
  "geometry": {"coordinates":[-87.25133,36.4845],"type":"Point"}
}