{
  "type": "Feature",
  "properties": {
    "addr:full":"8504 Macon Rd Cordova TN 38018",
    "addr:housenumber":"8504",
    "addr:postcode":"38018",
    "addr:street":"Macon Rd",
    "iso:country":"US",
    "sg:address":"8504 Macon Rd",
    "sg:city":"Cordova",
    "sg:classifiers":[
        {
            "category":"Shopping",
            "type":"Retail Goods"
        }
    ],
    "sg:phone":"+1 901 755 5554",
    "sg:postcode":"38018",
    "sg:province":"TN",
    "sg:tags":[
        "seasonal"
    ],
    "wof:name":"Home For The Holidays",
    "wof:placetype":"venue"
},
  "geometry": {"coordinates":[-89.779331,35.155998],"type":"Point"}
}