{
  "type": "Feature",
  "properties": {
    "addr:full":"4876 Meadow Ave Cleveland TN 37312",
    "addr:housenumber":"4876",
    "addr:postcode":"37312",
    "addr:street":"Meadow Ave",
    "iso:country":"US",
    "sg:address":"4876 Meadow Ave",
    "sg:city":"Cleveland",
    "sg:classifiers":[
        {
            "category":"Professional",
            "subcategory":"Management & Consulting",
            "type":"Services"
        }
    ],
    "sg:phone":"+1 423 473 7726",
    "sg:postcode":"37312",
    "sg:province":"TN",
    "sg:tags":[
        "consultant"
    ],
    "wof:name":"Kmk Consulting",
    "wof:placetype":"venue"
},
  "geometry": {"coordinates":[-84.852513,35.217696],"type":"Point"}
}