{
  "type": "Feature",
  "properties": {
    "addr:full":"9605 Kingston Pike Knoxville TN 37922",
    "addr:housenumber":"9605",
    "addr:postcode":"37922",
    "addr:street":"Kingston Pike",
    "iso:country":"US",
    "sg:address":"9605 Kingston Pike",
    "sg:city":"Knoxville",
    "sg:phone":"+1 865 690 1740",
    "sg:postcode":"37922",
    "sg:province":"TN",
    "wof:name":"La-Z-Boy Furniture Galleries",
    "wof:placetype":"venue"
},
  "geometry": {"coordinates":[-84.105385,35.907955],"type":"Point"}
}