{
  "type": "Feature",
  "properties": {
    "addr:full":"1735 W Main St Lebanon TN 37087",
    "addr:housenumber":"1735",
    "addr:postcode":"37087",
    "addr:street":"W Main St",
    "iso:country":"US",
    "sg:address":"1735 W Main St",
    "sg:city":"Lebanon",
    "sg:classifiers":[
        {
            "category":"Sports & Exercise",
            "subcategory":"Gym",
            "type":"Entertainment"
        }
    ],
    "sg:phone":"+1 615 449 0031",
    "sg:postcode":"37087",
    "sg:province":"TN",
    "sg:tags":[
        "club",
        "health",
        "studio",
        "gymnasium",
        "athletic"
    ],
    "wof:name":"Sports Village Inc",
    "wof:placetype":"venue"
},
  "geometry": {"coordinates":[-86.35004600000001,36.22342],"type":"Point"}
}