{
  "type": "Feature",
  "properties": {
    "addr:full":"1284 Kerr Ave Memphis TN 38106",
    "addr:housenumber":"1284",
    "addr:postcode":"38106",
    "addr:street":"Kerr Ave",
    "iso:country":"US",
    "sg:address":"1284 Kerr Ave",
    "sg:city":"Memphis",
    "sg:classifiers":[
        {
            "category":"Education",
            "subcategory":"Library",
            "type":"Public Place"
        }
    ],
    "sg:phone":"+1 901 775 5110",
    "sg:postcode":"38106",
    "sg:province":"TN",
    "wof:name":"M A Branch",
    "wof:placetype":"venue"
},
  "geometry": {"coordinates":[-90.018491,35.106835],"type":"Point"}
}