{
  "type": "Feature",
  "properties": {
    "addr:full":"105 Tower Dr NE Knoxville TN 37912",
    "addr:housenumber":"105",
    "addr:postcode":"37912",
    "addr:street":"Tower Dr Ne",
    "iso:country":"US",
    "sg:address":"105 Tower Dr NE",
    "sg:city":"Knoxville",
    "sg:classifiers":[
        {
            "category":"Building & Trades",
            "subcategory":"Construction",
            "type":"Services"
        }
    ],
    "sg:phone":"+1 865 687 1005",
    "sg:postcode":"37912",
    "sg:province":"TN",
    "sg:tags":[
        "house",
        "contractor"
    ],
    "wof:name":"Fence Unlimited",
    "wof:placetype":"venue"
},
  "geometry": {"coordinates":[-83.97497199999999,36.014625],"type":"Point"}
}