{
  "type": "Feature",
  "properties": {
    "addr:full":"2219 Dover Rd Woodlawn TN 37191",
    "addr:housenumber":"2219",
    "addr:postcode":"37191",
    "addr:street":"Dover Rd",
    "iso:country":"US",
    "sg:address":"2219 Dover Rd",
    "sg:city":"Woodlawn",
    "sg:classifiers":[
        {
            "category":"Restaurant",
            "type":"Food & Drink"
        }
    ],
    "sg:phone":"+1 931 920 2252",
    "sg:postcode":"37191",
    "sg:province":"TN",
    "sg:tags":[
        "fast"
    ],
    "wof:name":"Bojangles Restaurant",
    "wof:placetype":"venue"
},
  "geometry": {"coordinates":[-87.498531,36.545685],"type":"Point"}
}