{
  "type": "Feature",
  "properties": {
    "iso:country":"US",
    "sg:address":"3731 Ringgold Rd",
    "sg:city":"Chattanooga",
    "sg:classifiers":[
        {
            "category":"Professional",
            "subcategory":"Accounting & Tax Preparation",
            "type":"Services"
        }
    ],
    "sg:phone":"+1 423 624 4886",
    "sg:postcode":"37412",
    "sg:province":"TN",
    "wof:name":"Townsend & Assoc",
    "wof:placetype":"venue"
},
  "geometry": {"coordinates":[-85.255788,34.999132],"type":"Point"}
}