{
  "type": "Feature",
  "properties": {
    "iso:country":"US",
    "sg:address":"1306 Rock Creek Trce",
    "sg:city":"Whites Creek",
    "sg:classifiers":[
        {
            "category":"Building & Trades",
            "subcategory":"Construction",
            "type":"Services"
        }
    ],
    "sg:phone":"+1 615 876 7622",
    "sg:postcode":"37189",
    "sg:province":"TN",
    "sg:tags":[
        "general",
        "contractor"
    ],
    "wof:name":"David L Williams Construction",
    "wof:placetype":"venue"
},
  "geometry": {"coordinates":[-86.79867299999999,36.239066],"type":"Point"}
}