{
  "type": "Feature",
  "properties": {
    "iso:country":"US",
    "sg:address":"5211 Maryland Way",
    "sg:city":"Brentwood",
    "sg:classifiers":[
        {
            "category":"Government",
            "subcategory":"Office",
            "type":"Public Place"
        }
    ],
    "sg:phone":"+1 615 371 0060",
    "sg:postcode":"37027",
    "sg:province":"TN",
    "sg:tags":[
        "village"
    ],
    "wof:name":"Brentwood City Admin",
    "wof:placetype":"venue"
},
  "geometry": {"coordinates":[-86.80579299999999,36.03514],"type":"Point"}
}