{
  "type": "Feature",
  "properties": {
    "iso:country":"US",
    "sg:address":"118 N Lafayette Ave",
    "sg:city":"Brownsville",
    "sg:classifiers":[
        {
            "category":"Government",
            "subcategory":"Office",
            "type":"Public Place"
        },
        {
            "category":"Government",
            "subcategory":"Fire Station",
            "type":"Public Place"
        }
    ],
    "sg:phone":"+1 731 772 1215",
    "sg:postcode":"38012",
    "sg:province":"TN",
    "sg:tags":[
        "department",
        "village"
    ],
    "wof:name":"Brownsville Cty Cntrl Dispatch",
    "wof:placetype":"venue"
},
  "geometry": {"coordinates":[-89.26286,35.59564],"type":"Point"}
}