{
  "type": "Feature",
  "properties": {
    "addr:full":"4918 Kingston Pike Knoxville TN 37919",
    "addr:housenumber":"4918",
    "addr:postcode":"37919",
    "addr:street":"Kingston Pike",
    "iso:country":"US",
    "sg:address":"4918 Kingston Pike",
    "sg:city":"Knoxville",
    "sg:classifiers":[
        {
            "category":"Retail",
            "subcategory":"Car Wash",
            "type":"Services"
        }
    ],
    "sg:phone":"+1 865 922 7698",
    "sg:postcode":"37919",
    "sg:province":"TN",
    "sg:tags":[
        "automobile",
        "detail",
        "clean"
    ],
    "wof:name":"Howard Horn Pinstriping",
    "wof:placetype":"venue"
},
  "geometry": {"coordinates":[-83.986586,35.940155],"type":"Point"}
}