{
  "type": "Feature",
  "properties": {
    "addr:full":"308 Tammy Dr Powell TN 37849",
    "addr:housenumber":"308",
    "addr:postcode":"37849",
    "addr:street":"Tammy Dr",
    "iso:country":"US",
    "sg:address":"308 Tammy Dr",
    "sg:city":"Powell",
    "sg:classifiers":[
        {
            "category":"Retail",
            "subcategory":"Auto Repair",
            "type":"Services"
        }
    ],
    "sg:phone":"+1 865 938 3550",
    "sg:postcode":"37849",
    "sg:province":"TN",
    "sg:tags":[
        "body"
    ],
    "wof:name":"Larry Griffy",
    "wof:placetype":"venue"
},
  "geometry": {"coordinates":[-84.00803999999999,36.0528],"type":"Point"}
}