{
  "type": "Feature",
  "properties": {
    "iso:country":"US",
    "sg:address":"7 Meadowood Dr",
    "sg:city":"Jackson",
    "sg:classifiers":[
        {
            "category":"Building & Trades",
            "subcategory":"Cleaning & Sanitation",
            "type":"Services"
        }
    ],
    "sg:phone":"+1 731 668 0051",
    "sg:postcode":"38305",
    "sg:province":"TN",
    "sg:tags":[
        "maintenance"
    ],
    "wof:name":"E Pack Janitorial Services",
    "wof:placetype":"venue"
},
  "geometry": {"coordinates":[-88.832195,35.72063],"type":"Point"}
}