{
  "type": "Feature",
  "properties": {
    "iso:country":"US",
    "sg:address":"2413 Cedar Creek Dr",
    "sg:city":"Chattanooga",
    "sg:classifiers":[
        {
            "category":"Manufacturing",
            "subcategory":"Printing",
            "type":"Manufacturing & Wholesale Goods"
        }
    ],
    "sg:phone":"+1 423 899 6362",
    "sg:postcode":"37421",
    "sg:province":"TN",
    "sg:tags":[
        "commercial"
    ],
    "wof:name":"Ballparks Inc",
    "wof:placetype":"venue"
},
  "geometry": {"coordinates":[-85.109162,35.024237],"type":"Point"}
}