{
  "type": "Feature",
  "properties": {
    "iso:country":"US",
    "sg:address":"926 Center View Rd",
    "sg:city":"Sevierville",
    "sg:classifiers":[
        {
            "category":"Shopping",
            "subcategory":"Used Merchandise",
            "type":"Retail Goods"
        }
    ],
    "sg:phone":"+1 865 774 8009",
    "sg:postcode":"37862",
    "sg:province":"TN",
    "wof:name":"Shields Merchantile & Emporium",
    "wof:placetype":"venue"
},
  "geometry": {"coordinates":[-83.550721,35.822835],"type":"Point"}
}