{
  "type": "Feature",
  "properties": {
    "addr:full":"8515 Macon Rd Cordova TN 38018",
    "addr:housenumber":"8515",
    "addr:postcode":"38018",
    "addr:street":"Macon Rd",
    "iso:country":"US",
    "sg:address":"8515 Macon Rd",
    "sg:city":"Cordova",
    "sg:classifiers":[
        {
            "category":"Building & Trades",
            "subcategory":"Pest Control",
            "type":"Services"
        }
    ],
    "sg:phone":"+1 901 737 7378",
    "sg:postcode":"38018",
    "sg:province":"TN",
    "sg:website":"http://www.midsouthtrust.com",
    "wof:name":"AAA Termite Control",
    "wof:placetype":"venue"
},
  "geometry": {"coordinates":[-89.778842,35.155905],"type":"Point"}
}