{
  "type": "Feature",
  "properties": {
    "iso:country":"US",
    "sg:address":"7307 Nolensville Rd",
    "sg:city":"Nolensville",
    "sg:classifiers":[
        {
            "category":"Professional",
            "subcategory":"Business Services",
            "type":"Services"
        }
    ],
    "sg:phone":"+1 615 776 7224",
    "sg:postcode":"37135",
    "sg:province":"TN",
    "sg:tags":[
        "interior",
        "consultant",
        "design",
        "decorator"
    ],
    "wof:name":"Cathy Lynn's Home Decor",
    "wof:placetype":"venue"
},
  "geometry": {"coordinates":[-86.669736,35.952708],"type":"Point"}
}