{
  "type": "Feature",
  "properties": {
    "addr:full":"4679 Elvis Presley Blvd Memphis TN 38116",
    "addr:housenumber":"4679",
    "addr:postcode":"38116",
    "addr:street":"Elvis Presley Blvd",
    "iso:country":"US",
    "sg:address":"4679 Elvis Presley Blvd",
    "sg:city":"Memphis",
    "sg:classifiers":[
        {
            "category":"Autos & Motor Vehicles",
            "subcategory":"Fuel & Gas Station",
            "type":"Retail Goods"
        }
    ],
    "sg:phone":"+1 901 398 2385",
    "sg:postcode":"38116",
    "sg:province":"TN",
    "sg:tags":[
        "oil"
    ],
    "wof:name":"Exxon Mobil Corp",
    "wof:placetype":"venue"
},
  "geometry": {"coordinates":[-90.025282,35.02056],"type":"Point"}
}