{
  "type": "Feature",
  "properties": {
    "iso:country":"US",
    "sg:address":"307 Wesley St",
    "sg:city":"Johnson City",
    "sg:classifiers":[
        {
            "category":"Professional",
            "subcategory":"Management & Consulting",
            "type":"Services"
        }
    ],
    "sg:phone":"+1 423 282 2118",
    "sg:postcode":"37601",
    "sg:province":"TN",
    "sg:tags":[
        "support",
        "facility"
    ],
    "wof:name":"Upper East Reg Juvenile Det",
    "wof:placetype":"venue"
},
  "geometry": {"coordinates":[-82.37648900000001,36.351516],"type":"Point"}
}