{
  "type": "Feature",
  "properties": {
    "iso:country":"US",
    "sg:address":"3106 N Broadway St",
    "sg:city":"Knoxville",
    "sg:classifiers":[
        {
            "category":"Building & Trades",
            "subcategory":"Cleaning & Sanitation",
            "type":"Services"
        }
    ],
    "sg:phone":"+1 865 219 8688",
    "sg:postcode":"37917",
    "sg:province":"TN",
    "sg:tags":[
        "maintenance"
    ],
    "wof:name":"National Building Service T",
    "wof:placetype":"venue"
},
  "geometry": {"coordinates":[-83.92572800000001,36.001191],"type":"Point"}
}