{
  "type": "Feature",
  "properties": {
    "iso:country":"US",
    "sg:address":"1132 W Madison Ave",
    "sg:city":"Athens",
    "sg:classifiers":[
        {
            "category":"Health Services",
            "subcategory":"Doctor",
            "type":"Services"
        }
    ],
    "sg:phone":"+1 423 745 5405",
    "sg:postcode":"37303",
    "sg:province":"TN",
    "wof:name":"J L Dugan DDS",
    "wof:placetype":"venue"
},
  "geometry": {"coordinates":[-84.608356,35.440653],"type":"Point"}
}