{
  "type": "Feature",
  "properties": {
    "addr:full":"328 Logan St Seymour TN 37865",
    "addr:housenumber":"328",
    "addr:postcode":"37865",
    "addr:street":"Logan St",
    "iso:country":"US",
    "sg:address":"328 Logan St",
    "sg:city":"Seymour",
    "sg:classifiers":[
        {
            "category":"Building & Trades",
            "subcategory":"Construction",
            "type":"Services"
        }
    ],
    "sg:phone":"+1 865 577 6169",
    "sg:postcode":"37865",
    "sg:province":"TN",
    "wof:name":"Max D Baker Contractor",
    "wof:placetype":"venue"
},
  "geometry": {"coordinates":[-83.757064,35.864683],"type":"Point"}
}