{
  "type": "Feature",
  "properties": {
    "addr:full":"501 S Lindell St Martin TN 38237",
    "addr:housenumber":"501",
    "addr:postcode":"38237",
    "addr:street":"S Lindell St",
    "iso:country":"US",
    "sg:address":"501 S Lindell St",
    "sg:city":"Martin",
    "sg:classifiers":[
        {
            "category":"Government",
            "subcategory":"Office",
            "type":"Public Place"
        }
    ],
    "sg:phone":"+1 731 587 9523",
    "sg:postcode":"38237",
    "sg:province":"TN",
    "wof:name":"Weakley County Electric System",
    "wof:placetype":"venue"
},
  "geometry": {"coordinates":[-88.850647,36.342062],"type":"Point"}
}