{
  "type": "Feature",
  "properties": {
    "iso:country":"US",
    "sg:address":"765 Florence Rd",
    "sg:city":"Savannah",
    "sg:classifiers":[
        {
            "category":"Social Services",
            "subcategory":"Adult Care",
            "type":"Services"
        },
        {
            "category":"Organizations",
            "subcategory":"Political Organization",
            "type":"Services"
        }
    ],
    "sg:phone":"+1 731 925 9424",
    "sg:postcode":"38372",
    "sg:province":"TN",
    "sg:tags":[
        "foster"
    ],
    "wof:name":"Foster Care",
    "wof:placetype":"venue"
},
  "geometry": {"coordinates":[-88.239369,35.212321],"type":"Point"}
}