{
  "type": "Feature",
  "properties": {
    "iso:country":"US",
    "sg:address":"7810 Barker Rd",
    "sg:city":"Corryton",
    "sg:classifiers":[
        {
            "category":"Shopping",
            "subcategory":"Gifts & Souvenirs",
            "type":"Retail Goods"
        }
    ],
    "sg:phone":"+1 865 689 6736",
    "sg:postcode":"37721",
    "sg:province":"TN",
    "sg:tags":[
        "collectible"
    ],
    "wof:name":"Jack & Terri's Collectibles",
    "wof:placetype":"venue"
},
  "geometry": {"coordinates":[-83.856871,36.139376],"type":"Point"}
}