{
  "type": "Feature",
  "properties": {
    "addr:full":"5900 Chapman Hwy Knoxville TN 37920",
    "addr:housenumber":"5900",
    "addr:postcode":"37920",
    "addr:street":"Chapman Hwy",
    "iso:country":"US",
    "sg:address":"5900 Chapman Hwy",
    "sg:city":"Knoxville",
    "sg:classifiers":[
        {
            "category":"Retail",
            "subcategory":"Veterinary Services",
            "type":"Services"
        }
    ],
    "sg:phone":"+1 865 577 0344",
    "sg:postcode":"37920",
    "sg:province":"TN",
    "wof:name":"Dogwood Animal Hospital",
    "wof:placetype":"venue"
},
  "geometry": {"coordinates":[-83.88057499999999,35.921959],"type":"Point"}
}