{
  "type": "Feature",
  "properties": {
    "iso:country":"US",
    "sg:address":"153 Fence Ln",
    "sg:city":"Crossville",
    "sg:classifiers":[
        {
            "category":"Retail",
            "subcategory":"Animal Services",
            "type":"Services"
        }
    ],
    "sg:phone":"+1 931 456 8685",
    "sg:postcode":"38571",
    "sg:province":"TN",
    "wof:name":"Bed & Biscuit Kennel",
    "wof:placetype":"venue"
},
  "geometry": {"coordinates":[-84.938902,35.990763],"type":"Point"}
}