{
  "type": "Feature",
  "properties": {
    "iso:country":"US",
    "sg:address":"1655 Potter Town Rd",
    "sg:city":"Midway",
    "sg:classifiers":[
        {
            "category":"Building & Trades",
            "subcategory":"Cleaning & Sanitation",
            "type":"Services"
        }
    ],
    "sg:phone":"+1 423 235 9700",
    "sg:postcode":"37809",
    "sg:province":"TN",
    "sg:tags":[
        "janitor"
    ],
    "sg:website":"www.ihservices.com",
    "wof:name":"I H Svc",
    "wof:placetype":"venue"
},
  "geometry": {"coordinates":[-83.023016,36.203077],"type":"Point"}
}