{
  "type": "Feature",
  "properties": {
    "iso:country":"US",
    "sg:address":"616 Adams Ave",
    "sg:city":"Memphis",
    "sg:classifiers":[
        {
            "category":"Social Services",
            "type":"Services"
        }
    ],
    "sg:phone":"+1 901 405 8444",
    "sg:postcode":"38105",
    "sg:province":"TN",
    "sg:tags":[
        "probation"
    ],
    "wof:name":"Hanover House",
    "wof:placetype":"venue"
},
  "geometry": {"coordinates":[-90.037549,35.144513],"type":"Point"}
}