{
  "type": "Feature",
  "properties": {
    "addr:full":"3707 Clubview Dr Memphis TN 38125",
    "addr:housenumber":"3707",
    "addr:postcode":"38125",
    "addr:street":"Clubview Dr",
    "iso:country":"US",
    "sg:address":"3707 Clubview Dr",
    "sg:city":"Memphis",
    "sg:classifiers":[
        {
            "category":"Professional",
            "subcategory":"Detective & Security Services",
            "type":"Services"
        }
    ],
    "sg:phone":"+1 901 755 5080",
    "sg:postcode":"38125",
    "sg:province":"TN",
    "sg:tags":[
        "equipment",
        "electrical",
        "system"
    ],
    "wof:name":"Matrix Alarm Company Inc",
    "wof:placetype":"venue"
},
  "geometry": {"coordinates":[-89.78927899999999,35.047959],"type":"Point"}
}