{
  "type": "Feature",
  "properties": {
    "iso:country":"US",
    "sg:address":"1608 Bell Rd",
    "sg:city":"Nashville",
    "sg:classifiers":[
        {
            "category":"Organizations",
            "subcategory":"Religious Organization",
            "type":"Services"
        }
    ],
    "sg:phone":"+1 615 833 4444",
    "sg:postcode":"37211",
    "sg:province":"TN",
    "wof:name":"Bell Road Church Of Christ",
    "wof:placetype":"venue"
},
  "geometry": {"coordinates":[-86.697396,36.044896],"type":"Point"}
}