{
  "type": "Feature",
  "properties": {
    "addr:full":"2201 Davidson Graveyard Rd Clarksville TN 37043",
    "addr:housenumber":"2201",
    "addr:postcode":"37043",
    "addr:street":"Davidson Graveyard Rd",
    "iso:country":"US",
    "sg:address":"2201 Davidson Graveyard Rd",
    "sg:city":"Clarksville",
    "sg:classifiers":[
        {
            "category":"Retail",
            "subcategory":"Portrait Studio",
            "type":"Services"
        }
    ],
    "sg:phone":"+1 931 551 5145",
    "sg:postcode":"37043",
    "sg:province":"TN",
    "sg:tags":[
        "photo"
    ],
    "wof:name":"Winters Cozette Photographers",
    "wof:placetype":"venue"
},
  "geometry": {"coordinates":[-87.26049999999999,36.429597],"type":"Point"}
}