{
  "type": "Feature",
  "properties": {
    "iso:country":"US",
    "sg:address":"1036 W Poplar Ave",
    "sg:city":"Collierville",
    "sg:classifiers":[
        {
            "category":"Restaurant",
            "type":"Food & Drink"
        }
    ],
    "sg:menulink":"http://www.allmenus.com/tn/collierville/179185-chick-fil-a/menu/",
    "sg:phone":"+1 901 853 1786",
    "sg:postcode":"38017",
    "sg:province":"TN",
    "sg:tags":[
        "wrap",
        "soup",
        "american",
        "sandwich",
        "salad"
    ],
    "wof:name":"Chick-fil-A",
    "wof:placetype":"venue"
},
  "geometry": {"coordinates":[-89.69690900000001,35.046815],"type":"Point"}
}