{
  "type": "Feature",
  "properties": {
    "iso:country":"US",
    "sg:address":"1188 Long Hollow Pike",
    "sg:city":"Gallatin",
    "sg:classifiers":[
        {
            "category":"Organizations",
            "subcategory":"Non-profit Organization",
            "type":"Services"
        }
    ],
    "sg:phone":"+1 615 452 7337",
    "sg:postcode":"37066",
    "sg:province":"TN",
    "sg:tags":[
        "human"
    ],
    "wof:name":"Good Neighbor Mission",
    "wof:placetype":"venue"
},
  "geometry": {"coordinates":[-86.475461,36.387707],"type":"Point"}
}