{
  "type": "Feature",
  "properties": {
    "iso:country":"US",
    "sg:address":"200 Hayfield Rd",
    "sg:city":"Knoxville",
    "sg:classifiers":[
        {
            "category":"Shopping",
            "subcategory":"Department Store",
            "type":"Retail Goods"
        }
    ],
    "sg:phone":"+1 865 694 9029",
    "sg:postcode":"37922",
    "sg:province":"TN",
    "wof:name":"Peebles",
    "wof:placetype":"venue"
},
  "geometry": {"coordinates":[-84.10364800000001,35.910631],"type":"Point"}
}