{
  "type": "Feature",
  "properties": {
    "iso:country":"US",
    "sg:address":"220 S Peters Rd",
    "sg:city":"Knoxville",
    "sg:classifiers":[
        {
            "category":"Banks & Credit Unions",
            "subcategory":"Investment Brokerage",
            "type":"Services"
        }
    ],
    "sg:phone":"+1 865 693 6891",
    "sg:postcode":"37923",
    "sg:province":"TN",
    "sg:tags":[
        "consultant",
        "planning",
        "financial"
    ],
    "wof:name":"Capital Investments Inc",
    "wof:placetype":"venue"
},
  "geometry": {"coordinates":[-84.079525,35.909323],"type":"Point"}
}