{
  "type": "Feature",
  "properties": {
    "iso:country":"US",
    "sg:address":"401 Acorn Ct",
    "sg:city":"Smyrna",
    "sg:classifiers":[
        {
            "category":"Professional",
            "type":"Services"
        }
    ],
    "sg:phone":"+1 615 223 6344",
    "sg:postcode":"37167",
    "sg:province":"TN",
    "wof:name":"Tennessee Web Mall",
    "wof:placetype":"venue"
},
  "geometry": {"coordinates":[-86.52578,35.962671],"type":"Point"}
}