{
  "type": "Feature",
  "properties": {
    "iso:country":"US",
    "sg:address":"167 Stanley St",
    "sg:city":"Oneida",
    "sg:classifiers":[
        {
            "category":"Real Estate",
            "subcategory":"Real Estate Agent",
            "type":"Services"
        }
    ],
    "sg:phone":"+1 423 569 3362",
    "sg:postcode":"37841",
    "sg:province":"TN",
    "wof:name":"Slavens Rentals",
    "wof:placetype":"venue"
},
  "geometry": {"coordinates":[-84.52207799999999,36.503202],"type":"Point"}
}