{
  "type": "Feature",
  "properties": {
    "iso:country":"US",
    "sg:address":"1111 Morrison Viola Rd",
    "sg:city":"Morrison",
    "sg:classifiers":[
        {
            "category":"Retail",
            "subcategory":"Auto Repair",
            "type":"Services"
        }
    ],
    "sg:phone":"+1 931 635 2868",
    "sg:postcode":"37357",
    "sg:province":"TN",
    "sg:tags":[
        "general"
    ],
    "wof:name":"Greg Hullett Automotive",
    "wof:placetype":"venue"
},
  "geometry": {"coordinates":[-85.900784,35.593894],"type":"Point"}
}