{
  "type": "Feature",
  "properties": {
    "addr:full":"1834 Cowden Ave Memphis TN 38104",
    "addr:housenumber":"1834",
    "addr:postcode":"38104",
    "addr:street":"Cowden Ave",
    "iso:country":"US",
    "sg:address":"1834 Cowden Ave",
    "sg:city":"Memphis",
    "sg:classifiers":[
        {
            "category":"Professional",
            "subcategory":"Art Services",
            "type":"Services"
        }
    ],
    "sg:phone":"+1 901 722 9708",
    "sg:postcode":"38104",
    "sg:province":"TN",
    "sg:tags":[
        "graphic",
        "designer"
    ],
    "wof:name":"Himber Design",
    "wof:placetype":"venue"
},
  "geometry": {"coordinates":[-90.000366,35.12817],"type":"Point"}
}