{
  "type": "Feature",
  "properties": {
    "iso:country":"US",
    "sg:address":"410 Springhouse Ct",
    "sg:city":"Franklin",
    "sg:classifiers":[
        {
            "category":"Building & Trades",
            "subcategory":"Construction",
            "type":"Services"
        }
    ],
    "sg:phone":"+1 615 595 6917",
    "sg:postcode":"37067",
    "sg:province":"TN",
    "sg:tags":[
        "contractor"
    ],
    "wof:name":"Clearview Contractors",
    "wof:placetype":"venue"
},
  "geometry": {"coordinates":[-86.808165,35.912429],"type":"Point"}
}