{
  "type": "Feature",
  "properties": {
    "iso:country":"US",
    "sg:address":"7592 Crow Cut Rd",
    "sg:city":"Fairview",
    "sg:classifiers":[
        {
            "category":"Building & Trades",
            "subcategory":"Construction",
            "type":"Services"
        }
    ],
    "sg:phone":"+1 615 799 2749",
    "sg:postcode":"37062",
    "sg:province":"TN",
    "wof:name":"Liberty Hill LLC",
    "wof:placetype":"venue"
},
  "geometry": {"coordinates":[-87.18305599999999,35.979019],"type":"Point"}
}