{
  "type": "Feature",
  "properties": {
    "iso:country":"US",
    "sg:address":"3660 Brookmeade St",
    "sg:city":"Memphis",
    "sg:classifiers":[
        {
            "category":"Travel",
            "subcategory":"Travel Agent",
            "type":"Entertainment"
        }
    ],
    "sg:phone":"+1 901 358 7773",
    "sg:postcode":"38127",
    "sg:province":"TN",
    "sg:tags":[
        "agency"
    ],
    "wof:name":"International Concierge",
    "wof:placetype":"venue"
},
  "geometry": {"coordinates":[-89.98032000000001,35.225982],"type":"Point"}
}