{
  "type": "Feature",
  "properties": {
    "iso:country":"US",
    "sg:address":"5891 Jardin Pl",
    "sg:city":"Memphis",
    "sg:classifiers":[
        {
            "category":"Wholesale",
            "subcategory":"Non-durable Goods",
            "type":"Manufacturing & Wholesale Goods"
        }
    ],
    "sg:phone":"+1 901 644 3931",
    "sg:postcode":"38141",
    "sg:province":"TN",
    "wof:name":"Cswltdcom",
    "wof:placetype":"venue"
},
  "geometry": {"coordinates":[-89.86898100000001,35.029771],"type":"Point"}
}