{
  "type": "Feature",
  "properties": {
    "iso:country":"US",
    "sg:address":"222 Forks of the River Pkwy",
    "sg:city":"Sevierville",
    "sg:classifiers":[
        {
            "category":"Personal",
            "subcategory":"Beauty Salon",
            "type":"Services"
        }
    ],
    "sg:phone":"+1 865 428 9972",
    "sg:postcode":"37862",
    "sg:province":"TN",
    "wof:name":"Guys & Dolls Hair Salon",
    "wof:placetype":"venue"
},
  "geometry": {"coordinates":[-83.567514,35.866783],"type":"Point"}
}