{
  "type": "Feature",
  "properties": {
    "addr:full":"1217 Pin Pointe Dr Collierville TN 38017",
    "addr:housenumber":"1217",
    "addr:postcode":"38017",
    "addr:street":"Pin Pointe Dr",
    "iso:country":"US",
    "sg:address":"1217 Pin Pointe Dr",
    "sg:city":"Collierville",
    "sg:classifiers":[
        {
            "category":"Professional",
            "subcategory":"Management & Consulting",
            "type":"Services"
        }
    ],
    "sg:phone":"+1 901 854 2531",
    "sg:postcode":"38017",
    "sg:province":"TN",
    "wof:name":"Sutherland Consult",
    "wof:placetype":"venue"
},
  "geometry": {"coordinates":[-89.68972100000001,35.072981],"type":"Point"}
}