{
  "type": "Feature",
  "properties": {
    "addr:full":"3048 Grandview Way White Pine TN 37890",
    "addr:housenumber":"3048",
    "addr:postcode":"37890",
    "addr:street":"Grandview Way",
    "iso:country":"US",
    "sg:address":"3048 Grandview Way",
    "sg:city":"White Pine",
    "sg:classifiers":[
        {
            "category":"Building & Trades",
            "subcategory":"Construction",
            "type":"Services"
        }
    ],
    "sg:phone":"+1 865 674 8585",
    "sg:postcode":"37890",
    "sg:province":"TN",
    "sg:tags":[
        "contractor"
    ],
    "wof:name":"Jim Arnolds Chimney Sweeps",
    "wof:placetype":"venue"
},
  "geometry": {"coordinates":[-83.276504,36.107026],"type":"Point"}
}