{
  "type": "Feature",
  "properties": {
    "iso:country":"US",
    "sg:address":"1228 Mississippi Ave",
    "sg:city":"Cookeville",
    "sg:classifiers":[
        {
            "category":"Home & Garden",
            "subcategory":"Building Materials",
            "type":"Retail Goods"
        }
    ],
    "sg:phone":"+1 931 525 7329",
    "sg:postcode":"38501",
    "sg:province":"TN",
    "wof:name":"TCI Fencing",
    "wof:placetype":"venue"
},
  "geometry": {"coordinates":[-85.500654,36.179323],"type":"Point"}
}