{
  "type": "Feature",
  "properties": {
    "addr:full":"1404 Dickerson Pike Nashville TN 37207",
    "addr:housenumber":"1404",
    "addr:postcode":"37207",
    "addr:street":"Dickerson Pike",
    "iso:country":"US",
    "sg:address":"1404 Dickerson Pike",
    "sg:city":"Nashville",
    "sg:classifiers":[
        {
            "category":"Travel",
            "subcategory":"Hotels & Motels",
            "type":"Entertainment"
        }
    ],
    "sg:phone":"+1 615 227 6768",
    "sg:postcode":"37207",
    "sg:province":"TN",
    "wof:name":"Metro Motel",
    "wof:placetype":"venue"
},
  "geometry": {"coordinates":[-86.772023,36.196174],"type":"Point"}
}