{
  "type": "Feature",
  "properties": {
    "iso:country":"US",
    "sg:address":"12610 State Hwy 69 N",
    "sg:city":"Cottage Grove",
    "sg:classifiers":[
        {
            "category":"Farming",
            "subcategory":"Farm",
            "type":"Manufacturing & Wholesale Goods"
        }
    ],
    "sg:phone":"+1 731 782 3331",
    "sg:postcode":"38224",
    "sg:province":"TN",
    "sg:tags":[
        "crop",
        "general"
    ],
    "wof:name":"Wilson Farm",
    "wof:placetype":"venue"
},
  "geometry": {"coordinates":[-88.47484799999999,36.429412],"type":"Point"}
}