{
  "type": "Feature",
  "properties": {
    "iso:country":"US",
    "sg:address":"980 Co Rd 100",
    "sg:city":"Jasper",
    "sg:classifiers":[
        {
            "category":"Health Services",
            "subcategory":"Doctor",
            "type":"Services"
        }
    ],
    "sg:phone":"+1 423 942 1602",
    "sg:postcode":"37303",
    "sg:province":"TN",
    "sg:tags":[
        "clinic"
    ],
    "wof:name":"Medical Arts Plaza",
    "wof:placetype":"venue"
},
  "geometry": {"coordinates":[-84.74203900000001,35.439549],"type":"Point"}
}