{
  "type": "Feature",
  "properties": {
    "addr:full":"4254 Ivy Ave Knoxville TN 37914",
    "addr:housenumber":"4254",
    "addr:postcode":"37914",
    "addr:street":"Ivy Ave",
    "iso:country":"US",
    "sg:address":"4254 Ivy Ave",
    "sg:city":"Knoxville",
    "sg:classifiers":[
        {
            "category":"Home & Garden",
            "subcategory":"Building Materials",
            "type":"Retail Goods"
        }
    ],
    "sg:phone":"+1 865 637 8717",
    "sg:postcode":"37914",
    "sg:province":"TN",
    "sg:tags":[
        "door"
    ],
    "wof:name":"Mid-South Automatic Door",
    "wof:placetype":"venue"
},
  "geometry": {"coordinates":[-83.863328,35.999859],"type":"Point"}
}