{
  "type": "Feature",
  "properties": {
    "iso:country":"US",
    "sg:address":"7030 Lee Hwy",
    "sg:city":"Chattanooga",
    "sg:classifiers":[
        {
            "category":"Banks & Credit Unions",
            "subcategory":"Bank",
            "type":"Services"
        }
    ],
    "sg:phone":"+1 423 296 8112",
    "sg:postcode":"37421",
    "sg:province":"TN",
    "sg:tags":[
        "loan",
        "mortgage",
        "real estate"
    ],
    "wof:name":"American First Mortgage",
    "wof:placetype":"venue"
},
  "geometry": {"coordinates":[-85.159273,35.04678],"type":"Point"}
}