{
  "type": "Feature",
  "properties": {
    "iso:country":"US",
    "sg:address":"7011 Shallowford Rd",
    "sg:city":"Chattanooga",
    "sg:classifiers":[
        {
            "category":"Health Services",
            "subcategory":"Doctor",
            "type":"Services"
        }
    ],
    "sg:phone":"+1 423 485 9008",
    "sg:postcode":"37421",
    "sg:province":"TN",
    "sg:tags":[
        "physician",
        "surgeon",
        "medical"
    ],
    "wof:name":"Rapha Medical Center",
    "wof:placetype":"venue"
},
  "geometry": {"coordinates":[-85.159817,35.044024],"type":"Point"}
}