{
  "type": "Feature",
  "properties": {
    "iso:country":"US",
    "sg:address":"210 Fisher Aly",
    "sg:city":"Lawrenceburg",
    "sg:classifiers":[
        {
            "category":"Personal",
            "subcategory":"Beauty Salon",
            "type":"Services"
        }
    ],
    "sg:phone":"+1 931 762 9055",
    "sg:postcode":"38464",
    "sg:province":"TN",
    "sg:tags":[
        "shop"
    ],
    "wof:name":"Touches",
    "wof:placetype":"venue"
},
  "geometry": {"coordinates":[-87.33931,35.244664],"type":"Point"}
}