{
  "type": "Feature",
  "properties": {
    "iso:country":"US",
    "sg:address":"125 W Main St",
    "sg:city":"Mountain City",
    "sg:classifiers":[
        {
            "category":"Home & Garden",
            "subcategory":"Furniture",
            "type":"Retail Goods"
        }
    ],
    "sg:phone":"+1 423 727 5716",
    "sg:postcode":"37683",
    "sg:province":"TN",
    "wof:name":"Furniture Liquidators",
    "wof:placetype":"venue"
},
  "geometry": {"coordinates":[-81.804225,36.474447],"type":"Point"}
}