{
  "type": "Feature",
  "properties": {
    "iso:country":"US",
    "sg:address":"10455 Monroe Rd",
    "sg:city":"Arlington",
    "sg:classifiers":[
        {
            "category":"Professional",
            "type":"Services"
        }
    ],
    "sg:phone":"+1 901 867 8127",
    "sg:postcode":"38002",
    "sg:province":"TN",
    "wof:name":"Pointe LLC",
    "wof:placetype":"venue"
},
  "geometry": {"coordinates":[-89.716381,35.224954],"type":"Point"}
}