{
  "type": "Feature",
  "properties": {
    "iso:country":"US",
    "sg:address":"178 2nd Ave N",
    "sg:city":"Nashville",
    "sg:classifiers":[
        {
            "category":"Real Estate",
            "subcategory":"Real Estate Operator",
            "type":"Services"
        }
    ],
    "sg:phone":"+1 615 256 6497",
    "sg:postcode":"37201",
    "sg:province":"TN",
    "sg:tags":[
        "building",
        "apartment"
    ],
    "wof:name":"Quarters Apartments",
    "wof:placetype":"venue"
},
  "geometry": {"coordinates":[-86.77660400000001,36.164208],"type":"Point"}
}