{
  "type": "Feature",
  "properties": {
    "addr:full":"168 Jack Miller Blvd Clarksville TN 37042",
    "addr:housenumber":"168",
    "addr:postcode":"37042",
    "addr:street":"Jack Miller Blvd",
    "iso:country":"US",
    "sg:address":"168 Jack Miller Blvd",
    "sg:city":"Clarksville",
    "sg:classifiers":[
        {
            "category":"Professional",
            "type":"Services"
        },
        {
            "category":"Education",
            "subcategory":"Special Training",
            "type":"Public Place"
        }
    ],
    "sg:phone":"+1 931 431 9762",
    "sg:postcode":"37042",
    "sg:province":"TN",
    "sg:tags":[
        "establishment"
    ],
    "wof:name":"Quantum Enterprise LP",
    "wof:placetype":"venue"
},
  "geometry": {"coordinates":[-87.426689,36.615877],"type":"Point"}
}