{
  "type": "Feature",
  "properties": {
    "addr:full":"302 Sunset Dr Johnson City TN 37604",
    "addr:housenumber":"302",
    "addr:postcode":"37604",
    "addr:street":"Sunset Dr",
    "iso:country":"US",
    "sg:address":"302 Sunset Dr",
    "sg:city":"Johnson City",
    "sg:classifiers":[
        {
            "category":"Health Services",
            "subcategory":"Optometrist",
            "type":"Services"
        }
    ],
    "sg:phone":"+1 423 282 5063",
    "sg:postcode":"37604",
    "sg:province":"TN",
    "wof:name":"Richard A Rosenberg Od",
    "wof:placetype":"venue"
},
  "geometry": {"coordinates":[-82.37653,36.343591],"type":"Point"}
}