{
  "type": "Feature",
  "properties": {
    "iso:country":"US",
    "sg:address":"6157 Homeland Dr",
    "sg:city":"Nashville",
    "sg:classifiers":[
        {
            "category":"Real Estate",
            "subcategory":"Real Estate Operator",
            "type":"Services"
        }
    ],
    "sg:phone":"+1 615 838 3039",
    "sg:postcode":"37218",
    "sg:province":"TN",
    "sg:tags":[
        "property",
        "lessor"
    ],
    "wof:name":"Juanita J Swett",
    "wof:placetype":"venue"
},
  "geometry": {"coordinates":[-86.836065,36.236542],"type":"Point"}
}