{
  "type": "Feature",
  "properties": {
    "addr:full":"629 W Iris Dr Nashville TN 37204",
    "addr:housenumber":"629",
    "addr:postcode":"37204",
    "addr:street":"W Iris Dr",
    "iso:country":"US",
    "sg:address":"629 W Iris Dr",
    "sg:city":"Nashville",
    "sg:classifiers":[
        {
            "category":"Real Estate",
            "subcategory":"Real Estate Agent",
            "type":"Services"
        }
    ],
    "sg:phone":"+1 615 385 1074",
    "sg:postcode":"37204",
    "sg:province":"TN",
    "sg:tags":[
        "agency"
    ],
    "wof:name":"Rice Realty Inc",
    "wof:placetype":"venue"
},
  "geometry": {"coordinates":[-86.768018,36.112395],"type":"Point"}
}