{
  "type": "Feature",
  "properties": {
    "addr:full":"713 Market St SW Knoxville TN 37902",
    "addr:housenumber":"713",
    "addr:postcode":"37902",
    "addr:street":"Market St Sw",
    "iso:country":"US",
    "sg:address":"713 Market St SW",
    "sg:city":"Knoxville",
    "sg:classifiers":[
        {
            "category":"Professional",
            "subcategory":"Lawyer & Legal Services",
            "type":"Services"
        }
    ],
    "sg:phone":"+1 865 329 3345",
    "sg:postcode":"37902",
    "sg:province":"TN",
    "sg:tags":[
        "attorney"
    ],
    "wof:name":"Patrick T Phillips",
    "wof:placetype":"venue"
},
  "geometry": {"coordinates":[-83.917902,35.962285],"type":"Point"}
}