{
  "type": "Feature",
  "properties": {
    "iso:country":"US",
    "sg:address":"4401 Asheville Hwy",
    "sg:city":"Knoxville",
    "sg:classifiers":[
        {
            "category":"Retail",
            "subcategory":"Auto Repair",
            "type":"Services"
        }
    ],
    "sg:phone":"+1 865 525 6472",
    "sg:postcode":"37914",
    "sg:province":"TN",
    "sg:tags":[
        "road"
    ],
    "wof:name":"Ogle's Wrecker Svc",
    "wof:placetype":"venue"
},
  "geometry": {"coordinates":[-83.863424,36.004712],"type":"Point"}
}