{
  "type": "Feature",
  "properties": {
    "iso:country":"US",
    "sg:address":"1697 Oak Hill Rd",
    "sg:city":"Germantown",
    "sg:classifiers":[
        {
            "category":"Real Estate",
            "subcategory":"Real Estate Operator",
            "type":"Services"
        }
    ],
    "sg:phone":"+1 901 758 2747",
    "sg:postcode":"38138",
    "sg:province":"TN",
    "sg:tags":[
        "dwelling"
    ],
    "wof:name":"Perkins Home Rentals",
    "wof:placetype":"venue"
},
  "geometry": {"coordinates":[-89.835308,35.102987],"type":"Point"}
}