{
  "type": "Feature",
  "properties": {
    "addr:full":"8 Depot Ln Sparta TN 38569",
    "addr:housenumber":"8",
    "addr:postcode":"38569",
    "addr:street":"Depot Ln",
    "iso:country":"US",
    "sg:address":"8 Depot Ln",
    "sg:city":"Sparta",
    "sg:classifiers":[
        {
            "category":"Retail",
            "subcategory":"Car Wash",
            "type":"Services"
        }
    ],
    "sg:phone":"+1 931 837 3851",
    "sg:postcode":"38569",
    "sg:province":"TN",
    "sg:tags":[
        "carwash"
    ],
    "wof:name":"Kleins Prof Auto Detail",
    "wof:placetype":"venue"
},
  "geometry": {"coordinates":[-85.854659,36.129318],"type":"Point"}
}