{
  "type": "Feature",
  "properties": {
    "addr:full":"1109 S Roan St Johnson City TN 37601",
    "addr:housenumber":"1109",
    "addr:postcode":"37601",
    "addr:street":"S Roan St",
    "iso:country":"US",
    "sg:address":"1109 S Roan St",
    "sg:city":"Johnson City",
    "sg:classifiers":[
        {
            "category":"Retail",
            "subcategory":"Auto Repair",
            "type":"Services"
        }
    ],
    "sg:phone":"+1 423 929 8140",
    "sg:postcode":"37601",
    "sg:province":"TN",
    "sg:tags":[
        "exhaust"
    ],
    "wof:name":"Discount Muffler & Brakes",
    "wof:placetype":"venue"
},
  "geometry": {"coordinates":[-82.346586,36.312599],"type":"Point"}
}