{
  "type": "Feature",
  "properties": {
    "iso:country":"US",
    "sg:address":"771 Fowler Ford Rd",
    "sg:city":"Portland",
    "sg:classifiers":[
        {
            "category":"Farming",
            "subcategory":"Dairy Farm",
            "type":"Manufacturing & Wholesale Goods"
        }
    ],
    "sg:phone":"+1 615 325 3792",
    "sg:postcode":"37148",
    "sg:province":"TN",
    "wof:name":"Raymond Hester",
    "wof:placetype":"venue"
},
  "geometry": {"coordinates":[-86.475415,36.56429],"type":"Point"}
}