{
  "type": "Feature",
  "properties": {
    "iso:country":"US",
    "sg:address":"4410 Raleigh Lagrange Dr",
    "sg:city":"Collierville",
    "sg:classifiers":[
        {
            "category":"Building & Trades",
            "subcategory":"Construction",
            "type":"Services"
        }
    ],
    "sg:phone":"+1 901 854 7189",
    "sg:postcode":"38017",
    "sg:province":"TN",
    "sg:tags":[
        "contractor"
    ],
    "wof:name":"Tile Concepts",
    "wof:placetype":"venue"
},
  "geometry": {"coordinates":[-89.620038,35.098645],"type":"Point"}
}