{
  "type": "Feature",
  "properties": {
    "iso:country":"US",
    "sg:address":"1142 Dolly Parton Pkwy",
    "sg:city":"Sevierville",
    "sg:classifiers":[
        {
            "category":"Professional",
            "subcategory":"Lawyer & Legal Services",
            "type":"Services"
        }
    ],
    "sg:phone":"+1 865 453 7990",
    "sg:postcode":"37862",
    "sg:province":"TN",
    "sg:tags":[
        "attorney"
    ],
    "wof:name":"George Garrison Attorney",
    "wof:placetype":"venue"
},
  "geometry": {"coordinates":[-83.53270500000001,35.863756],"type":"Point"}
}