{
  "type": "Feature",
  "properties": {
    "addr:full":"3340 Rocky Fork Rd Smyrna TN 37167",
    "addr:housenumber":"3340",
    "addr:postcode":"37167",
    "addr:street":"Rocky Fork Rd",
    "iso:country":"US",
    "sg:address":"3340 Rocky Fork Rd",
    "sg:city":"Smyrna",
    "sg:classifiers":[
        {
            "category":"Organizations",
            "subcategory":"Religious Organization",
            "type":"Services"
        }
    ],
    "sg:phone":"+1 615 459 0534",
    "sg:postcode":"37167",
    "sg:province":"TN",
    "sg:tags":[
        "church"
    ],
    "wof:name":"Mount View Baptist Church",
    "wof:placetype":"venue"
},
  "geometry": {"coordinates":[-86.561364,35.936987],"type":"Point"}
}