{
  "type": "Feature",
  "properties": {
    "iso:country":"US",
    "sg:address":"2200 Abbott Martin Rd",
    "sg:city":"Nashville",
    "sg:classifiers":[
        {
            "category":"Insurance",
            "subcategory":"Insurance Agent",
            "type":"Services"
        }
    ],
    "sg:phone":"+1 615 269 6635",
    "sg:postcode":"37215",
    "sg:province":"TN",
    "wof:name":"Lincoln Consulting Group Inc",
    "wof:placetype":"venue"
},
  "geometry": {"coordinates":[-86.82123,36.106586],"type":"Point"}
}