{
  "type": "Feature",
  "properties": {
    "iso:country":"US",
    "sg:address":"830 W Forest Ave",
    "sg:city":"Jackson",
    "sg:classifiers":[
        {
            "category":"Banks & Credit Unions",
            "subcategory":"Bank",
            "type":"Services"
        }
    ],
    "sg:phone":"+1 731 668 5329",
    "sg:postcode":"38301",
    "sg:province":"TN",
    "sg:tags":[
        "personal",
        "institution"
    ],
    "wof:name":"Eagle One Financial LLC",
    "wof:placetype":"venue"
},
  "geometry": {"coordinates":[-88.83831499999999,35.635796],"type":"Point"}
}