{
  "type": "Feature",
  "properties": {
    "iso:country":"US",
    "sg:address":"3638 Summer Ave",
    "sg:city":"Memphis",
    "sg:classifiers":[
        {
            "category":"Building & Trades",
            "subcategory":"Landscaping Services",
            "type":"Services"
        },
        {
            "category":"Building & Trades",
            "subcategory":"Pest Control",
            "type":"Services"
        }
    ],
    "sg:phone":"+1 901 452 1505",
    "sg:postcode":"38122",
    "sg:province":"TN",
    "sg:tags":[
        "lawn",
        "maintenance",
        "weed"
    ],
    "sg:website":"http://www.yourlawpartner.com/",
    "wof:name":"Jamison Pest & Lawn",
    "wof:placetype":"venue"
},
  "geometry": {"coordinates":[-89.939458,35.149367],"type":"Point"}
}