{
  "type": "Feature",
  "properties": {
    "addr:full":"18 Thompson Ln Nashville TN 37211",
    "addr:housenumber":"18",
    "addr:postcode":"37211",
    "addr:street":"Thompson Ln",
    "iso:country":"US",
    "sg:address":"18 Thompson Ln",
    "sg:city":"Nashville",
    "sg:classifiers":[
        {
            "category":"Insurance",
            "subcategory":"Insurance Agent",
            "type":"Services"
        }
    ],
    "sg:phone":"+1 615 331 1453",
    "sg:postcode":"37211",
    "sg:province":"TN",
    "wof:name":"Direct General Ins Agency",
    "wof:placetype":"venue"
},
  "geometry": {"coordinates":[-86.71924,36.116735],"type":"Point"}
}