{
  "type": "Feature",
  "properties": {
    "addr:full":"720 Madison St Shelbyville TN 37160",
    "addr:housenumber":"720",
    "addr:postcode":"37160",
    "addr:street":"Madison St",
    "iso:country":"US",
    "sg:address":"720 Madison St",
    "sg:city":"Shelbyville",
    "sg:classifiers":[
        {
            "category":"Autos & Motor Vehicles",
            "subcategory":"Auto Supplies",
            "type":"Retail Goods"
        }
    ],
    "sg:phone":"+1 931 684 1531",
    "sg:postcode":"37160",
    "sg:province":"TN",
    "sg:tags":[
        "equipment",
        "parts",
        "electrical",
        "automobile"
    ],
    "wof:name":"Advance Auto Parts Inc",
    "wof:placetype":"venue"
},
  "geometry": {"coordinates":[-86.44797699999999,35.487559],"type":"Point"}
}