{
  "type": "Feature",
  "properties": {
    "iso:country":"US",
    "sg:address":"595 N Germantown Pkwy",
    "sg:city":"Cordova",
    "sg:classifiers":[
        {
            "category":"Retail",
            "subcategory":"Car Wash",
            "type":"Services"
        }
    ],
    "sg:phone":"+1 901 752 8338",
    "sg:postcode":"38018",
    "sg:province":"TN",
    "sg:tags":[
        "polishing",
        "washing"
    ],
    "wof:name":"Sunshine Carwash",
    "wof:placetype":"venue"
},
  "geometry": {"coordinates":[-89.795557,35.141988],"type":"Point"}
}