{
  "type": "Feature",
  "properties": {
    "addr:full":"4751 Durbin Ave Memphis TN 38122",
    "addr:housenumber":"4751",
    "addr:postcode":"38122",
    "addr:street":"Durbin Ave",
    "iso:country":"US",
    "sg:address":"4751 Durbin Ave",
    "sg:city":"Memphis",
    "sg:classifiers":[
        {
            "category":"Shopping",
            "subcategory":"Bicycles & Sporting Goods",
            "type":"Retail Goods"
        }
    ],
    "sg:phone":"+1 901 761 2323",
    "sg:postcode":"38122",
    "sg:province":"TN",
    "wof:name":"Denkers",
    "wof:placetype":"venue"
},
  "geometry": {"coordinates":[-89.90557200000001,35.155803],"type":"Point"}
}