{
  "type": "Feature",
  "properties": {
    "iso:country":"US",
    "sg:address":"777 Washington Ave",
    "sg:city":"Memphis",
    "sg:classifiers":[
        {
            "category":"Health Services",
            "subcategory":"Doctor",
            "type":"Services"
        }
    ],
    "sg:phone":"+1 901 287 5222",
    "sg:postcode":"38105",
    "sg:province":"TN",
    "sg:tags":[
        "physician",
        "surgeon"
    ],
    "wof:name":"Tutor James Dudley MD",
    "wof:placetype":"venue"
},
  "geometry": {"coordinates":[-90.034843,35.14476],"type":"Point"}
}