{
  "type": "Feature",
  "properties": {
    "iso:country":"US",
    "sg:address":"331 N Main St",
    "sg:city":"Ripley",
    "sg:classifiers":[
        {
            "category":"Retail",
            "subcategory":"Auto Repair",
            "type":"Services"
        }
    ],
    "sg:phone":"+1 731 635 9264",
    "sg:postcode":"38063",
    "sg:province":"TN",
    "sg:tags":[
        "automotive",
        "cattle",
        "beef",
        "general"
    ],
    "wof:name":"Criners Huberg Garage",
    "wof:placetype":"venue"
},
  "geometry": {"coordinates":[-89.522842,35.759515],"type":"Point"}
}