{
  "type": "Feature",
  "properties": {
    "addr:city":"Murfreesboro",
    "addr:full":"415 S Academy St Murfreesboro, Tn 37130-3747",
    "addr:house_number":"415",
    "addr:housenumber":"415",
    "addr:postcode":"37130-3747",
    "addr:road":"S Academy St",
    "addr:state":"TN",
    "addr:street":"S Academy St",
    "iso:country":"US",
    "sg:address":"415 S Academy St",
    "sg:city":"Murfreesboro",
    "sg:classifiers":[
        {
            "category":"Recreation",
            "type":"Entertainment"
        }
    ],
    "sg:phone":"+1 615 867 2633",
    "sg:postcode":"37130",
    "sg:province":"TN",
    "sg:tags":[
        "historical"
    ],
    "wof:airports":[
        102526759
    ],
    "wof:name":"Bradley Academy Historical Association",
    "wof:placetype":"venue"
},
  "geometry": {"coordinates":[-86.38948000000001,35.84173],"type":"Point"}
}