{
  "type": "Feature",
  "properties": {
    "iso:country":"US",
    "sg:address":"8223 Daisy Dallas Rd",
    "sg:city":"Hixson",
    "sg:classifiers":[
        {
            "category":"Building & Trades",
            "subcategory":"Landscaping Services",
            "type":"Services"
        }
    ],
    "sg:phone":"+1 423 847 1613",
    "sg:postcode":"37343",
    "sg:province":"TN",
    "sg:tags":[
        "landscape",
        "contractor"
    ],
    "wof:name":"Grubb Landscaping Nrsy & Supls",
    "wof:placetype":"venue"
},
  "geometry": {"coordinates":[-85.159837,35.201793],"type":"Point"}
}