{
  "type": "Feature",
  "properties": {
    "iso:country":"US",
    "sg:address":"715 Water St",
    "sg:city":"Savannah",
    "sg:classifiers":[
        {
            "category":"Retail",
            "subcategory":"Repair Shop",
            "type":"Services"
        }
    ],
    "sg:phone":"+1 731 925 7222",
    "sg:postcode":"38372",
    "sg:province":"TN",
    "wof:name":"Scotts Tractor Repair",
    "wof:placetype":"venue"
},
  "geometry": {"coordinates":[-88.24985700000001,35.22395],"type":"Point"}
}