{
  "type": "Feature",
  "properties": {
    "addr:full":"2700 Lake Rd Dyersburg TN 38024",
    "addr:housenumber":"2700",
    "addr:postcode":"38024",
    "addr:street":"Lake Rd",
    "iso:country":"US",
    "sg:address":"2700 Lake Rd",
    "sg:city":"Dyersburg",
    "sg:classifiers":[
        {
            "category":"Shopping",
            "subcategory":"Computers & Home Electronics",
            "type":"Retail Goods"
        }
    ],
    "sg:phone":"+1 731 285 0345",
    "sg:postcode":"38024",
    "sg:province":"TN",
    "wof:name":"Radio Shack",
    "wof:placetype":"venue"
},
  "geometry": {"coordinates":[-89.39605299999999,36.066607],"type":"Point"}
}