{
  "type": "Feature",
  "properties": {
    "addr:full":"86 N Star Dr Jackson TN 38305",
    "addr:housenumber":"86",
    "addr:postcode":"38305",
    "addr:street":"N Star Dr",
    "iso:country":"US",
    "sg:address":"86 N Star Dr",
    "sg:city":"Jackson",
    "sg:classifiers":[
        {
            "category":"Building & Trades",
            "subcategory":"Construction",
            "type":"Services"
        }
    ],
    "sg:phone":"+1 731 661 9144",
    "sg:postcode":"38305",
    "sg:province":"TN",
    "sg:tags":[
        "home",
        "improvement"
    ],
    "wof:name":"Uselton Construction Co",
    "wof:placetype":"venue"
},
  "geometry": {"coordinates":[-88.854118,35.706021],"type":"Point"}
}