{
  "type": "Feature",
  "properties": {
    "iso:country":"US",
    "sg:address":"3935 Chambers Chapel Rd",
    "sg:city":"Arlington",
    "sg:classifiers":[
        {
            "category":"Farming",
            "subcategory":"Farm",
            "type":"Manufacturing & Wholesale Goods"
        }
    ],
    "sg:phone":"+1 901 867 3172",
    "sg:postcode":"38002",
    "sg:province":"TN",
    "sg:tags":[
        "feedlot",
        "cattle",
        "crop",
        "beef",
        "general"
    ],
    "wof:name":"Dogwood Oaks",
    "wof:placetype":"venue"
},
  "geometry": {"coordinates":[-89.697276,35.23508],"type":"Point"}
}