{
  "type": "Feature",
  "properties": {
    "iso:country":"US",
    "sg:address":"2402 Hwy 64 E",
    "sg:city":"Shelbyville",
    "sg:classifiers":[
        {
            "category":"Building & Trades",
            "subcategory":"Plumbing",
            "type":"Services"
        }
    ],
    "sg:phone":"+1 931 684 0423",
    "sg:postcode":"37160",
    "sg:province":"TN",
    "sg:tags":[
        "commercial",
        "industrial",
        "refrigeration",
        "also"
    ],
    "wof:name":"Lockes Refrigeration Service",
    "wof:placetype":"venue"
},
  "geometry": {"coordinates":[-86.39447199999999,35.477728],"type":"Point"}
}