{
  "type": "Feature",
  "properties": {
    "addr:full":"3029 Cages Bend Rd Gallatin TN 37066",
    "addr:housenumber":"3029",
    "addr:postcode":"37066",
    "addr:street":"Cages Bend Rd",
    "iso:country":"US",
    "sg:address":"3029 Cages Bend Rd",
    "sg:city":"Gallatin",
    "sg:classifiers":[
        {
            "category":"Professional",
            "subcategory":"Management & Consulting",
            "type":"Services"
        }
    ],
    "sg:phone":"+1 615 264 8458",
    "sg:postcode":"37066",
    "sg:province":"TN",
    "wof:name":"Grace Group",
    "wof:placetype":"venue"
},
  "geometry": {"coordinates":[-86.523383,36.299878],"type":"Point"}
}