{
  "type": "Feature",
  "properties": {
    "iso:country":"US",
    "sg:address":"24 Front St",
    "sg:city":"Big Sandy",
    "sg:classifiers":[
        {
            "category":"Restaurant",
            "type":"Food & Drink"
        }
    ],
    "sg:phone":"+1 731 593 3025",
    "sg:postcode":"38221",
    "sg:province":"TN",
    "wof:name":"Aaron's Restaurant",
    "wof:placetype":"venue"
},
  "geometry": {"coordinates":[-88.086494,36.235091],"type":"Point"}
}