{
  "type": "Feature",
  "properties": {
    "iso:country":"US",
    "sg:address":"1394 Hatcher Ln",
    "sg:city":"Columbia",
    "sg:classifiers":[
        {
            "category":"Health Services",
            "subcategory":"Doctor",
            "type":"Services"
        }
    ],
    "sg:phone":"+1 931 388 9388",
    "sg:postcode":"38401",
    "sg:province":"TN",
    "sg:tags":[
        "physician",
        "surgeon"
    ],
    "wof:name":"Columbia Multi Specialty Med",
    "wof:placetype":"venue"
},
  "geometry": {"coordinates":[-87.060171,35.603736],"type":"Point"}
}