{
  "type": "Feature",
  "properties": {
    "iso:country":"US",
    "sg:address":"144 Halliburton St",
    "sg:city":"Ripley",
    "sg:classifiers":[
        {
            "category":"Building & Trades",
            "subcategory":"Construction",
            "type":"Services"
        }
    ],
    "sg:phone":"+1 731 635 4082",
    "sg:postcode":"38063",
    "sg:province":"TN",
    "sg:tags":[
        "masonry",
        "contractor"
    ],
    "wof:name":"Pilcher Brothers Masonry",
    "wof:placetype":"venue"
},
  "geometry": {"coordinates":[-89.54715,35.728653],"type":"Point"}
}