{
  "type": "Feature",
  "properties": {
    "iso:country":"US",
    "sg:address":"805 W Main St",
    "sg:city":"Hendersonville",
    "sg:classifiers":[
        {
            "category":"Building & Trades",
            "subcategory":"Construction",
            "type":"Services"
        }
    ],
    "sg:phone":"+1 615 264 0897",
    "sg:postcode":"37075",
    "sg:province":"TN",
    "sg:tags":[
        "bathroom",
        "remodeling"
    ],
    "wof:name":"Re Bath Of North Tennessee",
    "wof:placetype":"venue"
},
  "geometry": {"coordinates":[-86.64542299999999,36.303451],"type":"Point"}
}