{
  "type": "Feature",
  "properties": {
    "addr:full":"501 Gould Dr Cookeville TN 38506",
    "addr:housenumber":"501",
    "addr:postcode":"38506",
    "addr:street":"Gould Dr",
    "iso:country":"US",
    "sg:address":"501 Gould Dr",
    "sg:city":"Cookeville",
    "sg:classifiers":[
        {
            "category":"Professional",
            "subcategory":"Management & Consulting",
            "type":"Services"
        },
        {
            "category":"Manufacturing",
            "subcategory":"Tools & Machinery",
            "type":"Manufacturing & Wholesale Goods"
        }
    ],
    "sg:phone":"+1 931 432 6140",
    "sg:postcode":"38506",
    "sg:province":"TN",
    "sg:tags":[
        "industrial",
        "for",
        "mfg",
        "consultant",
        "industry",
        "test"
    ],
    "wof:name":"PLM Corp",
    "wof:placetype":"venue"
},
  "geometry": {"coordinates":[-85.53622300000001,36.132843],"type":"Point"}
}