{
  "type": "Feature",
  "properties": {
    "iso:country":"US",
    "sg:address":"315 N Main St",
    "sg:city":"Memphis",
    "sg:classifiers":[
        {
            "category":"Personal",
            "subcategory":"Nail Salon",
            "type":"Services"
        }
    ],
    "sg:phone":"+1 901 544 9977",
    "sg:postcode":"38103",
    "sg:province":"TN",
    "wof:name":"Designer Nails and Hair by Evelyn",
    "wof:placetype":"venue"
},
  "geometry": {"coordinates":[-90.049532,35.153379],"type":"Point"}
}