{
  "type": "Feature",
  "properties": {
    "iso:country":"US",
    "sg:address":"512 N 1st Ave",
    "sg:city":"Lewisburg",
    "sg:classifiers":[
        {
            "category":"Shopping",
            "subcategory":"Clothing, Apparel, & Fashions",
            "type":"Retail Goods"
        }
    ],
    "sg:phone":"+1 931 359 7588",
    "sg:postcode":"37091",
    "sg:province":"TN",
    "wof:name":"Vintage Clothing Antq Jewelry",
    "wof:placetype":"venue"
},
  "geometry": {"coordinates":[-86.78744,35.45407],"type":"Point"}
}