{
  "type": "Feature",
  "properties": {
    "iso:country":"US",
    "sg:address":"1401 Meeks St",
    "sg:city":"Dyersburg",
    "sg:classifiers":[
        {
            "category":"Real Estate",
            "subcategory":"Real Estate Operator",
            "type":"Services"
        }
    ],
    "sg:phone":"+1 731 286 4874",
    "sg:postcode":"38024",
    "sg:province":"TN",
    "sg:tags":[
        "apartment"
    ],
    "wof:name":"Rose Garden Apartments",
    "wof:placetype":"venue"
},
  "geometry": {"coordinates":[-89.40587499999999,36.030511],"type":"Point"}
}