{
  "type": "Feature",
  "properties": {
    "iso:country":"US",
    "sg:address":"919 NW Broad St",
    "sg:city":"Murfreesboro",
    "sg:classifiers":[
        {
            "category":"Shopping",
            "type":"Retail Goods"
        }
    ],
    "sg:phone":"+1 615 890 0700",
    "sg:postcode":"37129",
    "sg:province":"TN",
    "sg:tags":[
        "merchandise"
    ],
    "wof:name":"Animal City",
    "wof:placetype":"venue"
},
  "geometry": {"coordinates":[-86.39379599999999,35.843491],"type":"Point"}
}