{
  "type": "Feature",
  "properties": {
    "iso:country":"US",
    "sg:address":"910 Creekside Rd",
    "sg:city":"Chattanooga",
    "sg:classifiers":[
        {
            "category":"Building & Trades",
            "subcategory":"Construction",
            "type":"Services"
        }
    ],
    "sg:phone":"+1 423 624 9446",
    "sg:postcode":"37406",
    "sg:province":"TN",
    "sg:tags":[
        "equipment",
        "dumbwaiter",
        "installation",
        "elevator"
    ],
    "wof:name":"Schindler Elevator Corporation",
    "wof:placetype":"venue"
},
  "geometry": {"coordinates":[-85.254818,35.090985],"type":"Point"}
}