{
  "type": "Feature",
  "properties": {
    "iso:country":"US",
    "sg:address":"351 Elysian Fields Rd",
    "sg:city":"Nashville",
    "sg:classifiers":[
        {
            "category":"Building & Trades",
            "subcategory":"Cleaning & Sanitation",
            "type":"Services"
        }
    ],
    "sg:phone":"+1 615 414 7165",
    "sg:postcode":"37211",
    "sg:province":"TN",
    "sg:tags":[
        "butler",
        "maid"
    ],
    "wof:name":"Cinderella",
    "wof:placetype":"venue"
},
  "geometry": {"coordinates":[-86.72940699999999,36.086131],"type":"Point"}
}