{
  "type": "Feature",
  "properties": {
    "iso:country":"US",
    "sg:address":"228 W Valley Dr",
    "sg:city":"Kingsport",
    "sg:classifiers":[
        {
            "category":"Building & Trades",
            "subcategory":"Construction",
            "type":"Services"
        }
    ],
    "sg:phone":"+1 423 349 5150",
    "sg:postcode":"37664",
    "sg:province":"TN",
    "sg:tags":[
        "excavation",
        "contractor"
    ],
    "wof:name":"Larry Byington Construction",
    "wof:placetype":"venue"
},
  "geometry": {"coordinates":[-82.58142700000001,36.439319],"type":"Point"}
}