{
  "type": "Feature",
  "properties": {
    "iso:country":"US",
    "sg:address":"1707 Lockett Pl",
    "sg:city":"Memphis",
    "sg:classifiers":[
        {
            "category":"Insurance",
            "subcategory":"Insurance Agent",
            "type":"Services"
        }
    ],
    "sg:phone":"+1 901 462 0051",
    "sg:postcode":"38104",
    "sg:province":"TN",
    "wof:name":"Massachusetts Mutual Life Ins",
    "wof:placetype":"venue"
},
  "geometry": {"coordinates":[-90.00452799999999,35.13767],"type":"Point"}
}