{
  "type": "Feature",
  "properties": {
    "iso:country":"US",
    "sg:address":"7538 Majors Rd",
    "sg:city":"Corryton",
    "sg:classifiers":[
        {
            "category":"Retail",
            "subcategory":"Laundry & Dry Cleaning",
            "type":"Services"
        }
    ],
    "sg:phone":"+1 865 922 7997",
    "sg:postcode":"37721",
    "sg:province":"TN",
    "sg:tags":[
        "repairing",
        "rug",
        "carpet"
    ],
    "wof:name":"Carpet-Craft",
    "wof:placetype":"venue"
},
  "geometry": {"coordinates":[-83.874895,36.125368],"type":"Point"}
}