{
  "type": "Feature",
  "properties": {
    "iso:country":"US",
    "sg:address":"130 W Trinity Ln",
    "sg:city":"Nashville",
    "sg:classifiers":[
        {
            "category":"Restaurant",
            "type":"Food & Drink"
        }
    ],
    "sg:menulink":"http://www.allmenus.com/tn/nashville/139957-subway/menu/",
    "sg:phone":"+1 615 226 3753",
    "sg:postcode":"37207",
    "sg:province":"TN",
    "sg:tags":[
        "american",
        "sandwich"
    ],
    "wof:name":"Subway",
    "wof:placetype":"venue"
},
  "geometry": {"coordinates":[-86.771919,36.205365],"type":"Point"}
}