{
  "type": "Feature",
  "properties": {
    "iso:country":"US",
    "sg:address":"101 Ladbrook Ln",
    "sg:city":"Knoxville",
    "sg:classifiers":[
        {
            "category":"Wholesale",
            "subcategory":"Office Equipment",
            "type":"Manufacturing & Wholesale Goods"
        }
    ],
    "sg:phone":"+1 865 673 3081",
    "sg:postcode":"37922",
    "sg:province":"TN",
    "sg:tags":[
        "register",
        "cash",
        "supply"
    ],
    "wof:name":"Business Information Solutions",
    "wof:placetype":"venue"
},
  "geometry": {"coordinates":[-84.13294399999999,35.899256],"type":"Point"}
}