{
  "type": "Feature",
  "properties": {
    "iso:country":"US",
    "sg:address":"520 E Mary St",
    "sg:city":"Bristol",
    "sg:classifiers":[
        {
            "category":"Manufacturing",
            "subcategory":"Chemicals & Compounds",
            "type":"Manufacturing & Wholesale Goods"
        }
    ],
    "sg:phone":"+1 276 669 5521",
    "sg:postcode":"24201",
    "sg:province":"TN",
    "sg:tags":[
        "specialty"
    ],
    "wof:name":"Acco Cowan",
    "wof:placetype":"venue"
},
  "geometry": {"coordinates":[-82.16925999999999,36.596914],"type":"Point"}
}