{
  "type": "Feature",
  "properties": {
    "iso:country":"US",
    "sg:address":"2459 Smithville Hwy",
    "sg:city":"Mc Minnville",
    "sg:classifiers":[
        {
            "category":"Real Estate",
            "subcategory":"Real Estate Agent",
            "type":"Services"
        }
    ],
    "sg:phone":"+1 931 668 6181",
    "sg:postcode":"37110",
    "sg:province":"TN",
    "wof:name":"Discovery Realty",
    "wof:placetype":"venue"
},
  "geometry": {"coordinates":[-85.783646,35.714824],"type":"Point"}
}