{
  "type": "Feature",
  "properties": {
    "iso:country":"US",
    "sg:address":"9251 Chevoit Dr",
    "sg:city":"Brentwood",
    "sg:classifiers":[
        {
            "category":"Shopping",
            "subcategory":"Clothing, Apparel, & Fashions",
            "type":"Retail Goods"
        }
    ],
    "sg:phone":"+1 615 377 3008",
    "sg:postcode":"37027",
    "sg:province":"TN",
    "sg:tags":[
        "tailor"
    ],
    "wof:name":"Victor's Hong Kong Tailoring",
    "wof:placetype":"venue"
},
  "geometry": {"coordinates":[-86.76235699999999,36.009089],"type":"Point"}
}