{
  "type": "Feature",
  "properties": {
    "addr:full":"7714 E Andrew Johnson Hwy Whitesburg TN 37891",
    "addr:housenumber":"7714",
    "addr:postcode":"37891",
    "addr:street":"E Andrew Johnson Hwy",
    "iso:country":"US",
    "sg:address":"7714 E Andrew Johnson Hwy",
    "sg:city":"Whitesburg",
    "sg:classifiers":[
        {
            "category":"Food & Beverages",
            "subcategory":"Groceries & Convenience Stores",
            "type":"Retail Goods"
        }
    ],
    "sg:phone":"+1 423 235 6469",
    "sg:postcode":"37891",
    "sg:province":"TN",
    "wof:name":"Unicorn Mart & Grill",
    "wof:placetype":"venue"
},
  "geometry": {"coordinates":[-83.166685,36.26376],"type":"Point"}
}