{
  "type": "Feature",
  "properties": {
    "addr:full":"8059 Neshoba Rd Germantown TN 38138",
    "addr:housenumber":"8059",
    "addr:postcode":"38138",
    "addr:street":"Neshoba Rd",
    "iso:country":"US",
    "sg:address":"8059 Neshoba Rd",
    "sg:city":"Germantown",
    "sg:classifiers":[
        {
            "category":"Real Estate",
            "subcategory":"Real Estate Agent",
            "type":"Services"
        }
    ],
    "sg:phone":"+1 901 767 4670",
    "sg:postcode":"38138",
    "sg:province":"TN",
    "sg:tags":[
        "investment"
    ],
    "wof:name":"Wamble & Co",
    "wof:placetype":"venue"
},
  "geometry": {"coordinates":[-89.79547599999999,35.101052],"type":"Point"}
}