{
  "type": "Feature",
  "properties": {
    "iso:country":"US",
    "sg:address":"205 W Walnut St",
    "sg:city":"Johnson City",
    "sg:classifiers":[
        {
            "category":"Professional",
            "subcategory":"Lawyer & Legal Services",
            "type":"Services"
        }
    ],
    "sg:phone":"+1 423 926 0827",
    "sg:postcode":"37604",
    "sg:province":"TN",
    "wof:name":"Clifton Corker",
    "wof:placetype":"venue"
},
  "geometry": {"coordinates":[-82.351512,36.313431],"type":"Point"}
}