{
  "type": "Feature",
  "properties": {
    "iso:country":"US",
    "sg:address":"1507 Memorial Blvd",
    "sg:city":"Murfreesboro",
    "sg:classifiers":[
        {
            "category":"Professional",
            "type":"Services"
        }
    ],
    "sg:phone":"+1 615 904 7336",
    "sg:postcode":"37129",
    "sg:province":"TN",
    "wof:name":"Marcy Hardwick",
    "wof:placetype":"venue"
},
  "geometry": {"coordinates":[-86.396692,35.853097],"type":"Point"}
}