{
  "type": "Feature",
  "properties": {
    "iso:country":"US",
    "sg:address":"1115 N Eastman Rd",
    "sg:city":"Kingsport",
    "sg:classifiers":[
        {
            "category":"Health Services",
            "subcategory":"Optometrist",
            "type":"Services"
        }
    ],
    "sg:phone":"+1 423 246 2733",
    "sg:postcode":"37664",
    "sg:province":"TN",
    "wof:name":"Barry B Watson Od",
    "wof:placetype":"venue"
},
  "geometry": {"coordinates":[-82.53141599999999,36.530442],"type":"Point"}
}