{
  "type": "Feature",
  "properties": {
    "addr:full":"400 W Main St Sevierville TN 37862",
    "addr:housenumber":"400",
    "addr:postcode":"37862",
    "addr:street":"W Main St",
    "iso:country":"US",
    "sg:address":"400 W Main St",
    "sg:city":"Sevierville",
    "sg:classifiers":[
        {
            "category":"Retail",
            "subcategory":"Repair Shop",
            "type":"Services"
        }
    ],
    "sg:phone":"+1 865 765 0433",
    "sg:postcode":"37862",
    "sg:province":"TN",
    "sg:tags":[
        "equipment",
        "hydraulic"
    ],
    "wof:name":"Mountain View Hydraulics",
    "wof:placetype":"venue"
},
  "geometry": {"coordinates":[-83.571499,35.870392],"type":"Point"}
}