{
  "type": "Feature",
  "properties": {
    "iso:country":"US",
    "sg:address":"414 Sunset St",
    "sg:city":"Somerville",
    "sg:classifiers":[
        {
            "category":"Building & Trades",
            "subcategory":"Construction",
            "type":"Services"
        }
    ],
    "sg:phone":"+1 901 465 5431",
    "sg:postcode":"38068",
    "sg:province":"TN",
    "sg:tags":[
        "general",
        "contractor"
    ],
    "wof:name":"Somerset Construction Corp",
    "wof:placetype":"venue"
},
  "geometry": {"coordinates":[-89.355582,35.239817],"type":"Point"}
}