{
  "type": "Feature",
  "properties": {
    "addr:full":"5580 Blue Springs Pkwy Greeneville TN 37818",
    "addr:housenumber":"5580",
    "addr:postcode":"37818",
    "addr:street":"Blue Springs Pkwy",
    "iso:country":"US",
    "sg:address":"5580 Blue Springs Pkwy",
    "sg:city":"Greeneville",
    "sg:classifiers":[
        {
            "category":"Restaurant",
            "type":"Food & Drink"
        }
    ],
    "sg:phone":"+1 423 422 6101",
    "sg:postcode":"37818",
    "sg:province":"TN",
    "sg:tags":[
        "eating"
    ],
    "wof:name":"11 E Bar & Grill",
    "wof:placetype":"venue"
},
  "geometry": {"coordinates":[-82.92280100000001,36.19017],"type":"Point"}
}