{
  "type": "Feature",
  "properties": {
    "iso:country":"US",
    "sg:address":"770 N Spring St",
    "sg:city":"Mc Minnville",
    "sg:classifiers":[
        {
            "category":"Home & Garden",
            "subcategory":"Building Materials",
            "type":"Retail Goods"
        }
    ],
    "sg:phone":"+1 931 473 9663",
    "sg:postcode":"37110",
    "sg:province":"TN",
    "sg:website":"www.supremebuilding.com",
    "wof:name":"Supreme Building Products",
    "wof:placetype":"venue"
},
  "geometry": {"coordinates":[-85.766361,35.698643],"type":"Point"}
}