{
  "type": "Feature",
  "properties": {
    "addr:full":"2062 Dunlap Orphanage Rd Brighton TN 38011",
    "addr:housenumber":"2062",
    "addr:postcode":"38011",
    "addr:street":"Dunlap Orphanage Rd",
    "iso:country":"US",
    "sg:address":"2062 Dunlap Orphanage Rd",
    "sg:city":"Brighton",
    "sg:classifiers":[
        {
            "category":"Wholesale",
            "subcategory":"Machinery & Supplies",
            "type":"Manufacturing & Wholesale Goods"
        }
    ],
    "sg:phone":"+1 901 634 5006",
    "sg:postcode":"38011",
    "sg:province":"TN",
    "sg:tags":[
        "equipment",
        "industrial"
    ],
    "wof:name":"Joon Handling LLC",
    "wof:placetype":"venue"
},
  "geometry": {"coordinates":[-89.68873499999999,35.404675],"type":"Point"}
}