{
  "type": "Feature",
  "properties": {
    "iso:country":"US",
    "sg:address":"6960 Eastgate Blvd",
    "sg:city":"Lebanon",
    "sg:classifiers":[
        {
            "category":"Banks & Credit Unions",
            "subcategory":"Financial Services",
            "type":"Services"
        }
    ],
    "sg:phone":"+1 615 754 0553",
    "sg:postcode":"37090",
    "sg:province":"TN",
    "sg:tags":[
        "investor"
    ],
    "wof:name":"Froehlig Howes Investments",
    "wof:placetype":"venue"
},
  "geometry": {"coordinates":[-86.416535,36.186652],"type":"Point"}
}