{
  "type": "Feature",
  "properties": {
    "iso:country":"US",
    "sg:address":"105 State Hwy 32",
    "sg:city":"Cosby",
    "sg:classifiers":[
        {
            "category":"Government",
            "subcategory":"Fire Station",
            "type":"Public Place"
        }
    ],
    "sg:phone":"+1 423 487 4439",
    "sg:postcode":"37722",
    "sg:province":"TN",
    "sg:tags":[
        "department"
    ],
    "wof:name":"Cosby Volunteer Fire Dept",
    "wof:placetype":"venue"
},
  "geometry": {"coordinates":[-83.235698,35.793622],"type":"Point"}
}