{
  "type": "Feature",
  "properties": {
    "addr:full":"2130 W Poplar Ave Collierville TN 38017",
    "addr:housenumber":"2130",
    "addr:postcode":"38017",
    "addr:street":"W Poplar Ave",
    "iso:country":"US",
    "sg:address":"2130 W Poplar Ave",
    "sg:city":"Collierville",
    "sg:classifiers":[
        {
            "category":"Restaurant",
            "type":"Food & Drink"
        }
    ],
    "sg:menulink":"http://www.allmenus.com/tn/memphis/256675-super-suppers/menu/",
    "sg:phone":"+1 901 853 9173",
    "sg:postcode":"38017",
    "sg:province":"TN",
    "sg:tags":[
        "new",
        "american"
    ],
    "wof:name":"Super Suppers",
    "wof:placetype":"venue"
},
  "geometry": {"coordinates":[-89.732463,35.051628],"type":"Point"}
}