{
  "type": "Feature",
  "properties": {
    "iso:country":"US",
    "sg:address":"142 W Knight St",
    "sg:city":"Portland",
    "sg:classifiers":[
        {
            "category":"Banks & Credit Unions",
            "subcategory":"Bank",
            "type":"Services"
        }
    ],
    "sg:phone":"+1 615 323 1690",
    "sg:postcode":"37148",
    "sg:province":"TN",
    "sg:tags":[
        "loan"
    ],
    "wof:name":"World Finance Corp",
    "wof:placetype":"venue"
},
  "geometry": {"coordinates":[-86.51580199999999,36.575565],"type":"Point"}
}