{
  "type": "Feature",
  "properties": {
    "iso:country":"US",
    "sg:address":"238 Mc Williams St",
    "sg:city":"Waynesboro",
    "sg:classifiers":[
        {
            "category":"Real Estate",
            "subcategory":"Real Estate Agent",
            "type":"Services"
        }
    ],
    "sg:phone":"+1 931 722 5793",
    "sg:postcode":"38485",
    "sg:province":"TN",
    "sg:website":"www.webbrealty.net",
    "wof:name":"WEBB Realty",
    "wof:placetype":"venue"
},
  "geometry": {"coordinates":[-87.766738,35.314698],"type":"Point"}
}