{
  "type": "Feature",
  "properties": {
    "addr:full":"5766 Brainerd Rd Chattanooga TN 37411",
    "addr:housenumber":"5766",
    "addr:postcode":"37411",
    "addr:street":"Brainerd Rd",
    "iso:country":"US",
    "sg:address":"5766 Brainerd Rd",
    "sg:city":"Chattanooga",
    "sg:classifiers":[
        {
            "category":"Education",
            "subcategory":"Dance Studio",
            "type":"Public Place"
        }
    ],
    "sg:phone":"+1 423 892 5861",
    "sg:postcode":"37411",
    "sg:province":"TN",
    "sg:tags":[
        "instruction"
    ],
    "wof:name":"Fred Astaire Dance Studio",
    "wof:placetype":"venue"
},
  "geometry": {"coordinates":[-85.21126,35.013621],"type":"Point"}
}