{
  "type": "Feature",
  "properties": {
    "addr:full":"415 W Central Ave La Follette TN 37766",
    "addr:housenumber":"415",
    "addr:postcode":"37766",
    "addr:street":"W Central Ave La Follette",
    "iso:country":"US",
    "sg:address":"415 W Central Ave",
    "sg:city":"La Follette",
    "sg:classifiers":[
        {
            "category":"Building & Trades",
            "subcategory":"Equipment Rental",
            "type":"Services"
        }
    ],
    "sg:phone":"+1 423 562 8111",
    "sg:postcode":"37766",
    "sg:province":"TN",
    "sg:tags":[
        "home",
        "respiratory",
        "rent"
    ],
    "wof:name":"American Oxygen Home Care",
    "wof:placetype":"venue"
},
  "geometry": {"coordinates":[-84.12667500000001,36.377414],"type":"Point"}
}