{
  "type": "Feature",
  "properties": {
    "iso:country":"US",
    "sg:address":"3439 Northbend Cir",
    "sg:city":"Alcoa",
    "sg:classifiers":[
        {
            "category":"Retail",
            "subcategory":"Car Wash",
            "type":"Services"
        }
    ],
    "sg:phone":"+1 865 977 1998",
    "sg:postcode":"37701",
    "sg:province":"TN",
    "sg:tags":[
        "automobile",
        "detail",
        "clean"
    ],
    "wof:name":"Beetle Auto Svc",
    "wof:placetype":"venue"
},
  "geometry": {"coordinates":[-83.967894,35.8299],"type":"Point"}
}