{
  "type": "Feature",
  "properties": {
    "addr:full":"300 James Robertson Pkwy Nashville TN 37201",
    "addr:housenumber":"300",
    "addr:postcode":"37201",
    "addr:street":"James Robertson Pkwy",
    "iso:country":"US",
    "sg:address":"300 James Robertson Pkwy",
    "sg:city":"Nashville",
    "sg:classifiers":[
        {
            "category":"Professional",
            "subcategory":"Lawyer & Legal Services",
            "type":"Services"
        }
    ],
    "sg:phone":"+1 615 256 1000",
    "sg:postcode":"37201",
    "sg:province":"TN",
    "wof:name":"High Law Office",
    "wof:placetype":"venue"
},
  "geometry": {"coordinates":[-86.781019,36.167267],"type":"Point"}
}