{
  "type": "Feature",
  "properties": {
    "iso:country":"US",
    "sg:address":"303 E Court St",
    "sg:city":"Dyersburg",
    "sg:classifiers":[
        {
            "category":"Shopping",
            "subcategory":"Discount & Variety Stores",
            "type":"Retail Goods"
        },
        {
            "category":"Shopping",
            "subcategory":"Department Store",
            "type":"Retail Goods"
        }
    ],
    "sg:phone":"+1 731 286 1207",
    "sg:postcode":"38024",
    "sg:province":"TN",
    "wof:name":"Family Dollar Stores",
    "wof:placetype":"venue"
},
  "geometry": {"coordinates":[-89.383709,36.032427],"type":"Point"}
}