{
  "type": "Feature",
  "properties": {
    "iso:country":"US",
    "sg:address":"2711 Sutherland Ave",
    "sg:city":"Knoxville",
    "sg:classifiers":[
        {
            "category":"Food & Beverages",
            "subcategory":"Groceries & Convenience Stores",
            "type":"Retail Goods"
        }
    ],
    "sg:phone":"+1 865 521 8931",
    "sg:postcode":"37919",
    "sg:province":"TN",
    "sg:tags":[
        "station",
        "gasoline"
    ],
    "wof:name":"Sutherland Avenue Market",
    "wof:placetype":"venue"
},
  "geometry": {"coordinates":[-83.960751,35.954162],"type":"Point"}
}