{
  "type": "Feature",
  "properties": {
    "iso:country":"US",
    "sg:address":"822 S Highland St",
    "sg:city":"Memphis",
    "sg:classifiers":[
        {
            "category":"Shopping",
            "subcategory":"Music",
            "type":"Retail Goods"
        }
    ],
    "sg:phone":"+1 901 324 1757",
    "sg:postcode":"38111",
    "sg:province":"TN",
    "wof:name":"River Records",
    "wof:placetype":"venue"
},
  "geometry": {"coordinates":[-89.945916,35.109109],"type":"Point"}
}