{
  "type": "Feature",
  "properties": {
    "iso:country":"US",
    "sg:address":"110 E Commercial Ave",
    "sg:city":"Monterey",
    "sg:classifiers":[
        {
            "category":"Insurance",
            "subcategory":"Insurance Agent",
            "type":"Services"
        }
    ],
    "sg:phone":"+1 931 839 2121",
    "sg:postcode":"38574",
    "sg:province":"TN",
    "wof:name":"Monterey Insurance",
    "wof:placetype":"venue"
},
  "geometry": {"coordinates":[-85.267906,36.147785],"type":"Point"}
}