{
  "type": "Feature",
  "properties": {
    "iso:country":"US",
    "sg:address":"507 E Main St",
    "sg:city":"Adamsville",
    "sg:classifiers":[
        {
            "category":"Restaurant",
            "type":"Food & Drink"
        }
    ],
    "sg:phone":"+1 731 632 3036",
    "sg:postcode":"38310",
    "sg:province":"TN",
    "wof:name":"Price's Bar-B-Que",
    "wof:placetype":"venue"
},
  "geometry": {"coordinates":[-88.380116,35.234353],"type":"Point"}
}