{
  "type": "Feature",
  "properties": {
    "iso:country":"US",
    "sg:address":"1103 Springer Rd",
    "sg:city":"Lawrenceburg",
    "sg:classifiers":[
        {
            "category":"Organizations",
            "subcategory":"Religious Organization",
            "type":"Services"
        }
    ],
    "sg:phone":"+1 931 766 0297",
    "sg:postcode":"38464",
    "sg:province":"TN",
    "sg:tags":[
        "church"
    ],
    "wof:name":"First United Pentecostal Chr",
    "wof:placetype":"venue"
},
  "geometry": {"coordinates":[-87.317094,35.249693],"type":"Point"}
}