{
  "type": "Feature",
  "properties": {
    "iso:country":"US",
    "sg:address":"418 Harding Dr",
    "sg:city":"Lebanon",
    "sg:classifiers":[
        {
            "category":"Education",
            "subcategory":"School",
            "type":"Public Place"
        }
    ],
    "sg:phone":"+1 615 444 1104",
    "sg:postcode":"37087",
    "sg:province":"TN",
    "sg:tags":[
        "secondary"
    ],
    "sg:website":"www.wcschools.com",
    "wof:name":"Wilson County Vocational Ctr",
    "wof:placetype":"venue"
},
  "geometry": {"coordinates":[-86.28142099999999,36.202935],"type":"Point"}
}