{
  "type": "Feature",
  "properties": {
    "addr:full":"4138 Dark Hollow Rd Mc Minnville TN 37110",
    "addr:housenumber":"4138",
    "addr:postcode":"37110",
    "addr:street":"Dark Hollow Rd",
    "iso:country":"US",
    "sg:address":"4138 Dark Hollow Rd",
    "sg:city":"Mc Minnville",
    "sg:classifiers":[
        {
            "category":"Organizations",
            "subcategory":"Professional Association",
            "type":"Services"
        }
    ],
    "sg:phone":"+1 931 668 3925",
    "sg:postcode":"37110",
    "sg:province":"TN",
    "wof:name":"National Caves Association",
    "wof:placetype":"venue"
},
  "geometry": {"coordinates":[-85.649196,35.683312],"type":"Point"}
}