{
  "type": "Feature",
  "properties": {
    "addr:full":"4780 Riverdale Rd Memphis TN 38141",
    "addr:housenumber":"4780",
    "addr:postcode":"38141",
    "addr:street":"Riverdale Rd",
    "iso:country":"US",
    "sg:address":"4780 Riverdale Rd",
    "sg:city":"Memphis",
    "sg:classifiers":[
        {
            "category":"Shopping",
            "subcategory":"Clothing, Apparel, & Fashions",
            "type":"Retail Goods"
        }
    ],
    "sg:phone":"+1 901 759 2246",
    "sg:postcode":"38141",
    "sg:province":"TN",
    "sg:website":"www.rainbowshops.com",
    "wof:name":"Rainbow",
    "wof:placetype":"venue"
},
  "geometry": {"coordinates":[-89.831068,35.017962],"type":"Point"}
}