{
  "type": "Feature",
  "properties": {
    "iso:country":"US",
    "sg:address":"426 N Main St",
    "sg:city":"Jamestown",
    "sg:classifiers":[
        {
            "category":"Autos & Motor Vehicles",
            "subcategory":"Automobile Sales",
            "type":"Retail Goods"
        }
    ],
    "sg:phone":"+1 931 879 1165",
    "sg:postcode":"38556",
    "sg:province":"TN",
    "sg:tags":[
        "car",
        "dealer"
    ],
    "wof:name":"Sells Auto Sales",
    "wof:placetype":"venue"
},
  "geometry": {"coordinates":[-84.93517300000001,36.434172],"type":"Point"}
}