{
  "type": "Feature",
  "properties": {
    "iso:country":"US",
    "sg:address":"4254 Maple Valley Rd",
    "sg:city":"Morristown",
    "sg:classifiers":[
        {
            "category":"Organizations",
            "subcategory":"Religious Organization",
            "type":"Services"
        }
    ],
    "sg:phone":"+1 423 586 4568",
    "sg:postcode":"37813",
    "sg:province":"TN",
    "sg:tags":[
        "church"
    ],
    "wof:name":"Way Of The Cross Of Mbc",
    "wof:placetype":"venue"
},
  "geometry": {"coordinates":[-83.353624,36.172176],"type":"Point"}
}