{
  "type": "Feature",
  "properties": {
    "addr:full":"1003 Glendale Ln Nashville TN 37204",
    "addr:housenumber":"1003",
    "addr:postcode":"37204",
    "addr:street":"Glendale Ln",
    "iso:country":"US",
    "sg:address":"1003 Glendale Ln",
    "sg:city":"Nashville",
    "sg:classifiers":[
        {
            "category":"Utilities",
            "subcategory":"Mobile Phone",
            "type":"Services"
        }
    ],
    "sg:phone":"+1 615 292 8020",
    "sg:postcode":"37204",
    "sg:province":"TN",
    "sg:tags":[
        "telephone",
        "cellular"
    ],
    "wof:name":"Gsquared Wireless",
    "wof:placetype":"venue"
},
  "geometry": {"coordinates":[-86.79183999999999,36.093],"type":"Point"}
}