{
  "type": "Feature",
  "properties": {
    "iso:country":"US",
    "sg:address":"1483 Mississippi Blvd",
    "sg:city":"Memphis",
    "sg:classifiers":[
        {
            "category":"Wholesale",
            "subcategory":"Electrical",
            "type":"Manufacturing & Wholesale Goods"
        }
    ],
    "sg:phone":"+1 901 774 8850",
    "sg:postcode":"38106",
    "sg:province":"TN",
    "sg:tags":[
        "control",
        "security",
        "system"
    ],
    "wof:name":"Security Consulants",
    "wof:placetype":"venue"
},
  "geometry": {"coordinates":[-90.031115,35.106391],"type":"Point"}
}