{
  "type": "Feature",
  "properties": {
    "iso:country":"US",
    "sg:address":"2600 Spottswood Ave",
    "sg:city":"Memphis",
    "sg:classifiers":[
        {
            "category":"Professional",
            "type":"Services"
        }
    ],
    "sg:phone":"+1 901 324 4993",
    "sg:postcode":"38114",
    "sg:province":"TN",
    "wof:name":"Caliber Intermodal",
    "wof:placetype":"venue"
},
  "geometry": {"coordinates":[-89.97553499999999,35.114273],"type":"Point"}
}