{
  "type": "Feature",
  "properties": {
    "iso:country":"US",
    "sg:address":"963 Oak Ridge Tpke",
    "sg:city":"Oak Ridge",
    "sg:classifiers":[
        {
            "category":"Retail",
            "subcategory":"Repair Shop",
            "type":"Services"
        }
    ],
    "sg:phone":"+1 865 482 5773",
    "sg:postcode":"37830",
    "sg:province":"TN",
    "wof:name":"Oak Ridge Locksmith",
    "wof:placetype":"venue"
},
  "geometry": {"coordinates":[-84.242775,36.02426],"type":"Point"}
}