{
  "type": "Feature",
  "properties": {
    "iso:country":"US",
    "sg:address":"140 Scenic Cir",
    "sg:city":"Tellico Plains",
    "sg:classifiers":[
        {
            "category":"Food & Beverages",
            "subcategory":"Groceries & Convenience Stores",
            "type":"Retail Goods"
        }
    ],
    "sg:phone":"+1 423 253 7774",
    "sg:postcode":"37385",
    "sg:province":"TN",
    "wof:name":"Indian Boundary Outpost",
    "wof:placetype":"venue"
},
  "geometry": {"coordinates":[-84.307637,35.392077],"type":"Point"}
}