{
  "type": "Feature",
  "properties": {
    "addr:full":"3956 Jackson Ave Memphis TN 38128",
    "addr:housenumber":"3956",
    "addr:postcode":"38128",
    "addr:street":"Jackson Ave",
    "iso:country":"US",
    "sg:address":"3956 Jackson Ave",
    "sg:city":"Memphis",
    "sg:classifiers":[
        {
            "category":"Shopping",
            "subcategory":"Clothing, Apparel, & Fashions",
            "type":"Retail Goods"
        }
    ],
    "sg:phone":"+1 901 581 6352",
    "sg:postcode":"38128",
    "sg:province":"TN",
    "sg:tags":[
        "salvage",
        "surplus",
        "merchandise"
    ],
    "wof:name":"Insurance Salvage",
    "wof:placetype":"venue"
},
  "geometry": {"coordinates":[-89.93206000000001,35.18402],"type":"Point"}
}