{
  "type": "Feature",
  "properties": {
    "iso:country":"US",
    "sg:address":"2501 Overbrook Cir NW",
    "sg:city":"Cleveland",
    "sg:classifiers":[
        {
            "category":"Health Services",
            "subcategory":"Nursing And Care Facility",
            "type":"Services"
        }
    ],
    "sg:phone":"+1 423 472 4877",
    "sg:postcode":"37312",
    "sg:province":"TN",
    "sg:tags":[
        "home",
        "retirement",
        "community"
    ],
    "wof:name":"Vision Seniorcare Partners",
    "wof:placetype":"venue"
},
  "geometry": {"coordinates":[-84.90579099999999,35.205218],"type":"Point"}
}