{
  "type": "Feature",
  "properties": {
    "addr:full":"840 Thomas St Memphis TN 38107",
    "addr:housenumber":"840",
    "addr:postcode":"38107",
    "addr:street":"Thomas St",
    "iso:country":"US",
    "sg:address":"840 Thomas St",
    "sg:city":"Memphis",
    "sg:classifiers":[
        {
            "category":"Food & Beverages",
            "subcategory":"Groceries & Convenience Stores",
            "type":"Retail Goods"
        }
    ],
    "sg:phone":"+1 901 576 8200",
    "sg:postcode":"38107",
    "sg:province":"TN",
    "wof:name":"Super Station",
    "wof:placetype":"venue"
},
  "geometry": {"coordinates":[-90.036289,35.166434],"type":"Point"}
}