{
  "type": "Feature",
  "properties": {
    "iso:country":"US",
    "sg:address":"24 Corporate Blvd",
    "sg:city":"Jackson",
    "sg:classifiers":[
        {
            "category":"Organizations",
            "subcategory":"Religious Organization",
            "type":"Services"
        }
    ],
    "sg:phone":"+1 731 664 5540",
    "sg:postcode":"38305",
    "sg:province":"TN",
    "wof:name":"United Mthdst Trsrers Cnfrence",
    "wof:placetype":"venue"
},
  "geometry": {"coordinates":[-88.825846,35.668417],"type":"Point"}
}