{
  "type": "Feature",
  "properties": {
    "addr:full":"301 N Jackson St Tullahoma TN 37388",
    "addr:housenumber":"301",
    "addr:postcode":"37388",
    "addr:street":"N Jackson St",
    "iso:country":"US",
    "sg:address":"301 N Jackson St",
    "sg:city":"Tullahoma",
    "sg:classifiers":[
        {
            "category":"Health Services",
            "subcategory":"Doctor",
            "type":"Services"
        }
    ],
    "sg:phone":"+1 931 455 4020",
    "sg:postcode":"37388",
    "sg:province":"TN",
    "sg:tags":[
        "physician",
        "surgeon"
    ],
    "wof:name":"Surgery Centers Management",
    "wof:placetype":"venue"
},
  "geometry": {"coordinates":[-86.21413099999999,35.364739],"type":"Point"}
}