{
  "type": "Feature",
  "properties": {
    "iso:country":"US",
    "sg:address":"5159 Overview Ridge",
    "sg:city":"Memphis",
    "sg:classifiers":[
        {
            "category":"Professional",
            "type":"Services"
        }
    ],
    "sg:phone":"+1 901 547 1943",
    "sg:postcode":"38141",
    "sg:province":"TN",
    "wof:name":"Kelmin Inc",
    "wof:placetype":"venue"
},
  "geometry": {"coordinates":[-89.83398200000001,35.007443],"type":"Point"}
}