{
  "type": "Feature",
  "properties": {
    "iso:country":"US",
    "sg:address":"3079 Mosley Ferry Rd",
    "sg:city":"Ashland City",
    "sg:classifiers":[
        {
            "category":"Food & Beverages",
            "subcategory":"Groceries & Convenience Stores",
            "type":"Retail Goods"
        }
    ],
    "sg:phone":"+1 615 307 3784",
    "sg:postcode":"37015",
    "sg:province":"TN",
    "wof:name":"Opal Turtle Market",
    "wof:placetype":"venue"
},
  "geometry": {"coordinates":[-87.226313,36.368859],"type":"Point"}
}