{
  "type": "Feature",
  "properties": {
    "addr:full":"104 Glenrose Ave Nashville TN 37210",
    "addr:housenumber":"104",
    "addr:postcode":"37210",
    "addr:street":"Glenrose Ave",
    "iso:country":"US",
    "sg:address":"104 Glenrose Ave",
    "sg:city":"Nashville",
    "sg:classifiers":[
        {
            "category":"Utilities",
            "subcategory":"Cable",
            "type":"Services"
        }
    ],
    "sg:phone":"+1 615 254 9394",
    "sg:postcode":"37210",
    "sg:province":"TN",
    "sg:tags":[
        "television"
    ],
    "wof:name":"Pro Systems",
    "wof:placetype":"venue"
},
  "geometry": {"coordinates":[-86.74220800000001,36.125403],"type":"Point"}
}