{
  "type": "Feature",
  "properties": {
    "iso:country":"US",
    "sg:address":"3800 New Getwell Rd",
    "sg:city":"Memphis",
    "sg:classifiers":[
        {
            "category":"Real Estate",
            "subcategory":"Real Estate Agent",
            "type":"Services"
        }
    ],
    "sg:phone":"+1 901 366 4354",
    "sg:postcode":"38118",
    "sg:province":"TN",
    "sg:tags":[
        "finding",
        "apartment",
        "rental"
    ],
    "sg:website":"www.dixierents.com",
    "wof:name":"Dixie Rents",
    "wof:placetype":"venue"
},
  "geometry": {"coordinates":[-89.93321400000001,35.047015],"type":"Point"}
}