{
  "type": "Feature",
  "properties": {
    "iso:country":"US",
    "sg:address":"111 Ledford Mill Rd",
    "sg:city":"Tullahoma",
    "sg:classifiers":[
        {
            "category":"Manufacturing",
            "subcategory":"Tools & Machinery",
            "type":"Manufacturing & Wholesale Goods"
        }
    ],
    "sg:phone":"+1 931 454 9625",
    "sg:postcode":"37388",
    "sg:province":"TN",
    "sg:tags":[
        "machine",
        "shop"
    ],
    "wof:name":"Guthrie Machine Shop",
    "wof:placetype":"venue"
},
  "geometry": {"coordinates":[-86.242269,35.393498],"type":"Point"}
}