{
  "type": "Feature",
  "properties": {
    "iso:country":"US",
    "sg:address":"516 Inman St",
    "sg:city":"Morristown",
    "sg:classifiers":[
        {
            "category":"Manufacturing",
            "subcategory":"Metals",
            "type":"Manufacturing & Wholesale Goods"
        }
    ],
    "sg:phone":"+1 423 586 7269",
    "sg:postcode":"37813",
    "sg:province":"TN",
    "sg:tags":[
        "saw",
        "mfg"
    ],
    "wof:name":"Saw Sams Shop",
    "wof:placetype":"venue"
},
  "geometry": {"coordinates":[-83.28433,36.211774],"type":"Point"}
}