{
  "type": "Feature",
  "properties": {
    "addr:full":"3007 15th Ave Chattanooga TN 37407",
    "addr:housenumber":"3007",
    "addr:postcode":"37407",
    "addr:street":"15Th Ave",
    "iso:country":"US",
    "sg:address":"3007 15th Ave",
    "sg:city":"Chattanooga",
    "sg:classifiers":[
        {
            "category":"Shopping",
            "subcategory":"Beauty & Cosmetics",
            "type":"Retail Goods"
        }
    ],
    "sg:phone":"+1 423 624 0195",
    "sg:postcode":"37407",
    "sg:province":"TN",
    "sg:tags":[
        "merchandise"
    ],
    "wof:name":"Mary Kay Cosemitics",
    "wof:placetype":"venue"
},
  "geometry": {"coordinates":[-85.275116,35.004232],"type":"Point"}
}