{
  "type": "Feature",
  "properties": {
    "iso:country":"US",
    "sg:address":"910 E Center St",
    "sg:city":"Kingsport",
    "sg:classifiers":[
        {
            "category":"Shopping",
            "subcategory":"Computers & Home Electronics",
            "type":"Retail Goods"
        }
    ],
    "sg:phone":"+1 423 246 4552",
    "sg:postcode":"37660",
    "sg:province":"TN",
    "wof:name":"US Internet Inc",
    "wof:placetype":"venue"
},
  "geometry": {"coordinates":[-82.550848,36.543519],"type":"Point"}
}