{
  "type": "Feature",
  "properties": {
    "iso:country":"US",
    "sg:address":"3846 Red Cardinal Dr NE",
    "sg:city":"Cleveland",
    "sg:classifiers":[
        {
            "category":"Shopping",
            "subcategory":"Clothing, Apparel, & Fashions",
            "type":"Retail Goods"
        }
    ],
    "sg:phone":"+1 423 478 5646",
    "sg:postcode":"37312",
    "sg:province":"TN",
    "wof:name":"Marthas Fashion",
    "wof:placetype":"venue"
},
  "geometry": {"coordinates":[-84.838362,35.179118],"type":"Point"}
}