{
  "type": "Feature",
  "properties": {
    "iso:country":"US",
    "sg:address":"12283 US Hwy 64",
    "sg:city":"Eads",
    "sg:classifiers":[
        {
            "category":"Building & Trades",
            "subcategory":"Construction",
            "type":"Services"
        }
    ],
    "sg:phone":"+1 901 767 8834",
    "sg:postcode":"38028",
    "sg:province":"TN",
    "sg:tags":[
        "resurfacing",
        "laying",
        "refinishing",
        "floor"
    ],
    "wof:name":"Ammons Floor Svc",
    "wof:placetype":"venue"
},
  "geometry": {"coordinates":[-89.650744,35.209977],"type":"Point"}
}