{
  "type": "Feature",
  "properties": {
    "addr:full":"208 Hicks Dr Sevierville TN 37862",
    "addr:housenumber":"208",
    "addr:postcode":"37862",
    "addr:street":"Hicks Dr",
    "iso:country":"US",
    "sg:address":"208 Hicks Dr",
    "sg:city":"Sevierville",
    "sg:classifiers":[
        {
            "category":"Organizations",
            "subcategory":"Religious Organization",
            "type":"Services"
        }
    ],
    "sg:phone":"+1 865 453 8009",
    "sg:postcode":"37862",
    "sg:province":"TN",
    "sg:tags":[
        "church"
    ],
    "wof:name":"Sevierville Church Of Christ",
    "wof:placetype":"venue"
},
  "geometry": {"coordinates":[-83.57217799999999,35.85556],"type":"Point"}
}