{
  "type": "Feature",
  "properties": {
    "iso:country":"US",
    "sg:address":"3213 Brainerd Rd",
    "sg:city":"Chattanooga",
    "sg:classifiers":[
        {
            "category":"Wholesale",
            "subcategory":"Machinery & Supplies",
            "type":"Manufacturing & Wholesale Goods"
        }
    ],
    "sg:phone":"+1 423 622 2002",
    "sg:postcode":"37411",
    "sg:province":"TN",
    "sg:tags":[
        "salon",
        "beauty"
    ],
    "wof:name":"Special Treasure's",
    "wof:placetype":"venue"
},
  "geometry": {"coordinates":[-85.25420200000001,35.027412],"type":"Point"}
}