{
  "type": "Feature",
  "properties": {
    "iso:country":"US",
    "sg:address":"18524 Martel Rd",
    "sg:city":"Lenoir City",
    "sg:classifiers":[
        {
            "category":"Professional",
            "type":"Services"
        }
    ],
    "sg:phone":"+1 865 988 4557",
    "sg:postcode":"37772",
    "sg:province":"TN",
    "wof:name":"Jon L Saggio",
    "wof:placetype":"venue"
},
  "geometry": {"coordinates":[-84.195903,35.834226],"type":"Point"}
}