{
  "type": "Feature",
  "properties": {
    "iso:country":"US",
    "sg:address":"1523 Cornersville Hwy",
    "sg:city":"Lewisburg",
    "sg:classifiers":[
        {
            "category":"Personal",
            "type":"Services"
        }
    ],
    "sg:phone":"+1 931 359 2182",
    "sg:postcode":"37091",
    "sg:province":"TN",
    "wof:name":"Maple Winds",
    "wof:placetype":"venue"
},
  "geometry": {"coordinates":[-86.80456100000001,35.408991],"type":"Point"}
}