{
  "type": "Feature",
  "properties": {
    "iso:country":"US",
    "sg:address":"8870 Cedar Springs Ln",
    "sg:city":"Knoxville",
    "sg:classifiers":[
        {
            "category":"Health Services",
            "subcategory":"Health Practitioner",
            "type":"Services"
        }
    ],
    "sg:phone":"+1 865 690 0510",
    "sg:postcode":"37923",
    "sg:province":"TN",
    "sg:tags":[
        "psychologist"
    ],
    "wof:name":"Robert L Whitaker PHD",
    "wof:placetype":"venue"
},
  "geometry": {"coordinates":[-84.077642,35.91247],"type":"Point"}
}