{
  "type": "Feature",
  "properties": {
    "addr:full":"2000 N Germantown Pkwy Cordova TN 38016",
    "addr:housenumber":"2000",
    "addr:postcode":"38016",
    "addr:street":"N Germantown Pkwy",
    "iso:country":"US",
    "sg:address":"2000 N Germantown Pkwy",
    "sg:city":"Cordova",
    "sg:classifiers":[
        {
            "category":"Organizations",
            "subcategory":"Religious Organization",
            "type":"Services"
        }
    ],
    "sg:phone":"+1 901 756 8850",
    "sg:postcode":"38016",
    "sg:province":"TN",
    "sg:tags":[
        "church"
    ],
    "sg:website":"www.stlukememphis.org",
    "wof:name":"St Luke Evang Lutheran Church",
    "wof:placetype":"venue"
},
  "geometry": {"coordinates":[-89.79269499999999,35.180822],"type":"Point"}
}