{
  "type": "Feature",
  "properties": {
    "iso:country":"US",
    "sg:address":"424 S College St",
    "sg:city":"Covington",
    "sg:classifiers":[
        {
            "category":"Personal",
            "subcategory":"Beauty Salon",
            "type":"Services"
        }
    ],
    "sg:phone":"+1 901 475 9393",
    "sg:postcode":"38019",
    "sg:province":"TN",
    "sg:tags":[
        "shop"
    ],
    "wof:name":"Hair Fashions",
    "wof:placetype":"venue"
},
  "geometry": {"coordinates":[-89.648825,35.561834],"type":"Point"}
}