{
  "type": "Feature",
  "properties": {
    "addr:full":"505 Market St Chattanooga TN 37402",
    "addr:housenumber":"505",
    "addr:postcode":"37402",
    "addr:street":"Market St",
    "iso:country":"US",
    "sg:address":"505 Market St",
    "sg:city":"Chattanooga",
    "sg:classifiers":[
        {
            "category":"Restaurant",
            "type":"Food & Drink"
        }
    ],
    "sg:phone":"+1 423 265 1522",
    "sg:postcode":"37402",
    "sg:province":"TN",
    "sg:tags":[
        "eating"
    ],
    "wof:name":"China Cafeteria",
    "wof:placetype":"venue"
},
  "geometry": {"coordinates":[-85.309622,35.049732],"type":"Point"}
}