{
  "type": "Feature",
  "properties": {
    "iso:country":"US",
    "sg:address":"105 S Cumberland St",
    "sg:city":"Lebanon",
    "sg:classifiers":[
        {
            "category":"Social Services",
            "type":"Services"
        }
    ],
    "sg:phone":"+1 615 443 2002",
    "sg:postcode":"37087",
    "sg:province":"TN",
    "sg:tags":[
        "organization",
        "welfare"
    ],
    "wof:name":"CASA",
    "wof:placetype":"venue"
},
  "geometry": {"coordinates":[-86.291089,36.207566],"type":"Point"}
}