{
  "type": "Feature",
  "properties": {
    "iso:country":"US",
    "sg:address":"1123 12th Ave S",
    "sg:city":"Nashville",
    "sg:classifiers":[
        {
            "category":"Wholesale",
            "subcategory":"Groceries",
            "type":"Manufacturing & Wholesale Goods"
        }
    ],
    "sg:phone":"+1 615 242 3235",
    "sg:postcode":"37203",
    "sg:province":"TN",
    "sg:tags":[
        "general"
    ],
    "wof:name":"Save-A-Lot",
    "wof:placetype":"venue"
},
  "geometry": {"coordinates":[-86.786413,36.1452],"type":"Point"}
}