{
  "type": "Feature",
  "properties": {
    "iso:country":"US",
    "sg:address":"2157 Silver City Rd",
    "sg:city":"Russellville",
    "sg:classifiers":[
        {
            "category":"Building & Trades",
            "subcategory":"Equipment Rental",
            "type":"Services"
        }
    ],
    "sg:phone":"+1 423 587 2080",
    "sg:postcode":"37860",
    "sg:province":"TN",
    "sg:tags":[
        "toilet"
    ],
    "wof:name":"Lakeway Service Systems Inc",
    "wof:placetype":"venue"
},
  "geometry": {"coordinates":[-83.17571,36.215401],"type":"Point"}
}