{
  "type": "Feature",
  "properties": {
    "iso:country":"US",
    "sg:address":"7515 Corporate Center Dr",
    "sg:city":"Germantown",
    "sg:classifiers":[
        {
            "category":"Building & Trades",
            "subcategory":"Construction",
            "type":"Services"
        }
    ],
    "sg:phone":"+1 901 757 8081",
    "sg:postcode":"38138",
    "sg:province":"TN",
    "sg:tags":[
        "home",
        "builder"
    ],
    "wof:name":"Riverbirch Builders Inc",
    "wof:placetype":"venue"
},
  "geometry": {"coordinates":[-89.811983,35.089469],"type":"Point"}
}