{
  "type": "Feature",
  "properties": {
    "iso:country":"US",
    "sg:address":"1406 County Hospital Rd",
    "sg:city":"Nashville",
    "sg:classifiers":[
        {
            "category":"Building & Trades",
            "subcategory":"Construction",
            "type":"Services"
        }
    ],
    "sg:phone":"+1 615 386 8996",
    "sg:postcode":"37218",
    "sg:province":"TN",
    "sg:tags":[
        "home",
        "builder"
    ],
    "wof:name":"Home Builders Institute",
    "wof:placetype":"venue"
},
  "geometry": {"coordinates":[-86.85190799999999,36.183677],"type":"Point"}
}