{
  "type": "Feature",
  "properties": {
    "addr:full":"527 W Main St Rogersville TN 37857",
    "addr:housenumber":"527",
    "addr:postcode":"37857",
    "addr:street":"W Main St",
    "iso:country":"US",
    "sg:address":"527 W Main St",
    "sg:city":"Rogersville",
    "sg:classifiers":[
        {
            "category":"Retail",
            "subcategory":"Repair Shop",
            "type":"Services"
        }
    ],
    "sg:phone":"+1 423 272 7697",
    "sg:postcode":"37857",
    "sg:province":"TN",
    "sg:tags":[
        "television",
        "radio",
        "satellite"
    ],
    "wof:name":"Fugates TV Sls Stllite Sls Svc",
    "wof:placetype":"venue"
},
  "geometry": {"coordinates":[-83.01214299999999,36.404544],"type":"Point"}
}