{
  "type": "Feature",
  "properties": {
    "iso:country":"US",
    "sg:address":"632 Lee St",
    "sg:city":"Dyersburg",
    "sg:classifiers":[
        {
            "category":"Professional",
            "subcategory":"Business Services",
            "type":"Services"
        }
    ],
    "sg:phone":"+1 731 286 4334",
    "sg:postcode":"38024",
    "sg:province":"TN",
    "wof:name":"Crawfords",
    "wof:placetype":"venue"
},
  "geometry": {"coordinates":[-89.394088,36.036042],"type":"Point"}
}