{
  "type": "Feature",
  "properties": {
    "iso:country":"US",
    "sg:address":"9270 Erie Rd",
    "sg:city":"Sweetwater",
    "sg:classifiers":[
        {
            "category":"Professional",
            "subcategory":"Management & Consulting",
            "type":"Services"
        }
    ],
    "sg:phone":"+1 865 213 0160",
    "sg:postcode":"37874",
    "sg:province":"TN",
    "wof:name":"Restaurant Consultants",
    "wof:placetype":"venue"
},
  "geometry": {"coordinates":[-84.56734400000001,35.647621],"type":"Point"}
}