{
  "type": "Feature",
  "properties": {
    "iso:country":"US",
    "sg:address":"105 Ford Ave",
    "sg:city":"Kingsport",
    "sg:classifiers":[
        {
            "category":"Restaurant",
            "type":"Food & Drink"
        }
    ],
    "sg:phone":"+1 423 239 8079",
    "sg:postcode":"37663",
    "sg:province":"TN",
    "sg:tags":[
        "eating"
    ],
    "wof:name":"Burger King",
    "wof:placetype":"venue"
},
  "geometry": {"coordinates":[-82.49073799999999,36.477789],"type":"Point"}
}