{
  "type": "Feature",
  "properties": {
    "iso:country":"US",
    "sg:address":"110 Hampton Pl",
    "sg:city":"Nashville",
    "sg:classifiers":[
        {
            "category":"Building & Trades",
            "subcategory":"Equipment Rental",
            "type":"Services"
        }
    ],
    "sg:phone":"+1 615 783 4443",
    "sg:postcode":"37215",
    "sg:province":"TN",
    "sg:tags":[
        "aircraft",
        "leasing",
        "charter"
    ],
    "wof:name":"CAF Inc",
    "wof:placetype":"venue"
},
  "geometry": {"coordinates":[-86.810429,36.115859],"type":"Point"}
}