{
  "type": "Feature",
  "properties": {
    "iso:country":"US",
    "sg:address":"2827 Glasgow St",
    "sg:city":"Memphis",
    "sg:classifiers":[
        {
            "category":"Building & Trades",
            "subcategory":"Plumbing",
            "type":"Services"
        }
    ],
    "sg:phone":"+1 901 358 8366",
    "sg:postcode":"38127",
    "sg:province":"TN",
    "sg:tags":[
        "contractor"
    ],
    "wof:name":"Dean Hvac",
    "wof:placetype":"venue"
},
  "geometry": {"coordinates":[-90.010221,35.202714],"type":"Point"}
}