{
  "type": "Feature",
  "properties": {
    "iso:country":"US",
    "sg:address":"1424 McCallie Ave",
    "sg:city":"Chattanooga",
    "sg:classifiers":[
        {
            "category":"Wholesale",
            "subcategory":"Jewelry",
            "type":"Manufacturing & Wholesale Goods"
        }
    ],
    "sg:phone":"+1 423 629 2449",
    "sg:postcode":"37404",
    "sg:province":"TN",
    "sg:tags":[
        "stone",
        "jeweler",
        "supply"
    ],
    "wof:name":"Kingston's Jewelers Supply",
    "wof:placetype":"venue"
},
  "geometry": {"coordinates":[-85.280564,35.038006],"type":"Point"}
}