{
  "type": "Feature",
  "properties": {
    "iso:country":"US",
    "sg:address":"5159 Wheelis Dr",
    "sg:city":"Memphis",
    "sg:classifiers":[
        {
            "category":"Organizations",
            "subcategory":"Religious Organization",
            "type":"Services"
        }
    ],
    "sg:phone":"+1 901 362 9035",
    "sg:postcode":"38117",
    "sg:province":"TN",
    "wof:name":"McGlown 3 & Associates",
    "wof:placetype":"venue"
},
  "geometry": {"coordinates":[-89.888891,35.114566],"type":"Point"}
}