{
  "type": "Feature",
  "properties": {
    "iso:country":"US",
    "sg:address":"8024 Stage Hills Blvd",
    "sg:city":"Bartlett",
    "sg:classifiers":[
        {
            "category":"Professional",
            "subcategory":"Computer Services",
            "type":"Services"
        }
    ],
    "sg:phone":"+1 901 888 2932",
    "sg:postcode":"38133",
    "sg:province":"TN",
    "sg:tags":[
        "internet"
    ],
    "wof:name":"Internetone",
    "wof:placetype":"venue"
},
  "geometry": {"coordinates":[-89.800202,35.209249],"type":"Point"}
}