{
  "type": "Feature",
  "properties": {
    "addr:full":"500 Bill Jones Dr Springfield TN 37172",
    "addr:housenumber":"500",
    "addr:postcode":"37172",
    "addr:street":"Bill Jones Dr",
    "iso:country":"US",
    "sg:address":"500 Bill Jones Dr",
    "sg:city":"Springfield",
    "sg:classifiers":[
        {
            "category":"Social Services",
            "subcategory":"Child Care",
            "type":"Services"
        }
    ],
    "sg:phone":"+1 615 384 8255",
    "sg:postcode":"37172",
    "sg:province":"TN",
    "sg:tags":[
        "day"
    ],
    "wof:name":"Juanita Cunningham",
    "wof:placetype":"venue"
},
  "geometry": {"coordinates":[-86.86403799999999,36.495694],"type":"Point"}
}