{
  "type": "Feature",
  "properties": {
    "iso:country":"US",
    "sg:address":"3867 US Hwy 19E",
    "sg:city":"Elizabethton",
    "sg:classifiers":[
        {
            "category":"Shopping",
            "subcategory":"Computers & Home Electronics",
            "type":"Retail Goods"
        }
    ],
    "sg:phone":"+1 423 543 1537",
    "sg:postcode":"37643",
    "sg:province":"TN",
    "sg:tags":[
        "equipment",
        "dealer"
    ],
    "wof:name":"K & L Computers",
    "wof:placetype":"venue"
},
  "geometry": {"coordinates":[-82.198937,36.315771],"type":"Point"}
}