{
  "type": "Feature",
  "properties": {
    "iso:country":"US",
    "sg:address":"671 Dumplin Valley Rd E",
    "sg:city":"Jefferson City",
    "sg:classifiers":[
        {
            "category":"Retail",
            "subcategory":"Animal Services",
            "type":"Services"
        }
    ],
    "sg:phone":"+1 865 397 8048",
    "sg:postcode":"37760",
    "sg:province":"TN",
    "wof:name":"Purrfect Pets",
    "wof:placetype":"venue"
},
  "geometry": {"coordinates":[-83.439983,36.0801],"type":"Point"}
}