{
  "type": "Feature",
  "properties": {
    "iso:country":"US",
    "sg:address":"6081 Summer Ave",
    "sg:city":"Memphis",
    "sg:classifiers":[
        {
            "category":"Personal",
            "type":"Services"
        },
        {
            "category":"Real Estate",
            "subcategory":"Real Estate Operator",
            "type":"Services"
        }
    ],
    "sg:phone":"+1 901 382 2994",
    "sg:postcode":"38134",
    "sg:province":"TN",
    "sg:tags":[
        "apartment"
    ],
    "wof:name":"Glen Townhomes The",
    "wof:placetype":"venue"
},
  "geometry": {"coordinates":[-89.860023,35.180155],"type":"Point"}
}