{
  "type": "Feature",
  "properties": {
    "iso:country":"US",
    "sg:address":"269 Palmer Rd",
    "sg:city":"Gatlinburg",
    "sg:classifiers":[
        {
            "category":"Food & Beverages",
            "subcategory":"Groceries & Convenience Stores",
            "type":"Retail Goods"
        }
    ],
    "sg:phone":"+1 865 436 4710",
    "sg:postcode":"37738",
    "sg:province":"TN",
    "wof:name":"Masons Mountain Market Inc",
    "wof:placetype":"venue"
},
  "geometry": {"coordinates":[-83.46718799999999,35.731756],"type":"Point"}
}