{
  "type": "Feature",
  "properties": {
    "iso:country":"US",
    "sg:address":"5818 Sunset Rd",
    "sg:city":"Knoxville",
    "sg:classifiers":[
        {
            "category":"Professional",
            "subcategory":"Business Services",
            "type":"Services"
        }
    ],
    "sg:phone":"+1 865 637 3156",
    "sg:postcode":"37914",
    "sg:province":"TN",
    "wof:name":"Greenes Jewelry Services",
    "wof:placetype":"venue"
},
  "geometry": {"coordinates":[-83.84349400000001,36.000418],"type":"Point"}
}