{
  "type": "Feature",
  "properties": {
    "addr:full":"328 E Trinity Ln Nashville TN 37207",
    "addr:housenumber":"328",
    "addr:postcode":"37207",
    "addr:street":"E Trinity Ln",
    "iso:country":"US",
    "sg:address":"328 E Trinity Ln",
    "sg:city":"Nashville",
    "sg:classifiers":[
        {
            "category":"Retail",
            "subcategory":"Laundry & Dry Cleaning",
            "type":"Services"
        }
    ],
    "sg:phone":"+1 615 228 6495",
    "sg:postcode":"37207",
    "sg:province":"TN",
    "sg:tags":[
        "cleaners"
    ],
    "wof:name":"Discount Cleaners",
    "wof:placetype":"venue"
},
  "geometry": {"coordinates":[-86.761368,36.205312],"type":"Point"}
}