{
  "type": "Feature",
  "properties": {
    "iso:country":"US",
    "sg:address":"5713 Green Grove Rd",
    "sg:city":"Hartsville",
    "sg:classifiers":[
        {
            "category":"Personal",
            "subcategory":"Beauty Salon",
            "type":"Services"
        }
    ],
    "sg:phone":"+1 615 655 5201",
    "sg:postcode":"37074",
    "sg:province":"TN",
    "wof:name":"Kathy's Kuntry Kuts & Styles",
    "wof:placetype":"venue"
},
  "geometry": {"coordinates":[-86.176734,36.456296],"type":"Point"}
}