{
  "type": "Feature",
  "properties": {
    "iso:country":"US",
    "sg:address":"298 Broadway St",
    "sg:city":"Martin",
    "sg:classifiers":[
        {
            "category":"Professional",
            "subcategory":"Lawyer & Legal Services",
            "type":"Services"
        }
    ],
    "sg:phone":"+1 731 587 3909",
    "sg:postcode":"38237",
    "sg:province":"TN",
    "sg:tags":[
        "attorney"
    ],
    "wof:name":"E Kyle Crowe Law Offices",
    "wof:placetype":"venue"
},
  "geometry": {"coordinates":[-88.848724,36.343784],"type":"Point"}
}