{
  "type": "Feature",
  "properties": {
    "iso:country":"US",
    "sg:address":"752 Summerville Rd",
    "sg:city":"Kingsport",
    "sg:classifiers":[
        {
            "category":"Wholesale",
            "subcategory":"Non-durable Goods",
            "type":"Manufacturing & Wholesale Goods"
        }
    ],
    "sg:phone":"+1 423 239 9976",
    "sg:postcode":"37663",
    "sg:province":"TN",
    "sg:tags":[
        "dry",
        "goods-wholesale"
    ],
    "wof:name":"Stonewalls Hobby And Model Sup",
    "wof:placetype":"venue"
},
  "geometry": {"coordinates":[-82.526698,36.476312],"type":"Point"}
}