{
  "type": "Feature",
  "properties": {
    "addr:full":"4023 Arrowhead Rd Memphis TN 38118",
    "addr:housenumber":"4023",
    "addr:postcode":"38118",
    "addr:street":"Arrowhead Rd",
    "iso:country":"US",
    "sg:address":"4023 Arrowhead Rd",
    "sg:city":"Memphis",
    "sg:classifiers":[
        {
            "category":"Building & Trades",
            "subcategory":"Landscaping Services",
            "type":"Services"
        }
    ],
    "sg:phone":"+1 901 366 9843",
    "sg:postcode":"38118",
    "sg:province":"TN",
    "sg:tags":[
        "landscape",
        "contractor"
    ],
    "wof:name":"Tony's Landscaping",
    "wof:placetype":"venue"
},
  "geometry": {"coordinates":[-89.930722,35.071626],"type":"Point"}
}