{
  "type": "Feature",
  "properties": {
    "addr:full":"954 Woodway Dr Morristown TN 37814",
    "addr:housenumber":"954",
    "addr:postcode":"37814",
    "addr:street":"Woodway Dr",
    "iso:country":"US",
    "sg:address":"954 Woodway Dr",
    "sg:city":"Morristown",
    "sg:classifiers":[
        {
            "category":"Recreation",
            "type":"Entertainment"
        }
    ],
    "sg:phone":"+1 423 317 9694",
    "sg:postcode":"37814",
    "sg:province":"TN",
    "wof:name":"High Roller Limos",
    "wof:placetype":"venue"
},
  "geometry": {"coordinates":[-83.369012,36.199641],"type":"Point"}
}