{
  "type": "Feature",
  "properties": {
    "iso:country":"US",
    "sg:address":"463 Parkway",
    "sg:city":"Gatlinburg",
    "sg:classifiers":[
        {
            "category":"Restaurant",
            "type":"Food & Drink"
        }
    ],
    "sg:phone":"+1 865 430 8082",
    "sg:postcode":"37738",
    "sg:province":"TN",
    "wof:name":"Pear Tree Cafe",
    "wof:placetype":"venue"
},
  "geometry": {"coordinates":[-83.51072600000001,35.715442],"type":"Point"}
}