{
  "type": "Feature",
  "properties": {
    "iso:country":"US",
    "sg:address":"7400 US Hwy 70 S",
    "sg:city":"Nashville",
    "sg:classifiers":[
        {
            "category":"Organizations",
            "subcategory":"Religious Organization",
            "type":"Services"
        }
    ],
    "sg:phone":"+1 615 646 2711",
    "sg:postcode":"37221",
    "sg:province":"TN",
    "sg:tags":[
        "church"
    ],
    "sg:website":"www.bellevuebaptist.com",
    "wof:name":"Bellevue Baptist Church",
    "wof:placetype":"venue"
},
  "geometry": {"coordinates":[-86.93530800000001,36.074031],"type":"Point"}
}