{
  "type": "Feature",
  "properties": {
    "iso:country":"US",
    "sg:address":"5419 Malachi Cir",
    "sg:city":"Knoxville",
    "sg:classifiers":[
        {
            "category":"Professional",
            "subcategory":"Accounting & Tax Preparation",
            "type":"Services"
        }
    ],
    "sg:phone":"+1 865 922 0147",
    "sg:postcode":"37918",
    "sg:province":"TN",
    "sg:tags":[
        "billing"
    ],
    "wof:name":"Medical Billing Specialist",
    "wof:placetype":"venue"
},
  "geometry": {"coordinates":[-83.89198,36.096894],"type":"Point"}
}