{
  "type": "Feature",
  "properties": {
    "addr:full":"203 N Main St Dickson TN 37055",
    "addr:housenumber":"203",
    "addr:postcode":"37055",
    "addr:street":"N Main St",
    "iso:country":"US",
    "sg:address":"203 N Main St",
    "sg:city":"Dickson",
    "sg:classifiers":[
        {
            "category":"Home & Garden",
            "subcategory":"Furniture",
            "type":"Retail Goods"
        }
    ],
    "sg:phone":"+1 615 446 2736",
    "sg:postcode":"37055",
    "sg:province":"TN",
    "sg:tags":[
        "appliance"
    ],
    "wof:name":"Barber Furniture Company Inc",
    "wof:placetype":"venue"
},
  "geometry": {"coordinates":[-87.38538699999999,36.078476],"type":"Point"}
}