{
  "type": "Feature",
  "properties": {
    "addr:full":"125 Market St E Fayetteville TN 37334",
    "addr:housenumber":"125",
    "addr:postcode":"37334",
    "addr:street":"Market St E",
    "iso:country":"US",
    "sg:address":"125 Market St E",
    "sg:city":"Fayetteville",
    "sg:classifiers":[
        {
            "category":"Professional",
            "subcategory":"Lawyer & Legal Services",
            "type":"Services"
        }
    ],
    "sg:phone":"+1 931 433 3505",
    "sg:postcode":"37334",
    "sg:province":"TN",
    "sg:tags":[
        "attorney"
    ],
    "wof:name":"Monks Realty & Auction Co",
    "wof:placetype":"venue"
},
  "geometry": {"coordinates":[-86.570421,35.151197],"type":"Point"}
}