{
  "type": "Feature",
  "properties": {
    "addr:full":"8651 Asheville Hwy Knoxville TN 37924",
    "addr:housenumber":"8651",
    "addr:postcode":"37924",
    "addr:street":"Asheville Hwy",
    "iso:country":"US",
    "sg:address":"8651 Asheville Hwy",
    "sg:city":"Knoxville",
    "sg:classifiers":[
        {
            "category":"Home & Garden",
            "subcategory":"Building Materials",
            "type":"Retail Goods"
        }
    ],
    "sg:phone":"+1 865 933 4858",
    "sg:postcode":"37924",
    "sg:province":"TN",
    "sg:tags":[
        "door"
    ],
    "sg:website":"www.farmergaragedoor.com",
    "wof:name":"Farmer Garage Door",
    "wof:placetype":"venue"
},
  "geometry": {"coordinates":[-83.73571099999999,36.025596],"type":"Point"}
}