{
  "type": "Feature",
  "properties": {
    "addr:full":"726 East Ave Chattanooga TN 37411",
    "addr:housenumber":"726",
    "addr:postcode":"37411",
    "addr:street":"East Ave",
    "iso:country":"US",
    "sg:address":"726 East Ave",
    "sg:city":"Chattanooga",
    "sg:classifiers":[
        {
            "category":"Shopping",
            "subcategory":"Clothing, Apparel, & Fashions",
            "type":"Retail Goods"
        }
    ],
    "sg:phone":"+1 423 622 5429",
    "sg:postcode":"37411",
    "sg:province":"TN",
    "sg:tags":[
        "uniform"
    ],
    "wof:name":"Lays Uniforms & Things",
    "wof:placetype":"venue"
},
  "geometry": {"coordinates":[-85.234692,35.034441],"type":"Point"}
}