{
  "type": "Feature",
  "properties": {
    "iso:country":"US",
    "sg:address":"195 Coran Rd",
    "sg:city":"Rogersville",
    "sg:classifiers":[
        {
            "category":"Wholesale",
            "subcategory":"Farm Supplies",
            "type":"Manufacturing & Wholesale Goods"
        }
    ],
    "sg:phone":"+1 423 272 6956",
    "sg:postcode":"37857",
    "sg:province":"TN",
    "wof:name":"Hawkins Farmers Co-Op",
    "wof:placetype":"venue"
},
  "geometry": {"coordinates":[-83.011366,36.355824],"type":"Point"}
}