{
  "type": "Feature",
  "properties": {
    "iso:country":"US",
    "sg:address":"1505 Dunn Ave",
    "sg:city":"Memphis",
    "sg:classifiers":[
        {
            "category":"Food & Beverages",
            "subcategory":"Bakery",
            "type":"Retail Goods"
        }
    ],
    "sg:phone":"+1 901 942 2555",
    "sg:postcode":"38106",
    "sg:province":"TN",
    "sg:tags":[
        "baker"
    ],
    "wof:name":"Pie N The Sky",
    "wof:placetype":"venue"
},
  "geometry": {"coordinates":[-90.010932,35.092584],"type":"Point"}
}