{
  "type": "Feature",
  "properties": {
    "addr:full":"1740 N Germantown Pkwy Cordova TN 38016",
    "addr:housenumber":"1740",
    "addr:postcode":"38016",
    "addr:street":"N Germantown Pkwy",
    "iso:country":"US",
    "sg:address":"1740 N Germantown Pkwy",
    "sg:city":"Cordova",
    "sg:classifiers":[
        {
            "category":"Professional",
            "subcategory":"Business Services",
            "type":"Services"
        }
    ],
    "sg:phone":"+1 901 751 0343",
    "sg:postcode":"38016",
    "sg:province":"TN",
    "sg:tags":[
        "packaging"
    ],
    "wof:name":"Boxes & More",
    "wof:placetype":"venue"
},
  "geometry": {"coordinates":[-89.792843,35.172675],"type":"Point"}
}