{
  "type": "Feature",
  "properties": {
    "iso:country":"US",
    "sg:address":"4170 State Hwy 54",
    "sg:city":"Paris",
    "sg:classifiers":[
        {
            "category":"Professional",
            "subcategory":"Engineering",
            "type":"Services"
        }
    ],
    "sg:phone":"+1 731 642 9163",
    "sg:postcode":"38242",
    "sg:province":"TN",
    "sg:tags":[
        "engineer"
    ],
    "wof:name":"Electrical Service & Systems",
    "wof:placetype":"venue"
},
  "geometry": {"coordinates":[-88.40039400000001,36.296357],"type":"Point"}
}