{
  "type": "Feature",
  "properties": {
    "iso:country":"US",
    "sg:address":"3955 E Holmes Rd",
    "sg:city":"Memphis",
    "sg:classifiers":[
        {
            "category":"Professional",
            "type":"Services"
        }
    ],
    "sg:phone":"+1 901 565 9906",
    "sg:postcode":"38118",
    "sg:province":"TN",
    "sg:tags":[
        "establishment"
    ],
    "wof:name":"Conlon Co",
    "wof:placetype":"venue"
},
  "geometry": {"coordinates":[-89.924119,35.005985],"type":"Point"}
}