{
  "type": "Feature",
  "properties": {
    "addr:full":"1767 Kansas St Memphis TN 38109",
    "addr:housenumber":"1767",
    "addr:postcode":"38109",
    "addr:street":"Kansas St",
    "iso:country":"US",
    "sg:address":"1767 Kansas St",
    "sg:city":"Memphis",
    "sg:classifiers":[
        {
            "category":"Shopping",
            "subcategory":"Shoes",
            "type":"Retail Goods"
        }
    ],
    "sg:phone":"+1 901 948 2436",
    "sg:postcode":"38109",
    "sg:province":"TN",
    "wof:name":"Millers Shoe Shop",
    "wof:placetype":"venue"
},
  "geometry": {"coordinates":[-90.065335,35.099262],"type":"Point"}
}