{
  "type": "Feature",
  "properties": {
    "iso:country":"US",
    "sg:address":"1104 Marshall Rd",
    "sg:city":"Union City",
    "sg:classifiers":[
        {
            "category":"Restaurant",
            "type":"Food & Drink"
        }
    ],
    "sg:phone":"+1 731 885 0060",
    "sg:postcode":"38261",
    "sg:province":"TN",
    "sg:tags":[
        "seafood"
    ],
    "wof:name":"Catfish Galley",
    "wof:placetype":"venue"
},
  "geometry": {"coordinates":[-89.110524,36.466506],"type":"Point"}
}