{
  "type": "Feature",
  "properties": {
    "addr:full":"545 S Main St Memphis TN 38103",
    "addr:housenumber":"545",
    "addr:postcode":"38103",
    "addr:street":"S Main St",
    "iso:country":"US",
    "sg:address":"545 S Main St",
    "sg:city":"Memphis",
    "sg:classifiers":[
        {
            "category":"Travel",
            "subcategory":"Travel Agent",
            "type":"Entertainment"
        }
    ],
    "sg:phone":"+1 901 526 0052",
    "sg:postcode":"38103",
    "sg:province":"TN",
    "sg:tags":[
        "passenger",
        "railroad",
        "transportation",
        "arrangement"
    ],
    "sg:website":"http://www.amtrak.com",
    "wof:name":"Amtrak",
    "wof:placetype":"venue"
},
  "geometry": {"coordinates":[-90.05898000000001,35.13255],"type":"Point"}
}