{
  "type": "Feature",
  "properties": {
    "iso:country":"US",
    "sg:address":"300 S White St",
    "sg:city":"Athens",
    "sg:classifiers":[
        {
            "category":"Personal",
            "subcategory":"Tanning Parlor",
            "type":"Services"
        },
        {
            "category":"Personal",
            "type":"Services"
        }
    ],
    "sg:phone":"+1 423 745 3119",
    "sg:postcode":"37303",
    "sg:province":"TN",
    "sg:tags":[
        "salon"
    ],
    "wof:name":"Paradise Tan and Travel",
    "wof:placetype":"venue"
},
  "geometry": {"coordinates":[-84.591632,35.438623],"type":"Point"}
}