{
  "type": "Feature",
  "properties": {
    "addr:full":"2003 Sweetwood Ln Knoxville TN 37932",
    "addr:housenumber":"2003",
    "addr:postcode":"37932",
    "addr:street":"Sweetwood Ln",
    "iso:country":"US",
    "sg:address":"2003 Sweetwood Ln",
    "sg:city":"Knoxville",
    "sg:classifiers":[
        {
            "category":"Professional",
            "subcategory":"Computer Services",
            "type":"Services"
        }
    ],
    "sg:phone":"+1 865 470 9088",
    "sg:postcode":"37932",
    "sg:province":"TN",
    "sg:tags":[
        "information",
        "retrieval"
    ],
    "wof:name":"Information Systems Associate",
    "wof:placetype":"venue"
},
  "geometry": {"coordinates":[-84.163259,35.939989],"type":"Point"}
}