{
  "type": "Feature",
  "properties": {
    "addr:full":"504 Concord Rd Knoxville TN 37934",
    "addr:housenumber":"504",
    "addr:postcode":"37934",
    "addr:street":"Concord Rd",
    "iso:country":"US",
    "sg:address":"504 Concord Rd",
    "sg:city":"Knoxville",
    "sg:classifiers":[
        {
            "category":"Building & Trades",
            "subcategory":"Construction",
            "type":"Services"
        },
        {
            "category":"Manufacturing",
            "subcategory":"Buildings",
            "type":"Manufacturing & Wholesale Goods"
        }
    ],
    "sg:phone":"+1 865 647 5647",
    "sg:postcode":"37934",
    "sg:province":"TN",
    "sg:tags":[
        "home",
        "builder",
        "log",
        "cabin"
    ],
    "wof:name":"Allen Log & Timber Frame Homes",
    "wof:placetype":"venue"
},
  "geometry": {"coordinates":[-84.147328,35.875266],"type":"Point"}
}