{
  "type": "Feature",
  "properties": {
    "addr:full":"2680 Rental Rd Memphis TN 38118",
    "addr:housenumber":"2680",
    "addr:postcode":"38118",
    "addr:street":"Rental Rd",
    "iso:country":"US",
    "sg:address":"2680 Rental Rd",
    "sg:city":"Memphis",
    "sg:classifiers":[
        {
            "category":"Retail",
            "subcategory":"Auto Rental",
            "type":"Services"
        }
    ],
    "sg:phone":"+1 901 345 0070",
    "sg:postcode":"38118",
    "sg:province":"TN",
    "sg:tags":[
        "renting",
        "automobile"
    ],
    "wof:name":"National Car Rental",
    "wof:placetype":"venue"
},
  "geometry": {"coordinates":[-89.97682,35.069518],"type":"Point"}
}