{
  "type": "Feature",
  "properties": {
    "iso:country":"US",
    "sg:address":"213 S Sampson Ave",
    "sg:city":"Dyersburg",
    "sg:classifiers":[
        {
            "category":"Retail",
            "subcategory":"Auto Repair",
            "type":"Services"
        }
    ],
    "sg:phone":"+1 731 285 0577",
    "sg:postcode":"38024",
    "sg:province":"TN",
    "sg:tags":[
        "repairing",
        "automobile",
        "radiator"
    ],
    "wof:name":"Quality Radiator Svc",
    "wof:placetype":"venue"
},
  "geometry": {"coordinates":[-89.382138,36.0313],"type":"Point"}
}