{
  "type": "Feature",
  "properties": {
    "addr:full":"2709 Fairview St Knoxville TN 37917",
    "addr:housenumber":"2709",
    "addr:postcode":"37917",
    "addr:street":"Fairview St",
    "iso:country":"US",
    "sg:address":"2709 Fairview St",
    "sg:city":"Knoxville",
    "sg:classifiers":[
        {
            "category":"Retail",
            "subcategory":"Animal Services",
            "type":"Services"
        }
    ],
    "sg:phone":"+1 865 525 1294",
    "sg:postcode":"37917",
    "sg:province":"TN",
    "sg:tags":[
        "cat",
        "dog",
        "kennel"
    ],
    "wof:name":"Adelle's Pet Nanny Care",
    "wof:placetype":"venue"
},
  "geometry": {"coordinates":[-83.916938,36.001064],"type":"Point"}
}