{
  "type": "Feature",
  "properties": {
    "addr:full":"170 N Oak Grove Rd Memphis TN 38120",
    "addr:housenumber":"170",
    "addr:postcode":"38120",
    "addr:street":"N Oak Grove Rd",
    "iso:country":"US",
    "sg:address":"170 N Oak Grove Rd",
    "sg:city":"Memphis",
    "sg:classifiers":[
        {
            "category":"Organizations",
            "subcategory":"Religious Organization",
            "type":"Services"
        }
    ],
    "sg:phone":"+1 901 683 2451",
    "sg:postcode":"38120",
    "sg:province":"TN",
    "wof:name":"Richland Baptist Church",
    "wof:placetype":"venue"
},
  "geometry": {"coordinates":[-89.878947,35.135906],"type":"Point"}
}