{
  "type": "Feature",
  "properties": {
    "addr:full":"3543 Rock Springs Rd Smyrna TN 37167",
    "addr:housenumber":"3543",
    "addr:postcode":"37167",
    "addr:street":"Rock Springs Rd",
    "iso:country":"US",
    "sg:address":"3543 Rock Springs Rd",
    "sg:city":"Smyrna",
    "sg:classifiers":[
        {
            "category":"Building & Trades",
            "subcategory":"Construction",
            "type":"Services"
        }
    ],
    "sg:phone":"+1 615 479 5969",
    "sg:postcode":"37167",
    "sg:province":"TN",
    "sg:tags":[
        "wallpaper",
        "painting",
        "contractor"
    ],
    "wof:name":"Don Noes Painting",
    "wof:placetype":"venue"
},
  "geometry": {"coordinates":[-86.57805500000001,35.960752],"type":"Point"}
}