{
  "type": "Feature",
  "properties": {
    "iso:country":"US",
    "sg:address":"2927 N Grundy Quarles Hwy",
    "sg:city":"Gainesboro",
    "sg:classifiers":[
        {
            "category":"Health Services",
            "subcategory":"Nursing And Care Facility",
            "type":"Services"
        }
    ],
    "sg:phone":"+1 931 268 0293",
    "sg:postcode":"38562",
    "sg:province":"TN",
    "sg:tags":[
        "home",
        "convalescent"
    ],
    "wof:name":"Mabry Health Care & Rehab Ctr",
    "wof:placetype":"venue"
},
  "geometry": {"coordinates":[-85.63723400000001,36.427951],"type":"Point"}
}