{
  "type": "Feature",
  "properties": {
    "iso:country":"US",
    "sg:address":"1005 Castlerock Ct",
    "sg:city":"Knoxville",
    "sg:classifiers":[
        {
            "category":"Professional",
            "subcategory":"Management & Consulting",
            "type":"Services"
        }
    ],
    "sg:phone":"+1 865 694 7698",
    "sg:postcode":"37919",
    "sg:province":"TN",
    "sg:tags":[
        "consultant",
        "business"
    ],
    "wof:name":"Human Capital Consulting Group",
    "wof:placetype":"venue"
},
  "geometry": {"coordinates":[-84.025338,35.913132],"type":"Point"}
}