{
  "type": "Feature",
  "properties": {
    "iso:country":"US",
    "sg:address":"3612 Park Ave",
    "sg:city":"Memphis",
    "sg:classifiers":[
        {
            "category":"Professional",
            "subcategory":"Management & Consulting",
            "type":"Services"
        },
        {
            "category":"Real Estate",
            "subcategory":"Real Estate Agent",
            "type":"Services"
        }
    ],
    "sg:phone":"+1 901 458 1525",
    "sg:postcode":"38111",
    "sg:province":"TN",
    "sg:tags":[
        "consultant"
    ],
    "wof:name":"Apm Management Inc",
    "wof:placetype":"venue"
},
  "geometry": {"coordinates":[-89.942083,35.107792],"type":"Point"}
}