{
  "type": "Feature",
  "properties": {
    "addr:full":"527 Tulip Grove Rd Hermitage TN 37076",
    "addr:housenumber":"527",
    "addr:postcode":"37076",
    "addr:street":"Tulip Grove Rd",
    "iso:country":"US",
    "sg:address":"527 Tulip Grove Rd",
    "sg:city":"Hermitage",
    "sg:classifiers":[
        {
            "category":"Building & Trades",
            "subcategory":"Construction",
            "type":"Services"
        }
    ],
    "sg:phone":"+1 615 336 7142",
    "sg:postcode":"37076",
    "sg:province":"TN",
    "sg:tags":[
        "general",
        "contractor"
    ],
    "wof:name":"Terry's Construction",
    "wof:placetype":"venue"
},
  "geometry": {"coordinates":[-86.58937,36.210681],"type":"Point"}
}