{
  "type": "Feature",
  "properties": {
    "iso:country":"US",
    "sg:address":"1021 Elaine Trl",
    "sg:city":"Chattanooga",
    "sg:classifiers":[
        {
            "category":"Restaurant",
            "type":"Food & Drink"
        }
    ],
    "sg:phone":"+1 423 855 0288",
    "sg:postcode":"37421",
    "sg:province":"TN",
    "sg:tags":[
        "family"
    ],
    "wof:name":"Krystal Restaurant",
    "wof:placetype":"venue"
},
  "geometry": {"coordinates":[-85.16855099999999,35.007522],"type":"Point"}
}