{
  "type": "Feature",
  "properties": {
    "addr:full":"2153 Bobo Section Rd Hazel Green TN 35750",
    "addr:housenumber":"2153",
    "addr:postcode":"35750",
    "addr:street":"Bobo Section Rd",
    "iso:country":"US",
    "sg:address":"2153 Bobo Section Rd",
    "sg:city":"Hazel Green",
    "sg:classifiers":[
        {
            "category":"Retail",
            "subcategory":"Repair Shop",
            "type":"Services"
        }
    ],
    "sg:phone":"+1 256 828 6111",
    "sg:postcode":"35750",
    "sg:province":"TN",
    "sg:tags":[
        "refrigeration"
    ],
    "wof:name":"Johnny J Moseley",
    "wof:placetype":"venue"
},
  "geometry": {"coordinates":[-86.643159,34.962153],"type":"Point"}
}