{
  "type": "Feature",
  "properties": {
    "iso:country":"US",
    "sg:address":"1505 S Cedar Ave",
    "sg:city":"South Pittsburg",
    "sg:classifiers":[
        {
            "category":"Wholesale",
            "subcategory":"Toys & Hobbies",
            "type":"Manufacturing & Wholesale Goods"
        }
    ],
    "sg:phone":"+1 423 837 7700",
    "sg:postcode":"37380",
    "sg:province":"TN",
    "sg:tags":[
        "firework"
    ],
    "sg:website":"www.fireworksoutlet.com",
    "wof:name":"Mike Killian Fireworks",
    "wof:placetype":"venue"
},
  "geometry": {"coordinates":[-85.717324,34.996928],"type":"Point"}
}