{
  "type": "Feature",
  "properties": {
    "addr:full":"615 Tulip Grove Rd Hermitage TN 37076",
    "addr:housenumber":"615",
    "addr:postcode":"37076",
    "addr:street":"Tulip Grove Rd",
    "iso:country":"US",
    "sg:address":"615 Tulip Grove Rd",
    "sg:city":"Hermitage",
    "sg:classifiers":[
        {
            "category":"Professional",
            "subcategory":"Business Services",
            "type":"Services"
        }
    ],
    "sg:phone":"+1 615 885 9663",
    "sg:postcode":"37076",
    "sg:province":"TN",
    "wof:name":"Joyner & Lewis Enterprises LLC",
    "wof:placetype":"venue"
},
  "geometry": {"coordinates":[-86.591414,36.203353],"type":"Point"}
}