{
  "type": "Feature",
  "properties": {
    "iso:country":"US",
    "sg:address":"1000 S Cooper St",
    "sg:city":"Memphis",
    "sg:classifiers":[
        {
            "category":"Education",
            "subcategory":"Dance Studio",
            "type":"Public Place"
        }
    ],
    "sg:phone":"+1 901 274 8101",
    "sg:postcode":"38104",
    "sg:province":"TN",
    "sg:tags":[
        "instruction",
        "dancing"
    ],
    "wof:name":"Memphis Cultural Arts Enrchmnt",
    "wof:placetype":"venue"
},
  "geometry": {"coordinates":[-89.99108099999999,35.118082],"type":"Point"}
}