{
  "type": "Feature",
  "properties": {
    "iso:country":"US",
    "sg:address":"640 Buffalo Rd",
    "sg:city":"Blountville",
    "sg:classifiers":[
        {
            "category":"Freight",
            "type":"Transportation"
        }
    ],
    "sg:phone":"+1 423 323 3048",
    "sg:postcode":"37617",
    "sg:province":"TN",
    "sg:tags":[
        "commercial",
        "storage"
    ],
    "wof:name":"Boone Lake Mini Storage",
    "wof:placetype":"venue"
},
  "geometry": {"coordinates":[-82.32139,36.491443],"type":"Point"}
}