{
  "type": "Feature",
  "properties": {
    "iso:country":"US",
    "sg:address":"50 West Ave",
    "sg:city":"Crossville",
    "sg:classifiers":[
        {
            "category":"Professional",
            "subcategory":"Lawyer & Legal Services",
            "type":"Services"
        }
    ],
    "sg:phone":"+1 931 484 5500",
    "sg:postcode":"38555",
    "sg:province":"TN",
    "sg:tags":[
        "attorney"
    ],
    "wof:name":"Cynthia Davis",
    "wof:placetype":"venue"
},
  "geometry": {"coordinates":[-85.026516,35.945917],"type":"Point"}
}