{
  "type": "Feature",
  "properties": {
    "addr:full":"936 Old Clark Rd Winchester TN 37398",
    "addr:housenumber":"936",
    "addr:postcode":"37398",
    "addr:street":"Old Clark Rd",
    "iso:country":"US",
    "sg:address":"936 Old Clark Rd",
    "sg:city":"Winchester",
    "sg:classifiers":[
        {
            "category":"Social Services",
            "subcategory":"Child Care",
            "type":"Services"
        }
    ],
    "sg:phone":"+1 931 962 2163",
    "sg:postcode":"37398",
    "sg:province":"TN",
    "sg:tags":[
        "day"
    ],
    "wof:name":"Clark Cuddle Care",
    "wof:placetype":"venue"
},
  "geometry": {"coordinates":[-86.11197199999999,35.128767],"type":"Point"}
}