{
  "type": "Feature",
  "properties": {
    "addr:full":"341 Cool Springs Blvd Franklin TN 37067",
    "addr:housenumber":"341",
    "addr:postcode":"37067",
    "addr:street":"Cool Springs Blvd",
    "iso:country":"US",
    "sg:address":"341 Cool Springs Blvd",
    "sg:city":"Franklin",
    "sg:classifiers":[
        {
            "category":"Banks & Credit Unions",
            "subcategory":"Investment Brokerage",
            "type":"Services"
        }
    ],
    "sg:phone":"+1 615 778 7600",
    "sg:postcode":"37067",
    "sg:province":"TN",
    "sg:tags":[
        "security",
        "stock",
        "bond"
    ],
    "wof:name":"Merrill Lynch",
    "wof:placetype":"venue"
},
  "geometry": {"coordinates":[-86.830147,35.942225],"type":"Point"}
}