{
  "type": "Feature",
  "properties": {
    "iso:country":"US",
    "sg:address":"801 Jefferson St",
    "sg:city":"Nashville",
    "sg:classifiers":[
        {
            "category":"Autos & Motor Vehicles",
            "subcategory":"Fuel & Gas Station",
            "type":"Retail Goods"
        }
    ],
    "sg:phone":"+1 615 251 7020",
    "sg:postcode":"37208",
    "sg:province":"TN",
    "sg:tags":[
        "oil"
    ],
    "wof:name":"BP Oil Co",
    "wof:placetype":"venue"
},
  "geometry": {"coordinates":[-86.791966,36.173141],"type":"Point"}
}