{
  "type": "Feature",
  "properties": {
    "iso:country":"US",
    "sg:address":"9273 Speerberry Ln",
    "sg:city":"Cordova",
    "sg:classifiers":[
        {
            "category":"Professional",
            "subcategory":"Business Services",
            "type":"Services"
        }
    ],
    "sg:phone":"+1 901 413 3890",
    "sg:postcode":"38016",
    "sg:province":"TN",
    "sg:tags":[
        "company",
        "production",
        "music"
    ],
    "wof:name":"Laid Back Entertainment",
    "wof:placetype":"venue"
},
  "geometry": {"coordinates":[-89.755855,35.168211],"type":"Point"}
}