{
  "type": "Feature",
  "properties": {
    "iso:country":"US",
    "sg:address":"226 E Court Ave",
    "sg:city":"Selmer",
    "sg:classifiers":[
        {
            "category":"Restaurant",
            "type":"Food & Drink"
        }
    ],
    "sg:menulink":"http://www.allmenus.com/tn/selmer/85755-dominos-pizza/menu/",
    "sg:phone":"+1 731 645 9907",
    "sg:postcode":"38375",
    "sg:province":"TN",
    "sg:tags":[
        "american",
        "wing",
        "pizza"
    ],
    "wof:name":"Domino's Pizza",
    "wof:placetype":"venue"
},
  "geometry": {"coordinates":[-88.588013,35.167773],"type":"Point"}
}