{
  "type": "Feature",
  "properties": {
    "addr:full":"115 Cannon Dr Atwood TN 38220",
    "addr:housenumber":"115",
    "addr:postcode":"38220",
    "addr:street":"Cannon Dr",
    "iso:country":"US",
    "sg:address":"115 Cannon Dr",
    "sg:city":"Atwood",
    "sg:classifiers":[
        {
            "category":"Organizations",
            "subcategory":"Religious Organization",
            "type":"Services"
        }
    ],
    "sg:phone":"+1 731 662 7798",
    "sg:postcode":"38220",
    "sg:province":"TN",
    "wof:name":"United Methodist Parsonage",
    "wof:placetype":"venue"
},
  "geometry": {"coordinates":[-88.673193,35.97301],"type":"Point"}
}