{
  "type": "Feature",
  "properties": {
    "iso:country":"US",
    "sg:address":"1902 Lamont St",
    "sg:city":"Kingsport",
    "sg:classifiers":[
        {
            "category":"Building & Trades",
            "subcategory":"Plumbing",
            "type":"Services"
        }
    ],
    "sg:phone":"+1 423 247 9829",
    "sg:postcode":"37664",
    "sg:province":"TN",
    "sg:tags":[
        "contractor"
    ],
    "wof:name":"Hammonds Gas Services LLC",
    "wof:placetype":"venue"
},
  "geometry": {"coordinates":[-82.536773,36.546208],"type":"Point"}
}