{
  "type": "Feature",
  "properties": {
    "iso:country":"US",
    "sg:address":"204 Washington St E",
    "sg:city":"Fayetteville",
    "sg:classifiers":[
        {
            "category":"Education",
            "subcategory":"Dance Studio",
            "type":"Public Place"
        }
    ],
    "sg:phone":"+1 931 455 0689",
    "sg:postcode":"37334",
    "sg:province":"TN",
    "sg:tags":[
        "instruction",
        "dancing"
    ],
    "wof:name":"Denise Kendricks Dance Academy",
    "wof:placetype":"venue"
},
  "geometry": {"coordinates":[-86.568896,35.153859],"type":"Point"}
}