{
  "type": "Feature",
  "properties": {
    "addr:full":"2900 Sutherland Ave Knoxville TN 37919",
    "addr:housenumber":"2900",
    "addr:postcode":"37919",
    "addr:street":"Sutherland Ave",
    "iso:country":"US",
    "sg:address":"2900 Sutherland Ave",
    "sg:city":"Knoxville",
    "sg:classifiers":[
        {
            "category":"Manufacturing",
            "subcategory":"Tools & Machinery",
            "type":"Manufacturing & Wholesale Goods"
        }
    ],
    "sg:phone":"+1 865 524 2285",
    "sg:postcode":"37919",
    "sg:province":"TN",
    "sg:tags":[
        "surgical",
        "merchandise",
        "mfg"
    ],
    "wof:name":"Appalachian Orthotic and Prost",
    "wof:placetype":"venue"
},
  "geometry": {"coordinates":[-83.96314599999999,35.953373],"type":"Point"}
}