{
  "type": "Feature",
  "properties": {
    "iso:country":"US",
    "sg:address":"404 College St",
    "sg:city":"Lafayette",
    "sg:classifiers":[
        {
            "category":"Utilities",
            "subcategory":"Telephone",
            "type":"Services"
        }
    ],
    "sg:phone":"+1 615 688 4219",
    "sg:postcode":"37083",
    "sg:province":"TN",
    "sg:tags":[
        "communications"
    ],
    "wof:name":"Info Ed",
    "wof:placetype":"venue"
},
  "geometry": {"coordinates":[-86.02947899999999,36.519805],"type":"Point"}
}