{
  "type": "Feature",
  "properties": {
    "iso:country":"US",
    "sg:address":"189 Gravel Woods Rd",
    "sg:city":"Midway",
    "sg:classifiers":[
        {
            "category":"Manufacturing",
            "subcategory":"Building Materials",
            "type":"Manufacturing & Wholesale Goods"
        }
    ],
    "sg:phone":"+1 423 422 4439",
    "sg:postcode":"37809",
    "sg:province":"TN",
    "sg:tags":[
        "mfg",
        "floor",
        "roof",
        "member",
        "wood",
        "truss",
        "structural"
    ],
    "wof:name":"Weems Roof Truss Co Inc",
    "wof:placetype":"venue"
},
  "geometry": {"coordinates":[-83.01418700000001,36.197374],"type":"Point"}
}