{
  "type": "Feature",
  "properties": {
    "iso:country":"US",
    "sg:address":"336 N Spring St",
    "sg:city":"Sparta",
    "sg:classifiers":[
        {
            "category":"Organizations",
            "subcategory":"Non-profit Organization",
            "type":"Services"
        },
        {
            "category":"Social Services",
            "type":"Services"
        }
    ],
    "sg:phone":"+1 931 836 2746",
    "sg:postcode":"38583",
    "sg:province":"TN",
    "sg:tags":[
        "alternative",
        "clinic",
        "abortion",
        "specialty",
        "outpatient"
    ],
    "wof:name":"Open Arms Pregnancy Center",
    "wof:placetype":"venue"
},
  "geometry": {"coordinates":[-85.473141,35.944292],"type":"Point"}
}