{
  "type": "Feature",
  "properties": {
    "addr:full":"3322 W End Ave Nashville TN 37203",
    "addr:housenumber":"3322",
    "addr:postcode":"37203",
    "addr:street":"W End Ave",
    "iso:country":"US",
    "sg:address":"3322 W End Ave",
    "sg:city":"Nashville",
    "sg:classifiers":[
        {
            "category":"Government",
            "subcategory":"Police Station",
            "type":"Public Place"
        }
    ],
    "sg:phone":"+1 615 292 5159",
    "sg:postcode":"37203",
    "sg:province":"TN",
    "sg:tags":[
        "federal"
    ],
    "sg:website":"www.fbi.gov.com",
    "wof:name":"Federal Bureau-Investigation",
    "wof:placetype":"venue"
},
  "geometry": {"coordinates":[-86.81894800000001,36.139636],"type":"Point"}
}