{
  "type": "Feature",
  "properties": {
    "iso:country":"US",
    "sg:address":"1417 Sugar Creek Rd",
    "sg:city":"Laurel Bloomery",
    "sg:classifiers":[
        {
            "category":"Recreation",
            "type":"Entertainment"
        }
    ],
    "sg:phone":"+1 423 727 1696",
    "sg:postcode":"37680",
    "sg:province":"TN",
    "wof:name":"Budding Co",
    "wof:placetype":"venue"
},
  "geometry": {"coordinates":[-81.72631800000001,36.580431],"type":"Point"}
}