{
  "type": "Feature",
  "properties": {
    "iso:country":"US",
    "sg:address":"810 S Cass St",
    "sg:city":"Corinth",
    "sg:classifiers":[
        {
            "category":"Shopping",
            "subcategory":"Department Store",
            "type":"Retail Goods"
        }
    ],
    "sg:phone":"+1 662 287 3165",
    "sg:postcode":"38834",
    "sg:province":"TN",
    "wof:name":"JC Penney",
    "wof:placetype":"venue"
},
  "geometry": {"coordinates":[-88.51799099999999,34.925402],"type":"Point"}
}