{
  "type": "Feature",
  "properties": {
    "addr:full":"620 Donelson Pkwy Dover TN 37058",
    "addr:housenumber":"620",
    "addr:postcode":"37058",
    "addr:street":"Donelson Pkwy",
    "iso:country":"US",
    "sg:address":"620 Donelson Pkwy",
    "sg:city":"Dover",
    "sg:classifiers":[
        {
            "category":"Restaurant",
            "type":"Food & Drink"
        },
        {
            "category":"Wholesale",
            "subcategory":"Non-durable Goods",
            "type":"Manufacturing & Wholesale Goods"
        }
    ],
    "sg:phone":"+1 931 232 1118",
    "sg:postcode":"37058",
    "sg:province":"TN",
    "sg:tags":[
        "eating",
        "novelty"
    ],
    "wof:name":"K Z Accessory",
    "wof:placetype":"venue"
},
  "geometry": {"coordinates":[-87.842304,36.484719],"type":"Point"}
}