{
  "type": "Feature",
  "properties": {
    "iso:country":"US",
    "sg:address":"910 N McLean Blvd",
    "sg:city":"Memphis",
    "sg:classifiers":[
        {
            "category":"Building & Trades",
            "subcategory":"Plumbing",
            "type":"Services"
        }
    ],
    "sg:phone":"+1 901 725 9888",
    "sg:postcode":"38107",
    "sg:province":"TN",
    "sg:tags":[
        "plumbing",
        "contractor"
    ],
    "wof:name":"Gas & Plumbing Specialist",
    "wof:placetype":"venue"
},
  "geometry": {"coordinates":[-89.996076,35.161764],"type":"Point"}
}