{
  "type": "Feature",
  "properties": {
    "iso:country":"US",
    "sg:address":"300 E Webster St",
    "sg:city":"Madison",
    "sg:classifiers":[
        {
            "category":"Health Services",
            "subcategory":"Clinic",
            "type":"Services"
        }
    ],
    "sg:phone":"+1 615 860 3486",
    "sg:postcode":"37115",
    "sg:province":"TN",
    "wof:name":"Middle Tn Med & Scientific",
    "wof:placetype":"venue"
},
  "geometry": {"coordinates":[-86.71768899999999,36.25192],"type":"Point"}
}