{
  "type": "Feature",
  "properties": {
    "iso:country":"US",
    "sg:address":"1655 Gallatin Pike N",
    "sg:city":"Madison",
    "sg:classifiers":[
        {
            "category":"Shopping",
            "subcategory":"Crafts & Fabrics",
            "type":"Retail Goods"
        }
    ],
    "sg:phone":"+1 615 870 0150",
    "sg:postcode":"37115",
    "sg:province":"TN",
    "sg:tags":[
        "shop"
    ],
    "wof:name":"Jo-Ann Etc",
    "wof:placetype":"venue"
},
  "geometry": {"coordinates":[-86.700067,36.295969],"type":"Point"}
}