{
  "type": "Feature",
  "properties": {
    "addr:full":"2060 Gallatin Pike N Madison TN 37115",
    "addr:housenumber":"2060",
    "addr:postcode":"37115",
    "addr:street":"Gallatin Pike N",
    "iso:country":"US",
    "sg:address":"2060 Gallatin Pike N",
    "sg:city":"Madison",
    "sg:classifiers":[
        {
            "category":"Social Services",
            "type":"Services"
        }
    ],
    "sg:phone":"+1 615 859 7559",
    "sg:postcode":"37115",
    "sg:province":"TN",
    "sg:tags":[
        "organization",
        "welfare"
    ],
    "wof:name":"Tornado Donation Ctr",
    "wof:placetype":"venue"
},
  "geometry": {"coordinates":[-86.69299700000001,36.301863],"type":"Point"}
}