{
  "type": "Feature",
  "properties": {
    "iso:country":"US",
    "sg:address":"620 Market St SW",
    "sg:city":"Knoxville",
    "sg:classifiers":[
        {
            "category":"Utilities",
            "subcategory":"Telephone",
            "type":"Services"
        }
    ],
    "sg:phone":"+1 865 539 8565",
    "sg:postcode":"37902",
    "sg:province":"TN",
    "wof:name":"BellSouth",
    "wof:placetype":"venue"
},
  "geometry": {"coordinates":[-83.918307,35.963248],"type":"Point"}
}