{
  "type": "Feature",
  "properties": {
    "iso:country":"US",
    "sg:address":"2637 Broad Ave",
    "sg:city":"Memphis",
    "sg:classifiers":[
        {
            "category":"Food & Beverages",
            "subcategory":"Groceries & Convenience Stores",
            "type":"Retail Goods"
        }
    ],
    "sg:phone":"+1 901 327 1731",
    "sg:postcode":"38112",
    "sg:province":"TN",
    "sg:tags":[
        "grocer",
        "super",
        "supermarket"
    ],
    "wof:name":"Broad Street Market",
    "wof:placetype":"venue"
},
  "geometry": {"coordinates":[-89.97144400000001,35.147616],"type":"Point"}
}