{
  "type": "Feature",
  "properties": {
    "iso:country":"US",
    "sg:address":"45 E G E Patterson Ave",
    "sg:city":"Memphis",
    "sg:classifiers":[
        {
            "category":"Professional",
            "type":"Services"
        }
    ],
    "sg:phone":"+1 901 527 2272",
    "sg:postcode":"38103",
    "sg:province":"TN",
    "sg:tags":[
        "establishment"
    ],
    "wof:name":"Paramount Productions",
    "wof:placetype":"venue"
},
  "geometry": {"coordinates":[-90.060295,35.132758],"type":"Point"}
}