{
  "type": "Feature",
  "properties": {
    "iso:country":"US",
    "sg:address":"702 Madison St",
    "sg:city":"Shelbyville",
    "sg:classifiers":[
        {
            "category":"Shopping",
            "subcategory":"Computers & Home Electronics",
            "type":"Retail Goods"
        }
    ],
    "sg:phone":"+1 931 684 4600",
    "sg:postcode":"37160",
    "sg:province":"TN",
    "wof:name":"Satellite Solutions",
    "wof:placetype":"venue"
},
  "geometry": {"coordinates":[-86.448808,35.48766],"type":"Point"}
}