{
  "type": "Feature",
  "properties": {
    "iso:country":"US",
    "sg:address":"395 Village Green Dr",
    "sg:city":"Nashville",
    "sg:classifiers":[
        {
            "category":"Organizations",
            "subcategory":"Religious Organization",
            "type":"Services"
        }
    ],
    "sg:phone":"+1 615 365 8232",
    "sg:postcode":"37217",
    "sg:province":"TN",
    "wof:name":"In Gods Hands Production",
    "wof:placetype":"venue"
},
  "geometry": {"coordinates":[-86.633833,36.089463],"type":"Point"}
}