{
  "type": "Feature",
  "properties": {
    "iso:country":"US",
    "sg:address":"2108 Indian Ridge Rd",
    "sg:city":"Johnson City",
    "sg:classifiers":[
        {
            "category":"Organizations",
            "subcategory":"Religious Organization",
            "type":"Services"
        }
    ],
    "sg:phone":"+1 423 928 8552",
    "sg:postcode":"37604",
    "sg:province":"TN",
    "sg:tags":[
        "church"
    ],
    "wof:name":"Bread Of Life Fellowship",
    "wof:placetype":"venue"
},
  "geometry": {"coordinates":[-82.399708,36.321467],"type":"Point"}
}