{
  "type": "Feature",
  "properties": {
    "iso:country":"US",
    "sg:address":"911 Cave Rd",
    "sg:city":"Jefferson City",
    "sg:classifiers":[
        {
            "category":"Building & Trades",
            "subcategory":"Construction",
            "type":"Services"
        }
    ],
    "sg:phone":"+1 865 475 7326",
    "sg:postcode":"37760",
    "sg:province":"TN",
    "sg:tags":[
        "carpentry",
        "contractor"
    ],
    "wof:name":"Custom Carpentry",
    "wof:placetype":"venue"
},
  "geometry": {"coordinates":[-83.498439,36.096843],"type":"Point"}
}