{
  "type": "Feature",
  "properties": {
    "iso:country":"US",
    "sg:address":"102 Woodmont Blvd",
    "sg:city":"Nashville",
    "sg:classifiers":[
        {
            "category":"Professional",
            "subcategory":"Accounting & Tax Preparation",
            "type":"Services"
        }
    ],
    "sg:phone":"+1 615 297 1200",
    "sg:postcode":"37205",
    "sg:province":"TN",
    "wof:name":"Career Blazers LLC",
    "wof:placetype":"venue"
},
  "geometry": {"coordinates":[-86.84618399999999,36.12357],"type":"Point"}
}