{
  "type": "Feature",
  "properties": {
    "iso:country":"US",
    "sg:address":"600 28th Ave N",
    "sg:city":"Nashville",
    "sg:classifiers":[
        {
            "category":"Social Services",
            "subcategory":"Child Care",
            "type":"Services"
        }
    ],
    "sg:phone":"+1 615 320 9842",
    "sg:postcode":"37208",
    "sg:province":"TN",
    "wof:name":"D L Williams Learning Ctr",
    "wof:placetype":"venue"
},
  "geometry": {"coordinates":[-86.818691,36.15538],"type":"Point"}
}