{
  "type": "Feature",
  "properties": {
    "addr:full":"830 W Andrew Johnson Hwy Greeneville TN 37745",
    "addr:housenumber":"830",
    "addr:postcode":"37745",
    "addr:street":"W Andrew Johnson Hwy",
    "iso:country":"US",
    "sg:address":"830 W Andrew Johnson Hwy",
    "sg:city":"Greeneville",
    "sg:classifiers":[
        {
            "category":"Autos & Motor Vehicles",
            "subcategory":"Automobile Sales",
            "type":"Retail Goods"
        }
    ],
    "sg:phone":"+1 423 639 9942",
    "sg:postcode":"37745",
    "sg:province":"TN",
    "sg:tags":[
        "car",
        "dealer"
    ],
    "wof:name":"Moore's Auto Sales",
    "wof:placetype":"venue"
},
  "geometry": {"coordinates":[-82.836568,36.174106],"type":"Point"}
}