{
  "type": "Feature",
  "properties": {
    "addr:full":"905 21st St SW Knoxville TN 37916",
    "addr:housenumber":"905",
    "addr:postcode":"37916",
    "addr:street":"21St St Sw",
    "iso:country":"US",
    "sg:address":"905 21st St SW",
    "sg:city":"Knoxville",
    "sg:classifiers":[
        {
            "category":"Professional",
            "type":"Services"
        }
    ],
    "sg:phone":"+1 865 544 1153",
    "sg:postcode":"37916",
    "sg:province":"TN",
    "sg:tags":[
        "establishment"
    ],
    "wof:name":"Johnson & Galyon",
    "wof:placetype":"venue"
},
  "geometry": {"coordinates":[-83.937325,35.952554],"type":"Point"}
}