{
  "type": "Feature",
  "properties": {
    "iso:country":"US",
    "sg:address":"509 Spry Rd",
    "sg:city":"Bradyville",
    "sg:classifiers":[
        {
            "category":"Building & Trades",
            "subcategory":"Construction",
            "type":"Services"
        }
    ],
    "sg:phone":"+1 615 765 5913",
    "sg:postcode":"37026",
    "sg:province":"TN",
    "sg:tags":[
        "flooring",
        "contractor"
    ],
    "wof:name":"Tile Masters",
    "wof:placetype":"venue"
},
  "geometry": {"coordinates":[-86.082956,35.644794],"type":"Point"}
}