{
  "type": "Feature",
  "properties": {
    "iso:country":"US",
    "sg:address":"310 Wharf St",
    "sg:city":"Loudon",
    "sg:classifiers":[
        {
            "category":"Professional",
            "subcategory":"Lawyer & Legal Services",
            "type":"Services"
        }
    ],
    "sg:phone":"+1 865 458 8800",
    "sg:postcode":"37774",
    "sg:province":"TN",
    "sg:tags":[
        "attorney"
    ],
    "wof:name":"J Edward Murphy",
    "wof:placetype":"venue"
},
  "geometry": {"coordinates":[-84.338668,35.741186],"type":"Point"}
}