{
  "type": "Feature",
  "properties": {
    "iso:country":"US",
    "sg:address":"2814 Bransford Ave",
    "sg:city":"Nashville",
    "sg:classifiers":[
        {
            "category":"Shopping",
            "subcategory":"Florist",
            "type":"Retail Goods"
        }
    ],
    "sg:phone":"+1 615 297 5389",
    "sg:postcode":"37204",
    "sg:province":"TN",
    "wof:name":"Designer's Studio",
    "wof:placetype":"venue"
},
  "geometry": {"coordinates":[-86.7667,36.11388],"type":"Point"}
}