{
  "type": "Feature",
  "properties": {
    "addr:full":"405 Tennessee Ave Athens TN 37303",
    "addr:housenumber":"405",
    "addr:postcode":"37303",
    "addr:street":"Tennessee Ave",
    "iso:country":"US",
    "sg:address":"405 Tennessee Ave",
    "sg:city":"Athens",
    "sg:classifiers":[
        {
            "category":"Building & Trades",
            "subcategory":"Equipment Rental",
            "type":"Services"
        }
    ],
    "sg:phone":"+1 423 745 3833",
    "sg:postcode":"37303",
    "sg:province":"TN",
    "sg:tags":[
        "yard"
    ],
    "wof:name":"Weddings By Verenna",
    "wof:placetype":"venue"
},
  "geometry": {"coordinates":[-84.598679,35.455798],"type":"Point"}
}