{
  "type": "Feature",
  "properties": {
    "iso:country":"US",
    "sg:address":"203 Larchmont Ave",
    "sg:city":"Chattanooga",
    "sg:classifiers":[
        {
            "category":"Professional",
            "subcategory":"Business Services",
            "type":"Services"
        }
    ],
    "sg:phone":"+1 423 622 3821",
    "sg:postcode":"37411",
    "sg:province":"TN",
    "wof:name":"Divine Creations",
    "wof:placetype":"venue"
},
  "geometry": {"coordinates":[-85.232083,35.00992],"type":"Point"}
}