{
  "type": "Feature",
  "properties": {
    "iso:country":"US",
    "sg:address":"226 Eagle Point Dr",
    "sg:city":"Rockwood",
    "sg:classifiers":[
        {
            "category":"Wholesale",
            "subcategory":"Auto Parts",
            "type":"Manufacturing & Wholesale Goods"
        }
    ],
    "sg:phone":"+1 865 354 6609",
    "sg:postcode":"37854",
    "sg:province":"TN",
    "sg:tags":[
        "used"
    ],
    "wof:name":"Lakeside Barge & Erosion Contr",
    "wof:placetype":"venue"
},
  "geometry": {"coordinates":[-84.7449,35.766206],"type":"Point"}
}