{
  "type": "Feature",
  "properties": {
    "iso:country":"US",
    "sg:address":"107 Hiller Dr",
    "sg:city":"Old Hickory",
    "sg:classifiers":[
        {
            "category":"Organizations",
            "subcategory":"Non-profit Organization",
            "type":"Services"
        }
    ],
    "sg:phone":"+1 615 847 4227",
    "sg:postcode":"37138",
    "sg:province":"TN",
    "sg:tags":[
        "disability"
    ],
    "wof:name":"Disability Asscociates",
    "wof:placetype":"venue"
},
  "geometry": {"coordinates":[-86.675451,36.278957],"type":"Point"}
}