{
  "type": "Feature",
  "properties": {
    "iso:country":"US",
    "sg:address":"2560 Bells Hwy",
    "sg:city":"Jackson",
    "sg:classifiers":[
        {
            "category":"Autos & Motor Vehicles",
            "subcategory":"Automobile Sales",
            "type":"Retail Goods"
        }
    ],
    "sg:phone":"+1 731 664 1860",
    "sg:postcode":"38305",
    "sg:province":"TN",
    "sg:tags":[
        "truck"
    ],
    "wof:name":"Tri-State Truck Ctr",
    "wof:placetype":"venue"
},
  "geometry": {"coordinates":[-88.878016,35.657883],"type":"Point"}
}