{
  "type": "Feature",
  "properties": {
    "iso:country":"US",
    "sg:address":"4844 Peninsula Pointe Dr",
    "sg:city":"Hermitage",
    "sg:classifiers":[
        {
            "category":"Wholesale",
            "subcategory":"Vending Machines",
            "type":"Manufacturing & Wholesale Goods"
        }
    ],
    "sg:phone":"+1 615 886 0929",
    "sg:postcode":"37076",
    "sg:province":"TN",
    "wof:name":"Candyland Vending",
    "wof:placetype":"venue"
},
  "geometry": {"coordinates":[-86.591972,36.153186],"type":"Point"}
}