{
  "type": "Feature",
  "properties": {
    "iso:country":"US",
    "sg:address":"116 Front St",
    "sg:city":"Smyrna",
    "sg:classifiers":[
        {
            "category":"Shopping",
            "subcategory":"Bicycles & Sporting Goods",
            "type":"Retail Goods"
        }
    ],
    "sg:phone":"+1 615 459 9272",
    "sg:postcode":"37167",
    "sg:province":"TN",
    "wof:name":"Swafford Sporting Goods",
    "wof:placetype":"venue"
},
  "geometry": {"coordinates":[-86.518827,35.980776],"type":"Point"}
}