{
  "type": "Feature",
  "properties": {
    "iso:country":"US",
    "sg:address":"3343 Big Springs Rd",
    "sg:city":"Maryville",
    "sg:classifiers":[
        {
            "category":"Organizations",
            "subcategory":"Membership Organization",
            "type":"Services"
        }
    ],
    "sg:phone":"+1 865 995 2009",
    "sg:postcode":"37801",
    "sg:province":"TN",
    "wof:name":"Shades of The Past St Rod Assn",
    "wof:placetype":"venue"
},
  "geometry": {"coordinates":[-84.075253,35.740166],"type":"Point"}
}