{
  "type": "Feature",
  "properties": {
    "iso:country":"US",
    "sg:address":"2300 Clifton Ave",
    "sg:city":"Nashville",
    "sg:classifiers":[
        {
            "category":"Professional",
            "type":"Services"
        }
    ],
    "sg:phone":"+1 615 837 7575",
    "sg:postcode":"37209",
    "sg:province":"TN",
    "sg:tags":[
        "establishment"
    ],
    "wof:name":"Project Cure",
    "wof:placetype":"venue"
},
  "geometry": {"coordinates":[-86.810844,36.15799],"type":"Point"}
}