{
  "type": "Feature",
  "properties": {
    "iso:country":"US",
    "sg:address":"14390 Lebanon Rd",
    "sg:city":"Old Hickory",
    "sg:classifiers":[
        {
            "category":"Restaurant",
            "type":"Food & Drink"
        }
    ],
    "sg:phone":"+1 615 758 6385",
    "sg:postcode":"37138",
    "sg:province":"TN",
    "wof:name":"Gourmet Ribs",
    "wof:placetype":"venue"
},
  "geometry": {"coordinates":[-86.566233,36.22033],"type":"Point"}
}