{
  "type": "Feature",
  "properties": {
    "iso:country":"US",
    "sg:address":"4295 Cromwell Rd",
    "sg:city":"Chattanooga",
    "sg:classifiers":[
        {
            "category":"Home & Garden",
            "subcategory":"Household Appliances",
            "type":"Retail Goods"
        },
        {
            "category":"Wholesale",
            "subcategory":"Electrical",
            "type":"Manufacturing & Wholesale Goods"
        }
    ],
    "sg:phone":"+1 423 490 0015",
    "sg:postcode":"37421",
    "sg:province":"TN",
    "sg:tags":[
        "major"
    ],
    "wof:name":"Absolute Appliance Distrs",
    "wof:placetype":"venue"
},
  "geometry": {"coordinates":[-85.198635,35.066118],"type":"Point"}
}