{
  "type": "Feature",
  "properties": {
    "iso:country":"US",
    "sg:address":"1055 Rinda Rd",
    "sg:city":"Greenfield",
    "sg:classifiers":[
        {
            "category":"Retail",
            "subcategory":"Repair Shop",
            "type":"Services"
        }
    ],
    "sg:phone":"+1 731 235 9036",
    "sg:postcode":"38230",
    "sg:province":"TN",
    "wof:name":"Electronic Service & Guns",
    "wof:placetype":"venue"
},
  "geometry": {"coordinates":[-88.709271,36.133427],"type":"Point"}
}