{
  "type": "Feature",
  "properties": {
    "iso:country":"US",
    "sg:address":"5428 Misty Valley Dr",
    "sg:city":"Ooltewah",
    "sg:classifiers":[
        {
            "category":"Wholesale",
            "subcategory":"Vending Machines",
            "type":"Manufacturing & Wholesale Goods"
        }
    ],
    "sg:phone":"+1 423 396 3609",
    "sg:postcode":"37363",
    "sg:province":"TN",
    "sg:tags":[
        "operator"
    ],
    "wof:name":"Superior Vending Inc",
    "wof:placetype":"venue"
},
  "geometry": {"coordinates":[-85.03250300000001,35.067174],"type":"Point"}
}