{
  "type": "Feature",
  "properties": {
    "addr:full":"2001 Lacy Ln Maryville TN 37801",
    "addr:housenumber":"2001",
    "addr:postcode":"37801",
    "addr:street":"Lacy Ln",
    "iso:country":"US",
    "sg:address":"2001 Lacy Ln",
    "sg:city":"Maryville",
    "sg:classifiers":[
        {
            "category":"Recreation",
            "type":"Entertainment"
        }
    ],
    "sg:phone":"+1 865 984 9495",
    "sg:postcode":"37801",
    "sg:province":"TN",
    "sg:tags":[
        "instruction",
        "gymnastic"
    ],
    "wof:name":"Tumble Bear Gymnastics",
    "wof:placetype":"venue"
},
  "geometry": {"coordinates":[-84.003636,35.734035],"type":"Point"}
}