{
  "type": "Feature",
  "properties": {
    "iso:country":"US",
    "sg:address":"104 Carlock Ave",
    "sg:city":"Harriman",
    "sg:classifiers":[
        {
            "category":"Retail",
            "subcategory":"Auto Repair",
            "type":"Services"
        }
    ],
    "sg:phone":"+1 865 882 8773",
    "sg:postcode":"37748",
    "sg:province":"TN",
    "sg:tags":[
        "machine",
        "automobile",
        "shop"
    ],
    "wof:name":"Randy's Precision Engine Svc",
    "wof:placetype":"venue"
},
  "geometry": {"coordinates":[-84.564745,35.917067],"type":"Point"}
}