{
  "type": "Feature",
  "properties": {
    "iso:country":"US",
    "sg:address":"6334 Dawn Haven Dr",
    "sg:city":"Millington",
    "sg:classifiers":[
        {
            "category":"Professional",
            "type":"Services"
        }
    ],
    "sg:phone":"+1 901 873 0571",
    "sg:postcode":"38053",
    "sg:province":"TN",
    "sg:tags":[
        "establishment"
    ],
    "wof:name":"Southern Meadows Mobile Hm Cmm",
    "wof:placetype":"venue"
},
  "geometry": {"coordinates":[-89.854591,35.332334],"type":"Point"}
}