{
  "type": "Feature",
  "properties": {
    "iso:country":"US",
    "sg:address":"101 Cross Timbers Dr",
    "sg:city":"Nashville",
    "sg:classifiers":[
        {
            "category":"Organizations",
            "subcategory":"Religious Organization",
            "type":"Services"
        }
    ],
    "sg:phone":"+1 615 646 2711",
    "sg:postcode":"37221",
    "sg:province":"TN",
    "sg:tags":[
        "church"
    ],
    "sg:website":"www.bellevuebaptist.com",
    "wof:name":"Bellevue Baptist Church",
    "wof:placetype":"venue"
},
  "geometry": {"coordinates":[-86.935395,36.07591],"type":"Point"}
}