{
  "type": "Feature",
  "properties": {
    "iso:country":"US",
    "sg:address":"5825 Deer Estates Dr",
    "sg:city":"Nashville",
    "sg:classifiers":[
        {
            "category":"Shopping",
            "subcategory":"Stationery & Office Supplies",
            "type":"Retail Goods"
        }
    ],
    "sg:phone":"+1 615 646 4840",
    "sg:postcode":"37221",
    "sg:province":"TN",
    "sg:tags":[
        "envelope",
        "store"
    ],
    "wof:name":"Sincerely Yours",
    "wof:placetype":"venue"
},
  "geometry": {"coordinates":[-86.959486,36.036774],"type":"Point"}
}