{
  "type": "Feature",
  "properties": {
    "iso:country":"US",
    "sg:address":"106 E 8th Ave",
    "sg:city":"Springfield",
    "sg:classifiers":[
        {
            "category":"Home & Garden",
            "subcategory":"Furniture",
            "type":"Retail Goods"
        }
    ],
    "sg:phone":"+1 615 384 6134",
    "sg:postcode":"37172",
    "sg:province":"TN",
    "wof:name":"Jackson Sales Inc",
    "wof:placetype":"venue"
},
  "geometry": {"coordinates":[-86.884199,36.506859],"type":"Point"}
}