{
  "type": "Feature",
  "properties": {
    "iso:country":"US",
    "sg:address":"332 Saint George Ave",
    "sg:city":"Dyersburg",
    "sg:classifiers":[
        {
            "category":"Building & Trades",
            "subcategory":"Construction",
            "type":"Services"
        }
    ],
    "sg:phone":"+1 731 285 9289",
    "sg:postcode":"38024",
    "sg:province":"TN",
    "sg:tags":[
        "house"
    ],
    "wof:name":"Byars Construction Company",
    "wof:placetype":"venue"
},
  "geometry": {"coordinates":[-89.40287600000001,36.031244],"type":"Point"}
}