{
  "type": "Feature",
  "properties": {
    "iso:country":"US",
    "sg:address":"133 Public Sq",
    "sg:city":"Lebanon",
    "sg:classifiers":[
        {
            "category":"Professional",
            "subcategory":"Art Services",
            "type":"Services"
        }
    ],
    "sg:phone":"+1 615 443 2353",
    "sg:postcode":"37087",
    "sg:province":"TN",
    "sg:tags":[
        "commercial",
        "design"
    ],
    "wof:name":"Trouy Design",
    "wof:placetype":"venue"
},
  "geometry": {"coordinates":[-86.29138399999999,36.207886],"type":"Point"}
}