{
  "type": "Feature",
  "properties": {
    "iso:country":"US",
    "sg:address":"1485 Mountain Ranch Rd",
    "sg:city":"Newport",
    "sg:classifiers":[
        {
            "category":"Social Services",
            "subcategory":"Child Care",
            "type":"Services"
        }
    ],
    "sg:phone":"+1 423 623 1080",
    "sg:postcode":"37821",
    "sg:province":"TN",
    "wof:name":"Kids World Learning Ctr",
    "wof:placetype":"venue"
},
  "geometry": {"coordinates":[-83.208865,35.919818],"type":"Point"}
}