{
  "type": "Feature",
  "properties": {
    "iso:country":"US",
    "sg:address":"419 Sunnyside Dr",
    "sg:city":"Nashville",
    "sg:classifiers":[
        {
            "category":"Banks & Credit Unions",
            "subcategory":"Financial Services",
            "type":"Services"
        }
    ],
    "sg:phone":"+1 615 298 2289",
    "sg:postcode":"37205",
    "sg:province":"TN",
    "sg:tags":[
        "investor"
    ],
    "wof:name":"Rider Investments LP",
    "wof:placetype":"venue"
},
  "geometry": {"coordinates":[-86.85021,36.109783],"type":"Point"}
}