{
  "type": "Feature",
  "properties": {
    "addr:full":"2485 Memorial Blvd Murfreesboro TN 37129",
    "addr:housenumber":"2485",
    "addr:postcode":"37129",
    "addr:street":"Memorial Blvd",
    "iso:country":"US",
    "sg:address":"2485 Memorial Blvd",
    "sg:city":"Murfreesboro",
    "sg:classifiers":[
        {
            "category":"Shopping",
            "subcategory":"Pharmacy",
            "type":"Retail Goods"
        }
    ],
    "sg:phone":"+1 615 904 9907",
    "sg:postcode":"37129",
    "sg:province":"TN",
    "wof:name":"Eckerd",
    "wof:placetype":"venue"
},
  "geometry": {"coordinates":[-86.394059,35.856909],"type":"Point"}
}