{
  "type": "Feature",
  "properties": {
    "addr:full":"1587 State Hwy 91 Mountain City TN 37683",
    "addr:housenumber":"1587",
    "addr:postcode":"37683",
    "addr:street":"State Hwy 91",
    "iso:country":"US",
    "sg:address":"1587 State Hwy 91",
    "sg:city":"Mountain City",
    "sg:classifiers":[
        {
            "category":"Government",
            "subcategory":"Office",
            "type":"Public Place"
        }
    ],
    "sg:phone":"+1 423 727 2933",
    "sg:postcode":"37683",
    "sg:province":"TN",
    "sg:tags":[
        "village"
    ],
    "wof:name":"Rambo Springs Filter Plant",
    "wof:placetype":"venue"
},
  "geometry": {"coordinates":[-81.78729800000001,36.495184],"type":"Point"}
}