{
  "type": "Feature",
  "properties": {
    "addr:full":"3939 Whitebrook Dr Memphis TN 38118",
    "addr:housenumber":"3939",
    "addr:postcode":"38118",
    "addr:street":"Whitebrook Dr",
    "iso:country":"US",
    "sg:address":"3939 Whitebrook Dr",
    "sg:city":"Memphis",
    "sg:classifiers":[
        {
            "category":"Personal",
            "type":"Services"
        }
    ],
    "sg:phone":"+1 901 367 9835",
    "sg:postcode":"38118",
    "sg:province":"TN",
    "sg:tags":[
        "credit",
        "debt",
        "counseling"
    ],
    "wof:name":"American Fair Credit Assn",
    "wof:placetype":"venue"
},
  "geometry": {"coordinates":[-89.931847,35.060352],"type":"Point"}
}