{
  "type": "Feature",
  "properties": {
    "iso:country":"US",
    "sg:address":"307 S Main St",
    "sg:city":"Greeneville",
    "sg:classifiers":[
        {
            "category":"Organizations",
            "subcategory":"Religious Organization",
            "type":"Services"
        }
    ],
    "sg:phone":"+1 423 638 6224",
    "sg:postcode":"37743",
    "sg:province":"TN",
    "wof:name":"Christ United Methodist Church",
    "wof:placetype":"venue"
},
  "geometry": {"coordinates":[-82.83257999999999,36.160121],"type":"Point"}
}