{
  "type": "Feature",
  "properties": {
    "iso:country":"US",
    "sg:address":"8279 Old Hwy 43",
    "sg:city":"Mt Pleasant",
    "sg:classifiers":[
        {
            "category":"Organizations",
            "subcategory":"Religious Organization",
            "type":"Services"
        }
    ],
    "sg:phone":"+1 931 379 9049",
    "sg:postcode":"38474",
    "sg:province":"TN",
    "sg:tags":[
        "church"
    ],
    "wof:name":"Fuqua Missionary Baptist Chrch",
    "wof:placetype":"venue"
},
  "geometry": {"coordinates":[-87.240161,35.485545],"type":"Point"}
}