{
  "type": "Feature",
  "properties": {
    "addr:full":"1006 Over Mountain Dr Elizabethton TN 37643",
    "addr:housenumber":"1006",
    "addr:postcode":"37643",
    "addr:street":"Over Mountain Dr",
    "iso:country":"US",
    "sg:address":"1006 Over Mountain Dr",
    "sg:city":"Elizabethton",
    "sg:classifiers":[
        {
            "category":"Restaurant",
            "type":"Food & Drink"
        }
    ],
    "sg:menulink":"http://www.allmenus.com/tn/elizabethton/153358-bojangles/menu/",
    "sg:phone":"+1 423 543 3500",
    "sg:postcode":"37643",
    "sg:province":"TN",
    "sg:tags":[
        "chicken",
        "sandwich",
        "american"
    ],
    "wof:name":"Bojangle's",
    "wof:placetype":"venue"
},
  "geometry": {"coordinates":[-82.24641200000001,36.346798],"type":"Point"}
}