{
  "type": "Feature",
  "properties": {
    "iso:country":"US",
    "sg:address":"815 W 5th North St",
    "sg:city":"Morristown",
    "sg:classifiers":[
        {
            "category":"Health Services",
            "subcategory":"Doctor",
            "type":"Services"
        }
    ],
    "sg:phone":"+1 423 586 5031",
    "sg:postcode":"37814",
    "sg:province":"TN",
    "sg:tags":[
        "physician",
        "surgeon"
    ],
    "wof:name":"Cindy Perry MD",
    "wof:placetype":"venue"
},
  "geometry": {"coordinates":[-83.303918,36.21353],"type":"Point"}
}