{
  "type": "Feature",
  "properties": {
    "iso:country":"US",
    "sg:address":"2135 Chapman Rd",
    "sg:city":"Chattanooga",
    "sg:classifiers":[
        {
            "category":"Professional",
            "subcategory":"Management & Consulting",
            "type":"Services"
        }
    ],
    "sg:phone":"+1 423 892 1868",
    "sg:postcode":"37421",
    "sg:province":"TN",
    "wof:name":"Bowers Transportation Group",
    "wof:placetype":"venue"
},
  "geometry": {"coordinates":[-85.188789,35.058141],"type":"Point"}
}