{
  "type": "Feature",
  "properties": {
    "iso:country":"US",
    "sg:address":"5234 Saundersville Rd",
    "sg:city":"Old Hickory",
    "sg:classifiers":[
        {
            "category":"Real Estate",
            "subcategory":"Real Estate Agent",
            "type":"Services"
        }
    ],
    "sg:phone":"+1 615 773 1833",
    "sg:postcode":"37138",
    "sg:province":"TN",
    "wof:name":"West End Realty",
    "wof:placetype":"venue"
},
  "geometry": {"coordinates":[-86.55925499999999,36.255171],"type":"Point"}
}