{
  "type": "Feature",
  "properties": {
    "addr:full":"2083 Holt Town Rd Newport TN 37821",
    "addr:housenumber":"2083",
    "addr:postcode":"37821",
    "addr:street":"Holt Town Rd",
    "iso:country":"US",
    "sg:address":"2083 Holt Town Rd",
    "sg:city":"Newport",
    "sg:classifiers":[
        {
            "category":"Building & Trades",
            "subcategory":"Construction",
            "type":"Services"
        }
    ],
    "sg:phone":"+1 423 613 5594",
    "sg:postcode":"37821",
    "sg:province":"TN",
    "sg:tags":[
        "excavation",
        "contractor"
    ],
    "wof:name":"Fish Excavating",
    "wof:placetype":"venue"
},
  "geometry": {"coordinates":[-83.205476,36.084362],"type":"Point"}
}