{
  "type": "Feature",
  "properties": {
    "addr:full":"1766 September Ave Memphis TN 38116",
    "addr:housenumber":"1766",
    "addr:postcode":"38116",
    "addr:street":"September Ave",
    "iso:country":"US",
    "sg:address":"1766 September Ave",
    "sg:city":"Memphis",
    "sg:classifiers":[
        {
            "category":"Retail",
            "subcategory":"Auto Repair",
            "type":"Services"
        }
    ],
    "sg:phone":"+1 901 332 8500",
    "sg:postcode":"38116",
    "sg:province":"TN",
    "sg:tags":[
        "body",
        "automobile",
        "painting"
    ],
    "wof:name":"Kelly's Auto Body & Svc",
    "wof:placetype":"venue"
},
  "geometry": {"coordinates":[-90.007092,35.054765],"type":"Point"}
}