{
  "type": "Feature",
  "properties": {
    "addr:full":"221 Shenendoah Dr Friendsville TN 37737",
    "addr:housenumber":"221",
    "addr:postcode":"37737",
    "addr:street":"Shenendoah Dr",
    "iso:country":"US",
    "sg:address":"221 Shenendoah Dr",
    "sg:city":"Friendsville",
    "sg:classifiers":[
        {
            "category":"Building & Trades",
            "subcategory":"Landscaping Services",
            "type":"Services"
        }
    ],
    "sg:phone":"+1 865 995 1503",
    "sg:postcode":"37737",
    "sg:province":"TN",
    "wof:name":"Ground Maintenance",
    "wof:placetype":"venue"
},
  "geometry": {"coordinates":[-84.10458199999999,35.745504],"type":"Point"}
}