{
  "type": "Feature",
  "properties": {
    "iso:country":"US",
    "sg:address":"4631 Central Valley Rd",
    "sg:city":"Murfreesboro",
    "sg:classifiers":[
        {
            "category":"Building & Trades",
            "subcategory":"Landscaping Services",
            "type":"Services"
        }
    ],
    "sg:phone":"+1 615 904 2211",
    "sg:postcode":"37129",
    "sg:province":"TN",
    "sg:tags":[
        "landscape",
        "contractor"
    ],
    "wof:name":"Turf Dynamics",
    "wof:placetype":"venue"
},
  "geometry": {"coordinates":[-86.438985,35.972795],"type":"Point"}
}