{
  "type": "Feature",
  "properties": {
    "iso:country":"US",
    "sg:address":"2171 Judicial Dr",
    "sg:city":"Germantown",
    "sg:classifiers":[
        {
            "category":"Professional",
            "type":"Services"
        }
    ],
    "sg:phone":"+1 901 624 7243",
    "sg:postcode":"38138",
    "sg:province":"TN",
    "sg:tags":[
        "establishment"
    ],
    "wof:name":"One Call",
    "wof:placetype":"venue"
},
  "geometry": {"coordinates":[-89.81303200000001,35.089078],"type":"Point"}
}