{
  "type": "Feature",
  "properties": {
    "addr:full":"702 28th Ave N Nashville TN 37208",
    "addr:housenumber":"702",
    "addr:postcode":"37208",
    "addr:street":"28Th Ave N",
    "iso:country":"US",
    "sg:address":"702 28th Ave N",
    "sg:city":"Nashville",
    "sg:classifiers":[
        {
            "category":"Food & Beverages",
            "subcategory":"Groceries & Convenience Stores",
            "type":"Retail Goods"
        },
        {
            "category":"Autos & Motor Vehicles",
            "subcategory":"Fuel & Gas Station",
            "type":"Retail Goods"
        }
    ],
    "sg:phone":"+1 615 327 4184",
    "sg:postcode":"37208",
    "sg:province":"TN",
    "sg:tags":[
        "oil"
    ],
    "wof:name":"Clifton Phillips 66",
    "wof:placetype":"venue"
},
  "geometry": {"coordinates":[-86.818815,36.160083],"type":"Point"}
}