{
  "type": "Feature",
  "properties": {
    "addr:full":"900 N Chancery St Mc Minnville TN 37110",
    "addr:housenumber":"900",
    "addr:postcode":"37110",
    "addr:street":"N Chancery St",
    "iso:country":"US",
    "sg:address":"900 N Chancery St",
    "sg:city":"Mc Minnville",
    "sg:classifiers":[
        {
            "category":"Banks & Credit Unions",
            "subcategory":"Bank",
            "type":"Services"
        }
    ],
    "sg:phone":"+1 931 507 1422",
    "sg:postcode":"37110",
    "sg:province":"TN",
    "wof:name":"Homeland Community Bank Inc",
    "wof:placetype":"venue"
},
  "geometry": {"coordinates":[-85.786141,35.6989],"type":"Point"}
}