{
  "type": "Feature",
  "properties": {
    "iso:country":"US",
    "sg:address":"508 Withrow Rd",
    "sg:city":"Mc Donald",
    "sg:classifiers":[
        {
            "category":"Government",
            "subcategory":"Office",
            "type":"Public Place"
        }
    ],
    "sg:phone":"+1 423 728 7006",
    "sg:postcode":"37353",
    "sg:province":"TN",
    "sg:website":"www.bradleyco.net",
    "wof:name":"Bradley Pike Road Supt",
    "wof:placetype":"venue"
},
  "geometry": {"coordinates":[-84.95583499999999,35.155699],"type":"Point"}
}