{
  "type": "Feature",
  "properties": {
    "addr:full":"6207 Chapman Hwy Knoxville TN 37920",
    "addr:housenumber":"6207",
    "addr:postcode":"37920",
    "addr:street":"Chapman Hwy",
    "iso:country":"US",
    "sg:address":"6207 Chapman Hwy",
    "sg:city":"Knoxville",
    "sg:classifiers":[
        {
            "category":"Health Services",
            "subcategory":"Doctor",
            "type":"Services"
        }
    ],
    "sg:phone":"+1 865 577 5561",
    "sg:postcode":"37920",
    "sg:province":"TN",
    "sg:tags":[
        "physician",
        "surgeon"
    ],
    "wof:name":"Free Medical Clinic Of America",
    "wof:placetype":"venue"
},
  "geometry": {"coordinates":[-83.87013399999999,35.92111],"type":"Point"}
}