{
  "type": "Feature",
  "properties": {
    "iso:country":"US",
    "sg:address":"36 Ball Park Rd",
    "sg:city":"Sewanee",
    "sg:classifiers":[
        {
            "category":"Retail",
            "subcategory":"Laundry & Dry Cleaning",
            "type":"Services"
        }
    ],
    "sg:phone":"+1 931 598 0116",
    "sg:postcode":"37375",
    "sg:province":"TN",
    "sg:tags":[
        "drycleaning",
        "plant",
        "cleaners"
    ],
    "wof:name":"Sewanne Cleaners",
    "wof:placetype":"venue"
},
  "geometry": {"coordinates":[-85.917683,35.193951],"type":"Point"}
}