{
  "type": "Feature",
  "properties": {
    "addr:full":"238 Morton Ave Nashville TN 37211",
    "addr:housenumber":"238",
    "addr:postcode":"37211",
    "addr:street":"Morton Ave",
    "iso:country":"US",
    "sg:address":"238 Morton Ave",
    "sg:city":"Nashville",
    "sg:classifiers":[
        {
            "category":"Home & Garden",
            "subcategory":"Building Materials",
            "type":"Retail Goods"
        }
    ],
    "sg:phone":"+1 615 400 7803",
    "sg:postcode":"37211",
    "sg:province":"TN",
    "sg:tags":[
        "stone"
    ],
    "wof:name":"Summerfield Stone",
    "wof:placetype":"venue"
},
  "geometry": {"coordinates":[-86.740995,36.106357],"type":"Point"}
}