{
  "type": "Feature",
  "properties": {
    "iso:country":"US",
    "sg:address":"806 University St",
    "sg:city":"Martin",
    "sg:classifiers":[
        {
            "category":"Restaurant",
            "type":"Food & Drink"
        }
    ],
    "sg:phone":"+1 731 588 2822",
    "sg:postcode":"38237",
    "sg:province":"TN",
    "wof:name":"Los Portales",
    "wof:placetype":"venue"
},
  "geometry": {"coordinates":[-88.872743,36.347605],"type":"Point"}
}