{
  "type": "Feature",
  "properties": {
    "addr:full":"100 W Broadway St Lenoir City TN 37771",
    "addr:housenumber":"100",
    "addr:postcode":"37771",
    "addr:street":"W Broadway St",
    "iso:country":"US",
    "sg:address":"100 W Broadway St",
    "sg:city":"Lenoir City",
    "sg:classifiers":[
        {
            "category":"Education",
            "subcategory":"Library",
            "type":"Public Place"
        }
    ],
    "sg:phone":"+1 865 986 3210",
    "sg:postcode":"37771",
    "sg:province":"TN",
    "wof:name":"Lenoir City Public Library",
    "wof:placetype":"venue"
},
  "geometry": {"coordinates":[-84.265745,35.791118],"type":"Point"}
}