{
  "type": "Feature",
  "properties": {
    "addr:full":"135 Brantley Dr Covington TN 38019",
    "addr:housenumber":"135",
    "addr:postcode":"38019",
    "addr:street":"Brantley Dr",
    "iso:country":"US",
    "sg:address":"135 Brantley Dr",
    "sg:city":"Covington",
    "sg:classifiers":[
        {
            "category":"Retail",
            "subcategory":"Repair Shop",
            "type":"Services"
        }
    ],
    "sg:phone":"+1 901 476 9068",
    "sg:postcode":"38019",
    "sg:province":"TN",
    "sg:tags":[
        "natural",
        "gas",
        "meter"
    ],
    "wof:name":"Sullivan Ntral Gas Measurement",
    "wof:placetype":"venue"
},
  "geometry": {"coordinates":[-89.58463,35.524353],"type":"Point"}
}