{
  "type": "Feature",
  "properties": {
    "addr:full":"1702 US Hwy 51 S Covington TN 38019",
    "addr:housenumber":"1702",
    "addr:postcode":"38019",
    "addr:street":"Us Hwy 51 S",
    "iso:country":"US",
    "sg:address":"1702 US Hwy 51 S",
    "sg:city":"Covington",
    "sg:classifiers":[
        {
            "category":"Personal",
            "subcategory":"Beauty Salon",
            "type":"Services"
        }
    ],
    "sg:phone":"+1 901 475 0077",
    "sg:postcode":"38019",
    "sg:province":"TN",
    "wof:name":"Jennifer's Beauty Salon",
    "wof:placetype":"venue"
},
  "geometry": {"coordinates":[-89.666737,35.54163],"type":"Point"}
}