{
  "type": "Feature",
  "properties": {
    "iso:country":"US",
    "sg:address":"6109 Vance Cir",
    "sg:city":"Chattanooga",
    "sg:classifiers":[
        {
            "category":"Wholesale",
            "subcategory":"Durable Goods & Equipment",
            "type":"Manufacturing & Wholesale Goods"
        }
    ],
    "sg:phone":"+1 423 892 1837",
    "sg:postcode":"37421",
    "sg:province":"TN",
    "wof:name":"Db Little Acoustics & Woodwork",
    "wof:placetype":"venue"
},
  "geometry": {"coordinates":[-85.188076,35.034674],"type":"Point"}
}