{
  "type": "Feature",
  "properties": {
    "addr:full":"5325 Nolensville Pike Nashville TN 37211",
    "addr:housenumber":"5325",
    "addr:postcode":"37211",
    "addr:street":"Nolensville Pike",
    "iso:country":"US",
    "sg:address":"5325 Nolensville Pike",
    "sg:city":"Nashville",
    "sg:classifiers":[
        {
            "category":"Organizations",
            "subcategory":"Religious Organization",
            "type":"Services"
        }
    ],
    "sg:phone":"+1 615 333 9979",
    "sg:postcode":"37211",
    "sg:province":"TN",
    "sg:tags":[
        "church"
    ],
    "sg:website":"www.usasungshin.org",
    "wof:name":"Korean Episcopal Chr",
    "wof:placetype":"venue"
},
  "geometry": {"coordinates":[-86.714488,36.051693],"type":"Point"}
}