{
  "type": "Feature",
  "properties": {
    "addr:full":"540 Brick Church Park Dr Nashville TN 37207",
    "addr:housenumber":"540",
    "addr:postcode":"37207",
    "addr:street":"Brick Church Park Dr",
    "iso:country":"US",
    "sg:address":"540 Brick Church Park Dr",
    "sg:city":"Nashville",
    "sg:classifiers":[
        {
            "category":"Professional",
            "subcategory":"Advertising",
            "type":"Services"
        }
    ],
    "sg:phone":"+1 615 227 1667",
    "sg:postcode":"37207",
    "sg:province":"TN",
    "sg:tags":[
        "mailing",
        "shipping"
    ],
    "wof:name":"Customize Business Svc",
    "wof:placetype":"venue"
},
  "geometry": {"coordinates":[-86.7859,36.224876],"type":"Point"}
}