{
  "type": "Feature",
  "properties": {
    "iso:country":"US",
    "sg:address":"259 Thomas Rd",
    "sg:city":"Benton",
    "sg:classifiers":[
        {
            "category":"Manufacturing",
            "subcategory":"Lumber",
            "type":"Manufacturing & Wholesale Goods"
        }
    ],
    "sg:phone":"+1 423 338 8969",
    "sg:postcode":"37307",
    "sg:province":"TN",
    "sg:tags":[
        "operation",
        "timber",
        "tract"
    ],
    "wof:name":"Ward Tree Service",
    "wof:placetype":"venue"
},
  "geometry": {"coordinates":[-84.686268,35.167491],"type":"Point"}
}