{
  "type": "Feature",
  "properties": {
    "iso:country":"US",
    "sg:address":"309 S Belmont St",
    "sg:city":"Johnson City",
    "sg:classifiers":[
        {
            "category":"Banks & Credit Unions",
            "subcategory":"Bank",
            "type":"Services"
        }
    ],
    "sg:phone":"+1 423 434 4631",
    "sg:postcode":"37604",
    "sg:province":"TN",
    "sg:tags":[
        "loan",
        "institution",
        "business"
    ],
    "wof:name":"Service Loan Company",
    "wof:placetype":"venue"
},
  "geometry": {"coordinates":[-82.364154,36.316792],"type":"Point"}
}