{
  "type": "Feature",
  "properties": {
    "iso:country":"US",
    "sg:address":"2940 Huntsville Hwy",
    "sg:city":"Fayetteville",
    "sg:classifiers":[
        {
            "category":"Utilities",
            "subcategory":"Fuel Oil & Lpg",
            "type":"Services"
        }
    ],
    "sg:phone":"+1 931 433 0073",
    "sg:postcode":"37334",
    "sg:province":"TN",
    "sg:tags":[
        "liquefied",
        "gas",
        "petroleum"
    ],
    "wof:name":"Country Gas & Appliances",
    "wof:placetype":"venue"
},
  "geometry": {"coordinates":[-86.57368200000001,35.05055],"type":"Point"}
}