{
  "type": "Feature",
  "properties": {
    "addr:full":"275 Howard Rd Puryear TN 38251",
    "addr:housenumber":"275",
    "addr:postcode":"38251",
    "addr:street":"Howard Rd",
    "iso:country":"US",
    "sg:address":"275 Howard Rd",
    "sg:city":"Puryear",
    "sg:classifiers":[
        {
            "category":"Real Estate",
            "subcategory":"Real Estate Operator",
            "type":"Services"
        }
    ],
    "sg:phone":"+1 731 247 5420",
    "sg:postcode":"38251",
    "sg:province":"TN",
    "sg:tags":[
        "property",
        "lessor"
    ],
    "wof:name":"J B Orr",
    "wof:placetype":"venue"
},
  "geometry": {"coordinates":[-88.33018199999999,36.456123],"type":"Point"}
}