{
  "type": "Feature",
  "properties": {
    "iso:country":"US",
    "sg:address":"203 E Cedar St",
    "sg:city":"Goodlettsville",
    "sg:classifiers":[
        {
            "category":"Retail",
            "subcategory":"Animal Services",
            "type":"Services"
        }
    ],
    "sg:phone":"+1 615 851 0022",
    "sg:postcode":"37072",
    "sg:province":"TN",
    "wof:name":"Paw Prints In Goodlettsville",
    "wof:placetype":"venue"
},
  "geometry": {"coordinates":[-86.709733,36.323951],"type":"Point"}
}