{
  "type": "Feature",
  "properties": {
    "iso:country":"US",
    "sg:address":"105 S Main St",
    "sg:city":"Greeneville",
    "sg:classifiers":[
        {
            "category":"Shopping",
            "subcategory":"Clothing, Apparel, & Fashions",
            "type":"Retail Goods"
        }
    ],
    "sg:phone":"+1 423 798 9000",
    "sg:postcode":"37743",
    "sg:province":"TN",
    "wof:name":"Splurge",
    "wof:placetype":"venue"
},
  "geometry": {"coordinates":[-82.83083600000001,36.163137],"type":"Point"}
}