{
  "type": "Feature",
  "properties": {
    "iso:country":"US",
    "sg:address":"1800 9th Ave N",
    "sg:city":"Nashville",
    "sg:classifiers":[
        {
            "category":"Education",
            "subcategory":"School",
            "type":"Public Place"
        }
    ],
    "sg:phone":"+1 615 291 6382",
    "sg:postcode":"37208",
    "sg:province":"TN",
    "sg:tags":[
        "elementary",
        "secondary"
    ],
    "wof:name":"Buena Vista Jones Paideia Mgnt",
    "wof:placetype":"venue"
},
  "geometry": {"coordinates":[-86.801841,36.181053],"type":"Point"}
}