{
  "type": "Feature",
  "properties": {
    "iso:country":"US",
    "sg:address":"12123 Armstrong Rd",
    "sg:city":"Soddy Daisy",
    "sg:classifiers":[
        {
            "category":"Manufacturing",
            "subcategory":"Lumber",
            "type":"Manufacturing & Wholesale Goods"
        }
    ],
    "sg:phone":"+1 423 332 6237",
    "sg:postcode":"37379",
    "sg:province":"TN",
    "sg:tags":[
        "forestry"
    ],
    "wof:name":"Tri State Forestry Consultants",
    "wof:placetype":"venue"
},
  "geometry": {"coordinates":[-85.100987,35.288288],"type":"Point"}
}