{
  "type": "Feature",
  "properties": {
    "iso:country":"US",
    "sg:address":"700 Main St",
    "sg:city":"Nashville",
    "sg:classifiers":[
        {
            "category":"Building & Trades",
            "subcategory":"Landscaping Services",
            "type":"Services"
        },
        {
            "category":"Building & Trades",
            "subcategory":"Pest Control",
            "type":"Services"
        }
    ],
    "sg:phone":"+1 615 309 4999",
    "sg:postcode":"37206",
    "sg:province":"TN",
    "sg:tags":[
        "lawn",
        "mothproofing",
        "maintenance"
    ],
    "wof:name":"Mcclouds Termite & Pest Control",
    "wof:placetype":"venue"
},
  "geometry": {"coordinates":[-86.76093299999999,36.174549],"type":"Point"}
}