{
  "type": "Feature",
  "properties": {
    "iso:country":"US",
    "sg:address":"4881 Canada Rd",
    "sg:city":"Arlington",
    "sg:classifiers":[
        {
            "category":"Retail",
            "subcategory":"Repair Shop",
            "type":"Services"
        }
    ],
    "sg:phone":"+1 901 386 7415",
    "sg:postcode":"38002",
    "sg:province":"TN",
    "wof:name":"Palmer Truck & Equipment Inc",
    "wof:placetype":"venue"
},
  "geometry": {"coordinates":[-89.747688,35.251107],"type":"Point"}
}