{
  "type": "Feature",
  "properties": {
    "iso:country":"US",
    "sg:address":"7644 Sagefield Dr",
    "sg:city":"Knoxville",
    "sg:classifiers":[
        {
            "category":"Building & Trades",
            "subcategory":"Construction",
            "type":"Services"
        }
    ],
    "sg:phone":"+1 865 577 4035",
    "sg:postcode":"37920",
    "sg:province":"TN",
    "sg:tags":[
        "house",
        "painter"
    ],
    "wof:name":"George A Harb & Son Painting",
    "wof:placetype":"venue"
},
  "geometry": {"coordinates":[-83.826915,35.911647],"type":"Point"}
}