{
  "type": "Feature",
  "properties": {
    "iso:country":"US",
    "sg:address":"189 Little Green St",
    "sg:city":"Nashville",
    "sg:classifiers":[
        {
            "category":"Autos & Motor Vehicles",
            "subcategory":"Automobile Sales",
            "type":"Retail Goods"
        }
    ],
    "sg:phone":"+1 615 726 6061",
    "sg:postcode":"37210",
    "sg:province":"TN",
    "sg:tags":[
        "car",
        "dealer"
    ],
    "wof:name":"Mr Cars",
    "wof:placetype":"venue"
},
  "geometry": {"coordinates":[-86.749167,36.152998],"type":"Point"}
}