{
  "type": "Feature",
  "properties": {
    "iso:country":"US",
    "sg:address":"2820 Dickerson Pike",
    "sg:city":"Nashville",
    "sg:classifiers":[
        {
            "category":"Travel",
            "subcategory":"Hotels & Motels",
            "type":"Entertainment"
        }
    ],
    "sg:phone":"+1 615 226 0545",
    "sg:postcode":"37207",
    "sg:province":"TN",
    "sg:tags":[
        "operation"
    ],
    "wof:name":"Colonial Court Motel",
    "wof:placetype":"venue"
},
  "geometry": {"coordinates":[-86.76255,36.219462],"type":"Point"}
}