{
  "type": "Feature",
  "properties": {
    "iso:country":"US",
    "sg:address":"6 E Madison Ave",
    "sg:city":"Athens",
    "sg:classifiers":[
        {
            "category":"Government",
            "subcategory":"Office",
            "type":"Public Place"
        }
    ],
    "sg:phone":"+1 423 745 2743",
    "sg:postcode":"37303",
    "sg:province":"TN",
    "sg:tags":[
        "county",
        "taxation"
    ],
    "wof:name":"Mc Minn Cnty Property Assessor",
    "wof:placetype":"venue"
},
  "geometry": {"coordinates":[-84.592637,35.442445],"type":"Point"}
}