{
  "type": "Feature",
  "properties": {
    "iso:country":"US",
    "sg:address":"4731 Adams Rd",
    "sg:city":"Hixson",
    "sg:classifiers":[
        {
            "category":"Manufacturing",
            "subcategory":"Glass & Minerals",
            "type":"Manufacturing & Wholesale Goods"
        }
    ],
    "sg:phone":"+1 423 870 5133",
    "sg:postcode":"37343",
    "sg:province":"TN",
    "sg:tags":[
        "ready",
        "concrete",
        "mfg"
    ],
    "wof:name":"M & M Ready Mix Concrete Inc",
    "wof:placetype":"venue"
},
  "geometry": {"coordinates":[-85.23342599999999,35.134205],"type":"Point"}
}