{
  "type": "Feature",
  "properties": {
    "addr:full":"1655 Gallatin Pike N Madison TN 37115",
    "addr:housenumber":"1655",
    "addr:postcode":"37115",
    "addr:street":"Gallatin Pike N",
    "iso:country":"US",
    "sg:address":"1655 Gallatin Pike N",
    "sg:city":"Madison",
    "sg:classifiers":[
        {
            "category":"Home & Garden",
            "subcategory":"Household Appliances",
            "type":"Retail Goods"
        }
    ],
    "sg:phone":"+1 615 425 2385",
    "sg:postcode":"37115",
    "sg:province":"TN",
    "sg:tags":[
        "machine",
        "sewing"
    ],
    "wof:name":"Sally Cheney's World Of Sewing",
    "wof:placetype":"venue"
},
  "geometry": {"coordinates":[-86.700067,36.295969],"type":"Point"}
}