{
  "type": "Feature",
  "properties": {
    "iso:country":"US",
    "sg:address":"4467 Black Mountain Rd",
    "sg:city":"Hartford",
    "sg:phone":"+1 423 487 3985",
    "sg:postcode":"37753",
    "sg:province":"TN",
    "sg:tags":[
        "farm",
        "tobacco"
    ],
    "wof:name":"Black Tilman",
    "wof:placetype":"venue"
},
  "geometry": {"coordinates":[-83.10695,35.823375],"type":"Point"}
}