{
  "type": "Feature",
  "properties": {
    "iso:country":"US",
    "sg:address":"50 State Hwy 210",
    "sg:city":"Dyersburg",
    "sg:classifiers":[
        {
            "category":"Freight",
            "type":"Transportation"
        }
    ],
    "sg:phone":"+1 731 287 7444",
    "sg:postcode":"38024",
    "sg:province":"TN",
    "sg:tags":[
        "commercial",
        "storage"
    ],
    "wof:name":"Affordable Space Ctr",
    "wof:placetype":"venue"
},
  "geometry": {"coordinates":[-89.392934,35.9845],"type":"Point"}
}