{
  "type": "Feature",
  "properties": {
    "iso:country":"US",
    "sg:address":"238 White Oak Valley Rd NW",
    "sg:city":"Cleveland",
    "sg:classifiers":[
        {
            "category":"Home & Garden",
            "subcategory":"Building Materials",
            "type":"Retail Goods"
        }
    ],
    "sg:phone":"+1 423 479 3736",
    "sg:postcode":"37353",
    "sg:province":"TN",
    "sg:tags":[
        "lumber",
        "other"
    ],
    "wof:name":"Calvin Withrow Lumber",
    "wof:placetype":"venue"
},
  "geometry": {"coordinates":[-84.96716600000001,35.178579],"type":"Point"}
}