{
  "type": "Feature",
  "properties": {
    "iso:country":"US",
    "sg:address":"2270 Ermine Dr",
    "sg:city":"Clarksville",
    "sg:classifiers":[
        {
            "category":"Real Estate",
            "subcategory":"Real Estate Operator",
            "type":"Services"
        }
    ],
    "sg:phone":"+1 931 648 6218",
    "sg:postcode":"37043",
    "sg:province":"TN",
    "sg:tags":[
        "building",
        "nonresidential"
    ],
    "wof:name":"Lane Lee Properties Inc",
    "wof:placetype":"venue"
},
  "geometry": {"coordinates":[-87.281193,36.506392],"type":"Point"}
}