{
  "type": "Feature",
  "properties": {
    "iso:country":"US",
    "sg:address":"2865 Kirby Rd",
    "sg:city":"Memphis",
    "sg:classifiers":[
        {
            "category":"Food & Beverages",
            "subcategory":"Liquor & Beverages",
            "type":"Retail Goods"
        }
    ],
    "sg:phone":"+1 901 756 1993",
    "sg:postcode":"38119",
    "sg:province":"TN",
    "sg:tags":[
        "wine"
    ],
    "wof:name":"Kirby Wine & Liquors",
    "wof:placetype":"venue"
},
  "geometry": {"coordinates":[-89.842579,35.071004],"type":"Point"}
}