{
  "type": "Feature",
  "properties": {
    "iso:country":"US",
    "sg:address":"101 S Church St",
    "sg:city":"Waverly",
    "sg:classifiers":[
        {
            "category":"Health Services",
            "subcategory":"Doctor",
            "type":"Services"
        }
    ],
    "sg:phone":"+1 931 296 5833",
    "sg:postcode":"37185",
    "sg:province":"TN",
    "sg:tags":[
        "clinic"
    ],
    "wof:name":"Memorial Clinic",
    "wof:placetype":"venue"
},
  "geometry": {"coordinates":[-87.794264,36.083191],"type":"Point"}
}