{
  "type": "Feature",
  "properties": {
    "addr:full":"257 M C Junkin Rd Tellico Plains TN 37385",
    "addr:housenumber":"257;c",
    "addr:postcode":"37385",
    "addr:street":"M;Junkin Rd",
    "iso:country":"US",
    "sg:address":"257 M C Junkin Rd",
    "sg:city":"Tellico Plains",
    "sg:classifiers":[
        {
            "category":"Building & Trades",
            "subcategory":"Plumbing",
            "type":"Services"
        }
    ],
    "sg:phone":"+1 423 261 2465",
    "sg:postcode":"37385",
    "sg:province":"TN",
    "sg:tags":[
        "conditioning",
        "air",
        "system",
        "contractor"
    ],
    "wof:name":"Dalton's Service Co",
    "wof:placetype":"venue"
},
  "geometry": {"coordinates":[-84.28691499999999,35.284969],"type":"Point"}
}