{
  "type": "Feature",
  "properties": {
    "iso:country":"US",
    "sg:address":"111 Sunshine Cir",
    "sg:city":"Elizabethton",
    "sg:classifiers":[
        {
            "category":"Building & Trades",
            "subcategory":"Landscaping Services",
            "type":"Services"
        }
    ],
    "sg:phone":"+1 423 543 5879",
    "sg:postcode":"37643",
    "sg:province":"TN",
    "sg:tags":[
        "lawn",
        "care"
    ],
    "wof:name":"Fraser Lawn Service",
    "wof:placetype":"venue"
},
  "geometry": {"coordinates":[-82.201795,36.319256],"type":"Point"}
}