{
  "type": "Feature",
  "properties": {
    "iso:country":"US",
    "sg:address":"124 Shockley Dr",
    "sg:city":"Hazel Green",
    "sg:classifiers":[
        {
            "category":"Professional",
            "type":"Services"
        }
    ],
    "sg:phone":"+1 256 431 2432",
    "sg:postcode":"35750",
    "sg:province":"TN",
    "wof:name":"E & S Solutions",
    "wof:placetype":"venue"
},
  "geometry": {"coordinates":[-86.553578,34.976782],"type":"Point"}
}