{
  "type": "Feature",
  "properties": {
    "iso:country":"US",
    "sg:address":"2180 Yum Yum Rd",
    "sg:city":"Somerville",
    "sg:classifiers":[
        {
            "category":"Freight",
            "type":"Transportation"
        }
    ],
    "sg:phone":"+1 901 465 9388",
    "sg:postcode":"38068",
    "sg:province":"TN",
    "sg:tags":[
        "hauling",
        "trucking"
    ],
    "wof:name":"JSW Corp",
    "wof:placetype":"venue"
},
  "geometry": {"coordinates":[-89.365202,35.314311],"type":"Point"}
}