{
  "type": "Feature",
  "properties": {
    "addr:full":"4083 Highway 411 Ocoee TN 37361",
    "addr:housenumber":"4083",
    "addr:postcode":"37361",
    "addr:street":"Highway 411",
    "iso:country":"US",
    "sg:address":"4083 Highway 411",
    "sg:city":"Ocoee",
    "sg:classifiers":[
        {
            "category":"Restaurant",
            "type":"Food & Drink"
        }
    ],
    "sg:menulink":"http://www.allmenus.com/tn/parksville/154982-hardees/menu/",
    "sg:phone":"+1 423 338 4083",
    "sg:postcode":"37361",
    "sg:province":"TN",
    "sg:tags":[
        "burger",
        "american"
    ],
    "wof:name":"Hardee's",
    "wof:placetype":"venue"
},
  "geometry": {"coordinates":[-84.71740800000001,35.128853],"type":"Point"}
}