{
  "type": "Feature",
  "properties": {
    "iso:country":"US",
    "sg:address":"2045 State Hwy 107",
    "sg:city":"Jonesborough",
    "sg:classifiers":[
        {
            "category":"Manufacturing",
            "subcategory":"Tools & Machinery",
            "type":"Manufacturing & Wholesale Goods"
        }
    ],
    "sg:phone":"+1 423 791 8377",
    "sg:postcode":"37659",
    "sg:province":"TN",
    "sg:tags":[
        "instrument",
        "mfg"
    ],
    "wof:name":"Surgical Energies Inc",
    "wof:placetype":"venue"
},
  "geometry": {"coordinates":[-82.566405,36.151429],"type":"Point"}
}