{
  "type": "Feature",
  "properties": {
    "iso:country":"US",
    "sg:address":"1328 Stair Ave NW",
    "sg:city":"Knoxville",
    "sg:classifiers":[
        {
            "category":"Organizations",
            "subcategory":"Religious Organization",
            "type":"Services"
        }
    ],
    "sg:phone":"+1 865 524 6200",
    "sg:postcode":"37921",
    "sg:province":"TN",
    "sg:tags":[
        "church"
    ],
    "wof:name":"Faith Independent Baptist Chur",
    "wof:placetype":"venue"
},
  "geometry": {"coordinates":[-83.946118,35.975433],"type":"Point"}
}