{
  "type": "Feature",
  "properties": {
    "iso:country":"US",
    "sg:address":"1833 W Broad St",
    "sg:city":"Cookeville",
    "sg:classifiers":[
        {
            "category":"Autos & Motor Vehicles",
            "subcategory":"Boat Sales",
            "type":"Retail Goods"
        }
    ],
    "sg:phone":"+1 931 528 5777",
    "sg:postcode":"38501",
    "sg:province":"TN",
    "sg:tags":[
        "equipment",
        "marine",
        "supply"
    ],
    "wof:name":"M & R Boat & Motor Repair",
    "wof:placetype":"venue"
},
  "geometry": {"coordinates":[-85.554817,36.174445],"type":"Point"}
}