{
  "type": "Feature",
  "properties": {
    "addr:full":"2550 E Morris Blvd Morristown TN 37813",
    "addr:housenumber":"2550",
    "addr:postcode":"37813",
    "addr:street":"E Morris Blvd",
    "iso:country":"US",
    "sg:address":"2550 E Morris Blvd",
    "sg:city":"Morristown",
    "sg:classifiers":[
        {
            "category":"Professional",
            "subcategory":"Accounting & Tax Preparation",
            "type":"Services"
        }
    ],
    "sg:phone":"+1 423 581 5333",
    "sg:postcode":"37813",
    "sg:province":"TN",
    "sg:tags":[
        "return",
        "filing"
    ],
    "wof:name":"H & R Block Tax Svc",
    "wof:placetype":"venue"
},
  "geometry": {"coordinates":[-83.261027,36.222691],"type":"Point"}
}