{
  "type": "Feature",
  "properties": {
    "addr:full":"1787 US Hwy 27 Dayton TN 37321",
    "addr:housenumber":"1787",
    "addr:postcode":"37321",
    "addr:street":"Us Hwy 27",
    "iso:country":"US",
    "sg:address":"1787 US Hwy 27",
    "sg:city":"Dayton",
    "sg:classifiers":[
        {
            "category":"Building & Trades",
            "subcategory":"Pest Control",
            "type":"Services"
        }
    ],
    "sg:phone":"+1 423 775 9989",
    "sg:postcode":"37321",
    "sg:province":"TN",
    "wof:name":"Scenicland Pest Control",
    "wof:placetype":"venue"
},
  "geometry": {"coordinates":[-85.010137,35.497509],"type":"Point"}
}