{
  "type": "Feature",
  "properties": {
    "iso:country":"US",
    "sg:address":"7301 Rotherwood Dr SW",
    "sg:city":"Knoxville",
    "sg:classifiers":[
        {
            "category":"Building & Trades",
            "subcategory":"Construction",
            "type":"Services"
        }
    ],
    "sg:phone":"+1 865 584 5152",
    "sg:postcode":"37919",
    "sg:province":"TN",
    "sg:tags":[
        "house"
    ],
    "wof:name":"Crowder Construction Inc",
    "wof:placetype":"venue"
},
  "geometry": {"coordinates":[-84.018733,35.915611],"type":"Point"}
}