{
  "type": "Feature",
  "properties": {
    "iso:country":"US",
    "sg:address":"116 N Northshore Dr",
    "sg:city":"Knoxville",
    "sg:classifiers":[
        {
            "category":"Personal",
            "subcategory":"Barber",
            "type":"Services"
        }
    ],
    "sg:phone":"+1 865 588 7227",
    "sg:postcode":"37919",
    "sg:province":"TN",
    "wof:name":"Belle Cook's",
    "wof:placetype":"venue"
},
  "geometry": {"coordinates":[-84.002496,35.933887],"type":"Point"}
}