{
  "type": "Feature",
  "properties": {
    "addr:full":"248 Lakeview Dr SE Cleveland TN 37323",
    "addr:housenumber":"248",
    "addr:postcode":"37323",
    "addr:street":"Lakeview Dr Se",
    "iso:country":"US",
    "sg:address":"248 Lakeview Dr SE",
    "sg:city":"Cleveland",
    "sg:classifiers":[
        {
            "category":"Building & Trades",
            "subcategory":"Plumbing",
            "type":"Services"
        }
    ],
    "sg:phone":"+1 423 478 7778",
    "sg:postcode":"37323",
    "sg:province":"TN",
    "sg:tags":[
        "conditioning",
        "air",
        "system",
        "contractor"
    ],
    "wof:name":"Central Heating & Air Co",
    "wof:placetype":"venue"
},
  "geometry": {"coordinates":[-84.846834,35.140631],"type":"Point"}
}