{
  "type": "Feature",
  "properties": {
    "iso:country":"US",
    "sg:address":"3306 Overton Crossing St",
    "sg:city":"Memphis",
    "sg:classifiers":[
        {
            "category":"Personal",
            "subcategory":"Beauty Salon",
            "type":"Services"
        }
    ],
    "sg:phone":"+1 901 353 0346",
    "sg:postcode":"38127",
    "sg:province":"TN",
    "sg:tags":[
        "hair",
        "stylist"
    ],
    "wof:name":"X-Quizite Essentials",
    "wof:placetype":"venue"
},
  "geometry": {"coordinates":[-89.993965,35.216724],"type":"Point"}
}