{
  "type": "Feature",
  "properties": {
    "addr:full":"2833 Western Ave Knoxville TN 37921",
    "addr:housenumber":"2833",
    "addr:postcode":"37921",
    "addr:street":"Western Ave",
    "iso:country":"US",
    "sg:address":"2833 Western Ave",
    "sg:city":"Knoxville",
    "sg:classifiers":[
        {
            "category":"Restaurant",
            "type":"Food & Drink"
        },
        {
            "category":"Bars & Pubs",
            "type":"Food & Drink"
        }
    ],
    "sg:phone":"+1 865 673 3050",
    "sg:postcode":"37921",
    "sg:province":"TN",
    "sg:tags":[
        "eating"
    ],
    "wof:name":"Ronnie's Bar & Grill",
    "wof:placetype":"venue"
},
  "geometry": {"coordinates":[-83.96226299999999,35.975388],"type":"Point"}
}