{
  "type": "Feature",
  "properties": {
    "iso:country":"US",
    "sg:address":"174 Neely St",
    "sg:city":"Collierville",
    "sg:classifiers":[
        {
            "category":"Building & Trades",
            "subcategory":"Construction",
            "type":"Services"
        }
    ],
    "sg:phone":"+1 901 853 9979",
    "sg:postcode":"38017",
    "sg:province":"TN",
    "sg:tags":[
        "concrete",
        "contractor"
    ],
    "wof:name":"Renegade Gunite Co",
    "wof:placetype":"venue"
},
  "geometry": {"coordinates":[-89.66259100000001,35.04103],"type":"Point"}
}