{
  "type": "Feature",
  "properties": {
    "addr:full":"2021 N Highland Ave Jackson TN 38305",
    "addr:housenumber":"2021",
    "addr:postcode":"38305",
    "addr:street":"N Highland Ave",
    "iso:country":"US",
    "sg:address":"2021 N Highland Ave",
    "sg:city":"Jackson",
    "sg:classifiers":[
        {
            "category":"Retail",
            "subcategory":"Portrait Studio",
            "type":"Services"
        }
    ],
    "sg:phone":"+1 731 664 1467",
    "sg:postcode":"38305",
    "sg:province":"TN",
    "wof:name":"Sears Portrait Studio",
    "wof:placetype":"venue"
},
  "geometry": {"coordinates":[-88.828042,35.655954],"type":"Point"}
}