{
  "type": "Feature",
  "properties": {
    "addr:full":"4790 Waterlevel Hwy Cleveland TN 37323",
    "addr:housenumber":"4790",
    "addr:postcode":"37323",
    "addr:street":"Waterlevel Hwy",
    "iso:country":"US",
    "sg:address":"4790 Waterlevel Hwy",
    "sg:city":"Cleveland",
    "sg:classifiers":[
        {
            "category":"Autos & Motor Vehicles",
            "subcategory":"Automobile Sales",
            "type":"Retail Goods"
        }
    ],
    "sg:phone":"+1 423 479 9081",
    "sg:postcode":"37323",
    "sg:province":"TN",
    "sg:tags":[
        "car",
        "dealer"
    ],
    "wof:name":"Randy Goins Used Cars",
    "wof:placetype":"venue"
},
  "geometry": {"coordinates":[-84.80306,35.143214],"type":"Point"}
}