{
  "type": "Feature",
  "properties": {
    "iso:country":"US",
    "sg:address":"14380 Central Pike",
    "sg:city":"Mount Juliet",
    "sg:classifiers":[
        {
            "category":"Building & Trades",
            "subcategory":"Construction",
            "type":"Services"
        }
    ],
    "sg:phone":"+1 615 453 0042",
    "sg:postcode":"37122",
    "sg:province":"TN",
    "sg:tags":[
        "floor",
        "laying",
        "contractor"
    ],
    "wof:name":"Als Hardwood & Laminate",
    "wof:placetype":"venue"
},
  "geometry": {"coordinates":[-86.413534,36.134082],"type":"Point"}
}