{
  "type": "Feature",
  "properties": {
    "iso:country":"US",
    "sg:address":"1720 Old Fort Pkwy",
    "sg:city":"Murfreesboro",
    "sg:classifiers":[
        {
            "category":"Shopping",
            "subcategory":"Hobbies, Toys, & Games",
            "type":"Retail Goods"
        }
    ],
    "sg:phone":"+1 615 907 2954",
    "sg:postcode":"37129",
    "sg:province":"TN",
    "wof:name":"Kb Toys",
    "wof:placetype":"venue"
},
  "geometry": {"coordinates":[-86.428973,35.845833],"type":"Point"}
}