{
  "type": "Feature",
  "properties": {
    "iso:country":"US",
    "sg:address":"9450 S Northshore Dr",
    "sg:city":"Knoxville",
    "sg:classifiers":[
        {
            "category":"Retail",
            "subcategory":"Veterinary Services",
            "type":"Services"
        }
    ],
    "sg:phone":"+1 865 560 0480",
    "sg:postcode":"37922",
    "sg:province":"TN",
    "sg:tags":[
        "hospital",
        "animal"
    ],
    "wof:name":"My Pets Animal Hospital",
    "wof:placetype":"venue"
},
  "geometry": {"coordinates":[-84.065567,35.862644],"type":"Point"}
}