{
  "type": "Feature",
  "properties": {
    "iso:country":"US",
    "sg:address":"212 Knoxville Ave",
    "sg:city":"Lebanon",
    "sg:classifiers":[
        {
            "category":"Wholesale",
            "subcategory":"Scrap",
            "type":"Manufacturing & Wholesale Goods"
        }
    ],
    "sg:phone":"+1 615 443 2386",
    "sg:postcode":"37087",
    "sg:province":"TN",
    "sg:tags":[
        "oil"
    ],
    "wof:name":"Continental Oil",
    "wof:placetype":"venue"
},
  "geometry": {"coordinates":[-86.29009600000001,36.201458],"type":"Point"}
}