{
  "type": "Feature",
  "properties": {
    "iso:country":"US",
    "sg:address":"11200 Kingston Pike",
    "sg:city":"Knoxville",
    "sg:classifiers":[
        {
            "category":"Banks & Credit Unions",
            "subcategory":"Bank",
            "type":"Services"
        },
        {
            "category":"Banks & Credit Unions",
            "subcategory":"Financial Services",
            "type":"Services"
        }
    ],
    "sg:phone":"+1 865 675 9444",
    "sg:postcode":"37934",
    "sg:province":"TN",
    "sg:tags":[
        "loan"
    ],
    "sg:website":"http://www.tnbank.net",
    "wof:name":"TNBank",
    "wof:placetype":"venue"
},
  "geometry": {"coordinates":[-84.153458,35.884418],"type":"Point"}
}