{
  "type": "Feature",
  "properties": {
    "iso:country":"US",
    "sg:address":"5130 Stage Rd",
    "sg:city":"Memphis",
    "sg:classifiers":[
        {
            "category":"Health Services",
            "subcategory":"Medical Lab",
            "type":"Services"
        }
    ],
    "sg:phone":"+1 901 385 2636",
    "sg:postcode":"38134",
    "sg:province":"TN",
    "sg:tags":[
        "laboratory"
    ],
    "wof:name":"HealthSouth",
    "wof:placetype":"venue"
},
  "geometry": {"coordinates":[-89.891813,35.206879],"type":"Point"}
}