{
  "type": "Feature",
  "properties": {
    "iso:country":"US",
    "sg:address":"134 Sylvis Rd",
    "sg:city":"Dickson",
    "sg:classifiers":[
        {
            "category":"Social Services",
            "subcategory":"Child Care",
            "type":"Services"
        }
    ],
    "sg:phone":"+1 615 446 2334",
    "sg:postcode":"37055",
    "sg:province":"TN",
    "sg:tags":[
        "day"
    ],
    "wof:name":"Care Day",
    "wof:placetype":"venue"
},
  "geometry": {"coordinates":[-87.370262,36.107109],"type":"Point"}
}