{
  "type": "Feature",
  "properties": {
    "iso:country":"US",
    "sg:address":"209 Knoxville Ave",
    "sg:city":"Lebanon",
    "sg:phone":"+1 615 453 1081",
    "sg:postcode":"37087",
    "sg:province":"TN",
    "sg:tags":[
        "gas"
    ],
    "wof:name":"Quality Propane Gas Inc",
    "wof:placetype":"venue"
},
  "geometry": {"coordinates":[-86.290108,36.20161],"type":"Point"}
}