{
  "type": "Feature",
  "properties": {
    "addr:full":"523 Lake Rd Dyersburg TN 38024",
    "addr:housenumber":"523",
    "addr:postcode":"38024",
    "addr:street":"Lake Rd",
    "iso:country":"US",
    "sg:address":"523 Lake Rd",
    "sg:city":"Dyersburg",
    "sg:classifiers":[
        {
            "category":"Personal",
            "subcategory":"Beauty Salon",
            "type":"Services"
        },
        {
            "category":"Personal",
            "subcategory":"Day Spa",
            "type":"Services"
        }
    ],
    "sg:phone":"+1 731 286 1986",
    "sg:postcode":"38024",
    "sg:province":"TN",
    "sg:website":"http://www.tranquilitysalonanspa.com",
    "wof:name":"Tranquility Salon & Spa",
    "wof:placetype":"venue"
},
  "geometry": {"coordinates":[-89.393259,36.0372],"type":"Point"}
}