{
  "type": "Feature",
  "properties": {
    "addr:full":"8920 Dave Thomas Ln Baxter TN 38544",
    "addr:postcode":"8920;38544",
    "addr:street":"Dave Thomas Ln",
    "iso:country":"US",
    "sg:address":"8920 Dave Thomas Ln",
    "sg:city":"Baxter",
    "sg:classifiers":[
        {
            "category":"Real Estate",
            "subcategory":"Surveying",
            "type":"Services"
        }
    ],
    "sg:phone":"+1 931 858 1425",
    "sg:postcode":"38544",
    "sg:province":"TN",
    "wof:name":"Helton/Associates",
    "wof:placetype":"venue"
},
  "geometry": {"coordinates":[-85.655832,36.089776],"type":"Point"}
}