{
  "type": "Feature",
  "properties": {
    "iso:country":"US",
    "sg:address":"3068 S Perkins Rd",
    "sg:city":"Memphis",
    "sg:classifiers":[
        {
            "category":"Restaurant",
            "type":"Food & Drink"
        }
    ],
    "sg:menulink":"http://www.allmenus.com/tn/memphis/201783-mcdonalds/menu/",
    "sg:phone":"+1 901 365 7570",
    "sg:postcode":"38118",
    "sg:province":"TN",
    "sg:tags":[
        "burger",
        "american"
    ],
    "wof:name":"McDonald's",
    "wof:placetype":"venue"
},
  "geometry": {"coordinates":[-89.905148,35.064969],"type":"Point"}
}