{
  "type": "Feature",
  "properties": {
    "addr:full":"1828 Old Murfreesboro Pike Nashville TN 37217",
    "addr:housenumber":"1828",
    "addr:postcode":"37217",
    "addr:street":"Old Murfreesboro Pike",
    "iso:country":"US",
    "sg:address":"1828 Old Murfreesboro Pike",
    "sg:city":"Nashville",
    "sg:classifiers":[
        {
            "category":"Social Services",
            "subcategory":"Child Care",
            "type":"Services"
        }
    ],
    "sg:phone":"+1 615 361 5540",
    "sg:postcode":"37217",
    "sg:province":"TN",
    "wof:name":"Enfants' House Daycare",
    "wof:placetype":"venue"
},
  "geometry": {"coordinates":[-86.666478,36.103628],"type":"Point"}
}