{
  "type": "Feature",
  "properties": {
    "addr:full":"508 W Main St Franklin TN 37064",
    "addr:housenumber":"508",
    "addr:postcode":"37064",
    "addr:street":"W Main St",
    "iso:country":"US",
    "sg:address":"508 W Main St",
    "sg:city":"Franklin",
    "sg:classifiers":[
        {
            "category":"Government",
            "subcategory":"Fire Station",
            "type":"Public Place"
        }
    ],
    "sg:phone":"+1 615 790 5821",
    "sg:postcode":"37064",
    "sg:province":"TN",
    "sg:tags":[
        "county",
        "protection"
    ],
    "wof:name":"Williamson County Rescue Squad",
    "wof:placetype":"venue"
},
  "geometry": {"coordinates":[-86.871696,35.923969],"type":"Point"}
}