{
  "type": "Feature",
  "properties": {
    "addr:full":"1271 Sunvalley Cove Memphis TN 38109",
    "addr:housenumber":"1271",
    "addr:postcode":"38109",
    "addr:street":"Sunvalley Cove",
    "iso:country":"US",
    "sg:address":"1271 Sunvalley Cove",
    "sg:city":"Memphis",
    "sg:classifiers":[
        {
            "category":"Professional",
            "subcategory":"Business Services",
            "type":"Services"
        }
    ],
    "sg:phone":"+1 901 785 3197",
    "sg:postcode":"38109",
    "sg:province":"TN",
    "wof:name":"Lewis Marketing",
    "wof:placetype":"venue"
},
  "geometry": {"coordinates":[-90.10593299999999,35.023213],"type":"Point"}
}