{
  "type": "Feature",
  "properties": {
    "iso:country":"US",
    "sg:address":"492 Lewis Rd",
    "sg:city":"Mc Minnville",
    "sg:classifiers":[
        {
            "category":"Shopping",
            "subcategory":"Gifts & Souvenirs",
            "type":"Retail Goods"
        }
    ],
    "sg:phone":"+1 931 815 2716",
    "sg:postcode":"37110",
    "sg:province":"TN",
    "sg:tags":[
        "shop"
    ],
    "wof:name":"Good Vibrations Adult Nvlts",
    "wof:placetype":"venue"
},
  "geometry": {"coordinates":[-85.63765100000001,35.606316],"type":"Point"}
}