{
  "type": "Feature",
  "properties": {
    "addr:full":"1 Northgate Park Chattanooga TN 37415",
    "addr:housenumber":"1",
    "addr:postcode":"37415",
    "addr:street":"Northgate",
    "iso:country":"US",
    "sg:address":"1 Northgate Park",
    "sg:city":"Chattanooga",
    "sg:classifiers":[
        {
            "category":"Banks & Credit Unions",
            "subcategory":"Bank",
            "type":"Services"
        }
    ],
    "sg:phone":"+1 423 634 2204",
    "sg:postcode":"37415",
    "sg:province":"TN",
    "wof:name":"Regions Bank",
    "wof:placetype":"venue"
},
  "geometry": {"coordinates":[-85.237217,35.133289],"type":"Point"}
}