{
  "type": "Feature",
  "properties": {
    "iso:country":"US",
    "sg:address":"49 Music Sq E",
    "sg:city":"Nashville",
    "sg:classifiers":[
        {
            "category":"Professional",
            "subcategory":"Computer Services",
            "type":"Services"
        }
    ],
    "sg:phone":"+1 615 514 0326",
    "sg:postcode":"37203",
    "sg:province":"TN",
    "sg:tags":[
        "processing",
        "datum"
    ],
    "wof:name":"First Data Corp",
    "wof:placetype":"venue"
},
  "geometry": {"coordinates":[-86.792231,36.148384],"type":"Point"}
}