{
  "type": "Feature",
  "properties": {
    "iso:country":"US",
    "sg:address":"1509 Robinson Rd",
    "sg:city":"Old Hickory",
    "sg:classifiers":[
        {
            "category":"Health Services",
            "subcategory":"Doctor",
            "type":"Services"
        }
    ],
    "sg:phone":"+1 615 847 3530",
    "sg:postcode":"37138",
    "sg:province":"TN",
    "wof:name":"William O White Debra W Jones",
    "wof:placetype":"venue"
},
  "geometry": {"coordinates":[-86.65314600000001,36.255371],"type":"Point"}
}