{
  "type": "Feature",
  "properties": {
    "iso:country":"US",
    "sg:address":"801 Dominican Dr",
    "sg:city":"Nashville",
    "sg:classifiers":[
        {
            "category":"Organizations",
            "subcategory":"Religious Organization",
            "type":"Services"
        }
    ],
    "sg:phone":"+1 615 256 5486",
    "sg:postcode":"37228",
    "sg:province":"TN",
    "sg:tags":[
        "monastery",
        "convent"
    ],
    "sg:website":"www.nashvilledominican.org",
    "wof:name":"St Cecilia Motherhouse",
    "wof:placetype":"venue"
},
  "geometry": {"coordinates":[-86.802376,36.186912],"type":"Point"}
}