{
  "type": "Feature",
  "properties": {
    "addr:full":"28353 Lambert Rd Ardmore AL 35739",
    "addr:housenumber":"28353",
    "addr:postcode":"35739",
    "addr:street":"Lambert Rd",
    "iso:country":"US",
    "sg:address":"28353 Lambert Rd",
    "sg:city":"Ardmore",
    "sg:classifiers":[
        {
            "category":"Building & Trades",
            "subcategory":"Electrical",
            "type":"Services"
        }
    ],
    "sg:phone":"+1 256 423 6542",
    "sg:postcode":"35739",
    "sg:province":"AL",
    "sg:tags":[
        "electrical",
        "contractor"
    ],
    "wof:name":"Dixie Electric LLC",
    "wof:placetype":"venue"
},
  "geometry": {"coordinates":[-86.83747700000001,34.967808],"type":"Point"}
}