{
  "type": "Feature",
  "properties": {
    "iso:country":"US",
    "sg:address":"620 Snapps Ferry Rd",
    "sg:city":"Kingsport",
    "sg:classifiers":[
        {
            "category":"School Buses",
            "type":"Transportation"
        }
    ],
    "sg:phone":"+1 423 349 4914",
    "sg:postcode":"37663",
    "sg:province":"TN",
    "wof:name":"Lane Transportation Company",
    "wof:placetype":"venue"
},
  "geometry": {"coordinates":[-82.557862,36.441816],"type":"Point"}
}