{
  "type": "Feature",
  "properties": {
    "iso:country":"US",
    "sg:address":"9303 Rockvale Rd",
    "sg:city":"Rockvale",
    "sg:classifiers":[
        {
            "category":"Organizations",
            "subcategory":"Religious Organization",
            "type":"Services"
        }
    ],
    "sg:phone":"+1 615 274 2731",
    "sg:postcode":"37153",
    "sg:province":"TN",
    "wof:name":"Rockvale Church Of Christ",
    "wof:placetype":"venue"
},
  "geometry": {"coordinates":[-86.543834,35.750819],"type":"Point"}
}