{
  "type": "Feature",
  "properties": {
    "addr:full":"713 Hwy 76 White House TN 37188",
    "addr:housenumber":"713",
    "addr:postcode":"37188",
    "addr:street":"Hwy 76",
    "iso:country":"US",
    "sg:address":"713 Hwy 76",
    "sg:city":"White House",
    "sg:classifiers":[
        {
            "category":"Food & Beverages",
            "subcategory":"Groceries & Convenience Stores",
            "type":"Retail Goods"
        }
    ],
    "sg:phone":"+1 615 672 7912",
    "sg:postcode":"37188",
    "sg:province":"TN",
    "wof:name":"Keystop Of White House",
    "wof:placetype":"venue"
},
  "geometry": {"coordinates":[-86.674353,36.469532],"type":"Point"}
}