{
  "type": "Feature",
  "properties": {
    "addr:full":"522 Rosedale Ave Covington TN 38019",
    "addr:housenumber":"522",
    "addr:postcode":"38019",
    "addr:street":"Rosedale Ave",
    "iso:country":"US",
    "sg:address":"522 Rosedale Ave",
    "sg:city":"Covington",
    "sg:classifiers":[
        {
            "category":"Building & Trades",
            "subcategory":"Landscaping Services",
            "type":"Services"
        }
    ],
    "sg:phone":"+1 901 476 5462",
    "sg:postcode":"38019",
    "sg:province":"TN",
    "wof:name":"Topps Tree Trimming LLC",
    "wof:placetype":"venue"
},
  "geometry": {"coordinates":[-89.650503,35.55237],"type":"Point"}
}