{
  "type": "Feature",
  "properties": {
    "addr:full":"3569 Hickory Hill Rd Memphis TN 38115",
    "addr:housenumber":"3569",
    "addr:postcode":"38115",
    "addr:street":"Hickory Hill Rd",
    "iso:country":"US",
    "sg:address":"3569 Hickory Hill Rd",
    "sg:city":"Memphis",
    "sg:classifiers":[
        {
            "category":"Recreation",
            "type":"Entertainment"
        }
    ],
    "sg:phone":"+1 901 205 1800",
    "sg:postcode":"38115",
    "sg:province":"TN",
    "wof:name":"Taekwondo University",
    "wof:placetype":"venue"
},
  "geometry": {"coordinates":[-89.86644,35.050566],"type":"Point"}
}