{
  "type": "Feature",
  "properties": {
    "addr:full":"1191 Norma Aly Memphis TN 38109",
    "addr:housenumber":"1191",
    "addr:postcode":"38109",
    "addr:street":"Norma Aly",
    "iso:country":"US",
    "sg:address":"1191 Norma Aly",
    "sg:city":"Memphis",
    "sg:classifiers":[
        {
            "category":"Transit Center",
            "subcategory":"Freight",
            "type":"Transportation"
        },
        {
            "category":"Freight",
            "type":"Transportation"
        }
    ],
    "sg:phone":"+1 901 785 9553",
    "sg:postcode":"38109",
    "sg:province":"TN",
    "sg:tags":[
        "local",
        "trucking-motor",
        "trucking"
    ],
    "wof:name":"Robinson Trucking",
    "wof:placetype":"venue"
},
  "geometry": {"coordinates":[-90.103656,35.00223],"type":"Point"}
}