{
  "type": "Feature",
  "properties": {
    "iso:country":"US",
    "sg:address":"311 Butler Dr",
    "sg:city":"Murfreesboro",
    "sg:classifiers":[
        {
            "category":"Organizations",
            "subcategory":"Professional Association",
            "type":"Services"
        }
    ],
    "sg:phone":"+1 615 893 2242",
    "sg:postcode":"37127",
    "sg:province":"TN",
    "sg:tags":[
        "business"
    ],
    "wof:name":"Middle Tenn Assn of Rltors Inc",
    "wof:placetype":"venue"
},
  "geometry": {"coordinates":[-86.386217,35.801951],"type":"Point"}
}