{
  "type": "Feature",
  "properties": {
    "iso:country":"US",
    "sg:address":"147 Public Sq",
    "sg:city":"Lebanon",
    "sg:classifiers":[
        {
            "category":"Shopping",
            "subcategory":"Gifts & Souvenirs",
            "type":"Retail Goods"
        }
    ],
    "sg:phone":"+1 615 443 4996",
    "sg:postcode":"37087",
    "sg:province":"TN",
    "wof:name":"Palm Court",
    "wof:placetype":"venue"
},
  "geometry": {"coordinates":[-86.290988,36.207763],"type":"Point"}
}