{
  "type": "Feature",
  "properties": {
    "iso:country":"US",
    "sg:address":"227 Dickson Ave",
    "sg:city":"Dickson",
    "sg:classifiers":[
        {
            "category":"Organizations",
            "subcategory":"Religious Organization",
            "type":"Services"
        }
    ],
    "sg:phone":"+1 615 740 9882",
    "sg:postcode":"37055",
    "sg:province":"TN",
    "sg:tags":[
        "church"
    ],
    "wof:name":"Oasis Family Worship Ctr",
    "wof:placetype":"venue"
},
  "geometry": {"coordinates":[-87.39932,36.082735],"type":"Point"}
}