{
  "type": "Feature",
  "properties": {
    "addr:full":"80 Harts Bridge Rd W Jackson TN 38301",
    "addr:housenumber":"80",
    "addr:postcode":"38301",
    "addr:street":"Harts Bridge Rd W",
    "iso:country":"US",
    "sg:address":"80 Harts Bridge Rd W",
    "sg:city":"Jackson",
    "sg:classifiers":[
        {
            "category":"Freight",
            "type":"Transportation"
        }
    ],
    "sg:phone":"+1 731 427 7678",
    "sg:postcode":"38301",
    "sg:province":"TN",
    "sg:tags":[
        "commercial",
        "storage"
    ],
    "wof:name":"Stor-Ur-Stuf Storage",
    "wof:placetype":"venue"
},
  "geometry": {"coordinates":[-88.820719,35.569622],"type":"Point"}
}