{
  "type": "Feature",
  "properties": {
    "iso:country":"US",
    "sg:address":"6730 Todd Ln",
    "sg:city":"Knoxville",
    "sg:classifiers":[
        {
            "category":"Local Transit",
            "type":"Transportation"
        }
    ],
    "sg:phone":"+1 865 670 9777",
    "sg:postcode":"37921",
    "sg:province":"TN",
    "sg:tags":[
        "limousine"
    ],
    "wof:name":"Great Impressions Limo Svc",
    "wof:placetype":"venue"
},
  "geometry": {"coordinates":[-84.03805699999999,35.994387],"type":"Point"}
}