{
  "type": "Feature",
  "properties": {
    "iso:country":"US",
    "sg:address":"504 Hillwood St",
    "sg:city":"Kenton",
    "sg:classifiers":[
        {
            "category":"Farming",
            "subcategory":"Farm",
            "type":"Manufacturing & Wholesale Goods"
        }
    ],
    "sg:phone":"+1 731 749 5900",
    "sg:postcode":"38233",
    "sg:province":"TN",
    "sg:tags":[
        "crop",
        "general"
    ],
    "wof:name":"Fields Farms",
    "wof:placetype":"venue"
},
  "geometry": {"coordinates":[-89.01237999999999,36.199067],"type":"Point"}
}