{
  "type": "Feature",
  "properties": {
    "iso:country":"US",
    "sg:address":"425 W Court St",
    "sg:city":"Dyersburg",
    "sg:classifiers":[
        {
            "category":"Government",
            "subcategory":"Office",
            "type":"Public Place"
        }
    ],
    "sg:phone":"+1 731 288 2542",
    "sg:postcode":"38024",
    "sg:province":"TN",
    "sg:tags":[
        "village"
    ],
    "wof:name":"Dyersburg Property Taxes",
    "wof:placetype":"venue"
},
  "geometry": {"coordinates":[-89.390366,36.033186],"type":"Point"}
}