{
  "type": "Feature",
  "properties": {
    "addr:full":"128 Hwy 75 Blountville TN 37617",
    "addr:housenumber":"128",
    "addr:postcode":"37617",
    "addr:street":"Hwy 75",
    "iso:country":"US",
    "sg:address":"128 Hwy 75",
    "sg:city":"Blountville",
    "sg:classifiers":[
        {
            "category":"Wholesale",
            "subcategory":"Electrical",
            "type":"Manufacturing & Wholesale Goods"
        }
    ],
    "sg:phone":"+1 423 354 0455",
    "sg:postcode":"37617",
    "sg:province":"TN",
    "sg:tags":[
        "electric",
        "motor"
    ],
    "wof:name":"S W Svc",
    "wof:placetype":"venue"
},
  "geometry": {"coordinates":[-82.33631200000001,36.527931],"type":"Point"}
}