{
  "type": "Feature",
  "properties": {
    "iso:country":"US",
    "sg:address":"1003 Due West Valley Dr",
    "sg:city":"Madison",
    "sg:classifiers":[
        {
            "category":"Building & Trades",
            "subcategory":"Plumbing",
            "type":"Services"
        }
    ],
    "sg:phone":"+1 615 865 2766",
    "sg:postcode":"37115",
    "sg:province":"TN",
    "sg:tags":[
        "product",
        "management",
        "energy",
        "system"
    ],
    "wof:name":"Value Energy Corp",
    "wof:placetype":"venue"
},
  "geometry": {"coordinates":[-86.75051499999999,36.254439],"type":"Point"}
}