{
  "type": "Feature",
  "properties": {
    "addr:full":"142 Heritage Park Dr Murfreesboro TN 37129",
    "addr:housenumber":"142",
    "addr:postcode":"37129",
    "addr:street":"Heritage Park Dr",
    "iso:country":"US",
    "sg:address":"142 Heritage Park Dr",
    "sg:city":"Murfreesboro",
    "sg:classifiers":[
        {
            "category":"Building & Trades",
            "subcategory":"Construction",
            "type":"Services"
        }
    ],
    "sg:phone":"+1 615 849 1706",
    "sg:postcode":"37129",
    "sg:province":"TN",
    "sg:tags":[
        "home",
        "builder"
    ],
    "wof:name":"Walker Homes LLC",
    "wof:placetype":"venue"
},
  "geometry": {"coordinates":[-86.386876,35.873927],"type":"Point"}
}