{
  "type": "Feature",
  "properties": {
    "iso:country":"US",
    "sg:address":"405 Tivoli Trl",
    "sg:city":"Springfield",
    "sg:classifiers":[
        {
            "category":"Organizations",
            "subcategory":"Religious Organization",
            "type":"Services"
        }
    ],
    "sg:phone":"+1 615 384 2556",
    "sg:postcode":"37172",
    "sg:province":"TN",
    "sg:tags":[
        "church"
    ],
    "wof:name":"Bethel Apostolic Temple",
    "wof:placetype":"venue"
},
  "geometry": {"coordinates":[-86.8784,36.48343],"type":"Point"}
}