{
  "type": "Feature",
  "properties": {
    "iso:country":"US",
    "sg:address":"148 Belle Forest Cir",
    "sg:city":"Nashville",
    "sg:classifiers":[
        {
            "category":"Personal",
            "subcategory":"Beauty Salon",
            "type":"Services"
        }
    ],
    "sg:phone":"+1 615 662 9180",
    "sg:postcode":"37221",
    "sg:province":"TN",
    "sg:tags":[
        "shop"
    ],
    "wof:name":"Musical Shears",
    "wof:placetype":"venue"
},
  "geometry": {"coordinates":[-86.922997,36.076459],"type":"Point"}
}