{
  "type": "Feature",
  "properties": {
    "iso:country":"US",
    "sg:address":"679 Belle Watley Ln",
    "sg:city":"Collierville",
    "sg:classifiers":[
        {
            "category":"Building & Trades",
            "subcategory":"Construction",
            "type":"Services"
        }
    ],
    "sg:phone":"+1 901 861 0064",
    "sg:postcode":"38017",
    "sg:province":"TN",
    "sg:tags":[
        "paving",
        "contractor"
    ],
    "wof:name":"Tri-State Paving Inc",
    "wof:placetype":"venue"
},
  "geometry": {"coordinates":[-89.64269,35.064993],"type":"Point"}
}