{
  "type": "Feature",
  "properties": {
    "addr:full":"209 Broken Arrow Pt Kingston TN 37763",
    "addr:housenumber":"209",
    "addr:postcode":"37763",
    "addr:street":"Broken;Pt",
    "iso:country":"US",
    "sg:address":"209 Broken Arrow Pt",
    "sg:city":"Kingston",
    "sg:classifiers":[
        {
            "category":"Professional",
            "type":"Services"
        }
    ],
    "sg:phone":"+1 865 717 1477",
    "sg:postcode":"37763",
    "sg:province":"TN",
    "wof:name":"Carlie E Miles",
    "wof:placetype":"venue"
},
  "geometry": {"coordinates":[-84.516255,35.799572],"type":"Point"}
}