{
  "type": "Feature",
  "properties": {
    "addr:full":"121 N Main St Lexington TN 38351",
    "addr:housenumber":"121",
    "addr:postcode":"38351",
    "addr:street":"N Main St",
    "iso:country":"US",
    "sg:address":"121 N Main St",
    "sg:city":"Lexington",
    "sg:classifiers":[
        {
            "category":"Shopping",
            "subcategory":"Gifts & Souvenirs",
            "type":"Retail Goods"
        }
    ],
    "sg:phone":"+1 731 968 1619",
    "sg:postcode":"38351",
    "sg:province":"TN",
    "wof:name":"Gift Garden",
    "wof:placetype":"venue"
},
  "geometry": {"coordinates":[-88.39684200000001,35.652295],"type":"Point"}
}