{
  "type": "Feature",
  "properties": {
    "iso:country":"US",
    "sg:address":"909 Congress Pkwy NW",
    "sg:city":"Athens",
    "sg:classifiers":[
        {
            "category":"Personal",
            "subcategory":"Beauty Salon",
            "type":"Services"
        }
    ],
    "sg:phone":"+1 423 745 8369",
    "sg:postcode":"37303",
    "sg:province":"TN",
    "sg:tags":[
        "shop"
    ],
    "wof:name":"Hair Dimensions",
    "wof:placetype":"venue"
},
  "geometry": {"coordinates":[-84.61605,35.45792],"type":"Point"}
}