{
  "type": "Feature",
  "properties": {
    "addr:full":"897 N Maple St Adamsville TN 38310",
    "addr:housenumber":"897",
    "addr:postcode":"38310",
    "addr:street":"N Maple St",
    "iso:country":"US",
    "sg:address":"897 N Maple St",
    "sg:city":"Adamsville",
    "sg:classifiers":[
        {
            "category":"Organizations",
            "subcategory":"Religious Organization",
            "type":"Services"
        }
    ],
    "sg:phone":"+1 731 688 5125",
    "sg:postcode":"38310",
    "sg:province":"TN",
    "sg:tags":[
        "church"
    ],
    "wof:name":"Calvary Baptist Church",
    "wof:placetype":"venue"
},
  "geometry": {"coordinates":[-88.391086,35.277364],"type":"Point"}
}