{
  "type": "Feature",
  "properties": {
    "iso:country":"US",
    "sg:address":"209 Henslee Dr",
    "sg:city":"Dickson",
    "sg:classifiers":[
        {
            "category":"Education",
            "subcategory":"Dance Studio",
            "type":"Public Place"
        }
    ],
    "sg:phone":"+1 615 446 6851",
    "sg:postcode":"37055",
    "sg:province":"TN",
    "wof:name":"Miss Amys School of Arts",
    "wof:placetype":"venue"
},
  "geometry": {"coordinates":[-87.373718,36.076656],"type":"Point"}
}