{
  "type": "Feature",
  "properties": {
    "addr:full":"3501 Sims Rd Sevierville TN 37876",
    "addr:housenumber":"3501",
    "addr:postcode":"37876",
    "addr:street":"Sims Rd",
    "iso:country":"US",
    "sg:address":"3501 Sims Rd",
    "sg:city":"Sevierville",
    "sg:classifiers":[
        {
            "category":"Retail",
            "subcategory":"Laundry & Dry Cleaning",
            "type":"Services"
        }
    ],
    "sg:phone":"+1 865 908 3914",
    "sg:postcode":"37876",
    "sg:province":"TN",
    "sg:tags":[
        "cleaner",
        "rug",
        "carpet"
    ],
    "wof:name":"Quality Carpet Care",
    "wof:placetype":"venue"
},
  "geometry": {"coordinates":[-83.417061,35.92347],"type":"Point"}
}