{
  "type": "Feature",
  "properties": {
    "iso:country":"US",
    "sg:address":"1173 Trotwood Ave",
    "sg:city":"Columbia",
    "sg:classifiers":[
        {
            "category":"Shopping",
            "subcategory":"Gifts & Souvenirs",
            "type":"Retail Goods"
        }
    ],
    "sg:phone":"+1 931 490 2292",
    "sg:postcode":"38401",
    "sg:province":"TN",
    "sg:tags":[
        "shop"
    ],
    "wof:name":"Morning Glory's Gifts & Herbs",
    "wof:placetype":"venue"
},
  "geometry": {"coordinates":[-87.060323,35.610936],"type":"Point"}
}