{
  "type": "Feature",
  "properties": {
    "addr:full":"2335 Federal Dr Dyersburg TN 38024",
    "addr:housenumber":"2335",
    "addr:postcode":"38024",
    "addr:street":"Federal Dr",
    "iso:country":"US",
    "sg:address":"2335 Federal Dr",
    "sg:city":"Dyersburg",
    "sg:classifiers":[
        {
            "category":"Shopping",
            "subcategory":"Computers & Home Electronics",
            "type":"Retail Goods"
        }
    ],
    "sg:phone":"+1 731 286 4217",
    "sg:postcode":"38024",
    "sg:province":"TN",
    "sg:tags":[
        "equipment",
        "dealer"
    ],
    "wof:name":"Computer Line",
    "wof:placetype":"venue"
},
  "geometry": {"coordinates":[-89.388352,36.059148],"type":"Point"}
}