{
  "type": "Feature",
  "properties": {
    "iso:country":"US",
    "sg:address":"1536 Independence Ave",
    "sg:city":"Mount Carmel",
    "sg:classifiers":[
        {
            "category":"Organizations",
            "subcategory":"Religious Organization",
            "type":"Services"
        }
    ],
    "sg:phone":"+1 423 357 8363",
    "sg:postcode":"37645",
    "sg:province":"TN",
    "wof:name":"Freedom Baptist Church",
    "wof:placetype":"venue"
},
  "geometry": {"coordinates":[-82.66623,36.578331],"type":"Point"}
}