{
  "type": "Feature",
  "properties": {
    "iso:country":"US",
    "sg:address":"3975 Brainerd Rd",
    "sg:city":"Chattanooga",
    "sg:classifiers":[
        {
            "category":"Organizations",
            "subcategory":"Religious Organization",
            "type":"Services"
        }
    ],
    "sg:phone":"+1 423 624 7907",
    "sg:postcode":"37411",
    "sg:province":"TN",
    "wof:name":"Kingly Ministries",
    "wof:placetype":"venue"
},
  "geometry": {"coordinates":[-85.239718,35.01871],"type":"Point"}
}