{
  "type": "Feature",
  "properties": {
    "addr:full":"205 High Point Dr Johnson City TN 37601",
    "addr:housenumber":"205",
    "addr:postcode":"37601",
    "addr:street":"High Point Dr",
    "iso:country":"US",
    "sg:address":"205 High Point Dr",
    "sg:city":"Johnson City",
    "sg:classifiers":[
        {
            "category":"Building & Trades",
            "subcategory":"Construction",
            "type":"Services"
        }
    ],
    "sg:phone":"+1 423 610 0501",
    "sg:postcode":"37601",
    "sg:province":"TN",
    "sg:tags":[
        "house"
    ],
    "wof:name":"Service of Johnson City",
    "wof:placetype":"venue"
},
  "geometry": {"coordinates":[-82.38193099999999,36.358688],"type":"Point"}
}