{
  "type": "Feature",
  "properties": {
    "iso:country":"US",
    "sg:address":"216 W Lincoln St",
    "sg:city":"Tullahoma",
    "sg:classifiers":[
        {
            "category":"Organizations",
            "subcategory":"Labor Organization",
            "type":"Services"
        }
    ],
    "sg:phone":"+1 931 455 7222",
    "sg:postcode":"37388",
    "sg:province":"TN",
    "wof:name":"United Steel Wkrs Amer Local",
    "wof:placetype":"venue"
},
  "geometry": {"coordinates":[-86.21211,35.36124],"type":"Point"}
}