{
  "type": "Feature",
  "properties": {
    "addr:full":"304 Sand Hill Rd La Vergne TN 37086",
    "addr:housenumber":"304",
    "addr:postcode":"37086",
    "addr:street":"Sand Hill Rd",
    "iso:country":"US",
    "sg:address":"304 Sand Hill Rd",
    "sg:city":"La Vergne",
    "sg:classifiers":[
        {
            "category":"Wholesale",
            "subcategory":"Auto Parts",
            "type":"Manufacturing & Wholesale Goods"
        }
    ],
    "sg:phone":"+1 615 793 5573",
    "sg:postcode":"37086",
    "sg:province":"TN",
    "sg:tags":[
        "equipment",
        "truck"
    ],
    "wof:name":"Swamps Diesel Performance",
    "wof:placetype":"venue"
},
  "geometry": {"coordinates":[-86.56055000000001,36.025695],"type":"Point"}
}