{
  "type": "Feature",
  "properties": {
    "iso:country":"US",
    "sg:address":"241 Neals Landing Rd",
    "sg:city":"Knoxville",
    "sg:classifiers":[
        {
            "category":"Manufacturing",
            "subcategory":"Printing",
            "type":"Manufacturing & Wholesale Goods"
        }
    ],
    "sg:phone":"+1 865 933 7257",
    "sg:postcode":"37924",
    "sg:province":"TN",
    "sg:tags":[
        "commercial"
    ],
    "wof:name":"Printer's Printer Inc",
    "wof:placetype":"venue"
},
  "geometry": {"coordinates":[-83.77709900000001,36.023558],"type":"Point"}
}