{
  "type": "Feature",
  "properties": {
    "iso:country":"US",
    "sg:address":"7331 Cavender Rd",
    "sg:city":"Lyles",
    "sg:classifiers":[
        {
            "category":"Shopping",
            "subcategory":"Gifts & Souvenirs",
            "type":"Retail Goods"
        }
    ],
    "sg:phone":"+1 931 670 4107",
    "sg:postcode":"37098",
    "sg:province":"TN",
    "wof:name":"Gifts & More Inc",
    "wof:placetype":"venue"
},
  "geometry": {"coordinates":[-87.302694,35.885368],"type":"Point"}
}