{
  "type": "Feature",
  "properties": {
    "iso:country":"US",
    "sg:address":"4342 Northgate Dr",
    "sg:city":"Knoxville",
    "sg:classifiers":[
        {
            "category":"Personal",
            "subcategory":"Beauty Salon",
            "type":"Services"
        }
    ],
    "sg:phone":"+1 865 689 5322",
    "sg:postcode":"37938",
    "sg:province":"TN",
    "sg:tags":[
        "shop"
    ],
    "wof:name":"New Edition Hairstyles",
    "wof:placetype":"venue"
},
  "geometry": {"coordinates":[-83.931575,36.087798],"type":"Point"}
}