{
  "type": "Feature",
  "properties": {
    "iso:country":"US",
    "sg:address":"623 Parkway",
    "sg:city":"Gatlinburg",
    "sg:classifiers":[
        {
            "category":"Shopping",
            "subcategory":"Clothing, Apparel, & Fashions",
            "type":"Retail Goods"
        }
    ],
    "sg:phone":"+1 865 436 4377",
    "sg:postcode":"37738",
    "sg:province":"TN",
    "sg:tags":[
        "sweatshirt",
        "t"
    ],
    "wof:name":"Weekend Warriors",
    "wof:placetype":"venue"
},
  "geometry": {"coordinates":[-83.513605,35.712924],"type":"Point"}
}