{
  "type": "Feature",
  "properties": {
    "iso:country":"US",
    "sg:address":"6320 Waterford Dr",
    "sg:city":"Brentwood",
    "sg:classifiers":[
        {
            "category":"Professional",
            "type":"Services"
        }
    ],
    "sg:phone":"+1 615 376 5501",
    "sg:postcode":"37027",
    "sg:province":"TN",
    "wof:name":"Valkyrie Manage",
    "wof:placetype":"venue"
},
  "geometry": {"coordinates":[-86.84663500000001,36.021382],"type":"Point"}
}