{
  "type": "Feature",
  "properties": {
    "addr:full":"6295 Maison Privee Cv Memphis TN 38120",
    "addr:housenumber":"6295",
    "addr:postcode":"38120",
    "addr:street":"Maison Privee Cv",
    "iso:country":"US",
    "sg:address":"6295 Maison Privee Cv",
    "sg:city":"Memphis",
    "sg:classifiers":[
        {
            "category":"Shopping",
            "subcategory":"Stationery & Office Supplies",
            "type":"Retail Goods"
        },
        {
            "category":"Wholesale",
            "subcategory":"Stationery",
            "type":"Manufacturing & Wholesale Goods"
        }
    ],
    "sg:phone":"+1 901 821 8383",
    "sg:postcode":"38120",
    "sg:province":"TN",
    "sg:tags":[
        "announcement",
        "envelope",
        "engravers-stationery",
        "invitation",
        "store"
    ],
    "wof:name":"Something So Write",
    "wof:placetype":"venue"
},
  "geometry": {"coordinates":[-89.852091,35.107472],"type":"Point"}
}