{
  "type": "Feature",
  "properties": {
    "iso:country":"US",
    "sg:address":"1009 Grace Dr",
    "sg:city":"Johnson City",
    "sg:classifiers":[
        {
            "category":"Organizations",
            "subcategory":"Community Association",
            "type":"Services"
        }
    ],
    "sg:phone":"+1 423 282 3230",
    "sg:postcode":"37604",
    "sg:province":"TN",
    "wof:name":"Escape Mtn Prperty Owners Assn",
    "wof:placetype":"venue"
},
  "geometry": {"coordinates":[-82.391442,36.333791],"type":"Point"}
}