{
  "type": "Feature",
  "properties": {
    "addr:full":"530 Sanbyrn Dr Murfreesboro TN 37130",
    "addr:housenumber":"530",
    "addr:postcode":"37130",
    "addr:street":"Sanbyrn Dr",
    "iso:country":"US",
    "sg:address":"530 Sanbyrn Dr",
    "sg:city":"Murfreesboro",
    "sg:classifiers":[
        {
            "category":"Building & Trades",
            "subcategory":"Cleaning & Sanitation",
            "type":"Services"
        }
    ],
    "sg:phone":"+1 615 867 7760",
    "sg:postcode":"37130",
    "sg:province":"TN",
    "sg:tags":[
        "janitor"
    ],
    "wof:name":"Master Clean",
    "wof:placetype":"venue"
},
  "geometry": {"coordinates":[-86.38301,35.828392],"type":"Point"}
}