{
  "type": "Feature",
  "properties": {
    "iso:country":"US",
    "sg:address":"1540 Amherst Rd",
    "sg:city":"Knoxville",
    "sg:classifiers":[
        {
            "category":"Manufacturing",
            "subcategory":"Wood Products",
            "type":"Manufacturing & Wholesale Goods"
        }
    ],
    "sg:phone":"+1 865 558 3995",
    "sg:postcode":"37909",
    "sg:province":"TN",
    "sg:tags":[
        "mfg"
    ],
    "sg:website":"www.propaklogistics.com",
    "wof:name":"Propak Logistics",
    "wof:placetype":"venue"
},
  "geometry": {"coordinates":[-84.01724299999999,35.957667],"type":"Point"}
}