{
  "type": "Feature",
  "properties": {
    "addr:full":"3481 Foster Chapel Rd Columbia TN 38401",
    "addr:housenumber":"3481",
    "addr:postcode":"38401",
    "addr:street":"Foster Chapel Rd",
    "iso:country":"US",
    "sg:address":"3481 Foster Chapel Rd",
    "sg:city":"Columbia",
    "sg:phone":"+1 931 583 2371",
    "sg:postcode":"38401",
    "sg:province":"TN",
    "sg:tags":[
        "farm",
        "corn"
    ],
    "wof:name":"Ralph Sims",
    "wof:placetype":"venue"
},
  "geometry": {"coordinates":[-87.209552,35.657776],"type":"Point"}
}