{
  "type": "Feature",
  "properties": {
    "addr:full":"1116 Monte Bella Pl Franklin TN 37067",
    "addr:housenumber":"1116",
    "addr:postcode":"37067",
    "addr:street":"Monte Bella Pl",
    "iso:country":"US",
    "sg:address":"1116 Monte Bella Pl",
    "sg:city":"Franklin",
    "sg:classifiers":[
        {
            "category":"Professional",
            "subcategory":"Computer Services",
            "type":"Services"
        }
    ],
    "sg:phone":"+1 615 364 7968",
    "sg:postcode":"37067",
    "sg:province":"TN",
    "sg:tags":[
        "related"
    ],
    "wof:name":"Brian Winsett",
    "wof:placetype":"venue"
},
  "geometry": {"coordinates":[-86.82171200000001,35.905137],"type":"Point"}
}