{
  "type": "Feature",
  "properties": {
    "iso:country":"US",
    "sg:address":"8813 Pebble Creek Rd",
    "sg:city":"Chattanooga",
    "sg:classifiers":[
        {
            "category":"Professional",
            "subcategory":"Management & Consulting",
            "type":"Services"
        }
    ],
    "sg:phone":"+1 423 855 9293",
    "sg:postcode":"37421",
    "sg:province":"TN",
    "sg:tags":[
        "consultant"
    ],
    "wof:name":"STK Consulting",
    "wof:placetype":"venue"
},
  "geometry": {"coordinates":[-85.120971,35.024042],"type":"Point"}
}