{
  "type": "Feature",
  "properties": {
    "iso:country":"US",
    "sg:address":"2213 Memorial Blvd",
    "sg:city":"Springfield",
    "sg:classifiers":[
        {
            "category":"Professional",
            "type":"Services"
        },
        {
            "category":"Recreation",
            "type":"Entertainment"
        }
    ],
    "sg:phone":"+1 615 384 3994",
    "sg:postcode":"37172",
    "sg:province":"TN",
    "sg:tags":[
        "psychic",
        "medium"
    ],
    "wof:name":"Psychic Vision Center",
    "wof:placetype":"venue"
},
  "geometry": {"coordinates":[-86.872715,36.491468],"type":"Point"}
}