{
  "type": "Feature",
  "properties": {
    "iso:country":"US",
    "sg:address":"1745 N Graham St",
    "sg:city":"Memphis",
    "sg:classifiers":[
        {
            "category":"Retail",
            "subcategory":"Auto Repair",
            "type":"Services"
        }
    ],
    "sg:phone":"+1 901 864 7543",
    "sg:postcode":"38108",
    "sg:province":"TN",
    "sg:tags":[
        "body",
        "automobile",
        "painting",
        "repairing"
    ],
    "wof:name":"Laraza Body Shop",
    "wof:placetype":"venue"
},
  "geometry": {"coordinates":[-89.92670200000001,35.17978],"type":"Point"}
}