{
  "type": "Feature",
  "properties": {
    "addr:full":"2270 Elliston Dr Cleveland TN 37311",
    "addr:housenumber":"2270",
    "addr:postcode":"37311",
    "addr:street":"Elliston Dr",
    "iso:country":"US",
    "sg:address":"2270 Elliston Dr",
    "sg:city":"Cleveland",
    "sg:classifiers":[
        {
            "category":"Autos & Motor Vehicles",
            "subcategory":"Automobile Sales",
            "type":"Retail Goods"
        }
    ],
    "sg:phone":"+1 423 728 5779",
    "sg:postcode":"37311",
    "sg:province":"TN",
    "sg:tags":[
        "car",
        "dealer"
    ],
    "wof:name":"Holliday Auto Sales",
    "wof:placetype":"venue"
},
  "geometry": {"coordinates":[-84.914052,35.147511],"type":"Point"}
}