{
  "type": "Feature",
  "properties": {
    "iso:country":"US",
    "sg:address":"5813 Lee Hwy",
    "sg:city":"Chattanooga",
    "sg:classifiers":[
        {
            "category":"Professional",
            "subcategory":"Accounting & Tax Preparation",
            "type":"Services"
        },
        {
            "category":"Insurance",
            "subcategory":"Insurance Agent",
            "type":"Services"
        },
        {
            "category":"Insurance",
            "subcategory":"Hazard Insurance",
            "type":"Services"
        }
    ],
    "sg:phone":"+1 423 899 3404",
    "sg:postcode":"37421",
    "sg:province":"TN",
    "sg:tags":[
        "property",
        "insured",
        "bookkeeping",
        "adjuster",
        "replacement"
    ],
    "wof:name":"Receivables Management Group Inc",
    "wof:placetype":"venue"
},
  "geometry": {"coordinates":[-85.20025800000001,35.021237],"type":"Point"}
}