{
  "type": "Feature",
  "properties": {
    "iso:country":"US",
    "sg:address":"1785 Fort Henry Dr",
    "sg:city":"Kingsport",
    "sg:classifiers":[
        {
            "category":"Home & Garden",
            "subcategory":"Garden Supply",
            "type":"Retail Goods"
        }
    ],
    "sg:phone":"+1 423 245 7303",
    "sg:postcode":"37664",
    "sg:province":"TN",
    "sg:tags":[
        "lawn",
        "mower"
    ],
    "wof:name":"Warranty One Mobile Mower Rpr",
    "wof:placetype":"venue"
},
  "geometry": {"coordinates":[-82.52619900000001,36.531157],"type":"Point"}
}