{
  "type": "Feature",
  "properties": {
    "iso:country":"US",
    "sg:address":"1800 Galleria Blvd",
    "sg:city":"Franklin",
    "sg:classifiers":[
        {
            "category":"Coffee & Tea",
            "type":"Food & Drink"
        }
    ],
    "sg:menulink":"http://www.allmenus.com/tn/brentwood/121486-the-coffee-beanery/menu/",
    "sg:phone":"+1 615 771 7608",
    "sg:postcode":"37067",
    "sg:province":"TN",
    "sg:tags":[
        "american",
        "diner"
    ],
    "wof:name":"The Coffee Beanery",
    "wof:placetype":"venue"
},
  "geometry": {"coordinates":[-86.81488,35.956],"type":"Point"}
}