{
  "type": "Feature",
  "properties": {
    "iso:country":"US",
    "sg:address":"6675 Stage Rd Bartlett",
    "sg:city":"Memphis",
    "sg:classifiers":[
        {
            "category":"Banks & Credit Unions",
            "subcategory":"Bank",
            "type":"Services"
        },
        {
            "category":"Banks & Credit Unions",
            "subcategory":"Financial Services",
            "type":"Services"
        }
    ],
    "sg:phone":"+1 901 382 2265",
    "sg:postcode":"38134",
    "sg:province":"TN",
    "sg:tags":[
        "commercial",
        "loan",
        "saving",
        "mortgage"
    ],
    "sg:website":"http://www.bancorpsouth.com",
    "wof:name":"BancorpSouth",
    "wof:placetype":"venue"
},
  "geometry": {"coordinates":[-89.84050000000001,35.204868],"type":"Point"}
}