{
  "type": "Feature",
  "properties": {
    "iso:country":"US",
    "sg:address":"2960 Emerald St",
    "sg:city":"Memphis",
    "sg:classifiers":[
        {
            "category":"Education",
            "subcategory":"School",
            "type":"Public Place"
        }
    ],
    "sg:phone":"+1 901 416 2550",
    "sg:postcode":"38115",
    "sg:province":"TN",
    "wof:name":"Fox Meadows Elementary School",
    "wof:placetype":"venue"
},
  "geometry": {"coordinates":[-89.88032800000001,35.067429],"type":"Point"}
}