{
  "type": "Feature",
  "properties": {
    "iso:country":"US",
    "sg:address":"1590 Nashville Hwy",
    "sg:city":"Lewisburg",
    "sg:classifiers":[
        {
            "category":"Autos & Motor Vehicles",
            "subcategory":"Automobile Sales",
            "type":"Retail Goods"
        }
    ],
    "sg:phone":"+1 931 270 1340",
    "sg:postcode":"37091",
    "sg:province":"TN",
    "sg:tags":[
        "car",
        "dealer"
    ],
    "wof:name":"Eady's Auto Sales",
    "wof:placetype":"venue"
},
  "geometry": {"coordinates":[-86.769358,35.470036],"type":"Point"}
}