{
  "type": "Feature",
  "properties": {
    "addr:full":"5901 Industrial Park Dr Lenoir City TN 37771",
    "addr:housenumber":"5901",
    "addr:postcode":"37771",
    "addr:street":"Industrial Park Dr",
    "iso:country":"US",
    "sg:address":"5901 Industrial Park Dr",
    "sg:city":"Lenoir City",
    "sg:classifiers":[
        {
            "category":"Manufacturing",
            "subcategory":"Furniture",
            "type":"Manufacturing & Wholesale Goods"
        }
    ],
    "sg:phone":"+1 865 988 9818",
    "sg:postcode":"37771",
    "sg:province":"TN",
    "wof:name":"Berkline Corp",
    "wof:placetype":"venue"
},
  "geometry": {"coordinates":[-84.277287,35.778992],"type":"Point"}
}