{
  "type": "Feature",
  "properties": {
    "iso:country":"US",
    "sg:address":"308 S Main St",
    "sg:city":"Lobelville",
    "sg:classifiers":[
        {
            "category":"Personal",
            "subcategory":"Beauty Salon",
            "type":"Services"
        }
    ],
    "sg:phone":"+1 931 593 3957",
    "sg:postcode":"37097",
    "sg:province":"TN",
    "wof:name":"Jacqueline's Cutting Edge",
    "wof:placetype":"venue"
},
  "geometry": {"coordinates":[-87.784007,35.769551],"type":"Point"}
}