{
  "type": "Feature",
  "properties": {
    "iso:country":"US",
    "sg:address":"2111 N Roan St",
    "sg:city":"Johnson City",
    "sg:classifiers":[
        {
            "category":"Shopping",
            "subcategory":"Clothing, Apparel, & Fashions",
            "type":"Retail Goods"
        }
    ],
    "sg:phone":"+1 423 282 6685",
    "sg:postcode":"37601",
    "sg:province":"TN",
    "wof:name":"Casual Male Big & Tall",
    "wof:placetype":"venue"
},
  "geometry": {"coordinates":[-82.376425,36.343272],"type":"Point"}
}