{
  "type": "Feature",
  "properties": {
    "addr:full":"220 Locust St Morristown TN 37813",
    "addr:housenumber":"220",
    "addr:postcode":"37813",
    "addr:street":"Locust St",
    "iso:country":"US",
    "sg:address":"220 Locust St",
    "sg:city":"Morristown",
    "sg:classifiers":[
        {
            "category":"Autos & Motor Vehicles",
            "subcategory":"Automobile Sales",
            "type":"Retail Goods"
        }
    ],
    "sg:phone":"+1 423 581 5611",
    "sg:postcode":"37813",
    "sg:province":"TN",
    "sg:tags":[
        "car",
        "dealer"
    ],
    "wof:name":"Right Choice Auto",
    "wof:placetype":"venue"
},
  "geometry": {"coordinates":[-83.283231,36.215907],"type":"Point"}
}