{
  "type": "Feature",
  "properties": {
    "addr:full":"4683 Old Broadway NE Knoxville TN 37918",
    "addr:housenumber":"4683",
    "addr:postcode":"37918",
    "addr:street":"Old Broadway Ne",
    "iso:country":"US",
    "sg:address":"4683 Old Broadway NE",
    "sg:city":"Knoxville",
    "sg:classifiers":[
        {
            "category":"Autos & Motor Vehicles",
            "subcategory":"Automobile Sales",
            "type":"Retail Goods"
        }
    ],
    "sg:phone":"+1 865 281 2493",
    "sg:postcode":"37918",
    "sg:province":"TN",
    "sg:tags":[
        "used"
    ],
    "wof:name":"Classic Car Sales",
    "wof:placetype":"venue"
},
  "geometry": {"coordinates":[-83.924375,36.018604],"type":"Point"}
}