{
  "type": "Feature",
  "properties": {
    "iso:country":"US",
    "sg:address":"877 Jefferson Ave",
    "sg:city":"Memphis",
    "sg:classifiers":[
        {
            "category":"Health Services",
            "subcategory":"Doctor",
            "type":"Services"
        }
    ],
    "sg:phone":"+1 901 448 4454",
    "sg:postcode":"38103",
    "sg:province":"TN",
    "sg:tags":[
        "physician",
        "surgeon",
        "anesthesiology",
        "surgeons"
    ],
    "wof:name":"Khan, Arshad, Md - University Of Tennessee",
    "wof:placetype":"venue"
},
  "geometry": {"coordinates":[-90.04383900000001,35.145081],"type":"Point"}
}