{
  "type": "Feature",
  "properties": {
    "iso:country":"US",
    "sg:address":"217 E High St",
    "sg:city":"Lebanon",
    "sg:classifiers":[
        {
            "category":"Professional",
            "subcategory":"Accounting & Tax Preparation",
            "type":"Services"
        }
    ],
    "sg:phone":"+1 615 443 4967",
    "sg:postcode":"37087",
    "sg:province":"TN",
    "sg:tags":[
        "return",
        "filing"
    ],
    "wof:name":"H & R Block Tax Svc",
    "wof:placetype":"venue"
},
  "geometry": {"coordinates":[-86.28752299999999,36.21218],"type":"Point"}
}