{
  "type": "Feature",
  "properties": {
    "iso:country":"US",
    "sg:address":"1420 Prospect Elkton Rd",
    "sg:city":"Prospect",
    "sg:classifiers":[
        {
            "category":"Recreation",
            "type":"Entertainment"
        }
    ],
    "sg:phone":"+1 931 363 1836",
    "sg:postcode":"38455",
    "sg:province":"TN",
    "sg:tags":[
        "martial",
        "arts",
        "instruction"
    ],
    "wof:name":"Middle Tennessee Bujinkan Dojo",
    "wof:placetype":"venue"
},
  "geometry": {"coordinates":[-86.92346000000001,35.045935],"type":"Point"}
}