{
  "type": "Feature",
  "properties": {
    "addr:full":"3120 Parkway Pigeon Forge TN 37863",
    "addr:housenumber":"3120",
    "addr:postcode":"37863",
    "addr:street":"Parkway",
    "iso:country":"US",
    "sg:address":"3120 Parkway",
    "sg:city":"Pigeon Forge",
    "sg:classifiers":[
        {
            "category":"Shopping",
            "subcategory":"Pharmacy",
            "type":"Retail Goods"
        }
    ],
    "sg:phone":"+1 865 453 9096",
    "sg:postcode":"37863",
    "sg:province":"TN",
    "wof:name":"Stewart's Discount Drugs",
    "wof:placetype":"venue"
},
  "geometry": {"coordinates":[-83.56064000000001,35.793551],"type":"Point"}
}