{
  "type": "Feature",
  "properties": {
    "iso:country":"US",
    "sg:address":"307 E Jefferson Pike",
    "sg:city":"Murfreesboro",
    "sg:classifiers":[
        {
            "category":"Organizations",
            "subcategory":"Religious Organization",
            "type":"Services"
        }
    ],
    "sg:phone":"+1 615 890 3834",
    "sg:postcode":"37130",
    "sg:province":"TN",
    "sg:tags":[
        "church"
    ],
    "sg:website":"www.heartlandbaptist.org",
    "wof:name":"Heartland Baptist",
    "wof:placetype":"venue"
},
  "geometry": {"coordinates":[-86.37682599999999,35.948965],"type":"Point"}
}