{
  "type": "Feature",
  "properties": {
    "iso:country":"US",
    "sg:address":"135 Boulder St",
    "sg:city":"Maryville",
    "sg:classifiers":[
        {
            "category":"Building & Trades",
            "subcategory":"Plumbing",
            "type":"Services"
        }
    ],
    "sg:phone":"+1 865 679 9335",
    "sg:postcode":"37804",
    "sg:province":"TN",
    "sg:tags":[
        "leak",
        "detecting"
    ],
    "wof:name":"S & R Roofing & Painting",
    "wof:placetype":"venue"
},
  "geometry": {"coordinates":[-83.962287,35.820331],"type":"Point"}
}