{
  "type": "Feature",
  "properties": {
    "addr:full":"4807 Arrowhead Trl Chattanooga TN 37411",
    "addr:housenumber":"4807",
    "addr:postcode":"37411",
    "addr:street":"Arrowhead Trl",
    "iso:country":"US",
    "sg:address":"4807 Arrowhead Trl",
    "sg:city":"Chattanooga",
    "sg:classifiers":[
        {
            "category":"Building & Trades",
            "subcategory":"Construction",
            "type":"Services"
        }
    ],
    "sg:phone":"+1 423 899 0663",
    "sg:postcode":"37411",
    "sg:province":"TN",
    "sg:tags":[
        "hanging",
        "contractor"
    ],
    "wof:name":"Triple A Paper Hanging",
    "wof:placetype":"venue"
},
  "geometry": {"coordinates":[-85.222443,35.023821],"type":"Point"}
}