{
  "type": "Feature",
  "properties": {
    "iso:country":"US",
    "sg:address":"724 Central Ave W",
    "sg:city":"Springfield",
    "sg:classifiers":[
        {
            "category":"Manufacturing",
            "subcategory":"Tools & Machinery",
            "type":"Manufacturing & Wholesale Goods"
        }
    ],
    "sg:phone":"+1 615 384 2501",
    "sg:postcode":"37172",
    "sg:province":"TN",
    "sg:tags":[
        "machine",
        "shop"
    ],
    "wof:name":"Precision Products-Tn Inc",
    "wof:placetype":"venue"
},
  "geometry": {"coordinates":[-86.895663,36.502397],"type":"Point"}
}