{
  "type": "Feature",
  "properties": {
    "iso:country":"US",
    "sg:address":"140 Adams Ave",
    "sg:city":"Memphis",
    "sg:classifiers":[
        {
            "category":"Government",
            "subcategory":"Office",
            "type":"Public Place"
        }
    ],
    "sg:phone":"+1 901 545 4022",
    "sg:postcode":"38103",
    "sg:province":"TN",
    "sg:tags":[
        "county",
        "security"
    ],
    "wof:name":"Bailey D'Army",
    "wof:placetype":"venue"
},
  "geometry": {"coordinates":[-90.049824,35.147783],"type":"Point"}
}