{
  "type": "Feature",
  "properties": {
    "iso:country":"US",
    "sg:address":"1680 Fort Campbell Blvd",
    "sg:city":"Clarksville",
    "sg:classifiers":[
        {
            "category":"Banks & Credit Unions",
            "subcategory":"Bank",
            "type":"Services"
        }
    ],
    "sg:phone":"+1 931 221 0656",
    "sg:postcode":"37042",
    "sg:province":"TN",
    "sg:tags":[
        "national",
        "commercial"
    ],
    "wof:name":"US Bancorp",
    "wof:placetype":"venue"
},
  "geometry": {"coordinates":[-87.410465,36.581182],"type":"Point"}
}