{
  "type": "Feature",
  "properties": {
    "addr:full":"4792 Arms Ave Memphis TN 38128",
    "addr:housenumber":"4792",
    "addr:postcode":"38128",
    "addr:street":"Arms Ave",
    "iso:country":"US",
    "sg:address":"4792 Arms Ave",
    "sg:city":"Memphis",
    "sg:classifiers":[
        {
            "category":"Recreation",
            "type":"Entertainment"
        }
    ],
    "sg:phone":"+1 901 386 7977",
    "sg:postcode":"38128",
    "sg:province":"TN",
    "sg:tags":[
        "concessionaire"
    ],
    "wof:name":"Cutie Pie Snacks",
    "wof:placetype":"venue"
},
  "geometry": {"coordinates":[-89.903047,35.220798],"type":"Point"}
}