{
  "type": "Feature",
  "properties": {
    "iso:country":"US",
    "sg:address":"6004 Brandywine Ln",
    "sg:city":"Chattanooga",
    "sg:classifiers":[
        {
            "category":"Professional",
            "subcategory":"Computer Services",
            "type":"Services"
        }
    ],
    "sg:phone":"+1 423 874 1991",
    "sg:postcode":"37415",
    "sg:province":"TN",
    "wof:name":"At Home Computers",
    "wof:placetype":"venue"
},
  "geometry": {"coordinates":[-85.26062,35.160287],"type":"Point"}
}