{
  "type": "Feature",
  "properties": {
    "iso:country":"US",
    "sg:address":"314 S Cannon Blvd",
    "sg:city":"Shelbyville",
    "sg:classifiers":[
        {
            "category":"Retail",
            "subcategory":"Auto Rental",
            "type":"Services"
        }
    ],
    "sg:phone":"+1 931 680 0115",
    "sg:postcode":"37160",
    "sg:province":"TN",
    "sg:tags":[
        "truck"
    ],
    "wof:name":"Moving Center of Shelbyville",
    "wof:placetype":"venue"
},
  "geometry": {"coordinates":[-86.464524,35.480014],"type":"Point"}
}