{
  "type": "Feature",
  "properties": {
    "iso:country":"US",
    "sg:address":"2680 Johnson Chapel Rd",
    "sg:city":"Sparta",
    "sg:classifiers":[
        {
            "category":"Recreation",
            "type":"Entertainment"
        }
    ],
    "sg:phone":"+1 931 761 3883",
    "sg:postcode":"38583",
    "sg:province":"TN",
    "sg:tags":[
        "center"
    ],
    "wof:name":"Johnson Chapel Rec Area",
    "wof:placetype":"venue"
},
  "geometry": {"coordinates":[-85.669406,35.990522],"type":"Point"}
}