{
  "type": "Feature",
  "properties": {
    "iso:country":"US",
    "sg:address":"230 E Main St",
    "sg:city":"Hendersonville",
    "sg:classifiers":[
        {
            "category":"Bars & Pubs",
            "type":"Food & Drink"
        }
    ],
    "sg:phone":"+1 615 822 1455",
    "sg:postcode":"37075",
    "sg:province":"TN",
    "sg:tags":[
        "drinking"
    ],
    "wof:name":"Woodland Group Inc",
    "wof:placetype":"venue"
},
  "geometry": {"coordinates":[-86.603711,36.308785],"type":"Point"}
}