{
  "type": "Feature",
  "properties": {
    "iso:country":"US",
    "sg:address":"810 Tate St",
    "sg:city":"Corinth",
    "sg:classifiers":[
        {
            "category":"Organizations",
            "subcategory":"Professional Association",
            "type":"Services"
        }
    ],
    "sg:phone":"+1 662 287 5269",
    "sg:postcode":"38834",
    "sg:province":"TN",
    "sg:tags":[
        "chamber",
        "commerce"
    ],
    "wof:name":"Alliance",
    "wof:placetype":"venue"
},
  "geometry": {"coordinates":[-88.518872,34.931538],"type":"Point"}
}