{
  "type": "Feature",
  "properties": {
    "iso:country":"US",
    "sg:address":"387 Old Bildad Rd",
    "sg:city":"Smithville",
    "sg:classifiers":[
        {
            "category":"Professional",
            "subcategory":"Accounting & Tax Preparation",
            "type":"Services"
        }
    ],
    "sg:phone":"+1 615 597 3966",
    "sg:postcode":"37166",
    "sg:province":"TN",
    "wof:name":"Customize Electronic Billing",
    "wof:placetype":"venue"
},
  "geometry": {"coordinates":[-85.754566,35.872923],"type":"Point"}
}