{
  "type": "Feature",
  "properties": {
    "addr:full":"204 20th St SE Cleveland TN 37311",
    "addr:housenumber":"204",
    "addr:postcode":"37311",
    "addr:street":"20Th St Se",
    "iso:country":"US",
    "sg:address":"204 20th St SE",
    "sg:city":"Cleveland",
    "sg:classifiers":[
        {
            "category":"Retail",
            "subcategory":"Auto Repair",
            "type":"Services"
        }
    ],
    "sg:phone":"+1 423 473 1700",
    "sg:postcode":"37311",
    "sg:province":"TN",
    "sg:tags":[
        "body",
        "automobile",
        "painting"
    ],
    "wof:name":"M & O Body Repair",
    "wof:placetype":"venue"
},
  "geometry": {"coordinates":[-84.8852,35.142503],"type":"Point"}
}