{
  "type": "Feature",
  "properties": {
    "iso:country":"US",
    "sg:address":"462 Walker Rd",
    "sg:city":"Dayton",
    "sg:classifiers":[
        {
            "category":"Building & Trades",
            "subcategory":"Electrical",
            "type":"Services"
        }
    ],
    "sg:phone":"+1 423 775 1360",
    "sg:postcode":"37321",
    "sg:province":"TN",
    "sg:tags":[
        "electrical",
        "contractor"
    ],
    "wof:name":"B King Electrical",
    "wof:placetype":"venue"
},
  "geometry": {"coordinates":[-85.101986,35.560574],"type":"Point"}
}