{
  "type": "Feature",
  "properties": {
    "addr:full":"695 Robertson Rd Lynnville TN 38472",
    "addr:housenumber":"695",
    "addr:postcode":"38472",
    "addr:street":"Robertson Rd",
    "iso:country":"US",
    "sg:address":"695 Robertson Rd",
    "sg:city":"Lynnville",
    "sg:classifiers":[
        {
            "category":"Farming",
            "subcategory":"Dairy Farm",
            "type":"Manufacturing & Wholesale Goods"
        }
    ],
    "sg:phone":"+1 931 527 3980",
    "sg:postcode":"38472",
    "sg:province":"TN",
    "wof:name":"Dwain Hickman",
    "wof:placetype":"venue"
},
  "geometry": {"coordinates":[-86.97178,35.410824],"type":"Point"}
}