{
  "type": "Feature",
  "properties": {
    "addr:full":"6822 Mc Cutcheon Rd Chattanooga TN 37421",
    "addr:housenumber":"6822",
    "addr:postcode":"37421",
    "addr:street":"Mc Cutcheon Rd",
    "iso:country":"US",
    "sg:address":"6822 Mc Cutcheon Rd",
    "sg:city":"Chattanooga",
    "sg:classifiers":[
        {
            "category":"Insurance",
            "subcategory":"Insurance Agent",
            "type":"Services"
        }
    ],
    "sg:phone":"+1 423 899 8400",
    "sg:postcode":"37421",
    "sg:province":"TN",
    "wof:name":"Hamilton Place Insurance",
    "wof:placetype":"venue"
},
  "geometry": {"coordinates":[-85.16389599999999,35.049383],"type":"Point"}
}