{
  "type": "Feature",
  "properties": {
    "iso:country":"US",
    "sg:address":"413 Clearwater Dr",
    "sg:city":"Nashville",
    "sg:classifiers":[
        {
            "category":"Social Services",
            "subcategory":"Child Care",
            "type":"Services"
        }
    ],
    "sg:phone":"+1 615 367 0700",
    "sg:postcode":"37217",
    "sg:province":"TN",
    "wof:name":"Tender Loving Childcare",
    "wof:placetype":"venue"
},
  "geometry": {"coordinates":[-86.62719800000001,36.078794],"type":"Point"}
}