{
  "type": "Feature",
  "properties": {
    "addr:full":"3700 E Magnolia Ave Knoxville TN 37914",
    "addr:housenumber":"3700",
    "addr:postcode":"37914",
    "addr:street":"E Magnolia Ave",
    "iso:country":"US",
    "sg:address":"3700 E Magnolia Ave",
    "sg:city":"Knoxville",
    "sg:classifiers":[
        {
            "category":"Restaurant",
            "type":"Food & Drink"
        }
    ],
    "sg:phone":"+1 865 523 3550",
    "sg:postcode":"37914",
    "sg:province":"TN",
    "sg:tags":[
        "eating"
    ],
    "sg:website":"www.buddysbarbq.com",
    "wof:name":"Buddy's Bar-B-Q",
    "wof:placetype":"venue"
},
  "geometry": {"coordinates":[-83.87907800000001,35.998249],"type":"Point"}
}