{
  "type": "Feature",
  "properties": {
    "iso:country":"US",
    "sg:address":"4535 Harding Pike Ste 208",
    "sg:city":"Nashville",
    "sg:classifiers":[
        {
            "category":"Professional",
            "subcategory":"Management & Consulting",
            "type":"Services"
        },
        {
            "category":"Banks & Credit Unions",
            "subcategory":"Investment Brokerage",
            "type":"Services"
        },
        {
            "category":"Banks & Credit Unions",
            "subcategory":"Financial Services",
            "type":"Services"
        }
    ],
    "sg:phone":"+1 615 298 3000",
    "sg:postcode":"37205",
    "sg:province":"TN",
    "sg:tags":[
        "financing",
        "retirement",
        "consultant",
        "planning",
        "plan",
        "annuity",
        "insurance"
    ],
    "sg:website":"http://www.timgreerfinancialplanner.com",
    "wof:name":"FSC Securities Corp",
    "wof:placetype":"venue"
},
  "geometry": {"coordinates":[-86.849423,36.123666],"type":"Point"}
}