{
  "type": "Feature",
  "properties": {
    "iso:country":"US",
    "sg:address":"901 Cainsville Rd",
    "sg:city":"Lebanon",
    "sg:classifiers":[
        {
            "category":"Autos & Motor Vehicles",
            "subcategory":"Automobile Sales",
            "type":"Retail Goods"
        },
        {
            "category":"Retail",
            "subcategory":"Auto Repair",
            "type":"Services"
        }
    ],
    "sg:phone":"+1 615 453 7757",
    "sg:postcode":"37087",
    "sg:province":"TN",
    "sg:tags":[
        "automotive",
        "sport",
        "ma",
        "trailer",
        "utility"
    ],
    "wof:name":"Trailer Depot LLC",
    "wof:placetype":"venue"
},
  "geometry": {"coordinates":[-86.28128,36.191158],"type":"Point"}
}