{
  "type": "Feature",
  "properties": {
    "addr:full":"4910 Columbia Pike Spring Hill TN 37174",
    "addr:housenumber":"4910",
    "addr:postcode":"37174",
    "addr:street":"Columbia Pike",
    "iso:country":"US",
    "sg:address":"4910 Columbia Pike",
    "sg:city":"Spring Hill",
    "sg:classifiers":[
        {
            "category":"Retail",
            "subcategory":"Laundry & Dry Cleaning",
            "type":"Services"
        }
    ],
    "sg:phone":"+1 615 302 0034",
    "sg:postcode":"37174",
    "sg:province":"TN",
    "sg:tags":[
        "drycleaning",
        "plant"
    ],
    "wof:name":"Fashion Cleaners",
    "wof:placetype":"venue"
},
  "geometry": {"coordinates":[-86.883368,35.845683],"type":"Point"}
}