{
  "type": "Feature",
  "properties": {
    "iso:country":"US",
    "sg:address":"120 Smith Cir",
    "sg:city":"Loretto",
    "sg:classifiers":[
        {
            "category":"Organizations",
            "subcategory":"Religious Organization",
            "type":"Services"
        }
    ],
    "sg:phone":"+1 931 853 7285",
    "sg:postcode":"38469",
    "sg:province":"TN",
    "sg:tags":[
        "clergy"
    ],
    "wof:name":"Freedom Christian Church",
    "wof:placetype":"venue"
},
  "geometry": {"coordinates":[-87.412672,35.101728],"type":"Point"}
}