{
  "type": "Feature",
  "properties": {
    "iso:country":"US",
    "sg:address":"7459 Sparta Hwy",
    "sg:city":"Crossville",
    "sg:classifiers":[
        {
            "category":"Shopping",
            "subcategory":"Hobbies, Toys, & Games",
            "type":"Retail Goods"
        }
    ],
    "sg:phone":"+1 931 277 3776",
    "sg:postcode":"38572",
    "sg:province":"TN",
    "sg:tags":[
        "equipment",
        "ceramic",
        "supply"
    ],
    "wof:name":"Creative Ceramics",
    "wof:placetype":"venue"
},
  "geometry": {"coordinates":[-85.15242499999999,35.96937],"type":"Point"}
}