{
  "type": "Feature",
  "properties": {
    "iso:country":"US",
    "sg:address":"305 Hwy 31",
    "sg:city":"Mooresburg",
    "sg:classifiers":[
        {
            "category":"Education",
            "subcategory":"School",
            "type":"Public Place"
        }
    ],
    "sg:phone":"+1 423 272 9597",
    "sg:postcode":"37811",
    "sg:province":"TN",
    "wof:name":"Mooresburg Elementary School",
    "wof:placetype":"venue"
},
  "geometry": {"coordinates":[-83.22825,36.345847],"type":"Point"}
}