{
  "type": "Feature",
  "properties": {
    "iso:country":"US",
    "sg:address":"130 E Washington Ave",
    "sg:city":"Athens",
    "sg:classifiers":[
        {
            "category":"Insurance",
            "subcategory":"Insurance Agent",
            "type":"Services"
        }
    ],
    "sg:phone":"+1 423 745 0875",
    "sg:postcode":"37303",
    "sg:province":"TN",
    "wof:name":"Autoinsurance Network Inc",
    "wof:placetype":"venue"
},
  "geometry": {"coordinates":[-84.592175,35.44317],"type":"Point"}
}