{
  "type": "Feature",
  "properties": {
    "iso:country":"US",
    "sg:address":"2965 Bannockburn Rd",
    "sg:city":"Memphis",
    "sg:classifiers":[
        {
            "category":"Shopping",
            "subcategory":"Clothing, Apparel, & Fashions",
            "type":"Retail Goods"
        }
    ],
    "sg:phone":"+1 901 358 8296",
    "sg:postcode":"38128",
    "sg:province":"TN",
    "wof:name":"Shop With Mr Sean",
    "wof:placetype":"venue"
},
  "geometry": {"coordinates":[-89.958946,35.206125],"type":"Point"}
}