{
  "type": "Feature",
  "properties": {
    "addr:full":"83 Industrial Park Dr Hendersonville TN 37075",
    "addr:housenumber":"83",
    "addr:postcode":"37075",
    "addr:street":"Industrial Park Dr",
    "iso:country":"US",
    "sg:address":"83 Industrial Park Dr",
    "sg:city":"Hendersonville",
    "sg:classifiers":[
        {
            "category":"Home & Garden",
            "subcategory":"Furniture",
            "type":"Retail Goods"
        }
    ],
    "sg:phone":"+1 615 264 9370",
    "sg:postcode":"37075",
    "sg:province":"TN",
    "sg:tags":[
        "top",
        "counter"
    ],
    "wof:name":"Elite Installation & Design",
    "wof:placetype":"venue"
},
  "geometry": {"coordinates":[-86.637022,36.308993],"type":"Point"}
}