{
  "type": "Feature",
  "properties": {
    "iso:country":"US",
    "sg:address":"1361 Elvis Presley Blvd",
    "sg:city":"Memphis",
    "sg:classifiers":[
        {
            "category":"Health Services",
            "subcategory":"Clinic",
            "type":"Services"
        },
        {
            "category":"Health Services",
            "subcategory":"Health Practitioner",
            "type":"Services"
        }
    ],
    "sg:phone":"+1 901 346 4321",
    "sg:postcode":"38106",
    "sg:province":"TN",
    "sg:tags":[
        "therapist",
        "therapy",
        "physical"
    ],
    "wof:name":"Omega Rehab Group Inc",
    "wof:placetype":"venue"
},
  "geometry": {"coordinates":[-90.021582,35.108818],"type":"Point"}
}