{
  "type": "Feature",
  "properties": {
    "addr:full":"1215 Spring Place Rd SE Cleveland TN 37311",
    "addr:housenumber":"1215",
    "addr:postcode":"37311",
    "addr:street":"Spring Place Rd Se",
    "iso:country":"US",
    "sg:address":"1215 Spring Place Rd SE",
    "sg:city":"Cleveland",
    "sg:classifiers":[
        {
            "category":"Autos & Motor Vehicles",
            "subcategory":"Automobile Sales",
            "type":"Retail Goods"
        }
    ],
    "sg:phone":"+1 423 339 3327",
    "sg:postcode":"37311",
    "sg:province":"TN",
    "sg:tags":[
        "car",
        "dealer"
    ],
    "wof:name":"Prince Auto Sales",
    "wof:placetype":"venue"
},
  "geometry": {"coordinates":[-84.871696,35.14126],"type":"Point"}
}