{
  "type": "Feature",
  "properties": {
    "addr:full":"3100 Houston Levee Rd Germantown TN 38139",
    "addr:housenumber":"3100",
    "addr:postcode":"38139",
    "addr:street":"Houston Levee Rd",
    "iso:country":"US",
    "sg:address":"3100 Houston Levee Rd",
    "sg:city":"Germantown",
    "sg:classifiers":[
        {
            "category":"Organizations",
            "subcategory":"Religious Organization",
            "type":"Services"
        }
    ],
    "sg:phone":"+1 901 854 7100",
    "sg:postcode":"38139",
    "sg:province":"TN",
    "wof:name":"Church of Rdmer Epscpal Church",
    "wof:placetype":"venue"
},
  "geometry": {"coordinates":[-89.731971,35.064649],"type":"Point"}
}