{
  "type": "Feature",
  "properties": {
    "iso:country":"US",
    "sg:address":"6250 Ringgold Rd",
    "sg:city":"Chattanooga",
    "sg:classifiers":[
        {
            "category":"Professional",
            "type":"Services"
        }
    ],
    "sg:phone":"+1 423 296 9955",
    "sg:postcode":"37412",
    "sg:province":"TN",
    "wof:name":"O S M S",
    "wof:placetype":"venue"
},
  "geometry": {"coordinates":[-85.212547,34.989695],"type":"Point"}
}