{
  "type": "Feature",
  "properties": {
    "iso:country":"US",
    "sg:address":"627 S Pkwy E",
    "sg:city":"Memphis",
    "sg:classifiers":[
        {
            "category":"Shopping",
            "subcategory":"Clothing, Apparel, & Fashions",
            "type":"Retail Goods"
        }
    ],
    "sg:phone":"+1 901 775 5180",
    "sg:postcode":"38106",
    "sg:province":"TN",
    "sg:tags":[
        "family"
    ],
    "wof:name":"Mike Fashions",
    "wof:placetype":"venue"
},
  "geometry": {"coordinates":[-90.041842,35.107174],"type":"Point"}
}