{
  "type": "Feature",
  "properties": {
    "addr:full":"369 Garfield St Mc Minnville TN 37110",
    "addr:housenumber":"369",
    "addr:postcode":"37110",
    "addr:street":"Garfield St",
    "iso:country":"US",
    "sg:address":"369 Garfield St",
    "sg:city":"Mc Minnville",
    "sg:classifiers":[
        {
            "category":"Social Services",
            "subcategory":"Child Care",
            "type":"Services"
        }
    ],
    "sg:phone":"+1 931 473 9402",
    "sg:postcode":"37110",
    "sg:province":"TN",
    "wof:name":"Smarty Pants Learning Ctr",
    "wof:placetype":"venue"
},
  "geometry": {"coordinates":[-85.782495,35.689674],"type":"Point"}
}