{
  "type": "Feature",
  "properties": {
    "addr:full":"3625 Gleason Dr Chattanooga TN 37412",
    "addr:housenumber":"3625",
    "addr:postcode":"37412",
    "addr:street":"Gleason Dr",
    "iso:country":"US",
    "sg:address":"3625 Gleason Dr",
    "sg:city":"Chattanooga",
    "sg:classifiers":[
        {
            "category":"Banks & Credit Unions",
            "subcategory":"Investment Brokerage",
            "type":"Services"
        },
        {
            "category":"Professional",
            "subcategory":"Management & Consulting",
            "type":"Services"
        }
    ],
    "sg:phone":"+1 423 629 9787",
    "sg:postcode":"37412",
    "sg:province":"TN",
    "sg:tags":[
        "consultant",
        "planning",
        "financial"
    ],
    "wof:name":"Christian Chattanooga Finance",
    "wof:placetype":"venue"
},
  "geometry": {"coordinates":[-85.25102800000001,35.009844],"type":"Point"}
}