{
  "type": "Feature",
  "properties": {
    "iso:country":"US",
    "sg:address":"399 Tripp Rd",
    "sg:city":"Lawrenceburg",
    "sg:classifiers":[
        {
            "category":"Health Services",
            "subcategory":"Clinic",
            "type":"Services"
        }
    ],
    "sg:phone":"+1 931 762 5510",
    "sg:postcode":"38464",
    "sg:province":"TN",
    "sg:tags":[
        "home"
    ],
    "wof:name":"NHC Home Care",
    "wof:placetype":"venue"
},
  "geometry": {"coordinates":[-87.339252,35.27382],"type":"Point"}
}