{
  "type": "Feature",
  "properties": {
    "iso:country":"US",
    "sg:address":"1151 Williamson St",
    "sg:city":"Milan",
    "sg:classifiers":[
        {
            "category":"Professional",
            "subcategory":"Advertising",
            "type":"Services"
        }
    ],
    "sg:phone":"+1 731 723 8330",
    "sg:postcode":"38358",
    "sg:province":"TN",
    "sg:tags":[
        "distribution"
    ],
    "wof:name":"West Tennessee Cabnt Dstrbtng",
    "wof:placetype":"venue"
},
  "geometry": {"coordinates":[-88.75943599999999,35.919533],"type":"Point"}
}