{
  "type": "Feature",
  "properties": {
    "addr:full":"625 State Hwy 114 S Scotts Hill TN 38374",
    "addr:housenumber":"625",
    "addr:postcode":"38374",
    "addr:street":"State Hwy 114 S",
    "iso:country":"US",
    "sg:address":"625 State Hwy 114 S",
    "sg:city":"Scotts Hill",
    "sg:classifiers":[
        {
            "category":"Restaurant",
            "type":"Food & Drink"
        }
    ],
    "sg:phone":"+1 731 549 3600",
    "sg:postcode":"38374",
    "sg:province":"TN",
    "wof:name":"Pizza Shack",
    "wof:placetype":"venue"
},
  "geometry": {"coordinates":[-88.250128,35.522165],"type":"Point"}
}