{
  "type": "Feature",
  "properties": {
    "addr:full":"3024 Bus Park Cir Goodlettsville TN 37072",
    "addr:housenumber":"3024",
    "addr:postcode":"37072",
    "addr:street":"Bus Park Cir",
    "iso:country":"US",
    "sg:address":"3024 Bus Park Cir",
    "sg:city":"Goodlettsville",
    "sg:classifiers":[
        {
            "category":"Insurance",
            "subcategory":"Insurance Agent",
            "type":"Services"
        }
    ],
    "sg:phone":"+1 615 851 3600",
    "sg:postcode":"37072",
    "sg:province":"TN",
    "wof:name":"State Farm Insurance",
    "wof:placetype":"venue"
},
  "geometry": {"coordinates":[-86.701573,36.329789],"type":"Point"}
}