{
  "type": "Feature",
  "properties": {
    "addr:full":"2000 Taft Hwy Signal Mountain TN 37377",
    "addr:housenumber":"2000",
    "addr:postcode":"37377",
    "addr:street":"Taft Hwy",
    "iso:country":"US",
    "sg:address":"2000 Taft Hwy",
    "sg:city":"Signal Mountain",
    "sg:classifiers":[
        {
            "category":"Home & Garden",
            "subcategory":"Hardware",
            "type":"Retail Goods"
        }
    ],
    "sg:phone":"+1 423 517 0177",
    "sg:postcode":"37377",
    "sg:province":"TN",
    "sg:tags":[
        "store"
    ],
    "sg:website":"www.acehardware.com",
    "wof:name":"Ace Hardware",
    "wof:placetype":"venue"
},
  "geometry": {"coordinates":[-85.317345,35.155231],"type":"Point"}
}