{
  "type": "Feature",
  "properties": {
    "addr:full":"9730 Shelbyville Pike Bell Buckle TN 37020",
    "addr:housenumber":"9730",
    "addr:postcode":"37020",
    "addr:street":"Shelbyville Pike",
    "iso:country":"US",
    "sg:address":"9730 Shelbyville Pike",
    "sg:city":"Bell Buckle",
    "sg:classifiers":[
        {
            "category":"Retail",
            "subcategory":"Auto Repair",
            "type":"Services"
        }
    ],
    "sg:phone":"+1 615 233 5512",
    "sg:postcode":"37020",
    "sg:province":"TN",
    "sg:tags":[
        "truck"
    ],
    "wof:name":"Gambill's Truck & Surplus",
    "wof:placetype":"venue"
},
  "geometry": {"coordinates":[-86.416254,35.714001],"type":"Point"}
}