{
  "type": "Feature",
  "properties": {
    "iso:country":"US",
    "sg:address":"958 Tobitt Rd",
    "sg:city":"Mc Minnville",
    "sg:classifiers":[
        {
            "category":"Professional",
            "subcategory":"Accounting & Tax Preparation",
            "type":"Services"
        }
    ],
    "sg:phone":"+1 931 939 3426",
    "sg:postcode":"37110",
    "sg:province":"TN",
    "sg:tags":[
        "accountant"
    ],
    "wof:name":"David Bratcher Accounting Svc",
    "wof:placetype":"venue"
},
  "geometry": {"coordinates":[-85.91898399999999,35.745846],"type":"Point"}
}