{
  "type": "Feature",
  "properties": {
    "iso:country":"US",
    "sg:address":"256 S Camilla St",
    "sg:city":"Memphis",
    "sg:classifiers":[
        {
            "category":"Personal",
            "subcategory":"Beauty Salon",
            "type":"Services"
        }
    ],
    "sg:phone":"+1 901 527 7000",
    "sg:postcode":"38104",
    "sg:province":"TN",
    "wof:name":"Heavenly Hair Care",
    "wof:placetype":"venue"
},
  "geometry": {"coordinates":[-90.026861,35.13537],"type":"Point"}
}