{
  "type": "Feature",
  "properties": {
    "iso:country":"US",
    "sg:address":"201 Terminal Rd",
    "sg:city":"Clarksville",
    "sg:classifiers":[
        {
            "category":"Retail",
            "subcategory":"Auto Repair",
            "type":"Services"
        }
    ],
    "sg:phone":"+1 800 800 2727",
    "sg:postcode":"37040",
    "sg:province":"TN",
    "sg:tags":[
        "glass",
        "replacement"
    ],
    "wof:name":"Safelite Autoglass",
    "wof:placetype":"venue"
},
  "geometry": {"coordinates":[-87.298039,36.588573],"type":"Point"}
}