{
  "type": "Feature",
  "properties": {
    "iso:country":"US",
    "sg:address":"319 Broad St",
    "sg:city":"Baxter",
    "sg:classifiers":[
        {
            "category":"Health Services",
            "subcategory":"Doctor",
            "type":"Services"
        }
    ],
    "sg:phone":"+1 931 858 3790",
    "sg:postcode":"38544",
    "sg:province":"TN",
    "sg:tags":[
        "clinic"
    ],
    "wof:name":"Putnam County Rural Health",
    "wof:placetype":"venue"
},
  "geometry": {"coordinates":[-85.639844,36.154845],"type":"Point"}
}