{
  "type": "Feature",
  "properties": {
    "iso:country":"US",
    "sg:address":"2097 Pennington Gap",
    "sg:city":"Memphis",
    "sg:classifiers":[
        {
            "category":"Real Estate",
            "subcategory":"Real Estate Agent",
            "type":"Services"
        }
    ],
    "sg:phone":"+1 901 213 4621",
    "sg:postcode":"38134",
    "sg:province":"TN",
    "sg:tags":[
        "management"
    ],
    "wof:name":"M & S Properties",
    "wof:placetype":"venue"
},
  "geometry": {"coordinates":[-89.875488,35.183141],"type":"Point"}
}