{
  "type": "Feature",
  "properties": {
    "iso:country":"US",
    "sg:address":"8024 Hamilton Mill Dr",
    "sg:city":"Chattanooga",
    "sg:classifiers":[
        {
            "category":"Banks & Credit Unions",
            "subcategory":"Financial Services",
            "type":"Services"
        }
    ],
    "sg:phone":"+1 423 893 7385",
    "sg:postcode":"37421",
    "sg:province":"TN",
    "sg:tags":[
        "investor"
    ],
    "wof:name":"Legacy Investment Group LLC",
    "wof:placetype":"venue"
},
  "geometry": {"coordinates":[-85.13075000000001,35.027838],"type":"Point"}
}