{
  "type": "Feature",
  "properties": {
    "iso:country":"US",
    "sg:address":"24 Music Sq W",
    "sg:city":"Nashville",
    "sg:classifiers":[
        {
            "category":"Professional",
            "subcategory":"Art Services",
            "type":"Services"
        }
    ],
    "sg:phone":"+1 615 254 4536",
    "sg:postcode":"37203",
    "sg:province":"TN",
    "sg:tags":[
        "graphic",
        "designer"
    ],
    "sg:website":"www.billtylerdesigns.com",
    "wof:name":"Bill Tyler Designs",
    "wof:placetype":"venue"
},
  "geometry": {"coordinates":[-86.79286500000001,36.152001],"type":"Point"}
}