{
  "type": "Feature",
  "properties": {
    "iso:country":"US",
    "sg:address":"516 W Main St",
    "sg:city":"Smithville",
    "sg:classifiers":[
        {
            "category":"Shopping",
            "subcategory":"Pharmacy",
            "type":"Retail Goods"
        }
    ],
    "sg:phone":"+1 615 597 7822",
    "sg:postcode":"37166",
    "sg:province":"TN",
    "wof:name":"Johnny's Drugs",
    "wof:placetype":"venue"
},
  "geometry": {"coordinates":[-85.82815600000001,35.959168],"type":"Point"}
}