{
  "type": "Feature",
  "properties": {
    "iso:country":"US",
    "sg:address":"1057 Park St",
    "sg:city":"Westmoreland",
    "sg:classifiers":[
        {
            "category":"Manufacturing",
            "subcategory":"Printing",
            "type":"Manufacturing & Wholesale Goods"
        }
    ],
    "sg:phone":"+1 615 644 4841",
    "sg:postcode":"37186",
    "sg:province":"TN",
    "sg:tags":[
        "newspaper",
        "publishing"
    ],
    "wof:name":"Rural Newspaper Inc",
    "wof:placetype":"venue"
},
  "geometry": {"coordinates":[-86.247314,36.562605],"type":"Point"}
}