{
  "type": "Feature",
  "properties": {
    "iso:country":"US",
    "sg:address":"117 S Church St",
    "sg:city":"Murfreesboro",
    "sg:classifiers":[
        {
            "category":"Shopping",
            "subcategory":"Clothing, Apparel, & Fashions",
            "type":"Retail Goods"
        }
    ],
    "sg:phone":"+1 615 890 3807",
    "sg:postcode":"37130",
    "sg:province":"TN",
    "sg:tags":[
        "aerobic",
        "dance",
        "sh",
        "costume"
    ],
    "wof:name":"Middle Tenn Dnce Gymnstics Sup",
    "wof:placetype":"venue"
},
  "geometry": {"coordinates":[-86.39138800000001,35.845774],"type":"Point"}
}