{
  "type": "Feature",
  "properties": {
    "addr:full":"694 S Willow Ave Cookeville TN 38501",
    "addr:housenumber":"694",
    "addr:postcode":"38501",
    "addr:street":"S Willow Ave",
    "iso:country":"US",
    "sg:address":"694 S Willow Ave",
    "sg:city":"Cookeville",
    "sg:classifiers":[
        {
            "category":"Organizations",
            "subcategory":"Religious Organization",
            "type":"Services"
        }
    ],
    "sg:phone":"+1 931 526 3086",
    "sg:postcode":"38501",
    "sg:province":"TN",
    "sg:website":"www.younglife.org",
    "wof:name":"Young Life",
    "wof:placetype":"venue"
},
  "geometry": {"coordinates":[-85.51903900000001,36.148471],"type":"Point"}
}