{
  "type": "Feature",
  "properties": {
    "addr:full":"700 Colonial Rd Memphis TN 38117",
    "addr:housenumber":"700",
    "addr:postcode":"38117",
    "addr:street":"Colonial Rd",
    "iso:country":"US",
    "sg:address":"700 Colonial Rd",
    "sg:city":"Memphis",
    "sg:classifiers":[
        {
            "category":"Banks & Credit Unions",
            "subcategory":"Investment Brokerage",
            "type":"Services"
        },
        {
            "category":"Professional",
            "type":"Services"
        }
    ],
    "sg:phone":"+1 901 767 5576",
    "sg:postcode":"38117",
    "sg:province":"TN",
    "sg:tags":[
        "advisory",
        "financial"
    ],
    "wof:name":"Cks Advisors LLC",
    "wof:placetype":"venue"
},
  "geometry": {"coordinates":[-89.90195300000001,35.113944],"type":"Point"}
}