{
  "type": "Feature",
  "properties": {
    "addr:full":"2515 Volunteer Pkwy Bristol TN 37620",
    "addr:housenumber":"2515",
    "addr:postcode":"37620",
    "addr:street":"Volunteer Pkwy",
    "iso:country":"US",
    "sg:address":"2515 Volunteer Pkwy",
    "sg:city":"Bristol",
    "sg:classifiers":[
        {
            "category":"Retail",
            "subcategory":"Veterinary Services",
            "type":"Services"
        }
    ],
    "sg:phone":"+1 423 968 7543",
    "sg:postcode":"37620",
    "sg:province":"TN",
    "wof:name":"Volunteer Animal Clinic",
    "wof:placetype":"venue"
},
  "geometry": {"coordinates":[-82.24767300000001,36.530746],"type":"Point"}
}