{
  "type": "Feature",
  "properties": {
    "iso:country":"US",
    "sg:address":"205 Burrville Rd",
    "sg:city":"Sunbright",
    "sg:classifiers":[
        {
            "category":"Professional",
            "type":"Services"
        }
    ],
    "sg:phone":"+1 423 628 5283",
    "sg:postcode":"37726",
    "sg:province":"TN",
    "sg:tags":[
        "establishment"
    ],
    "wof:name":"WECO",
    "wof:placetype":"venue"
},
  "geometry": {"coordinates":[-84.779016,36.255294],"type":"Point"}
}