{
  "type": "Feature",
  "properties": {
    "iso:country":"US",
    "sg:address":"123 Market St E",
    "sg:city":"Fayetteville",
    "sg:classifiers":[
        {
            "category":"Shopping",
            "subcategory":"Used Merchandise",
            "type":"Retail Goods"
        }
    ],
    "sg:phone":"+1 931 438 0585",
    "sg:postcode":"37334",
    "sg:province":"TN",
    "sg:tags":[
        "antique"
    ],
    "wof:name":"His & Hers Antique Shop",
    "wof:placetype":"venue"
},
  "geometry": {"coordinates":[-86.57044399999999,35.1512],"type":"Point"}
}