{
  "type": "Feature",
  "properties": {
    "addr:full":"839 Briley Pkwy Nashville TN 37217",
    "addr:housenumber":"839",
    "addr:postcode":"37217",
    "addr:street":"Briley Pkwy",
    "iso:country":"US",
    "sg:address":"839 Briley Pkwy",
    "sg:city":"Nashville",
    "sg:classifiers":[
        {
            "category":"Restaurant",
            "type":"Food & Drink"
        }
    ],
    "sg:phone":"+1 615 361 6649",
    "sg:postcode":"37217",
    "sg:province":"TN",
    "wof:name":"Denny's",
    "wof:placetype":"venue"
},
  "geometry": {"coordinates":[-86.70030800000001,36.139517],"type":"Point"}
}