{
  "type": "Feature",
  "properties": {
    "iso:country":"US",
    "sg:address":"1332 Volunteer Pkwy",
    "sg:city":"Bristol",
    "sg:classifiers":[
        {
            "category":"Banks & Credit Unions",
            "subcategory":"Bank",
            "type":"Services"
        }
    ],
    "sg:phone":"+1 423 764 3133",
    "sg:postcode":"37620",
    "sg:province":"TN",
    "sg:tags":[
        "personal",
        "institution"
    ],
    "wof:name":"TranSouth Financial Corp",
    "wof:placetype":"venue"
},
  "geometry": {"coordinates":[-82.20943200000001,36.562066],"type":"Point"}
}