{
  "type": "Feature",
  "properties": {
    "iso:country":"US",
    "sg:address":"109 Jordan Dr",
    "sg:city":"Chattanooga",
    "sg:classifiers":[
        {
            "category":"Banks & Credit Unions",
            "subcategory":"Bank",
            "type":"Services"
        }
    ],
    "sg:phone":"+1 423 238 4663",
    "sg:postcode":"37421",
    "sg:province":"TN",
    "sg:tags":[
        "loan",
        "real estate"
    ],
    "wof:name":"Galaxy Mortgage",
    "wof:placetype":"venue"
},
  "geometry": {"coordinates":[-85.163434,35.045485],"type":"Point"}
}