{
  "type": "Feature",
  "properties": {
    "iso:country":"US",
    "sg:address":"5186 Brunswick Rd",
    "sg:city":"Brunswick",
    "sg:classifiers":[
        {
            "category":"Freight",
            "type":"Transportation"
        }
    ],
    "sg:phone":"+1 901 372 2686",
    "sg:postcode":"38002",
    "sg:province":"TN",
    "sg:tags":[
        "commercial",
        "storage"
    ],
    "wof:name":"Brunswick Mini Storage Sales",
    "wof:placetype":"venue"
},
  "geometry": {"coordinates":[-89.768524,35.267076],"type":"Point"}
}