{
  "type": "Feature",
  "properties": {
    "addr:full":"4960 Edmondson Pike Nashville TN 37211",
    "addr:housenumber":"4960",
    "addr:postcode":"37211",
    "addr:street":"Edmondson Pike",
    "iso:country":"US",
    "sg:address":"4960 Edmondson Pike",
    "sg:city":"Nashville",
    "sg:classifiers":[
        {
            "category":"Building & Trades",
            "subcategory":"Construction",
            "type":"Services"
        }
    ],
    "sg:phone":"+1 615 315 0853",
    "sg:postcode":"37211",
    "sg:province":"TN",
    "sg:tags":[
        "hanging",
        "contractor"
    ],
    "wof:name":"Shiny Painting",
    "wof:placetype":"venue"
},
  "geometry": {"coordinates":[-86.731347,36.07446],"type":"Point"}
}