{
  "type": "Feature",
  "properties": {
    "addr:full":"9700 Westland Dr Knoxville TN 37922",
    "addr:housenumber":"9700",
    "addr:postcode":"37922",
    "addr:street":"Westland Dr",
    "iso:country":"US",
    "sg:address":"9700 Westland Dr",
    "sg:city":"Knoxville",
    "sg:classifiers":[
        {
            "category":"Insurance",
            "subcategory":"Insurance Agent",
            "type":"Services"
        }
    ],
    "sg:phone":"+1 865 588 7000",
    "sg:postcode":"37922",
    "sg:province":"TN",
    "wof:name":"William Blount & Assoc",
    "wof:placetype":"venue"
},
  "geometry": {"coordinates":[-84.09549,35.875378],"type":"Point"}
}