{
  "type": "Feature",
  "properties": {
    "iso:country":"US",
    "sg:address":"2406 Chiswood St",
    "sg:city":"Memphis",
    "sg:classifiers":[
        {
            "category":"Retail",
            "subcategory":"Auto Repair",
            "type":"Services"
        }
    ],
    "sg:phone":"+1 901 382 7000",
    "sg:postcode":"38134",
    "sg:province":"TN",
    "sg:tags":[
        "body",
        "automobile",
        "painting"
    ],
    "sg:website":"http://www.memphiscollision.com",
    "wof:name":"Memphis Collision Repair",
    "wof:placetype":"venue"
},
  "geometry": {"coordinates":[-89.892669,35.191056],"type":"Point"}
}