{
  "type": "Feature",
  "properties": {
    "iso:country":"US",
    "sg:address":"539 Skyview Dr",
    "sg:city":"Ashland City",
    "sg:classifiers":[
        {
            "category":"Professional",
            "subcategory":"Business Services",
            "type":"Services"
        }
    ],
    "sg:phone":"+1 615 792 6442",
    "sg:postcode":"37015",
    "sg:province":"TN",
    "wof:name":"Fatboy Enterprises",
    "wof:placetype":"venue"
},
  "geometry": {"coordinates":[-87.060924,36.291992],"type":"Point"}
}