{
  "type": "Feature",
  "properties": {
    "addr:full":"4015 Raleigh Millington Rd Memphis TN 38128",
    "addr:housenumber":"4015",
    "addr:postcode":"38128",
    "addr:street":"Raleigh Millington Rd",
    "iso:country":"US",
    "sg:address":"4015 Raleigh Millington Rd",
    "sg:city":"Memphis",
    "sg:classifiers":[
        {
            "category":"Recreation",
            "subcategory":"Arcade",
            "type":"Entertainment"
        }
    ],
    "sg:phone":"+1 901 377 3525",
    "sg:postcode":"38128",
    "sg:province":"TN",
    "sg:tags":[
        "device",
        "operator",
        "amusement",
        "devices",
        "repair"
    ],
    "wof:name":"Double D Amusements & Vending",
    "wof:placetype":"venue"
},
  "geometry": {"coordinates":[-89.925759,35.237347],"type":"Point"}
}