{
  "type": "Feature",
  "properties": {
    "addr:full":"800 Old Hickory Blvd Jackson TN 38305",
    "addr:housenumber":"800",
    "addr:postcode":"38305",
    "addr:street":"Old Hickory Blvd",
    "iso:country":"US",
    "sg:address":"800 Old Hickory Blvd",
    "sg:city":"Jackson",
    "sg:classifiers":[
        {
            "category":"Real Estate",
            "subcategory":"Real Estate Operator",
            "type":"Services"
        }
    ],
    "sg:phone":"+1 731 668 3157",
    "sg:postcode":"38305",
    "sg:province":"TN",
    "sg:tags":[
        "apartment",
        "complex"
    ],
    "wof:name":"Hartland Place Apartments",
    "wof:placetype":"venue"
},
  "geometry": {"coordinates":[-88.858626,35.655124],"type":"Point"}
}