{
  "type": "Feature",
  "properties": {
    "iso:country":"US",
    "sg:address":"317 S Jackson St",
    "sg:city":"Tullahoma",
    "sg:classifiers":[
        {
            "category":"Shopping",
            "subcategory":"Clothing, Apparel, & Fashions",
            "type":"Retail Goods"
        }
    ],
    "sg:phone":"+1 931 461 5648",
    "sg:postcode":"37388",
    "sg:province":"TN",
    "sg:tags":[
        "knit"
    ],
    "wof:name":"Imagiknit",
    "wof:placetype":"venue"
},
  "geometry": {"coordinates":[-86.209126,35.359224],"type":"Point"}
}