{
  "type": "Feature",
  "properties": {
    "addr:full":"1109 W Andrew Johnson Hwy Greeneville TN 37745",
    "addr:housenumber":"1109",
    "addr:postcode":"37745",
    "addr:street":"W Andrew Johnson Hwy",
    "iso:country":"US",
    "sg:address":"1109 W Andrew Johnson Hwy",
    "sg:city":"Greeneville",
    "sg:classifiers":[
        {
            "category":"Retail",
            "subcategory":"Repair Shop",
            "type":"Services"
        }
    ],
    "sg:phone":"+1 423 639 9626",
    "sg:postcode":"37745",
    "sg:province":"TN",
    "sg:tags":[
        "equipment",
        "hydraulic"
    ],
    "wof:name":"Industrial Hydraulics Repairs",
    "wof:placetype":"venue"
},
  "geometry": {"coordinates":[-82.84123099999999,36.172815],"type":"Point"}
}