{
  "type": "Feature",
  "properties": {
    "addr:full":"19 Public Sq Columbia TN 38401",
    "addr:housenumber":"19",
    "addr:postcode":"38401",
    "addr:street":"Public Sq",
    "iso:country":"US",
    "sg:address":"19 Public Sq",
    "sg:city":"Columbia",
    "sg:classifiers":[
        {
            "category":"Professional",
            "subcategory":"Accounting & Tax Preparation",
            "type":"Services"
        }
    ],
    "sg:phone":"+1 931 381 5047",
    "sg:postcode":"38401",
    "sg:province":"TN",
    "sg:tags":[
        "accountant"
    ],
    "wof:name":"Joe T Kelley CPA",
    "wof:placetype":"venue"
},
  "geometry": {"coordinates":[-87.033835,35.614483],"type":"Point"}
}