{
  "type": "Feature",
  "properties": {
    "iso:country":"US",
    "sg:address":"1008 Lebanon Pike",
    "sg:city":"Nashville",
    "sg:classifiers":[
        {
            "category":"Autos & Motor Vehicles",
            "subcategory":"Automobile Sales",
            "type":"Retail Goods"
        }
    ],
    "sg:phone":"+1 615 726 4945",
    "sg:postcode":"37210",
    "sg:province":"TN",
    "sg:tags":[
        "used"
    ],
    "wof:name":"Import Connection Inc",
    "wof:placetype":"venue"
},
  "geometry": {"coordinates":[-86.72232200000001,36.153678],"type":"Point"}
}