{
  "type": "Feature",
  "properties": {
    "iso:country":"US",
    "sg:address":"2400 Crestmoor Rd",
    "sg:city":"Nashville",
    "sg:phone":"+1 615 292 3552",
    "sg:postcode":"37215",
    "sg:province":"TN",
    "sg:website":"http://www.prudentialproperties.com",
    "wof:name":"Prudential Woodmont Realty",
    "wof:placetype":"venue"
},
  "geometry": {"coordinates":[-86.818169,36.10981],"type":"Point"}
}