{
  "type": "Feature",
  "properties": {
    "iso:country":"US",
    "sg:address":"279 Jd Yarnell Industrial Pkwy",
    "sg:city":"Clinton",
    "sg:classifiers":[
        {
            "category":"Professional",
            "type":"Services"
        }
    ],
    "sg:phone":"+1 865 457 5888",
    "sg:postcode":"37716",
    "sg:province":"TN",
    "sg:tags":[
        "establishment"
    ],
    "wof:name":"Ten Tech",
    "wof:placetype":"venue"
},
  "geometry": {"coordinates":[-84.105372,36.103326],"type":"Point"}
}