{
  "type": "Feature",
  "properties": {
    "addr:full":"4000 7th Ave Chattanooga TN 37407",
    "addr:housenumber":"4000",
    "addr:postcode":"37407",
    "addr:street":"7Th Ave",
    "iso:country":"US",
    "sg:address":"4000 7th Ave",
    "sg:city":"Chattanooga",
    "sg:classifiers":[
        {
            "category":"Building & Trades",
            "subcategory":"Plumbing",
            "type":"Services"
        }
    ],
    "sg:phone":"+1 423 867 2290",
    "sg:postcode":"37407",
    "sg:province":"TN",
    "sg:tags":[
        "mechanical",
        "contractor"
    ],
    "wof:name":"Southeast Co Inc",
    "wof:placetype":"venue"
},
  "geometry": {"coordinates":[-85.28643700000001,34.997738],"type":"Point"}
}