{
  "type": "Feature",
  "properties": {
    "addr:full":"841 Wren Rd Goodlettsville TN 37072",
    "addr:housenumber":"841",
    "addr:postcode":"37072",
    "addr:street":"Wren Rd",
    "iso:country":"US",
    "sg:address":"841 Wren Rd",
    "sg:city":"Goodlettsville",
    "sg:classifiers":[
        {
            "category":"Personal",
            "type":"Services"
        },
        {
            "category":"Personal",
            "subcategory":"Beauty Salon",
            "type":"Services"
        }
    ],
    "sg:phone":"+1 615 851 1243",
    "sg:postcode":"37072",
    "sg:province":"TN",
    "wof:name":"New Image Hair & Tanning",
    "wof:placetype":"venue"
},
  "geometry": {"coordinates":[-86.703172,36.302682],"type":"Point"}
}