{
  "type": "Feature",
  "properties": {
    "iso:country":"US",
    "sg:address":"1721 Main St",
    "sg:city":"White Pine",
    "sg:classifiers":[
        {
            "category":"Health Services",
            "subcategory":"Doctor",
            "type":"Services"
        }
    ],
    "sg:phone":"+1 865 674 2709",
    "sg:postcode":"37890",
    "sg:province":"TN",
    "sg:tags":[
        "physician",
        "surgeon"
    ],
    "wof:name":"James Schindler MD",
    "wof:placetype":"venue"
},
  "geometry": {"coordinates":[-83.285251,36.109569],"type":"Point"}
}