{
  "type": "Feature",
  "properties": {
    "iso:country":"US",
    "sg:address":"6034 Weems Rd",
    "sg:city":"Knoxville",
    "sg:classifiers":[
        {
            "category":"Organizations",
            "subcategory":"Membership Organization",
            "type":"Services"
        }
    ],
    "sg:phone":"+1 865 689 2572",
    "sg:postcode":"37918",
    "sg:province":"TN",
    "wof:name":"Wisdomquest",
    "wof:placetype":"venue"
},
  "geometry": {"coordinates":[-83.93657,36.046755],"type":"Point"}
}