{
  "type": "Feature",
  "properties": {
    "addr:full":"1830 Shady Hill Reagan Rd Reagan TN 38368",
    "addr:housenumber":"1830",
    "addr:postcode":"38368",
    "addr:street":"Shady Hill Reagan Rd",
    "iso:country":"US",
    "sg:address":"1830 Shady Hill Reagan Rd",
    "sg:city":"Reagan",
    "sg:phone":"+1 731 968 6228",
    "sg:postcode":"38368",
    "sg:province":"TN",
    "sg:tags":[
        "farm",
        "corn",
        "soybean"
    ],
    "wof:name":"Joe Smith",
    "wof:placetype":"venue"
},
  "geometry": {"coordinates":[-88.336359,35.544054],"type":"Point"}
}