{
  "type": "Feature",
  "properties": {
    "addr:full":"1900 Bishops Bridge Rd Knoxville TN 37922",
    "addr:housenumber":"1900",
    "addr:postcode":"37922",
    "addr:street":"Bishops Bridge Rd",
    "iso:country":"US",
    "sg:address":"1900 Bishops Bridge Rd",
    "sg:city":"Knoxville",
    "sg:classifiers":[
        {
            "category":"Building & Trades",
            "subcategory":"Plumbing",
            "type":"Services"
        }
    ],
    "sg:phone":"+1 865 977 6039",
    "sg:postcode":"37922",
    "sg:province":"TN",
    "sg:tags":[
        "plumbing",
        "contractor"
    ],
    "wof:name":"Ready Eddie Plumbing Svc",
    "wof:placetype":"venue"
},
  "geometry": {"coordinates":[-84.064786,35.867478],"type":"Point"}
}