{
  "type": "Feature",
  "properties": {
    "addr:full":"7773 Ridgewood Rd Goodlettsville TN 37072",
    "addr:housenumber":"7773",
    "addr:postcode":"37072",
    "addr:street":"Ridgewood Rd",
    "iso:country":"US",
    "sg:address":"7773 Ridgewood Rd",
    "sg:city":"Goodlettsville",
    "sg:classifiers":[
        {
            "category":"Retail",
            "subcategory":"Repair Shop",
            "type":"Services"
        }
    ],
    "sg:phone":"+1 615 876 2969",
    "sg:postcode":"37072",
    "sg:province":"TN",
    "sg:tags":[
        "antique",
        "restoring"
    ],
    "wof:name":"James L Horne Antiquary",
    "wof:placetype":"venue"
},
  "geometry": {"coordinates":[-86.84108999999999,36.355086],"type":"Point"}
}