{
  "type": "Feature",
  "properties": {
    "iso:country":"US",
    "sg:address":"2655 Teaster Ln",
    "sg:city":"Pigeon Forge",
    "sg:classifiers":[
        {
            "category":"Shopping",
            "subcategory":"Shoes",
            "type":"Retail Goods"
        }
    ],
    "sg:phone":"+1 865 428 6555",
    "sg:postcode":"37863",
    "sg:province":"TN",
    "sg:tags":[
        "shoe",
        "store"
    ],
    "wof:name":"Wolveirng Worldwide",
    "wof:placetype":"venue"
},
  "geometry": {"coordinates":[-83.55472899999999,35.794374],"type":"Point"}
}