{
  "type": "Feature",
  "properties": {
    "addr:full":"333 Troy Cir SW Knoxville TN 37919",
    "addr:housenumber":"333",
    "addr:postcode":"37919",
    "addr:street":"Troy Cir Sw",
    "iso:country":"US",
    "sg:address":"333 Troy Cir SW",
    "sg:city":"Knoxville",
    "sg:classifiers":[
        {
            "category":"Professional",
            "subcategory":"Business Services",
            "type":"Services"
        }
    ],
    "sg:phone":"+1 865 558 0081",
    "sg:postcode":"37919",
    "sg:province":"TN",
    "sg:tags":[
        "interior",
        "consultant",
        "design",
        "decorator"
    ],
    "wof:name":"Molly Bland Interiors",
    "wof:placetype":"venue"
},
  "geometry": {"coordinates":[-84.004813,35.927423],"type":"Point"}
}