{
  "type": "Feature",
  "properties": {
    "iso:country":"US",
    "sg:address":"654 Eads Bluff Rd NW",
    "sg:city":"Georgetown",
    "sg:classifiers":[
        {
            "category":"Travel",
            "subcategory":"Travel Agent",
            "type":"Entertainment"
        }
    ],
    "sg:phone":"+1 423 336 3058",
    "sg:postcode":"37310",
    "sg:province":"TN",
    "sg:tags":[
        "agency"
    ],
    "wof:name":"Ad Mart Services Inc",
    "wof:placetype":"venue"
},
  "geometry": {"coordinates":[-84.85838800000001,35.325831],"type":"Point"}
}