{
  "type": "Feature",
  "properties": {
    "iso:country":"US",
    "sg:address":"1519 Preston Dr",
    "sg:city":"Nashville",
    "sg:classifiers":[
        {
            "category":"Building & Trades",
            "subcategory":"Construction",
            "type":"Services"
        }
    ],
    "sg:phone":"+1 615 226 4848",
    "sg:postcode":"37206",
    "sg:province":"TN",
    "sg:tags":[
        "house"
    ],
    "wof:name":"J B Home Repair",
    "wof:placetype":"venue"
},
  "geometry": {"coordinates":[-86.71724,36.195448],"type":"Point"}
}