{
  "type": "Feature",
  "properties": {
    "iso:country":"US",
    "sg:address":"209 Church St",
    "sg:city":"Lafayette",
    "sg:classifiers":[
        {
            "category":"Retail",
            "subcategory":"Auto Repair",
            "type":"Services"
        }
    ],
    "sg:phone":"+1 615 666 5459",
    "sg:postcode":"37083",
    "sg:province":"TN",
    "sg:tags":[
        "automobile",
        "electric"
    ],
    "wof:name":"S & J Auto Electric",
    "wof:placetype":"venue"
},
  "geometry": {"coordinates":[-86.032955,36.522373],"type":"Point"}
}