{
  "type": "Feature",
  "properties": {
    "iso:country":"US",
    "sg:address":"1302 Plymouth Ave",
    "sg:city":"Nashville",
    "sg:classifiers":[
        {
            "category":"Professional",
            "subcategory":"Management & Consulting",
            "type":"Services"
        }
    ],
    "sg:phone":"+1 615 258 3900",
    "sg:postcode":"37216",
    "sg:province":"TN",
    "wof:name":"Over Road Marketing Co",
    "wof:placetype":"venue"
},
  "geometry": {"coordinates":[-86.711584,36.220532],"type":"Point"}
}