{
  "type": "Feature",
  "properties": {
    "addr:full":"5494 Stage Rd Bartlett TN 38134",
    "addr:housenumber":"5494",
    "addr:postcode":"38134",
    "addr:street":"Stage Rd",
    "iso:country":"US",
    "sg:address":"5494 Stage Rd",
    "sg:city":"Bartlett",
    "sg:classifiers":[
        {
            "category":"Retail",
            "subcategory":"Auto Repair",
            "type":"Services"
        }
    ],
    "sg:phone":"+1 901 371 8873",
    "sg:postcode":"38134",
    "sg:province":"TN",
    "sg:tags":[
        "automotive",
        "brake"
    ],
    "wof:name":"C & F Brake & Alignment Svc",
    "wof:placetype":"venue"
},
  "geometry": {"coordinates":[-89.879867,35.205139],"type":"Point"}
}