{
  "type": "Feature",
  "properties": {
    "iso:country":"US",
    "sg:address":"2747 Hillsboro Hwy",
    "sg:city":"Manchester",
    "sg:classifiers":[
        {
            "category":"Autos & Motor Vehicles",
            "subcategory":"Automobile Sales",
            "type":"Retail Goods"
        }
    ],
    "sg:phone":"+1 931 728 2212",
    "sg:postcode":"37355",
    "sg:province":"TN",
    "sg:tags":[
        "car",
        "dealer"
    ],
    "sg:website":"www.robertsnissan.com",
    "wof:name":"Roberts Nissan",
    "wof:placetype":"venue"
},
  "geometry": {"coordinates":[-86.042328,35.454058],"type":"Point"}
}