{
  "type": "Feature",
  "properties": {
    "addr:full":"7822 Eden Ln Knoxville TN 37938",
    "addr:housenumber":"7822",
    "addr:postcode":"37938",
    "addr:street":"Eden Ln",
    "iso:country":"US",
    "sg:address":"7822 Eden Ln",
    "sg:city":"Knoxville",
    "sg:classifiers":[
        {
            "category":"Banks & Credit Unions",
            "subcategory":"Bank",
            "type":"Services"
        }
    ],
    "sg:phone":"+1 865 922 9341",
    "sg:postcode":"37938",
    "sg:province":"TN",
    "sg:tags":[
        "loan",
        "broker"
    ],
    "wof:name":"Kathy Winstead",
    "wof:placetype":"venue"
},
  "geometry": {"coordinates":[-83.966477,36.090116],"type":"Point"}
}