{
  "type": "Feature",
  "properties": {
    "iso:country":"US",
    "sg:address":"34 Kirby Rd",
    "sg:city":"Lexington",
    "sg:classifiers":[
        {
            "category":"Manufacturing",
            "subcategory":"Metals",
            "type":"Manufacturing & Wholesale Goods"
        }
    ],
    "sg:phone":"+1 731 968 6774",
    "sg:postcode":"38315",
    "sg:province":"TN",
    "sg:tags":[
        "machine",
        "screw",
        "product"
    ],
    "sg:website":"www.truecutmanufacturing.com",
    "wof:name":"Truecut Manufacturing",
    "wof:placetype":"venue"
},
  "geometry": {"coordinates":[-88.594174,35.272589],"type":"Point"}
}