{
  "type": "Feature",
  "properties": {
    "iso:country":"US",
    "sg:address":"434 Mauldeth Rd",
    "sg:city":"Chattanooga",
    "sg:classifiers":[
        {
            "category":"Building & Trades",
            "subcategory":"Construction",
            "type":"Services"
        }
    ],
    "sg:phone":"+1 423 874 0810",
    "sg:postcode":"37415",
    "sg:province":"TN",
    "sg:tags":[
        "paper",
        "painting",
        "hanging"
    ],
    "wof:name":"Michael Bunch Painting",
    "wof:placetype":"venue"
},
  "geometry": {"coordinates":[-85.279455,35.115372],"type":"Point"}
}