{
  "type": "Feature",
  "properties": {
    "iso:country":"US",
    "sg:address":"3315 Overton Crossing St",
    "sg:city":"Memphis",
    "sg:classifiers":[
        {
            "category":"Real Estate",
            "subcategory":"Real Estate Services",
            "type":"Services"
        },
        {
            "category":"Wholesale",
            "subcategory":"Machinery & Supplies",
            "type":"Manufacturing & Wholesale Goods"
        },
        {
            "category":"Manufacturing",
            "subcategory":"Building Materials",
            "type":"Manufacturing & Wholesale Goods"
        }
    ],
    "sg:phone":"+1 901 357 1261",
    "sg:postcode":"38127",
    "sg:province":"TN",
    "sg:tags":[
        "industrial",
        "gage",
        "equipment",
        "pump",
        "filtering",
        "gauge"
    ],
    "sg:website":"http://www.centromemphis.com",
    "wof:name":"Centro Inc",
    "wof:placetype":"venue"
},
  "geometry": {"coordinates":[-89.99396,35.216734],"type":"Point"}
}