{
  "type": "Feature",
  "properties": {
    "addr:full":"682 Spurgeon Ln Blountville TN 37617",
    "addr:housenumber":"682",
    "addr:postcode":"37617",
    "addr:street":"Spurgeon Ln",
    "iso:country":"US",
    "sg:address":"682 Spurgeon Ln",
    "sg:city":"Blountville",
    "sg:classifiers":[
        {
            "category":"Professional",
            "type":"Services"
        }
    ],
    "sg:phone":"+1 423 279 9182",
    "sg:postcode":"37617",
    "sg:province":"TN",
    "wof:name":"Moto Planet Inc",
    "wof:placetype":"venue"
},
  "geometry": {"coordinates":[-82.419259,36.498912],"type":"Point"}
}