{
  "type": "Feature",
  "properties": {
    "addr:full":"124 Thunder Trl Hohenwald TN 38462",
    "addr:housenumber":"124",
    "addr:postcode":"38462",
    "addr:street":"Thunder Trl",
    "iso:country":"US",
    "sg:address":"124 Thunder Trl",
    "sg:city":"Hohenwald",
    "sg:classifiers":[
        {
            "category":"Retail",
            "subcategory":"Auto Repair",
            "type":"Services"
        }
    ],
    "sg:phone":"+1 931 796 4221",
    "sg:postcode":"38462",
    "sg:province":"TN",
    "sg:tags":[
        "general"
    ],
    "wof:name":"Dans Garage",
    "wof:placetype":"venue"
},
  "geometry": {"coordinates":[-87.543836,35.573339],"type":"Point"}
}