{
  "type": "Feature",
  "properties": {
    "iso:country":"US",
    "sg:address":"4045 S Access Rd",
    "sg:city":"Chattanooga",
    "sg:classifiers":[
        {
            "category":"Manufacturing",
            "subcategory":"Building Materials",
            "type":"Manufacturing & Wholesale Goods"
        }
    ],
    "sg:phone":"+1 423 622 4988",
    "sg:postcode":"37406",
    "sg:province":"TN",
    "wof:name":"Custom Counters & Doors",
    "wof:placetype":"venue"
},
  "geometry": {"coordinates":[-85.21535900000001,35.087745],"type":"Point"}
}