{
  "type": "Feature",
  "properties": {
    "iso:country":"US",
    "sg:address":"8085 Sag Harbor Cir",
    "sg:city":"Cordova",
    "sg:classifiers":[
        {
            "category":"Building & Trades",
            "subcategory":"Cleaning & Sanitation",
            "type":"Services"
        }
    ],
    "sg:phone":"+1 901 337 1267",
    "sg:postcode":"38016",
    "sg:province":"TN",
    "sg:tags":[
        "maintenance"
    ],
    "wof:name":"Pib Cleaning Services Inc",
    "wof:placetype":"venue"
},
  "geometry": {"coordinates":[-89.79549900000001,35.165957],"type":"Point"}
}