{
  "type": "Feature",
  "properties": {
    "iso:country":"US",
    "sg:address":"1173 Trotwood Ave",
    "sg:city":"Columbia",
    "sg:classifiers":[
        {
            "category":"Restaurant",
            "type":"Food & Drink"
        }
    ],
    "sg:phone":"+1 931 388 0804",
    "sg:postcode":"38401",
    "sg:province":"TN",
    "sg:tags":[
        "eating"
    ],
    "wof:name":"Buckhead Coffee House",
    "wof:placetype":"venue"
},
  "geometry": {"coordinates":[-87.060323,35.610936],"type":"Point"}
}