{
  "type": "Feature",
  "properties": {
    "iso:country":"US",
    "sg:address":"530 Harding Pl",
    "sg:city":"Nashville",
    "sg:classifiers":[
        {
            "category":"Real Estate",
            "subcategory":"Real Estate Operator",
            "type":"Services"
        }
    ],
    "sg:phone":"+1 615 832 0677",
    "sg:postcode":"37211",
    "sg:province":"TN",
    "sg:tags":[
        "building",
        "apartment"
    ],
    "wof:name":"Candlewood Apts",
    "wof:placetype":"venue"
},
  "geometry": {"coordinates":[-86.734458,36.077187],"type":"Point"}
}