{
  "type": "Feature",
  "properties": {
    "iso:country":"US",
    "sg:address":"191 E Industrial Park Dr",
    "sg:city":"Jacksboro",
    "sg:classifiers":[
        {
            "category":"Professional",
            "type":"Services"
        }
    ],
    "sg:phone":"+1 423 562 3357",
    "sg:postcode":"37757",
    "sg:province":"TN",
    "wof:name":"Altech Fabrication Inc",
    "wof:placetype":"venue"
},
  "geometry": {"coordinates":[-84.168108,36.324023],"type":"Point"}
}