{
  "type": "Feature",
  "properties": {
    "addr:full":"115 Lloyd St Oneida TN 37841",
    "addr:housenumber":"115",
    "addr:postcode":"37841",
    "addr:street":"Lloyd St",
    "iso:country":"US",
    "sg:address":"115 Lloyd St",
    "sg:city":"Oneida",
    "sg:classifiers":[
        {
            "category":"Organizations",
            "subcategory":"Community Association",
            "type":"Services"
        }
    ],
    "sg:phone":"+1 423 569 3776",
    "sg:postcode":"37841",
    "sg:province":"TN",
    "sg:tags":[
        "club"
    ],
    "wof:name":"Iue-Cwa Local 706",
    "wof:placetype":"venue"
},
  "geometry": {"coordinates":[-84.526079,36.50465],"type":"Point"}
}