{
  "type": "Feature",
  "properties": {
    "addr:full":"6263 N Lee Hwy Cleveland TN 37312",
    "addr:housenumber":"6263",
    "addr:postcode":"37312",
    "addr:street":"N Lee Hwy",
    "iso:country":"US",
    "sg:address":"6263 N Lee Hwy",
    "sg:city":"Cleveland",
    "sg:classifiers":[
        {
            "category":"Professional",
            "subcategory":"Engineering",
            "type":"Services"
        }
    ],
    "sg:phone":"+1 423 473 6010",
    "sg:postcode":"37312",
    "sg:province":"TN",
    "wof:name":"Custom Control Solutions",
    "wof:placetype":"venue"
},
  "geometry": {"coordinates":[-84.81631400000001,35.230101],"type":"Point"}
}