{
  "type": "Feature",
  "properties": {
    "iso:country":"US",
    "sg:address":"6 Public Sq",
    "sg:city":"Lawrenceburg",
    "sg:classifiers":[
        {
            "category":"Communications",
            "subcategory":"Radio Station",
            "type":"Services"
        }
    ],
    "sg:phone":"+1 931 762 4411",
    "sg:postcode":"38464",
    "sg:province":"TN",
    "sg:tags":[
        "company",
        "broadcasting"
    ],
    "wof:name":"WDXE",
    "wof:placetype":"venue"
},
  "geometry": {"coordinates":[-87.3351,35.240356],"type":"Point"}
}