{
  "type": "Feature",
  "properties": {
    "iso:country":"US",
    "sg:address":"239 Palisade St",
    "sg:city":"Memphis",
    "sg:classifiers":[
        {
            "category":"Shopping",
            "subcategory":"Used Merchandise",
            "type":"Retail Goods"
        }
    ],
    "sg:phone":"+1 901 324 8105",
    "sg:postcode":"38111",
    "sg:province":"TN",
    "wof:name":"Walker Antiques",
    "wof:placetype":"venue"
},
  "geometry": {"coordinates":[-89.95209800000001,35.124893],"type":"Point"}
}