{
  "type": "Feature",
  "properties": {
    "iso:country":"US",
    "sg:address":"8415 Woodbrook Dr",
    "sg:city":"Knoxville",
    "sg:classifiers":[
        {
            "category":"Insurance",
            "subcategory":"Insurance Agent",
            "type":"Services"
        }
    ],
    "sg:phone":"+1 865 693 6745",
    "sg:postcode":"37919",
    "sg:province":"TN",
    "sg:website":"www.tmlrmp.org",
    "wof:name":"TML Risk Management Pool",
    "wof:placetype":"venue"
},
  "geometry": {"coordinates":[-84.054587,35.912646],"type":"Point"}
}