{
  "type": "Feature",
  "properties": {
    "addr:full":"269 Germantown Bend Cove Cordova TN 38018",
    "addr:housenumber":"269",
    "addr:postcode":"38018",
    "addr:street":"Germantown Bend Cove",
    "iso:country":"US",
    "sg:address":"269 Germantown Bend Cove",
    "sg:city":"Cordova",
    "sg:classifiers":[
        {
            "category":"Insurance",
            "subcategory":"Life Insurance",
            "type":"Services"
        }
    ],
    "sg:phone":"+1 901 753 9561",
    "sg:postcode":"38018",
    "sg:province":"TN",
    "sg:tags":[
        "carrier"
    ],
    "wof:name":"Thompson Wendell",
    "wof:placetype":"venue"
},
  "geometry": {"coordinates":[-89.79838100000001,35.123571],"type":"Point"}
}