{
  "type": "Feature",
  "properties": {
    "addr:full":"1943 Bristol Ct Brentwood TN 37027",
    "addr:housenumber":"1943",
    "addr:postcode":"37027",
    "addr:street":"Bristol Ct",
    "iso:country":"US",
    "sg:address":"1943 Bristol Ct",
    "sg:city":"Brentwood",
    "sg:classifiers":[
        {
            "category":"Professional",
            "subcategory":"Business Services",
            "type":"Services"
        }
    ],
    "sg:phone":"+1 615 377 8881",
    "sg:postcode":"37027",
    "sg:province":"TN",
    "wof:name":"Grotto",
    "wof:placetype":"venue"
},
  "geometry": {"coordinates":[-86.864238,36.040156],"type":"Point"}
}