{
  "type": "Feature",
  "properties": {
    "addr:full":"1631 16th Ave N Nashville TN 37208",
    "addr:housenumber":"1631",
    "addr:postcode":"37208",
    "addr:street":"16Th Ave N",
    "iso:country":"US",
    "sg:address":"1631 16th Ave N",
    "sg:city":"Nashville",
    "sg:classifiers":[
        {
            "category":"Food & Beverages",
            "subcategory":"Candy",
            "type":"Retail Goods"
        }
    ],
    "sg:phone":"+1 615 320 3147",
    "sg:postcode":"37208",
    "sg:province":"TN",
    "wof:name":"Caruthers Deli",
    "wof:placetype":"venue"
},
  "geometry": {"coordinates":[-86.806719,36.1765],"type":"Point"}
}