{
  "type": "Feature",
  "properties": {
    "addr:full":"22 Mayberry St Sparta TN 38583",
    "addr:housenumber":"22",
    "addr:postcode":"38583",
    "addr:street":"Mayberry St",
    "iso:country":"US",
    "sg:address":"22 Mayberry St",
    "sg:city":"Sparta",
    "sg:classifiers":[
        {
            "category":"Restaurant",
            "type":"Food & Drink"
        }
    ],
    "sg:phone":"+1 931 836 2118",
    "sg:postcode":"38583",
    "sg:province":"TN",
    "wof:name":"2nd Act Deli",
    "wof:placetype":"venue"
},
  "geometry": {"coordinates":[-85.47651,35.932007],"type":"Point"}
}