{
  "type": "Feature",
  "properties": {
    "addr:full":"6720 Heritage Business Ct Chattanooga TN 37421",
    "addr:housenumber":"6720",
    "addr:postcode":"37421",
    "addr:street":"Heritage Business Ct",
    "iso:country":"US",
    "sg:address":"6720 Heritage Business Ct",
    "sg:city":"Chattanooga",
    "sg:classifiers":[
        {
            "category":"Professional",
            "subcategory":"Management & Consulting",
            "type":"Services"
        }
    ],
    "sg:phone":"+1 423 553 1945",
    "sg:postcode":"37421",
    "sg:province":"TN",
    "sg:tags":[
        "consultant",
        "safety"
    ],
    "wof:name":"Tennessee Safety & Health Inc",
    "wof:placetype":"venue"
},
  "geometry": {"coordinates":[-85.17444500000001,35.035746],"type":"Point"}
}