{
  "type": "Feature",
  "properties": {
    "addr:full":"2228 Massa Ave Cookeville TN 38501",
    "addr:housenumber":"2228",
    "addr:postcode":"38501",
    "addr:street":"Massa Ave",
    "iso:country":"US",
    "sg:address":"2228 Massa Ave",
    "sg:city":"Cookeville",
    "sg:classifiers":[
        {
            "category":"Real Estate",
            "subcategory":"Real Estate Operator",
            "type":"Services"
        }
    ],
    "sg:phone":"+1 931 526 1349",
    "sg:postcode":"38501",
    "sg:province":"TN",
    "sg:tags":[
        "property",
        "lessor"
    ],
    "wof:name":"J Ford Homes",
    "wof:placetype":"venue"
},
  "geometry": {"coordinates":[-85.50206799999999,36.195351],"type":"Point"}
}