{
  "type": "Feature",
  "properties": {
    "addr:full":"4456 Miser Station Rd Friendsville TN 37737",
    "addr:housenumber":"4456",
    "addr:postcode":"37737",
    "addr:street":"Miser Station Rd",
    "iso:country":"US",
    "sg:address":"4456 Miser Station Rd",
    "sg:city":"Friendsville",
    "sg:classifiers":[
        {
            "category":"Autos & Motor Vehicles",
            "subcategory":"Automobile Sales",
            "type":"Retail Goods"
        }
    ],
    "sg:phone":"+1 865 995 2884",
    "sg:postcode":"37737",
    "sg:province":"TN",
    "sg:tags":[
        "used"
    ],
    "wof:name":"Wayne R Special Interest Auto",
    "wof:placetype":"venue"
},
  "geometry": {"coordinates":[-84.10680600000001,35.784436],"type":"Point"}
}