{
  "type": "Feature",
  "properties": {
    "iso:country":"US",
    "sg:address":"116 N Hill St",
    "sg:city":"Morristown",
    "sg:classifiers":[
        {
            "category":"Shopping",
            "subcategory":"Discount & Variety Stores",
            "type":"Retail Goods"
        }
    ],
    "sg:phone":"+1 423 586 6210",
    "sg:postcode":"37814",
    "sg:province":"TN",
    "sg:tags":[
        "merchandise",
        "general"
    ],
    "wof:name":"Tennessee Bank Supply",
    "wof:placetype":"venue"
},
  "geometry": {"coordinates":[-83.29160299999999,36.215132],"type":"Point"}
}