{
  "type": "Feature",
  "properties": {
    "addr:full":"101 S Court Sq Livingston TN 38570",
    "addr:housenumber":"101",
    "addr:postcode":"38570",
    "addr:street":"S Court Sq",
    "iso:country":"US",
    "sg:address":"101 S Court Sq",
    "sg:city":"Livingston",
    "sg:classifiers":[
        {
            "category":"Shopping",
            "subcategory":"Clothing, Apparel, & Fashions",
            "type":"Retail Goods"
        }
    ],
    "sg:phone":"+1 931 823 7572",
    "sg:postcode":"38570",
    "sg:province":"TN",
    "sg:tags":[
        "m"
    ],
    "wof:name":"Wedding Loft",
    "wof:placetype":"venue"
},
  "geometry": {"coordinates":[-85.32248199999999,36.383191],"type":"Point"}
}