{
  "type": "Feature",
  "properties": {
    "iso:country":"US",
    "sg:address":"2927 Sidco Dr",
    "sg:city":"Nashville",
    "sg:classifiers":[
        {
            "category":"Professional",
            "subcategory":"Art Services",
            "type":"Services"
        }
    ],
    "sg:phone":"+1 615 255 6655",
    "sg:postcode":"37204",
    "sg:province":"TN",
    "sg:tags":[
        "commercial",
        "design"
    ],
    "wof:name":"Design 29",
    "wof:placetype":"venue"
},
  "geometry": {"coordinates":[-86.755463,36.109595],"type":"Point"}
}