{
  "type": "Feature",
  "properties": {
    "addr:full":"7510 Lee Hwy Ste 5 Chattanooga TN 37421",
    "addr:housenumber":"7510",
    "addr:postcode":"37421",
    "addr:street":"Lee Hwy Ste 5",
    "iso:country":"US",
    "sg:address":"7510 Lee Hwy Ste 5",
    "sg:city":"Chattanooga",
    "sg:classifiers":[
        {
            "category":"Personal",
            "subcategory":"Nail Salon",
            "type":"Services"
        }
    ],
    "sg:phone":"+1 423 510 8131",
    "sg:postcode":"37421",
    "sg:province":"TN",
    "wof:name":"Hollywood Nails",
    "wof:placetype":"venue"
},
  "geometry": {"coordinates":[-85.140531,35.056924],"type":"Point"}
}