{
  "type": "Feature",
  "properties": {
    "iso:country":"US",
    "sg:address":"208 North Ave",
    "sg:city":"Henderson",
    "sg:classifiers":[
        {
            "category":"Health Services",
            "subcategory":"Doctor",
            "type":"Services"
        }
    ],
    "sg:phone":"+1 731 989 2116",
    "sg:postcode":"38340",
    "sg:province":"TN",
    "sg:tags":[
        "medical"
    ],
    "wof:name":"Erika Creech MD",
    "wof:placetype":"venue"
},
  "geometry": {"coordinates":[-88.642558,35.441086],"type":"Point"}
}