{
  "type": "Feature",
  "properties": {
    "iso:country":"US",
    "sg:address":"1705 Division St",
    "sg:city":"Nashville",
    "sg:classifiers":[
        {
            "category":"Insurance",
            "subcategory":"Insurance Agent",
            "type":"Services"
        }
    ],
    "sg:phone":"+1 615 248 0080",
    "sg:postcode":"37203",
    "sg:province":"TN",
    "wof:name":"AFLAC",
    "wof:placetype":"venue"
},
  "geometry": {"coordinates":[-86.79344399999999,36.151807],"type":"Point"}
}