{
  "type": "Feature",
  "properties": {
    "addr:full":"303 W Rhea Ave Spring City TN 37381",
    "addr:housenumber":"303",
    "addr:postcode":"37381",
    "addr:street":"W Rhea Ave",
    "iso:country":"US",
    "sg:address":"303 W Rhea Ave",
    "sg:city":"Spring City",
    "sg:classifiers":[
        {
            "category":"Travel",
            "subcategory":"Hotels & Motels",
            "type":"Entertainment"
        }
    ],
    "sg:phone":"+1 423 365 9425",
    "sg:postcode":"37381",
    "sg:province":"TN",
    "wof:name":"Candlewick Inn",
    "wof:placetype":"venue"
},
  "geometry": {"coordinates":[-84.862601,35.694556],"type":"Point"}
}