{
  "type": "Feature",
  "properties": {
    "addr:full":"1538 Industrial Rd Greeneville TN 37745",
    "addr:housenumber":"1538",
    "addr:postcode":"37745",
    "addr:street":"Industrial Rd",
    "iso:country":"US",
    "sg:address":"1538 Industrial Rd",
    "sg:city":"Greeneville",
    "sg:classifiers":[
        {
            "category":"Wholesale",
            "subcategory":"Machinery & Supplies",
            "type":"Manufacturing & Wholesale Goods"
        }
    ],
    "sg:phone":"+1 423 787 7979",
    "sg:postcode":"37745",
    "sg:province":"TN",
    "sg:tags":[
        "mason",
        "contractor"
    ],
    "wof:name":"East Tennessee Mason Supl Inc",
    "wof:placetype":"venue"
},
  "geometry": {"coordinates":[-82.802424,36.184459],"type":"Point"}
}