{
  "type": "Feature",
  "properties": {
    "iso:country":"US",
    "sg:address":"6074 E Brainerd Rd",
    "sg:city":"Chattanooga",
    "sg:classifiers":[
        {
            "category":"Banks & Credit Unions",
            "subcategory":"Investment Brokerage",
            "type":"Services"
        }
    ],
    "sg:phone":"+1 423 899 6964",
    "sg:postcode":"37421",
    "sg:province":"TN",
    "sg:tags":[
        "security"
    ],
    "wof:name":"Raymond James Financial Svc",
    "wof:placetype":"venue"
},
  "geometry": {"coordinates":[-85.204251,35.016579],"type":"Point"}
}