{
  "type": "Feature",
  "properties": {
    "iso:country":"US",
    "sg:address":"1028 Aslinger Cir",
    "sg:city":"Sale Creek",
    "sg:classifiers":[
        {
            "category":"Professional",
            "type":"Services"
        }
    ],
    "sg:phone":"+1 423 332 6170",
    "sg:postcode":"37373",
    "sg:province":"TN",
    "wof:name":"James R Grant",
    "wof:placetype":"venue"
},
  "geometry": {"coordinates":[-85.062951,35.410586],"type":"Point"}
}