{
  "type": "Feature",
  "properties": {
    "iso:country":"US",
    "sg:address":"800 S Anderson St",
    "sg:city":"Tullahoma",
    "sg:classifiers":[
        {
            "category":"Retail",
            "subcategory":"Auto Repair",
            "type":"Services"
        }
    ],
    "sg:phone":"+1 931 455 0004",
    "sg:postcode":"37388",
    "sg:province":"TN",
    "sg:tags":[
        "muffler",
        "exhaust",
        "system"
    ],
    "wof:name":"Performance Plus Custom Exhst",
    "wof:placetype":"venue"
},
  "geometry": {"coordinates":[-86.19824,35.357782],"type":"Point"}
}