{
  "type": "Feature",
  "properties": {
    "iso:country":"US",
    "sg:address":"5034 Thoroughbred Ln",
    "sg:city":"Brentwood",
    "sg:classifiers":[
        {
            "category":"Insurance",
            "subcategory":"Insurance Agent",
            "type":"Services"
        }
    ],
    "sg:phone":"+1 615 370 4611",
    "sg:postcode":"37027",
    "sg:province":"TN",
    "sg:tags":[
        "security"
    ],
    "wof:name":"Assett Alliance",
    "wof:placetype":"venue"
},
  "geometry": {"coordinates":[-86.79309600000001,36.036994],"type":"Point"}
}