{
  "type": "Feature",
  "properties": {
    "iso:country":"US",
    "sg:address":"5819 Old Harding Pike",
    "sg:city":"Nashville",
    "sg:classifiers":[
        {
            "category":"Social Services",
            "type":"Services"
        }
    ],
    "sg:phone":"+1 615 353 1444",
    "sg:postcode":"37205",
    "sg:province":"TN",
    "wof:name":"Susan Edd Hammonds-White",
    "wof:placetype":"venue"
},
  "geometry": {"coordinates":[-86.87219399999999,36.101439],"type":"Point"}
}