{
  "type": "Feature",
  "properties": {
    "iso:country":"US",
    "sg:address":"3690 N Chapel Rd",
    "sg:city":"Franklin",
    "sg:classifiers":[
        {
            "category":"Professional",
            "subcategory":"Business Services",
            "type":"Services"
        }
    ],
    "sg:phone":"+1 615 790 3255",
    "sg:postcode":"37067",
    "sg:province":"TN",
    "wof:name":"Jerrell Cagle Auctions",
    "wof:placetype":"venue"
},
  "geometry": {"coordinates":[-86.76611200000001,35.906275],"type":"Point"}
}