{
  "type": "Feature",
  "properties": {
    "iso:country":"US",
    "sg:address":"980 Sandys Camp Rd",
    "sg:city":"Big Sandy",
    "sg:classifiers":[
        {
            "category":"Travel",
            "subcategory":"Hotels & Motels",
            "type":"Entertainment"
        }
    ],
    "sg:phone":"+1 731 593 1121",
    "sg:postcode":"38221",
    "sg:province":"TN",
    "sg:tags":[
        "operation"
    ],
    "wof:name":"Reith Resort",
    "wof:placetype":"venue"
},
  "geometry": {"coordinates":[-87.980086,36.302766],"type":"Point"}
}