{
  "type": "Feature",
  "properties": {
    "addr:full":"5326 Lance Dr Knoxville TN 37909",
    "addr:housenumber":"5326",
    "addr:postcode":"37909",
    "addr:street":"Lance Dr",
    "iso:country":"US",
    "sg:address":"5326 Lance Dr",
    "sg:city":"Knoxville",
    "sg:classifiers":[
        {
            "category":"Farming",
            "subcategory":"Livestock Farm",
            "type":"Manufacturing & Wholesale Goods"
        }
    ],
    "sg:phone":"+1 865 588 8445",
    "sg:postcode":"37909",
    "sg:province":"TN",
    "sg:tags":[
        "feedlot",
        "field",
        "crop",
        "beef",
        "cattle"
    ],
    "wof:name":"Estate of Jh Shanks",
    "wof:placetype":"venue"
},
  "geometry": {"coordinates":[-83.998929,35.953876],"type":"Point"}
}