{
  "type": "Feature",
  "properties": {
    "addr:full":"871 Bluff Rd Drummonds TN 38023",
    "addr:housenumber":"871",
    "addr:postcode":"38023",
    "addr:street":"Bluff Rd",
    "iso:country":"US",
    "sg:address":"871 Bluff Rd",
    "sg:city":"Drummonds",
    "sg:classifiers":[
        {
            "category":"Utilities",
            "subcategory":"Refuse",
            "type":"Services"
        },
        {
            "category":"Transit Center",
            "subcategory":"Freight",
            "type":"Transportation"
        },
        {
            "category":"Freight",
            "type":"Transportation"
        }
    ],
    "sg:phone":"+1 901 835 4050",
    "sg:postcode":"38023",
    "sg:province":"TN",
    "sg:tags":[
        "local",
        "truck",
        "trucking-motor",
        "dump",
        "trucking"
    ],
    "wof:name":"Randy Armstrong Trucking",
    "wof:placetype":"venue"
},
  "geometry": {"coordinates":[-89.947419,35.433782],"type":"Point"}
}