{
  "type": "Feature",
  "properties": {
    "addr:full":"6616 Asheville Hwy Knoxville TN 37924",
    "addr:housenumber":"6616",
    "addr:postcode":"37924",
    "addr:street":"Asheville Hwy",
    "iso:country":"US",
    "sg:address":"6616 Asheville Hwy",
    "sg:city":"Knoxville",
    "sg:classifiers":[
        {
            "category":"Shopping",
            "subcategory":"Used Merchandise",
            "type":"Retail Goods"
        }
    ],
    "sg:phone":"+1 865 637 4321",
    "sg:postcode":"37924",
    "sg:province":"TN",
    "sg:tags":[
        "shop",
        "thrift"
    ],
    "wof:name":"One More Thrift",
    "wof:placetype":"venue"
},
  "geometry": {"coordinates":[-83.80951399999999,36.018282],"type":"Point"}
}