{
  "type": "Feature",
  "properties": {
    "addr:full":"7312 Shallowford Rd Chattanooga TN 37421",
    "addr:housenumber":"7312",
    "addr:postcode":"37421",
    "addr:street":"Shallowford Rd",
    "iso:country":"US",
    "sg:address":"7312 Shallowford Rd",
    "sg:city":"Chattanooga",
    "sg:classifiers":[
        {
            "category":"Travel",
            "subcategory":"Hotels & Motels",
            "type":"Entertainment"
        }
    ],
    "sg:phone":"+1 423 893 7400",
    "sg:postcode":"37421",
    "sg:province":"TN",
    "wof:name":"Wingate Inn",
    "wof:placetype":"venue"
},
  "geometry": {"coordinates":[-85.154454,35.041924],"type":"Point"}
}