{
  "type": "Feature",
  "properties": {
    "iso:country":"US",
    "sg:address":"364 Jernigan Rd",
    "sg:city":"Portland",
    "sg:classifiers":[
        {
            "category":"Professional",
            "subcategory":"Computer Services",
            "type":"Services"
        }
    ],
    "sg:phone":"+1 615 202 9712",
    "sg:postcode":"37148",
    "sg:province":"TN",
    "sg:tags":[
        "consultant",
        "designer"
    ],
    "wof:name":"Absolute Information Solutions",
    "wof:placetype":"venue"
},
  "geometry": {"coordinates":[-86.588955,36.574497],"type":"Point"}
}