{
  "type": "Feature",
  "properties": {
    "iso:country":"US",
    "sg:address":"10 N Maple St",
    "sg:city":"Henry",
    "sg:classifiers":[
        {
            "category":"Local Transit",
            "type":"Transportation"
        }
    ],
    "sg:phone":"+1 731 243 3518",
    "sg:postcode":"38231",
    "sg:province":"TN",
    "sg:tags":[
        "passenger"
    ],
    "wof:name":"Scotts Transport",
    "wof:placetype":"venue"
},
  "geometry": {"coordinates":[-88.41902399999999,36.206561],"type":"Point"}
}