{
  "type": "Feature",
  "properties": {
    "addr:full":"2421 E Broadway Ave Maryville TN 37804",
    "addr:housenumber":"2421",
    "addr:postcode":"37804",
    "addr:street":"E Broadway Ave",
    "iso:country":"US",
    "sg:address":"2421 E Broadway Ave",
    "sg:city":"Maryville",
    "sg:classifiers":[
        {
            "category":"Banks & Credit Unions",
            "subcategory":"Bank",
            "type":"Services"
        }
    ],
    "sg:phone":"+1 865 984 1861",
    "sg:postcode":"37804",
    "sg:province":"TN",
    "sg:tags":[
        "loan"
    ],
    "wof:name":"Money To Go",
    "wof:placetype":"venue"
},
  "geometry": {"coordinates":[-83.947168,35.786751],"type":"Point"}
}