{
  "type": "Feature",
  "properties": {
    "iso:country":"US",
    "sg:address":"650 Heil Quaker Ave",
    "sg:city":"Lewisburg",
    "sg:classifiers":[
        {
            "category":"Professional",
            "subcategory":"Management & Consulting",
            "type":"Services"
        }
    ],
    "sg:phone":"+1 931 359 3511",
    "sg:postcode":"37091",
    "sg:province":"TN",
    "sg:tags":[
        "marketing",
        "program"
    ],
    "wof:name":"International Comfort Products",
    "wof:placetype":"venue"
},
  "geometry": {"coordinates":[-86.80296,35.458883],"type":"Point"}
}