{
  "type": "Feature",
  "properties": {
    "iso:country":"US",
    "sg:address":"8685 Timber Creek Dr",
    "sg:city":"Cordova",
    "sg:classifiers":[
        {
            "category":"Shopping",
            "type":"Retail Goods"
        },
        {
            "category":"Autos & Motor Vehicles",
            "subcategory":"Motorcycle Sales",
            "type":"Retail Goods"
        }
    ],
    "sg:phone":"+1 901 757 5947",
    "sg:postcode":"38018",
    "sg:province":"TN",
    "sg:tags":[
        "all",
        "terrain",
        "merchandise"
    ],
    "wof:name":"G & H Discount Atv Supply",
    "wof:placetype":"venue"
},
  "geometry": {"coordinates":[-89.775879,35.148448],"type":"Point"}
}