{
  "type": "Feature",
  "properties": {
    "iso:country":"US",
    "sg:address":"1259 Jackson Felts Rd",
    "sg:city":"Joelton",
    "sg:classifiers":[
        {
            "category":"Building & Trades",
            "subcategory":"Construction",
            "type":"Services"
        }
    ],
    "sg:phone":"+1 615 746 8756",
    "sg:postcode":"37080",
    "sg:province":"TN",
    "sg:tags":[
        "acoustical",
        "contractor"
    ],
    "wof:name":"Advanced Interiors Inc",
    "wof:placetype":"venue"
},
  "geometry": {"coordinates":[-86.934759,36.345881],"type":"Point"}
}