{
  "type": "Feature",
  "properties": {
    "iso:country":"US",
    "sg:address":"1705 Ridgeway Dr",
    "sg:city":"Kingsport",
    "sg:classifiers":[
        {
            "category":"Wholesale",
            "subcategory":"Vending Machines",
            "type":"Manufacturing & Wholesale Goods"
        }
    ],
    "sg:phone":"+1 423 246 9408",
    "sg:postcode":"37664",
    "sg:province":"TN",
    "sg:tags":[
        "operator"
    ],
    "wof:name":"Telecard Wholesale Co",
    "wof:placetype":"venue"
},
  "geometry": {"coordinates":[-82.50261999999999,36.527008],"type":"Point"}
}