{
  "type": "Feature",
  "properties": {
    "iso:country":"US",
    "sg:address":"100 W North Creek Rd",
    "sg:city":"Springfield",
    "sg:classifiers":[
        {
            "category":"Banks & Credit Unions",
            "subcategory":"Bank",
            "type":"Services"
        }
    ],
    "sg:phone":"+1 615 384 1590",
    "sg:postcode":"37167",
    "sg:province":"TN",
    "sg:tags":[
        "loan"
    ],
    "sg:website":"www.thecreditunionrobtco.org",
    "wof:name":"Credit Union-Robertson County",
    "wof:placetype":"venue"
},
  "geometry": {"coordinates":[-86.562335,35.897671],"type":"Point"}
}