{
  "type": "Feature",
  "properties": {
    "iso:country":"US",
    "sg:address":"204 S Church Ave",
    "sg:city":"Henderson",
    "sg:classifiers":[
        {
            "category":"Restaurant",
            "type":"Food & Drink"
        }
    ],
    "sg:phone":"+1 731 989 2816",
    "sg:postcode":"38340",
    "sg:province":"TN",
    "wof:name":"Bell's Drive In",
    "wof:placetype":"venue"
},
  "geometry": {"coordinates":[-88.642886,35.435267],"type":"Point"}
}