{
  "type": "Feature",
  "properties": {
    "addr:full":"2601 Hillsboro Pike Nashville TN 37212",
    "addr:housenumber":"2601",
    "addr:postcode":"37212",
    "addr:street":"Hillsboro Pike",
    "iso:country":"US",
    "sg:address":"2601 Hillsboro Pike",
    "sg:city":"Nashville",
    "sg:classifiers":[
        {
            "category":"Professional",
            "type":"Services"
        }
    ],
    "sg:phone":"+1 615 297 1663",
    "sg:postcode":"37212",
    "sg:province":"TN",
    "sg:tags":[
        "establishment"
    ],
    "wof:name":"Charley Foundation",
    "wof:placetype":"venue"
},
  "geometry": {"coordinates":[-86.80600699999999,36.124559],"type":"Point"}
}