{
  "type": "Feature",
  "properties": {
    "iso:country":"US",
    "sg:address":"1414 W Main St",
    "sg:city":"Greeneville",
    "sg:classifiers":[
        {
            "category":"Shopping",
            "subcategory":"Discount & Variety Stores",
            "type":"Retail Goods"
        }
    ],
    "sg:phone":"+1 423 638 8101",
    "sg:postcode":"37743",
    "sg:province":"TN",
    "sg:tags":[
        "merchandise",
        "general"
    ],
    "wof:name":"Co-Op Main Store",
    "wof:placetype":"venue"
},
  "geometry": {"coordinates":[-82.85498800000001,36.149732],"type":"Point"}
}