{
  "type": "Feature",
  "properties": {
    "addr:full":"603 E Northfield Blvd Murfreesboro TN 37130",
    "addr:housenumber":"603",
    "addr:postcode":"37130",
    "addr:street":"E Northfield Blvd",
    "iso:country":"US",
    "sg:address":"603 E Northfield Blvd",
    "sg:city":"Murfreesboro",
    "sg:classifiers":[
        {
            "category":"Professional",
            "subcategory":"Management & Consulting",
            "type":"Services"
        }
    ],
    "sg:phone":"+1 615 867 7141",
    "sg:postcode":"37130",
    "sg:province":"TN",
    "sg:tags":[
        "consultant"
    ],
    "wof:name":"New Directions Cnsltng Group",
    "wof:placetype":"venue"
},
  "geometry": {"coordinates":[-86.37875099999999,35.865992],"type":"Point"}
}