{
  "type": "Feature",
  "properties": {
    "addr:full":"3325 Perimeter Hill Dr Nashville TN 37211",
    "addr:housenumber":"3325",
    "addr:postcode":"37211",
    "addr:street":"Perimeter Hill Dr",
    "iso:country":"US",
    "sg:address":"3325 Perimeter Hill Dr",
    "sg:city":"Nashville",
    "sg:classifiers":[
        {
            "category":"Banks & Credit Unions",
            "subcategory":"Investment Brokerage",
            "type":"Services"
        }
    ],
    "sg:phone":"+1 615 332 6300",
    "sg:postcode":"37211",
    "sg:province":"TN",
    "sg:tags":[
        "security"
    ],
    "wof:name":"UBS Financial Services Inc",
    "wof:placetype":"venue"
},
  "geometry": {"coordinates":[-86.692075,36.084909],"type":"Point"}
}