{
  "type": "Feature",
  "properties": {
    "addr:full":"215 SE Broad St Murfreesboro TN 37130",
    "addr:housenumber":"215",
    "addr:postcode":"37130",
    "addr:street":"Se Broad St",
    "iso:country":"US",
    "sg:address":"215 SE Broad St",
    "sg:city":"Murfreesboro",
    "sg:classifiers":[
        {
            "category":"Personal",
            "subcategory":"Beauty Salon",
            "type":"Services"
        }
    ],
    "sg:phone":"+1 615 907 8065",
    "sg:postcode":"37130",
    "sg:province":"TN",
    "sg:tags":[
        "shop"
    ],
    "wof:name":"Nora Parker",
    "wof:placetype":"venue"
},
  "geometry": {"coordinates":[-86.390389,35.841467],"type":"Point"}
}