{
  "type": "Feature",
  "properties": {
    "addr:full":"300 S Main St Middleton TN 38052",
    "addr:housenumber":"300",
    "addr:postcode":"38052",
    "addr:street":"S Main St",
    "iso:country":"US",
    "sg:address":"300 S Main St",
    "sg:city":"Middleton",
    "sg:classifiers":[
        {
            "category":"Government",
            "subcategory":"Fire Station",
            "type":"Public Place"
        }
    ],
    "sg:phone":"+1 731 376 8409",
    "sg:postcode":"38052",
    "sg:province":"TN",
    "sg:tags":[
        "department"
    ],
    "wof:name":"Middleton Fire Dept",
    "wof:placetype":"venue"
},
  "geometry": {"coordinates":[-88.892701,35.058649],"type":"Point"}
}