{
  "type": "Feature",
  "properties": {
    "addr:full":"2944 Kraft Dr Nashville TN 37204",
    "addr:housenumber":"2944",
    "addr:postcode":"37204",
    "addr:street":"Kraft Dr",
    "iso:country":"US",
    "sg:address":"2944 Kraft Dr",
    "sg:city":"Nashville",
    "sg:classifiers":[
        {
            "category":"Wholesale",
            "subcategory":"Hardware",
            "type":"Manufacturing & Wholesale Goods"
        },
        {
            "category":"Building & Trades",
            "subcategory":"Equipment Rental",
            "type":"Services"
        },
        {
            "category":"Home & Garden",
            "subcategory":"Hardware",
            "type":"Retail Goods"
        }
    ],
    "sg:phone":"+1 615 690 2273",
    "sg:postcode":"37204",
    "sg:province":"TN",
    "sg:tags":[
        "contractor",
        "hardware-builders",
        "store",
        "supply"
    ],
    "wof:name":"Care Supply Co",
    "wof:placetype":"venue"
},
  "geometry": {"coordinates":[-86.758619,36.106041],"type":"Point"}
}