{
  "type": "Feature",
  "properties": {
    "addr:full":"1160 Garner Rd Martin TN 38237",
    "addr:housenumber":"1160",
    "addr:postcode":"38237",
    "addr:street":"Garner Rd",
    "iso:country":"US",
    "sg:address":"1160 Garner Rd",
    "sg:city":"Martin",
    "sg:phone":"+1 731 587 2343",
    "sg:postcode":"38237",
    "sg:province":"TN",
    "sg:tags":[
        "farm",
        "corn",
        "wheat",
        "soybean"
    ],
    "wof:name":"Coates Farms",
    "wof:placetype":"venue"
},
  "geometry": {"coordinates":[-88.90746,36.326705],"type":"Point"}
}