{
  "type": "Feature",
  "properties": {
    "iso:country":"US",
    "sg:address":"831 Glastonbury Rd",
    "sg:city":"Nashville",
    "sg:classifiers":[
        {
            "category":"Shopping",
            "subcategory":"Clothing, Apparel, & Fashions",
            "type":"Retail Goods"
        }
    ],
    "sg:phone":"+1 615 367 9874",
    "sg:postcode":"37217",
    "sg:province":"TN",
    "sg:tags":[
        "designer",
        "jewelry",
        "custom"
    ],
    "wof:name":"Abercrombie & Gay",
    "wof:placetype":"venue"
},
  "geometry": {"coordinates":[-86.702597,36.13365],"type":"Point"}
}