{
  "type": "Feature",
  "properties": {
    "iso:country":"US",
    "sg:address":"3286 Northpark Blvd",
    "sg:city":"Alcoa",
    "sg:classifiers":[
        {
            "category":"Professional",
            "subcategory":"Engineering",
            "type":"Services"
        }
    ],
    "sg:phone":"+1 865 980 3500",
    "sg:postcode":"37701",
    "sg:province":"TN",
    "wof:name":"C2rl Inc",
    "wof:placetype":"venue"
},
  "geometry": {"coordinates":[-83.969151,35.829127],"type":"Point"}
}