{
  "type": "Feature",
  "properties": {
    "iso:country":"US",
    "sg:address":"808 Chippendale Rd",
    "sg:city":"Kingsport",
    "sg:classifiers":[
        {
            "category":"Real Estate",
            "subcategory":"Real Estate Agent",
            "type":"Services"
        }
    ],
    "sg:phone":"+1 423 246 0030",
    "sg:postcode":"37660",
    "sg:province":"TN",
    "wof:name":"Jr Morin Assoc",
    "wof:placetype":"venue"
},
  "geometry": {"coordinates":[-82.59892000000001,36.537057],"type":"Point"}
}