{
  "type": "Feature",
  "properties": {
    "addr:full":"1611 Hamill Rd Hixson TN 37343",
    "addr:housenumber":"1611",
    "addr:postcode":"37343",
    "addr:street":"Hamill Rd",
    "iso:country":"US",
    "sg:address":"1611 Hamill Rd",
    "sg:city":"Hixson",
    "sg:classifiers":[
        {
            "category":"Health Services",
            "subcategory":"Medical Lab",
            "type":"Services"
        }
    ],
    "sg:phone":"+1 423 875 4545",
    "sg:postcode":"37343",
    "sg:province":"TN",
    "sg:tags":[
        "laboratory",
        "dental"
    ],
    "wof:name":"Kirton Dental Lab",
    "wof:placetype":"venue"
},
  "geometry": {"coordinates":[-85.24825800000001,35.118492],"type":"Point"}
}