{
  "type": "Feature",
  "properties": {
    "iso:country":"US",
    "sg:address":"817 S Garden St",
    "sg:city":"Columbia",
    "sg:classifiers":[
        {
            "category":"Building & Trades",
            "subcategory":"Cleaning & Sanitation",
            "type":"Services"
        }
    ],
    "sg:phone":"+1 931 388 3958",
    "sg:postcode":"38401",
    "sg:province":"TN",
    "sg:tags":[
        "maintenance"
    ],
    "wof:name":"Fedserv Industries Inc",
    "wof:placetype":"venue"
},
  "geometry": {"coordinates":[-87.035493,35.614781],"type":"Point"}
}