{
  "type": "Feature",
  "properties": {
    "addr:full":"6730 Winchester Rd Memphis TN 38115",
    "addr:housenumber":"6730",
    "addr:postcode":"38115",
    "addr:street":"Winchester Rd",
    "iso:country":"US",
    "sg:address":"6730 Winchester Rd",
    "sg:city":"Memphis",
    "sg:classifiers":[
        {
            "category":"Shopping",
            "subcategory":"Used Merchandise",
            "type":"Retail Goods"
        }
    ],
    "sg:phone":"+1 901 507 2079",
    "sg:postcode":"38115",
    "sg:province":"TN",
    "sg:tags":[
        "shop",
        "thrift"
    ],
    "wof:name":"Goodwill Industries",
    "wof:placetype":"venue"
},
  "geometry": {"coordinates":[-89.839389,35.04949],"type":"Point"}
}