{
  "type": "Feature",
  "properties": {
    "iso:country":"US",
    "sg:address":"514 Steam Plant Rd",
    "sg:city":"Gallatin",
    "sg:classifiers":[
        {
            "category":"Building & Trades",
            "subcategory":"Construction",
            "type":"Services"
        }
    ],
    "sg:phone":"+1 615 452 7663",
    "sg:postcode":"37066",
    "sg:province":"TN",
    "sg:tags":[
        "erectors",
        "machinery"
    ],
    "wof:name":"Graphic Equipment Movers",
    "wof:placetype":"venue"
},
  "geometry": {"coordinates":[-86.42394400000001,36.380358],"type":"Point"}
}