{
  "type": "Feature",
  "properties": {
    "addr:full":"4793 State Hwy 58 Chattanooga TN 37416",
    "addr:housenumber":"4793",
    "addr:postcode":"37416",
    "addr:street":"State Hwy 58",
    "iso:country":"US",
    "sg:address":"4793 State Hwy 58",
    "sg:city":"Chattanooga",
    "sg:classifiers":[
        {
            "category":"Banks & Credit Unions",
            "subcategory":"Bank",
            "type":"Services"
        }
    ],
    "sg:phone":"+1 423 553 9990",
    "sg:postcode":"37416",
    "sg:province":"TN",
    "sg:tags":[
        "loan"
    ],
    "wof:name":"Quickcheck Advance",
    "wof:placetype":"venue"
},
  "geometry": {"coordinates":[-85.187038,35.089523],"type":"Point"}
}