{
  "type": "Feature",
  "properties": {
    "iso:country":"US",
    "sg:address":"635 Shute Ln",
    "sg:city":"Old Hickory",
    "sg:classifiers":[
        {
            "category":"Professional",
            "type":"Services"
        },
        {
            "category":"Home & Garden",
            "subcategory":"Household Appliances",
            "type":"Retail Goods"
        }
    ],
    "sg:phone":"+1 615 883 2628",
    "sg:postcode":"37138",
    "sg:province":"TN",
    "sg:tags":[
        "cleaners",
        "establishment",
        "vacuum"
    ],
    "sg:website":"www.rainbowsystems.com",
    "wof:name":"L T Berry Enterprises",
    "wof:placetype":"venue"
},
  "geometry": {"coordinates":[-86.60472,36.21606],"type":"Point"}
}