{
  "type": "Feature",
  "properties": {
    "iso:country":"US",
    "sg:address":"8818 Windhaven Dr",
    "sg:city":"Ooltewah",
    "sg:classifiers":[
        {
            "category":"Wholesale",
            "subcategory":"Stationery",
            "type":"Manufacturing & Wholesale Goods"
        }
    ],
    "sg:phone":"+1 423 238 9344",
    "sg:postcode":"37363",
    "sg:province":"TN",
    "sg:tags":[
        "business",
        "form",
        "system"
    ],
    "wof:name":"PCS Business Forms Inc",
    "wof:placetype":"venue"
},
  "geometry": {"coordinates":[-85.07856,35.087569],"type":"Point"}
}