{
  "type": "Feature",
  "properties": {
    "iso:country":"US",
    "sg:address":"1704 Driftwood Dr",
    "sg:city":"Powell",
    "sg:classifiers":[
        {
            "category":"Autos & Motor Vehicles",
            "subcategory":"Auto Supplies",
            "type":"Retail Goods"
        }
    ],
    "sg:phone":"+1 865 947 3767",
    "sg:postcode":"37849",
    "sg:province":"TN",
    "sg:tags":[
        "filter",
        "gas"
    ],
    "wof:name":"Accurate Air Filter Svc",
    "wof:placetype":"venue"
},
  "geometry": {"coordinates":[-84.030519,36.035857],"type":"Point"}
}