{
  "type": "Feature",
  "properties": {
    "addr:full":"536 S Hill St Morristown TN 37813",
    "addr:housenumber":"536",
    "addr:postcode":"37813",
    "addr:street":"S Hill St",
    "iso:country":"US",
    "sg:address":"536 S Hill St",
    "sg:city":"Morristown",
    "sg:classifiers":[
        {
            "category":"Wholesale",
            "subcategory":"Office Equipment",
            "type":"Manufacturing & Wholesale Goods"
        }
    ],
    "sg:phone":"+1 423 586 7411",
    "sg:postcode":"37813",
    "sg:province":"TN",
    "sg:tags":[
        "system",
        "automation"
    ],
    "wof:name":"Control Services",
    "wof:placetype":"venue"
},
  "geometry": {"coordinates":[-83.28813,36.209496],"type":"Point"}
}