{
  "type": "Feature",
  "properties": {
    "addr:full":"401 Market St Clinton TN 37716",
    "addr:housenumber":"401",
    "addr:postcode":"37716",
    "addr:street":"Market St",
    "iso:country":"US",
    "sg:address":"401 Market St",
    "sg:city":"Clinton",
    "sg:classifiers":[
        {
            "category":"Insurance",
            "subcategory":"Insurance Agent",
            "type":"Services"
        }
    ],
    "sg:phone":"+1 865 463 8600",
    "sg:postcode":"37716",
    "sg:province":"TN",
    "wof:name":"David Lane Insurance",
    "wof:placetype":"venue"
},
  "geometry": {"coordinates":[-84.129572,36.104065],"type":"Point"}
}