{
  "type": "Feature",
  "properties": {
    "iso:country":"US",
    "sg:address":"512 Nawakwa Trl",
    "sg:city":"Madison",
    "sg:classifiers":[
        {
            "category":"Shopping",
            "subcategory":"Bicycles & Sporting Goods",
            "type":"Retail Goods"
        }
    ],
    "sg:phone":"+1 615 868 1689",
    "sg:postcode":"37115",
    "sg:province":"TN",
    "wof:name":"Madison Babe Ruth Baseball",
    "wof:placetype":"venue"
},
  "geometry": {"coordinates":[-86.665391,36.23658],"type":"Point"}
}