{
  "type": "Feature",
  "properties": {
    "iso:country":"US",
    "sg:address":"3221 W Governor John Sevier Hwy",
    "sg:city":"Knoxville",
    "sg:classifiers":[
        {
            "category":"Health Services",
            "subcategory":"Doctor",
            "type":"Services"
        }
    ],
    "sg:phone":"+1 865 579 3000",
    "sg:postcode":"37920",
    "sg:province":"TN",
    "wof:name":"Eddy S Grayson Jr DDS PC",
    "wof:placetype":"venue"
},
  "geometry": {"coordinates":[-83.943018,35.887572],"type":"Point"}
}