{
  "type": "Feature",
  "properties": {
    "addr:full":"5980 Maynardville Hwy Maynardville TN 37807",
    "addr:housenumber":"5980",
    "addr:postcode":"37807",
    "addr:street":"Maynardville Hwy",
    "iso:country":"US",
    "sg:address":"5980 Maynardville Hwy",
    "sg:city":"Maynardville",
    "sg:classifiers":[
        {
            "category":"Autos & Motor Vehicles",
            "subcategory":"Automobile Sales",
            "type":"Retail Goods"
        }
    ],
    "sg:phone":"+1 865 992 9999",
    "sg:postcode":"37807",
    "sg:province":"TN",
    "sg:tags":[
        "car",
        "dealer"
    ],
    "wof:name":"33 Auto Sales",
    "wof:placetype":"venue"
},
  "geometry": {"coordinates":[-83.75312599999999,36.310696],"type":"Point"}
}