{
  "type": "Feature",
  "properties": {
    "iso:country":"US",
    "sg:address":"674 E Church St",
    "sg:city":"Lexington",
    "sg:classifiers":[
        {
            "category":"Retail",
            "subcategory":"Car Wash",
            "type":"Services"
        }
    ],
    "sg:phone":"+1 731 968 0734",
    "sg:postcode":"38351",
    "sg:province":"TN",
    "sg:tags":[
        "polishing",
        "washing"
    ],
    "wof:name":"Hail's Used Cars",
    "wof:placetype":"venue"
},
  "geometry": {"coordinates":[-88.37876300000001,35.64163],"type":"Point"}
}