{
  "type": "Feature",
  "properties": {
    "addr:full":"4366 Malone Rd Memphis TN 38118",
    "addr:housenumber":"4366",
    "addr:postcode":"38118",
    "addr:street":"Malone Rd",
    "iso:country":"US",
    "sg:address":"4366 Malone Rd",
    "sg:city":"Memphis",
    "sg:classifiers":[
        {
            "category":"Wholesale",
            "subcategory":"Non-durable Goods",
            "type":"Manufacturing & Wholesale Goods"
        },
        {
            "category":"Shopping",
            "type":"Retail Goods"
        }
    ],
    "sg:phone":"+1 901 566 2280",
    "sg:postcode":"38118",
    "sg:province":"TN",
    "sg:tags":[
        "shop",
        "pet",
        "supply",
        "foods-wholesale",
        "manufacturer"
    ],
    "sg:website":"http://www.sergeants.com",
    "wof:name":"Sergeant's Pet Products",
    "wof:placetype":"venue"
},
  "geometry": {"coordinates":[-89.919222,35.027495],"type":"Point"}
}