{
  "type": "Feature",
  "properties": {
    "iso:country":"US",
    "sg:address":"5506 Old Hickory Blvd",
    "sg:city":"Nashville",
    "sg:classifiers":[
        {
            "category":"Retail",
            "subcategory":"Portrait Studio",
            "type":"Services"
        }
    ],
    "sg:phone":"+1 615 885 0213",
    "sg:postcode":"37218",
    "sg:province":"TN",
    "sg:tags":[
        "photographer"
    ],
    "wof:name":"Olan Mills Portrait Studio",
    "wof:placetype":"venue"
},
  "geometry": {"coordinates":[-86.90390600000001,36.242088],"type":"Point"}
}