{
  "type": "Feature",
  "properties": {
    "addr:full":"400 Palmetto St Chattanooga TN 37403",
    "addr:housenumber":"400",
    "addr:postcode":"37403",
    "addr:street":"Palmetto St",
    "iso:country":"US",
    "sg:address":"400 Palmetto St",
    "sg:city":"Chattanooga",
    "sg:classifiers":[
        {
            "category":"Professional",
            "subcategory":"Management & Consulting",
            "type":"Services"
        }
    ],
    "sg:phone":"+1 423 425 4018",
    "sg:postcode":"37403",
    "sg:province":"TN",
    "wof:name":"UTC Facilities Plant MGT",
    "wof:placetype":"venue"
},
  "geometry": {"coordinates":[-85.29388899999999,35.047319],"type":"Point"}
}