{
  "type": "Feature",
  "properties": {
    "addr:full":"111 W Market St Dyersburg TN 38024",
    "addr:housenumber":"111",
    "addr:postcode":"38024",
    "addr:street":"W Market St",
    "iso:country":"US",
    "sg:address":"111 W Market St",
    "sg:city":"Dyersburg",
    "sg:classifiers":[
        {
            "category":"Organizations",
            "subcategory":"Non-profit Organization",
            "type":"Services"
        }
    ],
    "sg:phone":"+1 731 287 9933",
    "sg:postcode":"38024",
    "sg:province":"TN",
    "wof:name":"Downtown Dyersburg Devmnt Assn",
    "wof:placetype":"venue"
},
  "geometry": {"coordinates":[-89.386686,36.031942],"type":"Point"}
}