{
  "type": "Feature",
  "properties": {
    "iso:country":"US",
    "sg:address":"20 Sanders Bluff Rd",
    "sg:city":"Humboldt",
    "sg:classifiers":[
        {
            "category":"Real Estate",
            "subcategory":"Real Estate Operator",
            "type":"Services"
        }
    ],
    "sg:phone":"+1 731 824 0111",
    "sg:postcode":"38343",
    "sg:province":"TN",
    "sg:tags":[
        "mobile",
        "home",
        "community"
    ],
    "wof:name":"Stan's Home Ctr Inc",
    "wof:placetype":"venue"
},
  "geometry": {"coordinates":[-88.847212,35.755941],"type":"Point"}
}