{
  "type": "Feature",
  "properties": {
    "iso:country":"US",
    "sg:address":"242 Bonita Dr",
    "sg:city":"Memphis",
    "sg:classifiers":[
        {
            "category":"Shopping",
            "subcategory":"Clothing, Apparel, & Fashions",
            "type":"Retail Goods"
        }
    ],
    "sg:phone":"+1 901 396 6433",
    "sg:postcode":"38109",
    "sg:province":"TN",
    "wof:name":"Zulas Boutique",
    "wof:placetype":"venue"
},
  "geometry": {"coordinates":[-90.05274300000001,35.03701],"type":"Point"}
}