{
  "type": "Feature",
  "properties": {
    "addr:full":"307 Will Dunavant Rd Decaturville TN 38329",
    "addr:housenumber":"307",
    "addr:postcode":"38329",
    "addr:street":"Will Dunavant Rd",
    "iso:country":"US",
    "sg:address":"307 Will Dunavant Rd",
    "sg:city":"Decaturville",
    "sg:phone":"+1 731 852 3104",
    "sg:postcode":"38329",
    "sg:province":"TN",
    "sg:tags":[
        "farm",
        "corn"
    ],
    "wof:name":"Bobby Myracle",
    "wof:placetype":"venue"
},
  "geometry": {"coordinates":[-88.174891,35.570766],"type":"Point"}
}