{
  "type": "Feature",
  "properties": {
    "iso:country":"US",
    "sg:address":"805 Pennell Ln",
    "sg:city":"Dyersburg",
    "sg:classifiers":[
        {
            "category":"Shopping",
            "subcategory":"Department Store",
            "type":"Retail Goods"
        }
    ],
    "sg:phone":"+1 731 285 3838",
    "sg:postcode":"38024",
    "sg:province":"TN",
    "wof:name":"Freds",
    "wof:placetype":"venue"
},
  "geometry": {"coordinates":[-89.3994,36.062742],"type":"Point"}
}