{
  "type": "Feature",
  "properties": {
    "addr:full":"3575 Cobb Rd Arlington TN 38002",
    "addr:housenumber":"3575",
    "addr:postcode":"38002",
    "addr:street":"Cobb Rd",
    "iso:country":"US",
    "sg:address":"3575 Cobb Rd",
    "sg:city":"Arlington",
    "sg:classifiers":[
        {
            "category":"Home & Garden",
            "subcategory":"Mobile Homes",
            "type":"Retail Goods"
        }
    ],
    "sg:phone":"+1 901 867 3541",
    "sg:postcode":"38002",
    "sg:province":"TN",
    "wof:name":"Haven Homes LLC",
    "wof:placetype":"venue"
},
  "geometry": {"coordinates":[-89.719932,35.216596],"type":"Point"}
}