{
  "type": "Feature",
  "properties": {
    "iso:country":"US",
    "sg:address":"615 Harding Pl F13",
    "sg:city":"Nashville",
    "sg:classifiers":[
        {
            "category":"Organizations",
            "subcategory":"Religious Organization",
            "type":"Services"
        }
    ],
    "sg:phone":"+1 615 812 6283",
    "sg:postcode":"37211",
    "sg:province":"TN",
    "sg:tags":[
        "clergy"
    ],
    "wof:name":"Mcfarlin Natha",
    "wof:placetype":"venue"
},
  "geometry": {"coordinates":[-86.74166099999999,36.07766],"type":"Point"}
}