{
  "type": "Feature",
  "properties": {
    "iso:country":"US",
    "sg:address":"3462 Post Oak Rd",
    "sg:city":"Belvidere",
    "sg:classifiers":[
        {
            "category":"Building & Trades",
            "subcategory":"Construction",
            "type":"Services"
        }
    ],
    "sg:phone":"+1 931 967 5163",
    "sg:postcode":"37306",
    "sg:province":"TN",
    "sg:tags":[
        "residential"
    ],
    "wof:name":"Curtis Construction",
    "wof:placetype":"venue"
},
  "geometry": {"coordinates":[-86.239909,35.143525],"type":"Point"}
}