{
  "type": "Feature",
  "properties": {
    "addr:full":"105 Meadow View Rd Bristol TN 37620",
    "addr:housenumber":"105",
    "addr:postcode":"37620",
    "addr:street":"Meadow View Rd",
    "iso:country":"US",
    "sg:address":"105 Meadow View Rd",
    "sg:city":"Bristol",
    "sg:classifiers":[
        {
            "category":"Wholesale",
            "subcategory":"Medical Equipment & Supplies",
            "type":"Manufacturing & Wholesale Goods"
        },
        {
            "category":"Health Services",
            "subcategory":"Clinic",
            "type":"Services"
        }
    ],
    "sg:phone":"+1 423 764 4480",
    "sg:postcode":"37620",
    "sg:province":"TN",
    "sg:tags":[
        "home",
        "physician",
        "surgeon",
        "care"
    ],
    "wof:name":"Respiratory Home Care LLC",
    "wof:placetype":"venue"
},
  "geometry": {"coordinates":[-82.230217,36.585912],"type":"Point"}
}