{
  "type": "Feature",
  "properties": {
    "iso:country":"US",
    "sg:address":"710 Boat Dock Ln",
    "sg:city":"Hartsville",
    "sg:classifiers":[
        {
            "category":"Building & Trades",
            "subcategory":"Construction",
            "type":"Services"
        }
    ],
    "sg:phone":"+1 615 374 9999",
    "sg:postcode":"37074",
    "sg:province":"TN",
    "sg:tags":[
        "house"
    ],
    "wof:name":"Allframe Construction Inc",
    "wof:placetype":"venue"
},
  "geometry": {"coordinates":[-86.203784,36.378197],"type":"Point"}
}