{
  "type": "Feature",
  "properties": {
    "iso:country":"US",
    "sg:address":"1010 Wilder Pl",
    "sg:city":"Knoxville",
    "sg:classifiers":[
        {
            "category":"Building & Trades",
            "subcategory":"Plumbing",
            "type":"Services"
        }
    ],
    "sg:phone":"+1 865 522 1124",
    "sg:postcode":"37915",
    "sg:province":"TN",
    "sg:tags":[
        "contractor"
    ],
    "wof:name":"Mechanical Services",
    "wof:placetype":"venue"
},
  "geometry": {"coordinates":[-83.892658,35.972679],"type":"Point"}
}