{
  "type": "Feature",
  "properties": {
    "iso:country":"US",
    "sg:address":"209 10th Ave S Suite 112",
    "sg:city":"Nashville",
    "sg:classifiers":[
        {
            "category":"Education",
            "subcategory":"College",
            "type":"Public Place"
        },
        {
            "category":"Personal",
            "subcategory":"Barber",
            "type":"Services"
        }
    ],
    "sg:phone":"+1 615 248 1927",
    "sg:postcode":"37203",
    "sg:province":"TN",
    "sg:tags":[
        "school",
        "beauty"
    ],
    "sg:website":"http://www.genesiscareer.com",
    "wof:name":"Genesis Career Group, Inc",
    "wof:placetype":"venue"
},
  "geometry": {"coordinates":[-86.782723,36.155961],"type":"Point"}
}