{
  "type": "Feature",
  "properties": {
    "addr:full":"655 Inman St E Cleveland TN 37311",
    "addr:housenumber":"655",
    "addr:postcode":"37311",
    "addr:street":"Inman St E",
    "iso:country":"US",
    "sg:address":"655 Inman St E",
    "sg:city":"Cleveland",
    "sg:classifiers":[
        {
            "category":"Retail",
            "subcategory":"Auto Repair",
            "type":"Services"
        }
    ],
    "sg:phone":"+1 423 472 7090",
    "sg:postcode":"37311",
    "sg:province":"TN",
    "sg:tags":[
        "wrecker"
    ],
    "wof:name":"Presswood Wrecker Svc",
    "wof:placetype":"venue"
},
  "geometry": {"coordinates":[-84.867003,35.155368],"type":"Point"}
}