{
  "type": "Feature",
  "properties": {
    "addr:full":"1406 Timber Valley Dr Nashville TN 37214",
    "addr:housenumber":"1406",
    "addr:postcode":"37214",
    "addr:street":"Timber Valley Dr",
    "iso:country":"US",
    "sg:address":"1406 Timber Valley Dr",
    "sg:city":"Nashville",
    "sg:classifiers":[
        {
            "category":"Professional",
            "subcategory":"Computer Services",
            "type":"Services"
        }
    ],
    "sg:phone":"+1 615 872 8718",
    "sg:postcode":"37214",
    "sg:province":"TN",
    "sg:tags":[
        "programing",
        "custom"
    ],
    "wof:name":"Softwareshack",
    "wof:placetype":"venue"
},
  "geometry": {"coordinates":[-86.637759,36.129997],"type":"Point"}
}