{
  "type": "Feature",
  "properties": {
    "iso:country":"US",
    "sg:address":"10304 Chapman Hwy",
    "sg:city":"Seymour",
    "sg:classifiers":[
        {
            "category":"Banks & Credit Unions",
            "subcategory":"Bank",
            "type":"Services"
        }
    ],
    "sg:phone":"+1 865 429 6404",
    "sg:postcode":"37865",
    "sg:province":"TN",
    "sg:tags":[
        "national",
        "commercial"
    ],
    "wof:name":"SunTrust",
    "wof:placetype":"venue"
},
  "geometry": {"coordinates":[-83.78469200000001,35.881977],"type":"Point"}
}