{
  "type": "Feature",
  "properties": {
    "addr:full":"3100 Walnut Grove Rd Memphis TN 38111",
    "addr:housenumber":"3100",
    "addr:postcode":"38111",
    "addr:street":"Walnut Grove Rd",
    "iso:country":"US",
    "sg:address":"3100 Walnut Grove Rd",
    "sg:city":"Memphis",
    "sg:classifiers":[
        {
            "category":"Professional",
            "subcategory":"Accounting & Tax Preparation",
            "type":"Services"
        }
    ],
    "sg:phone":"+1 901 323 2014",
    "sg:postcode":"38111",
    "sg:province":"TN",
    "sg:tags":[
        "bookkeeping",
        "general"
    ],
    "wof:name":"Azal Bookkeeping Svc",
    "wof:placetype":"venue"
},
  "geometry": {"coordinates":[-89.958872,35.134057],"type":"Point"}
}