{
  "type": "Feature",
  "properties": {
    "iso:country":"US",
    "sg:address":"1060 Plunk Rd",
    "sg:city":"Henderson",
    "sg:classifiers":[
        {
            "category":"Shopping",
            "subcategory":"Hobbies, Toys, & Games",
            "type":"Retail Goods"
        }
    ],
    "sg:phone":"+1 731 989 6842",
    "sg:postcode":"38340",
    "sg:province":"TN",
    "wof:name":"Lovable Bears",
    "wof:placetype":"venue"
},
  "geometry": {"coordinates":[-88.499906,35.437463],"type":"Point"}
}