{
  "type": "Feature",
  "properties": {
    "addr:full":"1852 N Main St Shelbyville TN 37160",
    "addr:housenumber":"1852",
    "addr:postcode":"37160",
    "addr:street":"N Main St",
    "iso:country":"US",
    "sg:address":"1852 N Main St",
    "sg:city":"Shelbyville",
    "sg:classifiers":[
        {
            "category":"Personal",
            "subcategory":"Tanning Parlor",
            "type":"Services"
        },
        {
            "category":"Manufacturing",
            "subcategory":"Tools & Machinery",
            "type":"Manufacturing & Wholesale Goods"
        }
    ],
    "sg:phone":"+1 931 684 1221",
    "sg:postcode":"37160",
    "sg:province":"TN",
    "sg:tags":[
        "equipment",
        "salon",
        "lighting",
        "mfg"
    ],
    "wof:name":"Sunny Daze Tanning Salon",
    "wof:placetype":"venue"
},
  "geometry": {"coordinates":[-86.45558,35.513482],"type":"Point"}
}