{
  "type": "Feature",
  "properties": {
    "iso:country":"US",
    "sg:address":"413 Hampstead S",
    "sg:city":"Antioch",
    "sg:classifiers":[
        {
            "category":"Health Services",
            "subcategory":"Doctor",
            "type":"Services"
        }
    ],
    "sg:phone":"+1 615 399 8600",
    "sg:postcode":"37013",
    "sg:province":"TN",
    "sg:tags":[
        "medical"
    ],
    "wof:name":"Onadeko Olayinka",
    "wof:placetype":"venue"
},
  "geometry": {"coordinates":[-86.66657600000001,36.076858],"type":"Point"}
}