{
  "type": "Feature",
  "properties": {
    "iso:country":"US",
    "sg:address":"309 N Church Ave",
    "sg:city":"Dyersburg",
    "sg:classifiers":[
        {
            "category":"Professional",
            "subcategory":"Business Services",
            "type":"Services"
        },
        {
            "category":"Government",
            "subcategory":"Post Office",
            "type":"Public Place"
        },
        {
            "category":"Government",
            "subcategory":"Office",
            "type":"Public Place"
        }
    ],
    "sg:phone":"+1 800 275 8777",
    "sg:postcode":"38024",
    "sg:province":"TN",
    "sg:tags":[
        "mail",
        "government-united",
        "state",
        "shipping"
    ],
    "sg:website":"http://www.usps.com",
    "wof:name":"United States Postal Service",
    "wof:placetype":"venue"
},
  "geometry": {"coordinates":[-89.387655,36.034691],"type":"Point"}
}