{
  "type": "Feature",
  "properties": {
    "iso:country":"US",
    "sg:address":"3931 Pheasant Dr",
    "sg:city":"Nashville",
    "sg:classifiers":[
        {
            "category":"Organizations",
            "subcategory":"Religious Organization",
            "type":"Services"
        }
    ],
    "sg:phone":"+1 615 726 1586",
    "sg:postcode":"37218",
    "sg:province":"TN",
    "wof:name":"Fred Gipson",
    "wof:placetype":"venue"
},
  "geometry": {"coordinates":[-86.832436,36.214549],"type":"Point"}
}