{
  "type": "Feature",
  "properties": {
    "addr:full":"1564 Wilhite Creek Rd Sevierville TN 37876",
    "addr:housenumber":"1564",
    "addr:postcode":"37876",
    "addr:street":"Wilhite Creek Rd",
    "iso:country":"US",
    "sg:address":"1564 Wilhite Creek Rd",
    "sg:city":"Sevierville",
    "sg:classifiers":[
        {
            "category":"Government",
            "subcategory":"Fire Station",
            "type":"Public Place"
        }
    ],
    "sg:phone":"+1 865 429 3729",
    "sg:postcode":"37876",
    "sg:province":"TN",
    "sg:tags":[
        "department",
        "volunteer"
    ],
    "wof:name":"English Mtn Vlntr Fire Dprtmnt",
    "wof:placetype":"venue"
},
  "geometry": {"coordinates":[-83.32827899999999,35.865518],"type":"Point"}
}