{
  "type": "Feature",
  "properties": {
    "iso:country":"US",
    "sg:address":"1302 Railroad Ave",
    "sg:city":"Shelbyville",
    "sg:classifiers":[
        {
            "category":"Professional",
            "subcategory":"Business Services",
            "type":"Services"
        }
    ],
    "sg:phone":"+1 931 684 6777",
    "sg:postcode":"37160",
    "sg:province":"TN",
    "wof:name":"Big B Express",
    "wof:placetype":"venue"
},
  "geometry": {"coordinates":[-86.371464,35.524477],"type":"Point"}
}