{
  "type": "Feature",
  "properties": {
    "iso:country":"US",
    "sg:address":"158 Salem Rd",
    "sg:city":"Minor Hill",
    "sg:classifiers":[
        {
            "category":"Utilities",
            "subcategory":"Telephone",
            "type":"Services"
        }
    ],
    "sg:phone":"+1 931 565 3400",
    "sg:postcode":"38473",
    "sg:province":"TN",
    "sg:tags":[
        "company"
    ],
    "wof:name":"Ardmore Telephone Co",
    "wof:placetype":"venue"
},
  "geometry": {"coordinates":[-87.154928,35.047365],"type":"Point"}
}