{
  "type": "Feature",
  "properties": {
    "addr:full":"5238 Donlyn Dr Hixson TN 37343",
    "addr:housenumber":"5238",
    "addr:postcode":"37343",
    "addr:street":"Donlyn Dr",
    "iso:country":"US",
    "sg:address":"5238 Donlyn Dr",
    "sg:city":"Hixson",
    "sg:classifiers":[
        {
            "category":"Personal",
            "subcategory":"Beauty Salon",
            "type":"Services"
        }
    ],
    "sg:phone":"+1 423 870 1107",
    "sg:postcode":"37343",
    "sg:province":"TN",
    "sg:tags":[
        "shop"
    ],
    "wof:name":"Hammers & Nails Inc",
    "wof:placetype":"venue"
},
  "geometry": {"coordinates":[-85.260479,35.130233],"type":"Point"}
}