{
  "type": "Feature",
  "properties": {
    "addr:full":"4124 Seminary Rd Smyrna TN 37167",
    "addr:housenumber":"4124",
    "addr:postcode":"37167",
    "addr:street":"Seminary Rd",
    "iso:country":"US",
    "sg:address":"4124 Seminary Rd",
    "sg:city":"Smyrna",
    "sg:classifiers":[
        {
            "category":"Professional",
            "type":"Services"
        }
    ],
    "sg:phone":"+1 615 355 2070",
    "sg:postcode":"37167",
    "sg:province":"TN",
    "wof:name":"Billy A Robinson",
    "wof:placetype":"venue"
},
  "geometry": {"coordinates":[-86.549108,35.927552],"type":"Point"}
}