{
  "type": "Feature",
  "properties": {
    "iso:country":"US",
    "sg:address":"500 Mountain View Dr",
    "sg:city":"Pulaski",
    "sg:classifiers":[
        {
            "category":"Banks & Credit Unions",
            "subcategory":"Financial Services",
            "type":"Services"
        }
    ],
    "sg:phone":"+1 931 363 8986",
    "sg:postcode":"38478",
    "sg:province":"TN",
    "sg:tags":[
        "investor"
    ],
    "wof:name":"S & D Investments Inc",
    "wof:placetype":"venue"
},
  "geometry": {"coordinates":[-87.04353999999999,35.228548],"type":"Point"}
}