{
  "type": "Feature",
  "properties": {
    "iso:country":"US",
    "sg:address":"510 Melton Hill Dr",
    "sg:city":"Clinton",
    "sg:classifiers":[
        {
            "category":"Professional",
            "subcategory":"Secretarial Services",
            "type":"Services"
        }
    ],
    "sg:phone":"+1 865 457 4027",
    "sg:postcode":"37716",
    "sg:province":"TN",
    "sg:tags":[
        "reporting",
        "court"
    ],
    "wof:name":"Joan S Roberts",
    "wof:placetype":"venue"
},
  "geometry": {"coordinates":[-84.14874399999999,36.080132],"type":"Point"}
}