{
  "type": "Feature",
  "properties": {
    "iso:country":"US",
    "sg:address":"6970 Morganton Rd",
    "sg:city":"Greenback",
    "sg:classifiers":[
        {
            "category":"Farming",
            "subcategory":"Livestock Farm",
            "type":"Manufacturing & Wholesale Goods"
        }
    ],
    "sg:phone":"+1 865 856 5757",
    "sg:postcode":"37742",
    "sg:province":"TN",
    "sg:tags":[
        "general"
    ],
    "wof:name":"Billy Potter",
    "wof:placetype":"venue"
},
  "geometry": {"coordinates":[-84.181026,35.656684],"type":"Point"}
}