{
  "type": "Feature",
  "properties": {
    "addr:full":"3438 Murphy Ln Columbia TN 38401",
    "addr:housenumber":"3438",
    "addr:postcode":"38401",
    "addr:street":"Murphy Ln",
    "iso:country":"US",
    "sg:address":"3438 Murphy Ln",
    "sg:city":"Columbia",
    "sg:classifiers":[
        {
            "category":"Professional",
            "type":"Services"
        }
    ],
    "sg:phone":"+1 931 840 5518",
    "sg:postcode":"38401",
    "sg:province":"TN",
    "wof:name":"Carter L Hardison",
    "wof:placetype":"venue"
},
  "geometry": {"coordinates":[-87.024202,35.545278],"type":"Point"}
}