{
  "type": "Feature",
  "properties": {
    "iso:country":"US",
    "sg:address":"611 W Elk Ave",
    "sg:city":"Elizabethton",
    "sg:classifiers":[
        {
            "category":"Building & Trades",
            "subcategory":"Equipment Rental",
            "type":"Services"
        }
    ],
    "sg:phone":"+1 423 547 1010",
    "sg:postcode":"37643",
    "sg:province":"TN",
    "sg:tags":[
        "leasing",
        "furniture"
    ],
    "wof:name":"Aarons Sales & Lease Ownership",
    "wof:placetype":"venue"
},
  "geometry": {"coordinates":[-82.233293,36.351419],"type":"Point"}
}