{
  "type": "Feature",
  "properties": {
    "iso:country":"US",
    "sg:address":"1237 Jefferson Davis Dr",
    "sg:city":"Brentwood",
    "sg:classifiers":[
        {
            "category":"Arts & Performance",
            "subcategory":"Theater",
            "type":"Entertainment"
        }
    ],
    "sg:phone":"+1 615 373 7965",
    "sg:postcode":"37027",
    "sg:province":"TN",
    "sg:tags":[
        "bureau"
    ],
    "wof:name":"Mardi Gras Band",
    "wof:placetype":"venue"
},
  "geometry": {"coordinates":[-86.817234,36.060658],"type":"Point"}
}