{
  "type": "Feature",
  "properties": {
    "iso:country":"US",
    "sg:address":"5247 Lance Dr",
    "sg:city":"Knoxville",
    "sg:classifiers":[
        {
            "category":"Recreation",
            "type":"Entertainment"
        }
    ],
    "sg:phone":"+1 865 558 9456",
    "sg:postcode":"37909",
    "sg:province":"TN",
    "wof:name":"Timbercrest Recreational Cente",
    "wof:placetype":"venue"
},
  "geometry": {"coordinates":[-84.001729,35.953291],"type":"Point"}
}