{
  "type": "Feature",
  "properties": {
    "iso:country":"US",
    "sg:address":"201 E Depot St",
    "sg:city":"Shelbyville",
    "sg:classifiers":[
        {
            "category":"Cinema",
            "subcategory":"Movie Theater",
            "type":"Entertainment"
        }
    ],
    "sg:phone":"+1 931 684 7306",
    "sg:postcode":"37160",
    "sg:province":"TN",
    "wof:name":"Capri Twin Theatre",
    "wof:placetype":"venue"
},
  "geometry": {"coordinates":[-86.459131,35.482392],"type":"Point"}
}