{
  "type": "Feature",
  "properties": {
    "iso:country":"US",
    "sg:address":"9349 Park West Blvd",
    "sg:city":"Knoxville",
    "sg:classifiers":[
        {
            "category":"Health Services",
            "subcategory":"Doctor",
            "type":"Services"
        }
    ],
    "sg:phone":"+1 865 693 0050",
    "sg:postcode":"37923",
    "sg:province":"TN",
    "sg:tags":[
        "surgery",
        "plastic"
    ],
    "wof:name":"Harper K Allen MD PC",
    "wof:placetype":"venue"
},
  "geometry": {"coordinates":[-84.10053000000001,35.918054],"type":"Point"}
}