{
  "type": "Feature",
  "properties": {
    "iso:country":"US",
    "sg:address":"1375 Rock Creek Rd",
    "sg:city":"Erwin",
    "sg:classifiers":[
        {
            "category":"Building & Trades",
            "subcategory":"Construction",
            "type":"Services"
        }
    ],
    "sg:phone":"+1 423 743 2171",
    "sg:postcode":"37650",
    "sg:province":"TN",
    "sg:tags":[
        "house"
    ],
    "wof:name":"Robinson Home Builder Inc",
    "wof:placetype":"venue"
},
  "geometry": {"coordinates":[-82.37082599999999,36.143496],"type":"Point"}
}