{
  "type": "Feature",
  "properties": {
    "iso:country":"US",
    "sg:address":"4219 Double S Rd",
    "sg:city":"Dayton",
    "sg:classifiers":[
        {
            "category":"Building & Trades",
            "subcategory":"Plumbing",
            "type":"Services"
        }
    ],
    "sg:phone":"+1 423 775 6825",
    "sg:postcode":"37321",
    "sg:province":"TN",
    "sg:tags":[
        "contractor"
    ],
    "wof:name":"Bieber Plumbing",
    "wof:placetype":"venue"
},
  "geometry": {"coordinates":[-84.94199500000001,35.492016],"type":"Point"}
}