{
  "type": "Feature",
  "properties": {
    "addr:full":"510 S Highland St Memphis TN 38111",
    "addr:housenumber":"510",
    "addr:postcode":"38111",
    "addr:street":"S Highland St",
    "iso:country":"US",
    "sg:address":"510 S Highland St",
    "sg:city":"Memphis",
    "sg:classifiers":[
        {
            "category":"Home & Garden",
            "subcategory":"Home Furnishings",
            "type":"Retail Goods"
        }
    ],
    "sg:phone":"+1 901 324 4088",
    "sg:postcode":"38111",
    "sg:province":"TN",
    "sg:tags":[
        "apartments-furnished"
    ],
    "wof:name":"Stratum On Highland",
    "wof:placetype":"venue"
},
  "geometry": {"coordinates":[-89.945655,35.117516],"type":"Point"}
}