{
  "type": "Feature",
  "properties": {
    "addr:full":"205 Powell St Decherd TN 37324",
    "addr:housenumber":"205",
    "addr:postcode":"37324",
    "addr:street":"Powell St",
    "iso:country":"US",
    "sg:address":"205 Powell St",
    "sg:city":"Decherd",
    "sg:classifiers":[
        {
            "category":"Shopping",
            "subcategory":"Used Merchandise",
            "type":"Retail Goods"
        }
    ],
    "sg:phone":"+1 931 967 9672",
    "sg:postcode":"37324",
    "sg:province":"TN",
    "sg:tags":[
        "shop",
        "thrift"
    ],
    "wof:name":"This & That Store",
    "wof:placetype":"venue"
},
  "geometry": {"coordinates":[-86.075086,35.20985],"type":"Point"}
}