{
  "type": "Feature",
  "properties": {
    "iso:country":"US",
    "sg:address":"668 S College St",
    "sg:city":"Winchester",
    "sg:classifiers":[
        {
            "category":"Restaurant",
            "type":"Food & Drink"
        }
    ],
    "sg:menulink":"http://www.allmenus.com/tn/winchester/85770-dominos-pizza/menu/",
    "sg:phone":"+1 931 967 4400",
    "sg:postcode":"37398",
    "sg:province":"TN",
    "sg:tags":[
        "american",
        "wing",
        "pizza"
    ],
    "wof:name":"Domino's Pizza",
    "wof:placetype":"venue"
},
  "geometry": {"coordinates":[-86.105385,35.181743],"type":"Point"}
}