{
  "type": "Feature",
  "properties": {
    "addr:full":"395 Sheep Ranch Rd SE Cleveland TN 37323",
    "addr:housenumber":"395",
    "addr:postcode":"37323",
    "addr:street":"Sheep Ranch Rd Se",
    "iso:country":"US",
    "sg:address":"395 Sheep Ranch Rd SE",
    "sg:city":"Cleveland",
    "sg:classifiers":[
        {
            "category":"Professional",
            "type":"Services"
        }
    ],
    "sg:phone":"+1 423 559 0369",
    "sg:postcode":"37323",
    "sg:province":"TN",
    "wof:name":"Ernest Maroon",
    "wof:placetype":"venue"
},
  "geometry": {"coordinates":[-84.857775,35.070941],"type":"Point"}
}