{
  "type": "Feature",
  "properties": {
    "iso:country":"US",
    "sg:address":"350 Okeema Way",
    "sg:city":"Loudon",
    "sg:classifiers":[
        {
            "category":"Professional",
            "type":"Services"
        }
    ],
    "sg:phone":"+1 865 408 1450",
    "sg:postcode":"37774",
    "sg:province":"TN",
    "sg:tags":[
        "establishment"
    ],
    "wof:name":"Close & Close",
    "wof:placetype":"venue"
},
  "geometry": {"coordinates":[-84.266319,35.738741],"type":"Point"}
}