{
  "type": "Feature",
  "properties": {
    "addr:full":"10 Airways Blvd Nashville TN 37217",
    "addr:housenumber":"10",
    "addr:postcode":"37217",
    "addr:street":"Airways Blvd",
    "iso:country":"US",
    "sg:address":"10 Airways Blvd",
    "sg:city":"Nashville",
    "sg:classifiers":[
        {
            "category":"Airport",
            "type":"Transportation"
        }
    ],
    "sg:phone":"+1 615 367 2100",
    "sg:postcode":"37217",
    "sg:province":"TN",
    "sg:tags":[
        "aircraft",
        "maintenance"
    ],
    "wof:name":"Embraer Aircraft Maintenance Service Inc",
    "wof:placetype":"venue"
},
  "geometry": {"coordinates":[-86.693516,36.128515],"type":"Point"}
}