{
  "type": "Feature",
  "properties": {
    "addr:full":"1090 Lewis St Memphis TN 38107",
    "addr:housenumber":"1090",
    "addr:postcode":"38107",
    "addr:street":"Lewis St",
    "iso:country":"US",
    "sg:address":"1090 Lewis St",
    "sg:city":"Memphis",
    "sg:classifiers":[
        {
            "category":"Building & Trades",
            "subcategory":"Construction",
            "type":"Services"
        }
    ],
    "sg:phone":"+1 901 794 2443",
    "sg:postcode":"38107",
    "sg:province":"TN",
    "sg:tags":[
        "roofing",
        "contractor"
    ],
    "wof:name":"Boyd Roofing",
    "wof:placetype":"venue"
},
  "geometry": {"coordinates":[-90.019311,35.167697],"type":"Point"}
}