{
  "type": "Feature",
  "properties": {
    "iso:country":"US",
    "sg:address":"127 W Jackson Ave",
    "sg:city":"Knoxville",
    "sg:classifiers":[
        {
            "category":"Utilities",
            "subcategory":"Mobile Phone",
            "type":"Services"
        }
    ],
    "sg:phone":"+1 865 633 6577",
    "sg:postcode":"37902",
    "sg:province":"TN",
    "sg:tags":[
        "communication",
        "radiotelephone"
    ],
    "wof:name":"Walls Wireless",
    "wof:placetype":"venue"
},
  "geometry": {"coordinates":[-83.920789,35.968901],"type":"Point"}
}