{
  "type": "Feature",
  "properties": {
    "addr:full":"8222 Chapman Hwy Knoxville TN 37920",
    "addr:housenumber":"8222",
    "addr:postcode":"37920",
    "addr:street":"Chapman Hwy",
    "iso:country":"US",
    "sg:address":"8222 Chapman Hwy",
    "sg:city":"Knoxville",
    "sg:classifiers":[
        {
            "category":"Personal",
            "subcategory":"Beauty Salon",
            "type":"Services"
        }
    ],
    "sg:phone":"+1 865 573 0505",
    "sg:postcode":"37920",
    "sg:province":"TN",
    "wof:name":"Tene's Beauty Shop",
    "wof:placetype":"venue"
},
  "geometry": {"coordinates":[-83.819644,35.900401],"type":"Point"}
}