{
  "type": "Feature",
  "properties": {
    "addr:full":"3314 Poplar Ave Memphis TN 38111",
    "addr:housenumber":"3314",
    "addr:postcode":"38111",
    "addr:street":"Poplar Ave",
    "iso:country":"US",
    "sg:address":"3314 Poplar Ave",
    "sg:city":"Memphis",
    "sg:classifiers":[
        {
            "category":"Health Services",
            "subcategory":"Optometrist",
            "type":"Services"
        }
    ],
    "sg:phone":"+1 901 324 3189",
    "sg:postcode":"38111",
    "sg:province":"TN",
    "wof:name":"Mid South Vision Ctr",
    "wof:placetype":"venue"
},
  "geometry": {"coordinates":[-89.950947,35.129369],"type":"Point"}
}