{
  "type": "Feature",
  "properties": {
    "addr:full":"8700 Cumbernauld Cir N Germantown TN 38139",
    "addr:postcode":"8700;38139",
    "addr:street":"Cumbernauld Cir N",
    "iso:country":"US",
    "sg:address":"8700 Cumbernauld Cir N",
    "sg:city":"Germantown",
    "sg:classifiers":[
        {
            "category":"Banks & Credit Unions",
            "subcategory":"Bank",
            "type":"Services"
        }
    ],
    "sg:phone":"+1 901 737 3347",
    "sg:postcode":"38139",
    "sg:province":"TN",
    "wof:name":"Memphis State Swimming Inc",
    "wof:placetype":"venue"
},
  "geometry": {"coordinates":[-89.770139,35.090868],"type":"Point"}
}