{
  "type": "Feature",
  "properties": {
    "addr:full":"140 Monroe Ave Memphis TN 38103",
    "addr:housenumber":"140",
    "addr:postcode":"38103",
    "addr:street":"Monroe Ave",
    "iso:country":"US",
    "sg:address":"140 Monroe Ave",
    "sg:city":"Memphis",
    "sg:classifiers":[
        {
            "category":"Banks & Credit Unions",
            "subcategory":"Bank",
            "type":"Services"
        }
    ],
    "sg:phone":"+1 901 523 8040",
    "sg:postcode":"38103",
    "sg:province":"TN",
    "sg:tags":[
        "personal",
        "loan",
        "institution"
    ],
    "wof:name":"Chesterfield Finance Co",
    "wof:placetype":"venue"
},
  "geometry": {"coordinates":[-90.051378,35.143781],"type":"Point"}
}