{
  "type": "Feature",
  "properties": {
    "iso:country":"US",
    "sg:address":"409 Orleans St",
    "sg:city":"Johnson City",
    "sg:classifiers":[
        {
            "category":"Building & Trades",
            "subcategory":"Plumbing",
            "type":"Services"
        }
    ],
    "sg:phone":"+1 423 928 3592",
    "sg:postcode":"37601",
    "sg:province":"TN",
    "sg:tags":[
        "conditioning",
        "air",
        "system",
        "contractor"
    ],
    "wof:name":"Bailey's Heating & Air Cond",
    "wof:placetype":"venue"
},
  "geometry": {"coordinates":[-82.331886,36.320062],"type":"Point"}
}