{
  "type": "Feature",
  "properties": {
    "iso:country":"US",
    "sg:address":"35 E Main St",
    "sg:city":"Munford",
    "sg:classifiers":[
        {
            "category":"Health Services",
            "subcategory":"Doctor",
            "type":"Services"
        }
    ],
    "sg:phone":"+1 901 837 9282",
    "sg:postcode":"38058",
    "sg:province":"TN",
    "sg:tags":[
        "dentist"
    ],
    "wof:name":"Melvin D Gillihan DDS",
    "wof:placetype":"venue"
},
  "geometry": {"coordinates":[-89.815614,35.449457],"type":"Point"}
}