{
  "type": "Feature",
  "properties": {
    "addr:full":"5208 Luttrell Rd Knoxville TN 37918",
    "addr:postcode":"5208;37918",
    "addr:street":"Luttrell Rd",
    "iso:country":"US",
    "sg:address":"5208 Luttrell Rd",
    "sg:city":"Knoxville",
    "sg:classifiers":[
        {
            "category":"Education",
            "subcategory":"Special Training",
            "type":"Public Place"
        }
    ],
    "sg:phone":"+1 865 688 6503",
    "sg:postcode":"37918",
    "sg:province":"TN",
    "wof:name":"Tracy Rodgers Piano Lesso",
    "wof:placetype":"venue"
},
  "geometry": {"coordinates":[-83.87509300000001,36.068913],"type":"Point"}
}