{
  "type": "Feature",
  "properties": {
    "addr:full":"422 Walnut St Baxter TN 38544",
    "addr:housenumber":"422",
    "addr:postcode":"38544",
    "addr:street":"Walnut St",
    "iso:country":"US",
    "sg:address":"422 Walnut St",
    "sg:city":"Baxter",
    "sg:classifiers":[
        {
            "category":"Health Services",
            "subcategory":"Clinic",
            "type":"Services"
        }
    ],
    "sg:phone":"+1 931 858 0911",
    "sg:postcode":"38544",
    "sg:province":"TN",
    "sg:tags":[
        "home"
    ],
    "wof:name":"Elk Valley Home Health",
    "wof:placetype":"venue"
},
  "geometry": {"coordinates":[-85.63843900000001,36.156515],"type":"Point"}
}