{
  "type": "Feature",
  "properties": {
    "iso:country":"US",
    "sg:address":"6921 Kingston Pike",
    "sg:city":"Knoxville",
    "sg:classifiers":[
        {
            "category":"Food & Beverages",
            "subcategory":"Groceries & Convenience Stores",
            "type":"Retail Goods"
        }
    ],
    "sg:phone":"+1 865 588 9151",
    "sg:postcode":"37919",
    "sg:province":"TN",
    "wof:name":"Weigel's Farm Store",
    "wof:placetype":"venue"
},
  "geometry": {"coordinates":[-84.0214,35.932415],"type":"Point"}
}