{
  "type": "Feature",
  "properties": {
    "addr:full":"4538 State Hwy 58 Chattanooga TN 37416",
    "addr:housenumber":"4538",
    "addr:postcode":"37416",
    "addr:street":"State Hwy 58",
    "iso:country":"US",
    "sg:address":"4538 State Hwy 58",
    "sg:city":"Chattanooga",
    "sg:classifiers":[
        {
            "category":"Banks & Credit Unions",
            "subcategory":"Bank",
            "type":"Services"
        }
    ],
    "sg:phone":"+1 423 634 4000",
    "sg:postcode":"37416",
    "sg:province":"TN",
    "wof:name":"AM South Bank",
    "wof:placetype":"venue"
},
  "geometry": {"coordinates":[-85.194677,35.085169],"type":"Point"}
}