{
  "type": "Feature",
  "properties": {
    "addr:full":"311 Hawkins Rd Clarksville TN 37040",
    "addr:housenumber":"311",
    "addr:postcode":"37040",
    "addr:street":"Hawkins Rd",
    "iso:country":"US",
    "sg:address":"311 Hawkins Rd",
    "sg:city":"Clarksville",
    "sg:classifiers":[
        {
            "category":"Health Services",
            "subcategory":"Clinic",
            "type":"Services"
        }
    ],
    "sg:phone":"+1 931 920 5750",
    "sg:postcode":"37040",
    "sg:province":"TN",
    "wof:name":"Sterling Medical",
    "wof:placetype":"venue"
},
  "geometry": {"coordinates":[-87.360364,36.494287],"type":"Point"}
}