{
  "type": "Feature",
  "properties": {
    "iso:country":"US",
    "sg:address":"18 McKnight Rd",
    "sg:city":"Newbern",
    "sg:classifiers":[
        {
            "category":"Home & Garden",
            "subcategory":"Furniture",
            "type":"Retail Goods"
        }
    ],
    "sg:phone":"+1 731 635 5504",
    "sg:postcode":"38059",
    "sg:province":"TN",
    "wof:name":"Bennys Sales",
    "wof:placetype":"venue"
},
  "geometry": {"coordinates":[-89.17920100000001,36.147223],"type":"Point"}
}