{
  "type": "Feature",
  "properties": {
    "iso:country":"US",
    "sg:address":"8120 Heiskell Rd",
    "sg:city":"Powell",
    "sg:classifiers":[
        {
            "category":"Retail",
            "subcategory":"Veterinary Services",
            "type":"Services"
        }
    ],
    "sg:phone":"+1 865 938 0620",
    "sg:postcode":"37849",
    "sg:province":"TN",
    "wof:name":"Anthony L Jenkins Dvm",
    "wof:placetype":"venue"
},
  "geometry": {"coordinates":[-84.018863,36.052682],"type":"Point"}
}