{
  "type": "Feature",
  "properties": {
    "iso:country":"US",
    "sg:address":"291 Tusculum Rd",
    "sg:city":"Antioch",
    "sg:classifiers":[
        {
            "category":"Freight",
            "type":"Transportation"
        }
    ],
    "sg:phone":"+1 615 833 6207",
    "sg:postcode":"37013",
    "sg:province":"TN",
    "sg:tags":[
        "operator",
        "local",
        "trucking"
    ],
    "wof:name":"Adams Moving Co",
    "wof:placetype":"venue"
},
  "geometry": {"coordinates":[-86.704932,36.059743],"type":"Point"}
}