{
  "type": "Feature",
  "properties": {
    "iso:country":"US",
    "sg:address":"421 S Broad St",
    "sg:city":"Lexington",
    "sg:classifiers":[
        {
            "category":"Food & Beverages",
            "subcategory":"Groceries & Convenience Stores",
            "type":"Retail Goods"
        }
    ],
    "sg:phone":"+1 731 450 0119",
    "sg:postcode":"38351",
    "sg:province":"TN",
    "wof:name":"Sav A Lot",
    "wof:placetype":"venue"
},
  "geometry": {"coordinates":[-88.401759,35.6435],"type":"Point"}
}