{
  "type": "Feature",
  "properties": {
    "addr:full":"325 3rd Ave N Nashville TN 37201",
    "addr:housenumber":"325",
    "addr:postcode":"37201",
    "addr:street":"3Rd Ave N",
    "iso:country":"US",
    "sg:address":"325 3rd Ave N",
    "sg:city":"Nashville",
    "sg:classifiers":[
        {
            "category":"Wholesale",
            "subcategory":"Vending Machines",
            "type":"Manufacturing & Wholesale Goods"
        }
    ],
    "sg:phone":"+1 615 242 6507",
    "sg:postcode":"37201",
    "sg:province":"TN",
    "sg:tags":[
        "food",
        "automatic",
        "product",
        "retail",
        "through"
    ],
    "wof:name":"Candy Man Vending Service",
    "wof:placetype":"venue"
},
  "geometry": {"coordinates":[-86.778634,36.165487],"type":"Point"}
}