{
  "type": "Feature",
  "properties": {
    "iso:country":"US",
    "sg:address":"1309 N Washington St",
    "sg:city":"Tullahoma",
    "sg:classifiers":[
        {
            "category":"Wholesale",
            "subcategory":"Beer",
            "type":"Manufacturing & Wholesale Goods"
        }
    ],
    "sg:phone":"+1 931 455 5571",
    "sg:postcode":"37388",
    "sg:province":"TN",
    "sg:tags":[
        "ale"
    ],
    "wof:name":"L & H Distributing Co",
    "wof:placetype":"venue"
},
  "geometry": {"coordinates":[-86.222976,35.380097],"type":"Point"}
}