{
  "type": "Feature",
  "properties": {
    "addr:full":"2576 N Ford St Clarksville TN 37042",
    "addr:housenumber":"2576",
    "addr:postcode":"37042",
    "addr:street":"N Ford St",
    "iso:country":"US",
    "sg:address":"2576 N Ford St",
    "sg:city":"Clarksville",
    "sg:classifiers":[
        {
            "category":"Organizations",
            "subcategory":"Community Association",
            "type":"Services"
        }
    ],
    "sg:phone":"+1 931 645 8385",
    "sg:postcode":"37042",
    "sg:province":"TN",
    "sg:tags":[
        "fraternal"
    ],
    "wof:name":"Fraternal Order Of Police",
    "wof:placetype":"venue"
},
  "geometry": {"coordinates":[-87.368279,36.555405],"type":"Point"}
}