{
  "type": "Feature",
  "properties": {
    "iso:country":"US",
    "sg:address":"1228 Northgate Business Pkwy",
    "sg:city":"Madison",
    "sg:classifiers":[
        {
            "category":"Retail",
            "subcategory":"Repair Shop",
            "type":"Services"
        },
        {
            "category":"Home & Garden",
            "subcategory":"Garden Supply",
            "type":"Retail Goods"
        }
    ],
    "sg:phone":"+1 615 865 6608",
    "sg:postcode":"37115",
    "sg:province":"TN",
    "sg:tags":[
        "engine",
        "lawn",
        "mower"
    ],
    "wof:name":"Fixwell Power Equipment Inc",
    "wof:placetype":"venue"
},
  "geometry": {"coordinates":[-86.690305,36.285552],"type":"Point"}
}