{
  "type": "Feature",
  "properties": {
    "iso:country":"US",
    "sg:address":"1522 State Hwy 88",
    "sg:city":"Gates",
    "sg:phone":"+1 731 836 9546",
    "sg:postcode":"38037",
    "sg:province":"TN",
    "sg:tags":[
        "farm",
        "corn"
    ],
    "wof:name":"Mike Carmack Farm",
    "wof:placetype":"venue"
},
  "geometry": {"coordinates":[-89.636151,35.895165],"type":"Point"}
}