{
  "type": "Feature",
  "properties": {
    "iso:country":"US",
    "sg:address":"8 W Dempster Ave",
    "sg:city":"Memphis",
    "sg:classifiers":[
        {
            "category":"Organizations",
            "subcategory":"Religious Organization",
            "type":"Services"
        }
    ],
    "sg:phone":"+1 901 948 5227",
    "sg:postcode":"38109",
    "sg:province":"TN",
    "sg:tags":[
        "church"
    ],
    "wof:name":"United Missionary Baptist Chr",
    "wof:placetype":"venue"
},
  "geometry": {"coordinates":[-90.064279,35.085727],"type":"Point"}
}