{
  "type": "Feature",
  "properties": {
    "iso:country":"US",
    "sg:address":"3250 Jackson Ave",
    "sg:city":"Memphis",
    "sg:classifiers":[
        {
            "category":"Shopping",
            "subcategory":"Clothing, Apparel, & Fashions",
            "type":"Retail Goods"
        }
    ],
    "sg:phone":"+1 901 458 7111",
    "sg:postcode":"38108",
    "sg:province":"TN",
    "wof:name":"Simply 6",
    "wof:placetype":"venue"
},
  "geometry": {"coordinates":[-89.951521,35.165749],"type":"Point"}
}