{
  "type": "Feature",
  "properties": {
    "addr:full":"2048 Fishing Ford Rd Belfast TN 37019",
    "addr:housenumber":"2048",
    "addr:postcode":"37019",
    "addr:street":"Fishing Ford Rd",
    "iso:country":"US",
    "sg:address":"2048 Fishing Ford Rd",
    "sg:city":"Belfast",
    "sg:classifiers":[
        {
            "category":"Autos & Motor Vehicles",
            "subcategory":"Automobile Sales",
            "type":"Retail Goods"
        }
    ],
    "sg:phone":"+1 931 276 2338",
    "sg:postcode":"37019",
    "sg:province":"TN",
    "sg:tags":[
        "used",
        "animal"
    ],
    "wof:name":"Hidden Hollow Sales",
    "wof:placetype":"venue"
},
  "geometry": {"coordinates":[-86.70830599999999,35.404767],"type":"Point"}
}