{
  "type": "Feature",
  "properties": {
    "iso:country":"US",
    "sg:address":"2437 Montvale Rd",
    "sg:city":"Maryville",
    "sg:classifiers":[
        {
            "category":"Building & Trades",
            "subcategory":"Electrical",
            "type":"Services"
        }
    ],
    "sg:phone":"+1 865 977 1744",
    "sg:postcode":"37803",
    "sg:province":"TN",
    "sg:tags":[
        "electrical",
        "contractor"
    ],
    "wof:name":"Southeastern Elec Contructors",
    "wof:placetype":"venue"
},
  "geometry": {"coordinates":[-83.966652,35.715733],"type":"Point"}
}