{
  "type": "Feature",
  "properties": {
    "iso:country":"US",
    "sg:address":"100 N Seven Oaks Dr",
    "sg:city":"Knoxville",
    "sg:classifiers":[
        {
            "category":"Restaurant",
            "type":"Food & Drink"
        }
    ],
    "sg:phone":"+1 865 560 8838",
    "sg:postcode":"37922",
    "sg:province":"TN",
    "wof:name":"China Buffet",
    "wof:placetype":"venue"
},
  "geometry": {"coordinates":[-84.098806,35.913996],"type":"Point"}
}