{
  "type": "Feature",
  "properties": {
    "iso:country":"US",
    "sg:address":"2863 Harley Rd",
    "sg:city":"Morristown",
    "sg:classifiers":[
        {
            "category":"Professional",
            "subcategory":"Business Services",
            "type":"Services"
        }
    ],
    "sg:phone":"+1 423 587 4605",
    "sg:postcode":"37813",
    "sg:province":"TN",
    "wof:name":"Jds & Assoc LLC",
    "wof:placetype":"venue"
},
  "geometry": {"coordinates":[-83.323482,36.174084],"type":"Point"}
}