{
  "type": "Feature",
  "properties": {
    "iso:country":"US",
    "sg:address":"1515 Goodbar Ave",
    "sg:city":"Memphis",
    "sg:classifiers":[
        {
            "category":"Banks & Credit Unions",
            "subcategory":"Investment Brokerage",
            "type":"Services"
        }
    ],
    "sg:phone":"+1 901 722 2455",
    "sg:postcode":"38104",
    "sg:province":"TN",
    "sg:tags":[
        "advisory"
    ],
    "wof:name":"Financial Counselors America",
    "wof:placetype":"venue"
},
  "geometry": {"coordinates":[-90.012055,35.128508],"type":"Point"}
}