{
  "type": "Feature",
  "properties": {
    "iso:country":"US",
    "sg:address":"10409 Cogdill Rd",
    "sg:city":"Knoxville",
    "sg:classifiers":[
        {
            "category":"Professional",
            "type":"Services"
        },
        {
            "category":"Personal",
            "type":"Services"
        },
        {
            "category":"Retail",
            "subcategory":"Storage",
            "type":"Services"
        }
    ],
    "sg:phone":"+1 865 951 7294",
    "sg:postcode":"37932",
    "sg:province":"TN",
    "sg:tags":[
        "full",
        "household",
        "material",
        "commercial",
        "movers-commercial",
        "industrial",
        "moving",
        "services-labor",
        "mover"
    ],
    "sg:website":"http://www.tomtracker.com/redirect.cfm?bID=18703&hID=123840",
    "wof:name":"Dodson's Moving & Storage Co., Inc",
    "wof:placetype":"venue"
},
  "geometry": {"coordinates":[-84.131787,35.913325],"type":"Point"}
}