{
  "type": "Feature",
  "properties": {
    "addr:full":"585 S Mount Juliet Rd Mt Juliet TN 37122",
    "addr:housenumber":"585",
    "addr:postcode":"37122",
    "addr:street":"S Mount Juliet Rd",
    "iso:country":"US",
    "sg:address":"585 S Mount Juliet Rd",
    "sg:city":"Mt Juliet",
    "sg:classifiers":[
        {
            "category":"Farming",
            "subcategory":"Farm",
            "type":"Manufacturing & Wholesale Goods"
        }
    ],
    "sg:phone":"+1 615 758 3266",
    "sg:postcode":"37122",
    "sg:province":"TN",
    "wof:name":"Rocky Top Farm",
    "wof:placetype":"venue"
},
  "geometry": {"coordinates":[-86.51487899999999,36.163032],"type":"Point"}
}