{
  "type": "Feature",
  "properties": {
    "addr:full":"1016 US Hwy 45 Selmer TN 38375",
    "addr:housenumber":"1016",
    "addr:postcode":"38375",
    "addr:street":"Us Hwy 45",
    "iso:country":"US",
    "sg:address":"1016 US Hwy 45",
    "sg:city":"Selmer",
    "sg:classifiers":[
        {
            "category":"Autos & Motor Vehicles",
            "subcategory":"Recreational Vehicle Sales",
            "type":"Retail Goods"
        }
    ],
    "sg:phone":"+1 731 645 9640",
    "sg:postcode":"38375",
    "sg:province":"TN",
    "wof:name":"Mid-SOUTH Rv",
    "wof:placetype":"venue"
},
  "geometry": {"coordinates":[-88.57149699999999,35.139496],"type":"Point"}
}