{
  "type": "Feature",
  "properties": {
    "addr:full":"2431 N Germantown Pkwy Cordova TN 38016",
    "addr:housenumber":"2431",
    "addr:postcode":"38016",
    "addr:street":"N Germantown Pkwy",
    "iso:country":"US",
    "sg:address":"2431 N Germantown Pkwy",
    "sg:city":"Cordova",
    "sg:classifiers":[
        {
            "category":"Health Services",
            "subcategory":"Optometrist",
            "type":"Services"
        }
    ],
    "sg:phone":"+1 901 214 0014",
    "sg:postcode":"38016",
    "sg:province":"TN",
    "wof:name":"Mike M Sandy OD",
    "wof:placetype":"venue"
},
  "geometry": {"coordinates":[-89.792548,35.192955],"type":"Point"}
}