{
  "type": "Feature",
  "properties": {
    "iso:country":"US",
    "sg:address":"102 Woodmont Blvd",
    "sg:city":"Nashville",
    "sg:classifiers":[
        {
            "category":"Professional",
            "subcategory":"Computer Services",
            "type":"Services"
        },
        {
            "category":"Shopping",
            "subcategory":"Computers & Home Electronics",
            "type":"Retail Goods"
        }
    ],
    "sg:phone":"+1 615 777 2727",
    "sg:postcode":"37205",
    "sg:province":"TN",
    "sg:tags":[
        "development",
        "software"
    ],
    "sg:website":"www.digichart.com",
    "wof:name":"Digichart Inc",
    "wof:placetype":"venue"
},
  "geometry": {"coordinates":[-86.84618399999999,36.12357],"type":"Point"}
}