{
  "type": "Feature",
  "properties": {
    "addr:full":"334 Hughes Rd E Jackson TN 38305",
    "addr:housenumber":"334",
    "addr:postcode":"38305",
    "addr:street":"Hughes Rd E",
    "iso:country":"US",
    "sg:address":"334 Hughes Rd E",
    "sg:city":"Jackson",
    "sg:classifiers":[
        {
            "category":"Education",
            "subcategory":"School",
            "type":"Public Place"
        }
    ],
    "sg:phone":"+1 731 424 5127",
    "sg:postcode":"38305",
    "sg:province":"TN",
    "wof:name":"Palm Construction School",
    "wof:placetype":"venue"
},
  "geometry": {"coordinates":[-88.64856899999999,35.772148],"type":"Point"}
}