{
  "type": "Feature",
  "properties": {
    "iso:country":"US",
    "sg:address":"201 2nd Ave",
    "sg:city":"Columbia",
    "sg:classifiers":[
        {
            "category":"Farming",
            "subcategory":"Farm",
            "type":"Manufacturing & Wholesale Goods"
        }
    ],
    "sg:phone":"+1 931 384 0192",
    "sg:postcode":"38401",
    "sg:province":"TN",
    "sg:tags":[
        "crop",
        "general"
    ],
    "wof:name":"Colin Brady Farms",
    "wof:placetype":"venue"
},
  "geometry": {"coordinates":[-87.02659199999999,35.62016],"type":"Point"}
}