{
  "type": "Feature",
  "properties": {
    "iso:country":"US",
    "sg:address":"829 NW Broad St",
    "sg:city":"Murfreesboro",
    "sg:classifiers":[
        {
            "category":"Restaurant",
            "type":"Food & Drink"
        }
    ],
    "sg:phone":"+1 615 893 1217",
    "sg:postcode":"37129",
    "sg:province":"TN",
    "sg:website":"www.checkers.com",
    "wof:name":"Checkers Drive-In Restaurant",
    "wof:placetype":"venue"
},
  "geometry": {"coordinates":[-86.394733,35.844647],"type":"Point"}
}