{
  "type": "Feature",
  "properties": {
    "iso:country":"US",
    "sg:address":"1254 Lamar Ave",
    "sg:city":"Memphis",
    "sg:classifiers":[
        {
            "category":"Real Estate",
            "subcategory":"Real Estate Agent",
            "type":"Services"
        }
    ],
    "sg:phone":"+1 901 722 5004",
    "sg:postcode":"38104",
    "sg:province":"TN",
    "sg:tags":[
        "management"
    ],
    "wof:name":"Cross Management",
    "wof:placetype":"venue"
},
  "geometry": {"coordinates":[-90.019293,35.127841],"type":"Point"}
}