{
  "type": "Feature",
  "properties": {
    "iso:country":"US",
    "sg:address":"900 S Gay St",
    "sg:city":"Knoxville",
    "sg:classifiers":[
        {
            "category":"Arts & Performance",
            "subcategory":"Theater",
            "type":"Entertainment"
        }
    ],
    "sg:phone":"+1 865 246 0842",
    "sg:postcode":"37902",
    "sg:province":"TN",
    "sg:tags":[
        "group"
    ],
    "wof:name":"Impact Sports & Entrmt LLC",
    "wof:placetype":"venue"
},
  "geometry": {"coordinates":[-83.91572600000001,35.960934],"type":"Point"}
}