{
  "type": "Feature",
  "properties": {
    "iso:country":"US",
    "sg:address":"7275 Goodlett Farms Pkwy",
    "sg:city":"Cordova",
    "sg:classifiers":[
        {
            "category":"Manufacturing",
            "subcategory":"Tools & Machinery",
            "type":"Manufacturing & Wholesale Goods"
        }
    ],
    "sg:phone":"+1 901 381 2304",
    "sg:postcode":"38016",
    "sg:province":"TN",
    "sg:tags":[
        "physician",
        "surgeon"
    ],
    "sg:website":"www.luciteinternational.com",
    "wof:name":"Lucite International",
    "wof:placetype":"venue"
},
  "geometry": {"coordinates":[-89.818663,35.18036],"type":"Point"}
}