{
  "type": "Feature",
  "properties": {
    "iso:country":"US",
    "sg:address":"3736 S Mendenhall Rd",
    "sg:city":"Memphis",
    "sg:classifiers":[
        {
            "category":"Restaurant",
            "type":"Food & Drink"
        }
    ],
    "sg:phone":"+1 901 794 9600",
    "sg:postcode":"38115",
    "sg:province":"TN",
    "sg:tags":[
        "pizza"
    ],
    "wof:name":"East Memphis Pizza & Subs Factory",
    "wof:placetype":"venue"
},
  "geometry": {"coordinates":[-89.885965,35.046828],"type":"Point"}
}