{
  "type": "Feature",
  "properties": {
    "iso:country":"US",
    "sg:address":"7936 Blueberry Rd",
    "sg:city":"Powell",
    "sg:classifiers":[
        {
            "category":"Professional",
            "subcategory":"Testing Lab",
            "type":"Services"
        }
    ],
    "sg:phone":"+1 865 938 2388",
    "sg:postcode":"37849",
    "sg:province":"TN",
    "sg:tags":[
        "laboratory"
    ],
    "wof:name":"Kelco",
    "wof:placetype":"venue"
},
  "geometry": {"coordinates":[-84.00984200000001,36.053144],"type":"Point"}
}