{
  "type": "Feature",
  "properties": {
    "addr:full":"3497 Stanton Rd Memphis TN 38108",
    "addr:housenumber":"3497",
    "addr:postcode":"38108",
    "addr:street":"Stanton Rd",
    "iso:country":"US",
    "sg:address":"3497 Stanton Rd",
    "sg:city":"Memphis",
    "sg:classifiers":[
        {
            "category":"Retail",
            "subcategory":"Repair Shop",
            "type":"Services"
        }
    ],
    "sg:phone":"+1 901 388 1550",
    "sg:postcode":"38108",
    "sg:province":"TN",
    "sg:tags":[
        "valve"
    ],
    "sg:website":"www.tvimem.com",
    "wof:name":"Tri State Valve & Instrument",
    "wof:placetype":"venue"
},
  "geometry": {"coordinates":[-89.94253999999999,35.174751],"type":"Point"}
}