{
  "type": "Feature",
  "properties": {
    "iso:country":"US",
    "sg:address":"724 N Edgewood Dr",
    "sg:city":"Sparta",
    "sg:classifiers":[
        {
            "category":"Personal",
            "subcategory":"Beauty Salon",
            "type":"Services"
        }
    ],
    "sg:phone":"+1 931 738 2595",
    "sg:postcode":"38583",
    "sg:province":"TN",
    "sg:tags":[
        "shop"
    ],
    "wof:name":"Nu Look Beauty Hut",
    "wof:placetype":"venue"
},
  "geometry": {"coordinates":[-85.47701499999999,35.965003],"type":"Point"}
}