{
  "type": "Feature",
  "properties": {
    "iso:country":"US",
    "sg:address":"4321 Green Shanty Rd",
    "sg:city":"Ooltewah",
    "sg:classifiers":[
        {
            "category":"Building & Trades",
            "subcategory":"Construction",
            "type":"Services"
        }
    ],
    "sg:phone":"+1 423 892 0438",
    "sg:postcode":"37363",
    "sg:province":"TN",
    "sg:tags":[
        "installation",
        "pump",
        "gas"
    ],
    "wof:name":"Shipley Ulyess & Son Cnstr Co",
    "wof:placetype":"venue"
},
  "geometry": {"coordinates":[-85.11147699999999,35.052831],"type":"Point"}
}