{
  "type": "Feature",
  "properties": {
    "iso:country":"US",
    "sg:address":"2656 Parkway",
    "sg:city":"Pigeon Forge",
    "sg:classifiers":[
        {
            "category":"Restaurant",
            "type":"Food & Drink"
        }
    ],
    "sg:phone":"+1 865 428 2496",
    "sg:postcode":"37863",
    "sg:province":"TN",
    "sg:tags":[
        "pizza"
    ],
    "wof:name":"Geno's Pizza Inc",
    "wof:placetype":"venue"
},
  "geometry": {"coordinates":[-83.57406,35.802932],"type":"Point"}
}