{
  "type": "Feature",
  "properties": {
    "iso:country":"US",
    "sg:address":"3414 Old Hickory Blvd",
    "sg:city":"Old Hickory",
    "sg:classifiers":[
        {
            "category":"Building & Trades",
            "subcategory":"Electrical",
            "type":"Services"
        }
    ],
    "sg:phone":"+1 615 847 8268",
    "sg:postcode":"37138",
    "sg:province":"TN",
    "sg:tags":[
        "electric",
        "contractor"
    ],
    "wof:name":"ASAP Mike's Electrical Rpr",
    "wof:placetype":"venue"
},
  "geometry": {"coordinates":[-86.633928,36.241753],"type":"Point"}
}