{
  "type": "Feature",
  "properties": {
    "addr:full":"911 Decatur Pike Athens TN 37303",
    "addr:housenumber":"911",
    "addr:postcode":"37303",
    "addr:street":"Decatur Pike",
    "iso:country":"US",
    "sg:address":"911 Decatur Pike",
    "sg:city":"Athens",
    "sg:classifiers":[
        {
            "category":"Shopping",
            "subcategory":"Discount & Variety Stores",
            "type":"Retail Goods"
        },
        {
            "category":"Shopping",
            "subcategory":"Department Store",
            "type":"Retail Goods"
        }
    ],
    "sg:phone":"+1 423 745 2346",
    "sg:postcode":"37303",
    "sg:province":"TN",
    "wof:name":"Family Dollar Stores",
    "wof:placetype":"venue"
},
  "geometry": {"coordinates":[-84.6129,35.448287],"type":"Point"}
}