{
  "type": "Feature",
  "properties": {
    "iso:country":"US",
    "sg:address":"142 Beeler Rd",
    "sg:city":"Maynardville",
    "sg:classifiers":[
        {
            "category":"Building & Trades",
            "subcategory":"Construction",
            "type":"Services"
        }
    ],
    "sg:phone":"+1 865 992 9881",
    "sg:postcode":"37807",
    "sg:province":"TN",
    "sg:tags":[
        "sandblasting"
    ],
    "wof:name":"Pro Coatings",
    "wof:placetype":"venue"
},
  "geometry": {"coordinates":[-83.89647600000001,36.239971],"type":"Point"}
}