{
  "type": "Feature",
  "properties": {
    "addr:full":"801 Lafayette Rd Clarksville TN 37042",
    "addr:housenumber":"801",
    "addr:postcode":"37042",
    "iso:country":"US",
    "sg:address":"801 Lafayette Rd",
    "sg:city":"Clarksville",
    "sg:classifiers":[
        {
            "category":"Organizations",
            "subcategory":"Religious Organization",
            "type":"Services"
        }
    ],
    "sg:phone":"+1 931 645 1748",
    "sg:postcode":"37042",
    "sg:province":"TN",
    "wof:name":"The Corporation of The Pres of",
    "wof:placetype":"venue"
},
  "geometry": {"coordinates":[-87.432045,36.575656],"type":"Point"}
}