{
  "type": "Feature",
  "properties": {
    "iso:country":"US",
    "sg:address":"1804 Dahlia Dr",
    "sg:city":"Nashville",
    "sg:classifiers":[
        {
            "category":"Building & Trades",
            "subcategory":"Construction",
            "type":"Services"
        }
    ],
    "sg:phone":"+1 615 889 9559",
    "sg:postcode":"37210",
    "sg:province":"TN",
    "sg:tags":[
        "remodeling",
        "handyman"
    ],
    "wof:name":"Home Tech",
    "wof:placetype":"venue"
},
  "geometry": {"coordinates":[-86.71265699999999,36.161762],"type":"Point"}
}