{
  "type": "Feature",
  "properties": {
    "iso:country":"US",
    "sg:address":"7306 Fountain Grove Rd",
    "sg:city":"Morrison",
    "sg:classifiers":[
        {
            "category":"Freight",
            "type":"Transportation"
        }
    ],
    "sg:phone":"+1 931 728 3977",
    "sg:postcode":"37357",
    "sg:province":"TN",
    "sg:tags":[
        "grain",
        "elevator"
    ],
    "wof:name":"Smith Grain Co",
    "wof:placetype":"venue"
},
  "geometry": {"coordinates":[-85.928938,35.533741],"type":"Point"}
}