{
  "type": "Feature",
  "properties": {
    "addr:full":"125 Stonebridge Blvd Jackson TN 38305",
    "addr:housenumber":"125",
    "addr:postcode":"38305",
    "addr:street":"Stonebridge Blvd",
    "iso:country":"US",
    "sg:address":"125 Stonebridge Blvd",
    "sg:city":"Jackson",
    "sg:classifiers":[
        {
            "category":"Social Services",
            "subcategory":"Child Care",
            "type":"Services"
        }
    ],
    "sg:phone":"+1 731 660 0001",
    "sg:postcode":"38305",
    "sg:province":"TN",
    "sg:tags":[
        "sitting"
    ],
    "sg:website":"www.sittersandmore.com",
    "wof:name":"Sitters & More",
    "wof:placetype":"venue"
},
  "geometry": {"coordinates":[-88.85237600000001,35.676408],"type":"Point"}
}