{
  "type": "Feature",
  "properties": {
    "addr:full":"360 Deaderick St Nashville TN 37201",
    "addr:housenumber":"360",
    "addr:postcode":"37201",
    "addr:street":"Deaderick St",
    "iso:country":"US",
    "sg:address":"360 Deaderick St",
    "sg:city":"Nashville",
    "sg:classifiers":[
        {
            "category":"Freight",
            "type":"Transportation"
        }
    ],
    "sg:phone":"+1 615 248 2212",
    "sg:postcode":"37201",
    "sg:province":"TN",
    "sg:tags":[
        "delivery",
        "courier"
    ],
    "wof:name":"Road Runner Courier Svc LLC",
    "wof:placetype":"venue"
},
  "geometry": {"coordinates":[-86.779698,36.166203],"type":"Point"}
}