{
  "type": "Feature",
  "properties": {
    "iso:country":"US",
    "sg:address":"6786 Kamali Ave",
    "sg:city":"Cordova",
    "sg:classifiers":[
        {
            "category":"Freight",
            "type":"Transportation"
        }
    ],
    "sg:phone":"+1 901 382 8090",
    "sg:postcode":"38018",
    "sg:province":"TN",
    "wof:name":"Harbour Transportation",
    "wof:placetype":"venue"
},
  "geometry": {"coordinates":[-89.83602,35.161122],"type":"Point"}
}