{
  "type": "Feature",
  "properties": {
    "iso:country":"US",
    "sg:address":"108 Bridge St",
    "sg:city":"Franklin",
    "sg:classifiers":[
        {
            "category":"Restaurant",
            "type":"Food & Drink"
        }
    ],
    "sg:phone":"+1 615 790 6998",
    "sg:postcode":"37064",
    "sg:province":"TN",
    "sg:tags":[
        "caterer"
    ],
    "wof:name":"Monell's At Franklin Catering",
    "wof:placetype":"venue"
},
  "geometry": {"coordinates":[-86.868667,35.927501],"type":"Point"}
}