{
  "type": "Feature",
  "properties": {
    "iso:country":"US",
    "sg:address":"7236 Bonny Oaks Dr",
    "sg:city":"Chattanooga",
    "sg:classifiers":[
        {
            "category":"Place Of Worship",
            "subcategory":"Church",
            "type":"Public Place"
        },
        {
            "category":"Place Of Worship",
            "type":"Public Place"
        }
    ],
    "sg:phone":"+1 423 892 2173",
    "sg:postcode":"37421",
    "sg:province":"TN",
    "sg:tags":[
        "churches-baptist"
    ],
    "sg:website":"http://www.silverdalebc.com",
    "wof:name":"Silverdale Baptist Church",
    "wof:placetype":"venue"
},
  "geometry": {"coordinates":[-85.138931,35.062752],"type":"Point"}
}