{
  "type": "Feature",
  "properties": {
    "addr:full":"1270 Jackson Pond Cir Cordova TN 38018",
    "addr:housenumber":"1270",
    "addr:postcode":"38018",
    "addr:street":"Jackson Pond Cir",
    "iso:country":"US",
    "sg:address":"1270 Jackson Pond Cir",
    "sg:city":"Cordova",
    "sg:classifiers":[
        {
            "category":"Government",
            "subcategory":"Office",
            "type":"Public Place"
        }
    ],
    "sg:phone":"+1 901 309 1761",
    "sg:postcode":"38018",
    "sg:province":"TN",
    "sg:tags":[
        "township",
        "government-city",
        "village"
    ],
    "wof:name":"City Of Memphis",
    "wof:placetype":"venue"
},
  "geometry": {"coordinates":[-89.737971,35.160699],"type":"Point"}
}