{
  "type": "Feature",
  "properties": {
    "iso:country":"US",
    "sg:address":"132 S Lowe Ave",
    "sg:city":"Cookeville",
    "sg:classifiers":[
        {
            "category":"Health Services",
            "subcategory":"Doctor",
            "type":"Services"
        }
    ],
    "sg:phone":"+1 931 526 3151",
    "sg:postcode":"38501",
    "sg:province":"TN",
    "sg:tags":[
        "clinic",
        "medical"
    ],
    "wof:name":"Cookeville Chiroprctc & Physcl",
    "wof:placetype":"venue"
},
  "geometry": {"coordinates":[-85.49881000000001,36.160773],"type":"Point"}
}