{
  "type": "Feature",
  "properties": {
    "iso:country":"US",
    "sg:address":"5510 Old Hickory Blvd",
    "sg:city":"Hermitage",
    "sg:classifiers":[
        {
            "category":"Personal",
            "subcategory":"Beauty Salon",
            "type":"Services"
        }
    ],
    "sg:phone":"+1 615 889 6374",
    "sg:postcode":"37076",
    "sg:province":"TN",
    "wof:name":"Style America",
    "wof:placetype":"venue"
},
  "geometry": {"coordinates":[-86.60787500000001,36.182198],"type":"Point"}
}