{
  "type": "Feature",
  "properties": {
    "addr:full":"359 Grant Hwy Gordonsville TN 38563",
    "addr:housenumber":"359",
    "addr:postcode":"38563",
    "addr:street":"Grant Hwy",
    "iso:country":"US",
    "sg:address":"359 Grant Hwy",
    "sg:city":"Gordonsville",
    "sg:classifiers":[
        {
            "category":"Wholesale",
            "subcategory":"Construction Materials",
            "type":"Manufacturing & Wholesale Goods"
        }
    ],
    "sg:phone":"+1 615 683 4220",
    "sg:postcode":"38563",
    "sg:province":"TN",
    "wof:name":"Grant Cedar Mill",
    "wof:placetype":"venue"
},
  "geometry": {"coordinates":[-86.07203699999999,36.185656],"type":"Point"}
}