{
  "type": "Feature",
  "properties": {
    "addr:full":"1902 University Ave Knoxville TN 37921",
    "addr:housenumber":"1902",
    "addr:postcode":"37921",
    "addr:street":"University Ave",
    "iso:country":"US",
    "sg:address":"1902 University Ave",
    "sg:city":"Knoxville",
    "sg:classifiers":[
        {
            "category":"Retail",
            "subcategory":"Auto Repair",
            "type":"Services"
        }
    ],
    "sg:phone":"+1 865 525 5582",
    "sg:postcode":"37921",
    "sg:province":"TN",
    "sg:tags":[
        "body"
    ],
    "wof:name":"Custom Paint & Body",
    "wof:placetype":"venue"
},
  "geometry": {"coordinates":[-83.94225,35.965101],"type":"Point"}
}