{
  "type": "Feature",
  "properties": {
    "iso:country":"US",
    "sg:address":"519 Carver Ln",
    "sg:city":"Lebanon",
    "sg:classifiers":[
        {
            "category":"Manufacturing",
            "subcategory":"Apparel",
            "type":"Manufacturing & Wholesale Goods"
        }
    ],
    "sg:phone":"+1 615 812 5374",
    "sg:postcode":"37087",
    "sg:province":"TN",
    "sg:tags":[
        "mfg"
    ],
    "wof:name":"Finishing Room",
    "wof:placetype":"venue"
},
  "geometry": {"coordinates":[-86.33448,36.246342],"type":"Point"}
}