{
  "type": "Feature",
  "properties": {
    "addr:full":"120 Sugar Maple N Hendersonville TN 37075",
    "addr:housenumber":"120",
    "addr:postcode":"37075",
    "addr:street":"Sugar Maple N",
    "iso:country":"US",
    "sg:address":"120 Sugar Maple N",
    "sg:city":"Hendersonville",
    "sg:classifiers":[
        {
            "category":"Shopping",
            "subcategory":"Gifts & Souvenirs",
            "type":"Retail Goods"
        }
    ],
    "sg:phone":"+1 615 822 6060",
    "sg:postcode":"37075",
    "sg:province":"TN",
    "wof:name":"Heavenly Wshes Gfts Design LLC",
    "wof:placetype":"venue"
},
  "geometry": {"coordinates":[-86.586293,36.303298],"type":"Point"}
}