{
  "type": "Feature",
  "properties": {
    "iso:country":"US",
    "sg:address":"3018 Patty View Way",
    "sg:city":"Sevierville",
    "sg:classifiers":[
        {
            "category":"Building & Trades",
            "subcategory":"Construction",
            "type":"Services"
        }
    ],
    "sg:phone":"+1 865 654 3731",
    "sg:postcode":"37862",
    "sg:province":"TN",
    "sg:tags":[
        "house"
    ],
    "wof:name":"Do Construction Inc",
    "wof:placetype":"venue"
},
  "geometry": {"coordinates":[-83.692442,35.758082],"type":"Point"}
}