{
  "type": "Feature",
  "properties": {
    "addr:full":"6304 Booth Ct Kingsport TN 37663",
    "addr:housenumber":"6304",
    "addr:postcode":"37663",
    "addr:street":"Booth Ct",
    "iso:country":"US",
    "sg:address":"6304 Booth Ct",
    "sg:city":"Kingsport",
    "sg:classifiers":[
        {
            "category":"Government",
            "subcategory":"Office",
            "type":"Public Place"
        }
    ],
    "sg:phone":"+1 423 361 0661",
    "sg:postcode":"37663",
    "sg:province":"TN",
    "sg:tags":[
        "on",
        "instructor",
        "management",
        "emergency"
    ],
    "wof:name":"Richard A Ranker",
    "wof:placetype":"venue"
},
  "geometry": {"coordinates":[-82.466145,36.445446],"type":"Point"}
}