{
  "type": "Feature",
  "properties": {
    "iso:country":"US",
    "sg:address":"6400 Shelby View Dr",
    "sg:city":"Memphis",
    "sg:classifiers":[
        {
            "category":"Wholesale",
            "subcategory":"Furniture",
            "type":"Manufacturing & Wholesale Goods"
        }
    ],
    "sg:phone":"+1 800 251 9881",
    "sg:postcode":"38134",
    "sg:province":"TN",
    "sg:tags":[
        "product",
        "f",
        "paper",
        "imaging",
        "po",
        "printed"
    ],
    "wof:name":"Hamco Business Info Sups Co",
    "wof:placetype":"venue"
},
  "geometry": {"coordinates":[-89.850032,35.178104],"type":"Point"}
}