{
  "type": "Feature",
  "properties": {
    "iso:country":"US",
    "sg:address":"122 Depot Ln",
    "sg:city":"Townsend",
    "sg:classifiers":[
        {
            "category":"Restaurant",
            "type":"Food & Drink"
        }
    ],
    "sg:phone":"+1 865 448 1924",
    "sg:postcode":"37819",
    "sg:province":"TN",
    "sg:tags":[
        "eating"
    ],
    "wof:name":"Miss Lilys Cafe Flor & Catrg",
    "wof:placetype":"venue"
},
  "geometry": {"coordinates":[-84.165385,36.554791],"type":"Point"}
}