{
  "type": "Feature",
  "properties": {
    "iso:country":"US",
    "sg:address":"5 N 3rd St",
    "sg:city":"Memphis",
    "sg:classifiers":[
        {
            "category":"Banks & Credit Unions",
            "subcategory":"Investment Brokerage",
            "type":"Services"
        }
    ],
    "sg:phone":"+1 901 524 0801",
    "sg:postcode":"38103",
    "sg:province":"TN",
    "sg:tags":[
        "consultant",
        "financing"
    ],
    "wof:name":"Tab Buford & Assoc",
    "wof:placetype":"venue"
},
  "geometry": {"coordinates":[-90.050234,35.144911],"type":"Point"}
}