{
  "type": "Feature",
  "properties": {
    "iso:country":"US",
    "sg:address":"1291 E Madison Ave",
    "sg:city":"Athens",
    "sg:classifiers":[
        {
            "category":"Organizations",
            "subcategory":"Religious Organization",
            "type":"Services"
        }
    ],
    "sg:phone":"+1 423 745 4277",
    "sg:postcode":"37303",
    "sg:province":"TN",
    "sg:tags":[
        "church"
    ],
    "wof:name":"St Mary's Catholic Church",
    "wof:placetype":"venue"
},
  "geometry": {"coordinates":[-84.576695,35.452246],"type":"Point"}
}