{
  "type": "Feature",
  "properties": {
    "iso:country":"US",
    "sg:address":"6409 E Valley Ct",
    "sg:city":"Nashville",
    "sg:classifiers":[
        {
            "category":"Professional",
            "type":"Services"
        }
    ],
    "sg:phone":"+1 615 352 4147",
    "sg:postcode":"37205",
    "sg:province":"TN",
    "wof:name":"Kids Lit LLC",
    "wof:placetype":"venue"
},
  "geometry": {"coordinates":[-86.88145299999999,36.100513],"type":"Point"}
}