{
  "type": "Feature",
  "properties": {
    "iso:country":"US",
    "sg:address":"2065 Fletcher Creek Dr",
    "sg:city":"Memphis",
    "sg:classifiers":[
        {
            "category":"Building & Trades",
            "subcategory":"Plumbing",
            "type":"Services"
        }
    ],
    "sg:phone":"+1 901 362 5000",
    "sg:postcode":"38133",
    "sg:province":"TN",
    "sg:tags":[
        "plumbing",
        "contractor"
    ],
    "wof:name":"White Plumbing & Mechanical",
    "wof:placetype":"venue"
},
  "geometry": {"coordinates":[-89.838632,35.182145],"type":"Point"}
}