{
  "type": "Feature",
  "properties": {
    "addr:full":"5014 Autumnwood Dr Memphis TN 38116",
    "addr:housenumber":"5014",
    "addr:postcode":"38116",
    "addr:street":"Autumnwood Dr",
    "iso:country":"US",
    "sg:address":"5014 Autumnwood Dr",
    "sg:city":"Memphis",
    "sg:classifiers":[
        {
            "category":"Professional",
            "subcategory":"Management & Consulting",
            "type":"Services"
        }
    ],
    "sg:phone":"+1 901 348 0027",
    "sg:postcode":"38116",
    "sg:province":"TN",
    "sg:tags":[
        "marketing",
        "consultant"
    ],
    "wof:name":"Newbern Rooks Marketing Consul",
    "wof:placetype":"venue"
},
  "geometry": {"coordinates":[-90.01275200000001,35.013343],"type":"Point"}
}