{
  "type": "Feature",
  "properties": {
    "iso:country":"US",
    "sg:address":"733 Pine Grove Rd",
    "sg:city":"Winfield",
    "sg:classifiers":[
        {
            "category":"Government",
            "subcategory":"Office",
            "type":"Public Place"
        }
    ],
    "sg:phone":"+1 423 569 4400",
    "sg:postcode":"37892",
    "sg:province":"TN",
    "sg:tags":[
        "village"
    ],
    "wof:name":"Winfield Police Dept",
    "wof:placetype":"venue"
},
  "geometry": {"coordinates":[-84.44927199999999,36.541843],"type":"Point"}
}