{
  "type": "Feature",
  "properties": {
    "iso:country":"US",
    "sg:address":"6456 Keswick Dr",
    "sg:city":"Memphis",
    "sg:classifiers":[
        {
            "category":"Real Estate",
            "subcategory":"Real Estate Agent",
            "type":"Services"
        }
    ],
    "sg:phone":"+1 901 763 1325",
    "sg:postcode":"38119",
    "sg:province":"TN",
    "sg:tags":[
        "inspection"
    ],
    "wof:name":"Home Team",
    "wof:placetype":"venue"
},
  "geometry": {"coordinates":[-89.847728,35.081072],"type":"Point"}
}