{
  "type": "Feature",
  "properties": {
    "iso:country":"US",
    "sg:address":"328 Chickamauga Ave NE",
    "sg:city":"Knoxville",
    "sg:classifiers":[
        {
            "category":"Social Services",
            "subcategory":"Child Care",
            "type":"Services"
        }
    ],
    "sg:phone":"+1 865 687 2274",
    "sg:postcode":"37917",
    "sg:province":"TN",
    "sg:tags":[
        "day"
    ],
    "wof:name":"Lincoln Park Play School",
    "wof:placetype":"venue"
},
  "geometry": {"coordinates":[-83.94257899999999,35.998063],"type":"Point"}
}