{
  "type": "Feature",
  "properties": {
    "iso:country":"US",
    "sg:address":"1212 Thomas St",
    "sg:city":"Memphis",
    "sg:classifiers":[
        {
            "category":"Health Services",
            "subcategory":"Clinic",
            "type":"Services"
        }
    ],
    "sg:phone":"+1 901 525 3800",
    "sg:postcode":"38107",
    "sg:province":"TN",
    "sg:tags":[
        "medical"
    ],
    "wof:name":"Harriette, Nellie Center For Health",
    "wof:placetype":"venue"
},
  "geometry": {"coordinates":[-90.03594,35.174756],"type":"Point"}
}