{
  "type": "Feature",
  "properties": {
    "iso:country":"US",
    "sg:address":"11908 Burchard Rd",
    "sg:city":"Soddy Daisy",
    "sg:classifiers":[
        {
            "category":"Building & Trades",
            "subcategory":"Electrical",
            "type":"Services"
        }
    ],
    "sg:phone":"+1 423 332 0685",
    "sg:postcode":"37379",
    "sg:province":"TN",
    "sg:tags":[
        "electrical",
        "contractor"
    ],
    "wof:name":"Watts Electric Inc",
    "wof:placetype":"venue"
},
  "geometry": {"coordinates":[-85.169281,35.313187],"type":"Point"}
}