{
  "type": "Feature",
  "properties": {
    "iso:country":"US",
    "sg:address":"111 S Cannon St",
    "sg:city":"Woodbury",
    "sg:classifiers":[
        {
            "category":"Personal",
            "subcategory":"Beauty Salon",
            "type":"Services"
        }
    ],
    "sg:phone":"+1 615 563 4247",
    "sg:postcode":"37190",
    "sg:province":"TN",
    "sg:tags":[
        "shop"
    ],
    "wof:name":"Hair Shop",
    "wof:placetype":"venue"
},
  "geometry": {"coordinates":[-86.069981,35.827519],"type":"Point"}
}