{
  "type": "Feature",
  "properties": {
    "iso:country":"US",
    "sg:address":"1136 S Wilcox Dr",
    "sg:city":"Kingsport",
    "sg:classifiers":[
        {
            "category":"Personal",
            "subcategory":"Beauty Salon",
            "type":"Services"
        }
    ],
    "sg:phone":"+1 423 247 6995",
    "sg:postcode":"37660",
    "sg:province":"TN",
    "sg:tags":[
        "shop"
    ],
    "wof:name":"Joniques Beauty Salon",
    "wof:placetype":"venue"
},
  "geometry": {"coordinates":[-82.561849,36.519986],"type":"Point"}
}