{
  "type": "Feature",
  "properties": {
    "iso:country":"US",
    "sg:address":"903 Moscow Ave",
    "sg:city":"Hickman",
    "sg:classifiers":[
        {
            "category":"Organizations",
            "subcategory":"Religious Organization",
            "type":"Services"
        }
    ],
    "sg:phone":"+1 270 236 9233",
    "sg:postcode":"42050",
    "sg:province":"TN",
    "wof:name":"Pleasant Hill Church",
    "wof:placetype":"venue"
},
  "geometry": {"coordinates":[-89.184095,36.571183],"type":"Point"}
}