{
  "type": "Feature",
  "properties": {
    "iso:country":"US",
    "sg:address":"417 S Washington St",
    "sg:city":"Ripley",
    "sg:classifiers":[
        {
            "category":"Wholesale",
            "subcategory":"Construction Materials",
            "type":"Manufacturing & Wholesale Goods"
        },
        {
            "category":"Real Estate",
            "subcategory":"Real Estate Agent",
            "type":"Services"
        }
    ],
    "sg:phone":"+1 731 635 2333",
    "sg:postcode":"38063",
    "sg:province":"TN",
    "sg:tags":[
        "property",
        "residential",
        "management",
        "commercial"
    ],
    "wof:name":"Allied Properties LP",
    "wof:placetype":"venue"
},
  "geometry": {"coordinates":[-89.54295999999999,35.731792],"type":"Point"}
}