{
  "type": "Feature",
  "properties": {
    "addr:full":"255 E Anderson Ave Knoxville TN 37917",
    "addr:housenumber":"255",
    "addr:postcode":"37917",
    "addr:street":"E Anderson Ave",
    "iso:country":"US",
    "sg:address":"255 E Anderson Ave",
    "sg:city":"Knoxville",
    "sg:classifiers":[
        {
            "category":"Retail",
            "subcategory":"Auto Repair",
            "type":"Services"
        }
    ],
    "sg:phone":"+1 865 329 0431",
    "sg:postcode":"37917",
    "sg:province":"TN",
    "sg:tags":[
        "recreational",
        "vehicle"
    ],
    "wof:name":"Dan Miller On Site Rv Repair",
    "wof:placetype":"venue"
},
  "geometry": {"coordinates":[-83.927094,35.983645],"type":"Point"}
}