{
  "type": "Feature",
  "properties": {
    "iso:country":"US",
    "sg:address":"4606 Elvis Presley Blvd",
    "sg:city":"Memphis",
    "sg:classifiers":[
        {
            "category":"Banks & Credit Unions",
            "subcategory":"Bank",
            "type":"Services"
        }
    ],
    "sg:phone":"+1 901 398 1342",
    "sg:postcode":"38116",
    "sg:province":"TN",
    "sg:tags":[
        "mortgage"
    ],
    "sg:website":"http://www.tristatebank.com",
    "wof:name":"Tri-State Bank Of Memphis",
    "wof:placetype":"venue"
},
  "geometry": {"coordinates":[-90.02520199999999,35.022903],"type":"Point"}
}