{
  "type": "Feature",
  "properties": {
    "addr:full":"524 Donelson Pike Nashville TN 37214",
    "addr:housenumber":"524",
    "addr:postcode":"37214",
    "addr:street":"Donelson Pike",
    "iso:country":"US",
    "sg:address":"524 Donelson Pike",
    "sg:city":"Nashville",
    "sg:classifiers":[
        {
            "category":"Personal",
            "subcategory":"Beauty Salon",
            "type":"Services"
        }
    ],
    "sg:phone":"+1 615 889 9880",
    "sg:postcode":"37214",
    "sg:province":"TN",
    "wof:name":"Cut N Care",
    "wof:placetype":"venue"
},
  "geometry": {"coordinates":[-86.666515,36.146802],"type":"Point"}
}