{
  "type": "Feature",
  "properties": {
    "iso:country":"US",
    "sg:address":"3675 Winpark Ct",
    "sg:city":"Memphis",
    "sg:classifiers":[
        {
            "category":"Wholesale",
            "subcategory":"Machinery & Supplies",
            "type":"Manufacturing & Wholesale Goods"
        }
    ],
    "sg:phone":"+1 901 759 1998",
    "sg:postcode":"38118",
    "sg:province":"TN",
    "sg:tags":[
        "salon",
        "beauty"
    ],
    "wof:name":"Forest Hill Ctr",
    "wof:placetype":"venue"
},
  "geometry": {"coordinates":[-89.94745399999999,35.047949],"type":"Point"}
}