{
  "type": "Feature",
  "properties": {
    "iso:country":"US",
    "sg:address":"21050 E Main St",
    "sg:city":"Huntingdon",
    "sg:classifiers":[
        {
            "category":"Restaurant",
            "type":"Food & Drink"
        }
    ],
    "sg:phone":"+1 731 986 0255",
    "sg:postcode":"38344",
    "sg:province":"TN",
    "sg:tags":[
        "eating"
    ],
    "wof:name":"Hardees",
    "wof:placetype":"venue"
},
  "geometry": {"coordinates":[-88.404888,36.007658],"type":"Point"}
}