{
  "type": "Feature",
  "properties": {
    "addr:full":"455 E Chester St Jackson TN 38301",
    "addr:housenumber":"455",
    "addr:postcode":"38301",
    "addr:street":"E Chester St",
    "iso:country":"US",
    "sg:address":"455 E Chester St",
    "sg:city":"Jackson",
    "sg:classifiers":[
        {
            "category":"Shopping",
            "type":"Retail Goods"
        }
    ],
    "sg:phone":"+1 731 422 7949",
    "sg:postcode":"38301",
    "sg:province":"TN",
    "sg:tags":[
        "cosmetic",
        "perfume"
    ],
    "wof:name":"Right Connection",
    "wof:placetype":"venue"
},
  "geometry": {"coordinates":[-88.814251,35.612584],"type":"Point"}
}