{
  "type": "Feature",
  "properties": {
    "iso:country":"US",
    "sg:address":"8951 Hester Beasley Rd",
    "sg:city":"Nashville",
    "sg:classifiers":[
        {
            "category":"Building & Trades",
            "subcategory":"Construction",
            "type":"Services"
        }
    ],
    "sg:phone":"+1 615 646 5495",
    "sg:postcode":"37221",
    "sg:province":"TN",
    "sg:tags":[
        "painter"
    ],
    "wof:name":"B & R Painting Co",
    "wof:placetype":"venue"
},
  "geometry": {"coordinates":[-87.010947,36.014914],"type":"Point"}
}