{
  "type": "Feature",
  "properties": {
    "iso:country":"US",
    "sg:address":"338 Baskins Creek Rd",
    "sg:city":"Gatlinburg",
    "sg:classifiers":[
        {
            "category":"Travel",
            "subcategory":"Hotels & Motels",
            "type":"Entertainment"
        }
    ],
    "sg:phone":"+1 865 430 8512",
    "sg:postcode":"37738",
    "sg:province":"TN",
    "sg:tags":[
        "chalet",
        "rental",
        "cabin"
    ],
    "wof:name":"Affordable Discount Rsrvtns",
    "wof:placetype":"venue"
},
  "geometry": {"coordinates":[-83.512552,35.70961],"type":"Point"}
}