{
  "type": "Feature",
  "properties": {
    "iso:country":"US",
    "sg:address":"1005 McLean Ave",
    "sg:city":"Signal Mountain",
    "sg:classifiers":[
        {
            "category":"Organizations",
            "subcategory":"Religious Organization",
            "type":"Services"
        }
    ],
    "sg:phone":"+1 423 886 2437",
    "sg:postcode":"37377",
    "sg:province":"TN",
    "wof:name":"Taft Highway Church of Christ",
    "wof:placetype":"venue"
},
  "geometry": {"coordinates":[-85.317063,35.169573],"type":"Point"}
}