{
  "type": "Feature",
  "properties": {
    "addr:full":"625 Sycamore Dr NE Cleveland TN 37312",
    "addr:housenumber":"625",
    "addr:postcode":"37312",
    "addr:street":"Sycamore Dr Ne",
    "iso:country":"US",
    "sg:address":"625 Sycamore Dr NE",
    "sg:city":"Cleveland",
    "sg:classifiers":[
        {
            "category":"Shopping",
            "subcategory":"Bicycles & Sporting Goods",
            "type":"Retail Goods"
        }
    ],
    "sg:phone":"+1 423 479 8808",
    "sg:postcode":"37312",
    "sg:province":"TN",
    "wof:name":"J Miles Custom Rods",
    "wof:placetype":"venue"
},
  "geometry": {"coordinates":[-84.85358100000001,35.178721],"type":"Point"}
}