{
  "type": "Feature",
  "properties": {
    "addr:full":"3609 Hampton Ave Nashville TN 37215",
    "addr:housenumber":"3609",
    "addr:postcode":"37215",
    "addr:street":"Hampton Ave",
    "iso:country":"US",
    "sg:address":"3609 Hampton Ave",
    "sg:city":"Nashville",
    "sg:classifiers":[
        {
            "category":"Professional",
            "type":"Services"
        }
    ],
    "sg:phone":"+1 615 335 6760",
    "sg:postcode":"37215",
    "sg:province":"TN",
    "sg:tags":[
        "establishment"
    ],
    "wof:name":"Merrick Music",
    "wof:placetype":"venue"
},
  "geometry": {"coordinates":[-86.830456,36.117771],"type":"Point"}
}