{
  "type": "Feature",
  "properties": {
    "iso:country":"US",
    "sg:address":"11113 Crown Point Dr",
    "sg:city":"Knoxville",
    "sg:classifiers":[
        {
            "category":"Shopping",
            "subcategory":"Jewelry",
            "type":"Retail Goods"
        }
    ],
    "sg:phone":"+1 865 675 6604",
    "sg:postcode":"37919",
    "sg:province":"TN",
    "wof:name":"Moonlight Jewelry",
    "wof:placetype":"venue"
},
  "geometry": {"coordinates":[-84.134103,35.885033],"type":"Point"}
}