{
  "type": "Feature",
  "properties": {
    "addr:full":"1011 Alvin Weinberg Dr Oak Ridge TN 37830",
    "addr:housenumber":"1011",
    "addr:postcode":"37830",
    "addr:street":"Alvin Weinberg Dr",
    "iso:country":"US",
    "sg:address":"1011 Alvin Weinberg Dr",
    "sg:city":"Oak Ridge",
    "sg:classifiers":[
        {
            "category":"Manufacturing",
            "subcategory":"Tools & Machinery",
            "type":"Manufacturing & Wholesale Goods"
        }
    ],
    "sg:phone":"+1 865 483 7383",
    "sg:postcode":"37830",
    "sg:province":"TN",
    "sg:tags":[
        "machine",
        "shop"
    ],
    "wof:name":"Neal Tool & Machine",
    "wof:placetype":"venue"
},
  "geometry": {"coordinates":[-84.23413499999999,35.975724],"type":"Point"}
}