{
  "type": "Feature",
  "properties": {
    "addr:full":"5410 Main St Spring Hill TN 37174",
    "addr:housenumber":"5410",
    "addr:postcode":"37174",
    "addr:street":"Main St",
    "iso:country":"US",
    "sg:address":"5410 Main St",
    "sg:city":"Spring Hill",
    "sg:classifiers":[
        {
            "category":"Restaurant",
            "type":"Food & Drink"
        }
    ],
    "sg:menulink":"http://www.allmenus.com/tn/spring-hill/140219-subway/menu/",
    "sg:phone":"+1 931 486 0893",
    "sg:postcode":"37174",
    "sg:province":"TN",
    "sg:tags":[
        "american",
        "sandwich"
    ],
    "wof:name":"Subway",
    "wof:placetype":"venue"
},
  "geometry": {"coordinates":[-86.935221,35.745266],"type":"Point"}
}