{
  "type": "Feature",
  "properties": {
    "iso:country":"US",
    "sg:address":"2820 US Hwy 11 Bus",
    "sg:city":"Athens",
    "sg:classifiers":[
        {
            "category":"Organizations",
            "subcategory":"Religious Organization",
            "type":"Services"
        }
    ],
    "sg:phone":"+1 423 744 7159",
    "sg:postcode":"37303",
    "sg:province":"TN",
    "sg:tags":[
        "church"
    ],
    "wof:name":"Athens United Pentecostal Chr",
    "wof:placetype":"venue"
},
  "geometry": {"coordinates":[-84.644431,35.428001],"type":"Point"}
}