{
  "type": "Feature",
  "properties": {
    "iso:country":"US",
    "sg:address":"4125 Canadaville Loop",
    "sg:city":"Eads",
    "sg:classifiers":[
        {
            "category":"Manufacturing",
            "subcategory":"Building Materials",
            "type":"Manufacturing & Wholesale Goods"
        }
    ],
    "sg:phone":"+1 901 853 0769",
    "sg:postcode":"38028",
    "sg:province":"TN",
    "sg:tags":[
        "mfg",
        "cabinet",
        "wood",
        "carpentry",
        "contractor",
        "kitchen"
    ],
    "wof:name":"Cabinets & Such",
    "wof:placetype":"venue"
},
  "geometry": {"coordinates":[-89.569193,35.169361],"type":"Point"}
}