{
  "type": "Feature",
  "properties": {
    "iso:country":"US",
    "sg:address":"6699 Fletcher Creek Cove",
    "sg:city":"Memphis",
    "sg:classifiers":[
        {
            "category":"Building & Trades",
            "subcategory":"Construction",
            "type":"Services"
        }
    ],
    "sg:phone":"+1 901 372 0545",
    "sg:postcode":"38133",
    "sg:province":"TN",
    "sg:tags":[
        "floor"
    ],
    "wof:name":"Imagine 21 Inc",
    "wof:placetype":"venue"
},
  "geometry": {"coordinates":[-89.839033,35.179579],"type":"Point"}
}