{
  "type": "Feature",
  "properties": {
    "addr:full":"1350 Corinth Rd Darden TN 38328",
    "addr:housenumber":"1350",
    "addr:postcode":"38328",
    "addr:street":"Corinth Rd",
    "iso:country":"US",
    "sg:address":"1350 Corinth Rd",
    "sg:city":"Darden",
    "sg:classifiers":[
        {
            "category":"Organizations",
            "subcategory":"Religious Organization",
            "type":"Services"
        }
    ],
    "sg:phone":"+1 731 845 5220",
    "sg:postcode":"38328",
    "sg:province":"TN",
    "wof:name":"Corinth Baptist Church",
    "wof:placetype":"venue"
},
  "geometry": {"coordinates":[-88.23856600000001,35.657056],"type":"Point"}
}