{
  "type": "Feature",
  "properties": {
    "iso:country":"US",
    "sg:address":"355 Kinchloe Mill Rd",
    "sg:city":"Jonesborough",
    "sg:classifiers":[
        {
            "category":"Restaurant",
            "type":"Food & Drink"
        }
    ],
    "sg:phone":"+1 423 349 4445",
    "sg:postcode":"37659",
    "sg:province":"TN",
    "wof:name":"Tinker's Gas & Diner",
    "wof:placetype":"venue"
},
  "geometry": {"coordinates":[-82.53609299999999,36.415485],"type":"Point"}
}