{
  "type": "Feature",
  "properties": {
    "iso:country":"US",
    "sg:address":"7 Greenbriar Cove",
    "sg:city":"Jackson",
    "sg:classifiers":[
        {
            "category":"Communications",
            "subcategory":"Film & Video Production",
            "type":"Services"
        }
    ],
    "sg:phone":"+1 731 668 8232",
    "sg:postcode":"38305",
    "sg:province":"TN",
    "sg:tags":[
        "taping"
    ],
    "wof:name":"D'Lomar Marketing",
    "wof:placetype":"venue"
},
  "geometry": {"coordinates":[-88.92918,35.684654],"type":"Point"}
}