{
  "type": "Feature",
  "properties": {
    "iso:country":"US",
    "sg:address":"3150 Lenox Park Blvd",
    "sg:city":"Memphis",
    "sg:classifiers":[
        {
            "category":"Wholesale",
            "subcategory":"Non-durable Goods",
            "type":"Manufacturing & Wholesale Goods"
        }
    ],
    "sg:phone":"+1 901 682 3632",
    "sg:postcode":"38115",
    "sg:province":"TN",
    "sg:tags":[
        "product",
        "specialty",
        "promotional"
    ],
    "wof:name":"Zebra Marketing Corporation",
    "wof:placetype":"venue"
},
  "geometry": {"coordinates":[-89.841854,35.062604],"type":"Point"}
}