{
  "type": "Feature",
  "properties": {
    "addr:full":"10201 Galen Rd Lafayette TN 37083",
    "addr:housenumber":"10201",
    "addr:postcode":"37083",
    "addr:street":"Galen Rd",
    "iso:country":"US",
    "sg:address":"10201 Galen Rd",
    "sg:city":"Lafayette",
    "sg:classifiers":[
        {
            "category":"Restaurant",
            "type":"Food & Drink"
        }
    ],
    "sg:phone":"+1 615 666 3331",
    "sg:postcode":"37083",
    "sg:province":"TN",
    "sg:tags":[
        "barbecue"
    ],
    "wof:name":"Crossroads Bar BQ",
    "wof:placetype":"venue"
},
  "geometry": {"coordinates":[-85.90810500000001,36.595268],"type":"Point"}
}