{
  "type": "Feature",
  "properties": {
    "addr:full":"564 Aspen Rd Newport TN 37821",
    "addr:housenumber":"564",
    "addr:postcode":"37821",
    "addr:street":"Aspen Rd",
    "iso:country":"US",
    "sg:address":"564 Aspen Rd",
    "sg:city":"Newport",
    "sg:classifiers":[
        {
            "category":"Building & Trades",
            "subcategory":"Plumbing",
            "type":"Services"
        }
    ],
    "sg:phone":"+1 423 623 8383",
    "sg:postcode":"37821",
    "sg:province":"TN",
    "sg:tags":[
        "contractor"
    ],
    "wof:name":"Rj Vassar & Sons",
    "wof:placetype":"venue"
},
  "geometry": {"coordinates":[-83.17092599999999,35.941759],"type":"Point"}
}