{
  "type": "Feature",
  "properties": {
    "addr:full":"529 West Ave Crossville TN 38555",
    "addr:housenumber":"529",
    "addr:postcode":"38555",
    "addr:street":"West Ave",
    "iso:country":"US",
    "sg:address":"529 West Ave",
    "sg:city":"Crossville",
    "sg:classifiers":[
        {
            "category":"Personal",
            "subcategory":"Beauty Salon",
            "type":"Services"
        }
    ],
    "sg:phone":"+1 931 484 6620",
    "sg:postcode":"38555",
    "sg:province":"TN",
    "wof:name":"Just Cuttin Up",
    "wof:placetype":"venue"
},
  "geometry": {"coordinates":[-85.031384,35.950448],"type":"Point"}
}