{
  "type": "Feature",
  "properties": {
    "iso:country":"US",
    "sg:address":"36 Sandstone Cir",
    "sg:city":"Jackson",
    "sg:classifiers":[
        {
            "category":"Social Services",
            "type":"Services"
        }
    ],
    "sg:phone":"+1 731 512 0387",
    "sg:postcode":"38305",
    "sg:province":"TN",
    "wof:name":"Richard Spring",
    "wof:placetype":"venue"
},
  "geometry": {"coordinates":[-88.853306,35.676324],"type":"Point"}
}