{
  "type": "Feature",
  "properties": {
    "iso:country":"US",
    "sg:address":"411 Independence Ct",
    "sg:city":"Franklin",
    "sg:classifiers":[
        {
            "category":"Insurance",
            "subcategory":"Insurance Agent",
            "type":"Services"
        }
    ],
    "sg:phone":"+1 615 794 5551",
    "sg:postcode":"37086",
    "sg:province":"TN",
    "wof:name":"Robert Scales",
    "wof:placetype":"venue"
},
  "geometry": {"coordinates":[-86.56996599999999,36.029857],"type":"Point"}
}