{
  "type": "Feature",
  "properties": {
    "iso:country":"US",
    "sg:address":"203 S 1st St",
    "sg:city":"Pulaski",
    "sg:classifiers":[
        {
            "category":"Government",
            "subcategory":"Office",
            "type":"Public Place"
        }
    ],
    "sg:phone":"+1 931 363 2147",
    "sg:postcode":"38478",
    "sg:province":"TN",
    "sg:tags":[
        "village"
    ],
    "wof:name":"Pulaski Building Inspector",
    "wof:placetype":"venue"
},
  "geometry": {"coordinates":[-87.031432,35.197874],"type":"Point"}
}