{
  "type": "Feature",
  "properties": {
    "iso:country":"US",
    "sg:address":"7 Perry Cir",
    "sg:city":"Johnson City",
    "sg:classifiers":[
        {
            "category":"Building & Trades",
            "subcategory":"Construction",
            "type":"Services"
        }
    ],
    "sg:phone":"+1 423 434 2889",
    "sg:postcode":"37604",
    "sg:province":"TN",
    "sg:tags":[
        "home",
        "builder"
    ],
    "wof:name":"Home Place Enhancement",
    "wof:placetype":"venue"
},
  "geometry": {"coordinates":[-82.37269499999999,36.291396],"type":"Point"}
}