{
  "type": "Feature",
  "properties": {
    "iso:country":"US",
    "sg:address":"1305 Woodridge Dr",
    "sg:city":"Knoxville",
    "sg:classifiers":[
        {
            "category":"Shopping",
            "subcategory":"Hobbies, Toys, & Games",
            "type":"Retail Goods"
        }
    ],
    "sg:phone":"+1 865 560 5621",
    "sg:postcode":"37919",
    "sg:province":"TN",
    "wof:name":"Heathers Hobbies",
    "wof:placetype":"venue"
},
  "geometry": {"coordinates":[-84.026782,35.901275],"type":"Point"}
}