{
  "type": "Feature",
  "properties": {
    "addr:full":"7837 Timber Glow Trl Knoxville TN 37938",
    "addr:housenumber":"7837",
    "addr:postcode":"37938",
    "addr:street":"Timber Glow Trl",
    "iso:country":"US",
    "sg:address":"7837 Timber Glow Trl",
    "sg:city":"Knoxville",
    "sg:classifiers":[
        {
            "category":"Professional",
            "subcategory":"Management & Consulting",
            "type":"Services"
        }
    ],
    "sg:phone":"+1 865 922 3380",
    "sg:postcode":"37938",
    "sg:province":"TN",
    "sg:tags":[
        "counselor",
        "public",
        "relations"
    ],
    "wof:name":"Hanley-Wilson & Associates",
    "wof:placetype":"venue"
},
  "geometry": {"coordinates":[-83.968817,36.087053],"type":"Point"}
}