{
  "type": "Feature",
  "properties": {
    "iso:country":"US",
    "sg:address":"9706 E Brainerd Rd",
    "sg:city":"Ooltewah",
    "sg:classifiers":[
        {
            "category":"Autos & Motor Vehicles",
            "subcategory":"Automobile Sales",
            "type":"Retail Goods"
        }
    ],
    "sg:phone":"+1 423 553 1889",
    "sg:postcode":"37363",
    "sg:province":"TN",
    "sg:tags":[
        "used"
    ],
    "wof:name":"Philco Auto Sales",
    "wof:placetype":"venue"
},
  "geometry": {"coordinates":[-85.089878,34.998088],"type":"Point"}
}