{
  "type": "Feature",
  "properties": {
    "addr:full":"7826 Cove Ridge Dr Hixson TN 37343",
    "addr:housenumber":"7826",
    "addr:postcode":"37343",
    "addr:street":"Cove Ridge Dr",
    "iso:country":"US",
    "sg:address":"7826 Cove Ridge Dr",
    "sg:city":"Hixson",
    "sg:classifiers":[
        {
            "category":"Autos & Motor Vehicles",
            "subcategory":"Automobile Sales",
            "type":"Retail Goods"
        }
    ],
    "sg:phone":"+1 423 870 7000",
    "sg:postcode":"37343",
    "sg:province":"TN",
    "sg:tags":[
        "car",
        "dealer"
    ],
    "wof:name":"Consumer First Automotive Ctr",
    "wof:placetype":"venue"
},
  "geometry": {"coordinates":[-85.150256,35.173285],"type":"Point"}
}