{
  "type": "Feature",
  "properties": {
    "addr:full":"949 Grover Reece Rd Trade TN 37691",
    "addr:housenumber":"949",
    "addr:postcode":"37691",
    "addr:street":"Grover Reece Rd",
    "iso:country":"US",
    "sg:address":"949 Grover Reece Rd",
    "sg:city":"Trade",
    "sg:classifiers":[
        {
            "category":"Building & Trades",
            "subcategory":"Construction",
            "type":"Services"
        }
    ],
    "sg:phone":"+1 423 727 5246",
    "sg:postcode":"37691",
    "sg:province":"TN",
    "sg:tags":[
        "house",
        "real estate"
    ],
    "wof:name":"Ivywood Construction",
    "wof:placetype":"venue"
},
  "geometry": {"coordinates":[-81.771665,36.377019],"type":"Point"}
}