{
  "type": "Feature",
  "properties": {
    "addr:full":"9718 Laverne Ln Knoxville TN 37922",
    "addr:housenumber":"9718",
    "addr:postcode":"37922",
    "addr:street":"Laverne Ln",
    "iso:country":"US",
    "sg:address":"9718 Laverne Ln",
    "sg:city":"Knoxville",
    "sg:classifiers":[
        {
            "category":"Shopping",
            "subcategory":"Computers & Home Electronics",
            "type":"Retail Goods"
        }
    ],
    "sg:phone":"+1 865 693 6600",
    "sg:postcode":"37922",
    "sg:province":"TN",
    "sg:tags":[
        "equipment",
        "electronic",
        "supply"
    ],
    "wof:name":"Zenith Electronics",
    "wof:placetype":"venue"
},
  "geometry": {"coordinates":[-84.08819699999999,35.865972],"type":"Point"}
}