{
  "type": "Feature",
  "properties": {
    "iso:country":"US",
    "sg:address":"2579 Hwy 45",
    "sg:city":"Humboldt",
    "sg:classifiers":[
        {
            "category":"Restaurant",
            "type":"Food & Drink"
        }
    ],
    "sg:phone":"+1 731 784 7688",
    "sg:postcode":"38343",
    "sg:province":"TN",
    "wof:name":"Mc Donald's",
    "wof:placetype":"venue"
},
  "geometry": {"coordinates":[-88.915178,35.837353],"type":"Point"}
}