{
  "type": "Feature",
  "properties": {
    "iso:country":"US",
    "sg:address":"806 Mulberry St",
    "sg:city":"Loudon",
    "sg:classifiers":[
        {
            "category":"Insurance",
            "subcategory":"Insurance Agent",
            "type":"Services"
        }
    ],
    "sg:phone":"+1 865 458 5433",
    "sg:postcode":"37774",
    "sg:province":"TN",
    "wof:name":"Financial Dynamics-East Tenn",
    "wof:placetype":"venue"
},
  "geometry": {"coordinates":[-84.344114,35.736884],"type":"Point"}
}