{
  "type": "Feature",
  "properties": {
    "iso:country":"US",
    "sg:address":"4010 W Andrew Johnson Hwy",
    "sg:city":"Morristown",
    "sg:classifiers":[
        {
            "category":"Home & Garden",
            "subcategory":"Building Materials",
            "type":"Retail Goods"
        }
    ],
    "sg:phone":"+1 423 586 2206",
    "sg:postcode":"37814",
    "sg:province":"TN",
    "sg:tags":[
        "wallpaper"
    ],
    "wof:name":"Quality Products Inc",
    "wof:placetype":"venue"
},
  "geometry": {"coordinates":[-83.35314099999999,36.194897],"type":"Point"}
}