{
  "type": "Feature",
  "properties": {
    "iso:country":"US",
    "sg:address":"4389 Leatherwood Ave",
    "sg:city":"Memphis",
    "sg:classifiers":[
        {
            "category":"Retail",
            "subcategory":"Repair Shop",
            "type":"Services"
        }
    ],
    "sg:phone":"+1 901 682 5797",
    "sg:postcode":"38117",
    "sg:province":"TN",
    "sg:tags":[
        "refrigeration"
    ],
    "wof:name":"Bb Appliance Heating & Air",
    "wof:placetype":"venue"
},
  "geometry": {"coordinates":[-89.914874,35.086693],"type":"Point"}
}