{
  "type": "Feature",
  "properties": {
    "iso:country":"US",
    "sg:address":"6506 W Poplar Ave",
    "sg:city":"Collierville",
    "sg:classifiers":[
        {
            "category":"Restaurant",
            "type":"Food & Drink"
        }
    ],
    "sg:phone":"+1 901 853 7700",
    "sg:postcode":"38017",
    "sg:province":"TN",
    "sg:website":"www.mcdonalds.com",
    "wof:name":"Mc Donald's",
    "wof:placetype":"venue"
},
  "geometry": {"coordinates":[-89.71718300000001,35.047903],"type":"Point"}
}