{
  "type": "Feature",
  "properties": {
    "iso:country":"US",
    "sg:address":"4159 Summer Ave",
    "sg:city":"Memphis",
    "sg:classifiers":[
        {
            "category":"Restaurant",
            "type":"Food & Drink"
        }
    ],
    "sg:phone":"+1 901 323 7003",
    "sg:postcode":"38122",
    "sg:province":"TN",
    "sg:tags":[
        "mexican"
    ],
    "wof:name":"Taqueria Garibaldi",
    "wof:placetype":"venue"
},
  "geometry": {"coordinates":[-89.922209,35.149007],"type":"Point"}
}