{
  "type": "Feature",
  "properties": {
    "addr:full":"357 S Charles G Seivers Blvd Clinton TN 37716",
    "addr:housenumber":"357",
    "addr:postcode":"37716",
    "addr:street":"S Charles G Seivers Blvd",
    "iso:country":"US",
    "sg:address":"357 S Charles G Seivers Blvd",
    "sg:city":"Clinton",
    "sg:classifiers":[
        {
            "category":"Restaurant",
            "type":"Food & Drink"
        }
    ],
    "sg:menulink":"http://www.allmenus.com/tn/clinton/203579-mcdonalds/menu/",
    "sg:phone":"+1 865 457 9500",
    "sg:postcode":"37716",
    "sg:province":"TN",
    "sg:tags":[
        "burger",
        "american"
    ],
    "wof:name":"McDonald's",
    "wof:placetype":"venue"
},
  "geometry": {"coordinates":[-84.136613,36.094324],"type":"Point"}
}