{
  "type": "Feature",
  "properties": {
    "iso:country":"US",
    "sg:address":"5179 Pryor Ln",
    "sg:city":"Westmoreland",
    "sg:classifiers":[
        {
            "category":"Building & Trades",
            "subcategory":"Construction",
            "type":"Services"
        }
    ],
    "sg:phone":"+1 615 666 7578",
    "sg:postcode":"37186",
    "sg:province":"TN",
    "sg:tags":[
        "roofing",
        "contractor"
    ],
    "wof:name":"Black Seal Roofing",
    "wof:placetype":"venue"
},
  "geometry": {"coordinates":[-86.13130099999999,36.594892],"type":"Point"}
}