{
  "type": "Feature",
  "properties": {
    "iso:country":"US",
    "sg:address":"104 Broadrick St",
    "sg:city":"Tullahoma",
    "sg:classifiers":[
        {
            "category":"Building & Trades",
            "subcategory":"Electrical",
            "type":"Services"
        }
    ],
    "sg:phone":"+1 931 455 4612",
    "sg:postcode":"37388",
    "sg:province":"TN",
    "sg:tags":[
        "electric",
        "contractor"
    ],
    "wof:name":"Cranford's Electric Svc",
    "wof:placetype":"venue"
},
  "geometry": {"coordinates":[-86.191244,35.373758],"type":"Point"}
}