{
  "type": "Feature",
  "properties": {
    "iso:country":"US",
    "sg:address":"659 Thompson Ln",
    "sg:city":"Nashville",
    "sg:classifiers":[
        {
            "category":"Building & Trades",
            "subcategory":"Plumbing",
            "type":"Services"
        }
    ],
    "sg:phone":"+1 615 256 8131",
    "sg:postcode":"37211",
    "sg:province":"TN",
    "sg:tags":[
        "electrical",
        "contractor",
        "sheet",
        "mfg"
    ],
    "wof:name":"Comfort Control Inc",
    "wof:placetype":"venue"
},
  "geometry": {"coordinates":[-86.75692600000001,36.11135],"type":"Point"}
}