{
  "type": "Feature",
  "properties": {
    "iso:country":"US",
    "sg:address":"108 Cat Bird Ave",
    "sg:city":"Parrottsville",
    "sg:classifiers":[
        {
            "category":"Building & Trades",
            "subcategory":"Construction",
            "type":"Services"
        }
    ],
    "sg:phone":"+1 423 623 2159",
    "sg:postcode":"37843",
    "sg:province":"TN",
    "sg:tags":[
        "house"
    ],
    "wof:name":"AAA Quality Builders",
    "wof:placetype":"venue"
},
  "geometry": {"coordinates":[-83.09241400000001,36.009491],"type":"Point"}
}