{
  "type": "Feature",
  "properties": {
    "iso:country":"US",
    "sg:address":"3656 Lamar Ave",
    "sg:city":"Memphis",
    "sg:classifiers":[
        {
            "category":"Retail",
            "subcategory":"Auto Repair",
            "type":"Services"
        }
    ],
    "sg:phone":"+1 901 281 0126",
    "sg:postcode":"38118",
    "sg:province":"TN",
    "sg:tags":[
        "body",
        "painting",
        "repairing",
        "automobile"
    ],
    "wof:name":"Slick Auto Body Repair",
    "wof:placetype":"venue"
},
  "geometry": {"coordinates":[-89.893967,35.015251],"type":"Point"}
}