{
  "type": "Feature",
  "properties": {
    "addr:full":"320 Quinco Dr Henderson TN 38340",
    "addr:housenumber":"320",
    "addr:postcode":"38340",
    "addr:street":"Quinco Dr",
    "iso:country":"US",
    "sg:address":"320 Quinco Dr",
    "sg:city":"Henderson",
    "sg:classifiers":[
        {
            "category":"Local Transit",
            "type":"Transportation"
        }
    ],
    "sg:phone":"+1 731 989 2127",
    "sg:postcode":"38340",
    "sg:province":"TN",
    "sg:tags":[
        "passenger",
        "ambulance"
    ],
    "wof:name":"Medical Center E M S",
    "wof:placetype":"venue"
},
  "geometry": {"coordinates":[-88.61677,35.446844],"type":"Point"}
}