{
  "type": "Feature",
  "properties": {
    "iso:country":"US",
    "sg:address":"208 Utley Dr",
    "sg:city":"Goodlettsville",
    "sg:classifiers":[
        {
            "category":"Building & Trades",
            "subcategory":"Construction",
            "type":"Services"
        }
    ],
    "sg:phone":"+1 615 519 1218",
    "sg:postcode":"37072",
    "sg:province":"TN",
    "sg:tags":[
        "general",
        "contractor"
    ],
    "wof:name":"JOM Construction",
    "wof:placetype":"venue"
},
  "geometry": {"coordinates":[-86.726259,36.338364],"type":"Point"}
}