{
  "type": "Feature",
  "properties": {
    "iso:country":"US",
    "sg:address":"607 Franklin Limestone Rd",
    "sg:city":"Nashville",
    "sg:classifiers":[
        {
            "category":"Freight",
            "type":"Transportation"
        }
    ],
    "sg:phone":"+1 615 361 0804",
    "sg:postcode":"37217",
    "sg:province":"TN",
    "sg:tags":[
        "operator",
        "local",
        "trucking"
    ],
    "wof:name":"Little Trucking Company",
    "wof:placetype":"venue"
},
  "geometry": {"coordinates":[-86.661186,36.089997],"type":"Point"}
}