{
  "type": "Feature",
  "properties": {
    "iso:country":"US",
    "sg:address":"110 N Campbell Station Rd",
    "sg:city":"Knoxville",
    "sg:classifiers":[
        {
            "category":"Health Services",
            "subcategory":"Doctor",
            "type":"Services"
        }
    ],
    "sg:phone":"+1 865 690 2992",
    "sg:postcode":"37934",
    "sg:province":"TN",
    "sg:tags":[
        "physician",
        "surgeon"
    ],
    "wof:name":"Campbell Station Internal Med",
    "wof:placetype":"venue"
},
  "geometry": {"coordinates":[-84.16051299999999,35.881508],"type":"Point"}
}