{
  "type": "Feature",
  "properties": {
    "addr:full":"627 Gallatin Ave Nashville TN 37206",
    "addr:housenumber":"627",
    "addr:postcode":"37206",
    "addr:street":"Gallatin Ave",
    "iso:country":"US",
    "sg:address":"627 Gallatin Ave",
    "sg:city":"Nashville",
    "sg:classifiers":[
        {
            "category":"Shopping",
            "subcategory":"Pharmacy",
            "type":"Retail Goods"
        }
    ],
    "sg:phone":"+1 615 868 6305",
    "sg:postcode":"37206",
    "sg:province":"TN",
    "wof:name":"Walgreens",
    "wof:placetype":"venue"
},
  "geometry": {"coordinates":[-86.748536,36.183226],"type":"Point"}
}