{
  "type": "Feature",
  "properties": {
    "iso:country":"US",
    "sg:address":"7755 Winchester Rd",
    "sg:city":"Memphis",
    "sg:classifiers":[
        {
            "category":"Restaurant",
            "type":"Food & Drink"
        }
    ],
    "sg:menulink":"http://www.allmenus.com/tn/memphis/31405-logans-roadhouse/menu/",
    "sg:phone":"+1 901 759 1430",
    "sg:postcode":"38125",
    "sg:province":"TN",
    "sg:tags":[
        "american"
    ],
    "wof:name":"Logan's Roadhouse",
    "wof:placetype":"venue"
},
  "geometry": {"coordinates":[-89.805319,35.049409],"type":"Point"}
}