{
  "type": "Feature",
  "properties": {
    "addr:full":"5909 Shelby Oaks Dr Memphis TN 38134",
    "addr:housenumber":"5909",
    "addr:postcode":"38134",
    "addr:street":"Shelby Oaks Dr",
    "iso:country":"US",
    "sg:address":"5909 Shelby Oaks Dr",
    "sg:city":"Memphis",
    "sg:classifiers":[
        {
            "category":"Government",
            "subcategory":"Office",
            "type":"Public Place"
        }
    ],
    "sg:phone":"+1 901 388 2208",
    "sg:postcode":"38134",
    "sg:province":"TN",
    "sg:tags":[
        "armed",
        "force",
        "recruiting"
    ],
    "wof:name":"US Army Recruiting",
    "wof:placetype":"venue"
},
  "geometry": {"coordinates":[-89.866238,35.166052],"type":"Point"}
}