{
  "type": "Feature",
  "properties": {
    "iso:country":"US",
    "sg:address":"8772 Cherry Spring Dr",
    "sg:city":"Cordova",
    "sg:classifiers":[
        {
            "category":"Professional",
            "type":"Services"
        }
    ],
    "sg:phone":"+1 901 377 7890",
    "sg:postcode":"38016",
    "sg:province":"TN",
    "wof:name":"Cordaire Inc",
    "wof:placetype":"venue"
},
  "geometry": {"coordinates":[-89.76923600000001,35.19034],"type":"Point"}
}