{
  "type": "Feature",
  "properties": {
    "iso:country":"US",
    "sg:address":"1777 Old Gray Station Rd",
    "sg:city":"Gray",
    "sg:classifiers":[
        {
            "category":"Professional",
            "subcategory":"Management & Consulting",
            "type":"Services"
        }
    ],
    "sg:phone":"+1 423 610 0013",
    "sg:postcode":"37615",
    "sg:province":"TN",
    "sg:tags":[
        "communications",
        "consultant"
    ],
    "wof:name":"T C Enterprises",
    "wof:placetype":"venue"
},
  "geometry": {"coordinates":[-82.40952799999999,36.382479],"type":"Point"}
}