{
  "type": "Feature",
  "properties": {
    "addr:full":"3599 Eagle Trce Memphis TN 38125",
    "addr:housenumber":"3599",
    "addr:postcode":"38125",
    "addr:street":"Eagle Trce",
    "iso:country":"US",
    "sg:address":"3599 Eagle Trce",
    "sg:city":"Memphis",
    "sg:classifiers":[
        {
            "category":"Food & Beverages",
            "subcategory":"Groceries & Convenience Stores",
            "type":"Retail Goods"
        }
    ],
    "sg:phone":"+1 901 757 0473",
    "sg:postcode":"38125",
    "sg:province":"TN",
    "wof:name":"Corner Food Store 2",
    "wof:placetype":"venue"
},
  "geometry": {"coordinates":[-89.785613,35.0513],"type":"Point"}
}