{
  "type": "Feature",
  "properties": {
    "iso:country":"US",
    "sg:address":"2503 Cruzen St",
    "sg:city":"Nashville",
    "sg:classifiers":[
        {
            "category":"Retail",
            "subcategory":"Auto Repair",
            "type":"Services"
        }
    ],
    "sg:phone":"+1 615 255 3685",
    "sg:postcode":"37211",
    "sg:province":"TN",
    "sg:tags":[
        "repairing",
        "automobile"
    ],
    "sg:website":"www.karplusinc.com",
    "wof:name":"KAR Plus Inc",
    "wof:placetype":"venue"
},
  "geometry": {"coordinates":[-86.751707,36.115684],"type":"Point"}
}