{
  "type": "Feature",
  "properties": {
    "iso:country":"US",
    "sg:address":"3716 Rockwood Ave",
    "sg:city":"Memphis",
    "sg:classifiers":[
        {
            "category":"Building & Trades",
            "subcategory":"Construction",
            "type":"Services"
        }
    ],
    "sg:phone":"+1 901 323 9599",
    "sg:postcode":"38122",
    "sg:province":"TN",
    "sg:tags":[
        "contractor"
    ],
    "wof:name":"Carefree Siding",
    "wof:placetype":"venue"
},
  "geometry": {"coordinates":[-89.933936,35.164073],"type":"Point"}
}