{
  "type": "Feature",
  "properties": {
    "addr:full":"3124 Richmond Hill Dr Nashville TN 37207",
    "addr:housenumber":"3124",
    "addr:postcode":"37207",
    "addr:street":"Richmond Hill Dr",
    "iso:country":"US",
    "sg:address":"3124 Richmond Hill Dr",
    "sg:city":"Nashville",
    "sg:classifiers":[
        {
            "category":"Retail",
            "subcategory":"Car Wash",
            "type":"Services"
        }
    ],
    "sg:phone":"+1 615 668 9369",
    "sg:postcode":"37207",
    "sg:province":"TN",
    "sg:tags":[
        "automobile",
        "detail",
        "clean"
    ],
    "wof:name":"Wilson's Car Beautification",
    "wof:placetype":"venue"
},
  "geometry": {"coordinates":[-86.778447,36.235517],"type":"Point"}
}