{
  "type": "Feature",
  "properties": {
    "addr:full":"804 Scott St Dyersburg TN 38024",
    "addr:housenumber":"804",
    "addr:postcode":"38024",
    "addr:street":"Scott St",
    "iso:country":"US",
    "sg:address":"804 Scott St",
    "sg:city":"Dyersburg",
    "sg:classifiers":[
        {
            "category":"Professional",
            "subcategory":"Business Services",
            "type":"Services"
        }
    ],
    "sg:phone":"+1 731 285 3816",
    "sg:postcode":"38024",
    "sg:province":"TN",
    "wof:name":"B P P Courier Service",
    "wof:placetype":"venue"
},
  "geometry": {"coordinates":[-89.397245,36.033149],"type":"Point"}
}