{
  "type": "Feature",
  "properties": {
    "iso:country":"US",
    "sg:address":"2714 John Deere Dr",
    "sg:city":"Knoxville",
    "sg:classifiers":[
        {
            "category":"Wholesale",
            "subcategory":"Machinery & Supplies",
            "type":"Manufacturing & Wholesale Goods"
        }
    ],
    "sg:phone":"+1 865 524 9874",
    "sg:postcode":"37917",
    "sg:province":"TN",
    "sg:tags":[
        "pipe",
        "fitting"
    ],
    "wof:name":"Hajoca Corp",
    "wof:placetype":"venue"
},
  "geometry": {"coordinates":[-83.895822,35.996969],"type":"Point"}
}