{
  "type": "Feature",
  "properties": {
    "iso:country":"US",
    "sg:address":"1555 Bear Creek Pike",
    "sg:city":"Columbia",
    "sg:classifiers":[
        {
            "category":"Restaurant",
            "type":"Food & Drink"
        }
    ],
    "sg:phone":"+1 931 381 2234",
    "sg:postcode":"38401",
    "sg:province":"TN",
    "sg:tags":[
        "eating",
        "merchandise",
        "general"
    ],
    "wof:name":"Stans Restaurant",
    "wof:placetype":"venue"
},
  "geometry": {"coordinates":[-86.89661599999999,35.643215],"type":"Point"}
}