{
  "type": "Feature",
  "properties": {
    "iso:country":"US",
    "sg:address":"3333 Lebanon Pike",
    "sg:city":"Hermitage",
    "sg:classifiers":[
        {
            "category":"Organizations",
            "subcategory":"Non-profit Organization",
            "type":"Services"
        }
    ],
    "sg:phone":"+1 615 889 6740",
    "sg:postcode":"37214",
    "sg:province":"TN",
    "sg:website":"www.tssaa.org",
    "wof:name":"Tennessee Secondary School",
    "wof:placetype":"venue"
},
  "geometry": {"coordinates":[-86.62985399999999,36.187727],"type":"Point"}
}