{
  "type": "Feature",
  "properties": {
    "addr:full":"2214 Paris Rd Knoxville TN 37912",
    "addr:housenumber":"2214",
    "addr:postcode":"37912",
    "addr:street":"Paris Rd",
    "iso:country":"US",
    "sg:address":"2214 Paris Rd",
    "sg:city":"Knoxville",
    "sg:classifiers":[
        {
            "category":"Building & Trades",
            "subcategory":"Construction",
            "type":"Services"
        }
    ],
    "sg:phone":"+1 865 524 4645",
    "sg:postcode":"37912",
    "sg:province":"TN",
    "sg:tags":[
        "contractor"
    ],
    "wof:name":"Acoustic Ball & Drywall",
    "wof:placetype":"venue"
},
  "geometry": {"coordinates":[-83.982175,35.986626],"type":"Point"}
}