{
  "type": "Feature",
  "properties": {
    "addr:full":"1701 Broad St Chattanooga TN 37402",
    "addr:housenumber":"1701",
    "addr:postcode":"37402",
    "addr:street":"Broad St",
    "iso:country":"US",
    "sg:address":"1701 Broad St",
    "sg:city":"Chattanooga",
    "sg:classifiers":[
        {
            "category":"Freight",
            "type":"Transportation"
        }
    ],
    "sg:phone":"+1 423 267 1234",
    "sg:postcode":"37402",
    "sg:province":"TN",
    "sg:tags":[
        "commercial",
        "storage"
    ],
    "wof:name":"Southside Storage",
    "wof:placetype":"venue"
},
  "geometry": {"coordinates":[-85.312614,35.035084],"type":"Point"}
}