{
  "type": "Feature",
  "properties": {
    "iso:country":"US",
    "sg:address":"1606 Galloway Ave",
    "sg:city":"Memphis",
    "sg:classifiers":[
        {
            "category":"Professional",
            "subcategory":"Management & Consulting",
            "type":"Services"
        }
    ],
    "sg:phone":"+1 901 272 0228",
    "sg:postcode":"38112",
    "sg:province":"TN",
    "sg:tags":[
        "business"
    ],
    "wof:name":"Buddy Fey Engineering",
    "wof:placetype":"venue"
},
  "geometry": {"coordinates":[-90.00615500000001,35.151158],"type":"Point"}
}