{
  "type": "Feature",
  "properties": {
    "iso:country":"US",
    "sg:address":"777 Old Hwy 68",
    "sg:city":"Sweetwater",
    "sg:classifiers":[
        {
            "category":"Professional",
            "subcategory":"Employment Agencies",
            "type":"Services"
        }
    ],
    "sg:phone":"+1 423 337 3370",
    "sg:postcode":"37874",
    "sg:province":"TN",
    "sg:tags":[
        "temporary"
    ],
    "wof:name":"Randstad North America LP",
    "wof:placetype":"venue"
},
  "geometry": {"coordinates":[-84.46016400000001,35.593388],"type":"Point"}
}