{
  "type": "Feature",
  "properties": {
    "addr:full":"435 Howell Rd Martin TN 38237",
    "addr:housenumber":"435",
    "addr:postcode":"38237",
    "addr:street":"Howell Rd",
    "iso:country":"US",
    "sg:address":"435 Howell Rd",
    "sg:city":"Martin",
    "sg:classifiers":[
        {
            "category":"Freight",
            "type":"Transportation"
        }
    ],
    "sg:phone":"+1 731 587 1923",
    "sg:postcode":"38237",
    "sg:province":"TN",
    "sg:tags":[
        "over",
        "local",
        "hauling",
        "road"
    ],
    "wof:name":"Sets LLC",
    "wof:placetype":"venue"
},
  "geometry": {"coordinates":[-88.89131999999999,36.366644],"type":"Point"}
}