{
  "type": "Feature",
  "properties": {
    "addr:full":"760 E Northfield Blvd Murfreesboro TN 37130",
    "addr:housenumber":"760",
    "addr:postcode":"37130",
    "addr:street":"E Northfield Blvd",
    "iso:country":"US",
    "sg:address":"760 E Northfield Blvd",
    "sg:city":"Murfreesboro",
    "sg:classifiers":[
        {
            "category":"Food & Beverages",
            "subcategory":"Groceries & Convenience Stores",
            "type":"Retail Goods"
        }
    ],
    "sg:phone":"+1 615 896 9988",
    "sg:postcode":"37130",
    "sg:province":"TN",
    "wof:name":"Quick Stop Food Mart",
    "wof:placetype":"venue"
},
  "geometry": {"coordinates":[-86.374481,35.868515],"type":"Point"}
}