{
  "type": "Feature",
  "properties": {
    "iso:country":"US",
    "sg:address":"15 Century Blvd",
    "sg:city":"Nashville",
    "sg:classifiers":[
        {
            "category":"Communications",
            "subcategory":"Radio Station",
            "type":"Services"
        }
    ],
    "sg:phone":"+1 615 871 1160",
    "sg:postcode":"37214",
    "sg:province":"TN",
    "sg:tags":[
        "company",
        "broadcasting"
    ],
    "wof:name":"W Crt AM Radio 1160",
    "wof:placetype":"venue"
},
  "geometry": {"coordinates":[-86.68598299999999,36.146354],"type":"Point"}
}