{
  "type": "Feature",
  "properties": {
    "iso:country":"US",
    "sg:address":"2419 Washington Pike",
    "sg:city":"Knoxville",
    "sg:classifiers":[
        {
            "category":"Shopping",
            "subcategory":"Pharmacy",
            "type":"Retail Goods"
        }
    ],
    "sg:phone":"+1 865 524 3453",
    "sg:postcode":"37917",
    "sg:province":"TN",
    "wof:name":"Mac's Pharmacy",
    "wof:placetype":"venue"
},
  "geometry": {"coordinates":[-83.91096899999999,36.002951],"type":"Point"}
}