{
  "type": "Feature",
  "properties": {
    "iso:country":"US",
    "sg:address":"1011 N Idlewild St",
    "sg:city":"Memphis",
    "sg:classifiers":[
        {
            "category":"Shopping",
            "subcategory":"Computers & Home Electronics",
            "type":"Retail Goods"
        }
    ],
    "sg:phone":"+1 901 278 5494",
    "sg:postcode":"38107",
    "sg:province":"TN",
    "wof:name":"Wright 1 Computer Services",
    "wof:placetype":"venue"
},
  "geometry": {"coordinates":[-89.99745,35.164824],"type":"Point"}
}