{
  "type": "Feature",
  "properties": {
    "addr:full":"600 N 4th St Memphis TN 38107",
    "addr:housenumber":"600",
    "addr:postcode":"38107",
    "addr:street":"N 4Th St",
    "iso:country":"US",
    "sg:address":"600 N 4th St",
    "sg:city":"Memphis",
    "sg:classifiers":[
        {
            "category":"Place Of Worship",
            "type":"Public Place"
        }
    ],
    "sg:phone":"+1 901 525 2017",
    "sg:postcode":"38107",
    "sg:province":"TN",
    "sg:tags":[
        "church"
    ],
    "wof:name":"St James A M E Church",
    "wof:placetype":"venue"
},
  "geometry": {"coordinates":[-90.04266699999999,35.160015],"type":"Point"}
}