{
  "type": "Feature",
  "properties": {
    "iso:country":"US",
    "sg:address":"2803 Foster Ave",
    "sg:city":"Nashville",
    "sg:classifiers":[
        {
            "category":"Social Services",
            "type":"Services"
        }
    ],
    "sg:phone":"+1 615 837 8100",
    "sg:postcode":"37210",
    "sg:province":"TN",
    "sg:tags":[
        "professional",
        "counselor"
    ],
    "wof:name":"Gabester Counseling Svc",
    "wof:placetype":"venue"
},
  "geometry": {"coordinates":[-86.74343399999999,36.114023],"type":"Point"}
}