{
  "type": "Feature",
  "properties": {
    "addr:full":"243 Burem Rd Rogersville TN 37857",
    "addr:housenumber":"243",
    "addr:postcode":"37857",
    "addr:street":"Burem Rd",
    "iso:country":"US",
    "sg:address":"243 Burem Rd",
    "sg:city":"Rogersville",
    "sg:classifiers":[
        {
            "category":"Wholesale",
            "subcategory":"Machinery & Supplies",
            "type":"Manufacturing & Wholesale Goods"
        }
    ],
    "sg:phone":"+1 423 272 7400",
    "sg:postcode":"37857",
    "sg:province":"TN",
    "sg:tags":[
        "tractor"
    ],
    "wof:name":"Romoco Inc",
    "wof:placetype":"venue"
},
  "geometry": {"coordinates":[-82.957452,36.418693],"type":"Point"}
}