{
  "type": "Feature",
  "properties": {
    "iso:country":"US",
    "sg:address":"140 Park Dr",
    "sg:city":"Jonesborough",
    "sg:classifiers":[
        {
            "category":"Real Estate",
            "subcategory":"Real Estate Agent",
            "type":"Services"
        }
    ],
    "sg:phone":"+1 423 913 0410",
    "sg:postcode":"37659",
    "sg:province":"TN",
    "wof:name":"Professional Appraisals LLC",
    "wof:placetype":"venue"
},
  "geometry": {"coordinates":[-82.427316,36.295913],"type":"Point"}
}