{
  "type": "Feature",
  "properties": {
    "addr:full":"206 E Main St Jackson TN 38301",
    "addr:housenumber":"206",
    "addr:postcode":"38301",
    "addr:street":"E Main St",
    "iso:country":"US",
    "sg:address":"206 E Main St",
    "sg:city":"Jackson",
    "sg:classifiers":[
        {
            "category":"Professional",
            "subcategory":"Detective & Security Services",
            "type":"Services"
        }
    ],
    "sg:phone":"+1 731 427 1562",
    "sg:postcode":"38301",
    "sg:province":"TN",
    "sg:tags":[
        "car"
    ],
    "wof:name":"AMata Hari Hari Invstigations",
    "wof:placetype":"venue"
},
  "geometry": {"coordinates":[-88.81726999999999,35.614205],"type":"Point"}
}