{
  "type": "Feature",
  "properties": {
    "iso:country":"US",
    "sg:address":"1149 Trotwood Ave",
    "sg:city":"Columbia",
    "sg:classifiers":[
        {
            "category":"Retail",
            "subcategory":"Auto Repair",
            "type":"Services"
        }
    ],
    "sg:phone":"+1 931 490 9700",
    "sg:postcode":"38401",
    "sg:province":"TN",
    "sg:tags":[
        "general"
    ],
    "wof:name":"Central Auto Repair",
    "wof:placetype":"venue"
},
  "geometry": {"coordinates":[-87.057971,35.612066],"type":"Point"}
}