{
  "type": "Feature",
  "properties": {
    "iso:country":"US",
    "sg:address":"1813 Wilson St",
    "sg:city":"Chattanooga",
    "sg:classifiers":[
        {
            "category":"Organizations",
            "subcategory":"Religious Organization",
            "type":"Services"
        }
    ],
    "sg:phone":"+1 423 698 7578",
    "sg:postcode":"37406",
    "sg:province":"TN",
    "sg:tags":[
        "church"
    ],
    "wof:name":"Wesley Chapel Christian Commun",
    "wof:placetype":"venue"
},
  "geometry": {"coordinates":[-85.267563,35.053154],"type":"Point"}
}