{
  "type": "Feature",
  "properties": {
    "iso:country":"US",
    "sg:address":"130 Hightop Rd",
    "sg:city":"Midway",
    "sg:phone":"+1 423 422 6971",
    "sg:postcode":"37809",
    "sg:province":"TN",
    "sg:tags":[
        "farm",
        "tobacco"
    ],
    "wof:name":"James I Brobeck",
    "wof:placetype":"venue"
},
  "geometry": {"coordinates":[-82.98881299999999,36.174691],"type":"Point"}
}