{
  "type": "Feature",
  "properties": {
    "addr:full":"301 W College St Kenton TN 38233",
    "addr:housenumber":"301",
    "addr:postcode":"38233",
    "addr:street":"W College St",
    "iso:country":"US",
    "sg:address":"301 W College St",
    "sg:city":"Kenton",
    "sg:classifiers":[
        {
            "category":"Organizations",
            "subcategory":"Religious Organization",
            "type":"Services"
        }
    ],
    "sg:phone":"+1 731 749 5600",
    "sg:postcode":"38233",
    "sg:province":"TN",
    "wof:name":"Cumberland Presbyterian Church",
    "wof:placetype":"venue"
},
  "geometry": {"coordinates":[-89.012844,36.202615],"type":"Point"}
}