{
  "type": "Feature",
  "properties": {
    "addr:full":"2648 Volunteer Pkwy Bristol TN 37620",
    "addr:housenumber":"2648",
    "addr:postcode":"37620",
    "addr:street":"Volunteer Pkwy",
    "iso:country":"US",
    "sg:address":"2648 Volunteer Pkwy",
    "sg:city":"Bristol",
    "sg:classifiers":[
        {
            "category":"Food & Beverages",
            "subcategory":"Groceries & Convenience Stores",
            "type":"Retail Goods"
        }
    ],
    "sg:phone":"+1 423 878 6000",
    "sg:postcode":"37620",
    "sg:province":"TN",
    "wof:name":"Speedway Market",
    "wof:placetype":"venue"
},
  "geometry": {"coordinates":[-82.257645,36.523708],"type":"Point"}
}