{
  "type": "Feature",
  "properties": {
    "iso:country":"US",
    "sg:address":"5895 Waterlevel Hwy",
    "sg:city":"Cleveland",
    "sg:classifiers":[
        {
            "category":"Manufacturing",
            "subcategory":"Tools & Machinery",
            "type":"Manufacturing & Wholesale Goods"
        }
    ],
    "sg:phone":"+1 423 476 5101",
    "sg:postcode":"37323",
    "sg:province":"TN",
    "sg:tags":[
        "industrial",
        "mfg"
    ],
    "wof:name":"Dwight Orrs Shop",
    "wof:placetype":"venue"
},
  "geometry": {"coordinates":[-84.767488,35.135007],"type":"Point"}
}