{
  "type": "Feature",
  "properties": {
    "addr:full":"5073 Columbia Pike Spring Hill TN 37174",
    "addr:housenumber":"5073",
    "addr:postcode":"37174",
    "addr:street":"Columbia Pike",
    "iso:country":"US",
    "sg:address":"5073 Columbia Pike",
    "sg:city":"Spring Hill",
    "sg:classifiers":[
        {
            "category":"Health Services",
            "subcategory":"Doctor",
            "type":"Services"
        }
    ],
    "sg:phone":"+1 615 302 4200",
    "sg:postcode":"37174",
    "sg:province":"TN",
    "sg:tags":[
        "dentist"
    ],
    "wof:name":"Snodgrass & King Dental Assn",
    "wof:placetype":"venue"
},
  "geometry": {"coordinates":[-86.882081,35.837569],"type":"Point"}
}