{
  "type": "Feature",
  "properties": {
    "iso:country":"US",
    "sg:address":"1416 Lehr Dr",
    "sg:city":"Memphis",
    "sg:classifiers":[
        {
            "category":"Restaurant",
            "type":"Food & Drink"
        }
    ],
    "sg:phone":"+1 901 398 5591",
    "sg:postcode":"38116",
    "sg:province":"TN",
    "sg:tags":[
        "eating"
    ],
    "wof:name":"Why Not Catering",
    "wof:placetype":"venue"
},
  "geometry": {"coordinates":[-90.016053,35.04667],"type":"Point"}
}