{
  "type": "Feature",
  "properties": {
    "iso:country":"US",
    "sg:address":"1725 S Highland Ave",
    "sg:city":"Jackson",
    "sg:classifiers":[
        {
            "category":"Professional",
            "subcategory":"Accounting & Tax Preparation",
            "type":"Services"
        }
    ],
    "sg:phone":"+1 731 422 4410",
    "sg:postcode":"38301",
    "sg:province":"TN",
    "sg:tags":[
        "return",
        "filing"
    ],
    "wof:name":"H & R Block Tax Svc",
    "wof:placetype":"venue"
},
  "geometry": {"coordinates":[-88.812417,35.558172],"type":"Point"}
}