{
  "type": "Feature",
  "properties": {
    "iso:country":"US",
    "sg:address":"217 Copperridge Trl",
    "sg:city":"Rockvale",
    "sg:classifiers":[
        {
            "category":"Home & Garden",
            "subcategory":"Home Furnishings",
            "type":"Retail Goods"
        }
    ],
    "sg:phone":"+1 615 274 3077",
    "sg:postcode":"37153",
    "sg:province":"TN",
    "sg:tags":[
        "beveled",
        "glass",
        "ornamental"
    ],
    "wof:name":"Stellar Glass",
    "wof:placetype":"venue"
},
  "geometry": {"coordinates":[-86.552449,35.739714],"type":"Point"}
}