{
  "type": "Feature",
  "properties": {
    "iso:country":"US",
    "sg:address":"2948 Rocky Mound Rd",
    "sg:city":"Westmoreland",
    "sg:classifiers":[
        {
            "category":"Building & Trades",
            "subcategory":"Construction",
            "type":"Services"
        }
    ],
    "sg:phone":"+1 615 644 4991",
    "sg:postcode":"37186",
    "sg:province":"TN",
    "sg:tags":[
        "carpentry",
        "contractor"
    ],
    "wof:name":"Hackert & Sons Cabinets",
    "wof:placetype":"venue"
},
  "geometry": {"coordinates":[-86.172917,36.578787],"type":"Point"}
}