{
  "type": "Feature",
  "properties": {
    "iso:country":"US",
    "sg:address":"3841 Green Hills Village Dr",
    "sg:city":"Nashville",
    "sg:classifiers":[
        {
            "category":"Sports & Exercise",
            "subcategory":"Gym",
            "type":"Entertainment"
        }
    ],
    "sg:phone":"+1 615 292 6600",
    "sg:postcode":"37215",
    "sg:province":"TN",
    "sg:tags":[
        "club",
        "health",
        "studio",
        "gymnasium"
    ],
    "wof:name":"Delta",
    "wof:placetype":"venue"
},
  "geometry": {"coordinates":[-86.81591899999999,36.107604],"type":"Point"}
}