{
  "type": "Feature",
  "properties": {
    "iso:country":"US",
    "sg:address":"2736 Monte Vista Dr",
    "sg:city":"Maryville",
    "sg:classifiers":[
        {
            "category":"Retail",
            "subcategory":"Repair Shop",
            "type":"Services"
        }
    ],
    "sg:phone":"+1 865 977 7545",
    "sg:postcode":"37803",
    "sg:province":"TN",
    "wof:name":"Anderson Repairs",
    "wof:placetype":"venue"
},
  "geometry": {"coordinates":[-84.014984,35.704599],"type":"Point"}
}