{
  "type": "Feature",
  "properties": {
    "iso:country":"US",
    "sg:address":"141 S Martinwood Rd",
    "sg:city":"Knoxville",
    "sg:classifiers":[
        {
            "category":"Professional",
            "subcategory":"Advertising",
            "type":"Services"
        }
    ],
    "sg:phone":"+1 865 692 3737",
    "sg:postcode":"37923",
    "sg:province":"TN",
    "sg:tags":[
        "counselor"
    ],
    "wof:name":"Spectrum Design",
    "wof:placetype":"venue"
},
  "geometry": {"coordinates":[-84.070714,35.91674],"type":"Point"}
}