{
  "type": "Feature",
  "properties": {
    "iso:country":"US",
    "sg:address":"5770 Old Hickory Blvd",
    "sg:city":"Hermitage",
    "sg:classifiers":[
        {
            "category":"Restaurant",
            "type":"Food & Drink"
        }
    ],
    "sg:phone":"+1 615 872 0470",
    "sg:postcode":"37076",
    "sg:province":"TN",
    "sg:tags":[
        "eating"
    ],
    "wof:name":"Cinco De Mayo",
    "wof:placetype":"venue"
},
  "geometry": {"coordinates":[-86.601664,36.171678],"type":"Point"}
}