{
  "type": "Feature",
  "properties": {
    "iso:country":"US",
    "sg:address":"9408 Apison Pike",
    "sg:city":"Ooltewah",
    "sg:classifiers":[
        {
            "category":"Restaurant",
            "type":"Food & Drink"
        }
    ],
    "sg:menulink":"http://www.allmenus.com/tn/chattanooga/84377-papa-johns-pizza/menu/",
    "sg:phone":"+1 423 396 4433",
    "sg:postcode":"37363",
    "sg:province":"TN",
    "sg:tags":[
        "american",
        "pizza"
    ],
    "wof:name":"Papa John's Pizza",
    "wof:placetype":"venue"
},
  "geometry": {"coordinates":[-85.06965,35.060229],"type":"Point"}
}