{
  "type": "Feature",
  "properties": {
    "iso:country":"US",
    "sg:address":"298 Sam Ridley Pkwy E",
    "sg:city":"Smyrna",
    "sg:classifiers":[
        {
            "category":"Personal",
            "subcategory":"Beauty Salon",
            "type":"Services"
        }
    ],
    "sg:phone":"+1 615 220 9596",
    "sg:postcode":"37167",
    "sg:province":"TN",
    "wof:name":"Pavonine Barber & Beauty Salon",
    "wof:placetype":"venue"
},
  "geometry": {"coordinates":[-86.52278,35.996584],"type":"Point"}
}