{
  "type": "Feature",
  "properties": {
    "iso:country":"US",
    "sg:address":"835 Oak Leaf Dr",
    "sg:city":"Old Hickory",
    "sg:classifiers":[
        {
            "category":"Building & Trades",
            "subcategory":"Cleaning & Sanitation",
            "type":"Services"
        }
    ],
    "sg:phone":"+1 615 232 8715",
    "sg:postcode":"37138",
    "sg:province":"TN",
    "sg:tags":[
        "maintenance"
    ],
    "wof:name":"MA Cleaning Svc",
    "wof:placetype":"venue"
},
  "geometry": {"coordinates":[-86.58381199999999,36.213521],"type":"Point"}
}