{
  "type": "Feature",
  "properties": {
    "addr:full":"2911 8th Ave Chattanooga TN 37407",
    "addr:housenumber":"2911",
    "addr:postcode":"37407",
    "addr:street":"8Th Ave",
    "iso:country":"US",
    "sg:address":"2911 8th Ave",
    "sg:city":"Chattanooga",
    "sg:classifiers":[
        {
            "category":"Professional",
            "subcategory":"Advertising",
            "type":"Services"
        }
    ],
    "sg:phone":"+1 423 622 1428",
    "sg:postcode":"37407",
    "sg:province":"TN",
    "sg:tags":[
        "distribution"
    ],
    "wof:name":"Webster Distributing Co Inc",
    "wof:placetype":"venue"
},
  "geometry": {"coordinates":[-85.280393,35.007726],"type":"Point"}
}