{
  "type": "Feature",
  "properties": {
    "iso:country":"US",
    "sg:address":"1656 N Shelby Oaks Dr",
    "sg:city":"Memphis",
    "sg:classifiers":[
        {
            "category":"Professional",
            "type":"Services"
        }
    ],
    "sg:phone":"+1 901 843 4000",
    "sg:postcode":"38134",
    "sg:province":"TN",
    "sg:tags":[
        "establishment"
    ],
    "wof:name":"Outsource It",
    "wof:placetype":"venue"
},
  "geometry": {"coordinates":[-89.85514499999999,35.169759],"type":"Point"}
}