{
  "type": "Feature",
  "properties": {
    "iso:country":"US",
    "sg:address":"2216 Hamilton Place Blvd",
    "sg:city":"Chattanooga",
    "sg:classifiers":[
        {
            "category":"Shopping",
            "subcategory":"Stationery & Office Supplies",
            "type":"Retail Goods"
        }
    ],
    "sg:phone":"+1 423 510 9654",
    "sg:postcode":"37421",
    "sg:province":"TN",
    "wof:name":"Staples The Office Superstore",
    "wof:placetype":"venue"
},
  "geometry": {"coordinates":[-85.15513,35.040422],"type":"Point"}
}