{
  "type": "Feature",
  "properties": {
    "addr:full":"6894 US Hwy 411 S Greenback TN 37742",
    "addr:housenumber":"6894",
    "addr:postcode":"37742",
    "addr:street":"Us Hwy 411 S",
    "iso:country":"US",
    "sg:address":"6894 US Hwy 411 S",
    "sg:city":"Greenback",
    "sg:classifiers":[
        {
            "category":"Retail",
            "subcategory":"Auto Rental",
            "type":"Services"
        }
    ],
    "sg:phone":"+1 865 856 8007",
    "sg:postcode":"37742",
    "sg:province":"TN",
    "sg:tags":[
        "renting",
        "truck",
        "leasing"
    ],
    "wof:name":"U-Haul Co",
    "wof:placetype":"venue"
},
  "geometry": {"coordinates":[-84.160759,35.636232],"type":"Point"}
}