{
  "type": "Feature",
  "properties": {
    "iso:country":"US",
    "sg:address":"3055 Lebanon Pike",
    "sg:city":"Nashville",
    "sg:classifiers":[
        {
            "category":"Insurance",
            "subcategory":"Hazard Insurance",
            "type":"Services"
        }
    ],
    "sg:phone":"+1 615 234 0305",
    "sg:postcode":"37214",
    "sg:province":"TN",
    "sg:tags":[
        "agency"
    ],
    "wof:name":"Saint Paul Travellers",
    "wof:placetype":"venue"
},
  "geometry": {"coordinates":[-86.64777100000001,36.173792],"type":"Point"}
}