{
  "type": "Feature",
  "properties": {
    "addr:full":"225 W King St Jackson TN 38301",
    "addr:housenumber":"225",
    "addr:postcode":"38301",
    "addr:street":"W King St",
    "iso:country":"US",
    "sg:address":"225 W King St",
    "sg:city":"Jackson",
    "sg:classifiers":[
        {
            "category":"Government",
            "subcategory":"Police Station",
            "type":"Public Place"
        }
    ],
    "sg:phone":"+1 731 423 5790",
    "sg:postcode":"38301",
    "sg:province":"TN",
    "sg:tags":[
        "state"
    ],
    "sg:website":"www.tbi.state.tn.us",
    "wof:name":"Investigation Bureau",
    "wof:placetype":"venue"
},
  "geometry": {"coordinates":[-88.822199,35.624197],"type":"Point"}
}