{
  "type": "Feature",
  "properties": {
    "iso:country":"US",
    "sg:address":"1174 Rock Church Rd",
    "sg:city":"Dickson",
    "sg:classifiers":[
        {
            "category":"Manufacturing",
            "subcategory":"Metals",
            "type":"Manufacturing & Wholesale Goods"
        },
        {
            "category":"Building & Trades",
            "subcategory":"Construction",
            "type":"Services"
        }
    ],
    "sg:phone":"+1 615 446 2632",
    "sg:postcode":"37055",
    "sg:province":"TN",
    "sg:tags":[
        "steel",
        "repair",
        "structural",
        "welding",
        "contractor"
    ],
    "wof:name":"Stokes Steel & Construction",
    "wof:placetype":"venue"
},
  "geometry": {"coordinates":[-87.314001,36.096064],"type":"Point"}
}