{
  "type": "Feature",
  "properties": {
    "iso:country":"US",
    "sg:address":"2831 Wilma Rudolph Blvd",
    "sg:city":"Clarksville",
    "sg:classifiers":[
        {
            "category":"Insurance",
            "subcategory":"Health Insurance",
            "type":"Services"
        }
    ],
    "sg:phone":"+1 931 245 7000",
    "sg:postcode":"37040",
    "sg:province":"TN",
    "sg:tags":[
        "carrier"
    ],
    "wof:name":"Occupational Healthline",
    "wof:placetype":"venue"
},
  "geometry": {"coordinates":[-87.292227,36.589867],"type":"Point"}
}