{
  "type": "Feature",
  "properties": {
    "iso:country":"US",
    "sg:address":"1334 Stuart St",
    "sg:city":"Chattanooga",
    "sg:classifiers":[
        {
            "category":"Manufacturing",
            "subcategory":"Metals",
            "type":"Manufacturing & Wholesale Goods"
        },
        {
            "category":"Shopping",
            "subcategory":"Clothing, Apparel, & Fashions",
            "type":"Retail Goods"
        }
    ],
    "sg:phone":"+1 423 698 2416",
    "sg:postcode":"37406",
    "sg:province":"TN",
    "sg:tags":[
        "pattern",
        "foundry",
        "maker"
    ],
    "wof:name":"Chattanooga Pattern & Foundry Co",
    "wof:placetype":"venue"
},
  "geometry": {"coordinates":[-85.261543,35.075957],"type":"Point"}
}