{
  "type": "Feature",
  "properties": {
    "iso:country":"US",
    "sg:address":"4701 Gallatin Pike",
    "sg:city":"Nashville",
    "sg:classifiers":[
        {
            "category":"Shopping",
            "subcategory":"Tobacco",
            "type":"Retail Goods"
        }
    ],
    "sg:phone":"+1 615 226 5110",
    "sg:postcode":"37216",
    "sg:province":"TN",
    "sg:tags":[
        "cigarette",
        "cigar"
    ],
    "wof:name":"Ag Discount Tobacco Center",
    "wof:placetype":"venue"
},
  "geometry": {"coordinates":[-86.72505200000001,36.230148],"type":"Point"}
}