{
  "type": "Feature",
  "properties": {
    "iso:country":"US",
    "sg:address":"4137 Kirby Pkwy",
    "sg:city":"Memphis",
    "sg:classifiers":[
        {
            "category":"Health Services",
            "subcategory":"Doctor",
            "type":"Services"
        }
    ],
    "sg:phone":"+1 901 433 0701",
    "sg:postcode":"38115",
    "sg:province":"TN",
    "wof:name":"Graves DDS Dr Sheldon",
    "wof:placetype":"venue"
},
  "geometry": {"coordinates":[-89.847598,35.035555],"type":"Point"}
}