{
  "type": "Feature",
  "properties": {
    "addr:full":"5166 Pleasant Hill Rd Memphis TN 38118",
    "addr:housenumber":"5166",
    "addr:postcode":"38118",
    "addr:street":"Pleasant Hill Rd",
    "iso:country":"US",
    "sg:address":"5166 Pleasant Hill Rd",
    "sg:city":"Memphis",
    "sg:classifiers":[
        {
            "category":"Professional",
            "type":"Services"
        }
    ],
    "sg:phone":"+1 901 547 0429",
    "sg:postcode":"38118",
    "sg:province":"TN",
    "sg:tags":[
        "establishment"
    ],
    "wof:name":"Thomson",
    "wof:placetype":"venue"
},
  "geometry": {"coordinates":[-89.90157600000001,35.013177],"type":"Point"}
}