{
  "type": "Feature",
  "properties": {
    "iso:country":"US",
    "sg:address":"201 Rudy Cir",
    "sg:city":"Nashville",
    "sg:phone":"+1 615 391 5263",
    "sg:postcode":"37214",
    "sg:province":"TN",
    "sg:website":"http://www.mcdonalds.com",
    "wof:name":"McDonald's",
    "wof:placetype":"venue"
},
  "geometry": {"coordinates":[-86.693718,36.220112],"type":"Point"}
}