{
  "type": "Feature",
  "properties": {
    "addr:full":"4040 Murfreesboro Rd Franklin TN 37067",
    "addr:housenumber":"4040",
    "addr:postcode":"37067",
    "addr:street":"Murfreesboro Rd",
    "iso:country":"US",
    "sg:address":"4040 Murfreesboro Rd",
    "sg:city":"Franklin",
    "sg:classifiers":[
        {
            "category":"Organizations",
            "subcategory":"Religious Organization",
            "type":"Services"
        }
    ],
    "sg:phone":"+1 615 790 6605",
    "sg:postcode":"37067",
    "sg:province":"TN",
    "sg:tags":[
        "church"
    ],
    "sg:website":"www.fcctn.org",
    "wof:name":"Franklin Christian Church",
    "wof:placetype":"venue"
},
  "geometry": {"coordinates":[-86.812465,35.910174],"type":"Point"}
}