{
  "type": "Feature",
  "properties": {
    "addr:full":"30 Whitworth Blvd Nashville TN 37205",
    "addr:housenumber":"30",
    "addr:postcode":"37205",
    "addr:street":"Whitworth Blvd",
    "iso:country":"US",
    "sg:address":"30 Whitworth Blvd",
    "sg:city":"Nashville",
    "sg:classifiers":[
        {
            "category":"Communications",
            "subcategory":"Radio Station",
            "type":"Services"
        }
    ],
    "sg:phone":"+1 615 460 9384",
    "sg:postcode":"37205",
    "sg:province":"TN",
    "sg:tags":[
        "evaluation",
        "research"
    ],
    "wof:name":"Dr Kenneth Wong",
    "wof:placetype":"venue"
},
  "geometry": {"coordinates":[-86.82161000000001,36.128059],"type":"Point"}
}