{
  "type": "Feature",
  "properties": {
    "addr:full":"3000 Ferrell Park Cove Memphis TN 38116",
    "addr:housenumber":"3000",
    "addr:postcode":"38116",
    "addr:street":"Ferrell Park Cove",
    "iso:country":"US",
    "sg:address":"3000 Ferrell Park Cove",
    "sg:city":"Memphis",
    "sg:classifiers":[
        {
            "category":"Building & Trades",
            "subcategory":"Equipment Rental",
            "type":"Services"
        },
        {
            "category":"Building & Trades",
            "subcategory":"Construction",
            "type":"Services"
        }
    ],
    "sg:phone":"+1 901 346 5800",
    "sg:postcode":"38116",
    "sg:province":"TN",
    "sg:tags":[
        "merchandise",
        "shoring",
        "special",
        "t"
    ],
    "sg:website":"www.trenchsafety.com",
    "wof:name":"Trench Safety and Supply Inc",
    "wof:placetype":"venue"
},
  "geometry": {"coordinates":[-90.008425,35.066205],"type":"Point"}
}