{
  "type": "Feature",
  "properties": {
    "iso:country":"US",
    "sg:address":"406 Union Ave SW",
    "sg:city":"Knoxville",
    "sg:classifiers":[
        {
            "category":"Organizations",
            "subcategory":"Non-profit Organization",
            "type":"Services"
        }
    ],
    "sg:phone":"+1 865 523 1178",
    "sg:postcode":"37902",
    "sg:province":"TN",
    "sg:website":"www.knoxvillesymphony.com",
    "wof:name":"Knoxville Symphony Society",
    "wof:placetype":"venue"
},
  "geometry": {"coordinates":[-83.91936099999999,35.964594],"type":"Point"}
}