{
  "type": "Feature",
  "properties": {
    "iso:country":"US",
    "sg:address":"620 Matheny Ln",
    "sg:city":"Paris",
    "sg:classifiers":[
        {
            "category":"Farming",
            "subcategory":"Livestock Farm",
            "type":"Manufacturing & Wholesale Goods"
        }
    ],
    "sg:phone":"+1 731 642 6608",
    "sg:postcode":"38242",
    "sg:province":"TN",
    "sg:tags":[
        "beef",
        "feedlot",
        "cattle"
    ],
    "wof:name":"Ricky Matheny",
    "wof:placetype":"venue"
},
  "geometry": {"coordinates":[-88.404201,36.286764],"type":"Point"}
}