{
  "type": "Feature",
  "properties": {
    "addr:full":"3733 Ringgold Rd Chattanooga TN 37412",
    "addr:housenumber":"3733",
    "addr:postcode":"37412",
    "addr:street":"Ringgold Rd",
    "iso:country":"US",
    "sg:address":"3733 Ringgold Rd",
    "sg:city":"Chattanooga",
    "sg:classifiers":[
        {
            "category":"Retail",
            "subcategory":"Auto Rental",
            "type":"Services"
        }
    ],
    "sg:phone":"+1 423 493 4790",
    "sg:postcode":"37412",
    "sg:province":"TN",
    "sg:tags":[
        "passenger",
        "car"
    ],
    "wof:name":"Dollar Day & More",
    "wof:placetype":"venue"
},
  "geometry": {"coordinates":[-85.255814,34.999152],"type":"Point"}
}