{
  "type": "Feature",
  "properties": {
    "iso:country":"US",
    "sg:address":"130 Circle Dr",
    "sg:city":"Hendersonville",
    "sg:classifiers":[
        {
            "category":"Professional",
            "subcategory":"Engineering",
            "type":"Services"
        }
    ],
    "sg:phone":"+1 615 264 3415",
    "sg:postcode":"37075",
    "sg:province":"TN",
    "wof:name":"Foster Engineering & Energy",
    "wof:placetype":"venue"
},
  "geometry": {"coordinates":[-86.631939,36.262539],"type":"Point"}
}