{
  "type": "Feature",
  "properties": {
    "addr:full":"1190 Rock Island Rd Rock Island TN 38581",
    "addr:housenumber":"1190",
    "addr:postcode":"38581",
    "addr:street":"Rock Island Rd",
    "iso:country":"US",
    "sg:address":"1190 Rock Island Rd",
    "sg:city":"Rock Island",
    "sg:classifiers":[
        {
            "category":"Government",
            "subcategory":"Post Office",
            "type":"Public Place"
        }
    ],
    "sg:phone":"+1 931 686 2523",
    "sg:postcode":"38581",
    "sg:province":"TN",
    "wof:name":"US Post Office",
    "wof:placetype":"venue"
},
  "geometry": {"coordinates":[-85.613724,35.789043],"type":"Point"}
}