{
  "type": "Feature",
  "properties": {
    "addr:full":"1005 Carmack Blvd Columbia TN 38401",
    "addr:housenumber":"1005",
    "addr:postcode":"38401",
    "addr:street":"Carmack Blvd",
    "iso:country":"US",
    "sg:address":"1005 Carmack Blvd",
    "sg:city":"Columbia",
    "sg:classifiers":[
        {
            "category":"Food & Beverages",
            "subcategory":"Groceries & Convenience Stores",
            "type":"Retail Goods"
        }
    ],
    "sg:phone":"+1 931 388 1588",
    "sg:postcode":"38401",
    "sg:province":"TN",
    "sg:tags":[
        "grocer"
    ],
    "wof:name":"Super Rama Foods",
    "wof:placetype":"venue"
},
  "geometry": {"coordinates":[-87.03576099999999,35.612017],"type":"Point"}
}