{
  "type": "Feature",
  "properties": {
    "addr:full":"1980 Oak Grove Dr Moscow TN 38057",
    "addr:housenumber":"1980",
    "addr:postcode":"38057",
    "addr:street":"Oak Grove Dr",
    "iso:country":"US",
    "sg:address":"1980 Oak Grove Dr",
    "sg:city":"Moscow",
    "sg:classifiers":[
        {
            "category":"Organizations",
            "subcategory":"Religious Organization",
            "type":"Services"
        }
    ],
    "sg:phone":"+1 901 877 3344",
    "sg:postcode":"38057",
    "sg:province":"TN",
    "sg:tags":[
        "church"
    ],
    "wof:name":"Oak Grove Baptist Church",
    "wof:placetype":"venue"
},
  "geometry": {"coordinates":[-89.42115200000001,35.019635],"type":"Point"}
}