{
  "type": "Feature",
  "properties": {
    "iso:country":"US",
    "sg:address":"2509 McCallie Ave",
    "sg:city":"Chattanooga",
    "sg:classifiers":[
        {
            "category":"Professional",
            "type":"Services"
        },
        {
            "category":"Professional",
            "subcategory":"Business Services",
            "type":"Services"
        }
    ],
    "sg:phone":"+1 423 622 6792",
    "sg:postcode":"37404",
    "sg:province":"TN",
    "sg:tags":[
        "interior",
        "consultant",
        "design",
        "decorator"
    ],
    "wof:name":"Lydia's Hand Painting",
    "wof:placetype":"venue"
},
  "geometry": {"coordinates":[-85.26389399999999,35.031981],"type":"Point"}
}