{
  "type": "Feature",
  "properties": {
    "addr:full":"1800 Mallory Ln Brentwood TN 37027",
    "addr:housenumber":"1800",
    "addr:postcode":"37027",
    "addr:street":"Mallory Ln",
    "iso:country":"US",
    "sg:address":"1800 Mallory Ln",
    "sg:city":"Brentwood",
    "sg:classifiers":[
        {
            "category":"Professional",
            "type":"Services"
        }
    ],
    "sg:phone":"+1 615 376 9330",
    "sg:postcode":"37027",
    "sg:province":"TN",
    "sg:tags":[
        "establishment"
    ],
    "wof:name":"Cumberland Capital Inc",
    "wof:placetype":"venue"
},
  "geometry": {"coordinates":[-86.815934,35.958985],"type":"Point"}
}