{
  "type": "Feature",
  "properties": {
    "addr:full":"3570 Old Getwell Rd Memphis TN 38118",
    "addr:housenumber":"3570",
    "addr:postcode":"38118",
    "addr:street":"Old Getwell Rd",
    "iso:country":"US",
    "sg:address":"3570 Old Getwell Rd",
    "sg:city":"Memphis",
    "sg:classifiers":[
        {
            "category":"Wholesale",
            "subcategory":"Stationery",
            "type":"Manufacturing & Wholesale Goods"
        }
    ],
    "sg:phone":"+1 901 754 1286",
    "sg:postcode":"38118",
    "sg:province":"TN",
    "sg:tags":[
        "packaging",
        "material"
    ],
    "wof:name":"Packaging Associates",
    "wof:placetype":"venue"
},
  "geometry": {"coordinates":[-89.93711500000001,35.049028],"type":"Point"}
}