{
  "type": "Feature",
  "properties": {
    "iso:country":"US",
    "sg:address":"206 S Armstrong St",
    "sg:city":"Rogersville",
    "sg:classifiers":[
        {
            "category":"Freight",
            "type":"Transportation"
        }
    ],
    "sg:phone":"+1 423 272 8321",
    "sg:postcode":"37857",
    "sg:province":"TN",
    "sg:tags":[
        "farm",
        "product",
        "warehousing",
        "rep",
        "machinery"
    ],
    "wof:name":"Growers Warehouse",
    "wof:placetype":"venue"
},
  "geometry": {"coordinates":[-83.012767,36.402466],"type":"Point"}
}