{
  "type": "Feature",
  "properties": {
    "iso:country":"US",
    "sg:address":"1612 Lone Oak Rd",
    "sg:city":"Paris",
    "sg:classifiers":[
        {
            "category":"Retail",
            "subcategory":"Repair Shop",
            "type":"Services"
        }
    ],
    "sg:phone":"+1 731 644 0311",
    "sg:postcode":"38242",
    "sg:province":"TN",
    "sg:tags":[
        "lock",
        "locksmith"
    ],
    "wof:name":"Scammerhorn Locksmith Service",
    "wof:placetype":"venue"
},
  "geometry": {"coordinates":[-88.296269,36.301013],"type":"Point"}
}