{
  "type": "Feature",
  "properties": {
    "addr:full":"500 E College St Dickson TN 37055",
    "addr:housenumber":"500",
    "addr:postcode":"37055",
    "addr:street":"E College St",
    "iso:country":"US",
    "sg:address":"500 E College St",
    "sg:city":"Dickson",
    "sg:classifiers":[
        {
            "category":"Communications",
            "subcategory":"Radio Station",
            "type":"Services"
        }
    ],
    "sg:phone":"+1 615 446 3764",
    "sg:postcode":"37055",
    "sg:province":"TN",
    "wof:name":"Wfgz Froggy 94",
    "wof:placetype":"venue"
},
  "geometry": {"coordinates":[-87.383365,36.07356],"type":"Point"}
}