{
  "type": "Feature",
  "properties": {
    "addr:full":"1807 Bartlett Rd Memphis TN 38134",
    "addr:housenumber":"1807",
    "addr:postcode":"38134",
    "addr:street":"Bartlett Rd",
    "iso:country":"US",
    "sg:address":"1807 Bartlett Rd",
    "sg:city":"Memphis",
    "sg:classifiers":[
        {
            "category":"Retail",
            "subcategory":"Auto Repair",
            "type":"Services"
        }
    ],
    "sg:phone":"+1 901 371 8737",
    "sg:postcode":"38134",
    "sg:province":"TN",
    "sg:tags":[
        "wrecker"
    ],
    "wof:name":"Expressway Towing Svc",
    "wof:placetype":"venue"
},
  "geometry": {"coordinates":[-89.880279,35.17593],"type":"Point"}
}