{
  "type": "Feature",
  "properties": {
    "iso:country":"US",
    "sg:address":"775 Raider Dr",
    "sg:city":"Cleveland",
    "sg:classifiers":[
        {
            "category":"Professional",
            "type":"Services"
        }
    ],
    "sg:phone":"+1 423 476 7669",
    "sg:postcode":"37312",
    "sg:province":"TN",
    "sg:tags":[
        "establishment"
    ],
    "wof:name":"Dough Boy 24 Hour Teller",
    "wof:placetype":"venue"
},
  "geometry": {"coordinates":[-84.86446599999999,35.191375],"type":"Point"}
}