{
  "type": "Feature",
  "properties": {
    "iso:country":"US",
    "sg:address":"7390 US Hwy 64",
    "sg:city":"Oakland",
    "sg:classifiers":[
        {
            "category":"Real Estate",
            "subcategory":"Real Estate Agent",
            "type":"Services"
        }
    ],
    "sg:phone":"+1 901 795 7139",
    "sg:postcode":"38068",
    "sg:province":"TN",
    "wof:name":"Parrish & Assoc Inc",
    "wof:placetype":"venue"
},
  "geometry": {"coordinates":[-89.51230200000001,35.228879],"type":"Point"}
}