{
  "type": "Feature",
  "properties": {
    "iso:country":"US",
    "sg:address":"1228 Wayne Rd",
    "sg:city":"Savannah",
    "sg:classifiers":[
        {
            "category":"Utilities",
            "subcategory":"Cable",
            "type":"Services"
        }
    ],
    "sg:phone":"+1 731 925 8593",
    "sg:postcode":"38372",
    "sg:province":"TN",
    "sg:tags":[
        "television"
    ],
    "wof:name":"Imtermedia",
    "wof:placetype":"venue"
},
  "geometry": {"coordinates":[-88.24094100000001,35.226499],"type":"Point"}
}