{
  "type": "Feature",
  "properties": {
    "iso:country":"US",
    "sg:address":"530 E Broadway Ave",
    "sg:city":"Maryville",
    "sg:classifiers":[
        {
            "category":"Health Services",
            "subcategory":"Health Practitioner",
            "type":"Services"
        }
    ],
    "sg:phone":"+1 865 982 6370",
    "sg:postcode":"37804",
    "sg:province":"TN",
    "sg:tags":[
        "psychologist"
    ],
    "wof:name":"R Jeff Slavin PHD",
    "wof:placetype":"venue"
},
  "geometry": {"coordinates":[-83.967966,35.759468],"type":"Point"}
}