{
  "type": "Feature",
  "properties": {
    "iso:country":"US",
    "sg:address":"259 Co Rd 617",
    "sg:city":"Athens",
    "sg:classifiers":[
        {
            "category":"Farming",
            "subcategory":"Livestock Farm",
            "type":"Manufacturing & Wholesale Goods"
        }
    ],
    "sg:phone":"+1 423 263 1205",
    "sg:postcode":"37303",
    "sg:province":"TN",
    "sg:tags":[
        "beef",
        "feedlot",
        "cattle"
    ],
    "wof:name":"Ralph Loveday Farm",
    "wof:placetype":"venue"
},
  "geometry": {"coordinates":[-84.57255499999999,35.334361],"type":"Point"}
}