{
  "type": "Feature",
  "properties": {
    "iso:country":"US",
    "sg:address":"5901 California Ave",
    "sg:city":"Nashville",
    "sg:classifiers":[
        {
            "category":"Manufacturing",
            "subcategory":"Tools & Machinery",
            "type":"Manufacturing & Wholesale Goods"
        }
    ],
    "sg:phone":"+1 615 383 6803",
    "sg:postcode":"37209",
    "sg:province":"TN",
    "sg:tags":[
        "equipment",
        "electric"
    ],
    "sg:website":"www.dixiewire.com",
    "wof:name":"Dixie Wire Co",
    "wof:placetype":"venue"
},
  "geometry": {"coordinates":[-86.858857,36.16475],"type":"Point"}
}