{
  "type": "Feature",
  "properties": {
    "iso:country":"US",
    "sg:address":"133 Commerce St",
    "sg:city":"Sevierville",
    "sg:classifiers":[
        {
            "category":"Professional",
            "subcategory":"Business Services",
            "type":"Services"
        }
    ],
    "sg:phone":"+1 865 428 2522",
    "sg:postcode":"37862",
    "sg:province":"TN",
    "wof:name":"Ace Bonding of Sevier County",
    "wof:placetype":"venue"
},
  "geometry": {"coordinates":[-83.56652200000001,35.86822],"type":"Point"}
}