{
  "type": "Feature",
  "properties": {
    "iso:country":"US",
    "sg:address":"1436 N Mount Juliet Rd",
    "sg:city":"Mt Juliet",
    "sg:classifiers":[
        {
            "category":"Building & Trades",
            "subcategory":"Construction",
            "type":"Services"
        }
    ],
    "sg:phone":"+1 615 773 8980",
    "sg:postcode":"37122",
    "sg:province":"TN",
    "sg:tags":[
        "contractor"
    ],
    "wof:name":"Wooten Construction",
    "wof:placetype":"venue"
},
  "geometry": {"coordinates":[-86.51544199999999,36.192165],"type":"Point"}
}