{
  "type": "Feature",
  "properties": {
    "iso:country":"US",
    "sg:address":"1055 Neelys Bend Rd",
    "sg:city":"Madison",
    "sg:classifiers":[
        {
            "category":"Organizations",
            "subcategory":"Religious Organization",
            "type":"Services"
        }
    ],
    "sg:phone":"+1 615 868 0699",
    "sg:postcode":"37115",
    "sg:province":"TN",
    "sg:tags":[
        "church"
    ],
    "wof:name":"Jesus Of Nazareth Chr Intl Inc",
    "wof:placetype":"venue"
},
  "geometry": {"coordinates":[-86.68153599999999,36.247523],"type":"Point"}
}