{
  "type": "Feature",
  "properties": {
    "iso:country":"US",
    "sg:address":"27 Medical Center Dr",
    "sg:city":"Jackson",
    "sg:classifiers":[
        {
            "category":"Health Services",
            "subcategory":"Doctor",
            "type":"Services"
        }
    ],
    "sg:phone":"+1 731 422 2272",
    "sg:postcode":"38301",
    "sg:province":"TN",
    "sg:tags":[
        "physician",
        "surgeon",
        "medical"
    ],
    "wof:name":"Advanced Kidney Specialists PC",
    "wof:placetype":"venue"
},
  "geometry": {"coordinates":[-88.82925899999999,35.637849],"type":"Point"}
}