{
  "type": "Feature",
  "properties": {
    "iso:country":"US",
    "sg:address":"256 N Florence Ave",
    "sg:city":"Jellico",
    "sg:classifiers":[
        {
            "category":"Organizations",
            "subcategory":"Religious Organization",
            "type":"Services"
        }
    ],
    "sg:phone":"+1 423 784 8260",
    "sg:postcode":"37762",
    "sg:province":"TN",
    "sg:tags":[
        "church"
    ],
    "wof:name":"Church-God Mountain Assembly",
    "wof:placetype":"venue"
},
  "geometry": {"coordinates":[-84.13481899999999,36.581133],"type":"Point"}
}