{
  "type": "Feature",
  "properties": {
    "iso:country":"US",
    "sg:address":"2361 Memorial Blvd",
    "sg:city":"Murfreesboro",
    "sg:classifiers":[
        {
            "category":"Health Services",
            "subcategory":"Optometrist",
            "type":"Services"
        }
    ],
    "sg:phone":"+1 615 896 0082",
    "sg:postcode":"37129",
    "sg:province":"TN",
    "wof:name":"Accu-Vision Optical",
    "wof:placetype":"venue"
},
  "geometry": {"coordinates":[-86.395492,35.854664],"type":"Point"}
}