{
  "type": "Feature",
  "properties": {
    "iso:country":"US",
    "sg:address":"1903 S Highland Park Ave",
    "sg:city":"Chattanooga",
    "sg:classifiers":[
        {
            "category":"Building & Trades",
            "subcategory":"Construction",
            "type":"Services"
        }
    ],
    "sg:phone":"+1 423 624 7369",
    "sg:postcode":"37404",
    "sg:province":"TN",
    "sg:tags":[
        "concrete",
        "cutting",
        "breaking",
        "sawing"
    ],
    "sg:website":"www.sawconcrete.com",
    "wof:name":"True-Line Coring & Cutting",
    "wof:placetype":"venue"
},
  "geometry": {"coordinates":[-85.28920599999999,35.022623],"type":"Point"}
}