{
  "type": "Feature",
  "properties": {
    "iso:country":"US",
    "sg:address":"139 Holly Forest",
    "sg:city":"Nashville",
    "sg:classifiers":[
        {
            "category":"Professional",
            "type":"Services"
        }
    ],
    "sg:phone":"+1 615 646 6511",
    "sg:postcode":"37221",
    "sg:province":"TN",
    "wof:name":"Ben Boley Arts",
    "wof:placetype":"venue"
},
  "geometry": {"coordinates":[-86.91413900000001,36.072986],"type":"Point"}
}