{
  "type": "Feature",
  "properties": {
    "iso:country":"US",
    "sg:address":"1 Oldham St",
    "sg:city":"Nashville",
    "sg:classifiers":[
        {
            "category":"Retail",
            "subcategory":"Car Wash",
            "type":"Services"
        }
    ],
    "sg:phone":"+1 615 242 3551",
    "sg:postcode":"37213",
    "sg:province":"TN",
    "sg:tags":[
        "truck",
        "cleaning"
    ],
    "wof:name":"Burnette's Truck Wash Inc",
    "wof:placetype":"venue"
},
  "geometry": {"coordinates":[-86.775032,36.174476],"type":"Point"}
}