{
  "type": "Feature",
  "properties": {
    "iso:country":"US",
    "sg:address":"3131 Brethren Church Rd",
    "sg:city":"White Pine",
    "sg:classifiers":[
        {
            "category":"Professional",
            "subcategory":"Business Services",
            "type":"Services"
        }
    ],
    "sg:phone":"+1 865 397 7655",
    "sg:postcode":"37890",
    "sg:province":"TN",
    "wof:name":"Rdr Management Group LLC",
    "wof:placetype":"venue"
},
  "geometry": {"coordinates":[-83.343658,36.05367],"type":"Point"}
}