{
  "type": "Feature",
  "properties": {
    "iso:country":"US",
    "sg:address":"307 Shadow Walk Rd",
    "sg:city":"Chattanooga",
    "sg:classifiers":[
        {
            "category":"Organizations",
            "subcategory":"Religious Organization",
            "type":"Services"
        }
    ],
    "sg:phone":"+1 423 894 4829",
    "sg:postcode":"37421",
    "sg:province":"TN",
    "wof:name":"7th Heaven",
    "wof:placetype":"venue"
},
  "geometry": {"coordinates":[-85.107288,35.009113],"type":"Point"}
}