{
  "type": "Feature",
  "properties": {
    "addr:full":"811 Easy St Lebanon TN 37087",
    "addr:housenumber":"811",
    "addr:postcode":"37087",
    "addr:street":"Easy St",
    "iso:country":"US",
    "sg:address":"811 Easy St",
    "sg:city":"Lebanon",
    "sg:classifiers":[
        {
            "category":"Manufacturing",
            "subcategory":"Building Materials",
            "type":"Manufacturing & Wholesale Goods"
        }
    ],
    "sg:phone":"+1 615 453 5422",
    "sg:postcode":"37087",
    "sg:province":"TN",
    "sg:tags":[
        "mfg",
        "wood",
        "kitchen",
        "cabinet"
    ],
    "wof:name":"American Cabinet",
    "wof:placetype":"venue"
},
  "geometry": {"coordinates":[-86.312065,36.209462],"type":"Point"}
}