{
  "type": "Feature",
  "properties": {
    "addr:full":"11533 Kingston Pike Knoxville TN 37934",
    "addr:housenumber":"11533",
    "addr:postcode":"37934",
    "addr:street":"Kingston Pike",
    "iso:country":"US",
    "sg:address":"11533 Kingston Pike",
    "sg:city":"Knoxville",
    "sg:classifiers":[
        {
            "category":"Food & Beverages",
            "subcategory":"Dairy",
            "type":"Retail Goods"
        }
    ],
    "sg:phone":"+1 865 966 5986",
    "sg:postcode":"37934",
    "sg:province":"TN",
    "sg:tags":[
        "yogurt"
    ],
    "wof:name":"Colgurt's Yogurt",
    "wof:placetype":"venue"
},
  "geometry": {"coordinates":[-84.166432,35.8785],"type":"Point"}
}