{
  "type": "Feature",
  "properties": {
    "iso:country":"US",
    "sg:address":"1005 Lynn Garden Dr",
    "sg:city":"Kingsport",
    "sg:classifiers":[
        {
            "category":"Food & Beverages",
            "subcategory":"Groceries & Convenience Stores",
            "type":"Retail Goods"
        }
    ],
    "sg:phone":"+1 423 245 3012",
    "sg:postcode":"37665",
    "sg:province":"TN",
    "sg:tags":[
        "market"
    ],
    "wof:name":"El Corita",
    "wof:placetype":"venue"
},
  "geometry": {"coordinates":[-82.56620599999999,36.571978],"type":"Point"}
}