{
  "type": "Feature",
  "properties": {
    "addr:full":"1300 Chestnut St Chattanooga TN 37402",
    "addr:housenumber":"1300",
    "addr:postcode":"37402",
    "addr:street":"Chestnut St",
    "iso:country":"US",
    "sg:address":"1300 Chestnut St",
    "sg:city":"Chattanooga",
    "sg:classifiers":[
        {
            "category":"Wholesale",
            "subcategory":"Stationery",
            "type":"Manufacturing & Wholesale Goods"
        }
    ],
    "sg:phone":"+1 423 266 2728",
    "sg:postcode":"37402",
    "sg:province":"TN",
    "sg:tags":[
        "product",
        "paper"
    ],
    "sg:website":"www.jacobspaper.com",
    "wof:name":"Jacobs Wholesale & Paper Co",
    "wof:placetype":"venue"
},
  "geometry": {"coordinates":[-85.312805,35.039463],"type":"Point"}
}