{
  "type": "Feature",
  "properties": {
    "iso:country":"US",
    "sg:address":"250 N Main St",
    "sg:city":"Memphis",
    "sg:classifiers":[
        {
            "category":"Shopping",
            "subcategory":"Gifts & Souvenirs",
            "type":"Retail Goods"
        }
    ],
    "sg:phone":"+1 901 527 6288",
    "sg:postcode":"38103",
    "sg:province":"TN",
    "sg:tags":[
        "shop"
    ],
    "wof:name":"Gift Shop Business Center",
    "wof:placetype":"venue"
},
  "geometry": {"coordinates":[-90.050168,35.151791],"type":"Point"}
}