{
  "type": "Feature",
  "properties": {
    "iso:country":"US",
    "sg:address":"6987 Shadow Oaks Dr",
    "sg:city":"Memphis",
    "sg:classifiers":[
        {
            "category":"Food & Beverages",
            "subcategory":"Meat & Fish",
            "type":"Retail Goods"
        }
    ],
    "sg:phone":"+1 901 753 7496",
    "sg:postcode":"38125",
    "sg:province":"TN",
    "wof:name":"Mr TS Specialty Meats",
    "wof:placetype":"venue"
},
  "geometry": {"coordinates":[-89.829441,35.029231],"type":"Point"}
}