{
  "type": "Feature",
  "properties": {
    "iso:country":"US",
    "sg:address":"1207 New Home Rd",
    "sg:city":"Dowelltown",
    "sg:classifiers":[
        {
            "category":"Building & Trades",
            "subcategory":"Construction",
            "type":"Services"
        }
    ],
    "sg:phone":"+1 615 597 8501",
    "sg:postcode":"37059",
    "sg:province":"TN",
    "sg:tags":[
        "house"
    ],
    "wof:name":"Tim Staley Construction LLC",
    "wof:placetype":"venue"
},
  "geometry": {"coordinates":[-85.863722,35.965443],"type":"Point"}
}