{
  "type": "Feature",
  "properties": {
    "addr:full":"710 Myatt Dr Madison TN 37115",
    "addr:housenumber":"710",
    "addr:postcode":"37115",
    "addr:street":"Myatt Dr",
    "iso:country":"US",
    "sg:address":"710 Myatt Dr",
    "sg:city":"Madison",
    "sg:classifiers":[
        {
            "category":"Wholesale",
            "subcategory":"Chemicals & Plastics",
            "type":"Manufacturing & Wholesale Goods"
        },
        {
            "category":"Manufacturing",
            "subcategory":"Chemicals & Compounds",
            "type":"Manufacturing & Wholesale Goods"
        }
    ],
    "sg:phone":"+1 615 612 1573",
    "sg:postcode":"37115",
    "sg:province":"TN",
    "sg:tags":[
        "preparation",
        "mfg"
    ],
    "wof:name":"Chemway",
    "wof:placetype":"venue"
},
  "geometry": {"coordinates":[-86.696602,36.293884],"type":"Point"}
}