{
  "type": "Feature",
  "properties": {
    "iso:country":"US",
    "sg:address":"1441 Vinton Ave",
    "sg:city":"Memphis",
    "sg:classifiers":[
        {
            "category":"Real Estate",
            "subcategory":"Real Estate Agent",
            "type":"Services"
        },
        {
            "category":"Professional",
            "subcategory":"Business Services",
            "type":"Services"
        }
    ],
    "sg:phone":"+1 901 726 1034",
    "sg:postcode":"38104",
    "sg:province":"TN",
    "sg:tags":[
        "sales"
    ],
    "wof:name":"Bryant John M Estate Sales",
    "wof:placetype":"venue"
},
  "geometry": {"coordinates":[-90.01654,35.13058],"type":"Point"}
}