{
  "type": "Feature",
  "properties": {
    "addr:full":"2033 Dilton Mankin Rd Murfreesboro TN 37127",
    "addr:housenumber":"2033",
    "addr:postcode":"37127",
    "addr:street":"Dilton Mankin Rd",
    "iso:country":"US",
    "sg:address":"2033 Dilton Mankin Rd",
    "sg:city":"Murfreesboro",
    "sg:classifiers":[
        {
            "category":"Building & Trades",
            "subcategory":"Construction",
            "type":"Services"
        }
    ],
    "sg:phone":"+1 615 907 1848",
    "sg:postcode":"37127",
    "sg:province":"TN",
    "sg:tags":[
        "home",
        "improvement"
    ],
    "wof:name":"Classic Handyman Co",
    "wof:placetype":"venue"
},
  "geometry": {"coordinates":[-86.324978,35.791505],"type":"Point"}
}