{
  "type": "Feature",
  "properties": {
    "iso:country":"US",
    "sg:address":"130 Davis St",
    "sg:city":"Portland",
    "sg:classifiers":[
        {
            "category":"Professional",
            "subcategory":"Advertising",
            "type":"Services"
        }
    ],
    "sg:phone":"+1 615 325 0404",
    "sg:postcode":"37148",
    "sg:province":"TN",
    "sg:tags":[
        "distribution"
    ],
    "sg:website":"www.cissellmfg.com",
    "wof:name":"Cissell Distribution Ctr",
    "wof:placetype":"venue"
},
  "geometry": {"coordinates":[-86.51713700000001,36.590296],"type":"Point"}
}