{
  "type": "Feature",
  "properties": {
    "addr:full":"1829 State Hwy 12 N Ashland City TN 37015",
    "addr:housenumber":"1829",
    "addr:postcode":"37015",
    "addr:street":"State Hwy 12 N",
    "iso:country":"US",
    "sg:address":"1829 State Hwy 12 N",
    "sg:city":"Ashland City",
    "sg:classifiers":[
        {
            "category":"Organizations",
            "subcategory":"Religious Organization",
            "type":"Services"
        }
    ],
    "sg:phone":"+1 615 792 8710",
    "sg:postcode":"37015",
    "sg:province":"TN",
    "sg:tags":[
        "church"
    ],
    "wof:name":"Jehovah's Witnesses",
    "wof:placetype":"venue"
},
  "geometry": {"coordinates":[-87.094962,36.305433],"type":"Point"}
}