{
  "type": "Feature",
  "properties": {
    "iso:country":"US",
    "sg:address":"3936 Ringgold Rd",
    "sg:city":"Chattanooga",
    "sg:classifiers":[
        {
            "category":"Professional",
            "subcategory":"Lawyer & Legal Services",
            "type":"Services"
        }
    ],
    "sg:phone":"+1 423 510 0054",
    "sg:postcode":"37412",
    "sg:province":"TN",
    "sg:tags":[
        "attorney"
    ],
    "wof:name":"Cohen & Cohen",
    "wof:placetype":"venue"
},
  "geometry": {"coordinates":[-85.250754,34.997513],"type":"Point"}
}