{
  "type": "Feature",
  "properties": {
    "iso:country":"US",
    "sg:address":"20 Moore Ln",
    "sg:city":"Oak Ridge",
    "sg:classifiers":[
        {
            "category":"Wholesale",
            "subcategory":"Medical Equipment & Supplies",
            "type":"Manufacturing & Wholesale Goods"
        },
        {
            "category":"Professional",
            "subcategory":"Management & Consulting",
            "type":"Services"
        }
    ],
    "sg:phone":"+1 865 806 6773",
    "sg:postcode":"37830",
    "sg:province":"TN",
    "sg:tags":[
        "business"
    ],
    "wof:name":"Accelerator Consulting Service",
    "wof:placetype":"venue"
},
  "geometry": {"coordinates":[-84.308378,36.006192],"type":"Point"}
}