{
  "type": "Feature",
  "properties": {
    "addr:full":"3108 Lumberjack Rd Nashville TN 37214",
    "addr:housenumber":"3108",
    "addr:postcode":"37214",
    "addr:street":"Lumberjack Rd",
    "iso:country":"US",
    "sg:address":"3108 Lumberjack Rd",
    "sg:city":"Nashville",
    "sg:classifiers":[
        {
            "category":"Shopping",
            "subcategory":"Beauty & Cosmetics",
            "type":"Retail Goods"
        }
    ],
    "sg:phone":"+1 615 885 4630",
    "sg:postcode":"37214",
    "sg:province":"TN",
    "sg:tags":[
        "merchandise"
    ],
    "wof:name":"Mary Kay Cosmetics",
    "wof:placetype":"venue"
},
  "geometry": {"coordinates":[-86.63359199999999,36.141847],"type":"Point"}
}