{
  "type": "Feature",
  "properties": {
    "iso:country":"US",
    "sg:address":"206 E Main St",
    "sg:city":"Jackson",
    "sg:classifiers":[
        {
            "category":"Professional",
            "subcategory":"Management & Consulting",
            "type":"Services"
        }
    ],
    "sg:phone":"+1 731 422 2289",
    "sg:postcode":"38301",
    "sg:province":"TN",
    "sg:tags":[
        "personnel",
        "consultant"
    ],
    "wof:name":"Indemand Staffing-West Tn",
    "wof:placetype":"venue"
},
  "geometry": {"coordinates":[-88.81726999999999,35.614205],"type":"Point"}
}