{
  "type": "Feature",
  "properties": {
    "iso:country":"US",
    "sg:address":"130 Hidden Acres Rd",
    "sg:city":"Paris",
    "sg:classifiers":[
        {
            "category":"Organizations",
            "subcategory":"Religious Organization",
            "type":"Services"
        }
    ],
    "sg:phone":"+1 731 641 0155",
    "sg:postcode":"38242",
    "sg:province":"TN",
    "sg:tags":[
        "church"
    ],
    "wof:name":"Vine",
    "wof:placetype":"venue"
},
  "geometry": {"coordinates":[-88.268612,36.32401],"type":"Point"}
}