{
  "type": "Feature",
  "properties": {
    "addr:full":"4208 Winchester Rd Memphis TN 38118",
    "addr:housenumber":"4208",
    "addr:postcode":"38118",
    "addr:street":"Winchester Rd",
    "iso:country":"US",
    "sg:address":"4208 Winchester Rd",
    "sg:city":"Memphis",
    "sg:classifiers":[
        {
            "category":"Personal",
            "subcategory":"Beauty Salon",
            "type":"Services"
        }
    ],
    "sg:phone":"+1 901 794 3488",
    "sg:postcode":"38118",
    "sg:province":"TN",
    "sg:tags":[
        "shop"
    ],
    "wof:name":"Royal Nail",
    "wof:placetype":"venue"
},
  "geometry": {"coordinates":[-89.92238399999999,35.051664],"type":"Point"}
}