{
  "type": "Feature",
  "properties": {
    "addr:full":"602 S Hancock St Murfreesboro TN 37130",
    "addr:housenumber":"602",
    "addr:postcode":"37130",
    "addr:street":"S Hancock St",
    "iso:country":"US",
    "sg:address":"602 S Hancock St",
    "sg:city":"Murfreesboro",
    "sg:classifiers":[
        {
            "category":"Education",
            "subcategory":"Special Training",
            "type":"Public Place"
        }
    ],
    "sg:phone":"+1 615 896 5800",
    "sg:postcode":"37130",
    "sg:province":"TN",
    "sg:tags":[
        "reading",
        "instruction",
        "improvement"
    ],
    "wof:name":"Even Start",
    "wof:placetype":"venue"
},
  "geometry": {"coordinates":[-86.38093000000001,35.837844],"type":"Point"}
}