{
  "type": "Feature",
  "properties": {
    "iso:country":"US",
    "sg:address":"5340 Rock Ridge Cove",
    "sg:city":"Memphis",
    "sg:classifiers":[
        {
            "category":"Professional",
            "subcategory":"Management & Consulting",
            "type":"Services"
        }
    ],
    "sg:phone":"+1 901 380 8553",
    "sg:postcode":"38134",
    "sg:province":"TN",
    "sg:tags":[
        "heavy",
        "repair",
        "training",
        "consultant",
        "safety",
        "crane"
    ],
    "wof:name":"Grace Crane Servi Ce Inc",
    "wof:placetype":"venue"
},
  "geometry": {"coordinates":[-89.884604,35.184652],"type":"Point"}
}