{
  "type": "Feature",
  "properties": {
    "iso:country":"US",
    "sg:address":"1831 Hitching Post Dr",
    "sg:city":"Knoxville",
    "sg:classifiers":[
        {
            "category":"Professional",
            "type":"Services"
        }
    ],
    "sg:phone":"+1 865 694 8368",
    "sg:postcode":"37931",
    "sg:province":"TN",
    "sg:tags":[
        "establishment"
    ],
    "wof:name":"Ayso Region 275",
    "wof:placetype":"venue"
},
  "geometry": {"coordinates":[-84.110625,35.955367],"type":"Point"}
}