{
  "type": "Feature",
  "properties": {
    "iso:country":"US",
    "sg:address":"331 Rockwell Farm Ln",
    "sg:city":"Knoxville",
    "sg:classifiers":[
        {
            "category":"Shopping",
            "type":"Retail Goods"
        }
    ],
    "sg:phone":"+1 865 671 3896",
    "sg:postcode":"37934",
    "sg:province":"TN",
    "sg:tags":[
        "miscellaneous",
        "store"
    ],
    "wof:name":"Carver Collections",
    "wof:placetype":"venue"
},
  "geometry": {"coordinates":[-84.208207,35.861755],"type":"Point"}
}