{
  "type": "Feature",
  "properties": {
    "addr:full":"7455 E Andrew Johnson Hwy Chuckey TN 37641",
    "addr:housenumber":"7455",
    "addr:postcode":"37641",
    "addr:street":"E Andrew Johnson Hwy",
    "iso:country":"US",
    "sg:address":"7455 E Andrew Johnson Hwy",
    "sg:city":"Chuckey",
    "sg:classifiers":[
        {
            "category":"Retail",
            "subcategory":"Auto Rental",
            "type":"Services"
        }
    ],
    "sg:phone":"+1 423 257 8941",
    "sg:postcode":"37641",
    "sg:province":"TN",
    "sg:tags":[
        "renting",
        "truck",
        "leasing"
    ],
    "wof:name":"U-Haul Co",
    "wof:placetype":"venue"
},
  "geometry": {"coordinates":[-82.71184599999999,36.212204],"type":"Point"}
}