{
  "type": "Feature",
  "properties": {
    "iso:country":"US",
    "sg:address":"1236 Northgate Business Pkwy",
    "sg:city":"Madison",
    "sg:classifiers":[
        {
            "category":"Personal",
            "subcategory":"Beauty Salon",
            "type":"Services"
        }
    ],
    "sg:phone":"+1 615 612 1605",
    "sg:postcode":"37115",
    "sg:province":"TN",
    "sg:tags":[
        "shop"
    ],
    "wof:name":"Frizzells Salon & Spa",
    "wof:placetype":"venue"
},
  "geometry": {"coordinates":[-86.689682,36.285631],"type":"Point"}
}