{
  "type": "Feature",
  "properties": {
    "addr:full":"5205 Tennessee Ave Nashville TN 37209",
    "addr:housenumber":"5205",
    "addr:postcode":"37209",
    "addr:street":"Tennessee Ave",
    "iso:country":"US",
    "sg:address":"5205 Tennessee Ave",
    "sg:city":"Nashville",
    "sg:classifiers":[
        {
            "category":"Wholesale",
            "subcategory":"Construction Materials",
            "type":"Manufacturing & Wholesale Goods"
        }
    ],
    "sg:phone":"+1 615 292 0404",
    "sg:postcode":"37209",
    "sg:province":"TN",
    "wof:name":"Tuff Coat Pavement Maintenance",
    "wof:placetype":"venue"
},
  "geometry": {"coordinates":[-86.85178000000001,36.160824],"type":"Point"}
}