{
  "type": "Feature",
  "properties": {
    "addr:full":"3655 N Chapel Rd Franklin TN 37067",
    "addr:housenumber":"3655",
    "addr:postcode":"37067",
    "addr:street":"N Chapel Rd",
    "iso:country":"US",
    "sg:address":"3655 N Chapel Rd",
    "sg:city":"Franklin",
    "sg:classifiers":[
        {
            "category":"Professional",
            "subcategory":"Business Services",
            "type":"Services"
        }
    ],
    "sg:phone":"+1 615 790 8512",
    "sg:postcode":"37067",
    "sg:province":"TN",
    "wof:name":"Btl Enterprises",
    "wof:placetype":"venue"
},
  "geometry": {"coordinates":[-86.769401,35.902084],"type":"Point"}
}