{
  "type": "Feature",
  "properties": {
    "iso:country":"US",
    "sg:address":"1816 Hamill Rd",
    "sg:city":"Hixson",
    "sg:classifiers":[
        {
            "category":"Health Services",
            "subcategory":"Clinic",
            "type":"Services"
        }
    ],
    "sg:phone":"+1 423 875 0020",
    "sg:postcode":"37343",
    "sg:province":"TN",
    "sg:tags":[
        "kidney",
        "dialysis",
        "center"
    ],
    "wof:name":"Dialysis Clinic Inc",
    "wof:placetype":"venue"
},
  "geometry": {"coordinates":[-85.24304600000001,35.121494],"type":"Point"}
}