{
  "type": "Feature",
  "properties": {
    "iso:country":"US",
    "sg:address":"45 Vaughns Gap Rd",
    "sg:city":"Nashville",
    "sg:classifiers":[
        {
            "category":"Professional",
            "type":"Services"
        }
    ],
    "sg:phone":"+1 615 354 9142",
    "sg:postcode":"37205",
    "sg:province":"TN",
    "wof:name":"Duct Doctor of TN LLC",
    "wof:placetype":"venue"
},
  "geometry": {"coordinates":[-86.885626,36.084378],"type":"Point"}
}