{
  "type": "Feature",
  "properties": {
    "iso:country":"US",
    "sg:address":"2000 Church St",
    "sg:city":"Nashville",
    "sg:classifiers":[
        {
            "category":"Health Services",
            "subcategory":"Clinic",
            "type":"Services"
        }
    ],
    "sg:phone":"+1 615 284 6348",
    "sg:postcode":"37203",
    "sg:province":"TN",
    "sg:tags":[
        "physician",
        "surgeon",
        "bureau",
        "information"
    ],
    "sg:website":"www.baptisthospital.com",
    "wof:name":"Carefinders Physician Referral",
    "wof:placetype":"venue"
},
  "geometry": {"coordinates":[-86.802683,36.152429],"type":"Point"}
}