{
  "type": "Feature",
  "properties": {
    "addr:full":"230 Great Circle Rd Nashville TN 37228",
    "addr:housenumber":"230",
    "addr:postcode":"37228",
    "addr:street":"Great Circle Rd",
    "iso:country":"US",
    "sg:address":"230 Great Circle Rd",
    "sg:city":"Nashville",
    "sg:classifiers":[
        {
            "category":"Wholesale",
            "subcategory":"Hardware",
            "type":"Manufacturing & Wholesale Goods"
        }
    ],
    "sg:phone":"+1 615 256 6529",
    "sg:postcode":"37228",
    "sg:province":"TN",
    "sg:tags":[
        "ice",
        "freezer",
        "cream"
    ],
    "wof:name":"Fortune Equipment Co Of Nshvll",
    "wof:placetype":"venue"
},
  "geometry": {"coordinates":[-86.793538,36.197772],"type":"Point"}
}