{
  "type": "Feature",
  "properties": {
    "iso:country":"US",
    "sg:address":"515 James Robertson Pkwy",
    "sg:city":"Nashville",
    "sg:classifiers":[
        {
            "category":"Building & Trades",
            "subcategory":"Plumbing",
            "type":"Services"
        }
    ],
    "sg:phone":"+1 615 242 3927",
    "sg:postcode":"37219",
    "sg:province":"TN",
    "sg:tags":[
        "grocery",
        "contractor"
    ],
    "wof:name":"Capitol Refrigeration",
    "wof:placetype":"venue"
},
  "geometry": {"coordinates":[-86.784977,36.168455],"type":"Point"}
}