{
  "type": "Feature",
  "properties": {
    "iso:country":"US",
    "sg:address":"101 Jefferson Ave",
    "sg:city":"Oak Ridge",
    "sg:classifiers":[
        {
            "category":"Sports & Exercise",
            "subcategory":"Gym",
            "type":"Entertainment"
        }
    ],
    "sg:phone":"+1 865 483 5561",
    "sg:postcode":"37830",
    "sg:province":"TN",
    "sg:tags":[
        "club",
        "health",
        "studio",
        "gymnasium"
    ],
    "wof:name":"Lifter's Club",
    "wof:placetype":"venue"
},
  "geometry": {"coordinates":[-84.282246,36.008969],"type":"Point"}
}