{
  "type": "Feature",
  "properties": {
    "iso:country":"US",
    "sg:address":"2202 Jefferson Ct",
    "sg:city":"Franklin",
    "sg:classifiers":[
        {
            "category":"Professional",
            "type":"Services"
        }
    ],
    "sg:phone":"+1 615 794 6811",
    "sg:postcode":"37064",
    "sg:province":"TN",
    "wof:name":"Cookeville-Slm LLC",
    "wof:placetype":"venue"
},
  "geometry": {"coordinates":[-86.86837199999999,35.875109],"type":"Point"}
}