{
  "type": "Feature",
  "properties": {
    "addr:full":"6709 Albunda Dr NW Knoxville TN 37919",
    "addr:housenumber":"6709",
    "addr:postcode":"37919",
    "addr:street":"Albunda Dr Nw",
    "iso:country":"US",
    "sg:address":"6709 Albunda Dr NW",
    "sg:city":"Knoxville",
    "sg:classifiers":[
        {
            "category":"Retail",
            "subcategory":"Auto Repair",
            "type":"Services"
        }
    ],
    "sg:phone":"+1 865 588 6529",
    "sg:postcode":"37919",
    "sg:province":"TN",
    "sg:tags":[
        "automobile",
        "lubrication"
    ],
    "wof:name":"Kwikoil Drive Thru Oil Change",
    "wof:placetype":"venue"
},
  "geometry": {"coordinates":[-84.014951,35.930544],"type":"Point"}
}