{
  "type": "Feature",
  "properties": {
    "addr:full":"5315 N Broadway St Knoxville TN 37918",
    "addr:housenumber":"5315",
    "addr:postcode":"37918",
    "addr:street":"N Broadway St",
    "iso:country":"US",
    "sg:address":"5315 N Broadway St",
    "sg:city":"Knoxville",
    "sg:classifiers":[
        {
            "category":"Health Services",
            "subcategory":"Optometrist",
            "type":"Services"
        }
    ],
    "sg:phone":"+1 865 689 3333",
    "sg:postcode":"37918",
    "sg:province":"TN",
    "sg:tags":[
        "optical",
        "good"
    ],
    "wof:name":"Phillip Jarmon Od",
    "wof:placetype":"venue"
},
  "geometry": {"coordinates":[-83.932446,36.035613],"type":"Point"}
}