{
  "type": "Feature",
  "properties": {
    "addr:full":"3256 Yates St Memphis TN 38134",
    "addr:housenumber":"3256",
    "addr:postcode":"38134",
    "addr:street":"Yates St",
    "iso:country":"US",
    "sg:address":"3256 Yates St",
    "sg:city":"Memphis",
    "sg:classifiers":[
        {
            "category":"Shopping",
            "subcategory":"Hobbies, Toys, & Games",
            "type":"Retail Goods"
        }
    ],
    "sg:phone":"+1 901 386 6072",
    "sg:postcode":"38134",
    "sg:province":"TN",
    "wof:name":"Adorables",
    "wof:placetype":"venue"
},
  "geometry": {"coordinates":[-89.876936,35.214303],"type":"Point"}
}