{
  "type": "Feature",
  "properties": {
    "iso:country":"US",
    "sg:address":"300 Moore St",
    "sg:city":"Bristol",
    "sg:classifiers":[
        {
            "category":"Health Services",
            "subcategory":"Chiropractor",
            "type":"Services"
        }
    ],
    "sg:phone":"+1 276 591 5448",
    "sg:postcode":"24201",
    "sg:province":"TN",
    "wof:name":"Muncy Family Chiropractic",
    "wof:placetype":"venue"
},
  "geometry": {"coordinates":[-82.18183500000001,36.59908],"type":"Point"}
}