{
  "type": "Feature",
  "properties": {
    "iso:country":"US",
    "sg:address":"4522 Blue Springs Pkwy",
    "sg:city":"Greeneville",
    "sg:classifiers":[
        {
            "category":"Building & Trades",
            "subcategory":"Construction",
            "type":"Services"
        }
    ],
    "sg:phone":"+1 423 639 6691",
    "sg:postcode":"37743",
    "sg:province":"TN",
    "sg:tags":[
        "millwright"
    ],
    "wof:name":"Team Millwright & Maintenance",
    "wof:placetype":"venue"
},
  "geometry": {"coordinates":[-82.92703899999999,36.19094],"type":"Point"}
}