{
  "type": "Feature",
  "properties": {
    "addr:full":"218 Poor Valley Rd Rogersville TN 37857",
    "addr:housenumber":"218",
    "addr:postcode":"37857",
    "addr:street":"Poor Valley Rd",
    "iso:country":"US",
    "sg:address":"218 Poor Valley Rd",
    "sg:city":"Rogersville",
    "sg:classifiers":[
        {
            "category":"Building & Trades",
            "subcategory":"Construction",
            "type":"Services"
        }
    ],
    "sg:phone":"+1 423 921 9371",
    "sg:postcode":"37857",
    "sg:province":"TN",
    "sg:tags":[
        "carpenter"
    ],
    "wof:name":"Steve's Carpentry Work",
    "wof:placetype":"venue"
},
  "geometry": {"coordinates":[-83.029718,36.491676],"type":"Point"}
}