{
  "type": "Feature",
  "properties": {
    "iso:country":"US",
    "sg:address":"1702 Fairview Rd",
    "sg:city":"Tellico Plains",
    "sg:classifiers":[
        {
            "category":"Professional",
            "type":"Services"
        }
    ],
    "sg:phone":"+1 423 253 7417",
    "sg:postcode":"37385",
    "sg:province":"TN",
    "wof:name":"Jackson Odell Jr",
    "wof:placetype":"venue"
},
  "geometry": {"coordinates":[-84.283502,35.435038],"type":"Point"}
}