{
  "type": "Feature",
  "properties": {
    "addr:full":"481 Bakertown Rd Antioch TN 37013",
    "addr:housenumber":"481",
    "addr:postcode":"37013",
    "addr:street":"Bakertown Rd",
    "iso:country":"US",
    "sg:address":"481 Bakertown Rd",
    "sg:city":"Antioch",
    "sg:classifiers":[
        {
            "category":"Autos & Motor Vehicles",
            "subcategory":"Auto Supplies",
            "type":"Retail Goods"
        }
    ],
    "sg:phone":"+1 615 423 4610",
    "sg:postcode":"37013",
    "sg:province":"TN",
    "sg:tags":[
        "automobile",
        "parts"
    ],
    "wof:name":"Solomax Auto Exports & Parts",
    "wof:placetype":"venue"
},
  "geometry": {"coordinates":[-86.689688,36.073374],"type":"Point"}
}