{
  "type": "Feature",
  "properties": {
    "iso:country":"US",
    "sg:address":"2560 Parkway",
    "sg:city":"Pigeon Forge",
    "sg:classifiers":[
        {
            "category":"Restaurant",
            "type":"Food & Drink"
        }
    ],
    "sg:phone":"+1 865 453 2615",
    "sg:postcode":"37863",
    "sg:province":"TN",
    "wof:name":"SCS Restaurants Inc",
    "wof:placetype":"venue"
},
  "geometry": {"coordinates":[-83.576386,35.805326],"type":"Point"}
}