{
  "type": "Feature",
  "properties": {
    "iso:country":"US",
    "sg:address":"840 Hickory Grove Loop",
    "sg:city":"Oakland",
    "sg:classifiers":[
        {
            "category":"Professional",
            "subcategory":"Business Services",
            "type":"Services"
        }
    ],
    "sg:phone":"+1 901 466 0224",
    "sg:postcode":"38060",
    "sg:province":"TN",
    "wof:name":"Cdcrn",
    "wof:placetype":"venue"
},
  "geometry": {"coordinates":[-89.439436,35.215382],"type":"Point"}
}