{
  "type": "Feature",
  "properties": {
    "iso:country":"US",
    "sg:address":"5195 Winchester Rd",
    "sg:city":"Memphis",
    "sg:classifiers":[
        {
            "category":"Shopping",
            "subcategory":"Computers & Home Electronics",
            "type":"Retail Goods"
        }
    ],
    "sg:phone":"+1 901 365 4914",
    "sg:postcode":"38118",
    "sg:province":"TN",
    "sg:tags":[
        "high",
        "fidelity",
        "stereophonic"
    ],
    "sg:website":"www.autoradio1.com",
    "wof:name":"Auto Radio",
    "wof:placetype":"venue"
},
  "geometry": {"coordinates":[-89.890612,35.050568],"type":"Point"}
}