{
  "type": "Feature",
  "properties": {
    "addr:full":"1226 7th Ave N Nashville TN 37208",
    "addr:housenumber":"1226",
    "addr:postcode":"37208",
    "addr:street":"7Th Ave N",
    "iso:country":"US",
    "sg:address":"1226 7th Ave N",
    "sg:city":"Nashville",
    "sg:classifiers":[
        {
            "category":"Social Services",
            "type":"Services"
        }
    ],
    "sg:phone":"+1 615 242 1554",
    "sg:postcode":"37208",
    "sg:province":"TN",
    "sg:tags":[
        "organization",
        "welfare"
    ],
    "wof:name":"North Nashville Outreach",
    "wof:placetype":"venue"
},
  "geometry": {"coordinates":[-86.791172,36.175344],"type":"Point"}
}