{
  "type": "Feature",
  "properties": {
    "addr:full":"1661 International Dr Memphis TN 38120",
    "addr:housenumber":"1661",
    "addr:postcode":"38120",
    "addr:street":"International Dr",
    "iso:country":"US",
    "sg:address":"1661 International Dr",
    "sg:city":"Memphis",
    "sg:classifiers":[
        {
            "category":"Banks & Credit Unions",
            "subcategory":"Bank",
            "type":"Services"
        }
    ],
    "sg:phone":"+1 901 818 3106",
    "sg:postcode":"38120",
    "sg:province":"TN",
    "sg:tags":[
        "loan",
        "real estate"
    ],
    "wof:name":"Long Beach Mortgage",
    "wof:placetype":"venue"
},
  "geometry": {"coordinates":[-89.848375,35.10395],"type":"Point"}
}