{
  "type": "Feature",
  "properties": {
    "iso:country":"US",
    "sg:address":"200 Paragon Mills Rd",
    "sg:city":"Nashville",
    "sg:classifiers":[
        {
            "category":"Real Estate",
            "subcategory":"Real Estate Agent",
            "type":"Services"
        }
    ],
    "sg:phone":"+1 615 834 1380",
    "sg:postcode":"37211",
    "sg:province":"TN",
    "sg:tags":[
        "management"
    ],
    "wof:name":"Prestige Pointe Apartments",
    "wof:placetype":"venue"
},
  "geometry": {"coordinates":[-86.701674,36.086387],"type":"Point"}
}