{
  "type": "Feature",
  "properties": {
    "iso:country":"US",
    "sg:address":"3865 Jernigan Rd",
    "sg:city":"White House",
    "sg:classifiers":[
        {
            "category":"Freight",
            "type":"Transportation"
        }
    ],
    "sg:phone":"+1 615 654 0509",
    "sg:postcode":"37188",
    "sg:province":"TN",
    "sg:tags":[
        "operator",
        "local",
        "trucking"
    ],
    "wof:name":"Justice Trucking",
    "wof:placetype":"venue"
},
  "geometry": {"coordinates":[-86.68074,36.513162],"type":"Point"}
}