{
  "type": "Feature",
  "properties": {
    "iso:country":"US",
    "sg:address":"2551 Reese Point Dr",
    "sg:city":"Memphis",
    "sg:classifiers":[
        {
            "category":"Insurance",
            "subcategory":"Hazard Insurance",
            "type":"Services"
        }
    ],
    "sg:phone":"+1 901 921 3537",
    "sg:postcode":"38133",
    "sg:province":"TN",
    "sg:tags":[
        "commercial",
        "business"
    ],
    "wof:name":"Direct Insurance",
    "wof:placetype":"venue"
},
  "geometry": {"coordinates":[-89.827782,35.195518],"type":"Point"}
}