{
  "type": "Feature",
  "properties": {
    "addr:full":"925 Main St Jasper TN 37347",
    "addr:housenumber":"925",
    "addr:postcode":"37347",
    "addr:street":"Main St",
    "iso:country":"US",
    "sg:address":"925 Main St",
    "sg:city":"Jasper",
    "sg:classifiers":[
        {
            "category":"Government",
            "subcategory":"Fire Station",
            "type":"Public Place"
        }
    ],
    "sg:phone":"+1 423 837 0111",
    "sg:postcode":"37347",
    "sg:province":"TN",
    "sg:tags":[
        "department"
    ],
    "wof:name":"Kimball Volunteer Fire Department",
    "wof:placetype":"venue"
},
  "geometry": {"coordinates":[-85.630527,35.073679],"type":"Point"}
}