{
  "type": "Feature",
  "properties": {
    "iso:country":"US",
    "sg:address":"49 Lindsey Marie Ln",
    "sg:city":"Munford",
    "sg:classifiers":[
        {
            "category":"Professional",
            "subcategory":"Art Services",
            "type":"Services"
        }
    ],
    "sg:phone":"+1 901 837 1989",
    "sg:postcode":"38058",
    "sg:province":"TN",
    "sg:tags":[
        "commercial",
        "design"
    ],
    "wof:name":"C B F Graphics & Design",
    "wof:placetype":"venue"
},
  "geometry": {"coordinates":[-89.81837400000001,35.458661],"type":"Point"}
}