{
  "type": "Feature",
  "properties": {
    "iso:country":"US",
    "sg:address":"514 Kraft St",
    "sg:city":"Clarksville",
    "sg:classifiers":[
        {
            "category":"Retail",
            "subcategory":"Repair Shop",
            "type":"Services"
        }
    ],
    "sg:phone":"+1 931 647 8708",
    "sg:postcode":"37040",
    "sg:province":"TN",
    "sg:tags":[
        "lock",
        "locksmith"
    ],
    "sg:website":"www.gloverslock.com",
    "wof:name":"Glover's Lock Svc",
    "wof:placetype":"venue"
},
  "geometry": {"coordinates":[-87.356871,36.541878],"type":"Point"}
}