{
  "type": "Feature",
  "properties": {
    "addr:full":"3604 Woodlawn School Rd Knoxville TN 37920",
    "addr:housenumber":"3604",
    "addr:postcode":"37920",
    "addr:street":"Woodlawn School Rd",
    "iso:country":"US",
    "sg:address":"3604 Woodlawn School Rd",
    "sg:city":"Knoxville",
    "sg:classifiers":[
        {
            "category":"Professional",
            "subcategory":"Lawyer & Legal Services",
            "type":"Services"
        }
    ],
    "sg:phone":"+1 865 573 7070",
    "sg:postcode":"37920",
    "sg:province":"TN",
    "wof:name":"Wayne K Houser Jr",
    "wof:placetype":"venue"
},
  "geometry": {"coordinates":[-83.716908,35.950275],"type":"Point"}
}