{
  "type": "Feature",
  "properties": {
    "iso:country":"US",
    "sg:address":"3810 Kings Ln",
    "sg:city":"Nashville",
    "sg:classifiers":[
        {
            "category":"Social Services",
            "subcategory":"Child Care",
            "type":"Services"
        }
    ],
    "sg:phone":"+1 615 876 4086",
    "sg:postcode":"37218",
    "sg:province":"TN",
    "sg:tags":[
        "day"
    ],
    "wof:name":"Temple Acamdemy Pre Sch",
    "wof:placetype":"venue"
},
  "geometry": {"coordinates":[-86.84443899999999,36.217827],"type":"Point"}
}