{
  "type": "Feature",
  "properties": {
    "iso:country":"US",
    "sg:address":"252 Poplar Ave",
    "sg:city":"Memphis",
    "sg:classifiers":[
        {
            "category":"Banks & Credit Unions",
            "subcategory":"Bank",
            "type":"Services"
        }
    ],
    "sg:phone":"+1 901 745 2274",
    "sg:postcode":"38103",
    "sg:province":"TN",
    "sg:tags":[
        "loan"
    ],
    "wof:name":"Golden Title Loans & Cash Adv",
    "wof:placetype":"venue"
},
  "geometry": {"coordinates":[-90.047938,35.149477],"type":"Point"}
}