{
  "type": "Feature",
  "properties": {
    "addr:full":"701 Royal Oaks Dr Columbia TN 38401",
    "addr:housenumber":"701",
    "addr:postcode":"38401",
    "addr:street":"Royal Oaks Dr",
    "iso:country":"US",
    "sg:address":"701 Royal Oaks Dr",
    "sg:city":"Columbia",
    "sg:classifiers":[
        {
            "category":"Professional",
            "subcategory":"Art Services",
            "type":"Services"
        }
    ],
    "sg:phone":"+1 931 388 0616",
    "sg:postcode":"38401",
    "sg:province":"TN",
    "sg:tags":[
        "photographer"
    ],
    "wof:name":"J M Graphical Studios & Photo",
    "wof:placetype":"venue"
},
  "geometry": {"coordinates":[-87.045548,35.638203],"type":"Point"}
}