{
  "type": "Feature",
  "properties": {
    "iso:country":"US",
    "sg:address":"310 Main St",
    "sg:city":"Williamsburg",
    "sg:classifiers":[
        {
            "category":"Government",
            "subcategory":"Court House",
            "type":"Public Place"
        }
    ],
    "sg:phone":"+1 606 549 6005",
    "sg:postcode":"40769",
    "sg:province":"TN",
    "sg:tags":[
        "county",
        "counsel"
    ],
    "wof:name":"Whitley County Attorney",
    "wof:placetype":"venue"
},
  "geometry": {"coordinates":[-84.160009,36.742762],"type":"Point"}
}