{
  "type": "Feature",
  "properties": {
    "addr:full":"1676 Farmington Dr Cookeville TN 38501",
    "addr:housenumber":"1676",
    "addr:postcode":"38501",
    "addr:street":"Farmington Dr",
    "iso:country":"US",
    "sg:address":"1676 Farmington Dr",
    "sg:city":"Cookeville",
    "sg:classifiers":[
        {
            "category":"Retail",
            "subcategory":"Laundry & Dry Cleaning",
            "type":"Services"
        }
    ],
    "sg:phone":"+1 931 544 7753",
    "sg:postcode":"38501",
    "sg:province":"TN",
    "sg:tags":[
        "cleaners",
        "rug",
        "carpet"
    ],
    "wof:name":"Carl's Carpet Cleaning",
    "wof:placetype":"venue"
},
  "geometry": {"coordinates":[-85.529906,36.193359],"type":"Point"}
}