{
  "type": "Feature",
  "properties": {
    "addr:full":"309 Hillview Dr Sparta TN 38583",
    "addr:housenumber":"309",
    "addr:postcode":"38583",
    "addr:street":"Hillview Dr",
    "iso:country":"US",
    "sg:address":"309 Hillview Dr",
    "sg:city":"Sparta",
    "sg:classifiers":[
        {
            "category":"Farming",
            "subcategory":"Nursery",
            "type":"Manufacturing & Wholesale Goods"
        }
    ],
    "sg:phone":"+1 931 836 2443",
    "sg:postcode":"38583",
    "sg:province":"TN",
    "sg:tags":[
        "ornamental"
    ],
    "wof:name":"Thumbs Up Nursery",
    "wof:placetype":"venue"
},
  "geometry": {"coordinates":[-85.459306,35.916411],"type":"Point"}
}