{
  "type": "Feature",
  "properties": {
    "addr:full":"6909 Maynardville Pike Knoxville TN 37918",
    "addr:housenumber":"6909",
    "addr:postcode":"37918",
    "addr:street":"Maynardville Pike",
    "iso:country":"US",
    "sg:address":"6909 Maynardville Pike",
    "sg:city":"Knoxville",
    "sg:classifiers":[
        {
            "category":"Recreation",
            "type":"Entertainment"
        }
    ],
    "sg:phone":"+1 865 922 0612",
    "sg:postcode":"37918",
    "sg:province":"TN",
    "sg:tags":[
        "parlor",
        "billiard"
    ],
    "wof:name":"Black Oak Billiards",
    "wof:placetype":"venue"
},
  "geometry": {"coordinates":[-83.927514,36.071422],"type":"Point"}
}