{
  "type": "Feature",
  "properties": {
    "iso:country":"US",
    "sg:address":"123 Country Club Rd",
    "sg:city":"Niota",
    "sg:classifiers":[
        {
            "category":"Organizations",
            "subcategory":"Community Association",
            "type":"Services"
        }
    ],
    "sg:phone":"+1 423 337 6463",
    "sg:postcode":"37826",
    "sg:province":"TN",
    "sg:tags":[
        "club"
    ],
    "wof:name":"Springbrook Golf & Country Clb",
    "wof:placetype":"venue"
},
  "geometry": {"coordinates":[-84.559226,35.517484],"type":"Point"}
}