{
  "type": "Feature",
  "properties": {
    "iso:country":"US",
    "sg:address":"403 Laurel Ln",
    "sg:city":"Lookout Mountain",
    "sg:classifiers":[
        {
            "category":"Retail",
            "subcategory":"Portrait Studio",
            "type":"Services"
        }
    ],
    "sg:phone":"+1 423 821 0516",
    "sg:postcode":"37350",
    "sg:province":"TN",
    "sg:tags":[
        "photographer"
    ],
    "wof:name":"Westcliffe Studio Inc",
    "wof:placetype":"venue"
},
  "geometry": {"coordinates":[-85.351382,35.000837],"type":"Point"}
}