{
  "type": "Feature",
  "properties": {
    "iso:country":"US",
    "sg:address":"5010 Linbar Dr",
    "sg:city":"Nashville",
    "sg:classifiers":[
        {
            "category":"Building & Trades",
            "subcategory":"Construction",
            "type":"Services"
        }
    ],
    "sg:phone":"+1 615 256 4040",
    "sg:postcode":"37211",
    "sg:province":"TN",
    "sg:tags":[
        "siding",
        "contractor"
    ],
    "wof:name":"Remodel America",
    "wof:placetype":"venue"
},
  "geometry": {"coordinates":[-86.701973,36.08223],"type":"Point"}
}