{
  "type": "Feature",
  "properties": {
    "addr:full":"123 Clinch Dr Columbia TN 38401",
    "addr:housenumber":"123",
    "addr:postcode":"38401",
    "addr:street":"Clinch Dr",
    "iso:country":"US",
    "sg:address":"123 Clinch Dr",
    "sg:city":"Columbia",
    "sg:classifiers":[
        {
            "category":"Organizations",
            "subcategory":"Religious Organization",
            "type":"Services"
        }
    ],
    "sg:phone":"+1 931 388 8156",
    "sg:postcode":"38401",
    "sg:province":"TN",
    "sg:tags":[
        "church"
    ],
    "wof:name":"Macedonia Church Of Christ",
    "wof:placetype":"venue"
},
  "geometry": {"coordinates":[-87.04750300000001,35.624452],"type":"Point"}
}