{
  "type": "Feature",
  "properties": {
    "addr:full":"104 Woodmont Blvd. Suite 203 Nashville TN 37205",
    "addr:housenumber":"104",
    "addr:postcode":"37205",
    "addr:street":"Woodmont Blvd. Suite 203",
    "iso:country":"US",
    "sg:address":"104 Woodmont Blvd. Suite 203",
    "sg:city":"Nashville",
    "sg:classifiers":[
        {
            "category":"Professional",
            "subcategory":"Computer Services",
            "type":"Services"
        }
    ],
    "sg:phone":"+1 615 403 1297",
    "sg:postcode":"37205",
    "sg:province":"TN",
    "sg:tags":[
        "child-safety",
        "amber-alert",
        "parenting",
        "parent-resource"
    ],
    "sg:website":"http://instantamber.com",
    "wof:name":"InstantAmber",
    "wof:placetype":"venue"
},
  "geometry": {"coordinates":[-86.844703,36.121995],"type":"Point"}
}