{
  "type": "Feature",
  "properties": {
    "iso:country":"US",
    "sg:address":"2005 Forrest St",
    "sg:city":"Dyersburg",
    "sg:classifiers":[
        {
            "category":"Manufacturing",
            "subcategory":"Motor Vehicles & Parts",
            "type":"Manufacturing & Wholesale Goods"
        }
    ],
    "sg:phone":"+1 731 285 3310",
    "sg:postcode":"38024",
    "sg:province":"TN",
    "sg:tags":[
        "auto",
        "mfg",
        "system",
        "exhaust"
    ],
    "sg:website":"www.hecomfg.com",
    "wof:name":"Heckethorn Manufacturing Co",
    "wof:placetype":"venue"
},
  "geometry": {"coordinates":[-89.41422300000001,36.035413],"type":"Point"}
}