{
  "type": "Feature",
  "properties": {
    "addr:full":"85 Highland Rd Mc Minnville TN 37110",
    "addr:housenumber":"85",
    "addr:postcode":"37110",
    "addr:street":"Highland Rd",
    "iso:country":"US",
    "sg:address":"85 Highland Rd",
    "sg:city":"Mc Minnville",
    "sg:classifiers":[
        {
            "category":"Manufacturing",
            "subcategory":"Tools & Machinery",
            "type":"Manufacturing & Wholesale Goods"
        }
    ],
    "sg:phone":"+1 931 668 3186",
    "sg:postcode":"37110",
    "sg:province":"TN",
    "sg:tags":[
        "metalworking",
        "mfg"
    ],
    "wof:name":"HI Land Machinist Company",
    "wof:placetype":"venue"
},
  "geometry": {"coordinates":[-85.770622,35.758459],"type":"Point"}
}