{
  "type": "Feature",
  "properties": {
    "iso:country":"US",
    "sg:address":"9310 Apison Pike",
    "sg:city":"Ooltewah",
    "sg:classifiers":[
        {
            "category":"Health Services",
            "subcategory":"Doctor",
            "type":"Services"
        }
    ],
    "sg:phone":"+1 423 338 7777",
    "sg:postcode":"37315",
    "sg:province":"TN",
    "sg:tags":[
        "dentist"
    ],
    "wof:name":"Southern Hospitality",
    "wof:placetype":"venue"
},
  "geometry": {"coordinates":[-85.071702,35.061639],"type":"Point"}
}