{
  "type": "Feature",
  "properties": {
    "iso:country":"US",
    "sg:address":"199 Smith Rd",
    "sg:city":"Sparta",
    "sg:classifiers":[
        {
            "category":"Organizations",
            "subcategory":"Community Association",
            "type":"Services"
        }
    ],
    "sg:phone":"+1 931 935 2708",
    "sg:postcode":"38583",
    "sg:province":"TN",
    "sg:tags":[
        "club"
    ],
    "wof:name":"Watering Hole Bar & Carry Out",
    "wof:placetype":"venue"
},
  "geometry": {"coordinates":[-85.245726,35.888392],"type":"Point"}
}