{
  "type": "Feature",
  "properties": {
    "addr:full":"1180 Cumberland Dr Clarksville TN 37040",
    "addr:housenumber":"1180",
    "addr:postcode":"37040",
    "addr:street":"Cumberland Dr",
    "iso:country":"US",
    "sg:address":"1180 Cumberland Dr",
    "sg:city":"Clarksville",
    "sg:classifiers":[
        {
            "category":"Organizations",
            "subcategory":"Community Association",
            "type":"Services"
        }
    ],
    "sg:phone":"+1 931 552 4681",
    "sg:postcode":"37040",
    "sg:province":"TN",
    "sg:tags":[
        "club"
    ],
    "wof:name":"Clarksville Jaycees",
    "wof:placetype":"venue"
},
  "geometry": {"coordinates":[-87.369962,36.503826],"type":"Point"}
}