{
  "type": "Feature",
  "properties": {
    "iso:country":"US",
    "sg:address":"2600 Little Bartons Creek Rd",
    "sg:city":"Cumberland Furn",
    "sg:classifiers":[
        {
            "category":"Home & Garden",
            "subcategory":"Hardware",
            "type":"Retail Goods"
        }
    ],
    "sg:phone":"+1 931 387 0029",
    "sg:postcode":"37051",
    "sg:province":"TN",
    "wof:name":"Parker Home Hardware",
    "wof:placetype":"venue"
},
  "geometry": {"coordinates":[-87.375525,36.320646],"type":"Point"}
}