{
  "type": "Feature",
  "properties": {
    "iso:country":"US",
    "sg:address":"294 W Old Andrew Johnson Hwy",
    "sg:city":"Jefferson City",
    "sg:classifiers":[
        {
            "category":"Restaurant",
            "type":"Food & Drink"
        }
    ],
    "sg:phone":"+1 865 475 3791",
    "sg:postcode":"37760",
    "sg:province":"TN",
    "sg:tags":[
        "eating"
    ],
    "wof:name":"Cook House",
    "wof:placetype":"venue"
},
  "geometry": {"coordinates":[-83.504876,36.119324],"type":"Point"}
}