{
  "type": "Feature",
  "properties": {
    "iso:country":"US",
    "sg:address":"620 Trebor Dr",
    "sg:city":"Goodlettsville",
    "sg:classifiers":[
        {
            "category":"Building & Trades",
            "subcategory":"Landscaping Services",
            "type":"Services"
        }
    ],
    "sg:phone":"+1 615 207 4600",
    "sg:postcode":"37072",
    "sg:province":"TN",
    "sg:tags":[
        "lawn",
        "maintenance",
        "grounds"
    ],
    "wof:name":"In His Name Lawncare",
    "wof:placetype":"venue"
},
  "geometry": {"coordinates":[-86.738106,36.285662],"type":"Point"}
}