{
  "type": "Feature",
  "properties": {
    "iso:country":"US",
    "sg:address":"6010 Macon Cv",
    "sg:city":"Memphis",
    "sg:classifiers":[
        {
            "category":"Travel",
            "subcategory":"Hotels & Motels",
            "type":"Entertainment"
        },
        {
            "category":"Retail",
            "subcategory":"Event Space",
            "type":"Services"
        }
    ],
    "sg:phone":"+1 901 384 0010",
    "sg:postcode":"38134",
    "sg:province":"TN",
    "sg:tags":[
        "facility",
        "meeting",
        "hall",
        "planning",
        "reception",
        "lodging",
        "corporate",
        "banquet"
    ],
    "sg:website":"http://www.fairfieldinn.com",
    "wof:name":"Fairfield Inn",
    "wof:placetype":"venue"
},
  "geometry": {"coordinates":[-89.86635699999999,35.162893],"type":"Point"}
}