{
  "type": "Feature",
  "properties": {
    "addr:full":"1718 Lively Rd Maryville TN 37801",
    "addr:housenumber":"1718",
    "addr:postcode":"37801",
    "addr:street":"Lively Rd",
    "iso:country":"US",
    "sg:address":"1718 Lively Rd",
    "sg:city":"Maryville",
    "sg:classifiers":[
        {
            "category":"Building & Trades",
            "subcategory":"Construction",
            "type":"Services"
        }
    ],
    "sg:phone":"+1 865 983 2910",
    "sg:postcode":"37801",
    "sg:province":"TN",
    "sg:tags":[
        "electrical",
        "contractor"
    ],
    "wof:name":"Nanney Sign & Crane Services",
    "wof:placetype":"venue"
},
  "geometry": {"coordinates":[-84.014734,35.779331],"type":"Point"}
}