{
  "type": "Feature",
  "properties": {
    "iso:country":"US",
    "sg:address":"7721 US Hwy 64",
    "sg:city":"Memphis",
    "sg:classifiers":[
        {
            "category":"Wholesale",
            "subcategory":"Machinery & Supplies",
            "type":"Manufacturing & Wholesale Goods"
        }
    ],
    "sg:phone":"+1 901 377 3392",
    "sg:postcode":"38133",
    "sg:province":"TN",
    "sg:tags":[
        "bearing"
    ],
    "wof:name":"J & M Supply Radial Ball Co",
    "wof:placetype":"venue"
},
  "geometry": {"coordinates":[-89.80512400000001,35.204624],"type":"Point"}
}