{
  "type": "Feature",
  "properties": {
    "iso:country":"US",
    "sg:address":"42 Federal Dr",
    "sg:city":"Jackson",
    "sg:classifiers":[
        {
            "category":"Personal",
            "subcategory":"Beauty Salon",
            "type":"Services"
        }
    ],
    "sg:phone":"+1 731 660 0247",
    "sg:postcode":"38305",
    "sg:province":"TN",
    "sg:tags":[
        "shop"
    ],
    "wof:name":"Appearances Hair & Nail Studio",
    "wof:placetype":"venue"
},
  "geometry": {"coordinates":[-88.834203,35.66796],"type":"Point"}
}