{
  "type": "Feature",
  "properties": {
    "iso:country":"US",
    "sg:address":"2629 N Hinton Rd",
    "sg:city":"Clarksville",
    "sg:classifiers":[
        {
            "category":"Building & Trades",
            "subcategory":"Construction",
            "type":"Services"
        }
    ],
    "sg:phone":"+1 931 551 4247",
    "sg:postcode":"37043",
    "sg:province":"TN",
    "sg:tags":[
        "woodworker"
    ],
    "wof:name":"Pens & More",
    "wof:placetype":"venue"
},
  "geometry": {"coordinates":[-87.213685,36.398075],"type":"Point"}
}