{
  "type": "Feature",
  "properties": {
    "addr:full":"872 Isabelle St Memphis TN 38122",
    "addr:housenumber":"872",
    "addr:postcode":"38122",
    "addr:street":"Isabelle St",
    "iso:country":"US",
    "sg:address":"872 Isabelle St",
    "sg:city":"Memphis",
    "sg:classifiers":[
        {
            "category":"Food & Beverages",
            "subcategory":"Groceries & Convenience Stores",
            "type":"Retail Goods"
        }
    ],
    "sg:phone":"+1 901 458 0351",
    "sg:postcode":"38122",
    "sg:province":"TN",
    "sg:tags":[
        "grocer"
    ],
    "wof:name":"Amco Mini Mart",
    "wof:placetype":"venue"
},
  "geometry": {"coordinates":[-89.935351,35.153749],"type":"Point"}
}