{
  "type": "Feature",
  "properties": {
    "addr:full":"214 2nd Ave N Nashville TN 37201",
    "addr:housenumber":"214",
    "addr:postcode":"37201",
    "addr:street":"2Nd Ave N",
    "iso:country":"US",
    "sg:address":"214 2nd Ave N",
    "sg:city":"Nashville",
    "sg:classifiers":[
        {
            "category":"Government",
            "subcategory":"Office",
            "type":"Public Place"
        }
    ],
    "sg:phone":"+1 615 862 6026",
    "sg:postcode":"37201",
    "sg:province":"TN",
    "sg:tags":[
        "state",
        "program"
    ],
    "wof:name":"Port Authority",
    "wof:placetype":"venue"
},
  "geometry": {"coordinates":[-86.776461,36.163931],"type":"Point"}
}