{
  "type": "Feature",
  "properties": {
    "iso:country":"US",
    "sg:address":"2121 Old Rock Island Rd",
    "sg:city":"Rock Island",
    "sg:classifiers":[
        {
            "category":"Education",
            "subcategory":"School",
            "type":"Public Place"
        }
    ],
    "sg:phone":"+1 931 686 2392",
    "sg:postcode":"38581",
    "sg:province":"TN",
    "wof:name":"East Side Elementary",
    "wof:placetype":"venue"
},
  "geometry": {"coordinates":[-85.66133000000001,35.738995],"type":"Point"}
}