{
  "type": "Feature",
  "properties": {
    "addr:full":"1087 Louisville Hwy Goodlettsville TN 37072",
    "addr:housenumber":"1087",
    "addr:postcode":"37072",
    "addr:street":"Louisville Hwy",
    "iso:country":"US",
    "sg:address":"1087 Louisville Hwy",
    "sg:city":"Goodlettsville",
    "sg:classifiers":[
        {
            "category":"Retail",
            "subcategory":"Repair Shop",
            "type":"Services"
        }
    ],
    "sg:phone":"+1 615 851 7058",
    "sg:postcode":"37072",
    "sg:province":"TN",
    "sg:tags":[
        "mfg",
        "luggage"
    ],
    "wof:name":"Benchcraft Electronics",
    "wof:placetype":"venue"
},
  "geometry": {"coordinates":[-86.71156000000001,36.364219],"type":"Point"}
}