{
  "type": "Feature",
  "properties": {
    "iso:country":"US",
    "sg:address":"336 Main St",
    "sg:city":"Huntland",
    "sg:classifiers":[
        {
            "category":"Organizations",
            "subcategory":"Religious Organization",
            "type":"Services"
        }
    ],
    "sg:phone":"+1 931 469 7153",
    "sg:postcode":"37345",
    "sg:province":"TN",
    "sg:tags":[
        "church"
    ],
    "wof:name":"Beans Creek Primitive Baptist",
    "wof:placetype":"venue"
},
  "geometry": {"coordinates":[-86.269615,35.060255],"type":"Point"}
}