{
  "type": "Feature",
  "properties": {
    "iso:country":"US",
    "sg:address":"252 Houston Rd",
    "sg:city":"Crossville",
    "sg:classifiers":[
        {
            "category":"Restaurant",
            "type":"Food & Drink"
        }
    ],
    "sg:phone":"+1 931 484 1585",
    "sg:postcode":"38555",
    "sg:province":"TN",
    "sg:tags":[
        "eating"
    ],
    "wof:name":"Edgewood Restaurant",
    "wof:placetype":"venue"
},
  "geometry": {"coordinates":[-84.986227,35.86304],"type":"Point"}
}