{
  "type": "Feature",
  "properties": {
    "iso:country":"US",
    "sg:address":"1405 Robinson Rd",
    "sg:city":"Old Hickory",
    "sg:classifiers":[
        {
            "category":"Autos & Motor Vehicles",
            "subcategory":"Boat Sales",
            "type":"Retail Goods"
        }
    ],
    "sg:phone":"+1 615 847 0460",
    "sg:postcode":"37138",
    "sg:province":"TN",
    "sg:tags":[
        "top",
        "upholstery",
        "cover"
    ],
    "wof:name":"Canvas Unique",
    "wof:placetype":"venue"
},
  "geometry": {"coordinates":[-86.65404700000001,36.255983],"type":"Point"}
}