{
  "type": "Feature",
  "properties": {
    "addr:full":"4715 Whiteoaks Ln Arlington TN 38002",
    "addr:housenumber":"4715",
    "addr:postcode":"38002",
    "addr:street":"Whiteoaks Ln",
    "iso:country":"US",
    "sg:address":"4715 Whiteoaks Ln",
    "sg:city":"Arlington",
    "sg:classifiers":[
        {
            "category":"Building & Trades",
            "subcategory":"Construction",
            "type":"Services"
        }
    ],
    "sg:phone":"+1 901 353 2300",
    "sg:postcode":"38002",
    "sg:province":"TN",
    "sg:tags":[
        "industrial",
        "nonresidential",
        "supply"
    ],
    "wof:name":"Prime Contractors Inc",
    "wof:placetype":"venue"
},
  "geometry": {"coordinates":[-89.779578,35.255747],"type":"Point"}
}