{
  "type": "Feature",
  "properties": {
    "addr:full":"3082 Coleman Rd Memphis TN 38128",
    "addr:housenumber":"3082",
    "addr:postcode":"38128",
    "addr:street":"Coleman Rd",
    "iso:country":"US",
    "sg:address":"3082 Coleman Rd",
    "sg:city":"Memphis",
    "sg:classifiers":[
        {
            "category":"Professional",
            "subcategory":"Computer Services",
            "type":"Services"
        }
    ],
    "sg:phone":"+1 901 387 1876",
    "sg:postcode":"38128",
    "sg:province":"TN",
    "sg:tags":[
        "related"
    ],
    "wof:name":"Brian Jay & Co Homepage",
    "wof:placetype":"venue"
},
  "geometry": {"coordinates":[-89.91454400000001,35.209604],"type":"Point"}
}