{
  "type": "Feature",
  "properties": {
    "iso:country":"US",
    "sg:address":"1017 S Main St",
    "sg:city":"Columbia",
    "sg:classifiers":[
        {
            "category":"Sports & Exercise",
            "subcategory":"Gym",
            "type":"Entertainment"
        }
    ],
    "sg:phone":"+1 931 381 6610",
    "sg:postcode":"38401",
    "sg:province":"TN",
    "sg:tags":[
        "club",
        "health",
        "studio",
        "gymnasium"
    ],
    "wof:name":"Curves",
    "wof:placetype":"venue"
},
  "geometry": {"coordinates":[-87.034192,35.611905],"type":"Point"}
}