{
  "type": "Feature",
  "properties": {
    "addr:full":"7200 US Hwy 64 Oakland TN 38060",
    "addr:housenumber":"7200",
    "addr:postcode":"38060",
    "addr:street":"Us Hwy 64",
    "iso:country":"US",
    "sg:address":"7200 US Hwy 64",
    "sg:city":"Oakland",
    "sg:classifiers":[
        {
            "category":"Restaurant",
            "type":"Food & Drink"
        }
    ],
    "sg:phone":"+1 901 466 9777",
    "sg:postcode":"38060",
    "sg:province":"TN",
    "wof:name":"Mc Donald's",
    "wof:placetype":"venue"
},
  "geometry": {"coordinates":[-89.51722599999999,35.228873],"type":"Point"}
}