{
  "type": "Feature",
  "properties": {
    "addr:full":"4320 Bernard Rd Joelton TN 37080",
    "addr:housenumber":"4320",
    "addr:postcode":"37080",
    "addr:street":"Bernard Rd",
    "iso:country":"US",
    "sg:address":"4320 Bernard Rd",
    "sg:city":"Joelton",
    "sg:classifiers":[
        {
            "category":"Professional",
            "subcategory":"Detective & Security Services",
            "type":"Services"
        }
    ],
    "sg:phone":"+1 615 851 7799",
    "sg:postcode":"37080",
    "sg:province":"TN",
    "wof:name":"Columbus Investigating Svc",
    "wof:placetype":"venue"
},
  "geometry": {"coordinates":[-86.90346599999999,36.300423],"type":"Point"}
}