{
  "type": "Feature",
  "properties": {
    "addr:full":"390 S Lowe Ave Cookeville TN 38501",
    "addr:housenumber":"390",
    "addr:postcode":"38501",
    "addr:street":"S Lowe Ave",
    "iso:country":"US",
    "sg:address":"390 S Lowe Ave",
    "sg:city":"Cookeville",
    "sg:classifiers":[
        {
            "category":"Building & Trades",
            "subcategory":"Construction",
            "type":"Services"
        }
    ],
    "sg:phone":"+1 931 372 0092",
    "sg:postcode":"38501",
    "sg:province":"TN",
    "sg:tags":[
        "general",
        "contractor"
    ],
    "wof:name":"Cypress Bend Construction Co",
    "wof:placetype":"venue"
},
  "geometry": {"coordinates":[-85.49938,36.153794],"type":"Point"}
}