{
  "type": "Feature",
  "properties": {
    "addr:full":"110 Tyler Dr Portland TN 37148",
    "addr:housenumber":"110",
    "addr:postcode":"37148",
    "addr:street":"Tyler Dr",
    "iso:country":"US",
    "sg:address":"110 Tyler Dr",
    "sg:city":"Portland",
    "sg:classifiers":[
        {
            "category":"Freight",
            "type":"Transportation"
        }
    ],
    "sg:phone":"+1 615 325 8049",
    "sg:postcode":"37148",
    "sg:province":"TN",
    "sg:tags":[
        "special"
    ],
    "wof:name":"All Climate Storage",
    "wof:placetype":"venue"
},
  "geometry": {"coordinates":[-86.525964,36.581523],"type":"Point"}
}