{
  "type": "Feature",
  "properties": {
    "iso:country":"US",
    "sg:address":"108 W Court St",
    "sg:city":"Dyersburg",
    "sg:classifiers":[
        {
            "category":"Government",
            "subcategory":"Jail",
            "type":"Public Place"
        }
    ],
    "sg:phone":"+1 731 287 7937",
    "sg:postcode":"38024",
    "sg:province":"TN",
    "sg:tags":[
        "govt",
        "state",
        "institution"
    ],
    "wof:name":"Westate Corrections Misdemanor",
    "wof:placetype":"venue"
},
  "geometry": {"coordinates":[-89.386683,36.03292],"type":"Point"}
}