{
  "type": "Feature",
  "properties": {
    "iso:country":"US",
    "sg:address":"1115 Virginia Ave",
    "sg:city":"Murfreesboro",
    "sg:classifiers":[
        {
            "category":"Professional",
            "subcategory":"Management & Consulting",
            "type":"Services"
        }
    ],
    "sg:phone":"+1 615 907 2727",
    "sg:postcode":"37130",
    "sg:province":"TN",
    "sg:tags":[
        "consultant",
        "educational"
    ],
    "wof:name":"Early Age",
    "wof:placetype":"venue"
},
  "geometry": {"coordinates":[-86.383814,35.830232],"type":"Point"}
}