{
  "type": "Feature",
  "properties": {
    "iso:country":"US",
    "sg:address":"2120 Island Home Blvd",
    "sg:city":"Knoxville",
    "sg:classifiers":[
        {
            "category":"Professional",
            "type":"Services"
        }
    ],
    "sg:phone":"+1 865 609 8791",
    "sg:postcode":"37920",
    "sg:province":"TN",
    "wof:name":"White Balloon",
    "wof:placetype":"venue"
},
  "geometry": {"coordinates":[-83.885385,35.958865],"type":"Point"}
}