{
  "type": "Feature",
  "properties": {
    "addr:full":"4442 Tarleton Dr Memphis TN 38128",
    "addr:housenumber":"4442",
    "addr:postcode":"38128",
    "addr:street":"Tarleton Dr",
    "iso:country":"US",
    "sg:address":"4442 Tarleton Dr",
    "sg:city":"Memphis",
    "sg:classifiers":[
        {
            "category":"Real Estate",
            "subcategory":"Real Estate Agent",
            "type":"Services"
        }
    ],
    "sg:phone":"+1 901 388 9008",
    "sg:postcode":"38128",
    "sg:province":"TN",
    "sg:tags":[
        "inspection"
    ],
    "wof:name":"Midsouth Home Inspections",
    "wof:placetype":"venue"
},
  "geometry": {"coordinates":[-89.93310700000001,35.248104],"type":"Point"}
}