{
  "type": "Feature",
  "properties": {
    "iso:country":"US",
    "sg:address":"10422 S Lee Hwy",
    "sg:city":"Mc Donald",
    "sg:classifiers":[
        {
            "category":"Wholesale",
            "subcategory":"Machinery & Supplies",
            "type":"Manufacturing & Wholesale Goods"
        }
    ],
    "sg:phone":"+1 423 238 5088",
    "sg:postcode":"37353",
    "sg:province":"TN",
    "sg:tags":[
        "industrial"
    ],
    "wof:name":"United Transmission & Conveyer",
    "wof:placetype":"venue"
},
  "geometry": {"coordinates":[-85.02390699999999,35.084485],"type":"Point"}
}