{
  "type": "Feature",
  "properties": {
    "iso:country":"US",
    "sg:address":"30 Dyersburg Hwy",
    "sg:city":"Trenton",
    "sg:classifiers":[
        {
            "category":"Building & Trades",
            "subcategory":"Plumbing",
            "type":"Services"
        }
    ],
    "sg:phone":"+1 731 855 2471",
    "sg:postcode":"38382",
    "sg:province":"TN",
    "sg:tags":[
        "contractor"
    ],
    "wof:name":"Jerrys Country Air & Heating",
    "wof:placetype":"venue"
},
  "geometry": {"coordinates":[-88.96032599999999,35.981261],"type":"Point"}
}