{
  "type": "Feature",
  "properties": {
    "addr:full":"645 N Mclean Blvd Memphis TN 38107",
    "addr:housenumber":"645",
    "addr:postcode":"38107",
    "addr:street":"N Mclean Blvd",
    "iso:country":"US",
    "sg:address":"645 N Mclean Blvd",
    "sg:city":"Memphis",
    "sg:classifiers":[
        {
            "category":"Restaurant",
            "type":"Food & Drink"
        }
    ],
    "sg:phone":"+1 901 278 9127",
    "sg:postcode":"38107",
    "sg:province":"TN",
    "sg:tags":[
        "grill",
        "bar",
        "italian"
    ],
    "wof:name":"Dino's Grill",
    "wof:placetype":"venue"
},
  "geometry": {"coordinates":[-89.997163,35.155053],"type":"Point"}
}