{
  "type": "Feature",
  "properties": {
    "iso:country":"US",
    "sg:address":"7229 Clinton Hwy",
    "sg:city":"Powell",
    "sg:classifiers":[
        {
            "category":"Health Services",
            "subcategory":"Doctor",
            "type":"Services"
        }
    ],
    "sg:phone":"+1 865 938 8900",
    "sg:postcode":"37849",
    "sg:province":"TN",
    "sg:tags":[
        "clinic"
    ],
    "wof:name":"Powell Minor Er",
    "wof:placetype":"venue"
},
  "geometry": {"coordinates":[-84.042888,36.015334],"type":"Point"}
}