{
  "type": "Feature",
  "properties": {
    "iso:country":"US",
    "sg:address":"225 Doc Norton Rd",
    "sg:city":"Maryville",
    "sg:classifiers":[
        {
            "category":"Government",
            "subcategory":"Fire Station",
            "type":"Public Place"
        }
    ],
    "sg:phone":"+1 865 977 8003",
    "sg:postcode":"37804",
    "sg:province":"TN",
    "sg:tags":[
        "department"
    ],
    "wof:name":"Blount County Fire Dept",
    "wof:placetype":"venue"
},
  "geometry": {"coordinates":[-83.82755899999999,35.812914],"type":"Point"}
}