{
  "type": "Feature",
  "properties": {
    "iso:country":"US",
    "sg:address":"7777 Cedar Creek Rd",
    "sg:city":"Townsend",
    "sg:classifiers":[
        {
            "category":"Home & Garden",
            "subcategory":"Furniture",
            "type":"Retail Goods"
        }
    ],
    "sg:phone":"+1 865 448 6066",
    "sg:postcode":"37882",
    "sg:province":"TN",
    "sg:tags":[
        "equipment",
        "kitchen",
        "cabinet"
    ],
    "wof:name":"Cedar Creek Wood Works",
    "wof:placetype":"venue"
},
  "geometry": {"coordinates":[-83.751442,35.690294],"type":"Point"}
}