{
  "type": "Feature",
  "properties": {
    "iso:country":"US",
    "sg:address":"336 Charles Ave",
    "sg:city":"Atoka",
    "sg:classifiers":[
        {
            "category":"Building & Trades",
            "subcategory":"Construction",
            "type":"Services"
        }
    ],
    "sg:phone":"+1 901 837 6100",
    "sg:postcode":"38058",
    "sg:province":"TN",
    "sg:tags":[
        "contractor"
    ],
    "wof:name":"Starnes Tile & Marble",
    "wof:placetype":"venue"
},
  "geometry": {"coordinates":[-89.811391,35.441448],"type":"Point"}
}