{
  "type": "Feature",
  "properties": {
    "iso:country":"US",
    "sg:address":"550 Port Royal Rd",
    "sg:city":"Clarksville",
    "sg:classifiers":[
        {
            "category":"Wholesale",
            "subcategory":"Farm Supplies",
            "type":"Manufacturing & Wholesale Goods"
        }
    ],
    "sg:phone":"+1 931 485 2087",
    "sg:postcode":"37040",
    "sg:province":"TN",
    "sg:tags":[
        "bean"
    ],
    "sg:website":"www.calmainefoods.com",
    "wof:name":"Cal-Maine Foods Inc",
    "wof:placetype":"venue"
},
  "geometry": {"coordinates":[-87.18837499999999,36.632175],"type":"Point"}
}