{
  "type": "Feature",
  "properties": {
    "addr:full":"1201 Pilleaux Dr Knoxville TN 37912",
    "addr:housenumber":"1201",
    "addr:postcode":"37912",
    "addr:street":"Pilleaux Dr",
    "iso:country":"US",
    "sg:address":"1201 Pilleaux Dr",
    "sg:city":"Knoxville",
    "sg:classifiers":[
        {
            "category":"Recreation",
            "type":"Entertainment"
        }
    ],
    "sg:phone":"+1 865 992 6112",
    "sg:postcode":"37912",
    "sg:province":"TN",
    "wof:name":"Cherokee Paintball II",
    "wof:placetype":"venue"
},
  "geometry": {"coordinates":[-83.95827199999999,36.032094],"type":"Point"}
}