{
  "type": "Feature",
  "properties": {
    "addr:full":"27 E Geeter Rd Memphis TN 38109",
    "addr:housenumber":"27",
    "addr:postcode":"38109",
    "addr:street":"E Geeter Rd",
    "iso:country":"US",
    "sg:address":"27 E Geeter Rd",
    "sg:city":"Memphis",
    "sg:classifiers":[
        {
            "category":"Organizations",
            "subcategory":"Religious Organization",
            "type":"Services"
        }
    ],
    "sg:phone":"+1 901 789 4400",
    "sg:postcode":"38109",
    "sg:province":"TN",
    "sg:tags":[
        "church"
    ],
    "wof:name":"Georgia Avenue Baptist Church",
    "wof:placetype":"venue"
},
  "geometry": {"coordinates":[-90.063294,35.018528],"type":"Point"}
}