{
  "type": "Feature",
  "properties": {
    "iso:country":"US",
    "sg:address":"1297 Austin Springs Rd",
    "sg:city":"Piney Flats",
    "sg:classifiers":[
        {
            "category":"Professional",
            "type":"Services"
        }
    ],
    "sg:phone":"+1 423 283 0885",
    "sg:postcode":"37686",
    "sg:province":"TN",
    "wof:name":"Jerry D Davis",
    "wof:placetype":"venue"
},
  "geometry": {"coordinates":[-82.34593599999999,36.399038],"type":"Point"}
}