{
  "type": "Feature",
  "properties": {
    "addr:full":"1501 Longsought Rd Lexington TN 38388",
    "addr:housenumber":"1501",
    "addr:postcode":"38388",
    "addr:street":"Longsought Rd",
    "iso:country":"US",
    "sg:address":"1501 Longsought Rd",
    "sg:city":"Lexington",
    "sg:classifiers":[
        {
            "category":"Wholesale",
            "subcategory":"Farm Supplies",
            "type":"Manufacturing & Wholesale Goods"
        }
    ],
    "sg:phone":"+1 731 968 5375",
    "sg:postcode":"38388",
    "sg:province":"TN",
    "sg:tags":[
        "livestock"
    ],
    "wof:name":"Guy Walker Livestock Dealer",
    "wof:placetype":"venue"
},
  "geometry": {"coordinates":[-88.4119,35.723533],"type":"Point"}
}