{
  "type": "Feature",
  "properties": {
    "iso:country":"US",
    "sg:address":"3770 Robinson Rd",
    "sg:city":"Thompsons Station",
    "sg:classifiers":[
        {
            "category":"Building & Trades",
            "subcategory":"Construction",
            "type":"Services"
        }
    ],
    "sg:phone":"+1 615 591 7603",
    "sg:postcode":"37179",
    "sg:province":"TN",
    "sg:tags":[
        "residential"
    ],
    "wof:name":"Woods Construction",
    "wof:placetype":"venue"
},
  "geometry": {"coordinates":[-87.021423,35.827896],"type":"Point"}
}