{
  "type": "Feature",
  "properties": {
    "iso:country":"US",
    "sg:address":"713 West Ave",
    "sg:city":"Crossville",
    "sg:classifiers":[
        {
            "category":"Banks & Credit Unions",
            "subcategory":"Investment Brokerage",
            "type":"Services"
        }
    ],
    "sg:phone":"+1 931 484 3573",
    "sg:postcode":"38555",
    "sg:province":"TN",
    "sg:tags":[
        "security"
    ],
    "wof:name":"Allied Services Insurance",
    "wof:placetype":"venue"
},
  "geometry": {"coordinates":[-85.032444,35.951052],"type":"Point"}
}