{
  "type": "Feature",
  "properties": {
    "addr:full":"6770 Kirby Lawn Cove Memphis TN 38119",
    "addr:housenumber":"6770",
    "addr:postcode":"38119",
    "addr:street":"Kirby Lawn Cove",
    "iso:country":"US",
    "sg:address":"6770 Kirby Lawn Cove",
    "sg:city":"Memphis",
    "sg:classifiers":[
        {
            "category":"Building & Trades",
            "subcategory":"Construction",
            "type":"Services"
        }
    ],
    "sg:phone":"+1 901 878 0042",
    "sg:postcode":"38119",
    "sg:province":"TN",
    "sg:tags":[
        "contractor"
    ],
    "wof:name":"All American Siding Windo",
    "wof:placetype":"venue"
},
  "geometry": {"coordinates":[-89.837761,35.066353],"type":"Point"}
}