{
  "type": "Feature",
  "properties": {
    "iso:country":"US",
    "sg:address":"1000 Jackson St",
    "sg:city":"Nashville",
    "sg:classifiers":[
        {
            "category":"Health Services",
            "subcategory":"Doctor",
            "type":"Services"
        }
    ],
    "sg:phone":"+1 615 851 7102",
    "sg:postcode":"37208",
    "sg:province":"TN",
    "sg:tags":[
        "dentist"
    ],
    "wof:name":"Richard Barkley DDS",
    "wof:placetype":"venue"
},
  "geometry": {"coordinates":[-86.794173,36.170476],"type":"Point"}
}