{
  "type": "Feature",
  "properties": {
    "iso:country":"US",
    "sg:address":"130 Shelton Rd",
    "sg:city":"Manchester",
    "sg:classifiers":[
        {
            "category":"Restaurant",
            "type":"Food & Drink"
        }
    ],
    "sg:phone":"+1 931 728 6995",
    "sg:postcode":"37355",
    "sg:province":"TN",
    "sg:tags":[
        "shop",
        "coffee"
    ],
    "wof:name":"Coffee County Veteran Assn",
    "wof:placetype":"venue"
},
  "geometry": {"coordinates":[-86.067412,35.467723],"type":"Point"}
}