{
  "type": "Feature",
  "properties": {
    "iso:country":"US",
    "sg:address":"7312 Etheld Reda Dr",
    "sg:city":"Knoxville",
    "sg:classifiers":[
        {
            "category":"Retail",
            "subcategory":"Repair Shop",
            "type":"Services"
        }
    ],
    "sg:phone":"+1 865 254 2456",
    "sg:postcode":"37931",
    "sg:province":"TN",
    "sg:tags":[
        "electrical"
    ],
    "wof:name":"AAA Appliance Repair Co",
    "wof:placetype":"venue"
},
  "geometry": {"coordinates":[-84.106894,35.998444],"type":"Point"}
}