{
  "type": "Feature",
  "properties": {
    "addr:full":"2537 Decatur Pike Athens TN 37303",
    "addr:housenumber":"2537",
    "addr:postcode":"37303",
    "addr:street":"Decatur Pike",
    "iso:country":"US",
    "sg:address":"2537 Decatur Pike",
    "sg:city":"Athens",
    "sg:classifiers":[
        {
            "category":"Manufacturing",
            "subcategory":"Buildings",
            "type":"Manufacturing & Wholesale Goods"
        }
    ],
    "sg:phone":"+1 423 745 5725",
    "sg:postcode":"37303",
    "sg:province":"TN",
    "sg:tags":[
        "home",
        "log",
        "cabin"
    ],
    "sg:website":"www.tnloghomes.com",
    "wof:name":"Tennessee Log Homes",
    "wof:placetype":"venue"
},
  "geometry": {"coordinates":[-84.641043,35.461427],"type":"Point"}
}