{
  "type": "Feature",
  "properties": {
    "iso:country":"US",
    "sg:address":"441 E Chester St",
    "sg:city":"Jackson",
    "sg:classifiers":[
        {
            "category":"Professional",
            "subcategory":"Business Services",
            "type":"Services"
        }
    ],
    "sg:phone":"+1 731 424 2140",
    "sg:postcode":"38301",
    "sg:province":"TN",
    "wof:name":"Highland House Productions",
    "wof:placetype":"venue"
},
  "geometry": {"coordinates":[-88.81397699999999,35.612569],"type":"Point"}
}