{
  "type": "Feature",
  "properties": {
    "iso:country":"US",
    "sg:address":"1800 Highway 51 S",
    "sg:city":"Ripley",
    "sg:classifiers":[
        {
            "category":"Health Services",
            "subcategory":"Dentist",
            "type":"Services"
        }
    ],
    "sg:phone":"+1 731 635 5000",
    "sg:postcode":"38063",
    "sg:province":"TN",
    "wof:name":"Crowder, Roy E Jr DDS",
    "wof:placetype":"venue"
},
  "geometry": {"coordinates":[-89.560889,35.729021],"type":"Point"}
}