{
  "type": "Feature",
  "properties": {
    "addr:full":"5000 Norwind Ln Knoxville TN 37912",
    "addr:housenumber":"5000",
    "addr:postcode":"37912",
    "addr:street":"Norwind Ln",
    "iso:country":"US",
    "sg:address":"5000 Norwind Ln",
    "sg:city":"Knoxville",
    "sg:classifiers":[
        {
            "category":"Restaurant",
            "type":"Food & Drink"
        }
    ],
    "sg:phone":"+1 865 688 8001",
    "sg:postcode":"37912",
    "sg:province":"TN",
    "sg:tags":[
        "family"
    ],
    "wof:name":"Krystal Restaurant",
    "wof:placetype":"venue"
},
  "geometry": {"coordinates":[-83.98164199999999,35.999843],"type":"Point"}
}