{
  "type": "Feature",
  "properties": {
    "iso:country":"US",
    "sg:address":"1110 Market St",
    "sg:city":"Chattanooga",
    "sg:classifiers":[
        {
            "category":"Shopping",
            "subcategory":"Jewelry",
            "type":"Retail Goods"
        }
    ],
    "sg:phone":"+1 423 756 1778",
    "sg:postcode":"37402",
    "sg:province":"TN",
    "wof:name":"Goldsmith Shoppe",
    "wof:placetype":"venue"
},
  "geometry": {"coordinates":[-85.30932199999999,35.042864],"type":"Point"}
}