{
  "type": "Feature",
  "properties": {
    "addr:full":"3415 Steekee Creek Rd Loudon TN 37774",
    "addr:housenumber":"3415",
    "addr:postcode":"37774",
    "addr:street":"Steekee Creek Rd",
    "iso:country":"US",
    "sg:address":"3415 Steekee Creek Rd",
    "sg:city":"Loudon",
    "sg:classifiers":[
        {
            "category":"Autos & Motor Vehicles",
            "subcategory":"Fuel & Gas Station",
            "type":"Retail Goods"
        }
    ],
    "sg:phone":"+1 865 458 5278",
    "sg:postcode":"37774",
    "sg:province":"TN",
    "sg:tags":[
        "station",
        "gasoline",
        "oil"
    ],
    "wof:name":"Toad's Service",
    "wof:placetype":"venue"
},
  "geometry": {"coordinates":[-84.347663,35.687821],"type":"Point"}
}