{
  "type": "Feature",
  "properties": {
    "iso:country":"US",
    "sg:address":"7147 S Springs Dr",
    "sg:city":"Franklin",
    "sg:classifiers":[
        {
            "category":"Restaurant",
            "type":"Food & Drink"
        }
    ],
    "sg:phone":"+1 615 435 8819",
    "sg:postcode":"37067",
    "sg:province":"TN",
    "sg:website":"www.texasroadhouse.com",
    "wof:name":"Texas Roadhouse",
    "wof:placetype":"venue"
},
  "geometry": {"coordinates":[-86.814861,35.953607],"type":"Point"}
}