{
  "type": "Feature",
  "properties": {
    "iso:country":"US",
    "sg:address":"1885 Hwy 73",
    "sg:city":"Newport",
    "sg:classifiers":[
        {
            "category":"Retail",
            "subcategory":"Auto Repair",
            "type":"Services"
        }
    ],
    "sg:phone":"+1 423 623 0530",
    "sg:postcode":"37821",
    "sg:province":"TN",
    "sg:tags":[
        "truck"
    ],
    "wof:name":"Frank's Truck Repair",
    "wof:placetype":"venue"
},
  "geometry": {"coordinates":[-83.184871,35.880594],"type":"Point"}
}