{
  "type": "Feature",
  "properties": {
    "iso:country":"US",
    "sg:address":"727 US Hwy 51 N",
    "sg:city":"Covington",
    "sg:classifiers":[
        {
            "category":"Shopping",
            "subcategory":"Jewelry",
            "type":"Retail Goods"
        }
    ],
    "sg:phone":"+1 901 476 8387",
    "sg:postcode":"38019",
    "sg:province":"TN",
    "sg:tags":[
        "rep"
    ],
    "wof:name":"Brasfield J Wm Jewelers",
    "wof:placetype":"venue"
},
  "geometry": {"coordinates":[-89.64567099999999,35.571956],"type":"Point"}
}