{
  "type": "Feature",
  "properties": {
    "addr:full":"1289 E Crestwood Dr Memphis TN 38119",
    "addr:housenumber":"1289",
    "addr:postcode":"38119",
    "addr:street":"E Crestwood Dr",
    "iso:country":"US",
    "sg:address":"1289 E Crestwood Dr",
    "sg:city":"Memphis",
    "sg:classifiers":[
        {
            "category":"Professional",
            "subcategory":"Business Services",
            "type":"Services"
        }
    ],
    "sg:phone":"+1 901 683 7459",
    "sg:postcode":"38119",
    "sg:province":"TN",
    "sg:tags":[
        "information",
        "referral"
    ],
    "wof:name":"D Musarra Inc",
    "wof:placetype":"venue"
},
  "geometry": {"coordinates":[-89.87587000000001,35.095197],"type":"Point"}
}