{
  "type": "Feature",
  "properties": {
    "iso:country":"US",
    "sg:address":"5950 Shallowford Rd",
    "sg:city":"Chattanooga",
    "sg:classifiers":[
        {
            "category":"Restaurant",
            "type":"Food & Drink"
        }
    ],
    "sg:phone":"+1 423 499 6355",
    "sg:postcode":"37421",
    "sg:province":"TN",
    "wof:name":"Steamboat Oriental Express",
    "wof:placetype":"venue"
},
  "geometry": {"coordinates":[-85.194227,35.054598],"type":"Point"}
}