{
  "type": "Feature",
  "properties": {
    "iso:country":"US",
    "sg:address":"1030 Jefferson Ave",
    "sg:city":"Memphis",
    "sg:classifiers":[
        {
            "category":"Health Services",
            "subcategory":"Hospital",
            "type":"Services"
        }
    ],
    "sg:phone":"+1 901 523 8990",
    "sg:postcode":"38104",
    "sg:province":"TN",
    "sg:website":"www.usajobs.opm.gov",
    "wof:name":"Memphis Veterans Affairs Med",
    "wof:placetype":"venue"
},
  "geometry": {"coordinates":[-90.026176,35.142635],"type":"Point"}
}