{
  "type": "Feature",
  "properties": {
    "addr:full":"1111 N Northshore Dr Knoxville TN 37919",
    "addr:housenumber":"1111",
    "addr:postcode":"37919",
    "addr:street":"N Northshore Dr",
    "iso:country":"US",
    "sg:address":"1111 N Northshore Dr",
    "sg:city":"Knoxville",
    "sg:classifiers":[
        {
            "category":"Professional",
            "subcategory":"Lawyer & Legal Services",
            "type":"Services"
        }
    ],
    "sg:phone":"+1 865 971 4600",
    "sg:postcode":"37919",
    "sg:province":"TN",
    "sg:tags":[
        "attorney"
    ],
    "wof:name":"Norton & Luhn",
    "wof:placetype":"venue"
},
  "geometry": {"coordinates":[-84.003055,35.937232],"type":"Point"}
}