{
  "type": "Feature",
  "properties": {
    "iso:country":"US",
    "sg:address":"1207 Shelby Ave",
    "sg:city":"Nashville",
    "sg:classifiers":[
        {
            "category":"Manufacturing",
            "subcategory":"Printing",
            "type":"Manufacturing & Wholesale Goods"
        }
    ],
    "sg:phone":"+1 615 397 7863",
    "sg:postcode":"37206",
    "sg:province":"TN",
    "sg:tags":[
        "publisher"
    ],
    "wof:name":"Orbital Publishing",
    "wof:placetype":"venue"
},
  "geometry": {"coordinates":[-86.748189,36.171029],"type":"Point"}
}