{
  "type": "Feature",
  "properties": {
    "iso:country":"US",
    "sg:address":"322 Wilhagan Rd",
    "sg:city":"Nashville",
    "sg:classifiers":[
        {
            "category":"Building & Trades",
            "subcategory":"Construction",
            "type":"Services"
        }
    ],
    "sg:phone":"+1 615 361 4110",
    "sg:postcode":"37217",
    "sg:province":"TN",
    "sg:tags":[
        "house"
    ],
    "wof:name":"C S Hasty Construction Company",
    "wof:placetype":"venue"
},
  "geometry": {"coordinates":[-86.717147,36.137443],"type":"Point"}
}