{
  "type": "Feature",
  "properties": {
    "addr:full":"1811 Thomas Rd Memphis TN 38134",
    "addr:housenumber":"1811",
    "addr:postcode":"38134",
    "addr:street":"Thomas Rd",
    "iso:country":"US",
    "sg:address":"1811 Thomas Rd",
    "sg:city":"Memphis",
    "sg:classifiers":[
        {
            "category":"Autos & Motor Vehicles",
            "subcategory":"Auto Supplies",
            "type":"Retail Goods"
        }
    ],
    "sg:phone":"+1 901 388 3728",
    "sg:postcode":"38134",
    "sg:province":"TN",
    "sg:website":"www.memphismustang.com",
    "wof:name":"Classic Mustang Specialists",
    "wof:placetype":"venue"
},
  "geometry": {"coordinates":[-89.887815,35.177765],"type":"Point"}
}