{
  "type": "Feature",
  "properties": {
    "iso:country":"US",
    "sg:address":"8134 Country Village Dr",
    "sg:city":"Cordova",
    "sg:classifiers":[
        {
            "category":"Health Services",
            "subcategory":"Doctor",
            "type":"Services"
        }
    ],
    "sg:phone":"+1 901 309 1025",
    "sg:postcode":"38016",
    "sg:province":"TN",
    "sg:tags":[
        "physician",
        "surgeon"
    ],
    "wof:name":"Lakeside Behavioral Health",
    "wof:placetype":"venue"
},
  "geometry": {"coordinates":[-89.79142299999999,35.160106],"type":"Point"}
}