{
  "type": "Feature",
  "properties": {
    "iso:country":"US",
    "sg:address":"349 Lafe Cox Rd",
    "sg:city":"Johnson City",
    "sg:classifiers":[
        {
            "category":"Wholesale",
            "subcategory":"Drugs",
            "type":"Manufacturing & Wholesale Goods"
        }
    ],
    "sg:phone":"+1 423 926 4413",
    "sg:postcode":"37604",
    "sg:province":"TN",
    "sg:tags":[
        "pharmaceutical",
        "product"
    ],
    "sg:website":"www.crownlaboratories.com",
    "wof:name":"Crown Laboratories",
    "wof:placetype":"venue"
},
  "geometry": {"coordinates":[-82.341846,36.300878],"type":"Point"}
}