{
  "type": "Feature",
  "properties": {
    "addr:full":"504 Jaynes St Halls TN 38040",
    "addr:housenumber":"504",
    "addr:postcode":"38040",
    "addr:street":"Jaynes St",
    "iso:country":"US",
    "sg:address":"504 Jaynes St",
    "sg:city":"Halls",
    "sg:classifiers":[
        {
            "category":"Home & Garden",
            "subcategory":"Carpets & Floor Coverings",
            "type":"Retail Goods"
        }
    ],
    "sg:phone":"+1 731 836 9729",
    "sg:postcode":"38040",
    "sg:province":"TN",
    "sg:tags":[
        "building",
        "material"
    ],
    "wof:name":"Home Discount Center",
    "wof:placetype":"venue"
},
  "geometry": {"coordinates":[-89.390529,35.880649],"type":"Point"}
}