{
  "type": "Feature",
  "properties": {
    "iso:country":"US",
    "sg:address":"309 S Church Ave",
    "sg:city":"Henderson",
    "sg:classifiers":[
        {
            "category":"Retail",
            "subcategory":"Car Wash",
            "type":"Services"
        }
    ],
    "sg:phone":"+1 731 989 5553",
    "sg:postcode":"38340",
    "sg:province":"TN",
    "sg:tags":[
        "carwash"
    ],
    "wof:name":"Dannys Prof Car Clean-Up",
    "wof:placetype":"venue"
},
  "geometry": {"coordinates":[-88.642567,35.435085],"type":"Point"}
}