{
  "type": "Feature",
  "properties": {
    "iso:country":"US",
    "sg:address":"515 Waldron Rd",
    "sg:city":"La Vergne",
    "sg:classifiers":[
        {
            "category":"Restaurant",
            "type":"Food & Drink"
        }
    ],
    "sg:menulink":"http://www.allmenus.com/tn/smyrna/166316-arbys/menu/",
    "sg:phone":"+1 615 793 7800",
    "sg:postcode":"37086",
    "sg:province":"TN",
    "sg:tags":[
        "burger",
        "american"
    ],
    "wof:name":"Arby's",
    "wof:placetype":"venue"
},
  "geometry": {"coordinates":[-86.595797,35.999292],"type":"Point"}
}