{
  "type": "Feature",
  "properties": {
    "iso:country":"US",
    "sg:address":"2715 Prestwick Ct",
    "sg:city":"Kingsport",
    "sg:classifiers":[
        {
            "category":"Personal",
            "subcategory":"Massage",
            "type":"Services"
        },
        {
            "category":"Shopping",
            "subcategory":"Beauty & Cosmetics",
            "type":"Retail Goods"
        },
        {
            "category":"Personal",
            "subcategory":"Beauty Salon",
            "type":"Services"
        }
    ],
    "sg:phone":"+1 423 245 1721",
    "sg:postcode":"37660",
    "sg:province":"TN",
    "sg:tags":[
        "therapist",
        "perfume",
        "salons-equipment",
        "supply"
    ],
    "wof:name":"Divine Essentials",
    "wof:placetype":"venue"
},
  "geometry": {"coordinates":[-82.49335000000001,36.561664],"type":"Point"}
}