{
  "type": "Feature",
  "properties": {
    "iso:country":"US",
    "sg:address":"1817 N Locust Ave",
    "sg:city":"Lawrenceburg",
    "sg:classifiers":[
        {
            "category":"Restaurant",
            "type":"Food & Drink"
        }
    ],
    "sg:menulink":"http://www.allmenus.com/tn/lawrenceburg/214760-ponderosa-steak-house/menu/",
    "sg:phone":"+1 931 762 6261",
    "sg:postcode":"38464",
    "sg:province":"TN",
    "sg:tags":[
        "american",
        "steakhouse"
    ],
    "wof:name":"Ponderosa Steak House",
    "wof:placetype":"venue"
},
  "geometry": {"coordinates":[-87.323863,35.264409],"type":"Point"}
}