{
  "type": "Feature",
  "properties": {
    "iso:country":"US",
    "sg:address":"1213 Division St",
    "sg:city":"Nashville",
    "sg:classifiers":[
        {
            "category":"Building & Trades",
            "subcategory":"Construction",
            "type":"Services"
        }
    ],
    "sg:phone":"+1 615 254 1853",
    "sg:postcode":"37203",
    "sg:province":"TN",
    "sg:tags":[
        "general",
        "nonresidential",
        "contractor"
    ],
    "wof:name":"T E Akers & Company",
    "wof:placetype":"venue"
},
  "geometry": {"coordinates":[-86.785624,36.151144],"type":"Point"}
}