{
  "type": "Feature",
  "properties": {
    "iso:country":"US",
    "sg:address":"219 Lincoln Cir",
    "sg:city":"Jackson",
    "sg:classifiers":[
        {
            "category":"Social Services",
            "subcategory":"Child Care",
            "type":"Services"
        }
    ],
    "sg:phone":"+1 731 423 0928",
    "sg:postcode":"38301",
    "sg:province":"TN",
    "sg:tags":[
        "kindergarten",
        "academic",
        "school"
    ],
    "wof:name":"Lincoln Courts Headstart",
    "wof:placetype":"venue"
},
  "geometry": {"coordinates":[-88.798587,35.632636],"type":"Point"}
}