{
  "type": "Feature",
  "properties": {
    "addr:full":"2004 E Broadway Ave Maryville TN 37804",
    "addr:housenumber":"2004",
    "addr:postcode":"37804",
    "addr:street":"E Broadway Ave",
    "iso:country":"US",
    "sg:address":"2004 E Broadway Ave",
    "sg:city":"Maryville",
    "sg:classifiers":[
        {
            "category":"Health Services",
            "subcategory":"Chiropractor",
            "type":"Services"
        }
    ],
    "sg:phone":"+1 865 982 4301",
    "sg:postcode":"37804",
    "sg:province":"TN",
    "wof:name":"Blount Chiropractic Ctr",
    "wof:placetype":"venue"
},
  "geometry": {"coordinates":[-83.95375,35.775851],"type":"Point"}
}