{
  "type": "Feature",
  "properties": {
    "iso:country":"US",
    "sg:address":"410 Bryant Ln",
    "sg:city":"Savannah",
    "sg:classifiers":[
        {
            "category":"Professional",
            "subcategory":"Management & Consulting",
            "type":"Services"
        }
    ],
    "sg:phone":"+1 731 925 7204",
    "sg:postcode":"38372",
    "sg:province":"TN",
    "sg:tags":[
        "medical",
        "training",
        "testing",
        "occupational"
    ],
    "wof:name":"E M S Inc",
    "wof:placetype":"venue"
},
  "geometry": {"coordinates":[-88.104822,35.328526],"type":"Point"}
}