{
  "type": "Feature",
  "properties": {
    "iso:country":"US",
    "sg:address":"2219 Alydar Run",
    "sg:city":"Murfreesboro",
    "sg:classifiers":[
        {
            "category":"Freight",
            "type":"Transportation"
        }
    ],
    "sg:phone":"+1 615 849 6969",
    "sg:postcode":"37127",
    "sg:province":"TN",
    "sg:tags":[
        "delivery"
    ],
    "wof:name":"Custom Courier",
    "wof:placetype":"venue"
},
  "geometry": {"coordinates":[-86.356346,35.800184],"type":"Point"}
}