{
  "type": "Feature",
  "properties": {
    "addr:full":"1595 Holcomb Rd Mc Minnville TN 37110",
    "addr:housenumber":"1595",
    "addr:postcode":"37110",
    "addr:street":"Holcomb Rd",
    "iso:country":"US",
    "sg:address":"1595 Holcomb Rd",
    "sg:city":"Mc Minnville",
    "sg:classifiers":[
        {
            "category":"Shopping",
            "subcategory":"Used Merchandise",
            "type":"Retail Goods"
        }
    ],
    "sg:phone":"+1 931 939 3220",
    "sg:postcode":"37110",
    "sg:province":"TN",
    "wof:name":"McMinnville Pawn Shop",
    "wof:placetype":"venue"
},
  "geometry": {"coordinates":[-85.866305,35.798352],"type":"Point"}
}