{
  "type": "Feature",
  "properties": {
    "iso:country":"US",
    "sg:address":"10130 2nd St",
    "sg:city":"Gates",
    "sg:classifiers":[
        {
            "category":"Shopping",
            "subcategory":"Luggage & Leather Goods",
            "type":"Retail Goods"
        }
    ],
    "sg:phone":"+1 731 836 9833",
    "sg:postcode":"38037",
    "sg:province":"TN",
    "wof:name":"Joyce's Leather",
    "wof:placetype":"venue"
},
  "geometry": {"coordinates":[-89.405773,35.838959],"type":"Point"}
}