{
  "type": "Feature",
  "properties": {
    "iso:country":"US",
    "sg:address":"1206 Topside Rd",
    "sg:city":"Louisville",
    "sg:classifiers":[
        {
            "category":"Professional",
            "subcategory":"Business Services",
            "type":"Services"
        }
    ],
    "sg:phone":"+1 865 983 4581",
    "sg:postcode":"37777",
    "sg:province":"TN",
    "sg:tags":[
        "coffee"
    ],
    "wof:name":"Standard Coffee Service Co",
    "wof:placetype":"venue"
},
  "geometry": {"coordinates":[-83.967133,35.861733],"type":"Point"}
}