{
  "type": "Feature",
  "properties": {
    "iso:country":"US",
    "sg:address":"6503 Slater St",
    "sg:city":"Chattanooga",
    "sg:classifiers":[
        {
            "category":"Shopping",
            "subcategory":"Used Merchandise",
            "type":"Retail Goods"
        }
    ],
    "sg:phone":"+1 423 893 9594",
    "sg:postcode":"37412",
    "sg:province":"TN",
    "wof:name":"Scrupples",
    "wof:placetype":"venue"
},
  "geometry": {"coordinates":[-85.206953,34.990403],"type":"Point"}
}