{
  "type": "Feature",
  "properties": {
    "iso:country":"US",
    "sg:address":"8705 Unicorn Dr",
    "sg:city":"Knoxville",
    "sg:classifiers":[
        {
            "category":"Building & Trades",
            "subcategory":"Electrical",
            "type":"Services"
        }
    ],
    "sg:phone":"+1 865 690 6200",
    "sg:postcode":"37923",
    "sg:province":"TN",
    "sg:tags":[
        "electric",
        "contractor"
    ],
    "wof:name":"Secon",
    "wof:placetype":"venue"
},
  "geometry": {"coordinates":[-84.075472,35.919681],"type":"Point"}
}