{
  "type": "Feature",
  "properties": {
    "iso:country":"US",
    "sg:address":"722 Robertsville Rd",
    "sg:city":"Oak Ridge",
    "sg:classifiers":[
        {
            "category":"Manufacturing",
            "subcategory":"Tools & Machinery",
            "type":"Manufacturing & Wholesale Goods"
        }
    ],
    "sg:phone":"+1 865 482 4038",
    "sg:postcode":"37830",
    "sg:province":"TN",
    "sg:tags":[
        "manufacture",
        "equipment",
        "peripheral",
        "computer"
    ],
    "wof:name":"Elo Touchsystems Inc",
    "wof:placetype":"venue"
},
  "geometry": {"coordinates":[-84.31013,35.998459],"type":"Point"}
}