{
  "type": "Feature",
  "properties": {
    "addr:full":"821 Tusculum Blvd Greeneville TN 37745",
    "addr:housenumber":"821",
    "addr:postcode":"37745",
    "addr:street":"Tusculum Blvd",
    "iso:country":"US",
    "sg:address":"821 Tusculum Blvd",
    "sg:city":"Greeneville",
    "sg:classifiers":[
        {
            "category":"Personal",
            "subcategory":"Beauty Salon",
            "type":"Services"
        }
    ],
    "sg:phone":"+1 423 638 6431",
    "sg:postcode":"37745",
    "sg:province":"TN",
    "sg:tags":[
        "shop"
    ],
    "wof:name":"Portia Family Hair Care Center",
    "wof:placetype":"venue"
},
  "geometry": {"coordinates":[-82.81483900000001,36.170777],"type":"Point"}
}