{
  "type": "Feature",
  "properties": {
    "iso:country":"US",
    "sg:address":"24 Robertson St",
    "sg:city":"Lexington",
    "sg:classifiers":[
        {
            "category":"Retail",
            "subcategory":"Auto Repair",
            "type":"Services"
        }
    ],
    "sg:phone":"+1 731 968 7993",
    "sg:postcode":"38351",
    "sg:province":"TN",
    "sg:tags":[
        "repairing",
        "automobile",
        "general"
    ],
    "wof:name":"Tolley Automotive Inc",
    "wof:placetype":"venue"
},
  "geometry": {"coordinates":[-88.40613500000001,35.642061],"type":"Point"}
}