{
  "type": "Feature",
  "properties": {
    "addr:full":"5128 Charlotte Pike Nashville TN 37209",
    "addr:housenumber":"5128",
    "addr:postcode":"37209",
    "addr:street":"Charlotte Pike",
    "iso:country":"US",
    "sg:address":"5128 Charlotte Pike",
    "sg:city":"Nashville",
    "sg:classifiers":[
        {
            "category":"Personal",
            "subcategory":"Beauty Salon",
            "type":"Services"
        }
    ],
    "sg:phone":"+1 615 269 9319",
    "sg:postcode":"37209",
    "sg:province":"TN",
    "sg:tags":[
        "school"
    ],
    "wof:name":"Jon Nave Univ Of Cosmetology",
    "wof:placetype":"venue"
},
  "geometry": {"coordinates":[-86.848934,36.152032],"type":"Point"}
}