{
  "type": "Feature",
  "properties": {
    "iso:country":"US",
    "sg:address":"1304 Phillips St SW",
    "sg:city":"Cleveland",
    "sg:classifiers":[
        {
            "category":"Home & Garden",
            "subcategory":"Building Materials",
            "type":"Retail Goods"
        },
        {
            "category":"Building & Trades",
            "subcategory":"Construction",
            "type":"Services"
        }
    ],
    "sg:phone":"+1 423 472 8810",
    "sg:postcode":"37311",
    "sg:province":"TN",
    "sg:tags":[
        "painter"
    ],
    "wof:name":"Maples Professional Painting",
    "wof:placetype":"venue"
},
  "geometry": {"coordinates":[-84.894926,35.1522],"type":"Point"}
}