{
  "type": "Feature",
  "properties": {
    "addr:full":"2721 Frayser Blvd Memphis TN 38127",
    "addr:housenumber":"2721",
    "addr:postcode":"38127",
    "addr:street":"Frayser Blvd",
    "iso:country":"US",
    "sg:address":"2721 Frayser Blvd",
    "sg:city":"Memphis",
    "sg:classifiers":[
        {
            "category":"Personal",
            "subcategory":"Beauty Salon",
            "type":"Services"
        }
    ],
    "sg:phone":"+1 901 357 4359",
    "sg:postcode":"38127",
    "sg:province":"TN",
    "sg:tags":[
        "shop"
    ],
    "wof:name":"Cook's Cut N Curl",
    "wof:placetype":"venue"
},
  "geometry": {"coordinates":[-89.975183,35.221078],"type":"Point"}
}