{
  "type": "Feature",
  "properties": {
    "iso:country":"US",
    "sg:address":"1490 Mifflin Rd",
    "sg:city":"Jackson",
    "sg:classifiers":[
        {
            "category":"Farming",
            "subcategory":"Farm",
            "type":"Manufacturing & Wholesale Goods"
        }
    ],
    "sg:phone":"+1 731 423 3478",
    "sg:postcode":"38301",
    "sg:province":"TN",
    "wof:name":"Horton Farm",
    "wof:placetype":"venue"
},
  "geometry": {"coordinates":[-88.688849,35.585552],"type":"Point"}
}