{
  "type": "Feature",
  "properties": {
    "addr:full":"1898 Parkview Cove Memphis TN 38104",
    "addr:housenumber":"1898",
    "addr:postcode":"38104",
    "addr:street":"Parkview Cove",
    "iso:country":"US",
    "sg:address":"1898 Parkview Cove",
    "sg:city":"Memphis",
    "sg:classifiers":[
        {
            "category":"Professional",
            "subcategory":"Lawyer & Legal Services",
            "type":"Services"
        }
    ],
    "sg:phone":"+1 901 603 7573",
    "sg:postcode":"38104",
    "sg:province":"TN",
    "sg:tags":[
        "specialized"
    ],
    "wof:name":"Mark Erskine",
    "wof:placetype":"venue"
},
  "geometry": {"coordinates":[-89.997575,35.13925],"type":"Point"}
}