{
  "type": "Feature",
  "properties": {
    "addr:full":"1287 E Main St Rogersville TN 37857",
    "addr:housenumber":"1287",
    "addr:postcode":"37857",
    "addr:street":"E Main St",
    "iso:country":"US",
    "sg:address":"1287 E Main St",
    "sg:city":"Rogersville",
    "sg:classifiers":[
        {
            "category":"Shopping",
            "subcategory":"Computers & Home Electronics",
            "type":"Retail Goods"
        }
    ],
    "sg:phone":"+1 423 272 4635",
    "sg:postcode":"37857",
    "sg:province":"TN",
    "sg:tags":[
        "equipment",
        "electronic",
        "supply"
    ],
    "wof:name":"Radio Shack",
    "wof:placetype":"venue"
},
  "geometry": {"coordinates":[-82.98980899999999,36.414809],"type":"Point"}
}