{
  "type": "Feature",
  "properties": {
    "addr:full":"147 Jefferson Ave Memphis TN 38103",
    "addr:housenumber":"147",
    "addr:postcode":"38103",
    "addr:street":"Jefferson Ave",
    "iso:country":"US",
    "sg:address":"147 Jefferson Ave",
    "sg:city":"Memphis",
    "sg:classifiers":[
        {
            "category":"Professional",
            "subcategory":"Credit Reporting & Collection",
            "type":"Services"
        }
    ],
    "sg:phone":"+1 901 572 7076",
    "sg:postcode":"38103",
    "sg:province":"TN",
    "sg:tags":[
        "agency"
    ],
    "wof:name":"Hanna & Assoc",
    "wof:placetype":"venue"
},
  "geometry": {"coordinates":[-90.050552,35.146733],"type":"Point"}
}