{
  "type": "Feature",
  "properties": {
    "addr:full":"3700 N Germantown Rd Memphis TN 38133",
    "addr:housenumber":"3700",
    "addr:postcode":"38133",
    "addr:street":"N Germantown Rd",
    "iso:country":"US",
    "sg:address":"3700 N Germantown Rd",
    "sg:city":"Memphis",
    "sg:classifiers":[
        {
            "category":"Retail",
            "subcategory":"Funeral Services",
            "type":"Services"
        }
    ],
    "sg:phone":"+1 901 388 5135",
    "sg:postcode":"38133",
    "sg:province":"TN",
    "sg:tags":[
        "director"
    ],
    "wof:name":"Memphis Funeral Home and Memorial Gardens",
    "wof:placetype":"venue"
},
  "geometry": {"coordinates":[-89.792023,35.226299],"type":"Point"}
}