{
  "type": "Feature",
  "properties": {
    "iso:country":"US",
    "sg:address":"5512 Ringgold Rd",
    "sg:city":"Chattanooga",
    "sg:classifiers":[
        {
            "category":"Professional",
            "subcategory":"Business Services",
            "type":"Services"
        }
    ],
    "sg:phone":"+1 423 893 9544",
    "sg:postcode":"37412",
    "sg:province":"TN",
    "sg:tags":[
        "real estate"
    ],
    "wof:name":"Driver Michaela",
    "wof:placetype":"venue"
},
  "geometry": {"coordinates":[-85.227256,34.992447],"type":"Point"}
}