{
  "type": "Feature",
  "properties": {
    "addr:full":"3998 Adamson Branch Rd Liberty TN 37095",
    "addr:housenumber":"3998",
    "addr:postcode":"37095",
    "addr:street":"Adamson Branch Rd",
    "iso:country":"US",
    "sg:address":"3998 Adamson Branch Rd",
    "sg:city":"Liberty",
    "sg:classifiers":[
        {
            "category":"Manufacturing",
            "subcategory":"Chemicals & Compounds",
            "type":"Manufacturing & Wholesale Goods"
        }
    ],
    "sg:phone":"+1 615 536 5086",
    "sg:postcode":"37095",
    "sg:province":"TN",
    "sg:tags":[
        "mfg"
    ],
    "wof:name":"Speedy Clean Products",
    "wof:placetype":"venue"
},
  "geometry": {"coordinates":[-85.95105700000001,35.933227],"type":"Point"}
}