{
  "type": "Feature",
  "properties": {
    "iso:country":"US",
    "sg:address":"784 McGavock Pike",
    "sg:city":"Nashville",
    "sg:classifiers":[
        {
            "category":"Building & Trades",
            "subcategory":"Construction",
            "type":"Services"
        },
        {
            "category":"Professional",
            "subcategory":"Management & Consulting",
            "type":"Services"
        }
    ],
    "sg:phone":"+1 615 883 7335",
    "sg:postcode":"37214",
    "sg:province":"TN",
    "sg:tags":[
        "residential",
        "commercial"
    ],
    "sg:website":"www.icfbuildersinc.com",
    "wof:name":"ICf Builders and Consultants",
    "wof:placetype":"venue"
},
  "geometry": {"coordinates":[-86.684134,36.147933],"type":"Point"}
}