{
  "type": "Feature",
  "properties": {
    "addr:full":"4097 Hord Rd Murfreesboro TN 37129",
    "addr:housenumber":"4097",
    "addr:postcode":"37129",
    "addr:street":"Hord Rd",
    "iso:country":"US",
    "sg:address":"4097 Hord Rd",
    "sg:city":"Murfreesboro",
    "sg:classifiers":[
        {
            "category":"Building & Trades",
            "subcategory":"Construction",
            "type":"Services"
        }
    ],
    "sg:phone":"+1 615 896 5150",
    "sg:postcode":"37129",
    "sg:province":"TN",
    "sg:tags":[
        "contractor"
    ],
    "wof:name":"Aarrons Siding Co",
    "wof:placetype":"venue"
},
  "geometry": {"coordinates":[-86.459053,35.889701],"type":"Point"}
}