{
  "type": "Feature",
  "properties": {
    "iso:country":"US",
    "sg:address":"131 Willow St",
    "sg:city":"Tellico Plains",
    "sg:classifiers":[
        {
            "category":"Organizations",
            "subcategory":"Religious Organization",
            "type":"Services"
        }
    ],
    "sg:phone":"+1 423 253 3214",
    "sg:postcode":"37385",
    "sg:province":"TN",
    "wof:name":"Tellico Plains Church Of God",
    "wof:placetype":"venue"
},
  "geometry": {"coordinates":[-84.29376000000001,35.358059],"type":"Point"}
}