{
  "type": "Feature",
  "properties": {
    "addr:full":"685 E Mallory Ave Memphis TN 38106",
    "addr:housenumber":"685",
    "addr:postcode":"38106",
    "addr:street":"E Mallory Ave",
    "iso:country":"US",
    "sg:address":"685 E Mallory Ave",
    "sg:city":"Memphis",
    "sg:classifiers":[
        {
            "category":"Organizations",
            "subcategory":"Religious Organization",
            "type":"Services"
        }
    ],
    "sg:phone":"+1 901 774 5431",
    "sg:postcode":"38106",
    "sg:province":"TN",
    "sg:tags":[
        "church"
    ],
    "wof:name":"Longview Heights Church",
    "wof:placetype":"venue"
},
  "geometry": {"coordinates":[-90.04230699999999,35.086262],"type":"Point"}
}