{
  "type": "Feature",
  "properties": {
    "addr:full":"3295 Poplar Ave # 109 Memphis TN 38111",
    "addr:housenumber":"3295",
    "addr:postcode":"38111",
    "addr:street":"Poplar Ave # 109",
    "iso:country":"US",
    "sg:address":"3295 Poplar Ave # 109",
    "sg:city":"Memphis",
    "sg:classifiers":[
        {
            "category":"Banks & Credit Unions",
            "subcategory":"Bank",
            "type":"Services"
        }
    ],
    "sg:phone":"+1 901 844 2075",
    "sg:postcode":"38111",
    "sg:province":"TN",
    "sg:tags":[
        "saving",
        "commercial"
    ],
    "sg:website":"http://www.i-bankonline.com",
    "wof:name":"Independent Bank",
    "wof:placetype":"venue"
},
  "geometry": {"coordinates":[-89.951975,35.129595],"type":"Point"}
}