{
  "type": "Feature",
  "properties": {
    "iso:country":"US",
    "sg:address":"191 S Highland St",
    "sg:city":"Memphis",
    "sg:classifiers":[
        {
            "category":"Food & Beverages",
            "subcategory":"Liquor & Beverages",
            "type":"Retail Goods"
        }
    ],
    "sg:phone":"+1 901 458 0929",
    "sg:postcode":"38111",
    "sg:province":"TN",
    "sg:website":"www.bustersliquors.com",
    "wof:name":"Buster's Liquors & Wines",
    "wof:placetype":"venue"
},
  "geometry": {"coordinates":[-89.94530399999999,35.127561],"type":"Point"}
}