{
  "type": "Feature",
  "properties": {
    "iso:country":"US",
    "sg:address":"4729 Adams Rd",
    "sg:city":"Hixson",
    "sg:classifiers":[
        {
            "category":"Manufacturing",
            "subcategory":"Tools & Machinery",
            "type":"Manufacturing & Wholesale Goods"
        }
    ],
    "sg:phone":"+1 423 875 2824",
    "sg:postcode":"37343",
    "sg:province":"TN",
    "sg:tags":[
        "devices",
        "mfg"
    ],
    "wof:name":"Electrical Maintenance",
    "wof:placetype":"venue"
},
  "geometry": {"coordinates":[-85.23342599999999,35.1343],"type":"Point"}
}