{
  "type": "Feature",
  "properties": {
    "iso:country":"US",
    "sg:address":"7051 Mc Cutcheon Rd",
    "sg:city":"Chattanooga",
    "sg:classifiers":[
        {
            "category":"Travel",
            "subcategory":"Hotels & Motels",
            "type":"Entertainment"
        }
    ],
    "sg:phone":"+1 423 899 2300",
    "sg:postcode":"37421",
    "sg:province":"TN",
    "sg:tags":[
        "operation"
    ],
    "wof:name":"Country Suites By Carlson",
    "wof:placetype":"venue"
},
  "geometry": {"coordinates":[-85.156131,35.046701],"type":"Point"}
}