{
  "type": "Feature",
  "properties": {
    "addr:full":"1761 Fowler Hollow Rd Lynnville TN 38472",
    "addr:housenumber":"1761",
    "addr:postcode":"38472",
    "addr:street":"Fowler Hollow Rd",
    "iso:country":"US",
    "sg:address":"1761 Fowler Hollow Rd",
    "sg:city":"Lynnville",
    "sg:classifiers":[
        {
            "category":"Building & Trades",
            "subcategory":"Landscaping Services",
            "type":"Services"
        }
    ],
    "sg:phone":"+1 931 527 3764",
    "sg:postcode":"38472",
    "sg:province":"TN",
    "wof:name":"L&W Lawn Care",
    "wof:placetype":"venue"
},
  "geometry": {"coordinates":[-86.92409000000001,35.401512],"type":"Point"}
}