{
  "type": "Feature",
  "properties": {
    "addr:full":"3756 Deer Xing Memphis TN 38115",
    "addr:housenumber":"3756",
    "addr:postcode":"38115",
    "addr:street":"Deer Xing",
    "iso:country":"US",
    "sg:address":"3756 Deer Xing",
    "sg:city":"Memphis",
    "sg:classifiers":[
        {
            "category":"Professional",
            "type":"Services"
        }
    ],
    "sg:phone":"+1 901 794 1374",
    "sg:postcode":"38115",
    "sg:province":"TN",
    "wof:name":"Patti PS Inc",
    "wof:placetype":"venue"
},
  "geometry": {"coordinates":[-89.84387599999999,35.044565],"type":"Point"}
}