{
  "type": "Feature",
  "properties": {
    "iso:country":"US",
    "sg:address":"635 High St",
    "sg:city":"Huntingdon",
    "sg:classifiers":[
        {
            "category":"Health Services",
            "subcategory":"Nursing And Care Facility",
            "type":"Services"
        }
    ],
    "sg:phone":"+1 731 986 8943",
    "sg:postcode":"38344",
    "sg:province":"TN",
    "sg:tags":[
        "skilled",
        "intermediate"
    ],
    "sg:website":"www.kindredhealthcare.com",
    "wof:name":"Huntingdon Health & Rehab Ctr",
    "wof:placetype":"venue"
},
  "geometry": {"coordinates":[-88.407557,36.025168],"type":"Point"}
}