{
  "type": "Feature",
  "properties": {
    "iso:country":"US",
    "sg:address":"2803 Foster Ave",
    "sg:city":"Nashville",
    "sg:classifiers":[
        {
            "category":"Banks & Credit Unions",
            "subcategory":"Bank",
            "type":"Services"
        }
    ],
    "sg:phone":"+1 615 834 3900",
    "sg:postcode":"37210",
    "sg:province":"TN",
    "sg:tags":[
        "loan",
        "real estate"
    ],
    "wof:name":"American Residential Funding",
    "wof:placetype":"venue"
},
  "geometry": {"coordinates":[-86.74343399999999,36.114023],"type":"Point"}
}