{
  "type": "Feature",
  "properties": {
    "iso:country":"US",
    "sg:address":"2202 Dickerson Pike",
    "sg:city":"Nashville",
    "sg:classifiers":[
        {
            "category":"Autos & Motor Vehicles",
            "subcategory":"Fuel & Gas Station",
            "type":"Retail Goods"
        }
    ],
    "sg:phone":"+1 615 650 5522",
    "sg:postcode":"37207",
    "sg:province":"TN",
    "sg:tags":[
        "oil"
    ],
    "wof:name":"Phillips 66",
    "wof:placetype":"venue"
},
  "geometry": {"coordinates":[-86.768338,36.206793],"type":"Point"}
}