{
  "type": "Feature",
  "properties": {
    "addr:full":"503 Old Airport Rd Bristol TN 24201",
    "addr:housenumber":"503",
    "addr:postcode":"24201",
    "addr:street":"Old Airport Rd",
    "iso:country":"US",
    "sg:address":"503 Old Airport Rd",
    "sg:city":"Bristol",
    "sg:classifiers":[
        {
            "category":"Retail",
            "subcategory":"Auto Repair",
            "type":"Services"
        }
    ],
    "sg:phone":"+1 276 669 8003",
    "sg:postcode":"24201",
    "sg:province":"TN",
    "sg:tags":[
        "automobile",
        "customizing"
    ],
    "wof:name":"Need For Speed",
    "wof:placetype":"venue"
},
  "geometry": {"coordinates":[-82.12884699999999,36.618528],"type":"Point"}
}