{
  "type": "Feature",
  "properties": {
    "iso:country":"US",
    "sg:address":"340 W Bockman Way",
    "sg:city":"Sparta",
    "sg:classifiers":[
        {
            "category":"Manufacturing",
            "subcategory":"Food",
            "type":"Manufacturing & Wholesale Goods"
        }
    ],
    "sg:phone":"+1 931 836 8089",
    "sg:postcode":"38583",
    "sg:province":"TN",
    "sg:tags":[
        "cookie",
        "cracker"
    ],
    "wof:name":"Charis",
    "wof:placetype":"venue"
},
  "geometry": {"coordinates":[-85.471294,35.929175],"type":"Point"}
}