{
  "type": "Feature",
  "properties": {
    "iso:country":"US",
    "sg:address":"41 Shavers Rd",
    "sg:city":"Decaturville",
    "sg:classifiers":[
        {
            "category":"Building & Trades",
            "subcategory":"Construction",
            "type":"Services"
        }
    ],
    "sg:phone":"+1 731 852 2552",
    "sg:postcode":"38329",
    "sg:province":"TN",
    "sg:tags":[
        "house"
    ],
    "wof:name":"Raney Raney Construction",
    "wof:placetype":"venue"
},
  "geometry": {"coordinates":[-88.194603,35.515978],"type":"Point"}
}