{
  "type": "Feature",
  "properties": {
    "iso:country":"US",
    "sg:address":"2930 Winchester Rd",
    "sg:city":"Memphis",
    "sg:classifiers":[
        {
            "category":"Airline",
            "type":"Transportation"
        }
    ],
    "sg:phone":"+1 901 346 3108",
    "sg:postcode":"38118",
    "sg:province":"TN",
    "sg:tags":[
        "company"
    ],
    "wof:name":"Casino Express Airlines",
    "wof:placetype":"venue"
},
  "geometry": {"coordinates":[-89.965441,35.052707],"type":"Point"}
}