{
  "type": "Feature",
  "properties": {
    "iso:country":"US",
    "sg:address":"1702 Old Gray Station Rd",
    "sg:city":"Gray",
    "sg:classifiers":[
        {
            "category":"Autos & Motor Vehicles",
            "subcategory":"Automobile Sales",
            "type":"Retail Goods"
        }
    ],
    "sg:phone":"+1 423 282 3661",
    "sg:postcode":"37615",
    "sg:province":"TN",
    "sg:tags":[
        "car",
        "dealer"
    ],
    "wof:name":"Nave's Auto Sales Wholesale",
    "wof:placetype":"venue"
},
  "geometry": {"coordinates":[-82.411902,36.384097],"type":"Point"}
}