{
  "type": "Feature",
  "properties": {
    "iso:country":"US",
    "sg:address":"7230 Harper Rd",
    "sg:city":"Joelton",
    "sg:classifiers":[
        {
            "category":"Building & Trades",
            "subcategory":"Construction",
            "type":"Services"
        }
    ],
    "sg:phone":"+1 615 876 2934",
    "sg:postcode":"37080",
    "sg:province":"TN",
    "sg:tags":[
        "masonry"
    ],
    "wof:name":"Archie Mason Frye Contractor",
    "wof:placetype":"venue"
},
  "geometry": {"coordinates":[-86.91475,36.32787],"type":"Point"}
}