{
  "type": "Feature",
  "properties": {
    "addr:full":"599 John Wright Rd Mount Juliet TN 37122",
    "addr:housenumber":"599",
    "addr:postcode":"37122",
    "addr:street":"John Wright Rd",
    "iso:country":"US",
    "sg:address":"599 John Wright Rd",
    "sg:city":"Mount Juliet",
    "sg:classifiers":[
        {
            "category":"Building & Trades",
            "subcategory":"Construction",
            "type":"Services"
        }
    ],
    "sg:phone":"+1 615 773 7045",
    "sg:postcode":"37122",
    "sg:province":"TN",
    "sg:tags":[
        "house"
    ],
    "wof:name":"Kelly Heaton",
    "wof:placetype":"venue"
},
  "geometry": {"coordinates":[-86.54686599999999,36.176401],"type":"Point"}
}