{
  "type": "Feature",
  "properties": {
    "iso:country":"US",
    "sg:address":"309 N Main St",
    "sg:city":"Springfield",
    "sg:classifiers":[
        {
            "category":"Banks & Credit Unions",
            "subcategory":"Financial Services",
            "type":"Services"
        }
    ],
    "sg:phone":"+1 615 384 2658",
    "sg:postcode":"37172",
    "sg:province":"TN",
    "sg:tags":[
        "investor"
    ],
    "wof:name":"Onstott Investment Partnership",
    "wof:placetype":"venue"
},
  "geometry": {"coordinates":[-86.884331,36.513582],"type":"Point"}
}