{
  "type": "Feature",
  "properties": {
    "addr:full":"2516 Stones River Ct Nashville TN 37214",
    "addr:housenumber":"2516",
    "addr:postcode":"37214",
    "addr:street":"Stones River Ct",
    "iso:country":"US",
    "sg:address":"2516 Stones River Ct",
    "sg:city":"Nashville",
    "sg:classifiers":[
        {
            "category":"Professional",
            "subcategory":"Accounting & Tax Preparation",
            "type":"Services"
        }
    ],
    "sg:phone":"+1 615 889 3885",
    "sg:postcode":"37214",
    "sg:province":"TN",
    "sg:tags":[
        "accountant"
    ],
    "wof:name":"M B Cottle CPA",
    "wof:placetype":"venue"
},
  "geometry": {"coordinates":[-86.67160699999999,36.194927],"type":"Point"}
}