{
  "type": "Feature",
  "properties": {
    "iso:country":"US",
    "sg:address":"105 Hilltop Dr",
    "sg:city":"Chattanooga",
    "sg:classifiers":[
        {
            "category":"Professional",
            "type":"Services"
        }
    ],
    "sg:phone":"+1 423 624 7754",
    "sg:postcode":"37411",
    "sg:province":"TN",
    "wof:name":"A Knights Work",
    "wof:placetype":"venue"
},
  "geometry": {"coordinates":[-85.244485,35.018909],"type":"Point"}
}