{
  "type": "Feature",
  "properties": {
    "addr:full":"102 Cedar Ave Knoxville TN 37917",
    "addr:housenumber":"102",
    "addr:postcode":"37917",
    "addr:street":"Cedar Ave",
    "iso:country":"US",
    "sg:address":"102 Cedar Ave",
    "sg:city":"Knoxville",
    "sg:classifiers":[
        {
            "category":"Retail",
            "subcategory":"Auto Repair",
            "type":"Services"
        }
    ],
    "sg:phone":"+1 865 688 2100",
    "sg:postcode":"37917",
    "sg:province":"TN",
    "sg:tags":[
        "automotive"
    ],
    "wof:name":"Valvoline Instant Oil Change",
    "wof:placetype":"venue"
},
  "geometry": {"coordinates":[-83.946433,35.99541],"type":"Point"}
}