{
  "type": "Feature",
  "properties": {
    "iso:country":"US",
    "sg:address":"6514 Deane Hill Dr",
    "sg:city":"Knoxville",
    "sg:classifiers":[
        {
            "category":"Food & Beverages",
            "subcategory":"Liquor & Beverages",
            "type":"Retail Goods"
        }
    ],
    "sg:phone":"+1 865 693 2883",
    "sg:postcode":"37919",
    "sg:province":"TN",
    "sg:tags":[
        "beer",
        "ale"
    ],
    "wof:name":"Malt Beverage Media Svc",
    "wof:placetype":"venue"
},
  "geometry": {"coordinates":[-84.010463,35.929772],"type":"Point"}
}