{
  "type": "Feature",
  "properties": {
    "addr:full":"3700 S Mendenhall Rd Memphis TN 38115",
    "addr:housenumber":"3700",
    "addr:postcode":"38115",
    "addr:street":"S Mendenhall Rd",
    "iso:country":"US",
    "sg:address":"3700 S Mendenhall Rd",
    "sg:city":"Memphis",
    "sg:classifiers":[
        {
            "category":"Banks & Credit Unions",
            "subcategory":"Bank",
            "type":"Services"
        }
    ],
    "sg:phone":"+1 901 375 9733",
    "sg:postcode":"38115",
    "sg:province":"TN",
    "sg:tags":[
        "loan"
    ],
    "wof:name":"Mr Cash",
    "wof:placetype":"venue"
},
  "geometry": {"coordinates":[-89.886117,35.048209],"type":"Point"}
}