{
  "type": "Feature",
  "properties": {
    "addr:full":"269 Crystal Ln South Pittsburg TN 37380",
    "addr:housenumber":"269",
    "addr:postcode":"37380",
    "addr:street":"Crystal Ln",
    "iso:country":"US",
    "sg:address":"269 Crystal Ln",
    "sg:city":"South Pittsburg",
    "sg:classifiers":[
        {
            "category":"Restaurant",
            "type":"Food & Drink"
        }
    ],
    "sg:phone":"+1 423 837 7081",
    "sg:postcode":"37380",
    "sg:province":"TN",
    "wof:name":"Taco Bell",
    "wof:placetype":"venue"
},
  "geometry": {"coordinates":[-85.66488200000001,35.007038],"type":"Point"}
}