{
  "type": "Feature",
  "properties": {
    "iso:country":"US",
    "sg:address":"269 Crystal Ln",
    "sg:city":"South Pittsburg",
    "sg:classifiers":[
        {
            "category":"Restaurant",
            "type":"Food & Drink"
        }
    ],
    "sg:phone":"+1 423 837 7081",
    "sg:postcode":"37380",
    "sg:province":"TN",
    "wof:name":"Taco Bell",
    "wof:placetype":"venue"
},
  "geometry": {"coordinates":[-85.66488200000001,35.007038],"type":"Point"}
}