{
  "type": "Feature",
  "properties": {
    "iso:country":"US",
    "sg:address":"789 Miller Rd",
    "sg:city":"Clinton",
    "sg:classifiers":[
        {
            "category":"Building & Trades",
            "subcategory":"Landscaping Services",
            "type":"Services"
        }
    ],
    "sg:phone":"+1 865 494 7727",
    "sg:postcode":"37716",
    "sg:province":"TN",
    "sg:tags":[
        "lawn",
        "maintenance",
        "grounds"
    ],
    "wof:name":"Ron's Lawn Care",
    "wof:placetype":"venue"
},
  "geometry": {"coordinates":[-84.101833,36.165392],"type":"Point"}
}