{
  "type": "Feature",
  "properties": {
    "iso:country":"US",
    "sg:address":"23412 Beals Chapel Rd",
    "sg:city":"Lenoir City",
    "sg:classifiers":[
        {
            "category":"Shopping",
            "subcategory":"Hobbies, Toys, & Games",
            "type":"Retail Goods"
        }
    ],
    "sg:phone":"+1 865 986 1962",
    "sg:postcode":"37772",
    "sg:province":"TN",
    "sg:tags":[
        "doll"
    ],
    "wof:name":"ABC Dolls",
    "wof:placetype":"venue"
},
  "geometry": {"coordinates":[-84.194093,35.791557],"type":"Point"}
}