{
  "type": "Feature",
  "properties": {
    "iso:country":"US",
    "sg:address":"5455 Crestview Dr",
    "sg:city":"Memphis",
    "sg:classifiers":[
        {
            "category":"Wholesale",
            "subcategory":"Durable Goods & Equipment",
            "type":"Manufacturing & Wholesale Goods"
        }
    ],
    "sg:phone":"+1 901 386 3400",
    "sg:postcode":"38134",
    "sg:province":"TN",
    "sg:tags":[
        "representative",
        "manufacturer"
    ],
    "wof:name":"Glaco Inc",
    "wof:placetype":"venue"
},
  "geometry": {"coordinates":[-89.880634,35.170623],"type":"Point"}
}