{
  "type": "Feature",
  "properties": {
    "iso:country":"US",
    "sg:address":"179 Sunhaven Dr",
    "sg:city":"Jackson",
    "sg:classifiers":[
        {
            "category":"Retail",
            "subcategory":"Car Wash",
            "type":"Services"
        }
    ],
    "sg:phone":"+1 731 668 1633",
    "sg:postcode":"38305",
    "sg:province":"TN",
    "sg:tags":[
        "automobile",
        "detail",
        "clean"
    ],
    "wof:name":"First Class Mobile Detail",
    "wof:placetype":"venue"
},
  "geometry": {"coordinates":[-88.84070199999999,35.67947],"type":"Point"}
}