{
  "type": "Feature",
  "properties": {
    "iso:country":"US",
    "sg:address":"5858 Ridgeway Center Pkwy",
    "sg:city":"Memphis",
    "sg:classifiers":[
        {
            "category":"Real Estate",
            "subcategory":"Real Estate Operator",
            "type":"Services"
        }
    ],
    "sg:phone":"+1 901 683 3346",
    "sg:postcode":"38120",
    "sg:province":"TN",
    "sg:tags":[
        "condominium"
    ],
    "wof:name":"Condominum Management Asscts",
    "wof:placetype":"venue"
},
  "geometry": {"coordinates":[-89.865739,35.104905],"type":"Point"}
}