{
  "type": "Feature",
  "properties": {
    "iso:country":"US",
    "sg:address":"710 Shelby Shea Way",
    "sg:city":"Bolivar",
    "sg:classifiers":[
        {
            "category":"Real Estate",
            "subcategory":"Real Estate Operator",
            "type":"Services"
        }
    ],
    "sg:phone":"+1 731 658 6110",
    "sg:postcode":"38008",
    "sg:province":"TN",
    "sg:tags":[
        "mobile",
        "home",
        "community"
    ],
    "wof:name":"Bolivar Mobile Home Community",
    "wof:placetype":"venue"
},
  "geometry": {"coordinates":[-89.02205600000001,35.285666],"type":"Point"}
}