{
  "type": "Feature",
  "properties": {
    "iso:country":"US",
    "sg:address":"60 S Broad St",
    "sg:city":"Lexington",
    "sg:classifiers":[
        {
            "category":"Professional",
            "subcategory":"Detective & Security Services",
            "type":"Services"
        }
    ],
    "sg:phone":"+1 731 968 6403",
    "sg:postcode":"38351",
    "sg:province":"TN",
    "sg:tags":[
        "guard",
        "patrol"
    ],
    "wof:name":"Care Services Inc",
    "wof:placetype":"venue"
},
  "geometry": {"coordinates":[-88.39510300000001,35.649598],"type":"Point"}
}