{
  "type": "Feature",
  "properties": {
    "iso:country":"US",
    "sg:address":"114 Spicer Rd",
    "sg:city":"Gordonsville",
    "sg:classifiers":[
        {
            "category":"Manufacturing",
            "subcategory":"Motor Vehicles & Parts",
            "type":"Manufacturing & Wholesale Goods"
        }
    ],
    "sg:phone":"+1 615 683 3000",
    "sg:postcode":"38570",
    "sg:province":"TN",
    "sg:tags":[
        "automotive",
        "industry",
        "engineered",
        "for",
        "mfg"
    ],
    "wof:name":"Dura Automotive Systems Inc",
    "wof:placetype":"venue"
},
  "geometry": {"coordinates":[-85.33703800000001,36.35556],"type":"Point"}
}