{
  "type": "Feature",
  "properties": {
    "addr:full":"313 N Public Sq Smithville TN 37166",
    "addr:housenumber":"313",
    "addr:postcode":"37166",
    "addr:street":"N Public Sq",
    "iso:country":"US",
    "sg:address":"313 N Public Sq",
    "sg:city":"Smithville",
    "sg:classifiers":[
        {
            "category":"Shopping",
            "subcategory":"Gifts & Souvenirs",
            "type":"Retail Goods"
        }
    ],
    "sg:phone":"+1 615 597 4443",
    "sg:postcode":"37166",
    "sg:province":"TN",
    "sg:tags":[
        "shop"
    ],
    "wof:name":"De Kalb County Florist",
    "wof:placetype":"venue"
},
  "geometry": {"coordinates":[-85.81290199999999,35.96106],"type":"Point"}
}