{
  "type": "Feature",
  "properties": {
    "iso:country":"US",
    "sg:address":"1317 Hickory Valley Rd",
    "sg:city":"Chattanooga",
    "sg:classifiers":[
        {
            "category":"Professional",
            "subcategory":"Accounting & Tax Preparation",
            "type":"Services"
        }
    ],
    "sg:phone":"+1 423 499 8116",
    "sg:postcode":"37421",
    "sg:province":"TN",
    "sg:tags":[
        "accountant"
    ],
    "wof:name":"Steven A Scruggs CPA",
    "wof:placetype":"venue"
},
  "geometry": {"coordinates":[-85.181079,35.018534],"type":"Point"}
}