{
  "type": "Feature",
  "properties": {
    "addr:full":"4678 Lebanon Pike Hermitage TN 37076",
    "addr:housenumber":"4678",
    "addr:postcode":"37076",
    "addr:street":"Lebanon Pike",
    "iso:country":"US",
    "sg:address":"4678 Lebanon Pike",
    "sg:city":"Hermitage",
    "sg:classifiers":[
        {
            "category":"Personal",
            "subcategory":"Beauty Salon",
            "type":"Services"
        }
    ],
    "sg:phone":"+1 615 883 7421",
    "sg:postcode":"37076",
    "sg:province":"TN",
    "sg:tags":[
        "shop"
    ],
    "wof:name":"Supercuts",
    "wof:placetype":"venue"
},
  "geometry": {"coordinates":[-86.603426,36.2151],"type":"Point"}
}