{
  "type": "Feature",
  "properties": {
    "iso:country":"US",
    "sg:address":"3063 Airways Blvd",
    "sg:city":"Memphis",
    "sg:classifiers":[
        {
            "category":"Professional",
            "subcategory":"Management & Consulting",
            "type":"Services"
        }
    ],
    "sg:phone":"+1 901 396 8767",
    "sg:postcode":"38131",
    "sg:province":"TN",
    "sg:tags":[
        "retail",
        "direct",
        "sales"
    ],
    "wof:name":"Touch of Life",
    "wof:placetype":"venue"
},
  "geometry": {"coordinates":[-89.991235,35.062773],"type":"Point"}
}