{
  "type": "Feature",
  "properties": {
    "addr:full":"414 Edith Ave Memphis TN 38126",
    "addr:housenumber":"414",
    "addr:postcode":"38126",
    "addr:street":"Edith Ave",
    "iso:country":"US",
    "sg:address":"414 Edith Ave",
    "sg:city":"Memphis",
    "sg:classifiers":[
        {
            "category":"Place Of Worship",
            "type":"Public Place"
        }
    ],
    "sg:phone":"+1 901 948 2058",
    "sg:postcode":"38126",
    "sg:province":"TN",
    "sg:tags":[
        "church"
    ],
    "wof:name":"Higginbottom, E W Sr Rev",
    "wof:placetype":"venue"
},
  "geometry": {"coordinates":[-90.047989,35.116859],"type":"Point"}
}