{
  "type": "Feature",
  "properties": {
    "iso:country":"US",
    "sg:address":"3754 Park Ave",
    "sg:city":"Memphis",
    "sg:classifiers":[
        {
            "category":"Retail",
            "subcategory":"Laundry & Dry Cleaning",
            "type":"Services"
        }
    ],
    "sg:phone":"+1 901 458 1860",
    "sg:postcode":"38111",
    "sg:province":"TN",
    "sg:tags":[
        "cleaners",
        "rug",
        "carpet"
    ],
    "wof:name":"Budget Carpet Cleaners-Memphis",
    "wof:placetype":"venue"
},
  "geometry": {"coordinates":[-89.93678,35.10772],"type":"Point"}
}