{
  "type": "Feature",
  "properties": {
    "addr:full":"8521 Beaverwood Dr Germantown TN 38138",
    "addr:housenumber":"8521",
    "addr:postcode":"38138",
    "addr:street":"Beaverwood Dr",
    "iso:country":"US",
    "sg:address":"8521 Beaverwood Dr",
    "sg:city":"Germantown",
    "sg:classifiers":[
        {
            "category":"Professional",
            "subcategory":"Management & Consulting",
            "type":"Services"
        }
    ],
    "sg:phone":"+1 901 759 9490",
    "sg:postcode":"38138",
    "sg:province":"TN",
    "sg:tags":[
        "business"
    ],
    "wof:name":"Salisbury Group LLC",
    "wof:placetype":"venue"
},
  "geometry": {"coordinates":[-89.778587,35.066791],"type":"Point"}
}