{
  "type": "Feature",
  "properties": {
    "iso:country":"US",
    "sg:address":"2235 State Hwy 47",
    "sg:city":"White Bluff",
    "sg:classifiers":[
        {
            "category":"Real Estate",
            "subcategory":"Real Estate Operator",
            "type":"Services"
        }
    ],
    "sg:phone":"+1 615 797 5264",
    "sg:postcode":"37187",
    "sg:province":"TN",
    "sg:tags":[
        "building",
        "apartment"
    ],
    "wof:name":"Bluff Trace Apartments Ltd",
    "wof:placetype":"venue"
},
  "geometry": {"coordinates":[-87.22686299999999,36.120615],"type":"Point"}
}