{
  "type": "Feature",
  "properties": {
    "iso:country":"US",
    "sg:address":"4469 American Way",
    "sg:city":"Memphis",
    "sg:classifiers":[
        {
            "category":"Shopping",
            "subcategory":"Clothing, Apparel, & Fashions",
            "type":"Retail Goods"
        }
    ],
    "sg:phone":"+1 901 368 0094",
    "sg:postcode":"38118",
    "sg:province":"TN",
    "wof:name":"Simply Fashions Store 98",
    "wof:placetype":"venue"
},
  "geometry": {"coordinates":[-89.912733,35.071805],"type":"Point"}
}