{
  "type": "Feature",
  "properties": {
    "iso:country":"US",
    "sg:address":"2300 Rotary Park Dr",
    "sg:city":"Clarksville",
    "sg:classifiers":[
        {
            "category":"Wholesale",
            "subcategory":"Farm Supplies",
            "type":"Manufacturing & Wholesale Goods"
        }
    ],
    "sg:phone":"+1 931 503 0406",
    "sg:postcode":"37043",
    "sg:province":"TN",
    "wof:name":"Seasonal Gardens",
    "wof:placetype":"venue"
},
  "geometry": {"coordinates":[-87.272809,36.500538],"type":"Point"}
}