{
  "type": "Feature",
  "properties": {
    "iso:country":"US",
    "sg:address":"10529 Lexington Dr",
    "sg:city":"Knoxville",
    "sg:classifiers":[
        {
            "category":"Manufacturing",
            "subcategory":"Printing",
            "type":"Manufacturing & Wholesale Goods"
        }
    ],
    "sg:phone":"+1 865 525 2830",
    "sg:postcode":"37932",
    "sg:province":"TN",
    "wof:name":"Threds Inc",
    "wof:placetype":"venue"
},
  "geometry": {"coordinates":[-84.138834,35.910462],"type":"Point"}
}