{
  "type": "Feature",
  "properties": {
    "iso:country":"US",
    "sg:address":"5705 Commander Dr",
    "sg:city":"Arlington",
    "sg:classifiers":[
        {
            "category":"Manufacturing",
            "subcategory":"Metals",
            "type":"Manufacturing & Wholesale Goods"
        },
        {
            "category":"Professional",
            "subcategory":"Management & Consulting",
            "type":"Services"
        }
    ],
    "sg:phone":"+1 901 867 0039",
    "sg:postcode":"38002",
    "sg:province":"TN",
    "sg:tags":[
        "outdoor",
        "mfg",
        "marketing",
        "program",
        "fountain",
        "drinking"
    ],
    "sg:website":"www.mostdependable.com",
    "wof:name":"Most Dependable Fountains Inc",
    "wof:placetype":"venue"
},
  "geometry": {"coordinates":[-89.674378,35.280721],"type":"Point"}
}