{
  "type": "Feature",
  "properties": {
    "addr:full":"207 Short St Hornbeak TN 38232",
    "addr:housenumber":"207",
    "addr:postcode":"38232",
    "addr:street":"Short St",
    "iso:country":"US",
    "sg:address":"207 Short St",
    "sg:city":"Hornbeak",
    "sg:classifiers":[
        {
            "category":"Organizations",
            "subcategory":"Religious Organization",
            "type":"Services"
        }
    ],
    "sg:phone":"+1 731 538 9500",
    "sg:postcode":"38232",
    "sg:province":"TN",
    "sg:tags":[
        "church"
    ],
    "wof:name":"Hornbeak Baptist Church",
    "wof:placetype":"venue"
},
  "geometry": {"coordinates":[-89.296907,36.333975],"type":"Point"}
}