{
  "type": "Feature",
  "properties": {
    "addr:full":"6060 Maiden Ln Memphis TN 38120",
    "addr:housenumber":"6060",
    "addr:postcode":"38120",
    "addr:street":"Maiden Ln",
    "iso:country":"US",
    "sg:address":"6060 Maiden Ln",
    "sg:city":"Memphis",
    "sg:classifiers":[
        {
            "category":"Health Services",
            "subcategory":"Doctor",
            "type":"Services"
        }
    ],
    "sg:phone":"+1 901 680 0606",
    "sg:postcode":"38120",
    "sg:province":"TN",
    "sg:tags":[
        "clinic",
        "medical"
    ],
    "wof:name":"Marc S Silberberg MD",
    "wof:placetype":"venue"
},
  "geometry": {"coordinates":[-89.858949,35.11234],"type":"Point"}
}