{
  "type": "Feature",
  "properties": {
    "iso:country":"US",
    "sg:address":"516 Kraft St",
    "sg:city":"Clarksville",
    "sg:classifiers":[
        {
            "category":"Autos & Motor Vehicles",
            "subcategory":"Automobile Sales",
            "type":"Retail Goods"
        }
    ],
    "sg:phone":"+1 931 552 0590",
    "sg:postcode":"37040",
    "sg:province":"TN",
    "sg:tags":[
        "used"
    ],
    "wof:name":"Taylor Auto Sales",
    "wof:placetype":"venue"
},
  "geometry": {"coordinates":[-87.35683,36.541877],"type":"Point"}
}