{
  "type": "Feature",
  "properties": {
    "addr:full":"3950 Central Ave Memphis TN 38111",
    "addr:housenumber":"3950",
    "addr:postcode":"38111",
    "addr:street":"Central Ave",
    "iso:country":"US",
    "sg:address":"3950 Central Ave",
    "sg:city":"Memphis",
    "sg:classifiers":[
        {
            "category":"Health Services",
            "subcategory":"Doctor",
            "type":"Services"
        },
        {
            "category":"Health Services",
            "subcategory":"Clinic",
            "type":"Services"
        }
    ],
    "sg:phone":"+1 901 458 6291",
    "sg:postcode":"38111",
    "sg:province":"TN",
    "sg:tags":[
        "psychological",
        "psychologist"
    ],
    "wof:name":"Haynes Bradley P Psyd",
    "wof:placetype":"venue"
},
  "geometry": {"coordinates":[-89.930088,35.122779],"type":"Point"}
}