{
  "type": "Feature",
  "properties": {
    "addr:full":"4060 Trinity Rd Franklin TN 37067",
    "addr:housenumber":"4060",
    "addr:postcode":"37067",
    "addr:street":"Trinity Rd",
    "iso:country":"US",
    "sg:address":"4060 Trinity Rd",
    "sg:city":"Franklin",
    "sg:classifiers":[
        {
            "category":"Organizations",
            "subcategory":"Professional Association",
            "type":"Services"
        }
    ],
    "sg:phone":"+1 615 395 7541",
    "sg:postcode":"37067",
    "sg:province":"TN",
    "wof:name":"Impact Training Systems",
    "wof:placetype":"venue"
},
  "geometry": {"coordinates":[-86.752955,35.87527],"type":"Point"}
}