{
  "type": "Feature",
  "properties": {
    "iso:country":"US",
    "sg:address":"713 S 14th St",
    "sg:city":"Nashville",
    "sg:classifiers":[
        {
            "category":"Building & Trades",
            "subcategory":"Plumbing",
            "type":"Services"
        }
    ],
    "sg:phone":"+1 615 226 9877",
    "sg:postcode":"37206",
    "sg:province":"TN",
    "sg:tags":[
        "contractor"
    ],
    "wof:name":"Simmons Heating",
    "wof:placetype":"venue"
},
  "geometry": {"coordinates":[-86.74720000000001,36.167522],"type":"Point"}
}