{
  "type": "Feature",
  "properties": {
    "iso:country":"US",
    "sg:address":"459 Alcoa Trl",
    "sg:city":"Maryville",
    "sg:classifiers":[
        {
            "category":"Home & Garden",
            "subcategory":"Mobile Homes",
            "type":"Retail Goods"
        }
    ],
    "sg:phone":"+1 865 380 3000",
    "sg:postcode":"37804",
    "sg:province":"TN",
    "wof:name":"Clayton Homes Inc",
    "wof:placetype":"venue"
},
  "geometry": {"coordinates":[-83.94622099999999,35.812525],"type":"Point"}
}