{
  "type": "Feature",
  "properties": {
    "iso:country":"US",
    "sg:address":"6010 Dunham Springs Rd",
    "sg:city":"Nashville",
    "sg:classifiers":[
        {
            "category":"Building & Trades",
            "subcategory":"Construction",
            "type":"Services"
        }
    ],
    "sg:phone":"+1 615 352 7222",
    "sg:postcode":"37205",
    "sg:province":"TN",
    "sg:tags":[
        "contractor"
    ],
    "wof:name":"Bolton Ventures LLC",
    "wof:placetype":"venue"
},
  "geometry": {"coordinates":[-86.870295,36.126936],"type":"Point"}
}