{
  "type": "Feature",
  "properties": {
    "iso:country":"US",
    "sg:address":"355 Belvedere Dr N",
    "sg:city":"Gallatin",
    "sg:classifiers":[
        {
            "category":"Government",
            "subcategory":"Office",
            "type":"Public Place"
        }
    ],
    "sg:phone":"+1 615 451 5858",
    "sg:postcode":"37066",
    "sg:province":"TN",
    "sg:tags":[
        "county",
        "program"
    ],
    "wof:name":"Sumner County Environmental",
    "wof:placetype":"venue"
},
  "geometry": {"coordinates":[-86.48056099999999,36.37988],"type":"Point"}
}