{
  "type": "Feature",
  "properties": {
    "addr:full":"710 State Hwy 57 Collierville TN 38017",
    "addr:housenumber":"710",
    "addr:postcode":"38017",
    "addr:street":"State Hwy 57",
    "iso:country":"US",
    "sg:address":"710 State Hwy 57",
    "sg:city":"Collierville",
    "sg:classifiers":[
        {
            "category":"Home & Garden",
            "subcategory":"Building Materials",
            "type":"Retail Goods"
        }
    ],
    "sg:phone":"+1 901 854 7733",
    "sg:postcode":"38017",
    "sg:province":"TN",
    "sg:tags":[
        "shutter"
    ],
    "sg:website":"www.customshutterstore.com",
    "wof:name":"Custom Shutter Store LLC",
    "wof:placetype":"venue"
},
  "geometry": {"coordinates":[-89.685828,35.04611],"type":"Point"}
}