{
  "type": "Feature",
  "properties": {
    "iso:country":"US",
    "sg:address":"923 W Baxter Ave",
    "sg:city":"Knoxville",
    "sg:classifiers":[
        {
            "category":"Organizations",
            "subcategory":"Religious Organization",
            "type":"Services"
        }
    ],
    "sg:phone":"+1 865 546 1199",
    "sg:postcode":"37921",
    "sg:province":"TN",
    "sg:tags":[
        "church"
    ],
    "wof:name":"West Baxter Avenue Bapt Church",
    "wof:placetype":"venue"
},
  "geometry": {"coordinates":[-83.937891,35.975285],"type":"Point"}
}