{
  "type": "Feature",
  "properties": {
    "iso:country":"US",
    "sg:address":"9651 Fredonia Rd",
    "sg:city":"Manchester",
    "sg:classifiers":[
        {
            "category":"Farming",
            "subcategory":"Nursery",
            "type":"Manufacturing & Wholesale Goods"
        }
    ],
    "sg:phone":"+1 931 394 2713",
    "sg:postcode":"37355",
    "sg:province":"TN",
    "sg:tags":[
        "ornamental"
    ],
    "wof:name":"Gands Greenhouse",
    "wof:placetype":"venue"
},
  "geometry": {"coordinates":[-86.144336,35.617777],"type":"Point"}
}