{
  "type": "Feature",
  "properties": {
    "iso:country":"US",
    "sg:address":"215 N Broadway",
    "sg:city":"Portland",
    "sg:classifiers":[
        {
            "category":"Autos & Motor Vehicles",
            "subcategory":"Automobile Sales",
            "type":"Retail Goods"
        }
    ],
    "sg:phone":"+1 615 325 3388",
    "sg:postcode":"37148",
    "sg:province":"TN",
    "sg:tags":[
        "car",
        "dealer"
    ],
    "wof:name":"Portland Auto Sales & Svc",
    "wof:placetype":"venue"
},
  "geometry": {"coordinates":[-86.516685,36.58311],"type":"Point"}
}