{
  "type": "Feature",
  "properties": {
    "iso:country":"US",
    "sg:address":"430 Airport Rd",
    "sg:city":"Greeneville",
    "sg:classifiers":[
        {
            "category":"Professional",
            "subcategory":"Employment Agencies",
            "type":"Services"
        }
    ],
    "sg:phone":"+1 423 636 7259",
    "sg:postcode":"37745",
    "sg:province":"TN",
    "sg:tags":[
        "operator",
        "supply",
        "help",
        "trucking"
    ],
    "wof:name":"Sky Knight LLC",
    "wof:placetype":"venue"
},
  "geometry": {"coordinates":[-82.805086,36.193547],"type":"Point"}
}