{
  "type": "Feature",
  "properties": {
    "iso:country":"US",
    "sg:address":"1212 Murfreesboro Rd",
    "sg:city":"Franklin",
    "sg:classifiers":[
        {
            "category":"Retail",
            "subcategory":"Auto Repair",
            "type":"Services"
        }
    ],
    "sg:phone":"+1 615 591 7024",
    "sg:postcode":"37064",
    "sg:province":"TN",
    "sg:tags":[
        "automotive"
    ],
    "wof:name":"Valvoline Instant Oil Change",
    "wof:placetype":"venue"
},
  "geometry": {"coordinates":[-86.83117900000001,35.915589],"type":"Point"}
}