{
  "type": "Feature",
  "properties": {
    "iso:country":"US",
    "sg:address":"6925 Shallowford Rd",
    "sg:city":"Chattanooga",
    "sg:classifiers":[
        {
            "category":"Restaurant",
            "type":"Food & Drink"
        }
    ],
    "sg:menulink":"http://www.allmenus.com/tn/chattanooga/247426-the-palms/menu/",
    "sg:phone":"+1 423 499 5055",
    "sg:postcode":"37421",
    "sg:province":"TN",
    "sg:tags":[
        "american"
    ],
    "wof:name":"The Palms",
    "wof:placetype":"venue"
},
  "geometry": {"coordinates":[-85.16127400000001,35.044614],"type":"Point"}
}