{
  "type": "Feature",
  "properties": {
    "addr:full":"8718 S Northshore Dr Knoxville TN 37922",
    "addr:housenumber":"8718",
    "addr:postcode":"37922",
    "addr:street":"S Northshore Dr",
    "iso:country":"US",
    "sg:address":"8718 S Northshore Dr",
    "sg:city":"Knoxville",
    "sg:classifiers":[
        {
            "category":"Home & Garden",
            "subcategory":"Garden Supply",
            "type":"Retail Goods"
        }
    ],
    "sg:phone":"+1 865 692 0052",
    "sg:postcode":"37922",
    "sg:province":"TN",
    "sg:tags":[
        "nurseryman"
    ],
    "wof:name":"Creekside Nurseries",
    "wof:placetype":"venue"
},
  "geometry": {"coordinates":[-84.04002,35.880625],"type":"Point"}
}