{
  "type": "Feature",
  "properties": {
    "iso:country":"US",
    "sg:address":"1200 Peabody Ave",
    "sg:city":"Memphis",
    "sg:classifiers":[
        {
            "category":"Health Services",
            "subcategory":"Doctor",
            "type":"Services"
        }
    ],
    "sg:phone":"+1 901 272 0003",
    "sg:postcode":"38104",
    "sg:province":"TN",
    "sg:tags":[
        "physician",
        "surgeon"
    ],
    "wof:name":"Church Health Ctr",
    "wof:placetype":"venue"
},
  "geometry": {"coordinates":[-90.02230400000001,35.132858],"type":"Point"}
}