{
  "type": "Feature",
  "properties": {
    "addr:full":"300 W Watauga Ave Johnson City TN 37604",
    "addr:housenumber":"300",
    "addr:postcode":"37604",
    "addr:street":"W Watauga Ave",
    "iso:country":"US",
    "sg:address":"300 W Watauga Ave",
    "sg:city":"Johnson City",
    "sg:classifiers":[
        {
            "category":"Health Services",
            "subcategory":"Doctor",
            "type":"Services"
        }
    ],
    "sg:phone":"+1 423 926 0135",
    "sg:postcode":"37604",
    "sg:province":"TN",
    "wof:name":"H Lee Malone DDS",
    "wof:placetype":"venue"
},
  "geometry": {"coordinates":[-82.359403,36.31807],"type":"Point"}
}