{
  "type": "Feature",
  "properties": {
    "addr:full":"215 Broad St Chattanooga TN 37402",
    "addr:housenumber":"215",
    "addr:postcode":"37402",
    "addr:street":"Broad St",
    "iso:country":"US",
    "sg:address":"215 Broad St",
    "sg:city":"Chattanooga",
    "sg:classifiers":[
        {
            "category":"Retail",
            "subcategory":"Auto Repair",
            "type":"Services"
        }
    ],
    "sg:phone":"+1 423 266 6190",
    "sg:postcode":"37402",
    "sg:province":"TN",
    "sg:tags":[
        "general"
    ],
    "wof:name":"Carta North Garage",
    "wof:placetype":"venue"
},
  "geometry": {"coordinates":[-85.31089799999999,35.054389],"type":"Point"}
}