{
  "type": "Feature",
  "properties": {
    "iso:country":"US",
    "sg:address":"8 Stonebridge Blvd",
    "sg:city":"Jackson",
    "sg:classifiers":[
        {
            "category":"Banks & Credit Unions",
            "subcategory":"Investment Brokerage",
            "type":"Services"
        }
    ],
    "sg:phone":"+1 731 668 9774",
    "sg:postcode":"38305",
    "sg:province":"TN",
    "sg:tags":[
        "security"
    ],
    "wof:name":"Browning Investment Group",
    "wof:placetype":"venue"
},
  "geometry": {"coordinates":[-88.85374400000001,35.671851],"type":"Point"}
}