{
  "type": "Feature",
  "properties": {
    "iso:country":"US",
    "sg:address":"1314 6th Ave N",
    "sg:city":"Nashville",
    "sg:classifiers":[
        {
            "category":"Building & Trades",
            "subcategory":"Construction",
            "type":"Services"
        }
    ],
    "sg:phone":"+1 615 256 6144",
    "sg:postcode":"37208",
    "sg:province":"TN",
    "sg:tags":[
        "general",
        "contractor"
    ],
    "sg:website":"www.kiddway.com",
    "wof:name":"Kiddway Corp",
    "wof:placetype":"venue"
},
  "geometry": {"coordinates":[-86.79034299999999,36.176523],"type":"Point"}
}