{
  "type": "Feature",
  "properties": {
    "iso:country":"US",
    "sg:address":"4622 Lebanon Pike",
    "sg:city":"Hermitage",
    "sg:classifiers":[
        {
            "category":"Personal",
            "subcategory":"Beauty Salon",
            "type":"Services"
        }
    ],
    "sg:phone":"+1 615 889 6661",
    "sg:postcode":"37076",
    "sg:province":"TN",
    "sg:tags":[
        "shop"
    ],
    "wof:name":"Alexs VIP Hair Lounge",
    "wof:placetype":"venue"
},
  "geometry": {"coordinates":[-86.599255,36.2152],"type":"Point"}
}