{
  "type": "Feature",
  "properties": {
    "addr:full":"710 1st St Lawrenceburg TN 38464",
    "addr:housenumber":"710",
    "addr:postcode":"38464",
    "addr:street":"1St St",
    "iso:country":"US",
    "sg:address":"710 1st St",
    "sg:city":"Lawrenceburg",
    "sg:classifiers":[
        {
            "category":"Real Estate",
            "subcategory":"Developer",
            "type":"Services"
        }
    ],
    "sg:phone":"+1 931 762 8751",
    "sg:postcode":"38464",
    "sg:province":"TN",
    "sg:tags":[
        "cemetery"
    ],
    "wof:name":"Blair Cemetery Inc",
    "wof:placetype":"venue"
},
  "geometry": {"coordinates":[-87.31564,35.243001],"type":"Point"}
}