{
  "type": "Feature",
  "properties": {
    "addr:full":"106 Mason Ct Franklin TN 37055",
    "addr:housenumber":"106",
    "addr:postcode":"37055",
    "addr:street":"Mason Ct",
    "iso:country":"US",
    "sg:address":"106 Mason Ct",
    "sg:city":"Franklin",
    "sg:classifiers":[
        {
            "category":"Professional",
            "subcategory":"Business Services",
            "type":"Services"
        }
    ],
    "sg:phone":"+1 615 771 9595",
    "sg:postcode":"37055",
    "sg:province":"TN",
    "sg:tags":[
        "notary"
    ],
    "wof:name":"Golden State Notary",
    "wof:placetype":"venue"
},
  "geometry": {"coordinates":[-87.37508800000001,36.063191],"type":"Point"}
}