{
  "type": "Feature",
  "properties": {
    "iso:country":"US",
    "sg:address":"241 Taylor Rd",
    "sg:city":"Bradford",
    "sg:phone":"+1 731 742 2882",
    "sg:postcode":"38316",
    "sg:province":"TN",
    "sg:tags":[
        "farm",
        "corn",
        "wheat",
        "soybean"
    ],
    "wof:name":"Ronnie Arnold",
    "wof:placetype":"venue"
},
  "geometry": {"coordinates":[-88.77739699999999,36.099212],"type":"Point"}
}