{
  "type": "Feature",
  "properties": {
    "addr:full":"16035 Highland Dr Mc Kenzie TN 38201",
    "addr:housenumber":"16035",
    "addr:postcode":"38201",
    "addr:street":"Highland Dr",
    "iso:country":"US",
    "sg:address":"16035 Highland Dr",
    "sg:city":"Mc Kenzie",
    "sg:classifiers":[
        {
            "category":"Home & Garden",
            "subcategory":"Carpets & Floor Coverings",
            "type":"Retail Goods"
        }
    ],
    "sg:phone":"+1 731 352 2139",
    "sg:postcode":"38201",
    "sg:province":"TN",
    "sg:tags":[
        "dealer",
        "rug"
    ],
    "wof:name":"Tommy's Carpet",
    "wof:placetype":"venue"
},
  "geometry": {"coordinates":[-88.510204,36.128635],"type":"Point"}
}