{
  "type": "Feature",
  "properties": {
    "iso:country":"US",
    "sg:address":"16 Fredonia Rd",
    "sg:city":"Crossville",
    "sg:classifiers":[
        {
            "category":"Retail",
            "subcategory":"Animal Services",
            "type":"Services"
        }
    ],
    "sg:phone":"+1 423 949 9513",
    "sg:postcode":"38571",
    "sg:province":"TN",
    "sg:tags":[
        "pet",
        "grooming",
        "washing"
    ],
    "wof:name":"Lil's Grooming Salon",
    "wof:placetype":"venue"
},
  "geometry": {"coordinates":[-85.04670299999999,36.016882],"type":"Point"}
}