{
  "type": "Feature",
  "properties": {
    "addr:full":"305 W Broad St Smithville TN 37166",
    "addr:housenumber":"305",
    "addr:postcode":"37166",
    "addr:street":"W Broad St",
    "iso:country":"US",
    "sg:address":"305 W Broad St",
    "sg:city":"Smithville",
    "sg:classifiers":[
        {
            "category":"Restaurant",
            "type":"Food & Drink"
        }
    ],
    "sg:phone":"+1 615 597 1022",
    "sg:postcode":"37166",
    "sg:province":"TN",
    "wof:name":"Susie's Restaurant",
    "wof:placetype":"venue"
},
  "geometry": {"coordinates":[-85.817685,35.957569],"type":"Point"}
}