{
  "type": "Feature",
  "properties": {
    "iso:country":"US",
    "sg:address":"1219 Finley Rd",
    "sg:city":"Memphis",
    "sg:classifiers":[
        {
            "category":"Communications",
            "type":"Services"
        }
    ],
    "sg:phone":"+1 901 888 4639",
    "sg:postcode":"38116",
    "sg:province":"TN",
    "sg:tags":[
        "carrier"
    ],
    "wof:name":"RNC Communications",
    "wof:placetype":"venue"
},
  "geometry": {"coordinates":[-90.024675,35.029657],"type":"Point"}
}