{
  "type": "Feature",
  "properties": {
    "iso:country":"US",
    "sg:address":"88 Hillview Dr",
    "sg:city":"Munford",
    "sg:classifiers":[
        {
            "category":"Autos & Motor Vehicles",
            "subcategory":"Motorcycle Sales",
            "type":"Retail Goods"
        }
    ],
    "sg:phone":"+1 901 837 4808",
    "sg:postcode":"38058",
    "sg:province":"TN",
    "sg:tags":[
        "scooter"
    ],
    "wof:name":"American Roadrider",
    "wof:placetype":"venue"
},
  "geometry": {"coordinates":[-89.824038,35.444991],"type":"Point"}
}