{
  "type": "Feature",
  "properties": {
    "addr:full":"2207 Ealing Cir Germantown TN 38138",
    "addr:housenumber":"2207",
    "addr:postcode":"38138",
    "addr:street":"Ealing Cir",
    "iso:country":"US",
    "sg:address":"2207 Ealing Cir",
    "sg:city":"Germantown",
    "sg:classifiers":[
        {
            "category":"Professional",
            "type":"Services"
        }
    ],
    "sg:phone":"+1 901 624 2090",
    "sg:postcode":"38138",
    "sg:province":"TN",
    "wof:name":"Amco Service Corp Of",
    "wof:placetype":"venue"
},
  "geometry": {"coordinates":[-89.799442,35.089432],"type":"Point"}
}