{
  "type": "Feature",
  "properties": {
    "iso:country":"US",
    "sg:address":"651 S Riverside Dr",
    "sg:city":"Clarksville",
    "sg:classifiers":[
        {
            "category":"Shopping",
            "subcategory":"Bicycles & Sporting Goods",
            "type":"Retail Goods"
        }
    ],
    "sg:phone":"+1 931 553 8553",
    "sg:postcode":"37040",
    "sg:province":"TN",
    "wof:name":"Magoos Sports Bar",
    "wof:placetype":"venue"
},
  "geometry": {"coordinates":[-87.363024,36.519777],"type":"Point"}
}