{
  "type": "Feature",
  "properties": {
    "addr:full":"152 W Main St Linden TN 37096",
    "addr:housenumber":"152",
    "addr:postcode":"37096",
    "addr:street":"W Main St",
    "iso:country":"US",
    "sg:address":"152 W Main St",
    "sg:city":"Linden",
    "sg:classifiers":[
        {
            "category":"Retail",
            "subcategory":"Repair Shop",
            "type":"Services"
        }
    ],
    "sg:phone":"+1 931 589 9548",
    "sg:postcode":"37096",
    "sg:province":"TN",
    "sg:tags":[
        "related"
    ],
    "wof:name":"Linden Repair Svc Computer Ln",
    "wof:placetype":"venue"
},
  "geometry": {"coordinates":[-87.839685,35.617123],"type":"Point"}
}