{
  "type": "Feature",
  "properties": {
    "iso:country":"US",
    "sg:address":"1012 Gilmore Ave",
    "sg:city":"Nashville",
    "sg:classifiers":[
        {
            "category":"Organizations",
            "subcategory":"Religious Organization",
            "type":"Services"
        }
    ],
    "sg:phone":"+1 615 269 9179",
    "sg:postcode":"37204",
    "sg:province":"TN",
    "wof:name":"Hands of God Christian Outrch",
    "wof:placetype":"venue"
},
  "geometry": {"coordinates":[-86.787789,36.124649],"type":"Point"}
}