{
  "type": "Feature",
  "properties": {
    "iso:country":"US",
    "sg:address":"272 California Ave",
    "sg:city":"Dayton",
    "sg:classifiers":[
        {
            "category":"Government",
            "subcategory":"Office",
            "type":"Public Place"
        }
    ],
    "sg:phone":"+1 423 775 8418",
    "sg:postcode":"37321",
    "sg:province":"TN",
    "sg:tags":[
        "village"
    ],
    "wof:name":"Dayton Maintenance Dept",
    "wof:placetype":"venue"
},
  "geometry": {"coordinates":[-85.022109,35.490514],"type":"Point"}
}