{
  "type": "Feature",
  "properties": {
    "addr:full":"3301 Trevor St Nashville TN 37209",
    "addr:housenumber":"3301",
    "addr:postcode":"37209",
    "addr:street":"Trevor St",
    "iso:country":"US",
    "sg:address":"3301 Trevor St",
    "sg:city":"Nashville",
    "sg:classifiers":[
        {
            "category":"Building & Trades",
            "subcategory":"Plumbing",
            "type":"Services"
        }
    ],
    "sg:phone":"+1 615 329 3636",
    "sg:postcode":"37209",
    "sg:province":"TN",
    "sg:tags":[
        "contractor"
    ],
    "wof:name":"Howard Groves",
    "wof:placetype":"venue"
},
  "geometry": {"coordinates":[-86.824322,36.154299],"type":"Point"}
}