{
  "type": "Feature",
  "properties": {
    "addr:full":"4973 Hwy 127 S Crossville TN 38572",
    "addr:housenumber":"4973",
    "addr:postcode":"38572",
    "addr:street":"Hwy 127 S",
    "iso:country":"US",
    "sg:address":"4973 Hwy 127 S",
    "sg:city":"Crossville",
    "sg:classifiers":[
        {
            "category":"Professional",
            "type":"Services"
        }
    ],
    "sg:phone":"+1 931 707 9911",
    "sg:postcode":"38572",
    "sg:province":"TN",
    "sg:tags":[
        "establishment"
    ],
    "wof:name":"Letter Bug",
    "wof:placetype":"venue"
},
  "geometry": {"coordinates":[-84.995642,35.891152],"type":"Point"}
}