{
  "type": "Feature",
  "properties": {
    "addr:full":"2018 Memorial Blvd Springfield TN 37172",
    "addr:housenumber":"2018",
    "addr:postcode":"37172",
    "addr:street":"Memorial Blvd",
    "iso:country":"US",
    "sg:address":"2018 Memorial Blvd",
    "sg:city":"Springfield",
    "sg:classifiers":[
        {
            "category":"Restaurant",
            "type":"Food & Drink"
        }
    ],
    "sg:menulink":"http://www.allmenus.com/tn/springfield-greenbrier/214932-burger-king/menu/",
    "sg:phone":"+1 615 382 0083",
    "sg:postcode":"37172",
    "sg:province":"TN",
    "sg:tags":[
        "burger",
        "american"
    ],
    "wof:name":"Burger King",
    "wof:placetype":"venue"
},
  "geometry": {"coordinates":[-86.877976,36.494759],"type":"Point"}
}