{
  "type": "Feature",
  "properties": {
    "addr:full":"42 Ball Park Rd Summertown TN 38483",
    "addr:housenumber":"42",
    "addr:postcode":"38483",
    "addr:street":"Ball Park Rd",
    "iso:country":"US",
    "sg:address":"42 Ball Park Rd",
    "sg:city":"Summertown",
    "sg:classifiers":[
        {
            "category":"Social Services",
            "type":"Services"
        }
    ],
    "sg:phone":"+1 931 964 3551",
    "sg:postcode":"38483",
    "sg:province":"TN",
    "sg:tags":[
        "youth",
        "organization",
        "center"
    ],
    "wof:name":"Summertown Dixie Youth",
    "wof:placetype":"venue"
},
  "geometry": {"coordinates":[-87.31619999999999,35.445237],"type":"Point"}
}