{
  "type": "Feature",
  "properties": {
    "addr:full":"2321 Campbell Park Dr Columbia TN 38401",
    "addr:housenumber":"2321",
    "addr:postcode":"38401",
    "addr:street":"Campbell Park Dr",
    "iso:country":"US",
    "sg:address":"2321 Campbell Park Dr",
    "sg:city":"Columbia",
    "sg:classifiers":[
        {
            "category":"Professional",
            "type":"Services"
        }
    ],
    "sg:phone":"+1 931 540 0780",
    "sg:postcode":"38401",
    "sg:province":"TN",
    "wof:name":"Xtreme Liners of Columbia",
    "wof:placetype":"venue"
},
  "geometry": {"coordinates":[-87.032448,35.589701],"type":"Point"}
}