{
  "type": "Feature",
  "properties": {
    "addr:full":"955 Pickard Rd Cottage Grove TN 38224",
    "addr:housenumber":"955",
    "addr:postcode":"38224",
    "addr:street":"Pickard Rd",
    "iso:country":"US",
    "sg:address":"955 Pickard Rd",
    "sg:city":"Cottage Grove",
    "sg:classifiers":[
        {
            "category":"Professional",
            "type":"Services"
        }
    ],
    "sg:phone":"+1 731 782 3953",
    "sg:postcode":"38224",
    "sg:province":"TN",
    "wof:name":"Derksen Portable Bui",
    "wof:placetype":"venue"
},
  "geometry": {"coordinates":[-88.493833,36.398831],"type":"Point"}
}