{
  "type": "Feature",
  "properties": {
    "addr:full":"2105 Madison Grove Ln Knoxville TN 37922",
    "addr:housenumber":"2105",
    "addr:postcode":"37922",
    "addr:street":"Madison Grove Ln",
    "iso:country":"US",
    "sg:address":"2105 Madison Grove Ln",
    "sg:city":"Knoxville",
    "sg:classifiers":[
        {
            "category":"Home & Garden",
            "subcategory":"Furniture",
            "type":"Retail Goods"
        }
    ],
    "sg:phone":"+1 865 691 9596",
    "sg:postcode":"37922",
    "sg:province":"TN",
    "wof:name":"Slumber Parties By Angie",
    "wof:placetype":"venue"
},
  "geometry": {"coordinates":[-84.041088,35.87527],"type":"Point"}
}