{
  "type": "Feature",
  "properties": {
    "iso:country":"US",
    "sg:address":"104 Kay Ln",
    "sg:city":"Somerville",
    "sg:classifiers":[
        {
            "category":"Shopping",
            "subcategory":"Florist",
            "type":"Retail Goods"
        }
    ],
    "sg:phone":"+1 901 465 3674",
    "sg:postcode":"38068",
    "sg:province":"TN",
    "wof:name":"Myers Flower & Gift Shop",
    "wof:placetype":"venue"
},
  "geometry": {"coordinates":[-89.349315,35.227804],"type":"Point"}
}