{
  "type": "Feature",
  "properties": {
    "addr:full":"1199 Murfreesboro Pike Nashville TN 37217",
    "addr:housenumber":"1199",
    "addr:postcode":"37217",
    "addr:street":"Murfreesboro Pike",
    "iso:country":"US",
    "sg:address":"1199 Murfreesboro Pike",
    "sg:city":"Nashville",
    "sg:classifiers":[
        {
            "category":"Building & Trades",
            "subcategory":"Construction",
            "type":"Services"
        }
    ],
    "sg:phone":"+1 615 399 7189",
    "sg:postcode":"37217",
    "sg:province":"TN",
    "sg:tags":[
        "contractor"
    ],
    "wof:name":"M&M Roofing",
    "wof:placetype":"venue"
},
  "geometry": {"coordinates":[-86.704835,36.121822],"type":"Point"}
}