{
  "type": "Feature",
  "properties": {
    "addr:full":"10992 Hwy 51 S Atoka TN 38004",
    "addr:housenumber":"10992",
    "addr:postcode":"38004",
    "addr:street":"Hwy 51 S",
    "iso:country":"US",
    "sg:address":"10992 Hwy 51 S",
    "sg:city":"Atoka",
    "sg:classifiers":[
        {
            "category":"Health Services",
            "subcategory":"Health Practitioner",
            "type":"Services"
        }
    ],
    "sg:phone":"+1 901 383 8686",
    "sg:postcode":"38004",
    "sg:province":"TN",
    "sg:tags":[
        "therapist",
        "physical"
    ],
    "wof:name":"Mid-South Physical Therapy Inc",
    "wof:placetype":"venue"
},
  "geometry": {"coordinates":[-89.784254,35.447317],"type":"Point"}
}