{
  "type": "Feature",
  "properties": {
    "addr:full":"1717 Airbase Rd Louisville TN 37777",
    "addr:postcode":"1717;37777",
    "addr:street":"Airbase Rd",
    "iso:country":"US",
    "sg:address":"1717 Airbase Rd",
    "sg:city":"Louisville",
    "sg:classifiers":[
        {
            "category":"Retail",
            "subcategory":"Car Wash",
            "type":"Services"
        }
    ],
    "sg:phone":"+1 865 977 6472",
    "sg:postcode":"37777",
    "sg:province":"TN",
    "sg:tags":[
        "automobile",
        "detail",
        "clean"
    ],
    "wof:name":"Twin City Detail Shop",
    "wof:placetype":"venue"
},
  "geometry": {"coordinates":[-83.975818,35.831636],"type":"Point"}
}