{
  "type": "Feature",
  "properties": {
    "iso:country":"US",
    "sg:address":"3300 W Market St",
    "sg:city":"Johnson City",
    "sg:classifiers":[
        {
            "category":"Restaurant",
            "type":"Food & Drink"
        }
    ],
    "sg:menulink":"http://www.allmenus.com/tn/johnson-city/191700-sonic/menu/",
    "sg:phone":"+1 423 975 0015",
    "sg:postcode":"37604",
    "sg:province":"TN",
    "sg:tags":[
        "burger",
        "american"
    ],
    "wof:name":"Sonic",
    "wof:placetype":"venue"
},
  "geometry": {"coordinates":[-82.41215200000001,36.312146],"type":"Point"}
}