{
  "type": "Feature",
  "properties": {
    "iso:country":"US",
    "sg:address":"1007 N Cumberland St",
    "sg:city":"Lebanon",
    "sg:classifiers":[
        {
            "category":"Sports & Exercise",
            "subcategory":"Bowling",
            "type":"Entertainment"
        }
    ],
    "sg:phone":"+1 615 449 0876",
    "sg:postcode":"37087",
    "sg:province":"TN",
    "sg:tags":[
        "center"
    ],
    "wof:name":"Lebanon Lanes",
    "wof:placetype":"venue"
},
  "geometry": {"coordinates":[-86.29018000000001,36.225142],"type":"Point"}
}