{
  "type": "Feature",
  "properties": {
    "addr:full":"11803 Kingston Pike Knoxville TN 37934",
    "addr:housenumber":"11803",
    "addr:postcode":"37934",
    "addr:street":"Kingston Pike",
    "iso:country":"US",
    "sg:address":"11803 Kingston Pike",
    "sg:city":"Knoxville",
    "sg:classifiers":[
        {
            "category":"Professional",
            "subcategory":"Testing Lab",
            "type":"Services"
        }
    ],
    "sg:phone":"+1 865 966 0750",
    "sg:postcode":"37934",
    "sg:province":"TN",
    "sg:tags":[
        "measuring",
        "air",
        "pollution"
    ],
    "wof:name":"Ambientaire",
    "wof:placetype":"venue"
},
  "geometry": {"coordinates":[-84.17495700000001,35.874783],"type":"Point"}
}