{
  "type": "Feature",
  "properties": {
    "iso:country":"US",
    "sg:address":"5628 Pleasant View Rd",
    "sg:city":"Memphis",
    "sg:classifiers":[
        {
            "category":"Wholesale",
            "subcategory":"Stationery",
            "type":"Manufacturing & Wholesale Goods"
        },
        {
            "category":"Professional",
            "subcategory":"Advertising",
            "type":"Services"
        }
    ],
    "sg:phone":"+1 901 525 3614",
    "sg:postcode":"38134",
    "sg:province":"TN",
    "sg:tags":[
        "sup",
        "m",
        "specialty",
        "mfg"
    ],
    "sg:website":"www.mccormickbusinessproducts.com",
    "wof:name":"Mc Cormick Business Products",
    "wof:placetype":"venue"
},
  "geometry": {"coordinates":[-89.87619599999999,35.173482],"type":"Point"}
}