{
  "type": "Feature",
  "properties": {
    "iso:country":"US",
    "sg:address":"9307 Kingston Pike",
    "sg:city":"Knoxville",
    "sg:classifiers":[
        {
            "category":"Banks & Credit Unions",
            "subcategory":"Bank",
            "type":"Services"
        }
    ],
    "sg:phone":"+1 865 539 4344",
    "sg:postcode":"37922",
    "sg:province":"TN",
    "wof:name":"Oak Ridge Federal Credit Union",
    "wof:placetype":"venue"
},
  "geometry": {"coordinates":[-84.095381,35.910189],"type":"Point"}
}