{
  "type": "Feature",
  "properties": {
    "addr:full":"938 Gilchrist Stantonville Rd Adamsville TN 38310",
    "addr:housenumber":"938",
    "addr:postcode":"38310",
    "addr:street":"Gilchrist Stantonville Rd",
    "iso:country":"US",
    "sg:address":"938 Gilchrist Stantonville Rd",
    "sg:city":"Adamsville",
    "sg:classifiers":[
        {
            "category":"Manufacturing",
            "subcategory":"Apparel",
            "type":"Manufacturing & Wholesale Goods"
        }
    ],
    "sg:phone":"+1 731 632 3353",
    "sg:postcode":"38310",
    "sg:province":"TN",
    "sg:tags":[
        "house",
        "furnishing",
        "drapery"
    ],
    "sg:website":"www.sportscushions.com",
    "wof:name":"Sports Production LTD",
    "wof:placetype":"venue"
},
  "geometry": {"coordinates":[-88.428076,35.205806],"type":"Point"}
}