{
  "type": "Feature",
  "properties": {
    "iso:country":"US",
    "sg:address":"1725 Main St",
    "sg:city":"Tazewell",
    "sg:classifiers":[
        {
            "category":"Professional",
            "subcategory":"Business Services",
            "type":"Services"
        }
    ],
    "sg:phone":"+1 423 626 5592",
    "sg:postcode":"37879",
    "sg:province":"TN",
    "sg:tags":[
        "auctioneer"
    ],
    "wof:name":"Stone Auction Hot Line",
    "wof:placetype":"venue"
},
  "geometry": {"coordinates":[-83.569001,36.454581],"type":"Point"}
}