{
  "type": "Feature",
  "properties": {
    "iso:country":"US",
    "sg:address":"2020 Broomfield Rd",
    "sg:city":"Cleveland",
    "sg:classifiers":[
        {
            "category":"Banks & Credit Unions",
            "subcategory":"Bank",
            "type":"Services"
        }
    ],
    "sg:phone":"+1 423 472 3220",
    "sg:postcode":"37323",
    "sg:province":"TN",
    "wof:name":"Sun Trust Bank",
    "wof:placetype":"venue"
},
  "geometry": {"coordinates":[-84.85849899999999,35.13094],"type":"Point"}
}