{
  "type": "Feature",
  "properties": {
    "iso:country":"US",
    "sg:address":"111 Denise Dr",
    "sg:city":"Antioch",
    "sg:classifiers":[
        {
            "category":"Professional",
            "subcategory":"Business Services",
            "type":"Services"
        }
    ],
    "sg:phone":"+1 615 445 7991",
    "sg:postcode":"37013",
    "sg:province":"TN",
    "wof:name":"J T Phillips Media Group",
    "wof:placetype":"venue"
},
  "geometry": {"coordinates":[-86.68436199999999,36.076581],"type":"Point"}
}