{
  "type": "Feature",
  "properties": {
    "iso:country":"US",
    "sg:address":"1 Public Sq",
    "sg:city":"Columbia",
    "sg:classifiers":[
        {
            "category":"Professional",
            "type":"Services"
        }
    ],
    "sg:phone":"+1 931 375 5301",
    "sg:postcode":"38401",
    "sg:province":"TN",
    "wof:name":"Mattie Glenn Ofc",
    "wof:placetype":"venue"
},
  "geometry": {"coordinates":[-87.033823,35.615142],"type":"Point"}
}