{
  "type": "Feature",
  "properties": {
    "addr:full":"3646 Brainerd Rd Chattanooga TN 37411",
    "addr:housenumber":"3646",
    "addr:postcode":"37411",
    "addr:street":"Brainerd Rd",
    "iso:country":"US",
    "sg:address":"3646 Brainerd Rd",
    "sg:city":"Chattanooga",
    "sg:classifiers":[
        {
            "category":"Shopping",
            "subcategory":"Clothing, Apparel, & Fashions",
            "type":"Retail Goods"
        }
    ],
    "sg:phone":"+1 423 622 8222",
    "sg:postcode":"37411",
    "sg:province":"TN",
    "sg:tags":[
        "furnishing"
    ],
    "wof:name":"Barry Manufacturing Mens Wear",
    "wof:placetype":"venue"
},
  "geometry": {"coordinates":[-85.24512199999999,35.023526],"type":"Point"}
}