{
  "type": "Feature",
  "properties": {
    "iso:country":"US",
    "sg:address":"3412 W Andrew Johnson Hwy",
    "sg:city":"Morristown",
    "sg:classifiers":[
        {
            "category":"Restaurant",
            "type":"Food & Drink"
        }
    ],
    "sg:phone":"+1 423 587 0175",
    "sg:postcode":"37814",
    "sg:province":"TN",
    "sg:website":"www.ocharleys.com",
    "wof:name":"O'Charley's",
    "wof:placetype":"venue"
},
  "geometry": {"coordinates":[-83.34091100000001,36.199621],"type":"Point"}
}