{
  "type": "Feature",
  "properties": {
    "addr:full":"8945 Dogwood Rd Germantown TN 38139",
    "addr:housenumber":"8945",
    "addr:postcode":"38139",
    "addr:street":"Dogwood Rd",
    "iso:country":"US",
    "sg:address":"8945 Dogwood Rd",
    "sg:city":"Germantown",
    "sg:classifiers":[
        {
            "category":"Organizations",
            "subcategory":"Professional Association",
            "type":"Services"
        }
    ],
    "sg:phone":"+1 901 753 0374",
    "sg:postcode":"38139",
    "sg:province":"TN",
    "wof:name":"YWCA Child Care",
    "wof:placetype":"venue"
},
  "geometry": {"coordinates":[-89.767832,35.085626],"type":"Point"}
}