{
  "type": "Feature",
  "properties": {
    "iso:country":"US",
    "sg:address":"1555 Brookdale Ave",
    "sg:city":"Cookeville",
    "sg:classifiers":[
        {
            "category":"Professional",
            "subcategory":"Business Services",
            "type":"Services"
        }
    ],
    "sg:phone":"+1 931 432 5255",
    "sg:postcode":"38506",
    "sg:province":"TN",
    "wof:name":"Whits Sales",
    "wof:placetype":"venue"
},
  "geometry": {"coordinates":[-85.526214,36.127777],"type":"Point"}
}