{
  "type": "Feature",
  "properties": {
    "iso:country":"US",
    "sg:address":"804 Westborough Rd",
    "sg:city":"Knoxville",
    "sg:classifiers":[
        {
            "category":"Professional",
            "subcategory":"Business Services",
            "type":"Services"
        }
    ],
    "sg:phone":"+1 865 691 6158",
    "sg:postcode":"37909",
    "sg:province":"TN",
    "wof:name":"Inspector Clsaus HM Insptn Svc",
    "wof:placetype":"venue"
},
  "geometry": {"coordinates":[-84.054545,35.942219],"type":"Point"}
}