{
  "type": "Feature",
  "properties": {
    "iso:country":"US",
    "sg:address":"4417 Roellen Newbern Rd",
    "sg:city":"Newbern",
    "sg:classifiers":[
        {
            "category":"Farming",
            "subcategory":"Farm & Veterinary Services",
            "type":"Manufacturing & Wholesale Goods"
        }
    ],
    "sg:phone":"+1 731 627 2622",
    "sg:postcode":"38059",
    "sg:province":"TN",
    "wof:name":"Pate Properties",
    "wof:placetype":"venue"
},
  "geometry": {"coordinates":[-89.277224,36.079332],"type":"Point"}
}