{
  "type": "Feature",
  "properties": {
    "addr:full":"515 Donelson Pike Nashville TN 37214",
    "addr:housenumber":"515",
    "addr:postcode":"37214",
    "addr:street":"Donelson Pike",
    "iso:country":"US",
    "sg:address":"515 Donelson Pike",
    "sg:city":"Nashville",
    "sg:classifiers":[
        {
            "category":"Autos & Motor Vehicles",
            "subcategory":"Automobile Sales",
            "type":"Retail Goods"
        }
    ],
    "sg:phone":"+1 615 889 3922",
    "sg:postcode":"37214",
    "sg:province":"TN",
    "sg:tags":[
        "car",
        "used",
        "dealer"
    ],
    "wof:name":"Musictown Motor Cars",
    "wof:placetype":"venue"
},
  "geometry": {"coordinates":[-86.666253,36.147628],"type":"Point"}
}