{
  "type": "Feature",
  "properties": {
    "iso:country":"US",
    "sg:address":"522 Carta Rd",
    "sg:city":"Knoxville",
    "sg:classifiers":[
        {
            "category":"Building & Trades",
            "subcategory":"Landscaping Services",
            "type":"Services"
        }
    ],
    "sg:phone":"+1 865 637 5976",
    "sg:postcode":"37914",
    "sg:province":"TN",
    "sg:tags":[
        "lawn",
        "maintenance",
        "grounds"
    ],
    "wof:name":"Malcolm's Lawn Care Svc",
    "wof:placetype":"venue"
},
  "geometry": {"coordinates":[-83.856707,36.012402],"type":"Point"}
}