{
  "type": "Feature",
  "properties": {
    "addr:full":"730 Cool Springs Blvd Franklin TN 37067",
    "addr:housenumber":"730",
    "addr:postcode":"37067",
    "addr:street":"Cool Springs Blvd",
    "iso:country":"US",
    "sg:address":"730 Cool Springs Blvd",
    "sg:city":"Franklin",
    "sg:classifiers":[
        {
            "category":"Banks & Credit Unions",
            "subcategory":"Investment Brokerage",
            "type":"Services"
        }
    ],
    "sg:phone":"+1 615 778 2898",
    "sg:postcode":"37067",
    "sg:province":"TN",
    "sg:tags":[
        "trader",
        "commodity"
    ],
    "wof:name":"Eco-Energy Inc",
    "wof:placetype":"venue"
},
  "geometry": {"coordinates":[-86.80359900000001,35.945029],"type":"Point"}
}