{
  "type": "Feature",
  "properties": {
    "addr:full":"3898 Lawrenceburg Hwy Pulaski TN 38478",
    "addr:housenumber":"3898",
    "addr:postcode":"38478",
    "addr:street":"Lawrenceburg Hwy",
    "iso:country":"US",
    "sg:address":"3898 Lawrenceburg Hwy",
    "sg:city":"Pulaski",
    "sg:classifiers":[
        {
            "category":"Shopping",
            "subcategory":"Hobbies, Toys, & Games",
            "type":"Retail Goods"
        }
    ],
    "sg:phone":"+1 931 363 8125",
    "sg:postcode":"38478",
    "sg:province":"TN",
    "sg:tags":[
        "craft",
        "supply"
    ],
    "wof:name":"Family Album",
    "wof:placetype":"venue"
},
  "geometry": {"coordinates":[-87.069361,35.207748],"type":"Point"}
}