{
  "type": "Feature",
  "properties": {
    "addr:full":"3221 Harrison Pike Chattanooga TN 37406",
    "addr:housenumber":"3221",
    "addr:postcode":"37406",
    "addr:street":"Harrison Pike",
    "iso:country":"US",
    "sg:address":"3221 Harrison Pike",
    "sg:city":"Chattanooga",
    "sg:classifiers":[
        {
            "category":"Organizations",
            "subcategory":"Non-profit Organization",
            "type":"Services"
        }
    ],
    "sg:phone":"+1 423 624 9992",
    "sg:postcode":"37406",
    "sg:province":"TN",
    "wof:name":"Home Builders Assn",
    "wof:placetype":"venue"
},
  "geometry": {"coordinates":[-85.21550999999999,35.087832],"type":"Point"}
}