{
  "type": "Feature",
  "properties": {
    "addr:full":"1226 Longview Dr Centerville TN 37033",
    "addr:housenumber":"1226",
    "addr:postcode":"37033",
    "addr:street":"Longview Dr",
    "iso:country":"US",
    "sg:address":"1226 Longview Dr",
    "sg:city":"Centerville",
    "sg:classifiers":[
        {
            "category":"Home & Garden",
            "subcategory":"Household Appliances",
            "type":"Retail Goods"
        },
        {
            "category":"Building & Trades",
            "subcategory":"Construction",
            "type":"Services"
        }
    ],
    "sg:phone":"+1 931 729 4004",
    "sg:postcode":"37033",
    "sg:province":"TN",
    "sg:tags":[
        "system",
        "specialty",
        "pump",
        "heating",
        "heat",
        "contractor",
        "air conditioning"
    ],
    "wof:name":"TNT Heating Cooling & Refrigeration",
    "wof:placetype":"venue"
},
  "geometry": {"coordinates":[-87.502456,35.790131],"type":"Point"}
}