{
  "type": "Feature",
  "properties": {
    "iso:country":"US",
    "sg:address":"531 N Church St",
    "sg:city":"Livingston",
    "sg:classifiers":[
        {
            "category":"Health Services",
            "subcategory":"Doctor",
            "type":"Services"
        }
    ],
    "sg:phone":"+1 931 823 7980",
    "sg:postcode":"38570",
    "sg:province":"TN",
    "sg:tags":[
        "physician",
        "surgeon"
    ],
    "wof:name":"Twin Lakes Medical Imaging",
    "wof:placetype":"venue"
},
  "geometry": {"coordinates":[-85.323565,36.386763],"type":"Point"}
}