{
  "type": "Feature",
  "properties": {
    "addr:full":"8024 Stage Hills Blvd Memphis TN 38133",
    "addr:housenumber":"8024",
    "addr:postcode":"38133",
    "addr:street":"Stage Hills Blvd",
    "iso:country":"US",
    "sg:address":"8024 Stage Hills Blvd",
    "sg:city":"Memphis",
    "sg:classifiers":[
        {
            "category":"Professional",
            "subcategory":"Advertising",
            "type":"Services"
        }
    ],
    "sg:phone":"+1 901 382 3091",
    "sg:postcode":"38133",
    "sg:province":"TN",
    "sg:tags":[
        "distribution"
    ],
    "wof:name":"Medx Distribution",
    "wof:placetype":"venue"
},
  "geometry": {"coordinates":[-89.800202,35.209249],"type":"Point"}
}