{
  "type": "Feature",
  "properties": {
    "addr:full":"689 Davidson St Nashville TN 37206",
    "addr:housenumber":"689",
    "addr:postcode":"37206",
    "addr:street":"Davidson St",
    "iso:country":"US",
    "sg:address":"689 Davidson St",
    "sg:city":"Nashville",
    "sg:classifiers":[
        {
            "category":"Manufacturing",
            "subcategory":"Printing",
            "type":"Manufacturing & Wholesale Goods"
        }
    ],
    "sg:phone":"+1 615 256 3661",
    "sg:postcode":"37206",
    "sg:province":"TN",
    "sg:tags":[
        "commercial"
    ],
    "wof:name":"Marshall & Bruce Co",
    "wof:placetype":"venue"
},
  "geometry": {"coordinates":[-86.753747,36.161666],"type":"Point"}
}