{
  "type": "Feature",
  "properties": {
    "iso:country":"US",
    "sg:address":"201 E Main St",
    "sg:city":"Murfreesboro",
    "sg:classifiers":[
        {
            "category":"Insurance",
            "subcategory":"Insurance Agent",
            "type":"Services"
        }
    ],
    "sg:phone":"+1 615 890 4776",
    "sg:postcode":"37130",
    "sg:province":"TN",
    "wof:name":"Horace Mann Insurance Co",
    "wof:placetype":"venue"
},
  "geometry": {"coordinates":[-86.389793,35.845875],"type":"Point"}
}