{
  "type": "Feature",
  "properties": {
    "addr:full":"800 Holly Ave South Pittsburg TN 37380",
    "addr:housenumber":"800",
    "addr:postcode":"37380",
    "addr:street":"Holly Ave",
    "iso:country":"US",
    "sg:address":"800 Holly Ave",
    "sg:city":"South Pittsburg",
    "sg:classifiers":[
        {
            "category":"Shopping",
            "subcategory":"Optical Goods",
            "type":"Retail Goods"
        }
    ],
    "sg:phone":"+1 423 837 8834",
    "sg:postcode":"37380",
    "sg:province":"TN",
    "sg:tags":[
        "store"
    ],
    "wof:name":"Randall Vinson Dr",
    "wof:placetype":"venue"
},
  "geometry": {"coordinates":[-85.71145799999999,35.006259],"type":"Point"}
}