{
  "type": "Feature",
  "properties": {
    "iso:country":"US",
    "sg:address":"2415 Epperson Springs Rd",
    "sg:city":"Westmoreland",
    "sg:classifiers":[
        {
            "category":"Government",
            "subcategory":"Office",
            "type":"Public Place"
        }
    ],
    "sg:phone":"+1 615 644 3938",
    "sg:postcode":"37186",
    "sg:province":"TN",
    "sg:tags":[
        "village"
    ],
    "wof:name":"Davis Branch Pumping Station",
    "wof:placetype":"venue"
},
  "geometry": {"coordinates":[-86.245403,36.562504],"type":"Point"}
}