{
  "type": "Feature",
  "properties": {
    "iso:country":"US",
    "sg:address":"321 W McKnight Dr",
    "sg:city":"Murfreesboro",
    "sg:classifiers":[
        {
            "category":"Recreation",
            "type":"Entertainment"
        }
    ],
    "sg:phone":"+1 615 890 6611",
    "sg:postcode":"37129",
    "sg:province":"TN",
    "sg:tags":[
        "gymnastic"
    ],
    "wof:name":"Tumble Kids Gymnastics",
    "wof:placetype":"venue"
},
  "geometry": {"coordinates":[-86.39183,35.859987],"type":"Point"}
}