{
  "type": "Feature",
  "properties": {
    "iso:country":"US",
    "sg:address":"1226 N Highland Ave",
    "sg:city":"Jackson",
    "sg:classifiers":[
        {
            "category":"Professional",
            "subcategory":"Advertising",
            "type":"Services"
        }
    ],
    "sg:phone":"+1 731 427 8915",
    "sg:postcode":"38301",
    "sg:province":"TN",
    "sg:tags":[
        "counselor"
    ],
    "wof:name":"Smart Ads Productions",
    "wof:placetype":"venue"
},
  "geometry": {"coordinates":[-88.81856999999999,35.63368],"type":"Point"}
}