{
  "type": "Feature",
  "properties": {
    "iso:country":"US",
    "sg:address":"101 Wilder Tower",
    "sg:city":"Memphis",
    "sg:classifiers":[
        {
            "category":"Education",
            "subcategory":"University",
            "type":"Public Place"
        }
    ],
    "sg:phone":"+1 901 678 2056",
    "sg:postcode":"38152",
    "sg:province":"TN",
    "sg:tags":[
        "college"
    ],
    "sg:website":"http://www.memphis.edu/",
    "wof:name":"University of Memphis Admissions",
    "wof:placetype":"venue"
},
  "geometry": {"coordinates":[-89.943771,35.12748],"type":"Point"}
}