{
  "type": "Feature",
  "properties": {
    "iso:country":"US",
    "sg:address":"6375 Bonny Oaks Dr",
    "sg:city":"Chattanooga",
    "sg:classifiers":[
        {
            "category":"Professional",
            "subcategory":"Accounting & Tax Preparation",
            "type":"Services"
        }
    ],
    "sg:phone":"+1 423 238 4172",
    "sg:postcode":"37416",
    "sg:province":"TN",
    "sg:tags":[
        "return",
        "filing"
    ],
    "wof:name":"ADH Financial Systems Inc",
    "wof:placetype":"venue"
},
  "geometry": {"coordinates":[-85.170203,35.074609],"type":"Point"}
}