{
  "type": "Feature",
  "properties": {
    "iso:country":"US",
    "sg:address":"3501 Rossville Blvd",
    "sg:city":"Chattanooga",
    "sg:classifiers":[
        {
            "category":"Banks & Credit Unions",
            "subcategory":"Bank",
            "type":"Services"
        }
    ],
    "sg:phone":"+1 423 867 7101",
    "sg:postcode":"37407",
    "sg:province":"TN",
    "sg:tags":[
        "cashing",
        "check"
    ],
    "wof:name":"Payment Center",
    "wof:placetype":"venue"
},
  "geometry": {"coordinates":[-85.29241399999999,35.002649],"type":"Point"}
}