{
  "type": "Feature",
  "properties": {
    "iso:country":"US",
    "sg:address":"9127 Highway 100",
    "sg:city":"Nashville",
    "sg:classifiers":[
        {
            "category":"Travel",
            "subcategory":"Hotels & Motels",
            "type":"Entertainment"
        },
        {
            "category":"Travel",
            "subcategory":"Bed & Breakfast",
            "type":"Entertainment"
        }
    ],
    "sg:phone":"+1 615 646 5082",
    "sg:postcode":"37221",
    "sg:province":"TN",
    "sg:tags":[
        "inn",
        "lodging"
    ],
    "wof:name":"Apple Brook Bed & Breakfast",
    "wof:placetype":"venue"
},
  "geometry": {"coordinates":[-87.023331,36.025383],"type":"Point"}
}