{
  "type": "Feature",
  "properties": {
    "iso:country":"US",
    "sg:address":"3958 Nonaville Rd",
    "sg:city":"Mount Juliet",
    "sg:classifiers":[
        {
            "category":"Freight",
            "type":"Transportation"
        }
    ],
    "sg:phone":"+1 615 758 6226",
    "sg:postcode":"37122",
    "sg:province":"TN",
    "wof:name":"Stephens Solution Inc",
    "wof:placetype":"venue"
},
  "geometry": {"coordinates":[-86.539744,36.277215],"type":"Point"}
}