{
  "type": "Feature",
  "properties": {
    "iso:country":"US",
    "sg:address":"2803 E 5th Ave",
    "sg:city":"Knoxville",
    "sg:classifiers":[
        {
            "category":"Social Services",
            "type":"Services"
        }
    ],
    "sg:phone":"+1 865 523 6101",
    "sg:postcode":"37914",
    "sg:province":"TN",
    "wof:name":"Community of St Ninian In",
    "wof:placetype":"venue"
},
  "geometry": {"coordinates":[-83.89044,35.992836],"type":"Point"}
}