{
  "type": "Feature",
  "properties": {
    "iso:country":"US",
    "sg:address":"201 Elmore St",
    "sg:city":"Monterey",
    "sg:classifiers":[
        {
            "category":"Professional",
            "subcategory":"Accounting & Tax Preparation",
            "type":"Services"
        }
    ],
    "sg:phone":"+1 931 839 3431",
    "sg:postcode":"38574",
    "sg:province":"TN",
    "sg:tags":[
        "return",
        "filing"
    ],
    "wof:name":"H & R Block Tax Svc",
    "wof:placetype":"venue"
},
  "geometry": {"coordinates":[-85.261825,36.144901],"type":"Point"}
}