{
  "type": "Feature",
  "properties": {
    "iso:country":"US",
    "sg:address":"7417 Amberwood Dr",
    "sg:city":"Knoxville",
    "sg:classifiers":[
        {
            "category":"Building & Trades",
            "subcategory":"Construction",
            "type":"Services"
        }
    ],
    "sg:phone":"+1 865 693 7619",
    "sg:postcode":"37919",
    "sg:province":"TN",
    "sg:tags":[
        "contractor"
    ],
    "wof:name":"Jo Helton Contracting",
    "wof:placetype":"venue"
},
  "geometry": {"coordinates":[-84.026704,35.91407],"type":"Point"}
}