{
  "type": "Feature",
  "properties": {
    "addr:full":"245 N Walnut Bend Rd Cordova TN 38018",
    "addr:housenumber":"245",
    "addr:postcode":"38018",
    "addr:street":"N Walnut Bend Rd",
    "iso:country":"US",
    "sg:address":"245 N Walnut Bend Rd",
    "sg:city":"Cordova",
    "sg:classifiers":[
        {
            "category":"Health Services",
            "subcategory":"Health Practitioner",
            "type":"Services"
        }
    ],
    "sg:phone":"+1 901 758 1002",
    "sg:postcode":"38018",
    "sg:province":"TN",
    "sg:tags":[
        "nutritionist"
    ],
    "wof:name":"Nutri-Fax Inc",
    "wof:placetype":"venue"
},
  "geometry": {"coordinates":[-89.784823,35.131924],"type":"Point"}
}