{
  "type": "Feature",
  "properties": {
    "iso:country":"US",
    "sg:address":"44 Woodland Cir",
    "sg:city":"Lawrenceburg",
    "sg:classifiers":[
        {
            "category":"Professional",
            "type":"Services"
        }
    ],
    "sg:phone":"+1 931 766 5457",
    "sg:postcode":"38464",
    "sg:province":"TN",
    "wof:name":"Ferguson Kip",
    "wof:placetype":"venue"
},
  "geometry": {"coordinates":[-87.307744,35.266304],"type":"Point"}
}