{
  "type": "Feature",
  "properties": {
    "addr:full":"109 W Lauderdale St Tullahoma TN 37388",
    "addr:housenumber":"109",
    "addr:postcode":"37388",
    "addr:street":"W Lauderdale St",
    "iso:country":"US",
    "sg:address":"109 W Lauderdale St",
    "sg:city":"Tullahoma",
    "sg:classifiers":[
        {
            "category":"Autos & Motor Vehicles",
            "subcategory":"Auto Supplies",
            "type":"Retail Goods"
        }
    ],
    "sg:phone":"+1 931 455 4549",
    "sg:postcode":"37388",
    "sg:province":"TN",
    "wof:name":"OReilly Auto Parts",
    "wof:placetype":"venue"
},
  "geometry": {"coordinates":[-86.20960700000001,35.361147],"type":"Point"}
}