{
  "type": "Feature",
  "properties": {
    "iso:country":"US",
    "sg:address":"1120 Gallion Rd",
    "sg:city":"Cumberland Furnace",
    "sg:classifiers":[
        {
            "category":"Farming",
            "subcategory":"Livestock Farm",
            "type":"Manufacturing & Wholesale Goods"
        }
    ],
    "sg:phone":"+1 615 330 4256",
    "sg:postcode":"37051",
    "sg:province":"TN",
    "sg:tags":[
        "equine"
    ],
    "wof:name":"Jeff Travis",
    "wof:placetype":"venue"
},
  "geometry": {"coordinates":[-87.31839600000001,36.279956],"type":"Point"}
}