{
  "type": "Feature",
  "properties": {
    "iso:country":"US",
    "sg:address":"4823 Newcom Ave",
    "sg:city":"Knoxville",
    "sg:classifiers":[
        {
            "category":"Professional",
            "type":"Services"
        }
    ],
    "sg:phone":"+1 865 584 4906",
    "sg:postcode":"37919",
    "sg:province":"TN",
    "sg:tags":[
        "establishment"
    ],
    "wof:name":"El Dimante",
    "wof:placetype":"venue"
},
  "geometry": {"coordinates":[-83.984827,35.941505],"type":"Point"}
}