{
  "type": "Feature",
  "properties": {
    "iso:country":"US",
    "sg:address":"4701 High School Rd NE",
    "sg:city":"Knoxville",
    "sg:classifiers":[
        {
            "category":"Social Services",
            "subcategory":"Child Care",
            "type":"Services"
        }
    ],
    "sg:phone":"+1 865 687 7595",
    "sg:postcode":"37912",
    "sg:province":"TN",
    "wof:name":"Kids Place Inc",
    "wof:placetype":"venue"
},
  "geometry": {"coordinates":[-83.959374,36.011341],"type":"Point"}
}