{
  "type": "Feature",
  "properties": {
    "iso:country":"US",
    "sg:address":"4511 Oak Rd",
    "sg:city":"Arlington",
    "sg:classifiers":[
        {
            "category":"Education",
            "subcategory":"Special Training",
            "type":"Public Place"
        }
    ],
    "sg:phone":"+1 901 867 8178",
    "sg:postcode":"38002",
    "sg:province":"TN",
    "sg:tags":[
        "professional",
        "university",
        "college"
    ],
    "wof:name":"Gary Ton Consulting",
    "wof:placetype":"venue"
},
  "geometry": {"coordinates":[-89.825705,35.258421],"type":"Point"}
}