{
  "type": "Feature",
  "properties": {
    "iso:country":"US",
    "sg:address":"298 Germantown Bend Cv",
    "sg:city":"Cordova",
    "sg:classifiers":[
        {
            "category":"Insurance",
            "subcategory":"Hazard Insurance",
            "type":"Services"
        }
    ],
    "sg:phone":"+1 901 753 9960",
    "sg:postcode":"38018",
    "sg:province":"TN",
    "wof:name":"Benjamin Louis Wright Jr Agency - Nationwide Insurance",
    "wof:placetype":"venue"
},
  "geometry": {"coordinates":[-89.798686,35.12241],"type":"Point"}
}