{
  "type": "Feature",
  "properties": {
    "addr:full":"7741 S Northshore Dr Knoxville TN 37919",
    "addr:housenumber":"7741",
    "addr:postcode":"37919",
    "addr:street":"S Northshore Dr",
    "iso:country":"US",
    "sg:address":"7741 S Northshore Dr",
    "sg:city":"Knoxville",
    "sg:classifiers":[
        {
            "category":"Restaurant",
            "type":"Food & Drink"
        }
    ],
    "sg:phone":"+1 865 692 1310",
    "sg:postcode":"37919",
    "sg:province":"TN",
    "wof:name":"Casa Don Gallo Mexican Cuisine",
    "wof:placetype":"venue"
},
  "geometry": {"coordinates":[-84.021807,35.902708],"type":"Point"}
}