{
  "type": "Feature",
  "properties": {
    "iso:country":"US",
    "sg:address":"6256 Ringgold Rd",
    "sg:city":"Chattanooga",
    "sg:classifiers":[
        {
            "category":"Personal",
            "type":"Services"
        }
    ],
    "sg:phone":"+1 423 855 8181",
    "sg:postcode":"37412",
    "sg:province":"TN",
    "sg:tags":[
        "home",
        "health",
        "care"
    ],
    "wof:name":"Angels Visiting",
    "wof:placetype":"venue"
},
  "geometry": {"coordinates":[-85.212608,34.989702],"type":"Point"}
}