{
  "type": "Feature",
  "properties": {
    "addr:full":"1708 Golden Valley Dr Christiana TN 37037",
    "addr:housenumber":"1708",
    "addr:postcode":"37037",
    "addr:street":"Golden Valley Dr",
    "iso:country":"US",
    "sg:address":"1708 Golden Valley Dr",
    "sg:city":"Christiana",
    "sg:classifiers":[
        {
            "category":"Travel",
            "subcategory":"Travel Agent",
            "type":"Entertainment"
        }
    ],
    "sg:phone":"+1 615 907 8088",
    "sg:postcode":"37037",
    "sg:province":"TN",
    "sg:tags":[
        "agency"
    ],
    "wof:name":"All Around Travel",
    "wof:placetype":"venue"
},
  "geometry": {"coordinates":[-86.38161100000001,35.743286],"type":"Point"}
}