{
  "type": "Feature",
  "properties": {
    "addr:full":"497 Jonnie Dr Paris TN 38242",
    "addr:housenumber":"497",
    "addr:postcode":"38242",
    "addr:street":"Jonnie Dr",
    "iso:country":"US",
    "sg:address":"497 Jonnie Dr",
    "sg:city":"Paris",
    "sg:classifiers":[
        {
            "category":"Professional",
            "type":"Services"
        }
    ],
    "sg:phone":"+1 731 644 9273",
    "sg:postcode":"38242",
    "sg:province":"TN",
    "wof:name":"Michael Wiggins",
    "wof:placetype":"venue"
},
  "geometry": {"coordinates":[-88.243365,36.349903],"type":"Point"}
}