{
  "type": "Feature",
  "properties": {
    "iso:country":"US",
    "sg:address":"1306 Oakmont Rd",
    "sg:city":"Ashland City",
    "sg:classifiers":[
        {
            "category":"Building & Trades",
            "subcategory":"Construction",
            "type":"Services"
        }
    ],
    "sg:phone":"+1 615 792 1295",
    "sg:postcode":"37015",
    "sg:province":"TN",
    "sg:tags":[
        "contractor"
    ],
    "wof:name":"Stacys Roofing & Home RE",
    "wof:placetype":"venue"
},
  "geometry": {"coordinates":[-87.13836000000001,36.264243],"type":"Point"}
}