{
  "type": "Feature",
  "properties": {
    "addr:full":"1310 Charlotte Ave Nashville TN 37209",
    "addr:housenumber":"1310",
    "addr:postcode":"37209",
    "addr:street":"Charlotte Ave",
    "iso:country":"US",
    "sg:address":"1310 Charlotte Ave",
    "sg:city":"Nashville",
    "sg:classifiers":[
        {
            "category":"Retail",
            "subcategory":"Auto Repair",
            "type":"Services"
        }
    ],
    "sg:phone":"+1 615 327 0722",
    "sg:postcode":"37209",
    "sg:province":"TN",
    "sg:tags":[
        "automotive"
    ],
    "wof:name":"Kar Plus",
    "wof:placetype":"venue"
},
  "geometry": {"coordinates":[-86.793206,36.161051],"type":"Point"}
}