{
  "type": "Feature",
  "properties": {
    "iso:country":"US",
    "sg:address":"414 E Mountainview Rd",
    "sg:city":"Johnson City",
    "sg:classifiers":[
        {
            "category":"Real Estate",
            "subcategory":"Real Estate Operator",
            "type":"Services"
        }
    ],
    "sg:phone":"+1 423 282 6007",
    "sg:postcode":"37601",
    "sg:province":"TN",
    "sg:tags":[
        "building",
        "apartment"
    ],
    "wof:name":"Mountain View Villa Apartments",
    "wof:placetype":"venue"
},
  "geometry": {"coordinates":[-82.38864700000001,36.367098],"type":"Point"}
}