{
  "type": "Feature",
  "properties": {
    "addr:full":"5841 Hickory Cmns Memphis TN 38141",
    "addr:housenumber":"5841",
    "addr:postcode":"38141",
    "addr:street":"Hickory Cmns",
    "iso:country":"US",
    "sg:address":"5841 Hickory Cmns",
    "sg:city":"Memphis",
    "sg:classifiers":[
        {
            "category":"Professional",
            "type":"Services"
        }
    ],
    "sg:phone":"+1 901 365 9199",
    "sg:postcode":"38141",
    "sg:province":"TN",
    "wof:name":"Todays New Woman",
    "wof:placetype":"venue"
},
  "geometry": {"coordinates":[-89.869364,35.024276],"type":"Point"}
}