{
  "type": "Feature",
  "properties": {
    "iso:country":"US",
    "sg:address":"3686 S Germantown Rd",
    "sg:city":"Memphis",
    "sg:classifiers":[
        {
            "category":"Retail",
            "subcategory":"Storage",
            "type":"Services"
        }
    ],
    "sg:phone":"+1 901 756 9592",
    "sg:postcode":"38125",
    "sg:province":"TN",
    "sg:tags":[
        "household",
        "recreational",
        "commercial",
        "campers-storage",
        "vehicle"
    ],
    "wof:name":"U-Store-It",
    "wof:placetype":"venue"
},
  "geometry": {"coordinates":[-89.82356,35.047408],"type":"Point"}
}