{
  "type": "Feature",
  "properties": {
    "iso:country":"US",
    "sg:address":"204 Safe Harbor Dr",
    "sg:city":"Goodlettsville",
    "sg:classifiers":[
        {
            "category":"Real Estate",
            "subcategory":"Real Estate Operator",
            "type":"Services"
        }
    ],
    "sg:phone":"+1 615 859 4480",
    "sg:postcode":"37072",
    "sg:province":"TN",
    "sg:tags":[
        "building",
        "apartment"
    ],
    "wof:name":"Rivergate Acres Apartment",
    "wof:placetype":"venue"
},
  "geometry": {"coordinates":[-86.721192,36.298472],"type":"Point"}
}