{
  "type": "Feature",
  "properties": {
    "iso:country":"US",
    "sg:address":"743 N Main St",
    "sg:city":"Crossville",
    "sg:classifiers":[
        {
            "category":"Retail",
            "subcategory":"Auto Repair",
            "type":"Services"
        }
    ],
    "sg:phone":"+1 931 707 8628",
    "sg:postcode":"38555",
    "sg:province":"TN",
    "sg:tags":[
        "automotive"
    ],
    "wof:name":"Castrol Express Lube",
    "wof:placetype":"venue"
},
  "geometry": {"coordinates":[-85.032399,35.956976],"type":"Point"}
}