{
  "type": "Feature",
  "properties": {
    "iso:country":"US",
    "sg:address":"2653 Murfreesboro Pike",
    "sg:city":"Nashville",
    "sg:classifiers":[
        {
            "category":"Home & Garden",
            "subcategory":"Building Materials",
            "type":"Retail Goods"
        }
    ],
    "sg:phone":"+1 615 399 2630",
    "sg:postcode":"37217",
    "sg:province":"TN",
    "sg:tags":[
        "glass",
        "leaded"
    ],
    "wof:name":"Stained Glass Accessories",
    "wof:placetype":"venue"
},
  "geometry": {"coordinates":[-86.637398,36.07321],"type":"Point"}
}