{
  "type": "Feature",
  "properties": {
    "iso:country":"US",
    "sg:address":"2300 W Andrew Johnson Hwy",
    "sg:city":"Morristown",
    "sg:classifiers":[
        {
            "category":"Manufacturing",
            "subcategory":"Tools & Machinery",
            "type":"Manufacturing & Wholesale Goods"
        }
    ],
    "sg:phone":"+1 423 586 1610",
    "sg:postcode":"37814",
    "sg:province":"TN",
    "sg:tags":[
        "commercial",
        "laundry",
        "mach"
    ],
    "sg:website":"www.forentausa.com",
    "wof:name":"Forenta Inc",
    "wof:placetype":"venue"
},
  "geometry": {"coordinates":[-83.324558,36.205371],"type":"Point"}
}