{
  "type": "Feature",
  "properties": {
    "addr:full":"2826 N Central St Knoxville TN 37917",
    "addr:housenumber":"2826",
    "addr:postcode":"37917",
    "addr:street":"N Central St",
    "iso:country":"US",
    "sg:address":"2826 N Central St",
    "sg:city":"Knoxville",
    "sg:classifiers":[
        {
            "category":"Wholesale",
            "subcategory":"Scrap",
            "type":"Manufacturing & Wholesale Goods"
        }
    ],
    "sg:phone":"+1 865 524 2791",
    "sg:postcode":"37917",
    "sg:province":"TN",
    "sg:tags":[
        "recycling",
        "center"
    ],
    "wof:name":"Philip Services Corp",
    "wof:placetype":"venue"
},
  "geometry": {"coordinates":[-83.94367200000001,35.99254],"type":"Point"}
}