{
  "type": "Feature",
  "properties": {
    "addr:full":"832 Hayden Dr Clarksville TN 37043",
    "addr:housenumber":"832",
    "addr:postcode":"37043",
    "addr:street":"Hayden Dr",
    "iso:country":"US",
    "sg:address":"832 Hayden Dr",
    "sg:city":"Clarksville",
    "sg:classifiers":[
        {
            "category":"Building & Trades",
            "subcategory":"Construction",
            "type":"Services"
        }
    ],
    "sg:phone":"+1 931 645 8899",
    "sg:postcode":"37043",
    "sg:province":"TN",
    "sg:tags":[
        "house",
        "clea"
    ],
    "wof:name":"Austins Carpet & Uphl Clg",
    "wof:placetype":"venue"
},
  "geometry": {"coordinates":[-87.324725,36.507047],"type":"Point"}
}