{
  "type": "Feature",
  "properties": {
    "addr:full":"265 Allison Cove Trl Piney Flats TN 37686",
    "addr:housenumber":"265",
    "addr:postcode":"37686",
    "addr:street":"Allison Cove Trl",
    "iso:country":"US",
    "sg:address":"265 Allison Cove Trl",
    "sg:city":"Piney Flats",
    "sg:classifiers":[
        {
            "category":"Professional",
            "subcategory":"Engineering",
            "type":"Services"
        }
    ],
    "sg:phone":"+1 423 538 0488",
    "sg:postcode":"37686",
    "sg:province":"TN",
    "wof:name":"Randall C Tanner",
    "wof:placetype":"venue"
},
  "geometry": {"coordinates":[-82.382446,36.427329],"type":"Point"}
}