{
  "type": "Feature",
  "properties": {
    "iso:country":"US",
    "sg:address":"5404 Harding Pike",
    "sg:city":"Nashville",
    "sg:classifiers":[
        {
            "category":"Restaurant",
            "type":"Food & Drink"
        }
    ],
    "sg:phone":"+1 615 356 9398",
    "sg:postcode":"37205",
    "sg:province":"TN",
    "wof:name":"Finezza Italian Grille",
    "wof:placetype":"venue"
},
  "geometry": {"coordinates":[-86.868071,36.105828],"type":"Point"}
}