{
  "type": "Feature",
  "properties": {
    "iso:country":"US",
    "sg:address":"1270 E Hwy 22",
    "sg:city":"Union City",
    "sg:classifiers":[
        {
            "category":"Food & Beverages",
            "subcategory":"Groceries & Convenience Stores",
            "type":"Retail Goods"
        }
    ],
    "sg:phone":"+1 731 885 7119",
    "sg:postcode":"38261",
    "sg:province":"TN",
    "sg:tags":[
        "grocer",
        "station",
        "gasoline"
    ],
    "wof:name":"Old Lake Road Market",
    "wof:placetype":"venue"
},
  "geometry": {"coordinates":[-89.131028,36.440716],"type":"Point"}
}