{
  "type": "Feature",
  "properties": {
    "addr:full":"401 N Main St Jamestown TN 38556",
    "addr:housenumber":"401",
    "addr:postcode":"38556",
    "addr:street":"N Main St",
    "iso:country":"US",
    "sg:address":"401 N Main St",
    "sg:city":"Jamestown",
    "sg:classifiers":[
        {
            "category":"Restaurant",
            "type":"Food & Drink"
        }
    ],
    "sg:phone":"+1 931 879 1770",
    "sg:postcode":"38556",
    "sg:province":"TN",
    "wof:name":"Mc Donald's",
    "wof:placetype":"venue"
},
  "geometry": {"coordinates":[-84.935383,36.43434],"type":"Point"}
}