{
  "type": "Feature",
  "properties": {
    "iso:country":"US",
    "sg:address":"1341 Horn Springs Rd",
    "sg:city":"Lebanon",
    "sg:classifiers":[
        {
            "category":"Personal",
            "type":"Services"
        }
    ],
    "sg:phone":"+1 615 444 8100",
    "sg:postcode":"37087",
    "sg:province":"TN",
    "wof:name":"Sun Rays Inc",
    "wof:placetype":"venue"
},
  "geometry": {"coordinates":[-86.376401,36.260399],"type":"Point"}
}