{
  "type": "Feature",
  "properties": {
    "iso:country":"US",
    "sg:address":"416 Wilson Blvd N",
    "sg:city":"Nashville",
    "sg:classifiers":[
        {
            "category":"Professional",
            "subcategory":"Management & Consulting",
            "type":"Services"
        }
    ],
    "sg:phone":"+1 615 777 6401",
    "sg:postcode":"37205",
    "sg:province":"TN",
    "wof:name":"Work Institute",
    "wof:placetype":"venue"
},
  "geometry": {"coordinates":[-86.833635,36.13632],"type":"Point"}
}