{
  "type": "Feature",
  "properties": {
    "iso:country":"US",
    "sg:address":"2095 Madison Ave",
    "sg:city":"Memphis",
    "sg:classifiers":[
        {
            "category":"Home & Garden",
            "subcategory":"Home Furnishings",
            "type":"Retail Goods"
        }
    ],
    "sg:phone":"+1 901 278 9445",
    "sg:postcode":"38104",
    "sg:province":"TN",
    "wof:name":"Passions",
    "wof:placetype":"venue"
},
  "geometry": {"coordinates":[-89.99055199999999,35.136582],"type":"Point"}
}