{
  "type": "Feature",
  "properties": {
    "addr:full":"3725 Modern Industries Pkwy Chattanooga TN 37419",
    "addr:housenumber":"3725",
    "addr:postcode":"37419",
    "addr:street":"Pkwy",
    "iso:country":"US",
    "sg:address":"3725 Modern Industries Pkwy",
    "sg:city":"Chattanooga",
    "sg:classifiers":[
        {
            "category":"Travel",
            "subcategory":"Hotels & Motels",
            "type":"Entertainment"
        }
    ],
    "sg:phone":"+1 423 825 6100",
    "sg:postcode":"37419",
    "sg:province":"TN",
    "sg:website":"www.countryinns.com",
    "wof:name":"Country Inn & Suites",
    "wof:placetype":"venue"
},
  "geometry": {"coordinates":[-85.384547,35.016094],"type":"Point"}
}