{
  "type": "Feature",
  "properties": {
    "iso:country":"US",
    "sg:address":"227 Plum Nelly Cir",
    "sg:city":"Brentwood",
    "sg:classifiers":[
        {
            "category":"Building & Trades",
            "subcategory":"Construction",
            "type":"Services"
        }
    ],
    "sg:phone":"+1 615 377 0202",
    "sg:postcode":"37027",
    "sg:province":"TN",
    "wof:name":"Combs Paving LLC",
    "wof:placetype":"venue"
},
  "geometry": {"coordinates":[-86.77632199999999,36.037339],"type":"Point"}
}