{
  "type": "Feature",
  "properties": {
    "addr:full":"10 Mathis Dr Dickson TN 37055",
    "addr:housenumber":"10",
    "addr:postcode":"37055",
    "addr:street":"Mathis Dr",
    "iso:country":"US",
    "sg:address":"10 Mathis Dr",
    "sg:city":"Dickson",
    "sg:classifiers":[
        {
            "category":"Utilities",
            "subcategory":"Mobile Phone",
            "type":"Services"
        }
    ],
    "sg:phone":"+1 615 446 5056",
    "sg:postcode":"37055",
    "sg:province":"TN",
    "sg:tags":[
        "telephone",
        "cellular"
    ],
    "wof:name":"High Tech Communications",
    "wof:placetype":"venue"
},
  "geometry": {"coordinates":[-87.37571199999999,36.075781],"type":"Point"}
}