{
  "type": "Feature",
  "properties": {
    "addr:full":"269 Cedarcreek Dr Nashville TN 37211",
    "addr:housenumber":"269",
    "addr:postcode":"37211",
    "addr:street":"Cedarcreek Dr",
    "iso:country":"US",
    "sg:address":"269 Cedarcreek Dr",
    "sg:city":"Nashville",
    "sg:classifiers":[
        {
            "category":"Social Services",
            "subcategory":"Child Care",
            "type":"Services"
        }
    ],
    "sg:phone":"+1 615 315 0846",
    "sg:postcode":"37211",
    "sg:province":"TN",
    "wof:name":"Casandra's Home Day Care",
    "wof:placetype":"venue"
},
  "geometry": {"coordinates":[-86.704215,36.036065],"type":"Point"}
}