{
  "type": "Feature",
  "properties": {
    "iso:country":"US",
    "sg:address":"2762 Huntsville Hwy",
    "sg:city":"Fayetteville",
    "sg:classifiers":[
        {
            "category":"Food & Beverages",
            "subcategory":"Groceries & Convenience Stores",
            "type":"Retail Goods"
        }
    ],
    "sg:phone":"+1 931 433 6772",
    "sg:postcode":"37334",
    "sg:province":"TN",
    "sg:tags":[
        "grocer"
    ],
    "wof:name":"Piggly Wiggly",
    "wof:placetype":"venue"
},
  "geometry": {"coordinates":[-86.57167099999999,35.075554],"type":"Point"}
}