{
  "type": "Feature",
  "properties": {
    "iso:country":"US",
    "sg:address":"4700 State Hwy 58",
    "sg:city":"Chattanooga",
    "sg:classifiers":[
        {
            "category":"Shopping",
            "subcategory":"Pharmacy",
            "type":"Retail Goods"
        }
    ],
    "sg:phone":"+1 423 892 8802",
    "sg:postcode":"37416",
    "sg:province":"TN",
    "sg:website":"www.cvs.com",
    "wof:name":"CVS Pharmacy",
    "wof:placetype":"venue"
},
  "geometry": {"coordinates":[-85.18718699999999,35.089236],"type":"Point"}
}