{
  "type": "Feature",
  "properties": {
    "iso:country":"US",
    "sg:address":"211 Miles Ct",
    "sg:city":"Nashville",
    "sg:classifiers":[
        {
            "category":"Home & Garden",
            "subcategory":"Home Furnishings",
            "type":"Retail Goods"
        }
    ],
    "sg:phone":"+1 615 514 4000",
    "sg:postcode":"37209",
    "sg:province":"TN",
    "sg:tags":[
        "housewares"
    ],
    "sg:website":"www.bedbathandbeyond.com",
    "wof:name":"Bed Bath & Beyond Inc",
    "wof:placetype":"venue"
},
  "geometry": {"coordinates":[-86.88927099999999,36.088967],"type":"Point"}
}