{
  "type": "Feature",
  "properties": {
    "iso:country":"US",
    "sg:address":"901 N James Campbell Blvd",
    "sg:city":"Columbia",
    "sg:classifiers":[
        {
            "category":"Manufacturing",
            "subcategory":"Rubber & Plastics",
            "type":"Manufacturing & Wholesale Goods"
        }
    ],
    "sg:phone":"+1 931 388 5991",
    "sg:postcode":"38401",
    "sg:province":"TN",
    "sg:tags":[
        "marking",
        "mfg",
        "beads",
        "glass",
        "other",
        "tape",
        "hi",
        "thermoplastic"
    ],
    "wof:name":"Swarco Industries Inc",
    "wof:placetype":"venue"
},
  "geometry": {"coordinates":[-87.06499700000001,35.627226],"type":"Point"}
}