{
  "type": "Feature",
  "properties": {
    "iso:country":"US",
    "sg:address":"8600 State Hwy 22",
    "sg:city":"Dresden",
    "sg:classifiers":[
        {
            "category":"Government",
            "subcategory":"Office",
            "type":"Public Place"
        }
    ],
    "sg:phone":"+1 731 364 3149",
    "sg:postcode":"38225",
    "sg:province":"TN",
    "sg:tags":[
        "state",
        "resource"
    ],
    "wof:name":"Dept Of Children's Svc",
    "wof:placetype":"venue"
},
  "geometry": {"coordinates":[-88.713886,36.277795],"type":"Point"}
}