{
  "type": "Feature",
  "properties": {
    "iso:country":"US",
    "sg:address":"1680 Winchester Rd",
    "sg:city":"Memphis",
    "sg:classifiers":[
        {
            "category":"Banks & Credit Unions",
            "subcategory":"Bank",
            "type":"Services"
        }
    ],
    "sg:phone":"+1 901 346 1040",
    "sg:postcode":"38116",
    "sg:province":"TN",
    "sg:tags":[
        "loan",
        "broker"
    ],
    "wof:name":"Mid-South Title Loans",
    "wof:placetype":"venue"
},
  "geometry": {"coordinates":[-90.00769699999999,35.053846],"type":"Point"}
}