{
  "type": "Feature",
  "properties": {
    "iso:country":"US",
    "sg:address":"158 Todd St",
    "sg:city":"Harrogate",
    "sg:classifiers":[
        {
            "category":"Wholesale",
            "subcategory":"Plants",
            "type":"Manufacturing & Wholesale Goods"
        }
    ],
    "sg:phone":"+1 423 869 8559",
    "sg:postcode":"37752",
    "sg:province":"TN",
    "sg:tags":[
        "supply"
    ],
    "wof:name":"Unique Floral Wholesale",
    "wof:placetype":"venue"
},
  "geometry": {"coordinates":[-83.624065,36.58781],"type":"Point"}
}