{
  "type": "Feature",
  "properties": {
    "addr:full":"2887 Scenic Lake Cir Morristown TN 37814",
    "addr:housenumber":"2887",
    "addr:postcode":"37814",
    "addr:street":"Scenic Lake Cir",
    "iso:country":"US",
    "sg:address":"2887 Scenic Lake Cir",
    "sg:city":"Morristown",
    "sg:classifiers":[
        {
            "category":"Building & Trades",
            "subcategory":"Pest Control",
            "type":"Services"
        }
    ],
    "sg:phone":"+1 423 587 3918",
    "sg:postcode":"37814",
    "sg:province":"TN",
    "wof:name":"Legacy Stables Therapeutic Rid",
    "wof:placetype":"venue"
},
  "geometry": {"coordinates":[-83.24015799999999,36.280974],"type":"Point"}
}