{
  "type": "Feature",
  "properties": {
    "iso:country":"US",
    "sg:address":"940 Oldham Dr",
    "sg:city":"Nolensville",
    "sg:classifiers":[
        {
            "category":"Health Services",
            "subcategory":"Doctor",
            "type":"Services"
        }
    ],
    "sg:phone":"+1 615 776 8088",
    "sg:postcode":"37135",
    "sg:province":"TN",
    "sg:tags":[
        "clinic"
    ],
    "wof:name":"Nolensville Family Medicine",
    "wof:placetype":"venue"
},
  "geometry": {"coordinates":[-86.671328,35.961903],"type":"Point"}
}