{
  "type": "Feature",
  "properties": {
    "iso:country":"US",
    "sg:address":"7486 Forks River Rd",
    "sg:city":"Hurricane Mills",
    "sg:phone":"+1 931 296 3706",
    "sg:postcode":"37078",
    "sg:province":"TN",
    "sg:tags":[
        "farm",
        "corn",
        "soybean"
    ],
    "wof:name":"Eddie Mayberry",
    "wof:placetype":"venue"
},
  "geometry": {"coordinates":[-87.84011700000001,35.974391],"type":"Point"}
}