{
  "type": "Feature",
  "properties": {
    "iso:country":"US",
    "sg:address":"456 Distribution Pkwy",
    "sg:city":"Collierville",
    "sg:classifiers":[
        {
            "category":"Building & Trades",
            "subcategory":"Construction",
            "type":"Services"
        }
    ],
    "sg:phone":"+1 901 388 7442",
    "sg:postcode":"38017",
    "sg:province":"TN",
    "sg:tags":[
        "fire",
        "restoration",
        "damage"
    ],
    "wof:name":"Crdn Of The Midsouth",
    "wof:placetype":"venue"
},
  "geometry": {"coordinates":[-89.668752,35.031953],"type":"Point"}
}