{
  "type": "Feature",
  "properties": {
    "addr:full":"211 Woodshire Dr Smyrna TN 37167",
    "addr:housenumber":"211",
    "addr:postcode":"37167",
    "addr:street":"Woodshire Dr",
    "iso:country":"US",
    "sg:address":"211 Woodshire Dr",
    "sg:city":"Smyrna",
    "sg:classifiers":[
        {
            "category":"Building & Trades",
            "subcategory":"Plumbing",
            "type":"Services"
        }
    ],
    "sg:phone":"+1 615 220 3944",
    "sg:postcode":"37167",
    "sg:province":"TN",
    "sg:tags":[
        "plumbing",
        "contractor"
    ],
    "wof:name":"Smyrna Plumbing",
    "wof:placetype":"venue"
},
  "geometry": {"coordinates":[-86.488326,35.986805],"type":"Point"}
}