{
  "type": "Feature",
  "properties": {
    "iso:country":"US",
    "sg:address":"1701 E Main St",
    "sg:city":"Chattanooga",
    "sg:classifiers":[
        {
            "category":"Shopping",
            "subcategory":"Florist",
            "type":"Retail Goods"
        }
    ],
    "sg:phone":"+1 423 698 3303",
    "sg:postcode":"37404",
    "sg:province":"TN",
    "sg:website":"www.chatflorist.com",
    "wof:name":"Chattanooga Florist Inc",
    "wof:placetype":"venue"
},
  "geometry": {"coordinates":[-85.282613,35.02697],"type":"Point"}
}