{
  "type": "Feature",
  "properties": {
    "addr:full":"122 Indian Mound Cir Jacksboro TN 37757",
    "addr:housenumber":"122",
    "addr:postcode":"37757",
    "addr:street":"Indian Mound Cir",
    "iso:country":"US",
    "sg:address":"122 Indian Mound Cir",
    "sg:city":"Jacksboro",
    "sg:classifiers":[
        {
            "category":"Autos & Motor Vehicles",
            "subcategory":"Auto Supplies",
            "type":"Retail Goods"
        }
    ],
    "sg:phone":"+1 423 562 6111",
    "sg:postcode":"37757",
    "sg:province":"TN",
    "sg:tags":[
        "tire"
    ],
    "wof:name":"Goad's Wholesale Tire",
    "wof:placetype":"venue"
},
  "geometry": {"coordinates":[-84.18528999999999,36.332939],"type":"Point"}
}