{
  "type": "Feature",
  "properties": {
    "addr:full":"2227 Clayton Ave Memphis TN 38108",
    "addr:housenumber":"2227",
    "addr:postcode":"38108",
    "addr:street":"Clayton Ave",
    "iso:country":"US",
    "sg:address":"2227 Clayton Ave",
    "sg:city":"Memphis",
    "sg:classifiers":[
        {
            "category":"Shopping",
            "subcategory":"Gifts & Souvenirs",
            "type":"Retail Goods"
        }
    ],
    "sg:phone":"+1 901 270 8533",
    "sg:postcode":"38108",
    "sg:province":"TN",
    "sg:tags":[
        "basket",
        "parcel"
    ],
    "wof:name":"A Tiskit A Tasket",
    "wof:placetype":"venue"
},
  "geometry": {"coordinates":[-89.983103,35.176768],"type":"Point"}
}