{
  "type": "Feature",
  "properties": {
    "addr:full":"3224 Wrights Ferry Rd Louisville TN 37777",
    "addr:housenumber":"3224",
    "addr:postcode":"37777",
    "addr:street":"Wrights Ferry Rd",
    "iso:country":"US",
    "sg:address":"3224 Wrights Ferry Rd",
    "sg:city":"Louisville",
    "sg:classifiers":[
        {
            "category":"Professional",
            "subcategory":"Testing Lab",
            "type":"Services"
        }
    ],
    "sg:phone":"+1 865 588 6334",
    "sg:postcode":"37777",
    "sg:province":"TN",
    "sg:tags":[
        "process",
        "control",
        "specification",
        "involving"
    ],
    "wof:name":"I C T",
    "wof:placetype":"venue"
},
  "geometry": {"coordinates":[-83.97999799999999,35.8359],"type":"Point"}
}