{
  "type": "Feature",
  "properties": {
    "iso:country":"US",
    "sg:address":"420 Barkley Ct",
    "sg:city":"Antioch",
    "sg:classifiers":[
        {
            "category":"Professional",
            "subcategory":"Testing Lab",
            "type":"Services"
        }
    ],
    "sg:phone":"+1 615 370 8748",
    "sg:postcode":"37013",
    "sg:province":"TN",
    "sg:tags":[
        "correction",
        "radon"
    ],
    "wof:name":"Advanced Air",
    "wof:placetype":"venue"
},
  "geometry": {"coordinates":[-86.678984,36.036513],"type":"Point"}
}