{
  "type": "Feature",
  "properties": {
    "addr:full":"2823 E Oakland Ave Johnson City TN 37601",
    "addr:housenumber":"2823",
    "addr:postcode":"37601",
    "addr:street":"E Oakland Ave",
    "iso:country":"US",
    "sg:address":"2823 E Oakland Ave",
    "sg:city":"Johnson City",
    "sg:classifiers":[
        {
            "category":"Organizations",
            "subcategory":"Religious Organization",
            "type":"Services"
        }
    ],
    "sg:phone":"+1 423 282 0124",
    "sg:postcode":"37601",
    "sg:province":"TN",
    "wof:name":"Oakland Avenue Baptist Church",
    "wof:placetype":"venue"
},
  "geometry": {"coordinates":[-82.37479,36.359095],"type":"Point"}
}