{
  "type": "Feature",
  "properties": {
    "iso:country":"US",
    "sg:address":"530 Monticello Dr",
    "sg:city":"Seymour",
    "sg:classifiers":[
        {
            "category":"Professional",
            "subcategory":"Management & Consulting",
            "type":"Services"
        }
    ],
    "sg:phone":"+1 865 577 7237",
    "sg:postcode":"37865",
    "sg:province":"TN",
    "wof:name":"Lmr Marketing",
    "wof:placetype":"venue"
},
  "geometry": {"coordinates":[-83.758523,35.882869],"type":"Point"}
}