{
  "type": "Feature",
  "properties": {
    "iso:country":"US",
    "sg:address":"1160 Norwood Ln",
    "sg:city":"Clifton",
    "sg:classifiers":[
        {
            "category":"Shopping",
            "subcategory":"Tobacco",
            "type":"Retail Goods"
        }
    ],
    "sg:phone":"+1 731 925 1836",
    "sg:postcode":"38425",
    "sg:province":"TN",
    "sg:tags":[
        "product"
    ],
    "wof:name":"Norwoods",
    "wof:placetype":"venue"
},
  "geometry": {"coordinates":[-88.03052099999999,35.338651],"type":"Point"}
}