{
  "type": "Feature",
  "properties": {
    "addr:full":"10241 Chapman Hwy Seymour TN 37865",
    "addr:housenumber":"10241",
    "addr:postcode":"37865",
    "addr:street":"Chapman Hwy",
    "iso:country":"US",
    "sg:address":"10241 Chapman Hwy",
    "sg:city":"Seymour",
    "sg:classifiers":[
        {
            "category":"Restaurant",
            "type":"Food & Drink"
        }
    ],
    "sg:phone":"+1 865 579 1208",
    "sg:postcode":"37865",
    "sg:province":"TN",
    "wof:name":"Big Mama's Karaoke Cafe",
    "wof:placetype":"venue"
},
  "geometry": {"coordinates":[-83.788174,35.88292],"type":"Point"}
}