{
  "type": "Feature",
  "properties": {
    "iso:country":"US",
    "sg:address":"373 W Lincoln St",
    "sg:city":"Tullahoma",
    "sg:classifiers":[
        {
            "category":"Food & Beverages",
            "subcategory":"Groceries & Convenience Stores",
            "type":"Retail Goods"
        }
    ],
    "sg:phone":"+1 931 454 9252",
    "sg:postcode":"37388",
    "sg:province":"TN",
    "sg:tags":[
        "grocer"
    ],
    "wof:name":"Save-A-Lot",
    "wof:placetype":"venue"
},
  "geometry": {"coordinates":[-86.215057,35.359226],"type":"Point"}
}