{
  "type": "Feature",
  "properties": {
    "iso:country":"US",
    "sg:address":"3444 Jackson Ave",
    "sg:city":"Memphis",
    "sg:classifiers":[
        {
            "category":"Shopping",
            "subcategory":"Discount & Variety Stores",
            "type":"Retail Goods"
        }
    ],
    "sg:phone":"+1 901 323 1797",
    "sg:postcode":"38108",
    "sg:province":"TN",
    "sg:tags":[
        "merchandise",
        "general"
    ],
    "wof:name":"Don Freudenberg Sales",
    "wof:placetype":"venue"
},
  "geometry": {"coordinates":[-89.94635599999999,35.169661],"type":"Point"}
}