{
  "type": "Feature",
  "properties": {
    "iso:country":"US",
    "sg:address":"4117 Asheville Hwy",
    "sg:city":"Knoxville",
    "sg:classifiers":[
        {
            "category":"Retail",
            "subcategory":"Car Wash",
            "type":"Services"
        }
    ],
    "sg:phone":"+1 865 525 4299",
    "sg:postcode":"37914",
    "sg:province":"TN",
    "sg:tags":[
        "automobile",
        "detail",
        "clean"
    ],
    "wof:name":"Simply Clean Detailing More",
    "wof:placetype":"venue"
},
  "geometry": {"coordinates":[-83.86922800000001,36.00348],"type":"Point"}
}