{
  "type": "Feature",
  "properties": {
    "iso:country":"US",
    "sg:address":"190 Roberts Rd",
    "sg:city":"Luttrell",
    "sg:classifiers":[
        {
            "category":"Wholesale",
            "subcategory":"Auto Parts",
            "type":"Manufacturing & Wholesale Goods"
        }
    ],
    "sg:phone":"+1 865 992 3802",
    "sg:postcode":"37763",
    "sg:province":"TN",
    "sg:tags":[
        "used"
    ],
    "wof:name":"Allen & Roberts Auto Salvage",
    "wof:placetype":"venue"
},
  "geometry": {"coordinates":[-84.539512,35.881765],"type":"Point"}
}