{
  "type": "Feature",
  "properties": {
    "iso:country":"US",
    "sg:address":"326 Hickory Dr",
    "sg:city":"Manchester",
    "sg:classifiers":[
        {
            "category":"Manufacturing",
            "subcategory":"Lumber",
            "type":"Manufacturing & Wholesale Goods"
        }
    ],
    "sg:phone":"+1 931 723 4649",
    "sg:postcode":"37355",
    "sg:province":"TN",
    "sg:tags":[
        "hardwood",
        "mill"
    ],
    "wof:name":"Stock Shop",
    "wof:placetype":"venue"
},
  "geometry": {"coordinates":[-86.009337,35.549451],"type":"Point"}
}