{
  "type": "Feature",
  "properties": {
    "addr:full":"400 N Hill St Lenoir City TN 37771",
    "addr:housenumber":"400",
    "addr:postcode":"37771",
    "addr:street":"N Hill St",
    "iso:country":"US",
    "sg:address":"400 N Hill St",
    "sg:city":"Lenoir City",
    "sg:classifiers":[
        {
            "category":"Shopping",
            "subcategory":"Gifts & Souvenirs",
            "type":"Retail Goods"
        }
    ],
    "sg:phone":"+1 865 986 1718",
    "sg:postcode":"37771",
    "sg:province":"TN",
    "wof:name":"Wilhelminas Collectibles",
    "wof:placetype":"venue"
},
  "geometry": {"coordinates":[-84.266453,35.795014],"type":"Point"}
}