{
  "type": "Feature",
  "properties": {
    "addr:full":"399 Davids Way La Vergne TN 37086",
    "addr:housenumber":"399",
    "addr:postcode":"37086",
    "addr:street":"Davids Way",
    "iso:country":"US",
    "sg:address":"399 Davids Way",
    "sg:city":"La Vergne",
    "sg:classifiers":[
        {
            "category":"Building & Trades",
            "subcategory":"Construction",
            "type":"Services"
        }
    ],
    "sg:phone":"+1 615 793 0786",
    "sg:postcode":"37086",
    "sg:province":"TN",
    "sg:tags":[
        "house"
    ],
    "wof:name":"Prestige Homes of Lake Forest",
    "wof:placetype":"venue"
},
  "geometry": {"coordinates":[-86.555083,36.045329],"type":"Point"}
}