{
  "type": "Feature",
  "properties": {
    "iso:country":"US",
    "sg:address":"2075 Sunnyside Rd",
    "sg:city":"Covington",
    "sg:classifiers":[
        {
            "category":"Farming",
            "subcategory":"Farm & Veterinary Services",
            "type":"Manufacturing & Wholesale Goods"
        }
    ],
    "sg:phone":"+1 901 476 6675",
    "sg:postcode":"38011",
    "sg:province":"TN",
    "sg:tags":[
        "labor",
        "contractor"
    ],
    "wof:name":"Conrad Escue",
    "wof:placetype":"venue"
},
  "geometry": {"coordinates":[-89.671005,35.480785],"type":"Point"}
}