{
  "type": "Feature",
  "properties": {
    "iso:country":"US",
    "sg:address":"7265 Westport Rd",
    "sg:city":"Westport",
    "sg:classifiers":[
        {
            "category":"Government",
            "subcategory":"Post Office",
            "type":"Public Place"
        }
    ],
    "sg:phone":"+1 731 986 3882",
    "sg:postcode":"38387",
    "sg:province":"TN",
    "wof:name":"Westport Post Office",
    "wof:placetype":"venue"
},
  "geometry": {"coordinates":[-88.313309,35.895881],"type":"Point"}
}