{
  "type": "Feature",
  "properties": {
    "iso:country":"US",
    "sg:address":"203 Liberty Hill Loop",
    "sg:city":"Ethridge",
    "sg:classifiers":[
        {
            "category":"Manufacturing",
            "subcategory":"Tools & Machinery",
            "type":"Manufacturing & Wholesale Goods"
        }
    ],
    "sg:phone":"+1 931 829 2177",
    "sg:postcode":"38456",
    "sg:province":"TN",
    "sg:tags":[
        "die",
        "mfg"
    ],
    "wof:name":"Industrial Machine Works",
    "wof:placetype":"venue"
},
  "geometry": {"coordinates":[-87.20832299999999,35.335629],"type":"Point"}
}