{
  "type": "Feature",
  "properties": {
    "iso:country":"US",
    "sg:address":"3636 Katy Holler Rd",
    "sg:city":"Sevierville",
    "sg:classifiers":[
        {
            "category":"Wholesale",
            "subcategory":"Construction Materials",
            "type":"Manufacturing & Wholesale Goods"
        }
    ],
    "sg:phone":"+1 865 429 2267",
    "sg:postcode":"37862",
    "sg:province":"TN",
    "wof:name":"Fryes Smkey Mtn Cstm Cabinets",
    "wof:placetype":"venue"
},
  "geometry": {"coordinates":[-83.626975,35.707197],"type":"Point"}
}