{
  "type": "Feature",
  "properties": {
    "addr:full":"2037 N Broadway St Knoxville TN 37917",
    "addr:housenumber":"2037",
    "addr:postcode":"37917",
    "addr:street":"N Broadway St",
    "iso:country":"US",
    "sg:address":"2037 N Broadway St",
    "sg:city":"Knoxville",
    "sg:classifiers":[
        {
            "category":"Shopping",
            "subcategory":"Department Store",
            "type":"Retail Goods"
        }
    ],
    "sg:phone":"+1 865 546 7040",
    "sg:postcode":"37917",
    "sg:province":"TN",
    "sg:tags":[
        "shop"
    ],
    "wof:name":"Smart Pagers",
    "wof:placetype":"venue"
},
  "geometry": {"coordinates":[-83.92025099999999,35.99203],"type":"Point"}
}