{
  "type": "Feature",
  "properties": {
    "iso:country":"US",
    "sg:address":"5022 Judy Lynn Ave",
    "sg:city":"Memphis",
    "sg:classifiers":[
        {
            "category":"Organizations",
            "subcategory":"Religious Organization",
            "type":"Services"
        }
    ],
    "sg:phone":"+1 901 565 7733",
    "sg:postcode":"38118",
    "sg:province":"TN",
    "wof:name":"The Church Of The Living God Cwfs Inc",
    "wof:placetype":"venue"
},
  "geometry": {"coordinates":[-89.895782,35.07161],"type":"Point"}
}