{
  "type": "Feature",
  "properties": {
    "iso:country":"US",
    "sg:address":"165 S Forrest Ave",
    "sg:city":"Camden",
    "sg:classifiers":[
        {
            "category":"Personal",
            "subcategory":"Beauty Salon",
            "type":"Services"
        }
    ],
    "sg:phone":"+1 731 584 8004",
    "sg:postcode":"38320",
    "sg:province":"TN",
    "wof:name":"Cuts & More",
    "wof:placetype":"venue"
},
  "geometry": {"coordinates":[-88.09695600000001,36.054814],"type":"Point"}
}