{
  "type": "Feature",
  "properties": {
    "iso:country":"US",
    "sg:address":"740 E Meeting St",
    "sg:city":"Dandridge",
    "sg:classifiers":[
        {
            "category":"Freight",
            "type":"Transportation"
        }
    ],
    "sg:phone":"+1 865 397 8780",
    "sg:postcode":"37725",
    "sg:province":"TN",
    "sg:tags":[
        "commercial",
        "storage"
    ],
    "wof:name":"East Gate Indoor & Outdoor",
    "wof:placetype":"venue"
},
  "geometry": {"coordinates":[-83.389009,36.032003],"type":"Point"}
}