{
  "type": "Feature",
  "properties": {
    "addr:full":"26865 6th St Ardmore AL 35739",
    "addr:housenumber":"26865",
    "addr:postcode":"35739",
    "addr:street":"6Th St",
    "iso:country":"US",
    "sg:address":"26865 6th St",
    "sg:city":"Ardmore",
    "sg:classifiers":[
        {
            "category":"Government",
            "subcategory":"Office",
            "type":"Public Place"
        }
    ],
    "sg:phone":"+1 256 423 3891",
    "sg:postcode":"35739",
    "sg:province":"AL",
    "sg:tags":[
        "transportation"
    ],
    "wof:name":"Ardmore Welcome Center",
    "wof:placetype":"venue"
},
  "geometry": {"coordinates":[-86.840457,34.984675],"type":"Point"}
}