{
  "type": "Feature",
  "properties": {
    "iso:country":"US",
    "sg:address":"8949 Dayton Pike",
    "sg:city":"Soddy Daisy",
    "sg:classifiers":[
        {
            "category":"Home & Garden",
            "subcategory":"Furniture",
            "type":"Retail Goods"
        }
    ],
    "sg:phone":"+1 423 332 9918",
    "sg:postcode":"37379",
    "sg:province":"TN",
    "sg:tags":[
        "household",
        "store"
    ],
    "wof:name":"Broadway's Furniture",
    "wof:placetype":"venue"
},
  "geometry": {"coordinates":[-85.214006,35.227024],"type":"Point"}
}