{
  "type": "Feature",
  "properties": {
    "addr:full":"4701 Pleasant Ridge Rd Knoxville TN 37912",
    "addr:housenumber":"4701",
    "addr:postcode":"37912",
    "addr:street":"Pleasant Ridge Rd",
    "iso:country":"US",
    "sg:address":"4701 Pleasant Ridge Rd",
    "sg:city":"Knoxville",
    "sg:classifiers":[
        {
            "category":"Organizations",
            "subcategory":"Religious Organization",
            "type":"Services"
        }
    ],
    "sg:phone":"+1 865 522 6528",
    "sg:postcode":"37912",
    "sg:province":"TN",
    "wof:name":"Olivet Baptist Church",
    "wof:placetype":"venue"
},
  "geometry": {"coordinates":[-83.984568,35.986302],"type":"Point"}
}