{
  "type": "Feature",
  "properties": {
    "addr:full":"581 Dunbar Cave Rd Clarksville TN 37043",
    "addr:housenumber":"581",
    "addr:postcode":"37043",
    "addr:street":"Dunbar Cave Rd",
    "iso:country":"US",
    "sg:address":"581 Dunbar Cave Rd",
    "sg:city":"Clarksville",
    "sg:classifiers":[
        {
            "category":"Sports & Exercise",
            "subcategory":"Golf",
            "type":"Entertainment"
        }
    ],
    "sg:phone":"+1 931 648 0479",
    "sg:postcode":"37043",
    "sg:province":"TN",
    "sg:tags":[
        "course",
        "public"
    ],
    "wof:name":"Swan Lake Golf Course",
    "wof:placetype":"venue"
},
  "geometry": {"coordinates":[-87.301575,36.549561],"type":"Point"}
}