{
  "type": "Feature",
  "properties": {
    "iso:country":"US",
    "sg:address":"1272 Market St",
    "sg:city":"Chattanooga",
    "sg:classifiers":[
        {
            "category":"Wholesale",
            "subcategory":"Non-durable Goods",
            "type":"Manufacturing & Wholesale Goods"
        }
    ],
    "sg:phone":"+1 423 756 0403",
    "sg:postcode":"37402",
    "sg:province":"TN",
    "sg:tags":[
        "button"
    ],
    "wof:name":"Marcus Button Co",
    "wof:placetype":"venue"
},
  "geometry": {"coordinates":[-85.307985,35.040229],"type":"Point"}
}