{
  "type": "Feature",
  "properties": {
    "iso:country":"US",
    "sg:address":"1347 Burton Valley Rd",
    "sg:city":"Nashville",
    "sg:classifiers":[
        {
            "category":"Professional",
            "subcategory":"Business Services",
            "type":"Services"
        }
    ],
    "sg:phone":"+1 615 351 8062",
    "sg:postcode":"37215",
    "sg:province":"TN",
    "wof:name":"Rosenbury Interiors Debra",
    "wof:placetype":"venue"
},
  "geometry": {"coordinates":[-86.81045399999999,36.085044],"type":"Point"}
}