{
  "type": "Feature",
  "properties": {
    "iso:country":"US",
    "sg:address":"303 W Burton St",
    "sg:city":"Murfreesboro",
    "sg:classifiers":[
        {
            "category":"Personal",
            "subcategory":"Beauty Salon",
            "type":"Services"
        }
    ],
    "sg:phone":"+1 615 893 9114",
    "sg:postcode":"37130",
    "sg:province":"TN",
    "wof:name":"Styles 'r Us",
    "wof:placetype":"venue"
},
  "geometry": {"coordinates":[-86.39337500000001,35.84924],"type":"Point"}
}