{
  "type": "Feature",
  "properties": {
    "addr:full":"2901 Gallatin Pike Nashville TN 37216",
    "addr:housenumber":"2901",
    "addr:postcode":"37216",
    "addr:street":"Gallatin Pike",
    "iso:country":"US",
    "sg:address":"2901 Gallatin Pike",
    "sg:city":"Nashville",
    "sg:classifiers":[
        {
            "category":"Autos & Motor Vehicles",
            "subcategory":"Automobile Sales",
            "type":"Retail Goods"
        }
    ],
    "sg:phone":"+1 615 226 6877",
    "sg:postcode":"37216",
    "sg:province":"TN",
    "sg:tags":[
        "car",
        "dealer"
    ],
    "wof:name":"Perez Auto Dealer",
    "wof:placetype":"venue"
},
  "geometry": {"coordinates":[-86.739977,36.201015],"type":"Point"}
}