{
  "type": "Feature",
  "properties": {
    "addr:full":"8230 Concord Rd Brentwood TN 37027",
    "addr:housenumber":"8230",
    "addr:postcode":"37027",
    "addr:street":"Concord Rd",
    "iso:country":"US",
    "sg:address":"8230 Concord Rd",
    "sg:city":"Brentwood",
    "sg:classifiers":[
        {
            "category":"Professional",
            "subcategory":"Management & Consulting",
            "type":"Services"
        }
    ],
    "sg:phone":"+1 615 373 9908",
    "sg:postcode":"37027",
    "sg:province":"TN",
    "sg:tags":[
        "business"
    ],
    "wof:name":"Griffin Consulting",
    "wof:placetype":"venue"
},
  "geometry": {"coordinates":[-86.780995,35.995772],"type":"Point"}
}