{
  "type": "Feature",
  "properties": {
    "iso:country":"US",
    "sg:address":"405 Kimery Levee Rd",
    "sg:city":"Sharon",
    "sg:classifiers":[
        {
            "category":"Manufacturing",
            "subcategory":"Tools & Machinery",
            "type":"Manufacturing & Wholesale Goods"
        }
    ],
    "sg:phone":"+1 731 973 2111",
    "sg:postcode":"38255",
    "sg:province":"TN",
    "sg:tags":[
        "die",
        "maker"
    ],
    "wof:name":"Willis Tool & Die",
    "wof:placetype":"venue"
},
  "geometry": {"coordinates":[-88.886396,36.224423],"type":"Point"}
}