{
  "type": "Feature",
  "properties": {
    "addr:full":"116 Wilson Pike Brentwood TN 37027",
    "addr:housenumber":"116",
    "addr:postcode":"37027",
    "addr:street":"Wilson Pike",
    "iso:country":"US",
    "sg:address":"116 Wilson Pike",
    "sg:city":"Brentwood",
    "sg:classifiers":[
        {
            "category":"Professional",
            "subcategory":"Engineering",
            "type":"Services"
        }
    ],
    "sg:phone":"+1 615 309 8081",
    "sg:postcode":"37027",
    "sg:province":"TN",
    "sg:tags":[
        "engineer"
    ],
    "wof:name":"Ingram Civil Engineering",
    "wof:placetype":"venue"
},
  "geometry": {"coordinates":[-86.78563,36.0348],"type":"Point"}
}