{
  "type": "Feature",
  "properties": {
    "iso:country":"US",
    "sg:address":"2980 Mercer Rd",
    "sg:city":"Brownsville",
    "sg:classifiers":[
        {
            "category":"Retail",
            "subcategory":"Repair Shop",
            "type":"Services"
        }
    ],
    "sg:phone":"+1 731 772 6115",
    "sg:postcode":"38012",
    "sg:province":"TN",
    "sg:tags":[
        "equipment",
        "conditioning",
        "air"
    ],
    "wof:name":"Rightway Services",
    "wof:placetype":"venue"
},
  "geometry": {"coordinates":[-89.212022,35.573727],"type":"Point"}
}