{
  "type": "Feature",
  "properties": {
    "iso:country":"US",
    "sg:address":"6499 Hwy 104 E",
    "sg:city":"Dyersburg",
    "sg:classifiers":[
        {
            "category":"Professional",
            "type":"Services"
        }
    ],
    "sg:phone":"+1 731 285 7448",
    "sg:postcode":"38024",
    "sg:province":"TN",
    "wof:name":"Mary Newbill",
    "wof:placetype":"venue"
},
  "geometry": {"coordinates":[-89.263717,36.025699],"type":"Point"}
}