{
  "type": "Feature",
  "properties": {
    "iso:country":"US",
    "sg:address":"9502 Butler Dr",
    "sg:city":"Brentwood",
    "sg:classifiers":[
        {
            "category":"Insurance",
            "subcategory":"Insurance Agent",
            "type":"Services"
        }
    ],
    "sg:phone":"+1 615 776 3715",
    "sg:postcode":"37027",
    "sg:province":"TN",
    "wof:name":"Perritt & Assoc",
    "wof:placetype":"venue"
},
  "geometry": {"coordinates":[-86.740696,35.980614],"type":"Point"}
}