{
  "type": "Feature",
  "properties": {
    "addr:full":"11540 Lebanon Rd Mount Juliet TN 37122",
    "addr:housenumber":"11540",
    "addr:postcode":"37122",
    "addr:street":"Lebanon Rd",
    "iso:country":"US",
    "sg:address":"11540 Lebanon Rd",
    "sg:city":"Mount Juliet",
    "sg:classifiers":[
        {
            "category":"Restaurant",
            "type":"Food & Drink"
        }
    ],
    "sg:phone":"+1 615 754 0405",
    "sg:postcode":"37122",
    "sg:province":"TN",
    "sg:tags":[
        "eating"
    ],
    "wof:name":"Victors Pizza & Pasta",
    "wof:placetype":"venue"
},
  "geometry": {"coordinates":[-86.524967,36.231015],"type":"Point"}
}