{
  "type": "Feature",
  "properties": {
    "iso:country":"US",
    "sg:address":"1905 McClung Ave",
    "sg:city":"Knoxville",
    "sg:classifiers":[
        {
            "category":"Professional",
            "type":"Services"
        }
    ],
    "sg:phone":"+1 865 579 5525",
    "sg:postcode":"37920",
    "sg:province":"TN",
    "wof:name":"Jimmie K Spires",
    "wof:placetype":"venue"
},
  "geometry": {"coordinates":[-83.886509,35.951769],"type":"Point"}
}