{
  "type": "Feature",
  "properties": {
    "addr:full":"808 Nashville Hwy Columbia TN 38401",
    "addr:housenumber":"808",
    "addr:postcode":"38401",
    "addr:street":"Nashville Hwy",
    "iso:country":"US",
    "sg:address":"808 Nashville Hwy",
    "sg:city":"Columbia",
    "sg:classifiers":[
        {
            "category":"Banks & Credit Unions",
            "subcategory":"Bank",
            "type":"Services"
        }
    ],
    "sg:phone":"+1 931 388 2591",
    "sg:postcode":"38401",
    "sg:province":"TN",
    "sg:tags":[
        "loan"
    ],
    "wof:name":"Farm Credit Svc",
    "wof:placetype":"venue"
},
  "geometry": {"coordinates":[-87.02717800000001,35.628441],"type":"Point"}
}