{
  "type": "Feature",
  "properties": {
    "addr:full":"335 W Broadway St Newport TN 37821",
    "addr:housenumber":"335",
    "addr:postcode":"37821",
    "addr:street":"W Broadway St",
    "iso:country":"US",
    "sg:address":"335 W Broadway St",
    "sg:city":"Newport",
    "sg:classifiers":[
        {
            "category":"Food & Beverages",
            "subcategory":"Liquor & Beverages",
            "type":"Retail Goods"
        }
    ],
    "sg:phone":"+1 423 623 0449",
    "sg:postcode":"37821",
    "sg:province":"TN",
    "sg:tags":[
        "alcoholic"
    ],
    "wof:name":"West End Package Store",
    "wof:placetype":"venue"
},
  "geometry": {"coordinates":[-83.201673,35.968326],"type":"Point"}
}