{
  "type": "Feature",
  "properties": {
    "addr:full":"3071 Honey Tree Dr Germantown TN 38138",
    "addr:housenumber":"3071",
    "addr:postcode":"38138",
    "addr:street":"Honey Tree Dr",
    "iso:country":"US",
    "sg:address":"3071 Honey Tree Dr",
    "sg:city":"Germantown",
    "sg:classifiers":[
        {
            "category":"Professional",
            "subcategory":"Art Services",
            "type":"Services"
        }
    ],
    "sg:phone":"+1 901 754 7837",
    "sg:postcode":"38138",
    "sg:province":"TN",
    "sg:tags":[
        "commercial",
        "design"
    ],
    "wof:name":"Sugar Moon Inc",
    "wof:placetype":"venue"
},
  "geometry": {"coordinates":[-89.784615,35.064777],"type":"Point"}
}