{
  "type": "Feature",
  "properties": {
    "iso:country":"US",
    "sg:address":"101 N Valley View Dr",
    "sg:city":"Carthage",
    "sg:classifiers":[
        {
            "category":"Health Services",
            "subcategory":"Doctor",
            "type":"Services"
        }
    ],
    "sg:phone":"+1 615 735 1950",
    "sg:postcode":"37030",
    "sg:province":"TN",
    "wof:name":"Robert J Wright DDS",
    "wof:placetype":"venue"
},
  "geometry": {"coordinates":[-85.93804299999999,36.258268],"type":"Point"}
}