{
  "type": "Feature",
  "properties": {
    "iso:country":"US",
    "sg:address":"6953 Highland Park Dr",
    "sg:city":"Nashville",
    "sg:classifiers":[
        {
            "category":"Professional",
            "subcategory":"Accounting & Tax Preparation",
            "type":"Services"
        }
    ],
    "sg:phone":"+1 615 354 1155",
    "sg:postcode":"37205",
    "sg:province":"TN",
    "wof:name":"Roslyn B Landa CPA",
    "wof:placetype":"venue"
},
  "geometry": {"coordinates":[-86.888465,36.079374],"type":"Point"}
}