{
  "type": "Feature",
  "properties": {
    "iso:country":"US",
    "sg:address":"426 Cumberland St",
    "sg:city":"Chattanooga",
    "sg:classifiers":[
        {
            "category":"Manufacturing",
            "subcategory":"Electronics",
            "type":"Manufacturing & Wholesale Goods"
        }
    ],
    "sg:phone":"+1 423 697 0636",
    "sg:postcode":"37404",
    "sg:province":"TN",
    "sg:tags":[
        "repair",
        "assembly",
        "board",
        "circuit"
    ],
    "wof:name":"Thermal Transfer Composites",
    "wof:placetype":"venue"
},
  "geometry": {"coordinates":[-85.27963200000001,35.046455],"type":"Point"}
}