{
  "type": "Feature",
  "properties": {
    "iso:country":"US",
    "sg:address":"295 Washington Ave",
    "sg:city":"Memphis",
    "sg:classifiers":[
        {
            "category":"Professional",
            "subcategory":"Lawyer & Legal Services",
            "type":"Services"
        }
    ],
    "sg:phone":"+1 901 523 2364",
    "sg:postcode":"38103",
    "sg:province":"TN",
    "sg:tags":[
        "attorney"
    ],
    "wof:name":"Wilson Mc Rae Ivy & Mc Tyier",
    "wof:placetype":"venue"
},
  "geometry": {"coordinates":[-90.045333,35.147555],"type":"Point"}
}