{
  "type": "Feature",
  "properties": {
    "iso:country":"US",
    "sg:address":"353 Tanglewood Ct",
    "sg:city":"Nashville",
    "sg:classifiers":[
        {
            "category":"Restaurant",
            "type":"Food & Drink"
        }
    ],
    "sg:phone":"+1 615 333 7373",
    "sg:postcode":"37211",
    "sg:province":"TN",
    "wof:name":"Kebabs Gyros Greek Restaurant",
    "wof:placetype":"venue"
},
  "geometry": {"coordinates":[-86.71393,36.082217],"type":"Point"}
}