{
  "type": "Feature",
  "properties": {
    "iso:country":"US",
    "sg:address":"986 US Hwy 51 N",
    "sg:city":"Covington",
    "sg:classifiers":[
        {
            "category":"Shopping",
            "subcategory":"Gifts & Souvenirs",
            "type":"Retail Goods"
        }
    ],
    "sg:phone":"+1 901 475 0017",
    "sg:postcode":"38019",
    "sg:province":"TN",
    "sg:tags":[
        "chine",
        "collectible",
        "wallpaper",
        "shop"
    ],
    "wof:name":"Accents & Memories",
    "wof:placetype":"venue"
},
  "geometry": {"coordinates":[-89.638609,35.585371],"type":"Point"}
}