{
  "type": "Feature",
  "properties": {
    "addr:full":"410 Center St Piney Flats TN 37615",
    "addr:housenumber":"410",
    "addr:postcode":"37615",
    "addr:street":"Center St",
    "iso:country":"US",
    "sg:address":"410 Center St",
    "sg:city":"Piney Flats",
    "sg:classifiers":[
        {
            "category":"Wholesale",
            "subcategory":"Auto Parts",
            "type":"Manufacturing & Wholesale Goods"
        }
    ],
    "sg:phone":"+1 423 391 1332",
    "sg:postcode":"37615",
    "sg:province":"TN",
    "sg:tags":[
        "tire"
    ],
    "sg:website":"www.americantiredistributors.com",
    "wof:name":"American Tire Distributors",
    "wof:placetype":"venue"
},
  "geometry": {"coordinates":[-82.477966,36.420471],"type":"Point"}
}