{
  "type": "Feature",
  "properties": {
    "iso:country":"US",
    "sg:address":"401 American Rd",
    "sg:city":"Nashville",
    "sg:classifiers":[
        {
            "category":"Food & Beverages",
            "subcategory":"Groceries & Convenience Stores",
            "type":"Retail Goods"
        }
    ],
    "sg:phone":"+1 615 000 1111",
    "sg:postcode":"37209",
    "sg:province":"TN",
    "sg:tags":[
        "grocer"
    ],
    "wof:name":"Aldi",
    "wof:placetype":"venue"
},
  "geometry": {"coordinates":[-86.87356200000001,36.146488],"type":"Point"}
}