{
  "type": "Feature",
  "properties": {
    "iso:country":"US",
    "sg:address":"450 Crossroads Church Rd",
    "sg:city":"Camden",
    "sg:classifiers":[
        {
            "category":"Retail",
            "subcategory":"Repair Shop",
            "type":"Services"
        }
    ],
    "sg:phone":"+1 731 584 2165",
    "sg:postcode":"38320",
    "sg:province":"TN",
    "wof:name":"Jordan Uphl & Cstm Design",
    "wof:placetype":"venue"
},
  "geometry": {"coordinates":[-88.14776000000001,36.002315],"type":"Point"}
}