{
  "type": "Feature",
  "properties": {
    "iso:country":"US",
    "sg:address":"1309 Wells Station Rd",
    "sg:city":"Memphis",
    "sg:classifiers":[
        {
            "category":"Building & Trades",
            "subcategory":"Pest Control",
            "type":"Services"
        }
    ],
    "sg:phone":"+1 901 767 1166",
    "sg:postcode":"38108",
    "sg:province":"TN",
    "wof:name":"Aardvark Termite & Pest",
    "wof:placetype":"venue"
},
  "geometry": {"coordinates":[-89.917208,35.167279],"type":"Point"}
}