{
  "type": "Feature",
  "properties": {
    "iso:country":"US",
    "sg:address":"4922 Brainerd Rd",
    "sg:city":"Chattanooga",
    "sg:classifiers":[
        {
            "category":"Personal",
            "subcategory":"Beauty Salon",
            "type":"Services"
        }
    ],
    "sg:phone":"+1 423 892 4404",
    "sg:postcode":"37411",
    "sg:province":"TN",
    "sg:tags":[
        "hair",
        "stylist"
    ],
    "wof:name":"Aurora Designs",
    "wof:placetype":"venue"
},
  "geometry": {"coordinates":[-85.227119,35.012451],"type":"Point"}
}