{
  "type": "Feature",
  "properties": {
    "iso:country":"US",
    "sg:address":"5930 Quintis Loop",
    "sg:city":"Chattanooga",
    "sg:classifiers":[
        {
            "category":"Manufacturing",
            "subcategory":"Rubber & Plastics",
            "type":"Manufacturing & Wholesale Goods"
        }
    ],
    "sg:phone":"+1 423 899 0929",
    "sg:postcode":"37421",
    "sg:province":"TN",
    "sg:tags":[
        "product"
    ],
    "sg:website":"www.wna-inc.com",
    "wof:name":"Wna Amer Plastics Industries",
    "wof:placetype":"venue"
},
  "geometry": {"coordinates":[-85.199264,35.054519],"type":"Point"}
}