{
  "type": "Feature",
  "properties": {
    "addr:full":"251 Hicks Rd Sparta TN 38583",
    "addr:housenumber":"251",
    "addr:postcode":"38583",
    "addr:street":"Hicks Rd",
    "iso:country":"US",
    "sg:address":"251 Hicks Rd",
    "sg:city":"Sparta",
    "sg:classifiers":[
        {
            "category":"Professional",
            "type":"Services"
        }
    ],
    "sg:phone":"+1 931 739 3401",
    "sg:postcode":"38583",
    "sg:province":"TN",
    "sg:tags":[
        "establishment"
    ],
    "wof:name":"Young & Young",
    "wof:placetype":"venue"
},
  "geometry": {"coordinates":[-85.457984,35.894778],"type":"Point"}
}