{
  "type": "Feature",
  "properties": {
    "addr:full":"4711 Delashmitt Rd Hixson TN 37343",
    "addr:housenumber":"4711",
    "addr:postcode":"37343",
    "addr:street":"Delashmitt Rd",
    "iso:country":"US",
    "sg:address":"4711 Delashmitt Rd",
    "sg:city":"Hixson",
    "sg:classifiers":[
        {
            "category":"Organizations",
            "subcategory":"Religious Organization",
            "type":"Services"
        }
    ],
    "sg:phone":"+1 423 877 4779",
    "sg:postcode":"37343",
    "sg:province":"TN",
    "sg:tags":[
        "church"
    ],
    "wof:name":"Delashmitt Road Baptist Church",
    "wof:placetype":"venue"
},
  "geometry": {"coordinates":[-85.266678,35.132995],"type":"Point"}
}