{
  "type": "Feature",
  "properties": {
    "addr:full":"3196 Baja Valley Dr Memphis TN 38133",
    "addr:housenumber":"3196",
    "addr:postcode":"38133",
    "addr:street":"Baja Valley Dr",
    "iso:country":"US",
    "sg:address":"3196 Baja Valley Dr",
    "sg:city":"Memphis",
    "sg:classifiers":[
        {
            "category":"Professional",
            "subcategory":"Business Services",
            "type":"Services"
        }
    ],
    "sg:phone":"+1 901 385 1483",
    "sg:postcode":"38133",
    "sg:province":"TN",
    "wof:name":"Tri-State Drywall Inc",
    "wof:placetype":"venue"
},
  "geometry": {"coordinates":[-89.824433,35.212302],"type":"Point"}
}