{
  "type": "Feature",
  "properties": {
    "iso:country":"US",
    "sg:address":"602 Snodgrass Rd",
    "sg:city":"New Tazewell",
    "sg:classifiers":[
        {
            "category":"Social Services",
            "subcategory":"Child Care",
            "type":"Services"
        }
    ],
    "sg:phone":"+1 423 526 5750",
    "sg:postcode":"37825",
    "sg:province":"TN",
    "sg:tags":[
        "day"
    ],
    "wof:name":"Judys Day Care",
    "wof:placetype":"venue"
},
  "geometry": {"coordinates":[-83.618067,36.435279],"type":"Point"}
}