{
  "type": "Feature",
  "properties": {
    "iso:country":"US",
    "sg:address":"12140 Newport Hwy",
    "sg:city":"Greeneville",
    "sg:classifiers":[
        {
            "category":"Restaurant",
            "type":"Food & Drink"
        }
    ],
    "sg:phone":"+1 423 639 6797",
    "sg:postcode":"37743",
    "sg:province":"TN",
    "wof:name":"Caney Branch Restaurant",
    "wof:placetype":"venue"
},
  "geometry": {"coordinates":[-82.99252799999999,36.046892],"type":"Point"}
}