{
  "type": "Feature",
  "properties": {
    "iso:country":"US",
    "sg:address":"2021 21st Ave S Ste 431",
    "sg:city":"Nashville",
    "sg:classifiers":[
        {
            "category":"Organizations",
            "subcategory":"Membership Organization",
            "type":"Services"
        }
    ],
    "sg:phone":"+1 615 269 9090",
    "sg:postcode":"37212",
    "sg:province":"TN",
    "sg:tags":[
        "environmental",
        "ecological",
        "conservation"
    ],
    "sg:website":"http://www.tnconservationvoters.org",
    "wof:name":"Environmental Action Fund",
    "wof:placetype":"venue"
},
  "geometry": {"coordinates":[-86.801339,36.132934],"type":"Point"}
}