{
  "type": "Feature",
  "properties": {
    "iso:country":"US",
    "sg:address":"201 Gils St",
    "sg:city":"Smyrna",
    "sg:classifiers":[
        {
            "category":"Shopping",
            "subcategory":"Used Merchandise",
            "type":"Retail Goods"
        }
    ],
    "sg:phone":"+1 615 355 4172",
    "sg:postcode":"37167",
    "sg:province":"TN",
    "sg:tags":[
        "fixture",
        "store"
    ],
    "wof:name":"Hanks Enterprises Inc",
    "wof:placetype":"venue"
},
  "geometry": {"coordinates":[-86.491985,35.999333],"type":"Point"}
}