{
  "type": "Feature",
  "properties": {
    "iso:country":"US",
    "sg:address":"3802 Nolensville Pike",
    "sg:city":"Nashville",
    "sg:classifiers":[
        {
            "category":"Shopping",
            "subcategory":"Computers & Home Electronics",
            "type":"Retail Goods"
        }
    ],
    "sg:phone":"+1 615 835 0005",
    "sg:postcode":"37211",
    "sg:province":"TN",
    "sg:tags":[
        "equipment",
        "dealer"
    ],
    "wof:name":"Media Tech Computers",
    "wof:placetype":"venue"
},
  "geometry": {"coordinates":[-86.730906,36.087654],"type":"Point"}
}