{
  "type": "Feature",
  "properties": {
    "iso:country":"US",
    "sg:address":"6940 Short Tail Springs Rd",
    "sg:city":"Harrison",
    "sg:classifiers":[
        {
            "category":"Retail",
            "subcategory":"Auto Repair",
            "type":"Services"
        }
    ],
    "sg:phone":"+1 423 344 5887",
    "sg:postcode":"37341",
    "sg:province":"TN",
    "sg:tags":[
        "repairing",
        "automobile",
        "general"
    ],
    "wof:name":"Hood Automotive",
    "wof:placetype":"venue"
},
  "geometry": {"coordinates":[-85.107788,35.139003],"type":"Point"}
}