{
  "type": "Feature",
  "properties": {
    "iso:country":"US",
    "sg:address":"293 Saint Andrews Dr",
    "sg:city":"Franklin",
    "sg:classifiers":[
        {
            "category":"Manufacturing",
            "subcategory":"Printing",
            "type":"Manufacturing & Wholesale Goods"
        }
    ],
    "sg:phone":"+1 615 662 6948",
    "sg:postcode":"37069",
    "sg:province":"TN",
    "sg:tags":[
        "publishing"
    ],
    "wof:name":"Phoebe Claire Publishing LLC",
    "wof:placetype":"venue"
},
  "geometry": {"coordinates":[-86.948868,36.018959],"type":"Point"}
}