{
  "type": "Feature",
  "properties": {
    "iso:country":"US",
    "sg:address":"3229 Lascassas Pike",
    "sg:city":"Murfreesboro",
    "sg:classifiers":[
        {
            "category":"Food & Beverages",
            "subcategory":"Groceries & Convenience Stores",
            "type":"Retail Goods"
        }
    ],
    "sg:phone":"+1 615 893 7070",
    "sg:postcode":"37130",
    "sg:province":"TN",
    "wof:name":"96 Food Mart",
    "wof:placetype":"venue"
},
  "geometry": {"coordinates":[-86.329044,35.904768],"type":"Point"}
}