{
  "type": "Feature",
  "properties": {
    "iso:country":"US",
    "sg:address":"13340 Lebanon Rd",
    "sg:city":"Mount Juliet",
    "sg:classifiers":[
        {
            "category":"Shopping",
            "subcategory":"Optical Goods",
            "type":"Retail Goods"
        }
    ],
    "sg:phone":"+1 615 773 2171",
    "sg:postcode":"37122",
    "sg:province":"TN",
    "sg:tags":[
        "ophthalmic"
    ],
    "wof:name":"Fiber Optics Innovations",
    "wof:placetype":"venue"
},
  "geometry": {"coordinates":[-86.548131,36.222736],"type":"Point"}
}