{
  "type": "Feature",
  "properties": {
    "addr:full":"2405 Elvis Presley Blvd Memphis TN 38116",
    "addr:housenumber":"2405",
    "addr:postcode":"38116",
    "addr:street":"Elvis Presley Blvd",
    "iso:country":"US",
    "sg:address":"2405 Elvis Presley Blvd",
    "sg:city":"Memphis",
    "sg:classifiers":[
        {
            "category":"Autos & Motor Vehicles",
            "subcategory":"Automobile Sales",
            "type":"Retail Goods"
        }
    ],
    "sg:phone":"+1 901 774 2095",
    "sg:postcode":"38116",
    "sg:province":"TN",
    "sg:tags":[
        "used"
    ],
    "wof:name":"Fine Used Cars Inc",
    "wof:placetype":"venue"
},
  "geometry": {"coordinates":[-90.019474,35.078528],"type":"Point"}
}