{
  "type": "Feature",
  "properties": {
    "addr:full":"1653 E Stone Dr Kingsport TN 37660",
    "addr:housenumber":"1653",
    "addr:postcode":"37660",
    "addr:street":"E Stone Dr",
    "iso:country":"US",
    "sg:address":"1653 E Stone Dr",
    "sg:city":"Kingsport",
    "sg:classifiers":[
        {
            "category":"Utilities",
            "subcategory":"Telephone",
            "type":"Services"
        }
    ],
    "sg:phone":"+1 423 230 1080",
    "sg:postcode":"37660",
    "sg:province":"TN",
    "sg:tags":[
        "communications"
    ],
    "wof:name":"Alltel",
    "wof:placetype":"venue"
},
  "geometry": {"coordinates":[-82.518542,36.547677],"type":"Point"}
}