{
  "type": "Feature",
  "properties": {
    "addr:full":"2620 Walker Ln Nashville TN 37207",
    "addr:housenumber":"2620",
    "addr:postcode":"37207",
    "addr:street":"Walker Ln",
    "iso:country":"US",
    "sg:address":"2620 Walker Ln",
    "sg:city":"Nashville",
    "sg:classifiers":[
        {
            "category":"Building & Trades",
            "subcategory":"Construction",
            "type":"Services"
        }
    ],
    "sg:phone":"+1 615 320 0770",
    "sg:postcode":"37207",
    "sg:province":"TN",
    "sg:tags":[
        "demolition",
        "contractor"
    ],
    "wof:name":"Modern Day Wrecking Co",
    "wof:placetype":"venue"
},
  "geometry": {"coordinates":[-86.80915899999999,36.214998],"type":"Point"}
}