{
  "type": "Feature",
  "properties": {
    "addr:full":"118 S High St Winchester TN 37398",
    "addr:housenumber":"118",
    "addr:postcode":"37398",
    "addr:street":"S High St",
    "iso:country":"US",
    "sg:address":"118 S High St",
    "sg:city":"Winchester",
    "sg:classifiers":[
        {
            "category":"Government",
            "subcategory":"Office",
            "type":"Public Place"
        }
    ],
    "sg:phone":"+1 931 967 4062",
    "sg:postcode":"37398",
    "sg:province":"TN",
    "sg:tags":[
        "job",
        "unemployment"
    ],
    "wof:name":"Labor & Work Force Dev TN Dept",
    "wof:placetype":"venue"
},
  "geometry": {"coordinates":[-86.11281099999999,35.18497],"type":"Point"}
}