{
  "type": "Feature",
  "properties": {
    "iso:country":"US",
    "sg:address":"513 E Unaka Ave",
    "sg:city":"Johnson City",
    "sg:classifiers":[
        {
            "category":"Health Services",
            "subcategory":"Doctor",
            "type":"Services"
        }
    ],
    "sg:phone":"+1 423 232 1316",
    "sg:postcode":"37601",
    "sg:province":"TN",
    "wof:name":"H Charles Mohler DDS",
    "wof:placetype":"venue"
},
  "geometry": {"coordinates":[-82.35154199999999,36.327737],"type":"Point"}
}