{
  "type": "Feature",
  "properties": {
    "iso:country":"US",
    "sg:address":"499 Silver Cove",
    "sg:city":"Ripley",
    "sg:classifiers":[
        {
            "category":"Retail",
            "subcategory":"Auto Repair",
            "type":"Services"
        }
    ],
    "sg:phone":"+1 731 635 7405",
    "sg:postcode":"38063",
    "sg:province":"TN",
    "sg:tags":[
        "automotive"
    ],
    "wof:name":"Sound Xtreme",
    "wof:placetype":"venue"
},
  "geometry": {"coordinates":[-89.546486,35.722622],"type":"Point"}
}