{
  "type": "Feature",
  "properties": {
    "iso:country":"US",
    "sg:address":"1541 Spring Place Rd SE",
    "sg:city":"Cleveland",
    "sg:classifiers":[
        {
            "category":"Autos & Motor Vehicles",
            "subcategory":"Automobile Sales",
            "type":"Retail Goods"
        }
    ],
    "sg:phone":"+1 423 476 8448",
    "sg:postcode":"37311",
    "sg:province":"TN",
    "sg:tags":[
        "used"
    ],
    "wof:name":"Lenderman Auto Sales",
    "wof:placetype":"venue"
},
  "geometry": {"coordinates":[-84.865447,35.136929],"type":"Point"}
}