{
  "type": "Feature",
  "properties": {
    "iso:country":"US",
    "sg:address":"10321 Kingston Pike",
    "sg:city":"Knoxville",
    "sg:classifiers":[
        {
            "category":"Health Services",
            "subcategory":"Doctor",
            "type":"Services"
        },
        {
            "category":"Health Services",
            "subcategory":"Health Practitioner",
            "type":"Services"
        },
        {
            "category":"Health Services",
            "subcategory":"Chiropractor",
            "type":"Services"
        }
    ],
    "sg:phone":"+1 865 584 3565",
    "sg:postcode":"37922",
    "sg:province":"TN",
    "sg:tags":[
        "physician",
        "management",
        "pain",
        "chiropractic",
        "surgeons",
        "therapist",
        "surgeon",
        "physical"
    ],
    "wof:name":"Bearden Healthcare Associates",
    "wof:placetype":"venue"
},
  "geometry": {"coordinates":[-84.12626,35.899959],"type":"Point"}
}