{
  "type": "Feature",
  "properties": {
    "iso:country":"US",
    "sg:address":"1908 S Holly St",
    "sg:city":"Chattanooga",
    "sg:classifiers":[
        {
            "category":"Professional",
            "type":"Services"
        }
    ],
    "sg:phone":"+1 423 624 4328",
    "sg:postcode":"37404",
    "sg:province":"TN",
    "wof:name":"Danielle Dunn",
    "wof:placetype":"venue"
},
  "geometry": {"coordinates":[-85.287037,35.022961],"type":"Point"}
}