{
  "type": "Feature",
  "properties": {
    "addr:full":"215 Sycamore St Jackson TN 38301",
    "addr:housenumber":"215",
    "addr:postcode":"38301",
    "addr:street":"Sycamore St",
    "iso:country":"US",
    "sg:address":"215 Sycamore St",
    "sg:city":"Jackson",
    "sg:classifiers":[
        {
            "category":"Building & Trades",
            "subcategory":"Construction",
            "type":"Services"
        }
    ],
    "sg:phone":"+1 731 423 1777",
    "sg:postcode":"38301",
    "sg:province":"TN",
    "sg:tags":[
        "fire",
        "restoration",
        "damage"
    ],
    "sg:website":"www.criwecare.com",
    "wof:name":"Complete Restoration",
    "wof:placetype":"venue"
},
  "geometry": {"coordinates":[-88.820509,35.611888],"type":"Point"}
}