{
  "type": "Feature",
  "properties": {
    "addr:full":"1433 State Hwy 48 S Dickson TN 37055",
    "addr:housenumber":"1433",
    "addr:postcode":"37055",
    "addr:street":"State Hwy 48 S",
    "iso:country":"US",
    "sg:address":"1433 State Hwy 48 S",
    "sg:city":"Dickson",
    "sg:classifiers":[
        {
            "category":"Professional",
            "subcategory":"Detective & Security Services",
            "type":"Services"
        }
    ],
    "sg:phone":"+1 615 419 0311",
    "sg:postcode":"37055",
    "sg:province":"TN",
    "sg:tags":[
        "car"
    ],
    "wof:name":"Selvidge & Association LLC",
    "wof:placetype":"venue"
},
  "geometry": {"coordinates":[-87.424654,36.038328],"type":"Point"}
}