{
  "type": "Feature",
  "properties": {
    "addr:full":"1102 N 22nd Ave Humboldt TN 38343",
    "addr:housenumber":"1102",
    "addr:postcode":"38343",
    "addr:street":"N 22Nd Ave",
    "iso:country":"US",
    "sg:address":"1102 N 22nd Ave",
    "sg:city":"Humboldt",
    "sg:classifiers":[
        {
            "category":"Organizations",
            "subcategory":"Religious Organization",
            "type":"Services"
        }
    ],
    "sg:phone":"+1 731 784 4410",
    "sg:postcode":"38343",
    "sg:province":"TN",
    "sg:tags":[
        "baptist",
        "church"
    ],
    "wof:name":"Emmanuel Baptist Church",
    "wof:placetype":"venue"
},
  "geometry": {"coordinates":[-88.907546,35.827119],"type":"Point"}
}