{
  "type": "Feature",
  "properties": {
    "iso:country":"US",
    "sg:address":"140 Cusick Rd",
    "sg:city":"Alcoa",
    "sg:classifiers":[
        {
            "category":"Travel",
            "subcategory":"Hotels & Motels",
            "type":"Entertainment"
        }
    ],
    "sg:phone":"+1 865 984 9840",
    "sg:postcode":"37701",
    "sg:province":"TN",
    "sg:tags":[
        "operation"
    ],
    "wof:name":"Comfort Inn",
    "wof:placetype":"venue"
},
  "geometry": {"coordinates":[-83.980796,35.813214],"type":"Point"}
}