{
  "type": "Feature",
  "properties": {
    "addr:full":"7140 US Hwy 64 Bartlett TN 38133",
    "addr:housenumber":"7140",
    "addr:postcode":"38133",
    "addr:street":"Us Hwy 64",
    "iso:country":"US",
    "sg:address":"7140 US Hwy 64",
    "sg:city":"Bartlett",
    "sg:classifiers":[
        {
            "category":"Personal",
            "type":"Services"
        }
    ],
    "sg:phone":"+1 901 386 1106",
    "sg:postcode":"38133",
    "sg:province":"TN",
    "sg:tags":[
        "control",
        "weight"
    ],
    "wof:name":"Inches-A-Weigh",
    "wof:placetype":"venue"
},
  "geometry": {"coordinates":[-89.825576,35.204284],"type":"Point"}
}