{
  "type": "Feature",
  "properties": {
    "iso:country":"US",
    "sg:address":"3949 New Highway 96 W",
    "sg:city":"Franklin",
    "sg:classifiers":[
        {
            "category":"Retail",
            "subcategory":"Animal Services",
            "type":"Services"
        }
    ],
    "sg:phone":"+1 615 591 9060",
    "sg:postcode":"37064",
    "sg:province":"TN",
    "wof:name":"Sersland Heddin Inc",
    "wof:placetype":"venue"
},
  "geometry": {"coordinates":[-86.99926499999999,35.989814],"type":"Point"}
}