{
  "type": "Feature",
  "properties": {
    "addr:full":"1777 Zanzabar Rd Newport TN 37821",
    "addr:housenumber":"1777",
    "addr:postcode":"37821",
    "addr:street":"Zanzabar Rd",
    "iso:country":"US",
    "sg:address":"1777 Zanzabar Rd",
    "sg:city":"Newport",
    "sg:classifiers":[
        {
            "category":"Manufacturing",
            "subcategory":"Petroleum Products",
            "type":"Manufacturing & Wholesale Goods"
        }
    ],
    "sg:phone":"+1 423 623 3695",
    "sg:postcode":"37821",
    "sg:province":"TN",
    "sg:tags":[
        "asphalt",
        "mfg"
    ],
    "wof:name":"Charles Blalock & Sons Asphalt",
    "wof:placetype":"venue"
},
  "geometry": {"coordinates":[-83.188146,35.88414],"type":"Point"}
}