{
  "type": "Feature",
  "properties": {
    "iso:country":"US",
    "sg:address":"4409 Hwy 371",
    "sg:city":"Henning",
    "sg:classifiers":[
        {
            "category":"Professional",
            "type":"Services"
        }
    ],
    "sg:phone":"+1 731 635 5450",
    "sg:postcode":"38041",
    "sg:province":"TN",
    "wof:name":"Peyton & Mathis",
    "wof:placetype":"venue"
},
  "geometry": {"coordinates":[-89.706999,35.676563],"type":"Point"}
}