{
  "type": "Feature",
  "properties": {
    "iso:country":"US",
    "sg:address":"105 S Germantown Pkwy",
    "sg:city":"Cordova",
    "sg:classifiers":[
        {
            "category":"Restaurant",
            "type":"Food & Drink"
        }
    ],
    "sg:phone":"+1 901 755 5915",
    "sg:postcode":"38018",
    "sg:province":"TN",
    "sg:website":"www.raffertys.com",
    "wof:name":"West Tennessee Hunter Jumpers",
    "wof:placetype":"venue"
},
  "geometry": {"coordinates":[-89.798195,35.127515],"type":"Point"}
}