{
  "type": "Feature",
  "properties": {
    "iso:country":"US",
    "sg:address":"2785 Parkway",
    "sg:city":"Pigeon Forge",
    "sg:classifiers":[
        {
            "category":"Restaurant",
            "type":"Food & Drink"
        }
    ],
    "sg:phone":"+1 865 774 7707",
    "sg:postcode":"37863",
    "sg:province":"TN",
    "wof:name":"Happy Days Diner",
    "wof:placetype":"venue"
},
  "geometry": {"coordinates":[-83.56979,35.799639],"type":"Point"}
}