{
  "type": "Feature",
  "properties": {
    "iso:country":"US",
    "sg:address":"6960 Lee Hwy",
    "sg:city":"Chattanooga",
    "sg:classifiers":[
        {
            "category":"Personal",
            "subcategory":"Beauty Salon",
            "type":"Services"
        }
    ],
    "sg:phone":"+1 423 296 4151",
    "sg:postcode":"37421",
    "sg:province":"TN",
    "wof:name":"Aries II",
    "wof:placetype":"venue"
},
  "geometry": {"coordinates":[-85.16303600000001,35.044397],"type":"Point"}
}