{
  "type": "Feature",
  "properties": {
    "iso:country":"US",
    "sg:address":"137 Jordan Dr",
    "sg:city":"Chattanooga",
    "sg:classifiers":[
        {
            "category":"Real Estate",
            "subcategory":"Real Estate Agent",
            "type":"Services"
        }
    ],
    "sg:phone":"+1 423 855 1555",
    "sg:postcode":"37421",
    "sg:province":"TN",
    "sg:tags":[
        "consultant"
    ],
    "wof:name":"Results",
    "wof:placetype":"venue"
},
  "geometry": {"coordinates":[-85.16364900000001,35.04625],"type":"Point"}
}