{
  "type": "Feature",
  "properties": {
    "addr:full":"2184 Arch Rock Dr Sevierville TN 37876",
    "addr:housenumber":"2184",
    "addr:postcode":"37876",
    "addr:street":"Arch Rock Dr",
    "iso:country":"US",
    "sg:address":"2184 Arch Rock Dr",
    "sg:city":"Sevierville",
    "sg:classifiers":[
        {
            "category":"Shopping",
            "subcategory":"Clothing, Apparel, & Fashions",
            "type":"Retail Goods"
        }
    ],
    "sg:phone":"+1 865 429 4883",
    "sg:postcode":"37876",
    "sg:province":"TN",
    "sg:tags":[
        "novelty",
        "embroidered"
    ],
    "wof:name":"Smoky Mountain Embroidery",
    "wof:placetype":"venue"
},
  "geometry": {"coordinates":[-83.463317,35.861685],"type":"Point"}
}