{
  "type": "Feature",
  "properties": {
    "iso:country":"US",
    "sg:address":"80 Monroe Ave",
    "sg:city":"Memphis",
    "sg:classifiers":[
        {
            "category":"Shopping",
            "subcategory":"Computers & Home Electronics",
            "type":"Retail Goods"
        }
    ],
    "sg:phone":"+1 901 202 7015",
    "sg:postcode":"38103",
    "sg:province":"TN",
    "sg:tags":[
        "software"
    ],
    "wof:name":"Adan Technologies",
    "wof:placetype":"venue"
},
  "geometry": {"coordinates":[-90.053349,35.144311],"type":"Point"}
}