{
  "type": "Feature",
  "properties": {
    "iso:country":"US",
    "sg:address":"7189 E Holmes Rd",
    "sg:city":"Memphis",
    "sg:classifiers":[
        {
            "category":"Travel",
            "subcategory":"Travel Agent",
            "type":"Entertainment"
        }
    ],
    "sg:phone":"+1 901 737 0277",
    "sg:postcode":"38125",
    "sg:province":"TN",
    "sg:tags":[
        "agency",
        "bureau"
    ],
    "wof:name":"Majestic Travel",
    "wof:placetype":"venue"
},
  "geometry": {"coordinates":[-89.823364,35.005769],"type":"Point"}
}