{
  "type": "Feature",
  "properties": {
    "iso:country":"US",
    "sg:address":"116 W Melody Ln",
    "sg:city":"Corinth",
    "sg:classifiers":[
        {
            "category":"Freight",
            "type":"Transportation"
        }
    ],
    "sg:phone":"+1 662 287 1444",
    "sg:postcode":"38834",
    "sg:province":"TN",
    "sg:tags":[
        "broker",
        "trucking"
    ],
    "wof:name":"Cross Roads Transportation",
    "wof:placetype":"venue"
},
  "geometry": {"coordinates":[-88.494101,34.933327],"type":"Point"}
}