{
  "type": "Feature",
  "properties": {
    "iso:country":"US",
    "sg:address":"1825 Raven Hill Ct",
    "sg:city":"Knoxville",
    "sg:classifiers":[
        {
            "category":"Organizations",
            "subcategory":"Professional Association",
            "type":"Services"
        }
    ],
    "sg:phone":"+1 865 675 7695",
    "sg:postcode":"37922",
    "sg:province":"TN",
    "sg:tags":[
        "business"
    ],
    "wof:name":"Diamond Mfg Commerce Syst",
    "wof:placetype":"venue"
},
  "geometry": {"coordinates":[-84.100195,35.854724],"type":"Point"}
}