{
  "type": "Feature",
  "properties": {
    "addr:full":"707 W 12th St Columbia TN 38401",
    "addr:housenumber":"707",
    "addr:postcode":"38401",
    "addr:street":"W 12Th St",
    "iso:country":"US",
    "sg:address":"707 W 12th St",
    "sg:city":"Columbia",
    "sg:classifiers":[
        {
            "category":"Real Estate",
            "subcategory":"Real Estate Operator",
            "type":"Services"
        }
    ],
    "sg:phone":"+1 931 381 3873",
    "sg:postcode":"38401",
    "sg:province":"TN",
    "sg:tags":[
        "mobile",
        "home",
        "community"
    ],
    "wof:name":"Woodland Mobile Village",
    "wof:placetype":"venue"
},
  "geometry": {"coordinates":[-87.047067,35.608357],"type":"Point"}
}