{
  "type": "Feature",
  "properties": {
    "iso:country":"US",
    "sg:address":"1869 Harriet Dr",
    "sg:city":"Clarksville",
    "sg:classifiers":[
        {
            "category":"Building & Trades",
            "subcategory":"Construction",
            "type":"Services"
        }
    ],
    "sg:phone":"+1 931 551 4504",
    "sg:postcode":"37040",
    "sg:province":"TN",
    "sg:tags":[
        "carpentry",
        "contractor"
    ],
    "wof:name":"Trim Carpenter Work",
    "wof:placetype":"venue"
},
  "geometry": {"coordinates":[-87.33869199999999,36.555572],"type":"Point"}
}