{
  "type": "Feature",
  "properties": {
    "iso:country":"US",
    "sg:address":"3006 Connie Rd",
    "sg:city":"Knoxville",
    "sg:classifiers":[
        {
            "category":"Retail",
            "subcategory":"Repair Shop",
            "type":"Services"
        }
    ],
    "sg:phone":"+1 865 690 4279",
    "sg:postcode":"37909",
    "sg:province":"TN",
    "wof:name":"Rogers Uphostery",
    "wof:placetype":"venue"
},
  "geometry": {"coordinates":[-84.044144,35.940224],"type":"Point"}
}