{
  "type": "Feature",
  "properties": {
    "addr:full":"122 Cedar Ln Chattanooga TN 37421",
    "addr:housenumber":"122",
    "addr:postcode":"37421",
    "addr:street":"Cedar Ln",
    "iso:country":"US",
    "sg:address":"122 Cedar Ln",
    "sg:city":"Chattanooga",
    "sg:classifiers":[
        {
            "category":"Wholesale",
            "subcategory":"Durable Goods & Equipment",
            "type":"Manufacturing & Wholesale Goods"
        }
    ],
    "sg:phone":"+1 423 894 9417",
    "sg:postcode":"37421",
    "sg:province":"TN",
    "sg:tags":[
        "representative",
        "manufacturer"
    ],
    "wof:name":"CDH Assoc",
    "wof:placetype":"venue"
},
  "geometry": {"coordinates":[-85.200253,35.030081],"type":"Point"}
}