{
  "type": "Feature",
  "properties": {
    "iso:country":"US",
    "sg:address":"5007 Wyoming Ave",
    "sg:city":"Nashville",
    "sg:classifiers":[
        {
            "category":"Professional",
            "subcategory":"Business Services",
            "type":"Services"
        }
    ],
    "sg:phone":"+1 615 460 0157",
    "sg:postcode":"37209",
    "sg:province":"TN",
    "wof:name":"One Community Partners LLC",
    "wof:placetype":"venue"
},
  "geometry": {"coordinates":[-86.848176,36.145228],"type":"Point"}
}