{
  "type": "Feature",
  "properties": {
    "addr:full":"4701 Trousdale Dr Nashville TN 37220",
    "addr:housenumber":"4701",
    "addr:postcode":"37220",
    "addr:street":"Trousdale Dr",
    "iso:country":"US",
    "sg:address":"4701 Trousdale Dr",
    "sg:city":"Nashville",
    "sg:classifiers":[
        {
            "category":"Professional",
            "subcategory":"Computer Services",
            "type":"Services"
        }
    ],
    "sg:phone":"+1 615 331 9590",
    "sg:postcode":"37220",
    "sg:province":"TN",
    "sg:tags":[
        "consultant",
        "designer"
    ],
    "sg:website":"www.kbm-inc.com",
    "wof:name":"KBM",
    "wof:placetype":"venue"
},
  "geometry": {"coordinates":[-86.75845700000001,36.080417],"type":"Point"}
}