{
  "type": "Feature",
  "properties": {
    "iso:country":"US",
    "sg:address":"100 Tateho Dr",
    "sg:city":"Greeneville",
    "sg:classifiers":[
        {
            "category":"Professional",
            "type":"Services"
        }
    ],
    "sg:phone":"+1 423 787 0333",
    "sg:postcode":"37745",
    "sg:province":"TN",
    "sg:tags":[
        "establishment"
    ],
    "sg:website":"www.ucm-group.com",
    "wof:name":"Universal America Inc",
    "wof:placetype":"venue"
},
  "geometry": {"coordinates":[-82.79998999999999,36.18642],"type":"Point"}
}