{
  "type": "Feature",
  "properties": {
    "iso:country":"US",
    "sg:address":"1112 N Rutherford Blvd",
    "sg:city":"Murfreesboro",
    "sg:classifiers":[
        {
            "category":"Organizations",
            "subcategory":"Religious Organization",
            "type":"Services"
        }
    ],
    "sg:phone":"+1 615 893 1520",
    "sg:postcode":"37130",
    "sg:province":"TN",
    "wof:name":"North Boulevard Church Christ",
    "wof:placetype":"venue"
},
  "geometry": {"coordinates":[-86.35287099999999,35.854611],"type":"Point"}
}