{
  "type": "Feature",
  "properties": {
    "iso:country":"US",
    "sg:address":"3565 New Tullahoma Hwy",
    "sg:city":"Manchester",
    "sg:classifiers":[
        {
            "category":"Building & Trades",
            "subcategory":"Equipment Rental",
            "type":"Services"
        }
    ],
    "sg:phone":"+1 931 461 5000",
    "sg:postcode":"37355",
    "sg:province":"TN",
    "sg:tags":[
        "contractor"
    ],
    "wof:name":"Thompson Machinery",
    "wof:placetype":"venue"
},
  "geometry": {"coordinates":[-86.107501,35.429402],"type":"Point"}
}