{
  "type": "Feature",
  "properties": {
    "addr:full":"1395 Pennsylvania St Memphis TN 38106",
    "addr:housenumber":"1395",
    "addr:postcode":"38106",
    "addr:street":"Pennsylvania St",
    "iso:country":"US",
    "sg:address":"1395 Pennsylvania St",
    "sg:city":"Memphis",
    "sg:classifiers":[
        {
            "category":"Organizations",
            "subcategory":"Religious Organization",
            "type":"Services"
        }
    ],
    "sg:phone":"+1 901 942 2028",
    "sg:postcode":"38106",
    "sg:province":"TN",
    "wof:name":"Glad Tidings Church Cogic",
    "wof:placetype":"venue"
},
  "geometry": {"coordinates":[-90.06759,35.109619],"type":"Point"}
}