{
  "type": "Feature",
  "properties": {
    "addr:full":"1175 E College St Brownsville TN 38012",
    "addr:housenumber":"1175",
    "addr:postcode":"38012",
    "addr:street":"E College St",
    "iso:country":"US",
    "sg:address":"1175 E College St",
    "sg:city":"Brownsville",
    "sg:classifiers":[
        {
            "category":"Building & Trades",
            "subcategory":"Cleaning & Sanitation",
            "type":"Services"
        }
    ],
    "sg:phone":"+1 731 779 0803",
    "sg:postcode":"38012",
    "sg:province":"TN",
    "sg:tags":[
        "janitor"
    ],
    "wof:name":"Southern Building Svc",
    "wof:placetype":"venue"
},
  "geometry": {"coordinates":[-89.247297,35.598653],"type":"Point"}
}