{
  "type": "Feature",
  "properties": {
    "iso:country":"US",
    "sg:address":"1644 Mustang Dr",
    "sg:city":"Maryville",
    "sg:classifiers":[
        {
            "category":"Wholesale",
            "subcategory":"Auto Parts",
            "type":"Manufacturing & Wholesale Goods"
        }
    ],
    "sg:phone":"+1 865 984 5007",
    "sg:postcode":"37801",
    "sg:province":"TN",
    "sg:tags":[
        "surgical",
        "mfg"
    ],
    "wof:name":"Key Safety Restraint Systems",
    "wof:placetype":"venue"
},
  "geometry": {"coordinates":[-84.008179,35.758372],"type":"Point"}
}