{
  "type": "Feature",
  "properties": {
    "iso:country":"US",
    "sg:address":"23202 Clocktower Dr",
    "sg:city":"Franklin",
    "sg:classifiers":[
        {
            "category":"Organizations",
            "subcategory":"Professional Association",
            "type":"Services"
        }
    ],
    "sg:phone":"+1 615 771 9775",
    "sg:postcode":"37067",
    "sg:province":"TN",
    "sg:tags":[
        "business"
    ],
    "wof:name":"Benz Merch",
    "wof:placetype":"venue"
},
  "geometry": {"coordinates":[-86.836246,35.948507],"type":"Point"}
}