{
  "type": "Feature",
  "properties": {
    "addr:full":"595 Clear Valley Rd Cookeville TN 38501",
    "addr:housenumber":"595",
    "addr:postcode":"38501",
    "addr:street":"Clear Valley Rd",
    "iso:country":"US",
    "sg:address":"595 Clear Valley Rd",
    "sg:city":"Cookeville",
    "sg:classifiers":[
        {
            "category":"Utilities",
            "subcategory":"Electric",
            "type":"Services"
        }
    ],
    "sg:phone":"+1 931 526 8061",
    "sg:postcode":"38501",
    "sg:province":"TN",
    "wof:name":"Upper Cumberland EMC",
    "wof:placetype":"venue"
},
  "geometry": {"coordinates":[-85.548509,36.184892],"type":"Point"}
}