{
  "type": "Feature",
  "properties": {
    "iso:country":"US",
    "sg:address":"1560 Craft Center Rd",
    "sg:city":"Smithville",
    "sg:classifiers":[
        {
            "category":"Education",
            "subcategory":"Special Training",
            "type":"Public Place"
        }
    ],
    "sg:phone":"+1 615 597 6801",
    "sg:postcode":"37166",
    "sg:province":"TN",
    "wof:name":"Appalachian Center For Crafts",
    "wof:placetype":"venue"
},
  "geometry": {"coordinates":[-85.737131,36.039368],"type":"Point"}
}