{
  "type": "Feature",
  "properties": {
    "iso:country":"US",
    "sg:address":"719 S Jefferson Ave",
    "sg:city":"Cookeville",
    "sg:classifiers":[
        {
            "category":"Organizations",
            "subcategory":"Religious Organization",
            "type":"Services"
        }
    ],
    "sg:phone":"+1 931 528 8701",
    "sg:postcode":"38501",
    "sg:province":"TN",
    "sg:tags":[
        "church"
    ],
    "wof:name":"Praise Cathedral Cog",
    "wof:placetype":"venue"
},
  "geometry": {"coordinates":[-85.500961,36.145874],"type":"Point"}
}