{
  "type": "Feature",
  "properties": {
    "iso:country":"US",
    "sg:address":"126 Public Sq",
    "sg:city":"Lebanon",
    "sg:classifiers":[
        {
            "category":"Manufacturing",
            "subcategory":"Printing",
            "type":"Manufacturing & Wholesale Goods"
        }
    ],
    "sg:phone":"+1 615 444 8553",
    "sg:postcode":"37087",
    "sg:province":"TN",
    "sg:tags":[
        "printer"
    ],
    "wof:name":"Cornerstone Co",
    "wof:placetype":"venue"
},
  "geometry": {"coordinates":[-86.29115,36.207695],"type":"Point"}
}