{
  "type": "Feature",
  "properties": {
    "iso:country":"US",
    "sg:address":"1733 Witt Way Dr",
    "sg:city":"Spring Hill",
    "sg:classifiers":[
        {
            "category":"Building & Trades",
            "subcategory":"Landscaping Services",
            "type":"Services"
        }
    ],
    "sg:phone":"+1 615 302 1501",
    "sg:postcode":"37174",
    "sg:province":"TN",
    "sg:tags":[
        "lawn",
        "maintenance",
        "grounds"
    ],
    "wof:name":"Redman Lawn Care Inc",
    "wof:placetype":"venue"
},
  "geometry": {"coordinates":[-86.92663400000001,35.758401],"type":"Point"}
}