{
  "type": "Feature",
  "properties": {
    "iso:country":"US",
    "sg:address":"4439 Western Ave",
    "sg:city":"Knoxville",
    "sg:classifiers":[
        {
            "category":"Food & Beverages",
            "subcategory":"Groceries & Convenience Stores",
            "type":"Retail Goods"
        }
    ],
    "sg:phone":"+1 865 524 3304",
    "sg:postcode":"37921",
    "sg:province":"TN",
    "wof:name":"Cargo Oil",
    "wof:placetype":"venue"
},
  "geometry": {"coordinates":[-83.988309,35.973074],"type":"Point"}
}