{
  "type": "Feature",
  "properties": {
    "addr:full":"691 Main St Bean Station TN 37723",
    "addr:housenumber":"691",
    "addr:postcode":"37723",
    "addr:street":"Main St",
    "iso:country":"US",
    "sg:address":"691 Main St",
    "sg:city":"Bean Station",
    "sg:classifiers":[
        {
            "category":"Professional",
            "type":"Services"
        }
    ],
    "sg:phone":"+1 865 993 0713",
    "sg:postcode":"37723",
    "sg:province":"TN",
    "wof:name":"Grainger Today",
    "wof:placetype":"venue"
},
  "geometry": {"coordinates":[-84.885008,35.911299],"type":"Point"}
}