{
  "type": "Feature",
  "properties": {
    "addr:full":"88 N Mount Juliet Rd Mt Juliet TN 37122",
    "addr:housenumber":"88",
    "addr:postcode":"37122",
    "addr:street":"N Mount Juliet Rd",
    "iso:country":"US",
    "sg:address":"88 N Mount Juliet Rd",
    "sg:city":"Mt Juliet",
    "sg:classifiers":[
        {
            "category":"Autos & Motor Vehicles",
            "subcategory":"Fuel & Gas Station",
            "type":"Retail Goods"
        }
    ],
    "sg:phone":"+1 615 758 6888",
    "sg:postcode":"37122",
    "sg:province":"TN",
    "sg:tags":[
        "station",
        "gasoline",
        "oil"
    ],
    "wof:name":"Texaco",
    "wof:placetype":"venue"
},
  "geometry": {"coordinates":[-86.51308299999999,36.173601],"type":"Point"}
}