{
  "type": "Feature",
  "properties": {
    "iso:country":"US",
    "sg:address":"224 W North Creek Rd",
    "sg:city":"Springfield",
    "sg:classifiers":[
        {
            "category":"Health Services",
            "subcategory":"Doctor",
            "type":"Services"
        }
    ],
    "sg:phone":"+1 615 384 2482",
    "sg:postcode":"37167",
    "sg:province":"TN",
    "sg:tags":[
        "physician",
        "medical",
        "surgeon"
    ],
    "wof:name":"Tommy H Crunk Dr",
    "wof:placetype":"venue"
},
  "geometry": {"coordinates":[-86.561025,35.89746],"type":"Point"}
}