{
  "type": "Feature",
  "properties": {
    "iso:country":"US",
    "sg:address":"912 Brad Dr",
    "sg:city":"Memphis",
    "sg:classifiers":[
        {
            "category":"Retail",
            "subcategory":"Laundry & Dry Cleaning",
            "type":"Services"
        }
    ],
    "sg:phone":"+1 901 357 4761",
    "sg:postcode":"38127",
    "sg:province":"TN",
    "sg:tags":[
        "drycleaning",
        "plant"
    ],
    "wof:name":"HCW Computer Cleaners Inc",
    "wof:placetype":"venue"
},
  "geometry": {"coordinates":[-90.03229899999999,35.216404],"type":"Point"}
}