{
  "type": "Feature",
  "properties": {
    "iso:country":"US",
    "sg:address":"9816 Chestnut Ridge Rd",
    "sg:city":"Heiskell",
    "sg:classifiers":[
        {
            "category":"Building & Trades",
            "subcategory":"Construction",
            "type":"Services"
        }
    ],
    "sg:phone":"+1 865 947 4525",
    "sg:postcode":"37754",
    "sg:province":"TN",
    "sg:tags":[
        "excavation",
        "contractor"
    ],
    "wof:name":"Kellys Backhoe Service",
    "wof:placetype":"venue"
},
  "geometry": {"coordinates":[-84.061835,36.088543],"type":"Point"}
}