{
  "type": "Feature",
  "properties": {
    "iso:country":"US",
    "sg:address":"1835 Logue Rd",
    "sg:city":"Mt Juliet",
    "sg:classifiers":[
        {
            "category":"Sports & Exercise",
            "subcategory":"Golf",
            "type":"Entertainment"
        },
        {
            "category":"Recreation",
            "type":"Entertainment"
        }
    ],
    "sg:phone":"+1 615 449 7272",
    "sg:postcode":"37122",
    "sg:province":"TN",
    "sg:tags":[
        "club",
        "course",
        "membership"
    ],
    "sg:website":"www.americangolf.com",
    "wof:name":"Pine Creek Golf Course",
    "wof:placetype":"venue"
},
  "geometry": {"coordinates":[-86.478331,36.122717],"type":"Point"}
}