{
  "type": "Feature",
  "properties": {
    "iso:country":"US",
    "sg:address":"1114 Maplewood Rd",
    "sg:city":"Ashland City",
    "sg:classifiers":[
        {
            "category":"Building & Trades",
            "subcategory":"Construction",
            "type":"Services"
        }
    ],
    "sg:phone":"+1 615 792 1627",
    "sg:postcode":"37015",
    "sg:province":"TN",
    "sg:tags":[
        "general",
        "contractor"
    ],
    "wof:name":"Hill Violet Owner Of J & R",
    "wof:placetype":"venue"
},
  "geometry": {"coordinates":[-86.98513199999999,36.29496],"type":"Point"}
}