{
  "type": "Feature",
  "properties": {
    "iso:country":"US",
    "sg:address":"7608 Rutledge Pike",
    "sg:city":"Knoxville",
    "sg:classifiers":[
        {
            "category":"Food & Beverages",
            "subcategory":"Groceries & Convenience Stores",
            "type":"Retail Goods"
        }
    ],
    "sg:phone":"+1 865 971 3142",
    "sg:postcode":"37924",
    "sg:province":"TN",
    "wof:name":"KWIK Shop",
    "wof:placetype":"venue"
},
  "geometry": {"coordinates":[-83.80742499999999,36.047579],"type":"Point"}
}