{
  "type": "Feature",
  "properties": {
    "addr:full":"137 Ocoee Xing NW Cleveland TN 37312",
    "addr:housenumber":"137",
    "addr:postcode":"37312",
    "addr:street":"Ocoee Xing Nw",
    "iso:country":"US",
    "sg:address":"137 Ocoee Xing NW",
    "sg:city":"Cleveland",
    "sg:classifiers":[
        {
            "category":"Real Estate",
            "subcategory":"Real Estate Services",
            "type":"Services"
        },
        {
            "category":"Banks & Credit Unions",
            "subcategory":"Bank",
            "type":"Services"
        }
    ],
    "sg:phone":"+1 423 303 2580",
    "sg:postcode":"37312",
    "sg:province":"TN",
    "sg:tags":[
        "commercial",
        "loan",
        "saving"
    ],
    "sg:website":"http://www.firstnational.com",
    "wof:name":"First National Bank",
    "wof:placetype":"venue"
},
  "geometry": {"coordinates":[-84.85372,35.193806],"type":"Point"}
}