{
  "type": "Feature",
  "properties": {
    "iso:country":"US",
    "sg:address":"7807 E Lamar Alexander Pkwy",
    "sg:city":"Townsend",
    "sg:classifiers":[
        {
            "category":"Autos & Motor Vehicles",
            "subcategory":"Motorcycle Sales",
            "type":"Retail Goods"
        }
    ],
    "sg:phone":"+1 865 448 3321",
    "sg:postcode":"37882",
    "sg:province":"TN",
    "sg:tags":[
        "scooter"
    ],
    "wof:name":"Wheeler's Bike & Leather Wear",
    "wof:placetype":"venue"
},
  "geometry": {"coordinates":[-83.756068,35.676131],"type":"Point"}
}