{
  "type": "Feature",
  "properties": {
    "addr:full":"1034 Mulberry St Loudon TN 37774",
    "addr:housenumber":"1034",
    "addr:postcode":"37774",
    "addr:street":"Mulberry St",
    "iso:country":"US",
    "sg:address":"1034 Mulberry St",
    "sg:city":"Loudon",
    "sg:classifiers":[
        {
            "category":"Home & Garden",
            "subcategory":"Carpets & Floor Coverings",
            "type":"Retail Goods"
        }
    ],
    "sg:phone":"+1 865 408 0107",
    "sg:postcode":"37774",
    "sg:province":"TN",
    "sg:tags":[
        "dealer",
        "install",
        "rug"
    ],
    "wof:name":"R P's Certified Floor Covering",
    "wof:placetype":"venue"
},
  "geometry": {"coordinates":[-84.34881799999999,35.730785],"type":"Point"}
}