{
  "type": "Feature",
  "properties": {
    "iso:country":"US",
    "sg:address":"115 S Bunker Hill Rd",
    "sg:city":"Sparta",
    "sg:classifiers":[
        {
            "category":"Organizations",
            "subcategory":"Non-profit Organization",
            "type":"Services"
        },
        {
            "category":"Social Services",
            "type":"Services"
        }
    ],
    "sg:phone":"+1 931 761 3657",
    "sg:postcode":"38583",
    "sg:province":"TN",
    "sg:tags":[
        "action",
        "agency",
        "community"
    ],
    "wof:name":"North End Community Center",
    "wof:placetype":"venue"
},
  "geometry": {"coordinates":[-85.52315400000001,36.02697],"type":"Point"}
}