{
  "type": "Feature",
  "properties": {
    "iso:country":"US",
    "sg:address":"2635 Decatur Pike",
    "sg:city":"Athens",
    "sg:classifiers":[
        {
            "category":"Restaurant",
            "type":"Food & Drink"
        }
    ],
    "sg:menulink":"http://www.allmenus.com/tn/athens/214946-burger-king/menu/",
    "sg:phone":"+1 423 745 0049",
    "sg:postcode":"37303",
    "sg:province":"TN",
    "sg:tags":[
        "burger",
        "american"
    ],
    "wof:name":"Burger King",
    "wof:placetype":"venue"
},
  "geometry": {"coordinates":[-84.64649199999999,35.463804],"type":"Point"}
}