{
  "type": "Feature",
  "properties": {
    "addr:full":"1743 Westside Dr Maryville TN 37801",
    "addr:housenumber":"1743",
    "addr:postcode":"37801",
    "addr:street":"Westside Dr",
    "iso:country":"US",
    "sg:address":"1743 Westside Dr",
    "sg:city":"Maryville",
    "sg:classifiers":[
        {
            "category":"Real Estate",
            "subcategory":"Architect",
            "type":"Services"
        }
    ],
    "sg:phone":"+1 865 977 0741",
    "sg:postcode":"37801",
    "sg:province":"TN",
    "sg:tags":[
        "architectural"
    ],
    "wof:name":"Ledbetter Design",
    "wof:placetype":"venue"
},
  "geometry": {"coordinates":[-83.99694599999999,35.73483],"type":"Point"}
}