{
  "type": "Feature",
  "properties": {
    "iso:country":"US",
    "sg:address":"119 Market St E",
    "sg:city":"Fayetteville",
    "sg:classifiers":[
        {
            "category":"Shopping",
            "subcategory":"Jewelry",
            "type":"Retail Goods"
        }
    ],
    "sg:phone":"+1 931 433 3301",
    "sg:postcode":"37334",
    "sg:province":"TN",
    "sg:tags":[
        "jeweler"
    ],
    "wof:name":"Parks Jewelers",
    "wof:placetype":"venue"
},
  "geometry": {"coordinates":[-86.570538,35.151206],"type":"Point"}
}