{
  "type": "Feature",
  "properties": {
    "addr:full":"5888 State Hwy 57 E Michie TN 38357",
    "addr:housenumber":"5888",
    "addr:postcode":"38357",
    "addr:street":"State Hwy 57 E Michie",
    "iso:country":"US",
    "sg:address":"5888 State Hwy 57 E",
    "sg:city":"Michie",
    "sg:classifiers":[
        {
            "category":"Farming",
            "subcategory":"Crops",
            "type":"Manufacturing & Wholesale Goods"
        }
    ],
    "sg:phone":"+1 731 632 4712",
    "sg:postcode":"38357",
    "sg:province":"TN",
    "sg:tags":[
        "grove",
        "nut",
        "tree"
    ],
    "wof:name":"Estel Mills",
    "wof:placetype":"venue"
},
  "geometry": {"coordinates":[-88.44314,35.069956],"type":"Point"}
}