{
  "type": "Feature",
  "properties": {
    "iso:country":"US",
    "sg:address":"1203 9th Ave N",
    "sg:city":"Nashville",
    "sg:classifiers":[
        {
            "category":"Organizations",
            "subcategory":"Religious Organization",
            "type":"Services"
        }
    ],
    "sg:phone":"+1 615 256 4326",
    "sg:postcode":"37208",
    "sg:province":"TN",
    "sg:tags":[
        "church"
    ],
    "wof:name":"Fifteenth Avenue Baptst Church",
    "wof:placetype":"venue"
},
  "geometry": {"coordinates":[-86.793026,36.173734],"type":"Point"}
}