{
  "type": "Feature",
  "properties": {
    "iso:country":"US",
    "sg:address":"325 Springlake Rd",
    "sg:city":"Bristol",
    "sg:classifiers":[
        {
            "category":"Professional",
            "subcategory":"Research",
            "type":"Services"
        }
    ],
    "sg:phone":"+1 276 669 7071",
    "sg:postcode":"24201",
    "sg:province":"TN",
    "sg:tags":[
        "nonphysical",
        "commercial"
    ],
    "wof:name":"Hindman Company",
    "wof:placetype":"venue"
},
  "geometry": {"coordinates":[-82.14270999999999,36.621948],"type":"Point"}
}