{
  "type": "Feature",
  "properties": {
    "iso:country":"US",
    "sg:address":"1021 McCallie Ave",
    "sg:city":"Chattanooga",
    "sg:classifiers":[
        {
            "category":"Shopping",
            "subcategory":"Computers & Home Electronics",
            "type":"Retail Goods"
        }
    ],
    "sg:phone":"+1 423 629 2900",
    "sg:postcode":"37403",
    "sg:province":"TN",
    "sg:tags":[
        "software"
    ],
    "sg:website":"www.clinicaldatasys.com",
    "wof:name":"Clinical Data",
    "wof:placetype":"venue"
},
  "geometry": {"coordinates":[-85.28919999999999,35.041275],"type":"Point"}
}