{
  "type": "Feature",
  "properties": {
    "iso:country":"US",
    "sg:address":"103 Circle Dr",
    "sg:city":"Lebanon",
    "sg:classifiers":[
        {
            "category":"Professional",
            "type":"Services"
        }
    ],
    "sg:phone":"+1 615 443 1646",
    "sg:postcode":"37087",
    "sg:province":"TN",
    "sg:tags":[
        "establishment"
    ],
    "wof:name":"May Brothers Inc",
    "wof:placetype":"venue"
},
  "geometry": {"coordinates":[-86.298996,36.190349],"type":"Point"}
}