{
  "type": "Feature",
  "properties": {
    "iso:country":"US",
    "sg:address":"5101 Maryland Way",
    "sg:city":"Brentwood",
    "sg:classifiers":[
        {
            "category":"Personal",
            "type":"Services"
        },
        {
            "category":"Health Services",
            "subcategory":"Health Practitioner",
            "type":"Services"
        }
    ],
    "sg:phone":"+1 615 565 6283",
    "sg:postcode":"37027",
    "sg:province":"TN",
    "sg:tags":[
        "therapist",
        "specialty",
        "massage",
        "outpatient"
    ],
    "wof:name":"Institute For The Healing Arts",
    "wof:placetype":"venue"
},
  "geometry": {"coordinates":[-86.79871199999999,36.033107],"type":"Point"}
}