{
  "type": "Feature",
  "properties": {
    "iso:country":"US",
    "sg:address":"1110 Stuart St",
    "sg:city":"Chattanooga",
    "sg:classifiers":[
        {
            "category":"Autos & Motor Vehicles",
            "subcategory":"Fuel & Gas Station",
            "type":"Retail Goods"
        },
        {
            "category":"Autos & Motor Vehicles",
            "subcategory":"Auto Supplies",
            "type":"Retail Goods"
        },
        {
            "category":"Manufacturing",
            "subcategory":"Petroleum Products",
            "type":"Manufacturing & Wholesale Goods"
        },
        {
            "category":"Utilities",
            "subcategory":"Fuel Oil & Lpg",
            "type":"Services"
        },
        {
            "category":"Military Area",
            "subcategory":"Restricted Area",
            "type":"Public Place"
        }
    ],
    "sg:phone":"+1 423 629 3888",
    "sg:postcode":"37406",
    "sg:province":"TN",
    "sg:tags":[
        "petroleum-bottled",
        "diesel",
        "bulk",
        "economizer",
        "cutting",
        "gas-liquefied",
        "lubricant",
        "oils-fuel"
    ],
    "sg:website":"http://www.parmanlubricants.com",
    "wof:name":"Parman Energy",
    "wof:placetype":"venue"
},
  "geometry": {"coordinates":[-85.26402,35.07689],"type":"Point"}
}