{
  "type": "Feature",
  "properties": {
    "iso:country":"US",
    "sg:address":"556 Burnett Ln",
    "sg:city":"Covington",
    "sg:classifiers":[
        {
            "category":"Building & Trades",
            "subcategory":"Landscaping Services",
            "type":"Services"
        }
    ],
    "sg:phone":"+1 901 476 7178",
    "sg:postcode":"38019",
    "sg:province":"TN",
    "wof:name":"Will Farrington Family Cmtry",
    "wof:placetype":"venue"
},
  "geometry": {"coordinates":[-89.627234,35.541829],"type":"Point"}
}