{
  "type": "Feature",
  "properties": {
    "addr:full":"2400 McCallie Ave Chattanooga TN 37404",
    "addr:housenumber":"2400",
    "addr:postcode":"37404",
    "addr:street":"Mccallie Ave",
    "iso:country":"US",
    "sg:address":"2400 McCallie Ave",
    "sg:city":"Chattanooga",
    "sg:classifiers":[
        {
            "category":"Shopping",
            "subcategory":"Pharmacy",
            "type":"Retail Goods"
        }
    ],
    "sg:phone":"+1 423 629 7283",
    "sg:postcode":"37404",
    "sg:province":"TN",
    "sg:tags":[
        "equipment",
        "hospital",
        "outpatient",
        "drug"
    ],
    "wof:name":"S & J Discount Drugs & Hosp",
    "wof:placetype":"venue"
},
  "geometry": {"coordinates":[-85.266671,35.032934],"type":"Point"}
}