{
  "type": "Feature",
  "properties": {
    "iso:country":"US",
    "sg:address":"4550 City Park Dr",
    "sg:city":"Lenoir City",
    "sg:classifiers":[
        {
            "category":"Restaurant",
            "type":"Food & Drink"
        }
    ],
    "sg:menulink":"http://www.allmenus.com/tn/lenoir-city/210094-calhouns/menu/",
    "sg:phone":"+1 865 988 9838",
    "sg:postcode":"37772",
    "sg:province":"TN",
    "sg:tags":[
        "american"
    ],
    "wof:name":"Calhoun's",
    "wof:placetype":"venue"
},
  "geometry": {"coordinates":[-84.237714,35.79924],"type":"Point"}
}