{
  "type": "Feature",
  "properties": {
    "addr:full":"5397 Wilbanks Dr Hixson TN 37343",
    "addr:housenumber":"5397",
    "addr:postcode":"37343",
    "addr:street":"Wilbanks Dr",
    "iso:country":"US",
    "sg:address":"5397 Wilbanks Dr",
    "sg:city":"Hixson",
    "sg:classifiers":[
        {
            "category":"Building & Trades",
            "subcategory":"Construction",
            "type":"Services"
        }
    ],
    "sg:phone":"+1 423 843 0070",
    "sg:postcode":"37343",
    "sg:province":"TN",
    "sg:tags":[
        "roofing",
        "commercial",
        "contractor"
    ],
    "wof:name":"Sunset Engineered Systems LLC",
    "wof:placetype":"venue"
},
  "geometry": {"coordinates":[-85.231725,35.141184],"type":"Point"}
}