{
  "type": "Feature",
  "properties": {
    "iso:country":"US",
    "sg:address":"664 Peterson Lake Cove",
    "sg:city":"Collierville",
    "sg:classifiers":[
        {
            "category":"Real Estate",
            "subcategory":"Real Estate Agent",
            "type":"Services"
        }
    ],
    "sg:phone":"+1 901 853 4026",
    "sg:postcode":"38017",
    "sg:province":"TN",
    "wof:name":"Don Lemmons Benchmark Realty",
    "wof:placetype":"venue"
},
  "geometry": {"coordinates":[-89.670753,35.057861],"type":"Point"}
}