{
  "type": "Feature",
  "properties": {
    "addr:full":"301 Public Sq Franklin TN 37064",
    "addr:housenumber":"301",
    "addr:postcode":"37064",
    "addr:street":"Public Sq",
    "iso:country":"US",
    "sg:address":"301 Public Sq",
    "sg:city":"Franklin",
    "sg:classifiers":[
        {
            "category":"Real Estate",
            "subcategory":"Real Estate Agent",
            "type":"Services"
        }
    ],
    "sg:phone":"+1 615 794 5484",
    "sg:postcode":"37064",
    "sg:province":"TN",
    "wof:name":"Magli Realty Co",
    "wof:placetype":"venue"
},
  "geometry": {"coordinates":[-86.86882300000001,35.925035],"type":"Point"}
}