{
  "type": "Feature",
  "properties": {
    "iso:country":"US",
    "sg:address":"34 Tarkenton Dr",
    "sg:city":"Humboldt",
    "sg:classifiers":[
        {
            "category":"Food & Beverages",
            "subcategory":"Specialty",
            "type":"Retail Goods"
        }
    ],
    "sg:phone":"+1 731 423 8312",
    "sg:postcode":"38343",
    "sg:province":"TN",
    "sg:tags":[
        "health",
        "diet"
    ],
    "wof:name":"J & G Sales",
    "wof:placetype":"venue"
},
  "geometry": {"coordinates":[-88.856421,35.780886],"type":"Point"}
}