{
  "type": "Feature",
  "properties": {
    "iso:country":"US",
    "sg:address":"213 S 1st St",
    "sg:city":"Union City",
    "sg:classifiers":[
        {
            "category":"Shopping",
            "subcategory":"Jewelry",
            "type":"Retail Goods"
        }
    ],
    "sg:phone":"+1 731 885 9122",
    "sg:postcode":"38261",
    "sg:province":"TN",
    "sg:tags":[
        "repair",
        "manufacturer"
    ],
    "wof:name":"Warren Manufacturing Jewelers",
    "wof:placetype":"venue"
},
  "geometry": {"coordinates":[-89.057484,36.423005],"type":"Point"}
}