{
  "type": "Feature",
  "properties": {
    "iso:country":"US",
    "sg:address":"306 W Depot Ave",
    "sg:city":"Knoxville",
    "sg:classifiers":[
        {
            "category":"Real Estate",
            "subcategory":"Architect",
            "type":"Services"
        }
    ],
    "sg:phone":"+1 865 546 5772",
    "sg:postcode":"37917",
    "sg:province":"TN",
    "sg:tags":[
        "firm",
        "architectural"
    ],
    "sg:website":"www.bullocksmith.com",
    "wof:name":"Bullock Smith & Partners Inc",
    "wof:placetype":"venue"
},
  "geometry": {"coordinates":[-83.921872,35.969917],"type":"Point"}
}