{
  "type": "Feature",
  "properties": {
    "addr:full":"6957 Stage Rd Memphis TN 38133",
    "addr:housenumber":"6957",
    "addr:postcode":"38133",
    "addr:street":"Stage Rd",
    "iso:country":"US",
    "sg:address":"6957 Stage Rd",
    "sg:city":"Memphis",
    "sg:classifiers":[
        {
            "category":"Retail",
            "subcategory":"Auto Repair",
            "type":"Services"
        }
    ],
    "sg:phone":"+1 901 387 2112",
    "sg:postcode":"38133",
    "sg:province":"TN",
    "sg:tags":[
        "shop",
        "automobile"
    ],
    "wof:name":"Ai Collision",
    "wof:placetype":"venue"
},
  "geometry": {"coordinates":[-89.832516,35.205223],"type":"Point"}
}