{
  "type": "Feature",
  "properties": {
    "iso:country":"US",
    "sg:address":"18 Buntley Hill Rd",
    "sg:city":"Mulberry",
    "sg:classifiers":[
        {
            "category":"Building & Trades",
            "subcategory":"Construction",
            "type":"Services"
        }
    ],
    "sg:phone":"+1 931 433 0264",
    "sg:postcode":"37359",
    "sg:province":"TN",
    "sg:tags":[
        "hanging",
        "contractor"
    ],
    "wof:name":"Justin Sullivan",
    "wof:placetype":"venue"
},
  "geometry": {"coordinates":[-86.40561099999999,35.190959],"type":"Point"}
}