{
  "type": "Feature",
  "properties": {
    "addr:full":"5475 Poplar Ave Memphis TN 38119",
    "addr:housenumber":"5475",
    "addr:postcode":"38119",
    "addr:street":"Poplar Ave",
    "iso:country":"US",
    "sg:address":"5475 Poplar Ave",
    "sg:city":"Memphis",
    "sg:classifiers":[
        {
            "category":"Utilities",
            "subcategory":"Mobile Phone",
            "type":"Services"
        }
    ],
    "sg:phone":"+1 901 680 8540",
    "sg:postcode":"38119",
    "sg:province":"TN",
    "sg:tags":[
        "telephone",
        "cellular"
    ],
    "wof:name":"Cingular Wireless",
    "wof:placetype":"venue"
},
  "geometry": {"coordinates":[-89.879052,35.106115],"type":"Point"}
}