{
  "type": "Feature",
  "properties": {
    "iso:country":"US",
    "sg:address":"733 N Manassas St",
    "sg:city":"Memphis",
    "sg:classifiers":[
        {
            "category":"Organizations",
            "subcategory":"Religious Organization",
            "type":"Services"
        }
    ],
    "sg:phone":"+1 901 527 7003",
    "sg:postcode":"38107",
    "sg:province":"TN",
    "sg:tags":[
        "churches-baptist"
    ],
    "wof:name":"True Fellowship",
    "wof:placetype":"venue"
},
  "geometry": {"coordinates":[-90.032642,35.160705],"type":"Point"}
}