{
  "type": "Feature",
  "properties": {
    "iso:country":"US",
    "sg:address":"1024 Campbell St",
    "sg:city":"Jackson",
    "sg:classifiers":[
        {
            "category":"Restaurant",
            "type":"Food & Drink"
        }
    ],
    "sg:phone":"+1 731 423 8566",
    "sg:postcode":"38301",
    "sg:province":"TN",
    "wof:name":"Pig House Bar-B-Cue Inc",
    "wof:placetype":"venue"
},
  "geometry": {"coordinates":[-88.82284199999999,35.638736],"type":"Point"}
}