{
  "type": "Feature",
  "properties": {
    "iso:country":"US",
    "sg:address":"401 Maddox-Simpson Pkwy",
    "sg:city":"Lebanon",
    "sg:classifiers":[
        {
            "category":"Wholesale",
            "subcategory":"Groceries",
            "type":"Manufacturing & Wholesale Goods"
        }
    ],
    "sg:phone":"+1 615 444 2963",
    "sg:postcode":"37090",
    "sg:province":"TN",
    "sg:tags":[
        "food",
        "product"
    ],
    "sg:website":"www.pfglester.com",
    "wof:name":"PFG-Lester",
    "wof:placetype":"venue"
},
  "geometry": {"coordinates":[-86.297156,36.173414],"type":"Point"}
}