{
  "type": "Feature",
  "properties": {
    "iso:country":"US",
    "sg:address":"208 Jaclyn Ct",
    "sg:city":"Franklin",
    "sg:classifiers":[
        {
            "category":"Professional",
            "subcategory":"Management & Consulting",
            "type":"Services"
        }
    ],
    "sg:phone":"+1 615 595 7338",
    "sg:postcode":"37064",
    "sg:province":"TN",
    "sg:tags":[
        "public",
        "relations"
    ],
    "wof:name":"Steven Massie",
    "wof:placetype":"venue"
},
  "geometry": {"coordinates":[-86.86132499999999,35.897509],"type":"Point"}
}