{
  "type": "Feature",
  "properties": {
    "iso:country":"US",
    "sg:address":"4309 Deerfield Rd",
    "sg:city":"Knoxville",
    "sg:classifiers":[
        {
            "category":"Building & Trades",
            "subcategory":"Construction",
            "type":"Services"
        }
    ],
    "sg:phone":"+1 865 588 8698",
    "sg:postcode":"37921",
    "sg:province":"TN",
    "sg:tags":[
        "house"
    ],
    "wof:name":"Ccg Construction LLC",
    "wof:placetype":"venue"
},
  "geometry": {"coordinates":[-84.014548,35.982614],"type":"Point"}
}