{
  "type": "Feature",
  "properties": {
    "addr:full":"550 Carter Ln Smyrna TN 37167",
    "addr:housenumber":"550",
    "addr:postcode":"37167",
    "addr:street":"Carter Ln",
    "iso:country":"US",
    "sg:address":"550 Carter Ln",
    "sg:city":"Smyrna",
    "sg:classifiers":[
        {
            "category":"Building & Trades",
            "subcategory":"Construction",
            "type":"Services"
        }
    ],
    "sg:phone":"+1 615 459 3613",
    "sg:postcode":"37167",
    "sg:province":"TN",
    "sg:tags":[
        "home",
        "improvement"
    ],
    "wof:name":"All Star Remodeling",
    "wof:placetype":"venue"
},
  "geometry": {"coordinates":[-86.527873,35.952236],"type":"Point"}
}