{
  "type": "Feature",
  "properties": {
    "iso:country":"US",
    "sg:address":"846 Highway 51 N",
    "sg:city":"Ripley",
    "sg:classifiers":[
        {
            "category":"Autos & Motor Vehicles",
            "subcategory":"Fuel & Gas Station",
            "type":"Retail Goods"
        },
        {
            "category":"Food & Beverages",
            "subcategory":"Supermarket",
            "type":"Retail Goods"
        },
        {
            "category":"Food & Beverages",
            "subcategory":"Groceries & Convenience Stores",
            "type":"Retail Goods"
        }
    ],
    "sg:phone":"+1 731 635 4972",
    "sg:postcode":"38063",
    "sg:province":"TN",
    "sg:tags":[
        "super"
    ],
    "wof:name":"Short Stop Food Store",
    "wof:placetype":"venue"
},
  "geometry": {"coordinates":[-89.542068,35.764782],"type":"Point"}
}