{
  "type": "Feature",
  "properties": {
    "addr:full":"507 N Main St Cornersville TN 37047",
    "addr:housenumber":"507",
    "addr:postcode":"37047",
    "addr:street":"N Main St",
    "iso:country":"US",
    "sg:address":"507 N Main St",
    "sg:city":"Cornersville",
    "sg:classifiers":[
        {
            "category":"Retail",
            "subcategory":"Repair Shop",
            "type":"Services"
        }
    ],
    "sg:phone":"+1 931 293 2999",
    "sg:postcode":"37047",
    "sg:province":"TN",
    "sg:tags":[
        "repairing",
        "lawn",
        "mower"
    ],
    "wof:name":"Munchies Outdoor Power Eqpt",
    "wof:placetype":"venue"
},
  "geometry": {"coordinates":[-86.838348,35.373503],"type":"Point"}
}