{
  "type": "Feature",
  "properties": {
    "iso:country":"US",
    "sg:address":"349 E Pkwy",
    "sg:city":"Gatlinburg",
    "sg:classifiers":[
        {
            "category":"Shopping",
            "subcategory":"Tobacco",
            "type":"Retail Goods"
        }
    ],
    "sg:phone":"+1 865 436 4228",
    "sg:postcode":"37738",
    "sg:province":"TN",
    "sg:tags":[
        "cigarette",
        "cigar",
        "dealer"
    ],
    "wof:name":"East Park Tobacco Outlet",
    "wof:placetype":"venue"
},
  "geometry": {"coordinates":[-83.506484,35.716034],"type":"Point"}
}