{
  "type": "Feature",
  "properties": {
    "iso:country":"US",
    "sg:address":"1801 S Bell Ave",
    "sg:city":"Paris",
    "sg:classifiers":[
        {
            "category":"Wholesale",
            "subcategory":"Machinery & Supplies",
            "type":"Manufacturing & Wholesale Goods"
        }
    ],
    "sg:phone":"+1 731 642 6789",
    "sg:postcode":"38242",
    "sg:province":"TN",
    "sg:tags":[
        "janitor"
    ],
    "wof:name":"Universal Sales Co",
    "wof:placetype":"venue"
},
  "geometry": {"coordinates":[-88.29181699999999,36.310566],"type":"Point"}
}