{
  "type": "Feature",
  "properties": {
    "iso:country":"US",
    "sg:address":"2161 Mackie Rd",
    "sg:city":"Cookeville",
    "sg:classifiers":[
        {
            "category":"Building & Trades",
            "subcategory":"Construction",
            "type":"Services"
        }
    ],
    "sg:phone":"+1 931 520 3496",
    "sg:postcode":"38506",
    "sg:province":"TN",
    "sg:tags":[
        "hanging",
        "contractor"
    ],
    "wof:name":"Davids Painting",
    "wof:placetype":"venue"
},
  "geometry": {"coordinates":[-85.47938499999999,36.082492],"type":"Point"}
}