{
  "type": "Feature",
  "properties": {
    "iso:country":"US",
    "sg:address":"1720 W Andrew Johnson Hwy",
    "sg:city":"Morristown",
    "sg:classifiers":[
        {
            "category":"Shopping",
            "subcategory":"Clothing, Apparel, & Fashions",
            "type":"Retail Goods"
        }
    ],
    "sg:phone":"+1 423 586 5732",
    "sg:postcode":"37814",
    "sg:province":"TN",
    "wof:name":"DAWSONS MENS SHOP",
    "wof:placetype":"venue"
},
  "geometry": {"coordinates":[-83.314196,36.207361],"type":"Point"}
}