{
  "type": "Feature",
  "properties": {
    "addr:full":"2900 Hamilton Church Rd Antioch TN 37013",
    "addr:housenumber":"2900",
    "addr:postcode":"37013",
    "addr:street":"Hamilton Church Rd",
    "iso:country":"US",
    "sg:address":"2900 Hamilton Church Rd",
    "sg:city":"Antioch",
    "sg:classifiers":[
        {
            "category":"Real Estate",
            "subcategory":"Real Estate Operator",
            "type":"Services"
        }
    ],
    "sg:phone":"+1 615 731 4210",
    "sg:postcode":"37013",
    "sg:province":"TN",
    "sg:tags":[
        "building",
        "apartment"
    ],
    "wof:name":"Hickory Manor Apartments",
    "wof:placetype":"venue"
},
  "geometry": {"coordinates":[-86.636534,36.055088],"type":"Point"}
}