{
  "type": "Feature",
  "properties": {
    "iso:country":"US",
    "sg:address":"201 Evergreen St",
    "sg:city":"Greenfield",
    "sg:classifiers":[
        {
            "category":"Retail",
            "subcategory":"Auto Repair",
            "type":"Services"
        }
    ],
    "sg:phone":"+1 731 235 3085",
    "sg:postcode":"38230",
    "sg:province":"TN",
    "sg:tags":[
        "automotive",
        "general"
    ],
    "wof:name":"Coats Car Care",
    "wof:placetype":"venue"
},
  "geometry": {"coordinates":[-88.79822900000001,36.156317],"type":"Point"}
}