{
  "type": "Feature",
  "properties": {
    "iso:country":"US",
    "sg:address":"348 Shelton Rd",
    "sg:city":"Collierville",
    "sg:classifiers":[
        {
            "category":"Autos & Motor Vehicles",
            "subcategory":"Auto Supplies",
            "type":"Retail Goods"
        }
    ],
    "sg:phone":"+1 901 854 1747",
    "sg:postcode":"38017",
    "sg:province":"TN",
    "sg:tags":[
        "tire"
    ],
    "wof:name":"Collins Tire Svc",
    "wof:placetype":"venue"
},
  "geometry": {"coordinates":[-89.655153,35.074425],"type":"Point"}
}