{
  "type": "Feature",
  "properties": {
    "addr:full":"528 N Willow Ave Cookeville TN 38501",
    "addr:housenumber":"528",
    "addr:postcode":"38501",
    "addr:street":"N Willow Ave",
    "iso:country":"US",
    "sg:address":"528 N Willow Ave",
    "sg:city":"Cookeville",
    "sg:classifiers":[
        {
            "category":"Insurance",
            "subcategory":"Insurance Agent",
            "type":"Services"
        }
    ],
    "sg:phone":"+1 931 528 7988",
    "sg:postcode":"38501",
    "sg:province":"TN",
    "wof:name":"Nationwide Mutual Insurance",
    "wof:placetype":"venue"
},
  "geometry": {"coordinates":[-85.511926,36.17102],"type":"Point"}
}