{
  "type": "Feature",
  "properties": {
    "iso:country":"US",
    "sg:address":"4308 Mascarene Rd NW",
    "sg:city":"Knoxville",
    "sg:classifiers":[
        {
            "category":"Home & Garden",
            "subcategory":"Carpets & Floor Coverings",
            "type":"Retail Goods"
        }
    ],
    "sg:phone":"+1 865 588 1619",
    "sg:postcode":"37921",
    "sg:province":"TN",
    "wof:name":"Headrick Flooring",
    "wof:placetype":"venue"
},
  "geometry": {"coordinates":[-84.008745,35.971889],"type":"Point"}
}