{
  "type": "Feature",
  "properties": {
    "iso:country":"US",
    "sg:address":"4296 Hwy 31 W",
    "sg:city":"Cross Plains",
    "sg:classifiers":[
        {
            "category":"Freight",
            "type":"Transportation"
        }
    ],
    "sg:phone":"+1 615 654 4103",
    "sg:postcode":"37049",
    "sg:province":"TN",
    "sg:tags":[
        "commercial",
        "storage"
    ],
    "wof:name":"Crossroads Mini Storage",
    "wof:placetype":"venue"
},
  "geometry": {"coordinates":[-86.63841499999999,36.52288],"type":"Point"}
}