{
  "type": "Feature",
  "properties": {
    "iso:country":"US",
    "sg:address":"724 Bear Walk Way",
    "sg:city":"Gatlinburg",
    "sg:classifiers":[
        {
            "category":"Professional",
            "type":"Services"
        }
    ],
    "sg:phone":"+1 865 436 2509",
    "sg:postcode":"37738",
    "sg:province":"TN",
    "wof:name":"McGuffin Winter",
    "wof:placetype":"venue"
},
  "geometry": {"coordinates":[-83.52475200000001,35.723816],"type":"Point"}
}