{
  "type": "Feature",
  "properties": {
    "addr:full":"3512 Country Way Rd Antioch TN 37013",
    "addr:housenumber":"3512",
    "addr:postcode":"37013",
    "addr:street":"Country Way Rd",
    "iso:country":"US",
    "sg:address":"3512 Country Way Rd",
    "sg:city":"Antioch",
    "sg:classifiers":[
        {
            "category":"Personal",
            "subcategory":"Barber",
            "type":"Services"
        }
    ],
    "sg:phone":"+1 615 367 3947",
    "sg:postcode":"37013",
    "sg:province":"TN",
    "sg:tags":[
        "shop"
    ],
    "wof:name":"Essence Barber Shop",
    "wof:placetype":"venue"
},
  "geometry": {"coordinates":[-86.598658,36.073539],"type":"Point"}
}