{
  "type": "Feature",
  "properties": {
    "addr:full":"831 Cowan St Nashville TN 37207",
    "addr:housenumber":"831",
    "addr:postcode":"37207",
    "addr:street":"Cowan St",
    "iso:country":"US",
    "sg:address":"831 Cowan St",
    "sg:city":"Nashville",
    "sg:classifiers":[
        {
            "category":"Wholesale",
            "subcategory":"Furniture",
            "type":"Manufacturing & Wholesale Goods"
        }
    ],
    "sg:phone":"+1 615 238 2525",
    "sg:postcode":"37207",
    "sg:province":"TN",
    "sg:tags":[
        "furniture-wholesale",
        "manufacturer"
    ],
    "wof:name":"N D I Wholesale",
    "wof:placetype":"venue"
},
  "geometry": {"coordinates":[-86.777315,36.187187],"type":"Point"}
}