{
  "type": "Feature",
  "properties": {
    "iso:country":"US",
    "sg:address":"610 Franklin Limestone Rd",
    "sg:city":"Nashville",
    "sg:classifiers":[
        {
            "category":"Building & Trades",
            "subcategory":"Construction",
            "type":"Services"
        }
    ],
    "sg:phone":"+1 615 361 1008",
    "sg:postcode":"37217",
    "sg:province":"TN",
    "sg:tags":[
        "contractor"
    ],
    "wof:name":"Sky Line Roofing",
    "wof:placetype":"venue"
},
  "geometry": {"coordinates":[-86.66649700000001,36.082622],"type":"Point"}
}