{
  "type": "Feature",
  "properties": {
    "iso:country":"US",
    "sg:address":"1215 Currey Rd",
    "sg:city":"Nashville",
    "sg:classifiers":[
        {
            "category":"Shopping",
            "type":"Retail Goods"
        }
    ],
    "sg:phone":"+1 615 361 5126",
    "sg:postcode":"37217",
    "sg:province":"TN",
    "sg:tags":[
        "merchandise"
    ],
    "wof:name":"Keith Signs & Outdoor Advg",
    "wof:placetype":"venue"
},
  "geometry": {"coordinates":[-86.70399500000001,36.105264],"type":"Point"}
}