{
  "type": "Feature",
  "properties": {
    "addr:full":"449 N Broadway Portland TN 37148",
    "addr:housenumber":"449",
    "addr:postcode":"37148",
    "addr:street":"N Broadway",
    "iso:country":"US",
    "sg:address":"449 N Broadway",
    "sg:city":"Portland",
    "sg:classifiers":[
        {
            "category":"Professional",
            "type":"Services"
        }
    ],
    "sg:phone":"+1 615 323 1804",
    "sg:postcode":"37148",
    "sg:province":"TN",
    "wof:name":"La Fama",
    "wof:placetype":"venue"
},
  "geometry": {"coordinates":[-86.518114,36.584575],"type":"Point"}
}