{
  "type": "Feature",
  "properties": {
    "iso:country":"US",
    "sg:address":"1135 Brownlee Rd",
    "sg:city":"Memphis",
    "sg:classifiers":[
        {
            "category":"Professional",
            "type":"Services"
        }
    ],
    "sg:phone":"+1 901 344 0070",
    "sg:postcode":"38116",
    "sg:province":"TN",
    "wof:name":"Donelson Chavez",
    "wof:placetype":"venue"
},
  "geometry": {"coordinates":[-90.03360000000001,35.03256],"type":"Point"}
}