{
  "type": "Feature",
  "properties": {
    "addr:full":"803 Valley St Seymour TN 37865",
    "addr:housenumber":"803",
    "addr:postcode":"37865",
    "addr:street":"Valley St",
    "iso:country":"US",
    "sg:address":"803 Valley St",
    "sg:city":"Seymour",
    "sg:classifiers":[
        {
            "category":"Professional",
            "subcategory":"Business Services",
            "type":"Services"
        }
    ],
    "sg:phone":"+1 865 577 7217",
    "sg:postcode":"37865",
    "sg:province":"TN",
    "wof:name":"Tycot Enterprises",
    "wof:placetype":"venue"
},
  "geometry": {"coordinates":[-83.787277,35.863636],"type":"Point"}
}