{
  "type": "Feature",
  "properties": {
    "iso:country":"US",
    "sg:address":"1224 Applecross Dr",
    "sg:city":"Nashville",
    "sg:classifiers":[
        {
            "category":"Professional",
            "subcategory":"Business Services",
            "type":"Services"
        }
    ],
    "sg:phone":"+1 615 332 0250",
    "sg:postcode":"37220",
    "sg:province":"TN",
    "wof:name":"Whitfield Group Inc",
    "wof:placetype":"venue"
},
  "geometry": {"coordinates":[-86.750449,36.054851],"type":"Point"}
}