{
  "type": "Feature",
  "properties": {
    "iso:country":"US",
    "sg:address":"211 Cusick Rd",
    "sg:city":"Alcoa",
    "sg:classifiers":[
        {
            "category":"Restaurant",
            "type":"Food & Drink"
        }
    ],
    "sg:phone":"+1 865 984 3906",
    "sg:postcode":"37701",
    "sg:province":"TN",
    "sg:tags":[
        "drinking",
        "eating"
    ],
    "wof:name":"Alice's Place",
    "wof:placetype":"venue"
},
  "geometry": {"coordinates":[-83.978206,35.814468],"type":"Point"}
}