{
  "type": "Feature",
  "properties": {
    "addr:full":"1011 W Madison Ave Athens TN 37303",
    "addr:housenumber":"1011",
    "addr:postcode":"37303",
    "addr:street":"W Madison Ave",
    "iso:country":"US",
    "sg:address":"1011 W Madison Ave",
    "sg:city":"Athens",
    "sg:classifiers":[
        {
            "category":"Health Services",
            "subcategory":"Doctor",
            "type":"Services"
        }
    ],
    "sg:phone":"+1 423 507 8826",
    "sg:postcode":"37303",
    "sg:province":"TN",
    "sg:tags":[
        "physician",
        "surgeon"
    ],
    "wof:name":"Psychiatric Svc Of E Tenn",
    "wof:placetype":"venue"
},
  "geometry": {"coordinates":[-84.606921,35.439538],"type":"Point"}
}