{
  "type": "Feature",
  "properties": {
    "iso:country":"US",
    "sg:address":"285 Cumberland St",
    "sg:city":"Memphis",
    "sg:classifiers":[
        {
            "category":"Shopping",
            "subcategory":"Used Merchandise",
            "type":"Retail Goods"
        }
    ],
    "sg:phone":"+1 901 507 3040",
    "sg:postcode":"38112",
    "sg:province":"TN",
    "sg:tags":[
        "antique"
    ],
    "wof:name":"Rowland Enterprises Inc",
    "wof:placetype":"venue"
},
  "geometry": {"coordinates":[-89.96937699999999,35.143106],"type":"Point"}
}