{
  "type": "Feature",
  "properties": {
    "iso:country":"US",
    "sg:address":"1800 Mallory Ln",
    "sg:city":"Brentwood",
    "sg:classifiers":[
        {
            "category":"Shopping",
            "subcategory":"Clothing, Apparel, & Fashions",
            "type":"Retail Goods"
        }
    ],
    "sg:phone":"+1 615 771 3264",
    "sg:postcode":"37027",
    "sg:province":"TN",
    "wof:name":"Parisian Woman",
    "wof:placetype":"venue"
},
  "geometry": {"coordinates":[-86.815934,35.958985],"type":"Point"}
}