{
  "type": "Feature",
  "properties": {
    "iso:country":"US",
    "sg:address":"3333 Williams Enterprise Dr",
    "sg:city":"Cookeville",
    "sg:classifiers":[
        {
            "category":"Wholesale",
            "subcategory":"Beer",
            "type":"Manufacturing & Wholesale Goods"
        }
    ],
    "sg:phone":"+1 931 528 2200",
    "sg:postcode":"38506",
    "sg:province":"TN",
    "sg:tags":[
        "ale"
    ],
    "wof:name":"Williams Enterprises",
    "wof:placetype":"venue"
},
  "geometry": {"coordinates":[-85.502269,36.132322],"type":"Point"}
}