{
  "type": "Feature",
  "properties": {
    "iso:country":"US",
    "sg:address":"9101 Snowypointe Way",
    "sg:city":"Knoxville",
    "sg:classifiers":[
        {
            "category":"Shopping",
            "subcategory":"Computers & Home Electronics",
            "type":"Retail Goods"
        }
    ],
    "sg:phone":"+1 865 694 9893",
    "sg:postcode":"37931",
    "sg:province":"TN",
    "sg:tags":[
        "equipment",
        "electronic",
        "supply"
    ],
    "wof:name":"Marley Sales Group",
    "wof:placetype":"venue"
},
  "geometry": {"coordinates":[-84.072182,35.947097],"type":"Point"}
}