{
  "type": "Feature",
  "properties": {
    "iso:country":"US",
    "sg:address":"287 W Mitchell Rd",
    "sg:city":"Memphis",
    "sg:classifiers":[
        {
            "category":"Personal",
            "subcategory":"Beauty Salon",
            "type":"Services"
        }
    ],
    "sg:phone":"+1 901 785 1634",
    "sg:postcode":"38109",
    "sg:province":"TN",
    "sg:tags":[
        "shop"
    ],
    "wof:name":"L & L Connoisseur",
    "wof:placetype":"venue"
},
  "geometry": {"coordinates":[-90.07513,35.05561],"type":"Point"}
}