{
  "type": "Feature",
  "properties": {
    "iso:country":"US",
    "sg:address":"230 Island St",
    "sg:city":"Kingsport",
    "sg:classifiers":[
        {
            "category":"Health Services",
            "subcategory":"Medical Lab",
            "type":"Services"
        }
    ],
    "sg:phone":"+1 423 246 2220",
    "sg:postcode":"37660",
    "sg:province":"TN",
    "sg:tags":[
        "laboratory"
    ],
    "wof:name":"Kingsport Dental Lab Inc",
    "wof:placetype":"venue"
},
  "geometry": {"coordinates":[-82.55675599999999,36.544101],"type":"Point"}
}