{
  "type": "Feature",
  "properties": {
    "addr:full":"12281 Monterey Rd Collierville TN 38017",
    "addr:housenumber":"12281",
    "addr:postcode":"38017",
    "addr:street":"Monterey Rd",
    "iso:country":"US",
    "sg:address":"12281 Monterey Rd",
    "sg:city":"Collierville",
    "sg:classifiers":[
        {
            "category":"Professional",
            "subcategory":"Computer Services",
            "type":"Services"
        }
    ],
    "sg:phone":"+1 901 850 0415",
    "sg:postcode":"38017",
    "sg:province":"TN",
    "sg:tags":[
        "consultant",
        "designer"
    ],
    "wof:name":"Millennium Enterprises",
    "wof:placetype":"venue"
},
  "geometry": {"coordinates":[-89.653567,35.127396],"type":"Point"}
}