{
  "type": "Feature",
  "properties": {
    "iso:country":"US",
    "sg:address":"1522 State Hwy 130 W",
    "sg:city":"Shelbyville",
    "sg:classifiers":[
        {
            "category":"Building & Trades",
            "subcategory":"Construction",
            "type":"Services"
        }
    ],
    "sg:phone":"+1 931 684 2792",
    "sg:postcode":"37160",
    "sg:province":"TN",
    "sg:tags":[
        "repair",
        "asphalt"
    ],
    "wof:name":"Total Asphalt Repair",
    "wof:placetype":"venue"
},
  "geometry": {"coordinates":[-86.533958,35.420155],"type":"Point"}
}