{
  "type": "Feature",
  "properties": {
    "iso:country":"US",
    "sg:address":"2778 Shelby St",
    "sg:city":"Memphis",
    "sg:classifiers":[
        {
            "category":"Building & Trades",
            "subcategory":"Plumbing",
            "type":"Services"
        }
    ],
    "sg:phone":"+1 901 386 5131",
    "sg:postcode":"38134",
    "sg:province":"TN",
    "sg:tags":[
        "plumbing",
        "contractor"
    ],
    "wof:name":"Hastings Plumbing Co",
    "wof:placetype":"venue"
},
  "geometry": {"coordinates":[-89.874315,35.201664],"type":"Point"}
}