{
  "type": "Feature",
  "properties": {
    "iso:country":"US",
    "sg:address":"514 Travelers Ct",
    "sg:city":"Lebanon",
    "sg:classifiers":[
        {
            "category":"Professional",
            "type":"Services"
        }
    ],
    "sg:phone":"+1 615 449 5885",
    "sg:postcode":"37087",
    "sg:province":"TN",
    "sg:tags":[
        "establishment"
    ],
    "wof:name":"Capnoxygen",
    "wof:placetype":"venue"
},
  "geometry": {"coordinates":[-86.37185700000001,36.220366],"type":"Point"}
}