{
  "type": "Feature",
  "properties": {
    "addr:full":"1920 Shady Brook St Columbia TN 38401",
    "addr:housenumber":"1920",
    "addr:postcode":"38401",
    "addr:street":"Shady Brook St",
    "iso:country":"US",
    "sg:address":"1920 Shady Brook St",
    "sg:city":"Columbia",
    "sg:classifiers":[
        {
            "category":"Restaurant",
            "type":"Food & Drink"
        }
    ],
    "sg:menulink":"http://www.allmenus.com/tn/columbia/140013-subway/menu/",
    "sg:phone":"+1 931 388 7956",
    "sg:postcode":"38401",
    "sg:province":"TN",
    "sg:tags":[
        "american",
        "sandwich"
    ],
    "wof:name":"Subway",
    "wof:placetype":"venue"
},
  "geometry": {"coordinates":[-87.05758400000001,35.599489],"type":"Point"}
}