{
  "type": "Feature",
  "properties": {
    "iso:country":"US",
    "sg:address":"3617 Park Ave",
    "sg:city":"Memphis",
    "sg:classifiers":[
        {
            "category":"Social Services",
            "subcategory":"Child Care",
            "type":"Services"
        }
    ],
    "sg:phone":"+1 901 324 7788",
    "sg:postcode":"38111",
    "sg:province":"TN",
    "wof:name":"Lil Angels In Training",
    "wof:placetype":"venue"
},
  "geometry": {"coordinates":[-89.942016,35.10771],"type":"Point"}
}