{
  "type": "Feature",
  "properties": {
    "iso:country":"US",
    "sg:address":"1064 N Washington Ave",
    "sg:city":"Cookeville",
    "sg:classifiers":[
        {
            "category":"Restaurant",
            "type":"Food & Drink"
        }
    ],
    "sg:menulink":"http://www.allmenus.com/tn/cookeville/139918-subway/menu/",
    "sg:phone":"+1 931 520 1483",
    "sg:postcode":"38501",
    "sg:province":"TN",
    "sg:tags":[
        "american",
        "sandwich"
    ],
    "wof:name":"Subway",
    "wof:placetype":"venue"
},
  "geometry": {"coordinates":[-85.497359,36.176453],"type":"Point"}
}