{
  "type": "Feature",
  "properties": {
    "iso:country":"US",
    "sg:address":"632 S Perkins Rd",
    "sg:city":"Memphis",
    "sg:classifiers":[
        {
            "category":"Manufacturing",
            "subcategory":"Printing",
            "type":"Manufacturing & Wholesale Goods"
        }
    ],
    "sg:phone":"+1 901 682 9348",
    "sg:postcode":"38117",
    "sg:province":"TN",
    "sg:tags":[
        "publishing"
    ],
    "wof:name":"University Additions LTD",
    "wof:placetype":"venue"
},
  "geometry": {"coordinates":[-89.907425,35.11422],"type":"Point"}
}