{
  "type": "Feature",
  "properties": {
    "iso:country":"US",
    "sg:address":"40 Lynchburg Hwy",
    "sg:city":"Lynchburg",
    "sg:classifiers":[
        {
            "category":"Health Services",
            "subcategory":"Doctor",
            "type":"Services"
        }
    ],
    "sg:phone":"+1 931 759 4197",
    "sg:postcode":"37352",
    "sg:province":"TN",
    "sg:tags":[
        "physician",
        "surgeon"
    ],
    "wof:name":"Lynchburg Medical Clinic",
    "wof:placetype":"venue"
},
  "geometry": {"coordinates":[-86.373209,35.283552],"type":"Point"}
}