{
  "type": "Feature",
  "properties": {
    "iso:country":"US",
    "sg:address":"11123 US Hwy 421",
    "sg:city":"Trade",
    "sg:classifiers":[
        {
            "category":"Shopping",
            "subcategory":"Used Merchandise",
            "type":"Retail Goods"
        }
    ],
    "sg:phone":"+1 423 727 1272",
    "sg:postcode":"37691",
    "sg:province":"TN",
    "sg:tags":[
        "antique"
    ],
    "wof:name":"Trade Junction",
    "wof:placetype":"venue"
},
  "geometry": {"coordinates":[-81.74095,36.340697],"type":"Point"}
}