{
  "type": "Feature",
  "properties": {
    "iso:country":"US",
    "sg:address":"110 S Cumberland St",
    "sg:city":"Lebanon",
    "sg:classifiers":[
        {
            "category":"Real Estate",
            "subcategory":"Real Estate Agent",
            "type":"Services"
        }
    ],
    "sg:phone":"+1 615 965 0017",
    "sg:postcode":"37087",
    "sg:province":"TN",
    "wof:name":"J C Power Group",
    "wof:placetype":"venue"
},
  "geometry": {"coordinates":[-86.291262,36.207403],"type":"Point"}
}