{
  "type": "Feature",
  "properties": {
    "addr:full":"402 Northgate Mall Chattanooga TN 37415",
    "addr:housenumber":"402",
    "addr:postcode":"37415",
    "addr:street":"Northgate Mall",
    "iso:country":"US",
    "sg:address":"402 Northgate Mall",
    "sg:city":"Chattanooga",
    "sg:classifiers":[
        {
            "category":"Shopping",
            "type":"Retail Goods"
        },
        {
            "category":"Shopping",
            "subcategory":"Gifts & Souvenirs",
            "type":"Retail Goods"
        }
    ],
    "sg:phone":"+1 423 877 8473",
    "sg:postcode":"37415",
    "sg:province":"TN",
    "sg:tags":[
        "candle"
    ],
    "sg:website":"www.wicksnsticks.com",
    "wof:name":"Wicks n Sticks",
    "wof:placetype":"venue"
},
  "geometry": {"coordinates":[-85.244502,35.137833],"type":"Point"}
}