{
  "type": "Feature",
  "properties": {
    "iso:country":"US",
    "sg:address":"1845 Candy Owens Rd",
    "sg:city":"Moscow",
    "sg:classifiers":[
        {
            "category":"Organizations",
            "subcategory":"Religious Organization",
            "type":"Services"
        }
    ],
    "sg:phone":"+1 901 877 3672",
    "sg:postcode":"38057",
    "sg:province":"TN",
    "sg:tags":[
        "church"
    ],
    "wof:name":"Williams Tmple Holiness Church",
    "wof:placetype":"venue"
},
  "geometry": {"coordinates":[-89.405704,34.993927],"type":"Point"}
}