{
  "type": "Feature",
  "properties": {
    "iso:country":"US",
    "sg:address":"276 Murrell Rd",
    "sg:city":"Dickson",
    "sg:classifiers":[
        {
            "category":"Banks & Credit Unions",
            "subcategory":"Bank",
            "type":"Services"
        }
    ],
    "sg:phone":"+1 615 446 2187",
    "sg:postcode":"37055",
    "sg:province":"TN",
    "sg:tags":[
        "national",
        "commercial"
    ],
    "wof:name":"Steve Overton",
    "wof:placetype":"venue"
},
  "geometry": {"coordinates":[-87.37478900000001,36.029868],"type":"Point"}
}