{
  "type": "Feature",
  "properties": {
    "iso:country":"US",
    "sg:address":"5515 Brainerd Rd",
    "sg:city":"Chattanooga",
    "sg:classifiers":[
        {
            "category":"Banks & Credit Unions",
            "subcategory":"Bank",
            "type":"Services"
        },
        {
            "category":"Banks & Credit Unions",
            "subcategory":"Financial Services",
            "type":"Services"
        }
    ],
    "sg:phone":"+1 423 894 1058",
    "sg:postcode":"37411",
    "sg:province":"TN",
    "sg:tags":[
        "saving",
        "loan",
        "commercial"
    ],
    "sg:website":"http://www.regionsbank.com",
    "wof:name":"Regions Bank",
    "wof:placetype":"venue"
},
  "geometry": {"coordinates":[-85.22020500000001,35.00994],"type":"Point"}
}