{
  "type": "Feature",
  "properties": {
    "iso:country":"US",
    "sg:address":"4455 Chambers Chapel Rd",
    "sg:city":"Lakeland",
    "sg:classifiers":[
        {
            "category":"Freight",
            "type":"Transportation"
        }
    ],
    "sg:phone":"+1 901 867 7041",
    "sg:postcode":"38002",
    "sg:province":"TN",
    "sg:tags":[
        "trucking"
    ],
    "wof:name":"Big D Trucking",
    "wof:placetype":"venue"
},
  "geometry": {"coordinates":[-89.70917799999999,35.253226],"type":"Point"}
}