{
  "type": "Feature",
  "properties": {
    "addr:full":"3283 S 3rd St Memphis TN 38109",
    "addr:housenumber":"3283",
    "addr:postcode":"38109",
    "addr:street":"S 3Rd St",
    "iso:country":"US",
    "sg:address":"3283 S 3rd St",
    "sg:city":"Memphis",
    "sg:classifiers":[
        {
            "category":"Travel",
            "subcategory":"Hotels & Motels",
            "type":"Entertainment"
        }
    ],
    "sg:phone":"+1 901 345 1123",
    "sg:postcode":"38109",
    "sg:province":"TN",
    "wof:name":"Villa Inn",
    "wof:placetype":"venue"
},
  "geometry": {"coordinates":[-90.05981300000001,35.057854],"type":"Point"}
}