{
  "type": "Feature",
  "properties": {
    "iso:country":"US",
    "sg:address":"1930 Avalon Dr",
    "sg:city":"Nashville",
    "sg:classifiers":[
        {
            "category":"Building & Trades",
            "subcategory":"Construction",
            "type":"Services"
        }
    ],
    "sg:phone":"+1 615 596 7208",
    "sg:postcode":"37216",
    "sg:province":"TN",
    "sg:tags":[
        "general",
        "contractor"
    ],
    "wof:name":"A-1 Building & Floor Mntnc",
    "wof:placetype":"venue"
},
  "geometry": {"coordinates":[-86.71082800000001,36.208545],"type":"Point"}
}