{
  "type": "Feature",
  "properties": {
    "iso:country":"US",
    "sg:address":"1021 W Oakland Ave",
    "sg:city":"Johnson City",
    "sg:classifiers":[
        {
            "category":"Wholesale",
            "subcategory":"Durable Goods & Equipment",
            "type":"Manufacturing & Wholesale Goods"
        }
    ],
    "sg:phone":"+1 423 722 0100",
    "sg:postcode":"37604",
    "sg:province":"TN",
    "sg:tags":[
        "representative",
        "manufacturer"
    ],
    "sg:website":"www.permasteelisa.com",
    "wof:name":"Permasteelisa Cladding Tech",
    "wof:placetype":"venue"
},
  "geometry": {"coordinates":[-82.402124,36.350557],"type":"Point"}
}