{
  "type": "Feature",
  "properties": {
    "addr:full":"4301 E Pkwy Gatlinburg TN 37738",
    "addr:housenumber":"4301",
    "addr:postcode":"37738",
    "addr:street":"E Pkwy",
    "iso:country":"US",
    "sg:address":"4301 E Pkwy",
    "sg:city":"Gatlinburg",
    "sg:classifiers":[
        {
            "category":"Travel",
            "subcategory":"Hotels & Motels",
            "type":"Entertainment"
        }
    ],
    "sg:phone":"+1 865 436 4944",
    "sg:postcode":"37738",
    "sg:province":"TN",
    "sg:tags":[
        "cottage",
        "operation",
        "cabin"
    ],
    "sg:website":"www.fontainecabins.com",
    "wof:name":"Fontaine Log Cabin Rentals",
    "wof:placetype":"venue"
},
  "geometry": {"coordinates":[-83.32643400000001,35.76163],"type":"Point"}
}