{
  "type": "Feature",
  "properties": {
    "iso:country":"US",
    "sg:address":"5503 Tennessee Ave",
    "sg:city":"Nashville",
    "sg:classifiers":[
        {
            "category":"Organizations",
            "subcategory":"Religious Organization",
            "type":"Services"
        }
    ],
    "sg:phone":"+1 615 269 9830",
    "sg:postcode":"37209",
    "sg:province":"TN",
    "sg:tags":[
        "church"
    ],
    "wof:name":"West Nashville Southern Mthdst",
    "wof:placetype":"venue"
},
  "geometry": {"coordinates":[-86.855549,36.160688],"type":"Point"}
}