{
  "type": "Feature",
  "properties": {
    "iso:country":"US",
    "sg:address":"507 S Bells St",
    "sg:city":"Alamo",
    "sg:classifiers":[
        {
            "category":"Recreation",
            "type":"Entertainment"
        }
    ],
    "sg:phone":"+1 731 696 7655",
    "sg:postcode":"38001",
    "sg:province":"TN",
    "sg:tags":[
        "skating",
        "rink"
    ],
    "wof:name":"Blue Monkey Skate Rink & Fun",
    "wof:placetype":"venue"
},
  "geometry": {"coordinates":[-89.11735899999999,35.777309],"type":"Point"}
}