{
  "type": "Feature",
  "properties": {
    "addr:full":"8336 Oak Ridge Hwy Knoxville TN 37931",
    "addr:housenumber":"8336",
    "addr:postcode":"37931",
    "addr:street":"Oak Ridge Hwy",
    "iso:country":"US",
    "sg:address":"8336 Oak Ridge Hwy",
    "sg:city":"Knoxville",
    "sg:classifiers":[
        {
            "category":"Food & Beverages",
            "subcategory":"Bakery",
            "type":"Retail Goods"
        }
    ],
    "sg:phone":"+1 865 670 6667",
    "sg:postcode":"37931",
    "sg:province":"TN",
    "sg:tags":[
        "baker"
    ],
    "wof:name":"Bobby's Cakes & Gourmet Foods",
    "wof:placetype":"venue"
},
  "geometry": {"coordinates":[-84.14924499999999,35.977648],"type":"Point"}
}