{
  "type": "Feature",
  "properties": {
    "addr:full":"1089 Houston Smith Rd Iron City TN 38463",
    "addr:housenumber":"1089",
    "addr:postcode":"38463",
    "addr:street":"Houston Smith Rd",
    "iso:country":"US",
    "sg:address":"1089 Houston Smith Rd",
    "sg:city":"Iron City",
    "sg:classifiers":[
        {
            "category":"Manufacturing",
            "subcategory":"Lumber",
            "type":"Manufacturing & Wholesale Goods"
        }
    ],
    "sg:phone":"+1 931 724 9647",
    "sg:postcode":"38463",
    "sg:province":"TN",
    "sg:tags":[
        "logging"
    ],
    "wof:name":"Larry Robbins Logging",
    "wof:placetype":"venue"
},
  "geometry": {"coordinates":[-87.70676,35.079757],"type":"Point"}
}