{
  "type": "Feature",
  "properties": {
    "iso:country":"US",
    "sg:address":"6731 Wilbanks Rd",
    "sg:city":"Knoxville",
    "sg:classifiers":[
        {
            "category":"Wholesale",
            "subcategory":"Machinery & Supplies",
            "type":"Manufacturing & Wholesale Goods"
        }
    ],
    "sg:phone":"+1 865 688 0530",
    "sg:postcode":"37912",
    "sg:province":"TN",
    "sg:tags":[
        "equipment",
        "casket",
        "establishment"
    ],
    "wof:name":"Aurora Casket Company",
    "wof:placetype":"venue"
},
  "geometry": {"coordinates":[-83.996793,36.022692],"type":"Point"}
}