{
  "type": "Feature",
  "properties": {
    "addr:full":"4495 Lebanon Pike Hermitage TN 37076",
    "addr:housenumber":"4495",
    "addr:postcode":"37076",
    "addr:street":"Lebanon Pike",
    "iso:country":"US",
    "sg:address":"4495 Lebanon Pike",
    "sg:city":"Hermitage",
    "sg:classifiers":[
        {
            "category":"Coffee & Tea",
            "type":"Food & Drink"
        }
    ],
    "sg:menulink":"http://www.allmenus.com/tn/nashville/115318-starbucks-coffee/menu/",
    "sg:phone":"+1 615 316 0561",
    "sg:postcode":"37076",
    "sg:province":"TN",
    "sg:tags":[
        "american"
    ],
    "wof:name":"Starbucks Coffee",
    "wof:placetype":"venue"
},
  "geometry": {"coordinates":[-86.598765,36.215127],"type":"Point"}
}