{
  "type": "Feature",
  "properties": {
    "iso:country":"US",
    "sg:address":"301 W Main St",
    "sg:city":"Woodbury",
    "sg:classifiers":[
        {
            "category":"Government",
            "subcategory":"Court House",
            "type":"Public Place"
        }
    ],
    "sg:phone":"+1 615 563 8591",
    "sg:postcode":"37190",
    "sg:province":"TN",
    "sg:tags":[
        "state",
        "counsel"
    ],
    "wof:name":"Public Defender",
    "wof:placetype":"venue"
},
  "geometry": {"coordinates":[-86.072497,35.827835],"type":"Point"}
}