{
  "type": "Feature",
  "properties": {
    "iso:country":"US",
    "sg:address":"1075 Graysville Rd",
    "sg:city":"Chattanooga",
    "sg:classifiers":[
        {
            "category":"Health Services",
            "subcategory":"Doctor",
            "type":"Services"
        }
    ],
    "sg:phone":"+1 423 892 2919",
    "sg:postcode":"37421",
    "sg:province":"TN",
    "sg:tags":[
        "dentist"
    ],
    "wof:name":"White DDS",
    "wof:placetype":"venue"
},
  "geometry": {"coordinates":[-85.149396,35.000524],"type":"Point"}
}