{
  "type": "Feature",
  "properties": {
    "iso:country":"US",
    "sg:address":"2234 Truitt St",
    "sg:city":"Memphis",
    "sg:classifiers":[
        {
            "category":"Personal",
            "type":"Services"
        }
    ],
    "sg:phone":"+1 901 774 1634",
    "sg:postcode":"38114",
    "sg:province":"TN",
    "sg:tags":[
        "assistant"
    ],
    "wof:name":"Edwin Watts Tour",
    "wof:placetype":"venue"
},
  "geometry": {"coordinates":[-89.98957900000001,35.085665],"type":"Point"}
}