{
  "type": "Feature",
  "properties": {
    "iso:country":"US",
    "sg:address":"2921 Cummings Hwy",
    "sg:city":"Chattanooga",
    "sg:classifiers":[
        {
            "category":"Home & Garden",
            "subcategory":"Garden Supply",
            "type":"Retail Goods"
        }
    ],
    "sg:phone":"+1 423 821 4245",
    "sg:postcode":"37419",
    "sg:province":"TN",
    "sg:tags":[
        "sporting",
        "center"
    ],
    "wof:name":"Sun & Shade Garden Center",
    "wof:placetype":"venue"
},
  "geometry": {"coordinates":[-85.365506,35.02044],"type":"Point"}
}