{
  "type": "Feature",
  "properties": {
    "iso:country":"US",
    "sg:address":"1175 Vickery Ln",
    "sg:city":"Cordova",
    "sg:classifiers":[
        {
            "category":"Professional",
            "subcategory":"Management & Consulting",
            "type":"Services"
        }
    ],
    "sg:phone":"+1 901 751 7968",
    "sg:postcode":"38016",
    "sg:province":"TN",
    "wof:name":"Bencom LLC",
    "wof:placetype":"venue"
},
  "geometry": {"coordinates":[-89.779659,35.155931],"type":"Point"}
}