{
  "type": "Feature",
  "properties": {
    "iso:country":"US",
    "sg:address":"501 W Main St",
    "sg:city":"Decherd",
    "sg:classifiers":[
        {
            "category":"Professional",
            "subcategory":"Management & Consulting",
            "type":"Services"
        }
    ],
    "sg:phone":"+1 931 962 4895",
    "sg:postcode":"37324",
    "sg:province":"TN",
    "sg:tags":[
        "business"
    ],
    "wof:name":"National Technology Solutions",
    "wof:placetype":"venue"
},
  "geometry": {"coordinates":[-86.081406,35.207437],"type":"Point"}
}