{
  "type": "Feature",
  "properties": {
    "addr:full":"2795 Fort Campbell Blvd Clarksville TN 37042",
    "addr:housenumber":"2795",
    "addr:postcode":"37042",
    "addr:street":"Fort Campbell Blvd",
    "iso:country":"US",
    "sg:address":"2795 Fort Campbell Blvd",
    "sg:city":"Clarksville",
    "sg:classifiers":[
        {
            "category":"Shopping",
            "subcategory":"Discount & Variety Stores",
            "type":"Retail Goods"
        }
    ],
    "sg:phone":"+1 931 431 0168",
    "sg:postcode":"37042",
    "sg:province":"TN",
    "sg:tags":[
        "surplus",
        "army"
    ],
    "wof:name":"Mr Militaria LLC",
    "wof:placetype":"venue"
},
  "geometry": {"coordinates":[-87.432196,36.622459],"type":"Point"}
}