{
  "type": "Feature",
  "properties": {
    "iso:country":"US",
    "sg:address":"1232 S Wellington St",
    "sg:city":"Memphis",
    "sg:classifiers":[
        {
            "category":"Building & Trades",
            "subcategory":"Landscaping Services",
            "type":"Services"
        }
    ],
    "sg:phone":"+1 901 946 1400",
    "sg:postcode":"38106",
    "sg:province":"TN",
    "sg:tags":[
        "lawn",
        "care"
    ],
    "wof:name":"Earthworm Landscaping",
    "wof:placetype":"venue"
},
  "geometry": {"coordinates":[-90.04700200000001,35.113571],"type":"Point"}
}