{
  "type": "Feature",
  "properties": {
    "iso:country":"US",
    "sg:address":"625 Frosty Morn Dr",
    "sg:city":"Clarksville",
    "sg:classifiers":[
        {
            "category":"Real Estate",
            "subcategory":"Developer",
            "type":"Services"
        }
    ],
    "sg:phone":"+1 931 647 8768",
    "sg:postcode":"37040",
    "sg:province":"TN",
    "sg:tags":[
        "land"
    ],
    "wof:name":"Progress Properties",
    "wof:placetype":"venue"
},
  "geometry": {"coordinates":[-87.343222,36.538458],"type":"Point"}
}