{
  "type": "Feature",
  "properties": {
    "iso:country":"US",
    "sg:address":"5073 Whitehall Ave",
    "sg:city":"Memphis",
    "sg:classifiers":[
        {
            "category":"Wholesale",
            "subcategory":"Hardware",
            "type":"Manufacturing & Wholesale Goods"
        }
    ],
    "sg:phone":"+1 901 763 2998",
    "sg:postcode":"38117",
    "sg:province":"TN",
    "sg:tags":[
        "hardware-wholesale",
        "manufacturer"
    ],
    "wof:name":"Brad Howard Ca",
    "wof:placetype":"venue"
},
  "geometry": {"coordinates":[-89.890871,35.145743],"type":"Point"}
}