{
  "type": "Feature",
  "properties": {
    "iso:country":"US",
    "sg:address":"402 W Broadway St",
    "sg:city":"Newport",
    "sg:classifiers":[
        {
            "category":"Bars & Pubs",
            "type":"Food & Drink"
        }
    ],
    "sg:phone":"+1 423 625 2009",
    "sg:postcode":"37821",
    "sg:province":"TN",
    "wof:name":"Sandra's Bar",
    "wof:placetype":"venue"
},
  "geometry": {"coordinates":[-83.203309,35.968911],"type":"Point"}
}