{
  "type": "Feature",
  "properties": {
    "addr:full":"466 Brookside Village Way Gatlinburg TN 37738",
    "addr:housenumber":"466",
    "addr:postcode":"37738",
    "addr:street":"Brookside Village Way",
    "iso:country":"US",
    "sg:address":"466 Brookside Village Way",
    "sg:city":"Gatlinburg",
    "sg:classifiers":[
        {
            "category":"Restaurant",
            "type":"Food & Drink"
        }
    ],
    "sg:menulink":"http://www.allmenus.com/tn/gatlinburg/84328-papa-johns-pizza/menu/",
    "sg:phone":"+1 865 430 7777",
    "sg:postcode":"37738",
    "sg:province":"TN",
    "sg:tags":[
        "american",
        "pizza"
    ],
    "wof:name":"Papa John's Pizza",
    "wof:placetype":"venue"
},
  "geometry": {"coordinates":[-83.50229,35.715861],"type":"Point"}
}