{
  "type": "Feature",
  "properties": {
    "iso:country":"US",
    "sg:address":"9390 Cookeville Boat Dock Rd",
    "sg:city":"Baxter",
    "sg:classifiers":[
        {
            "category":"Organizations",
            "subcategory":"Religious Organization",
            "type":"Services"
        }
    ],
    "sg:phone":"+1 931 858 4859",
    "sg:postcode":"38544",
    "sg:province":"TN",
    "sg:tags":[
        "church"
    ],
    "wof:name":"Nash Grove Baptist Church",
    "wof:placetype":"venue"
},
  "geometry": {"coordinates":[-85.65709,36.057395],"type":"Point"}
}