{
  "type": "Feature",
  "properties": {
    "iso:country":"US",
    "sg:address":"1802 Memorial Blvd",
    "sg:city":"Murfreesboro",
    "sg:classifiers":[
        {
            "category":"Shopping",
            "subcategory":"Gifts & Souvenirs",
            "type":"Retail Goods"
        }
    ],
    "sg:phone":"+1 615 895 9012",
    "sg:postcode":"37129",
    "sg:province":"TN",
    "sg:tags":[
        "shop"
    ],
    "wof:name":"T L Trophies & Collectibles",
    "wof:placetype":"venue"
},
  "geometry": {"coordinates":[-86.397404,35.851669],"type":"Point"}
}