{
  "type": "Feature",
  "properties": {
    "iso:country":"US",
    "sg:address":"770 Douglas Bend Rd",
    "sg:city":"Gallatin",
    "sg:classifiers":[
        {
            "category":"Building & Trades",
            "subcategory":"Construction",
            "type":"Services"
        }
    ],
    "sg:phone":"+1 615 452 6049",
    "sg:postcode":"37066",
    "sg:province":"TN",
    "sg:tags":[
        "residential"
    ],
    "wof:name":"Osborne Construction Co",
    "wof:placetype":"venue"
},
  "geometry": {"coordinates":[-86.507289,36.327315],"type":"Point"}
}