{
  "type": "Feature",
  "properties": {
    "addr:full":"2128 Clinch Ave Knoxville TN 37916",
    "addr:housenumber":"2128",
    "addr:postcode":"37916",
    "addr:street":"Clinch Ave",
    "iso:country":"US",
    "sg:address":"2128 Clinch Ave",
    "sg:city":"Knoxville",
    "sg:classifiers":[
        {
            "category":"Real Estate",
            "subcategory":"Architect",
            "type":"Services"
        }
    ],
    "sg:phone":"+1 865 637 4156",
    "sg:postcode":"37916",
    "sg:province":"TN",
    "sg:website":"www.kbjmarchitects.com",
    "wof:name":"Kaatz Binkley Jones & Morris",
    "wof:placetype":"venue"
},
  "geometry": {"coordinates":[-83.9396,35.955806],"type":"Point"}
}