{
  "type": "Feature",
  "properties": {
    "iso:country":"US",
    "sg:address":"434 Sycamore Shoals Dr",
    "sg:city":"Elizabethton",
    "sg:classifiers":[
        {
            "category":"Building & Trades",
            "subcategory":"Electrical",
            "type":"Services"
        }
    ],
    "sg:phone":"+1 423 543 1113",
    "sg:postcode":"37643",
    "sg:province":"TN",
    "sg:tags":[
        "electrical",
        "contractor"
    ],
    "wof:name":"Tele Communications Services",
    "wof:placetype":"venue"
},
  "geometry": {"coordinates":[-82.271079,36.357403],"type":"Point"}
}