{
  "type": "Feature",
  "properties": {
    "iso:country":"US",
    "sg:address":"972 E Brooks Rd",
    "sg:city":"Memphis",
    "sg:classifiers":[
        {
            "category":"Restaurant",
            "type":"Food & Drink"
        }
    ],
    "sg:phone":"+1 901 396 3030",
    "sg:postcode":"38116",
    "sg:province":"TN",
    "sg:tags":[
        "style",
        "family"
    ],
    "wof:name":"Southern Belle's Restaurant",
    "wof:placetype":"venue"
},
  "geometry": {"coordinates":[-90.03146099999999,35.061715],"type":"Point"}
}