{
  "type": "Feature",
  "properties": {
    "addr:full":"600 N James Campbell Blvd Columbia TN 38401",
    "addr:housenumber":"600",
    "addr:postcode":"38401",
    "addr:street":"N James Campbell Blvd",
    "iso:country":"US",
    "sg:address":"600 N James Campbell Blvd",
    "sg:city":"Columbia",
    "sg:classifiers":[
        {
            "category":"Restaurant",
            "type":"Food & Drink"
        }
    ],
    "sg:menulink":"http://www.allmenus.com/tn/columbia/73059-pizza-hut/menu/",
    "sg:phone":"+1 931 388 1700",
    "sg:postcode":"38401",
    "sg:province":"TN",
    "sg:tags":[
        "american",
        "pizza"
    ],
    "wof:name":"Pizza Hut",
    "wof:placetype":"venue"
},
  "geometry": {"coordinates":[-87.05490899999999,35.627353],"type":"Point"}
}