{
  "type": "Feature",
  "properties": {
    "iso:country":"US",
    "sg:address":"2219 Murfreesboro Pike",
    "sg:city":"Nashville",
    "sg:classifiers":[
        {
            "category":"Restaurant",
            "type":"Food & Drink"
        }
    ],
    "sg:phone":"+1 615 627 5900",
    "sg:postcode":"37217",
    "sg:province":"TN",
    "wof:name":"Emiliano's Pizzeria",
    "wof:placetype":"venue"
},
  "geometry": {"coordinates":[-86.648771,36.086934],"type":"Point"}
}