{
  "type": "Feature",
  "properties": {
    "addr:full":"2306 Lebanon Pike Nashville TN 37214",
    "addr:housenumber":"2306",
    "addr:postcode":"37214",
    "addr:street":"Lebanon Pike",
    "iso:country":"US",
    "sg:address":"2306 Lebanon Pike",
    "sg:city":"Nashville",
    "sg:classifiers":[
        {
            "category":"Shopping",
            "subcategory":"Computers & Home Electronics",
            "type":"Retail Goods"
        }
    ],
    "sg:phone":"+1 615 889 8588",
    "sg:postcode":"37214",
    "sg:province":"TN",
    "sg:tags":[
        "equipment",
        "electronic",
        "supply"
    ],
    "wof:name":"Radio Shack",
    "wof:placetype":"venue"
},
  "geometry": {"coordinates":[-86.683724,36.168979],"type":"Point"}
}