{
  "type": "Feature",
  "properties": {
    "iso:country":"US",
    "sg:address":"2419 Kline Ave",
    "sg:city":"Nashville",
    "sg:classifiers":[
        {
            "category":"Wholesale",
            "subcategory":"Hardware",
            "type":"Manufacturing & Wholesale Goods"
        }
    ],
    "sg:phone":"+1 615 331 8611",
    "sg:postcode":"37211",
    "sg:province":"TN",
    "sg:website":"www.jcshardware.com",
    "wof:name":"Julian C Scruggs & Co",
    "wof:placetype":"venue"
},
  "geometry": {"coordinates":[-86.751857,36.118607],"type":"Point"}
}