{
  "type": "Feature",
  "properties": {
    "iso:country":"US",
    "sg:address":"112 N White St",
    "sg:city":"Athens",
    "sg:classifiers":[
        {
            "category":"Restaurant",
            "type":"Food & Drink"
        }
    ],
    "sg:phone":"+1 423 745 9978",
    "sg:postcode":"37303",
    "sg:province":"TN",
    "wof:name":"Mexi-Wing",
    "wof:placetype":"venue"
},
  "geometry": {"coordinates":[-84.594095,35.443495],"type":"Point"}
}