{
  "type": "Feature",
  "properties": {
    "iso:country":"US",
    "sg:address":"1605 Prosser Rd",
    "sg:city":"Knoxville",
    "sg:classifiers":[
        {
            "category":"Food & Beverages",
            "subcategory":"Specialty",
            "type":"Retail Goods"
        }
    ],
    "sg:phone":"+1 865 523 7810",
    "sg:postcode":"37914",
    "sg:province":"TN",
    "sg:tags":[
        "water",
        "bulk",
        "company"
    ],
    "sg:website":"www.chattanoogacocacola.com",
    "wof:name":"Laurel Mountain Spring Water",
    "wof:placetype":"venue"
},
  "geometry": {"coordinates":[-83.88763,36.002967],"type":"Point"}
}