{
  "type": "Feature",
  "properties": {
    "iso:country":"US",
    "sg:address":"2312 Loves Creek Rd NE",
    "sg:city":"Knoxville",
    "sg:classifiers":[
        {
            "category":"Building & Trades",
            "subcategory":"Landscaping Services",
            "type":"Services"
        }
    ],
    "sg:phone":"+1 865 637 8287",
    "sg:postcode":"37924",
    "sg:province":"TN",
    "sg:tags":[
        "lawn",
        "maintenance",
        "grounds"
    ],
    "wof:name":"Duncan's Landscape Supply",
    "wof:placetype":"venue"
},
  "geometry": {"coordinates":[-83.864208,36.031127],"type":"Point"}
}