{
  "type": "Feature",
  "properties": {
    "addr:full":"2841 Rural Hill Cir Nashville TN 37217",
    "addr:housenumber":"2841",
    "addr:postcode":"37217",
    "addr:street":"Rural Hill Cir",
    "iso:country":"US",
    "sg:address":"2841 Rural Hill Cir",
    "sg:city":"Nashville",
    "sg:classifiers":[
        {
            "category":"Professional",
            "type":"Services"
        }
    ],
    "sg:phone":"+1 615 366 4911",
    "sg:postcode":"37217",
    "sg:province":"TN",
    "wof:name":"John J Sweeney",
    "wof:placetype":"venue"
},
  "geometry": {"coordinates":[-86.621939,36.082318],"type":"Point"}
}