{
  "type": "Feature",
  "properties": {
    "iso:country":"US",
    "sg:address":"141 Rue de Grande",
    "sg:city":"Brentwood",
    "sg:classifiers":[
        {
            "category":"Manufacturing",
            "subcategory":"Printing",
            "type":"Manufacturing & Wholesale Goods"
        }
    ],
    "sg:phone":"+1 615 370 3587",
    "sg:postcode":"37027",
    "sg:province":"TN",
    "sg:tags":[
        "publisher"
    ],
    "sg:website":"www.twymantowery.com",
    "wof:name":"Wessex House Publishing",
    "wof:placetype":"venue"
},
  "geometry": {"coordinates":[-86.791589,35.963682],"type":"Point"}
}