{
  "type": "Feature",
  "properties": {
    "iso:country":"US",
    "sg:address":"9413 Apison Pike",
    "sg:city":"Ooltewah",
    "sg:classifiers":[
        {
            "category":"Restaurant",
            "type":"Food & Drink"
        }
    ],
    "sg:phone":"+1 423 396 3670",
    "sg:postcode":"37363",
    "sg:province":"TN",
    "wof:name":"Daves Place",
    "wof:placetype":"venue"
},
  "geometry": {"coordinates":[-85.069745,35.060844],"type":"Point"}
}