{
  "type": "Feature",
  "properties": {
    "addr:full":"495 Gallaher Rd Kingston TN 37763",
    "addr:housenumber":"495",
    "addr:postcode":"37763",
    "addr:street":"Gallaher Rd",
    "iso:country":"US",
    "sg:address":"495 Gallaher Rd",
    "sg:city":"Kingston",
    "sg:classifiers":[
        {
            "category":"Travel",
            "subcategory":"Hotels & Motels",
            "type":"Entertainment"
        }
    ],
    "sg:phone":"+1 865 376 2069",
    "sg:postcode":"37763",
    "sg:province":"TN",
    "sg:tags":[
        "operation"
    ],
    "wof:name":"Days Inn",
    "wof:placetype":"venue"
},
  "geometry": {"coordinates":[-84.443804,35.871395],"type":"Point"}
}