{
  "type": "Feature",
  "properties": {
    "iso:country":"US",
    "sg:address":"1001 Airport Rd",
    "sg:city":"Chattanooga",
    "sg:classifiers":[
        {
            "category":"Building & Trades",
            "subcategory":"Equipment Rental",
            "type":"Services"
        }
    ],
    "sg:phone":"+1 423 899 5614",
    "sg:postcode":"37421",
    "sg:province":"TN",
    "wof:name":"Moccasin Flying Club",
    "wof:placetype":"venue"
},
  "geometry": {"coordinates":[-85.19467299999999,35.032051],"type":"Point"}
}