{
  "type": "Feature",
  "properties": {
    "iso:country":"US",
    "sg:address":"914 Piney Grove Church Rd # 10",
    "sg:city":"Knoxville",
    "sg:classifiers":[
        {
            "category":"Personal",
            "type":"Services"
        }
    ],
    "sg:phone":"+1 865 694 0119",
    "sg:postcode":"37909",
    "sg:province":"TN",
    "sg:tags":[
        "butlers'",
        "maids'"
    ],
    "wof:name":"Classy Maids",
    "wof:placetype":"venue"
},
  "geometry": {"coordinates":[-84.042061,35.941901],"type":"Point"}
}