{
  "type": "Feature",
  "properties": {
    "iso:country":"US",
    "sg:address":"570 International Blvd",
    "sg:city":"Clarksville",
    "sg:classifiers":[
        {
            "category":"Professional",
            "subcategory":"Engineering",
            "type":"Services"
        }
    ],
    "sg:phone":"+1 931 542 0406",
    "sg:postcode":"37040",
    "sg:province":"TN",
    "sg:tags":[
        "engineer"
    ],
    "wof:name":"Us Engineering",
    "wof:placetype":"venue"
},
  "geometry": {"coordinates":[-87.258697,36.594423],"type":"Point"}
}