{
  "type": "Feature",
  "properties": {
    "iso:country":"US",
    "sg:address":"1180 Mount Hope Rd",
    "sg:city":"Mohawk",
    "sg:classifiers":[
        {
            "category":"Building & Trades",
            "subcategory":"Construction",
            "type":"Services"
        }
    ],
    "sg:phone":"+1 423 235 6789",
    "sg:postcode":"37810",
    "sg:province":"TN",
    "sg:tags":[
        "carpentry",
        "contractor"
    ],
    "wof:name":"Southeast Boors",
    "wof:placetype":"venue"
},
  "geometry": {"coordinates":[-83.087605,36.19726],"type":"Point"}
}