{
  "type": "Feature",
  "properties": {
    "iso:country":"US",
    "sg:address":"360 Huckleberry Rd",
    "sg:city":"Bluff City",
    "sg:classifiers":[
        {
            "category":"Professional",
            "subcategory":"Art Services",
            "type":"Services"
        }
    ],
    "sg:phone":"+1 423 538 6991",
    "sg:postcode":"37618",
    "sg:province":"TN",
    "sg:tags":[
        "photography",
        "commercial"
    ],
    "wof:name":"David S Dickerson",
    "wof:placetype":"venue"
},
  "geometry": {"coordinates":[-82.27781299999999,36.473717],"type":"Point"}
}