{
  "type": "Feature",
  "properties": {
    "addr:full":"1 Pryor Dr Chattanooga TN 37421",
    "addr:housenumber":"1",
    "addr:postcode":"37421",
    "addr:street":"Pryor Dr",
    "iso:country":"US",
    "sg:address":"1 Pryor Dr",
    "sg:city":"Chattanooga",
    "sg:classifiers":[
        {
            "category":"Freight",
            "type":"Transportation"
        }
    ],
    "sg:phone":"+1 423 899 1712",
    "sg:postcode":"37421",
    "sg:province":"TN",
    "sg:tags":[
        "warehouse",
        "merchandise"
    ],
    "sg:website":"www.publicstorage.com",
    "wof:name":"Public Storage",
    "wof:placetype":"venue"
},
  "geometry": {"coordinates":[-85.196596,35.066839],"type":"Point"}
}