{
  "type": "Feature",
  "properties": {
    "addr:full":"10470 Hwy 51 S Atoka TN 38004",
    "addr:housenumber":"10470",
    "addr:postcode":"38004",
    "addr:street":"Hwy 51 S",
    "iso:country":"US",
    "sg:address":"10470 Hwy 51 S",
    "sg:city":"Atoka",
    "sg:classifiers":[
        {
            "category":"Health Services",
            "subcategory":"Clinic",
            "type":"Services"
        }
    ],
    "sg:phone":"+1 901 840 4663",
    "sg:postcode":"38004",
    "sg:province":"TN",
    "sg:tags":[
        "home"
    ],
    "wof:name":"Home Health Care Of West Tn",
    "wof:placetype":"venue"
},
  "geometry": {"coordinates":[-89.77616399999999,35.453574],"type":"Point"}
}