{
  "type": "Feature",
  "properties": {
    "iso:country":"US",
    "sg:address":"609 Jefferson Ave",
    "sg:city":"Memphis",
    "sg:classifiers":[
        {
            "category":"Wholesale",
            "subcategory":"Machinery & Supplies",
            "type":"Manufacturing & Wholesale Goods"
        },
        {
            "category":"Building & Trades",
            "subcategory":"Construction",
            "type":"Services"
        }
    ],
    "sg:phone":"+1 901 527 0291",
    "sg:postcode":"38105",
    "sg:province":"TN",
    "sg:tags":[
        "repair",
        "industrial",
        "elevator",
        "mfg"
    ],
    "wof:name":"Otis Elevator Company",
    "wof:placetype":"venue"
},
  "geometry": {"coordinates":[-90.03825399999999,35.143455],"type":"Point"}
}