{
  "type": "Feature",
  "properties": {
    "iso:country":"US",
    "sg:address":"6068 Stage Rd",
    "sg:city":"Memphis",
    "sg:classifiers":[
        {
            "category":"Building & Trades",
            "subcategory":"Construction",
            "type":"Services"
        }
    ],
    "sg:phone":"+1 901 382 2135",
    "sg:postcode":"38134",
    "sg:province":"TN",
    "sg:tags":[
        "residential"
    ],
    "wof:name":"Lynmor Homes LLC",
    "wof:placetype":"venue"
},
  "geometry": {"coordinates":[-89.861221,35.204831],"type":"Point"}
}