{
  "type": "Feature",
  "properties": {
    "iso:country":"US",
    "sg:address":"167 N Main St",
    "sg:city":"Memphis",
    "sg:classifiers":[
        {
            "category":"Government",
            "subcategory":"Office",
            "type":"Public Place"
        }
    ],
    "sg:phone":"+1 901 495 1550",
    "sg:postcode":"38103",
    "sg:province":"TN",
    "wof:name":"Us Pretrail Svc",
    "wof:placetype":"venue"
},
  "geometry": {"coordinates":[-90.051405,35.148766],"type":"Point"}
}