{
  "type": "Feature",
  "properties": {
    "addr:full":"5909 Shelby Oaks Dr Memphis TN 38134",
    "addr:housenumber":"5909",
    "addr:postcode":"38134",
    "addr:street":"Shelby Oaks Dr",
    "iso:country":"US",
    "sg:address":"5909 Shelby Oaks Dr",
    "sg:city":"Memphis",
    "sg:classifiers":[
        {
            "category":"Professional",
            "subcategory":"Engineering",
            "type":"Services"
        }
    ],
    "sg:phone":"+1 901 371 0150",
    "sg:postcode":"38134",
    "sg:province":"TN",
    "sg:tags":[
        "engineer"
    ],
    "wof:name":"S R Consulting Engineering",
    "wof:placetype":"venue"
},
  "geometry": {"coordinates":[-89.866238,35.166052],"type":"Point"}
}