{
  "type": "Feature",
  "properties": {
    "iso:country":"US",
    "sg:address":"265 John Hunter Hwy",
    "sg:city":"Elora",
    "sg:classifiers":[
        {
            "category":"Building & Trades",
            "subcategory":"Construction",
            "type":"Services"
        }
    ],
    "sg:phone":"+1 931 937 7788",
    "sg:postcode":"37328",
    "sg:province":"AL",
    "sg:tags":[
        "carpentry",
        "contractor"
    ],
    "wof:name":"Lewis Cabinets",
    "wof:placetype":"venue"
},
  "geometry": {"coordinates":[-86.357615,35.018414],"type":"Point"}
}