{
  "type": "Feature",
  "properties": {
    "iso:country":"US",
    "sg:address":"101 Front St",
    "sg:city":"Gleason",
    "sg:classifiers":[
        {
            "category":"Education",
            "subcategory":"School",
            "type":"Public Place"
        }
    ],
    "sg:phone":"+1 731 648 5351",
    "sg:postcode":"38221",
    "sg:province":"TN",
    "sg:website":"www.gs.weakleyschools.com",
    "wof:name":"Gleason High School",
    "wof:placetype":"venue"
},
  "geometry": {"coordinates":[-88.085183,36.235013],"type":"Point"}
}