{
  "type": "Feature",
  "properties": {
    "iso:country":"US",
    "sg:address":"502 W Cumberland St",
    "sg:city":"Kingston",
    "sg:classifiers":[
        {
            "category":"Building & Trades",
            "subcategory":"Cleaning & Sanitation",
            "type":"Services"
        }
    ],
    "sg:phone":"+1 865 376 4491",
    "sg:postcode":"37763",
    "sg:province":"TN",
    "sg:tags":[
        "janitor"
    ],
    "wof:name":"Southeast Service Corp",
    "wof:placetype":"venue"
},
  "geometry": {"coordinates":[-84.517161,35.873024],"type":"Point"}
}