{
  "type": "Feature",
  "properties": {
    "iso:country":"US",
    "sg:address":"4271 Sidco Dr",
    "sg:city":"Nashville",
    "sg:classifiers":[
        {
            "category":"Travel",
            "subcategory":"Hotels & Motels",
            "type":"Entertainment"
        }
    ],
    "sg:phone":"+1 615 832 0093",
    "sg:postcode":"37204",
    "sg:province":"TN",
    "sg:tags":[
        "operation"
    ],
    "wof:name":"Red Roof Inn",
    "wof:placetype":"venue"
},
  "geometry": {"coordinates":[-86.762032,36.090588],"type":"Point"}
}