{
  "type": "Feature",
  "properties": {
    "addr:full":"3007 Rena St Pigeon Forge TN 37863",
    "addr:postcode":"3007;37863",
    "addr:street":"Rena St",
    "iso:country":"US",
    "sg:address":"3007 Rena St",
    "sg:city":"Pigeon Forge",
    "sg:classifiers":[
        {
            "category":"Professional",
            "subcategory":"Advertising",
            "type":"Services"
        }
    ],
    "sg:phone":"+1 865 908 0650",
    "sg:postcode":"37863",
    "sg:province":"TN",
    "sg:tags":[
        "commercial",
        "agency",
        "design"
    ],
    "sg:website":"www.brainstormcafe.com",
    "wof:name":"Brainstorm Cafe",
    "wof:placetype":"venue"
},
  "geometry": {"coordinates":[-83.565915,35.793454],"type":"Point"}
}