{
  "type": "Feature",
  "properties": {
    "iso:country":"US",
    "sg:address":"6604 Centennial Blvd",
    "sg:city":"Nashville",
    "sg:classifiers":[
        {
            "category":"Government",
            "subcategory":"Office",
            "type":"Public Place"
        }
    ],
    "sg:phone":"+1 615 741 4560",
    "sg:postcode":"37209",
    "sg:province":"TN",
    "sg:tags":[
        "station",
        "driver",
        "exam"
    ],
    "wof:name":"Driver Exam Station",
    "wof:placetype":"venue"
},
  "geometry": {"coordinates":[-86.870986,36.171271],"type":"Point"}
}