{
  "type": "Feature",
  "properties": {
    "iso:country":"US",
    "sg:address":"2443 Tinnin Rd",
    "sg:city":"Goodlettsville",
    "sg:classifiers":[
        {
            "category":"Retail",
            "subcategory":"Funeral Services",
            "type":"Services"
        }
    ],
    "sg:phone":"+1 615 859 4022",
    "sg:postcode":"37072",
    "sg:province":"TN",
    "sg:tags":[
        "home"
    ],
    "wof:name":"Buena Vista Funeral Home Inc",
    "wof:placetype":"venue"
},
  "geometry": {"coordinates":[-86.74238200000001,36.394429],"type":"Point"}
}