{
  "type": "Feature",
  "properties": {
    "iso:country":"US",
    "sg:address":"4409 Colorado Ave",
    "sg:city":"Nashville",
    "sg:classifiers":[
        {
            "category":"Organizations",
            "subcategory":"Religious Organization",
            "type":"Services"
        }
    ],
    "sg:phone":"+1 615 297 5187",
    "sg:postcode":"37209",
    "sg:province":"TN",
    "wof:name":"First Southern Methdst Church",
    "wof:placetype":"venue"
},
  "geometry": {"coordinates":[-86.840338,36.142242],"type":"Point"}
}