{
  "type": "Feature",
  "properties": {
    "iso:country":"US",
    "sg:address":"3124 Wilson Ave",
    "sg:city":"Knoxville",
    "sg:classifiers":[
        {
            "category":"Social Services",
            "subcategory":"Child Care",
            "type":"Services"
        }
    ],
    "sg:phone":"+1 865 637 9623",
    "sg:postcode":"37914",
    "sg:province":"TN",
    "sg:tags":[
        "day"
    ],
    "wof:name":"Y M C A",
    "wof:placetype":"venue"
},
  "geometry": {"coordinates":[-83.880987,35.989883],"type":"Point"}
}