{
  "type": "Feature",
  "properties": {
    "addr:full":"45 Jim Garrett Rd Crossville TN 38571",
    "addr:housenumber":"45",
    "addr:postcode":"38571",
    "addr:street":"Jim Garrett Rd",
    "iso:country":"US",
    "sg:address":"45 Jim Garrett Rd",
    "sg:city":"Crossville",
    "sg:classifiers":[
        {
            "category":"Organizations",
            "subcategory":"Professional Association",
            "type":"Services"
        }
    ],
    "sg:phone":"+1 931 277 5845",
    "sg:postcode":"38571",
    "sg:province":"TN",
    "sg:tags":[
        "community"
    ],
    "wof:name":"Mayland Community Organization",
    "wof:placetype":"venue"
},
  "geometry": {"coordinates":[-85.197537,36.04889],"type":"Point"}
}