{
  "type": "Feature",
  "properties": {
    "addr:full":"1956 US Hwy 11 E Jonesborough TN 37659",
    "addr:housenumber":"1956",
    "addr:postcode":"37659",
    "addr:street":"Us Hwy 11 E Jonesborough",
    "iso:country":"US",
    "sg:address":"1956 US Hwy 11 E",
    "sg:city":"Jonesborough",
    "sg:classifiers":[
        {
            "category":"Home & Garden",
            "subcategory":"Garden Supply",
            "type":"Retail Goods"
        }
    ],
    "sg:phone":"+1 423 753 2401",
    "sg:postcode":"37659",
    "sg:province":"TN",
    "sg:tags":[
        "center"
    ],
    "wof:name":"Old Towne Garden Ctr",
    "wof:placetype":"venue"
},
  "geometry": {"coordinates":[-82.51185700000001,36.286278],"type":"Point"}
}