{
  "type": "Feature",
  "properties": {
    "addr:full":"1360 W Main St Atwood TN 38220",
    "addr:housenumber":"1360",
    "addr:postcode":"38220",
    "addr:street":"W Main St",
    "iso:country":"US",
    "sg:address":"1360 W Main St",
    "sg:city":"Atwood",
    "sg:classifiers":[
        {
            "category":"Organizations",
            "subcategory":"Religious Organization",
            "type":"Services"
        }
    ],
    "sg:phone":"+1 731 662 7370",
    "sg:postcode":"38220",
    "sg:province":"TN",
    "sg:tags":[
        "church"
    ],
    "wof:name":"First Baptist Church",
    "wof:placetype":"venue"
},
  "geometry": {"coordinates":[-88.67858200000001,35.973026],"type":"Point"}
}