{
  "type": "Feature",
  "properties": {
    "iso:country":"US",
    "sg:address":"3354 Perimeter Hill Dr",
    "sg:city":"Nashville",
    "sg:classifiers":[
        {
            "category":"Real Estate",
            "subcategory":"Real Estate Agent",
            "type":"Services"
        }
    ],
    "sg:phone":"+1 615 300 0501",
    "sg:postcode":"37211",
    "sg:province":"TN",
    "wof:name":"Remax First Advange",
    "wof:placetype":"venue"
},
  "geometry": {"coordinates":[-86.69402700000001,36.084746],"type":"Point"}
}