{
  "type": "Feature",
  "properties": {
    "iso:country":"US",
    "sg:address":"1746 W Andrew Johnson Hwy",
    "sg:city":"Morristown",
    "sg:classifiers":[
        {
            "category":"Personal",
            "subcategory":"Beauty Salon",
            "type":"Services"
        }
    ],
    "sg:phone":"+1 423 587 0297",
    "sg:postcode":"37814",
    "sg:province":"TN",
    "sg:tags":[
        "shop"
    ],
    "wof:name":"Salon I Nail Care & Reflexolog",
    "wof:placetype":"venue"
},
  "geometry": {"coordinates":[-83.314722,36.207323],"type":"Point"}
}