{
  "type": "Feature",
  "properties": {
    "iso:country":"US",
    "sg:address":"438 Forrest Park Cir",
    "sg:city":"Franklin",
    "sg:classifiers":[
        {
            "category":"Organizations",
            "subcategory":"Religious Organization",
            "type":"Services"
        }
    ],
    "sg:phone":"+1 615 791 9803",
    "sg:postcode":"37064",
    "sg:province":"TN",
    "wof:name":"Solid Rock Ministries",
    "wof:placetype":"venue"
},
  "geometry": {"coordinates":[-86.83433100000001,35.896882],"type":"Point"}
}