{
  "type": "Feature",
  "properties": {
    "iso:country":"US",
    "sg:address":"1786 Newport Hwy",
    "sg:city":"Sevierville",
    "sg:classifiers":[
        {
            "category":"Home & Garden",
            "subcategory":"Furniture",
            "type":"Retail Goods"
        }
    ],
    "sg:phone":"+1 865 908 2400",
    "sg:postcode":"37876",
    "sg:province":"TN",
    "wof:name":"Sit & Sleep",
    "wof:placetype":"venue"
},
  "geometry": {"coordinates":[-83.498681,35.870098],"type":"Point"}
}