{
  "type": "Feature",
  "properties": {
    "iso:country":"US",
    "sg:address":"625 Rockwood Dr",
    "sg:city":"Hermitage",
    "sg:classifiers":[
        {
            "category":"Building & Trades",
            "subcategory":"Cleaning & Sanitation",
            "type":"Services"
        }
    ],
    "sg:phone":"+1 615 889 6153",
    "sg:postcode":"37076",
    "sg:province":"TN",
    "sg:tags":[
        "maintenance"
    ],
    "wof:name":"Eclean",
    "wof:placetype":"venue"
},
  "geometry": {"coordinates":[-86.60172,36.179229],"type":"Point"}
}