{
  "type": "Feature",
  "properties": {
    "iso:country":"US",
    "sg:address":"2600 Thousand Oaks Blvd",
    "sg:city":"Memphis",
    "sg:classifiers":[
        {
            "category":"Insurance",
            "subcategory":"Insurance Agent",
            "type":"Services"
        }
    ],
    "sg:phone":"+1 901 365 9818",
    "sg:postcode":"38118",
    "sg:province":"TN",
    "wof:name":"Barry C Young CLU",
    "wof:placetype":"venue"
},
  "geometry": {"coordinates":[-89.90193499999999,35.076747],"type":"Point"}
}