{
  "type": "Feature",
  "properties": {
    "iso:country":"US",
    "sg:address":"2599 Old Hwy 431",
    "sg:city":"Springfield",
    "sg:classifiers":[
        {
            "category":"Organizations",
            "subcategory":"Religious Organization",
            "type":"Services"
        }
    ],
    "sg:phone":"+1 615 384 8547",
    "sg:postcode":"37073",
    "sg:province":"TN",
    "sg:tags":[
        "church"
    ],
    "wof:name":"Banks Chapel United Methodist",
    "wof:placetype":"venue"
},
  "geometry": {"coordinates":[-86.89457400000001,36.444983],"type":"Point"}
}