{
  "type": "Feature",
  "properties": {
    "addr:full":"301 W Main St Alamo TN 38001",
    "addr:housenumber":"301",
    "addr:postcode":"38001",
    "addr:street":"W Main St",
    "iso:country":"US",
    "sg:address":"301 W Main St",
    "sg:city":"Alamo",
    "sg:classifiers":[
        {
            "category":"Real Estate",
            "subcategory":"Real Estate Operator",
            "type":"Services"
        }
    ],
    "sg:phone":"+1 731 696 4212",
    "sg:postcode":"38001",
    "sg:province":"TN",
    "sg:tags":[
        "building",
        "apartment"
    ],
    "wof:name":"Harber & Laman Apartments",
    "wof:placetype":"venue"
},
  "geometry": {"coordinates":[-89.13046300000001,35.785315],"type":"Point"}
}