{
  "type": "Feature",
  "properties": {
    "iso:country":"US",
    "sg:address":"295 Lebon Rd",
    "sg:city":"Nashville",
    "sg:classifiers":[
        {
            "category":"Building & Trades",
            "subcategory":"Construction",
            "type":"Services"
        }
    ],
    "sg:phone":"+1 615 781 8989",
    "sg:postcode":"37211",
    "sg:province":"TN",
    "sg:tags":[
        "hanging",
        "painter",
        "contractor"
    ],
    "wof:name":"Diversified Painting Cntrctrs",
    "wof:placetype":"venue"
},
  "geometry": {"coordinates":[-86.706146,36.080238],"type":"Point"}
}