{
  "type": "Feature",
  "properties": {
    "iso:country":"US",
    "sg:address":"4761 Knight Arnold Rd",
    "sg:city":"Memphis",
    "sg:classifiers":[
        {
            "category":"Retail",
            "subcategory":"Repair Shop",
            "type":"Services"
        }
    ],
    "sg:phone":"+1 901 363 6396",
    "sg:postcode":"38118",
    "sg:province":"TN",
    "sg:tags":[
        "lock",
        "locksmith"
    ],
    "wof:name":"Peifer Safe & Lock Co",
    "wof:placetype":"venue"
},
  "geometry": {"coordinates":[-89.903555,35.062332],"type":"Point"}
}