{
  "type": "Feature",
  "properties": {
    "iso:country":"US",
    "sg:address":"11600 Lanesborough Way",
    "sg:city":"Knoxville",
    "sg:classifiers":[
        {
            "category":"Professional",
            "subcategory":"Management & Consulting",
            "type":"Services"
        }
    ],
    "sg:phone":"+1 865 539 0146",
    "sg:postcode":"37934",
    "sg:province":"TN",
    "sg:tags":[
        "business"
    ],
    "wof:name":"Ambercom",
    "wof:placetype":"venue"
},
  "geometry": {"coordinates":[-84.18394499999999,35.893149],"type":"Point"}
}