{
  "type": "Feature",
  "properties": {
    "iso:country":"US",
    "sg:address":"710 S Perkins Rd",
    "sg:city":"Memphis",
    "sg:classifiers":[
        {
            "category":"Personal",
            "subcategory":"Beauty Salon",
            "type":"Services"
        }
    ],
    "sg:phone":"+1 901 683 5250",
    "sg:postcode":"38117",
    "sg:province":"TN",
    "wof:name":"Pleasure Island Salon & Day",
    "wof:placetype":"venue"
},
  "geometry": {"coordinates":[-89.90752999999999,35.111829],"type":"Point"}
}