{
  "type": "Feature",
  "properties": {
    "iso:country":"US",
    "sg:address":"745 Parkway",
    "sg:city":"Gatlinburg",
    "sg:classifiers":[
        {
            "category":"Shopping",
            "subcategory":"Gifts & Souvenirs",
            "type":"Retail Goods"
        }
    ],
    "sg:phone":"+1 865 430 2296",
    "sg:postcode":"37738",
    "sg:province":"TN",
    "sg:tags":[
        "shop"
    ],
    "wof:name":"Beaches R Us Body Jewelry",
    "wof:placetype":"venue"
},
  "geometry": {"coordinates":[-83.51694000000001,35.712076],"type":"Point"}
}