{
  "type": "Feature",
  "properties": {
    "iso:country":"US",
    "sg:address":"411 Veritas St",
    "sg:city":"Nashville",
    "sg:classifiers":[
        {
            "category":"Organizations",
            "subcategory":"Religious Organization",
            "type":"Services"
        }
    ],
    "sg:phone":"+1 615 832 0369",
    "sg:postcode":"37211",
    "sg:province":"TN",
    "sg:tags":[
        "church"
    ],
    "wof:name":"Radnor Church Of The Nazarene",
    "wof:placetype":"venue"
},
  "geometry": {"coordinates":[-86.738647,36.097621],"type":"Point"}
}