{
  "type": "Feature",
  "properties": {
    "iso:country":"US",
    "sg:address":"683 Conner Whitefield Rd",
    "sg:city":"Ripley",
    "sg:phone":"+1 731 635 4481",
    "sg:postcode":"38063",
    "sg:province":"TN",
    "sg:tags":[
        "farm",
        "soybean"
    ],
    "wof:name":"Mae M Lula",
    "wof:placetype":"venue"
},
  "geometry": {"coordinates":[-89.464538,35.722114],"type":"Point"}
}