{
  "type": "Feature",
  "properties": {
    "iso:country":"US",
    "sg:address":"1870 Union Ave",
    "sg:city":"Memphis",
    "sg:classifiers":[
        {
            "category":"Shopping",
            "subcategory":"Music",
            "type":"Retail Goods"
        }
    ],
    "sg:phone":"+1 901 726 0001",
    "sg:postcode":"38104",
    "sg:province":"TN",
    "sg:tags":[
        "video",
        "disc",
        "tape",
        "cassette"
    ],
    "wof:name":"Trophyman",
    "wof:placetype":"venue"
},
  "geometry": {"coordinates":[-89.999436,35.135191],"type":"Point"}
}