{
  "type": "Feature",
  "properties": {
    "addr:full":"3701 Amnicola Hwy Chattanooga TN 37406",
    "addr:housenumber":"3701",
    "addr:postcode":"37406",
    "addr:street":"Amnicola Hwy",
    "iso:country":"US",
    "sg:address":"3701 Amnicola Hwy",
    "sg:city":"Chattanooga",
    "sg:classifiers":[
        {
            "category":"Wholesale",
            "subcategory":"Farm Supplies",
            "type":"Manufacturing & Wholesale Goods"
        },
        {
            "category":"Wholesale",
            "subcategory":"Durable Goods & Equipment",
            "type":"Manufacturing & Wholesale Goods"
        }
    ],
    "sg:phone":"+1 423 697 8000",
    "sg:postcode":"37406",
    "sg:province":"TN",
    "sg:tags":[
        "supp",
        "importer",
        "crop"
    ],
    "sg:website":"www.nklawnandgarden.com",
    "wof:name":"N K Lawn & Garden Co",
    "wof:placetype":"venue"
},
  "geometry": {"coordinates":[-85.25904199999999,35.090402],"type":"Point"}
}