{
  "type": "Feature",
  "properties": {
    "addr:full":"2120 Merchants Row Ste 1 Germantown TN 38138",
    "addr:housenumber":"2120",
    "addr:postcode":"38138",
    "addr:street":"Merchants Row Ste 1",
    "iso:country":"US",
    "sg:address":"2120 Merchants Row Ste 1",
    "sg:city":"Germantown",
    "sg:classifiers":[
        {
            "category":"Professional",
            "type":"Services"
        }
    ],
    "sg:phone":"+1 901 752 1996",
    "sg:postcode":"38138",
    "sg:province":"TN",
    "sg:tags":[
        "caterer"
    ],
    "wof:name":"Tootsie's Catering",
    "wof:placetype":"venue"
},
  "geometry": {"coordinates":[-89.81260899999999,35.090912],"type":"Point"}
}