{
  "type": "Feature",
  "properties": {
    "addr:full":"540 Cinnamon Cir Crossville TN 38571",
    "addr:housenumber":"540",
    "addr:postcode":"38571",
    "addr:street":"Cinnamon Cir",
    "iso:country":"US",
    "sg:address":"540 Cinnamon Cir",
    "sg:city":"Crossville",
    "sg:classifiers":[
        {
            "category":"Building & Trades",
            "subcategory":"Construction",
            "type":"Services"
        }
    ],
    "sg:phone":"+1 931 979 2164",
    "sg:postcode":"38571",
    "sg:province":"TN",
    "sg:tags":[
        "residential",
        "house"
    ],
    "wof:name":"DLA Construction",
    "wof:placetype":"venue"
},
  "geometry": {"coordinates":[-85.059314,36.148632],"type":"Point"}
}