{
  "type": "Feature",
  "properties": {
    "addr:full":"108 Hawkins Rd Livingston TN 38570",
    "addr:housenumber":"108",
    "addr:postcode":"38570",
    "addr:street":"Hawkins Rd",
    "iso:country":"US",
    "sg:address":"108 Hawkins Rd",
    "sg:city":"Livingston",
    "sg:classifiers":[
        {
            "category":"Building & Trades",
            "subcategory":"Landscaping Services",
            "type":"Services"
        }
    ],
    "sg:phone":"+1 931 823 2483",
    "sg:postcode":"38570",
    "sg:province":"TN",
    "sg:tags":[
        "tree"
    ],
    "wof:name":"Ringley's Tree Service",
    "wof:placetype":"venue"
},
  "geometry": {"coordinates":[-85.34036999999999,36.375526],"type":"Point"}
}