{
  "type": "Feature",
  "properties": {
    "addr:full":"879 Hartman Ct Adams TN 37010",
    "addr:housenumber":"879",
    "addr:postcode":"37010",
    "addr:street":"Hartman Ct",
    "iso:country":"US",
    "sg:address":"879 Hartman Ct",
    "sg:city":"Adams",
    "sg:classifiers":[
        {
            "category":"Building & Trades",
            "subcategory":"Plumbing",
            "type":"Services"
        }
    ],
    "sg:phone":"+1 931 358 5512",
    "sg:postcode":"37010",
    "sg:province":"TN",
    "sg:tags":[
        "plumbing",
        "contractor"
    ],
    "wof:name":"Ray Wilbur Plumbing",
    "wof:placetype":"venue"
},
  "geometry": {"coordinates":[-87.202505,36.537708],"type":"Point"}
}