{
  "type": "Feature",
  "properties": {
    "addr:full":"253 Vickers Rd Mc Minnville TN 37110",
    "addr:housenumber":"253",
    "addr:postcode":"37110",
    "addr:street":"Vickers Rd",
    "iso:country":"US",
    "sg:address":"253 Vickers Rd",
    "sg:city":"Mc Minnville",
    "sg:phone":"+1 931 939 2432",
    "sg:postcode":"37110",
    "sg:province":"TN",
    "sg:tags":[
        "farm",
        "field",
        "corn",
        "crop"
    ],
    "wof:name":"Vickers John",
    "wof:placetype":"venue"
},
  "geometry": {"coordinates":[-85.96134499999999,35.761308],"type":"Point"}
}