{
  "type": "Feature",
  "properties": {
    "iso:country":"US",
    "sg:address":"3904 Gallatin Pike",
    "sg:city":"Nashville",
    "sg:classifiers":[
        {
            "category":"Banks & Credit Unions",
            "subcategory":"Bank",
            "type":"Services"
        }
    ],
    "sg:phone":"+1 615 748 2772",
    "sg:postcode":"37216",
    "sg:province":"TN",
    "wof:name":"AM South Bank",
    "wof:placetype":"venue"
},
  "geometry": {"coordinates":[-86.728374,36.217695],"type":"Point"}
}