{
  "type": "Feature",
  "properties": {
    "iso:country":"US",
    "sg:address":"1016 Gallatin Pike S",
    "sg:city":"Madison",
    "sg:classifiers":[
        {
            "category":"Restaurant",
            "type":"Food & Drink"
        }
    ],
    "sg:phone":"+1 615 868 2077",
    "sg:postcode":"37115",
    "sg:province":"TN",
    "wof:name":"Esfernandos Mexican Restaurant",
    "wof:placetype":"venue"
},
  "geometry": {"coordinates":[-86.71838700000001,36.250801],"type":"Point"}
}