{
  "type": "Feature",
  "properties": {
    "iso:country":"US",
    "sg:address":"1703 Sam Burlison Rd",
    "sg:city":"Burlison",
    "sg:classifiers":[
        {
            "category":"Building & Trades",
            "subcategory":"Construction",
            "type":"Services"
        }
    ],
    "sg:phone":"+1 901 476 3192",
    "sg:postcode":"38015",
    "sg:province":"TN",
    "sg:tags":[
        "downspouts",
        "gutter"
    ],
    "wof:name":"A Veterans Gutters",
    "wof:placetype":"venue"
},
  "geometry": {"coordinates":[-89.78242899999999,35.579093],"type":"Point"}
}