{
  "type": "Feature",
  "properties": {
    "addr:full":"4709 Lascassas Pike Lascassas TN 37085",
    "addr:housenumber":"4709",
    "addr:postcode":"37085",
    "addr:street":"Lascassas Pike",
    "iso:country":"US",
    "sg:address":"4709 Lascassas Pike",
    "sg:city":"Lascassas",
    "sg:classifiers":[
        {
            "category":"Restaurant",
            "type":"Food & Drink"
        }
    ],
    "sg:phone":"+1 615 893 0280",
    "sg:postcode":"37085",
    "sg:province":"TN",
    "wof:name":"Backroads Barbeque",
    "wof:placetype":"venue"
},
  "geometry": {"coordinates":[-86.30486999999999,35.921776],"type":"Point"}
}