{
  "type": "Feature",
  "properties": {
    "iso:country":"US",
    "sg:address":"3280 Sutherland Ave",
    "sg:city":"Knoxville",
    "sg:classifiers":[
        {
            "category":"Professional",
            "subcategory":"Lawyer & Legal Services",
            "type":"Services"
        }
    ],
    "sg:phone":"+1 865 588 3701",
    "sg:postcode":"37919",
    "sg:province":"TN",
    "sg:tags":[
        "attorney"
    ],
    "wof:name":"Cecilia Petersen",
    "wof:placetype":"venue"
},
  "geometry": {"coordinates":[-83.972624,35.949881],"type":"Point"}
}