{
  "type": "Feature",
  "properties": {
    "iso:country":"US",
    "sg:address":"1518 New Hope Rd",
    "sg:city":"Joelton",
    "sg:classifiers":[
        {
            "category":"Building & Trades",
            "subcategory":"Construction",
            "type":"Services"
        }
    ],
    "sg:phone":"+1 615 642 5672",
    "sg:postcode":"37080",
    "sg:province":"TN",
    "sg:tags":[
        "carpentry",
        "contractor"
    ],
    "wof:name":"X2 Miller General Carpentry",
    "wof:placetype":"venue"
},
  "geometry": {"coordinates":[-86.92572199999999,36.368318],"type":"Point"}
}