{
  "type": "Feature",
  "properties": {
    "iso:country":"US",
    "sg:address":"320 Summertown Hwy",
    "sg:city":"Hohenwald",
    "sg:classifiers":[
        {
            "category":"Wholesale",
            "subcategory":"Dairy",
            "type":"Manufacturing & Wholesale Goods"
        }
    ],
    "sg:phone":"+1 931 796 4844",
    "sg:postcode":"38462",
    "sg:province":"TN",
    "sg:tags":[
        "product"
    ],
    "wof:name":"Purity Dairies Inc",
    "wof:placetype":"venue"
},
  "geometry": {"coordinates":[-87.547327,35.538245],"type":"Point"}
}