{
  "type": "Feature",
  "properties": {
    "iso:country":"US",
    "sg:address":"6829 Benwood Dr",
    "sg:city":"Ooltewah",
    "sg:classifiers":[
        {
            "category":"Insurance",
            "subcategory":"Insurance Agent",
            "type":"Services"
        }
    ],
    "sg:phone":"+1 423 344 3997",
    "sg:postcode":"37363",
    "sg:province":"TN",
    "wof:name":"Aid Assoc For Lutherans",
    "wof:placetype":"venue"
},
  "geometry": {"coordinates":[-85.100803,35.117484],"type":"Point"}
}