{
  "type": "Feature",
  "properties": {
    "iso:country":"US",
    "sg:address":"2805 Foster Ave",
    "sg:city":"Nashville",
    "sg:classifiers":[
        {
            "category":"Insurance",
            "subcategory":"Insurance Agent",
            "type":"Services"
        }
    ],
    "sg:phone":"+1 615 315 9955",
    "sg:postcode":"37210",
    "sg:province":"TN",
    "wof:name":"Booker Insurance",
    "wof:placetype":"venue"
},
  "geometry": {"coordinates":[-86.743416,36.114139],"type":"Point"}
}