{
  "type": "Feature",
  "properties": {
    "iso:country":"US",
    "sg:address":"109 Eveningside Dr",
    "sg:city":"Chattanooga",
    "sg:classifiers":[
        {
            "category":"Professional",
            "subcategory":"Management & Consulting",
            "type":"Services"
        }
    ],
    "sg:phone":"+1 423 698 0597",
    "sg:postcode":"37404",
    "sg:province":"TN",
    "sg:tags":[
        "consultant"
    ],
    "wof:name":"Depriest & Associates, Inc",
    "wof:placetype":"venue"
},
  "geometry": {"coordinates":[-85.283655,35.027171],"type":"Point"}
}