{
  "type": "Feature",
  "properties": {
    "iso:country":"US",
    "sg:address":"108 Post Hill Ct",
    "sg:city":"Mc Minnville",
    "sg:classifiers":[
        {
            "category":"Health Services",
            "subcategory":"Doctor",
            "type":"Services"
        }
    ],
    "sg:phone":"+1 931 473 9927",
    "sg:postcode":"37110",
    "sg:province":"TN",
    "sg:tags":[
        "physician",
        "surgeon"
    ],
    "wof:name":"Andrew J Dean OD Residence",
    "wof:placetype":"venue"
},
  "geometry": {"coordinates":[-85.79270200000001,35.690368],"type":"Point"}
}