{
  "type": "Feature",
  "properties": {
    "iso:country":"US",
    "sg:address":"111 4th Ave S",
    "sg:city":"Nashville",
    "sg:classifiers":[
        {
            "category":"Manufacturing",
            "subcategory":"Printing",
            "type":"Manufacturing & Wholesale Goods"
        }
    ],
    "sg:phone":"+1 615 742 5312",
    "sg:postcode":"37210",
    "sg:province":"TN",
    "sg:tags":[
        "lithographic",
        "printer",
        "commercial"
    ],
    "wof:name":"Lewisburg Printing Co",
    "wof:placetype":"venue"
},
  "geometry": {"coordinates":[-86.77715000000001,36.160818],"type":"Point"}
}