{
  "type": "Feature",
  "properties": {
    "addr:full":"815 Ewing Ave Nashville TN 37203",
    "addr:housenumber":"815",
    "addr:postcode":"37203",
    "addr:street":"Ewing Ave",
    "iso:country":"US",
    "sg:address":"815 Ewing Ave",
    "sg:city":"Nashville",
    "sg:classifiers":[
        {
            "category":"Wholesale",
            "subcategory":"Electrical",
            "type":"Manufacturing & Wholesale Goods"
        }
    ],
    "sg:phone":"+1 615 254 7729",
    "sg:postcode":"37203",
    "sg:province":"TN",
    "sg:tags":[
        "water",
        "heater"
    ],
    "wof:name":"Nashville Supply House Inc",
    "wof:placetype":"venue"
},
  "geometry": {"coordinates":[-86.775711,36.150108],"type":"Point"}
}