{
  "type": "Feature",
  "properties": {
    "iso:country":"US",
    "sg:address":"713 Harahan Rd",
    "sg:city":"Memphis",
    "sg:classifiers":[
        {
            "category":"Place Of Worship",
            "type":"Public Place"
        },
        {
            "category":"Place Of Worship",
            "subcategory":"Temple",
            "type":"Public Place"
        }
    ],
    "sg:phone":"+1 901 789 4554",
    "sg:postcode":"38109",
    "sg:province":"TN",
    "sg:tags":[
        "church"
    ],
    "wof:name":"Gilgal Temple",
    "wof:placetype":"venue"
},
  "geometry": {"coordinates":[-90.087962,35.062763],"type":"Point"}
}