{
  "type": "Feature",
  "properties": {
    "iso:country":"US",
    "sg:address":"2075 Old Fort Pkwy",
    "sg:city":"Murfreesboro",
    "sg:classifiers":[
        {
            "category":"Shopping",
            "subcategory":"Hobbies, Toys, & Games",
            "type":"Retail Goods"
        }
    ],
    "sg:phone":"+1 615 896 6243",
    "sg:postcode":"37129",
    "sg:province":"TN",
    "wof:name":"Toys R Us",
    "wof:placetype":"venue"
},
  "geometry": {"coordinates":[-86.427001,35.846095],"type":"Point"}
}