{
  "type": "Feature",
  "properties": {
    "iso:country":"US",
    "sg:address":"174 Market Place Blvd",
    "sg:city":"Knoxville",
    "sg:classifiers":[
        {
            "category":"Banks & Credit Unions",
            "subcategory":"Investment Brokerage",
            "type":"Services"
        }
    ],
    "sg:phone":"+1 865 539 9170",
    "sg:postcode":"37922",
    "sg:province":"TN",
    "sg:tags":[
        "consultant",
        "planning",
        "financial"
    ],
    "wof:name":"Raymond James Financial Svc",
    "wof:placetype":"venue"
},
  "geometry": {"coordinates":[-84.091229,35.911869],"type":"Point"}
}