{
  "type": "Feature",
  "properties": {
    "iso:country":"US",
    "sg:address":"3086 Kefauver Dr",
    "sg:city":"Milan",
    "sg:classifiers":[
        {
            "category":"Wholesale",
            "subcategory":"Machinery & Supplies",
            "type":"Manufacturing & Wholesale Goods"
        }
    ],
    "sg:phone":"+1 731 723 7979",
    "sg:postcode":"38358",
    "sg:province":"TN",
    "sg:tags":[
        "pressure",
        "washing",
        "equipment"
    ],
    "wof:name":"Big Orange Supply",
    "wof:placetype":"venue"
},
  "geometry": {"coordinates":[-88.759652,35.905778],"type":"Point"}
}