{
  "type": "Feature",
  "properties": {
    "iso:country":"US",
    "sg:address":"3015 W Gallaher Ferry Rd",
    "sg:city":"Knoxville",
    "sg:classifiers":[
        {
            "category":"Retail",
            "subcategory":"Animal Services",
            "type":"Services"
        }
    ],
    "sg:phone":"+1 865 694 4455",
    "sg:postcode":"37932",
    "sg:province":"TN",
    "wof:name":"Woodhill Farms Inc",
    "wof:placetype":"venue"
},
  "geometry": {"coordinates":[-84.251441,35.927668],"type":"Point"}
}