{
  "type": "Feature",
  "properties": {
    "addr:full":"3601 Hillsboro Pike Nashville TN 37215",
    "addr:housenumber":"3601",
    "addr:postcode":"37215",
    "addr:street":"Hillsboro Pike",
    "iso:country":"US",
    "sg:address":"3601 Hillsboro Pike",
    "sg:city":"Nashville",
    "sg:classifiers":[
        {
            "category":"Social Services",
            "subcategory":"Child Care",
            "type":"Services"
        }
    ],
    "sg:phone":"+1 615 297 9962",
    "sg:postcode":"37215",
    "sg:province":"TN",
    "sg:tags":[
        "kindergarten",
        "academic",
        "school"
    ],
    "sg:website":"www.woodmontchristianpreschool.com",
    "wof:name":"Woodmont Christian Pre-School",
    "wof:placetype":"venue"
},
  "geometry": {"coordinates":[-86.811168,36.112607],"type":"Point"}
}