{
  "type": "Feature",
  "properties": {
    "iso:country":"US",
    "sg:address":"2838 Hickory Hill Rd",
    "sg:city":"Memphis",
    "sg:classifiers":[
        {
            "category":"Shopping",
            "subcategory":"Gifts & Souvenirs",
            "type":"Retail Goods"
        }
    ],
    "sg:phone":"+1 901 753 7570",
    "sg:postcode":"38115",
    "sg:province":"TN",
    "sg:tags":[
        "shop",
        "specialty"
    ],
    "wof:name":"Giftworks",
    "wof:placetype":"venue"
},
  "geometry": {"coordinates":[-89.86388599999999,35.071512],"type":"Point"}
}