{
  "type": "Feature",
  "properties": {
    "iso:country":"US",
    "sg:address":"1262 Williams Cove Rd",
    "sg:city":"Winchester",
    "sg:classifiers":[
        {
            "category":"Organizations",
            "subcategory":"Religious Organization",
            "type":"Services"
        }
    ],
    "sg:phone":"+1 931 967 0245",
    "sg:postcode":"37398",
    "sg:province":"TN",
    "sg:tags":[
        "church"
    ],
    "wof:name":"Goshen Cumberland Church",
    "wof:placetype":"venue"
},
  "geometry": {"coordinates":[-86.05936199999999,35.156621],"type":"Point"}
}