{
  "type": "Feature",
  "properties": {
    "addr:full":"657 Parkway Sevierville TN 37862",
    "addr:housenumber":"657",
    "addr:postcode":"37862",
    "addr:street":"Parkway",
    "iso:country":"US",
    "sg:address":"657 Parkway",
    "sg:city":"Sevierville",
    "sg:classifiers":[
        {
            "category":"Shopping",
            "subcategory":"Discount & Variety Stores",
            "type":"Retail Goods"
        }
    ],
    "sg:phone":"+1 865 908 0459",
    "sg:postcode":"37862",
    "sg:province":"TN",
    "wof:name":"Dollar Tree",
    "wof:placetype":"venue"
},
  "geometry": {"coordinates":[-83.56658400000001,35.85957],"type":"Point"}
}