{
  "type": "Feature",
  "properties": {
    "addr:full":"8008 Hamilton Mill Dr Chattanooga TN 37421",
    "addr:housenumber":"8008",
    "addr:postcode":"37421",
    "addr:street":"Hamilton Mill Dr",
    "iso:country":"US",
    "sg:address":"8008 Hamilton Mill Dr",
    "sg:city":"Chattanooga",
    "sg:classifiers":[
        {
            "category":"Professional",
            "subcategory":"Business Services",
            "type":"Services"
        }
    ],
    "sg:phone":"+1 423 490 8537",
    "sg:postcode":"37421",
    "sg:province":"TN",
    "wof:name":"Jopal Enterprises",
    "wof:placetype":"venue"
},
  "geometry": {"coordinates":[-85.131236,35.027169],"type":"Point"}
}