{
  "type": "Feature",
  "properties": {
    "iso:country":"US",
    "sg:address":"326 W Main St",
    "sg:city":"Sevierville",
    "sg:classifiers":[
        {
            "category":"Shopping",
            "subcategory":"Department Store",
            "type":"Retail Goods"
        }
    ],
    "sg:phone":"+1 865 428 5568",
    "sg:postcode":"37862",
    "sg:province":"TN",
    "wof:name":"Sears Roebuck & Co",
    "wof:placetype":"venue"
},
  "geometry": {"coordinates":[-83.573504,35.871057],"type":"Point"}
}