{
  "type": "Feature",
  "properties": {
    "iso:country":"US",
    "sg:address":"2606 Nolensville Pike",
    "sg:city":"Nashville",
    "sg:classifiers":[
        {
            "category":"Shopping",
            "subcategory":"Used Merchandise",
            "type":"Retail Goods"
        }
    ],
    "sg:phone":"+1 615 833 1355",
    "sg:postcode":"37211",
    "sg:province":"TN",
    "wof:name":"Nolensville Road Thrift Shop",
    "wof:placetype":"venue"
},
  "geometry": {"coordinates":[-86.748093,36.116762],"type":"Point"}
}