{
  "type": "Feature",
  "properties": {
    "iso:country":"US",
    "sg:address":"603 Hwy 259",
    "sg:city":"Portland",
    "sg:classifiers":[
        {
            "category":"Organizations",
            "subcategory":"Religious Organization",
            "type":"Services"
        }
    ],
    "sg:phone":"+1 615 325 5865",
    "sg:postcode":"37148",
    "sg:province":"TN",
    "sg:tags":[
        "church"
    ],
    "wof:name":"Mitchellville General Baptist",
    "wof:placetype":"venue"
},
  "geometry": {"coordinates":[-86.52550599999999,36.633281],"type":"Point"}
}