{
  "type": "Feature",
  "properties": {
    "iso:country":"US",
    "sg:address":"3805 Gallatin Pike",
    "sg:city":"Nashville",
    "sg:classifiers":[
        {
            "category":"Professional",
            "subcategory":"Lawyer & Legal Services",
            "type":"Services"
        }
    ],
    "sg:phone":"+1 615 254 6800",
    "sg:postcode":"37216",
    "sg:province":"TN",
    "sg:tags":[
        "attorney"
    ],
    "wof:name":"Cynthia Fitzgerald",
    "wof:placetype":"venue"
},
  "geometry": {"coordinates":[-86.730808,36.214179],"type":"Point"}
}