{
  "type": "Feature",
  "properties": {
    "iso:country":"US",
    "sg:address":"4388 Oakcrest Ln",
    "sg:city":"Hermitage",
    "sg:classifiers":[
        {
            "category":"Real Estate",
            "subcategory":"Real Estate Agent",
            "type":"Services"
        }
    ],
    "sg:phone":"+1 615 874 1345",
    "sg:postcode":"37076",
    "sg:province":"TN",
    "sg:tags":[
        "inspection"
    ],
    "wof:name":"World Inspection Network",
    "wof:placetype":"venue"
},
  "geometry": {"coordinates":[-86.59625200000001,36.191384],"type":"Point"}
}