{
  "type": "Feature",
  "properties": {
    "iso:country":"US",
    "sg:address":"831 Cherokee Ln",
    "sg:city":"Signal Mountain",
    "sg:classifiers":[
        {
            "category":"Professional",
            "subcategory":"Business Services",
            "type":"Services"
        }
    ],
    "sg:phone":"+1 423 886 9429",
    "sg:postcode":"37377",
    "sg:province":"TN",
    "wof:name":"Mountain Treasures",
    "wof:placetype":"venue"
},
  "geometry": {"coordinates":[-85.341382,35.120572],"type":"Point"}
}