{
  "type": "Feature",
  "properties": {
    "addr:full":"3557 Kearney Ave Memphis TN 38111",
    "addr:housenumber":"3557",
    "addr:postcode":"38111",
    "addr:street":"Kearney Ave",
    "iso:country":"US",
    "sg:address":"3557 Kearney Ave",
    "sg:city":"Memphis",
    "sg:classifiers":[
        {
            "category":"Building & Trades",
            "subcategory":"Construction",
            "type":"Services"
        }
    ],
    "sg:phone":"+1 901 679 5695",
    "sg:postcode":"38111",
    "sg:province":"TN",
    "sg:tags":[
        "painting",
        "contractor"
    ],
    "wof:name":"The Finishing Touch",
    "wof:placetype":"venue"
},
  "geometry": {"coordinates":[-89.943434,35.11242],"type":"Point"}
}