{
  "type": "Feature",
  "properties": {
    "iso:country":"US",
    "sg:address":"705 Cox Rd",
    "sg:city":"Cottage Grove",
    "sg:classifiers":[
        {
            "category":"Organizations",
            "subcategory":"Religious Organization",
            "type":"Services"
        }
    ],
    "sg:phone":"+1 731 782 3416",
    "sg:postcode":"38224",
    "sg:province":"TN",
    "sg:tags":[
        "church"
    ],
    "wof:name":"Bethel Fellowship",
    "wof:placetype":"venue"
},
  "geometry": {"coordinates":[-88.498965,36.360253],"type":"Point"}
}