{
  "type": "Feature",
  "properties": {
    "addr:full":"2549 Elvis Presley Blvd Memphis TN 38116",
    "addr:housenumber":"2549",
    "addr:postcode":"38116",
    "addr:street":"Elvis Presley Blvd",
    "iso:country":"US",
    "sg:address":"2549 Elvis Presley Blvd",
    "sg:city":"Memphis",
    "sg:classifiers":[
        {
            "category":"Wholesale",
            "subcategory":"Machinery & Supplies",
            "type":"Manufacturing & Wholesale Goods"
        },
        {
            "category":"Home & Garden",
            "subcategory":"Garden Supply",
            "type":"Retail Goods"
        }
    ],
    "sg:phone":"+1 901 947 1164",
    "sg:postcode":"38116",
    "sg:province":"TN",
    "sg:tags":[
        "engine",
        "lawn",
        "outdoor",
        "power",
        "mower",
        "equipment",
        "small"
    ],
    "sg:website":"www.midsouthsmallengines.com",
    "wof:name":"Mid-South Small Engines Inc",
    "wof:placetype":"venue"
},
  "geometry": {"coordinates":[-90.02024299999999,35.075478],"type":"Point"}
}