{
  "type": "Feature",
  "properties": {
    "iso:country":"US",
    "sg:address":"80 Depot Rd",
    "sg:city":"Cookeville",
    "sg:phone":"+1 931 528 9000",
    "sg:postcode":"38581",
    "sg:province":"TN",
    "sg:tags":[
        "gas"
    ],
    "wof:name":"Cumberland LP Gas",
    "wof:placetype":"venue"
},
  "geometry": {"coordinates":[-85.63456100000001,35.773467],"type":"Point"}
}