{
  "type": "Feature",
  "properties": {
    "iso:country":"US",
    "sg:address":"6079 US Hwy 51 N",
    "sg:city":"Millington",
    "sg:classifiers":[
        {
            "category":"Personal",
            "type":"Services"
        },
        {
            "category":"Personal",
            "subcategory":"Tattoo Parlor",
            "type":"Services"
        }
    ],
    "sg:phone":"+1 901 353 6250",
    "sg:postcode":"38053",
    "sg:province":"TN",
    "sg:tags":[
        "tattooing"
    ],
    "wof:name":"Mouse's Custom Tattoo",
    "wof:placetype":"venue"
},
  "geometry": {"coordinates":[-89.961759,35.293092],"type":"Point"}
}