{
  "type": "Feature",
  "properties": {
    "iso:country":"US",
    "sg:address":"7820 Horn Tavern Rd",
    "sg:city":"Fairview",
    "sg:classifiers":[
        {
            "category":"Wholesale",
            "subcategory":"Auto Parts",
            "type":"Manufacturing & Wholesale Goods"
        }
    ],
    "sg:phone":"+1 615 799 2583",
    "sg:postcode":"37062",
    "sg:province":"TN",
    "sg:tags":[
        "automobile",
        "rebuilt",
        "used"
    ],
    "wof:name":"Dan Brinkley Auto Salvage",
    "wof:placetype":"venue"
},
  "geometry": {"coordinates":[-87.130393,36.002059],"type":"Point"}
}