{
  "type": "Feature",
  "properties": {
    "iso:country":"US",
    "sg:address":"2485 Union Ave",
    "sg:city":"Memphis",
    "sg:classifiers":[
        {
            "category":"Education",
            "subcategory":"School",
            "type":"Public Place"
        }
    ],
    "sg:phone":"+1 901 325 4987",
    "sg:postcode":"38112",
    "sg:province":"TN",
    "wof:name":"Memphis City Schools",
    "wof:placetype":"venue"
},
  "geometry": {"coordinates":[-89.979321,35.133335],"type":"Point"}
}