{
  "type": "Feature",
  "properties": {
    "iso:country":"US",
    "sg:address":"1428 N Central St",
    "sg:city":"Knoxville",
    "sg:classifiers":[
        {
            "category":"Restaurant",
            "type":"Food & Drink"
        }
    ],
    "sg:phone":"+1 865 673 8145",
    "sg:postcode":"37917",
    "sg:province":"TN",
    "sg:tags":[
        "delicatessen"
    ],
    "wof:name":"Natours Time Out Deli",
    "wof:placetype":"venue"
},
  "geometry": {"coordinates":[-83.932067,35.983991],"type":"Point"}
}