{
  "type": "Feature",
  "properties": {
    "iso:country":"US",
    "sg:address":"4707 Papermill Dr",
    "sg:city":"Knoxville",
    "sg:classifiers":[
        {
            "category":"Health Services",
            "subcategory":"Clinic",
            "type":"Services"
        }
    ],
    "sg:phone":"+1 865 766 0197",
    "sg:postcode":"37909",
    "sg:province":"TN",
    "wof:name":"X L Health",
    "wof:placetype":"venue"
},
  "geometry": {"coordinates":[-83.98915,35.950134],"type":"Point"}
}