{
  "type": "Feature",
  "properties": {
    "iso:country":"US",
    "sg:address":"1554 Bartlett Rd",
    "sg:city":"Memphis",
    "sg:classifiers":[
        {
            "category":"Organizations",
            "subcategory":"Religious Organization",
            "type":"Services"
        }
    ],
    "sg:phone":"+1 901 386 1934",
    "sg:postcode":"38134",
    "sg:province":"TN",
    "sg:tags":[
        "church"
    ],
    "wof:name":"First Assembly Of God Church",
    "wof:placetype":"venue"
},
  "geometry": {"coordinates":[-89.88042,35.170507],"type":"Point"}
}