{
  "type": "Feature",
  "properties": {
    "iso:country":"US",
    "sg:address":"218 Williamsburg Cir",
    "sg:city":"Brentwood",
    "sg:classifiers":[
        {
            "category":"Professional",
            "subcategory":"Management & Consulting",
            "type":"Services"
        }
    ],
    "sg:phone":"+1 615 417 1484",
    "sg:postcode":"37027",
    "sg:province":"TN",
    "sg:tags":[
        "business"
    ],
    "wof:name":"Wilkins Consulting",
    "wof:placetype":"venue"
},
  "geometry": {"coordinates":[-86.793801,36.029076],"type":"Point"}
}