{
  "type": "Feature",
  "properties": {
    "iso:country":"US",
    "sg:address":"2051 Hamill Rd",
    "sg:city":"Hixson",
    "sg:classifiers":[
        {
            "category":"Health Services",
            "subcategory":"Hospital",
            "type":"Services"
        }
    ],
    "sg:phone":"+1 423 495 7100",
    "sg:postcode":"37343",
    "sg:province":"TN",
    "sg:website":"http://www.memorial.org/",
    "wof:name":"Memorial North Park Hospital",
    "wof:placetype":"venue"
},
  "geometry": {"coordinates":[-85.237977,35.123367],"type":"Point"}
}