{
  "type": "Feature",
  "properties": {
    "iso:country":"US",
    "sg:address":"215 6th Ave N",
    "sg:city":"Nashville",
    "sg:classifiers":[
        {
            "category":"Banks & Credit Unions",
            "subcategory":"Bank",
            "type":"Services"
        }
    ],
    "sg:phone":"+1 615 254 1841",
    "sg:postcode":"37219",
    "sg:province":"TN",
    "sg:tags":[
        "personal",
        "institution"
    ],
    "wof:name":"Nashville Finance Co",
    "wof:placetype":"venue"
},
  "geometry": {"coordinates":[-86.781407,36.162457],"type":"Point"}
}