{
  "type": "Feature",
  "properties": {
    "addr:full":"109 Chenoweth Ln La Vergne TN 37086",
    "addr:housenumber":"109",
    "addr:postcode":"37086",
    "addr:street":"Chenoweth Ln",
    "iso:country":"US",
    "sg:address":"109 Chenoweth Ln",
    "sg:city":"La Vergne",
    "sg:classifiers":[
        {
            "category":"Organizations",
            "subcategory":"Religious Organization",
            "type":"Services"
        }
    ],
    "sg:phone":"+1 615 213 8873",
    "sg:postcode":"37086",
    "sg:province":"TN",
    "wof:name":"Moriah Presbyterian Church",
    "wof:placetype":"venue"
},
  "geometry": {"coordinates":[-86.54229100000001,36.038822],"type":"Point"}
}