{
  "type": "Feature",
  "properties": {
    "iso:country":"US",
    "sg:address":"221 Clark St NW",
    "sg:city":"Knoxville",
    "sg:classifiers":[
        {
            "category":"Organizations",
            "subcategory":"Professional Association",
            "type":"Services"
        }
    ],
    "sg:phone":"+1 865 546 4665",
    "sg:postcode":"37921",
    "sg:province":"TN",
    "sg:website":"www.hbaknoxville.com",
    "wof:name":"Tennessee Valley Home Bldrs",
    "wof:placetype":"venue"
},
  "geometry": {"coordinates":[-83.931791,35.967232],"type":"Point"}
}