{
  "type": "Feature",
  "properties": {
    "addr:full":"567 Cason Ln Murfreesboro TN 37128",
    "addr:housenumber":"567",
    "addr:postcode":"37128",
    "addr:street":"Cason Ln",
    "iso:country":"US",
    "sg:address":"567 Cason Ln",
    "sg:city":"Murfreesboro",
    "sg:classifiers":[
        {
            "category":"Insurance",
            "subcategory":"Insurance Agent",
            "type":"Services"
        }
    ],
    "sg:phone":"+1 615 907 2558",
    "sg:postcode":"37128",
    "sg:province":"TN",
    "wof:name":"Horace Mann Co",
    "wof:placetype":"venue"
},
  "geometry": {"coordinates":[-86.440954,35.83781],"type":"Point"}
}