{
  "type": "Feature",
  "properties": {
    "iso:country":"US",
    "sg:address":"1329 Shadybrook Cove Ln",
    "sg:city":"Knoxville",
    "sg:classifiers":[
        {
            "category":"Wholesale",
            "subcategory":"Machinery & Supplies",
            "type":"Manufacturing & Wholesale Goods"
        },
        {
            "category":"Utilities",
            "subcategory":"Refuse",
            "type":"Services"
        }
    ],
    "sg:phone":"+1 865 670 8400",
    "sg:postcode":"37922",
    "sg:province":"TN",
    "sg:tags":[
        "equipment",
        "material",
        "container",
        "waste",
        "handling"
    ],
    "wof:name":"Specialty Containers Sales",
    "wof:placetype":"venue"
},
  "geometry": {"coordinates":[-84.091725,35.870333],"type":"Point"}
}