{
  "type": "Feature",
  "properties": {
    "iso:country":"US",
    "sg:address":"3818 Moss Rose Dr",
    "sg:city":"Nashville",
    "sg:classifiers":[
        {
            "category":"Professional",
            "subcategory":"Business Services",
            "type":"Services"
        }
    ],
    "sg:phone":"+1 615 227 0069",
    "sg:postcode":"37216",
    "sg:province":"TN",
    "wof:name":"Space Strategies Inc",
    "wof:placetype":"venue"
},
  "geometry": {"coordinates":[-86.70223799999999,36.208568],"type":"Point"}
}