{
  "type": "Feature",
  "properties": {
    "iso:country":"US",
    "sg:address":"812 Loposser Hollow Rd",
    "sg:city":"Seymour",
    "sg:classifiers":[
        {
            "category":"Real Estate",
            "subcategory":"Real Estate Agent",
            "type":"Services"
        }
    ],
    "sg:phone":"+1 865 579 5334",
    "sg:postcode":"37865",
    "sg:province":"TN",
    "sg:tags":[
        "agency",
        "rental"
    ],
    "wof:name":"Owl Oak Inc",
    "wof:placetype":"venue"
},
  "geometry": {"coordinates":[-83.71663599999999,35.871996],"type":"Point"}
}