{
  "type": "Feature",
  "properties": {
    "iso:country":"US",
    "sg:address":"6909 Mercer Rd",
    "sg:city":"Brownsville",
    "sg:classifiers":[
        {
            "category":"Farming",
            "subcategory":"Farm",
            "type":"Manufacturing & Wholesale Goods"
        }
    ],
    "sg:phone":"+1 731 772 4539",
    "sg:postcode":"38012",
    "sg:province":"TN",
    "sg:tags":[
        "crop",
        "general"
    ],
    "wof:name":"T&B Farms",
    "wof:placetype":"venue"
},
  "geometry": {"coordinates":[-89.16426800000001,35.538248],"type":"Point"}
}