{
  "type": "Feature",
  "properties": {
    "iso:country":"US",
    "sg:address":"563 S Water Ave",
    "sg:city":"Gallatin",
    "sg:classifiers":[
        {
            "category":"Food & Beverages",
            "subcategory":"Groceries & Convenience Stores",
            "type":"Retail Goods"
        }
    ],
    "sg:phone":"+1 615 206 6999",
    "sg:postcode":"37066",
    "sg:province":"TN",
    "sg:tags":[
        "grocer"
    ],
    "wof:name":"Bargains Discount Store",
    "wof:placetype":"venue"
},
  "geometry": {"coordinates":[-86.44311500000001,36.380009],"type":"Point"}
}