{
  "type": "Feature",
  "properties": {
    "iso:country":"US",
    "sg:address":"1472 Locust St",
    "sg:city":"Memphis",
    "sg:classifiers":[
        {
            "category":"Organizations",
            "subcategory":"Religious Organization",
            "type":"Services"
        }
    ],
    "sg:phone":"+1 901 327 8603",
    "sg:postcode":"38108",
    "sg:province":"TN",
    "sg:tags":[
        "church"
    ],
    "wof:name":"Morning Star Missionary Church",
    "wof:placetype":"venue"
},
  "geometry": {"coordinates":[-89.95751799999999,35.171689],"type":"Point"}
}