{
  "type": "Feature",
  "properties": {
    "iso:country":"US",
    "sg:address":"106 N White St",
    "sg:city":"Athens",
    "sg:classifiers":[
        {
            "category":"Professional",
            "subcategory":"Business Services",
            "type":"Services"
        }
    ],
    "sg:phone":"+1 423 745 4141",
    "sg:postcode":"37303",
    "sg:province":"TN",
    "sg:tags":[
        "interior",
        "consultant",
        "design",
        "decorator"
    ],
    "wof:name":"Pam's Pizazz",
    "wof:placetype":"venue"
},
  "geometry": {"coordinates":[-84.594037,35.443549],"type":"Point"}
}