{
  "type": "Feature",
  "properties": {
    "iso:country":"US",
    "sg:address":"2408 12th Ave S",
    "sg:city":"Nashville",
    "sg:classifiers":[
        {
            "category":"Professional",
            "subcategory":"Management & Consulting",
            "type":"Services"
        }
    ],
    "sg:phone":"+1 615 298 7701",
    "sg:postcode":"37204",
    "sg:province":"TN",
    "sg:tags":[
        "business"
    ],
    "wof:name":"Stragegic Business Consulting",
    "wof:placetype":"venue"
},
  "geometry": {"coordinates":[-86.78920599999999,36.126198],"type":"Point"}
}