{
  "type": "Feature",
  "properties": {
    "iso:country":"US",
    "sg:address":"2628 Nolensville Pike",
    "sg:city":"Nashville",
    "sg:classifiers":[
        {
            "category":"Shopping",
            "subcategory":"Clothing, Apparel, & Fashions",
            "type":"Retail Goods"
        }
    ],
    "sg:phone":"+1 615 832 4333",
    "sg:postcode":"37211",
    "sg:province":"TN",
    "sg:tags":[
        "business"
    ],
    "wof:name":"La Illusion",
    "wof:placetype":"venue"
},
  "geometry": {"coordinates":[-86.747917,36.116402],"type":"Point"}
}