{
  "type": "Feature",
  "properties": {
    "addr:full":"4740 Yale Rd Memphis TN 38128",
    "addr:housenumber":"4740",
    "addr:postcode":"38128",
    "addr:street":"Yale Rd",
    "iso:country":"US",
    "sg:address":"4740 Yale Rd",
    "sg:city":"Memphis",
    "sg:classifiers":[
        {
            "category":"Fast Food",
            "type":"Food & Drink"
        },
        {
            "category":"Restaurant",
            "type":"Food & Drink"
        }
    ],
    "sg:phone":"+1 901 937 6877",
    "sg:postcode":"38128",
    "sg:province":"TN",
    "sg:tags":[
        "style",
        "hamburger",
        "family",
        "house",
        "dog",
        "hot",
        "mexican",
        "steak"
    ],
    "wof:name":"Lindo Michoacan Restaurant",
    "wof:placetype":"venue"
},
  "geometry": {"coordinates":[-89.905317,35.221648],"type":"Point"}
}