{
  "type": "Feature",
  "properties": {
    "iso:country":"US",
    "sg:address":"900 Old Celina Rd",
    "sg:city":"Allons",
    "sg:classifiers":[
        {
            "category":"Freight",
            "type":"Transportation"
        }
    ],
    "sg:phone":"+1 931 823 7896",
    "sg:postcode":"38541",
    "sg:province":"TN",
    "sg:tags":[
        "operator",
        "trucking"
    ],
    "wof:name":"Jack Spears Trk",
    "wof:placetype":"venue"
},
  "geometry": {"coordinates":[-85.36319399999999,36.465169],"type":"Point"}
}