{
  "type": "Feature",
  "properties": {
    "addr:full":"1600 Broad St Chattanooga TN 37402",
    "addr:housenumber":"1600",
    "addr:postcode":"37402",
    "addr:street":"Broad St",
    "iso:country":"US",
    "sg:address":"1600 Broad St",
    "sg:city":"Chattanooga",
    "sg:classifiers":[
        {
            "category":"Retail",
            "subcategory":"Auto Repair",
            "type":"Services"
        },
        {
            "category":"Wholesale",
            "subcategory":"Auto Parts",
            "type":"Manufacturing & Wholesale Goods"
        }
    ],
    "sg:phone":"+1 423 266 3772",
    "sg:postcode":"37402",
    "sg:province":"TN",
    "sg:tags":[
        "repairing",
        "automobile",
        "product",
        "customizing"
    ],
    "sg:website":"www.grantsautotrim.com",
    "wof:name":"Grant's Auto Trim Inc",
    "wof:placetype":"venue"
},
  "geometry": {"coordinates":[-85.312157,35.035908],"type":"Point"}
}