{
  "type": "Feature",
  "properties": {
    "addr:full":"140 Sexton Ln Clinton TN 37716",
    "addr:housenumber":"140",
    "addr:postcode":"37716",
    "addr:street":"Sexton Ln",
    "iso:country":"US",
    "sg:address":"140 Sexton Ln",
    "sg:city":"Clinton",
    "sg:classifiers":[
        {
            "category":"Insurance",
            "subcategory":"Insurance Agent",
            "type":"Services"
        }
    ],
    "sg:phone":"+1 865 457 0467",
    "sg:postcode":"37716",
    "sg:province":"TN",
    "wof:name":"Terry Steil Insurance",
    "wof:placetype":"venue"
},
  "geometry": {"coordinates":[-84.164513,36.130565],"type":"Point"}
}