{
  "type": "Feature",
  "properties": {
    "iso:country":"US",
    "sg:address":"1556 Neelys Bend Rd",
    "sg:city":"Madison",
    "sg:classifiers":[
        {
            "category":"Professional",
            "subcategory":"Employment Agencies",
            "type":"Services"
        }
    ],
    "sg:phone":"+1 615 860 8286",
    "sg:postcode":"37115",
    "sg:province":"TN",
    "sg:tags":[
        "opportunity"
    ],
    "wof:name":"Baker & Baker Employment Svc",
    "wof:placetype":"venue"
},
  "geometry": {"coordinates":[-86.66744300000001,36.220065],"type":"Point"}
}