{
  "type": "Feature",
  "properties": {
    "addr:full":"678 George Rd Memphis TN 38109",
    "addr:housenumber":"678",
    "addr:postcode":"38109",
    "addr:street":"George Rd",
    "iso:country":"US",
    "sg:address":"678 George Rd",
    "sg:city":"Memphis",
    "sg:classifiers":[
        {
            "category":"Professional",
            "subcategory":"Engineering",
            "type":"Services"
        },
        {
            "category":"Building & Trades",
            "subcategory":"Construction",
            "type":"Services"
        }
    ],
    "sg:phone":"+1 901 786 9175",
    "sg:postcode":"38109",
    "sg:province":"TN",
    "sg:tags":[
        "repair",
        "management",
        "energy",
        "systems-service",
        "equipment",
        "solar",
        "engineer"
    ],
    "wof:name":"Msc Merchandising",
    "wof:placetype":"venue"
},
  "geometry": {"coordinates":[-90.08604099999999,35.015374],"type":"Point"}
}