{
  "type": "Feature",
  "properties": {
    "iso:country":"US",
    "sg:address":"1680 S Jefferson Ave",
    "sg:city":"Cookeville",
    "sg:classifiers":[
        {
            "category":"Shopping",
            "subcategory":"Clothing, Apparel, & Fashions",
            "type":"Retail Goods"
        }
    ],
    "sg:phone":"+1 931 528 5532",
    "sg:postcode":"38506",
    "sg:province":"TN",
    "sg:tags":[
        "leather"
    ],
    "wof:name":"Leather WORX",
    "wof:placetype":"venue"
},
  "geometry": {"coordinates":[-85.506956,36.116557],"type":"Point"}
}