{
  "type": "Feature",
  "properties": {
    "addr:full":"768 Forest Retreat Rd Hendersonville TN 37075",
    "addr:housenumber":"768",
    "addr:postcode":"37075",
    "addr:street":"Forest Retreat Rd",
    "iso:country":"US",
    "sg:address":"768 Forest Retreat Rd",
    "sg:city":"Hendersonville",
    "sg:classifiers":[
        {
            "category":"Organizations",
            "subcategory":"Religious Organization",
            "type":"Services"
        }
    ],
    "sg:phone":"+1 615 826 7575",
    "sg:postcode":"37075",
    "sg:province":"TN",
    "sg:tags":[
        "church"
    ],
    "sg:website":"www.celebrationoflife.com",
    "wof:name":"Celebration Of Life",
    "wof:placetype":"venue"
},
  "geometry": {"coordinates":[-86.638457,36.333363],"type":"Point"}
}