{
  "type": "Feature",
  "properties": {
    "iso:country":"US",
    "sg:address":"5540 Waynesboro Hwy",
    "sg:city":"Lawrenceburg",
    "sg:classifiers":[
        {
            "category":"Food & Beverages",
            "subcategory":"Groceries & Convenience Stores",
            "type":"Retail Goods"
        }
    ],
    "sg:phone":"+1 931 766 0150",
    "sg:postcode":"38464",
    "sg:province":"TN",
    "sg:tags":[
        "grocer"
    ],
    "wof:name":"Self's Market",
    "wof:placetype":"venue"
},
  "geometry": {"coordinates":[-87.510051,35.308812],"type":"Point"}
}