{
  "type": "Feature",
  "properties": {
    "iso:country":"US",
    "sg:address":"482 Troupe Rd",
    "sg:city":"Shelbyville",
    "sg:classifiers":[
        {
            "category":"Building & Trades",
            "subcategory":"Plumbing",
            "type":"Services"
        }
    ],
    "sg:phone":"+1 931 685 9338",
    "sg:postcode":"37160",
    "sg:province":"TN",
    "sg:tags":[
        "plumbing",
        "contractor"
    ],
    "wof:name":"J & P Septic Svc",
    "wof:placetype":"venue"
},
  "geometry": {"coordinates":[-86.513041,35.513915],"type":"Point"}
}