{
  "type": "Feature",
  "properties": {
    "iso:country":"US",
    "sg:address":"10179 Lee Hwy",
    "sg:city":"Ooltewah",
    "sg:classifiers":[
        {
            "category":"Building & Trades",
            "subcategory":"Construction",
            "type":"Services"
        }
    ],
    "sg:phone":"+1 423 238 7488",
    "sg:postcode":"37363",
    "sg:province":"TN",
    "wof:name":"Bowen Co",
    "wof:placetype":"venue"
},
  "geometry": {"coordinates":[-85.03210199999999,35.080607],"type":"Point"}
}