{
  "type": "Feature",
  "properties": {
    "addr:full":"1822 River Dr Nashville TN 37218",
    "addr:housenumber":"1822",
    "addr:postcode":"37218",
    "addr:street":"River Dr",
    "iso:country":"US",
    "sg:address":"1822 River Dr",
    "sg:city":"Nashville",
    "sg:classifiers":[
        {
            "category":"Shopping",
            "type":"Retail Goods"
        }
    ],
    "sg:phone":"+1 615 742 3141",
    "sg:postcode":"37218",
    "sg:province":"TN",
    "sg:tags":[
        "merchandise"
    ],
    "wof:name":"USA Discount Tobacco",
    "wof:placetype":"venue"
},
  "geometry": {"coordinates":[-86.834391,36.187116],"type":"Point"}
}