{
  "type": "Feature",
  "properties": {
    "addr:full":"403 N Main St Kingston Springs TN 37082",
    "addr:housenumber":"403",
    "addr:postcode":"37082",
    "addr:street":"N Main St",
    "iso:country":"US",
    "sg:address":"403 N Main St",
    "sg:city":"Kingston Springs",
    "sg:classifiers":[
        {
            "category":"Personal",
            "type":"Services"
        }
    ],
    "sg:phone":"+1 615 952 5540",
    "sg:postcode":"37082",
    "sg:province":"TN",
    "sg:tags":[
        "control",
        "weight"
    ],
    "wof:name":"Spens Fitness",
    "wof:placetype":"venue"
},
  "geometry": {"coordinates":[-87.115014,36.100587],"type":"Point"}
}