{
  "type": "Feature",
  "properties": {
    "iso:country":"US",
    "sg:address":"244 W Central Ave",
    "sg:city":"La Follette",
    "sg:classifiers":[
        {
            "category":"Banks & Credit Unions",
            "subcategory":"Bank",
            "type":"Services"
        }
    ],
    "sg:phone":"+1 423 907 8002",
    "sg:postcode":"37766",
    "sg:province":"TN",
    "sg:tags":[
        "depository",
        "banking"
    ],
    "wof:name":"First Volunteer Bank",
    "wof:placetype":"venue"
},
  "geometry": {"coordinates":[-84.124511,36.379324],"type":"Point"}
}