{
  "type": "Feature",
  "properties": {
    "addr:full":"3454 Hillridge St Memphis TN 38109",
    "addr:housenumber":"3454",
    "addr:postcode":"38109",
    "addr:street":"Hillridge St",
    "iso:country":"US",
    "sg:address":"3454 Hillridge St",
    "sg:city":"Memphis",
    "sg:classifiers":[
        {
            "category":"Organizations",
            "subcategory":"Religious Organization",
            "type":"Services"
        }
    ],
    "sg:phone":"+1 901 398 6721",
    "sg:postcode":"38109",
    "sg:province":"TN",
    "sg:tags":[
        "church"
    ],
    "wof:name":"Jehovah's Witnesses",
    "wof:placetype":"venue"
},
  "geometry": {"coordinates":[-90.05416200000001,35.054597],"type":"Point"}
}