{
  "type": "Feature",
  "properties": {
    "iso:country":"US",
    "sg:address":"1727 Bluff Rd",
    "sg:city":"Harriman",
    "sg:classifiers":[
        {
            "category":"Wholesale",
            "subcategory":"Non-durable Goods",
            "type":"Manufacturing & Wholesale Goods"
        }
    ],
    "sg:phone":"+1 865 882 9226",
    "sg:postcode":"37748",
    "sg:province":"TN",
    "wof:name":"Melton Company",
    "wof:placetype":"venue"
},
  "geometry": {"coordinates":[-84.557157,35.872963],"type":"Point"}
}