{
  "type": "Feature",
  "properties": {
    "iso:country":"US",
    "sg:address":"9105 3 Points Rd",
    "sg:city":"Mascot",
    "sg:classifiers":[
        {
            "category":"Retail",
            "subcategory":"Animal Services",
            "type":"Services"
        }
    ],
    "sg:phone":"+1 865 933 7811",
    "sg:postcode":"37806",
    "sg:province":"TN",
    "sg:tags":[
        "pet",
        "grooming",
        "washing"
    ],
    "wof:name":"Paw Prints Grooming & Boarding",
    "wof:placetype":"venue"
},
  "geometry": {"coordinates":[-83.77359800000001,36.076505],"type":"Point"}
}