{
  "type": "Feature",
  "properties": {
    "iso:country":"US",
    "sg:address":"1807 Shaw Chapel Rd",
    "sg:city":"Brownsville",
    "sg:classifiers":[
        {
            "category":"Building & Trades",
            "subcategory":"Construction",
            "type":"Services"
        }
    ],
    "sg:phone":"+1 731 772 6288",
    "sg:postcode":"38012",
    "sg:province":"TN",
    "sg:tags":[
        "house"
    ],
    "wof:name":"Cox Construction",
    "wof:placetype":"venue"
},
  "geometry": {"coordinates":[-89.282427,35.563338],"type":"Point"}
}