{
  "type": "Feature",
  "properties": {
    "addr:full":"133 Henslee Dr Dickson TN 37055",
    "addr:housenumber":"133",
    "addr:postcode":"37055",
    "addr:street":"Henslee Dr",
    "iso:country":"US",
    "sg:address":"133 Henslee Dr",
    "sg:city":"Dickson",
    "sg:classifiers":[
        {
            "category":"Personal",
            "subcategory":"Tanning Parlor",
            "type":"Services"
        }
    ],
    "sg:phone":"+1 615 446 9255",
    "sg:postcode":"37055",
    "sg:province":"TN",
    "sg:tags":[
        "salon"
    ],
    "wof:name":"Express Tans",
    "wof:placetype":"venue"
},
  "geometry": {"coordinates":[-87.36881,36.074757],"type":"Point"}
}