{
  "type": "Feature",
  "properties": {
    "iso:country":"US",
    "sg:address":"6226 Ringgold Rd",
    "sg:city":"Chattanooga",
    "sg:classifiers":[
        {
            "category":"Banks & Credit Unions",
            "subcategory":"Bank",
            "type":"Services"
        }
    ],
    "sg:phone":"+1 423 855 2131",
    "sg:postcode":"37412",
    "sg:province":"TN",
    "sg:tags":[
        "broker",
        "mortgage"
    ],
    "wof:name":"Atlas Mortgage LLC",
    "wof:placetype":"venue"
},
  "geometry": {"coordinates":[-85.212303,34.989667],"type":"Point"}
}