{
  "type": "Feature",
  "properties": {
    "iso:country":"US",
    "sg:address":"5179 Wheelis Dr",
    "sg:city":"Memphis",
    "sg:classifiers":[
        {
            "category":"Personal",
            "subcategory":"Beauty Salon",
            "type":"Services"
        }
    ],
    "sg:phone":"+1 901 683 1327",
    "sg:postcode":"38117",
    "sg:province":"TN",
    "wof:name":"Barnette's Ed",
    "wof:placetype":"venue"
},
  "geometry": {"coordinates":[-89.889157,35.114564],"type":"Point"}
}