{
  "type": "Feature",
  "properties": {
    "iso:country":"US",
    "sg:address":"581 Highpoint Dr",
    "sg:city":"Smyrna",
    "sg:classifiers":[
        {
            "category":"Professional",
            "subcategory":"Computer Services",
            "type":"Services"
        }
    ],
    "sg:phone":"+1 615 355 4685",
    "sg:postcode":"37167",
    "sg:province":"TN",
    "sg:tags":[
        "related"
    ],
    "wof:name":"Datasoft LLC",
    "wof:placetype":"venue"
},
  "geometry": {"coordinates":[-86.48808200000001,35.989228],"type":"Point"}
}