{
  "type": "Feature",
  "properties": {
    "iso:country":"US",
    "sg:address":"1205 S 4th St",
    "sg:city":"Union City",
    "sg:classifiers":[
        {
            "category":"Retail",
            "subcategory":"Auto Repair",
            "type":"Services"
        }
    ],
    "sg:phone":"+1 731 885 7411",
    "sg:postcode":"38261",
    "sg:province":"TN",
    "sg:tags":[
        "machine",
        "automobile",
        "shop"
    ],
    "wof:name":"Kelly's Engine Svc",
    "wof:placetype":"venue"
},
  "geometry": {"coordinates":[-89.061508,36.415867],"type":"Point"}
}