{
  "type": "Feature",
  "properties": {
    "addr:full":"2660 Slayden-Marion Rd Cumberland Furnace TN 37051",
    "addr:housenumber":"2660",
    "addr:postcode":"37051",
    "addr:street":"Slayden-Marion Rd",
    "iso:country":"US",
    "sg:address":"2660 Slayden-Marion Rd",
    "sg:city":"Cumberland Furnace",
    "sg:classifiers":[
        {
            "category":"Banks & Credit Unions",
            "subcategory":"Bank",
            "type":"Services"
        }
    ],
    "sg:phone":"+1 615 763 0078",
    "sg:postcode":"37051",
    "sg:province":"TN",
    "sg:tags":[
        "mortgage"
    ],
    "wof:name":"Steve Tressler",
    "wof:placetype":"venue"
},
  "geometry": {"coordinates":[-87.464268,36.28616],"type":"Point"}
}