{
  "type": "Feature",
  "properties": {
    "iso:country":"US",
    "sg:address":"321 S Bellevue Blvd",
    "sg:city":"Memphis",
    "sg:classifiers":[
        {
            "category":"Health Services",
            "subcategory":"Clinic",
            "type":"Services"
        },
        {
            "category":"Insurance",
            "subcategory":"Hazard Insurance",
            "type":"Services"
        }
    ],
    "sg:phone":"+1 901 272 7526",
    "sg:postcode":"38104",
    "sg:province":"TN",
    "sg:tags":[
        "medical",
        "commercial",
        "business"
    ],
    "wof:name":"Memphis Plan The",
    "wof:placetype":"venue"
},
  "geometry": {"coordinates":[-90.020791,35.133303],"type":"Point"}
}