{
  "type": "Feature",
  "properties": {
    "addr:full":"1701 Broad St Chattanooga TN 37402",
    "addr:housenumber":"1701",
    "addr:postcode":"37402",
    "addr:street":"Broad St",
    "iso:country":"US",
    "sg:address":"1701 Broad St",
    "sg:city":"Chattanooga",
    "sg:classifiers":[
        {
            "category":"Manufacturing",
            "subcategory":"Signs",
            "type":"Manufacturing & Wholesale Goods"
        }
    ],
    "sg:phone":"+1 423 265 1500",
    "sg:postcode":"37402",
    "sg:province":"TN",
    "wof:name":"Signs Now",
    "wof:placetype":"venue"
},
  "geometry": {"coordinates":[-85.312614,35.035084],"type":"Point"}
}