{
  "type": "Feature",
  "properties": {
    "iso:country":"US",
    "sg:address":"8000 Centerview Pkwy # 115",
    "sg:city":"Cordova",
    "sg:classifiers":[
        {
            "category":"Health Services",
            "subcategory":"Doctor",
            "type":"Services"
        },
        {
            "category":"Health Services",
            "subcategory":"Hospital",
            "type":"Services"
        }
    ],
    "sg:phone":"+1 901 756 7113",
    "sg:postcode":"38018",
    "sg:province":"TN",
    "sg:tags":[
        "nursing",
        "consultant",
        "medical",
        "practice",
        "home"
    ],
    "wof:name":"Pfms",
    "wof:placetype":"venue"
},
  "geometry": {"coordinates":[-89.795303,35.127579],"type":"Point"}
}