{
  "type": "Feature",
  "properties": {
    "iso:country":"US",
    "sg:address":"900 2nd Ave N",
    "sg:city":"Nashville",
    "sg:classifiers":[
        {
            "category":"Government",
            "subcategory":"Office",
            "type":"Public Place"
        }
    ],
    "sg:phone":"+1 615 329 1911",
    "sg:postcode":"37201",
    "sg:province":"TN",
    "sg:tags":[
        "state",
        "resource"
    ],
    "wof:name":"Note 24 Hour Child Abuse Svc",
    "wof:placetype":"venue"
},
  "geometry": {"coordinates":[-86.783019,36.174393],"type":"Point"}
}