{
  "type": "Feature",
  "properties": {
    "iso:country":"US",
    "sg:address":"130 S Cannon Ave",
    "sg:city":"Murfreesboro",
    "sg:classifiers":[
        {
            "category":"Building & Trades",
            "subcategory":"Plumbing",
            "type":"Services"
        }
    ],
    "sg:phone":"+1 615 890 4515",
    "sg:postcode":"37129",
    "sg:province":"TN",
    "sg:tags":[
        "conditioning",
        "air",
        "system",
        "contractor"
    ],
    "wof:name":"Tedder Co",
    "wof:placetype":"venue"
},
  "geometry": {"coordinates":[-86.401933,35.846006],"type":"Point"}
}