{
  "type": "Feature",
  "properties": {
    "iso:country":"US",
    "sg:address":"240 W Gaines St",
    "sg:city":"Lawrenceburg",
    "sg:classifiers":[
        {
            "category":"Government",
            "subcategory":"Court House",
            "type":"Public Place"
        }
    ],
    "sg:phone":"+1 931 762 7700",
    "sg:postcode":"38464",
    "sg:province":"TN",
    "sg:tags":[
        "county"
    ],
    "wof:name":"Lawrence County Chancery Court",
    "wof:placetype":"venue"
},
  "geometry": {"coordinates":[-87.336474,35.242547],"type":"Point"}
}