{
  "type": "Feature",
  "properties": {
    "iso:country":"US",
    "sg:address":"660 Mainstream Dr",
    "sg:city":"Nashville",
    "sg:classifiers":[
        {
            "category":"Professional",
            "subcategory":"Computer Services",
            "type":"Services"
        }
    ],
    "sg:phone":"+1 615 244 2122",
    "sg:postcode":"37228",
    "sg:province":"TN",
    "sg:tags":[
        "internet"
    ],
    "wof:name":"Comcast Cable Advertising",
    "wof:placetype":"venue"
},
  "geometry": {"coordinates":[-86.817739,36.196087],"type":"Point"}
}