{
  "type": "Feature",
  "properties": {
    "addr:full":"1500 Laura Ln Dyersburg TN 38024",
    "addr:housenumber":"1500",
    "addr:postcode":"38024",
    "addr:street":"Laura Ln",
    "iso:country":"US",
    "sg:address":"1500 Laura Ln",
    "sg:city":"Dyersburg",
    "sg:classifiers":[
        {
            "category":"Building & Trades",
            "subcategory":"Construction",
            "type":"Services"
        }
    ],
    "sg:phone":"+1 731 287 0440",
    "sg:postcode":"38024",
    "sg:province":"TN",
    "sg:tags":[
        "home",
        "family"
    ],
    "wof:name":"Luckett Construction",
    "wof:placetype":"venue"
},
  "geometry": {"coordinates":[-89.397667,36.047204],"type":"Point"}
}