{
  "type": "Feature",
  "properties": {
    "iso:country":"US",
    "sg:address":"8359 US Hwy 64",
    "sg:city":"Memphis",
    "sg:classifiers":[
        {
            "category":"Shopping",
            "subcategory":"Clothing, Apparel, & Fashions",
            "type":"Retail Goods"
        }
    ],
    "sg:phone":"+1 901 384 6463",
    "sg:postcode":"38133",
    "sg:province":"TN",
    "wof:name":"Lane Bryant",
    "wof:placetype":"venue"
},
  "geometry": {"coordinates":[-89.783559,35.204371],"type":"Point"}
}