{
  "type": "Feature",
  "properties": {
    "iso:country":"US",
    "sg:address":"212 Depot St",
    "sg:city":"Goodlettsville",
    "sg:classifiers":[
        {
            "category":"Manufacturing",
            "subcategory":"Tools & Machinery",
            "type":"Manufacturing & Wholesale Goods"
        }
    ],
    "sg:phone":"+1 615 851 5020",
    "sg:postcode":"37072",
    "sg:province":"TN",
    "sg:tags":[
        "machine",
        "shop"
    ],
    "wof:name":"Triple H Machine",
    "wof:placetype":"venue"
},
  "geometry": {"coordinates":[-86.710574,36.327141],"type":"Point"}
}