{
  "type": "Feature",
  "properties": {
    "iso:country":"US",
    "sg:address":"1221 N 2nd St",
    "sg:city":"Nashville",
    "sg:classifiers":[
        {
            "category":"Arts & Performance",
            "subcategory":"Theater",
            "type":"Entertainment"
        }
    ],
    "sg:phone":"+1 615 586 8143",
    "sg:postcode":"37207",
    "sg:province":"TN",
    "sg:tags":[
        "bureau"
    ],
    "wof:name":"X-Con Entertainment",
    "wof:placetype":"venue"
},
  "geometry": {"coordinates":[-86.76997,36.193798],"type":"Point"}
}