{
  "type": "Feature",
  "properties": {
    "iso:country":"US",
    "sg:address":"2710 Kanasita Dr",
    "sg:city":"Hixson",
    "sg:classifiers":[
        {
            "category":"Manufacturing",
            "subcategory":"Rubber & Plastics",
            "type":"Manufacturing & Wholesale Goods"
        }
    ],
    "sg:phone":"+1 423 877 3480",
    "sg:postcode":"37343",
    "sg:province":"TN",
    "sg:website":"www.lookoutind.com",
    "wof:name":"Lookout Industries",
    "wof:placetype":"venue"
},
  "geometry": {"coordinates":[-85.22872599999999,35.133587],"type":"Point"}
}