{
  "type": "Feature",
  "properties": {
    "iso:country":"US",
    "sg:address":"2436 Hargrove Ave",
    "sg:city":"Memphis",
    "sg:classifiers":[
        {
            "category":"Building & Trades",
            "subcategory":"Plumbing",
            "type":"Services"
        }
    ],
    "sg:phone":"+1 901 643 1654",
    "sg:postcode":"38127",
    "sg:province":"TN",
    "sg:tags":[
        "plumber",
        "industrial",
        "contractors-commercial"
    ],
    "wof:name":"Leto Green Plumbing",
    "wof:placetype":"venue"
},
  "geometry": {"coordinates":[-89.98242399999999,35.217355],"type":"Point"}
}