{
  "type": "Feature",
  "properties": {
    "iso:country":"US",
    "sg:address":"309 Kinzalow Dr",
    "sg:city":"Sweetwater",
    "sg:classifiers":[
        {
            "category":"Wholesale",
            "subcategory":"Electrical",
            "type":"Manufacturing & Wholesale Goods"
        }
    ],
    "sg:phone":"+1 423 337 0110",
    "sg:postcode":"37874",
    "sg:province":"TN",
    "sg:tags":[
        "video",
        "disc",
        "tape"
    ],
    "wof:name":"Twilight Entertainment Distr",
    "wof:placetype":"venue"
},
  "geometry": {"coordinates":[-84.445144,35.604322],"type":"Point"}
}