{
  "type": "Feature",
  "properties": {
    "iso:country":"US",
    "sg:address":"300 Merchants Dr",
    "sg:city":"Knoxville",
    "sg:classifiers":[
        {
            "category":"Professional",
            "subcategory":"Management & Consulting",
            "type":"Services"
        }
    ],
    "sg:phone":"+1 865 687 6794",
    "sg:postcode":"37912",
    "sg:province":"TN",
    "sg:tags":[
        "fuel"
    ],
    "wof:name":"Brass Management Co",
    "wof:placetype":"venue"
},
  "geometry": {"coordinates":[-83.97419600000001,36.009363],"type":"Point"}
}