{
  "type": "Feature",
  "properties": {
    "addr:full":"251 E Church St Lexington TN 38351",
    "addr:housenumber":"251",
    "addr:postcode":"38351",
    "addr:street":"E Church St",
    "iso:country":"US",
    "sg:address":"251 E Church St",
    "sg:city":"Lexington",
    "sg:classifiers":[
        {
            "category":"Personal",
            "subcategory":"Beauty Salon",
            "type":"Services"
        }
    ],
    "sg:phone":"+1 731 968 5499",
    "sg:postcode":"38351",
    "sg:province":"TN",
    "sg:tags":[
        "shop"
    ],
    "wof:name":"Final Touch",
    "wof:placetype":"venue"
},
  "geometry": {"coordinates":[-88.38756100000001,35.64547],"type":"Point"}
}