{
  "type": "Feature",
  "properties": {
    "iso:country":"US",
    "sg:address":"116 S Liberty St",
    "sg:city":"Jackson",
    "sg:classifiers":[
        {
            "category":"Professional",
            "subcategory":"Lawyer & Legal Services",
            "type":"Services"
        }
    ],
    "sg:phone":"+1 731 423 9333",
    "sg:postcode":"38301",
    "sg:province":"TN",
    "sg:tags":[
        "attorney"
    ],
    "wof:name":"Harold F Johnson",
    "wof:placetype":"venue"
},
  "geometry": {"coordinates":[-88.81819400000001,35.613572],"type":"Point"}
}