{
  "type": "Feature",
  "properties": {
    "iso:country":"US",
    "sg:address":"8207 Crowne Brook Cir",
    "sg:city":"Franklin",
    "sg:classifiers":[
        {
            "category":"Professional",
            "type":"Services"
        }
    ],
    "sg:phone":"+1 615 778 0885",
    "sg:postcode":"37067",
    "sg:province":"TN",
    "wof:name":"Mark Sweeney",
    "wof:placetype":"venue"
},
  "geometry": {"coordinates":[-86.802789,35.952518],"type":"Point"}
}