{
  "type": "Feature",
  "properties": {
    "iso:country":"US",
    "sg:address":"3260 State Hwy 57 W",
    "sg:city":"Ramer",
    "sg:classifiers":[
        {
            "category":"Freight",
            "type":"Transportation"
        }
    ],
    "sg:phone":"+1 731 689 0366",
    "sg:postcode":"38367",
    "sg:province":"TN",
    "sg:tags":[
        "trucking"
    ],
    "wof:name":"Cardinal Transport",
    "wof:placetype":"venue"
},
  "geometry": {"coordinates":[-88.602,35.072524],"type":"Point"}
}