{
  "type": "Feature",
  "properties": {
    "addr:full":"130 Old Denmark Rd Jackson TN 38301",
    "addr:housenumber":"130",
    "addr:postcode":"38301",
    "addr:street":"Old Denmark Rd",
    "iso:country":"US",
    "sg:address":"130 Old Denmark Rd",
    "sg:city":"Jackson",
    "sg:classifiers":[
        {
            "category":"Organizations",
            "subcategory":"Non-profit Organization",
            "type":"Services"
        },
        {
            "category":"Education",
            "subcategory":"School",
            "type":"Public Place"
        }
    ],
    "sg:phone":"+1 731 423 8924",
    "sg:postcode":"38301",
    "sg:province":"TN",
    "sg:tags":[
        "private"
    ],
    "sg:website":"www.tcalions.com",
    "wof:name":"Trinity Christian Academy Inc",
    "wof:placetype":"venue"
},
  "geometry": {"coordinates":[-88.880078,35.607536],"type":"Point"}
}