{
  "type": "Feature",
  "properties": {
    "iso:country":"US",
    "sg:address":"1730 Woodbine Ave",
    "sg:city":"Knoxville",
    "sg:classifiers":[
        {
            "category":"Autos & Motor Vehicles",
            "subcategory":"Automobile Sales",
            "type":"Retail Goods"
        }
    ],
    "sg:phone":"+1 865 525 5496",
    "sg:postcode":"37917",
    "sg:province":"TN",
    "sg:tags":[
        "wrecker"
    ],
    "wof:name":"Best Wrecker Svc",
    "wof:placetype":"venue"
},
  "geometry": {"coordinates":[-83.90751400000001,35.982084],"type":"Point"}
}