{
  "type": "Feature",
  "properties": {
    "iso:country":"US",
    "sg:address":"1300 State Hwy 100 W",
    "sg:city":"Centerville",
    "sg:classifiers":[
        {
            "category":"Cinema",
            "subcategory":"Movie Rental",
            "type":"Entertainment"
        }
    ],
    "sg:phone":"+1 931 729 2642",
    "sg:postcode":"37033",
    "sg:province":"TN",
    "sg:tags":[
        "video",
        "tape"
    ],
    "wof:name":"Hometown Video",
    "wof:placetype":"venue"
},
  "geometry": {"coordinates":[-87.47678999999999,35.719492],"type":"Point"}
}