{
  "type": "Feature",
  "properties": {
    "addr:full":"9319 Navaho Dr Brentwood TN 37027",
    "addr:housenumber":"9319",
    "addr:postcode":"37027",
    "addr:street":"Navaho Dr",
    "iso:country":"US",
    "sg:address":"9319 Navaho Dr",
    "sg:city":"Brentwood",
    "sg:classifiers":[
        {
            "category":"Professional",
            "subcategory":"Business Services",
            "type":"Services"
        }
    ],
    "sg:phone":"+1 615 309 8693",
    "sg:postcode":"37027",
    "sg:province":"TN",
    "wof:name":"Evaluation Design",
    "wof:placetype":"venue"
},
  "geometry": {"coordinates":[-86.759429,35.984023],"type":"Point"}
}