{
  "type": "Feature",
  "properties": {
    "addr:full":"406 W Burton St Murfreesboro TN 37130",
    "addr:housenumber":"406",
    "addr:postcode":"37130",
    "addr:street":"W Burton St",
    "iso:country":"US",
    "sg:address":"406 W Burton St",
    "sg:city":"Murfreesboro",
    "sg:classifiers":[
        {
            "category":"Home & Garden",
            "subcategory":"Home Furnishings",
            "type":"Retail Goods"
        }
    ],
    "sg:phone":"+1 615 893 8013",
    "sg:postcode":"37130",
    "sg:province":"TN",
    "sg:tags":[
        "wholesale",
        "lighting",
        "fixture",
        "equipment"
    ],
    "wof:name":"Neals Lighting Center",
    "wof:placetype":"venue"
},
  "geometry": {"coordinates":[-86.394535,35.849501],"type":"Point"}
}