{
  "type": "Feature",
  "properties": {
    "iso:country":"US",
    "sg:address":"1338 W College St",
    "sg:city":"Murfreesboro",
    "sg:classifiers":[
        {
            "category":"Insurance",
            "subcategory":"Insurance Agent",
            "type":"Services"
        }
    ],
    "sg:phone":"+1 615 890 1493",
    "sg:postcode":"37129",
    "sg:province":"TN",
    "wof:name":"Farmers Insurance Group",
    "wof:placetype":"venue"
},
  "geometry": {"coordinates":[-86.417314,35.866394],"type":"Point"}
}