{
  "type": "Feature",
  "properties": {
    "iso:country":"US",
    "sg:address":"9000 Executive Park Dr NW",
    "sg:city":"Knoxville",
    "sg:classifiers":[
        {
            "category":"Professional",
            "subcategory":"Business Services",
            "type":"Services"
        },
        {
            "category":"Personal",
            "type":"Services"
        }
    ],
    "sg:phone":"+1 865 531 7945",
    "sg:postcode":"37923",
    "sg:province":"TN",
    "sg:tags":[
        "department",
        "motor",
        "vehicle"
    ],
    "sg:website":"www.absautoservices.com",
    "wof:name":"ABS License & Titling Service",
    "wof:placetype":"venue"
},
  "geometry": {"coordinates":[-84.082804,35.921714],"type":"Point"}
}