{
  "type": "Feature",
  "properties": {
    "iso:country":"US",
    "sg:address":"4198 Webb Rd",
    "sg:city":"Chattanooga",
    "sg:classifiers":[
        {
            "category":"Organizations",
            "subcategory":"Religious Organization",
            "type":"Services"
        }
    ],
    "sg:phone":"+1 423 899 5490",
    "sg:postcode":"37416",
    "sg:province":"TN",
    "sg:tags":[
        "church"
    ],
    "wof:name":"Church Of God Seventh Day",
    "wof:placetype":"venue"
},
  "geometry": {"coordinates":[-85.185852,35.095843],"type":"Point"}
}