{
  "type": "Feature",
  "properties": {
    "addr:full":"368 Busby Rd Loretto TN 38469",
    "addr:housenumber":"368",
    "addr:postcode":"38469",
    "addr:street":"Busby Rd",
    "iso:country":"US",
    "sg:address":"368 Busby Rd",
    "sg:city":"Loretto",
    "sg:classifiers":[
        {
            "category":"Organizations",
            "subcategory":"Religious Organization",
            "type":"Services"
        }
    ],
    "sg:phone":"+1 931 853 6352",
    "sg:postcode":"38469",
    "sg:province":"TN",
    "sg:tags":[
        "church"
    ],
    "wof:name":"Loretto United Christn Church",
    "wof:placetype":"venue"
},
  "geometry": {"coordinates":[-87.46702999999999,35.113722],"type":"Point"}
}