{
  "type": "Feature",
  "properties": {
    "iso:country":"US",
    "sg:address":"4721 Griffith Dr",
    "sg:city":"Knoxville",
    "sg:classifiers":[
        {
            "category":"Marine",
            "type":"Transportation"
        }
    ],
    "sg:phone":"+1 865 523 6863",
    "sg:postcode":"37914",
    "sg:province":"TN",
    "sg:tags":[
        "water",
        "transport"
    ],
    "wof:name":"Victory Detail & Accessories",
    "wof:placetype":"venue"
},
  "geometry": {"coordinates":[-83.845747,35.978384],"type":"Point"}
}