{
  "type": "Feature",
  "properties": {
    "iso:country":"US",
    "sg:address":"2545 Byington Solway Rd",
    "sg:city":"Knoxville",
    "sg:classifiers":[
        {
            "category":"Freight",
            "type":"Transportation"
        }
    ],
    "sg:phone":"+1 865 691 6894",
    "sg:postcode":"37931",
    "sg:province":"TN",
    "sg:tags":[
        "general"
    ],
    "wof:name":"Karns Mini Storage",
    "wof:placetype":"venue"
},
  "geometry": {"coordinates":[-84.11810800000001,35.968182],"type":"Point"}
}