{
  "type": "Feature",
  "properties": {
    "iso:country":"US",
    "sg:address":"1031 Park St",
    "sg:city":"Westmoreland",
    "sg:classifiers":[
        {
            "category":"Personal",
            "subcategory":"Beauty Salon",
            "type":"Services"
        }
    ],
    "sg:phone":"+1 615 644 3540",
    "sg:postcode":"37186",
    "sg:province":"TN",
    "wof:name":"Daisy's Styles",
    "wof:placetype":"venue"
},
  "geometry": {"coordinates":[-86.247688,36.5615],"type":"Point"}
}