{
  "type": "Feature",
  "properties": {
    "iso:country":"US",
    "sg:address":"1228 S Russell St",
    "sg:city":"Portland",
    "sg:classifiers":[
        {
            "category":"Freight",
            "type":"Transportation"
        }
    ],
    "sg:phone":"+1 615 325 7501",
    "sg:postcode":"37148",
    "sg:province":"TN",
    "sg:tags":[
        "operator",
        "trucking"
    ],
    "wof:name":"Edd Read Trucking Co",
    "wof:placetype":"venue"
},
  "geometry": {"coordinates":[-86.500354,36.564005],"type":"Point"}
}