{
  "type": "Feature",
  "properties": {
    "iso:country":"US",
    "sg:address":"1185 Nashville Hwy",
    "sg:city":"Lewisburg",
    "sg:classifiers":[
        {
            "category":"Government",
            "subcategory":"Office",
            "type":"Public Place"
        }
    ],
    "sg:phone":"+1 931 270 9183",
    "sg:postcode":"37091",
    "sg:province":"TN",
    "sg:tags":[
        "state",
        "inspection"
    ],
    "wof:name":"Housing Development Agency",
    "wof:placetype":"venue"
},
  "geometry": {"coordinates":[-86.77596699999999,35.465346],"type":"Point"}
}