{
  "type": "Feature",
  "properties": {
    "iso:country":"US",
    "sg:address":"180 Claude Matherly Rd",
    "sg:city":"Butler",
    "sg:classifiers":[
        {
            "category":"Autos & Motor Vehicles",
            "subcategory":"Automobile Sales",
            "type":"Retail Goods"
        },
        {
            "category":"Autos & Motor Vehicles",
            "subcategory":"Auto Supplies",
            "type":"Retail Goods"
        }
    ],
    "sg:phone":"+1 423 768 2742",
    "sg:postcode":"37640",
    "sg:province":"TN",
    "sg:tags":[
        "car",
        "used",
        "dealer"
    ],
    "wof:name":"Butler Auto Sales & Parts",
    "wof:placetype":"venue"
},
  "geometry": {"coordinates":[-82.012112,36.364357],"type":"Point"}
}