{
  "type": "Feature",
  "properties": {
    "iso:country":"US",
    "sg:address":"714 Shenandoah Dr",
    "sg:city":"Brentwood",
    "sg:classifiers":[
        {
            "category":"Building & Trades",
            "subcategory":"Construction",
            "type":"Services"
        }
    ],
    "sg:phone":"+1 615 376 2615",
    "sg:postcode":"37027",
    "sg:province":"TN",
    "sg:tags":[
        "house"
    ],
    "wof:name":"Archway Builders",
    "wof:placetype":"venue"
},
  "geometry": {"coordinates":[-86.776023,36.00993],"type":"Point"}
}