{
  "type": "Feature",
  "properties": {
    "addr:full":"308 Space Park S Nashville TN 37211",
    "addr:postcode":"37211",
    "addr:street":"S",
    "iso:country":"US",
    "sg:address":"308 Space Park S",
    "sg:city":"Nashville",
    "sg:classifiers":[
        {
            "category":"Food & Beverages",
            "subcategory":"Specialty",
            "type":"Retail Goods"
        }
    ],
    "sg:phone":"+1 615 834 1623",
    "sg:postcode":"37211",
    "sg:province":"TN",
    "sg:tags":[
        "bulk",
        "water",
        "company",
        "sales",
        "direct"
    ],
    "sg:website":"www.tylermountainwater.com",
    "wof:name":"Tyler Mountain Spring Water",
    "wof:placetype":"venue"
},
  "geometry": {"coordinates":[-86.706461,36.097957],"type":"Point"}
}