{
  "type": "Feature",
  "properties": {
    "addr:full":"238 Fairview Rd Dickson TN 37055",
    "addr:housenumber":"238",
    "addr:postcode":"37055",
    "addr:street":"Fairview Rd",
    "iso:country":"US",
    "sg:address":"238 Fairview Rd",
    "sg:city":"Dickson",
    "sg:classifiers":[
        {
            "category":"Manufacturing",
            "subcategory":"Chemicals & Compounds",
            "type":"Manufacturing & Wholesale Goods"
        }
    ],
    "sg:phone":"+1 615 740 1020",
    "sg:postcode":"37055",
    "sg:province":"TN",
    "sg:tags":[
        "lotion"
    ],
    "wof:name":"Alice Inc",
    "wof:placetype":"venue"
},
  "geometry": {"coordinates":[-87.338382,36.111792],"type":"Point"}
}