{
  "type": "Feature",
  "properties": {
    "addr:full":"124 Trace Dr Goodlettsville TN 37072",
    "addr:housenumber":"124",
    "addr:postcode":"37072",
    "addr:street":"Trace Dr",
    "iso:country":"US",
    "sg:address":"124 Trace Dr",
    "sg:city":"Goodlettsville",
    "sg:classifiers":[
        {
            "category":"Professional",
            "type":"Services"
        }
    ],
    "sg:phone":"+1 615 859 7267",
    "sg:postcode":"37072",
    "sg:province":"TN",
    "wof:name":"Toni J Lewis",
    "wof:placetype":"venue"
},
  "geometry": {"coordinates":[-86.725105,36.361376],"type":"Point"}
}