{
  "type": "Feature",
  "properties": {
    "iso:country":"US",
    "sg:address":"308 W 45th St",
    "sg:city":"Chattanooga",
    "sg:classifiers":[
        {
            "category":"Utilities",
            "subcategory":"Refuse",
            "type":"Services"
        }
    ],
    "sg:phone":"+1 423 825 6091",
    "sg:postcode":"37410",
    "sg:province":"TN",
    "sg:tags":[
        "system"
    ],
    "wof:name":"Clay Charles W",
    "wof:placetype":"venue"
},
  "geometry": {"coordinates":[-85.317587,35.001374],"type":"Point"}
}