{
  "type": "Feature",
  "properties": {
    "addr:full":"425 Downs Blvd Franklin TN 37064",
    "addr:housenumber":"425",
    "addr:postcode":"37064",
    "addr:street":"Downs Blvd",
    "iso:country":"US",
    "sg:address":"425 Downs Blvd",
    "sg:city":"Franklin",
    "sg:classifiers":[
        {
            "category":"Real Estate",
            "subcategory":"Architect",
            "type":"Services"
        }
    ],
    "sg:phone":"+1 615 236 9000",
    "sg:postcode":"37064",
    "sg:province":"TN",
    "sg:tags":[
        "building",
        "construction"
    ],
    "sg:website":"www.civilconstructors.com",
    "wof:name":"Civil Constructors Inc",
    "wof:placetype":"venue"
},
  "geometry": {"coordinates":[-86.882929,35.908153],"type":"Point"}
}