{
  "type": "Feature",
  "properties": {
    "addr:full":"979 E 3rd St Chattanooga TN 37404",
    "addr:housenumber":"979",
    "addr:postcode":"37404",
    "addr:street":"E 3Rd St",
    "iso:country":"US",
    "sg:address":"979 E 3rd St",
    "sg:city":"Chattanooga",
    "sg:classifiers":[
        {
            "category":"Health Services",
            "subcategory":"Doctor",
            "type":"Services"
        }
    ],
    "sg:phone":"+1 423 267 5677",
    "sg:postcode":"37404",
    "sg:province":"TN",
    "sg:tags":[
        "medical"
    ],
    "wof:name":"Michael W Goodman MD",
    "wof:placetype":"venue"
},
  "geometry": {"coordinates":[-85.291888,35.04827],"type":"Point"}
}