{
  "type": "Feature",
  "properties": {
    "iso:country":"US",
    "sg:address":"207 Wayne St",
    "sg:city":"Columbia",
    "sg:classifiers":[
        {
            "category":"Retail",
            "subcategory":"Auto Repair",
            "type":"Services"
        }
    ],
    "sg:phone":"+1 931 840 0056",
    "sg:postcode":"38401",
    "sg:province":"TN",
    "sg:tags":[
        "transmission"
    ],
    "wof:name":"Better Bilt Trnsmssions AC Svc",
    "wof:placetype":"venue"
},
  "geometry": {"coordinates":[-87.03595300000001,35.592538],"type":"Point"}
}