{
  "type": "Feature",
  "properties": {
    "iso:country":"US",
    "sg:address":"6326 Carney Rd",
    "sg:city":"Whites Creek",
    "sg:classifiers":[
        {
            "category":"Organizations",
            "subcategory":"Religious Organization",
            "type":"Services"
        }
    ],
    "sg:phone":"+1 615 299 9654",
    "sg:postcode":"37189",
    "sg:province":"TN",
    "sg:tags":[
        "church"
    ],
    "wof:name":"Oakland Free Will Baptist C Hu",
    "wof:placetype":"venue"
},
  "geometry": {"coordinates":[-86.876107,36.273929],"type":"Point"}
}