{
  "type": "Feature",
  "properties": {
    "addr:full":"3401 State Hwy 81 S Jonesborough TN 37659",
    "addr:housenumber":"3401",
    "addr:postcode":"37659",
    "addr:street":"State Hwy 81 S",
    "iso:country":"US",
    "sg:address":"3401 State Hwy 81 S",
    "sg:city":"Jonesborough",
    "sg:classifiers":[
        {
            "category":"Food & Beverages",
            "subcategory":"Groceries & Convenience Stores",
            "type":"Retail Goods"
        }
    ],
    "sg:phone":"+1 423 753 4324",
    "sg:postcode":"37659",
    "sg:province":"TN",
    "sg:tags":[
        "grocer"
    ],
    "wof:name":"Crossroads Country Store",
    "wof:placetype":"venue"
},
  "geometry": {"coordinates":[-82.47006399999999,36.203971],"type":"Point"}
}