{
  "type": "Feature",
  "properties": {
    "iso:country":"US",
    "sg:address":"201 E Main St",
    "sg:city":"Woodbury",
    "sg:classifiers":[
        {
            "category":"Professional",
            "type":"Services"
        },
        {
            "category":"Retail",
            "subcategory":"Auto Repair",
            "type":"Services"
        }
    ],
    "sg:phone":"+1 615 563 6732",
    "sg:postcode":"37190",
    "sg:province":"TN",
    "sg:tags":[
        "automotive",
        "establishment"
    ],
    "wof:name":"Grizzle's Place",
    "wof:placetype":"venue"
},
  "geometry": {"coordinates":[-86.067066,35.827429],"type":"Point"}
}