{
  "type": "Feature",
  "properties": {
    "iso:country":"US",
    "sg:address":"5030 Georgetown Rd NW",
    "sg:city":"Cleveland",
    "sg:classifiers":[
        {
            "category":"Shopping",
            "subcategory":"Pharmacy",
            "type":"Retail Goods"
        }
    ],
    "sg:phone":"+1 423 472 5548",
    "sg:postcode":"37312",
    "sg:province":"TN",
    "wof:name":"Medi Mart Pharmacy",
    "wof:placetype":"venue"
},
  "geometry": {"coordinates":[-84.88420000000001,35.229362],"type":"Point"}
}