{
  "type": "Feature",
  "properties": {
    "addr:full":"6902 Middle Valley Rd Hixson TN 37343",
    "addr:housenumber":"6902",
    "addr:postcode":"37343",
    "addr:street":"Middle Valley Rd",
    "iso:country":"US",
    "sg:address":"6902 Middle Valley Rd",
    "sg:city":"Hixson",
    "sg:classifiers":[
        {
            "category":"Autos & Motor Vehicles",
            "subcategory":"Fuel & Gas Station",
            "type":"Retail Goods"
        }
    ],
    "sg:phone":"+1 423 842 0063",
    "sg:postcode":"37343",
    "sg:province":"TN",
    "sg:tags":[
        "oil"
    ],
    "wof:name":"Spur Market",
    "wof:placetype":"venue"
},
  "geometry": {"coordinates":[-85.20901499999999,35.168433],"type":"Point"}
}