{
  "type": "Feature",
  "properties": {
    "iso:country":"US",
    "sg:address":"535 Shute Ln",
    "sg:city":"Hendersonville",
    "sg:classifiers":[
        {
            "category":"Retail",
            "subcategory":"Funeral Services",
            "type":"Services"
        }
    ],
    "sg:phone":"+1 615 889 0361",
    "sg:postcode":"37075",
    "sg:province":"TN",
    "sg:tags":[
        "director"
    ],
    "wof:name":"Hermitage Funeral Home",
    "wof:placetype":"venue"
},
  "geometry": {"coordinates":[-86.533649,36.326382],"type":"Point"}
}