{
  "type": "Feature",
  "properties": {
    "iso:country":"US",
    "sg:address":"1500 Lyndhurst Dr",
    "sg:city":"Chattanooga",
    "sg:classifiers":[
        {
            "category":"Professional",
            "subcategory":"Lawyer & Legal Services",
            "type":"Services"
        }
    ],
    "sg:phone":"+1 423 265 8851",
    "sg:postcode":"37405",
    "sg:province":"TN",
    "wof:name":"Andrew L Berke",
    "wof:placetype":"venue"
},
  "geometry": {"coordinates":[-85.287432,35.069117],"type":"Point"}
}