{
  "type": "Feature",
  "properties": {
    "iso:country":"US",
    "sg:address":"3441 Dickerson Pike",
    "sg:city":"Nashville",
    "sg:classifiers":[
        {
            "category":"Health Services",
            "subcategory":"Hospital",
            "type":"Services"
        }
    ],
    "sg:phone":"+1 615 769 2000",
    "sg:postcode":"37207",
    "sg:province":"TN",
    "sg:tags":[
        "general"
    ],
    "sg:website":"www.tristarhealth.com",
    "wof:name":"Skyline Medical Center",
    "wof:placetype":"venue"
},
  "geometry": {"coordinates":[-86.757267,36.241272],"type":"Point"}
}