{
  "type": "Feature",
  "properties": {
    "addr:full":"898 N Hwy 45 W Union City TN 38261",
    "addr:housenumber":"898",
    "addr:postcode":"38261",
    "addr:street":"N Hwy 45 W",
    "iso:country":"US",
    "sg:address":"898 N Hwy 45 W",
    "sg:city":"Union City",
    "sg:classifiers":[
        {
            "category":"Manufacturing",
            "subcategory":"Metals",
            "type":"Manufacturing & Wholesale Goods"
        }
    ],
    "sg:phone":"+1 731 536 6473",
    "sg:postcode":"38261",
    "sg:province":"TN",
    "sg:tags":[
        "die",
        "tool",
        "mfg"
    ],
    "wof:name":"G & H Tool & Die Inc",
    "wof:placetype":"venue"
},
  "geometry": {"coordinates":[-89.06706,36.355851],"type":"Point"}
}