{
  "type": "Feature",
  "properties": {
    "iso:country":"US",
    "sg:address":"818 18th Ave S",
    "sg:city":"Nashville",
    "sg:classifiers":[
        {
            "category":"Professional",
            "subcategory":"Management & Consulting",
            "type":"Services"
        }
    ],
    "sg:phone":"+1 615 851 9541",
    "sg:postcode":"37203",
    "sg:province":"TN",
    "wof:name":"William B Fletcher Consulting",
    "wof:placetype":"venue"
},
  "geometry": {"coordinates":[-86.79466499999999,36.148927],"type":"Point"}
}