{
  "type": "Feature",
  "properties": {
    "iso:country":"US",
    "sg:address":"5517 Charlotte Pike",
    "sg:city":"Nashville",
    "sg:classifiers":[
        {
            "category":"Insurance",
            "subcategory":"Hazard Insurance",
            "type":"Services"
        },
        {
            "category":"Insurance",
            "subcategory":"Insurance Agent",
            "type":"Services"
        },
        {
            "category":"Insurance",
            "subcategory":"Life Insurance",
            "type":"Services"
        }
    ],
    "sg:phone":"+1 615 852 7910",
    "sg:postcode":"37209",
    "sg:province":"TN",
    "sg:tags":[
        "auto"
    ],
    "sg:website":"http://allstateagencies.com/roycewilliams/Welcome/?cid=OTC-Southern-Club-Blue-iYP094443yp&att=roycewilliams",
    "wof:name":"Royce Williams - Allstate Insurance Company",
    "wof:placetype":"venue"
},
  "geometry": {"coordinates":[-86.85587700000001,36.150659],"type":"Point"}
}