{
  "type": "Feature",
  "properties": {
    "iso:country":"US",
    "sg:address":"2624 Ashport Rd",
    "sg:city":"Jackson",
    "sg:classifiers":[
        {
            "category":"Organizations",
            "subcategory":"Religious Organization",
            "type":"Services"
        }
    ],
    "sg:phone":"+1 731 422 5246",
    "sg:postcode":"38305",
    "sg:province":"TN",
    "wof:name":"Salem CME Church",
    "wof:placetype":"venue"
},
  "geometry": {"coordinates":[-88.744895,35.724226],"type":"Point"}
}