{
  "type": "Feature",
  "properties": {
    "iso:country":"US",
    "sg:address":"3138 Antioch Rd",
    "sg:city":"Johnson City",
    "sg:classifiers":[
        {
            "category":"Shopping",
            "subcategory":"Gifts & Souvenirs",
            "type":"Retail Goods"
        }
    ],
    "sg:phone":"+1 423 232 7027",
    "sg:postcode":"37604",
    "sg:province":"TN",
    "wof:name":"Dakotas Gift Baskets",
    "wof:placetype":"venue"
},
  "geometry": {"coordinates":[-82.40916900000001,36.282834],"type":"Point"}
}