{
  "type": "Feature",
  "properties": {
    "addr:full":"2606 W Main St Union City TN 38261",
    "addr:housenumber":"2606",
    "addr:postcode":"38261",
    "addr:street":"W Main St",
    "iso:country":"US",
    "sg:address":"2606 W Main St",
    "sg:city":"Union City",
    "sg:classifiers":[
        {
            "category":"Food & Beverages",
            "subcategory":"Groceries & Convenience Stores",
            "type":"Retail Goods"
        }
    ],
    "sg:phone":"+1 731 885 5353",
    "sg:postcode":"38261",
    "sg:province":"TN",
    "wof:name":"Market Place",
    "wof:placetype":"venue"
},
  "geometry": {"coordinates":[-89.086916,36.434696],"type":"Point"}
}