{
  "type": "Feature",
  "properties": {
    "iso:country":"US",
    "sg:address":"1 Experiment Station Ln",
    "sg:city":"Columbia",
    "sg:classifiers":[
        {
            "category":"Health Services",
            "subcategory":"Chiropractor",
            "type":"Services"
        }
    ],
    "sg:phone":"+1 931 388 6437",
    "sg:postcode":"38401",
    "sg:province":"TN",
    "wof:name":"Columbia Chiropractic Hlth Ctr",
    "wof:placetype":"venue"
},
  "geometry": {"coordinates":[-87.06831099999999,35.605001],"type":"Point"}
}