{
  "type": "Feature",
  "properties": {
    "addr:full":"650 E Old Hickory Blvd Madison TN 37115",
    "addr:housenumber":"650",
    "addr:postcode":"37115",
    "addr:street":"E Old Hickory Blvd",
    "iso:country":"US",
    "sg:address":"650 E Old Hickory Blvd",
    "sg:city":"Madison",
    "sg:classifiers":[
        {
            "category":"Retail",
            "subcategory":"Auto Repair",
            "type":"Services"
        }
    ],
    "sg:phone":"+1 615 865 5404",
    "sg:postcode":"37115",
    "sg:province":"TN",
    "sg:tags":[
        "body",
        "automobile",
        "painting",
        "repairing"
    ],
    "wof:name":"Hoffman's Body Shop Inc",
    "wof:placetype":"venue"
},
  "geometry": {"coordinates":[-86.697639,36.26329],"type":"Point"}
}