{
  "type": "Feature",
  "properties": {
    "iso:country":"US",
    "sg:address":"316 Mystic Hill Dr",
    "sg:city":"Goodlettsville",
    "sg:classifiers":[
        {
            "category":"Building & Trades",
            "subcategory":"Construction",
            "type":"Services"
        }
    ],
    "sg:phone":"+1 615 859 6112",
    "sg:postcode":"37072",
    "sg:province":"TN",
    "sg:tags":[
        "hanging",
        "contractor"
    ],
    "wof:name":"W J Miller Painting Company",
    "wof:placetype":"venue"
},
  "geometry": {"coordinates":[-86.730559,36.338078],"type":"Point"}
}