{
  "type": "Feature",
  "properties": {
    "iso:country":"US",
    "sg:address":"117 Marina Dr NW",
    "sg:city":"Charleston",
    "sg:classifiers":[
        {
            "category":"Building & Trades",
            "subcategory":"Construction",
            "type":"Services"
        }
    ],
    "sg:phone":"+1 423 336 1991",
    "sg:postcode":"37310",
    "sg:province":"TN",
    "sg:tags":[
        "designer",
        "marine",
        "contractor"
    ],
    "wof:name":"Boatman Marine Repair",
    "wof:placetype":"venue"
},
  "geometry": {"coordinates":[-84.83493199999999,35.326671],"type":"Point"}
}