{
  "type": "Feature",
  "properties": {
    "iso:country":"US",
    "sg:address":"1511 Clifton Ln",
    "sg:city":"Nashville",
    "sg:classifiers":[
        {
            "category":"Professional",
            "subcategory":"Computer Services",
            "type":"Services"
        }
    ],
    "sg:phone":"+1 615 460 7515",
    "sg:postcode":"37215",
    "sg:province":"TN",
    "sg:tags":[
        "design",
        "system"
    ],
    "wof:name":"Pulley Cad Service",
    "wof:placetype":"venue"
},
  "geometry": {"coordinates":[-86.793936,36.114135],"type":"Point"}
}