{
  "type": "Feature",
  "properties": {
    "iso:country":"US",
    "sg:address":"4311 Springwind Rd",
    "sg:city":"Memphis",
    "sg:classifiers":[
        {
            "category":"Building & Trades",
            "subcategory":"Construction",
            "type":"Services"
        }
    ],
    "sg:phone":"+1 901 864 2929",
    "sg:postcode":"38141",
    "sg:province":"TN",
    "sg:tags":[
        "home",
        "improvement"
    ],
    "wof:name":"Hicks Advanced Home Imprvmt",
    "wof:placetype":"venue"
},
  "geometry": {"coordinates":[-89.85805999999999,35.030909],"type":"Point"}
}