{
  "type": "Feature",
  "properties": {
    "iso:country":"US",
    "sg:address":"42 Grindstone Ests",
    "sg:city":"Ooltewah",
    "sg:classifiers":[
        {
            "category":"Farming",
            "subcategory":"Farm",
            "type":"Manufacturing & Wholesale Goods"
        }
    ],
    "sg:phone":"+1 423 396 2886",
    "sg:postcode":"37363",
    "sg:province":"TN",
    "sg:tags":[
        "crop",
        "general"
    ],
    "wof:name":"Grindstone Estates Inc",
    "wof:placetype":"venue"
},
  "geometry": {"coordinates":[-85.02950300000001,35.063008],"type":"Point"}
}