{
  "type": "Feature",
  "properties": {
    "addr:full":"231 Serena Dr Hixson TN 37343",
    "addr:housenumber":"231",
    "addr:postcode":"37343",
    "addr:street":"Serena Dr",
    "iso:country":"US",
    "sg:address":"231 Serena Dr",
    "sg:city":"Hixson",
    "sg:classifiers":[
        {
            "category":"Building & Trades",
            "subcategory":"Landscaping Services",
            "type":"Services"
        }
    ],
    "sg:phone":"+1 423 842 9901",
    "sg:postcode":"37343",
    "sg:province":"TN",
    "wof:name":"Landscape Creations",
    "wof:placetype":"venue"
},
  "geometry": {"coordinates":[-85.174791,35.182679],"type":"Point"}
}