{
  "type": "Feature",
  "properties": {
    "addr:full":"218 Northgate Mall Chattanooga TN 37415",
    "addr:housenumber":"218",
    "addr:postcode":"37415",
    "addr:street":"Northgate Mall",
    "iso:country":"US",
    "sg:address":"218 Northgate Mall",
    "sg:city":"Chattanooga",
    "sg:classifiers":[
        {
            "category":"Shopping",
            "subcategory":"Clothing, Apparel, & Fashions",
            "type":"Retail Goods"
        }
    ],
    "sg:phone":"+1 423 877 2992",
    "sg:postcode":"37415",
    "sg:province":"TN",
    "sg:tags":[
        "sportswear"
    ],
    "wof:name":"Sports Stop",
    "wof:placetype":"venue"
},
  "geometry": {"coordinates":[-85.244643,35.137228],"type":"Point"}
}