{
  "type": "Feature",
  "properties": {
    "iso:country":"US",
    "sg:address":"3114 Kinross Ave",
    "sg:city":"Nashville",
    "sg:classifiers":[
        {
            "category":"Arts & Performance",
            "subcategory":"Theater",
            "type":"Entertainment"
        }
    ],
    "sg:phone":"+1 615 333 2202",
    "sg:postcode":"37211",
    "sg:province":"TN",
    "sg:tags":[
        "group"
    ],
    "wof:name":"Cpr Entertainment",
    "wof:placetype":"venue"
},
  "geometry": {"coordinates":[-86.733239,36.104713],"type":"Point"}
}