{
  "type": "Feature",
  "properties": {
    "iso:country":"US",
    "sg:address":"117 28th Ave N",
    "sg:city":"Nashville",
    "sg:classifiers":[
        {
            "category":"Health Services",
            "subcategory":"Doctor",
            "type":"Services"
        }
    ],
    "sg:phone":"+1 615 320 6020",
    "sg:postcode":"37203",
    "sg:province":"TN",
    "sg:tags":[
        "physician",
        "surgeon",
        "medical"
    ],
    "wof:name":"Jimmi H Logan MD",
    "wof:placetype":"venue"
},
  "geometry": {"coordinates":[-86.813214,36.146016],"type":"Point"}
}