{
  "type": "Feature",
  "properties": {
    "iso:country":"US",
    "sg:address":"792 W Main St",
    "sg:city":"Hendersonville",
    "sg:classifiers":[
        {
            "category":"Autos & Motor Vehicles",
            "subcategory":"Automobile Sales",
            "type":"Retail Goods"
        }
    ],
    "sg:phone":"+1 615 264 4636",
    "sg:postcode":"37075",
    "sg:province":"TN",
    "sg:tags":[
        "used"
    ],
    "wof:name":"Schaell Motors",
    "wof:placetype":"venue"
},
  "geometry": {"coordinates":[-86.644875,36.303558],"type":"Point"}
}