{
  "type": "Feature",
  "properties": {
    "iso:country":"US",
    "sg:address":"4704 Meredith Rd",
    "sg:city":"Knoxville",
    "sg:classifiers":[
        {
            "category":"Building & Trades",
            "subcategory":"Landscaping Services",
            "type":"Services"
        }
    ],
    "sg:phone":"+1 865 938 3227",
    "sg:postcode":"37921",
    "sg:province":"TN",
    "wof:name":"Holston Nursery & Lawn Care",
    "wof:placetype":"venue"
},
  "geometry": {"coordinates":[-84.06197299999999,35.995847],"type":"Point"}
}