{
  "type": "Feature",
  "properties": {
    "iso:country":"US",
    "sg:address":"13344 Lebanon Rd",
    "sg:city":"Mount Juliet",
    "sg:classifiers":[
        {
            "category":"Shopping",
            "subcategory":"Computers & Home Electronics",
            "type":"Retail Goods"
        }
    ],
    "sg:phone":"+1 615 758 5513",
    "sg:postcode":"37122",
    "sg:province":"TN",
    "wof:name":"Costa Entps Electronic Sls Ser",
    "wof:placetype":"venue"
},
  "geometry": {"coordinates":[-86.548207,36.222706],"type":"Point"}
}