{
  "type": "Feature",
  "properties": {
    "iso:country":"US",
    "sg:address":"100 N Main St",
    "sg:city":"Goodlettsville",
    "sg:classifiers":[
        {
            "category":"Professional",
            "subcategory":"Accounting & Tax Preparation",
            "type":"Services"
        }
    ],
    "sg:phone":"+1 615 851 5555",
    "sg:postcode":"37072",
    "sg:province":"TN",
    "sg:tags":[
        "consultant"
    ],
    "wof:name":"Salt Group",
    "wof:placetype":"venue"
},
  "geometry": {"coordinates":[-86.713422,36.323546],"type":"Point"}
}