{
  "type": "Feature",
  "properties": {
    "iso:country":"US",
    "sg:address":"4220 Nolensville Pike",
    "sg:city":"Nashville",
    "sg:classifiers":[
        {
            "category":"Professional",
            "subcategory":"Lawyer & Legal Services",
            "type":"Services"
        }
    ],
    "sg:phone":"+1 615 834 4300",
    "sg:postcode":"37211",
    "sg:province":"TN",
    "sg:tags":[
        "attorney"
    ],
    "wof:name":"Martha Child",
    "wof:placetype":"venue"
},
  "geometry": {"coordinates":[-86.724959,36.075516],"type":"Point"}
}