{
  "type": "Feature",
  "properties": {
    "iso:country":"US",
    "sg:address":"111 Old Lodge Ln",
    "sg:city":"Murfreesboro",
    "sg:classifiers":[
        {
            "category":"Government",
            "subcategory":"Office",
            "type":"Public Place"
        }
    ],
    "sg:phone":"+1 615 893 9501",
    "sg:postcode":"37129",
    "sg:province":"TN",
    "sg:tags":[
        "federal"
    ],
    "sg:website":"www.doi.gov",
    "wof:name":"US Interior Dept",
    "wof:placetype":"venue"
},
  "geometry": {"coordinates":[-86.433819,35.882504],"type":"Point"}
}