{
  "type": "Feature",
  "properties": {
    "addr:full":"5003 Market Pl Mt Juliet TN 37122",
    "addr:housenumber":"5003",
    "addr:postcode":"37122",
    "addr:street":"Market Pl",
    "iso:country":"US",
    "sg:address":"5003 Market Pl",
    "sg:city":"Mt Juliet",
    "sg:classifiers":[
        {
            "category":"Recreation",
            "type":"Entertainment"
        }
    ],
    "sg:phone":"+1 615 758 4791",
    "sg:postcode":"37122",
    "sg:province":"TN",
    "sg:tags":[
        "instruction",
        "gymnastic"
    ],
    "wof:name":"Universal Gymnastics Main",
    "wof:placetype":"venue"
},
  "geometry": {"coordinates":[-86.536303,36.233915],"type":"Point"}
}