{
  "type": "Feature",
  "properties": {
    "iso:country":"US",
    "sg:address":"5818 W Fox Bend Cove",
    "sg:city":"Memphis",
    "sg:classifiers":[
        {
            "category":"Communications",
            "type":"Services"
        }
    ],
    "sg:phone":"+1 901 360 9734",
    "sg:postcode":"38115",
    "sg:province":"TN",
    "sg:tags":[
        "communication"
    ],
    "wof:name":"Kendell Communication Service",
    "wof:placetype":"venue"
},
  "geometry": {"coordinates":[-89.869528,35.05504],"type":"Point"}
}