{
  "type": "Feature",
  "properties": {
    "iso:country":"US",
    "sg:address":"4422 Dayton Blvd",
    "sg:city":"Chattanooga",
    "sg:classifiers":[
        {
            "category":"Shopping",
            "subcategory":"Shoes",
            "type":"Retail Goods"
        }
    ],
    "sg:phone":"+1 423 875 8484",
    "sg:postcode":"37415",
    "sg:province":"TN",
    "wof:name":"Feet and Footz",
    "wof:placetype":"venue"
},
  "geometry": {"coordinates":[-85.28394900000001,35.128431],"type":"Point"}
}