{
  "type": "Feature",
  "properties": {
    "iso:country":"US",
    "sg:address":"2856 Wilma Rudolph Blvd",
    "sg:city":"Clarksville",
    "sg:classifiers":[
        {
            "category":"Banks & Credit Unions",
            "subcategory":"Bank",
            "type":"Services"
        }
    ],
    "sg:phone":"+1 931 552 7991",
    "sg:postcode":"37040",
    "sg:province":"TN",
    "sg:tags":[
        "financing"
    ],
    "wof:name":"Citi Financial",
    "wof:placetype":"venue"
},
  "geometry": {"coordinates":[-87.29244799999999,36.589796],"type":"Point"}
}