{
  "type": "Feature",
  "properties": {
    "iso:country":"US",
    "sg:address":"3236 E Stone Dr",
    "sg:city":"Kingsport",
    "sg:classifiers":[
        {
            "category":"Freight",
            "type":"Transportation"
        }
    ],
    "sg:phone":"+1 423 288 3821",
    "sg:postcode":"37660",
    "sg:province":"TN",
    "sg:tags":[
        "trucking"
    ],
    "wof:name":"West Side Transport Inc",
    "wof:placetype":"venue"
},
  "geometry": {"coordinates":[-82.461687,36.562574],"type":"Point"}
}