{
  "type": "Feature",
  "properties": {
    "iso:country":"US",
    "sg:address":"3411 Sweeney Hollow Rd",
    "sg:city":"Franklin",
    "sg:classifiers":[
        {
            "category":"Professional",
            "subcategory":"Business Services",
            "type":"Services"
        }
    ],
    "sg:phone":"+1 615 794 5712",
    "sg:postcode":"37064",
    "sg:province":"TN",
    "wof:name":"Franklin Entertainment Group",
    "wof:placetype":"venue"
},
  "geometry": {"coordinates":[-87.010732,35.875576],"type":"Point"}
}