{
  "type": "Feature",
  "properties": {
    "iso:country":"US",
    "sg:address":"2502 Winford Ave",
    "sg:city":"Nashville",
    "sg:classifiers":[
        {
            "category":"Retail",
            "subcategory":"Repair Shop",
            "type":"Services"
        }
    ],
    "sg:phone":"+1 615 259 2444",
    "sg:postcode":"37211",
    "sg:province":"TN",
    "sg:tags":[
        "ironwork"
    ],
    "wof:name":"Dillon's Welding Inc",
    "wof:placetype":"venue"
},
  "geometry": {"coordinates":[-86.752877,36.115231],"type":"Point"}
}