{
  "type": "Feature",
  "properties": {
    "iso:country":"US",
    "sg:address":"6038 Beauvoir Dr",
    "sg:city":"Millington",
    "sg:classifiers":[
        {
            "category":"Organizations",
            "subcategory":"Religious Organization",
            "type":"Services"
        }
    ],
    "sg:phone":"+1 901 873 0673",
    "sg:postcode":"38053",
    "sg:province":"TN",
    "wof:name":"Victory Word Ftih Chrch Otrach",
    "wof:placetype":"venue"
},
  "geometry": {"coordinates":[-89.912826,35.290654],"type":"Point"}
}