{
  "type": "Feature",
  "properties": {
    "iso:country":"US",
    "sg:address":"2545 Spottswood Ave",
    "sg:city":"Memphis",
    "sg:classifiers":[
        {
            "category":"Building & Trades",
            "subcategory":"Construction",
            "type":"Services"
        }
    ],
    "sg:phone":"+1 901 454 1598",
    "sg:postcode":"38114",
    "sg:province":"TN",
    "sg:tags":[
        "contractor"
    ],
    "wof:name":"Hurts Contract",
    "wof:placetype":"venue"
},
  "geometry": {"coordinates":[-89.97792699999999,35.114177],"type":"Point"}
}