{
  "type": "Feature",
  "properties": {
    "iso:country":"US",
    "sg:address":"8514 Dunhill Ln",
    "sg:city":"Hixson",
    "sg:classifiers":[
        {
            "category":"Professional",
            "subcategory":"Business Services",
            "type":"Services"
        }
    ],
    "sg:phone":"+1 423 842 4363",
    "sg:postcode":"37343",
    "sg:province":"TN",
    "wof:name":"Science Fiction and Fantasty",
    "wof:placetype":"venue"
},
  "geometry": {"coordinates":[-85.19825299999999,35.202176],"type":"Point"}
}