{
  "type": "Feature",
  "properties": {
    "addr:full":"1601 Francis Rd NW Knoxville TN 37909",
    "addr:housenumber":"1601",
    "addr:postcode":"37909",
    "addr:street":"Francis Rd Nw",
    "iso:country":"US",
    "sg:address":"1601 Francis Rd NW",
    "sg:city":"Knoxville",
    "sg:classifiers":[
        {
            "category":"Professional",
            "subcategory":"Computer Services",
            "type":"Services"
        }
    ],
    "sg:phone":"+1 865 691 3009",
    "sg:postcode":"37909",
    "sg:province":"TN",
    "wof:name":"Slenny's Machine",
    "wof:placetype":"venue"
},
  "geometry": {"coordinates":[-84.03528900000001,35.956483],"type":"Point"}
}