{
  "type": "Feature",
  "properties": {
    "iso:country":"US",
    "sg:address":"519 Donelson Pike",
    "sg:city":"Nashville",
    "sg:classifiers":[
        {
            "category":"Professional",
            "subcategory":"Employment Agencies",
            "type":"Services"
        }
    ],
    "sg:phone":"+1 615 872 9600",
    "sg:postcode":"37214",
    "sg:province":"TN",
    "sg:website":"http://www.adecco.com",
    "wof:name":"Adecco Employment Services",
    "wof:placetype":"venue"
},
  "geometry": {"coordinates":[-86.666298,36.148781],"type":"Point"}
}