{
  "type": "Feature",
  "properties": {
    "iso:country":"US",
    "sg:address":"1309 Ridgeway Cir",
    "sg:city":"Athens",
    "sg:classifiers":[
        {
            "category":"Communications",
            "type":"Services"
        }
    ],
    "sg:phone":"+1 423 745 8080",
    "sg:postcode":"37303",
    "sg:province":"TN",
    "sg:tags":[
        "communication"
    ],
    "wof:name":"Sliger Communications",
    "wof:placetype":"venue"
},
  "geometry": {"coordinates":[-84.613889,35.429776],"type":"Point"}
}