{
  "type": "Feature",
  "properties": {
    "iso:country":"US",
    "sg:address":"301 Market St E",
    "sg:city":"Fayetteville",
    "sg:classifiers":[
        {
            "category":"Social Services",
            "type":"Services"
        }
    ],
    "sg:phone":"+1 931 433 4081",
    "sg:postcode":"37334",
    "sg:province":"TN",
    "sg:tags":[
        "clinic",
        "specialty",
        "outpatient"
    ],
    "wof:name":"Vessell Vocational Services",
    "wof:placetype":"venue"
},
  "geometry": {"coordinates":[-86.56804700000001,35.151002],"type":"Point"}
}