{
  "type": "Feature",
  "properties": {
    "iso:country":"US",
    "sg:address":"5680 State Hwy 88",
    "sg:city":"Maury City",
    "sg:classifiers":[
        {
            "category":"Manufacturing",
            "subcategory":"Textiles",
            "type":"Manufacturing & Wholesale Goods"
        }
    ],
    "sg:phone":"+1 731 656 4320",
    "sg:postcode":"38040",
    "sg:province":"TN",
    "sg:tags":[
        "fabric"
    ],
    "wof:name":"Crockett Fabricating",
    "wof:placetype":"venue"
},
  "geometry": {"coordinates":[-89.48487799999999,35.907545],"type":"Point"}
}