{
  "type": "Feature",
  "properties": {
    "iso:country":"US",
    "sg:address":"4106 Elvis Presley Blvd",
    "sg:city":"Memphis",
    "sg:classifiers":[
        {
            "category":"Retail",
            "subcategory":"Laundry & Dry Cleaning",
            "type":"Services"
        }
    ],
    "sg:phone":"+1 901 398 0269",
    "sg:postcode":"38116",
    "sg:province":"TN",
    "sg:tags":[
        "cleaners"
    ],
    "wof:name":"Whitehaven Plaza 1 Hr Cleaners",
    "wof:placetype":"venue"
},
  "geometry": {"coordinates":[-90.025059,35.039473],"type":"Point"}
}