{
  "type": "Feature",
  "properties": {
    "iso:country":"US",
    "sg:address":"2608 Nolensville Pike",
    "sg:city":"Nashville",
    "sg:classifiers":[
        {
            "category":"Manufacturing",
            "subcategory":"Printing",
            "type":"Manufacturing & Wholesale Goods"
        }
    ],
    "sg:phone":"+1 615 832 1095",
    "sg:postcode":"37211",
    "sg:province":"TN",
    "sg:tags":[
        "newspaper"
    ],
    "wof:name":"Tennessee Latino",
    "wof:placetype":"venue"
},
  "geometry": {"coordinates":[-86.748183,36.116994],"type":"Point"}
}