{
  "type": "Feature",
  "properties": {
    "iso:country":"US",
    "sg:address":"758 W Lamar Alexander Pkwy",
    "sg:city":"Maryville",
    "sg:classifiers":[
        {
            "category":"Personal",
            "subcategory":"Barber",
            "type":"Services"
        }
    ],
    "sg:phone":"+1 865 983 8277",
    "sg:postcode":"37801",
    "sg:province":"TN",
    "wof:name":"Teffteller Barber Shop",
    "wof:placetype":"venue"
},
  "geometry": {"coordinates":[-83.984576,35.751631],"type":"Point"}
}