{
  "type": "Feature",
  "properties": {
    "iso:country":"US",
    "sg:address":"402 S Miles Ave",
    "sg:city":"Union City",
    "sg:classifiers":[
        {
            "category":"Organizations",
            "subcategory":"Religious Organization",
            "type":"Services"
        }
    ],
    "sg:phone":"+1 731 884 1133",
    "sg:postcode":"38261",
    "sg:province":"TN",
    "wof:name":"Greater Hope Baptist Church",
    "wof:placetype":"venue"
},
  "geometry": {"coordinates":[-89.04040999999999,36.421703],"type":"Point"}
}