{
  "type": "Feature",
  "properties": {
    "iso:country":"US",
    "sg:address":"1501 Huntsville Hwy",
    "sg:city":"Fayetteville",
    "sg:classifiers":[
        {
            "category":"Wholesale",
            "subcategory":"Toys & Hobbies",
            "type":"Manufacturing & Wholesale Goods"
        }
    ],
    "sg:phone":"+1 931 438 9284",
    "sg:postcode":"37334",
    "sg:province":"TN",
    "sg:tags":[
        "wholesaler"
    ],
    "wof:name":"Wholesale Supply L & S",
    "wof:placetype":"venue"
},
  "geometry": {"coordinates":[-86.566742,35.133074],"type":"Point"}
}