{
  "type": "Feature",
  "properties": {
    "iso:country":"US",
    "sg:address":"700 W Main St",
    "sg:city":"Byrdstown",
    "sg:classifiers":[
        {
            "category":"Insurance",
            "subcategory":"Insurance Agent",
            "type":"Services"
        }
    ],
    "sg:phone":"+1 931 864 3116",
    "sg:postcode":"38549",
    "sg:province":"TN",
    "sg:website":"www.keislinginsurance.com",
    "wof:name":"Keisling Insurance",
    "wof:placetype":"venue"
},
  "geometry": {"coordinates":[-85.143367,36.571779],"type":"Point"}
}