{
  "type": "Feature",
  "properties": {
    "iso:country":"US",
    "sg:address":"111 Penn Dr",
    "sg:city":"Trenton",
    "sg:classifiers":[
        {
            "category":"Building & Trades",
            "subcategory":"Construction",
            "type":"Services"
        }
    ],
    "sg:phone":"+1 731 855 0813",
    "sg:postcode":"38382",
    "sg:province":"TN",
    "sg:tags":[
        "downspouts",
        "gutter"
    ],
    "wof:name":"Dunn Rite Home Improvement",
    "wof:placetype":"venue"
},
  "geometry": {"coordinates":[-88.936032,35.95737],"type":"Point"}
}