{
  "type": "Feature",
  "properties": {
    "iso:country":"US",
    "sg:address":"1110 Parkway",
    "sg:city":"Gatlinburg",
    "sg:classifiers":[
        {
            "category":"Restaurant",
            "type":"Food & Drink"
        }
    ],
    "sg:phone":"+1 865 436 3800",
    "sg:postcode":"37738",
    "sg:province":"TN",
    "wof:name":"Peddler Restaurant The",
    "wof:placetype":"venue"
},
  "geometry": {"coordinates":[-83.521548,35.707744],"type":"Point"}
}