{
  "type": "Feature",
  "properties": {
    "iso:country":"US",
    "sg:address":"2432 Congress Pkwy NW",
    "sg:city":"Athens",
    "sg:classifiers":[
        {
            "category":"Food & Beverages",
            "subcategory":"Groceries & Convenience Stores",
            "type":"Retail Goods"
        }
    ],
    "sg:phone":"+1 423 746 0058",
    "sg:postcode":"37303",
    "sg:province":"TN",
    "wof:name":"Valley North",
    "wof:placetype":"venue"
},
  "geometry": {"coordinates":[-84.63803900000001,35.440038],"type":"Point"}
}