{
  "type": "Feature",
  "properties": {
    "addr:full":"1836 Cromwell Dr Nashville TN 37215",
    "addr:housenumber":"1836",
    "addr:postcode":"37215",
    "addr:street":"Cromwell Dr",
    "iso:country":"US",
    "sg:address":"1836 Cromwell Dr",
    "sg:city":"Nashville",
    "sg:classifiers":[
        {
            "category":"Professional",
            "subcategory":"Engineering",
            "type":"Services"
        }
    ],
    "sg:phone":"+1 615 309 9982",
    "sg:postcode":"37215",
    "sg:province":"TN",
    "sg:tags":[
        "engineer"
    ],
    "wof:name":"DGL Consulting",
    "wof:placetype":"venue"
},
  "geometry": {"coordinates":[-86.848725,36.050592],"type":"Point"}
}