{
  "type": "Feature",
  "properties": {
    "iso:country":"US",
    "sg:address":"6410 Flag Point Dr",
    "sg:city":"Ooltewah",
    "sg:classifiers":[
        {
            "category":"Building & Trades",
            "subcategory":"Construction",
            "type":"Services"
        }
    ],
    "sg:phone":"+1 423 238 9010",
    "sg:postcode":"37363",
    "sg:province":"TN",
    "sg:tags":[
        "residential"
    ],
    "wof:name":"Thorton Contracting",
    "wof:placetype":"venue"
},
  "geometry": {"coordinates":[-85.09560999999999,35.102157],"type":"Point"}
}