{
  "type": "Feature",
  "properties": {
    "addr:full":"2015 Grubb Rd Lenoir City TN 37771",
    "addr:housenumber":"2015",
    "addr:postcode":"37771",
    "addr:street":"Grubb Rd",
    "iso:country":"US",
    "sg:address":"2015 Grubb Rd",
    "sg:city":"Lenoir City",
    "sg:classifiers":[
        {
            "category":"Government",
            "subcategory":"Office",
            "type":"Public Place"
        }
    ],
    "sg:phone":"+1 865 986 2610",
    "sg:postcode":"37771",
    "sg:province":"TN",
    "sg:tags":[
        "federal"
    ],
    "wof:name":"US Army Corps Of Engineers",
    "wof:placetype":"venue"
},
  "geometry": {"coordinates":[-84.298709,35.872983],"type":"Point"}
}