{
  "type": "Feature",
  "properties": {
    "iso:country":"US",
    "sg:address":"703 Alcorn Dr",
    "sg:city":"Corinth",
    "sg:classifiers":[
        {
            "category":"Health Services",
            "subcategory":"Doctor",
            "type":"Services"
        }
    ],
    "sg:phone":"+1 662 286 2522",
    "sg:postcode":"38834",
    "sg:province":"TN",
    "sg:tags":[
        "physician",
        "surgeon"
    ],
    "wof:name":"Mathew B Johnson Jr MD",
    "wof:placetype":"venue"
},
  "geometry": {"coordinates":[-88.558707,34.935337],"type":"Point"}
}