{
  "type": "Feature",
  "properties": {
    "iso:country":"US",
    "sg:address":"2028 Duck Cove Dr",
    "sg:city":"Knoxville",
    "sg:classifiers":[
        {
            "category":"Professional",
            "subcategory":"Lawyer & Legal Services",
            "type":"Services"
        }
    ],
    "sg:phone":"+1 865 675 0678",
    "sg:postcode":"37922",
    "sg:province":"TN",
    "sg:tags":[
        "attorney",
        "bureau"
    ],
    "wof:name":"George Lambert Enterprises",
    "wof:placetype":"venue"
},
  "geometry": {"coordinates":[-84.165824,35.812508],"type":"Point"}
}