{
  "type": "Feature",
  "properties": {
    "iso:country":"US",
    "sg:address":"6215 Humphreys Blvd",
    "sg:city":"Memphis",
    "sg:classifiers":[
        {
            "category":"Health Services",
            "subcategory":"Doctor",
            "type":"Services"
        }
    ],
    "sg:phone":"+1 901 747 7001",
    "sg:postcode":"38120",
    "sg:province":"TN",
    "sg:tags":[
        "medical"
    ],
    "wof:name":"Michael P Berry MDPC",
    "wof:placetype":"venue"
},
  "geometry": {"coordinates":[-89.854752,35.129039],"type":"Point"}
}