{
  "type": "Feature",
  "properties": {
    "addr:full":"6094 Apple Tree Dr Memphis TN 38115",
    "addr:housenumber":"6094",
    "addr:postcode":"38115",
    "addr:street":"Apple Tree Dr",
    "iso:country":"US",
    "sg:address":"6094 Apple Tree Dr",
    "sg:city":"Memphis",
    "sg:classifiers":[
        {
            "category":"Organizations",
            "subcategory":"Professional Association",
            "type":"Services"
        }
    ],
    "sg:phone":"+1 901 366 9010",
    "sg:postcode":"38115",
    "sg:province":"TN",
    "wof:name":"Memphis Chapter Neca",
    "wof:placetype":"venue"
},
  "geometry": {"coordinates":[-89.861375,35.069003],"type":"Point"}
}