{
  "type": "Feature",
  "properties": {
    "iso:country":"US",
    "sg:address":"608 Melville Ave",
    "sg:city":"Chattanooga",
    "sg:classifiers":[
        {
            "category":"Professional",
            "type":"Services"
        }
    ],
    "sg:phone":"+1 423 622 2262",
    "sg:postcode":"37412",
    "sg:province":"TN",
    "wof:name":"Martha Hale",
    "wof:placetype":"venue"
},
  "geometry": {"coordinates":[-85.241309,35.007772],"type":"Point"}
}