{
  "type": "Feature",
  "properties": {
    "iso:country":"US",
    "sg:address":"3716 Burdan Cove",
    "sg:city":"Memphis",
    "sg:classifiers":[
        {
            "category":"Retail",
            "subcategory":"Auto Repair",
            "type":"Services"
        }
    ],
    "sg:phone":"+1 901 365 8598",
    "sg:postcode":"38118",
    "sg:province":"TN",
    "sg:tags":[
        "body"
    ],
    "wof:name":"Mobile Trim Team of Memphis",
    "wof:placetype":"venue"
},
  "geometry": {"coordinates":[-89.937129,35.043955],"type":"Point"}
}