{
  "type": "Feature",
  "properties": {
    "iso:country":"US",
    "sg:address":"3259 US Hwy 25E",
    "sg:city":"Tazewell",
    "sg:classifiers":[
        {
            "category":"Food & Beverages",
            "subcategory":"Groceries & Convenience Stores",
            "type":"Retail Goods"
        }
    ],
    "sg:phone":"+1 423 626 9136",
    "sg:postcode":"37879",
    "sg:province":"TN",
    "wof:name":"Get It N Go",
    "wof:placetype":"venue"
},
  "geometry": {"coordinates":[-83.59117999999999,36.491698],"type":"Point"}
}