{
  "type": "Feature",
  "properties": {
    "addr:full":"2208 Church St Culleoka TN 38451",
    "addr:housenumber":"2208",
    "addr:postcode":"38451",
    "addr:street":"Church St",
    "iso:country":"US",
    "sg:address":"2208 Church St",
    "sg:city":"Culleoka",
    "sg:classifiers":[
        {
            "category":"Personal",
            "subcategory":"Beauty Salon",
            "type":"Services"
        }
    ],
    "sg:phone":"+1 931 987 2543",
    "sg:postcode":"38451",
    "sg:province":"TN",
    "sg:tags":[
        "shop"
    ],
    "wof:name":"Looking Glass",
    "wof:placetype":"venue"
},
  "geometry": {"coordinates":[-86.983087,35.48205],"type":"Point"}
}