{
  "type": "Feature",
  "properties": {
    "iso:country":"US",
    "sg:address":"2011 Murphy Ave",
    "sg:city":"Nashville",
    "sg:classifiers":[
        {
            "category":"Health Services",
            "subcategory":"Doctor",
            "type":"Services"
        }
    ],
    "sg:phone":"+1 615 865 0360",
    "sg:postcode":"37203",
    "sg:province":"TN",
    "sg:tags":[
        "clinic",
        "medical"
    ],
    "wof:name":"Calvin J Channell MD",
    "wof:placetype":"venue"
},
  "geometry": {"coordinates":[-86.802955,36.156235],"type":"Point"}
}