{
  "type": "Feature",
  "properties": {
    "addr:full":"5000 American Way Memphis TN 38115",
    "addr:housenumber":"5000",
    "addr:postcode":"38115",
    "addr:street":"American Way",
    "iso:country":"US",
    "sg:address":"5000 American Way",
    "sg:city":"Memphis",
    "sg:classifiers":[
        {
            "category":"Restaurant",
            "type":"Food & Drink"
        }
    ],
    "sg:menulink":"http://www.allmenus.com/tn/memphis/140196-subway/menu/",
    "sg:phone":"+1 901 368 0934",
    "sg:postcode":"38115",
    "sg:province":"TN",
    "sg:tags":[
        "american",
        "sandwich"
    ],
    "wof:name":"Subway",
    "wof:placetype":"venue"
},
  "geometry": {"coordinates":[-89.894147,35.078664],"type":"Point"}
}