{
  "type": "Feature",
  "properties": {
    "iso:country":"US",
    "sg:address":"14111 Lillard Rd",
    "sg:city":"Soddy Daisy",
    "sg:classifiers":[
        {
            "category":"Organizations",
            "subcategory":"Religious Organization",
            "type":"Services"
        }
    ],
    "sg:phone":"+1 423 332 4117",
    "sg:postcode":"37379",
    "sg:province":"TN",
    "sg:tags":[
        "church"
    ],
    "wof:name":"Pleasant Hill AME Zion Church",
    "wof:placetype":"venue"
},
  "geometry": {"coordinates":[-85.08565900000001,35.337058],"type":"Point"}
}