{
  "type": "Feature",
  "properties": {
    "iso:country":"US",
    "sg:address":"3354 Perimeter Hill Dr",
    "sg:city":"Nashville",
    "sg:classifiers":[
        {
            "category":"Professional",
            "subcategory":"Engineering",
            "type":"Services"
        }
    ],
    "sg:phone":"+1 615 834 8300",
    "sg:postcode":"37211",
    "sg:province":"TN",
    "sg:tags":[
        "engineer"
    ],
    "wof:name":"Consolidated Technologies Inc",
    "wof:placetype":"venue"
},
  "geometry": {"coordinates":[-86.69402700000001,36.084746],"type":"Point"}
}