{
  "type": "Feature",
  "properties": {
    "addr:full":"3304 Charlotte Ave Nashville TN 37209",
    "addr:housenumber":"3304",
    "addr:postcode":"37209",
    "addr:street":"Charlotte Ave",
    "iso:country":"US",
    "sg:address":"3304 Charlotte Ave",
    "sg:city":"Nashville",
    "sg:classifiers":[
        {
            "category":"Professional",
            "subcategory":"Management & Consulting",
            "type":"Services"
        }
    ],
    "sg:phone":"+1 615 777 3300",
    "sg:postcode":"37209",
    "sg:province":"TN",
    "wof:name":"J Stein Publishers",
    "wof:placetype":"venue"
},
  "geometry": {"coordinates":[-86.825586,36.152862],"type":"Point"}
}