{
  "type": "Feature",
  "properties": {
    "addr:full":"79 Sunny Acres Dr Crossville TN 38555",
    "addr:housenumber":"79",
    "addr:postcode":"38555",
    "addr:street":"Sunny Acres Dr",
    "iso:country":"US",
    "sg:address":"79 Sunny Acres Dr",
    "sg:city":"Crossville",
    "sg:classifiers":[
        {
            "category":"Building & Trades",
            "subcategory":"Construction",
            "type":"Services"
        }
    ],
    "sg:phone":"+1 931 267 9275",
    "sg:postcode":"38555",
    "sg:province":"TN",
    "sg:tags":[
        "builder",
        "patio",
        "deck"
    ],
    "wof:name":"Anderson Home Improvements",
    "wof:placetype":"venue"
},
  "geometry": {"coordinates":[-84.920878,35.909712],"type":"Point"}
}