{
  "type": "Feature",
  "properties": {
    "iso:country":"US",
    "sg:address":"400 W Church St",
    "sg:city":"Greeneville",
    "sg:classifiers":[
        {
            "category":"Manufacturing",
            "subcategory":"Apparel",
            "type":"Manufacturing & Wholesale Goods"
        }
    ],
    "sg:phone":"+1 423 638 2881",
    "sg:postcode":"37745",
    "sg:province":"TN",
    "sg:tags":[
        "shirt"
    ],
    "wof:name":"Aus-Tex Mfg Co",
    "wof:placetype":"venue"
},
  "geometry": {"coordinates":[-82.836203,36.167587],"type":"Point"}
}