{
  "type": "Feature",
  "properties": {
    "iso:country":"US",
    "sg:address":"50 N Newsom St",
    "sg:city":"Mc Kenzie",
    "sg:classifiers":[
        {
            "category":"Professional",
            "type":"Services"
        }
    ],
    "sg:phone":"+1 731 352 5217",
    "sg:postcode":"38201",
    "sg:province":"TN",
    "wof:name":"Steve Jackson",
    "wof:placetype":"venue"
},
  "geometry": {"coordinates":[-88.513741,36.138294],"type":"Point"}
}