{
  "type": "Feature",
  "properties": {
    "iso:country":"US",
    "sg:address":"302 Gibson St",
    "sg:city":"Rogersville",
    "sg:classifiers":[
        {
            "category":"Personal",
            "subcategory":"Beauty Salon",
            "type":"Services"
        }
    ],
    "sg:phone":"+1 423 272 9343",
    "sg:postcode":"37857",
    "sg:province":"TN",
    "sg:tags":[
        "shop"
    ],
    "wof:name":"Rita's Beauty Shop",
    "wof:placetype":"venue"
},
  "geometry": {"coordinates":[-83.012518,36.401321],"type":"Point"}
}