{
  "type": "Feature",
  "properties": {
    "iso:country":"US",
    "sg:address":"4890 Kettle Mills Rd",
    "sg:city":"Hampshire",
    "sg:phone":"+1 931 285 2271",
    "sg:postcode":"38461",
    "sg:province":"TN",
    "sg:tags":[
        "farm",
        "tobacco"
    ],
    "wof:name":"Jimmy Morrow Farm",
    "wof:placetype":"venue"
},
  "geometry": {"coordinates":[-87.292886,35.677585],"type":"Point"}
}