{
  "type": "Feature",
  "properties": {
    "iso:country":"US",
    "sg:address":"1004 Old Tree Ct",
    "sg:city":"Nashville",
    "sg:classifiers":[
        {
            "category":"Professional",
            "subcategory":"Detective & Security Services",
            "type":"Services"
        }
    ],
    "sg:phone":"+1 615 390 3558",
    "sg:postcode":"37210",
    "sg:province":"TN",
    "sg:tags":[
        "system"
    ],
    "wof:name":"Total Protection Svc Inc",
    "wof:placetype":"venue"
},
  "geometry": {"coordinates":[-86.736598,36.145689],"type":"Point"}
}