{
  "type": "Feature",
  "properties": {
    "iso:country":"US",
    "sg:address":"1406 Cannon St",
    "sg:city":"Franklin",
    "sg:classifiers":[
        {
            "category":"Education",
            "subcategory":"School",
            "type":"Public Place"
        }
    ],
    "sg:phone":"+1 615 591 2802",
    "sg:postcode":"37064",
    "sg:province":"TN",
    "sg:website":"www.fssd.org",
    "wof:name":"Franklin School District Annex",
    "wof:placetype":"venue"
},
  "geometry": {"coordinates":[-86.882131,35.913272],"type":"Point"}
}