{
  "type": "Feature",
  "properties": {
    "iso:country":"US",
    "sg:address":"73 Monroe Ave",
    "sg:city":"Memphis",
    "sg:classifiers":[
        {
            "category":"Restaurant",
            "type":"Food & Drink"
        }
    ],
    "sg:phone":"+1 901 527 4773",
    "sg:postcode":"38103",
    "sg:province":"TN",
    "sg:tags":[
        "barbecue"
    ],
    "wof:name":"Mike's Bar-B-Que",
    "wof:placetype":"venue"
},
  "geometry": {"coordinates":[-90.05452,35.144546],"type":"Point"}
}