{
  "type": "Feature",
  "properties": {
    "addr:full":"801 Airpark Center Dr Nashville TN 37217",
    "addr:housenumber":"801",
    "addr:postcode":"37217",
    "addr:street":"Center Dr",
    "iso:country":"US",
    "sg:address":"801 Airpark Center Dr",
    "sg:city":"Nashville",
    "sg:classifiers":[
        {
            "category":"Retail",
            "subcategory":"Laundry & Dry Cleaning",
            "type":"Services"
        }
    ],
    "sg:phone":"+1 615 882 9991",
    "sg:postcode":"37217",
    "sg:province":"TN",
    "sg:tags":[
        "uniform",
        "supply"
    ],
    "sg:website":"www.gkservices.com",
    "wof:name":"G & K Svc",
    "wof:placetype":"venue"
},
  "geometry": {"coordinates":[-86.68039400000001,36.094515],"type":"Point"}
}