{
  "type": "Feature",
  "properties": {
    "iso:country":"US",
    "sg:address":"605 Magnolia Ln",
    "sg:city":"Nashville",
    "sg:classifiers":[
        {
            "category":"Professional",
            "type":"Services"
        }
    ],
    "sg:phone":"+1 615 837 6871",
    "sg:postcode":"37211",
    "sg:province":"TN",
    "sg:tags":[
        "establishment"
    ],
    "wof:name":"Ashley Holmertz Foundation",
    "wof:placetype":"venue"
},
  "geometry": {"coordinates":[-86.725425,36.038506],"type":"Point"}
}