{
  "type": "Feature",
  "properties": {
    "iso:country":"US",
    "sg:address":"102 Lake Crest Ln",
    "sg:city":"Oak Ridge",
    "sg:classifiers":[
        {
            "category":"Manufacturing",
            "subcategory":"Jewelry",
            "type":"Manufacturing & Wholesale Goods"
        }
    ],
    "sg:phone":"+1 865 988 6244",
    "sg:postcode":"37830",
    "sg:province":"TN",
    "wof:name":"Terrys Fine Jewelry",
    "wof:placetype":"venue"
},
  "geometry": {"coordinates":[-84.215435,36.057026],"type":"Point"}
}