{
  "type": "Feature",
  "properties": {
    "addr:full":"228 S Lindell St Martin TN 38237",
    "addr:housenumber":"228",
    "addr:postcode":"38237",
    "addr:street":"S Lindell St",
    "iso:country":"US",
    "sg:address":"228 S Lindell St",
    "sg:city":"Martin",
    "sg:classifiers":[
        {
            "category":"Sports & Exercise",
            "subcategory":"Gym",
            "type":"Entertainment"
        }
    ],
    "sg:phone":"+1 731 587 0881",
    "sg:postcode":"38237",
    "sg:province":"TN",
    "sg:tags":[
        "fitness",
        "physical",
        "facility"
    ],
    "wof:name":"Curves For Women",
    "wof:placetype":"venue"
},
  "geometry": {"coordinates":[-88.850166,36.344609],"type":"Point"}
}