{
  "type": "Feature",
  "properties": {
    "addr:full":"1248 Marlin Rd Memphis TN 38116",
    "addr:housenumber":"1248",
    "addr:postcode":"38116",
    "addr:street":"Marlin Rd",
    "iso:country":"US",
    "sg:address":"1248 Marlin Rd",
    "sg:city":"Memphis",
    "sg:classifiers":[
        {
            "category":"Personal",
            "subcategory":"Barber",
            "type":"Services"
        }
    ],
    "sg:phone":"+1 901 345 3063",
    "sg:postcode":"38116",
    "sg:province":"TN",
    "wof:name":"My Barber's Den",
    "wof:placetype":"venue"
},
  "geometry": {"coordinates":[-90.020594,35.034289],"type":"Point"}
}