{
  "type": "Feature",
  "properties": {
    "iso:country":"US",
    "sg:address":"1212 7th Ave N",
    "sg:city":"Nashville",
    "sg:classifiers":[
        {
            "category":"Shopping",
            "subcategory":"Books",
            "type":"Retail Goods"
        }
    ],
    "sg:phone":"+1 615 251 0122",
    "sg:postcode":"37208",
    "sg:province":"TN",
    "wof:name":"TN Books Direct LLC",
    "wof:placetype":"venue"
},
  "geometry": {"coordinates":[-86.791315,36.175577],"type":"Point"}
}