{
  "type": "Feature",
  "properties": {
    "iso:country":"US",
    "sg:address":"6081 Shelby Oaks Dr",
    "sg:city":"Memphis",
    "sg:classifiers":[
        {
            "category":"Bars & Pubs",
            "type":"Food & Drink"
        },
        {
            "category":"Restaurant",
            "type":"Food & Drink"
        }
    ],
    "sg:menulink":"http://www.allmenus.com/tn/memphis/29184-cracker-barrel-old-country-store/menu/",
    "sg:phone":"+1 901 382 5465",
    "sg:postcode":"38134",
    "sg:province":"TN",
    "sg:tags":[
        "american",
        "southern"
    ],
    "wof:name":"Cracker Barrel Old Country Store",
    "wof:placetype":"venue"
},
  "geometry": {"coordinates":[-89.861071,35.167743],"type":"Point"}
}