{
  "type": "Feature",
  "properties": {
    "addr:full":"2205 N Economy Rd Morristown TN 37814",
    "addr:housenumber":"2205",
    "addr:postcode":"37814",
    "addr:street":"N Economy Rd",
    "iso:country":"US",
    "sg:address":"2205 N Economy Rd",
    "sg:city":"Morristown",
    "sg:classifiers":[
        {
            "category":"Professional",
            "subcategory":"Management & Consulting",
            "type":"Services"
        }
    ],
    "sg:phone":"+1 423 581 1330",
    "sg:postcode":"37814",
    "sg:province":"TN",
    "sg:tags":[
        "business"
    ],
    "wof:name":"Marilyn J Medley",
    "wof:placetype":"venue"
},
  "geometry": {"coordinates":[-83.329581,36.212294],"type":"Point"}
}