{
  "type": "Feature",
  "properties": {
    "iso:country":"US",
    "sg:address":"3153 Highway 61 E",
    "sg:city":"Luttrell",
    "sg:classifiers":[
        {
            "category":"Restaurant",
            "type":"Food & Drink"
        }
    ],
    "sg:phone":"+1 865 992 9923",
    "sg:postcode":"37779",
    "sg:province":"TN",
    "sg:tags":[
        "pizza"
    ],
    "sg:website":"http://www.pizzaplusinc.com",
    "wof:name":"Pizza Plus Of Luttrell",
    "wof:placetype":"venue"
},
  "geometry": {"coordinates":[-83.742728,36.229014],"type":"Point"}
}