{
  "type": "Feature",
  "properties": {
    "addr:full":"2181 Old Fort Pkwy Murfreesboro TN 37129",
    "addr:housenumber":"2181",
    "addr:postcode":"37129",
    "addr:street":"Old Fort Pkwy",
    "iso:country":"US",
    "sg:address":"2181 Old Fort Pkwy",
    "sg:city":"Murfreesboro",
    "sg:classifiers":[
        {
            "category":"Restaurant",
            "type":"Food & Drink"
        }
    ],
    "sg:menulink":"http://www.allmenus.com/tn/murfreesboro/177835-jack-in-the-box/menu/",
    "sg:phone":"+1 615 904 1803",
    "sg:postcode":"37129",
    "sg:province":"TN",
    "sg:tags":[
        "burger",
        "american"
    ],
    "wof:name":"Jack in the Box",
    "wof:placetype":"venue"
},
  "geometry": {"coordinates":[-86.43035,35.846478],"type":"Point"}
}