{
  "type": "Feature",
  "properties": {
    "iso:country":"US",
    "sg:address":"335 N Mount Juliet Rd",
    "sg:city":"Mt Juliet",
    "sg:classifiers":[
        {
            "category":"Organizations",
            "subcategory":"Religious Organization",
            "type":"Services"
        }
    ],
    "sg:phone":"+1 615 773 4133",
    "sg:postcode":"37122",
    "sg:province":"TN",
    "sg:tags":[
        "church"
    ],
    "wof:name":"Faith Baptist Church",
    "wof:placetype":"venue"
},
  "geometry": {"coordinates":[-86.512851,36.175881],"type":"Point"}
}