{
  "type": "Feature",
  "properties": {
    "iso:country":"US",
    "sg:address":"14345 Lebanon Rd",
    "sg:city":"Old Hickory",
    "sg:classifiers":[
        {
            "category":"Autos & Motor Vehicles",
            "subcategory":"Automobile Sales",
            "type":"Retail Goods"
        }
    ],
    "sg:phone":"+1 615 754 2111",
    "sg:postcode":"37138",
    "sg:province":"TN",
    "sg:tags":[
        "used"
    ],
    "wof:name":"College Motors II Inc",
    "wof:placetype":"venue"
},
  "geometry": {"coordinates":[-86.565411,36.220577],"type":"Point"}
}