{
  "type": "Feature",
  "properties": {
    "addr:full":"3745 US Hwy 79 S Paris TN 38242",
    "addr:housenumber":"3745",
    "addr:postcode":"38242",
    "addr:street":"Us Hwy 79 S",
    "iso:country":"US",
    "sg:address":"3745 US Hwy 79 S",
    "sg:city":"Paris",
    "sg:classifiers":[
        {
            "category":"Retail",
            "subcategory":"Auto Repair",
            "type":"Services"
        }
    ],
    "sg:phone":"+1 731 642 1200",
    "sg:postcode":"38242",
    "sg:province":"TN",
    "sg:tags":[
        "body",
        "automobile",
        "painting"
    ],
    "wof:name":"Superior Auto Body",
    "wof:placetype":"venue"
},
  "geometry": {"coordinates":[-88.345259,36.257453],"type":"Point"}
}