{
  "type": "Feature",
  "properties": {
    "addr:full":"1006 Williams St Maryville TN 37803",
    "addr:housenumber":"1006",
    "addr:postcode":"37803",
    "addr:street":"Williams St",
    "iso:country":"US",
    "sg:address":"1006 Williams St",
    "sg:city":"Maryville",
    "sg:classifiers":[
        {
            "category":"Shopping",
            "subcategory":"Beauty & Cosmetics",
            "type":"Retail Goods"
        }
    ],
    "sg:phone":"+1 865 984 2246",
    "sg:postcode":"37803",
    "sg:province":"TN",
    "sg:tags":[
        "merchandise"
    ],
    "wof:name":"Mary Kay Cosmetics",
    "wof:placetype":"venue"
},
  "geometry": {"coordinates":[-83.976569,35.727317],"type":"Point"}
}