{
  "type": "Feature",
  "properties": {
    "addr:full":"5504 Central Avenue Pike Knoxville TN 37912",
    "addr:housenumber":"5504",
    "addr:postcode":"37912",
    "addr:street":"Central Avenue Pike",
    "iso:country":"US",
    "sg:address":"5504 Central Avenue Pike",
    "sg:city":"Knoxville",
    "sg:classifiers":[
        {
            "category":"Retail",
            "subcategory":"Car Wash",
            "type":"Services"
        }
    ],
    "sg:phone":"+1 865 688 8827",
    "sg:postcode":"37912",
    "sg:province":"TN",
    "sg:tags":[
        "carwash"
    ],
    "wof:name":"Magic Spray Car Wash Inc",
    "wof:placetype":"venue"
},
  "geometry": {"coordinates":[-83.97413899999999,36.01412],"type":"Point"}
}