{
  "type": "Feature",
  "properties": {
    "iso:country":"US",
    "sg:address":"1347 College St",
    "sg:city":"Clarksville",
    "sg:classifiers":[
        {
            "category":"Autos & Motor Vehicles",
            "subcategory":"Auto Supplies",
            "type":"Retail Goods"
        }
    ],
    "sg:phone":"+1 931 920 5599",
    "sg:postcode":"37040",
    "sg:province":"TN",
    "sg:tags":[
        "wheel",
        "cover"
    ],
    "wof:name":"Bobby's Custom Auto",
    "wof:placetype":"venue"
},
  "geometry": {"coordinates":[-87.337862,36.537812],"type":"Point"}
}