{
  "type": "Feature",
  "properties": {
    "addr:full":"3030 Covington Pike Memphis TN 38128",
    "addr:housenumber":"3030",
    "addr:postcode":"38128",
    "addr:street":"Covington Pike",
    "iso:country":"US",
    "sg:address":"3030 Covington Pike",
    "sg:city":"Memphis",
    "sg:classifiers":[
        {
            "category":"Professional",
            "subcategory":"Lawyer & Legal Services",
            "type":"Services"
        }
    ],
    "sg:phone":"+1 901 372 1600",
    "sg:postcode":"38128",
    "sg:province":"TN",
    "wof:name":"J D Drewry Atty",
    "wof:placetype":"venue"
},
  "geometry": {"coordinates":[-89.89458399999999,35.207781],"type":"Point"}
}