{
  "type": "Feature",
  "properties": {
    "addr:full":"425 Moreland Dr Kingsport TN 37660",
    "addr:housenumber":"425",
    "addr:postcode":"37660",
    "addr:street":"Moreland Dr",
    "iso:country":"US",
    "sg:address":"425 Moreland Dr",
    "sg:city":"Kingsport",
    "sg:classifiers":[
        {
            "category":"Manufacturing",
            "subcategory":"Chemicals & Compounds",
            "type":"Manufacturing & Wholesale Goods"
        }
    ],
    "sg:phone":"+1 423 246 1168",
    "sg:postcode":"37660",
    "sg:province":"TN",
    "sg:tags":[
        "gas"
    ],
    "wof:name":"Air Products & Chemicals Inc",
    "wof:placetype":"venue"
},
  "geometry": {"coordinates":[-82.54759199999999,36.513512],"type":"Point"}
}