{
  "type": "Feature",
  "properties": {
    "iso:country":"US",
    "sg:address":"1812 Maryville Pike",
    "sg:city":"Knoxville",
    "sg:classifiers":[
        {
            "category":"Restaurant",
            "type":"Food & Drink"
        }
    ],
    "sg:phone":"+1 865 573 4645",
    "sg:postcode":"37920",
    "sg:province":"TN",
    "wof:name":"Swann's Restaurant & Karaoke",
    "wof:placetype":"venue"
},
  "geometry": {"coordinates":[-83.935069,35.915024],"type":"Point"}
}