{
  "type": "Feature",
  "properties": {
    "iso:country":"US",
    "sg:address":"108 N Forrest Ave",
    "sg:city":"Camden",
    "sg:classifiers":[
        {
            "category":"Health Services",
            "subcategory":"Clinic",
            "type":"Services"
        }
    ],
    "sg:phone":"+1 731 584 1430",
    "sg:postcode":"38320",
    "sg:province":"TN",
    "wof:name":"Berry Clinic",
    "wof:placetype":"venue"
},
  "geometry": {"coordinates":[-88.097397,36.059739],"type":"Point"}
}