{
  "type": "Feature",
  "properties": {
    "iso:country":"US",
    "sg:address":"1234 W Main St",
    "sg:city":"Franklin",
    "sg:classifiers":[
        {
            "category":"Health Services",
            "subcategory":"Doctor",
            "type":"Services"
        }
    ],
    "sg:phone":"+1 615 791 0500",
    "sg:postcode":"37064",
    "sg:province":"TN",
    "sg:tags":[
        "physician",
        "surgeon"
    ],
    "wof:name":"Enrique R Arevalos MD",
    "wof:placetype":"venue"
},
  "geometry": {"coordinates":[-86.88179700000001,35.916592],"type":"Point"}
}