{
  "type": "Feature",
  "properties": {
    "addr:full":"1621 Service Merchandise Blvd Brentwood TN 37027",
    "addr:housenumber":"1621",
    "addr:postcode":"37027",
    "addr:street":"Service Merchandise Blvd",
    "iso:country":"US",
    "sg:address":"1621 Service Merchandise Blvd",
    "sg:city":"Brentwood",
    "sg:classifiers":[
        {
            "category":"Manufacturing",
            "subcategory":"Rubber & Plastics",
            "type":"Manufacturing & Wholesale Goods"
        }
    ],
    "sg:phone":"+1 615 377 6700",
    "sg:postcode":"37027",
    "sg:province":"TN",
    "sg:tags":[
        "mfg"
    ],
    "wof:name":"Eaton Corporation",
    "wof:placetype":"venue"
},
  "geometry": {"coordinates":[-86.809636,35.969499],"type":"Point"}
}