{
  "type": "Feature",
  "properties": {
    "iso:country":"US",
    "sg:address":"2999 Champions Dr",
    "sg:city":"Arlington",
    "sg:classifiers":[
        {
            "category":"Wholesale",
            "subcategory":"Durable Goods & Equipment",
            "type":"Manufacturing & Wholesale Goods"
        }
    ],
    "sg:phone":"+1 901 383 1424",
    "sg:postcode":"38002",
    "sg:province":"TN",
    "wof:name":"US Hospitality Supply LLC",
    "wof:placetype":"venue"
},
  "geometry": {"coordinates":[-89.754305,35.207129],"type":"Point"}
}