{
  "type": "Feature",
  "properties": {
    "addr:full":"721 Winton Rd Memphis TN 38117",
    "addr:housenumber":"721",
    "addr:postcode":"38117",
    "addr:street":"Winton Rd",
    "iso:country":"US",
    "sg:address":"721 Winton Rd",
    "sg:city":"Memphis",
    "sg:classifiers":[
        {
            "category":"Retail",
            "subcategory":"Car Wash",
            "type":"Services"
        }
    ],
    "sg:phone":"+1 901 685 1842",
    "sg:postcode":"38117",
    "sg:province":"TN",
    "sg:tags":[
        "polishing",
        "washing"
    ],
    "wof:name":"Sunshine Carwash",
    "wof:placetype":"venue"
},
  "geometry": {"coordinates":[-89.894125,35.111289],"type":"Point"}
}