{
  "type": "Feature",
  "properties": {
    "iso:country":"US",
    "sg:address":"253 Summers St",
    "sg:city":"Lexington",
    "sg:classifiers":[
        {
            "category":"Freight",
            "type":"Transportation"
        }
    ],
    "sg:phone":"+1 731 967 9911",
    "sg:postcode":"38351",
    "sg:province":"TN",
    "sg:tags":[
        "operator",
        "local",
        "trucking"
    ],
    "wof:name":"Jeffrey Trucking",
    "wof:placetype":"venue"
},
  "geometry": {"coordinates":[-88.396429,35.656811],"type":"Point"}
}