{
  "type": "Feature",
  "properties": {
    "iso:country":"US",
    "sg:address":"2310 Congress Pkwy NW",
    "sg:city":"Athens",
    "sg:classifiers":[
        {
            "category":"Banks & Credit Unions",
            "subcategory":"Bank",
            "type":"Services"
        }
    ],
    "sg:phone":"+1 423 507 1089",
    "sg:postcode":"37303",
    "sg:province":"TN",
    "sg:tags":[
        "loan"
    ],
    "wof:name":"American General Finance Inc",
    "wof:placetype":"venue"
},
  "geometry": {"coordinates":[-84.634969,35.442143],"type":"Point"}
}