{
  "type": "Feature",
  "properties": {
    "iso:country":"US",
    "sg:address":"2490 Chelsea Ave",
    "sg:city":"Memphis",
    "sg:classifiers":[
        {
            "category":"Social Services",
            "subcategory":"Child Care",
            "type":"Services"
        }
    ],
    "sg:phone":"+1 901 323 4601",
    "sg:postcode":"38108",
    "sg:province":"TN",
    "wof:name":"Chelsea Early Start Christian",
    "wof:placetype":"venue"
},
  "geometry": {"coordinates":[-89.973179,35.174609],"type":"Point"}
}