{
  "type": "Feature",
  "properties": {
    "iso:country":"US",
    "sg:address":"110 Elk Ave S",
    "sg:city":"Fayetteville",
    "sg:classifiers":[
        {
            "category":"Real Estate",
            "subcategory":"Architect",
            "type":"Services"
        }
    ],
    "sg:phone":"+1 931 438 4420",
    "sg:postcode":"37334",
    "sg:province":"TN",
    "wof:name":"L Hughes Assoc Architects",
    "wof:placetype":"venue"
},
  "geometry": {"coordinates":[-86.569177,35.151998],"type":"Point"}
}