{
  "type": "Feature",
  "properties": {
    "iso:country":"US",
    "sg:address":"4920 Sherman Oaks Dr",
    "sg:city":"Nashville",
    "sg:classifiers":[
        {
            "category":"Personal",
            "subcategory":"Beauty Salon",
            "type":"Services"
        }
    ],
    "sg:phone":"+1 615 731 3281",
    "sg:postcode":"37211",
    "sg:province":"TN",
    "wof:name":"Adeola International Hair Sln",
    "wof:placetype":"venue"
},
  "geometry": {"coordinates":[-86.706974,36.082075],"type":"Point"}
}