{
  "type": "Feature",
  "properties": {
    "iso:country":"US",
    "sg:address":"837 Esther Ln",
    "sg:city":"Murfreesboro",
    "sg:classifiers":[
        {
            "category":"Organizations",
            "subcategory":"Religious Organization",
            "type":"Services"
        }
    ],
    "sg:phone":"+1 615 890 9533",
    "sg:postcode":"37129",
    "sg:province":"TN",
    "sg:tags":[
        "church"
    ],
    "wof:name":"Murfreesboro Church Of Christ",
    "wof:placetype":"venue"
},
  "geometry": {"coordinates":[-86.405467,35.826025],"type":"Point"}
}