{
  "type": "Feature",
  "properties": {
    "iso:country":"US",
    "sg:address":"113 Gay St",
    "sg:city":"Erwin",
    "sg:classifiers":[
        {
            "category":"Personal",
            "subcategory":"Beauty Salon",
            "type":"Services"
        }
    ],
    "sg:phone":"+1 423 743 4422",
    "sg:postcode":"37650",
    "sg:province":"TN",
    "sg:tags":[
        "shop"
    ],
    "wof:name":"Katherine S Beauty Shop",
    "wof:placetype":"venue"
},
  "geometry": {"coordinates":[-82.41669,36.145356],"type":"Point"}
}