{
  "type": "Feature",
  "properties": {
    "addr:full":"156 N Manassas St Memphis TN 38105",
    "addr:housenumber":"156",
    "addr:postcode":"38105",
    "addr:street":"N Manassas St",
    "iso:country":"US",
    "sg:address":"156 N Manassas St",
    "sg:city":"Memphis",
    "sg:classifiers":[
        {
            "category":"Food & Beverages",
            "subcategory":"Groceries & Convenience Stores",
            "type":"Retail Goods"
        }
    ],
    "sg:phone":"+1 901 522 9306",
    "sg:postcode":"38105",
    "sg:province":"TN",
    "wof:name":"One Stop Market & Deli",
    "wof:placetype":"venue"
},
  "geometry": {"coordinates":[-90.03478,35.14567],"type":"Point"}
}