{
  "type": "Feature",
  "properties": {
    "addr:full":"1299 Winterberry Cove Germantown TN 38138",
    "addr:housenumber":"1299",
    "addr:postcode":"38138",
    "addr:street":"Winterberry Cove",
    "iso:country":"US",
    "sg:address":"1299 Winterberry Cove",
    "sg:city":"Germantown",
    "sg:classifiers":[
        {
            "category":"Banks & Credit Unions",
            "subcategory":"Financial Services",
            "type":"Services"
        }
    ],
    "sg:phone":"+1 901 756 4019",
    "sg:postcode":"38138",
    "sg:province":"TN",
    "sg:tags":[
        "company",
        "holding"
    ],
    "wof:name":"Trans Gulfstream Holdings",
    "wof:placetype":"venue"
},
  "geometry": {"coordinates":[-89.82759799999999,35.113474],"type":"Point"}
}