{
  "type": "Feature",
  "properties": {
    "iso:country":"US",
    "sg:address":"104 Park Cir",
    "sg:city":"Murfreesboro",
    "sg:classifiers":[
        {
            "category":"Insurance",
            "subcategory":"Insurance Agent",
            "type":"Services"
        }
    ],
    "sg:phone":"+1 615 364 7030",
    "sg:postcode":"37130",
    "sg:province":"TN",
    "wof:name":"Affordable Health Care",
    "wof:placetype":"venue"
},
  "geometry": {"coordinates":[-86.37389400000001,35.845454],"type":"Point"}
}