{
  "type": "Feature",
  "properties": {
    "iso:country":"US",
    "sg:address":"812 E Jackson Blvd",
    "sg:city":"Jonesborough",
    "sg:classifiers":[
        {
            "category":"Insurance",
            "subcategory":"Insurance Agent",
            "type":"Services"
        }
    ],
    "sg:phone":"+1 423 753 4751",
    "sg:postcode":"37659",
    "sg:province":"TN",
    "wof:name":"State Farm Insurance",
    "wof:placetype":"venue"
},
  "geometry": {"coordinates":[-82.462186,36.300968],"type":"Point"}
}