{
  "type": "Feature",
  "properties": {
    "addr:full":"18499 Alberta St Oneida TN 37841",
    "addr:housenumber":"18499",
    "addr:postcode":"37841",
    "addr:street":"Alberta St",
    "iso:country":"US",
    "sg:address":"18499 Alberta St",
    "sg:city":"Oneida",
    "sg:classifiers":[
        {
            "category":"Restaurant",
            "type":"Food & Drink"
        }
    ],
    "sg:phone":"+1 423 569 4002",
    "sg:postcode":"37841",
    "sg:province":"TN",
    "wof:name":"Phillips Drive In",
    "wof:placetype":"venue"
},
  "geometry": {"coordinates":[-84.49575400000001,36.52568],"type":"Point"}
}