{
  "type": "Feature",
  "properties": {
    "iso:country":"US",
    "sg:address":"501 W Chestnut St",
    "sg:city":"Johnson City",
    "sg:classifiers":[
        {
            "category":"Banks & Credit Unions",
            "subcategory":"Financial Services",
            "type":"Services"
        }
    ],
    "sg:phone":"+1 423 928 4433",
    "sg:postcode":"37604",
    "sg:province":"TN",
    "sg:tags":[
        "trust",
        "management"
    ],
    "wof:name":"Chestnut Investments LP",
    "wof:placetype":"venue"
},
  "geometry": {"coordinates":[-82.354258,36.306559],"type":"Point"}
}