{
  "type": "Feature",
  "properties": {
    "iso:country":"US",
    "sg:address":"200 Brocks Chapel Rd",
    "sg:city":"Greenfield",
    "sg:phone":"+1 731 235 3727",
    "sg:postcode":"38230",
    "sg:province":"TN",
    "sg:tags":[
        "farm",
        "corn",
        "wheat",
        "soybean"
    ],
    "wof:name":"Bob Grooms",
    "wof:placetype":"venue"
},
  "geometry": {"coordinates":[-88.835154,36.190073],"type":"Point"}
}