{
  "type": "Feature",
  "properties": {
    "iso:country":"US",
    "sg:address":"175 Northlake Dr",
    "sg:city":"Hendersonville",
    "sg:classifiers":[
        {
            "category":"Professional",
            "type":"Services"
        }
    ],
    "sg:phone":"+1 615 826 1810",
    "sg:postcode":"37075",
    "sg:province":"TN",
    "wof:name":"Mavity Cross Inc",
    "wof:placetype":"venue"
},
  "geometry": {"coordinates":[-86.58440299999999,36.306995],"type":"Point"}
}