{
  "type": "Feature",
  "properties": {
    "iso:country":"US",
    "sg:address":"867 High School Rd",
    "sg:city":"Selmer",
    "sg:classifiers":[
        {
            "category":"Professional",
            "type":"Services"
        }
    ],
    "sg:phone":"+1 731 645 3569",
    "sg:postcode":"38375",
    "sg:province":"TN",
    "sg:tags":[
        "establishment"
    ],
    "wof:name":"Selmer JC Ctr",
    "wof:placetype":"venue"
},
  "geometry": {"coordinates":[-88.54962399999999,35.158255],"type":"Point"}
}