{
  "type": "Feature",
  "properties": {
    "iso:country":"US",
    "sg:address":"4631 N Lee Hwy",
    "sg:city":"Cleveland",
    "sg:classifiers":[
        {
            "category":"Banks & Credit Unions",
            "subcategory":"Bank",
            "type":"Services"
        }
    ],
    "sg:phone":"+1 423 473 1608",
    "sg:postcode":"37312",
    "sg:province":"TN",
    "sg:tags":[
        "financing"
    ],
    "wof:name":"Beneficial Finance",
    "wof:placetype":"venue"
},
  "geometry": {"coordinates":[-84.835594,35.210329],"type":"Point"}
}