{
  "type": "Feature",
  "properties": {
    "iso:country":"US",
    "sg:address":"2306 Maryville Pike",
    "sg:city":"Knoxville",
    "sg:classifiers":[
        {
            "category":"Wholesale",
            "subcategory":"Farm Supplies",
            "type":"Manufacturing & Wholesale Goods"
        }
    ],
    "sg:phone":"+1 865 577 7568",
    "sg:postcode":"37920",
    "sg:province":"TN",
    "sg:tags":[
        "bulb",
        "seed"
    ],
    "wof:name":"Mayo Seed Co",
    "wof:placetype":"venue"
},
  "geometry": {"coordinates":[-83.93705199999999,35.913078],"type":"Point"}
}