{
  "type": "Feature",
  "properties": {
    "iso:country":"US",
    "sg:address":"214 Lakeview Rd",
    "sg:city":"Somerville",
    "sg:classifiers":[
        {
            "category":"Health Services",
            "subcategory":"Doctor",
            "type":"Services"
        }
    ],
    "sg:phone":"+1 901 516 4099",
    "sg:postcode":"38068",
    "sg:province":"TN",
    "sg:tags":[
        "physician",
        "surgeon"
    ],
    "wof:name":"Kathleen D Spiers MD",
    "wof:placetype":"venue"
},
  "geometry": {"coordinates":[-89.36367799999999,35.246],"type":"Point"}
}