{
  "type": "Feature",
  "properties": {
    "addr:full":"2256 Roslin Rd Jamestown TN 38556",
    "addr:housenumber":"2256",
    "addr:postcode":"38556",
    "addr:street":"Roslin Rd",
    "iso:country":"US",
    "sg:address":"2256 Roslin Rd",
    "sg:city":"Jamestown",
    "sg:classifiers":[
        {
            "category":"Farming",
            "subcategory":"Farm",
            "type":"Manufacturing & Wholesale Goods"
        }
    ],
    "sg:phone":"+1 931 863 5595",
    "sg:postcode":"38556",
    "sg:province":"TN",
    "sg:tags":[
        "crop",
        "general"
    ],
    "wof:name":"Labelle Acres",
    "wof:placetype":"venue"
},
  "geometry": {"coordinates":[-84.935293,36.232691],"type":"Point"}
}