{
  "type": "Feature",
  "properties": {
    "addr:full":"6215 Henry Ford Dr Nashville TN 37209",
    "addr:housenumber":"6215",
    "addr:postcode":"37209",
    "addr:street":"Henry Ford Dr",
    "iso:country":"US",
    "sg:address":"6215 Henry Ford Dr",
    "sg:city":"Nashville",
    "sg:classifiers":[
        {
            "category":"Organizations",
            "subcategory":"Religious Organization",
            "type":"Services"
        }
    ],
    "sg:phone":"+1 615 356 0867",
    "sg:postcode":"37209",
    "sg:province":"TN",
    "sg:tags":[
        "church"
    ],
    "wof:name":"W Nashville Freewill Bapt Ch",
    "wof:placetype":"venue"
},
  "geometry": {"coordinates":[-86.879676,36.15336],"type":"Point"}
}