{
  "type": "Feature",
  "properties": {
    "iso:country":"US",
    "sg:address":"2810 Silverdale Rd",
    "sg:city":"Chattanooga",
    "sg:classifiers":[
        {
            "category":"Banks & Credit Unions",
            "subcategory":"Bank",
            "type":"Services"
        }
    ],
    "sg:phone":"+1 423 954 9075",
    "sg:postcode":"37421",
    "sg:province":"TN",
    "sg:tags":[
        "loan",
        "real estate"
    ],
    "wof:name":"Hunter Mortgage LLC",
    "wof:placetype":"venue"
},
  "geometry": {"coordinates":[-85.140693,35.056829],"type":"Point"}
}