{
  "type": "Feature",
  "properties": {
    "addr:full":"1340 S Ellington Pkwy Lewisburg TN 37091",
    "addr:housenumber":"1340",
    "addr:postcode":"37091",
    "addr:street":"S Ellington Pkwy",
    "iso:country":"US",
    "sg:address":"1340 S Ellington Pkwy",
    "sg:city":"Lewisburg",
    "sg:classifiers":[
        {
            "category":"Retail",
            "subcategory":"Veterinary Services",
            "type":"Services"
        }
    ],
    "sg:phone":"+1 931 359 6376",
    "sg:postcode":"37091",
    "sg:province":"TN",
    "sg:tags":[
        "veterinarian",
        "merchandise"
    ],
    "sg:website":"www.companionah.com",
    "wof:name":"VCA Companion Animal Hospital",
    "wof:placetype":"venue"
},
  "geometry": {"coordinates":[-86.795239,35.428046],"type":"Point"}
}