{
  "type": "Feature",
  "properties": {
    "addr:full":"2022 Plateau Rd Crossville TN 38571",
    "addr:housenumber":"2022",
    "addr:postcode":"38571",
    "addr:street":"Plateau Rd",
    "iso:country":"US",
    "sg:address":"2022 Plateau Rd",
    "sg:city":"Crossville",
    "sg:classifiers":[
        {
            "category":"Organizations",
            "subcategory":"Religious Organization",
            "type":"Services"
        }
    ],
    "sg:phone":"+1 931 484 6060",
    "sg:postcode":"38571",
    "sg:province":"TN",
    "wof:name":"Church Of God Of Prophecy",
    "wof:placetype":"venue"
},
  "geometry": {"coordinates":[-85.091604,36.07876],"type":"Point"}
}