{
  "type": "Feature",
  "properties": {
    "iso:country":"US",
    "sg:address":"9727 Honey Hill Dr",
    "sg:city":"Bon Aqua",
    "sg:classifiers":[
        {
            "category":"Shopping",
            "subcategory":"Department Store",
            "type":"Retail Goods"
        }
    ],
    "sg:phone":"+1 931 670 4897",
    "sg:postcode":"37025",
    "sg:province":"TN",
    "wof:name":"East Hickman Thrift",
    "wof:placetype":"venue"
},
  "geometry": {"coordinates":[-87.234695,35.915258],"type":"Point"}
}