{
  "type": "Feature",
  "properties": {
    "addr:full":"208 Woodmere Mall Crossville TN 38555",
    "addr:housenumber":"208",
    "addr:postcode":"38555",
    "addr:street":"Woodmere Mall",
    "iso:country":"US",
    "sg:address":"208 Woodmere Mall",
    "sg:city":"Crossville",
    "sg:classifiers":[
        {
            "category":"Health Services",
            "subcategory":"Clinic",
            "type":"Services"
        }
    ],
    "sg:phone":"+1 931 456 1227",
    "sg:postcode":"38555",
    "sg:province":"TN",
    "sg:tags":[
        "home"
    ],
    "wof:name":"Cumberland Medical Ctr Home",
    "wof:placetype":"venue"
},
  "geometry": {"coordinates":[-85.03014400000001,35.956917],"type":"Point"}
}