{
  "type": "Feature",
  "properties": {
    "iso:country":"US",
    "sg:address":"918 W Broad St",
    "sg:city":"Smithville",
    "sg:classifiers":[
        {
            "category":"Professional",
            "subcategory":"Business Services",
            "type":"Services"
        }
    ],
    "sg:phone":"+1 615 597 8740",
    "sg:postcode":"37166",
    "sg:province":"TN",
    "wof:name":"Genetts Interpreting Services",
    "wof:placetype":"venue"
},
  "geometry": {"coordinates":[-85.84601600000001,35.963868],"type":"Point"}
}