{
  "type": "Feature",
  "properties": {
    "iso:country":"US",
    "sg:address":"1607 S Main St",
    "sg:city":"Columbia",
    "sg:classifiers":[
        {
            "category":"Shopping",
            "subcategory":"Used Merchandise",
            "type":"Retail Goods"
        }
    ],
    "sg:phone":"+1 931 388 5006",
    "sg:postcode":"38401",
    "sg:province":"TN",
    "wof:name":"Speckled Rooster",
    "wof:placetype":"venue"
},
  "geometry": {"coordinates":[-87.03818099999999,35.602422],"type":"Point"}
}