{
  "type": "Feature",
  "properties": {
    "iso:country":"US",
    "sg:address":"6215 Humphreys Blvd",
    "sg:city":"Memphis",
    "sg:phone":"+1 901 682 0630",
    "sg:postcode":"38120",
    "sg:province":"TN",
    "sg:website":"http://www.ruchclinic.com",
    "wof:name":"Ruch Clinic",
    "wof:placetype":"venue"
},
  "geometry": {"coordinates":[-89.855728,35.130402],"type":"Point"}
}