{
  "type": "Feature",
  "properties": {
    "iso:country":"US",
    "sg:address":"1013 E Lake Ct",
    "sg:city":"Nashville",
    "sg:classifiers":[
        {
            "category":"Social Services",
            "type":"Services"
        }
    ],
    "sg:phone":"+1 615 884 7899",
    "sg:postcode":"37214",
    "sg:province":"TN",
    "sg:tags":[
        "mission"
    ],
    "wof:name":"Jamaican Voice Intl Inc",
    "wof:placetype":"venue"
},
  "geometry": {"coordinates":[-86.638352,36.141133],"type":"Point"}
}