{
  "type": "Feature",
  "properties": {
    "iso:country":"US",
    "sg:address":"2292 Skyview Dr",
    "sg:city":"Centerville",
    "sg:classifiers":[
        {
            "category":"Arts & Performance",
            "subcategory":"Theater",
            "type":"Entertainment"
        }
    ],
    "sg:phone":"+1 931 729 2518",
    "sg:postcode":"37033",
    "sg:province":"TN",
    "sg:tags":[
        "bureau"
    ],
    "wof:name":"Centerville Entertainment",
    "wof:placetype":"venue"
},
  "geometry": {"coordinates":[-87.45285699999999,35.828081],"type":"Point"}
}