{
  "type": "Feature",
  "properties": {
    "addr:full":"1721 Transport Ave Memphis TN 38116",
    "addr:housenumber":"1721",
    "addr:postcode":"38116",
    "addr:street":"Transport Ave",
    "iso:country":"US",
    "sg:address":"1721 Transport Ave",
    "sg:city":"Memphis",
    "sg:classifiers":[
        {
            "category":"Autos & Motor Vehicles",
            "subcategory":"Automobile Sales",
            "type":"Retail Goods"
        }
    ],
    "sg:phone":"+1 901 332 3930",
    "sg:postcode":"38116",
    "sg:province":"TN",
    "wof:name":"South Land Truck Center",
    "wof:placetype":"venue"
},
  "geometry": {"coordinates":[-90.00532,35.065064],"type":"Point"}
}