{
  "type": "Feature",
  "properties": {
    "addr:full":"300 Tyler Rd Oak Ridge TN 37830",
    "addr:housenumber":"300",
    "addr:postcode":"37830",
    "addr:street":"Tyler Rd",
    "iso:country":"US",
    "sg:address":"300 Tyler Rd",
    "sg:city":"Oak Ridge",
    "sg:classifiers":[
        {
            "category":"Professional",
            "subcategory":"Lawyer & Legal Services",
            "type":"Services"
        }
    ],
    "sg:phone":"+1 865 483 6311",
    "sg:postcode":"37830",
    "sg:province":"TN",
    "sg:tags":[
        "attorney"
    ],
    "wof:name":"Harry L Lillard",
    "wof:placetype":"venue"
},
  "geometry": {"coordinates":[-84.24061399999999,36.026854],"type":"Point"}
}