{
  "type": "Feature",
  "properties": {
    "addr:full":"213 N Main St Middleton TN 38052",
    "addr:housenumber":"213",
    "addr:postcode":"38052",
    "addr:street":"N Main St",
    "iso:country":"US",
    "sg:address":"213 N Main St",
    "sg:city":"Middleton",
    "sg:classifiers":[
        {
            "category":"Organizations",
            "subcategory":"Religious Organization",
            "type":"Services"
        }
    ],
    "sg:phone":"+1 731 376 0475",
    "sg:postcode":"38052",
    "sg:province":"TN",
    "sg:tags":[
        "church"
    ],
    "wof:name":"Calvary Baptist Church",
    "wof:placetype":"venue"
},
  "geometry": {"coordinates":[-88.891066,35.065224],"type":"Point"}
}