{
  "type": "Feature",
  "properties": {
    "addr:full":"702 S White St Athens TN 37303",
    "addr:housenumber":"702",
    "addr:postcode":"37303",
    "addr:street":"S White St",
    "iso:country":"US",
    "sg:address":"702 S White St",
    "sg:city":"Athens",
    "sg:classifiers":[
        {
            "category":"Personal",
            "subcategory":"Barber",
            "type":"Services"
        }
    ],
    "sg:phone":"+1 423 746 1770",
    "sg:postcode":"37303",
    "sg:province":"TN",
    "wof:name":"Hair Central",
    "wof:placetype":"venue"
},
  "geometry": {"coordinates":[-84.588132,35.434724],"type":"Point"}
}