{
  "type": "Feature",
  "properties": {
    "iso:country":"US",
    "sg:address":"210 W Jackson St",
    "sg:city":"Bolivar",
    "sg:classifiers":[
        {
            "category":"Government",
            "subcategory":"Fire Station",
            "type":"Public Place"
        }
    ],
    "sg:phone":"+1 731 658 9545",
    "sg:postcode":"38008",
    "sg:province":"TN",
    "sg:tags":[
        "department"
    ],
    "wof:name":"Fireman's Quarters",
    "wof:placetype":"venue"
},
  "geometry": {"coordinates":[-88.990218,35.25714],"type":"Point"}
}