{
  "type": "Feature",
  "properties": {
    "iso:country":"US",
    "sg:address":"3812 Kenilworth Dr",
    "sg:city":"Knoxville",
    "sg:classifiers":[
        {
            "category":"Organizations",
            "subcategory":"Community Association",
            "type":"Services"
        }
    ],
    "sg:phone":"+1 865 637 7255",
    "sg:postcode":"37919",
    "sg:province":"TN",
    "wof:name":"Abbotts Crssing Hmeowners Assn",
    "wof:placetype":"venue"
},
  "geometry": {"coordinates":[-83.968997,35.939159],"type":"Point"}
}