{
  "type": "Feature",
  "properties": {
    "iso:country":"US",
    "sg:address":"2024 Hollywood Dr",
    "sg:city":"Jackson",
    "sg:classifiers":[
        {
            "category":"Local Transit",
            "type":"Transportation"
        }
    ],
    "sg:phone":"+1 731 664 3127",
    "sg:postcode":"38305",
    "sg:province":"TN",
    "sg:tags":[
        "limousine"
    ],
    "wof:name":"Jackson Limousine Svc",
    "wof:placetype":"venue"
},
  "geometry": {"coordinates":[-88.866848,35.650538],"type":"Point"}
}