{
  "type": "Feature",
  "properties": {
    "addr:full":"2785 Rock Springs Rd Charlotte TN 37036",
    "addr:housenumber":"2785",
    "addr:postcode":"37036",
    "addr:street":"Rock Springs Rd",
    "iso:country":"US",
    "sg:address":"2785 Rock Springs Rd",
    "sg:city":"Charlotte",
    "sg:classifiers":[
        {
            "category":"Restaurant",
            "type":"Food & Drink"
        }
    ],
    "sg:phone":"+1 615 789 3959",
    "sg:postcode":"37036",
    "sg:province":"TN",
    "wof:name":"Lloyd & Kay's Diner",
    "wof:placetype":"venue"
},
  "geometry": {"coordinates":[-87.266339,36.31692],"type":"Point"}
}