{
  "type": "Feature",
  "properties": {
    "iso:country":"US",
    "sg:address":"408 S 10th St",
    "sg:city":"Nashville",
    "sg:classifiers":[
        {
            "category":"Retail",
            "subcategory":"Repair Shop",
            "type":"Services"
        }
    ],
    "sg:phone":"+1 615 227 0333",
    "sg:postcode":"37206",
    "sg:province":"TN",
    "sg:tags":[
        "television",
        "radio"
    ],
    "wof:name":"Huffman Electronics",
    "wof:placetype":"venue"
},
  "geometry": {"coordinates":[-86.75228,36.172263],"type":"Point"}
}