{
  "type": "Feature",
  "properties": {
    "addr:full":"405 Boyd Ave Mc Minnville TN 37110",
    "addr:housenumber":"405",
    "addr:postcode":"37110",
    "addr:street":"Boyd Ave Mc Minnville",
    "iso:country":"US",
    "sg:address":"405 Boyd Ave",
    "sg:city":"Mc Minnville",
    "sg:classifiers":[
        {
            "category":"Manufacturing",
            "subcategory":"Lumber",
            "type":"Manufacturing & Wholesale Goods"
        }
    ],
    "sg:phone":"+1 931 473 8118",
    "sg:postcode":"37110",
    "sg:province":"TN",
    "sg:tags":[
        "company",
        "logging"
    ],
    "wof:name":"Oliver Logging",
    "wof:placetype":"venue"
},
  "geometry": {"coordinates":[-85.79070900000001,35.678083],"type":"Point"}
}