{
  "type": "Feature",
  "properties": {
    "addr:full":"1158 N Main St Mt Pleasant TN 38474",
    "addr:housenumber":"1158",
    "addr:postcode":"38474",
    "addr:street":"N Main St",
    "iso:country":"US",
    "sg:address":"1158 N Main St",
    "sg:city":"Mt Pleasant",
    "sg:classifiers":[
        {
            "category":"Government",
            "subcategory":"Fire Station",
            "type":"Public Place"
        }
    ],
    "sg:phone":"+1 931 379 0361",
    "sg:postcode":"38474",
    "sg:province":"TN",
    "sg:tags":[
        "department"
    ],
    "wof:name":"Mt Pleasant Fire Chief",
    "wof:placetype":"venue"
},
  "geometry": {"coordinates":[-87.18482299999999,35.554731],"type":"Point"}
}