{
  "type": "Feature",
  "properties": {
    "addr:full":"233 Taylor Dr Piney Flats TN 37686",
    "addr:housenumber":"233",
    "addr:postcode":"37686",
    "addr:street":"Taylor Dr Piney",
    "iso:country":"US",
    "sg:address":"233 Taylor Dr",
    "sg:city":"Piney Flats",
    "sg:classifiers":[
        {
            "category":"Building & Trades",
            "subcategory":"Electrical",
            "type":"Services"
        }
    ],
    "sg:phone":"+1 423 538 3507",
    "sg:postcode":"37686",
    "sg:province":"TN",
    "sg:tags":[
        "electrical",
        "contractor"
    ],
    "wof:name":"CM Electric",
    "wof:placetype":"venue"
},
  "geometry": {"coordinates":[-82.327979,36.409392],"type":"Point"}
}