{
  "type": "Feature",
  "properties": {
    "iso:country":"US",
    "sg:address":"3700 Dickerson Pike",
    "sg:city":"Nashville",
    "sg:classifiers":[
        {
            "category":"Retail",
            "subcategory":"Auto Repair",
            "type":"Services"
        }
    ],
    "sg:phone":"+1 615 865 2602",
    "sg:postcode":"37207",
    "sg:province":"TN",
    "sg:tags":[
        "tire"
    ],
    "wof:name":"Buds Tire & Alignment",
    "wof:placetype":"venue"
},
  "geometry": {"coordinates":[-86.75761199999999,36.261157],"type":"Point"}
}