{
  "type": "Feature",
  "properties": {
    "iso:country":"US",
    "sg:address":"306 Emery Dr",
    "sg:city":"Nashville",
    "sg:classifiers":[
        {
            "category":"Building & Trades",
            "subcategory":"Plumbing",
            "type":"Services"
        }
    ],
    "sg:phone":"+1 615 889 5325",
    "sg:postcode":"37214",
    "sg:province":"TN",
    "sg:tags":[
        "plumbing",
        "contractor"
    ],
    "wof:name":"Raynes Plumbing",
    "wof:placetype":"venue"
},
  "geometry": {"coordinates":[-86.677041,36.151895],"type":"Point"}
}