{
  "type": "Feature",
  "properties": {
    "iso:country":"US",
    "sg:address":"801 N Locust Ave",
    "sg:city":"Lawrenceburg",
    "sg:classifiers":[
        {
            "category":"Autos & Motor Vehicles",
            "subcategory":"Automobile Sales",
            "type":"Retail Goods"
        }
    ],
    "sg:phone":"+1 931 762 1690",
    "sg:postcode":"38464",
    "sg:province":"TN",
    "sg:tags":[
        "car",
        "dealer"
    ],
    "wof:name":"Performance Motors",
    "wof:placetype":"venue"
},
  "geometry": {"coordinates":[-87.32730100000001,35.248425],"type":"Point"}
}