{
  "type": "Feature",
  "properties": {
    "iso:country":"US",
    "sg:address":"1277 E Shelby Dr",
    "sg:city":"Memphis",
    "sg:classifiers":[
        {
            "category":"Banks & Credit Unions",
            "subcategory":"Bank",
            "type":"Services"
        }
    ],
    "sg:phone":"+1 901 348 3622",
    "sg:postcode":"38116",
    "sg:province":"TN",
    "sg:tags":[
        "commercial",
        "saving"
    ],
    "sg:website":"http://ad.doubleclick.net/clk;223972431;41535373;d?https://www.firsttennessee.com/Banking/Main?nicamp=Brand&nichan=Directory&nisrc=yellowpages&niseg=Banks",
    "wof:name":"FIRST TENNESSEE BANK",
    "wof:placetype":"venue"
},
  "geometry": {"coordinates":[-90.021612,35.02095],"type":"Point"}
}