{
  "type": "Feature",
  "properties": {
    "iso:country":"US",
    "sg:address":"550 Price Rd",
    "sg:city":"Spring City",
    "sg:classifiers":[
        {
            "category":"Building & Trades",
            "subcategory":"Construction",
            "type":"Services"
        }
    ],
    "sg:phone":"+1 423 365 9919",
    "sg:postcode":"37381",
    "sg:province":"TN",
    "sg:tags":[
        "house"
    ],
    "wof:name":"Miller Mountain Properties",
    "wof:placetype":"venue"
},
  "geometry": {"coordinates":[-84.891085,35.678045],"type":"Point"}
}