{
  "type": "Feature",
  "properties": {
    "iso:country":"US",
    "sg:address":"205 E Weaver St",
    "sg:city":"Clinton",
    "sg:classifiers":[
        {
            "category":"Insurance",
            "subcategory":"Insurance Agent",
            "type":"Services"
        }
    ],
    "sg:phone":"+1 865 457 2968",
    "sg:postcode":"37716",
    "sg:province":"TN",
    "wof:name":"Steve Pyatt Insurance",
    "wof:placetype":"venue"
},
  "geometry": {"coordinates":[-84.128321,36.10536],"type":"Point"}
}