{
  "type": "Feature",
  "properties": {
    "addr:full":"2611 Grandview Ave Nashville TN 37211",
    "addr:housenumber":"2611",
    "addr:postcode":"37211",
    "addr:street":"Grandview Ave",
    "iso:country":"US",
    "sg:address":"2611 Grandview Ave",
    "sg:city":"Nashville",
    "sg:classifiers":[
        {
            "category":"Organizations",
            "subcategory":"Non-profit Organization",
            "type":"Services"
        }
    ],
    "sg:phone":"+1 615 251 9007",
    "sg:postcode":"37211",
    "sg:province":"TN",
    "sg:tags":[
        "charitable",
        "institution"
    ],
    "wof:name":"Charitable Services Inc",
    "wof:placetype":"venue"
},
  "geometry": {"coordinates":[-86.748441,36.1142],"type":"Point"}
}