{
  "type": "Feature",
  "properties": {
    "iso:country":"US",
    "sg:address":"3756 Ringgold Rd",
    "sg:city":"Chattanooga",
    "sg:classifiers":[
        {
            "category":"Professional",
            "subcategory":"Engineering",
            "type":"Services"
        }
    ],
    "sg:phone":"+1 423 698 4376",
    "sg:postcode":"37412",
    "sg:province":"TN",
    "sg:tags":[
        "engineer"
    ],
    "wof:name":"Bill Kinnaman Consulting Engrg",
    "wof:placetype":"venue"
},
  "geometry": {"coordinates":[-85.25626200000001,34.999278],"type":"Point"}
}