{
  "type": "Feature",
  "properties": {
    "addr:full":"1282 Union Ave Memphis TN 38104",
    "addr:housenumber":"1282",
    "addr:postcode":"38104",
    "addr:street":"Union Ave",
    "iso:country":"US",
    "sg:address":"1282 Union Ave",
    "sg:city":"Memphis",
    "sg:classifiers":[
        {
            "category":"Health Services",
            "subcategory":"Clinic",
            "type":"Services"
        }
    ],
    "sg:phone":"+1 901 722 2000",
    "sg:postcode":"38104",
    "sg:province":"TN",
    "sg:tags":[
        "rehab",
        "hosp"
    ],
    "wof:name":"HealthSouth",
    "wof:placetype":"venue"
},
  "geometry": {"coordinates":[-90.019735,35.137237],"type":"Point"}
}