{
  "type": "Feature",
  "properties": {
    "iso:country":"US",
    "sg:address":"2105 Brentridge Cir",
    "sg:city":"Antioch",
    "sg:classifiers":[
        {
            "category":"Building & Trades",
            "subcategory":"Construction",
            "type":"Services"
        }
    ],
    "sg:phone":"+1 615 445 7733",
    "sg:postcode":"37013",
    "sg:province":"TN",
    "sg:tags":[
        "contractor"
    ],
    "wof:name":"Marblelife Of Tennessee",
    "wof:placetype":"venue"
},
  "geometry": {"coordinates":[-86.67942600000001,36.047828],"type":"Point"}
}