{
  "type": "Feature",
  "properties": {
    "iso:country":"US",
    "sg:address":"17 Henry Thompson Rd",
    "sg:city":"Taft",
    "sg:classifiers":[
        {
            "category":"Utilities",
            "subcategory":"Refuse",
            "type":"Services"
        }
    ],
    "sg:phone":"+1 931 425 0038",
    "sg:postcode":"38488",
    "sg:province":"TN",
    "sg:tags":[
        "garbage",
        "system",
        "collection"
    ],
    "wof:name":"Southwest Lincoln County Conve",
    "wof:placetype":"venue"
},
  "geometry": {"coordinates":[-86.71404800000001,35.02554],"type":"Point"}
}