{
  "type": "Feature",
  "properties": {
    "addr:full":"5646 Amalie Dr Nashville TN 37211",
    "addr:housenumber":"5646",
    "addr:postcode":"37211",
    "addr:street":"Amalie Dr",
    "iso:country":"US",
    "sg:address":"5646 Amalie Dr",
    "sg:city":"Nashville",
    "sg:classifiers":[
        {
            "category":"Real Estate",
            "subcategory":"Real Estate Operator",
            "type":"Services"
        }
    ],
    "sg:phone":"+1 615 331 3888",
    "sg:postcode":"37211",
    "sg:province":"TN",
    "sg:tags":[
        "apartment"
    ],
    "wof:name":"Countrywood Apartments",
    "wof:placetype":"venue"
},
  "geometry": {"coordinates":[-86.724604,36.048046],"type":"Point"}
}