{
  "type": "Feature",
  "properties": {
    "iso:country":"US",
    "sg:address":"1102 Appleton Dr",
    "sg:city":"Nashville",
    "sg:classifiers":[
        {
            "category":"Autos & Motor Vehicles",
            "subcategory":"Auto Supplies",
            "type":"Retail Goods"
        }
    ],
    "sg:phone":"+1 615 871 4434",
    "sg:postcode":"37210",
    "sg:province":"TN",
    "wof:name":"Bft",
    "wof:placetype":"venue"
},
  "geometry": {"coordinates":[-86.70175500000001,36.147972],"type":"Point"}
}