{
  "type": "Feature",
  "properties": {
    "iso:country":"US",
    "sg:address":"2001 E Main St",
    "sg:city":"Rogersville",
    "sg:classifiers":[
        {
            "category":"Education",
            "subcategory":"School",
            "type":"Public Place"
        }
    ],
    "sg:phone":"+1 423 272 9110",
    "sg:postcode":"37857",
    "sg:province":"TN",
    "wof:name":"Joseph Rogers Primary School",
    "wof:placetype":"venue"
},
  "geometry": {"coordinates":[-82.973597,36.432213],"type":"Point"}
}