{
  "type": "Feature",
  "properties": {
    "iso:country":"US",
    "sg:address":"32 W E H Crump Blvd",
    "sg:city":"Memphis",
    "sg:classifiers":[
        {
            "category":"Social Services",
            "type":"Services"
        }
    ],
    "sg:phone":"+1 901 947 8640",
    "sg:postcode":"38106",
    "sg:province":"TN",
    "sg:tags":[
        "probation"
    ],
    "wof:name":"Probation & Parole Ofc",
    "wof:placetype":"venue"
},
  "geometry": {"coordinates":[-90.062792,35.124785],"type":"Point"}
}