{
  "type": "Feature",
  "properties": {
    "iso:country":"US",
    "sg:address":"1400 18th Ave S",
    "sg:city":"Nashville",
    "sg:classifiers":[
        {
            "category":"Arts & Performance",
            "subcategory":"Theater",
            "type":"Entertainment"
        }
    ],
    "sg:phone":"+1 615 346 9000",
    "sg:postcode":"37212",
    "sg:province":"TN",
    "sg:tags":[
        "bureau",
        "concert"
    ],
    "sg:website":"www.cc.com",
    "wof:name":"S F X Nashville",
    "wof:placetype":"venue"
},
  "geometry": {"coordinates":[-86.796316,36.140387],"type":"Point"}
}