{
  "type": "Feature",
  "properties": {
    "iso:country":"US",
    "sg:address":"2607 Crump Dr",
    "sg:city":"Nashville",
    "sg:classifiers":[
        {
            "category":"Shopping",
            "subcategory":"Gifts & Souvenirs",
            "type":"Retail Goods"
        }
    ],
    "sg:phone":"+1 615 883 6887",
    "sg:postcode":"37214",
    "sg:province":"TN",
    "sg:tags":[
        "shop",
        "car",
        "museum"
    ],
    "wof:name":"Cars of The Stars",
    "wof:placetype":"venue"
},
  "geometry": {"coordinates":[-86.67449000000001,36.171339],"type":"Point"}
}