{
  "type": "Feature",
  "properties": {
    "iso:country":"US",
    "sg:address":"1055 Mineral Wells Ave",
    "sg:city":"Paris",
    "sg:classifiers":[
        {
            "category":"Shopping",
            "subcategory":"Used Merchandise",
            "type":"Retail Goods"
        }
    ],
    "sg:phone":"+1 731 642 0073",
    "sg:postcode":"38242",
    "sg:province":"TN",
    "sg:tags":[
        "shop",
        "consignment"
    ],
    "wof:name":"Stepp By Stepp Consignment",
    "wof:placetype":"venue"
},
  "geometry": {"coordinates":[-88.31181599999999,36.2876],"type":"Point"}
}