{
  "type": "Feature",
  "properties": {
    "iso:country":"US",
    "sg:address":"5215 Newport Hwy",
    "sg:city":"Greeneville",
    "sg:classifiers":[
        {
            "category":"Building & Trades",
            "subcategory":"Construction",
            "type":"Services"
        }
    ],
    "sg:phone":"+1 423 787 7773",
    "sg:postcode":"37743",
    "sg:province":"TN",
    "sg:tags":[
        "maker",
        "cabinet"
    ],
    "wof:name":"Gefellers Cabinetry",
    "wof:placetype":"venue"
},
  "geometry": {"coordinates":[-82.893677,36.126462],"type":"Point"}
}