{
  "type": "Feature",
  "properties": {
    "iso:country":"US",
    "sg:address":"740 US Hwy 64",
    "sg:city":"Adamsville",
    "sg:classifiers":[
        {
            "category":"Personal",
            "type":"Services"
        }
    ],
    "sg:phone":"+1 731 632 9449",
    "sg:postcode":"38310",
    "sg:province":"TN",
    "wof:name":"Immortal Art",
    "wof:placetype":"venue"
},
  "geometry": {"coordinates":[-88.356245,35.226071],"type":"Point"}
}