{
  "type": "Feature",
  "properties": {
    "addr:full":"4742 State Hwy 58 Chattanooga TN 37416",
    "addr:housenumber":"4742",
    "addr:postcode":"37416",
    "addr:street":"State Hwy 58",
    "iso:country":"US",
    "sg:address":"4742 State Hwy 58",
    "sg:city":"Chattanooga",
    "sg:classifiers":[
        {
            "category":"Building & Trades",
            "subcategory":"Equipment Rental",
            "type":"Services"
        }
    ],
    "sg:phone":"+1 423 296 9991",
    "sg:postcode":"37416",
    "sg:province":"TN",
    "sg:tags":[
        "appliance"
    ],
    "sg:website":"www.rentway.com",
    "wof:name":"Rent Way",
    "wof:placetype":"venue"
},
  "geometry": {"coordinates":[-85.188366,35.088384],"type":"Point"}
}