{
  "type": "Feature",
  "properties": {
    "addr:full":"2455 N 2nd St Memphis TN 38127",
    "addr:housenumber":"2455",
    "addr:postcode":"38127",
    "addr:street":"N 2Nd St",
    "iso:country":"US",
    "sg:address":"2455 N 2nd St",
    "sg:city":"Memphis",
    "sg:classifiers":[
        {
            "category":"Freight",
            "type":"Transportation"
        }
    ],
    "sg:phone":"+1 901 358 0151",
    "sg:postcode":"38127",
    "sg:province":"TN",
    "sg:tags":[
        "cargo",
        "handler",
        "marine"
    ],
    "wof:name":"Dupont",
    "wof:placetype":"venue"
},
  "geometry": {"coordinates":[-90.0532,35.20021],"type":"Point"}
}