{
  "type": "Feature",
  "properties": {
    "iso:country":"US",
    "sg:address":"442 E Economy Rd",
    "sg:city":"Morristown",
    "sg:classifiers":[
        {
            "category":"Professional",
            "subcategory":"Computer Services",
            "type":"Services"
        },
        {
            "category":"Professional",
            "subcategory":"Employment Agencies",
            "type":"Services"
        }
    ],
    "sg:phone":"+1 423 587 3189",
    "sg:postcode":"37814",
    "sg:province":"TN",
    "sg:tags":[
        "datum",
        "help",
        "contractor"
    ],
    "wof:name":"Craig Services L P",
    "wof:placetype":"venue"
},
  "geometry": {"coordinates":[-83.316903,36.208284],"type":"Point"}
}