{
  "type": "Feature",
  "properties": {
    "iso:country":"US",
    "sg:address":"521 W Poplar Ave",
    "sg:city":"Collierville",
    "sg:classifiers":[
        {
            "category":"Shopping",
            "subcategory":"Used Merchandise",
            "type":"Retail Goods"
        }
    ],
    "sg:phone":"+1 901 854 7063",
    "sg:postcode":"38017",
    "sg:province":"TN",
    "wof:name":"Panache Antiques Court",
    "wof:placetype":"venue"
},
  "geometry": {"coordinates":[-89.677972,35.045756],"type":"Point"}
}