{
  "type": "Feature",
  "properties": {
    "iso:country":"US",
    "sg:address":"150 Cherokee St",
    "sg:city":"Kingsport",
    "sg:classifiers":[
        {
            "category":"Professional",
            "subcategory":"Lawyer & Legal Services",
            "type":"Services"
        }
    ],
    "sg:phone":"+1 423 378 5866",
    "sg:postcode":"37660",
    "sg:province":"TN",
    "wof:name":"Toohey Mark H Attorney At Law",
    "wof:placetype":"venue"
},
  "geometry": {"coordinates":[-82.559335,36.54464],"type":"Point"}
}