{
  "type": "Feature",
  "properties": {
    "addr:full":"154 E Meeting St Dandridge TN 37725",
    "addr:housenumber":"154",
    "addr:postcode":"37725",
    "addr:street":"E Meeting St",
    "iso:country":"US",
    "sg:address":"154 E Meeting St",
    "sg:city":"Dandridge",
    "sg:classifiers":[
        {
            "category":"Insurance",
            "subcategory":"Insurance Agent",
            "type":"Services"
        }
    ],
    "sg:phone":"+1 865 397 3117",
    "sg:postcode":"37725",
    "sg:province":"TN",
    "wof:name":"Farm Bureau Insurance",
    "wof:placetype":"venue"
},
  "geometry": {"coordinates":[-83.410853,36.019366],"type":"Point"}
}