{
  "type": "Feature",
  "properties": {
    "iso:country":"US",
    "sg:address":"88 N Main St",
    "sg:city":"Collierville",
    "sg:classifiers":[
        {
            "category":"Home & Garden",
            "subcategory":"Home Furnishings",
            "type":"Retail Goods"
        }
    ],
    "sg:phone":"+1 901 854 5000",
    "sg:postcode":"38017",
    "sg:province":"TN",
    "sg:tags":[
        "pottery"
    ],
    "wof:name":"Courtyard Clay",
    "wof:placetype":"venue"
},
  "geometry": {"coordinates":[-89.664272,35.042682],"type":"Point"}
}