{
  "type": "Feature",
  "properties": {
    "iso:country":"US",
    "sg:address":"607 Bus Park Ln",
    "sg:city":"Knoxville",
    "sg:classifiers":[
        {
            "category":"Wholesale",
            "subcategory":"Stationery",
            "type":"Manufacturing & Wholesale Goods"
        },
        {
            "category":"Shopping",
            "subcategory":"Stationery & Office Supplies",
            "type":"Retail Goods"
        }
    ],
    "sg:phone":"+1 865 414 1102",
    "sg:postcode":"37932",
    "sg:province":"TN",
    "sg:website":"www.corporateexpress.com",
    "wof:name":"Corporate Express Inc",
    "wof:placetype":"venue"
},
  "geometry": {"coordinates":[-84.137079,35.916289],"type":"Point"}
}