{
  "type": "Feature",
  "properties": {
    "addr:full":"518 Scholarship Dr Nashville TN 37209",
    "addr:housenumber":"518",
    "addr:postcode":"37209",
    "addr:street":"Scholarship Dr",
    "iso:country":"US",
    "sg:address":"518 Scholarship Dr",
    "sg:city":"Nashville",
    "sg:classifiers":[
        {
            "category":"Organizations",
            "subcategory":"Religious Organization",
            "type":"Services"
        }
    ],
    "sg:phone":"+1 615 356 0405",
    "sg:postcode":"37209",
    "sg:province":"TN",
    "wof:name":"Family Ministries Inc",
    "wof:placetype":"venue"
},
  "geometry": {"coordinates":[-86.88318,36.152215],"type":"Point"}
}