{
  "type": "Feature",
  "properties": {
    "addr:full":"568 Waldron Rd La Vergne TN 37086",
    "addr:housenumber":"568",
    "addr:postcode":"37086",
    "addr:street":"Waldron Rd",
    "iso:country":"US",
    "sg:address":"568 Waldron Rd",
    "sg:city":"La Vergne",
    "sg:classifiers":[
        {
            "category":"Bars & Pubs",
            "type":"Food & Drink"
        }
    ],
    "sg:phone":"+1 615 213 1107",
    "sg:postcode":"37086",
    "sg:province":"TN",
    "sg:tags":[
        "drinking"
    ],
    "wof:name":"Curve Sports Bar & Grill",
    "wof:placetype":"venue"
},
  "geometry": {"coordinates":[-86.584276,36.01595],"type":"Point"}
}