{
  "type": "Feature",
  "properties": {
    "iso:country":"US",
    "sg:address":"1633 Bartlett Rd",
    "sg:city":"Bartlett",
    "sg:classifiers":[
        {
            "category":"Home & Garden",
            "subcategory":"Home Furnishings",
            "type":"Retail Goods"
        }
    ],
    "sg:phone":"+1 901 382 0800",
    "sg:postcode":"38134",
    "sg:province":"TN",
    "sg:tags":[
        "venetian",
        "blind"
    ],
    "wof:name":"Pro Blind",
    "wof:placetype":"venue"
},
  "geometry": {"coordinates":[-89.87933099999999,35.167757],"type":"Point"}
}