{
  "type": "Feature",
  "properties": {
    "iso:country":"US",
    "sg:address":"1278 Oscar Crowell Rd",
    "sg:city":"Beechgrove",
    "sg:classifiers":[
        {
            "category":"Manufacturing",
            "subcategory":"Printing",
            "type":"Manufacturing & Wholesale Goods"
        }
    ],
    "sg:phone":"+1 931 394 2515",
    "sg:postcode":"37018",
    "sg:province":"TN",
    "sg:tags":[
        "screen"
    ],
    "wof:name":"Innovations Screen Printing",
    "wof:placetype":"venue"
},
  "geometry": {"coordinates":[-86.228669,35.61081],"type":"Point"}
}