{
  "type": "Feature",
  "properties": {
    "addr:full":"878 Willow Tree Cir Cordova TN 38018",
    "addr:housenumber":"878",
    "addr:postcode":"38018",
    "addr:street":"Willow Tree Cir",
    "iso:country":"US",
    "sg:address":"878 Willow Tree Cir",
    "sg:city":"Cordova",
    "sg:classifiers":[
        {
            "category":"Health Services",
            "subcategory":"Doctor",
            "type":"Services"
        }
    ],
    "sg:phone":"+1 901 754 0191",
    "sg:postcode":"38018",
    "sg:province":"TN",
    "wof:name":"Southaven Family Dentistry",
    "wof:placetype":"venue"
},
  "geometry": {"coordinates":[-89.792547,35.147589],"type":"Point"}
}