{
  "type": "Feature",
  "properties": {
    "iso:country":"US",
    "sg:address":"5260 Edenshire Ave",
    "sg:city":"Memphis",
    "sg:classifiers":[
        {
            "category":"Personal",
            "subcategory":"Beauty Salon",
            "type":"Services"
        }
    ],
    "sg:phone":"+1 901 277 8403",
    "sg:postcode":"38117",
    "sg:province":"TN",
    "sg:tags":[
        "shop"
    ],
    "wof:name":"Auto Headliners",
    "wof:placetype":"venue"
},
  "geometry": {"coordinates":[-89.887925,35.101742],"type":"Point"}
}