{
  "type": "Feature",
  "properties": {
    "iso:country":"US",
    "sg:address":"198 Woodruff Rd",
    "sg:city":"Dresden",
    "sg:classifiers":[
        {
            "category":"Wholesale",
            "subcategory":"Farm Supplies",
            "type":"Manufacturing & Wholesale Goods"
        }
    ],
    "sg:phone":"+1 731 364 2065",
    "sg:postcode":"38225",
    "sg:province":"TN",
    "sg:tags":[
        "livestock"
    ],
    "wof:name":"Ralph Cooper",
    "wof:placetype":"venue"
},
  "geometry": {"coordinates":[-88.655253,36.311843],"type":"Point"}
}