{
  "type": "Feature",
  "properties": {
    "iso:country":"US",
    "sg:address":"1909 N Economy Rd",
    "sg:city":"Morristown",
    "sg:classifiers":[
        {
            "category":"Autos & Motor Vehicles",
            "subcategory":"Fuel & Gas Station",
            "type":"Retail Goods"
        }
    ],
    "sg:phone":"+1 423 581 4117",
    "sg:postcode":"37814",
    "sg:province":"TN",
    "sg:tags":[
        "oil"
    ],
    "wof:name":"Plaza Shell",
    "wof:placetype":"venue"
},
  "geometry": {"coordinates":[-83.319486,36.211014],"type":"Point"}
}