{
  "type": "Feature",
  "properties": {
    "addr:full":"7340 Glastonbury Rd Knoxville TN 37931",
    "addr:housenumber":"7340",
    "addr:postcode":"37931",
    "addr:street":"Glastonbury Rd",
    "iso:country":"US",
    "sg:address":"7340 Glastonbury Rd",
    "sg:city":"Knoxville",
    "sg:classifiers":[
        {
            "category":"Building & Trades",
            "subcategory":"Landscaping Services",
            "type":"Services"
        }
    ],
    "sg:phone":"+1 865 742 5830",
    "sg:postcode":"37931",
    "sg:province":"TN",
    "sg:tags":[
        "landscape",
        "snowplow"
    ],
    "wof:name":"Solid Rock Lawncare Inc",
    "wof:placetype":"venue"
},
  "geometry": {"coordinates":[-84.10741,35.994198],"type":"Point"}
}