{
  "type": "Feature",
  "properties": {
    "iso:country":"US",
    "sg:address":"4710 Mallard Ridge Dr",
    "sg:city":"Memphis",
    "sg:classifiers":[
        {
            "category":"Shopping",
            "subcategory":"Clothing, Apparel, & Fashions",
            "type":"Retail Goods"
        }
    ],
    "sg:phone":"+1 901 795 1848",
    "sg:postcode":"38141",
    "sg:province":"TN",
    "sg:tags":[
        "infant",
        "wear"
    ],
    "wof:name":"Kids For Less",
    "wof:placetype":"venue"
},
  "geometry": {"coordinates":[-89.84475500000001,35.01986],"type":"Point"}
}