{
  "type": "Feature",
  "properties": {
    "iso:country":"US",
    "sg:address":"100 N Main St",
    "sg:city":"Memphis",
    "sg:classifiers":[
        {
            "category":"Professional",
            "subcategory":"Business Services",
            "type":"Services"
        }
    ],
    "sg:phone":"+1 901 528 1901",
    "sg:postcode":"38103",
    "sg:province":"TN",
    "sg:tags":[
        "process",
        "server"
    ],
    "sg:website":"www.efs-private-process.com",
    "wof:name":"EFS Private Process",
    "wof:placetype":"venue"
},
  "geometry": {"coordinates":[-90.051801,35.147461],"type":"Point"}
}