{
  "type": "Feature",
  "properties": {
    "addr:full":"107 Harding Pl Nashville TN 37205",
    "addr:housenumber":"107",
    "addr:postcode":"37205",
    "addr:street":"Harding Pl",
    "iso:country":"US",
    "sg:address":"107 Harding Pl",
    "sg:city":"Nashville",
    "sg:classifiers":[
        {
            "category":"Social Services",
            "subcategory":"Adult Care",
            "type":"Services"
        }
    ],
    "sg:phone":"+1 615 353 1990",
    "sg:postcode":"37205",
    "sg:province":"TN",
    "sg:tags":[
        "home",
        "residential"
    ],
    "wof:name":"Homewood Residence-Brookmont",
    "wof:placetype":"venue"
},
  "geometry": {"coordinates":[-86.867994,36.101589],"type":"Point"}
}