{
  "type": "Feature",
  "properties": {
    "addr:full":"328 S Mill Ave Dyersburg TN 38024",
    "addr:housenumber":"328",
    "addr:postcode":"38024",
    "addr:street":"S Mill Ave",
    "iso:country":"US",
    "sg:address":"328 S Mill Ave",
    "sg:city":"Dyersburg",
    "sg:classifiers":[
        {
            "category":"Social Services",
            "type":"Services"
        }
    ],
    "sg:phone":"+1 731 286 5117",
    "sg:postcode":"38024",
    "sg:province":"TN",
    "sg:tags":[
        "organization",
        "welfare"
    ],
    "wof:name":"Salvation Army",
    "wof:placetype":"venue"
},
  "geometry": {"coordinates":[-89.387069,36.030959],"type":"Point"}
}