{
  "type": "Feature",
  "properties": {
    "addr:full":"106 Appomattox Ct Murfreesboro TN 37130",
    "addr:housenumber":"106",
    "addr:postcode":"37130",
    "addr:street":"Appomattox Ct",
    "iso:country":"US",
    "sg:address":"106 Appomattox Ct",
    "sg:city":"Murfreesboro",
    "sg:classifiers":[
        {
            "category":"Social Services",
            "subcategory":"Job Training",
            "type":"Services"
        }
    ],
    "sg:phone":"+1 615 907 6290",
    "sg:postcode":"37130",
    "sg:province":"TN",
    "sg:tags":[
        "career",
        "counseling",
        "vocational"
    ],
    "wof:name":"Career Concepts",
    "wof:placetype":"venue"
},
  "geometry": {"coordinates":[-86.34526700000001,35.949113],"type":"Point"}
}