{
  "type": "Feature",
  "properties": {
    "iso:country":"US",
    "sg:address":"506 Municipal Dr",
    "sg:city":"Jefferson City",
    "sg:classifiers":[
        {
            "category":"Wholesale",
            "subcategory":"Construction Materials",
            "type":"Manufacturing & Wholesale Goods"
        }
    ],
    "sg:phone":"+1 865 471 6300",
    "sg:postcode":"37760",
    "sg:province":"TN",
    "sg:tags":[
        "wooden",
        "door"
    ],
    "wof:name":"Ameridoor Inc",
    "wof:placetype":"venue"
},
  "geometry": {"coordinates":[-83.48803700000001,36.133033],"type":"Point"}
}