{
  "type": "Feature",
  "properties": {
    "iso:country":"US",
    "sg:address":"1506 Dodds Ave",
    "sg:city":"Chattanooga",
    "sg:classifiers":[
        {
            "category":"Retail",
            "subcategory":"Repair Shop",
            "type":"Services"
        }
    ],
    "sg:phone":"+1 423 698 7142",
    "sg:postcode":"37404",
    "sg:province":"TN",
    "sg:tags":[
        "electrical"
    ],
    "wof:name":"City Maintenance",
    "wof:placetype":"venue"
},
  "geometry": {"coordinates":[-85.270376,35.020806],"type":"Point"}
}