{
  "type": "Feature",
  "properties": {
    "iso:country":"US",
    "sg:address":"2270 S Parkway E",
    "sg:city":"Memphis",
    "sg:phone":"+1 901 278 5052",
    "sg:postcode":"38114",
    "sg:province":"TN",
    "sg:website":"http://www.forrent.com/apartment-community-profile/1032758.php?cmp=CAC-CSearchProfile",
    "wof:name":"Salem Manor",
    "wof:placetype":"venue"
},
  "geometry": {"coordinates":[-89.987662,35.114682],"type":"Point"}
}