{
  "type": "Feature",
  "properties": {
    "iso:country":"US",
    "sg:address":"3686 Oakdale Rd",
    "sg:city":"Westmoreland",
    "sg:classifiers":[
        {
            "category":"Building & Trades",
            "subcategory":"Cleaning & Sanitation",
            "type":"Services"
        }
    ],
    "sg:phone":"+1 615 666 5968",
    "sg:postcode":"37186",
    "sg:province":"TN",
    "sg:tags":[
        "maintenance"
    ],
    "wof:name":"Patsys Cleaning Svc",
    "wof:placetype":"venue"
},
  "geometry": {"coordinates":[-86.124379,36.561708],"type":"Point"}
}