{
  "type": "Feature",
  "properties": {
    "addr:full":"236 Clearview St Johnson City TN 37615",
    "addr:housenumber":"236",
    "addr:postcode":"37615",
    "addr:street":"Clearview St",
    "iso:country":"US",
    "sg:address":"236 Clearview St",
    "sg:city":"Johnson City",
    "sg:classifiers":[
        {
            "category":"Shopping",
            "subcategory":"Optical Goods",
            "type":"Retail Goods"
        }
    ],
    "sg:phone":"+1 423 477 3208",
    "sg:postcode":"37615",
    "sg:province":"TN",
    "sg:tags":[
        "optician"
    ],
    "sg:website":"www.visionworksllc.net",
    "wof:name":"Visionworks",
    "wof:placetype":"venue"
},
  "geometry": {"coordinates":[-82.42746200000001,36.40016],"type":"Point"}
}