{
  "type": "Feature",
  "properties": {
    "addr:full":"89 Trenton Hwy Bradford TN 38316",
    "addr:housenumber":"89",
    "addr:postcode":"38316",
    "addr:street":"Trenton Hwy",
    "iso:country":"US",
    "sg:address":"89 Trenton Hwy",
    "sg:city":"Bradford",
    "sg:classifiers":[
        {
            "category":"Retail",
            "subcategory":"Auto Repair",
            "type":"Services"
        }
    ],
    "sg:phone":"+1 731 742 3433",
    "sg:postcode":"38316",
    "sg:province":"TN",
    "sg:tags":[
        "general"
    ],
    "wof:name":"Clark Auto Trim",
    "wof:placetype":"venue"
},
  "geometry": {"coordinates":[-88.84929700000001,36.066128],"type":"Point"}
}