{
  "type": "Feature",
  "properties": {
    "addr:full":"2797 Anes Station Rd Lewisburg TN 37091",
    "addr:housenumber":"2797",
    "addr:postcode":"37091",
    "addr:street":"Anes Station Rd",
    "iso:country":"US",
    "sg:address":"2797 Anes Station Rd",
    "sg:city":"Lewisburg",
    "sg:phone":"+1 931 359 9004",
    "sg:postcode":"37091",
    "sg:province":"TN",
    "sg:tags":[
        "farm",
        "corn",
        "dairy"
    ],
    "wof:name":"Gilbert Hunter",
    "wof:placetype":"venue"
},
  "geometry": {"coordinates":[-86.75540100000001,35.552608],"type":"Point"}
}