{
  "type": "Feature",
  "properties": {
    "iso:country":"US",
    "sg:address":"930 N 1st St",
    "sg:city":"Pulaski",
    "sg:classifiers":[
        {
            "category":"Bars & Pubs",
            "type":"Food & Drink"
        }
    ],
    "sg:phone":"+1 931 363 2188",
    "sg:postcode":"38478",
    "sg:province":"TN",
    "sg:tags":[
        "drinking"
    ],
    "wof:name":"Night Life",
    "wof:placetype":"venue"
},
  "geometry": {"coordinates":[-87.02682799999999,35.209119],"type":"Point"}
}