{
  "type": "Feature",
  "properties": {
    "iso:country":"US",
    "sg:address":"5105 S National Dr",
    "sg:city":"Knoxville",
    "sg:classifiers":[
        {
            "category":"Manufacturing",
            "subcategory":"Electronics",
            "type":"Manufacturing & Wholesale Goods"
        }
    ],
    "sg:phone":"+1 865 673 0700",
    "sg:postcode":"37914",
    "sg:province":"TN",
    "sg:tags":[
        "equipment",
        "electronic",
        "supply"
    ],
    "sg:website":"www.panasonic.com",
    "wof:name":"Panasonic",
    "wof:placetype":"venue"
},
  "geometry": {"coordinates":[-83.837605,35.944292],"type":"Point"}
}