{
  "type": "Feature",
  "properties": {
    "iso:country":"US",
    "sg:address":"2030 Falling Waters Rd",
    "sg:city":"Knoxville",
    "sg:classifiers":[
        {
            "category":"Real Estate",
            "subcategory":"Real Estate Operator",
            "type":"Services"
        }
    ],
    "sg:phone":"+1 865 584 6905",
    "sg:postcode":"37922",
    "sg:province":"TN",
    "sg:tags":[
        "building",
        "parks"
    ],
    "wof:name":"One Falling Water",
    "wof:placetype":"venue"
},
  "geometry": {"coordinates":[-84.07058499999999,35.860751],"type":"Point"}
}