{
  "type": "Feature",
  "properties": {
    "addr:full":"1600 Lone Oak Rd Johnson City TN 37604",
    "addr:housenumber":"1600",
    "addr:postcode":"37604",
    "addr:street":"Lone Oak Rd",
    "iso:country":"US",
    "sg:address":"1600 Lone Oak Rd",
    "sg:city":"Johnson City",
    "sg:classifiers":[
        {
            "category":"Professional",
            "subcategory":"Business Services",
            "type":"Services"
        }
    ],
    "sg:phone":"+1 423 928 5854",
    "sg:postcode":"37604",
    "sg:province":"TN",
    "wof:name":"Tennissee Coupon Connecti",
    "wof:placetype":"venue"
},
  "geometry": {"coordinates":[-82.38381,36.286455],"type":"Point"}
}