{
  "type": "Feature",
  "properties": {
    "iso:country":"US",
    "sg:address":"3686 Wayne Ave",
    "sg:city":"Memphis",
    "sg:classifiers":[
        {
            "category":"Shopping",
            "subcategory":"Computers & Home Electronics",
            "type":"Retail Goods"
        }
    ],
    "sg:phone":"+1 901 327 1927",
    "sg:postcode":"38122",
    "sg:province":"TN",
    "wof:name":"Beyond Belief Car Audio & Elec",
    "wof:placetype":"venue"
},
  "geometry": {"coordinates":[-89.938609,35.160971],"type":"Point"}
}