{
  "type": "Feature",
  "properties": {
    "iso:country":"US",
    "sg:address":"205 Northgate Mall",
    "sg:city":"Chattanooga",
    "sg:classifiers":[
        {
            "category":"Shopping",
            "subcategory":"Gifts & Souvenirs",
            "type":"Retail Goods"
        }
    ],
    "sg:phone":"+1 423 870 3080",
    "sg:postcode":"37415",
    "sg:province":"TN",
    "wof:name":"Add 2 Home",
    "wof:placetype":"venue"
},
  "geometry": {"coordinates":[-85.244488,35.137227],"type":"Point"}
}