{
  "type": "Feature",
  "properties": {
    "iso:country":"US",
    "sg:address":"111 N Columbia Ave",
    "sg:city":"Lawrenceburg",
    "sg:classifiers":[
        {
            "category":"Shopping",
            "type":"Retail Goods"
        }
    ],
    "sg:phone":"+1 931 762 9462",
    "sg:postcode":"38464",
    "sg:province":"TN",
    "sg:tags":[
        "p",
        "hospital",
        "equipment",
        "through",
        "subsidiary",
        "rental"
    ],
    "wof:name":"Medi-Quip Inc",
    "wof:placetype":"venue"
},
  "geometry": {"coordinates":[-87.33345,35.241493],"type":"Point"}
}