{
  "type": "Feature",
  "properties": {
    "addr:full":"830 Crescent Centre Dr, Suite 510 Franklin TN 37067",
    "addr:housenumber":"830",
    "addr:postcode":"37067",
    "addr:street":"Crescent Centre Dr Suite 510",
    "iso:country":"US",
    "sg:address":"830 Crescent Centre Dr, Suite 510",
    "sg:city":"Franklin",
    "sg:classifiers":[
        {
            "category":"Professional",
            "subcategory":"Computer Services",
            "type":"Services"
        }
    ],
    "sg:phone":"+1 615 261 7600",
    "sg:postcode":"37067",
    "sg:province":"TN",
    "sg:website":"http://www.conclusivemarketing.com/",
    "wof:name":"Conclusive Marketing",
    "wof:placetype":"venue"
},
  "geometry": {"coordinates":[-86.810445,35.943455],"type":"Point"}
}