{
  "type": "Feature",
  "properties": {
    "iso:country":"US",
    "sg:address":"3277 Frayser View Dr",
    "sg:city":"Memphis",
    "sg:classifiers":[
        {
            "category":"Bars & Pubs",
            "type":"Food & Drink"
        }
    ],
    "sg:phone":"+1 901 357 0441",
    "sg:postcode":"38127",
    "sg:province":"TN",
    "sg:tags":[
        "drinking"
    ],
    "wof:name":"You Thirsty",
    "wof:placetype":"venue"
},
  "geometry": {"coordinates":[-89.99703599999999,35.216555],"type":"Point"}
}