{
  "type": "Feature",
  "properties": {
    "addr:full":"11399 Glen Birnham Rd Eads TN 38028",
    "addr:housenumber":"11399",
    "addr:postcode":"38028",
    "addr:street":"Glen Birnham Rd",
    "iso:country":"US",
    "sg:address":"11399 Glen Birnham Rd",
    "sg:city":"Eads",
    "sg:classifiers":[
        {
            "category":"Real Estate",
            "subcategory":"Real Estate Agent",
            "type":"Services"
        }
    ],
    "sg:phone":"+1 901 853 6434",
    "sg:postcode":"38028",
    "sg:province":"TN",
    "sg:tags":[
        "investment"
    ],
    "wof:name":"Cypress Capitol Partners",
    "wof:placetype":"venue"
},
  "geometry": {"coordinates":[-89.682757,35.146969],"type":"Point"}
}