{
  "type": "Feature",
  "properties": {
    "iso:country":"US",
    "sg:address":"851 Jefferson St",
    "sg:city":"Nashville",
    "sg:classifiers":[
        {
            "category":"Freight",
            "type":"Transportation"
        }
    ],
    "sg:phone":"+1 615 373 3834",
    "sg:postcode":"37208",
    "sg:province":"TN",
    "sg:tags":[
        "mover"
    ],
    "wof:name":"Anew Cannonburgh Moving & Stge",
    "wof:placetype":"venue"
},
  "geometry": {"coordinates":[-86.791456,36.17319],"type":"Point"}
}