{
  "type": "Feature",
  "properties": {
    "iso:country":"US",
    "sg:address":"165 S Arrowhead Dr",
    "sg:city":"Mc Minnville",
    "sg:classifiers":[
        {
            "category":"Shopping",
            "type":"Retail Goods"
        }
    ],
    "sg:phone":"+1 931 473 1711",
    "sg:postcode":"37110",
    "sg:province":"TN",
    "sg:tags":[
        "merchandise"
    ],
    "wof:name":"Unit Specialties",
    "wof:placetype":"venue"
},
  "geometry": {"coordinates":[-85.800775,35.669384],"type":"Point"}
}