{
  "type": "Feature",
  "properties": {
    "addr:full":"725 Old Hickory Blvd Jackson TN 38305",
    "addr:housenumber":"725",
    "addr:postcode":"38305",
    "addr:street":"Old Hickory Blvd",
    "iso:country":"US",
    "sg:address":"725 Old Hickory Blvd",
    "sg:city":"Jackson",
    "sg:classifiers":[
        {
            "category":"Professional",
            "subcategory":"Accounting & Tax Preparation",
            "type":"Services"
        }
    ],
    "sg:phone":"+1 731 664 7550",
    "sg:postcode":"38305",
    "sg:province":"TN",
    "sg:tags":[
        "return"
    ],
    "wof:name":"Jackson Hewitt Tax Service",
    "wof:placetype":"venue"
},
  "geometry": {"coordinates":[-88.85366999999999,35.656647],"type":"Point"}
}