{
  "type": "Feature",
  "properties": {
    "iso:country":"US",
    "sg:address":"391 W Bockman Way",
    "sg:city":"Sparta",
    "sg:classifiers":[
        {
            "category":"Personal",
            "subcategory":"Beauty Salon",
            "type":"Services"
        }
    ],
    "sg:phone":"+1 931 836 6490",
    "sg:postcode":"38583",
    "sg:province":"TN",
    "sg:tags":[
        "shop"
    ],
    "wof:name":"Fashions In Hair",
    "wof:placetype":"venue"
},
  "geometry": {"coordinates":[-85.471022,35.928886],"type":"Point"}
}