{
  "type": "Feature",
  "properties": {
    "iso:country":"US",
    "sg:address":"21 Gibson Hwy",
    "sg:city":"Milan",
    "sg:classifiers":[
        {
            "category":"Health Services",
            "subcategory":"Medical Lab",
            "type":"Services"
        }
    ],
    "sg:phone":"+1 731 686 2827",
    "sg:postcode":"38358",
    "sg:province":"TN",
    "sg:tags":[
        "laboratory",
        "dental"
    ],
    "wof:name":"Jim's Dental Arts Lab",
    "wof:placetype":"venue"
},
  "geometry": {"coordinates":[-88.782262,35.903283],"type":"Point"}
}