{
  "type": "Feature",
  "properties": {
    "iso:country":"US",
    "sg:address":"2728 Moss Valley Dr",
    "sg:city":"Memphis",
    "sg:classifiers":[
        {
            "category":"Real Estate",
            "subcategory":"Real Estate Agent",
            "type":"Services"
        }
    ],
    "sg:phone":"+1 901 379 1349",
    "sg:postcode":"38133",
    "sg:province":"TN",
    "wof:name":"James F Realtor Vinson",
    "wof:placetype":"venue"
},
  "geometry": {"coordinates":[-89.832026,35.201822],"type":"Point"}
}