{
  "type": "Feature",
  "properties": {
    "iso:country":"US",
    "sg:address":"820 W 14th St Ct",
    "sg:city":"Chattanooga",
    "sg:classifiers":[
        {
            "category":"Personal",
            "subcategory":"Beauty Salon",
            "type":"Services"
        }
    ],
    "sg:phone":"+1 423 267 0277",
    "sg:postcode":"37402",
    "sg:province":"TN",
    "wof:name":"Shonda's House Of Style",
    "wof:placetype":"venue"
},
  "geometry": {"coordinates":[-85.31894800000001,35.040938],"type":"Point"}
}