{
  "type": "Feature",
  "properties": {
    "addr:full":"724 S Ellington Pkwy Lewisburg TN 37091",
    "addr:housenumber":"724",
    "addr:postcode":"37091",
    "addr:street":"S Ellington Pkwy",
    "iso:country":"US",
    "sg:address":"724 S Ellington Pkwy",
    "sg:city":"Lewisburg",
    "sg:classifiers":[
        {
            "category":"Wholesale",
            "subcategory":"Farm Supplies",
            "type":"Manufacturing & Wholesale Goods"
        }
    ],
    "sg:phone":"+1 931 359 6493",
    "sg:postcode":"37091",
    "sg:province":"TN",
    "sg:tags":[
        "feed",
        "hardware"
    ],
    "wof:name":"Lewisburg Farm Center",
    "wof:placetype":"venue"
},
  "geometry": {"coordinates":[-86.774734,35.438258],"type":"Point"}
}