{
  "type": "Feature",
  "properties": {
    "iso:country":"US",
    "sg:address":"4888 Rocky Point Rd",
    "sg:city":"Cookeville",
    "sg:classifiers":[
        {
            "category":"Utilities",
            "subcategory":"Fuel Oil & Lpg",
            "type":"Services"
        }
    ],
    "sg:phone":"+1 931 525 6584",
    "sg:postcode":"38506",
    "sg:province":"TN",
    "sg:tags":[
        "liquefied",
        "gas",
        "petroleum"
    ],
    "wof:name":"A & C Propane Inc",
    "wof:placetype":"venue"
},
  "geometry": {"coordinates":[-85.41865199999999,36.129519],"type":"Point"}
}