{
  "type": "Feature",
  "properties": {
    "addr:full":"180 Wallace Rd Nashville TN 37211",
    "addr:housenumber":"180",
    "addr:postcode":"37211",
    "addr:street":"Wallace Rd",
    "iso:country":"US",
    "sg:address":"180 Wallace Rd",
    "sg:city":"Nashville",
    "sg:classifiers":[
        {
            "category":"Shopping",
            "subcategory":"Florist",
            "type":"Retail Goods"
        },
        {
            "category":"Professional",
            "subcategory":"Business Services",
            "type":"Services"
        }
    ],
    "sg:phone":"+1 615 424 7335",
    "sg:postcode":"37211",
    "sg:province":"TN",
    "wof:name":"R Y Patton Designs",
    "wof:placetype":"venue"
},
  "geometry": {"coordinates":[-86.70292999999999,36.080597],"type":"Point"}
}