{
  "type": "Feature",
  "properties": {
    "iso:country":"US",
    "sg:address":"703 College St",
    "sg:city":"Woodbury",
    "sg:classifiers":[
        {
            "category":"Manufacturing",
            "subcategory":"Tools & Machinery",
            "type":"Manufacturing & Wholesale Goods"
        }
    ],
    "sg:phone":"+1 615 563 1041",
    "sg:postcode":"37190",
    "sg:province":"TN",
    "sg:tags":[
        "shop",
        "machine",
        "component",
        "for",
        "mfg"
    ],
    "wof:name":"SPW Inc",
    "wof:placetype":"venue"
},
  "geometry": {"coordinates":[-86.075621,35.820115],"type":"Point"}
}