{
  "type": "Feature",
  "properties": {
    "iso:country":"US",
    "sg:address":"604 Burton Dr",
    "sg:city":"Franklin",
    "sg:classifiers":[
        {
            "category":"Health Services",
            "subcategory":"Clinic",
            "type":"Services"
        }
    ],
    "sg:phone":"+1 615 599 7278",
    "sg:postcode":"37067",
    "sg:province":"TN",
    "sg:tags":[
        "respiratory",
        "therapy"
    ],
    "sg:website":"www.rccsnashville.com",
    "wof:name":"Respiratory Care Consulting",
    "wof:placetype":"venue"
},
  "geometry": {"coordinates":[-86.788859,35.907422],"type":"Point"}
}