{
  "type": "Feature",
  "properties": {
    "addr:full":"2880 Midland Ave Memphis TN 38111",
    "addr:housenumber":"2880",
    "addr:postcode":"38111",
    "addr:street":"Midland Ave",
    "iso:country":"US",
    "sg:address":"2880 Midland Ave",
    "sg:city":"Memphis",
    "sg:classifiers":[
        {
            "category":"Manufacturing",
            "subcategory":"Glass & Minerals",
            "type":"Manufacturing & Wholesale Goods"
        }
    ],
    "sg:phone":"+1 901 458 9129",
    "sg:postcode":"38111",
    "sg:province":"TN",
    "sg:tags":[
        "mfg"
    ],
    "wof:name":"Carol Deforest Studio",
    "wof:placetype":"venue"
},
  "geometry": {"coordinates":[-89.965143,35.119734],"type":"Point"}
}