{
  "type": "Feature",
  "properties": {
    "iso:country":"US",
    "sg:address":"1740 Memorial Dr",
    "sg:city":"Clarksville",
    "sg:classifiers":[
        {
            "category":"Real Estate",
            "subcategory":"Architect",
            "type":"Services"
        }
    ],
    "sg:phone":"+1 931 647 6301",
    "sg:postcode":"37043",
    "sg:province":"TN",
    "wof:name":"Rufus Johnson Assoc",
    "wof:placetype":"venue"
},
  "geometry": {"coordinates":[-87.311702,36.515433],"type":"Point"}
}