{
  "type": "Feature",
  "properties": {
    "addr:full":"2811 Clifton Ave Nashville TN 37209",
    "addr:housenumber":"2811",
    "addr:postcode":"37209",
    "addr:street":"Clifton Ave",
    "iso:country":"US",
    "sg:address":"2811 Clifton Ave",
    "sg:city":"Nashville",
    "sg:classifiers":[
        {
            "category":"Shopping",
            "type":"Retail Goods"
        }
    ],
    "sg:phone":"+1 615 321 1122",
    "sg:postcode":"37209",
    "sg:province":"TN",
    "sg:tags":[
        "cosmetic",
        "perfume"
    ],
    "wof:name":"Qa Hair & Beauty Supply",
    "wof:placetype":"venue"
},
  "geometry": {"coordinates":[-86.81985899999999,36.158857],"type":"Point"}
}