{
  "type": "Feature",
  "properties": {
    "iso:country":"US",
    "sg:address":"6744 Martin Creek Rd",
    "sg:city":"Bloomington Spgs",
    "sg:classifiers":[
        {
            "category":"Home & Garden",
            "subcategory":"Furniture",
            "type":"Retail Goods"
        }
    ],
    "sg:phone":"+1 931 979 3435",
    "sg:postcode":"38545",
    "sg:province":"TN",
    "sg:tags":[
        "cabinet"
    ],
    "wof:name":"Hawkeye Cabinets Furniture",
    "wof:placetype":"venue"
},
  "geometry": {"coordinates":[-85.631522,36.2028],"type":"Point"}
}