{
  "type": "Feature",
  "properties": {
    "iso:country":"US",
    "sg:address":"4910 Columbia Pike",
    "sg:city":"Spring Hill",
    "sg:classifiers":[
        {
            "category":"Personal",
            "subcategory":"Beauty Salon",
            "type":"Services"
        }
    ],
    "sg:phone":"+1 615 302 3535",
    "sg:postcode":"37174",
    "sg:province":"TN",
    "sg:tags":[
        "shop"
    ],
    "wof:name":"Supercuts",
    "wof:placetype":"venue"
},
  "geometry": {"coordinates":[-86.883368,35.845683],"type":"Point"}
}