{
  "type": "Feature",
  "properties": {
    "iso:country":"US",
    "sg:address":"357 Young Rd",
    "sg:city":"Livingston",
    "sg:classifiers":[
        {
            "category":"Organizations",
            "subcategory":"Religious Organization",
            "type":"Services"
        }
    ],
    "sg:phone":"+1 931 823 2725",
    "sg:postcode":"38570",
    "sg:province":"TN",
    "sg:tags":[
        "church"
    ],
    "wof:name":"Jehovah's Witnesses",
    "wof:placetype":"venue"
},
  "geometry": {"coordinates":[-85.35251700000001,36.303352],"type":"Point"}
}