{
  "type": "Feature",
  "properties": {
    "addr:full":"3550 Jackson Ave Memphis TN 38108",
    "addr:housenumber":"3550",
    "addr:postcode":"38108",
    "addr:street":"Jackson Ave",
    "iso:country":"US",
    "sg:address":"3550 Jackson Ave",
    "sg:city":"Memphis",
    "sg:classifiers":[
        {
            "category":"Personal",
            "subcategory":"Barber",
            "type":"Services"
        }
    ],
    "sg:phone":"+1 901 327 2676",
    "sg:postcode":"38108",
    "sg:province":"TN",
    "wof:name":"Chrisstyle's",
    "wof:placetype":"venue"
},
  "geometry": {"coordinates":[-89.94257899999999,35.172466],"type":"Point"}
}