{
  "type": "Feature",
  "properties": {
    "iso:country":"US",
    "sg:address":"301 College St",
    "sg:city":"Newport",
    "sg:classifiers":[
        {
            "category":"Education",
            "subcategory":"Library",
            "type":"Public Place"
        }
    ],
    "sg:phone":"+1 423 623 9871",
    "sg:postcode":"37821",
    "sg:province":"TN",
    "wof:name":"NGS Library",
    "wof:placetype":"venue"
},
  "geometry": {"coordinates":[-83.18655099999999,35.964152],"type":"Point"}
}