{
  "type": "Feature",
  "properties": {
    "addr:full":"8310 Dayton Pike Soddy Daisy TN 37379",
    "addr:housenumber":"8310",
    "addr:postcode":"37379",
    "addr:street":"Dayton Pike",
    "iso:country":"US",
    "sg:address":"8310 Dayton Pike",
    "sg:city":"Soddy Daisy",
    "sg:classifiers":[
        {
            "category":"Organizations",
            "subcategory":"Religious Organization",
            "type":"Services"
        }
    ],
    "sg:phone":"+1 423 842 1044",
    "sg:postcode":"37379",
    "sg:province":"TN",
    "sg:tags":[
        "church"
    ],
    "wof:name":"North Hamilton Church-Christ",
    "wof:placetype":"venue"
},
  "geometry": {"coordinates":[-85.22752300000001,35.216053],"type":"Point"}
}