{
  "type": "Feature",
  "properties": {
    "addr:full":"13505 Dayton Pike Sale Creek TN 37373",
    "addr:housenumber":"13505",
    "addr:postcode":"37373",
    "addr:street":"Dayton Pike",
    "iso:country":"US",
    "sg:address":"13505 Dayton Pike",
    "sg:city":"Sale Creek",
    "sg:classifiers":[
        {
            "category":"Shopping",
            "subcategory":"Gifts & Souvenirs",
            "type":"Retail Goods"
        }
    ],
    "sg:phone":"+1 423 332 6598",
    "sg:postcode":"37373",
    "sg:province":"TN",
    "sg:tags":[
        "collectible"
    ],
    "wof:name":"Bargain Corner",
    "wof:placetype":"venue"
},
  "geometry": {"coordinates":[-85.12828399999999,35.343796],"type":"Point"}
}