{
  "type": "Feature",
  "properties": {
    "iso:country":"US",
    "sg:address":"1873 Hwy 70",
    "sg:city":"Kingston Springs",
    "sg:classifiers":[
        {
            "category":"Social Services",
            "subcategory":"Job Training",
            "type":"Services"
        }
    ],
    "sg:phone":"+1 615 353 4359",
    "sg:postcode":"37082",
    "sg:province":"TN",
    "sg:tags":[
        "agency",
        "rehabilitation",
        "vocational"
    ],
    "wof:name":"Mud Water & Light",
    "wof:placetype":"venue"
},
  "geometry": {"coordinates":[-87.141249,36.12122],"type":"Point"}
}