{
  "type": "Feature",
  "properties": {
    "addr:full":"306 S Church St Murfreesboro TN 37130",
    "addr:housenumber":"306",
    "addr:postcode":"37130",
    "addr:street":"S Church St",
    "iso:country":"US",
    "sg:address":"306 S Church St",
    "sg:city":"Murfreesboro",
    "sg:classifiers":[
        {
            "category":"Communications",
            "subcategory":"Radio Station",
            "type":"Services"
        }
    ],
    "sg:phone":"+1 615 893 1450",
    "sg:postcode":"37130",
    "sg:province":"TN",
    "sg:tags":[
        "broadcast"
    ],
    "wof:name":"Wgns-Talk Radio-AM 1450",
    "wof:placetype":"venue"
},
  "geometry": {"coordinates":[-86.391818,35.843853],"type":"Point"}
}