{
  "type": "Feature",
  "properties": {
    "addr:full":"1912 Lakelet Ct Knoxville TN 37922",
    "addr:housenumber":"1912",
    "addr:postcode":"37922",
    "addr:street":"Lakelet Ct",
    "iso:country":"US",
    "sg:address":"1912 Lakelet Ct",
    "sg:city":"Knoxville",
    "sg:classifiers":[
        {
            "category":"Professional",
            "type":"Services"
        }
    ],
    "sg:phone":"+1 865 357 4929",
    "sg:postcode":"37922",
    "sg:province":"TN",
    "sg:tags":[
        "establishment"
    ],
    "wof:name":"Square D Co",
    "wof:placetype":"venue"
},
  "geometry": {"coordinates":[-84.057896,35.868968],"type":"Point"}
}