{
  "type": "Feature",
  "properties": {
    "iso:country":"US",
    "sg:address":"3194 Velmagi St",
    "sg:city":"Memphis",
    "sg:classifiers":[
        {
            "category":"Manufacturing",
            "subcategory":"Pet Food",
            "type":"Manufacturing & Wholesale Goods"
        }
    ],
    "sg:phone":"+1 901 377 0412",
    "sg:postcode":"38128",
    "sg:province":"TN",
    "sg:tags":[
        "hay"
    ],
    "wof:name":"Alton D Hays Dist",
    "wof:placetype":"venue"
},
  "geometry": {"coordinates":[-89.906828,35.213743],"type":"Point"}
}