{
  "type": "Feature",
  "properties": {
    "addr:full":"1345 Shady Grove Rd Williston TN 38076",
    "addr:housenumber":"1345",
    "addr:postcode":"38076",
    "addr:street":"Shady Grove Rd",
    "iso:country":"US",
    "sg:address":"1345 Shady Grove Rd",
    "sg:city":"Williston",
    "sg:classifiers":[
        {
            "category":"Building & Trades",
            "subcategory":"Plumbing",
            "type":"Services"
        }
    ],
    "sg:phone":"+1 901 465 9578",
    "sg:postcode":"38076",
    "sg:province":"TN",
    "sg:tags":[
        "contractor"
    ],
    "wof:name":"Curtis Hardin Plumbing Co",
    "wof:placetype":"venue"
},
  "geometry": {"coordinates":[-89.398601,35.159212],"type":"Point"}
}