{
  "type": "Feature",
  "properties": {
    "addr:full":"202 S Main St Ashland City TN 37015",
    "addr:housenumber":"202",
    "addr:postcode":"37015",
    "addr:street":"S Main St",
    "iso:country":"US",
    "sg:address":"202 S Main St",
    "sg:city":"Ashland City",
    "sg:classifiers":[
        {
            "category":"Autos & Motor Vehicles",
            "subcategory":"Automobile Sales",
            "type":"Retail Goods"
        }
    ],
    "sg:phone":"+1 615 792 2378",
    "sg:postcode":"37015",
    "sg:province":"TN",
    "sg:tags":[
        "car",
        "leasing",
        "passenger"
    ],
    "wof:name":"Danny Holder Chevrolet Inc",
    "wof:placetype":"venue"
},
  "geometry": {"coordinates":[-87.06293700000001,36.273015],"type":"Point"}
}