{
  "type": "Feature",
  "properties": {
    "iso:country":"US",
    "sg:address":"1257 Dalemere Dr",
    "sg:city":"Nashville",
    "sg:classifiers":[
        {
            "category":"Retail",
            "subcategory":"Repair Shop",
            "type":"Services"
        }
    ],
    "sg:phone":"+1 615 228 9365",
    "sg:postcode":"37207",
    "sg:province":"TN",
    "sg:tags":[
        "lock",
        "locksmith"
    ],
    "wof:name":"Ace Lock & Key",
    "wof:placetype":"venue"
},
  "geometry": {"coordinates":[-86.765587,36.279515],"type":"Point"}
}