{
  "type": "Feature",
  "properties": {
    "iso:country":"US",
    "sg:address":"12830 Paris St",
    "sg:city":"Huntingdon",
    "sg:classifiers":[
        {
            "category":"Retail",
            "subcategory":"Laundry & Dry Cleaning",
            "type":"Services"
        }
    ],
    "sg:phone":"+1 731 986 8428",
    "sg:postcode":"38344",
    "sg:province":"TN",
    "sg:tags":[
        "drycleaning",
        "plant"
    ],
    "wof:name":"Modern Dry Cleaners",
    "wof:placetype":"venue"
},
  "geometry": {"coordinates":[-88.427729,36.000837],"type":"Point"}
}