{
  "type": "Feature",
  "properties": {
    "iso:country":"US",
    "sg:address":"1201 Westchester Dr",
    "sg:city":"Nashville",
    "sg:classifiers":[
        {
            "category":"Place Of Worship",
            "subcategory":"Church",
            "type":"Public Place"
        },
        {
            "category":"Place Of Worship",
            "type":"Public Place"
        }
    ],
    "sg:phone":"+1 615 865 2360",
    "sg:postcode":"37207",
    "sg:province":"TN",
    "sg:tags":[
        "churches-united",
        "methodist",
        "churches-methodist"
    ],
    "wof:name":"Bellshire United Methodist Church",
    "wof:placetype":"venue"
},
  "geometry": {"coordinates":[-86.761864,36.26363],"type":"Point"}
}