{
  "type": "Feature",
  "properties": {
    "addr:full":"1912 N Highland Ave Jackson TN 38305",
    "addr:housenumber":"1912",
    "addr:postcode":"38305",
    "addr:street":"N Highland Ave",
    "iso:country":"US",
    "sg:address":"1912 N Highland Ave",
    "sg:city":"Jackson",
    "sg:classifiers":[
        {
            "category":"Restaurant",
            "type":"Food & Drink"
        }
    ],
    "sg:phone":"+1 731 424 7045",
    "sg:postcode":"38305",
    "sg:province":"TN",
    "wof:name":"Wendy's",
    "wof:placetype":"venue"
},
  "geometry": {"coordinates":[-88.82914599999999,35.651258],"type":"Point"}
}