{
  "type": "Feature",
  "properties": {
    "iso:country":"US",
    "sg:address":"446 N Broadway",
    "sg:city":"Portland",
    "sg:classifiers":[
        {
            "category":"Real Estate",
            "subcategory":"Real Estate Agent",
            "type":"Services"
        }
    ],
    "sg:phone":"+1 615 325 4597",
    "sg:postcode":"37148",
    "sg:province":"TN",
    "wof:name":"Wally Gilliam Real Estate",
    "wof:placetype":"venue"
},
  "geometry": {"coordinates":[-86.51825700000001,36.584512],"type":"Point"}
}