{
  "type": "Feature",
  "properties": {
    "addr:full":"307 N Main St Clinton TN 37716",
    "addr:housenumber":"307",
    "addr:postcode":"37716",
    "addr:street":"N Main St",
    "iso:country":"US",
    "sg:address":"307 N Main St",
    "sg:city":"Clinton",
    "sg:classifiers":[
        {
            "category":"Shopping",
            "subcategory":"Used Merchandise",
            "type":"Retail Goods"
        }
    ],
    "sg:phone":"+1 865 463 7756",
    "sg:postcode":"37716",
    "sg:province":"TN",
    "sg:tags":[
        "antique"
    ],
    "wof:name":"Smoky Mountain Antiques LLC",
    "wof:placetype":"venue"
},
  "geometry": {"coordinates":[-84.132104,36.103048],"type":"Point"}
}