{
  "type": "Feature",
  "properties": {
    "iso:country":"US",
    "sg:address":"924 Due West Ave",
    "sg:city":"Madison",
    "sg:classifiers":[
        {
            "category":"Autos & Motor Vehicles",
            "subcategory":"Automobile Sales",
            "type":"Retail Goods"
        }
    ],
    "sg:phone":"+1 615 868 4976",
    "sg:postcode":"37115",
    "sg:province":"TN",
    "sg:tags":[
        "sell",
        "hot",
        "rod",
        "build"
    ],
    "wof:name":"Rods To Run Inc",
    "wof:placetype":"venue"
},
  "geometry": {"coordinates":[-86.747676,36.255261],"type":"Point"}
}