{
  "type": "Feature",
  "properties": {
    "addr:full":"1646 S Highland Ave Jackson TN 38301",
    "addr:housenumber":"1646",
    "addr:postcode":"38301",
    "addr:street":"S Highland Ave",
    "iso:country":"US",
    "sg:address":"1646 S Highland Ave",
    "sg:city":"Jackson",
    "sg:classifiers":[
        {
            "category":"Restaurant",
            "type":"Food & Drink"
        }
    ],
    "sg:phone":"+1 731 424 9605",
    "sg:postcode":"38301",
    "sg:province":"TN",
    "sg:tags":[
        "eating"
    ],
    "wof:name":"Wendys",
    "wof:placetype":"venue"
},
  "geometry": {"coordinates":[-88.814705,35.56697],"type":"Point"}
}