{
  "type": "Feature",
  "properties": {
    "iso:country":"US",
    "sg:address":"966 Double Bridge Rd",
    "sg:city":"Lewisburg",
    "sg:classifiers":[
        {
            "category":"Building & Trades",
            "subcategory":"Construction",
            "type":"Services"
        }
    ],
    "sg:phone":"+1 931 359 4442",
    "sg:postcode":"37091",
    "sg:province":"TN",
    "sg:tags":[
        "house",
        "contractor"
    ],
    "wof:name":"B & N Builders LLC",
    "wof:placetype":"venue"
},
  "geometry": {"coordinates":[-86.77366000000001,35.508328],"type":"Point"}
}