{
  "type": "Feature",
  "properties": {
    "iso:country":"US",
    "sg:address":"280 Grove Rd",
    "sg:city":"Collierville",
    "sg:classifiers":[
        {
            "category":"Retail",
            "subcategory":"Repair Shop",
            "type":"Services"
        }
    ],
    "sg:phone":"+1 901 853 4221",
    "sg:postcode":"38017",
    "sg:province":"TN",
    "sg:tags":[
        "equipment"
    ],
    "wof:name":"Robertson & Associates",
    "wof:placetype":"venue"
},
  "geometry": {"coordinates":[-89.58623900000001,35.148922],"type":"Point"}
}