{
  "type": "Feature",
  "properties": {
    "iso:country":"US",
    "sg:address":"1776 Union Ave",
    "sg:city":"Memphis",
    "sg:classifiers":[
        {
            "category":"Food & Beverages",
            "subcategory":"Bakery",
            "type":"Retail Goods"
        }
    ],
    "sg:phone":"+1 901 725 5595",
    "sg:postcode":"38104",
    "sg:province":"TN",
    "sg:tags":[
        "doughnut"
    ],
    "wof:name":"Howard's Donuts",
    "wof:placetype":"venue"
},
  "geometry": {"coordinates":[-90.001975,35.135456],"type":"Point"}
}