{
  "type": "Feature",
  "properties": {
    "addr:full":"1822 Price Ave Knoxville TN 37920",
    "addr:housenumber":"1822",
    "addr:postcode":"37920",
    "addr:street":"Price Ave",
    "iso:country":"US",
    "sg:address":"1822 Price Ave",
    "sg:city":"Knoxville",
    "sg:classifiers":[
        {
            "category":"Building & Trades",
            "subcategory":"Cleaning & Sanitation",
            "type":"Services"
        }
    ],
    "sg:phone":"+1 865 579 0486",
    "sg:postcode":"37920",
    "sg:province":"TN",
    "sg:tags":[
        "maintenance"
    ],
    "wof:name":"Mans Cleaning",
    "wof:placetype":"venue"
},
  "geometry": {"coordinates":[-83.88807300000001,35.949853],"type":"Point"}
}