{
  "type": "Feature",
  "properties": {
    "iso:country":"US",
    "sg:address":"5350 Poplar Ave",
    "sg:city":"Memphis",
    "sg:classifiers":[
        {
            "category":"Real Estate",
            "subcategory":"Real Estate Agent",
            "type":"Services"
        }
    ],
    "sg:phone":"+1 901 685 7936",
    "sg:postcode":"38119",
    "sg:province":"TN",
    "wof:name":"CB Richard Ellis Inc",
    "wof:placetype":"venue"
},
  "geometry": {"coordinates":[-89.882005,35.10701],"type":"Point"}
}