{
  "type": "Feature",
  "properties": {
    "iso:country":"US",
    "sg:address":"2106 N Roan St",
    "sg:city":"Johnson City",
    "sg:classifiers":[
        {
            "category":"Shopping",
            "subcategory":"Jewelry",
            "type":"Retail Goods"
        }
    ],
    "sg:phone":"+1 423 282 1525",
    "sg:postcode":"37601",
    "sg:province":"TN",
    "sg:tags":[
        "jeweler"
    ],
    "sg:website":"www.gemsandwhims.com",
    "wof:name":"Gems & Whims",
    "wof:placetype":"venue"
},
  "geometry": {"coordinates":[-82.376328,36.343432],"type":"Point"}
}