{
  "type": "Feature",
  "properties": {
    "iso:country":"US",
    "sg:address":"151 Kyker Ferry Rd",
    "sg:city":"Kodak",
    "sg:classifiers":[
        {
            "category":"Home & Garden",
            "subcategory":"Building Materials",
            "type":"Retail Goods"
        }
    ],
    "sg:phone":"+1 865 933 9206",
    "sg:postcode":"37764",
    "sg:province":"TN",
    "sg:tags":[
        "mixed",
        "concrete"
    ],
    "wof:name":"A & W/ECO Block",
    "wof:placetype":"venue"
},
  "geometry": {"coordinates":[-83.586803,35.95135],"type":"Point"}
}