{
  "type": "Feature",
  "properties": {
    "addr:full":"4119 N Broadway St Knoxville TN 37917",
    "addr:housenumber":"4119",
    "addr:postcode":"37917",
    "addr:street":"N Broadway St",
    "iso:country":"US",
    "sg:address":"4119 N Broadway St",
    "sg:city":"Knoxville",
    "sg:classifiers":[
        {
            "category":"Shopping",
            "subcategory":"Books",
            "type":"Retail Goods"
        },
        {
            "category":"Cinema",
            "subcategory":"Movie Rental",
            "type":"Entertainment"
        }
    ],
    "sg:phone":"+1 865 281 7777",
    "sg:postcode":"37917",
    "sg:province":"TN",
    "sg:tags":[
        "video",
        "tape",
        "dealer"
    ],
    "wof:name":"Rainbow Video Inc",
    "wof:placetype":"venue"
},
  "geometry": {"coordinates":[-83.925093,36.010079],"type":"Point"}
}