{
  "type": "Feature",
  "properties": {
    "addr:full":"205 Jackson St Oak Ridge TN 37874",
    "addr:housenumber":"205",
    "addr:postcode":"37874",
    "addr:street":"Jackson St",
    "iso:country":"US",
    "sg:address":"205 Jackson St",
    "sg:city":"Oak Ridge",
    "sg:classifiers":[
        {
            "category":"Shopping",
            "subcategory":"Hobbies, Toys, & Games",
            "type":"Retail Goods"
        },
        {
            "category":"Shopping",
            "subcategory":"Crafts & Fabrics",
            "type":"Retail Goods"
        }
    ],
    "sg:phone":"+1 865 483 7673",
    "sg:postcode":"37874",
    "sg:province":"TN",
    "sg:tags":[
        "material",
        "needlework"
    ],
    "wof:name":"Ridge Handicrafts Inc",
    "wof:placetype":"venue"
},
  "geometry": {"coordinates":[-84.479696,35.606969],"type":"Point"}
}