{
  "type": "Feature",
  "properties": {
    "iso:country":"US",
    "sg:address":"455 S Front St",
    "sg:city":"Memphis",
    "sg:classifiers":[
        {
            "category":"Manufacturing",
            "subcategory":"Tools & Machinery",
            "type":"Manufacturing & Wholesale Goods"
        }
    ],
    "sg:phone":"+1 901 527 4017",
    "sg:postcode":"38103",
    "sg:province":"TN",
    "sg:tags":[
        "filter"
    ],
    "sg:website":"www.carterco.com",
    "wof:name":"Carter & Co",
    "wof:placetype":"venue"
},
  "geometry": {"coordinates":[-90.06068500000001,35.134787],"type":"Point"}
}