{
  "type": "Feature",
  "properties": {
    "iso:country":"US",
    "sg:address":"294 Rosebud Rd",
    "sg:city":"Cumberland Gap",
    "sg:classifiers":[
        {
            "category":"Mining & Drilling",
            "type":"Manufacturing & Wholesale Goods"
        }
    ],
    "sg:phone":"+1 423 869 9171",
    "sg:postcode":"37724",
    "sg:province":"TN",
    "sg:tags":[
        "contractor"
    ],
    "wof:name":"Strata Mining Inc",
    "wof:placetype":"venue"
},
  "geometry": {"coordinates":[-83.691011,36.543968],"type":"Point"}
}