{
  "type": "Feature",
  "properties": {
    "iso:country":"US",
    "sg:address":"3059 Ashland City Rd",
    "sg:city":"Clarksville",
    "sg:classifiers":[
        {
            "category":"Building & Trades",
            "subcategory":"Construction",
            "type":"Services"
        }
    ],
    "sg:phone":"+1 931 358 4900",
    "sg:postcode":"37043",
    "sg:province":"TN",
    "sg:tags":[
        "maker",
        "cabinet"
    ],
    "wof:name":"Saachs Cabinets",
    "wof:placetype":"venue"
},
  "geometry": {"coordinates":[-87.257017,36.483567],"type":"Point"}
}