{
  "type": "Feature",
  "properties": {
    "iso:country":"US",
    "sg:address":"5384 Poplar Ave Ste 320",
    "sg:city":"Memphis",
    "sg:classifiers":[
        {
            "category":"Professional",
            "subcategory":"Management & Consulting",
            "type":"Services"
        },
        {
            "category":"Banks & Credit Unions",
            "subcategory":"Investment Brokerage",
            "type":"Services"
        },
        {
            "category":"Insurance",
            "subcategory":"Hazard Insurance",
            "type":"Services"
        },
        {
            "category":"Banks & Credit Unions",
            "subcategory":"Financial Services",
            "type":"Services"
        }
    ],
    "sg:phone":"+1 901 683 8310",
    "sg:postcode":"38119",
    "sg:province":"TN",
    "sg:tags":[
        "financing",
        "business",
        "resume",
        "consultant",
        "commercial",
        "agent",
        "planning"
    ],
    "wof:name":"J Henry & Company",
    "wof:placetype":"venue"
},
  "geometry": {"coordinates":[-89.882318,35.107014],"type":"Point"}
}