{
  "type": "Feature",
  "properties": {
    "iso:country":"US",
    "sg:address":"211 S Adams St",
    "sg:city":"Adams",
    "sg:classifiers":[
        {
            "category":"Retail",
            "subcategory":"Laundry & Dry Cleaning",
            "type":"Services"
        }
    ],
    "sg:phone":"+1 615 696 3126",
    "sg:postcode":"37010",
    "sg:province":"TN",
    "sg:tags":[
        "cleaners",
        "rug",
        "carpet"
    ],
    "wof:name":"Beams Quality Carpet Cleaning",
    "wof:placetype":"venue"
},
  "geometry": {"coordinates":[-87.070814,36.579581],"type":"Point"}
}