{
  "type": "Feature",
  "properties": {
    "iso:country":"US",
    "sg:address":"3908 Dayton Blvd",
    "sg:city":"Chattanooga",
    "sg:classifiers":[
        {
            "category":"Professional",
            "subcategory":"Business Services",
            "type":"Services"
        }
    ],
    "sg:phone":"+1 423 875 9828",
    "sg:postcode":"37415",
    "sg:province":"TN",
    "sg:tags":[
        "used",
        "merchandise"
    ],
    "wof:name":"Meeks Auction",
    "wof:placetype":"venue"
},
  "geometry": {"coordinates":[-85.28964999999999,35.119454],"type":"Point"}
}