{
  "type": "Feature",
  "properties": {
    "addr:full":"918 E Main St Chattanooga TN 37408",
    "addr:housenumber":"918",
    "addr:postcode":"37408",
    "addr:street":"E Main St",
    "iso:country":"US",
    "sg:address":"918 E Main St",
    "sg:city":"Chattanooga",
    "sg:classifiers":[
        {
            "category":"Wholesale",
            "subcategory":"Machinery & Supplies",
            "type":"Manufacturing & Wholesale Goods"
        }
    ],
    "sg:phone":"+1 423 485 1050",
    "sg:postcode":"37408",
    "sg:province":"TN",
    "sg:tags":[
        "equipment",
        "industrial"
    ],
    "wof:name":"Peak Industrial",
    "wof:placetype":"venue"
},
  "geometry": {"coordinates":[-85.29517800000001,35.031457],"type":"Point"}
}