{
  "type": "Feature",
  "properties": {
    "iso:country":"US",
    "sg:address":"39 S Main St",
    "sg:city":"Memphis",
    "sg:classifiers":[
        {
            "category":"Building & Trades",
            "subcategory":"Construction",
            "type":"Services"
        }
    ],
    "sg:phone":"+1 901 526 9848",
    "sg:postcode":"38103",
    "sg:province":"TN",
    "sg:tags":[
        "elevator"
    ],
    "wof:name":"Elevator Lines",
    "wof:placetype":"venue"
},
  "geometry": {"coordinates":[-90.053501,35.143739],"type":"Point"}
}