{
  "type": "Feature",
  "properties": {
    "iso:country":"US",
    "sg:address":"2535 Madison St",
    "sg:city":"Clarksville",
    "sg:classifiers":[
        {
            "category":"Personal",
            "subcategory":"Beauty Salon",
            "type":"Services"
        }
    ],
    "sg:phone":"+1 931 368 1500",
    "sg:postcode":"37043",
    "sg:province":"TN",
    "wof:name":"Amici & Co Salon",
    "wof:placetype":"venue"
},
  "geometry": {"coordinates":[-87.26173,36.506059],"type":"Point"}
}