{
  "type": "Feature",
  "properties": {
    "iso:country":"US",
    "sg:address":"823 E Meade Ave",
    "sg:city":"Madison",
    "sg:classifiers":[
        {
            "category":"Social Services",
            "subcategory":"Child Care",
            "type":"Services"
        }
    ],
    "sg:phone":"+1 615 868 5572",
    "sg:postcode":"37115",
    "sg:province":"TN",
    "wof:name":"Wee Keep Preschool & Child Cr",
    "wof:placetype":"venue"
},
  "geometry": {"coordinates":[-86.714989,36.252922],"type":"Point"}
}