{
  "type": "Feature",
  "properties": {
    "iso:country":"US",
    "sg:address":"3463 Wingood Cir",
    "sg:city":"Memphis",
    "sg:classifiers":[
        {
            "category":"Real Estate",
            "subcategory":"Real Estate Agent",
            "type":"Services"
        },
        {
            "category":"Real Estate",
            "subcategory":"Real Estate Operator",
            "type":"Services"
        }
    ],
    "sg:phone":"+1 901 365 8318",
    "sg:postcode":"38118",
    "sg:province":"TN",
    "sg:tags":[
        "apartment"
    ],
    "wof:name":"Wingood Manor Apartments",
    "wof:placetype":"venue"
},
  "geometry": {"coordinates":[-89.923123,35.05404],"type":"Point"}
}