{
  "type": "Feature",
  "properties": {
    "iso:country":"US",
    "sg:address":"349 Shelton Rd",
    "sg:city":"Collierville",
    "sg:classifiers":[
        {
            "category":"Professional",
            "subcategory":"Business Services",
            "type":"Services"
        }
    ],
    "sg:phone":"+1 901 861 6711",
    "sg:postcode":"38017",
    "sg:province":"TN",
    "wof:name":"Dlk Enterprises LLC",
    "wof:placetype":"venue"
},
  "geometry": {"coordinates":[-89.673419,35.074279],"type":"Point"}
}