{
  "type": "Feature",
  "properties": {
    "addr:full":"301 N Poplar St Kenton TN 38233",
    "addr:housenumber":"301",
    "addr:postcode":"38233",
    "addr:street":"N Poplar St",
    "iso:country":"US",
    "sg:address":"301 N Poplar St",
    "sg:city":"Kenton",
    "sg:classifiers":[
        {
            "category":"Food & Beverages",
            "subcategory":"Groceries & Convenience Stores",
            "type":"Retail Goods"
        }
    ],
    "sg:phone":"+1 731 749 5810",
    "sg:postcode":"38233",
    "sg:province":"TN",
    "wof:name":"Kenton Food Plaza",
    "wof:placetype":"venue"
},
  "geometry": {"coordinates":[-89.01328700000001,36.204594],"type":"Point"}
}