{
  "type": "Feature",
  "properties": {
    "iso:country":"US",
    "sg:address":"109 N Belvedere Blvd",
    "sg:city":"Memphis",
    "sg:classifiers":[
        {
            "category":"Building & Trades",
            "subcategory":"Cleaning & Sanitation",
            "type":"Services"
        }
    ],
    "sg:phone":"+1 901 604 0121",
    "sg:postcode":"38104",
    "sg:province":"TN",
    "sg:tags":[
        "janitor"
    ],
    "wof:name":"W & M Cleaning Svc",
    "wof:placetype":"venue"
},
  "geometry": {"coordinates":[-90.00458,35.141434],"type":"Point"}
}