{
  "type": "Feature",
  "properties": {
    "iso:country":"US",
    "sg:address":"3705 Outland Rd",
    "sg:city":"Memphis",
    "sg:classifiers":[
        {
            "category":"Shopping",
            "subcategory":"Gifts & Souvenirs",
            "type":"Retail Goods"
        }
    ],
    "sg:phone":"+1 901 363 6082",
    "sg:postcode":"38118",
    "sg:province":"TN",
    "wof:name":"Bits and Pieces",
    "wof:placetype":"venue"
},
  "geometry": {"coordinates":[-89.90178400000001,35.046366],"type":"Point"}
}