{
  "type": "Feature",
  "properties": {
    "iso:country":"US",
    "sg:address":"2889 Austin Peay Hwy",
    "sg:city":"Memphis",
    "sg:classifiers":[
        {
            "category":"Travel",
            "subcategory":"Hotels & Motels",
            "type":"Entertainment"
        }
    ],
    "sg:phone":"+1 901 386 0033",
    "sg:postcode":"38128",
    "sg:province":"TN",
    "sg:tags":[
        "lodging"
    ],
    "sg:website":"http://www.daysinn.com",
    "wof:name":"Days Inn",
    "wof:placetype":"venue"
},
  "geometry": {"coordinates":[-89.921694,35.203966],"type":"Point"}
}