{
  "type": "Feature",
  "properties": {
    "iso:country":"US",
    "sg:address":"924 W 4th North St",
    "sg:city":"Morristown",
    "sg:classifiers":[
        {
            "category":"Health Services",
            "subcategory":"Clinic",
            "type":"Services"
        }
    ],
    "sg:phone":"+1 423 586 0580",
    "sg:postcode":"37814",
    "sg:province":"TN",
    "wof:name":"Morristown Hamblen Healthcare",
    "wof:placetype":"venue"
},
  "geometry": {"coordinates":[-83.30498799999999,36.211714],"type":"Point"}
}