{
  "type": "Feature",
  "properties": {
    "iso:country":"US",
    "sg:address":"1301 8th Ave S",
    "sg:city":"Nashville",
    "sg:classifiers":[
        {
            "category":"Wholesale",
            "subcategory":"Office Equipment",
            "type":"Manufacturing & Wholesale Goods"
        }
    ],
    "sg:phone":"+1 615 385 4275",
    "sg:postcode":"37204",
    "sg:province":"TN",
    "sg:tags":[
        "register",
        "cash",
        "supply"
    ],
    "wof:name":"Hospitality Control Solutions",
    "wof:placetype":"venue"
},
  "geometry": {"coordinates":[-86.77839,36.139221],"type":"Point"}
}