{
  "type": "Feature",
  "properties": {
    "iso:country":"US",
    "sg:address":"2329 Duncan Rd",
    "sg:city":"Knoxville",
    "sg:classifiers":[
        {
            "category":"Freight",
            "type":"Transportation"
        },
        {
            "category":"Recreation",
            "subcategory":"Marina",
            "type":"Entertainment"
        }
    ],
    "sg:phone":"+1 865 212 9949",
    "sg:postcode":"37919",
    "sg:province":"TN",
    "sg:tags":[
        "dock",
        "operation"
    ],
    "wof:name":"Duncans Boat Dock",
    "wof:placetype":"venue"
},
  "geometry": {"coordinates":[-83.98772599999999,35.889818],"type":"Point"}
}