{
  "type": "Feature",
  "properties": {
    "iso:country":"US",
    "sg:address":"1051 Benson Ln",
    "sg:city":"Belvidere",
    "sg:classifiers":[
        {
            "category":"Farming",
            "subcategory":"Farm",
            "type":"Manufacturing & Wholesale Goods"
        }
    ],
    "sg:phone":"+1 931 967 3016",
    "sg:postcode":"37306",
    "sg:province":"TN",
    "sg:tags":[
        "crop",
        "general"
    ],
    "wof:name":"Jimmy J Latham",
    "wof:placetype":"venue"
},
  "geometry": {"coordinates":[-86.238822,35.123266],"type":"Point"}
}