{
  "type": "Feature",
  "properties": {
    "addr:full":"8366 Old Lee Hwy Ooltewah TN 37363",
    "addr:housenumber":"8366",
    "addr:postcode":"37363",
    "addr:street":"Old Lee Hwy",
    "iso:country":"US",
    "sg:address":"8366 Old Lee Hwy",
    "sg:city":"Ooltewah",
    "sg:classifiers":[
        {
            "category":"Personal",
            "type":"Services"
        }
    ],
    "sg:phone":"+1 423 238 5147",
    "sg:postcode":"37363",
    "sg:province":"TN",
    "sg:tags":[
        "consultant",
        "wedding"
    ],
    "wof:name":"Elaborations",
    "wof:placetype":"venue"
},
  "geometry": {"coordinates":[-85.095609,35.072542],"type":"Point"}
}