{
  "type": "Feature",
  "properties": {
    "iso:country":"US",
    "sg:address":"326 Southside Rd",
    "sg:city":"Cunningham",
    "sg:classifiers":[
        {
            "category":"Organizations",
            "subcategory":"Religious Organization",
            "type":"Services"
        }
    ],
    "sg:phone":"+1 931 387 2045",
    "sg:postcode":"37052",
    "sg:province":"TN",
    "sg:tags":[
        "church"
    ],
    "wof:name":"St Paul's Baptist Church",
    "wof:placetype":"venue"
},
  "geometry": {"coordinates":[-87.377424,36.384366],"type":"Point"}
}