{
  "type": "Feature",
  "properties": {
    "addr:full":"5004 Bayberry Dr NW Knoxville TN 37921",
    "addr:housenumber":"5004",
    "addr:postcode":"37921",
    "addr:street":"Bayberry Dr Nw",
    "iso:country":"US",
    "sg:address":"5004 Bayberry Dr NW",
    "sg:city":"Knoxville",
    "sg:classifiers":[
        {
            "category":"Professional",
            "subcategory":"Employment Agencies",
            "type":"Services"
        }
    ],
    "sg:phone":"+1 865 824 2747",
    "sg:postcode":"37921",
    "sg:province":"TN",
    "sg:tags":[
        "medical",
        "help"
    ],
    "wof:name":"Quality Mobile Medical Svcs",
    "wof:placetype":"venue"
},
  "geometry": {"coordinates":[-83.988596,35.98631],"type":"Point"}
}