{
  "type": "Feature",
  "properties": {
    "iso:country":"US",
    "sg:address":"4617 Creston Rd",
    "sg:city":"Crossville",
    "sg:classifiers":[
        {
            "category":"Organizations",
            "subcategory":"Religious Organization",
            "type":"Services"
        }
    ],
    "sg:phone":"+1 931 456 4815",
    "sg:postcode":"38571",
    "sg:province":"TN",
    "wof:name":"Calvary Baptist Church",
    "wof:placetype":"venue"
},
  "geometry": {"coordinates":[-85.06983700000001,36.054845],"type":"Point"}
}