{
  "type": "Feature",
  "properties": {
    "iso:country":"US",
    "sg:address":"1324 Springbrook Ave",
    "sg:city":"Memphis",
    "sg:classifiers":[
        {
            "category":"Wholesale",
            "subcategory":"Construction Materials",
            "type":"Manufacturing & Wholesale Goods"
        },
        {
            "category":"Wholesale",
            "subcategory":"Home Furnishings",
            "type":"Manufacturing & Wholesale Goods"
        }
    ],
    "sg:phone":"+1 901 332 8120",
    "sg:postcode":"38116",
    "sg:province":"TN",
    "sg:tags":[
        "supply",
        "fixture",
        "part",
        "plumbing",
        "fixtures",
        "supplies-wholesale",
        "manufacturer"
    ],
    "sg:website":"http://www.chrismoreinc.com",
    "wof:name":"Chris-More Inc",
    "wof:placetype":"venue"
},
  "geometry": {"coordinates":[-90.020821,35.062506],"type":"Point"}
}