{
  "type": "Feature",
  "properties": {
    "iso:country":"US",
    "sg:address":"547 Main St",
    "sg:city":"Jacksboro",
    "sg:classifiers":[
        {
            "category":"Personal",
            "subcategory":"Beauty Salon",
            "type":"Services"
        }
    ],
    "sg:phone":"+1 423 562 3989",
    "sg:postcode":"37757",
    "sg:province":"TN",
    "wof:name":"Jackie Byrd Beauty Shop",
    "wof:placetype":"venue"
},
  "geometry": {"coordinates":[-84.18222299999999,36.330472],"type":"Point"}
}