{
  "type": "Feature",
  "properties": {
    "addr:full":"5050 Poplar Ave Memphis TN 38117",
    "addr:housenumber":"5050",
    "addr:postcode":"38117",
    "addr:street":"Poplar Ave",
    "iso:country":"US",
    "sg:address":"5050 Poplar Ave",
    "sg:city":"Memphis",
    "sg:classifiers":[
        {
            "category":"Social Services",
            "type":"Services"
        }
    ],
    "sg:phone":"+1 901 682 6775",
    "sg:postcode":"38117",
    "sg:province":"TN",
    "sg:tags":[
        "youth",
        "organization",
        "center"
    ],
    "wof:name":"Agency For Youth & Family",
    "wof:placetype":"venue"
},
  "geometry": {"coordinates":[-89.894622,35.112664],"type":"Point"}
}