{
  "type": "Feature",
  "properties": {
    "iso:country":"US",
    "sg:address":"2600 Poplar Ave",
    "sg:city":"Memphis",
    "sg:classifiers":[
        {
            "category":"Health Services",
            "subcategory":"Clinic",
            "type":"Services"
        }
    ],
    "sg:phone":"+1 901 240 2839",
    "sg:postcode":"38104",
    "sg:province":"TN",
    "sg:tags":[
        "mental",
        "outpatient",
        "specialty"
    ],
    "wof:name":"Comprehensive Prof Svcs",
    "wof:placetype":"venue"
},
  "geometry": {"coordinates":[-89.97383600000001,35.137278],"type":"Point"}
}