{
  "type": "Feature",
  "properties": {
    "addr:full":"268 Ellis Rd Blountville TN 37617",
    "addr:housenumber":"268",
    "addr:postcode":"37617",
    "addr:street":"Ellis Rd",
    "iso:country":"US",
    "sg:address":"268 Ellis Rd",
    "sg:city":"Blountville",
    "sg:classifiers":[
        {
            "category":"Building & Trades",
            "subcategory":"Construction",
            "type":"Services"
        }
    ],
    "sg:phone":"+1 423 279 7100",
    "sg:postcode":"37617",
    "sg:province":"TN",
    "sg:tags":[
        "roofing",
        "contractor"
    ],
    "wof:name":"Cormier Roofing",
    "wof:placetype":"venue"
},
  "geometry": {"coordinates":[-82.349453,36.530368],"type":"Point"}
}