{
  "type": "Feature",
  "properties": {
    "iso:country":"US",
    "sg:address":"2306 N Economy Rd",
    "sg:city":"Morristown",
    "sg:classifiers":[
        {
            "category":"Real Estate",
            "subcategory":"Developer",
            "type":"Services"
        }
    ],
    "sg:phone":"+1 423 581 8060",
    "sg:postcode":"37814",
    "sg:province":"TN",
    "sg:website":"www.gibson-assoc.com",
    "wof:name":"Gibson & Assoc",
    "wof:placetype":"venue"
},
  "geometry": {"coordinates":[-83.329768,36.21246],"type":"Point"}
}