{
  "type": "Feature",
  "properties": {
    "iso:country":"US",
    "sg:address":"380 US Hwy 45 N",
    "sg:city":"Henderson",
    "sg:classifiers":[
        {
            "category":"Autos & Motor Vehicles",
            "subcategory":"Auto Supplies",
            "type":"Retail Goods"
        }
    ],
    "sg:phone":"+1 731 989 5429",
    "sg:postcode":"38340",
    "sg:province":"TN",
    "sg:tags":[
        "battery"
    ],
    "wof:name":"Peacock's Battery Exchange",
    "wof:placetype":"venue"
},
  "geometry": {"coordinates":[-88.650433,35.442886],"type":"Point"}
}