{
  "type": "Feature",
  "properties": {
    "iso:country":"US",
    "sg:address":"615 Meadowbrook Cir",
    "sg:city":"Livingston",
    "sg:classifiers":[
        {
            "category":"Autos & Motor Vehicles",
            "subcategory":"Automobile Sales",
            "type":"Retail Goods"
        }
    ],
    "sg:phone":"+1 931 823 5865",
    "sg:postcode":"38570",
    "sg:province":"TN",
    "sg:tags":[
        "body",
        "used"
    ],
    "wof:name":"Classy Corvettes & Autocraft",
    "wof:placetype":"venue"
},
  "geometry": {"coordinates":[-85.337677,36.321509],"type":"Point"}
}