{
  "type": "Feature",
  "properties": {
    "iso:country":"US",
    "sg:address":"2037 Campbell Rd",
    "sg:city":"Decaturville",
    "sg:classifiers":[
        {
            "category":"Health Services",
            "subcategory":"Health Practitioner",
            "type":"Services"
        }
    ],
    "sg:phone":"+1 731 852 2929",
    "sg:postcode":"38329",
    "sg:province":"TN",
    "wof:name":"Dennis R & Linda S Meeker",
    "wof:placetype":"venue"
},
  "geometry": {"coordinates":[-88.17605399999999,35.566113],"type":"Point"}
}