{
  "type": "Feature",
  "properties": {
    "iso:country":"US",
    "sg:address":"3330 Lyon Springs Rd",
    "sg:city":"Sevierville",
    "sg:classifiers":[
        {
            "category":"Travel",
            "subcategory":"Campground",
            "type":"Entertainment"
        }
    ],
    "sg:phone":"+1 865 453 1111",
    "sg:postcode":"37862",
    "sg:province":"TN",
    "sg:website":"www.tennissippi.com",
    "wof:name":"Wonderland Rv Park",
    "wof:placetype":"venue"
},
  "geometry": {"coordinates":[-83.65021900000001,35.709505],"type":"Point"}
}