{
  "type": "Feature",
  "properties": {
    "iso:country":"US",
    "sg:address":"500 W Lytle St",
    "sg:city":"Murfreesboro",
    "sg:classifiers":[
        {
            "category":"Wholesale",
            "subcategory":"Electrical",
            "type":"Manufacturing & Wholesale Goods"
        }
    ],
    "sg:phone":"+1 615 895 2065",
    "sg:postcode":"37130",
    "sg:province":"TN",
    "sg:tags":[
        "equipment",
        "electric",
        "apparatus",
        "supply"
    ],
    "sg:website":"www.mayerelectric.com",
    "wof:name":"Mayer Electric Supply Company",
    "wof:placetype":"venue"
},
  "geometry": {"coordinates":[-86.39570500000001,35.848544],"type":"Point"}
}