{
  "type": "Feature",
  "properties": {
    "addr:full":"82 Doctors Dr Munford TN 38058",
    "addr:housenumber":"82",
    "addr:postcode":"38058",
    "addr:street":"Doctors Dr",
    "iso:country":"US",
    "sg:address":"82 Doctors Dr",
    "sg:city":"Munford",
    "sg:classifiers":[
        {
            "category":"Shopping",
            "subcategory":"Bicycles & Sporting Goods",
            "type":"Retail Goods"
        }
    ],
    "sg:phone":"+1 901 837 1480",
    "sg:postcode":"38058",
    "sg:province":"TN",
    "wof:name":"Munford Sports Plus",
    "wof:placetype":"venue"
},
  "geometry": {"coordinates":[-89.79684,35.449024],"type":"Point"}
}