{
  "type": "Feature",
  "properties": {
    "iso:country":"US",
    "sg:address":"217 Connell St",
    "sg:city":"Goodlettsville",
    "sg:classifiers":[
        {
            "category":"Professional",
            "subcategory":"Art Services",
            "type":"Services"
        }
    ],
    "sg:phone":"+1 615 859 4875",
    "sg:postcode":"37072",
    "sg:province":"TN",
    "sg:tags":[
        "commercial",
        "graphic",
        "design"
    ],
    "sg:website":"www.robinsongraphicsinc.com",
    "wof:name":"Robinson Graphics Inc",
    "wof:placetype":"venue"
},
  "geometry": {"coordinates":[-86.70761,36.326306],"type":"Point"}
}