{
  "type": "Feature",
  "properties": {
    "addr:full":"6424 Memphis Arlington Rd Memphis TN 38135",
    "addr:housenumber":"6424",
    "addr:postcode":"38135",
    "addr:street":"Memphis Arlington Rd",
    "iso:country":"US",
    "sg:address":"6424 Memphis Arlington Rd",
    "sg:city":"Memphis",
    "sg:classifiers":[
        {
            "category":"Insurance",
            "subcategory":"Insurance Agent",
            "type":"Services"
        }
    ],
    "sg:phone":"+1 901 384 6823",
    "sg:postcode":"38135",
    "sg:province":"TN",
    "wof:name":"Carson Group Insurance",
    "wof:placetype":"venue"
},
  "geometry": {"coordinates":[-89.850155,35.225384],"type":"Point"}
}