{
  "type": "Feature",
  "properties": {
    "addr:full":"4011 Stewarts Ln Nashville TN 37218",
    "addr:housenumber":"4011",
    "addr:postcode":"37218",
    "addr:street":"Stewarts Ln",
    "iso:country":"US",
    "sg:address":"4011 Stewarts Ln",
    "sg:city":"Nashville",
    "sg:classifiers":[
        {
            "category":"Government",
            "subcategory":"Jail",
            "type":"Public Place"
        }
    ],
    "sg:phone":"+1 615 532 8408",
    "sg:postcode":"37218",
    "sg:province":"TN",
    "sg:tags":[
        "govt",
        "state",
        "institution"
    ],
    "wof:name":"Youth Development Warehouse",
    "wof:placetype":"venue"
},
  "geometry": {"coordinates":[-86.860747,36.208165],"type":"Point"}
}