{
  "type": "Feature",
  "properties": {
    "iso:country":"US",
    "sg:address":"323 Cosby Hwy",
    "sg:city":"Newport",
    "sg:classifiers":[
        {
            "category":"Restaurant",
            "type":"Food & Drink"
        }
    ],
    "sg:phone":"+1 423 623 2752",
    "sg:postcode":"37821",
    "sg:province":"TN",
    "sg:tags":[
        "eating"
    ],
    "wof:name":"Thai Kitchen",
    "wof:placetype":"venue"
},
  "geometry": {"coordinates":[-83.19443,35.963593],"type":"Point"}
}