{
  "type": "Feature",
  "properties": {
    "addr:full":"2851 Stage Village Cv Memphis TN 38134",
    "addr:housenumber":"2851",
    "addr:postcode":"38134",
    "addr:street":"Stage Village Cv",
    "iso:country":"US",
    "sg:address":"2851 Stage Village Cv",
    "sg:city":"Memphis",
    "sg:classifiers":[
        {
            "category":"Personal",
            "subcategory":"Beauty Salon",
            "type":"Services"
        },
        {
            "category":"Personal",
            "subcategory":"Barber",
            "type":"Services"
        }
    ],
    "sg:phone":"+1 901 382 2393",
    "sg:postcode":"38134",
    "sg:province":"TN",
    "sg:tags":[
        "hair",
        "accessory",
        "stylist",
        "supply"
    ],
    "sg:website":"http://www.fantasticsams.com",
    "wof:name":"Fantastic Sams",
    "wof:placetype":"venue"
},
  "geometry": {"coordinates":[-89.8554,35.203522],"type":"Point"}
}