{
  "type": "Feature",
  "properties": {
    "iso:country":"US",
    "sg:address":"654 Parkway",
    "sg:city":"Gatlinburg",
    "sg:classifiers":[
        {
            "category":"Professional",
            "type":"Services"
        }
    ],
    "sg:phone":"+1 865 436 9620",
    "sg:postcode":"37738",
    "sg:province":"TN",
    "sg:tags":[
        "establishment"
    ],
    "wof:name":"TAO Enterprises",
    "wof:placetype":"venue"
},
  "geometry": {"coordinates":[-83.514465,35.712845],"type":"Point"}
}