{
  "type": "Feature",
  "properties": {
    "iso:country":"US",
    "sg:address":"116 Franklin St",
    "sg:city":"Nashville",
    "sg:classifiers":[
        {
            "category":"Autos & Motor Vehicles",
            "subcategory":"Fuel & Gas Station",
            "type":"Retail Goods"
        }
    ],
    "sg:phone":"+1 615 661 5154",
    "sg:postcode":"37201",
    "sg:province":"TN",
    "sg:tags":[
        "station",
        "gasoline"
    ],
    "wof:name":"Exxon",
    "wof:placetype":"venue"
},
  "geometry": {"coordinates":[-86.77297299999999,36.157791],"type":"Point"}
}