{
  "type": "Feature",
  "properties": {
    "addr:full":"2131 Murfreesboro Pike Nashville TN 37217",
    "addr:housenumber":"2131",
    "addr:postcode":"37217",
    "addr:street":"Murfreesboro Pike",
    "iso:country":"US",
    "sg:address":"2131 Murfreesboro Pike",
    "sg:city":"Nashville",
    "sg:classifiers":[
        {
            "category":"Manufacturing",
            "subcategory":"Signs",
            "type":"Manufacturing & Wholesale Goods"
        },
        {
            "category":"Shopping",
            "subcategory":"Computers & Home Electronics",
            "type":"Retail Goods"
        }
    ],
    "sg:phone":"+1 615 366 0900",
    "sg:postcode":"37217",
    "sg:province":"TN",
    "sg:tags":[
        "equipment",
        "artwork",
        "creation",
        "electronic",
        "supply"
    ],
    "wof:name":"Electronic Artwork LLC",
    "wof:placetype":"venue"
},
  "geometry": {"coordinates":[-86.652798,36.093616],"type":"Point"}
}