{
  "type": "Feature",
  "properties": {
    "iso:country":"US",
    "sg:address":"748 Walnut Knoll Ln",
    "sg:city":"Cordova",
    "sg:classifiers":[
        {
            "category":"Insurance",
            "subcategory":"Insurance Agent",
            "type":"Services"
        }
    ],
    "sg:phone":"+1 901 309 0304",
    "sg:postcode":"38018",
    "sg:province":"TN",
    "wof:name":"Design Capital Strategies",
    "wof:placetype":"venue"
},
  "geometry": {"coordinates":[-89.793544,35.145843],"type":"Point"}
}