{
  "type": "Feature",
  "properties": {
    "addr:full":"710 Williams Springs Rd Afton TN 37616",
    "addr:housenumber":"710",
    "addr:postcode":"37616",
    "addr:street":"Williams Springs Rd",
    "iso:country":"US",
    "sg:address":"710 Williams Springs Rd",
    "sg:city":"Afton",
    "sg:classifiers":[
        {
            "category":"Professional",
            "subcategory":"Accounting & Tax Preparation",
            "type":"Services"
        }
    ],
    "sg:phone":"+1 423 638 4508",
    "sg:postcode":"37616",
    "sg:province":"TN",
    "sg:tags":[
        "return"
    ],
    "wof:name":"Gilland & Reevestax Service",
    "wof:placetype":"venue"
},
  "geometry": {"coordinates":[-82.754642,36.208349],"type":"Point"}
}