{
  "type": "Feature",
  "properties": {
    "iso:country":"US",
    "sg:address":"1003 Rolling Hills Dr",
    "sg:city":"Johnson City",
    "sg:classifiers":[
        {
            "category":"Building & Trades",
            "subcategory":"Construction",
            "type":"Services"
        }
    ],
    "sg:phone":"+1 423 929 8827",
    "sg:postcode":"37604",
    "sg:province":"TN",
    "sg:tags":[
        "hanging",
        "painter",
        "contractor"
    ],
    "wof:name":"John Phillips Painting LLC",
    "wof:placetype":"venue"
},
  "geometry": {"coordinates":[-82.34849800000001,36.291172],"type":"Point"}
}