{
  "type": "Feature",
  "properties": {
    "addr:full":"959 Prentice St Crossville TN 38555",
    "addr:housenumber":"959",
    "addr:postcode":"38555",
    "addr:street":"Prentice St",
    "iso:country":"US",
    "sg:address":"959 Prentice St",
    "sg:city":"Crossville",
    "sg:classifiers":[
        {
            "category":"Retail",
            "subcategory":"Repair Shop",
            "type":"Services"
        }
    ],
    "sg:phone":"+1 931 456 0786",
    "sg:postcode":"38555",
    "sg:province":"TN",
    "sg:tags":[
        "clocks",
        "parts"
    ],
    "wof:name":"Cumberland Clock Svc",
    "wof:placetype":"venue"
},
  "geometry": {"coordinates":[-85.04428799999999,35.930112],"type":"Point"}
}