{
  "type": "Feature",
  "properties": {
    "iso:country":"US",
    "sg:address":"534 Richwood Rd",
    "sg:city":"Dyersburg",
    "sg:classifiers":[
        {
            "category":"Professional",
            "subcategory":"Testing Lab",
            "type":"Services"
        }
    ],
    "sg:phone":"+1 731 285 3035",
    "sg:postcode":"38030",
    "sg:province":"TN",
    "sg:tags":[
        "laboratory"
    ],
    "wof:name":"Wagner & Associates",
    "wof:placetype":"venue"
},
  "geometry": {"coordinates":[-89.500213,36.02892],"type":"Point"}
}