{
  "type": "Feature",
  "properties": {
    "iso:country":"US",
    "sg:address":"918 England Dr",
    "sg:city":"Knoxville",
    "sg:classifiers":[
        {
            "category":"Home & Garden",
            "subcategory":"Home Furnishings",
            "type":"Retail Goods"
        }
    ],
    "sg:phone":"+1 865 694 7767",
    "sg:postcode":"37920",
    "sg:province":"TN",
    "sg:tags":[
        "window",
        "treatment"
    ],
    "wof:name":"Window Pros Inc",
    "wof:placetype":"venue"
},
  "geometry": {"coordinates":[-83.921924,35.934068],"type":"Point"}
}