{
  "type": "Feature",
  "properties": {
    "iso:country":"US",
    "sg:address":"101 Mooreland Dr",
    "sg:city":"Springfield",
    "sg:classifiers":[
        {
            "category":"Health Services",
            "subcategory":"Clinic",
            "type":"Services"
        }
    ],
    "sg:phone":"+1 615 212 0577",
    "sg:postcode":"37172",
    "sg:province":"TN",
    "wof:name":"Restoration Health Care",
    "wof:placetype":"venue"
},
  "geometry": {"coordinates":[-86.88129,36.492096],"type":"Point"}
}