{
  "type": "Feature",
  "properties": {
    "iso:country":"US",
    "sg:address":"6853 Shepp Rd",
    "sg:city":"Stanton",
    "sg:classifiers":[
        {
            "category":"Farming",
            "subcategory":"Farm",
            "type":"Manufacturing & Wholesale Goods"
        },
        {
            "category":"Real Estate",
            "subcategory":"Real Estate Operator",
            "type":"Services"
        }
    ],
    "sg:phone":"+1 731 772 2230",
    "sg:postcode":"38069",
    "sg:province":"TN",
    "sg:tags":[
        "property",
        "lessor"
    ],
    "wof:name":"Friedman Farms LLC",
    "wof:placetype":"venue"
},
  "geometry": {"coordinates":[-89.273279,35.483006],"type":"Point"}
}