{
  "type": "Feature",
  "properties": {
    "iso:country":"US",
    "sg:address":"1083 Tulip Grove Rd",
    "sg:city":"Hermitage",
    "sg:classifiers":[
        {
            "category":"Building & Trades",
            "subcategory":"Construction",
            "type":"Services"
        }
    ],
    "sg:phone":"+1 615 889 3492",
    "sg:postcode":"37076",
    "sg:province":"TN",
    "sg:tags":[
        "house"
    ],
    "wof:name":"Ewin Construction",
    "wof:placetype":"venue"
},
  "geometry": {"coordinates":[-86.59499700000001,36.181904],"type":"Point"}
}