{
  "type": "Feature",
  "properties": {
    "addr:full":"3948 Lebanon Pike Hermitage TN 37076",
    "addr:housenumber":"3948",
    "addr:postcode":"37076",
    "addr:street":"Lebanon Pike",
    "iso:country":"US",
    "sg:address":"3948 Lebanon Pike",
    "sg:city":"Hermitage",
    "sg:classifiers":[
        {
            "category":"Food & Beverages",
            "subcategory":"Bakery",
            "type":"Retail Goods"
        }
    ],
    "sg:phone":"+1 615 883 6011",
    "sg:postcode":"37076",
    "sg:province":"TN",
    "sg:tags":[
        "doughnut"
    ],
    "wof:name":"Granny's Donuts",
    "wof:placetype":"venue"
},
  "geometry": {"coordinates":[-86.623492,36.193357],"type":"Point"}
}