{
  "type": "Feature",
  "properties": {
    "addr:full":"222 Springview Dr Jackson TN 38305",
    "addr:housenumber":"222",
    "addr:postcode":"38305",
    "addr:street":"Springview Dr",
    "iso:country":"US",
    "sg:address":"222 Springview Dr",
    "sg:city":"Jackson",
    "sg:classifiers":[
        {
            "category":"Retail",
            "subcategory":"Portrait Studio",
            "type":"Services"
        }
    ],
    "sg:phone":"+1 731 513 0404",
    "sg:postcode":"38305",
    "sg:province":"TN",
    "wof:name":"Crossroads Productions",
    "wof:placetype":"venue"
},
  "geometry": {"coordinates":[-88.679838,35.73291],"type":"Point"}
}