{
  "type": "Feature",
  "properties": {
    "addr:full":"302 Bethany Ln Shelbyville TN 37160",
    "addr:housenumber":"302",
    "addr:postcode":"37160",
    "addr:street":"Bethany Ln",
    "iso:country":"US",
    "sg:address":"302 Bethany Ln",
    "sg:city":"Shelbyville",
    "sg:classifiers":[
        {
            "category":"Freight",
            "type":"Transportation"
        }
    ],
    "sg:phone":"+1 931 684 4546",
    "sg:postcode":"37160",
    "sg:province":"TN",
    "sg:tags":[
        "special"
    ],
    "wof:name":"Adcock Storage",
    "wof:placetype":"venue"
},
  "geometry": {"coordinates":[-86.439381,35.485354],"type":"Point"}
}