{
  "type": "Feature",
  "properties": {
    "iso:country":"US",
    "sg:address":"3889 Hwy 127 S",
    "sg:city":"Crossville",
    "sg:classifiers":[
        {
            "category":"Education",
            "subcategory":"School",
            "type":"Public Place"
        }
    ],
    "sg:phone":"+1 931 456 8344",
    "sg:postcode":"38572",
    "sg:province":"TN",
    "wof:name":"Homestead Elementary School",
    "wof:placetype":"venue"
},
  "geometry": {"coordinates":[-84.98586899999999,35.903561],"type":"Point"}
}