{
  "type": "Feature",
  "properties": {
    "addr:full":"2991 Spring Place Rd SE Cleveland TN 37323",
    "addr:housenumber":"2991",
    "addr:postcode":"37323",
    "addr:street":"Spring Place Rd Se",
    "iso:country":"US",
    "sg:address":"2991 Spring Place Rd SE",
    "sg:city":"Cleveland",
    "sg:classifiers":[
        {
            "category":"Personal",
            "subcategory":"Beauty Salon",
            "type":"Services"
        }
    ],
    "sg:phone":"+1 423 479 4862",
    "sg:postcode":"37323",
    "sg:province":"TN",
    "wof:name":"P J's Beauty Shop & Tanning Salon",
    "wof:placetype":"venue"
},
  "geometry": {"coordinates":[-84.83543400000001,35.115337],"type":"Point"}
}