{
  "type": "Feature",
  "properties": {
    "iso:country":"US",
    "sg:address":"150 Denning Ford Rd",
    "sg:city":"Portland",
    "sg:classifiers":[
        {
            "category":"Building & Trades",
            "subcategory":"Construction",
            "type":"Services"
        }
    ],
    "sg:phone":"+1 615 323 0939",
    "sg:postcode":"37148",
    "sg:province":"TN",
    "sg:tags":[
        "residential"
    ],
    "wof:name":"Dye Michael J & Assoc LLC",
    "wof:placetype":"venue"
},
  "geometry": {"coordinates":[-86.499511,36.59823],"type":"Point"}
}