{
  "type": "Feature",
  "properties": {
    "iso:country":"US",
    "sg:address":"1405 US Hwy 51 Bus",
    "sg:city":"Dyersburg",
    "sg:classifiers":[
        {
            "category":"Autos & Motor Vehicles",
            "subcategory":"Automobile Sales",
            "type":"Retail Goods"
        }
    ],
    "sg:phone":"+1 731 286 4401",
    "sg:postcode":"38024",
    "sg:province":"TN",
    "sg:tags":[
        "car",
        "dealer"
    ],
    "wof:name":"Sartin's Auto Sales",
    "wof:placetype":"venue"
},
  "geometry": {"coordinates":[-89.37239,36.046638],"type":"Point"}
}