{
  "type": "Feature",
  "properties": {
    "addr:full":"203 E Public Sq Centerville TN 37033",
    "addr:housenumber":"203",
    "addr:postcode":"37033",
    "addr:street":"Public Sq",
    "iso:country":"US",
    "sg:address":"203 E Public Sq",
    "sg:city":"Centerville",
    "sg:classifiers":[
        {
            "category":"Social Services",
            "type":"Services"
        }
    ],
    "sg:phone":"+1 931 729 4555",
    "sg:postcode":"37033",
    "sg:province":"TN",
    "wof:name":"Joe Duley Lcsw",
    "wof:placetype":"venue"
},
  "geometry": {"coordinates":[-87.466548,35.77845],"type":"Point"}
}