{
  "type": "Feature",
  "properties": {
    "addr:full":"210 Virgil Crowell Rd Unionville TN 37180",
    "addr:housenumber":"210",
    "addr:postcode":"37180",
    "addr:street":"Virgil Crowell Rd",
    "iso:country":"US",
    "sg:address":"210 Virgil Crowell Rd",
    "sg:city":"Unionville",
    "sg:classifiers":[
        {
            "category":"Building & Trades",
            "subcategory":"Construction",
            "type":"Services"
        }
    ],
    "sg:phone":"+1 931 294 5935",
    "sg:postcode":"37180",
    "sg:province":"TN",
    "sg:tags":[
        "housing"
    ],
    "wof:name":"Michael Tapps Framing",
    "wof:placetype":"venue"
},
  "geometry": {"coordinates":[-86.595007,35.561116],"type":"Point"}
}