{
  "type": "Feature",
  "properties": {
    "iso:country":"US",
    "sg:address":"3320 Woodbury Hwy",
    "sg:city":"Manchester",
    "sg:classifiers":[
        {
            "category":"Social Services",
            "subcategory":"Child Care",
            "type":"Services"
        }
    ],
    "sg:phone":"+1 931 728 8434",
    "sg:postcode":"37355",
    "sg:province":"TN",
    "sg:tags":[
        "kindergarten",
        "academic",
        "school"
    ],
    "wof:name":"New Union Pre-School",
    "wof:placetype":"venue"
},
  "geometry": {"coordinates":[-86.080359,35.534166],"type":"Point"}
}