{
  "type": "Feature",
  "properties": {
    "iso:country":"US",
    "sg:address":"1260 Punkton Rd",
    "sg:city":"Del Rio",
    "sg:classifiers":[
        {
            "category":"Farming",
            "subcategory":"Farm",
            "type":"Manufacturing & Wholesale Goods"
        }
    ],
    "sg:phone":"+1 423 487 5152",
    "sg:postcode":"37727",
    "sg:province":"TN",
    "sg:tags":[
        "agricultural",
        "production"
    ],
    "wof:name":"Ronnie A Jones",
    "wof:placetype":"venue"
},
  "geometry": {"coordinates":[-83.03557499999999,35.871823],"type":"Point"}
}