{
  "type": "Feature",
  "properties": {
    "addr:full":"320 John Carson Rd Telford TN 37690",
    "addr:housenumber":"320",
    "addr:postcode":"37690",
    "addr:street":"John Carson Rd",
    "iso:country":"US",
    "sg:address":"320 John Carson Rd",
    "sg:city":"Telford",
    "sg:classifiers":[
        {
            "category":"Professional",
            "type":"Services"
        }
    ],
    "sg:phone":"+1 423 753 5979",
    "sg:postcode":"37690",
    "sg:province":"TN",
    "wof:name":"Charles W Saylor",
    "wof:placetype":"venue"
},
  "geometry": {"coordinates":[-82.567396,36.287985],"type":"Point"}
}