{
  "type": "Feature",
  "properties": {
    "addr:full":"204 21st Ave N Nashville TN 37203",
    "addr:housenumber":"204",
    "addr:postcode":"37203",
    "addr:street":"21St Ave N",
    "iso:country":"US",
    "sg:address":"204 21st Ave N",
    "sg:city":"Nashville",
    "sg:classifiers":[
        {
            "category":"Restaurant",
            "type":"Food & Drink"
        }
    ],
    "sg:phone":"+1 615 329 8994",
    "sg:postcode":"37203",
    "sg:province":"TN",
    "sg:tags":[
        "eating"
    ],
    "sg:website":"www.nickandrudys.com",
    "wof:name":"Nick & Rudy's Steakhouse",
    "wof:placetype":"venue"
},
  "geometry": {"coordinates":[-86.80327699999999,36.153344],"type":"Point"}
}