{
  "type": "Feature",
  "properties": {
    "addr:full":"6250 Stage Rd Memphis TN 38134",
    "addr:housenumber":"6250",
    "addr:postcode":"38134",
    "addr:street":"Stage Rd",
    "iso:country":"US",
    "sg:address":"6250 Stage Rd",
    "sg:city":"Memphis",
    "sg:classifiers":[
        {
            "category":"Restaurant",
            "type":"Food & Drink"
        }
    ],
    "sg:menulink":"http://www.allmenus.com/tn/memphis/29290-exlines-best-pizza-in-town/menu/",
    "sg:phone":"+1 901 382 3433",
    "sg:postcode":"38134",
    "sg:province":"TN",
    "sg:tags":[
        "american",
        "pizza"
    ],
    "wof:name":"Exlines' Best Pizza in Town",
    "wof:placetype":"venue"
},
  "geometry": {"coordinates":[-89.854902,35.205096],"type":"Point"}
}