{
  "type": "Feature",
  "properties": {
    "iso:country":"US",
    "sg:address":"4335 Bull Run Rd",
    "sg:city":"Ashland City",
    "sg:classifiers":[
        {
            "category":"Farming",
            "subcategory":"Livestock Farm",
            "type":"Manufacturing & Wholesale Goods"
        }
    ],
    "sg:phone":"+1 615 254 6995",
    "sg:postcode":"37015",
    "sg:province":"TN",
    "sg:tags":[
        "beef",
        "feedlot",
        "cattle"
    ],
    "wof:name":"Joseph S Dozier",
    "wof:placetype":"venue"
},
  "geometry": {"coordinates":[-86.963831,36.230915],"type":"Point"}
}