{
  "type": "Feature",
  "properties": {
    "iso:country":"US",
    "sg:address":"1915 Brewer Rd",
    "sg:city":"Dyersburg",
    "sg:classifiers":[
        {
            "category":"Home & Garden",
            "subcategory":"Carpets & Floor Coverings",
            "type":"Retail Goods"
        }
    ],
    "sg:phone":"+1 731 287 7360",
    "sg:postcode":"38024",
    "sg:province":"TN",
    "sg:tags":[
        "dealer",
        "rug"
    ],
    "wof:name":"Dyersburg Floor Covering",
    "wof:placetype":"venue"
},
  "geometry": {"coordinates":[-89.41543299999999,36.041154],"type":"Point"}
}