{
  "type": "Feature",
  "properties": {
    "iso:country":"US",
    "sg:address":"340 Shipley Ferry Rd",
    "sg:city":"Blountville",
    "sg:classifiers":[
        {
            "category":"Wholesale",
            "subcategory":"Groceries",
            "type":"Manufacturing & Wholesale Goods"
        }
    ],
    "sg:phone":"+1 423 323 1379",
    "sg:postcode":"37617",
    "sg:province":"TN",
    "sg:tags":[
        "food",
        "broker"
    ],
    "wof:name":"Reese Brokerage Of E Tennessee",
    "wof:placetype":"venue"
},
  "geometry": {"coordinates":[-82.39494500000001,36.526639],"type":"Point"}
}