{
  "type": "Feature",
  "properties": {
    "addr:full":"322 N Maple St Lebanon TN 37087",
    "addr:housenumber":"322",
    "addr:postcode":"37087",
    "addr:street":"N Maple St",
    "iso:country":"US",
    "sg:address":"322 N Maple St",
    "sg:city":"Lebanon",
    "sg:classifiers":[
        {
            "category":"Social Services",
            "type":"Services"
        }
    ],
    "sg:phone":"+1 615 443 2774",
    "sg:postcode":"37087",
    "sg:province":"TN",
    "sg:tags":[
        "probation"
    ],
    "wof:name":"Probation Office",
    "wof:placetype":"venue"
},
  "geometry": {"coordinates":[-86.291983,36.211679],"type":"Point"}
}