{
  "type": "Feature",
  "properties": {
    "iso:country":"US",
    "sg:address":"5034 Nashville Hwy",
    "sg:city":"Mc Minnville",
    "sg:classifiers":[
        {
            "category":"Retail",
            "subcategory":"Repair Shop",
            "type":"Services"
        }
    ],
    "sg:phone":"+1 931 815 9293",
    "sg:postcode":"37110",
    "sg:province":"TN",
    "sg:tags":[
        "scooter",
        "motorcycle",
        "motor"
    ],
    "wof:name":"Kenny's Cycle Sales & Svc Inc",
    "wof:placetype":"venue"
},
  "geometry": {"coordinates":[-85.84793000000001,35.706115],"type":"Point"}
}