{
  "type": "Feature",
  "properties": {
    "addr:full":"610 Center St Morristown TN 37813",
    "addr:housenumber":"610",
    "addr:postcode":"37813",
    "addr:street":"Center St",
    "iso:country":"US",
    "sg:address":"610 Center St",
    "sg:city":"Morristown",
    "sg:classifiers":[
        {
            "category":"Organizations",
            "subcategory":"Labor Organization",
            "type":"Services"
        }
    ],
    "sg:phone":"+1 423 587 4959",
    "sg:postcode":"37813",
    "sg:province":"TN",
    "wof:name":"I B E W Local 365",
    "wof:placetype":"venue"
},
  "geometry": {"coordinates":[-83.285606,36.209311],"type":"Point"}
}