{
  "type": "Feature",
  "properties": {
    "addr:full":"663 Northview Dr Kodak TN 37764",
    "addr:housenumber":"663",
    "addr:postcode":"37764",
    "addr:street":"Northview Dr",
    "iso:country":"US",
    "sg:address":"663 Northview Dr",
    "sg:city":"Kodak",
    "sg:classifiers":[
        {
            "category":"Shopping",
            "type":"Retail Goods"
        }
    ],
    "sg:phone":"+1 865 933 9314",
    "sg:postcode":"37764",
    "sg:province":"TN",
    "sg:tags":[
        "merchandise"
    ],
    "wof:name":"Mountain Stream Spas",
    "wof:placetype":"venue"
},
  "geometry": {"coordinates":[-83.64211299999999,35.977948],"type":"Point"}
}