{
  "type": "Feature",
  "properties": {
    "iso:country":"US",
    "sg:address":"2118 Windsor St",
    "sg:city":"Chattanooga",
    "sg:classifiers":[
        {
            "category":"Professional",
            "type":"Services"
        }
    ],
    "sg:phone":"+1 423 629 2767",
    "sg:postcode":"37406",
    "sg:province":"TN",
    "wof:name":"Night Stalker",
    "wof:placetype":"venue"
},
  "geometry": {"coordinates":[-85.263189,35.047689],"type":"Point"}
}