{
  "type": "Feature",
  "properties": {
    "addr:full":"134 Wells Rd Powell TN 37849",
    "addr:housenumber":"134",
    "addr:postcode":"37849",
    "addr:street":"Wells Rd",
    "iso:country":"US",
    "sg:address":"134 Wells Rd",
    "sg:city":"Powell",
    "sg:classifiers":[
        {
            "category":"Education",
            "subcategory":"Special Training",
            "type":"Public Place"
        }
    ],
    "sg:phone":"+1 865 945 5031",
    "sg:postcode":"37849",
    "sg:province":"TN",
    "wof:name":"Boulton",
    "wof:placetype":"venue"
},
  "geometry": {"coordinates":[-84.08202199999999,36.035941],"type":"Point"}
}