{
  "type": "Feature",
  "properties": {
    "iso:country":"US",
    "sg:address":"2230 Osburn Rd",
    "sg:city":"Arrington",
    "sg:classifiers":[
        {
            "category":"Building & Trades",
            "subcategory":"Landscaping Services",
            "type":"Services"
        }
    ],
    "sg:phone":"+1 615 260 7998",
    "sg:postcode":"37014",
    "sg:province":"TN",
    "sg:tags":[
        "landscape",
        "contractor"
    ],
    "wof:name":"Men In Green",
    "wof:placetype":"venue"
},
  "geometry": {"coordinates":[-86.68195799999999,35.88964],"type":"Point"}
}