{
  "type": "Feature",
  "properties": {
    "addr:full":"2528 N Mount Juliet Rd Mt Juliet TN 37122",
    "addr:housenumber":"2528",
    "addr:postcode":"37122",
    "addr:street":"N Mount Juliet Rd",
    "iso:country":"US",
    "sg:address":"2528 N Mount Juliet Rd",
    "sg:city":"Mt Juliet",
    "sg:classifiers":[
        {
            "category":"Freight",
            "type":"Transportation"
        }
    ],
    "sg:phone":"+1 615 773 5301",
    "sg:postcode":"37122",
    "sg:province":"TN",
    "sg:tags":[
        "broker",
        "trucking"
    ],
    "wof:name":"USA Transportation",
    "wof:placetype":"venue"
},
  "geometry": {"coordinates":[-86.518209,36.204767],"type":"Point"}
}