{
  "type": "Feature",
  "properties": {
    "iso:country":"US",
    "sg:address":"1715 Mill Rd",
    "sg:city":"Trezevant",
    "sg:classifiers":[
        {
            "category":"Building & Trades",
            "subcategory":"Construction",
            "type":"Services"
        }
    ],
    "sg:phone":"+1 731 669 6296",
    "sg:postcode":"38258",
    "sg:province":"TN",
    "sg:tags":[
        "contractor"
    ],
    "wof:name":"Arnolds Repair",
    "wof:placetype":"venue"
},
  "geometry": {"coordinates":[-88.66874199999999,36.047803],"type":"Point"}
}