{
  "type": "Feature",
  "properties": {
    "iso:country":"US",
    "sg:address":"277 Jackson Ln W",
    "sg:city":"Greeneville",
    "sg:classifiers":[
        {
            "category":"Banks & Credit Unions",
            "subcategory":"Financial Services",
            "type":"Services"
        }
    ],
    "sg:phone":"+1 423 234 0077",
    "sg:postcode":"37745",
    "sg:province":"TN",
    "sg:tags":[
        "loan"
    ],
    "wof:name":"The Equity Network",
    "wof:placetype":"venue"
},
  "geometry": {"coordinates":[-82.74122800000001,36.370631],"type":"Point"}
}