{
  "type": "Feature",
  "properties": {
    "iso:country":"US",
    "sg:address":"5317 Wessex Dr",
    "sg:city":"Nashville",
    "sg:classifiers":[
        {
            "category":"Professional",
            "subcategory":"Art Services",
            "type":"Services"
        }
    ],
    "sg:phone":"+1 615 833 6038",
    "sg:postcode":"37211",
    "sg:province":"TN",
    "sg:tags":[
        "photography",
        "commercial"
    ],
    "wof:name":"X Press Studio",
    "wof:placetype":"venue"
},
  "geometry": {"coordinates":[-86.70802500000001,36.052466],"type":"Point"}
}