{
  "type": "Feature",
  "properties": {
    "addr:full":"525 Mainstream Dr Nashville TN 37228",
    "addr:housenumber":"525",
    "addr:postcode":"37228",
    "addr:street":"Mainstream Dr",
    "iso:country":"US",
    "sg:address":"525 Mainstream Dr",
    "sg:city":"Nashville",
    "sg:classifiers":[
        {
            "category":"Health Services",
            "subcategory":"Medical Lab",
            "type":"Services"
        }
    ],
    "sg:phone":"+1 615 687 2000",
    "sg:postcode":"37228",
    "sg:province":"TN",
    "sg:tags":[
        "laboratory"
    ],
    "wof:name":"Quest Diagnostics Inc",
    "wof:placetype":"venue"
},
  "geometry": {"coordinates":[-86.809682,36.19991],"type":"Point"}
}