{
  "type": "Feature",
  "properties": {
    "addr:full":"1008 Paddingdon Rd Knoxville TN 37922",
    "addr:housenumber":"1008",
    "addr:postcode":"37922",
    "addr:street":"Paddingdon Rd",
    "iso:country":"US",
    "sg:address":"1008 Paddingdon Rd",
    "sg:city":"Knoxville",
    "sg:classifiers":[
        {
            "category":"Shopping",
            "subcategory":"Gifts & Souvenirs",
            "type":"Retail Goods"
        }
    ],
    "sg:phone":"+1 865 692 9339",
    "sg:postcode":"37922",
    "sg:province":"TN",
    "wof:name":"Notable Gifts",
    "wof:placetype":"venue"
},
  "geometry": {"coordinates":[-84.040621,35.89607],"type":"Point"}
}