{
  "type": "Feature",
  "properties": {
    "iso:country":"US",
    "sg:address":"26909 Main St",
    "sg:city":"Ardmore",
    "sg:classifiers":[
        {
            "category":"Restaurant",
            "type":"Food & Drink"
        }
    ],
    "sg:menulink":"http://www.allmenus.com/tn/elkton/191626-sonic/menu/",
    "sg:phone":"+1 931 427 2522",
    "sg:postcode":"38449",
    "sg:province":"TN",
    "sg:tags":[
        "burger",
        "american"
    ],
    "wof:name":"Sonic",
    "wof:placetype":"venue"
},
  "geometry": {"coordinates":[-86.838632,34.992271],"type":"Point"}
}