{
  "type": "Feature",
  "properties": {
    "iso:country":"US",
    "sg:address":"2119 Antioch Pike",
    "sg:city":"Antioch",
    "sg:classifiers":[
        {
            "category":"Recreation",
            "subcategory":"Amusement Park",
            "type":"Entertainment"
        }
    ],
    "sg:phone":"+1 615 256 5902",
    "sg:postcode":"37013",
    "sg:province":"TN",
    "sg:website":"www.tdrowe.com",
    "wof:name":"T D Rowe Amusement",
    "wof:placetype":"venue"
},
  "geometry": {"coordinates":[-86.683846,36.06912],"type":"Point"}
}