{
  "type": "Feature",
  "properties": {
    "iso:country":"US",
    "sg:address":"570 Bennett Hill Rd",
    "sg:city":"Red Boiling Spgs",
    "sg:classifiers":[
        {
            "category":"Government",
            "subcategory":"Office",
            "type":"Public Place"
        }
    ],
    "sg:phone":"+1 615 699 2000",
    "sg:postcode":"37150",
    "sg:province":"TN",
    "sg:tags":[
        "federal",
        "planning",
        "dev"
    ],
    "wof:name":"Rural Development LLC",
    "wof:placetype":"venue"
},
  "geometry": {"coordinates":[-85.83986899999999,36.541398],"type":"Point"}
}