{
  "type": "Feature",
  "properties": {
    "iso:country":"US",
    "sg:address":"5432 Bell Forge Ln E",
    "sg:city":"Antioch",
    "sg:classifiers":[
        {
            "category":"Shopping",
            "type":"Retail Goods"
        }
    ],
    "sg:phone":"+1 615 731 0503",
    "sg:postcode":"37013",
    "sg:province":"TN",
    "sg:tags":[
        "pet",
        "shop"
    ],
    "sg:website":"www.superpetz.com",
    "wof:name":"Superpetz LLC",
    "wof:placetype":"venue"
},
  "geometry": {"coordinates":[-86.647667,36.047078],"type":"Point"}
}