{
  "type": "Feature",
  "properties": {
    "iso:country":"US",
    "sg:address":"1511 Jacobs Ave SW",
    "sg:city":"Cleveland",
    "sg:classifiers":[
        {
            "category":"Building & Trades",
            "subcategory":"Construction",
            "type":"Services"
        }
    ],
    "sg:phone":"+1 423 559 0315",
    "sg:postcode":"37311",
    "sg:province":"TN",
    "sg:tags":[
        "excavation",
        "contractor"
    ],
    "wof:name":"Alray Excavation",
    "wof:placetype":"venue"
},
  "geometry": {"coordinates":[-84.894081,35.152445],"type":"Point"}
}