{
  "type": "Feature",
  "properties": {
    "iso:country":"US",
    "sg:address":"1326 Chadwick Cir",
    "sg:city":"Memphis",
    "sg:classifiers":[
        {
            "category":"Real Estate",
            "subcategory":"Real Estate Operator",
            "type":"Services"
        }
    ],
    "sg:phone":"+1 901 721 6007",
    "sg:postcode":"38114",
    "sg:province":"TN",
    "sg:tags":[
        "apartment"
    ],
    "wof:name":"Copper St Apt & Duplexes",
    "wof:placetype":"venue"
},
  "geometry": {"coordinates":[-89.99192600000001,35.10744],"type":"Point"}
}