{
  "type": "Feature",
  "properties": {
    "iso:country":"US",
    "sg:address":"44 Forest Cove",
    "sg:city":"Jackson",
    "sg:classifiers":[
        {
            "category":"Health Services",
            "subcategory":"Doctor",
            "type":"Services"
        }
    ],
    "sg:phone":"+1 731 422 0213",
    "sg:postcode":"38301",
    "sg:province":"TN",
    "sg:tags":[
        "physician",
        "surgeon"
    ],
    "wof:name":"Robert J Gilroy MD",
    "wof:placetype":"venue"
},
  "geometry": {"coordinates":[-88.82758800000001,35.635137],"type":"Point"}
}