{
  "type": "Feature",
  "properties": {
    "addr:full":"6555 US Hwy 41 N Cedar Hill TN 37032",
    "addr:housenumber":"6555",
    "addr:postcode":"37032",
    "addr:street":"Us Hwy 41 N",
    "iso:country":"US",
    "sg:address":"6555 US Hwy 41 N",
    "sg:city":"Cedar Hill",
    "sg:classifiers":[
        {
            "category":"Autos & Motor Vehicles",
            "subcategory":"Fuel & Gas Station",
            "type":"Retail Goods"
        }
    ],
    "sg:phone":"+1 615 696 0551",
    "sg:postcode":"37032",
    "sg:province":"TN",
    "sg:tags":[
        "oil"
    ],
    "wof:name":"Billy's BP",
    "wof:placetype":"venue"
},
  "geometry": {"coordinates":[-86.996045,36.554376],"type":"Point"}
}