{
  "type": "Feature",
  "properties": {
    "addr:full":"260 Quarry Rd Harriman TN 37748",
    "addr:housenumber":"260",
    "addr:postcode":"37748",
    "addr:street":"Quarry Rd",
    "iso:country":"US",
    "sg:address":"260 Quarry Rd",
    "sg:city":"Harriman",
    "sg:classifiers":[
        {
            "category":"Mining & Drilling",
            "type":"Manufacturing & Wholesale Goods"
        }
    ],
    "sg:phone":"+1 865 882 0332",
    "sg:postcode":"37748",
    "sg:province":"TN",
    "sg:tags":[
        "stone",
        "crushing"
    ],
    "wof:name":"Marietta Martin Materials Inc",
    "wof:placetype":"venue"
},
  "geometry": {"coordinates":[-84.49994,35.939999],"type":"Point"}
}