{
  "type": "Feature",
  "properties": {
    "iso:country":"US",
    "sg:address":"1300 Sunny Dr",
    "sg:city":"Trenton",
    "sg:classifiers":[
        {
            "category":"Shopping",
            "type":"Retail Goods"
        }
    ],
    "sg:phone":"+1 731 855 9291",
    "sg:postcode":"38382",
    "sg:province":"TN",
    "sg:tags":[
        "cosmetic",
        "perfume"
    ],
    "wof:name":"Beauti Control Cosmetics",
    "wof:placetype":"venue"
},
  "geometry": {"coordinates":[-88.936993,35.964636],"type":"Point"}
}