{
  "type": "Feature",
  "properties": {
    "iso:country":"US",
    "sg:address":"4535 Benjestown Rd",
    "sg:city":"Memphis",
    "sg:classifiers":[
        {
            "category":"Organizations",
            "subcategory":"Religious Organization",
            "type":"Services"
        }
    ],
    "sg:phone":"+1 901 353 9349",
    "sg:postcode":"38127",
    "sg:province":"TN",
    "wof:name":"Victory Valley Bible",
    "wof:placetype":"venue"
},
  "geometry": {"coordinates":[-90.05571500000001,35.251373],"type":"Point"}
}