{
  "type": "Feature",
  "properties": {
    "iso:country":"US",
    "sg:address":"602 S Gay St",
    "sg:city":"Knoxville",
    "sg:classifiers":[
        {
            "category":"Professional",
            "subcategory":"Lawyer & Legal Services",
            "type":"Services"
        }
    ],
    "sg:phone":"+1 865 291 0111",
    "sg:postcode":"37902",
    "sg:province":"TN",
    "wof:name":"Holdenburg and Rodolfa LLC",
    "wof:placetype":"venue"
},
  "geometry": {"coordinates":[-83.917421,35.963918],"type":"Point"}
}