{
  "type": "Feature",
  "properties": {
    "iso:country":"US",
    "sg:address":"200 Old Hwy 30",
    "sg:city":"Dayton",
    "sg:classifiers":[
        {
            "category":"Restaurant",
            "type":"Food & Drink"
        }
    ],
    "sg:phone":"+1 423 775 2819",
    "sg:postcode":"37321",
    "sg:province":"TN",
    "sg:tags":[
        "eating"
    ],
    "wof:name":"China King Buffet",
    "wof:placetype":"venue"
},
  "geometry": {"coordinates":[-85.051874,35.5301],"type":"Point"}
}