{
  "type": "Feature",
  "properties": {
    "iso:country":"US",
    "sg:address":"125 Jesse Range Rd",
    "sg:city":"Jamestown",
    "sg:classifiers":[
        {
            "category":"Organizations",
            "subcategory":"Religious Organization",
            "type":"Services"
        }
    ],
    "sg:phone":"+1 931 879 8041",
    "sg:postcode":"38556",
    "sg:province":"TN",
    "sg:tags":[
        "church"
    ],
    "wof:name":"Pine Haven Baptist Church",
    "wof:placetype":"venue"
},
  "geometry": {"coordinates":[-84.92259199999999,36.353604],"type":"Point"}
}