{
  "type": "Feature",
  "properties": {
    "iso:country":"US",
    "sg:address":"6761 Hall Rd",
    "sg:city":"Greenbrier",
    "sg:classifiers":[
        {
            "category":"Bus Charters",
            "type":"Transportation"
        },
        {
            "category":"Retail",
            "subcategory":"Auto Repair",
            "type":"Services"
        }
    ],
    "sg:phone":"+1 615 643 7471",
    "sg:postcode":"37073",
    "sg:province":"TN",
    "wof:name":"Carl Logan & Son Bus Repair",
    "wof:placetype":"venue"
},
  "geometry": {"coordinates":[-86.755993,36.444752],"type":"Point"}
}