{
  "type": "Feature",
  "properties": {
    "addr:full":"100 Rosefield Dr Kingsport TN 37660",
    "addr:housenumber":"100",
    "addr:postcode":"37660",
    "addr:street":"Rosefield Dr",
    "iso:country":"US",
    "sg:address":"100 Rosefield Dr",
    "sg:city":"Kingsport",
    "sg:phone":"+1 423 247 1813",
    "sg:postcode":"37660",
    "sg:province":"TN",
    "sg:tags":[
        "wheat",
        "tobacco",
        "beef",
        "farm",
        "cattle",
        "feedlot"
    ],
    "wof:name":"J C Shanks Jr",
    "wof:placetype":"venue"
},
  "geometry": {"coordinates":[-82.54753599999999,36.55999],"type":"Point"}
}