{
  "type": "Feature",
  "properties": {
    "iso:country":"US",
    "sg:address":"24 Federal Dr",
    "sg:city":"Jackson",
    "sg:classifiers":[
        {
            "category":"Professional",
            "subcategory":"Advertising",
            "type":"Services"
        }
    ],
    "sg:phone":"+1 731 668 6562",
    "sg:postcode":"38305",
    "sg:province":"TN",
    "sg:tags":[
        "agency"
    ],
    "wof:name":"Second To None Advertising",
    "wof:placetype":"venue"
},
  "geometry": {"coordinates":[-88.834034,35.668417],"type":"Point"}
}