{
  "type": "Feature",
  "properties": {
    "iso:country":"US",
    "sg:address":"306 N White St",
    "sg:city":"Athens",
    "sg:classifiers":[
        {
            "category":"Home & Garden",
            "subcategory":"Furniture",
            "type":"Retail Goods"
        }
    ],
    "sg:phone":"+1 423 745 1642",
    "sg:postcode":"37303",
    "sg:province":"TN",
    "wof:name":"Mc Spadden Furniture Co",
    "wof:placetype":"venue"
},
  "geometry": {"coordinates":[-84.59450699999999,35.44425],"type":"Point"}
}