{
  "type": "Feature",
  "properties": {
    "addr:full":"6312 Kingston Pike Knoxville TN 37919",
    "addr:housenumber":"6312",
    "addr:postcode":"37919",
    "addr:street":"Kingston Pike",
    "iso:country":"US",
    "sg:address":"6312 Kingston Pike",
    "sg:city":"Knoxville",
    "sg:classifiers":[
        {
            "category":"Wholesale",
            "subcategory":"Auto Parts",
            "type":"Manufacturing & Wholesale Goods"
        }
    ],
    "sg:phone":"+1 865 330 0019",
    "sg:postcode":"37919",
    "sg:province":"TN",
    "wof:name":"Jsd Wholesale Distributing",
    "wof:placetype":"venue"
},
  "geometry": {"coordinates":[-84.005807,35.932134],"type":"Point"}
}