{
  "type": "Feature",
  "properties": {
    "iso:country":"US",
    "sg:address":"305 Clover Bottom Dr",
    "sg:city":"Kingsport",
    "sg:classifiers":[
        {
            "category":"Professional",
            "subcategory":"Management & Consulting",
            "type":"Services"
        }
    ],
    "sg:phone":"+1 423 349 6531",
    "sg:postcode":"37660",
    "sg:province":"TN",
    "sg:tags":[
        "business"
    ],
    "wof:name":"Comkin Corp",
    "wof:placetype":"venue"
},
  "geometry": {"coordinates":[-82.595506,36.475776],"type":"Point"}
}