{
  "type": "Feature",
  "properties": {
    "iso:country":"US",
    "sg:address":"3547 W Market St",
    "sg:city":"Johnson City",
    "sg:classifiers":[
        {
            "category":"Building & Trades",
            "subcategory":"Construction",
            "type":"Services"
        }
    ],
    "sg:phone":"+1 423 929 8080",
    "sg:postcode":"37604",
    "sg:province":"TN",
    "sg:tags":[
        "contractor"
    ],
    "wof:name":"Barnyard Fencing",
    "wof:placetype":"venue"
},
  "geometry": {"coordinates":[-82.419978,36.313008],"type":"Point"}
}