{
  "type": "Feature",
  "properties": {
    "addr:full":"851 Keith St NW Cleveland TN 37311",
    "addr:housenumber":"851",
    "addr:postcode":"37311",
    "addr:street":"Keith St Nw",
    "iso:country":"US",
    "sg:address":"851 Keith St NW",
    "sg:city":"Cleveland",
    "sg:classifiers":[
        {
            "category":"Restaurant",
            "type":"Food & Drink"
        }
    ],
    "sg:menulink":"http://www.allmenus.com/tn/cleveland/113924-planet-smoothie/menu/",
    "sg:phone":"+1 423 472 3582",
    "sg:postcode":"37311",
    "sg:province":"TN",
    "sg:tags":[
        "smoothy",
        "juice",
        "american"
    ],
    "wof:name":"Planet Smoothie",
    "wof:placetype":"venue"
},
  "geometry": {"coordinates":[-84.881018,35.166732],"type":"Point"}
}