{
  "type": "Feature",
  "properties": {
    "iso:country":"US",
    "sg:address":"185 Delvin Dr",
    "sg:city":"Antioch",
    "sg:classifiers":[
        {
            "category":"Social Services",
            "subcategory":"Child Care",
            "type":"Services"
        }
    ],
    "sg:phone":"+1 615 832 7505",
    "sg:postcode":"37013",
    "sg:province":"TN",
    "sg:tags":[
        "day"
    ],
    "wof:name":"Hollie Group Day Care Home",
    "wof:placetype":"venue"
},
  "geometry": {"coordinates":[-86.69371700000001,36.052577],"type":"Point"}
}