{
  "type": "Feature",
  "properties": {
    "iso:country":"US",
    "sg:address":"17 Mann Rd",
    "sg:city":"Lebanon",
    "sg:classifiers":[
        {
            "category":"Restaurant",
            "type":"Food & Drink"
        }
    ],
    "sg:phone":"+1 615 449 7939",
    "sg:postcode":"37087",
    "sg:province":"TN",
    "sg:tags":[
        "eating"
    ],
    "wof:name":"Perfect Cup Coffee House",
    "wof:placetype":"venue"
},
  "geometry": {"coordinates":[-86.32941099999999,36.275379],"type":"Point"}
}