{
  "type": "Feature",
  "properties": {
    "addr:full":"2102 Windsor St Murfreesboro TN 37130",
    "addr:housenumber":"2102",
    "addr:postcode":"37130",
    "addr:street":"Windsor St",
    "iso:country":"US",
    "sg:address":"2102 Windsor St",
    "sg:city":"Murfreesboro",
    "sg:classifiers":[
        {
            "category":"Banks & Credit Unions",
            "subcategory":"Financial Services",
            "type":"Services"
        }
    ],
    "sg:phone":"+1 615 890 4916",
    "sg:postcode":"37130",
    "sg:province":"TN",
    "sg:tags":[
        "trust",
        "management"
    ],
    "wof:name":"Thompson Family Partnership",
    "wof:placetype":"venue"
},
  "geometry": {"coordinates":[-86.35334899999999,35.859522],"type":"Point"}
}