{
  "type": "Feature",
  "properties": {
    "addr:full":"770 Highway 51 N Ripley TN 38063",
    "addr:housenumber":"770",
    "addr:postcode":"38063",
    "addr:street":"Highway 51 N",
    "iso:country":"US",
    "sg:address":"770 Highway 51 N",
    "sg:city":"Ripley",
    "sg:classifiers":[
        {
            "category":"Fast Food",
            "type":"Food & Drink"
        },
        {
            "category":"Restaurant",
            "type":"Food & Drink"
        }
    ],
    "sg:phone":"+1 731 635 0222",
    "sg:postcode":"38063",
    "sg:province":"TN",
    "sg:tags":[
        "chicken"
    ],
    "sg:website":"http://www.friedstock.com",
    "wof:name":"Kfc",
    "wof:placetype":"venue"
},
  "geometry": {"coordinates":[-89.54341100000001,35.763786],"type":"Point"}
}