{
  "type": "Feature",
  "properties": {
    "addr:full":"2415 Sinking Creek Rd Johnson City TN 37604",
    "addr:housenumber":"2415",
    "addr:postcode":"37604",
    "addr:street":"Sinking Creek Rd",
    "iso:country":"US",
    "sg:address":"2415 Sinking Creek Rd",
    "sg:city":"Johnson City",
    "sg:classifiers":[
        {
            "category":"Organizations",
            "subcategory":"Religious Organization",
            "type":"Services"
        }
    ],
    "sg:phone":"+1 423 928 5376",
    "sg:postcode":"37604",
    "sg:province":"TN",
    "wof:name":"Berea Free Will Baptist Church",
    "wof:placetype":"venue"
},
  "geometry": {"coordinates":[-82.36520299999999,36.282937],"type":"Point"}
}