{
  "type": "Feature",
  "properties": {
    "iso:country":"US",
    "sg:address":"39 Salem Rd",
    "sg:city":"Rutherford",
    "sg:classifiers":[
        {
            "category":"Professional",
            "subcategory":"Secretarial Services",
            "type":"Services"
        }
    ],
    "sg:phone":"+1 731 665 6371",
    "sg:postcode":"38369",
    "sg:province":"TN",
    "sg:tags":[
        "transcription",
        "medical"
    ],
    "wof:name":"I Type It",
    "wof:placetype":"venue"
},
  "geometry": {"coordinates":[-88.92610999999999,36.11592],"type":"Point"}
}