{
  "type": "Feature",
  "properties": {
    "iso:country":"US",
    "sg:address":"114 Atkins Dr",
    "sg:city":"Madisonville",
    "sg:classifiers":[
        {
            "category":"Real Estate",
            "subcategory":"Real Estate Operator",
            "type":"Services"
        }
    ],
    "sg:phone":"+1 423 442 2324",
    "sg:postcode":"37354",
    "sg:province":"TN",
    "sg:tags":[
        "property",
        "lessor"
    ],
    "wof:name":"Glenn Atkins",
    "wof:placetype":"venue"
},
  "geometry": {"coordinates":[-84.34456400000001,35.500475],"type":"Point"}
}