{
  "type": "Feature",
  "properties": {
    "iso:country":"US",
    "sg:address":"706 N Sherbrooke Dr",
    "sg:city":"Mount Carmel",
    "sg:classifiers":[
        {
            "category":"Building & Trades",
            "subcategory":"Construction",
            "type":"Services"
        }
    ],
    "sg:phone":"+1 423 956 5242",
    "sg:postcode":"37645",
    "sg:province":"TN",
    "sg:tags":[
        "contractor"
    ],
    "wof:name":"Cliff Parkers Tile",
    "wof:placetype":"venue"
},
  "geometry": {"coordinates":[-82.647611,36.580971],"type":"Point"}
}