{
  "type": "Feature",
  "properties": {
    "iso:country":"US",
    "sg:address":"1215 Ridge Rd",
    "sg:city":"Maryville",
    "sg:classifiers":[
        {
            "category":"Building & Trades",
            "subcategory":"Construction",
            "type":"Services"
        }
    ],
    "sg:phone":"+1 865 983 7603",
    "sg:postcode":"37803",
    "sg:province":"TN",
    "sg:tags":[
        "roofing",
        "contractor"
    ],
    "wof:name":"J H Tipton Roofing",
    "wof:placetype":"venue"
},
  "geometry": {"coordinates":[-83.963289,35.70548],"type":"Point"}
}