{
  "type": "Feature",
  "properties": {
    "addr:full":"825 Exocet Dr Cordova TN 38018",
    "addr:housenumber":"825",
    "addr:postcode":"38018",
    "addr:street":"Exocet Dr",
    "iso:country":"US",
    "sg:address":"825 Exocet Dr",
    "sg:city":"Cordova",
    "sg:classifiers":[
        {
            "category":"Professional",
            "type":"Services"
        }
    ],
    "sg:phone":"+1 901 751 1765",
    "sg:postcode":"38018",
    "sg:province":"TN",
    "sg:tags":[
        "establishment"
    ],
    "wof:name":"Wilkinson & Snowden Inc",
    "wof:placetype":"venue"
},
  "geometry": {"coordinates":[-89.796644,35.148681],"type":"Point"}
}