{
  "type": "Feature",
  "properties": {
    "iso:country":"US",
    "sg:address":"2460 Music Valley Dr",
    "sg:city":"Nashville",
    "sg:classifiers":[
        {
            "category":"Travel",
            "subcategory":"Hotels & Motels",
            "type":"Entertainment"
        }
    ],
    "sg:phone":"+1 615 889 0090",
    "sg:postcode":"37214",
    "sg:province":"TN",
    "sg:website":"www.musicvalleyhotels.com",
    "wof:name":"Red Roof Inn-Nashville Music",
    "wof:placetype":"venue"
},
  "geometry": {"coordinates":[-86.694281,36.222451],"type":"Point"}
}