{
  "type": "Feature",
  "properties": {
    "addr:full":"1590 Nashville Hwy Lewisburg TN 37091",
    "addr:housenumber":"1590",
    "addr:postcode":"37091",
    "addr:street":"Nashville Hwy",
    "iso:country":"US",
    "sg:address":"1590 Nashville Hwy",
    "sg:city":"Lewisburg",
    "sg:classifiers":[
        {
            "category":"Retail",
            "subcategory":"Auto Rental",
            "type":"Services"
        }
    ],
    "sg:phone":"+1 931 359 6722",
    "sg:postcode":"37091",
    "sg:province":"TN",
    "sg:tags":[
        "truck"
    ],
    "wof:name":"U-Haul",
    "wof:placetype":"venue"
},
  "geometry": {"coordinates":[-86.769358,35.470036],"type":"Point"}
}