{
  "type": "Feature",
  "properties": {
    "iso:country":"US",
    "sg:address":"409 Independence Ct",
    "sg:city":"Franklin",
    "sg:classifiers":[
        {
            "category":"Personal",
            "subcategory":"Beauty Salon",
            "type":"Services"
        }
    ],
    "sg:phone":"+1 615 790 6889",
    "sg:postcode":"37086",
    "sg:province":"TN",
    "sg:tags":[
        "shop"
    ],
    "wof:name":"Paradise Hair & Tans",
    "wof:placetype":"venue"
},
  "geometry": {"coordinates":[-86.569956,36.029856],"type":"Point"}
}