{
  "type": "Feature",
  "properties": {
    "iso:country":"US",
    "sg:address":"2903 S Orchard Knob Ave",
    "sg:city":"Chattanooga",
    "sg:classifiers":[
        {
            "category":"Building & Trades",
            "subcategory":"Construction",
            "type":"Services"
        }
    ],
    "sg:phone":"+1 423 821 2137",
    "sg:postcode":"37407",
    "sg:province":"TN",
    "sg:tags":[
        "concrete",
        "pumping"
    ],
    "wof:name":"Scenic City Concrete Pumping",
    "wof:placetype":"venue"
},
  "geometry": {"coordinates":[-85.287814,35.012083],"type":"Point"}
}