{
  "type": "Feature",
  "properties": {
    "iso:country":"US",
    "sg:address":"6158 E Shelby Dr",
    "sg:city":"Memphis",
    "sg:classifiers":[
        {
            "category":"Professional",
            "subcategory":"Management & Consulting",
            "type":"Services"
        }
    ],
    "sg:phone":"+1 901 365 2011",
    "sg:postcode":"38141",
    "sg:province":"TN",
    "sg:tags":[
        "personnel",
        "consultant"
    ],
    "wof:name":"Omnisource Integrated Supply",
    "wof:placetype":"venue"
},
  "geometry": {"coordinates":[-89.85547,35.020442],"type":"Point"}
}