{
  "type": "Feature",
  "properties": {
    "addr:full":"4201 13th Ave Chattanooga TN 37407",
    "addr:housenumber":"4201",
    "addr:postcode":"37407",
    "addr:street":"13Th Ave",
    "iso:country":"US",
    "sg:address":"4201 13th Ave",
    "sg:city":"Chattanooga",
    "sg:classifiers":[
        {
            "category":"Autos & Motor Vehicles",
            "subcategory":"Fuel & Gas Station",
            "type":"Retail Goods"
        }
    ],
    "sg:phone":"+1 423 886 3575",
    "sg:postcode":"37407",
    "sg:province":"TN",
    "sg:tags":[
        "station",
        "gasoline"
    ],
    "wof:name":"Ronnies Service Center",
    "wof:placetype":"venue"
},
  "geometry": {"coordinates":[-85.283508,34.99202],"type":"Point"}
}