{
  "type": "Feature",
  "properties": {
    "addr:full":"6213 Lonas Dr Knoxville TN 37909",
    "addr:housenumber":"6213",
    "addr:postcode":"37909",
    "addr:street":"Lonas Dr",
    "iso:country":"US",
    "sg:address":"6213 Lonas Dr",
    "sg:city":"Knoxville",
    "sg:classifiers":[
        {
            "category":"Insurance",
            "subcategory":"Insurance Agent",
            "type":"Services"
        }
    ],
    "sg:phone":"+1 865 588 3318",
    "sg:postcode":"37909",
    "sg:province":"TN",
    "wof:name":"Walker Insurance Group",
    "wof:placetype":"venue"
},
  "geometry": {"coordinates":[-84.009384,35.942947],"type":"Point"}
}