{
  "type": "Feature",
  "properties": {
    "iso:country":"US",
    "sg:address":"2133 Belcourt Ave",
    "sg:city":"Nashville",
    "sg:classifiers":[
        {
            "category":"Health Services",
            "subcategory":"Doctor",
            "type":"Services"
        }
    ],
    "sg:phone":"+1 615 269 5044",
    "sg:postcode":"37212",
    "sg:province":"TN",
    "wof:name":"Jeffrey B Clark DDS",
    "wof:placetype":"venue"
},
  "geometry": {"coordinates":[-86.80288299999999,36.13673],"type":"Point"}
}