{
  "type": "Feature",
  "properties": {
    "iso:country":"US",
    "sg:address":"224 Gip Manning Rd",
    "sg:city":"Clarksville",
    "sg:classifiers":[
        {
            "category":"Professional",
            "subcategory":"Business Services",
            "type":"Services"
        }
    ],
    "sg:phone":"+1 931 920 2786",
    "sg:postcode":"37042",
    "sg:province":"TN",
    "sg:tags":[
        "medical",
        "care"
    ],
    "wof:name":"USG",
    "wof:placetype":"venue"
},
  "geometry": {"coordinates":[-87.461967,36.495368],"type":"Point"}
}