{
  "type": "Feature",
  "properties": {
    "iso:country":"US",
    "sg:address":"2410 Glass St",
    "sg:city":"Chattanooga",
    "sg:classifiers":[
        {
            "category":"Food & Beverages",
            "subcategory":"Liquor & Beverages",
            "type":"Retail Goods"
        }
    ],
    "sg:phone":"+1 423 698 8751",
    "sg:postcode":"37406",
    "sg:province":"TN",
    "wof:name":"Sandy's Liquor Store",
    "wof:placetype":"venue"
},
  "geometry": {"coordinates":[-85.25172999999999,35.064614],"type":"Point"}
}