{
  "type": "Feature",
  "properties": {
    "iso:country":"US",
    "sg:address":"1301 Imperial Dr",
    "sg:city":"Columbia",
    "sg:classifiers":[
        {
            "category":"Wholesale",
            "subcategory":"Auto Parts",
            "type":"Manufacturing & Wholesale Goods"
        }
    ],
    "sg:phone":"+1 931 388 1477",
    "sg:postcode":"38401",
    "sg:province":"TN",
    "sg:tags":[
        "supply"
    ],
    "wof:name":"Custom Auto Accessory Ctr",
    "wof:placetype":"venue"
},
  "geometry": {"coordinates":[-86.993872,35.699384],"type":"Point"}
}