{
  "type": "Feature",
  "properties": {
    "iso:country":"US",
    "sg:address":"2713 Colony Park Dr",
    "sg:city":"Memphis",
    "sg:classifiers":[
        {
            "category":"Professional",
            "subcategory":"Employment Agencies",
            "type":"Services"
        }
    ],
    "sg:phone":"+1 901 794 9933",
    "sg:postcode":"38118",
    "sg:province":"TN",
    "sg:tags":[
        "help",
        "temp"
    ],
    "wof:name":"Express Personnel Services",
    "wof:placetype":"venue"
},
  "geometry": {"coordinates":[-89.921041,35.073459],"type":"Point"}
}