{
  "type": "Feature",
  "properties": {
    "iso:country":"US",
    "sg:address":"47 Birchwood Ln",
    "sg:city":"Crossville",
    "sg:classifiers":[
        {
            "category":"Building & Trades",
            "subcategory":"Construction",
            "type":"Services"
        }
    ],
    "sg:phone":"+1 931 484 6402",
    "sg:postcode":"38555",
    "sg:province":"TN",
    "sg:tags":[
        "general",
        "contractor"
    ],
    "wof:name":"Bowman Construction Co",
    "wof:placetype":"venue"
},
  "geometry": {"coordinates":[-85.039517,35.957598],"type":"Point"}
}