{
  "type": "Feature",
  "properties": {
    "iso:country":"US",
    "sg:address":"2954 Topside Rd",
    "sg:city":"Louisville",
    "sg:classifiers":[
        {
            "category":"Food & Beverages",
            "subcategory":"Groceries & Convenience Stores",
            "type":"Retail Goods"
        }
    ],
    "sg:phone":"+1 865 982 2926",
    "sg:postcode":"37777",
    "sg:province":"TN",
    "sg:tags":[
        "grocer"
    ],
    "wof:name":"Louisville Squire Market",
    "wof:placetype":"venue"
},
  "geometry": {"coordinates":[-84.027958,35.818133],"type":"Point"}
}