{
  "type": "Feature",
  "properties": {
    "iso:country":"US",
    "sg:address":"820 Fesslers Ln",
    "sg:city":"Nashville",
    "sg:classifiers":[
        {
            "category":"Insurance",
            "subcategory":"Insurance Agent",
            "type":"Services"
        }
    ],
    "sg:phone":"+1 615 833 9070",
    "sg:postcode":"37210",
    "sg:province":"TN",
    "wof:name":"Insurance Warehouse",
    "wof:placetype":"venue"
},
  "geometry": {"coordinates":[-86.746724,36.137944],"type":"Point"}
}