{
  "type": "Feature",
  "properties": {
    "addr:full":"542 Tusculum Blvd Greeneville TN 37745",
    "addr:housenumber":"542",
    "addr:postcode":"37745",
    "addr:street":"Tusculum Blvd",
    "iso:country":"US",
    "sg:address":"542 Tusculum Blvd",
    "sg:city":"Greeneville",
    "sg:classifiers":[
        {
            "category":"Restaurant",
            "type":"Food & Drink"
        }
    ],
    "sg:phone":"+1 423 639 7191",
    "sg:postcode":"37745",
    "sg:province":"TN",
    "wof:name":"Sno Biz Of Greeneville",
    "wof:placetype":"venue"
},
  "geometry": {"coordinates":[-82.81679800000001,36.17097],"type":"Point"}
}