{
  "type": "Feature",
  "properties": {
    "addr:full":"550 Andrew Johnson Hwy Strawberry Plns TN 37871",
    "addr:housenumber":"550",
    "addr:postcode":"37871",
    "addr:street":"Andrew Johnson Hwy Strawberry",
    "iso:country":"US",
    "sg:address":"550 Andrew Johnson Hwy",
    "sg:city":"Strawberry Plns",
    "sg:classifiers":[
        {
            "category":"Professional",
            "subcategory":"Lawyer & Legal Services",
            "type":"Services"
        }
    ],
    "sg:phone":"+1 865 933 7081",
    "sg:postcode":"37871",
    "sg:province":"TN",
    "sg:tags":[
        "attorney"
    ],
    "wof:name":"John M Norris",
    "wof:placetype":"venue"
},
  "geometry": {"coordinates":[-83.72375,36.035222],"type":"Point"}
}