{
  "type": "Feature",
  "properties": {
    "iso:country":"US",
    "sg:address":"6201 Hickory Valley Rd",
    "sg:city":"Nashville",
    "sg:classifiers":[
        {
            "category":"Manufacturing",
            "subcategory":"Toys & Sporting Goods",
            "type":"Manufacturing & Wholesale Goods"
        }
    ],
    "sg:phone":"+1 615 352 5100",
    "sg:postcode":"37205",
    "sg:province":"TN",
    "sg:tags":[
        "mfg"
    ],
    "wof:name":"Hillwood Tennis Shop",
    "wof:placetype":"venue"
},
  "geometry": {"coordinates":[-86.872917,36.121441],"type":"Point"}
}