{
  "type": "Feature",
  "properties": {
    "addr:full":"480 Mc Nally Dr Nashville TN 37211",
    "addr:housenumber":"480",
    "addr:postcode":"37211",
    "addr:street":"Mc Nally Dr",
    "iso:country":"US",
    "sg:address":"480 Mc Nally Dr",
    "sg:city":"Nashville",
    "sg:classifiers":[
        {
            "category":"Manufacturing",
            "subcategory":"Textiles",
            "type":"Manufacturing & Wholesale Goods"
        }
    ],
    "sg:phone":"+1 615 832 4080",
    "sg:postcode":"37211",
    "sg:province":"TN",
    "sg:tags":[
        "thread"
    ],
    "sg:website":"www.volunteerthread.com",
    "wof:name":"Volunteer Thread Co",
    "wof:placetype":"venue"
},
  "geometry": {"coordinates":[-86.73981499999999,36.09251],"type":"Point"}
}