{
  "type": "Feature",
  "properties": {
    "addr:full":"6 Francis St Chattanooga TN 37419",
    "addr:housenumber":"6",
    "addr:postcode":"37419",
    "addr:street":"Francis St",
    "iso:country":"US",
    "sg:address":"6 Francis St",
    "sg:city":"Chattanooga",
    "sg:classifiers":[
        {
            "category":"Building & Trades",
            "subcategory":"Construction",
            "type":"Services"
        }
    ],
    "sg:phone":"+1 423 821 4100",
    "sg:postcode":"37419",
    "sg:province":"TN",
    "sg:tags":[
        "contractor",
        "industrial",
        "general",
        "nonresidential"
    ],
    "sg:website":"www.gannconstruction.com",
    "wof:name":"Gann Construction Co",
    "wof:placetype":"venue"
},
  "geometry": {"coordinates":[-85.38618,35.024762],"type":"Point"}
}