{
  "type": "Feature",
  "properties": {
    "iso:country":"US",
    "sg:address":"1008 Alvin Weinberg Dr",
    "sg:city":"Oak Ridge",
    "sg:classifiers":[
        {
            "category":"Professional",
            "subcategory":"Research",
            "type":"Services"
        }
    ],
    "sg:phone":"+1 865 482 5992",
    "sg:postcode":"37830",
    "sg:province":"TN",
    "sg:tags":[
        "development",
        "laboratory"
    ],
    "wof:name":"Intraspec",
    "wof:placetype":"venue"
},
  "geometry": {"coordinates":[-84.234219,35.975888],"type":"Point"}
}