{
  "type": "Feature",
  "properties": {
    "addr:full":"14 Northumberland Nashville TN 37215",
    "addr:housenumber":"14",
    "addr:postcode":"37215",
    "addr:street":"Northumberland",
    "iso:country":"US",
    "sg:address":"14 Northumberland",
    "sg:city":"Nashville",
    "sg:classifiers":[
        {
            "category":"Wholesale",
            "subcategory":"Apparel",
            "type":"Manufacturing & Wholesale Goods"
        }
    ],
    "sg:phone":"+1 615 665 9064",
    "sg:postcode":"37215",
    "sg:province":"TN",
    "sg:tags":[
        "footwear"
    ],
    "wof:name":"Murtosa",
    "wof:placetype":"venue"
},
  "geometry": {"coordinates":[-86.83572100000001,36.088903],"type":"Point"}
}