{
  "type": "Feature",
  "properties": {
    "iso:country":"US",
    "sg:address":"11121 Kingston Pike",
    "sg:city":"Knoxville",
    "sg:classifiers":[
        {
            "category":"Sports & Exercise",
            "subcategory":"Gym",
            "type":"Entertainment"
        }
    ],
    "sg:phone":"+1 865 777 7874",
    "sg:postcode":"37934",
    "sg:province":"TN",
    "sg:tags":[
        "club",
        "health",
        "studio",
        "gymnasium"
    ],
    "wof:name":"Rush Fitness Complex",
    "wof:placetype":"venue"
},
  "geometry": {"coordinates":[-84.15137,35.885783],"type":"Point"}
}