{
  "type": "Feature",
  "properties": {
    "iso:country":"US",
    "sg:address":"1077 Kefauver Dr",
    "sg:city":"Milan",
    "sg:classifiers":[
        {
            "category":"Social Services",
            "type":"Services"
        }
    ],
    "sg:phone":"+1 731 686 9620",
    "sg:postcode":"38358",
    "sg:province":"TN",
    "sg:tags":[
        "organization",
        "welfare"
    ],
    "wof:name":"YMCA Teen Ctr",
    "wof:placetype":"venue"
},
  "geometry": {"coordinates":[-88.752382,35.906095],"type":"Point"}
}