{
  "type": "Feature",
  "properties": {
    "iso:country":"US",
    "sg:address":"537 Old Hwy 46 S",
    "sg:city":"Dickson",
    "sg:classifiers":[
        {
            "category":"Restaurant",
            "type":"Food & Drink"
        }
    ],
    "sg:phone":"+1 615 446 4246",
    "sg:postcode":"37055",
    "sg:province":"TN",
    "wof:name":"Roma Pasta & Pizza",
    "wof:placetype":"venue"
},
  "geometry": {"coordinates":[-87.330072,36.002094],"type":"Point"}
}