{
  "type": "Feature",
  "properties": {
    "addr:full":"280 Dunbar Cave Rd Clarksville TN 37043",
    "addr:housenumber":"280",
    "addr:postcode":"37043",
    "addr:street":"Dunbar Cave Rd",
    "iso:country":"US",
    "sg:address":"280 Dunbar Cave Rd",
    "sg:city":"Clarksville",
    "sg:classifiers":[
        {
            "category":"Organizations",
            "subcategory":"Religious Organization",
            "type":"Services"
        }
    ],
    "sg:phone":"+1 931 552 6643",
    "sg:postcode":"37043",
    "sg:province":"TN",
    "wof:name":"Saint Bethlehem Christn Church",
    "wof:placetype":"venue"
},
  "geometry": {"coordinates":[-87.321985,36.551992],"type":"Point"}
}