{
  "type": "Feature",
  "properties": {
    "iso:country":"US",
    "sg:address":"5892 Oakland Hills Ln",
    "sg:city":"Memphis",
    "sg:classifiers":[
        {
            "category":"Home & Garden",
            "subcategory":"Carpets & Floor Coverings",
            "type":"Retail Goods"
        }
    ],
    "sg:phone":"+1 901 362 0000",
    "sg:postcode":"38115",
    "sg:province":"TN",
    "wof:name":"Bryan's Floor Covering",
    "wof:placetype":"venue"
},
  "geometry": {"coordinates":[-89.867154,35.067644],"type":"Point"}
}