{
  "type": "Feature",
  "properties": {
    "iso:country":"US",
    "sg:address":"65 Monroe Ave",
    "sg:city":"Memphis",
    "sg:classifiers":[
        {
            "category":"Manufacturing",
            "subcategory":"Printing",
            "type":"Manufacturing & Wholesale Goods"
        }
    ],
    "sg:phone":"+1 901 523 2134",
    "sg:postcode":"38103",
    "sg:province":"TN",
    "sg:tags":[
        "equipment",
        "scanning",
        "printer",
        "plotting",
        "supply"
    ],
    "wof:name":"Gator Print",
    "wof:placetype":"venue"
},
  "geometry": {"coordinates":[-90.054114,35.144443],"type":"Point"}
}