{
  "type": "Feature",
  "properties": {
    "iso:country":"US",
    "sg:address":"5615 Lickton Pike",
    "sg:city":"Goodlettsville",
    "sg:classifiers":[
        {
            "category":"Wholesale",
            "subcategory":"Non-durable Goods",
            "type":"Manufacturing & Wholesale Goods"
        }
    ],
    "sg:phone":"+1 615 859 7165",
    "sg:postcode":"37072",
    "sg:province":"TN",
    "sg:tags":[
        "candle",
        "equipment"
    ],
    "wof:name":"Nashville Waxworks",
    "wof:placetype":"venue"
},
  "geometry": {"coordinates":[-86.786207,36.326605],"type":"Point"}
}