{
  "type": "Feature",
  "properties": {
    "iso:country":"US",
    "sg:address":"7061 Moores Ln",
    "sg:city":"Brentwood",
    "sg:classifiers":[
        {
            "category":"Shopping",
            "subcategory":"Florist",
            "type":"Retail Goods"
        }
    ],
    "sg:phone":"+1 615 376 6363",
    "sg:postcode":"37027",
    "sg:province":"TN",
    "wof:name":"Cool Spring Galleria Flower",
    "wof:placetype":"venue"
},
  "geometry": {"coordinates":[-86.822309,35.970673],"type":"Point"}
}