{
  "type": "Feature",
  "properties": {
    "iso:country":"US",
    "sg:address":"2009 Hall Dr",
    "sg:city":"Fayetteville",
    "sg:classifiers":[
        {
            "category":"Building & Trades",
            "subcategory":"Construction",
            "type":"Services"
        }
    ],
    "sg:phone":"+1 931 433 3327",
    "sg:postcode":"37334",
    "sg:province":"TN",
    "sg:tags":[
        "house"
    ],
    "wof:name":"Jon Edward Homes LLC",
    "wof:placetype":"venue"
},
  "geometry": {"coordinates":[-86.579391,35.040622],"type":"Point"}
}