{
  "type": "Feature",
  "properties": {
    "iso:country":"US",
    "sg:address":"675 Harding Pl",
    "sg:city":"Nashville",
    "sg:classifiers":[
        {
            "category":"Real Estate",
            "subcategory":"Real Estate Operator",
            "type":"Services"
        }
    ],
    "sg:phone":"+1 615 832 8429",
    "sg:postcode":"37211",
    "sg:province":"TN",
    "sg:tags":[
        "apartment"
    ],
    "wof:name":"Elysian Garden Apartments",
    "wof:placetype":"venue"
},
  "geometry": {"coordinates":[-86.748968,36.079921],"type":"Point"}
}