{
  "type": "Feature",
  "properties": {
    "iso:country":"US",
    "sg:address":"1061 Lemay Ct",
    "sg:city":"Joelton",
    "sg:classifiers":[
        {
            "category":"Insurance",
            "subcategory":"Title Insurance",
            "type":"Services"
        }
    ],
    "sg:phone":"+1 615 746 6391",
    "sg:postcode":"37080",
    "sg:province":"TN",
    "sg:tags":[
        "carrier"
    ],
    "wof:name":"Grtr Nshvll Ttl Co",
    "wof:placetype":"venue"
},
  "geometry": {"coordinates":[-86.947244,36.343201],"type":"Point"}
}