{
  "type": "Feature",
  "properties": {
    "addr:full":"1511 Everhart Dr NW Cleveland TN 37311",
    "addr:housenumber":"1511",
    "addr:postcode":"37311",
    "addr:street":"Everhart Dr Nw",
    "iso:country":"US",
    "sg:address":"1511 Everhart Dr NW",
    "sg:city":"Cleveland",
    "sg:classifiers":[
        {
            "category":"Building & Trades",
            "subcategory":"Equipment Rental",
            "type":"Services"
        }
    ],
    "sg:phone":"+1 423 472 2050",
    "sg:postcode":"37311",
    "sg:province":"TN",
    "wof:name":"Parton Rentals",
    "wof:placetype":"venue"
},
  "geometry": {"coordinates":[-84.88893899999999,35.176963],"type":"Point"}
}