{
  "type": "Feature",
  "properties": {
    "iso:country":"US",
    "sg:address":"1815 Hillsboro Blvd",
    "sg:city":"Manchester",
    "sg:classifiers":[
        {
            "category":"Real Estate",
            "subcategory":"Real Estate Agent",
            "type":"Services"
        }
    ],
    "sg:phone":"+1 931 728 7286",
    "sg:postcode":"37355",
    "sg:province":"TN",
    "sg:website":"www.cfisherrealtors.com",
    "wof:name":"Christine Fisher Realtors",
    "wof:placetype":"venue"
},
  "geometry": {"coordinates":[-86.06764699999999,35.464575],"type":"Point"}
}