{
  "type": "Feature",
  "properties": {
    "iso:country":"US",
    "sg:address":"1060 Commerce Park Dr",
    "sg:city":"Oak Ridge",
    "sg:classifiers":[
        {
            "category":"Education",
            "subcategory":"College",
            "type":"Public Place"
        }
    ],
    "sg:phone":"+1 865 574 1230",
    "sg:postcode":"37830",
    "sg:province":"TN",
    "wof:name":"Oak Ridge Grad Schl Biomedical",
    "wof:placetype":"venue"
},
  "geometry": {"coordinates":[-84.222247,35.990725],"type":"Point"}
}