{
  "type": "Feature",
  "properties": {
    "iso:country":"US",
    "sg:address":"1731 Shale Rd",
    "sg:city":"Newport",
    "sg:classifiers":[
        {
            "category":"Health Services",
            "subcategory":"Hospital",
            "type":"Services"
        }
    ],
    "sg:phone":"+1 423 625 2201",
    "sg:postcode":"37821",
    "sg:province":"TN",
    "sg:tags":[
        "general"
    ],
    "wof:name":"Cock County Baptist",
    "wof:placetype":"venue"
},
  "geometry": {"coordinates":[-83.223962,35.909152],"type":"Point"}
}