{
  "type": "Feature",
  "properties": {
    "addr:full":"143 6th Ave Huntingdon TN 38344",
    "addr:housenumber":"143",
    "addr:postcode":"38344",
    "addr:street":"6Th Ave",
    "iso:country":"US",
    "sg:address":"143 6th Ave",
    "sg:city":"Huntingdon",
    "sg:classifiers":[
        {
            "category":"Personal",
            "subcategory":"Beauty Salon",
            "type":"Services"
        }
    ],
    "sg:phone":"+1 731 986 9271",
    "sg:postcode":"38344",
    "sg:province":"TN",
    "sg:tags":[
        "shop"
    ],
    "wof:name":"Emily's Style Salon",
    "wof:placetype":"venue"
},
  "geometry": {"coordinates":[-88.42422500000001,36.004274],"type":"Point"}
}