{
  "type": "Feature",
  "properties": {
    "addr:full":"704 W Main St Jonesborough TN 37659",
    "addr:housenumber":"704",
    "addr:postcode":"37659",
    "addr:street":"W Main St",
    "iso:country":"US",
    "sg:address":"704 W Main St",
    "sg:city":"Jonesborough",
    "sg:classifiers":[
        {
            "category":"Shopping",
            "subcategory":"Gifts & Souvenirs",
            "type":"Retail Goods"
        }
    ],
    "sg:phone":"+1 423 753 3351",
    "sg:postcode":"37659",
    "sg:province":"TN",
    "sg:tags":[
        "shop"
    ],
    "wof:name":"Grapevine Cottage",
    "wof:placetype":"venue"
},
  "geometry": {"coordinates":[-82.48159699999999,36.289759],"type":"Point"}
}