{
  "type": "Feature",
  "properties": {
    "iso:country":"US",
    "sg:address":"1445 Frederick St NW",
    "sg:city":"Cleveland",
    "sg:classifiers":[
        {
            "category":"Professional",
            "subcategory":"Research",
            "type":"Services"
        }
    ],
    "sg:phone":"+1 423 479 4408",
    "sg:postcode":"37311",
    "sg:province":"TN",
    "sg:tags":[
        "development",
        "marketing",
        "product"
    ],
    "wof:name":"Gregory Supply Co",
    "wof:placetype":"venue"
},
  "geometry": {"coordinates":[-84.884466,35.187151],"type":"Point"}
}