{
  "type": "Feature",
  "properties": {
    "iso:country":"US",
    "sg:address":"1128 Darbytown Dr",
    "sg:city":"Nashville",
    "sg:classifiers":[
        {
            "category":"Shopping",
            "subcategory":"Clothing, Apparel, & Fashions",
            "type":"Retail Goods"
        }
    ],
    "sg:phone":"+1 615 868 5890",
    "sg:postcode":"37207",
    "sg:province":"TN",
    "sg:tags":[
        "alteration"
    ],
    "wof:name":"Stitch & Fit",
    "wof:placetype":"venue"
},
  "geometry": {"coordinates":[-86.762184,36.267322],"type":"Point"}
}