{
  "type": "Feature",
  "properties": {
    "iso:country":"US",
    "sg:address":"395 Florence Rd",
    "sg:city":"Savannah",
    "sg:classifiers":[
        {
            "category":"Professional",
            "subcategory":"Accounting & Tax Preparation",
            "type":"Services"
        }
    ],
    "sg:phone":"+1 731 925 3949",
    "sg:postcode":"38372",
    "sg:province":"TN",
    "sg:tags":[
        "accountant"
    ],
    "wof:name":"Beverly Jones CPA",
    "wof:placetype":"venue"
},
  "geometry": {"coordinates":[-88.23989899999999,35.219408],"type":"Point"}
}