{
  "type": "Feature",
  "properties": {
    "iso:country":"US",
    "sg:address":"8667 Green Heron Ln",
    "sg:city":"Cordova",
    "sg:classifiers":[
        {
            "category":"Home & Garden",
            "subcategory":"Carpets & Floor Coverings",
            "type":"Retail Goods"
        }
    ],
    "sg:phone":"+1 901 624 0272",
    "sg:postcode":"38018",
    "sg:province":"TN",
    "wof:name":"All About Floors Inc",
    "wof:placetype":"venue"
},
  "geometry": {"coordinates":[-89.774879,35.132509],"type":"Point"}
}