{
  "type": "Feature",
  "properties": {
    "addr:full":"100 New Shackle Island Rd Hendersonville TN 37075",
    "addr:housenumber":"100",
    "addr:postcode":"37075",
    "addr:street":"New Shackle Island Rd",
    "iso:country":"US",
    "sg:address":"100 New Shackle Island Rd",
    "sg:city":"Hendersonville",
    "sg:classifiers":[
        {
            "category":"Restaurant",
            "type":"Food & Drink"
        }
    ],
    "sg:phone":"+1 615 822 4999",
    "sg:postcode":"37075",
    "sg:province":"TN",
    "wof:name":"Ricardo's Restaurant & Tgr",
    "wof:placetype":"venue"
},
  "geometry": {"coordinates":[-86.632456,36.308948],"type":"Point"}
}