{
  "type": "Feature",
  "properties": {
    "iso:country":"US",
    "sg:address":"6415 Hixson Pike",
    "sg:city":"Hixson",
    "sg:classifiers":[
        {
            "category":"Shopping",
            "subcategory":"Gifts & Souvenirs",
            "type":"Retail Goods"
        }
    ],
    "sg:phone":"+1 423 847 0905",
    "sg:postcode":"37343",
    "sg:province":"TN",
    "sg:tags":[
        "shop"
    ],
    "wof:name":"Something Different",
    "wof:placetype":"venue"
},
  "geometry": {"coordinates":[-85.196482,35.157031],"type":"Point"}
}