{
  "type": "Feature",
  "properties": {
    "iso:country":"US",
    "sg:address":"2116 Summitt Ave",
    "sg:city":"Nashville",
    "sg:classifiers":[
        {
            "category":"Retail",
            "subcategory":"Repair Shop",
            "type":"Services"
        }
    ],
    "sg:phone":"+1 615 594 1176",
    "sg:postcode":"37218",
    "sg:province":"TN",
    "sg:tags":[
        "related"
    ],
    "wof:name":"Aquatic Creations",
    "wof:placetype":"venue"
},
  "geometry": {"coordinates":[-86.830454,36.198425],"type":"Point"}
}