{
  "type": "Feature",
  "properties": {
    "iso:country":"US",
    "sg:address":"934 Blythewood Rd SW",
    "sg:city":"Cleveland",
    "sg:classifiers":[
        {
            "category":"Autos & Motor Vehicles",
            "subcategory":"Automobile Sales",
            "type":"Retail Goods"
        }
    ],
    "sg:phone":"+1 423 339 8911",
    "sg:postcode":"37311",
    "sg:province":"TN",
    "wof:name":"Princes Auto Sales",
    "wof:placetype":"venue"
},
  "geometry": {"coordinates":[-84.915465,35.152012],"type":"Point"}
}