{
  "type": "Feature",
  "properties": {
    "addr:full":"217 US Hwy 79 Gibson TN 38358",
    "addr:housenumber":"217",
    "addr:postcode":"38358",
    "addr:street":"Us Hwy 79",
    "iso:country":"US",
    "sg:address":"217 US Hwy 79",
    "sg:city":"Gibson",
    "sg:classifiers":[
        {
            "category":"Retail",
            "subcategory":"Auto Repair",
            "type":"Services"
        }
    ],
    "sg:phone":"+1 731 787 6333",
    "sg:postcode":"38358",
    "sg:province":"TN",
    "sg:tags":[
        "truck"
    ],
    "wof:name":"Hill's Truck Svc",
    "wof:placetype":"venue"
},
  "geometry": {"coordinates":[-88.809645,35.891383],"type":"Point"}
}