{
  "type": "Feature",
  "properties": {
    "iso:country":"US",
    "sg:address":"1773 Thompsons Station Rd W",
    "sg:city":"Thompsons Sta",
    "sg:classifiers":[
        {
            "category":"Professional",
            "subcategory":"Engineering",
            "type":"Services"
        }
    ],
    "sg:phone":"+1 615 599 7351",
    "sg:postcode":"37179",
    "sg:province":"TN",
    "sg:tags":[
        "engineer"
    ],
    "wof:name":"Booker Engineering",
    "wof:placetype":"venue"
},
  "geometry": {"coordinates":[-86.93883,35.809026],"type":"Point"}
}