{
  "type": "Feature",
  "properties": {
    "iso:country":"US",
    "sg:address":"2039 Munson Rd",
    "sg:city":"Memphis",
    "sg:classifiers":[
        {
            "category":"Building & Trades",
            "subcategory":"Construction",
            "type":"Services"
        }
    ],
    "sg:phone":"+1 901 372 8848",
    "sg:postcode":"38134",
    "sg:province":"TN",
    "sg:tags":[
        "contractor"
    ],
    "wof:name":"Tile Instl & Service",
    "wof:placetype":"venue"
},
  "geometry": {"coordinates":[-89.86492200000001,35.176374],"type":"Point"}
}