{
  "type": "Feature",
  "properties": {
    "iso:country":"US",
    "sg:address":"190 Lancaster Rd",
    "sg:city":"Kingsport",
    "sg:classifiers":[
        {
            "category":"Utilities",
            "subcategory":"Refuse",
            "type":"Services"
        }
    ],
    "sg:phone":"+1 423 349 6429",
    "sg:postcode":"37663",
    "sg:province":"TN",
    "sg:tags":[
        "disposal",
        "waste"
    ],
    "wof:name":"Waste Tire Ctr",
    "wof:placetype":"venue"
},
  "geometry": {"coordinates":[-82.53395399999999,36.425321],"type":"Point"}
}