{
  "type": "Feature",
  "properties": {
    "iso:country":"US",
    "sg:address":"250 Old Hickory Blvd",
    "sg:city":"Nashville",
    "sg:classifiers":[
        {
            "category":"Professional",
            "type":"Services"
        }
    ],
    "sg:phone":"+1 615 371 6110",
    "sg:postcode":"37221",
    "sg:province":"TN",
    "sg:tags":[
        "establishment"
    ],
    "wof:name":"Blue Wing Inc",
    "wof:placetype":"venue"
},
  "geometry": {"coordinates":[-86.91884899999999,36.079879],"type":"Point"}
}