{
  "type": "Feature",
  "properties": {
    "addr:full":"2734 S Mendenhall Rd Memphis TN 38115",
    "addr:housenumber":"2734",
    "addr:postcode":"38115",
    "addr:street":"S Mendenhall Rd",
    "iso:country":"US",
    "sg:address":"2734 S Mendenhall Rd",
    "sg:city":"Memphis",
    "sg:classifiers":[
        {
            "category":"Autos & Motor Vehicles",
            "subcategory":"Automobile Sales",
            "type":"Retail Goods"
        }
    ],
    "sg:phone":"+1 901 205 7795",
    "sg:postcode":"38115",
    "sg:province":"TN",
    "sg:tags":[
        "used"
    ],
    "wof:name":"Schilling Used Cars",
    "wof:placetype":"venue"
},
  "geometry": {"coordinates":[-89.88476199999999,35.07416],"type":"Point"}
}