{
  "type": "Feature",
  "properties": {
    "addr:full":"3106 Braintree Rd Franklin TN 37069",
    "addr:housenumber":"3106",
    "addr:postcode":"37069",
    "addr:street":"Braintree Rd",
    "iso:country":"US",
    "sg:address":"3106 Braintree Rd",
    "sg:city":"Franklin",
    "sg:classifiers":[
        {
            "category":"Organizations",
            "subcategory":"Membership Organization",
            "type":"Services"
        }
    ],
    "sg:phone":"+1 615 790 3270",
    "sg:postcode":"37069",
    "sg:province":"TN",
    "wof:name":"Farmington Subdivision Assn",
    "wof:placetype":"venue"
},
  "geometry": {"coordinates":[-86.873296,35.985749],"type":"Point"}
}