{
  "type": "Feature",
  "properties": {
    "addr:full":"441 Harding Pl Nashville TN 37211",
    "addr:housenumber":"441",
    "addr:postcode":"37211",
    "addr:street":"Harding Pl",
    "iso:country":"US",
    "sg:address":"441 Harding Pl",
    "sg:city":"Nashville",
    "sg:classifiers":[
        {
            "category":"Shopping",
            "subcategory":"Computers & Home Electronics",
            "type":"Retail Goods"
        }
    ],
    "sg:phone":"+1 615 832 2228",
    "sg:postcode":"37211",
    "sg:province":"TN",
    "sg:tags":[
        "publishing"
    ],
    "wof:name":"American Spirit",
    "wof:placetype":"venue"
},
  "geometry": {"coordinates":[-86.73048300000001,36.078095],"type":"Point"}
}