{
  "type": "Feature",
  "properties": {
    "iso:country":"US",
    "sg:address":"200 Keith Ln",
    "sg:city":"Athens",
    "sg:classifiers":[
        {
            "category":"Education",
            "subcategory":"School",
            "type":"Public Place"
        }
    ],
    "sg:phone":"+1 423 745 1177",
    "sg:postcode":"37303",
    "sg:province":"TN",
    "wof:name":"Athens Junior High",
    "wof:placetype":"venue"
},
  "geometry": {"coordinates":[-84.60291599999999,35.435601],"type":"Point"}
}