{
  "type": "Feature",
  "properties": {
    "iso:country":"US",
    "sg:address":"420 S Water Ave",
    "sg:city":"Gallatin",
    "sg:classifiers":[
        {
            "category":"Travel",
            "subcategory":"Hotels & Motels",
            "type":"Entertainment"
        }
    ],
    "sg:phone":"+1 615 452 0219",
    "sg:postcode":"37066",
    "sg:province":"TN",
    "sg:tags":[
        "operation"
    ],
    "wof:name":"Galemont/Parkway Apartments",
    "wof:placetype":"venue"
},
  "geometry": {"coordinates":[-86.44425,36.382526],"type":"Point"}
}