{
  "type": "Feature",
  "properties": {
    "iso:country":"US",
    "sg:address":"1641 W Morris Blvd",
    "sg:city":"Morristown",
    "sg:classifiers":[
        {
            "category":"Professional",
            "subcategory":"Management & Consulting",
            "type":"Services"
        }
    ],
    "sg:phone":"+1 423 587 9779",
    "sg:postcode":"37813",
    "sg:province":"TN",
    "wof:name":"Digital Document Management",
    "wof:placetype":"venue"
},
  "geometry": {"coordinates":[-83.30959199999999,36.202983],"type":"Point"}
}