{
  "type": "Feature",
  "properties": {
    "iso:country":"US",
    "sg:address":"271 Mayfield Dr",
    "sg:city":"Smyrna",
    "sg:classifiers":[
        {
            "category":"Organizations",
            "subcategory":"Religious Organization",
            "type":"Services"
        }
    ],
    "sg:phone":"+1 615 355 1286",
    "sg:postcode":"37167",
    "sg:province":"TN",
    "wof:name":"Mayfield Drive Baptist Church",
    "wof:placetype":"venue"
},
  "geometry": {"coordinates":[-86.503231,35.975601],"type":"Point"}
}