{
  "type": "Feature",
  "properties": {
    "iso:country":"US",
    "sg:address":"3002 Tugaloo St",
    "sg:city":"Chattanooga",
    "sg:classifiers":[
        {
            "category":"Building & Trades",
            "subcategory":"Construction",
            "type":"Services"
        }
    ],
    "sg:phone":"+1 423 622 9460",
    "sg:postcode":"37406",
    "sg:province":"TN",
    "sg:tags":[
        "house"
    ],
    "wof:name":"Willie Woodward Remodeling",
    "wof:placetype":"venue"
},
  "geometry": {"coordinates":[-85.23235099999999,35.073609],"type":"Point"}
}