{
  "type": "Feature",
  "properties": {
    "iso:country":"US",
    "sg:address":"276 Lakewood Dr",
    "sg:city":"Crossville",
    "sg:classifiers":[
        {
            "category":"Professional",
            "subcategory":"Management & Consulting",
            "type":"Services"
        }
    ],
    "sg:phone":"+1 931 456 9486",
    "sg:postcode":"38558",
    "sg:province":"TN",
    "sg:tags":[
        "business"
    ],
    "wof:name":"Frye Consulting Corp",
    "wof:placetype":"venue"
},
  "geometry": {"coordinates":[-84.91155500000001,35.993679],"type":"Point"}
}