{
  "type": "Feature",
  "properties": {
    "iso:country":"US",
    "sg:address":"3006 Inverness Parkway Dr",
    "sg:city":"Memphis",
    "sg:classifiers":[
        {
            "category":"Travel",
            "subcategory":"Travel Agent",
            "type":"Entertainment"
        }
    ],
    "sg:phone":"+1 901 546 9036",
    "sg:postcode":"38115",
    "sg:province":"TN",
    "sg:tags":[
        "operator",
        "tour"
    ],
    "wof:name":"Sail N Tours",
    "wof:placetype":"venue"
},
  "geometry": {"coordinates":[-89.869207,35.066278],"type":"Point"}
}