{
  "type": "Feature",
  "properties": {
    "iso:country":"US",
    "sg:address":"975 E 3rd St",
    "sg:city":"Chattanooga",
    "sg:classifiers":[
        {
            "category":"Health Services",
            "subcategory":"Hospital",
            "type":"Services"
        }
    ],
    "sg:phone":"+1 423 778 7000",
    "sg:postcode":"37403",
    "sg:province":"TN",
    "sg:tags":[
        "medical",
        "general"
    ],
    "wof:name":"Erlanger Health System",
    "wof:placetype":"venue"
},
  "geometry": {"coordinates":[-85.290514,35.047755],"type":"Point"}
}