{
  "type": "Feature",
  "properties": {
    "iso:country":"US",
    "sg:address":"9530 S Harpeth Rd",
    "sg:city":"Nashville",
    "sg:classifiers":[
        {
            "category":"Organizations",
            "subcategory":"Community Association",
            "type":"Services"
        }
    ],
    "sg:phone":"+1 615 646 3874",
    "sg:postcode":"37221",
    "sg:province":"TN",
    "wof:name":"South Harpeth Civic Center",
    "wof:placetype":"venue"
},
  "geometry": {"coordinates":[-87.023048,36.028308],"type":"Point"}
}