{
  "type": "Feature",
  "properties": {
    "addr:full":"130 Timber Ridge Rd Erwin TN 37650",
    "addr:housenumber":"130",
    "addr:postcode":"37650",
    "addr:street":"Timber Ridge Rd",
    "iso:country":"US",
    "sg:address":"130 Timber Ridge Rd",
    "sg:city":"Erwin",
    "sg:classifiers":[
        {
            "category":"Professional",
            "subcategory":"Secretarial Services",
            "type":"Services"
        }
    ],
    "sg:phone":"+1 423 283 4668",
    "sg:postcode":"37650",
    "sg:province":"TN",
    "sg:tags":[
        "convention",
        "court",
        "reporter"
    ],
    "wof:name":"Fox Fire Reporting",
    "wof:placetype":"venue"
},
  "geometry": {"coordinates":[-82.443226,36.106523],"type":"Point"}
}