{
  "type": "Feature",
  "properties": {
    "iso:country":"US",
    "sg:address":"137 Dean Dr",
    "sg:city":"Clarksville",
    "sg:classifiers":[
        {
            "category":"Freight",
            "type":"Transportation"
        }
    ],
    "sg:phone":"+1 931 647 6851",
    "sg:postcode":"37040",
    "sg:province":"TN",
    "sg:tags":[
        "operator",
        "trucking"
    ],
    "wof:name":"Fireball Express",
    "wof:placetype":"venue"
},
  "geometry": {"coordinates":[-87.364662,36.512768],"type":"Point"}
}