{
  "type": "Feature",
  "properties": {
    "iso:country":"US",
    "sg:address":"1922 Edward Cove",
    "sg:city":"Memphis",
    "sg:classifiers":[
        {
            "category":"Professional",
            "type":"Services"
        }
    ],
    "sg:phone":"+1 901 272 0814",
    "sg:postcode":"38107",
    "sg:province":"TN",
    "wof:name":"Sp Processing",
    "wof:placetype":"venue"
},
  "geometry": {"coordinates":[-89.993517,35.166916],"type":"Point"}
}