{
  "type": "Feature",
  "properties": {
    "iso:country":"US",
    "sg:address":"817 E Oldham Ave",
    "sg:city":"Knoxville",
    "sg:classifiers":[
        {
            "category":"Health Services",
            "subcategory":"Doctor",
            "type":"Services"
        }
    ],
    "sg:phone":"+1 865 522 2229",
    "sg:postcode":"37917",
    "sg:province":"TN",
    "sg:tags":[
        "physician",
        "surgeon"
    ],
    "wof:name":"Nancy Vick Center For Women",
    "wof:placetype":"venue"
},
  "geometry": {"coordinates":[-83.926541,35.990771],"type":"Point"}
}