{
  "type": "Feature",
  "properties": {
    "iso:country":"US",
    "sg:address":"8835 Lonesome Pine Trl",
    "sg:city":"Mosheim",
    "sg:classifiers":[
        {
            "category":"Wholesale",
            "subcategory":"Computers",
            "type":"Manufacturing & Wholesale Goods"
        }
    ],
    "sg:phone":"+1 423 422 9706",
    "sg:postcode":"37818",
    "sg:province":"TN",
    "wof:name":"Associated Technologies",
    "wof:placetype":"venue"
},
  "geometry": {"coordinates":[-82.91945200000001,36.262063],"type":"Point"}
}