{
  "type": "Feature",
  "properties": {
    "iso:country":"US",
    "sg:address":"100 N Main St",
    "sg:city":"Bolivar",
    "sg:classifiers":[
        {
            "category":"Government",
            "subcategory":"Court House",
            "type":"Public Place"
        }
    ],
    "sg:phone":"+1 731 658 6382",
    "sg:postcode":"38008",
    "sg:province":"TN",
    "sg:tags":[
        "county"
    ],
    "wof:name":"Hardeman County Juvenile Court",
    "wof:placetype":"venue"
},
  "geometry": {"coordinates":[-88.98782799999999,35.256999],"type":"Point"}
}