{
  "type": "Feature",
  "properties": {
    "iso:country":"US",
    "sg:address":"1315 W Brushy Valley Dr",
    "sg:city":"Norris",
    "sg:classifiers":[
        {
            "category":"Building & Trades",
            "subcategory":"Landscaping Services",
            "type":"Services"
        }
    ],
    "sg:phone":"+1 865 494 8776",
    "sg:postcode":"37849",
    "sg:province":"TN",
    "sg:tags":[
        "designer",
        "landscape"
    ],
    "wof:name":"Robinson's Country Pleasantree",
    "wof:placetype":"venue"
},
  "geometry": {"coordinates":[-84.04781699999999,36.062574],"type":"Point"}
}