{
  "type": "Feature",
  "properties": {
    "addr:full":"3213 Old Clarksville Pike Ashland City TN 37015",
    "addr:housenumber":"3213",
    "addr:postcode":"37015",
    "addr:street":"Old Clarksville Pike",
    "iso:country":"US",
    "sg:address":"3213 Old Clarksville Pike",
    "sg:city":"Ashland City",
    "sg:classifiers":[
        {
            "category":"Retail",
            "subcategory":"Portrait Studio",
            "type":"Services"
        }
    ],
    "sg:phone":"+1 615 746 5410",
    "sg:postcode":"37015",
    "sg:province":"TN",
    "sg:tags":[
        "photographer"
    ],
    "wof:name":"Restored Memories Studio",
    "wof:placetype":"venue"
},
  "geometry": {"coordinates":[-87.044663,36.366058],"type":"Point"}
}