{
  "type": "Feature",
  "properties": {
    "iso:country":"US",
    "sg:address":"2828 Parkway",
    "sg:city":"Pigeon Forge",
    "sg:classifiers":[
        {
            "category":"Shopping",
            "type":"Retail Goods"
        }
    ],
    "sg:phone":"+1 865 908 5690",
    "sg:postcode":"37863",
    "sg:province":"TN",
    "sg:tags":[
        "factory",
        "outlet"
    ],
    "wof:name":"Buda Z Outlets",
    "wof:placetype":"venue"
},
  "geometry": {"coordinates":[-83.568259,35.798822],"type":"Point"}
}