{
  "type": "Feature",
  "properties": {
    "iso:country":"US",
    "sg:address":"1823 4th Ave N",
    "sg:city":"Nashville",
    "sg:classifiers":[
        {
            "category":"Professional",
            "subcategory":"Accounting & Tax Preparation",
            "type":"Services"
        }
    ],
    "sg:phone":"+1 615 255 9395",
    "sg:postcode":"37208",
    "sg:province":"TN",
    "sg:tags":[
        "bookkeeping",
        "billing"
    ],
    "wof:name":"Brooks Billing Service",
    "wof:placetype":"venue"
},
  "geometry": {"coordinates":[-86.79247100000001,36.184616],"type":"Point"}
}