{
  "type": "Feature",
  "properties": {
    "iso:country":"US",
    "sg:address":"8900 Martin Mill Pike",
    "sg:city":"Knoxville",
    "sg:classifiers":[
        {
            "category":"Building & Trades",
            "subcategory":"Construction",
            "type":"Services"
        }
    ],
    "sg:phone":"+1 865 755 6933",
    "sg:postcode":"37920",
    "sg:province":"TN",
    "sg:tags":[
        "general",
        "contractor"
    ],
    "wof:name":"Talon Co",
    "wof:placetype":"venue"
},
  "geometry": {"coordinates":[-83.871821,35.84767],"type":"Point"}
}