{
  "type": "Feature",
  "properties": {
    "iso:country":"US",
    "sg:address":"4219 Hillsboro Pike",
    "sg:city":"Nashville",
    "sg:classifiers":[
        {
            "category":"Health Services",
            "subcategory":"Clinic",
            "type":"Services"
        }
    ],
    "sg:phone":"+1 615 292 7111",
    "sg:postcode":"37215",
    "sg:province":"TN",
    "sg:tags":[
        "consulting",
        "specialty",
        "business",
        "outpatient"
    ],
    "wof:name":"R & G Getaway Tours",
    "wof:placetype":"venue"
},
  "geometry": {"coordinates":[-86.820027,36.099991],"type":"Point"}
}