{
  "type": "Feature",
  "properties": {
    "iso:country":"US",
    "sg:address":"1415 Lakeview Dr",
    "sg:city":"Collierville",
    "sg:classifiers":[
        {
            "category":"Building & Trades",
            "subcategory":"Construction",
            "type":"Services"
        }
    ],
    "sg:phone":"+1 901 301 9327",
    "sg:postcode":"38017",
    "sg:province":"TN",
    "sg:tags":[
        "excavating",
        "contractor"
    ],
    "wof:name":"D & G Excavating",
    "wof:placetype":"venue"
},
  "geometry": {"coordinates":[-89.61665000000001,35.141833],"type":"Point"}
}