{
  "type": "Feature",
  "properties": {
    "addr:full":"4092 Brownsville Hwy Jackson TN 38301",
    "addr:housenumber":"4092",
    "addr:postcode":"38301",
    "addr:street":"Brownsville Hwy",
    "iso:country":"US",
    "sg:address":"4092 Brownsville Hwy",
    "sg:city":"Jackson",
    "sg:classifiers":[
        {
            "category":"Manufacturing",
            "subcategory":"Lumber",
            "type":"Manufacturing & Wholesale Goods"
        }
    ],
    "sg:phone":"+1 731 422 6332",
    "sg:postcode":"38301",
    "sg:province":"TN",
    "sg:tags":[
        "a",
        "sawmill",
        "operates"
    ],
    "wof:name":"Lynn Haynes Lumber Company",
    "wof:placetype":"venue"
},
  "geometry": {"coordinates":[-88.984861,35.614376],"type":"Point"}
}