{
  "type": "Feature",
  "properties": {
    "iso:country":"US",
    "sg:address":"209 Gothic Ct",
    "sg:city":"Franklin",
    "sg:classifiers":[
        {
            "category":"Banks & Credit Unions",
            "subcategory":"Bank",
            "type":"Services"
        }
    ],
    "sg:phone":"+1 615 503 9600",
    "sg:postcode":"37067",
    "sg:province":"TN",
    "sg:tags":[
        "broker",
        "mortgage"
    ],
    "wof:name":"Advantage One",
    "wof:placetype":"venue"
},
  "geometry": {"coordinates":[-86.824263,35.951644],"type":"Point"}
}