{
  "type": "Feature",
  "properties": {
    "addr:full":"619 Sumrow St Halls TN 38040",
    "addr:housenumber":"619",
    "addr:postcode":"38040",
    "addr:street":"Sumrow St",
    "iso:country":"US",
    "sg:address":"619 Sumrow St",
    "sg:city":"Halls",
    "sg:phone":"+1 731 836 5267",
    "sg:postcode":"38040",
    "sg:province":"TN",
    "sg:tags":[
        "farm",
        "cotton"
    ],
    "wof:name":"Jerry Horner",
    "wof:placetype":"venue"
},
  "geometry": {"coordinates":[-89.40082,35.884133],"type":"Point"}
}