{
  "type": "Feature",
  "properties": {
    "iso:country":"US",
    "sg:address":"3454 Winchester Rd",
    "sg:city":"Memphis",
    "sg:classifiers":[
        {
            "category":"Food & Beverages",
            "subcategory":"Groceries & Convenience Stores",
            "type":"Retail Goods"
        }
    ],
    "sg:phone":"+1 901 795 6971",
    "sg:postcode":"38118",
    "sg:province":"TN",
    "wof:name":"Mike's Omega Express",
    "wof:placetype":"venue"
},
  "geometry": {"coordinates":[-89.949591,35.052287],"type":"Point"}
}