{
  "type": "Feature",
  "properties": {
    "iso:country":"US",
    "sg:address":"4310 Crestview Dr",
    "sg:city":"Chattanooga",
    "sg:classifiers":[
        {
            "category":"Place Of Worship",
            "subcategory":"Church",
            "type":"Public Place"
        },
        {
            "category":"Place Of Worship",
            "type":"Public Place"
        }
    ],
    "sg:phone":"+1 423 875 8028",
    "sg:postcode":"37415",
    "sg:province":"TN",
    "sg:tags":[
        "churches-non-denominational"
    ],
    "wof:name":"Gospel Chapel Church",
    "wof:placetype":"venue"
},
  "geometry": {"coordinates":[-85.280036,35.121875],"type":"Point"}
}