{
  "type": "Feature",
  "properties": {
    "addr:full":"126 E Main St Newbern TN 38059",
    "addr:housenumber":"126",
    "addr:postcode":"38059",
    "addr:street":"E Main St",
    "iso:country":"US",
    "sg:address":"126 E Main St",
    "sg:city":"Newbern",
    "sg:classifiers":[
        {
            "category":"Shopping",
            "subcategory":"Pharmacy",
            "type":"Retail Goods"
        }
    ],
    "sg:phone":"+1 731 627 2221",
    "sg:postcode":"38059",
    "sg:province":"TN",
    "sg:tags":[
        "drug"
    ],
    "wof:name":"Main Street Family Pharmacy",
    "wof:placetype":"venue"
},
  "geometry": {"coordinates":[-89.262405,36.11303],"type":"Point"}
}