{
  "type": "Feature",
  "properties": {
    "addr:full":"1004 18th Ave S Nashville TN 37212",
    "addr:housenumber":"1004",
    "addr:postcode":"37212",
    "addr:street":"18Th Ave S",
    "iso:country":"US",
    "sg:address":"1004 18th Ave S",
    "sg:city":"Nashville",
    "sg:classifiers":[
        {
            "category":"Manufacturing",
            "subcategory":"Printing",
            "type":"Manufacturing & Wholesale Goods"
        }
    ],
    "sg:phone":"+1 615 292 5100",
    "sg:postcode":"37212",
    "sg:province":"TN",
    "sg:tags":[
        "publisher",
        "music"
    ],
    "wof:name":"Big Tractor Music",
    "wof:placetype":"venue"
},
  "geometry": {"coordinates":[-86.79562,36.143713],"type":"Point"}
}