{
  "type": "Feature",
  "properties": {
    "addr:full":"2013 Jefferson St Nashville TN 37208",
    "addr:housenumber":"2013",
    "addr:postcode":"37208",
    "addr:street":"Jefferson St",
    "iso:country":"US",
    "sg:address":"2013 Jefferson St",
    "sg:city":"Nashville",
    "sg:classifiers":[
        {
            "category":"Banks & Credit Unions",
            "subcategory":"Bank",
            "type":"Services"
        }
    ],
    "sg:phone":"+1 615 327 9153",
    "sg:postcode":"37208",
    "sg:province":"TN",
    "sg:tags":[
        "state",
        "commercial"
    ],
    "wof:name":"Citizens Savings Bank & Tr Co",
    "wof:placetype":"venue"
},
  "geometry": {"coordinates":[-86.81204,36.168673],"type":"Point"}
}