{
  "type": "Feature",
  "properties": {
    "iso:country":"US",
    "sg:address":"5108 S 1st St",
    "sg:city":"Milan",
    "sg:classifiers":[
        {
            "category":"Real Estate",
            "subcategory":"Real Estate Agent",
            "type":"Services"
        },
        {
            "category":"Professional",
            "subcategory":"Business Services",
            "type":"Services"
        }
    ],
    "sg:phone":"+1 731 686 3341",
    "sg:postcode":"38358",
    "sg:province":"TN",
    "sg:website":"www.hickmanrealty.com",
    "wof:name":"Hickman Realty Group Inc",
    "wof:placetype":"venue"
},
  "geometry": {"coordinates":[-88.752118,35.911533],"type":"Point"}
}