{
  "type": "Feature",
  "properties": {
    "iso:country":"US",
    "sg:address":"111 2nd Ave N",
    "sg:city":"Nashville",
    "sg:classifiers":[
        {
            "category":"Shopping",
            "subcategory":"Stationery & Office Supplies",
            "type":"Retail Goods"
        },
        {
            "category":"Shopping",
            "subcategory":"Gifts & Souvenirs",
            "type":"Retail Goods"
        }
    ],
    "sg:phone":"+1 615 251 4092",
    "sg:postcode":"37201",
    "sg:province":"TN",
    "sg:tags":[
        "shop",
        "store"
    ],
    "sg:website":"http://www.marketstreetmercantile.com",
    "wof:name":"Market Street Mercantile",
    "wof:placetype":"venue"
},
  "geometry": {"coordinates":[-86.775338,36.162181],"type":"Point"}
}