{
  "type": "Feature",
  "properties": {
    "iso:country":"US",
    "sg:address":"222 E Broadway Blvd",
    "sg:city":"Jefferson City",
    "sg:classifiers":[
        {
            "category":"Insurance",
            "subcategory":"Insurance Agent",
            "type":"Services"
        }
    ],
    "sg:phone":"+1 865 475 7184",
    "sg:postcode":"37760",
    "sg:province":"TN",
    "wof:name":"Modern Woodmen Of America",
    "wof:placetype":"venue"
},
  "geometry": {"coordinates":[-83.484461,36.117453],"type":"Point"}
}