{
  "type": "Feature",
  "properties": {
    "iso:country":"US",
    "sg:address":"3213 N Watkins St",
    "sg:city":"Memphis",
    "sg:classifiers":[
        {
            "category":"Retail",
            "subcategory":"Auto Repair",
            "type":"Services"
        }
    ],
    "sg:phone":"+1 901 353 4541",
    "sg:postcode":"38127",
    "sg:province":"TN",
    "wof:name":"Cj Auto Repair",
    "wof:placetype":"venue"
},
  "geometry": {"coordinates":[-90.003609,35.213425],"type":"Point"}
}