{
  "type": "Feature",
  "properties": {
    "addr:full":"30 Bragg Cir Crossville TN 38555",
    "addr:housenumber":"30",
    "addr:postcode":"38555",
    "addr:street":"Bragg Cir",
    "iso:country":"US",
    "sg:address":"30 Bragg Cir",
    "sg:city":"Crossville",
    "sg:classifiers":[
        {
            "category":"Organizations",
            "subcategory":"Religious Organization",
            "type":"Services"
        }
    ],
    "sg:phone":"+1 931 484 0128",
    "sg:postcode":"38555",
    "sg:province":"TN",
    "wof:name":"Calvary Mssonary Baptst Church",
    "wof:placetype":"venue"
},
  "geometry": {"coordinates":[-85.05723999999999,35.921802],"type":"Point"}
}