{
  "type": "Feature",
  "properties": {
    "iso:country":"US",
    "sg:address":"1310 E Andrew Johnson Hwy",
    "sg:city":"Greeneville",
    "sg:classifiers":[
        {
            "category":"Shopping",
            "subcategory":"Optical Goods",
            "type":"Retail Goods"
        }
    ],
    "sg:phone":"+1 423 638 6236",
    "sg:postcode":"37641",
    "sg:province":"TN",
    "wof:name":"Tri City Opticians",
    "wof:placetype":"venue"
},
  "geometry": {"coordinates":[-82.799993,36.176902],"type":"Point"}
}