{
  "type": "Feature",
  "properties": {
    "iso:country":"US",
    "sg:address":"3400 Atoka Idaville Rd",
    "sg:city":"Atoka",
    "sg:classifiers":[
        {
            "category":"Place Of Worship",
            "subcategory":"Church",
            "type":"Public Place"
        },
        {
            "category":"Place Of Worship",
            "type":"Public Place"
        }
    ],
    "sg:phone":"+1 901 837 8210",
    "sg:postcode":"38004",
    "sg:province":"TN",
    "sg:tags":[
        "churches-presbyterian-arp",
        "churches-reformed",
        "churches-presbyterian",
        "churches-christian-reformed"
    ],
    "wof:name":"Salem Associate Reformed Presbyterian Church Inc",
    "wof:placetype":"venue"
},
  "geometry": {"coordinates":[-89.736424,35.435931],"type":"Point"}
}