{
  "type": "Feature",
  "properties": {
    "iso:country":"US",
    "sg:address":"1200 Paradise Dr",
    "sg:city":"Powell",
    "sg:classifiers":[
        {
            "category":"Banks & Credit Unions",
            "subcategory":"Financial Services",
            "type":"Services"
        }
    ],
    "sg:phone":"+1 865 947 7152",
    "sg:postcode":"37849",
    "sg:province":"TN",
    "sg:tags":[
        "investment",
        "closed"
    ],
    "wof:name":"Thomas Clan LLC",
    "wof:placetype":"venue"
},
  "geometry": {"coordinates":[-84.03060499999999,36.043174],"type":"Point"}
}