{
  "type": "Feature",
  "properties": {
    "iso:country":"US",
    "sg:address":"2021 Gallatin Pike N",
    "sg:city":"Madison",
    "sg:classifiers":[
        {
            "category":"Insurance",
            "subcategory":"Life Insurance",
            "type":"Services"
        }
    ],
    "sg:phone":"+1 615 851 5063",
    "sg:postcode":"37115",
    "sg:province":"TN",
    "sg:tags":[
        "carrier",
        "carrie"
    ],
    "wof:name":"Life Insurance Company Georgia",
    "wof:placetype":"venue"
},
  "geometry": {"coordinates":[-86.694529,36.301026],"type":"Point"}
}