{
  "type": "Feature",
  "properties": {
    "iso:country":"US",
    "sg:address":"1368 Colbert Cove",
    "sg:city":"Collierville",
    "sg:classifiers":[
        {
            "category":"Banks & Credit Unions",
            "subcategory":"Financial Services",
            "type":"Services"
        }
    ],
    "sg:phone":"+1 901 853 0183",
    "sg:postcode":"38017",
    "sg:province":"TN",
    "sg:tags":[
        "investor"
    ],
    "wof:name":"Jackman Investments Inc",
    "wof:placetype":"venue"
},
  "geometry": {"coordinates":[-89.68536899999999,35.008641],"type":"Point"}
}