{
  "type": "Feature",
  "properties": {
    "addr:full":"5150 American Way Memphis TN 38118",
    "addr:housenumber":"5150",
    "addr:postcode":"38118",
    "addr:street":"American Way",
    "iso:country":"US",
    "sg:address":"5150 American Way",
    "sg:city":"Memphis",
    "sg:classifiers":[
        {
            "category":"Food & Beverages",
            "subcategory":"Groceries & Convenience Stores",
            "type":"Retail Goods"
        }
    ],
    "sg:phone":"+1 901 795 0121",
    "sg:postcode":"38118",
    "sg:province":"TN",
    "sg:tags":[
        "grocer"
    ],
    "wof:name":"Piggly Wiggly",
    "wof:placetype":"venue"
},
  "geometry": {"coordinates":[-89.891142,35.077804],"type":"Point"}
}