{
  "type": "Feature",
  "properties": {
    "addr:full":"942 Fowler St Clinton TN 37716",
    "addr:housenumber":"942",
    "addr:postcode":"37716",
    "addr:street":"Fowler St",
    "iso:country":"US",
    "sg:address":"942 Fowler St",
    "sg:city":"Clinton",
    "sg:classifiers":[
        {
            "category":"Professional",
            "subcategory":"Engineering",
            "type":"Services"
        }
    ],
    "sg:phone":"+1 865 457 4355",
    "sg:postcode":"37716",
    "sg:province":"TN",
    "wof:name":"Natural Resource Services",
    "wof:placetype":"venue"
},
  "geometry": {"coordinates":[-84.122699,36.114363],"type":"Point"}
}