{
  "type": "Feature",
  "properties": {
    "addr:full":"1395 Volunteer Pkwy Bristol TN 37620",
    "addr:housenumber":"1395",
    "addr:postcode":"37620",
    "addr:street":"Volunteer Pkwy",
    "iso:country":"US",
    "sg:address":"1395 Volunteer Pkwy",
    "sg:city":"Bristol",
    "sg:classifiers":[
        {
            "category":"Banks & Credit Unions",
            "subcategory":"Bank",
            "type":"Services"
        }
    ],
    "sg:phone":"+1 423 844 0452",
    "sg:postcode":"37620",
    "sg:province":"TN",
    "sg:tags":[
        "company",
        "consumer",
        "finance"
    ],
    "wof:name":"Credit Bureau of Bristol",
    "wof:placetype":"venue"
},
  "geometry": {"coordinates":[-82.211922,36.559099],"type":"Point"}
}