{
  "type": "Feature",
  "properties": {
    "addr:full":"45 Crossland Ave Clarksville TN 37040",
    "addr:housenumber":"45",
    "addr:postcode":"37040",
    "addr:street":"Crossland Ave",
    "iso:country":"US",
    "sg:address":"45 Crossland Ave",
    "sg:city":"Clarksville",
    "sg:classifiers":[
        {
            "category":"Personal",
            "subcategory":"Beauty Salon",
            "type":"Services"
        }
    ],
    "sg:phone":"+1 931 645 1747",
    "sg:postcode":"37040",
    "sg:province":"TN",
    "sg:tags":[
        "shop"
    ],
    "wof:name":"Riverside California Concept",
    "wof:placetype":"venue"
},
  "geometry": {"coordinates":[-87.36233799999999,36.520491],"type":"Point"}
}