{
  "type": "Feature",
  "properties": {
    "iso:country":"US",
    "sg:address":"1218 Huntsville Hwy",
    "sg:city":"Fayetteville",
    "sg:classifiers":[
        {
            "category":"Building & Trades",
            "subcategory":"Equipment Rental",
            "type":"Services"
        }
    ],
    "sg:phone":"+1 931 433 2985",
    "sg:postcode":"37334",
    "sg:province":"TN",
    "sg:tags":[
        "yard"
    ],
    "wof:name":"Rent-A-Center",
    "wof:placetype":"venue"
},
  "geometry": {"coordinates":[-86.56797,35.14051],"type":"Point"}
}