{
  "type": "Feature",
  "properties": {
    "iso:country":"US",
    "sg:address":"1211 S Pkwy E",
    "sg:city":"Memphis",
    "sg:classifiers":[
        {
            "category":"Retail",
            "subcategory":"Auto Repair",
            "type":"Services"
        }
    ],
    "sg:phone":"+1 901 947 6847",
    "sg:postcode":"38106",
    "sg:province":"TN",
    "sg:tags":[
        "repairing",
        "automobile",
        "radiator"
    ],
    "wof:name":"Radiator Exchange & Works",
    "wof:placetype":"venue"
},
  "geometry": {"coordinates":[-90.022569,35.10943],"type":"Point"}
}