{
  "type": "Feature",
  "properties": {
    "iso:country":"US",
    "sg:address":"3169 Lebanon Pike",
    "sg:city":"Nashville",
    "sg:classifiers":[
        {
            "category":"Banks & Credit Unions",
            "subcategory":"Bank",
            "type":"Services"
        }
    ],
    "sg:phone":"+1 615 750 8610",
    "sg:postcode":"37214",
    "sg:province":"TN",
    "sg:tags":[
        "state",
        "commercial"
    ],
    "wof:name":"Bank Of Nashville",
    "wof:placetype":"venue"
},
  "geometry": {"coordinates":[-86.63903999999999,36.183533],"type":"Point"}
}