{
  "type": "Feature",
  "properties": {
    "addr:full":"204 N Cutler St Greeneville TN 37745",
    "addr:housenumber":"204",
    "addr:postcode":"37745",
    "addr:street":"N Cutler St",
    "iso:country":"US",
    "sg:address":"204 N Cutler St",
    "sg:city":"Greeneville",
    "sg:classifiers":[
        {
            "category":"Government",
            "subcategory":"Office",
            "type":"Public Place"
        }
    ],
    "sg:phone":"+1 423 798 1700",
    "sg:postcode":"37745",
    "sg:province":"TN",
    "wof:name":"Greene County Purchasing Dept",
    "wof:placetype":"venue"
},
  "geometry": {"coordinates":[-82.834109,36.16634],"type":"Point"}
}