{
  "type": "Feature",
  "properties": {
    "iso:country":"US",
    "sg:address":"11800 Mcauley St",
    "sg:city":"Arlington",
    "sg:classifiers":[
        {
            "category":"Structure",
            "subcategory":"Office Building",
            "type":"Public Place"
        }
    ],
    "sg:phone":"+1 901 867 0594",
    "sg:postcode":"38002",
    "sg:province":"TN",
    "sg:tags":[
        "park"
    ],
    "wof:name":"Dennis L Schaedle Propert",
    "wof:placetype":"venue"
},
  "geometry": {"coordinates":[-89.66962599999999,35.288291],"type":"Point"}
}