{
  "type": "Feature",
  "properties": {
    "iso:country":"US",
    "sg:address":"4440 US Hwy 70",
    "sg:city":"Cedar Grove",
    "sg:classifiers":[
        {
            "category":"Manufacturing",
            "subcategory":"Metals",
            "type":"Manufacturing & Wholesale Goods"
        },
        {
            "category":"Manufacturing",
            "subcategory":"Tools & Machinery",
            "type":"Manufacturing & Wholesale Goods"
        }
    ],
    "sg:phone":"+1 731 987 9978",
    "sg:postcode":"38321",
    "sg:province":"TN",
    "sg:tags":[
        "repair",
        "works",
        "mfg",
        "die",
        "maker",
        "blast",
        "furnace",
        "welding"
    ],
    "wof:name":"Dienamic Tool & Die Inc",
    "wof:placetype":"venue"
},
  "geometry": {"coordinates":[-88.58266399999999,35.832718],"type":"Point"}
}