{
  "type": "Feature",
  "properties": {
    "iso:country":"US",
    "sg:address":"5049 Coke Cove",
    "sg:city":"Memphis",
    "sg:classifiers":[
        {
            "category":"Building & Trades",
            "subcategory":"Cleaning & Sanitation",
            "type":"Services"
        }
    ],
    "sg:phone":"+1 901 366 0067",
    "sg:postcode":"38127",
    "sg:province":"TN",
    "sg:tags":[
        "janitor"
    ],
    "wof:name":"Simpson & Son Janitorial Svc",
    "wof:placetype":"venue"
},
  "geometry": {"coordinates":[-90.032403,35.263354],"type":"Point"}
}