{
  "type": "Feature",
  "properties": {
    "addr:full":"9 E College St Brownsville TN 38012",
    "addr:housenumber":"9",
    "addr:postcode":"38012",
    "addr:street":"E College St",
    "iso:country":"US",
    "sg:address":"9 E College St",
    "sg:city":"Brownsville",
    "sg:classifiers":[
        {
            "category":"Health Services",
            "subcategory":"Clinic",
            "type":"Services"
        }
    ],
    "sg:phone":"+1 731 772 2655",
    "sg:postcode":"38012",
    "sg:province":"TN",
    "sg:tags":[
        "home",
        "care"
    ],
    "wof:name":"Homechoice Health Service Inc",
    "wof:placetype":"venue"
},
  "geometry": {"coordinates":[-89.262164,35.595816],"type":"Point"}
}