{
  "type": "Feature",
  "properties": {
    "iso:country":"US",
    "sg:address":"328 College St",
    "sg:city":"Clarksville",
    "sg:classifiers":[
        {
            "category":"Autos & Motor Vehicles",
            "subcategory":"Automobile Sales",
            "type":"Retail Goods"
        }
    ],
    "sg:phone":"+1 931 647 3353",
    "sg:postcode":"37040",
    "sg:province":"TN",
    "sg:tags":[
        "car",
        "dealer"
    ],
    "sg:website":"www.jenkinsandwynneflm.com",
    "wof:name":"Jenkins and Wynne Honda",
    "wof:placetype":"venue"
},
  "geometry": {"coordinates":[-87.357365,36.530511],"type":"Point"}
}