{
  "type": "Feature",
  "properties": {
    "addr:full":"3038 Nolensville Pike Nashville TN 37211",
    "addr:housenumber":"3038",
    "addr:postcode":"37211",
    "addr:street":"Nolensville Pike",
    "iso:country":"US",
    "sg:address":"3038 Nolensville Pike",
    "sg:city":"Nashville",
    "sg:classifiers":[
        {
            "category":"Health Services",
            "subcategory":"Doctor",
            "type":"Services"
        }
    ],
    "sg:phone":"+1 615 331 2483",
    "sg:postcode":"37211",
    "sg:province":"TN",
    "wof:name":"Nashville Dental Center PC",
    "wof:placetype":"venue"
},
  "geometry": {"coordinates":[-86.741647,36.104137],"type":"Point"}
}