{
  "type": "Feature",
  "properties": {
    "addr:full":"1352 W College St Murfreesboro TN 37129",
    "addr:housenumber":"1352",
    "addr:postcode":"37129",
    "addr:street":"W College St",
    "iso:country":"US",
    "sg:address":"1352 W College St",
    "sg:city":"Murfreesboro",
    "sg:classifiers":[
        {
            "category":"Manufacturing",
            "subcategory":"Tools & Machinery",
            "type":"Manufacturing & Wholesale Goods"
        }
    ],
    "sg:phone":"+1 615 867 7534",
    "sg:postcode":"37129",
    "sg:province":"TN",
    "sg:tags":[
        "food",
        "product",
        "parts",
        "7",
        "mfg"
    ],
    "wof:name":"Packers Supply Company",
    "wof:placetype":"venue"
},
  "geometry": {"coordinates":[-86.41698,35.866033],"type":"Point"}
}