{
  "type": "Feature",
  "properties": {
    "addr:full":"106 Public Sq Waynesboro TN 38474",
    "addr:housenumber":"106",
    "addr:postcode":"38474",
    "addr:street":"Public Sq",
    "iso:country":"US",
    "sg:address":"106 Public Sq",
    "sg:city":"Waynesboro",
    "sg:classifiers":[
        {
            "category":"Shopping",
            "subcategory":"Gifts & Souvenirs",
            "type":"Retail Goods"
        }
    ],
    "sg:phone":"+1 931 722 7322",
    "sg:postcode":"38474",
    "sg:province":"TN",
    "sg:tags":[
        "shop"
    ],
    "wof:name":"Helton's",
    "wof:placetype":"venue"
},
  "geometry": {"coordinates":[-87.20731499999999,35.533955],"type":"Point"}
}