{
  "type": "Feature",
  "properties": {
    "iso:country":"US",
    "sg:address":"2982 Austin Peay Hwy",
    "sg:city":"Memphis",
    "sg:classifiers":[
        {
            "category":"Retail",
            "subcategory":"Repair Shop",
            "type":"Services"
        }
    ],
    "sg:phone":"+1 901 388 1911",
    "sg:postcode":"38128",
    "sg:province":"TN",
    "sg:tags":[
        "television",
        "radio"
    ],
    "wof:name":"Jay Hogan Television Service",
    "wof:placetype":"venue"
},
  "geometry": {"coordinates":[-89.92144500000001,35.206953],"type":"Point"}
}