{
  "type": "Feature",
  "properties": {
    "iso:country":"US",
    "sg:address":"129 Hollow Dr",
    "sg:city":"Crossville",
    "sg:classifiers":[
        {
            "category":"Retail",
            "subcategory":"Repair Shop",
            "type":"Services"
        }
    ],
    "sg:phone":"+1 931 707 7654",
    "sg:postcode":"38571",
    "sg:province":"TN",
    "wof:name":"Randys Repair Inc",
    "wof:placetype":"venue"
},
  "geometry": {"coordinates":[-85.065842,36.100243],"type":"Point"}
}