{
  "type": "Feature",
  "properties": {
    "iso:country":"US",
    "sg:address":"397 Perkins Exd",
    "sg:city":"Memphis",
    "sg:classifiers":[
        {
            "category":"Real Estate",
            "subcategory":"Real Estate Operator",
            "type":"Services"
        }
    ],
    "sg:phone":"+1 901 761 3193",
    "sg:postcode":"38117",
    "sg:province":"TN",
    "sg:tags":[
        "mall",
        "shopping",
        "center"
    ],
    "wof:name":"Laurel Wood Shopping Ctr",
    "wof:placetype":"venue"
},
  "geometry": {"coordinates":[-89.908601,35.119396],"type":"Point"}
}