{
  "type": "Feature",
  "properties": {
    "iso:country":"US",
    "sg:address":"1431 Upper Middle Creek Rd",
    "sg:city":"Sevierville",
    "sg:classifiers":[
        {
            "category":"Social Services",
            "subcategory":"Child Care",
            "type":"Services"
        }
    ],
    "sg:phone":"+1 865 428 6104",
    "sg:postcode":"37876",
    "sg:province":"TN",
    "sg:tags":[
        "day"
    ],
    "wof:name":"Happy Land Day Care",
    "wof:placetype":"venue"
},
  "geometry": {"coordinates":[-83.519875,35.783119],"type":"Point"}
}