{
  "type": "Feature",
  "properties": {
    "iso:country":"US",
    "sg:address":"375 Demeka Dr",
    "sg:city":"Somerville",
    "sg:classifiers":[
        {
            "category":"Farming",
            "subcategory":"Livestock Farm",
            "type":"Manufacturing & Wholesale Goods"
        }
    ],
    "sg:phone":"+1 901 465 9245",
    "sg:postcode":"38068",
    "sg:province":"TN",
    "sg:tags":[
        "trade",
        "cattle",
        "beef",
        "feedlot",
        "contractor"
    ],
    "wof:name":"Virgil Proctor",
    "wof:placetype":"venue"
},
  "geometry": {"coordinates":[-89.362538,35.174421],"type":"Point"}
}