{
  "type": "Feature",
  "properties": {
    "iso:country":"US",
    "sg:address":"33 Music Sq W",
    "sg:city":"Nashville",
    "sg:classifiers":[
        {
            "category":"Professional",
            "subcategory":"Business Services",
            "type":"Services"
        }
    ],
    "sg:phone":"+1 615 742 1250",
    "sg:postcode":"37203",
    "sg:province":"TN",
    "sg:tags":[
        "record",
        "company"
    ],
    "wof:name":"Blue Plate Music Inc",
    "wof:placetype":"venue"
},
  "geometry": {"coordinates":[-86.793464,36.149112],"type":"Point"}
}