{
  "type": "Feature",
  "properties": {
    "iso:country":"US",
    "sg:address":"2400 Fairbrook Dr",
    "sg:city":"Nashville",
    "sg:classifiers":[
        {
            "category":"Shopping",
            "subcategory":"Music",
            "type":"Retail Goods"
        }
    ],
    "sg:phone":"+1 615 883 8409",
    "sg:postcode":"37214",
    "sg:province":"TN",
    "wof:name":"Planet Ears Records",
    "wof:placetype":"venue"
},
  "geometry": {"coordinates":[-86.68676000000001,36.205629],"type":"Point"}
}