{
  "type": "Feature",
  "properties": {
    "iso:country":"US",
    "sg:address":"474 US Hwy 72 W",
    "sg:city":"Collierville",
    "sg:classifiers":[
        {
            "category":"Retail",
            "subcategory":"Veterinary Services",
            "type":"Services"
        }
    ],
    "sg:phone":"+1 901 854 1500",
    "sg:postcode":"38017",
    "sg:province":"TN",
    "sg:tags":[
        "veterinarian"
    ],
    "wof:name":"Collierville Animal Clinic",
    "wof:placetype":"venue"
},
  "geometry": {"coordinates":[-89.678044,35.039984],"type":"Point"}
}