{
  "type": "Feature",
  "properties": {
    "iso:country":"US",
    "sg:address":"1307 West Ave",
    "sg:city":"Crossville",
    "sg:classifiers":[
        {
            "category":"Banks & Credit Unions",
            "subcategory":"Bank",
            "type":"Services"
        }
    ],
    "sg:phone":"+1 931 707 1470",
    "sg:postcode":"38555",
    "sg:province":"TN",
    "sg:tags":[
        "loan",
        "real estate"
    ],
    "wof:name":"Mortgage Investors Group",
    "wof:placetype":"venue"
},
  "geometry": {"coordinates":[-85.04111399999999,35.958927],"type":"Point"}
}