{
  "type": "Feature",
  "properties": {
    "iso:country":"US",
    "sg:address":"1758 W Andrew Johnson Hwy",
    "sg:city":"Greeneville",
    "sg:classifiers":[
        {
            "category":"Banks & Credit Unions",
            "subcategory":"Bank",
            "type":"Services"
        }
    ],
    "sg:phone":"+1 423 722 0616",
    "sg:postcode":"37743",
    "sg:province":"TN",
    "sg:tags":[
        "personal",
        "institution"
    ],
    "wof:name":"Southeastern Lending",
    "wof:placetype":"venue"
},
  "geometry": {"coordinates":[-82.851831,36.172642],"type":"Point"}
}