{
  "type": "Feature",
  "properties": {
    "iso:country":"US",
    "sg:address":"256 New Middleton Hwy",
    "sg:city":"Gordonsville",
    "sg:classifiers":[
        {
            "category":"Government",
            "subcategory":"Office",
            "type":"Public Place"
        }
    ],
    "sg:phone":"+1 615 683 8982",
    "sg:postcode":"38563",
    "sg:province":"TN",
    "sg:tags":[
        "transportation"
    ],
    "wof:name":"Materials & Test",
    "wof:placetype":"venue"
},
  "geometry": {"coordinates":[-85.978631,36.181376],"type":"Point"}
}