{
  "type": "Feature",
  "properties": {
    "iso:country":"US",
    "sg:address":"7586 Lowrance Rd",
    "sg:city":"Memphis",
    "sg:classifiers":[
        {
            "category":"Building & Trades",
            "subcategory":"Cleaning & Sanitation",
            "type":"Services"
        }
    ],
    "sg:phone":"+1 901 757 4300",
    "sg:postcode":"38125",
    "sg:province":"TN",
    "sg:tags":[
        "maintenance"
    ],
    "wof:name":"Sandra A Maynard",
    "wof:placetype":"venue"
},
  "geometry": {"coordinates":[-89.811075,35.036815],"type":"Point"}
}