{
  "type": "Feature",
  "properties": {
    "addr:full":"6020 Shallowford Rd Chattanooga TN 37421",
    "addr:housenumber":"6020",
    "addr:postcode":"37421",
    "addr:street":"Shallowford Rd",
    "iso:country":"US",
    "sg:address":"6020 Shallowford Rd",
    "sg:city":"Chattanooga",
    "sg:classifiers":[
        {
            "category":"Shopping",
            "type":"Retail Goods"
        }
    ],
    "sg:phone":"+1 423 553 5100",
    "sg:postcode":"37421",
    "sg:province":"TN",
    "sg:tags":[
        "merchandise"
    ],
    "wof:name":"Nextel",
    "wof:placetype":"venue"
},
  "geometry": {"coordinates":[-85.189537,35.053959],"type":"Point"}
}