{
  "type": "Feature",
  "properties": {
    "addr:full":"4525 Harding Pike Nashville TN 37205",
    "addr:housenumber":"4525",
    "addr:postcode":"37205",
    "addr:street":"Harding Pike",
    "iso:country":"US",
    "sg:address":"4525 Harding Pike",
    "sg:city":"Nashville",
    "sg:classifiers":[
        {
            "category":"Health Services",
            "subcategory":"Clinic",
            "type":"Services"
        }
    ],
    "sg:phone":"+1 615 620 4555",
    "sg:postcode":"37205",
    "sg:province":"TN",
    "wof:name":"Healthcare Management",
    "wof:placetype":"venue"
},
  "geometry": {"coordinates":[-86.849125,36.123857],"type":"Point"}
}