{
  "type": "Feature",
  "properties": {
    "iso:country":"US",
    "sg:address":"1013 S Glade St",
    "sg:city":"Columbia",
    "sg:classifiers":[
        {
            "category":"Professional",
            "subcategory":"Business Services",
            "type":"Services"
        }
    ],
    "sg:phone":"+1 615 480 4494",
    "sg:postcode":"38401",
    "sg:province":"TN",
    "wof:name":"Good Willys New & Used",
    "wof:placetype":"venue"
},
  "geometry": {"coordinates":[-87.03119599999999,35.610824],"type":"Point"}
}