{
  "type": "Feature",
  "properties": {
    "iso:country":"US",
    "sg:address":"105 S Jackson St",
    "sg:city":"Tullahoma",
    "sg:classifiers":[
        {
            "category":"Home & Garden",
            "subcategory":"Furniture",
            "type":"Retail Goods"
        }
    ],
    "sg:phone":"+1 931 455 8595",
    "sg:postcode":"37388",
    "sg:province":"TN",
    "sg:tags":[
        "house",
        "furnishing"
    ],
    "wof:name":"Arnold's Furniture Inc",
    "wof:placetype":"venue"
},
  "geometry": {"coordinates":[-86.211257,35.361625],"type":"Point"}
}