{
  "type": "Feature",
  "properties": {
    "iso:country":"US",
    "sg:address":"4278 Bonny Oaks Dr",
    "sg:city":"Chattanooga",
    "sg:classifiers":[
        {
            "category":"Communications",
            "subcategory":"Radio Station",
            "type":"Services"
        }
    ],
    "sg:phone":"+1 423 698 8839",
    "sg:postcode":"37406",
    "sg:province":"TN",
    "sg:tags":[
        "television"
    ],
    "wof:name":"W Y H B Channel 39",
    "wof:placetype":"venue"
},
  "geometry": {"coordinates":[-85.21408700000001,35.0808],"type":"Point"}
}