{
  "type": "Feature",
  "properties": {
    "iso:country":"US",
    "sg:address":"5854 Airline Rd",
    "sg:city":"Arlington",
    "sg:classifiers":[
        {
            "category":"Government",
            "subcategory":"Office",
            "type":"Public Place"
        }
    ],
    "sg:phone":"+1 901 867 2620",
    "sg:postcode":"38002",
    "sg:province":"TN",
    "sg:tags":[
        "village"
    ],
    "wof:name":"Arlington Town Office",
    "wof:placetype":"venue"
},
  "geometry": {"coordinates":[-89.67353199999999,35.289665],"type":"Point"}
}