{
  "type": "Feature",
  "properties": {
    "addr:full":"681 Dutchmans Dr Hermitage TN 37076",
    "addr:housenumber":"681",
    "addr:postcode":"37076",
    "addr:street":"Dutchmans Dr",
    "iso:country":"US",
    "sg:address":"681 Dutchmans Dr",
    "sg:city":"Hermitage",
    "sg:classifiers":[
        {
            "category":"Professional",
            "type":"Services"
        }
    ],
    "sg:phone":"+1 615 874 3493",
    "sg:postcode":"37076",
    "sg:province":"TN",
    "wof:name":"Say K Lam",
    "wof:placetype":"venue"
},
  "geometry": {"coordinates":[-86.595856,36.204615],"type":"Point"}
}