{
  "type": "Feature",
  "properties": {
    "addr:full":"5075 Ooltewah Ringgold Rd Ooltewah TN 37363",
    "addr:housenumber":"5075",
    "addr:postcode":"37363",
    "addr:street":"Ooltewah Ringgold Rd",
    "iso:country":"US",
    "sg:address":"5075 Ooltewah Ringgold Rd",
    "sg:city":"Ooltewah",
    "sg:classifiers":[
        {
            "category":"Building & Trades",
            "subcategory":"Landscaping Services",
            "type":"Services"
        }
    ],
    "sg:phone":"+1 423 238 6308",
    "sg:postcode":"37363",
    "sg:province":"TN",
    "sg:tags":[
        "landscape",
        "contractor"
    ],
    "wof:name":"B & R Landscaping & Tree Svc",
    "wof:placetype":"venue"
},
  "geometry": {"coordinates":[-85.06636899999999,35.06203],"type":"Point"}
}