{
  "type": "Feature",
  "properties": {
    "iso:country":"US",
    "sg:address":"108 Dyer St",
    "sg:city":"Columbia",
    "sg:classifiers":[
        {
            "category":"Retail",
            "subcategory":"Auto Repair",
            "type":"Services"
        }
    ],
    "sg:phone":"+1 931 540 0271",
    "sg:postcode":"38401",
    "sg:province":"TN",
    "sg:tags":[
        "repairing",
        "automobile",
        "general"
    ],
    "wof:name":"Dan's Auto Care",
    "wof:placetype":"venue"
},
  "geometry": {"coordinates":[-87.039383,35.590022],"type":"Point"}
}