{
  "type": "Feature",
  "properties": {
    "iso:country":"US",
    "sg:address":"163 Oakdale Ln",
    "sg:city":"Sparta",
    "sg:classifiers":[
        {
            "category":"Professional",
            "subcategory":"Computer Services",
            "type":"Services"
        }
    ],
    "sg:phone":"+1 931 738 8200",
    "sg:postcode":"38583",
    "sg:province":"TN",
    "wof:name":"Professional Computer Svc",
    "wof:placetype":"venue"
},
  "geometry": {"coordinates":[-85.492952,35.910574],"type":"Point"}
}