{
  "type": "Feature",
  "properties": {
    "addr:full":"1080 Cairo Bend Rd Lebanon TN 37087",
    "addr:housenumber":"1080",
    "addr:postcode":"37087",
    "addr:street":"Cairo Bend Rd",
    "iso:country":"US",
    "sg:address":"1080 Cairo Bend Rd",
    "sg:city":"Lebanon",
    "sg:classifiers":[
        {
            "category":"Utilities",
            "subcategory":"Mobile Phone",
            "type":"Services"
        }
    ],
    "sg:phone":"+1 615 444 2057",
    "sg:postcode":"37087",
    "sg:province":"TN",
    "sg:tags":[
        "communication",
        "radiotelephone"
    ],
    "wof:name":"Nextel",
    "wof:placetype":"venue"
},
  "geometry": {"coordinates":[-86.399997,36.256208],"type":"Point"}
}