{
  "type": "Feature",
  "properties": {
    "iso:country":"US",
    "sg:address":"4264 Jamesborough Pl",
    "sg:city":"Nashville",
    "sg:classifiers":[
        {
            "category":"Professional",
            "subcategory":"Art Services",
            "type":"Services"
        }
    ],
    "sg:phone":"+1 615 292 1783",
    "sg:postcode":"37215",
    "sg:province":"TN",
    "sg:tags":[
        "artist"
    ],
    "wof:name":"Jamesboro Studio",
    "wof:placetype":"venue"
},
  "geometry": {"coordinates":[-86.804452,36.092306],"type":"Point"}
}