{
  "type": "Feature",
  "properties": {
    "addr:full":"2812 Lebanon Pike Nashville TN 37214",
    "addr:housenumber":"2812",
    "addr:postcode":"37214",
    "addr:street":"Lebanon Pike",
    "iso:country":"US",
    "sg:address":"2812 Lebanon Pike",
    "sg:city":"Nashville",
    "sg:classifiers":[
        {
            "category":"Manufacturing",
            "subcategory":"Printing",
            "type":"Manufacturing & Wholesale Goods"
        }
    ],
    "sg:phone":"+1 615 889 2854",
    "sg:postcode":"37214",
    "sg:province":"TN",
    "sg:tags":[
        "print",
        "photocopying",
        "lithographic"
    ],
    "wof:name":"Print Shop The",
    "wof:placetype":"venue"
},
  "geometry": {"coordinates":[-86.66204500000001,36.167374],"type":"Point"}
}