{
  "type": "Feature",
  "properties": {
    "addr:full":"5475 Fox Plaza Dr Memphis TN 38115",
    "addr:housenumber":"5475",
    "addr:postcode":"38115",
    "addr:street":"Fox Plaza Dr",
    "iso:country":"US",
    "sg:address":"5475 Fox Plaza Dr",
    "sg:city":"Memphis",
    "sg:classifiers":[
        {
            "category":"Retail",
            "subcategory":"Auto Repair",
            "type":"Services"
        }
    ],
    "sg:phone":"+1 901 794 1454",
    "sg:postcode":"38115",
    "sg:province":"TN",
    "sg:tags":[
        "body",
        "automobile",
        "painting"
    ],
    "sg:website":"www.team1autobody.com",
    "wof:name":"Team 1 Auto Body & Glass",
    "wof:placetype":"venue"
},
  "geometry": {"coordinates":[-89.883771,35.074402],"type":"Point"}
}