{
  "type": "Feature",
  "properties": {
    "iso:country":"US",
    "sg:address":"1167 S Lowry St",
    "sg:city":"Smyrna",
    "sg:classifiers":[
        {
            "category":"Organizations",
            "subcategory":"Religious Organization",
            "type":"Services"
        }
    ],
    "sg:phone":"+1 615 459 7854",
    "sg:postcode":"37167",
    "sg:province":"TN",
    "wof:name":"Southside Church Of Christ",
    "wof:placetype":"venue"
},
  "geometry": {"coordinates":[-86.48424300000001,35.942778],"type":"Point"}
}