{
  "type": "Feature",
  "properties": {
    "iso:country":"US",
    "sg:address":"2119 Old Ashland City Rd",
    "sg:city":"Clarksville",
    "sg:classifiers":[
        {
            "category":"Retail",
            "subcategory":"Auto Repair",
            "type":"Services"
        }
    ],
    "sg:phone":"+1 931 645 4549",
    "sg:postcode":"37043",
    "sg:province":"TN",
    "sg:tags":[
        "repairing",
        "automobile",
        "general"
    ],
    "wof:name":"Crain's Automotive",
    "wof:placetype":"venue"
},
  "geometry": {"coordinates":[-87.312709,36.513125],"type":"Point"}
}