{
  "type": "Feature",
  "properties": {
    "iso:country":"US",
    "sg:address":"110 Lagoon St",
    "sg:city":"Decaturville",
    "sg:classifiers":[
        {
            "category":"Recreation",
            "subcategory":"Marina",
            "type":"Entertainment"
        }
    ],
    "sg:phone":"+1 731 852 2743",
    "sg:postcode":"38310",
    "sg:province":"TN",
    "wof:name":"Gumdale Marina",
    "wof:placetype":"venue"
},
  "geometry": {"coordinates":[-88.374978,35.233909],"type":"Point"}
}