{
  "type": "Feature",
  "properties": {
    "iso:country":"US",
    "sg:address":"493 Linden Ave",
    "sg:city":"Memphis",
    "sg:classifiers":[
        {
            "category":"Building & Trades",
            "subcategory":"Construction",
            "type":"Services"
        }
    ],
    "sg:phone":"+1 901 537 1300",
    "sg:postcode":"38126",
    "sg:province":"TN",
    "sg:tags":[
        "contractor"
    ],
    "wof:name":"Salton Companies",
    "wof:placetype":"venue"
},
  "geometry": {"coordinates":[-90.044946,35.136746],"type":"Point"}
}