{
  "type": "Feature",
  "properties": {
    "addr:full":"138 Tangency Dr Gray TN 37615",
    "addr:housenumber":"138",
    "addr:postcode":"37615",
    "addr:street":"Tangency Dr",
    "iso:country":"US",
    "sg:address":"138 Tangency Dr",
    "sg:city":"Gray",
    "sg:classifiers":[
        {
            "category":"Professional",
            "subcategory":"Advertising",
            "type":"Services"
        }
    ],
    "sg:phone":"+1 423 477 5733",
    "sg:postcode":"37615",
    "sg:province":"TN",
    "sg:tags":[
        "counselor"
    ],
    "wof:name":"Great Scott Design",
    "wof:placetype":"venue"
},
  "geometry": {"coordinates":[-82.420646,36.392879],"type":"Point"}
}