{
  "type": "Feature",
  "properties": {
    "iso:country":"US",
    "sg:address":"69 Orchard Hill Rd",
    "sg:city":"Fayetteville",
    "sg:classifiers":[
        {
            "category":"Building & Trades",
            "subcategory":"Construction",
            "type":"Services"
        }
    ],
    "sg:phone":"+1 931 433 9706",
    "sg:postcode":"37334",
    "sg:province":"TN",
    "sg:tags":[
        "roofing",
        "contractor"
    ],
    "wof:name":"Roofing Services Co Inc",
    "wof:placetype":"venue"
},
  "geometry": {"coordinates":[-86.584962,35.105023],"type":"Point"}
}