{
  "type": "Feature",
  "properties": {
    "iso:country":"US",
    "sg:address":"3000 S Mall Rd",
    "sg:city":"Knoxville",
    "sg:classifiers":[
        {
            "category":"Banks & Credit Unions",
            "subcategory":"Bank",
            "type":"Services"
        }
    ],
    "sg:phone":"+1 865 546 5973",
    "sg:postcode":"37924",
    "sg:province":"TN",
    "sg:tags":[
        "cashing",
        "check"
    ],
    "wof:name":"Cash Advance Til Payday",
    "wof:placetype":"venue"
},
  "geometry": {"coordinates":[-83.87602099999999,36.029585],"type":"Point"}
}