{
  "type": "Feature",
  "properties": {
    "addr:full":"2717 E Oakland Ave Johnson City TN 37601",
    "addr:housenumber":"2717",
    "addr:postcode":"37601",
    "addr:street":"E Oakland Ave",
    "iso:country":"US",
    "sg:address":"2717 E Oakland Ave",
    "sg:city":"Johnson City",
    "sg:classifiers":[
        {
            "category":"Professional",
            "subcategory":"Accounting & Tax Preparation",
            "type":"Services"
        }
    ],
    "sg:phone":"+1 423 282 2021",
    "sg:postcode":"37601",
    "sg:province":"TN",
    "sg:tags":[
        "accountant"
    ],
    "wof:name":"Robert L Weaver CPA",
    "wof:placetype":"venue"
},
  "geometry": {"coordinates":[-82.370424,36.358822],"type":"Point"}
}