{
  "type": "Feature",
  "properties": {
    "iso:country":"US",
    "sg:address":"3421 Elder Mountain Rd",
    "sg:city":"Chattanooga",
    "sg:classifiers":[
        {
            "category":"Wholesale",
            "subcategory":"Computers",
            "type":"Manufacturing & Wholesale Goods"
        }
    ],
    "sg:phone":"+1 423 821 1822",
    "sg:postcode":"37419",
    "sg:province":"TN",
    "sg:tags":[
        "trade"
    ],
    "wof:name":"Quality Software Solutions",
    "wof:placetype":"venue"
},
  "geometry": {"coordinates":[-85.36299200000001,35.04268],"type":"Point"}
}