{
  "type": "Feature",
  "properties": {
    "iso:country":"US",
    "sg:address":"2783 Smith Springs Rd",
    "sg:city":"Nashville",
    "sg:classifiers":[
        {
            "category":"Social Services",
            "subcategory":"Child Care",
            "type":"Services"
        }
    ],
    "sg:phone":"+1 615 366 5028",
    "sg:postcode":"37217",
    "sg:province":"TN",
    "sg:tags":[
        "day"
    ],
    "wof:name":"Church of Christ Preschool",
    "wof:placetype":"venue"
},
  "geometry": {"coordinates":[-86.610316,36.088366],"type":"Point"}
}