{
  "type": "Feature",
  "properties": {
    "iso:country":"US",
    "sg:address":"6745 US Hwy 79 N",
    "sg:city":"Buchanan",
    "sg:classifiers":[
        {
            "category":"Education",
            "subcategory":"School",
            "type":"Public Place"
        }
    ],
    "sg:phone":"+1 731 644 1600",
    "sg:postcode":"38222",
    "sg:province":"TN",
    "wof:name":"Lakewood Elementary School",
    "wof:placetype":"venue"
},
  "geometry": {"coordinates":[-88.21241499999999,36.36088],"type":"Point"}
}