{
  "type": "Feature",
  "properties": {
    "iso:country":"US",
    "sg:address":"507 Dolly Parton Pkwy",
    "sg:city":"Sevierville",
    "sg:classifiers":[
        {
            "category":"Insurance",
            "subcategory":"Insurance Agent",
            "type":"Services"
        }
    ],
    "sg:phone":"+1 865 908 3680",
    "sg:postcode":"37862",
    "sg:province":"TN",
    "wof:name":"David Owenby Agency",
    "wof:placetype":"venue"
},
  "geometry": {"coordinates":[-83.554771,35.86638],"type":"Point"}
}