{
  "type": "Feature",
  "properties": {
    "iso:country":"US",
    "sg:address":"1234 S 2nd St",
    "sg:city":"Union City",
    "sg:classifiers":[
        {
            "category":"Home & Garden",
            "subcategory":"Garden Supply",
            "type":"Retail Goods"
        }
    ],
    "sg:phone":"+1 731 885 1510",
    "sg:postcode":"38261",
    "sg:province":"TN",
    "sg:tags":[
        "lawn"
    ],
    "wof:name":"Hill's Hardware & Sporting",
    "wof:placetype":"venue"
},
  "geometry": {"coordinates":[-89.05930499999999,36.41564],"type":"Point"}
}