{
  "type": "Feature",
  "properties": {
    "addr:full":"3409 Brick Church Pike Nashville TN 37207",
    "addr:housenumber":"3409",
    "addr:postcode":"37207",
    "addr:street":"Brick Church Pike",
    "iso:country":"US",
    "sg:address":"3409 Brick Church Pike",
    "sg:city":"Nashville",
    "sg:classifiers":[
        {
            "category":"Organizations",
            "subcategory":"Religious Organization",
            "type":"Services"
        }
    ],
    "sg:phone":"+1 615 262 9132",
    "sg:postcode":"37207",
    "sg:province":"TN",
    "sg:tags":[
        "church"
    ],
    "wof:name":"Gethsemane Baptist Church",
    "wof:placetype":"venue"
},
  "geometry": {"coordinates":[-86.779794,36.245435],"type":"Point"}
}