{
  "type": "Feature",
  "properties": {
    "iso:country":"US",
    "sg:address":"8311 US Hwy 51 N",
    "sg:city":"Millington",
    "sg:classifiers":[
        {
            "category":"Shopping",
            "subcategory":"Discount & Variety Stores",
            "type":"Retail Goods"
        },
        {
            "category":"Wholesale",
            "subcategory":"Electrical",
            "type":"Manufacturing & Wholesale Goods"
        }
    ],
    "sg:phone":"+1 901 872 4610",
    "sg:postcode":"38053",
    "sg:province":"TN",
    "sg:tags":[
        "general",
        "electric",
        "merchandise",
        "supply"
    ],
    "wof:name":"C & C Supply Company",
    "wof:placetype":"venue"
},
  "geometry": {"coordinates":[-89.897272,35.353743],"type":"Point"}
}