{
  "type": "Feature",
  "properties": {
    "iso:country":"US",
    "sg:address":"2587 Goodwill Ln",
    "sg:city":"Memphis",
    "sg:classifiers":[
        {
            "category":"Real Estate",
            "subcategory":"Real Estate Operator",
            "type":"Services"
        }
    ],
    "sg:phone":"+1 901 353 0919",
    "sg:postcode":"38108",
    "sg:province":"TN",
    "sg:tags":[
        "apartment"
    ],
    "wof:name":"Woodglen Village Apts",
    "wof:placetype":"venue"
},
  "geometry": {"coordinates":[-89.97105500000001,35.179769],"type":"Point"}
}