{
  "type": "Feature",
  "properties": {
    "iso:country":"US",
    "sg:address":"1401 Beaumont Ave",
    "sg:city":"Knoxville",
    "sg:classifiers":[
        {
            "category":"Building & Trades",
            "subcategory":"Construction",
            "type":"Services"
        }
    ],
    "sg:phone":"+1 865 521 7163",
    "sg:postcode":"37921",
    "sg:province":"TN",
    "sg:tags":[
        "floor",
        "laying",
        "contractor"
    ],
    "wof:name":"Garys Flooring",
    "wof:placetype":"venue"
},
  "geometry": {"coordinates":[-83.945382,35.974424],"type":"Point"}
}