{
  "type": "Feature",
  "properties": {
    "addr:full":"1503 Bartway Dr Murfreesboro TN 37130",
    "addr:housenumber":"1503",
    "addr:postcode":"37130",
    "addr:street":"Bartway Dr",
    "iso:country":"US",
    "sg:address":"1503 Bartway Dr",
    "sg:city":"Murfreesboro",
    "sg:classifiers":[
        {
            "category":"Building & Trades",
            "subcategory":"Construction",
            "type":"Services"
        }
    ],
    "sg:phone":"+1 615 896 3545",
    "sg:postcode":"37130",
    "sg:province":"TN",
    "sg:tags":[
        "dry wall",
        "contractor"
    ],
    "wof:name":"Archie Weeks Drywall",
    "wof:placetype":"venue"
},
  "geometry": {"coordinates":[-86.36484799999999,35.82131],"type":"Point"}
}