{
  "type": "Feature",
  "properties": {
    "iso:country":"US",
    "sg:address":"107 Wayne St",
    "sg:city":"Columbia",
    "sg:classifiers":[
        {
            "category":"Building & Trades",
            "subcategory":"Construction",
            "type":"Services"
        }
    ],
    "sg:phone":"+1 931 381 1114",
    "sg:postcode":"38401",
    "sg:province":"TN",
    "sg:tags":[
        "maker",
        "cabinet"
    ],
    "wof:name":"K B Cabinets",
    "wof:placetype":"venue"
},
  "geometry": {"coordinates":[-87.03966,35.592995],"type":"Point"}
}