{
  "type": "Feature",
  "properties": {
    "iso:country":"US",
    "sg:address":"1555 Forrest Hill Rd",
    "sg:city":"Bolivar",
    "sg:classifiers":[
        {
            "category":"Building & Trades",
            "subcategory":"Construction",
            "type":"Services"
        }
    ],
    "sg:phone":"+1 731 658 4765",
    "sg:postcode":"38008",
    "sg:province":"TN",
    "sg:tags":[
        "contractor"
    ],
    "wof:name":"Forrest Hill Iron Works",
    "wof:placetype":"venue"
},
  "geometry": {"coordinates":[-88.86745,35.261804],"type":"Point"}
}