{
  "type": "Feature",
  "properties": {
    "iso:country":"US",
    "sg:address":"5078 Esbon Holland Rd",
    "sg:city":"Springfield",
    "sg:classifiers":[
        {
            "category":"Professional",
            "type":"Services"
        }
    ],
    "sg:phone":"+1 615 382 8112",
    "sg:postcode":"37172",
    "sg:province":"TN",
    "wof:name":"Office Services",
    "wof:placetype":"venue"
},
  "geometry": {"coordinates":[-86.868923,36.611673],"type":"Point"}
}