{
  "type": "Feature",
  "properties": {
    "iso:country":"US",
    "sg:address":"2110 Wilkinson Pike",
    "sg:city":"Maryville",
    "sg:classifiers":[
        {
            "category":"Personal",
            "type":"Services"
        }
    ],
    "sg:phone":"+1 865 984 9386",
    "sg:postcode":"37803",
    "sg:province":"TN",
    "wof:name":"Magic Time Farm",
    "wof:placetype":"venue"
},
  "geometry": {"coordinates":[-83.944256,35.741419],"type":"Point"}
}