{
  "type": "Feature",
  "properties": {
    "addr:full":"26 Century Blvd Nashville TN 37214",
    "addr:housenumber":"26",
    "addr:postcode":"37214",
    "addr:street":"Century Blvd",
    "iso:country":"US",
    "sg:address":"26 Century Blvd",
    "sg:city":"Nashville",
    "sg:classifiers":[
        {
            "category":"Insurance",
            "subcategory":"Insurance Agent",
            "type":"Services"
        }
    ],
    "sg:phone":"+1 615 872 3680",
    "sg:postcode":"37214",
    "sg:province":"TN",
    "sg:tags":[
        "broker"
    ],
    "sg:website":"www.stewartsmith.com",
    "wof:name":"Stewart Smith Southeast Inc",
    "wof:placetype":"venue"
},
  "geometry": {"coordinates":[-86.685861,36.147776],"type":"Point"}
}