{
  "type": "Feature",
  "properties": {
    "iso:country":"US",
    "sg:address":"810 Union St",
    "sg:city":"Shelbyville",
    "sg:classifiers":[
        {
            "category":"Building & Trades",
            "subcategory":"Construction",
            "type":"Services"
        }
    ],
    "sg:phone":"+1 931 685 0199",
    "sg:postcode":"37160",
    "sg:province":"TN",
    "sg:tags":[
        "designer",
        "contractor",
        "merchandise",
        "dealer",
        "pool",
        "swimming"
    ],
    "wof:name":"Dynamic Designs Pools & Spas",
    "wof:placetype":"venue"
},
  "geometry": {"coordinates":[-86.474732,35.496836],"type":"Point"}
}