{
  "type": "Feature",
  "properties": {
    "iso:country":"US",
    "sg:address":"5321 Cedar Heights Dr",
    "sg:city":"Knoxville",
    "sg:classifiers":[
        {
            "category":"Professional",
            "subcategory":"Advertising",
            "type":"Services"
        }
    ],
    "sg:phone":"+1 865 281 0454",
    "sg:postcode":"37912",
    "sg:province":"TN",
    "sg:tags":[
        "distribution"
    ],
    "wof:name":"T & S Distributing Inc",
    "wof:placetype":"venue"
},
  "geometry": {"coordinates":[-83.96444,36.023588],"type":"Point"}
}