{
  "type": "Feature",
  "properties": {
    "iso:country":"US",
    "sg:address":"1708 Winchester Rd",
    "sg:city":"Memphis",
    "sg:classifiers":[
        {
            "category":"Autos & Motor Vehicles",
            "subcategory":"Fuel & Gas Station",
            "type":"Retail Goods"
        }
    ],
    "sg:phone":"+1 901 345 0352",
    "sg:postcode":"38116",
    "sg:province":"TN",
    "sg:tags":[
        "oil"
    ],
    "wof:name":"Shell",
    "wof:placetype":"venue"
},
  "geometry": {"coordinates":[-90.005354,35.053779],"type":"Point"}
}