{
  "type": "Feature",
  "properties": {
    "iso:country":"US",
    "sg:address":"1000 Market St",
    "sg:city":"Chattanooga",
    "sg:classifiers":[
        {
            "category":"Professional",
            "subcategory":"Lawyer & Legal Services",
            "type":"Services"
        }
    ],
    "sg:phone":"+1 423 756 1841",
    "sg:postcode":"37402",
    "sg:province":"TN",
    "sg:tags":[
        "attorney",
        "criminal",
        "law"
    ],
    "wof:name":"Dupree, Charles P",
    "wof:placetype":"venue"
},
  "geometry": {"coordinates":[-85.30941,35.044849],"type":"Point"}
}