{
  "type": "Feature",
  "properties": {
    "addr:full":"65 Horseshoe Bend Rd Elmwood TN 38560",
    "addr:housenumber":"65",
    "addr:postcode":"38560",
    "addr:street":"Horseshoe Bend Rd",
    "iso:country":"US",
    "sg:address":"65 Horseshoe Bend Rd",
    "sg:city":"Elmwood",
    "sg:classifiers":[
        {
            "category":"Professional",
            "subcategory":"Management & Consulting",
            "type":"Services"
        }
    ],
    "sg:phone":"+1 615 735 9358",
    "sg:postcode":"38560",
    "sg:province":"TN",
    "wof:name":"Wiser Chice Osha Law Cmpliance",
    "wof:placetype":"venue"
},
  "geometry": {"coordinates":[-85.887596,36.245389],"type":"Point"}
}