{
  "type": "Feature",
  "properties": {
    "iso:country":"US",
    "sg:address":"4424 Northgate Dr",
    "sg:city":"Knoxville",
    "sg:classifiers":[
        {
            "category":"Wholesale",
            "subcategory":"Sporting Goods",
            "type":"Manufacturing & Wholesale Goods"
        }
    ],
    "sg:phone":"+1 865 922 9602",
    "sg:postcode":"37938",
    "sg:province":"TN",
    "sg:tags":[
        "product",
        "golf"
    ],
    "wof:name":"BOAC Inc",
    "wof:placetype":"venue"
},
  "geometry": {"coordinates":[-83.929335,36.089472],"type":"Point"}
}