{
  "type": "Feature",
  "properties": {
    "iso:country":"US",
    "sg:address":"385 Kimball Crossing Dr",
    "sg:city":"Jasper",
    "sg:classifiers":[
        {
            "category":"Restaurant",
            "type":"Food & Drink"
        }
    ],
    "sg:menulink":"http://www.allmenus.com/tn/monteagle-south-pittsburg/166298-arbys/menu/",
    "sg:phone":"+1 615 837 7892",
    "sg:postcode":"37347",
    "sg:province":"TN",
    "sg:tags":[
        "burger",
        "american"
    ],
    "wof:name":"Arby's",
    "wof:placetype":"venue"
},
  "geometry": {"coordinates":[-85.685599,35.040807],"type":"Point"}
}