{
  "type": "Feature",
  "properties": {
    "iso:country":"US",
    "sg:address":"13196 Hwy 70 N",
    "sg:city":"Crossville",
    "sg:classifiers":[
        {
            "category":"Food & Beverages",
            "subcategory":"Groceries & Convenience Stores",
            "type":"Retail Goods"
        }
    ],
    "sg:phone":"+1 931 277 5910",
    "sg:postcode":"38571",
    "sg:province":"TN",
    "wof:name":"S & W Market & Deli",
    "wof:placetype":"venue"
},
  "geometry": {"coordinates":[-85.19872700000001,36.045803],"type":"Point"}
}