{
  "type": "Feature",
  "properties": {
    "iso:country":"US",
    "sg:address":"45 Vista Dr",
    "sg:city":"Chattanooga",
    "sg:classifiers":[
        {
            "category":"Building & Trades",
            "subcategory":"Cleaning & Sanitation",
            "type":"Services"
        }
    ],
    "sg:phone":"+1 423 697 0307",
    "sg:postcode":"37411",
    "sg:province":"TN",
    "sg:tags":[
        "maintenance"
    ],
    "wof:name":"Maids For You",
    "wof:placetype":"venue"
},
  "geometry": {"coordinates":[-85.24986699999999,35.022197],"type":"Point"}
}