{
  "type": "Feature",
  "properties": {
    "addr:full":"1905 S Church St Murfreesboro TN 37130",
    "addr:housenumber":"1905",
    "addr:postcode":"37130",
    "addr:street":"S Church St",
    "iso:country":"US",
    "sg:address":"1905 S Church St",
    "sg:city":"Murfreesboro",
    "sg:classifiers":[
        {
            "category":"Restaurant",
            "type":"Food & Drink"
        }
    ],
    "sg:phone":"+1 615 895 0955",
    "sg:postcode":"37130",
    "sg:province":"TN",
    "sg:tags":[
        "fast"
    ],
    "wof:name":"Wendys",
    "wof:placetype":"venue"
},
  "geometry": {"coordinates":[-86.39639699999999,35.814133],"type":"Point"}
}