{
  "type": "Feature",
  "properties": {
    "iso:country":"US",
    "sg:address":"1995 US Hwy 51 S",
    "sg:city":"Covington",
    "sg:classifiers":[
        {
            "category":"Health Services",
            "subcategory":"Doctor",
            "type":"Services"
        }
    ],
    "sg:phone":"+1 901 475 6607",
    "sg:postcode":"38019",
    "sg:province":"TN",
    "sg:tags":[
        "physician",
        "surgeon"
    ],
    "wof:name":"Richard Guerrant MD",
    "wof:placetype":"venue"
},
  "geometry": {"coordinates":[-89.67746200000001,35.534104],"type":"Point"}
}