{
  "type": "Feature",
  "properties": {
    "iso:country":"US",
    "sg:address":"6026 Granville Hwy",
    "sg:city":"Granville",
    "sg:classifiers":[
        {
            "category":"Social Services",
            "subcategory":"Adult Care",
            "type":"Services"
        }
    ],
    "sg:phone":"+1 931 653 4647",
    "sg:postcode":"38564",
    "sg:province":"TN",
    "sg:tags":[
        "organization",
        "senior",
        "citizen"
    ],
    "wof:name":"Granville Multi-Purpose Ctr",
    "wof:placetype":"venue"
},
  "geometry": {"coordinates":[-85.782715,36.276651],"type":"Point"}
}