{
  "type": "Feature",
  "properties": {
    "iso:country":"US",
    "sg:address":"3707 Doe Valley Cove",
    "sg:city":"Memphis",
    "sg:classifiers":[
        {
            "category":"Wholesale",
            "subcategory":"Vending Machines",
            "type":"Manufacturing & Wholesale Goods"
        }
    ],
    "sg:phone":"+1 901 372 5475",
    "sg:postcode":"38135",
    "sg:province":"TN",
    "sg:tags":[
        "operator",
        "automatic",
        "merchandising"
    ],
    "wof:name":"Custom Vending Services",
    "wof:placetype":"venue"
},
  "geometry": {"coordinates":[-89.833709,35.226328],"type":"Point"}
}