{
  "type": "Feature",
  "properties": {
    "iso:country":"US",
    "sg:address":"4724 Gann Store Rd",
    "sg:city":"Hixson",
    "sg:classifiers":[
        {
            "category":"Building & Trades",
            "subcategory":"Construction",
            "type":"Services"
        }
    ],
    "sg:phone":"+1 423 876 0076",
    "sg:postcode":"37343",
    "sg:province":"TN",
    "sg:tags":[
        "residential",
        "commercial"
    ],
    "wof:name":"Decor Weaver LLC",
    "wof:placetype":"venue"
},
  "geometry": {"coordinates":[-85.210922,35.118066],"type":"Point"}
}