{
  "type": "Feature",
  "properties": {
    "iso:country":"US",
    "sg:address":"1625 Brown Ave",
    "sg:city":"Cookeville",
    "sg:classifiers":[
        {
            "category":"Wholesale",
            "subcategory":"Electrical",
            "type":"Manufacturing & Wholesale Goods"
        }
    ],
    "sg:phone":"+1 931 528 7413",
    "sg:postcode":"38501",
    "sg:province":"TN",
    "sg:tags":[
        "elements",
        "electric",
        "heating"
    ],
    "wof:name":"Academy Industries Inc",
    "wof:placetype":"venue"
},
  "geometry": {"coordinates":[-85.488223,36.184651],"type":"Point"}
}