{
  "type": "Feature",
  "properties": {
    "iso:country":"US",
    "sg:address":"7214 Eastern Ave",
    "sg:city":"Germantown",
    "sg:classifiers":[
        {
            "category":"Professional",
            "subcategory":"Advertising",
            "type":"Services"
        }
    ],
    "sg:phone":"+1 901 363 1024",
    "sg:postcode":"38138",
    "sg:province":"TN",
    "sg:tags":[
        "counselor"
    ],
    "wof:name":"John Smiley Advertising Inc",
    "wof:placetype":"venue"
},
  "geometry": {"coordinates":[-89.821922,35.087614],"type":"Point"}
}