{
  "type": "Feature",
  "properties": {
    "iso:country":"US",
    "sg:address":"1827 Price Ave",
    "sg:city":"Knoxville",
    "sg:classifiers":[
        {
            "category":"Professional",
            "subcategory":"Computer Services",
            "type":"Services"
        }
    ],
    "sg:phone":"+1 865 609 8285",
    "sg:postcode":"37920",
    "sg:province":"TN",
    "sg:tags":[
        "datum"
    ],
    "wof:name":"Mainline Media",
    "wof:placetype":"venue"
},
  "geometry": {"coordinates":[-83.888126,35.950006],"type":"Point"}
}