{
  "type": "Feature",
  "properties": {
    "addr:full":"2436 Dogwood Trail Dr Germantown TN 38139",
    "addr:housenumber":"2436",
    "addr:postcode":"38139",
    "addr:street":"Dogwood Trail Dr",
    "iso:country":"US",
    "sg:address":"2436 Dogwood Trail Dr",
    "sg:city":"Germantown",
    "sg:classifiers":[
        {
            "category":"Wholesale",
            "subcategory":"Electrical",
            "type":"Manufacturing & Wholesale Goods"
        }
    ],
    "sg:phone":"+1 901 754 3269",
    "sg:postcode":"38139",
    "sg:province":"TN",
    "sg:tags":[
        "repair",
        "electronic"
    ],
    "wof:name":"Riverside Video Productions",
    "wof:placetype":"venue"
},
  "geometry": {"coordinates":[-89.77415000000001,35.083259],"type":"Point"}
}