{
  "type": "Feature",
  "properties": {
    "iso:country":"US",
    "sg:address":"1631 Decatur Pike",
    "sg:city":"Athens",
    "sg:classifiers":[
        {
            "category":"Shopping",
            "subcategory":"Clothing, Apparel, & Fashions",
            "type":"Retail Goods"
        }
    ],
    "sg:phone":"+1 423 746 4442",
    "sg:postcode":"37303",
    "sg:province":"TN",
    "sg:tags":[
        "infant",
        "wear"
    ],
    "wof:name":"Kiddie Go Round",
    "wof:placetype":"venue"
},
  "geometry": {"coordinates":[-84.624562,35.451135],"type":"Point"}
}