{
  "type": "Feature",
  "properties": {
    "iso:country":"US",
    "sg:address":"735 Ashwood Ave",
    "sg:city":"Lewisburg",
    "sg:classifiers":[
        {
            "category":"Organizations",
            "subcategory":"Labor Organization",
            "type":"Services"
        }
    ],
    "sg:phone":"+1 931 359 5170",
    "sg:postcode":"37091",
    "sg:province":"TN",
    "wof:name":"United Steelworkers of America",
    "wof:placetype":"venue"
},
  "geometry": {"coordinates":[-86.814131,35.439769],"type":"Point"}
}