{
  "type": "Feature",
  "properties": {
    "iso:country":"US",
    "sg:address":"3020 Baird St",
    "sg:city":"Milan",
    "sg:classifiers":[
        {
            "category":"Building & Trades",
            "subcategory":"Construction",
            "type":"Services"
        },
        {
            "category":"Shopping",
            "subcategory":"Computers & Home Electronics",
            "type":"Retail Goods"
        }
    ],
    "sg:phone":"+1 731 686 7554",
    "sg:postcode":"38358",
    "sg:province":"TN",
    "sg:tags":[
        "equipment",
        "satellite",
        "system",
        "antenna"
    ],
    "wof:name":"Antenna Beasley & Satellite",
    "wof:placetype":"venue"
},
  "geometry": {"coordinates":[-88.752987,35.917102],"type":"Point"}
}