{
  "type": "Feature",
  "properties": {
    "addr:full":"2806 Opryland Dr Nashville TN 37214",
    "addr:housenumber":"2806",
    "addr:postcode":"37214",
    "addr:street":"Opryland Dr",
    "iso:country":"US",
    "sg:address":"2806 Opryland Dr",
    "sg:city":"Nashville",
    "sg:classifiers":[
        {
            "category":"Shopping",
            "subcategory":"Musical Instruments",
            "type":"Retail Goods"
        }
    ],
    "sg:phone":"+1 615 316 6170",
    "sg:postcode":"37214",
    "sg:province":"TN",
    "sg:tags":[
        "music",
        "dealer"
    ],
    "wof:name":"Z Music Television",
    "wof:placetype":"venue"
},
  "geometry": {"coordinates":[-86.691639,36.209493],"type":"Point"}
}