{
  "type": "Feature",
  "properties": {
    "iso:country":"US",
    "sg:address":"650 E 1st South St",
    "sg:city":"Morristown",
    "sg:classifiers":[
        {
            "category":"Home & Garden",
            "subcategory":"Building Materials",
            "type":"Retail Goods"
        },
        {
            "category":"Retail",
            "subcategory":"Auto Repair",
            "type":"Services"
        }
    ],
    "sg:phone":"+1 423 586 7055",
    "sg:postcode":"37813",
    "sg:province":"TN",
    "sg:tags":[
        "glass",
        "window",
        "plate"
    ],
    "wof:name":"Tri State Auto Glass Inc",
    "wof:placetype":"venue"
},
  "geometry": {"coordinates":[-83.286467,36.215478],"type":"Point"}
}