{
  "type": "Feature",
  "properties": {
    "addr:full":"950 Rocky Oaks Trl Cordova TN 38018",
    "addr:housenumber":"950",
    "addr:postcode":"38018",
    "addr:street":"Rocky Oaks Trl",
    "iso:country":"US",
    "sg:address":"950 Rocky Oaks Trl",
    "sg:city":"Cordova",
    "sg:classifiers":[
        {
            "category":"Professional",
            "subcategory":"Lawyer & Legal Services",
            "type":"Services"
        }
    ],
    "sg:phone":"+1 901 754 2003",
    "sg:postcode":"38018",
    "sg:province":"TN",
    "wof:name":"Stanley J Kline",
    "wof:placetype":"venue"
},
  "geometry": {"coordinates":[-89.75551400000001,35.150904],"type":"Point"}
}