{
  "type": "Feature",
  "properties": {
    "iso:country":"US",
    "sg:address":"605 Littrell Rd",
    "sg:city":"Loretto",
    "sg:classifiers":[
        {
            "category":"Freight",
            "type":"Transportation"
        }
    ],
    "sg:phone":"+1 931 853 6198",
    "sg:postcode":"38469",
    "sg:province":"TN",
    "sg:tags":[
        "commercial",
        "storage"
    ],
    "wof:name":"Loretto Mini Storage",
    "wof:placetype":"venue"
},
  "geometry": {"coordinates":[-87.435248,35.05272],"type":"Point"}
}