{
  "type": "Feature",
  "properties": {
    "iso:country":"US",
    "sg:address":"4013 Highwood Dr",
    "sg:city":"Chattanooga",
    "sg:classifiers":[
        {
            "category":"Professional",
            "type":"Services"
        }
    ],
    "sg:phone":"+1 423 870 4791",
    "sg:postcode":"37415",
    "sg:province":"TN",
    "sg:tags":[
        "copy",
        "advertising",
        "writing"
    ],
    "wof:name":"Wright & Associates",
    "wof:placetype":"venue"
},
  "geometry": {"coordinates":[-85.253945,35.117361],"type":"Point"}
}