{
  "type": "Feature",
  "properties": {
    "iso:country":"US",
    "sg:address":"1107 Clairmonte Dr",
    "sg:city":"Franklin",
    "sg:classifiers":[
        {
            "category":"Building & Trades",
            "subcategory":"Construction",
            "type":"Services"
        }
    ],
    "sg:phone":"+1 615 791 4146",
    "sg:postcode":"37064",
    "sg:province":"TN",
    "sg:tags":[
        "house"
    ],
    "wof:name":"Radnor Homes",
    "wof:placetype":"venue"
},
  "geometry": {"coordinates":[-86.890396,35.927266],"type":"Point"}
}