{
  "type": "Feature",
  "properties": {
    "addr:full":"607 N Highland Ave Jackson TN 38301",
    "addr:housenumber":"607",
    "addr:postcode":"38301",
    "addr:street":"N Highland Ave",
    "iso:country":"US",
    "sg:address":"607 N Highland Ave",
    "sg:city":"Jackson",
    "sg:classifiers":[
        {
            "category":"Social Services",
            "type":"Services"
        }
    ],
    "sg:phone":"+1 731 425 4003",
    "sg:postcode":"38301",
    "sg:province":"TN",
    "sg:tags":[
        "shelter",
        "homeless"
    ],
    "wof:name":"Jocoa Arlington House",
    "wof:placetype":"venue"
},
  "geometry": {"coordinates":[-88.818995,35.626074],"type":"Point"}
}