{
  "type": "Feature",
  "properties": {
    "addr:full":"200 Manufacturers Rd Chattanooga TN 37405",
    "addr:housenumber":"200",
    "addr:postcode":"37405",
    "addr:street":"Manufacturers Rd",
    "iso:country":"US",
    "sg:address":"200 Manufacturers Rd",
    "sg:city":"Chattanooga",
    "sg:classifiers":[
        {
            "category":"Real Estate",
            "subcategory":"Real Estate Operator",
            "type":"Services"
        }
    ],
    "sg:phone":"+1 423 752 3211",
    "sg:postcode":"37405",
    "sg:province":"TN",
    "sg:tags":[
        "condominium"
    ],
    "wof:name":"One North Shr Condominium LLC",
    "wof:placetype":"venue"
},
  "geometry": {"coordinates":[-85.314735,35.062164],"type":"Point"}
}