{
  "type": "Feature",
  "properties": {
    "addr:full":"8423 Finger Rd Knoxville TN 37920",
    "addr:postcode":"8423;37920",
    "addr:street":"Finger Rd",
    "iso:country":"US",
    "sg:address":"8423 Finger Rd",
    "sg:city":"Knoxville",
    "sg:classifiers":[
        {
            "category":"Building & Trades",
            "subcategory":"Construction",
            "type":"Services"
        }
    ],
    "sg:phone":"+1 865 579 3023",
    "sg:postcode":"37920",
    "sg:province":"TN",
    "sg:tags":[
        "house"
    ],
    "wof:name":"J&E Maintenance",
    "wof:placetype":"venue"
},
  "geometry": {"coordinates":[-83.77150899999999,35.921033],"type":"Point"}
}