{
  "type": "Feature",
  "properties": {
    "iso:country":"US",
    "sg:address":"12035 Macon Rd",
    "sg:city":"Collierville",
    "sg:classifiers":[
        {
            "category":"Professional",
            "subcategory":"Computer Services",
            "type":"Services"
        }
    ],
    "sg:phone":"+1 803 644 4500",
    "sg:postcode":"38017",
    "sg:province":"TN",
    "sg:tags":[
        "design",
        "system"
    ],
    "wof:name":"Alchemi Unlimited",
    "wof:placetype":"venue"
},
  "geometry": {"coordinates":[-89.66357000000001,35.15919],"type":"Point"}
}