{
  "type": "Feature",
  "properties": {
    "iso:country":"US",
    "sg:address":"3669 N Watkins St",
    "sg:city":"Memphis",
    "sg:classifiers":[
        {
            "category":"Retail",
            "subcategory":"Auto Repair",
            "type":"Services"
        }
    ],
    "sg:phone":"+1 901 353 3677",
    "sg:postcode":"38127",
    "sg:province":"TN",
    "sg:tags":[
        "transmission",
        "repairing",
        "automobile"
    ],
    "wof:name":"Landons Pro One Transmission",
    "wof:placetype":"venue"
},
  "geometry": {"coordinates":[-90.003122,35.225716],"type":"Point"}
}