{
  "type": "Feature",
  "properties": {
    "iso:country":"US",
    "sg:address":"1036 Blinken St",
    "sg:city":"Knoxville",
    "sg:classifiers":[
        {
            "category":"Autos & Motor Vehicles",
            "subcategory":"Auto Supplies",
            "type":"Retail Goods"
        }
    ],
    "sg:phone":"+1 865 966 5095",
    "sg:postcode":"37932",
    "sg:province":"TN",
    "sg:tags":[
        "automobile",
        "parts"
    ],
    "wof:name":"Power Source USA",
    "wof:placetype":"venue"
},
  "geometry": {"coordinates":[-84.137912,35.926938],"type":"Point"}
}