{
  "type": "Feature",
  "properties": {
    "iso:country":"US",
    "sg:address":"29 T J Scott Rd",
    "sg:city":"Milan",
    "sg:classifiers":[
        {
            "category":"Manufacturing",
            "subcategory":"Tools & Machinery",
            "type":"Manufacturing & Wholesale Goods"
        }
    ],
    "sg:phone":"+1 731 686 0885",
    "sg:postcode":"38358",
    "sg:province":"TN",
    "sg:tags":[
        "die",
        "stampings",
        "metal",
        "mfg"
    ],
    "wof:name":"Nance Tool & Die Inc",
    "wof:placetype":"venue"
},
  "geometry": {"coordinates":[-88.838008,35.938049],"type":"Point"}
}