{
  "type": "Feature",
  "properties": {
    "addr:full":"2991 S 3rd St Memphis TN 38109",
    "addr:housenumber":"2991",
    "addr:postcode":"38109",
    "addr:street":"S 3Rd St",
    "iso:country":"US",
    "sg:address":"2991 S 3rd St",
    "sg:city":"Memphis",
    "sg:classifiers":[
        {
            "category":"Travel",
            "subcategory":"Hotels & Motels",
            "type":"Entertainment"
        }
    ],
    "sg:phone":"+1 901 344 9457",
    "sg:postcode":"38109",
    "sg:province":"TN",
    "sg:tags":[
        "operation"
    ],
    "wof:name":"Patel Bharat",
    "wof:placetype":"venue"
},
  "geometry": {"coordinates":[-90.058171,35.073468],"type":"Point"}
}