{
  "type": "Feature",
  "properties": {
    "iso:country":"US",
    "sg:address":"1214 Cerro Gordo Rd",
    "sg:city":"Jackson",
    "sg:classifiers":[
        {
            "category":"Organizations",
            "subcategory":"Religious Organization",
            "type":"Services"
        }
    ],
    "sg:phone":"+1 731 422 4871",
    "sg:postcode":"38301",
    "sg:province":"TN",
    "wof:name":"Cerro Gordo Child Dev Ctr",
    "wof:placetype":"venue"
},
  "geometry": {"coordinates":[-88.899439,35.579486],"type":"Point"}
}