{
  "type": "Feature",
  "properties": {
    "addr:full":"3314 Scheibler Rd Memphis TN 38128",
    "addr:housenumber":"3314",
    "addr:postcode":"38128",
    "addr:street":"Scheibler Rd",
    "iso:country":"US",
    "sg:address":"3314 Scheibler Rd",
    "sg:city":"Memphis",
    "sg:classifiers":[
        {
            "category":"Freight",
            "type":"Transportation"
        }
    ],
    "sg:phone":"+1 901 373 9358",
    "sg:postcode":"38128",
    "sg:province":"TN",
    "sg:tags":[
        "trucking"
    ],
    "wof:name":"Tri-State Delivery Inc",
    "wof:placetype":"venue"
},
  "geometry": {"coordinates":[-89.90696800000001,35.215749],"type":"Point"}
}