{
  "type": "Feature",
  "properties": {
    "iso:country":"US",
    "sg:address":"2131 Bandywood Dr",
    "sg:city":"Nashville",
    "sg:classifiers":[
        {
            "category":"Retail",
            "subcategory":"Repair Shop",
            "type":"Services"
        }
    ],
    "sg:phone":"+1 615 383 1043",
    "sg:postcode":"37215",
    "sg:province":"TN",
    "sg:tags":[
        "watch"
    ],
    "wof:name":"Nashville Watch Co",
    "wof:placetype":"venue"
},
  "geometry": {"coordinates":[-86.818963,36.104935],"type":"Point"}
}