{
  "type": "Feature",
  "properties": {
    "iso:country":"US",
    "sg:address":"2636 Muddy Pond Rd",
    "sg:city":"Monterey",
    "sg:classifiers":[
        {
            "category":"Travel",
            "subcategory":"Campground",
            "type":"Entertainment"
        }
    ],
    "sg:phone":"+1 931 445 3579",
    "sg:postcode":"38574",
    "sg:province":"TN",
    "sg:tags":[
        "camp"
    ],
    "wof:name":"Camp Monterey Inc",
    "wof:placetype":"venue"
},
  "geometry": {"coordinates":[-85.15297099999999,36.153659],"type":"Point"}
}