{
  "type": "Feature",
  "properties": {
    "iso:country":"US",
    "sg:address":"3444 N Fountaincrest Dr",
    "sg:city":"Knoxville",
    "sg:classifiers":[
        {
            "category":"Professional",
            "type":"Services"
        }
    ],
    "sg:phone":"+1 865 922 5949",
    "sg:postcode":"37918",
    "sg:province":"TN",
    "wof:name":"Just Bead It",
    "wof:placetype":"venue"
},
  "geometry": {"coordinates":[-83.94136,36.074104],"type":"Point"}
}