{
  "type": "Feature",
  "properties": {
    "iso:country":"US",
    "sg:address":"5157 Cedar Church Ln",
    "sg:city":"Greenback",
    "sg:classifiers":[
        {
            "category":"Building & Trades",
            "subcategory":"Construction",
            "type":"Services"
        }
    ],
    "sg:phone":"+1 865 856 6474",
    "sg:postcode":"37742",
    "sg:province":"TN",
    "sg:tags":[
        "house"
    ],
    "wof:name":"Smoky Branch Log Homes",
    "wof:placetype":"venue"
},
  "geometry": {"coordinates":[-84.10975500000001,35.676291],"type":"Point"}
}