{
  "type": "Feature",
  "properties": {
    "addr:full":"2769 Wolfcreek Pkwy Bartlett TN 38133",
    "addr:housenumber":"2769",
    "addr:postcode":"38133",
    "addr:street":"Wolfcreek Pkwy",
    "iso:country":"US",
    "sg:address":"2769 Wolfcreek Pkwy",
    "sg:city":"Bartlett",
    "sg:classifiers":[
        {
            "category":"Restaurant",
            "type":"Food & Drink"
        }
    ],
    "sg:phone":"+1 901 384 9080",
    "sg:postcode":"38133",
    "sg:province":"TN",
    "sg:tags":[
        "eating"
    ],
    "wof:name":"Red Sun Buffet",
    "wof:placetype":"venue"
},
  "geometry": {"coordinates":[-89.79458700000001,35.202443],"type":"Point"}
}