{
  "type": "Feature",
  "properties": {
    "iso:country":"US",
    "sg:address":"2001 E 3rd St",
    "sg:city":"Chattanooga",
    "sg:classifiers":[
        {
            "category":"Shopping",
            "subcategory":"Clothing, Apparel, & Fashions",
            "type":"Retail Goods"
        }
    ],
    "sg:phone":"+1 423 698 5749",
    "sg:postcode":"37404",
    "sg:province":"TN",
    "sg:tags":[
        "apparel",
        "clothing",
        "boys'",
        "women's"
    ],
    "wof:name":"Mc Daniel Outlet",
    "wof:placetype":"venue"
},
  "geometry": {"coordinates":[-85.27057600000001,35.040379],"type":"Point"}
}