{
  "type": "Feature",
  "properties": {
    "addr:full":"10161 Dayton Pike Soddy Daisy TN 37379",
    "addr:housenumber":"10161",
    "addr:postcode":"37379",
    "addr:street":"Dayton Pike",
    "iso:country":"US",
    "sg:address":"10161 Dayton Pike",
    "sg:city":"Soddy Daisy",
    "sg:classifiers":[
        {
            "category":"Building & Trades",
            "subcategory":"Equipment Rental",
            "type":"Services"
        }
    ],
    "sg:phone":"+1 423 332 5712",
    "sg:postcode":"37379",
    "sg:province":"TN",
    "sg:tags":[
        "leasing",
        "furniture"
    ],
    "wof:name":"American Rentals Inc",
    "wof:placetype":"venue"
},
  "geometry": {"coordinates":[-85.181251,35.255267],"type":"Point"}
}