{
  "type": "Feature",
  "properties": {
    "addr:full":"1425 N Highland Ave Jackson TN 38301",
    "addr:housenumber":"1425",
    "addr:postcode":"38301",
    "addr:street":"N Highland Ave",
    "iso:country":"US",
    "sg:address":"1425 N Highland Ave",
    "sg:city":"Jackson",
    "sg:classifiers":[
        {
            "category":"Shopping",
            "subcategory":"Tobacco",
            "type":"Retail Goods"
        }
    ],
    "sg:phone":"+1 731 422 6660",
    "sg:postcode":"38301",
    "sg:province":"TN",
    "sg:tags":[
        "cigarette",
        "cigar",
        "dealer"
    ],
    "wof:name":"Quick Stop Mini Market",
    "wof:placetype":"venue"
},
  "geometry": {"coordinates":[-88.824974,35.637938],"type":"Point"}
}