{
  "type": "Feature",
  "properties": {
    "iso:country":"US",
    "sg:address":"695 W Poplar Ave",
    "sg:city":"Collierville",
    "sg:classifiers":[
        {
            "category":"Shopping",
            "subcategory":"Florist",
            "type":"Retail Goods"
        }
    ],
    "sg:phone":"+1 901 853 5103",
    "sg:postcode":"38017",
    "sg:province":"TN",
    "wof:name":"From The Heart",
    "wof:placetype":"venue"
},
  "geometry": {"coordinates":[-89.686117,35.045968],"type":"Point"}
}