{
  "type": "Feature",
  "properties": {
    "iso:country":"US",
    "sg:address":"6311 Kingston Pike Ste 1E",
    "sg:city":"Knoxville",
    "sg:classifiers":[
        {
            "category":"Personal",
            "subcategory":"Massage",
            "type":"Services"
        },
        {
            "category":"Health Services",
            "subcategory":"Hospital",
            "type":"Services"
        },
        {
            "category":"Health Services",
            "subcategory":"Health Practitioner",
            "type":"Services"
        },
        {
            "category":"Health Services",
            "subcategory":"Clinic",
            "type":"Services"
        }
    ],
    "sg:phone":"+1 865 909 9998",
    "sg:postcode":"37919",
    "sg:province":"TN",
    "sg:tags":[
        "therapist",
        "therapy",
        "treatment",
        "sleep",
        "disorders-information",
        "physical"
    ],
    "wof:name":"The Touch Therapy Center",
    "wof:placetype":"venue"
},
  "geometry": {"coordinates":[-84.006604,35.932053],"type":"Point"}
}