{
  "type": "Feature",
  "properties": {
    "addr:full":"1005 E Broadway St Lenoir City TN 37771",
    "addr:housenumber":"1005",
    "addr:postcode":"37771",
    "addr:street":"E Broadway St",
    "iso:country":"US",
    "sg:address":"1005 E Broadway St",
    "sg:city":"Lenoir City",
    "sg:classifiers":[
        {
            "category":"Health Services",
            "subcategory":"Health Practitioner",
            "type":"Services"
        }
    ],
    "sg:phone":"+1 865 988 9004",
    "sg:postcode":"37771",
    "sg:province":"TN",
    "wof:name":"A Healthy Life Chiropractic",
    "wof:placetype":"venue"
},
  "geometry": {"coordinates":[-84.256957,35.796942],"type":"Point"}
}