{
  "type": "Feature",
  "properties": {
    "iso:country":"US",
    "sg:address":"150 Market Place Blvd",
    "sg:city":"Knoxville",
    "sg:classifiers":[
        {
            "category":"Banks & Credit Unions",
            "subcategory":"Bank",
            "type":"Services"
        }
    ],
    "sg:phone":"+1 865 531 1773",
    "sg:postcode":"37922",
    "sg:province":"TN",
    "sg:tags":[
        "loan",
        "mortgage",
        "real estate"
    ],
    "sg:website":"www.nationalcitymortgage.com",
    "wof:name":"National City Mortgage Co",
    "wof:placetype":"venue"
},
  "geometry": {"coordinates":[-84.091736,35.912748],"type":"Point"}
}