{
  "type": "Feature",
  "properties": {
    "iso:country":"US",
    "sg:address":"108 Cotton Gin Ct",
    "sg:city":"Brentwood",
    "sg:classifiers":[
        {
            "category":"Autos & Motor Vehicles",
            "subcategory":"Automobile Sales",
            "type":"Retail Goods"
        }
    ],
    "sg:phone":"+1 615 781 1069",
    "sg:postcode":"37027",
    "sg:province":"TN",
    "wof:name":"Mercury Sales Inc",
    "wof:placetype":"venue"
},
  "geometry": {"coordinates":[-86.756007,36.023245],"type":"Point"}
}