{
  "type": "Feature",
  "properties": {
    "iso:country":"US",
    "sg:address":"704 Perry St",
    "sg:city":"Athens",
    "sg:classifiers":[
        {
            "category":"Building & Trades",
            "subcategory":"Construction",
            "type":"Services"
        }
    ],
    "sg:phone":"+1 423 745 0097",
    "sg:postcode":"37303",
    "sg:province":"TN",
    "sg:tags":[
        "house"
    ],
    "wof:name":"Jerry Demay Builder",
    "wof:placetype":"venue"
},
  "geometry": {"coordinates":[-84.58162299999999,35.430734],"type":"Point"}
}