{
  "type": "Feature",
  "properties": {
    "iso:country":"US",
    "sg:address":"309 Bybee Branch Rd",
    "sg:city":"Mc Minnville",
    "sg:classifiers":[
        {
            "category":"Real Estate",
            "subcategory":"Real Estate Operator",
            "type":"Services"
        }
    ],
    "sg:phone":"+1 931 473 8783",
    "sg:postcode":"37110",
    "sg:province":"TN",
    "sg:tags":[
        "apartment"
    ],
    "wof:name":"Buckingham Apartments",
    "wof:placetype":"venue"
},
  "geometry": {"coordinates":[-85.79913999999999,35.706743],"type":"Point"}
}