{
  "type": "Feature",
  "properties": {
    "iso:country":"US",
    "sg:address":"1208 Northgate Business Pkwy",
    "sg:city":"Madison",
    "sg:classifiers":[
        {
            "category":"Communications",
            "subcategory":"Film & Video Production",
            "type":"Services"
        }
    ],
    "sg:phone":"+1 615 860 4995",
    "sg:postcode":"37115",
    "sg:province":"TN",
    "sg:tags":[
        "motion",
        "picture"
    ],
    "wof:name":"Rtm Productions Inc",
    "wof:placetype":"venue"
},
  "geometry": {"coordinates":[-86.69207900000001,36.28521],"type":"Point"}
}