{
  "type": "Feature",
  "properties": {
    "iso:country":"US",
    "sg:address":"4009 Hillsboro Pike",
    "sg:city":"Nashville",
    "sg:classifiers":[
        {
            "category":"Shopping",
            "subcategory":"Clothing, Apparel, & Fashions",
            "type":"Retail Goods"
        }
    ],
    "sg:phone":"+1 615 298 2188",
    "sg:postcode":"37215",
    "sg:province":"TN",
    "wof:name":"Cotton Mill Collection",
    "wof:placetype":"venue"
},
  "geometry": {"coordinates":[-86.815265,36.104363],"type":"Point"}
}