{
  "type": "Feature",
  "properties": {
    "iso:country":"US",
    "sg:address":"3805 Rolland Rd",
    "sg:city":"Nashville",
    "sg:classifiers":[
        {
            "category":"Professional",
            "subcategory":"Management & Consulting",
            "type":"Services"
        }
    ],
    "sg:phone":"+1 615 292 5804",
    "sg:postcode":"37205",
    "sg:province":"TN",
    "wof:name":"Alliance",
    "wof:placetype":"venue"
},
  "geometry": {"coordinates":[-86.829314,36.127984],"type":"Point"}
}