{
  "type": "Feature",
  "properties": {
    "iso:country":"US",
    "sg:address":"4005 Fountain Valley Dr",
    "sg:city":"Knoxville",
    "sg:classifiers":[
        {
            "category":"Health Services",
            "subcategory":"Hospital",
            "type":"Services"
        }
    ],
    "sg:phone":"+1 865 925 9000",
    "sg:postcode":"37918",
    "sg:province":"TN",
    "wof:name":"University Of Tn Medical Ctr",
    "wof:placetype":"venue"
},
  "geometry": {"coordinates":[-83.92558699999999,36.069531],"type":"Point"}
}