{
  "type": "Feature",
  "properties": {
    "iso:country":"US",
    "sg:address":"920 Woodmont Blvd",
    "sg:city":"Nashville",
    "sg:classifiers":[
        {
            "category":"Retail",
            "subcategory":"Portrait Studio",
            "type":"Services"
        },
        {
            "category":"Professional",
            "subcategory":"Art Services",
            "type":"Services"
        }
    ],
    "sg:phone":"+1 615 292 2025",
    "sg:postcode":"37204",
    "sg:province":"TN",
    "sg:tags":[
        "photographer",
        "photo"
    ],
    "wof:name":"Photiques Wedding Photography",
    "wof:placetype":"venue"
},
  "geometry": {"coordinates":[-86.783647,36.11049],"type":"Point"}
}