{
  "type": "Feature",
  "properties": {
    "iso:country":"US",
    "sg:address":"2745 State Hwy 193",
    "sg:city":"Collierville",
    "sg:classifiers":[
        {
            "category":"Personal",
            "type":"Services"
        }
    ],
    "sg:phone":"+1 901 854 0609",
    "sg:postcode":"38017",
    "sg:province":"TN",
    "sg:tags":[
        "wedding",
        "chapel"
    ],
    "wof:name":"Savannah Woods Plantation",
    "wof:placetype":"venue"
},
  "geometry": {"coordinates":[-89.592482,35.152534],"type":"Point"}
}