{
  "type": "Feature",
  "properties": {
    "addr:full":"257 Watauga Rd Elizabethton TN 37643",
    "addr:housenumber":"257",
    "addr:postcode":"37643",
    "addr:street":"Watauga Rd",
    "iso:country":"US",
    "sg:address":"257 Watauga Rd",
    "sg:city":"Elizabethton",
    "sg:classifiers":[
        {
            "category":"Retail",
            "subcategory":"Repair Shop",
            "type":"Services"
        }
    ],
    "sg:phone":"+1 423 547 3014",
    "sg:postcode":"37643",
    "sg:province":"TN",
    "sg:tags":[
        "electrical"
    ],
    "wof:name":"Harmons Appliance",
    "wof:placetype":"venue"
},
  "geometry": {"coordinates":[-82.237719,36.358577],"type":"Point"}
}