{
  "type": "Feature",
  "properties": {
    "iso:country":"US",
    "sg:address":"2804 W Andrew Johnson Hwy",
    "sg:city":"Morristown",
    "sg:classifiers":[
        {
            "category":"Shopping",
            "subcategory":"Discount & Variety Stores",
            "type":"Retail Goods"
        }
    ],
    "sg:phone":"+1 423 585 0445",
    "sg:postcode":"37814",
    "sg:province":"TN",
    "wof:name":"Dollar General",
    "wof:placetype":"venue"
},
  "geometry": {"coordinates":[-83.333417,36.201643],"type":"Point"}
}