{
  "type": "Feature",
  "properties": {
    "addr:full":"7114 Blue Springs Pkwy Mosheim TN 37818",
    "addr:housenumber":"7114",
    "addr:postcode":"37818",
    "addr:street":"Blue Springs Pkwy",
    "iso:country":"US",
    "sg:address":"7114 Blue Springs Pkwy",
    "sg:city":"Mosheim",
    "sg:classifiers":[
        {
            "category":"Personal",
            "subcategory":"Beauty Salon",
            "type":"Services"
        }
    ],
    "sg:phone":"+1 423 422 0024",
    "sg:postcode":"37818",
    "sg:province":"TN",
    "sg:tags":[
        "shop"
    ],
    "wof:name":"A J's Hair Salon",
    "wof:placetype":"venue"
},
  "geometry": {"coordinates":[-82.946209,36.19723],"type":"Point"}
}