{
  "type": "Feature",
  "properties": {
    "iso:country":"US",
    "sg:address":"2488 Birch Tree Dr",
    "sg:city":"Germantown",
    "sg:classifiers":[
        {
            "category":"Professional",
            "subcategory":"Business Services",
            "type":"Services"
        }
    ],
    "sg:phone":"+1 901 755 7452",
    "sg:postcode":"38138",
    "sg:province":"TN",
    "wof:name":"Nncy P Adair Dsgner/Art Conslt",
    "wof:placetype":"venue"
},
  "geometry": {"coordinates":[-89.82297800000001,35.081751],"type":"Point"}
}