{
  "type": "Feature",
  "properties": {
    "iso:country":"US",
    "sg:address":"1750 E Brooks Rd",
    "sg:city":"Memphis",
    "sg:classifiers":[
        {
            "category":"Real Estate",
            "subcategory":"Real Estate Operator",
            "type":"Services"
        }
    ],
    "sg:phone":"+1 901 346 6300",
    "sg:postcode":"38109",
    "sg:province":"TN",
    "sg:tags":[
        "building",
        "apartment"
    ],
    "wof:name":"Brooks Realty Partners LP",
    "wof:placetype":"venue"
},
  "geometry": {"coordinates":[-90.00525399999999,35.061058],"type":"Point"}
}