{
  "type": "Feature",
  "properties": {
    "addr:full":"1180 Orthodox Way Liberty TN 37095",
    "addr:housenumber":"1180",
    "addr:postcode":"37095",
    "addr:street":"Orthodox Way",
    "iso:country":"US",
    "sg:address":"1180 Orthodox Way",
    "sg:city":"Liberty",
    "sg:classifiers":[
        {
            "category":"Organizations",
            "subcategory":"Religious Organization",
            "type":"Services"
        }
    ],
    "sg:phone":"+1 615 536 5239",
    "sg:postcode":"37095",
    "sg:province":"TN",
    "sg:tags":[
        "church"
    ],
    "wof:name":"Agape Community Orthodox Chr",
    "wof:placetype":"venue"
},
  "geometry": {"coordinates":[-85.966847,35.95672],"type":"Point"}
}