{
  "type": "Feature",
  "properties": {
    "iso:country":"US",
    "sg:address":"504 Greenwood Ave",
    "sg:city":"Jackson",
    "sg:classifiers":[
        {
            "category":"Professional",
            "type":"Services"
        }
    ],
    "sg:phone":"+1 731 427 2043",
    "sg:postcode":"38301",
    "sg:province":"TN",
    "wof:name":"Ricky Flournoy",
    "wof:placetype":"venue"
},
  "geometry": {"coordinates":[-88.807041,35.633627],"type":"Point"}
}