{
  "type": "Feature",
  "properties": {
    "iso:country":"US",
    "sg:address":"1650 Cason Ln",
    "sg:city":"Murfreesboro",
    "sg:classifiers":[
        {
            "category":"Shopping",
            "subcategory":"Gifts & Souvenirs",
            "type":"Retail Goods"
        }
    ],
    "sg:phone":"+1 615 904 0029",
    "sg:postcode":"37128",
    "sg:province":"TN",
    "sg:tags":[
        "shop"
    ],
    "wof:name":"Afterthought Gifts",
    "wof:placetype":"venue"
},
  "geometry": {"coordinates":[-86.445701,35.816446],"type":"Point"}
}