{
  "type": "Feature",
  "properties": {
    "iso:country":"US",
    "sg:address":"969 McEvers Rd",
    "sg:city":"Memphis",
    "sg:classifiers":[
        {
            "category":"Retail",
            "subcategory":"Repair Shop",
            "type":"Services"
        }
    ],
    "sg:phone":"+1 901 761 2662",
    "sg:postcode":"38111",
    "sg:province":"TN",
    "wof:name":"Five Star Professional Svcs",
    "wof:placetype":"venue"
},
  "geometry": {"coordinates":[-89.933601,35.104612],"type":"Point"}
}