{
  "type": "Feature",
  "properties": {
    "iso:country":"US",
    "sg:address":"7345 Horton Hwy",
    "sg:city":"Greeneville",
    "sg:classifiers":[
        {
            "category":"Restaurant",
            "type":"Food & Drink"
        }
    ],
    "sg:phone":"+1 423 234 2417",
    "sg:postcode":"37745",
    "sg:province":"TN",
    "sg:tags":[
        "eating"
    ],
    "wof:name":"Baileyton Bar & Grill",
    "wof:placetype":"venue"
},
  "geometry": {"coordinates":[-82.83094199999999,36.336155],"type":"Point"}
}