{
  "type": "Feature",
  "properties": {
    "addr:full":"1374 Robinson Rd Old Hickory TN 37138",
    "addr:housenumber":"1374",
    "addr:postcode":"37138",
    "addr:street":"Robinson Rd",
    "iso:country":"US",
    "sg:address":"1374 Robinson Rd",
    "sg:city":"Old Hickory",
    "sg:classifiers":[
        {
            "category":"Food & Beverages",
            "subcategory":"Groceries & Convenience Stores",
            "type":"Retail Goods"
        }
    ],
    "sg:phone":"+1 615 847 3996",
    "sg:postcode":"37138",
    "sg:province":"TN",
    "wof:name":"HG Hill Food Stores",
    "wof:placetype":"venue"
},
  "geometry": {"coordinates":[-86.661857,36.262935],"type":"Point"}
}