{
  "type": "Feature",
  "properties": {
    "iso:country":"US",
    "sg:address":"407 Old Stone Bridge Rd",
    "sg:city":"Goodlettsville",
    "sg:classifiers":[
        {
            "category":"Wholesale",
            "subcategory":"Electrical",
            "type":"Manufacturing & Wholesale Goods"
        }
    ],
    "sg:phone":"+1 615 855 3027",
    "sg:postcode":"37072",
    "sg:province":"TN",
    "sg:tags":[
        "harness",
        "wire"
    ],
    "sg:website":"www.jcsinternational.com",
    "wof:name":"JCS Intl",
    "wof:placetype":"venue"
},
  "geometry": {"coordinates":[-86.716021,36.336782],"type":"Point"}
}