{
  "type": "Feature",
  "properties": {
    "addr:full":"160 S Broad St Lexington TN 38351",
    "addr:housenumber":"160",
    "addr:postcode":"38351",
    "addr:street":"S Broad St",
    "iso:country":"US",
    "sg:address":"160 S Broad St",
    "sg:city":"Lexington",
    "sg:classifiers":[
        {
            "category":"Government",
            "subcategory":"Post Office",
            "type":"Public Place"
        }
    ],
    "sg:phone":"+1 731 968 2446",
    "sg:postcode":"38351",
    "sg:province":"TN",
    "sg:tags":[
        "postal",
        "us"
    ],
    "wof:name":"US Post Office",
    "wof:placetype":"venue"
},
  "geometry": {"coordinates":[-88.39946999999999,35.646592],"type":"Point"}
}