{
  "type": "Feature",
  "properties": {
    "iso:country":"US",
    "sg:address":"806 Kingston St",
    "sg:city":"Lenoir City",
    "sg:classifiers":[
        {
            "category":"Wholesale",
            "subcategory":"Painting Supplies",
            "type":"Manufacturing & Wholesale Goods"
        }
    ],
    "sg:phone":"+1 865 986 2867",
    "sg:postcode":"37771",
    "sg:province":"TN",
    "sg:tags":[
        "hardware",
        "paint"
    ],
    "wof:name":"Jenkins E W Supply Company",
    "wof:placetype":"venue"
},
  "geometry": {"coordinates":[-84.271412,35.798577],"type":"Point"}
}