{
  "type": "Feature",
  "properties": {
    "addr:full":"1017 Beaver Rd Brighton TN 38058",
    "addr:housenumber":"1017",
    "addr:postcode":"38058",
    "addr:street":"Beaver Rd",
    "iso:country":"US",
    "sg:address":"1017 Beaver Rd",
    "sg:city":"Brighton",
    "sg:classifiers":[
        {
            "category":"Health Services",
            "subcategory":"Medical Lab",
            "type":"Services"
        }
    ],
    "sg:phone":"+1 901 837 1441",
    "sg:postcode":"38058",
    "sg:province":"TN",
    "sg:tags":[
        "laboratory",
        "dental"
    ],
    "wof:name":"Gillihan Dental Lab",
    "wof:placetype":"venue"
},
  "geometry": {"coordinates":[-89.81107900000001,35.462275],"type":"Point"}
}