{
  "type": "Feature",
  "properties": {
    "iso:country":"US",
    "sg:address":"540 Boiling Springs Rd",
    "sg:city":"Portland",
    "sg:classifiers":[
        {
            "category":"Farming",
            "subcategory":"Dairy Farm",
            "type":"Manufacturing & Wholesale Goods"
        }
    ],
    "sg:phone":"+1 615 325 3631",
    "sg:postcode":"37148",
    "sg:province":"TN",
    "wof:name":"Uppy Hills Dairy",
    "wof:placetype":"venue"
},
  "geometry": {"coordinates":[-86.512456,36.50551],"type":"Point"}
}