{
  "type": "Feature",
  "properties": {
    "iso:country":"US",
    "sg:address":"4690 Hungerford Rd",
    "sg:city":"Memphis",
    "sg:classifiers":[
        {
            "category":"Professional",
            "subcategory":"Management & Consulting",
            "type":"Services"
        }
    ],
    "sg:phone":"+1 901 363 9385",
    "sg:postcode":"38118",
    "sg:province":"TN",
    "wof:name":"Alliance Marketing",
    "wof:placetype":"venue"
},
  "geometry": {"coordinates":[-89.90645499999999,35.036132],"type":"Point"}
}