{
  "type": "Feature",
  "properties": {
    "iso:country":"US",
    "sg:address":"122 Reagan Rd",
    "sg:city":"Maryville",
    "sg:classifiers":[
        {
            "category":"Manufacturing",
            "subcategory":"Metals",
            "type":"Manufacturing & Wholesale Goods"
        }
    ],
    "sg:phone":"+1 865 983 1223",
    "sg:postcode":"37801",
    "sg:province":"TN",
    "sg:tags":[
        "steel"
    ],
    "wof:name":"Reagan Steel Co",
    "wof:placetype":"venue"
},
  "geometry": {"coordinates":[-84.03169,35.748503],"type":"Point"}
}