{
  "type": "Feature",
  "properties": {
    "iso:country":"US",
    "sg:address":"113 Porter St",
    "sg:city":"Murfreesboro",
    "sg:classifiers":[
        {
            "category":"Building & Trades",
            "subcategory":"Construction",
            "type":"Services"
        }
    ],
    "sg:phone":"+1 615 907 3822",
    "sg:postcode":"37127",
    "sg:province":"TN",
    "sg:tags":[
        "contractor"
    ],
    "wof:name":"Blue Feather Refinishing",
    "wof:placetype":"venue"
},
  "geometry": {"coordinates":[-86.395534,35.818384],"type":"Point"}
}