{
  "type": "Feature",
  "properties": {
    "iso:country":"US",
    "sg:address":"2739 Bartlett Blvd",
    "sg:city":"Memphis",
    "sg:classifiers":[
        {
            "category":"Personal",
            "subcategory":"Beauty Salon",
            "type":"Services"
        }
    ],
    "sg:phone":"+1 901 383 7761",
    "sg:postcode":"38134",
    "sg:province":"TN",
    "sg:website":"http://www.youriesalon.webs.com",
    "wof:name":"Yourie's Hair & Nail Salon",
    "wof:placetype":"venue"
},
  "geometry": {"coordinates":[-89.86729699999999,35.200441],"type":"Point"}
}