{
  "type": "Feature",
  "properties": {
    "addr:full":"253 Laboratory Rd Oak Ridge TN 37830",
    "addr:postcode":"37830",
    "addr:street":"Laboratory Rd",
    "iso:country":"US",
    "sg:address":"253 Laboratory Rd",
    "sg:city":"Oak Ridge",
    "sg:classifiers":[
        {
            "category":"Professional",
            "subcategory":"Engineering",
            "type":"Services"
        }
    ],
    "sg:phone":"+1 865 220 0590",
    "sg:postcode":"37830",
    "sg:province":"TN",
    "sg:tags":[
        "engineer"
    ],
    "wof:name":"Resource Engineering & Testing",
    "wof:placetype":"venue"
},
  "geometry": {"coordinates":[-84.234796,36.022956],"type":"Point"}
}