{
  "type": "Feature",
  "properties": {
    "iso:country":"US",
    "sg:address":"1700 McCaslin Rd",
    "sg:city":"Southside",
    "sg:phone":"+1 931 387 2315",
    "sg:postcode":"37171",
    "sg:province":"TN",
    "sg:tags":[
        "farm",
        "corn",
        "tobacco"
    ],
    "wof:name":"Ralph McCurdy",
    "wof:placetype":"venue"
},
  "geometry": {"coordinates":[-87.29601700000001,36.324937],"type":"Point"}
}