{
  "type": "Feature",
  "properties": {
    "iso:country":"US",
    "sg:address":"1444 Ray Burton Rd",
    "sg:city":"Lynchburg",
    "sg:classifiers":[
        {
            "category":"Travel",
            "subcategory":"Campground",
            "type":"Entertainment"
        }
    ],
    "sg:phone":"+1 931 759 9105",
    "sg:postcode":"37352",
    "sg:province":"TN",
    "sg:tags":[
        "camp"
    ],
    "wof:name":"TAG Inc",
    "wof:placetype":"venue"
},
  "geometry": {"coordinates":[-86.318169,35.265099],"type":"Point"}
}