{
  "type": "Feature",
  "properties": {
    "iso:country":"US",
    "sg:address":"131 Stephens St",
    "sg:city":"Benton",
    "sg:classifiers":[
        {
            "category":"Education",
            "subcategory":"School",
            "type":"Public Place"
        }
    ],
    "sg:phone":"+1 423 338 4506",
    "sg:postcode":"37307",
    "sg:province":"TN",
    "sg:website":"www.polkcountyschools.com",
    "wof:name":"Polk County Board Of Education",
    "wof:placetype":"venue"
},
  "geometry": {"coordinates":[-84.65442899999999,35.177421],"type":"Point"}
}