{
  "type": "Feature",
  "properties": {
    "iso:country":"US",
    "sg:address":"804 Olde Pioneer Trl",
    "sg:city":"Knoxville",
    "sg:classifiers":[
        {
            "category":"Professional",
            "subcategory":"Management & Consulting",
            "type":"Services"
        }
    ],
    "sg:phone":"+1 865 691 6121",
    "sg:postcode":"37923",
    "sg:province":"TN",
    "wof:name":"Joyce Cabe Consulting",
    "wof:placetype":"venue"
},
  "geometry": {"coordinates":[-84.06845199999999,35.899985],"type":"Point"}
}