{
  "type": "Feature",
  "properties": {
    "iso:country":"US",
    "sg:address":"3012 River Dr",
    "sg:city":"Nashville",
    "sg:classifiers":[
        {
            "category":"Banks & Credit Unions",
            "subcategory":"Investment Brokerage",
            "type":"Services"
        }
    ],
    "sg:phone":"+1 615 242 3785",
    "sg:postcode":"37218",
    "sg:province":"TN",
    "sg:tags":[
        "security"
    ],
    "wof:name":"Umoja Mutual Investments",
    "wof:placetype":"venue"
},
  "geometry": {"coordinates":[-86.83149899999999,36.192309],"type":"Point"}
}