{
  "type": "Feature",
  "properties": {
    "addr:full":"107 N Poplar St Dresden TN 38225",
    "addr:housenumber":"107",
    "addr:postcode":"38225",
    "addr:street":"N Poplar St",
    "iso:country":"US",
    "sg:address":"107 N Poplar St",
    "sg:city":"Dresden",
    "sg:classifiers":[
        {
            "category":"Restaurant",
            "type":"Food & Drink"
        }
    ],
    "sg:phone":"+1 731 364 5545",
    "sg:postcode":"38225",
    "sg:province":"TN",
    "sg:tags":[
        "pizza"
    ],
    "wof:name":"Pizza USA",
    "wof:placetype":"venue"
},
  "geometry": {"coordinates":[-88.70892000000001,36.291908],"type":"Point"}
}