{
  "type": "Feature",
  "properties": {
    "iso:country":"US",
    "sg:address":"227 Ward Cir",
    "sg:city":"Brentwood",
    "sg:classifiers":[
        {
            "category":"Social Services",
            "type":"Services"
        }
    ],
    "sg:phone":"+1 615 373 0443",
    "sg:postcode":"37027",
    "sg:province":"TN",
    "sg:tags":[
        "counselor",
        "marriage",
        "family"
    ],
    "wof:name":"Suzanne S Wilson",
    "wof:placetype":"venue"
},
  "geometry": {"coordinates":[-86.801889,36.033679],"type":"Point"}
}