{
  "type": "Feature",
  "properties": {
    "addr:full":"440 Hampton Cir Cookeville TN 38501",
    "addr:housenumber":"440",
    "addr:postcode":"38501",
    "addr:street":"Hampton Cir",
    "iso:country":"US",
    "sg:address":"440 Hampton Cir",
    "sg:city":"Cookeville",
    "sg:classifiers":[
        {
            "category":"Professional",
            "type":"Services"
        }
    ],
    "sg:phone":"+1 931 520 7511",
    "sg:postcode":"38501",
    "sg:province":"TN",
    "wof:name":"Snickerdoodles",
    "wof:placetype":"venue"
},
  "geometry": {"coordinates":[-85.491333,36.148922],"type":"Point"}
}