{
  "type": "Feature",
  "properties": {
    "iso:country":"US",
    "sg:address":"1535 W Andrew Johnson Hwy",
    "sg:city":"Greeneville",
    "sg:classifiers":[
        {
            "category":"Retail",
            "subcategory":"Auto Rental",
            "type":"Services"
        }
    ],
    "sg:phone":"+1 423 639 3595",
    "sg:postcode":"37745",
    "sg:province":"TN",
    "sg:tags":[
        "renting",
        "truck",
        "leasing"
    ],
    "wof:name":"H Haul Co 1535 W Andrews",
    "wof:placetype":"venue"
},
  "geometry": {"coordinates":[-82.849147,36.172519],"type":"Point"}
}