{
  "type": "Feature",
  "properties": {
    "iso:country":"US",
    "sg:address":"1123 3rd Ave N",
    "sg:city":"Nashville",
    "sg:classifiers":[
        {
            "category":"Organizations",
            "subcategory":"Labor Organization",
            "type":"Services"
        }
    ],
    "sg:phone":"+1 615 254 9468",
    "sg:postcode":"37208",
    "sg:province":"TN",
    "wof:name":"Painters and Glaziers Local Un",
    "wof:placetype":"venue"
},
  "geometry": {"coordinates":[-86.78527,36.175772],"type":"Point"}
}