{
  "type": "Feature",
  "properties": {
    "iso:country":"US",
    "sg:address":"701 Central Ave W",
    "sg:city":"Springfield",
    "sg:classifiers":[
        {
            "category":"Manufacturing",
            "subcategory":"Tobacco Products",
            "type":"Manufacturing & Wholesale Goods"
        }
    ],
    "sg:phone":"+1 615 384 4610",
    "sg:postcode":"37172",
    "sg:province":"TN",
    "wof:name":"Conwood Co LP",
    "wof:placetype":"venue"
},
  "geometry": {"coordinates":[-86.8959,36.502421],"type":"Point"}
}