{
  "type": "Feature",
  "properties": {
    "iso:country":"US",
    "sg:address":"5540 Hargrove Ridge Rd",
    "sg:city":"Franklin",
    "sg:classifiers":[
        {
            "category":"Utilities",
            "subcategory":"Refuse",
            "type":"Services"
        }
    ],
    "sg:phone":"+1 615 794 0460",
    "sg:postcode":"37064",
    "sg:province":"TN",
    "sg:tags":[
        "system"
    ],
    "wof:name":"Southall Sanitation",
    "wof:placetype":"venue"
},
  "geometry": {"coordinates":[-87.045035,35.920721],"type":"Point"}
}