{
  "type": "Feature",
  "properties": {
    "iso:country":"US",
    "sg:address":"2885 Bus Park Dr",
    "sg:city":"Memphis",
    "sg:classifiers":[
        {
            "category":"Wholesale",
            "subcategory":"Apparel",
            "type":"Manufacturing & Wholesale Goods"
        }
    ],
    "sg:phone":"+1 901 794 5173",
    "sg:postcode":"38118",
    "sg:province":"TN",
    "sg:tags":[
        "safety",
        "shoes"
    ],
    "wof:name":"Lehigh Safety Shoe Co",
    "wof:placetype":"venue"
},
  "geometry": {"coordinates":[-89.963645,35.07028],"type":"Point"}
}