{
  "type": "Feature",
  "properties": {
    "addr:full":"7670 Poplar Ave Germantown TN 38138",
    "addr:housenumber":"7670",
    "addr:postcode":"38138",
    "addr:street":"Poplar Ave",
    "iso:country":"US",
    "sg:address":"7670 Poplar Ave",
    "sg:city":"Germantown",
    "sg:classifiers":[
        {
            "category":"Shopping",
            "subcategory":"Department Store",
            "type":"Retail Goods"
        }
    ],
    "sg:phone":"+1 901 758 2822",
    "sg:postcode":"38138",
    "sg:province":"TN",
    "wof:name":"T J Maxx",
    "wof:placetype":"venue"
},
  "geometry": {"coordinates":[-89.80463899999999,35.090819],"type":"Point"}
}