{
  "type": "Feature",
  "properties": {
    "iso:country":"US",
    "sg:address":"5651 Frist Blvd",
    "sg:city":"Hermitage",
    "sg:classifiers":[
        {
            "category":"Health Services",
            "subcategory":"Doctor",
            "type":"Services"
        }
    ],
    "sg:phone":"+1 615 316 0100",
    "sg:postcode":"37076",
    "sg:province":"TN",
    "sg:tags":[
        "medical"
    ],
    "wof:name":"Occupatient Medical Svcs Inc",
    "wof:placetype":"venue"
},
  "geometry": {"coordinates":[-86.60653499999999,36.17976],"type":"Point"}
}