{
  "type": "Feature",
  "properties": {
    "addr:full":"107 Archway Ct Elizabethton TN 37643",
    "addr:housenumber":"107",
    "addr:postcode":"37643",
    "addr:street":"Archway Ct",
    "iso:country":"US",
    "sg:address":"107 Archway Ct",
    "sg:city":"Elizabethton",
    "sg:classifiers":[
        {
            "category":"Building & Trades",
            "subcategory":"Construction",
            "type":"Services"
        }
    ],
    "sg:phone":"+1 423 543 9770",
    "sg:postcode":"37643",
    "sg:province":"TN",
    "sg:tags":[
        "concrete",
        "contractor"
    ],
    "wof:name":"Lambert Bill Con & Epoxy Stone",
    "wof:placetype":"venue"
},
  "geometry": {"coordinates":[-82.201651,36.378002],"type":"Point"}
}