{
  "type": "Feature",
  "properties": {
    "addr:full":"7 Boonshill Rd Fayetteville TN 37334",
    "addr:housenumber":"7",
    "addr:postcode":"37334",
    "addr:street":"Boonshill Rd",
    "iso:country":"US",
    "sg:address":"7 Boonshill Rd",
    "sg:city":"Fayetteville",
    "sg:classifiers":[
        {
            "category":"Communications",
            "subcategory":"Radio Station",
            "type":"Services"
        }
    ],
    "sg:phone":"+1 931 433 3545",
    "sg:postcode":"37334",
    "sg:province":"TN",
    "sg:tags":[
        "company",
        "broadcasting"
    ],
    "wof:name":"WEKR",
    "wof:placetype":"venue"
},
  "geometry": {"coordinates":[-86.593333,35.158371],"type":"Point"}
}