{
  "type": "Feature",
  "properties": {
    "addr:full":"5959 Shallowford Rd Chattanooga TN 37421",
    "addr:housenumber":"5959",
    "addr:postcode":"37421",
    "addr:street":"Shallowford Rd",
    "iso:country":"US",
    "sg:address":"5959 Shallowford Rd",
    "sg:city":"Chattanooga",
    "sg:classifiers":[
        {
            "category":"Building & Trades",
            "subcategory":"Construction",
            "type":"Services"
        }
    ],
    "sg:phone":"+1 423 648 4580",
    "sg:postcode":"37421",
    "sg:province":"TN",
    "sg:tags":[
        "bathroom",
        "remodeling"
    ],
    "sg:website":"www.bathfitter.com",
    "wof:name":"Bath Fitter",
    "wof:placetype":"venue"
},
  "geometry": {"coordinates":[-85.19382299999999,35.054628],"type":"Point"}
}