{
  "type": "Feature",
  "properties": {
    "addr:full":"737 US Hwy 51 S Covington TN 38019",
    "addr:housenumber":"737",
    "addr:postcode":"38019",
    "addr:street":"Us Hwy 51 S",
    "iso:country":"US",
    "sg:address":"737 US Hwy 51 S",
    "sg:city":"Covington",
    "sg:classifiers":[
        {
            "category":"Personal",
            "subcategory":"Beauty Salon",
            "type":"Services"
        }
    ],
    "sg:phone":"+1 901 476 5528",
    "sg:postcode":"38019",
    "sg:province":"TN",
    "wof:name":"Belmont Garden Hair Care Ctr",
    "wof:placetype":"venue"
},
  "geometry": {"coordinates":[-89.653869,35.55818],"type":"Point"}
}