{
  "type": "Feature",
  "properties": {
    "iso:country":"US",
    "sg:address":"107 Music City Cir",
    "sg:city":"Nashville",
    "sg:classifiers":[
        {
            "category":"Professional",
            "subcategory":"Management & Consulting",
            "type":"Services"
        }
    ],
    "sg:phone":"+1 615 883 0085",
    "sg:postcode":"37214",
    "sg:province":"TN",
    "sg:tags":[
        "consultant"
    ],
    "wof:name":"Geo-Jobe Gis Consultants",
    "wof:placetype":"venue"
},
  "geometry": {"coordinates":[-86.69681,36.222991],"type":"Point"}
}