{
  "type": "Feature",
  "properties": {
    "iso:country":"US",
    "sg:address":"1418 Coachman Ln",
    "sg:city":"Knoxville",
    "sg:classifiers":[
        {
            "category":"Manufacturing",
            "subcategory":"Tools & Machinery",
            "type":"Manufacturing & Wholesale Goods"
        }
    ],
    "sg:phone":"+1 865 558 6335",
    "sg:postcode":"37919",
    "sg:province":"TN",
    "sg:tags":[
        "mill",
        "paper"
    ],
    "wof:name":"Associated Patents Co",
    "wof:placetype":"venue"
},
  "geometry": {"coordinates":[-83.99700300000001,35.914752],"type":"Point"}
}