{
  "type": "Feature",
  "properties": {
    "addr:full":"999 Vann Dr Jackson TN 38305",
    "addr:housenumber":"999",
    "addr:postcode":"38305",
    "addr:street":"Vann Dr",
    "iso:country":"US",
    "sg:address":"999 Vann Dr",
    "sg:city":"Jackson",
    "sg:classifiers":[
        {
            "category":"Bakery",
            "type":"Food & Drink"
        }
    ],
    "sg:menulink":"http://www.allmenus.com/tn/jackson/102332-perkins-restaurant--bakery/menu/",
    "sg:phone":"+1 731 661 9224",
    "sg:postcode":"38305",
    "sg:province":"TN",
    "sg:tags":[
        "sandwich",
        "salad",
        "soup",
        "american",
        "pastry",
        "wrap"
    ],
    "wof:name":"Perkins Restaurant & Bakery",
    "wof:placetype":"venue"
},
  "geometry": {"coordinates":[-88.85695800000001,35.67022],"type":"Point"}
}