{
  "type": "Feature",
  "properties": {
    "addr:full":"1099 S Main Ave Dyersburg TN 38024",
    "addr:housenumber":"1099",
    "addr:postcode":"38024",
    "addr:street":"S Main Ave",
    "iso:country":"US",
    "sg:address":"1099 S Main Ave",
    "sg:city":"Dyersburg",
    "sg:classifiers":[
        {
            "category":"Retail",
            "subcategory":"Repair Shop",
            "type":"Services"
        }
    ],
    "sg:phone":"+1 731 285 6967",
    "sg:postcode":"38024",
    "sg:province":"TN",
    "wof:name":"Smiths TV Service",
    "wof:placetype":"venue"
},
  "geometry": {"coordinates":[-89.394643,36.013227],"type":"Point"}
}