{
  "type": "Feature",
  "properties": {
    "iso:country":"US",
    "sg:address":"1335 Massachusetts Ave",
    "sg:city":"Knoxville",
    "sg:classifiers":[
        {
            "category":"Building & Trades",
            "subcategory":"Construction",
            "type":"Services"
        }
    ],
    "sg:phone":"+1 865 406 3689",
    "sg:postcode":"37921",
    "sg:province":"TN",
    "sg:tags":[
        "contractor"
    ],
    "wof:name":"Complete Drywall Service",
    "wof:placetype":"venue"
},
  "geometry": {"coordinates":[-83.95106199999999,35.979914],"type":"Point"}
}