{
  "type": "Feature",
  "properties": {
    "addr:full":"133 Main St Clifton TN 38425",
    "addr:housenumber":"133",
    "addr:postcode":"38425",
    "addr:street":"Main St",
    "iso:country":"US",
    "sg:address":"133 Main St",
    "sg:city":"Clifton",
    "sg:classifiers":[
        {
            "category":"Health Services",
            "subcategory":"Optometrist",
            "type":"Services"
        }
    ],
    "sg:phone":"+1 931 676 6993",
    "sg:postcode":"38425",
    "sg:province":"TN",
    "wof:name":"Savannah Eye Clinic",
    "wof:placetype":"venue"
},
  "geometry": {"coordinates":[-87.995105,35.386984],"type":"Point"}
}