{
  "type": "Feature",
  "properties": {
    "addr:full":"3065 Mount Moriah Dr Whiteville TN 38075",
    "addr:housenumber":"3065",
    "addr:postcode":"38075",
    "addr:street":"Mount Moriah Dr",
    "iso:country":"US",
    "sg:address":"3065 Mount Moriah Dr",
    "sg:city":"Whiteville",
    "sg:classifiers":[
        {
            "category":"Building & Trades",
            "subcategory":"Construction",
            "type":"Services"
        }
    ],
    "sg:phone":"+1 901 231 8279",
    "sg:postcode":"38075",
    "sg:province":"TN",
    "sg:tags":[
        "marine"
    ],
    "wof:name":"Upper Missouri River Corp",
    "wof:placetype":"venue"
},
  "geometry": {"coordinates":[-89.188242,35.327481],"type":"Point"}
}