{
  "type": "Feature",
  "properties": {
    "iso:country":"US",
    "sg:address":"713 W Main St",
    "sg:city":"Hendersonville",
    "sg:classifiers":[
        {
            "category":"Professional",
            "subcategory":"Computer Services",
            "type":"Services"
        }
    ],
    "sg:phone":"+1 615 264 6366",
    "sg:postcode":"37075",
    "sg:province":"TN",
    "sg:tags":[
        "internet"
    ],
    "wof:name":"Mid Tenn Information Network",
    "wof:placetype":"venue"
},
  "geometry": {"coordinates":[-86.641065,36.303036],"type":"Point"}
}