{
  "type": "Feature",
  "properties": {
    "iso:country":"US",
    "sg:address":"4057 Nolensville Pike",
    "sg:city":"Nashville",
    "sg:classifiers":[
        {
            "category":"Utilities",
            "subcategory":"Mobile Phone",
            "type":"Services"
        }
    ],
    "sg:phone":"+1 615 331 8996",
    "sg:postcode":"37211",
    "sg:province":"TN",
    "sg:tags":[
        "telephone",
        "cellular"
    ],
    "wof:name":"Cellular Com",
    "wof:placetype":"venue"
},
  "geometry": {"coordinates":[-86.72689099999999,36.08118],"type":"Point"}
}