{
  "type": "Feature",
  "properties": {
    "iso:country":"US",
    "sg:address":"3804 Elvis Presley Blvd",
    "sg:city":"Memphis",
    "sg:classifiers":[
        {
            "category":"Health Services",
            "subcategory":"Podiatrist",
            "type":"Services"
        }
    ],
    "sg:phone":"+1 901 396 2277",
    "sg:postcode":"38116",
    "sg:province":"TN",
    "sg:tags":[
        "medical"
    ],
    "wof:name":"Gold Robert H DPM",
    "wof:placetype":"venue"
},
  "geometry": {"coordinates":[-90.025031,35.046111],"type":"Point"}
}