{
  "type": "Feature",
  "properties": {
    "iso:country":"US",
    "sg:address":"226 11th Ave N",
    "sg:city":"Franklin",
    "sg:classifiers":[
        {
            "category":"Building & Trades",
            "subcategory":"Construction",
            "type":"Services"
        }
    ],
    "sg:phone":"+1 615 504 3113",
    "sg:postcode":"37064",
    "sg:province":"TN",
    "sg:tags":[
        "special",
        "contractor"
    ],
    "wof:name":"Pathway Home Design",
    "wof:placetype":"venue"
},
  "geometry": {"coordinates":[-86.879158,35.922386],"type":"Point"}
}