{
  "type": "Feature",
  "properties": {
    "addr:full":"325 Reed Strickland Ln Spring City TN 37381",
    "addr:housenumber":"325",
    "addr:postcode":"37381",
    "addr:street":"Reed Strickland Ln",
    "iso:country":"US",
    "sg:address":"325 Reed Strickland Ln",
    "sg:city":"Spring City",
    "sg:classifiers":[
        {
            "category":"Personal",
            "subcategory":"Beauty Salon",
            "type":"Services"
        }
    ],
    "sg:phone":"+1 423 365 5398",
    "sg:postcode":"37381",
    "sg:province":"TN",
    "sg:tags":[
        "shop"
    ],
    "wof:name":"Lapriel's Beauty Salon",
    "wof:placetype":"venue"
},
  "geometry": {"coordinates":[-84.8575,35.663545],"type":"Point"}
}