{
  "type": "Feature",
  "properties": {
    "iso:country":"US",
    "sg:address":"2647 Terrapin Creek Rd",
    "sg:city":"Cottage Grove",
    "sg:classifiers":[
        {
            "category":"Farming",
            "subcategory":"Poultry Farm",
            "type":"Manufacturing & Wholesale Goods"
        }
    ],
    "sg:phone":"+1 731 782 3128",
    "sg:postcode":"38224",
    "sg:province":"TN",
    "sg:tags":[
        "chicken"
    ],
    "wof:name":"Pine Grove Farm",
    "wof:placetype":"venue"
},
  "geometry": {"coordinates":[-88.49469000000001,36.487014],"type":"Point"}
}