{
  "type": "Feature",
  "properties": {
    "iso:country":"US",
    "sg:address":"1374 Railroad St",
    "sg:city":"Dayton",
    "sg:classifiers":[
        {
            "category":"Restaurant",
            "type":"Food & Drink"
        }
    ],
    "sg:phone":"+1 423 775 1877",
    "sg:postcode":"37321",
    "sg:province":"TN",
    "sg:tags":[
        "eating"
    ],
    "wof:name":"Western Sizzlin Steakhouse",
    "wof:placetype":"venue"
},
  "geometry": {"coordinates":[-85.014183,35.495378],"type":"Point"}
}