{
  "type": "Feature",
  "properties": {
    "addr:full":"806 4th Ave S Nashville TN 37210",
    "addr:housenumber":"806",
    "addr:postcode":"37210",
    "addr:street":"4Th Ave S",
    "iso:country":"US",
    "sg:address":"806 4th Ave S",
    "sg:city":"Nashville",
    "sg:classifiers":[
        {
            "category":"Professional",
            "type":"Services"
        }
    ],
    "sg:phone":"+1 615 248 4983",
    "sg:postcode":"37210",
    "sg:province":"TN",
    "wof:name":"Life Action Tennessee Inc",
    "wof:placetype":"venue"
},
  "geometry": {"coordinates":[-86.77126699999999,36.151982],"type":"Point"}
}