{
  "type": "Feature",
  "properties": {
    "iso:country":"US",
    "sg:address":"154 Crystal View Dr",
    "sg:city":"Cleveland",
    "sg:classifiers":[
        {
            "category":"Professional",
            "subcategory":"Accounting & Tax Preparation",
            "type":"Services"
        }
    ],
    "sg:phone":"+1 423 479 7872",
    "sg:postcode":"37312",
    "sg:province":"TN",
    "sg:tags":[
        "bookkeeping",
        "general"
    ],
    "wof:name":"J Wilson",
    "wof:placetype":"venue"
},
  "geometry": {"coordinates":[-84.920682,35.184099],"type":"Point"}
}