{
  "type": "Feature",
  "properties": {
    "addr:full":"122 Village Dr Greeneville TN 37745",
    "addr:housenumber":"122",
    "addr:postcode":"37745",
    "addr:street":"Village Dr",
    "iso:country":"US",
    "sg:address":"122 Village Dr",
    "sg:city":"Greeneville",
    "sg:classifiers":[
        {
            "category":"Health Services",
            "subcategory":"Hospital",
            "type":"Services"
        }
    ],
    "sg:phone":"+1 423 787 0238",
    "sg:postcode":"37745",
    "sg:province":"TN",
    "sg:tags":[
        "mental"
    ],
    "wof:name":"Behavioral Health-Greenville",
    "wof:placetype":"venue"
},
  "geometry": {"coordinates":[-82.801185,36.179813],"type":"Point"}
}