{
  "type": "Feature",
  "properties": {
    "iso:country":"US",
    "sg:address":"1149 W Main St",
    "sg:city":"Livingston",
    "sg:classifiers":[
        {
            "category":"Building & Trades",
            "subcategory":"Construction",
            "type":"Services"
        }
    ],
    "sg:phone":"+1 931 403 0837",
    "sg:postcode":"38570",
    "sg:province":"TN",
    "sg:tags":[
        "general",
        "contractor"
    ],
    "wof:name":"Berry Construction",
    "wof:placetype":"venue"
},
  "geometry": {"coordinates":[-85.337175,36.376708],"type":"Point"}
}