{
  "type": "Feature",
  "properties": {
    "iso:country":"US",
    "sg:address":"6023 Kevin Dr",
    "sg:city":"Memphis",
    "sg:classifiers":[
        {
            "category":"Personal",
            "type":"Services"
        }
    ],
    "sg:phone":"+1 901 386 7029",
    "sg:postcode":"38135",
    "sg:province":"TN",
    "wof:name":"Costumes Unlimited",
    "wof:placetype":"venue"
},
  "geometry": {"coordinates":[-89.86216400000001,35.21887],"type":"Point"}
}