{
  "type": "Feature",
  "properties": {
    "iso:country":"US",
    "sg:address":"4569 Old Lamar Ave",
    "sg:city":"Memphis",
    "sg:classifiers":[
        {
            "category":"Wholesale",
            "subcategory":"Durable Goods & Equipment",
            "type":"Manufacturing & Wholesale Goods"
        }
    ],
    "sg:phone":"+1 901 367 8944",
    "sg:postcode":"38118",
    "sg:province":"TN",
    "sg:tags":[
        "instrument",
        "aircraft"
    ],
    "wof:name":"T-AEROSPACE LLC",
    "wof:placetype":"venue"
},
  "geometry": {"coordinates":[-89.91076200000001,35.034487],"type":"Point"}
}