{
  "type": "Feature",
  "properties": {
    "addr:full":"1432 Memorial Blvd Murfreesboro TN 37129",
    "addr:housenumber":"1432",
    "addr:postcode":"37129",
    "addr:street":"Memorial Blvd",
    "iso:country":"US",
    "sg:address":"1432 Memorial Blvd",
    "sg:city":"Murfreesboro",
    "sg:classifiers":[
        {
            "category":"Cafe",
            "type":"Food & Drink"
        }
    ],
    "sg:menulink":"http://www.allmenus.com/tn/murfreesboro/210243-calypso-cafe/menu/",
    "sg:phone":"+1 615 217 8879",
    "sg:postcode":"37129",
    "sg:province":"TN",
    "sg:tags":[
        "american"
    ],
    "wof:name":"Calypso Cafe",
    "wof:placetype":"venue"
},
  "geometry": {"coordinates":[-86.38947899999999,35.862633],"type":"Point"}
}