{
  "type": "Feature",
  "properties": {
    "iso:country":"US",
    "sg:address":"7200 Strawberry Plains Pike",
    "sg:city":"Knoxville",
    "sg:classifiers":[
        {
            "category":"Restaurant",
            "type":"Food & Drink"
        }
    ],
    "sg:menulink":"http://www.allmenus.com/tn/knoxville/140282-subway/menu/",
    "sg:phone":"+1 865 544 1123",
    "sg:postcode":"37914",
    "sg:province":"TN",
    "sg:tags":[
        "american",
        "sandwich"
    ],
    "wof:name":"Subway",
    "wof:placetype":"venue"
},
  "geometry": {"coordinates":[-83.78179799999999,35.997003],"type":"Point"}
}