{
  "type": "Feature",
  "properties": {
    "addr:full":"2017 Stonebrook Pl Kingsport TN 37660",
    "addr:housenumber":"2017",
    "addr:postcode":"37660",
    "addr:street":"Stonebrook Pl",
    "iso:country":"US",
    "sg:address":"2017 Stonebrook Pl",
    "sg:city":"Kingsport",
    "sg:classifiers":[
        {
            "category":"Organizations",
            "subcategory":"Non-profit Organization",
            "type":"Services"
        }
    ],
    "sg:phone":"+1 423 224 1446",
    "sg:postcode":"37660",
    "sg:province":"TN",
    "wof:name":"Kitchen Magician",
    "wof:placetype":"venue"
},
  "geometry": {"coordinates":[-82.543215,36.557033],"type":"Point"}
}