{
  "type": "Feature",
  "properties": {
    "iso:country":"US",
    "sg:address":"2820 Coleman Rd",
    "sg:city":"Memphis",
    "sg:classifiers":[
        {
            "category":"Personal",
            "subcategory":"Beauty Salon",
            "type":"Services"
        }
    ],
    "sg:phone":"+1 901 385 3201",
    "sg:postcode":"38128",
    "sg:province":"TN",
    "sg:tags":[
        "shop"
    ],
    "wof:name":"Valentino's Hair Salon",
    "wof:placetype":"venue"
},
  "geometry": {"coordinates":[-89.913319,35.203172],"type":"Point"}
}