{
  "type": "Feature",
  "properties": {
    "iso:country":"US",
    "sg:address":"279 Exchange Ave",
    "sg:city":"Memphis",
    "sg:classifiers":[
        {
            "category":"Retail",
            "subcategory":"Repair Shop",
            "type":"Services"
        },
        {
            "category":"Professional",
            "subcategory":"Detective & Security Services",
            "type":"Services"
        }
    ],
    "sg:phone":"+1 901 522 9969",
    "sg:postcode":"38105",
    "sg:province":"TN",
    "sg:tags":[
        "skip",
        "tracing",
        "bail",
        "bond"
    ],
    "wof:name":"Gulf National Surety Inc",
    "wof:placetype":"venue"
},
  "geometry": {"coordinates":[-90.044456,35.149562],"type":"Point"}
}