{
  "type": "Feature",
  "properties": {
    "iso:country":"US",
    "sg:address":"604 N Roan St",
    "sg:city":"Johnson City",
    "sg:classifiers":[
        {
            "category":"Shopping",
            "type":"Retail Goods"
        }
    ],
    "sg:phone":"+1 423 926 7651",
    "sg:postcode":"37601",
    "sg:province":"TN",
    "sg:tags":[
        "hearing",
        "equipment",
        "supply",
        "impaired"
    ],
    "wof:name":"Ear Technology Corp",
    "wof:placetype":"venue"
},
  "geometry": {"coordinates":[-82.355762,36.321071],"type":"Point"}
}