{
  "type": "Feature",
  "properties": {
    "iso:country":"US",
    "sg:address":"142 E Main St",
    "sg:city":"Adamsville",
    "sg:classifiers":[
        {
            "category":"Restaurant",
            "type":"Food & Drink"
        }
    ],
    "sg:phone":"+1 731 632 1199",
    "sg:postcode":"38310",
    "sg:province":"TN",
    "sg:website":"www.sheriffbufordpusser.com",
    "wof:name":"Pusser's Restaurant",
    "wof:placetype":"venue"
},
  "geometry": {"coordinates":[-88.394514,35.236013],"type":"Point"}
}