{
  "type": "Feature",
  "properties": {
    "addr:full":"400 Main St W Knoxville TN 37902",
    "addr:housenumber":"400",
    "addr:postcode":"37902",
    "addr:street":"Main St W",
    "iso:country":"US",
    "sg:address":"400 Main St W",
    "sg:city":"Knoxville",
    "sg:classifiers":[
        {
            "category":"Education",
            "subcategory":"Library",
            "type":"Public Place"
        }
    ],
    "sg:phone":"+1 865 215 2368",
    "sg:postcode":"37902",
    "sg:province":"TN",
    "wof:name":"Law Library",
    "wof:placetype":"venue"
},
  "geometry": {"coordinates":[-83.91838199999999,35.96093],"type":"Point"}
}