{
  "type": "Feature",
  "properties": {
    "addr:full":"1060 W Deer Lodge Hwy Clarkrange TN 38553",
    "addr:housenumber":"1060",
    "addr:postcode":"38553",
    "addr:street":"W Deer Lodge Hwy",
    "iso:country":"US",
    "sg:address":"1060 W Deer Lodge Hwy",
    "sg:city":"Clarkrange",
    "sg:classifiers":[
        {
            "category":"Utilities",
            "subcategory":"Natural Gas",
            "type":"Services"
        }
    ],
    "sg:phone":"+1 931 863 3167",
    "sg:postcode":"38553",
    "sg:province":"TN",
    "sg:tags":[
        "company"
    ],
    "wof:name":"East Tenn Natural Gas Co",
    "wof:placetype":"venue"
},
  "geometry": {"coordinates":[-84.996971,36.182014],"type":"Point"}
}