{
  "type": "Feature",
  "properties": {
    "iso:country":"US",
    "sg:address":"640 Spence Ln",
    "sg:city":"Nashville",
    "sg:classifiers":[
        {
            "category":"Freight",
            "type":"Transportation"
        }
    ],
    "sg:phone":"+1 615 361 5434",
    "sg:postcode":"37217",
    "sg:province":"TN",
    "sg:tags":[
        "courier"
    ],
    "wof:name":"Courier Concepts",
    "wof:placetype":"venue"
},
  "geometry": {"coordinates":[-86.723085,36.139121],"type":"Point"}
}