{
  "type": "Feature",
  "properties": {
    "iso:country":"US",
    "sg:address":"710 Deery St",
    "sg:city":"Shelbyville",
    "sg:classifiers":[
        {
            "category":"Shopping",
            "subcategory":"Used Merchandise",
            "type":"Retail Goods"
        }
    ],
    "sg:phone":"+1 931 684 1370",
    "sg:postcode":"37160",
    "sg:province":"TN",
    "sg:tags":[
        "pawnbroker"
    ],
    "wof:name":"Don's Pawn & Gun",
    "wof:placetype":"venue"
},
  "geometry": {"coordinates":[-86.45448500000001,35.492999],"type":"Point"}
}