{
  "type": "Feature",
  "properties": {
    "iso:country":"US",
    "sg:address":"4215 Lamar Ave",
    "sg:city":"Memphis",
    "sg:classifiers":[
        {
            "category":"Wholesale",
            "subcategory":"Medical Equipment & Supplies",
            "type":"Manufacturing & Wholesale Goods"
        }
    ],
    "sg:phone":"+1 901 853 6498",
    "sg:postcode":"38118",
    "sg:province":"TN",
    "sg:tags":[
        "physician",
        "surgeon"
    ],
    "wof:name":"Bullit X Ray",
    "wof:placetype":"venue"
},
  "geometry": {"coordinates":[-89.92260400000001,35.048908],"type":"Point"}
}