{
  "type": "Feature",
  "properties": {
    "iso:country":"US",
    "sg:address":"1725 Scenic Valley Ln",
    "sg:city":"Knoxville",
    "sg:classifiers":[
        {
            "category":"Professional",
            "subcategory":"Engineering",
            "type":"Services"
        }
    ],
    "sg:phone":"+1 865 310 0014",
    "sg:postcode":"37922",
    "sg:province":"TN",
    "wof:name":"Eas",
    "wof:placetype":"venue"
},
  "geometry": {"coordinates":[-84.090943,35.862305],"type":"Point"}
}