{
  "type": "Feature",
  "properties": {
    "addr:full":"330 Franklin Rd Brentwood TN 37027",
    "addr:housenumber":"330",
    "addr:postcode":"37027",
    "addr:street":"Franklin Rd",
    "iso:country":"US",
    "sg:address":"330 Franklin Rd",
    "sg:city":"Brentwood",
    "sg:classifiers":[
        {
            "category":"Personal",
            "subcategory":"Beauty Salon",
            "type":"Services"
        }
    ],
    "sg:phone":"+1 615 373 1818",
    "sg:postcode":"37027",
    "sg:province":"TN",
    "sg:tags":[
        "shop"
    ],
    "wof:name":"Zbos Hair Company",
    "wof:placetype":"venue"
},
  "geometry": {"coordinates":[-86.792039,36.027179],"type":"Point"}
}