{
  "type": "Feature",
  "properties": {
    "iso:country":"US",
    "sg:address":"142 8th Ave N",
    "sg:city":"Nashville",
    "sg:classifiers":[
        {
            "category":"Communications",
            "subcategory":"Film & Video Production",
            "type":"Services"
        }
    ],
    "sg:phone":"+1 615 297 4410",
    "sg:postcode":"37203",
    "sg:province":"TN",
    "sg:tags":[
        "taping"
    ],
    "sg:website":"www.tomneff.com",
    "wof:name":"Image Productions",
    "wof:placetype":"venue"
},
  "geometry": {"coordinates":[-86.782707,36.159658],"type":"Point"}
}