{
  "type": "Feature",
  "properties": {
    "iso:country":"US",
    "sg:address":"540 Cardwell Rd",
    "sg:city":"Middleton",
    "sg:classifiers":[
        {
            "category":"Building & Trades",
            "subcategory":"Plumbing",
            "type":"Services"
        }
    ],
    "sg:phone":"+1 731 376 0704",
    "sg:postcode":"38052",
    "sg:province":"TN",
    "sg:tags":[
        "contractor"
    ],
    "wof:name":"Southern Weld",
    "wof:placetype":"venue"
},
  "geometry": {"coordinates":[-88.96560599999999,35.036401],"type":"Point"}
}