{
  "type": "Feature",
  "properties": {
    "addr:full":"245 E Main St Hendersonville TN 37075",
    "addr:housenumber":"245",
    "addr:postcode":"37075",
    "addr:street":"E Main St",
    "iso:country":"US",
    "sg:address":"245 E Main St",
    "sg:city":"Hendersonville",
    "sg:classifiers":[
        {
            "category":"Restaurant",
            "type":"Food & Drink"
        }
    ],
    "sg:phone":"+1 615 264 2764",
    "sg:postcode":"37075",
    "sg:province":"TN",
    "sg:tags":[
        "eating"
    ],
    "wof:name":"Pizza Hut",
    "wof:placetype":"venue"
},
  "geometry": {"coordinates":[-86.603117,36.308871],"type":"Point"}
}