{
  "type": "Feature",
  "properties": {
    "iso:country":"US",
    "sg:address":"565 Tranbarger Rd",
    "sg:city":"Church Hill",
    "sg:classifiers":[
        {
            "category":"Building & Trades",
            "subcategory":"Construction",
            "type":"Services"
        }
    ],
    "sg:phone":"+1 423 247 1417",
    "sg:postcode":"37642",
    "sg:province":"TN",
    "sg:tags":[
        "house"
    ],
    "wof:name":"Anderson Construction",
    "wof:placetype":"venue"
},
  "geometry": {"coordinates":[-82.631912,36.567719],"type":"Point"}
}