{
  "type": "Feature",
  "properties": {
    "addr:full":"5318 Ringgold Rd Chattanooga TN 37412",
    "addr:housenumber":"5318",
    "addr:postcode":"37412",
    "addr:street":"Ringgold Rd",
    "iso:country":"US",
    "sg:address":"5318 Ringgold Rd",
    "sg:city":"Chattanooga",
    "sg:classifiers":[
        {
            "category":"Restaurant",
            "type":"Food & Drink"
        }
    ],
    "sg:menulink":"http://www.allmenus.com/tn/east-ridge/176790-kfc---kentucky-fried-chicken/menu/",
    "sg:phone":"+1 423 894 7501",
    "sg:postcode":"37412",
    "sg:province":"TN",
    "sg:tags":[
        "american",
        "chicken"
    ],
    "wof:name":"KFC - Kentucky Fried Chicken",
    "wof:placetype":"venue"
},
  "geometry": {"coordinates":[-85.233656,34.994512],"type":"Point"}
}