{
  "type": "Feature",
  "properties": {
    "iso:country":"US",
    "sg:address":"1233 Southwest Ave",
    "sg:city":"Johnson City",
    "sg:classifiers":[
        {
            "category":"Health Services",
            "subcategory":"Clinic",
            "type":"Services"
        }
    ],
    "sg:phone":"+1 423 929 5961",
    "sg:postcode":"37604",
    "sg:province":"TN",
    "wof:name":"First Tenn Cmnty Hlth Agcy",
    "wof:placetype":"venue"
},
  "geometry": {"coordinates":[-82.360625,36.304228],"type":"Point"}
}