{
  "type": "Feature",
  "properties": {
    "iso:country":"US",
    "sg:address":"369 E G E Patterson Ave",
    "sg:city":"Memphis",
    "sg:classifiers":[
        {
            "category":"Education",
            "subcategory":"College",
            "type":"Public Place"
        }
    ],
    "sg:phone":"+1 901 332 4012",
    "sg:postcode":"38126",
    "sg:province":"TN",
    "wof:name":"Ch Mason Bible College",
    "wof:placetype":"venue"
},
  "geometry": {"coordinates":[-90.048547,35.132524],"type":"Point"}
}