{
  "type": "Feature",
  "properties": {
    "iso:country":"US",
    "sg:address":"6310 Poplar Ave",
    "sg:city":"Memphis",
    "sg:classifiers":[
        {
            "category":"Organizations",
            "subcategory":"Religious Organization",
            "type":"Services"
        }
    ],
    "sg:phone":"+1 901 681 0058",
    "sg:postcode":"38119",
    "sg:province":"TN",
    "sg:tags":[
        "church"
    ],
    "wof:name":"Shiloh Hiking Trail",
    "wof:placetype":"venue"
},
  "geometry": {"coordinates":[-89.85430700000001,35.101092],"type":"Point"}
}