{
  "type": "Feature",
  "properties": {
    "iso:country":"US",
    "sg:address":"1792 Tinnel Rd",
    "sg:city":"Lenoir City",
    "sg:classifiers":[
        {
            "category":"Building & Trades",
            "subcategory":"Construction",
            "type":"Services"
        }
    ],
    "sg:phone":"+1 865 986 9650",
    "sg:postcode":"37772",
    "sg:province":"TN",
    "sg:tags":[
        "house",
        "c",
        "contractor",
        "hanging"
    ],
    "wof:name":"Hicks Painting & Home Maint",
    "wof:placetype":"venue"
},
  "geometry": {"coordinates":[-84.249893,35.813998],"type":"Point"}
}