{
  "type": "Feature",
  "properties": {
    "iso:country":"US",
    "sg:address":"843 Paint Rock Ferry Rd",
    "sg:city":"Kingston",
    "sg:classifiers":[
        {
            "category":"Shopping",
            "subcategory":"Clothing, Apparel, & Fashions",
            "type":"Retail Goods"
        }
    ],
    "sg:phone":"+1 865 376 7484",
    "sg:postcode":"37763",
    "sg:province":"TN",
    "wof:name":"JB Jewelry",
    "wof:placetype":"venue"
},
  "geometry": {"coordinates":[-84.491142,35.843532],"type":"Point"}
}