{
  "type": "Feature",
  "properties": {
    "iso:country":"US",
    "sg:address":"13 Governors Way",
    "sg:city":"Brentwood",
    "sg:classifiers":[
        {
            "category":"Organizations",
            "subcategory":"Membership Organization",
            "type":"Services"
        }
    ],
    "sg:phone":"+1 615 776 3090",
    "sg:postcode":"37027",
    "sg:province":"TN",
    "sg:tags":[
        "charitable"
    ],
    "wof:name":"Lackey Foundation Inc",
    "wof:placetype":"venue"
},
  "geometry": {"coordinates":[-86.732872,35.979991],"type":"Point"}
}