{
  "type": "Feature",
  "properties": {
    "iso:country":"US",
    "sg:address":"200 Torry Rd",
    "sg:city":"La Follette",
    "sg:classifiers":[
        {
            "category":"Health Services",
            "subcategory":"Nursing And Care Facility",
            "type":"Services"
        }
    ],
    "sg:phone":"+1 423 907 1200",
    "sg:postcode":"37766",
    "sg:province":"TN",
    "sg:tags":[
        "home",
        "convalescent"
    ],
    "wof:name":"St Mary's Health & Renab",
    "wof:placetype":"venue"
},
  "geometry": {"coordinates":[-84.113168,36.391013],"type":"Point"}
}