{
  "type": "Feature",
  "properties": {
    "iso:country":"US",
    "sg:address":"2174 Leconte St",
    "sg:city":"Morristown",
    "sg:classifiers":[
        {
            "category":"Professional",
            "subcategory":"Business Services",
            "type":"Services"
        }
    ],
    "sg:phone":"+1 423 318 7100",
    "sg:postcode":"37814",
    "sg:province":"TN",
    "sg:tags":[
        "appraiser"
    ],
    "wof:name":"Kelley Appraisals",
    "wof:placetype":"venue"
},
  "geometry": {"coordinates":[-83.33278799999999,36.225521],"type":"Point"}
}