{
  "type": "Feature",
  "properties": {
    "addr:full":"1208 Woodbury Ct Knoxville TN 37922",
    "addr:housenumber":"1208",
    "addr:postcode":"37922",
    "addr:street":"Woodbury Ct",
    "iso:country":"US",
    "sg:address":"1208 Woodbury Ct",
    "sg:city":"Knoxville",
    "sg:classifiers":[
        {
            "category":"Building & Trades",
            "subcategory":"Construction",
            "type":"Services"
        }
    ],
    "sg:phone":"+1 865 691 4192",
    "sg:postcode":"37922",
    "sg:province":"TN",
    "sg:tags":[
        "contractor"
    ],
    "wof:name":"Tsg Contracting",
    "wof:placetype":"venue"
},
  "geometry": {"coordinates":[-84.04074900000001,35.892499],"type":"Point"}
}