{
  "type": "Feature",
  "properties": {
    "addr:full":"2702 Lead Mine Valley Rd SW Cleveland TN 37311",
    "addr:housenumber":"2702",
    "addr:postcode":"37311",
    "addr:street":"Lead Mine Valley Rd Sw",
    "iso:country":"US",
    "sg:address":"2702 Lead Mine Valley Rd SW",
    "sg:city":"Cleveland",
    "sg:classifiers":[
        {
            "category":"Organizations",
            "subcategory":"Religious Organization",
            "type":"Services"
        }
    ],
    "sg:phone":"+1 423 472 0932",
    "sg:postcode":"37311",
    "sg:province":"TN",
    "sg:tags":[
        "church"
    ],
    "wof:name":"Blue Springs Baptist Church",
    "wof:placetype":"venue"
},
  "geometry": {"coordinates":[-84.94041900000001,35.046665],"type":"Point"}
}