{
  "type": "Feature",
  "properties": {
    "iso:country":"US",
    "sg:address":"1333 Jackson Ave",
    "sg:city":"Memphis",
    "sg:classifiers":[
        {
            "category":"Personal",
            "subcategory":"Barber",
            "type":"Services"
        }
    ],
    "sg:phone":"+1 901 721 6041",
    "sg:postcode":"38107",
    "sg:province":"TN",
    "wof:name":"Haircuts",
    "wof:placetype":"venue"
},
  "geometry": {"coordinates":[-90.01391099999999,35.158218],"type":"Point"}
}