{
  "type": "Feature",
  "properties": {
    "iso:country":"US",
    "sg:address":"768 S Jefferson Ave",
    "sg:city":"Cookeville",
    "sg:classifiers":[
        {
            "category":"Restaurant",
            "type":"Food & Drink"
        }
    ],
    "sg:phone":"+1 931 646 4666",
    "sg:postcode":"38501",
    "sg:province":"TN",
    "sg:tags":[
        "eating"
    ],
    "wof:name":"Casa Fiesta Mexican Restaurant",
    "wof:placetype":"venue"
},
  "geometry": {"coordinates":[-85.500953,36.144455],"type":"Point"}
}