{
  "type": "Feature",
  "properties": {
    "iso:country":"US",
    "sg:address":"2116 Melody Dr",
    "sg:city":"Franklin",
    "sg:classifiers":[
        {
            "category":"Professional",
            "subcategory":"Management & Consulting",
            "type":"Services"
        }
    ],
    "sg:phone":"+1 615 791 0540",
    "sg:postcode":"37067",
    "sg:province":"TN",
    "sg:tags":[
        "business"
    ],
    "wof:name":"Spann Consulting",
    "wof:placetype":"venue"
},
  "geometry": {"coordinates":[-86.82122,35.900405],"type":"Point"}
}