{
  "type": "Feature",
  "properties": {
    "addr:full":"1214 Columbia Ave Franklin TN 37064",
    "addr:housenumber":"1214",
    "addr:postcode":"37064",
    "addr:street":"Columbia Ave",
    "iso:country":"US",
    "sg:address":"1214 Columbia Ave",
    "sg:city":"Franklin",
    "sg:classifiers":[
        {
            "category":"Organizations",
            "subcategory":"Non-profit Organization",
            "type":"Services"
        }
    ],
    "sg:phone":"+1 615 790 0548",
    "sg:postcode":"37064",
    "sg:province":"TN",
    "sg:tags":[
        "social"
    ],
    "wof:name":"Ceramic & Craft Workshop",
    "wof:placetype":"venue"
},
  "geometry": {"coordinates":[-86.873552,35.915766],"type":"Point"}
}