{
  "type": "Feature",
  "properties": {
    "iso:country":"US",
    "sg:address":"1500 Dickerson Pike",
    "sg:city":"Nashville",
    "sg:classifiers":[
        {
            "category":"Education",
            "subcategory":"School",
            "type":"Public Place"
        }
    ],
    "sg:phone":"+1 615 262 6725",
    "sg:postcode":"37207",
    "sg:province":"TN",
    "wof:name":"Shwab Elementary School",
    "wof:placetype":"venue"
},
  "geometry": {"coordinates":[-86.768715,36.205439],"type":"Point"}
}