{
  "type": "Feature",
  "properties": {
    "iso:country":"US",
    "sg:address":"301 E Magnolia Ave",
    "sg:city":"Knoxville",
    "sg:classifiers":[
        {
            "category":"Wholesale",
            "subcategory":"Machinery & Supplies",
            "type":"Manufacturing & Wholesale Goods"
        }
    ],
    "sg:phone":"+1 865 525 8405",
    "sg:postcode":"37917",
    "sg:province":"TN",
    "sg:tags":[
        "equipment",
        "industrial"
    ],
    "wof:name":"Add Rite Material Handling",
    "wof:placetype":"venue"
},
  "geometry": {"coordinates":[-83.91839899999999,35.973712],"type":"Point"}
}