{
  "type": "Feature",
  "properties": {
    "iso:country":"US",
    "sg:address":"1102 Kermit Dr",
    "sg:city":"Nashville",
    "sg:classifiers":[
        {
            "category":"Professional",
            "type":"Services"
        }
    ],
    "sg:phone":"+1 615 366 6115",
    "sg:postcode":"37217",
    "sg:province":"TN",
    "sg:tags":[
        "establishment"
    ],
    "wof:name":"Abco Dealers Inc",
    "wof:placetype":"venue"
},
  "geometry": {"coordinates":[-86.70391600000001,36.123741],"type":"Point"}
}