{
  "type": "Feature",
  "properties": {
    "iso:country":"US",
    "sg:address":"214 Centerview Dr",
    "sg:city":"Brentwood",
    "sg:classifiers":[
        {
            "category":"Professional",
            "subcategory":"Management & Consulting",
            "type":"Services"
        }
    ],
    "sg:phone":"+1 615 627 4235",
    "sg:postcode":"37027",
    "sg:province":"TN",
    "wof:name":"Health Care Enhncement Sytems",
    "wof:placetype":"venue"
},
  "geometry": {"coordinates":[-86.786991,36.030933],"type":"Point"}
}