{
  "type": "Feature",
  "properties": {
    "iso:country":"US",
    "sg:address":"835 E Trigg Ave",
    "sg:city":"Memphis",
    "sg:classifiers":[
        {
            "category":"Health Services",
            "subcategory":"Clinic",
            "type":"Services"
        }
    ],
    "sg:phone":"+1 901 942 7184",
    "sg:postcode":"38106",
    "sg:province":"TN",
    "sg:tags":[
        "home"
    ],
    "wof:name":"Family Home Health Agency",
    "wof:placetype":"venue"
},
  "geometry": {"coordinates":[-90.03388,35.111831],"type":"Point"}
}