{
  "type": "Feature",
  "properties": {
    "iso:country":"US",
    "sg:address":"810 Washington Ave",
    "sg:city":"Memphis",
    "sg:classifiers":[
        {
            "category":"Building & Trades",
            "subcategory":"Landscaping Services",
            "type":"Services"
        }
    ],
    "sg:phone":"+1 901 438 3336",
    "sg:postcode":"38105",
    "sg:province":"TN",
    "sg:tags":[
        "landscape",
        "contractor"
    ],
    "wof:name":"Landwork Of Memphis",
    "wof:placetype":"venue"
},
  "geometry": {"coordinates":[-90.03418000000001,35.144797],"type":"Point"}
}