{
  "type": "Feature",
  "properties": {
    "addr:full":"1702 Memorial Blvd Murfreesboro TN 37129",
    "addr:housenumber":"1702",
    "addr:postcode":"37129",
    "addr:street":"Memorial Blvd",
    "iso:country":"US",
    "sg:address":"1702 Memorial Blvd",
    "sg:city":"Murfreesboro",
    "sg:classifiers":[
        {
            "category":"Restaurant",
            "type":"Food & Drink"
        }
    ],
    "sg:menulink":"http://www.allmenus.com/tn/murfreesboro/215220-taco-bell/menu/",
    "sg:phone":"+1 615 896 5499",
    "sg:postcode":"37129",
    "sg:province":"TN",
    "sg:tags":[
        "mexican"
    ],
    "wof:name":"Taco Bell",
    "wof:placetype":"venue"
},
  "geometry": {"coordinates":[-86.38679999999999,35.868444],"type":"Point"}
}