{
  "type": "Feature",
  "properties": {
    "iso:country":"US",
    "sg:address":"106 Cranwill Dr",
    "sg:city":"Hendersonville",
    "sg:classifiers":[
        {
            "category":"Education",
            "subcategory":"Special Training",
            "type":"Public Place"
        }
    ],
    "sg:phone":"+1 615 822 0016",
    "sg:postcode":"37075",
    "sg:province":"TN",
    "wof:name":"Clay Lady House",
    "wof:placetype":"venue"
},
  "geometry": {"coordinates":[-86.638853,36.305398],"type":"Point"}
}