{
  "type": "Feature",
  "properties": {
    "iso:country":"US",
    "sg:address":"400 S Moore Rd",
    "sg:city":"Chattanooga",
    "sg:classifiers":[
        {
            "category":"Health Services",
            "subcategory":"Chiropractor",
            "type":"Services"
        }
    ],
    "sg:phone":"+1 423 894 4771",
    "sg:postcode":"37412",
    "sg:province":"TN",
    "sg:tags":[
        "chiropractic"
    ],
    "wof:name":"Chirohealth Chiropractic",
    "wof:placetype":"venue"
},
  "geometry": {"coordinates":[-85.231983,35.006046],"type":"Point"}
}