{
  "type": "Feature",
  "properties": {
    "addr:full":"240 Pruitt Rd Greeneville TN 37743",
    "addr:housenumber":"240",
    "addr:postcode":"37743",
    "addr:street":"Pruitt Rd",
    "iso:country":"US",
    "sg:address":"240 Pruitt Rd",
    "sg:city":"Greeneville",
    "sg:classifiers":[
        {
            "category":"Professional",
            "subcategory":"Business Services",
            "type":"Services"
        },
        {
            "category":"Retail",
            "subcategory":"Auto Repair",
            "type":"Services"
        }
    ],
    "sg:phone":"+1 423 783 9935",
    "sg:postcode":"37743",
    "sg:province":"TN",
    "sg:tags":[
        "truck"
    ],
    "wof:name":"Crick Enterprises LLC",
    "wof:placetype":"venue"
},
  "geometry": {"coordinates":[-82.88909700000001,36.168307],"type":"Point"}
}