{
  "type": "Feature",
  "properties": {
    "addr:full":"318 Seaboard Ln Franklin TN 37067",
    "addr:housenumber":"318",
    "addr:postcode":"37067",
    "addr:street":"Seaboard Ln",
    "iso:country":"US",
    "sg:address":"318 Seaboard Ln",
    "sg:city":"Franklin",
    "sg:classifiers":[
        {
            "category":"Shopping",
            "subcategory":"Catalog Store",
            "type":"Retail Goods"
        }
    ],
    "sg:phone":"+1 615 778 2100",
    "sg:postcode":"37067",
    "sg:province":"TN",
    "sg:tags":[
        "magazine",
        "sales",
        "subscription"
    ],
    "wof:name":"Magazinescom Inc",
    "wof:placetype":"venue"
},
  "geometry": {"coordinates":[-86.83069999999999,35.949594],"type":"Point"}
}