{
  "type": "Feature",
  "properties": {
    "addr:full":"1006 Columbine Lea Sevierville TN 37862",
    "addr:housenumber":"1006",
    "addr:postcode":"37862",
    "addr:street":"Columbine Lea",
    "iso:country":"US",
    "sg:address":"1006 Columbine Lea",
    "sg:city":"Sevierville",
    "sg:classifiers":[
        {
            "category":"Education",
            "subcategory":"Dance Studio",
            "type":"Public Place"
        }
    ],
    "sg:phone":"+1 865 774 4507",
    "sg:postcode":"37862",
    "sg:province":"TN",
    "sg:tags":[
        "instruction",
        "dancing"
    ],
    "wof:name":"Rhythm In The Hills",
    "wof:placetype":"venue"
},
  "geometry": {"coordinates":[-83.52342299999999,35.850044],"type":"Point"}
}