{
  "type": "Feature",
  "properties": {
    "iso:country":"US",
    "sg:address":"3106 Cummings Hwy",
    "sg:city":"Chattanooga",
    "sg:classifiers":[
        {
            "category":"Retail",
            "subcategory":"Auto Repair",
            "type":"Services"
        }
    ],
    "sg:phone":"+1 423 821 1660",
    "sg:postcode":"37419",
    "sg:province":"TN",
    "sg:tags":[
        "general"
    ],
    "wof:name":"Automotive Unlimited",
    "wof:placetype":"venue"
},
  "geometry": {"coordinates":[-85.369508,35.019637],"type":"Point"}
}