{
  "type": "Feature",
  "properties": {
    "addr:full":"555 Church St Nashville TN 37219",
    "addr:housenumber":"555",
    "addr:postcode":"37219",
    "addr:street":"Church St",
    "iso:country":"US",
    "sg:address":"555 Church St",
    "sg:city":"Nashville",
    "sg:classifiers":[
        {
            "category":"Shopping",
            "subcategory":"Clothing, Apparel, & Fashions",
            "type":"Retail Goods"
        }
    ],
    "sg:phone":"+1 615 255 3775",
    "sg:postcode":"37219",
    "sg:province":"TN",
    "wof:name":"Pg Fashion & Show",
    "wof:placetype":"venue"
},
  "geometry": {"coordinates":[-86.781363,36.162635],"type":"Point"}
}