{
  "type": "Feature",
  "properties": {
    "iso:country":"US",
    "sg:address":"1580 Hawthorne Lndg NW",
    "sg:city":"Cleveland",
    "sg:classifiers":[
        {
            "category":"Building & Trades",
            "subcategory":"Construction",
            "type":"Services"
        }
    ],
    "sg:phone":"+1 423 479 9813",
    "sg:postcode":"37312",
    "sg:province":"TN",
    "sg:tags":[
        "house"
    ],
    "wof:name":"Roberson Builders",
    "wof:placetype":"venue"
},
  "geometry": {"coordinates":[-84.87850400000001,35.208682],"type":"Point"}
}