{
  "type": "Feature",
  "properties": {
    "iso:country":"US",
    "sg:address":"706 S Chancery St",
    "sg:city":"Mc Minnville",
    "sg:classifiers":[
        {
            "category":"Social Services",
            "type":"Services"
        }
    ],
    "sg:phone":"+1 931 473 6221",
    "sg:postcode":"37110",
    "sg:province":"TN",
    "sg:tags":[
        "crisis",
        "intervention"
    ],
    "wof:name":"Families In Crisis Domestic",
    "wof:placetype":"venue"
},
  "geometry": {"coordinates":[-85.782219,35.666505],"type":"Point"}
}