{
  "type": "Feature",
  "properties": {
    "iso:country":"US",
    "sg:address":"387 Trunk St NE",
    "sg:city":"Cleveland",
    "sg:classifiers":[
        {
            "category":"Professional",
            "subcategory":"Business Services",
            "type":"Services"
        }
    ],
    "sg:phone":"+1 423 614 7696",
    "sg:postcode":"37311",
    "sg:province":"TN",
    "wof:name":"Centro Azteca",
    "wof:placetype":"venue"
},
  "geometry": {"coordinates":[-84.871726,35.15985],"type":"Point"}
}