{
  "type": "Feature",
  "properties": {
    "iso:country":"US",
    "sg:address":"5020 Bluff City Hwy",
    "sg:city":"Bluff City",
    "sg:classifiers":[
        {
            "category":"Manufacturing",
            "subcategory":"Metals",
            "type":"Manufacturing & Wholesale Goods"
        }
    ],
    "sg:phone":"+1 423 538 4990",
    "sg:postcode":"37618",
    "sg:province":"TN",
    "sg:tags":[
        "casting"
    ],
    "wof:name":"J & W Casting",
    "wof:placetype":"venue"
},
  "geometry": {"coordinates":[-82.281071,36.454643],"type":"Point"}
}