{
  "type": "Feature",
  "properties": {
    "addr:full":"1611 S Locust Ave Lawrenceburg TN 38464",
    "addr:housenumber":"1611",
    "addr:postcode":"38464",
    "addr:street":"S Locust Ave",
    "iso:country":"US",
    "sg:address":"1611 S Locust Ave",
    "sg:city":"Lawrenceburg",
    "sg:classifiers":[
        {
            "category":"Health Services",
            "subcategory":"Doctor",
            "type":"Services"
        }
    ],
    "sg:phone":"+1 931 762 6260",
    "sg:postcode":"38464",
    "sg:province":"TN",
    "sg:tags":[
        "physician",
        "surgeon"
    ],
    "wof:name":"Dayaker R Mallipeddi MD",
    "wof:placetype":"venue"
},
  "geometry": {"coordinates":[-87.337671,35.218783],"type":"Point"}
}