{
  "type": "Feature",
  "properties": {
    "iso:country":"US",
    "sg:address":"498 Cambridge Cir",
    "sg:city":"Russellville",
    "sg:classifiers":[
        {
            "category":"Retail",
            "subcategory":"Laundry & Dry Cleaning",
            "type":"Services"
        }
    ],
    "sg:phone":"+1 423 581 6730",
    "sg:postcode":"37860",
    "sg:province":"TN",
    "sg:tags":[
        "cleaners",
        "rug",
        "carpet"
    ],
    "wof:name":"Quality Carpet Cleaning",
    "wof:placetype":"venue"
},
  "geometry": {"coordinates":[-83.210503,36.255659],"type":"Point"}
}