{
  "type": "Feature",
  "properties": {
    "addr:full":"1147 Stonebridge Park Dr Franklin TN 37069",
    "addr:housenumber":"1147",
    "addr:postcode":"37069",
    "addr:street":"Stonebridge Park Dr",
    "iso:country":"US",
    "sg:address":"1147 Stonebridge Park Dr",
    "sg:city":"Franklin",
    "sg:classifiers":[
        {
            "category":"Professional",
            "subcategory":"Management & Consulting",
            "type":"Services"
        }
    ],
    "sg:phone":"+1 615 309 8219",
    "sg:postcode":"37069",
    "sg:province":"TN",
    "sg:tags":[
        "marketing",
        "consultant"
    ],
    "wof:name":"Rowan Sales & Marketing",
    "wof:placetype":"venue"
},
  "geometry": {"coordinates":[-86.892056,36.042153],"type":"Point"}
}