{
  "type": "Feature",
  "properties": {
    "iso:country":"US",
    "sg:address":"1325 Wolf Park Dr",
    "sg:city":"Germantown",
    "sg:classifiers":[
        {
            "category":"Health Services",
            "subcategory":"Clinic",
            "type":"Services"
        }
    ],
    "sg:phone":"+1 901 252 3403",
    "sg:postcode":"38138",
    "sg:province":"TN",
    "sg:tags":[
        "surgical",
        "center"
    ],
    "wof:name":"Wolf River Surgery Ctr",
    "wof:placetype":"venue"
},
  "geometry": {"coordinates":[-89.808136,35.113519],"type":"Point"}
}