{
  "type": "Feature",
  "properties": {
    "iso:country":"US",
    "sg:address":"1 Broadwood Cir",
    "sg:city":"Johnson City",
    "sg:classifiers":[
        {
            "category":"Professional",
            "subcategory":"Art Services",
            "type":"Services"
        }
    ],
    "sg:phone":"+1 423 232 2824",
    "sg:postcode":"37604",
    "sg:province":"TN",
    "sg:tags":[
        "photography",
        "commercial"
    ],
    "wof:name":"Glenn Hudson",
    "wof:placetype":"venue"
},
  "geometry": {"coordinates":[-82.379513,36.282885],"type":"Point"}
}