{
  "type": "Feature",
  "properties": {
    "addr:full":"109 Hazel Path Hendersonville TN 37075",
    "addr:housenumber":"109",
    "addr:postcode":"37075",
    "addr:street":"Hazel Path",
    "iso:country":"US",
    "sg:address":"109 Hazel Path",
    "sg:city":"Hendersonville",
    "sg:classifiers":[
        {
            "category":"Social Services",
            "type":"Services"
        }
    ],
    "sg:phone":"+1 615 824 1711",
    "sg:postcode":"37075",
    "sg:province":"TN",
    "sg:tags":[
        "professional",
        "counselor"
    ],
    "wof:name":"Floyd Dawson",
    "wof:placetype":"venue"
},
  "geometry": {"coordinates":[-86.607922,36.306083],"type":"Point"}
}