{
  "type": "Feature",
  "properties": {
    "addr:full":"255 Grandview Dr Kodak TN 37764",
    "addr:housenumber":"255",
    "addr:postcode":"37764",
    "addr:street":"Grandview Dr",
    "iso:country":"US",
    "sg:address":"255 Grandview Dr",
    "sg:city":"Kodak",
    "sg:classifiers":[
        {
            "category":"Travel",
            "subcategory":"Hotels & Motels",
            "type":"Entertainment"
        }
    ],
    "sg:phone":"+1 865 933 4496",
    "sg:postcode":"37764",
    "sg:province":"TN",
    "sg:tags":[
        "operation"
    ],
    "wof:name":"Sweetrock Cabins",
    "wof:placetype":"venue"
},
  "geometry": {"coordinates":[-83.587273,35.944417],"type":"Point"}
}