{
  "type": "Feature",
  "properties": {
    "iso:country":"US",
    "sg:address":"3600 Anderson Rd",
    "sg:city":"Nashville",
    "sg:classifiers":[
        {
            "category":"Cinema",
            "subcategory":"Movie Rental",
            "type":"Entertainment"
        }
    ],
    "sg:phone":"+1 615 360 9719",
    "sg:postcode":"37217",
    "sg:province":"TN",
    "sg:tags":[
        "leasing",
        "video",
        "disc",
        "tape"
    ],
    "wof:name":"Village Video",
    "wof:placetype":"venue"
},
  "geometry": {"coordinates":[-86.60639999999999,36.090683],"type":"Point"}
}