{
  "type": "Feature",
  "properties": {
    "iso:country":"US",
    "sg:address":"4784 State Hwy 58",
    "sg:city":"Chattanooga",
    "sg:classifiers":[
        {
            "category":"Building & Trades",
            "subcategory":"Equipment Rental",
            "type":"Services"
        }
    ],
    "sg:phone":"+1 423 499 4445",
    "sg:postcode":"37416",
    "sg:province":"TN",
    "sg:tags":[
        "leasing",
        "appliance",
        "furniture"
    ],
    "wof:name":"American Rentals",
    "wof:placetype":"venue"
},
  "geometry": {"coordinates":[-85.189572,35.087532],"type":"Point"}
}