{
  "type": "Feature",
  "properties": {
    "addr:full":"863 Rocky Forest Cove S Cordova TN 38018",
    "addr:housenumber":"863",
    "addr:postcode":"38018",
    "addr:street":"Rocky Forest Cove S Cordova",
    "iso:country":"US",
    "sg:address":"863 Rocky Forest Cove S",
    "sg:city":"Cordova",
    "sg:classifiers":[
        {
            "category":"Banks & Credit Unions",
            "subcategory":"Bank",
            "type":"Services"
        }
    ],
    "sg:phone":"+1 901 758 1992",
    "sg:postcode":"38018",
    "sg:province":"TN",
    "sg:tags":[
        "loan",
        "real estate"
    ],
    "wof:name":"E Z Credit Properties",
    "wof:placetype":"venue"
},
  "geometry": {"coordinates":[-89.751178,35.148815],"type":"Point"}
}