{
  "type": "Feature",
  "properties": {
    "iso:country":"US",
    "sg:address":"227 Y Rd",
    "sg:city":"Tazewell",
    "sg:classifiers":[
        {
            "category":"Building & Trades",
            "subcategory":"Construction",
            "type":"Services"
        }
    ],
    "sg:phone":"+1 423 626 5352",
    "sg:postcode":"37879",
    "sg:province":"TN",
    "sg:tags":[
        "excavation",
        "contractor"
    ],
    "wof:name":"Danny Coffey Construction Co",
    "wof:placetype":"venue"
},
  "geometry": {"coordinates":[-83.53457899999999,36.419915],"type":"Point"}
}