{
  "type": "Feature",
  "properties": {
    "addr:full":"66 Ned Cherry Rd Obion TN 38240",
    "addr:housenumber":"66",
    "addr:postcode":"38240",
    "addr:street":"Ned Cherry Rd",
    "iso:country":"US",
    "sg:address":"66 Ned Cherry Rd",
    "sg:city":"Obion",
    "sg:classifiers":[
        {
            "category":"Wholesale",
            "subcategory":"Farm Supplies",
            "type":"Manufacturing & Wholesale Goods"
        }
    ],
    "sg:phone":"+1 731 538 2807",
    "sg:postcode":"38240",
    "sg:province":"TN",
    "sg:tags":[
        "chemical",
        "agricultural",
        "seed",
        "fertilizer"
    ],
    "wof:name":"Lane Gin Co Inc",
    "wof:placetype":"venue"
},
  "geometry": {"coordinates":[-89.37755900000001,36.199983],"type":"Point"}
}