{
  "type": "Feature",
  "properties": {
    "addr:full":"125 International Blvd La Vergne TN 37086",
    "addr:housenumber":"125",
    "addr:postcode":"37086",
    "addr:street":"International Blvd",
    "iso:country":"US",
    "sg:address":"125 International Blvd",
    "sg:city":"La Vergne",
    "sg:classifiers":[
        {
            "category":"Wholesale",
            "subcategory":"Construction Materials",
            "type":"Manufacturing & Wholesale Goods"
        }
    ],
    "sg:phone":"+1 800 966 2568",
    "sg:postcode":"37086",
    "sg:province":"TN",
    "wof:name":"Custom - Crete",
    "wof:placetype":"venue"
},
  "geometry": {"coordinates":[-86.592743,36.014414],"type":"Point"}
}