{
  "type": "Feature",
  "properties": {
    "iso:country":"US",
    "sg:address":"102 William Northern Blvd",
    "sg:city":"Tullahoma",
    "sg:classifiers":[
        {
            "category":"Health Services",
            "subcategory":"Medical Lab",
            "type":"Services"
        }
    ],
    "sg:phone":"+1 931 455 2336",
    "sg:postcode":"37388",
    "sg:province":"TN",
    "sg:tags":[
        "laboratory"
    ],
    "wof:name":"Laboratory Corporation America",
    "wof:placetype":"venue"
},
  "geometry": {"coordinates":[-86.22938000000001,35.379207],"type":"Point"}
}