{
  "type": "Feature",
  "properties": {
    "iso:country":"US",
    "sg:address":"900 Rivergate Meadows Dr",
    "sg:city":"Goodlettsville",
    "sg:classifiers":[
        {
            "category":"Banks & Credit Unions",
            "subcategory":"Bank",
            "type":"Services"
        }
    ],
    "sg:phone":"+1 615 748 2706",
    "sg:postcode":"37072",
    "sg:province":"TN",
    "sg:website":"www.amsouth.com",
    "wof:name":"AM South Bank",
    "wof:placetype":"venue"
},
  "geometry": {"coordinates":[-86.709202,36.297318],"type":"Point"}
}