{
  "type": "Feature",
  "properties": {
    "addr:full":"203 Murrell St Dickson TN 37055",
    "addr:housenumber":"203",
    "addr:postcode":"37055",
    "addr:street":"Murrell St",
    "iso:country":"US",
    "sg:address":"203 Murrell St",
    "sg:city":"Dickson",
    "sg:classifiers":[
        {
            "category":"Personal",
            "subcategory":"Beauty Salon",
            "type":"Services"
        }
    ],
    "sg:phone":"+1 615 446 4712",
    "sg:postcode":"37055",
    "sg:province":"TN",
    "sg:tags":[
        "shop"
    ],
    "wof:name":"R P Salon",
    "wof:placetype":"venue"
},
  "geometry": {"coordinates":[-87.386909,36.077435],"type":"Point"}
}