{
  "type": "Feature",
  "properties": {
    "iso:country":"US",
    "sg:address":"1833 Welcome Ln",
    "sg:city":"Nashville",
    "sg:classifiers":[
        {
            "category":"Travel",
            "subcategory":"Hotels & Motels",
            "type":"Entertainment"
        }
    ],
    "sg:phone":"+1 615 228 8892",
    "sg:postcode":"37216",
    "sg:province":"TN",
    "sg:tags":[
        "operation"
    ],
    "sg:website":"www.riverwoodmansion.com",
    "wof:name":"Riverwood Mansion",
    "wof:placetype":"venue"
},
  "geometry": {"coordinates":[-86.71111999999999,36.199114],"type":"Point"}
}