{
  "type": "Feature",
  "properties": {
    "iso:country":"US",
    "sg:address":"2036 Westwind Dr",
    "sg:city":"Kingsport",
    "sg:classifiers":[
        {
            "category":"Professional",
            "subcategory":"Business Services",
            "type":"Services"
        }
    ],
    "sg:phone":"+1 423 378 5812",
    "sg:postcode":"37660",
    "sg:province":"TN",
    "wof:name":"Way You Live",
    "wof:placetype":"venue"
},
  "geometry": {"coordinates":[-82.599967,36.539394],"type":"Point"}
}