{
  "type": "Feature",
  "properties": {
    "iso:country":"US",
    "sg:address":"750 Adams Ave",
    "sg:city":"Memphis",
    "sg:classifiers":[
        {
            "category":"Real Estate",
            "subcategory":"Real Estate Operator",
            "type":"Services"
        }
    ],
    "sg:phone":"+1 901 525 0678",
    "sg:postcode":"38105",
    "sg:province":"TN",
    "sg:tags":[
        "apartment"
    ],
    "wof:name":"750 Adams Place",
    "wof:placetype":"venue"
},
  "geometry": {"coordinates":[-90.035613,35.143909],"type":"Point"}
}