{
  "type": "Feature",
  "properties": {
    "iso:country":"US",
    "sg:address":"1275 Wildwood Ave SE",
    "sg:city":"Cleveland",
    "sg:classifiers":[
        {
            "category":"Autos & Motor Vehicles",
            "subcategory":"Automobile Sales",
            "type":"Retail Goods"
        }
    ],
    "sg:phone":"+1 423 559 8095",
    "sg:postcode":"37311",
    "sg:province":"TN",
    "sg:tags":[
        "car",
        "used"
    ],
    "wof:name":"B & C Auto Sales",
    "wof:placetype":"venue"
},
  "geometry": {"coordinates":[-84.869567,35.145967],"type":"Point"}
}