{
  "type": "Feature",
  "properties": {
    "addr:full":"111 4th Ave S Nashville TN 37210",
    "addr:housenumber":"111",
    "addr:postcode":"37210",
    "addr:street":"4Th Ave S",
    "iso:country":"US",
    "sg:address":"111 4th Ave S",
    "sg:city":"Nashville",
    "sg:classifiers":[
        {
            "category":"Banks & Credit Unions",
            "subcategory":"Investment Brokerage",
            "type":"Services"
        },
        {
            "category":"Professional",
            "subcategory":"Management & Consulting",
            "type":"Services"
        }
    ],
    "sg:phone":"+1 615 369 6400",
    "sg:postcode":"37210",
    "sg:province":"TN",
    "sg:tags":[
        "consultant",
        "planning",
        "financial"
    ],
    "wof:name":"Jr S Investment Inc",
    "wof:placetype":"venue"
},
  "geometry": {"coordinates":[-86.77715000000001,36.160818],"type":"Point"}
}