{
  "type": "Feature",
  "properties": {
    "iso:country":"US",
    "sg:address":"1917 Church St",
    "sg:city":"Nashville",
    "sg:classifiers":[
        {
            "category":"Wholesale",
            "subcategory":"Furniture",
            "type":"Manufacturing & Wholesale Goods"
        }
    ],
    "sg:phone":"+1 615 327 2405",
    "sg:postcode":"37219",
    "sg:province":"TN",
    "wof:name":"Office Furniture NASHVILLE",
    "wof:placetype":"venue"
},
  "geometry": {"coordinates":[-86.80055,36.153495],"type":"Point"}
}