{
  "type": "Feature",
  "properties": {
    "iso:country":"US",
    "sg:address":"6700 E Dick Ford Ln",
    "sg:city":"Knoxville",
    "sg:classifiers":[
        {
            "category":"Building & Trades",
            "subcategory":"Electrical",
            "type":"Services"
        },
        {
            "category":"Building & Trades",
            "subcategory":"Landscaping Services",
            "type":"Services"
        }
    ],
    "sg:phone":"+1 865 609 9634",
    "sg:postcode":"37920",
    "sg:province":"TN",
    "sg:tags":[
        "lighting",
        "landscape"
    ],
    "wof:name":"Easy Gardener Inc",
    "wof:placetype":"venue"
},
  "geometry": {"coordinates":[-83.857202,35.917677],"type":"Point"}
}