{
  "type": "Feature",
  "properties": {
    "addr:full":"2640 Rental Rd Memphis TN 38118",
    "addr:housenumber":"2640",
    "addr:postcode":"38118",
    "addr:street":"Rental Rd",
    "iso:country":"US",
    "sg:address":"2640 Rental Rd",
    "sg:city":"Memphis",
    "sg:classifiers":[
        {
            "category":"Building & Trades",
            "subcategory":"Construction",
            "type":"Services"
        }
    ],
    "sg:phone":"+1 901 395 0122",
    "sg:postcode":"38118",
    "sg:province":"TN",
    "sg:tags":[
        "pipe",
        "line",
        "contractor"
    ],
    "wof:name":"Buckeye Partners",
    "wof:placetype":"venue"
},
  "geometry": {"coordinates":[-89.97569900000001,35.069539],"type":"Point"}
}