{
  "type": "Feature",
  "properties": {
    "iso:country":"US",
    "sg:address":"113 Dellwood Ln",
    "sg:city":"Johnson City",
    "sg:classifiers":[
        {
            "category":"Building & Trades",
            "subcategory":"Plumbing",
            "type":"Services"
        }
    ],
    "sg:phone":"+1 423 477 7774",
    "sg:postcode":"37615",
    "sg:province":"TN",
    "sg:tags":[
        "conditioning",
        "contractor"
    ],
    "wof:name":"James Moses Plumbing & Repair",
    "wof:placetype":"venue"
},
  "geometry": {"coordinates":[-82.41869,36.407779],"type":"Point"}
}