{
  "type": "Feature",
  "properties": {
    "iso:country":"US",
    "sg:address":"4539 Winchester Rd",
    "sg:city":"Memphis",
    "sg:classifiers":[
        {
            "category":"Recreation",
            "subcategory":"Arcade",
            "type":"Entertainment"
        }
    ],
    "sg:phone":"+1 901 433 0891",
    "sg:postcode":"38118",
    "sg:province":"TN",
    "sg:tags":[
        "amusement",
        "devices"
    ],
    "wof:name":"Eagle Distributing Co",
    "wof:placetype":"venue"
},
  "geometry": {"coordinates":[-89.914272,35.051241],"type":"Point"}
}