{
  "type": "Feature",
  "properties": {
    "addr:full":"112 Peach Tree Rd Byhalia TN 38611",
    "addr:housenumber":"112",
    "addr:postcode":"38611",
    "addr:street":"Peach Tree Rd",
    "iso:country":"US",
    "sg:address":"112 Peach Tree Rd",
    "sg:city":"Byhalia",
    "sg:classifiers":[
        {
            "category":"Building & Trades",
            "subcategory":"Construction",
            "type":"Services"
        }
    ],
    "sg:phone":"+1 662 838 4126",
    "sg:postcode":"38611",
    "sg:province":"TN",
    "sg:tags":[
        "house"
    ],
    "wof:name":"Bristow Construction",
    "wof:placetype":"venue"
},
  "geometry": {"coordinates":[-89.695859,34.894555],"type":"Point"}
}