{
  "type": "Feature",
  "properties": {
    "iso:country":"US",
    "sg:address":"823 N 2nd St",
    "sg:city":"Memphis",
    "sg:classifiers":[
        {
            "category":"Social Services",
            "subcategory":"Child Care",
            "type":"Services"
        }
    ],
    "sg:phone":"+1 901 523 8755",
    "sg:postcode":"38107",
    "sg:province":"TN",
    "wof:name":"Noah's Ark Christian Learning",
    "wof:placetype":"venue"
},
  "geometry": {"coordinates":[-90.043783,35.164362],"type":"Point"}
}