{
  "type": "Feature",
  "properties": {
    "addr:full":"675 Hwy 57 Grand Junction TN 38039",
    "addr:housenumber":"675",
    "addr:postcode":"38039",
    "addr:street":"Hwy 57",
    "iso:country":"US",
    "sg:address":"675 Hwy 57",
    "sg:city":"Grand Junction",
    "sg:classifiers":[
        {
            "category":"Travel",
            "subcategory":"Hotels & Motels",
            "type":"Entertainment"
        }
    ],
    "sg:phone":"+1 901 878 0031",
    "sg:postcode":"38039",
    "sg:province":"TN",
    "sg:tags":[
        "operation"
    ],
    "wof:name":"Hobsons Vacation Inn",
    "wof:placetype":"venue"
},
  "geometry": {"coordinates":[-89.17424099999999,35.050476],"type":"Point"}
}