{
  "type": "Feature",
  "properties": {
    "iso:country":"US",
    "sg:address":"2912 Donna Hill Dr",
    "sg:city":"Nashville",
    "sg:classifiers":[
        {
            "category":"Health Services",
            "subcategory":"Clinic",
            "type":"Services"
        }
    ],
    "sg:phone":"+1 615 872 9487",
    "sg:postcode":"37214",
    "sg:province":"TN",
    "sg:tags":[
        "home",
        "care"
    ],
    "wof:name":"Preciuos Touch Home Care Svc",
    "wof:placetype":"venue"
},
  "geometry": {"coordinates":[-86.682149,36.19874],"type":"Point"}
}