{
  "type": "Feature",
  "properties": {
    "iso:country":"US",
    "sg:address":"11130 Kingston Pike",
    "sg:city":"Knoxville",
    "sg:classifiers":[
        {
            "category":"Shopping",
            "subcategory":"Pharmacy",
            "type":"Retail Goods"
        }
    ],
    "sg:phone":"+1 865 675 4730",
    "sg:postcode":"37934",
    "sg:province":"TN",
    "wof:name":"Drugstore",
    "wof:placetype":"venue"
},
  "geometry": {"coordinates":[-84.15093,35.886019],"type":"Point"}
}