{
  "type": "Feature",
  "properties": {
    "iso:country":"US",
    "sg:address":"752 Hwy 13",
    "sg:city":"Cunningham",
    "sg:classifiers":[
        {
            "category":"Restaurant",
            "type":"Food & Drink"
        }
    ],
    "sg:phone":"+1 931 387 3555",
    "sg:postcode":"37052",
    "sg:province":"TN",
    "sg:tags":[
        "eating"
    ],
    "wof:name":"Country Diner",
    "wof:placetype":"venue"
},
  "geometry": {"coordinates":[-87.410698,36.384374],"type":"Point"}
}