{
  "type": "Feature",
  "properties": {
    "addr:full":"3955 New Highway 96 W Franklin TN 37064",
    "addr:housenumber":"3955",
    "addr:postcode":"37064",
    "addr:street":"New Highway 96 W",
    "iso:country":"US",
    "sg:address":"3955 New Highway 96 W",
    "sg:city":"Franklin",
    "sg:classifiers":[
        {
            "category":"Real Estate",
            "subcategory":"Developer",
            "type":"Services"
        }
    ],
    "sg:phone":"+1 615 794 6250",
    "sg:postcode":"37064",
    "sg:province":"TN",
    "sg:tags":[
        "development"
    ],
    "wof:name":"Reed Development",
    "wof:placetype":"venue"
},
  "geometry": {"coordinates":[-86.99982199999999,35.989934],"type":"Point"}
}