{
  "type": "Feature",
  "properties": {
    "addr:full":"3001 Bus Park Cir Goodlettsville TN 37072",
    "addr:housenumber":"3001",
    "addr:postcode":"37072",
    "addr:street":"Bus Park Cir",
    "iso:country":"US",
    "sg:address":"3001 Bus Park Cir",
    "sg:city":"Goodlettsville",
    "sg:classifiers":[
        {
            "category":"Health Services",
            "subcategory":"Nursing And Care Facility",
            "type":"Services"
        }
    ],
    "sg:phone":"+1 615 855 2040",
    "sg:postcode":"37072",
    "sg:province":"TN",
    "sg:tags":[
        "skilled"
    ],
    "wof:name":"Clare Brdge Cttage Gdlttsville",
    "wof:placetype":"venue"
},
  "geometry": {"coordinates":[-86.70066199999999,36.330147],"type":"Point"}
}