{
  "type": "Feature",
  "properties": {
    "iso:country":"US",
    "sg:address":"58 Oakhaven Dr",
    "sg:city":"Jackson",
    "sg:classifiers":[
        {
            "category":"Real Estate",
            "subcategory":"Real Estate Agent",
            "type":"Services"
        }
    ],
    "sg:phone":"+1 731 660 4663",
    "sg:postcode":"38305",
    "sg:province":"TN",
    "wof:name":"Merit Management",
    "wof:placetype":"venue"
},
  "geometry": {"coordinates":[-88.883419,35.701526],"type":"Point"}
}