{
  "type": "Feature",
  "properties": {
    "iso:country":"US",
    "sg:address":"113 Glenmont Dr",
    "sg:city":"Nashville",
    "sg:classifiers":[
        {
            "category":"Real Estate",
            "subcategory":"Real Estate Agent",
            "type":"Services"
        }
    ],
    "sg:phone":"+1 615 445 4566",
    "sg:postcode":"37210",
    "sg:province":"TN",
    "wof:name":"Wayne Harrell Realty",
    "wof:placetype":"venue"
},
  "geometry": {"coordinates":[-86.72318799999999,36.113438],"type":"Point"}
}