{
  "type": "Feature",
  "properties": {
    "iso:country":"US",
    "sg:address":"200 Narrow Gauge Rd",
    "sg:city":"Trenton",
    "sg:classifiers":[
        {
            "category":"Building & Trades",
            "subcategory":"Plumbing",
            "type":"Services"
        }
    ],
    "sg:phone":"+1 731 855 0043",
    "sg:postcode":"38382",
    "sg:province":"TN",
    "sg:tags":[
        "plumbing",
        "contractor"
    ],
    "wof:name":"Decker Plumbing & Sewer Svc",
    "wof:placetype":"venue"
},
  "geometry": {"coordinates":[-88.930336,36.018601],"type":"Point"}
}