{
  "type": "Feature",
  "properties": {
    "addr:full":"247 Slab Town Rd Sweetwater TN 37874",
    "addr:housenumber":"247",
    "addr:postcode":"37874",
    "addr:street":"Slab Town Rd",
    "iso:country":"US",
    "sg:address":"247 Slab Town Rd",
    "sg:city":"Sweetwater",
    "sg:classifiers":[
        {
            "category":"Shopping",
            "subcategory":"Crafts & Fabrics",
            "type":"Retail Goods"
        }
    ],
    "sg:phone":"+1 865 213 5642",
    "sg:postcode":"37874",
    "sg:province":"TN",
    "sg:tags":[
        "sewing"
    ],
    "wof:name":"Grannys Quilting Shop",
    "wof:placetype":"venue"
},
  "geometry": {"coordinates":[-84.568457,35.636668],"type":"Point"}
}