{
  "type": "Feature",
  "properties": {
    "addr:full":"603 Davidson St Nashville TN 37206",
    "addr:housenumber":"603",
    "addr:postcode":"37206",
    "addr:street":"Davidson St",
    "iso:country":"US",
    "sg:address":"603 Davidson St",
    "sg:city":"Nashville",
    "sg:classifiers":[
        {
            "category":"Manufacturing",
            "subcategory":"Building Materials",
            "type":"Manufacturing & Wholesale Goods"
        }
    ],
    "sg:phone":"+1 615 254 1710",
    "sg:postcode":"37206",
    "sg:province":"TN",
    "sg:tags":[
        "woodwork",
        "architectural",
        "mfg"
    ],
    "wof:name":"Cumberland Architectural Mllwk",
    "wof:placetype":"venue"
},
  "geometry": {"coordinates":[-86.755714,36.161447],"type":"Point"}
}