{
  "type": "Feature",
  "properties": {
    "addr:full":"12 Executive Park Dr Hendersonville TN 37075",
    "addr:housenumber":"12",
    "addr:postcode":"37075",
    "addr:street":"Executive Park Dr",
    "iso:country":"US",
    "sg:address":"12 Executive Park Dr",
    "sg:city":"Hendersonville",
    "sg:classifiers":[
        {
            "category":"Wholesale",
            "subcategory":"Hardware",
            "type":"Manufacturing & Wholesale Goods"
        }
    ],
    "sg:phone":"+1 615 822 2420",
    "sg:postcode":"37075",
    "sg:province":"TN",
    "sg:tags":[
        "tool"
    ],
    "wof:name":"R & K Tool Sales Inc",
    "wof:placetype":"venue"
},
  "geometry": {"coordinates":[-86.62808,36.302589],"type":"Point"}
}