{
  "type": "Feature",
  "properties": {
    "addr:full":"227 Mockingbird Rd Nashville TN 37205",
    "addr:housenumber":"227",
    "addr:postcode":"37205",
    "addr:street":"Mockingbird Rd",
    "iso:country":"US",
    "sg:address":"227 Mockingbird Rd",
    "sg:city":"Nashville",
    "sg:classifiers":[
        {
            "category":"Professional",
            "subcategory":"Management & Consulting",
            "type":"Services"
        }
    ],
    "sg:phone":"+1 615 269 7771",
    "sg:postcode":"37205",
    "sg:province":"TN",
    "sg:tags":[
        "business"
    ],
    "wof:name":"Bls Systems LLC",
    "wof:placetype":"venue"
},
  "geometry": {"coordinates":[-86.838228,36.135162],"type":"Point"}
}