{
  "type": "Feature",
  "properties": {
    "addr:full":"218 S Church St Waverly TN 37185",
    "addr:housenumber":"218",
    "addr:postcode":"37185",
    "addr:street":"S Church St",
    "iso:country":"US",
    "sg:address":"218 S Church St",
    "sg:city":"Waverly",
    "sg:classifiers":[
        {
            "category":"Restaurant",
            "type":"Food & Drink"
        }
    ],
    "sg:phone":"+1 931 296 9897",
    "sg:postcode":"37185",
    "sg:province":"TN",
    "wof:name":"Townhill Restaurant",
    "wof:placetype":"venue"
},
  "geometry": {"coordinates":[-87.79464,36.081232],"type":"Point"}
}