{
  "type": "Feature",
  "properties": {
    "addr:full":"3299 Tulane Rd Memphis TN 38116",
    "addr:housenumber":"3299",
    "addr:postcode":"38116",
    "addr:street":"Tulane Rd",
    "iso:country":"US",
    "sg:address":"3299 Tulane Rd",
    "sg:city":"Memphis",
    "sg:classifiers":[
        {
            "category":"Manufacturing",
            "subcategory":"Metals",
            "type":"Manufacturing & Wholesale Goods"
        }
    ],
    "sg:phone":"+1 901 396 6484",
    "sg:postcode":"38116",
    "sg:province":"TN",
    "sg:tags":[
        "barrels",
        "drum"
    ],
    "sg:website":"www.drumco.com",
    "wof:name":"Drumco Of Tennessee Inc",
    "wof:placetype":"venue"
},
  "geometry": {"coordinates":[-90.046375,35.061529],"type":"Point"}
}