{
  "type": "Feature",
  "properties": {
    "addr:full":"5767 E Shelby Dr Memphis TN 38118",
    "addr:housenumber":"5767",
    "addr:postcode":"38118",
    "addr:street":"E Shelby Dr",
    "iso:country":"US",
    "sg:address":"5767 E Shelby Dr",
    "sg:city":"Memphis",
    "sg:classifiers":[
        {
            "category":"Wholesale",
            "subcategory":"Hardware",
            "type":"Manufacturing & Wholesale Goods"
        }
    ],
    "sg:phone":"+1 901 797 8000",
    "sg:postcode":"38118",
    "sg:province":"TN",
    "sg:tags":[
        "equipment",
        "locksmith",
        "supply"
    ],
    "wof:name":"Mc Donald-Dash Locksmith Supl",
    "wof:placetype":"venue"
},
  "geometry": {"coordinates":[-89.86999900000001,35.020236],"type":"Point"}
}