{
  "type": "Feature",
  "properties": {
    "iso:country":"US",
    "sg:address":"1017 E 38th St",
    "sg:city":"Chattanooga",
    "sg:classifiers":[
        {
            "category":"Manufacturing",
            "subcategory":"Glass & Minerals",
            "type":"Manufacturing & Wholesale Goods"
        }
    ],
    "sg:phone":"+1 423 867 5417",
    "sg:postcode":"37407",
    "sg:province":"TN",
    "sg:tags":[
        "ready",
        "concrete",
        "mfg"
    ],
    "wof:name":"Trenton Ready Mix",
    "wof:placetype":"venue"
},
  "geometry": {"coordinates":[-85.304132,35.003245],"type":"Point"}
}