{
  "type": "Feature",
  "properties": {
    "iso:country":"US",
    "sg:address":"1 Outlet Village Blvd",
    "sg:city":"Lebanon",
    "sg:classifiers":[
        {
            "category":"Manufacturing",
            "subcategory":"Apparel",
            "type":"Manufacturing & Wholesale Goods"
        }
    ],
    "sg:phone":"+1 615 443 2954",
    "sg:postcode":"37090",
    "sg:province":"TN",
    "sg:tags":[
        "furnishing",
        "mfg"
    ],
    "wof:name":"Van Heusen",
    "wof:placetype":"venue"
},
  "geometry": {"coordinates":[-86.304975,36.178566],"type":"Point"}
}