{
  "type": "Feature",
  "properties": {
    "iso:country":"US",
    "sg:address":"2156 N Highland Ave",
    "sg:city":"Jackson",
    "sg:classifiers":[
        {
            "category":"Shopping",
            "type":"Retail Goods"
        }
    ],
    "sg:phone":"+1 731 664 4408",
    "sg:postcode":"38305",
    "sg:province":"TN",
    "sg:tags":[
        "hearing",
        "equipment",
        "supply",
        "impaired"
    ],
    "wof:name":"Beltone Hearing Aid Ctr",
    "wof:placetype":"venue"
},
  "geometry": {"coordinates":[-88.828226,35.660913],"type":"Point"}
}