{
  "type": "Feature",
  "properties": {
    "addr:full":"5407 Elmhurst Ave Memphis TN 38115",
    "addr:housenumber":"5407",
    "addr:postcode":"38115",
    "addr:street":"Elmhurst Ave",
    "iso:country":"US",
    "sg:address":"5407 Elmhurst Ave",
    "sg:city":"Memphis",
    "sg:classifiers":[
        {
            "category":"Organizations",
            "subcategory":"Religious Organization",
            "type":"Services"
        }
    ],
    "sg:phone":"+1 901 365 7086",
    "sg:postcode":"38115",
    "sg:province":"TN",
    "wof:name":"Christ Tabernacle",
    "wof:placetype":"venue"
},
  "geometry": {"coordinates":[-89.882172,35.069762],"type":"Point"}
}