{
  "type": "Feature",
  "properties": {
    "iso:country":"US",
    "sg:address":"2029 Fletcher Creek Dr",
    "sg:city":"Memphis",
    "sg:classifiers":[
        {
            "category":"Building & Trades",
            "subcategory":"Electrical",
            "type":"Services"
        }
    ],
    "sg:phone":"+1 901 373 4339",
    "sg:postcode":"38133",
    "sg:province":"TN",
    "sg:tags":[
        "industrial",
        "electrician",
        "contractors-commercial",
        "electric"
    ],
    "sg:website":"http://www.ekmark.com",
    "wof:name":"Electrical Contractor",
    "wof:placetype":"venue"
},
  "geometry": {"coordinates":[-89.838928,35.181021],"type":"Point"}
}