{
  "type": "Feature",
  "properties": {
    "addr:full":"113 Shelby St Kingsport TN 37660",
    "addr:housenumber":"113",
    "addr:postcode":"37660",
    "addr:street":"Shelby St",
    "iso:country":"US",
    "sg:address":"113 Shelby St",
    "sg:city":"Kingsport",
    "sg:classifiers":[
        {
            "category":"Wholesale",
            "subcategory":"Auto Parts",
            "type":"Manufacturing & Wholesale Goods"
        }
    ],
    "sg:phone":"+1 423 246 5550",
    "sg:postcode":"37660",
    "sg:province":"TN",
    "wof:name":"Carquest Auto Parts",
    "wof:placetype":"venue"
},
  "geometry": {"coordinates":[-82.561894,36.546841],"type":"Point"}
}