{
  "type": "Feature",
  "properties": {
    "addr:full":"1127 N Park Ave Brownsville TN 38012",
    "addr:housenumber":"1127",
    "addr:postcode":"38012",
    "addr:street":"N Park Ave",
    "iso:country":"US",
    "sg:address":"1127 N Park Ave",
    "sg:city":"Brownsville",
    "sg:classifiers":[
        {
            "category":"Freight",
            "type":"Transportation"
        }
    ],
    "sg:phone":"+1 731 772 4348",
    "sg:postcode":"38012",
    "sg:province":"TN",
    "sg:tags":[
        "terminal",
        "truck",
        "facility"
    ],
    "wof:name":"Lewis Brothers Trucking",
    "wof:placetype":"venue"
},
  "geometry": {"coordinates":[-89.25594100000001,35.604987],"type":"Point"}
}