{
  "type": "Feature",
  "properties": {
    "addr:full":"5449 Old Hwy 13 Cumberland City TN 37050",
    "addr:housenumber":"5449",
    "addr:postcode":"37050",
    "addr:street":"Old Hwy 13",
    "iso:country":"US",
    "sg:address":"5449 Old Hwy 13",
    "sg:city":"Cumberland City",
    "sg:classifiers":[
        {
            "category":"Shopping",
            "type":"Retail Goods"
        }
    ],
    "sg:phone":"+1 931 648 1410",
    "sg:postcode":"37050",
    "sg:province":"TN",
    "sg:tags":[
        "awning",
        "canopy"
    ],
    "wof:name":"Clarksville Aluminum Works",
    "wof:placetype":"venue"
},
  "geometry": {"coordinates":[-87.57005100000001,36.343683],"type":"Point"}
}