{
  "type": "Feature",
  "properties": {
    "iso:country":"US",
    "sg:address":"5205 Bobby Hicks Hwy",
    "sg:city":"Johnson City",
    "sg:classifiers":[
        {
            "category":"Restaurant",
            "type":"Food & Drink"
        }
    ],
    "sg:phone":"+1 423 477 0333",
    "sg:postcode":"37615",
    "sg:province":"TN",
    "sg:website":"www.zeros.com",
    "wof:name":"Zeros Subs",
    "wof:placetype":"venue"
},
  "geometry": {"coordinates":[-82.471801,36.413183],"type":"Point"}
}