{
  "type": "Feature",
  "properties": {
    "iso:country":"US",
    "sg:address":"615 E Andrew Johnson Hwy",
    "sg:city":"Greeneville",
    "sg:classifiers":[
        {
            "category":"Real Estate",
            "subcategory":"Real Estate Services",
            "type":"Services"
        }
    ],
    "sg:phone":"+1 423 636 0014",
    "sg:postcode":"37745",
    "sg:province":"TN",
    "sg:tags":[
        "company",
        "title"
    ],
    "wof:name":"By Pass Title Loan",
    "wof:placetype":"venue"
},
  "geometry": {"coordinates":[-82.813281,36.180139],"type":"Point"}
}