{
  "type": "Feature",
  "properties": {
    "addr:full":"4850 Hixson Pike Hixson TN 37343",
    "addr:housenumber":"4850",
    "addr:postcode":"37343",
    "addr:street":"Hixson Pike",
    "iso:country":"US",
    "sg:address":"4850 Hixson Pike",
    "sg:city":"Hixson",
    "sg:classifiers":[
        {
            "category":"Restaurant",
            "type":"Food & Drink"
        }
    ],
    "sg:menulink":"http://www.allmenus.com/tn/chattanooga/246284-krystal/menu/",
    "sg:phone":"+1 423 636 8124",
    "sg:postcode":"37343",
    "sg:province":"TN",
    "sg:tags":[
        "burger",
        "american"
    ],
    "wof:name":"Krystal",
    "wof:placetype":"venue"
},
  "geometry": {"coordinates":[-85.24630399999999,35.128707],"type":"Point"}
}