{
  "type": "Feature",
  "properties": {
    "addr:full":"600 E Church St Lewisburg TN 37091",
    "addr:housenumber":"600",
    "addr:postcode":"37091",
    "addr:street":"E Church St",
    "iso:country":"US",
    "sg:address":"600 E Church St",
    "sg:city":"Lewisburg",
    "sg:classifiers":[
        {
            "category":"Banks & Credit Unions",
            "subcategory":"Bank",
            "type":"Services"
        }
    ],
    "sg:phone":"+1 931 359 3911",
    "sg:postcode":"37091",
    "sg:province":"TN",
    "wof:name":"Epco Credit UNION",
    "wof:placetype":"venue"
},
  "geometry": {"coordinates":[-86.780845,35.449946],"type":"Point"}
}