{
  "type": "Feature",
  "properties": {
    "addr:full":"1469 Poplar Ave Memphis TN 38104",
    "addr:housenumber":"1469",
    "addr:postcode":"38104",
    "addr:street":"Poplar Ave",
    "iso:country":"US",
    "sg:address":"1469 Poplar Ave",
    "sg:city":"Memphis",
    "sg:classifiers":[
        {
            "category":"Professional",
            "type":"Services"
        }
    ],
    "sg:phone":"+1 901 278 2390",
    "sg:postcode":"38104",
    "sg:province":"TN",
    "sg:tags":[
        "establishment"
    ],
    "wof:name":"SBP",
    "wof:placetype":"venue"
},
  "geometry": {"coordinates":[-90.011833,35.143605],"type":"Point"}
}