{
  "type": "Feature",
  "properties": {
    "iso:country":"US",
    "sg:address":"3820 Cleghorn Ave",
    "sg:city":"Nashville",
    "sg:classifiers":[
        {
            "category":"Sports & Exercise",
            "subcategory":"Gym",
            "type":"Entertainment"
        }
    ],
    "sg:phone":"+1 615 383 3456",
    "sg:postcode":"37215",
    "sg:province":"TN",
    "sg:tags":[
        "club",
        "health",
        "studio",
        "gymnasium"
    ],
    "wof:name":"Club At Green Hills",
    "wof:placetype":"venue"
},
  "geometry": {"coordinates":[-86.819334,36.107161],"type":"Point"}
}