{
  "type": "Feature",
  "properties": {
    "iso:country":"US",
    "sg:address":"775 Tanglewood St",
    "sg:city":"Memphis",
    "sg:classifiers":[
        {
            "category":"Organizations",
            "subcategory":"Religious Organization",
            "type":"Services"
        }
    ],
    "sg:phone":"+1 901 726 4028",
    "sg:postcode":"38104",
    "sg:province":"TN",
    "wof:name":"Word Of Truth MB Church",
    "wof:placetype":"venue"
},
  "geometry": {"coordinates":[-89.99336700000001,35.124964],"type":"Point"}
}