{
  "type": "Feature",
  "properties": {
    "iso:country":"US",
    "sg:address":"801 Wilson Ave",
    "sg:city":"Tullahoma",
    "sg:classifiers":[
        {
            "category":"Health Services",
            "subcategory":"Nursing And Care Facility",
            "type":"Services"
        }
    ],
    "sg:phone":"+1 931 455 2000",
    "sg:postcode":"37388",
    "sg:province":"TN",
    "sg:tags":[
        "intermediate"
    ],
    "wof:name":"Place At Tullahoma",
    "wof:placetype":"venue"
},
  "geometry": {"coordinates":[-86.22722899999999,35.364995],"type":"Point"}
}