{
  "type": "Feature",
  "properties": {
    "iso:country":"US",
    "sg:address":"122 E Main St",
    "sg:city":"Adamsville",
    "sg:classifiers":[
        {
            "category":"Shopping",
            "subcategory":"Computers & Home Electronics",
            "type":"Retail Goods"
        }
    ],
    "sg:phone":"+1 731 632 3550",
    "sg:postcode":"38310",
    "sg:province":"TN",
    "sg:tags":[
        "equipment",
        "dealer"
    ],
    "sg:website":"www.cyber-tech-systems.com",
    "wof:name":"Cyber Tech Systems",
    "wof:placetype":"venue"
},
  "geometry": {"coordinates":[-88.393818,35.236042],"type":"Point"}
}