{
  "type": "Feature",
  "properties": {
    "iso:country":"US",
    "sg:address":"392 Allie Boynton Dr",
    "sg:city":"Manchester",
    "sg:classifiers":[
        {
            "category":"Retail",
            "subcategory":"Auto Repair",
            "type":"Services"
        }
    ],
    "sg:phone":"+1 931 728 3002",
    "sg:postcode":"37355",
    "sg:province":"TN",
    "sg:tags":[
        "repairing",
        "automobile"
    ],
    "wof:name":"Us Diesal & Auto Repair 24hr",
    "wof:placetype":"venue"
},
  "geometry": {"coordinates":[-86.15800299999999,35.554832],"type":"Point"}
}