{
  "type": "Feature",
  "properties": {
    "iso:country":"US",
    "sg:address":"P.O. Box 171062",
    "sg:city":"Nashville",
    "sg:classifiers":[
        {
            "category":"Professional",
            "subcategory":"Computer Services",
            "type":"Services"
        }
    ],
    "sg:phone":"+1 615 366 7281",
    "sg:postcode":"37217",
    "sg:province":"TN",
    "sg:website":"http://www.universalrobotics.com/",
    "wof:name":"Universal Robotics",
    "wof:placetype":"venue"
},
  "geometry": {"coordinates":[-86.662914,36.107372],"type":"Point"}
}