{
  "type": "Feature",
  "properties": {
    "iso:country":"US",
    "sg:address":"520 N McCombs St",
    "sg:city":"Martin",
    "sg:classifiers":[
        {
            "category":"Education",
            "subcategory":"School",
            "type":"Public Place"
        }
    ],
    "sg:phone":"+1 731 587 0879",
    "sg:postcode":"38237",
    "sg:province":"TN",
    "wof:name":"Unity Christian School",
    "wof:placetype":"venue"
},
  "geometry": {"coordinates":[-88.846897,36.345887],"type":"Point"}
}