{
  "type": "Feature",
  "properties": {
    "addr:full":"121 Hull Rd Madisonville TN 37354",
    "addr:housenumber":"121",
    "addr:postcode":"37354",
    "addr:street":"Hull Rd",
    "iso:country":"US",
    "sg:address":"121 Hull Rd",
    "sg:city":"Madisonville",
    "sg:classifiers":[
        {
            "category":"Banks & Credit Unions",
            "subcategory":"Investment Brokerage",
            "type":"Services"
        }
    ],
    "sg:phone":"+1 423 420 9680",
    "sg:postcode":"37354",
    "sg:province":"TN",
    "sg:tags":[
        "security"
    ],
    "wof:name":"Mike McKenzie",
    "wof:placetype":"venue"
},
  "geometry": {"coordinates":[-84.34238999999999,35.575682],"type":"Point"}
}