{
  "type": "Feature",
  "properties": {
    "iso:country":"US",
    "sg:address":"4362 Chickering Ln",
    "sg:city":"Nashville",
    "sg:classifiers":[
        {
            "category":"Professional",
            "subcategory":"Lawyer & Legal Services",
            "type":"Services"
        }
    ],
    "sg:phone":"+1 615 371 8550",
    "sg:postcode":"37215",
    "sg:province":"TN",
    "sg:tags":[
        "attorney"
    ],
    "wof:name":"Hagerty Peterson & Co",
    "wof:placetype":"venue"
},
  "geometry": {"coordinates":[-86.86071699999999,36.069493],"type":"Point"}
}