{
  "type": "Feature",
  "properties": {
    "iso:country":"US",
    "sg:address":"3055 Lebanon Pike # 1000",
    "sg:city":"Nashville",
    "sg:classifiers":[
        {
            "category":"Professional",
            "type":"Services"
        }
    ],
    "sg:phone":"+1 615 932 3000",
    "sg:postcode":"37214",
    "sg:province":"TN",
    "sg:tags":[
        "processing",
        "data"
    ],
    "sg:website":"http://www.emdeon.com",
    "wof:name":"Emdeon, Inc.",
    "wof:placetype":"venue"
},
  "geometry": {"coordinates":[-86.644676,36.178211],"type":"Point"}
}