{
  "type": "Feature",
  "properties": {
    "iso:country":"US",
    "sg:address":"120 Fain St",
    "sg:city":"Nashville",
    "sg:classifiers":[
        {
            "category":"Organizations",
            "subcategory":"Religious Organization",
            "type":"Services"
        }
    ],
    "sg:phone":"+1 615 256 6435",
    "sg:postcode":"37210",
    "sg:province":"TN",
    "sg:tags":[
        "church"
    ],
    "wof:name":"Fairfield Missionary Baptist",
    "wof:placetype":"venue"
},
  "geometry": {"coordinates":[-86.75568800000001,36.151634],"type":"Point"}
}