{
  "type": "Feature",
  "properties": {
    "iso:country":"US",
    "sg:address":"556 Annex Ave",
    "sg:city":"Nashville",
    "sg:classifiers":[
        {
            "category":"Retail",
            "subcategory":"Repair Shop",
            "type":"Services"
        }
    ],
    "sg:phone":"+1 615 356 8774",
    "sg:postcode":"37209",
    "sg:province":"TN",
    "sg:tags":[
        "welding"
    ],
    "wof:name":"Bud Love Welding",
    "wof:placetype":"venue"
},
  "geometry": {"coordinates":[-86.87832400000001,36.158555],"type":"Point"}
}