{
  "type": "Feature",
  "properties": {
    "addr:full":"3600 Sylvia Rd Dickson TN 37055",
    "addr:housenumber":"3600",
    "addr:postcode":"37055",
    "addr:street":"Sylvia Rd",
    "iso:country":"US",
    "sg:address":"3600 Sylvia Rd",
    "sg:city":"Dickson",
    "sg:classifiers":[
        {
            "category":"Farming",
            "subcategory":"Livestock Farm",
            "type":"Manufacturing & Wholesale Goods"
        }
    ],
    "sg:phone":"+1 615 789 5611",
    "sg:postcode":"37055",
    "sg:province":"TN",
    "sg:tags":[
        "beef",
        "feedlot",
        "cattle"
    ],
    "wof:name":"J Strokes",
    "wof:placetype":"venue"
},
  "geometry": {"coordinates":[-87.44048100000001,36.181112],"type":"Point"}
}