{
  "type": "Feature",
  "properties": {
    "iso:country":"US",
    "sg:address":"2220 Cornwall St",
    "sg:city":"Germantown",
    "sg:classifiers":[
        {
            "category":"Social Services",
            "type":"Services"
        }
    ],
    "sg:phone":"+1 901 751 8477",
    "sg:postcode":"38138",
    "sg:province":"TN",
    "sg:tags":[
        "worker"
    ],
    "wof:name":"Mike Gooch",
    "wof:placetype":"venue"
},
  "geometry": {"coordinates":[-89.821805,35.088159],"type":"Point"}
}