{
  "type": "Feature",
  "properties": {
    "addr:full":"1312 Memorial Blvd Murfreesboro TN 37129",
    "addr:housenumber":"1312",
    "addr:postcode":"37129",
    "addr:street":"Memorial Blvd",
    "iso:country":"US",
    "sg:address":"1312 Memorial Blvd",
    "sg:city":"Murfreesboro",
    "sg:classifiers":[
        {
            "category":"Professional",
            "subcategory":"Employment Agencies",
            "type":"Services"
        }
    ],
    "sg:phone":"+1 615 895 2333",
    "sg:postcode":"37129",
    "sg:province":"TN",
    "sg:tags":[
        "temporary",
        "help"
    ],
    "wof:name":"Manpower",
    "wof:placetype":"venue"
},
  "geometry": {"coordinates":[-86.39803499999999,35.850966],"type":"Point"}
}