{
  "type": "Feature",
  "properties": {
    "addr:full":"4570 Barfield Rd Memphis TN 38117",
    "addr:housenumber":"4570",
    "addr:postcode":"38117",
    "addr:street":"Barfield Rd",
    "iso:country":"US",
    "sg:address":"4570 Barfield Rd",
    "sg:city":"Memphis",
    "sg:classifiers":[
        {
            "category":"Real Estate",
            "subcategory":"Real Estate Agent",
            "type":"Services"
        }
    ],
    "sg:phone":"+1 901 683 7132",
    "sg:postcode":"38117",
    "sg:province":"TN",
    "sg:tags":[
        "insurance"
    ],
    "wof:name":"Will H Higgins Co Realtors",
    "wof:placetype":"venue"
},
  "geometry": {"coordinates":[-89.915055,35.136074],"type":"Point"}
}