{
  "type": "Feature",
  "properties": {
    "iso:country":"US",
    "sg:address":"906 Fairlane Dr",
    "sg:city":"Elizabethton",
    "sg:classifiers":[
        {
            "category":"Food & Beverages",
            "subcategory":"Groceries & Convenience Stores",
            "type":"Retail Goods"
        }
    ],
    "sg:phone":"+1 423 926 4779",
    "sg:postcode":"37643",
    "sg:province":"TN",
    "wof:name":"B and T Coner Market",
    "wof:placetype":"venue"
},
  "geometry": {"coordinates":[-82.19473499999999,36.340291],"type":"Point"}
}