{
  "type": "Feature",
  "properties": {
    "iso:country":"US",
    "sg:address":"6020 Frontier Ln",
    "sg:city":"Nashville",
    "sg:classifiers":[
        {
            "category":"Professional",
            "subcategory":"Business Services",
            "type":"Services"
        }
    ],
    "sg:phone":"+1 615 831 3337",
    "sg:postcode":"37211",
    "sg:province":"TN",
    "wof:name":"Language Linx Inc",
    "wof:placetype":"venue"
},
  "geometry": {"coordinates":[-86.739859,36.033112],"type":"Point"}
}