{
  "type": "Feature",
  "properties": {
    "iso:country":"US",
    "sg:address":"511 May St",
    "sg:city":"Sweetwater",
    "sg:classifiers":[
        {
            "category":"Real Estate",
            "subcategory":"Real Estate Operator",
            "type":"Services"
        }
    ],
    "sg:phone":"+1 423 337 4984",
    "sg:postcode":"37874",
    "sg:province":"TN",
    "sg:tags":[
        "retirement",
        "hotel",
        "apartment"
    ],
    "wof:name":"Garden's Of Wood Village",
    "wof:placetype":"venue"
},
  "geometry": {"coordinates":[-84.462801,35.595855],"type":"Point"}
}