{
  "type": "Feature",
  "properties": {
    "addr:full":"112 Westwood Place Suite 200 Brentwood TN 37027",
    "addr:housenumber":"112",
    "addr:postcode":"37027",
    "addr:street":"Westwood Place Suite 200",
    "iso:country":"US",
    "sg:address":"112 Westwood Place Suite 200",
    "sg:city":"Brentwood",
    "sg:classifiers":[
        {
            "category":"Professional",
            "subcategory":"Computer Services",
            "type":"Services"
        }
    ],
    "sg:phone":"+1 888 229 0746",
    "sg:postcode":"37027",
    "sg:province":"TN",
    "sg:website":"http://reputationadvocate.com/",
    "wof:name":"Reputation Advocate",
    "wof:placetype":"venue"
},
  "geometry": {"coordinates":[-86.805437,36.036862],"type":"Point"}
}