{
  "type": "Feature",
  "properties": {
    "iso:country":"US",
    "sg:address":"4970 Raleigh Lagrange Rd",
    "sg:city":"Memphis",
    "sg:classifiers":[
        {
            "category":"Building & Trades",
            "subcategory":"Landscaping Services",
            "type":"Services"
        }
    ],
    "sg:phone":"+1 901 385 7409",
    "sg:postcode":"38128",
    "sg:province":"TN",
    "sg:tags":[
        "landscape"
    ],
    "wof:name":"C&E Landscape",
    "wof:placetype":"venue"
},
  "geometry": {"coordinates":[-89.897649,35.194402],"type":"Point"}
}