{
  "type": "Feature",
  "properties": {
    "iso:country":"US",
    "sg:address":"106 S 2nd St",
    "sg:city":"Pulaski",
    "sg:classifiers":[
        {
            "category":"Personal",
            "subcategory":"Beauty Salon",
            "type":"Services"
        }
    ],
    "sg:phone":"+1 931 363 6060",
    "sg:postcode":"38478",
    "sg:province":"TN",
    "sg:tags":[
        "shop"
    ],
    "wof:name":"Jan's Salon Of Cosmetology",
    "wof:placetype":"venue"
},
  "geometry": {"coordinates":[-87.03187200000001,35.19922],"type":"Point"}
}