{
  "type": "Feature",
  "properties": {
    "addr:full":"714 E Ridgecrest Dr Kingston TN 37763",
    "addr:housenumber":"714",
    "addr:postcode":"37763",
    "addr:street":"E Ridgecrest Dr",
    "iso:country":"US",
    "sg:address":"714 E Ridgecrest Dr",
    "sg:city":"Kingston",
    "sg:classifiers":[
        {
            "category":"Wholesale",
            "subcategory":"Sporting Goods",
            "type":"Manufacturing & Wholesale Goods"
        }
    ],
    "sg:phone":"+1 865 388 0988",
    "sg:postcode":"37763",
    "sg:province":"TN",
    "wof:name":"Cheetah Recreational Equipment",
    "wof:placetype":"venue"
},
  "geometry": {"coordinates":[-84.512094,35.865012],"type":"Point"}
}