{
  "type": "Feature",
  "properties": {
    "addr:full":"302 W Church St Lewisburg TN 37091",
    "addr:housenumber":"302",
    "addr:postcode":"37091",
    "addr:street":"W Church St",
    "iso:country":"US",
    "sg:address":"302 W Church St",
    "sg:city":"Lewisburg",
    "sg:classifiers":[
        {
            "category":"Health Services",
            "subcategory":"Doctor",
            "type":"Services"
        }
    ],
    "sg:phone":"+1 931 359 6154",
    "sg:postcode":"37091",
    "sg:province":"TN",
    "sg:tags":[
        "dentist"
    ],
    "wof:name":"Bruce A Jenkins DDS",
    "wof:placetype":"venue"
},
  "geometry": {"coordinates":[-86.79158700000001,35.45032],"type":"Point"}
}