{
  "type": "Feature",
  "properties": {
    "addr:full":"307 S Spring St Murfreesboro TN 37130",
    "addr:housenumber":"307",
    "addr:postcode":"37130",
    "addr:street":"S Spring St",
    "iso:country":"US",
    "sg:address":"307 S Spring St",
    "sg:city":"Murfreesboro",
    "sg:classifiers":[
        {
            "category":"Shopping",
            "subcategory":"Photographic Equipment",
            "type":"Retail Goods"
        },
        {
            "category":"Retail",
            "subcategory":"Photofinishing",
            "type":"Services"
        }
    ],
    "sg:phone":"+1 615 278 3456",
    "sg:postcode":"37130",
    "sg:province":"TN",
    "sg:tags":[
        "shop",
        "photo",
        "finishing",
        "camera"
    ],
    "wof:name":"Bateys Photo & Imaging Center",
    "wof:placetype":"venue"
},
  "geometry": {"coordinates":[-86.39027,35.844753],"type":"Point"}
}