{
  "type": "Feature",
  "properties": {
    "addr:full":"2204 Elliston Pl Nashville TN 37203",
    "addr:housenumber":"2204",
    "addr:postcode":"37203",
    "addr:street":"Elliston Pl",
    "iso:country":"US",
    "sg:address":"2204 Elliston Pl",
    "sg:city":"Nashville",
    "sg:classifiers":[
        {
            "category":"Personal",
            "subcategory":"Piercing",
            "type":"Services"
        }
    ],
    "sg:phone":"+1 615 321 8777",
    "sg:postcode":"37203",
    "sg:province":"TN",
    "sg:tags":[
        "body"
    ],
    "wof:name":"Ink Gallery Tattoo II",
    "wof:placetype":"venue"
},
  "geometry": {"coordinates":[-86.80392500000001,36.151591],"type":"Point"}
}