{
  "type": "Feature",
  "properties": {
    "iso:country":"US",
    "sg:address":"104 Hunter Cove Rd",
    "sg:city":"Allons",
    "sg:classifiers":[
        {
            "category":"Building & Trades",
            "subcategory":"Construction",
            "type":"Services"
        }
    ],
    "sg:phone":"+1 931 823 3191",
    "sg:postcode":"38541",
    "sg:province":"TN",
    "sg:tags":[
        "contractor"
    ],
    "wof:name":"Black Hollow Construction",
    "wof:placetype":"venue"
},
  "geometry": {"coordinates":[-85.354218,36.461773],"type":"Point"}
}