{
  "type": "Feature",
  "properties": {
    "iso:country":"US",
    "sg:address":"2427 Amanda Ln",
    "sg:city":"Sevierville",
    "sg:classifiers":[
        {
            "category":"Professional",
            "subcategory":"Business Services",
            "type":"Services"
        }
    ],
    "sg:phone":"+1 865 908 7174",
    "sg:postcode":"37876",
    "sg:province":"TN",
    "wof:name":"Top Notch Engraving",
    "wof:placetype":"venue"
},
  "geometry": {"coordinates":[-83.456129,35.871643],"type":"Point"}
}