{
  "type": "Feature",
  "properties": {
    "iso:country":"US",
    "sg:address":"3112 Big Creek Rd",
    "sg:city":"Hartford",
    "sg:classifiers":[
        {
            "category":"Real Estate",
            "subcategory":"Developer",
            "type":"Services"
        }
    ],
    "sg:phone":"+1 423 487 3002",
    "sg:postcode":"37753",
    "sg:province":"TN",
    "wof:name":"Spring Hollow Land Development",
    "wof:placetype":"venue"
},
  "geometry": {"coordinates":[-83.143997,35.81662],"type":"Point"}
}