{
  "type": "Feature",
  "properties": {
    "iso:country":"US",
    "sg:address":"627 Old State Rte 34",
    "sg:city":"Jonesborough",
    "sg:classifiers":[
        {
            "category":"Social Services",
            "subcategory":"Child Care",
            "type":"Services"
        }
    ],
    "sg:phone":"+1 423 753 7828",
    "sg:postcode":"37659",
    "sg:province":"TN",
    "wof:name":"A B C'S & 12 3's",
    "wof:placetype":"venue"
},
  "geometry": {"coordinates":[-82.503472,36.25851],"type":"Point"}
}