{
  "type": "Feature",
  "properties": {
    "iso:country":"US",
    "sg:address":"5825 Asquith Pl",
    "sg:city":"Memphis",
    "sg:classifiers":[
        {
            "category":"Wholesale",
            "subcategory":"Machinery & Supplies",
            "type":"Manufacturing & Wholesale Goods"
        }
    ],
    "sg:phone":"+1 901 366 7113",
    "sg:postcode":"38115",
    "sg:province":"TN",
    "sg:tags":[
        "mobile",
        "pressure",
        "washing"
    ],
    "wof:name":"Shirls Pressure World",
    "wof:placetype":"venue"
},
  "geometry": {"coordinates":[-89.869185,35.072912],"type":"Point"}
}