{
  "type": "Feature",
  "properties": {
    "iso:country":"US",
    "sg:address":"5905 Weisbrook Ln",
    "sg:city":"Knoxville",
    "sg:classifiers":[
        {
            "category":"Manufacturing",
            "subcategory":"Tools & Machinery",
            "type":"Manufacturing & Wholesale Goods"
        }
    ],
    "sg:phone":"+1 865 212 0006",
    "sg:postcode":"37909",
    "sg:province":"TN",
    "sg:tags":[
        "rotating",
        "equipment",
        "monitoring",
        "mfg"
    ],
    "wof:name":"Machinery Anal & Reliab Syst",
    "wof:placetype":"venue"
},
  "geometry": {"coordinates":[-84.017437,35.955005],"type":"Point"}
}