{
  "type": "Feature",
  "properties": {
    "addr:full":"1105 Scottsville Rd Lafayette TN 37083",
    "addr:housenumber":"1105",
    "addr:postcode":"37083",
    "addr:street":"Scottsville Rd",
    "iso:country":"US",
    "sg:address":"1105 Scottsville Rd",
    "sg:city":"Lafayette",
    "sg:classifiers":[
        {
            "category":"Cinema",
            "subcategory":"Movie Rental",
            "type":"Entertainment"
        }
    ],
    "sg:phone":"+1 615 666 6015",
    "sg:postcode":"37083",
    "sg:province":"TN",
    "sg:tags":[
        "video",
        "tape"
    ],
    "wof:name":"Video Corner Inc",
    "wof:placetype":"venue"
},
  "geometry": {"coordinates":[-86.029068,36.532434],"type":"Point"}
}