{
  "type": "Feature",
  "properties": {
    "iso:country":"US",
    "sg:address":"638 W Poplar Ave",
    "sg:city":"Collierville",
    "sg:classifiers":[
        {
            "category":"Wholesale",
            "subcategory":"Painting Supplies",
            "type":"Manufacturing & Wholesale Goods"
        },
        {
            "category":"Manufacturing",
            "subcategory":"Chemicals & Compounds",
            "type":"Manufacturing & Wholesale Goods"
        }
    ],
    "sg:phone":"+1 901 850 9658",
    "sg:postcode":"38017",
    "sg:province":"TN",
    "sg:tags":[
        "paint-wholesale",
        "equipment",
        "manufacturer",
        "paint"
    ],
    "sg:website":"http://www.ppg.com",
    "wof:name":"Ppg 4463",
    "wof:placetype":"venue"
},
  "geometry": {"coordinates":[-89.68349600000001,35.045976],"type":"Point"}
}