{
  "type": "Feature",
  "properties": {
    "addr:full":"420 Pates Hill Rd Mosheim TN 37818",
    "addr:housenumber":"420",
    "addr:postcode":"37818",
    "addr:street":"Pates Hill Rd",
    "iso:country":"US",
    "sg:address":"420 Pates Hill Rd",
    "sg:city":"Mosheim",
    "sg:classifiers":[
        {
            "category":"Shopping",
            "type":"Retail Goods"
        }
    ],
    "sg:phone":"+1 423 636 1141",
    "sg:postcode":"37818",
    "sg:province":"TN",
    "sg:tags":[
        "merchandise"
    ],
    "wof:name":"I Do Shoppe",
    "wof:placetype":"venue"
},
  "geometry": {"coordinates":[-82.99199,36.111178],"type":"Point"}
}