{
  "type": "Feature",
  "properties": {
    "iso:country":"US",
    "sg:address":"3241 Southall Rd",
    "sg:city":"Franklin",
    "sg:classifiers":[
        {
            "category":"Food & Beverages",
            "subcategory":"Specialty",
            "type":"Retail Goods"
        }
    ],
    "sg:phone":"+1 615 794 1982",
    "sg:postcode":"37064",
    "sg:province":"TN",
    "wof:name":"Two Buddies Foods",
    "wof:placetype":"venue"
},
  "geometry": {"coordinates":[-86.956406,35.898919],"type":"Point"}
}