{
  "type": "Feature",
  "properties": {
    "iso:country":"US",
    "sg:address":"1800 McCallie Ave",
    "sg:city":"Chattanooga",
    "sg:classifiers":[
        {
            "category":"Social Services",
            "type":"Services"
        }
    ],
    "sg:phone":"+1 423 697 7130",
    "sg:postcode":"37404",
    "sg:province":"TN",
    "sg:tags":[
        "professional",
        "counselor"
    ],
    "sg:website":"www.partnershipfca.com",
    "wof:name":"Partnership For Families",
    "wof:placetype":"venue"
},
  "geometry": {"coordinates":[-85.27461099999999,35.035877],"type":"Point"}
}