{
  "type": "Feature",
  "properties": {
    "iso:country":"US",
    "sg:address":"4295 Cromwell Rd",
    "sg:city":"Chattanooga",
    "sg:classifiers":[
        {
            "category":"Wholesale",
            "subcategory":"Machinery & Supplies",
            "type":"Manufacturing & Wholesale Goods"
        }
    ],
    "sg:phone":"+1 423 894 4703",
    "sg:postcode":"37421",
    "sg:province":"TN",
    "sg:tags":[
        "tubing",
        "hose",
        "plastic"
    ],
    "wof:name":"Maintenance Rubber & Pump Co",
    "wof:placetype":"venue"
},
  "geometry": {"coordinates":[-85.198635,35.066118],"type":"Point"}
}