{
  "type": "Feature",
  "properties": {
    "iso:country":"US",
    "sg:address":"1201 Freightliner Dr",
    "sg:city":"Nashville",
    "sg:classifiers":[
        {
            "category":"Government",
            "subcategory":"Police Station",
            "type":"Public Place"
        }
    ],
    "sg:phone":"+1 615 862 7800",
    "sg:postcode":"37210",
    "sg:province":"TN",
    "sg:tags":[
        "protection"
    ],
    "wof:name":"Police Dept Metro Nashville",
    "wof:placetype":"venue"
},
  "geometry": {"coordinates":[-86.736709,36.156187],"type":"Point"}
}