{
  "type": "Feature",
  "properties": {
    "iso:country":"US",
    "sg:address":"817 Englewood Rd",
    "sg:city":"Madisonville",
    "sg:classifiers":[
        {
            "category":"Professional",
            "subcategory":"Printing & Photocopies",
            "type":"Services"
        }
    ],
    "sg:phone":"+1 423 420 9452",
    "sg:postcode":"37354",
    "sg:province":"TN",
    "sg:tags":[
        "duplicating",
        "copying"
    ],
    "wof:name":"K & S Signs",
    "wof:placetype":"venue"
},
  "geometry": {"coordinates":[-84.37374800000001,35.509861],"type":"Point"}
}