{
  "type": "Feature",
  "properties": {
    "iso:country":"US",
    "sg:address":"225 Pharr Ave",
    "sg:city":"Selmer",
    "sg:classifiers":[
        {
            "category":"Personal",
            "type":"Services"
        }
    ],
    "sg:phone":"+1 731 646 1180",
    "sg:postcode":"38375",
    "sg:province":"TN",
    "wof:name":"Ivy & Lace Wedding Chapel",
    "wof:placetype":"venue"
},
  "geometry": {"coordinates":[-88.592665,35.172555],"type":"Point"}
}