{
  "type": "Feature",
  "properties": {
    "iso:country":"US",
    "sg:address":"232 S Calderwood St",
    "sg:city":"Alcoa",
    "sg:classifiers":[
        {
            "category":"Government",
            "subcategory":"Office",
            "type":"Public Place"
        }
    ],
    "sg:phone":"+1 865 984 2764",
    "sg:postcode":"37701",
    "sg:province":"TN",
    "sg:tags":[
        "national",
        "security"
    ],
    "wof:name":"US Dept of the Air Force",
    "wof:placetype":"venue"
},
  "geometry": {"coordinates":[-83.976829,35.760795],"type":"Point"}
}