{
  "type": "Feature",
  "properties": {
    "addr:full":"147 California Ave Oak Ridge TN 37830",
    "addr:housenumber":"147",
    "addr:postcode":"37830",
    "addr:street":"California Ave",
    "iso:country":"US",
    "sg:address":"147 California Ave",
    "sg:city":"Oak Ridge",
    "sg:classifiers":[
        {
            "category":"Banks & Credit Unions",
            "subcategory":"Financial Services",
            "type":"Services"
        }
    ],
    "sg:phone":"+1 865 482 4181",
    "sg:postcode":"37830",
    "sg:province":"TN",
    "sg:tags":[
        "investor"
    ],
    "wof:name":"BAC Investment Properties LLC",
    "wof:placetype":"venue"
},
  "geometry": {"coordinates":[-84.222235,36.043659],"type":"Point"}
}