{
  "type": "Feature",
  "properties": {
    "iso:country":"US",
    "sg:address":"2637 Barron Ave",
    "sg:city":"Memphis",
    "sg:classifiers":[
        {
            "category":"Organizations",
            "subcategory":"Religious Organization",
            "type":"Services"
        }
    ],
    "sg:phone":"+1 901 743 0370",
    "sg:postcode":"38114",
    "sg:province":"TN",
    "wof:name":"Believers In Faith Missionary",
    "wof:placetype":"venue"
},
  "geometry": {"coordinates":[-89.975916,35.100783],"type":"Point"}
}