{
  "type": "Feature",
  "properties": {
    "addr:full":"707 E Trinity Ln Nashville TN 37207",
    "addr:housenumber":"707",
    "addr:postcode":"37207",
    "addr:street":"E Trinity Ln",
    "iso:country":"US",
    "sg:address":"707 E Trinity Ln",
    "sg:city":"Nashville",
    "sg:classifiers":[
        {
            "category":"Home & Garden",
            "subcategory":"Furniture",
            "type":"Retail Goods"
        }
    ],
    "sg:phone":"+1 615 227 7955",
    "sg:postcode":"37207",
    "sg:province":"TN",
    "sg:tags":[
        "mattress"
    ],
    "wof:name":"Mattress Plus",
    "wof:placetype":"venue"
},
  "geometry": {"coordinates":[-86.75036900000001,36.204694],"type":"Point"}
}