{
  "type": "Feature",
  "properties": {
    "iso:country":"US",
    "sg:address":"2130 Industrial Blvd",
    "sg:city":"Bristol",
    "sg:classifiers":[
        {
            "category":"Building & Trades",
            "subcategory":"Construction",
            "type":"Services"
        }
    ],
    "sg:phone":"+1 423 764 0274",
    "sg:postcode":"37620",
    "sg:province":"TN",
    "sg:tags":[
        "roofing",
        "contractor"
    ],
    "sg:website":"www.summitbsr.com",
    "wof:name":"Summit BSR Roofing",
    "wof:placetype":"venue"
},
  "geometry": {"coordinates":[-82.176378,36.553471],"type":"Point"}
}