{
  "type": "Feature",
  "properties": {
    "addr:full":"200 Paragon Mills Rd Nashville TN 37211",
    "addr:housenumber":"200",
    "addr:postcode":"37211",
    "addr:street":"Paragon Mills Rd",
    "iso:country":"US",
    "sg:address":"200 Paragon Mills Rd",
    "sg:city":"Nashville",
    "sg:classifiers":[
        {
            "category":"Professional",
            "type":"Services"
        }
    ],
    "sg:phone":"+1 615 333 7656",
    "sg:postcode":"37211",
    "sg:province":"TN",
    "wof:name":"Leveque Multi Svcs",
    "wof:placetype":"venue"
},
  "geometry": {"coordinates":[-86.701674,36.086387],"type":"Point"}
}