{
  "type": "Feature",
  "properties": {
    "addr:full":"997 Thea Fugate Rd Spring City TN 37381",
    "addr:housenumber":"997",
    "addr:postcode":"37381",
    "addr:street":"Thea Fugate Rd",
    "iso:country":"US",
    "sg:address":"997 Thea Fugate Rd",
    "sg:city":"Spring City",
    "sg:classifiers":[
        {
            "category":"Professional",
            "type":"Services"
        }
    ],
    "sg:phone":"+1 423 365 5964",
    "sg:postcode":"37381",
    "sg:province":"TN",
    "wof:name":"Kimberly Nixon",
    "wof:placetype":"venue"
},
  "geometry": {"coordinates":[-84.82492999999999,35.62651],"type":"Point"}
}