{
  "type": "Feature",
  "properties": {
    "iso:country":"US",
    "sg:address":"309 22nd Ave",
    "sg:city":"Nashville",
    "sg:classifiers":[
        {
            "category":"Banks & Credit Unions",
            "subcategory":"Bank",
            "type":"Services"
        }
    ],
    "sg:phone":"+1 615 748 4910",
    "sg:postcode":"37203",
    "sg:province":"TN",
    "sg:website":"www.suntrust.com",
    "wof:name":"Sun Trust Bank",
    "wof:placetype":"venue"
},
  "geometry": {"coordinates":[-86.80497099999999,36.15323],"type":"Point"}
}