{
  "type": "Feature",
  "properties": {
    "addr:full":"2112 Acklen Ave Nashville TN 37212",
    "addr:housenumber":"2112",
    "addr:postcode":"37212",
    "addr:street":"Acklen Ave",
    "iso:country":"US",
    "sg:address":"2112 Acklen Ave",
    "sg:city":"Nashville",
    "sg:classifiers":[
        {
            "category":"Professional",
            "subcategory":"Business Services",
            "type":"Services"
        }
    ],
    "sg:phone":"+1 615 463 2487",
    "sg:postcode":"37212",
    "sg:province":"TN",
    "wof:name":"Inservice Inc",
    "wof:placetype":"venue"
},
  "geometry": {"coordinates":[-86.80481399999999,36.136072],"type":"Point"}
}