{
  "type": "Feature",
  "properties": {
    "addr:full":"345 S Hall Rd Alcoa TN 37701",
    "addr:housenumber":"345",
    "addr:postcode":"37701",
    "addr:street":"S Hall Rd",
    "iso:country":"US",
    "sg:address":"345 S Hall Rd",
    "sg:city":"Alcoa",
    "sg:classifiers":[
        {
            "category":"Professional",
            "subcategory":"Lawyer & Legal Services",
            "type":"Services"
        }
    ],
    "sg:phone":"+1 865 981 4966",
    "sg:postcode":"37701",
    "sg:province":"TN",
    "sg:tags":[
        "attorney"
    ],
    "wof:name":"Snyder James H Jr Law Office",
    "wof:placetype":"venue"
},
  "geometry": {"coordinates":[-83.968957,35.76276],"type":"Point"}
}