{
  "type": "Feature",
  "properties": {
    "iso:country":"US",
    "sg:address":"19138 Central Pike",
    "sg:city":"Lebanon",
    "sg:classifiers":[
        {
            "category":"Organizations",
            "subcategory":"Religious Organization",
            "type":"Services"
        }
    ],
    "sg:phone":"+1 615 449 4819",
    "sg:postcode":"37090",
    "sg:province":"TN",
    "wof:name":"Baird Grove Mssnry Bptst Chrch",
    "wof:placetype":"venue"
},
  "geometry": {"coordinates":[-86.340469,36.105299],"type":"Point"}
}