{
  "type": "Feature",
  "properties": {
    "iso:country":"US",
    "sg:address":"13763 Tonja Ln S",
    "sg:city":"Soddy Daisy",
    "sg:classifiers":[
        {
            "category":"Building & Trades",
            "subcategory":"Construction",
            "type":"Services"
        }
    ],
    "sg:phone":"+1 423 332 1963",
    "sg:postcode":"37379",
    "sg:province":"TN",
    "sg:tags":[
        "residential"
    ],
    "wof:name":"Ferguson Construction",
    "wof:placetype":"venue"
},
  "geometry": {"coordinates":[-85.08558499999999,35.323577],"type":"Point"}
}