{
  "type": "Feature",
  "properties": {
    "addr:full":"25350 State Hwy 114 Bruceton TN 38317",
    "addr:housenumber":"25350",
    "addr:postcode":"38317",
    "addr:street":"State Hwy 114",
    "iso:country":"US",
    "sg:address":"25350 State Hwy 114",
    "sg:city":"Bruceton",
    "sg:classifiers":[
        {
            "category":"Sports & Exercise",
            "subcategory":"Gym",
            "type":"Entertainment"
        }
    ],
    "sg:phone":"+1 731 586 4208",
    "sg:postcode":"38317",
    "sg:province":"TN",
    "sg:tags":[
        "spa",
        "health"
    ],
    "wof:name":"Pamper Me Spa",
    "wof:placetype":"venue"
},
  "geometry": {"coordinates":[-88.268843,36.094672],"type":"Point"}
}