{
  "type": "Feature",
  "properties": {
    "iso:country":"US",
    "sg:address":"2584 Niblik Pass",
    "sg:city":"Cordova",
    "sg:classifiers":[
        {
            "category":"Professional",
            "type":"Services"
        }
    ],
    "sg:phone":"+1 901 385 0306",
    "sg:postcode":"38016",
    "sg:province":"TN",
    "sg:tags":[
        "establishment"
    ],
    "wof:name":"Tempstay Corp Housing",
    "wof:placetype":"venue"
},
  "geometry": {"coordinates":[-89.786022,35.196141],"type":"Point"}
}