{
  "type": "Feature",
  "properties": {
    "iso:country":"US",
    "sg:address":"2769 Wolfcreek Pkwy Ste 103",
    "sg:city":"Memphis",
    "sg:classifiers":[
        {
            "category":"Shopping",
            "subcategory":"Department Store",
            "type":"Retail Goods"
        },
        {
            "category":"Shopping",
            "type":"Retail Goods"
        },
        {
            "category":"Shopping",
            "subcategory":"Discount & Variety Stores",
            "type":"Retail Goods"
        }
    ],
    "sg:phone":"+1 901 372 7450",
    "sg:postcode":"38133",
    "sg:province":"TN",
    "sg:tags":[
        "merchandise"
    ],
    "sg:website":"http://www.dollartree.com/",
    "wof:name":"Dollar Tree",
    "wof:placetype":"venue"
},
  "geometry": {"coordinates":[-89.79369699999999,35.199452],"type":"Point"}
}