{
  "type": "Feature",
  "properties": {
    "iso:country":"US",
    "sg:address":"919 Massman Dr",
    "sg:city":"Nashville",
    "sg:classifiers":[
        {
            "category":"Professional",
            "type":"Services"
        }
    ],
    "sg:phone":"+1 615 361 1644",
    "sg:postcode":"37217",
    "sg:province":"TN",
    "wof:name":"Stephen McRedmond",
    "wof:placetype":"venue"
},
  "geometry": {"coordinates":[-86.709132,36.138749],"type":"Point"}
}