{
  "type": "Feature",
  "properties": {
    "iso:country":"US",
    "sg:address":"4624 Drummonds Rd",
    "sg:city":"Drummonds",
    "sg:classifiers":[
        {
            "category":"Food & Beverages",
            "subcategory":"Groceries & Convenience Stores",
            "type":"Retail Goods"
        }
    ],
    "sg:phone":"+1 901 835 4780",
    "sg:postcode":"38023",
    "sg:province":"TN",
    "wof:name":"B J'S Convenience Corner",
    "wof:placetype":"venue"
},
  "geometry": {"coordinates":[-89.89171,35.460246],"type":"Point"}
}