{
  "type": "Feature",
  "properties": {
    "addr:full":"141 N 3rd St Selmer TN 38375",
    "addr:housenumber":"141",
    "addr:postcode":"38375",
    "addr:street":"N 3Rd St",
    "iso:country":"US",
    "sg:address":"141 N 3rd St",
    "sg:city":"Selmer",
    "sg:classifiers":[
        {
            "category":"Social Services",
            "type":"Services"
        }
    ],
    "sg:phone":"+1 731 645 4357",
    "sg:postcode":"38375",
    "sg:province":"TN",
    "sg:tags":[
        "counseling"
    ],
    "wof:name":"Women's Resource & Rape Prog",
    "wof:placetype":"venue"
},
  "geometry": {"coordinates":[-88.59282899999999,35.170648],"type":"Point"}
}