{
  "type": "Feature",
  "properties": {
    "iso:country":"US",
    "sg:address":"440 Isbell Rd",
    "sg:city":"Madisonville",
    "sg:classifiers":[
        {
            "category":"Restaurant",
            "type":"Food & Drink"
        }
    ],
    "sg:phone":"+1 423 442 3343",
    "sg:postcode":"37354",
    "sg:province":"TN",
    "wof:name":"Cracker Box Cafe",
    "wof:placetype":"venue"
},
  "geometry": {"coordinates":[-84.372584,35.504542],"type":"Point"}
}