{
  "type": "Feature",
  "properties": {
    "iso:country":"US",
    "sg:address":"10417 Dodson Branch Hwy",
    "sg:city":"Gainesboro",
    "sg:classifiers":[
        {
            "category":"Government",
            "subcategory":"Office",
            "type":"Public Place"
        }
    ],
    "sg:phone":"+1 931 268 2540",
    "sg:postcode":"38562",
    "sg:province":"TN",
    "wof:name":"Roaring River Camp",
    "wof:placetype":"venue"
},
  "geometry": {"coordinates":[-85.63847199999999,36.37344],"type":"Point"}
}