{
  "type": "Feature",
  "properties": {
    "iso:country":"US",
    "sg:address":"1807 Clydesdale St",
    "sg:city":"Maryville",
    "sg:classifiers":[
        {
            "category":"Building & Trades",
            "subcategory":"Construction",
            "type":"Services"
        }
    ],
    "sg:phone":"+1 865 981 5774",
    "sg:postcode":"37801",
    "sg:province":"TN",
    "sg:tags":[
        "company"
    ],
    "wof:name":"Harrison Construction Co",
    "wof:placetype":"venue"
},
  "geometry": {"coordinates":[-84.025435,35.755841],"type":"Point"}
}