{
  "type": "Feature",
  "properties": {
    "addr:full":"3828 Sequoyah Ave Knoxville TN 37919",
    "addr:housenumber":"3828",
    "addr:postcode":"37919",
    "addr:street":"Sequoyah Ave",
    "iso:country":"US",
    "sg:address":"3828 Sequoyah Ave",
    "sg:city":"Knoxville",
    "sg:classifiers":[
        {
            "category":"Freight",
            "type":"Transportation"
        }
    ],
    "sg:phone":"+1 865 300 8503",
    "sg:postcode":"37919",
    "sg:province":"TN",
    "sg:tags":[
        "operator",
        "trucking"
    ],
    "wof:name":"J Linn Shirley",
    "wof:placetype":"venue"
},
  "geometry": {"coordinates":[-83.96658100000001,35.931224],"type":"Point"}
}