{
  "type": "Feature",
  "properties": {
    "iso:country":"US",
    "sg:address":"1224 Scenic Hill Dr",
    "sg:city":"Louisville",
    "sg:classifiers":[
        {
            "category":"Organizations",
            "subcategory":"Religious Organization",
            "type":"Services"
        }
    ],
    "sg:phone":"+1 865 977 1384",
    "sg:postcode":"37777",
    "sg:province":"TN",
    "sg:tags":[
        "church"
    ],
    "wof:name":"Hillview Baptist Church",
    "wof:placetype":"venue"
},
  "geometry": {"coordinates":[-83.966942,35.860406],"type":"Point"}
}