{
  "type": "Feature",
  "properties": {
    "iso:country":"US",
    "sg:address":"15 State Hwy 20",
    "sg:city":"Summertown",
    "sg:classifiers":[
        {
            "category":"Shopping",
            "subcategory":"Used Merchandise",
            "type":"Retail Goods"
        }
    ],
    "sg:phone":"+1 931 964 4877",
    "sg:postcode":"38483",
    "sg:province":"TN",
    "wof:name":"Like New Consignment",
    "wof:placetype":"venue"
},
  "geometry": {"coordinates":[-87.28901,35.440364],"type":"Point"}
}