{
  "type": "Feature",
  "properties": {
    "addr:full":"1121 N Main St Shelbyville TN 37160",
    "addr:housenumber":"1121",
    "addr:postcode":"37160",
    "addr:street":"N Main St",
    "iso:country":"US",
    "sg:address":"1121 N Main St",
    "sg:city":"Shelbyville",
    "sg:classifiers":[
        {
            "category":"Shopping",
            "subcategory":"Used Merchandise",
            "type":"Retail Goods"
        },
        {
            "category":"Banks & Credit Unions",
            "subcategory":"Bank",
            "type":"Services"
        }
    ],
    "sg:phone":"+1 931 684 6460",
    "sg:postcode":"37160",
    "sg:province":"TN",
    "sg:tags":[
        "cashing",
        "check"
    ],
    "wof:name":"Volunteer Pawn & Loan",
    "wof:placetype":"venue"
},
  "geometry": {"coordinates":[-86.457774,35.499953],"type":"Point"}
}