{
  "type": "Feature",
  "properties": {
    "iso:country":"US",
    "sg:address":"106 Public Sq",
    "sg:city":"Waynesboro",
    "sg:classifiers":[
        {
            "category":"Professional",
            "subcategory":"Lawyer & Legal Services",
            "type":"Services"
        }
    ],
    "sg:phone":"+1 931 722 3646",
    "sg:postcode":"38474",
    "sg:province":"TN",
    "sg:tags":[
        "attorney"
    ],
    "wof:name":"Gray Law Firm",
    "wof:placetype":"venue"
},
  "geometry": {"coordinates":[-87.20731499999999,35.533955],"type":"Point"}
}