{
  "type": "Feature",
  "properties": {
    "iso:country":"US",
    "sg:address":"5932 Babelay Rd",
    "sg:city":"Knoxville",
    "sg:classifiers":[
        {
            "category":"Retail",
            "subcategory":"Auto Repair",
            "type":"Services"
        }
    ],
    "sg:phone":"+1 865 687 6228",
    "sg:postcode":"37924",
    "sg:province":"TN",
    "sg:tags":[
        "automobile",
        "used",
        "general"
    ],
    "wof:name":"Broadway Foreign Cars",
    "wof:placetype":"venue"
},
  "geometry": {"coordinates":[-83.868264,36.047414],"type":"Point"}
}