{
  "type": "Feature",
  "properties": {
    "addr:full":"1301 Mccallie Ave Chattanooga TN 37404",
    "addr:housenumber":"1301",
    "addr:postcode":"37404",
    "addr:street":"Mccallie Ave",
    "iso:country":"US",
    "sg:address":"1301 Mccallie Ave",
    "sg:city":"Chattanooga",
    "sg:classifiers":[
        {
            "category":"Health Services",
            "subcategory":"Doctor",
            "type":"Services"
        }
    ],
    "sg:phone":"+1 423 622 0162",
    "sg:postcode":"37404",
    "sg:province":"TN",
    "sg:tags":[
        "physician",
        "family",
        "practice",
        "surgeons",
        "medicine"
    ],
    "wof:name":"Leonard J Hays Iii Md Pc",
    "wof:placetype":"venue"
},
  "geometry": {"coordinates":[-85.282867,35.03894],"type":"Point"}
}