{
  "type": "Feature",
  "properties": {
    "iso:country":"US",
    "sg:address":"10207 Technology Dr",
    "sg:city":"Knoxville",
    "sg:classifiers":[
        {
            "category":"Banks & Credit Unions",
            "subcategory":"Investment Brokerage",
            "type":"Services"
        }
    ],
    "sg:phone":"+1 865 777 4677",
    "sg:postcode":"37932",
    "sg:province":"TN",
    "sg:tags":[
        "stock",
        "bond"
    ],
    "sg:website":"www.ssnetwork.com",
    "wof:name":"Securities Service Network Inc",
    "wof:placetype":"venue"
},
  "geometry": {"coordinates":[-84.12875,35.9175],"type":"Point"}
}