{
  "type": "Feature",
  "properties": {
    "addr:full":"5248 Hickory Hollow Pkwy Antioch TN 37013",
    "addr:housenumber":"5248",
    "addr:postcode":"37013",
    "addr:street":"Hickory Hollow Pkwy",
    "iso:country":"US",
    "sg:address":"5248 Hickory Hollow Pkwy",
    "sg:city":"Antioch",
    "sg:classifiers":[
        {
            "category":"Home & Garden",
            "subcategory":"Home Furnishings",
            "type":"Retail Goods"
        }
    ],
    "sg:phone":"+1 615 731 3737",
    "sg:postcode":"37013",
    "sg:province":"TN",
    "wof:name":"Nubian Way",
    "wof:placetype":"venue"
},
  "geometry": {"coordinates":[-86.662412,36.049582],"type":"Point"}
}