{
  "type": "Feature",
  "properties": {
    "iso:country":"US",
    "sg:address":"586 Six Crowns St",
    "sg:city":"Collierville",
    "sg:classifiers":[
        {
            "category":"Building & Trades",
            "subcategory":"Construction",
            "type":"Services"
        }
    ],
    "sg:phone":"+1 901 853 0111",
    "sg:postcode":"38017",
    "sg:province":"TN",
    "sg:tags":[
        "shelter",
        "dealer",
        "storm",
        "contractor"
    ],
    "wof:name":"T N Tornado Shelters",
    "wof:placetype":"venue"
},
  "geometry": {"coordinates":[-89.67991000000001,35.055396],"type":"Point"}
}