{
  "type": "Feature",
  "properties": {
    "iso:country":"US",
    "sg:address":"1503 Fort Henry Dr",
    "sg:city":"Kingsport",
    "sg:classifiers":[
        {
            "category":"Personal",
            "subcategory":"Barber",
            "type":"Services"
        }
    ],
    "sg:phone":"+1 423 245 5812",
    "sg:postcode":"37664",
    "sg:province":"TN",
    "sg:tags":[
        "shop"
    ],
    "wof:name":"Indian Barber Shop",
    "wof:placetype":"venue"
},
  "geometry": {"coordinates":[-82.534656,36.539216],"type":"Point"}
}