{
  "type": "Feature",
  "properties": {
    "addr:full":"5214 Maryland Way Brentwood TN 37027",
    "addr:housenumber":"5214",
    "addr:postcode":"37027",
    "addr:street":"Maryland Way",
    "iso:country":"US",
    "sg:address":"5214 Maryland Way",
    "sg:city":"Brentwood",
    "sg:classifiers":[
        {
            "category":"Building & Trades",
            "subcategory":"Construction",
            "type":"Services"
        }
    ],
    "sg:phone":"+1 615 309 8200",
    "sg:postcode":"37027",
    "sg:province":"TN",
    "sg:tags":[
        "home",
        "builder",
        "contractor",
        "custom",
        "general"
    ],
    "wof:name":"Castle Contractors LLC",
    "wof:placetype":"venue"
},
  "geometry": {"coordinates":[-86.80595599999999,36.035085],"type":"Point"}
}