{
  "type": "Feature",
  "properties": {
    "iso:country":"US",
    "sg:address":"551 S Cooper St",
    "sg:city":"Memphis",
    "sg:classifiers":[
        {
            "category":"Shopping",
            "subcategory":"Tobacco",
            "type":"Retail Goods"
        }
    ],
    "sg:phone":"+1 901 278 2416",
    "sg:postcode":"38104",
    "sg:province":"TN",
    "sg:tags":[
        "product"
    ],
    "wof:name":"Wild Things",
    "wof:placetype":"venue"
},
  "geometry": {"coordinates":[-89.9906,35.130512],"type":"Point"}
}