{
  "type": "Feature",
  "properties": {
    "iso:country":"US",
    "sg:address":"8031 Sawyer Brown Rd",
    "sg:city":"Nashville",
    "sg:classifiers":[
        {
            "category":"Communications",
            "subcategory":"Film & Video Production",
            "type":"Services"
        }
    ],
    "sg:phone":"+1 615 578 0841",
    "sg:postcode":"37221",
    "sg:province":"TN",
    "sg:tags":[
        "motion"
    ],
    "wof:name":"Case Study Motion Pictures",
    "wof:placetype":"venue"
},
  "geometry": {"coordinates":[-86.940488,36.085085],"type":"Point"}
}