{
  "type": "Feature",
  "properties": {
    "addr:full":"122 S Main St Sparta TN 38583",
    "addr:housenumber":"122",
    "addr:postcode":"38583",
    "addr:street":"S Main St",
    "iso:country":"US",
    "sg:address":"122 S Main St",
    "sg:city":"Sparta",
    "sg:classifiers":[
        {
            "category":"Health Services",
            "subcategory":"Doctor",
            "type":"Services"
        }
    ],
    "sg:phone":"+1 931 836 3694",
    "sg:postcode":"38583",
    "sg:province":"TN",
    "wof:name":"Marilyn Poteet- Langford DDS",
    "wof:placetype":"venue"
},
  "geometry": {"coordinates":[-85.46442,35.924719],"type":"Point"}
}