{
  "type": "Feature",
  "properties": {
    "addr:full":"4660 Mirandy Rd Cookeville TN 38506",
    "addr:postcode":"4660;38506",
    "addr:street":"Mirandy Rd",
    "iso:country":"US",
    "sg:address":"4660 Mirandy Rd",
    "sg:city":"Cookeville",
    "sg:classifiers":[
        {
            "category":"Restaurant",
            "type":"Food & Drink"
        }
    ],
    "sg:phone":"+1 931 537 2230",
    "sg:postcode":"38506",
    "sg:province":"TN",
    "sg:tags":[
        "eating"
    ],
    "wof:name":"Harvard Corporation",
    "wof:placetype":"venue"
},
  "geometry": {"coordinates":[-85.442052,36.229008],"type":"Point"}
}