{
  "type": "Feature",
  "properties": {
    "iso:country":"US",
    "sg:address":"208 Brisbane Rd",
    "sg:city":"Oak Ridge",
    "sg:classifiers":[
        {
            "category":"Retail",
            "subcategory":"Auto Repair",
            "type":"Services"
        }
    ],
    "sg:phone":"+1 865 220 0400",
    "sg:postcode":"37830",
    "sg:province":"TN",
    "sg:tags":[
        "transmission"
    ],
    "wof:name":"Accountable Auto Transmission",
    "wof:placetype":"venue"
},
  "geometry": {"coordinates":[-84.214074,36.04161],"type":"Point"}
}