{
  "type": "Feature",
  "properties": {
    "addr:full":"2910 Montbell Dr Knoxville TN 37918",
    "addr:postcode":"2910;37918",
    "addr:street":"Montbell Dr",
    "iso:country":"US",
    "sg:address":"2910 Montbell Dr",
    "sg:city":"Knoxville",
    "sg:classifiers":[
        {
            "category":"Social Services",
            "type":"Services"
        }
    ],
    "sg:phone":"+1 865 689 3959",
    "sg:postcode":"37918",
    "sg:province":"TN",
    "sg:tags":[
        "youth",
        "organization",
        "center"
    ],
    "wof:name":"YMCA",
    "wof:placetype":"venue"
},
  "geometry": {"coordinates":[-83.933836,36.041671],"type":"Point"}
}