{
  "type": "Feature",
  "properties": {
    "iso:country":"US",
    "sg:address":"819 W Broad St",
    "sg:city":"Cookeville",
    "sg:classifiers":[
        {
            "category":"Retail",
            "subcategory":"Repair Shop",
            "type":"Services"
        }
    ],
    "sg:phone":"+1 931 528 1765",
    "sg:postcode":"38501",
    "sg:province":"TN",
    "sg:tags":[
        "boat"
    ],
    "wof:name":"S & R Marine Inc",
    "wof:placetype":"venue"
},
  "geometry": {"coordinates":[-85.52449799999999,36.169962],"type":"Point"}
}