{
  "type": "Feature",
  "properties": {
    "iso:country":"US",
    "sg:address":"6525 Annie Lee St",
    "sg:city":"Millington",
    "sg:classifiers":[
        {
            "category":"Building & Trades",
            "subcategory":"Construction",
            "type":"Services"
        }
    ],
    "sg:phone":"+1 901 218 1013",
    "sg:postcode":"38053",
    "sg:province":"TN",
    "sg:tags":[
        "contractor"
    ],
    "wof:name":"Donald W Ward Roofing Inc",
    "wof:placetype":"venue"
},
  "geometry": {"coordinates":[-89.914472,35.304106],"type":"Point"}
}