{
  "type": "Feature",
  "properties": {
    "iso:country":"US",
    "sg:address":"1102 Ski View Dr",
    "sg:city":"Gatlinburg",
    "sg:classifiers":[
        {
            "category":"Real Estate",
            "subcategory":"Real Estate Agent",
            "type":"Services"
        }
    ],
    "sg:phone":"+1 865 436 5100",
    "sg:postcode":"37738",
    "sg:province":"TN",
    "sg:tags":[
        "rental",
        "sharing",
        "leasing",
        "sales",
        "time"
    ],
    "wof:name":"Ski View Mountain Resort",
    "wof:placetype":"venue"
},
  "geometry": {"coordinates":[-83.55991400000001,35.707106],"type":"Point"}
}