{
  "type": "Feature",
  "properties": {
    "iso:country":"US",
    "sg:address":"1460 Old Fayetteville Hwy",
    "sg:city":"Lynchburg",
    "sg:classifiers":[
        {
            "category":"Shopping",
            "subcategory":"Used Merchandise",
            "type":"Retail Goods"
        }
    ],
    "sg:phone":"+1 931 759 4964",
    "sg:postcode":"37352",
    "sg:province":"TN",
    "sg:tags":[
        "antique"
    ],
    "wof:name":"Baker's Antiques",
    "wof:placetype":"venue"
},
  "geometry": {"coordinates":[-86.40333800000001,35.248925],"type":"Point"}
}