{
  "type": "Feature",
  "properties": {
    "iso:country":"US",
    "sg:address":"929 Spring Creek Rd",
    "sg:city":"Chattanooga",
    "sg:classifiers":[
        {
            "category":"Health Services",
            "subcategory":"Clinic",
            "type":"Services"
        },
        {
            "category":"Health Services",
            "subcategory":"Doctor",
            "type":"Services"
        }
    ],
    "sg:phone":"+1 423 855 5484",
    "sg:postcode":"37412",
    "sg:province":"TN",
    "sg:tags":[
        "physician",
        "surgeon"
    ],
    "wof:name":"Adult Medicine Health Center O",
    "wof:placetype":"venue"
},
  "geometry": {"coordinates":[-85.217886,34.999337],"type":"Point"}
}