{
  "type": "Feature",
  "properties": {
    "addr:full":"1008 S Jefferson Ave Cookeville TN 38501",
    "addr:housenumber":"1008",
    "addr:postcode":"38501",
    "addr:street":"S Jefferson Ave",
    "iso:country":"US",
    "sg:address":"1008 S Jefferson Ave",
    "sg:city":"Cookeville",
    "sg:classifiers":[
        {
            "category":"Shopping",
            "subcategory":"Jewelry",
            "type":"Retail Goods"
        }
    ],
    "sg:phone":"+1 931 525 7325",
    "sg:postcode":"38501",
    "sg:province":"TN",
    "sg:tags":[
        "jeweler"
    ],
    "wof:name":"Crabtree & Crane Jewelers",
    "wof:placetype":"venue"
},
  "geometry": {"coordinates":[-85.501705,36.138331],"type":"Point"}
}