{
  "type": "Feature",
  "properties": {
    "iso:country":"US",
    "sg:address":"410 Caney Valley Loop",
    "sg:city":"Surgoinsville",
    "sg:classifiers":[
        {
            "category":"Professional",
            "type":"Services"
        }
    ],
    "sg:phone":"+1 423 357 9263",
    "sg:postcode":"37873",
    "sg:province":"TN",
    "wof:name":"Communications Service Tech",
    "wof:placetype":"venue"
},
  "geometry": {"coordinates":[-82.793342,36.589503],"type":"Point"}
}