{
  "type": "Feature",
  "properties": {
    "iso:country":"US",
    "sg:address":"3902 Windy Ave",
    "sg:city":"Memphis",
    "sg:classifiers":[
        {
            "category":"Building & Trades",
            "subcategory":"Construction",
            "type":"Services"
        }
    ],
    "sg:phone":"+1 901 233 7862",
    "sg:postcode":"38128",
    "sg:province":"TN",
    "sg:tags":[
        "wallcoverings-installation",
        "wallpaper",
        "painting",
        "contractor"
    ],
    "wof:name":"Dan Dandy Painting",
    "wof:placetype":"venue"
},
  "geometry": {"coordinates":[-89.933891,35.238894],"type":"Point"}
}