{
  "type": "Feature",
  "properties": {
    "addr:full":"3855 Trenton Rd Clarksville TN 37040",
    "addr:housenumber":"3855",
    "addr:postcode":"37040",
    "addr:street":"Trenton Rd",
    "iso:country":"US",
    "sg:address":"3855 Trenton Rd",
    "sg:city":"Clarksville",
    "sg:classifiers":[
        {
            "category":"Shopping",
            "subcategory":"Discount & Variety Stores",
            "type":"Retail Goods"
        }
    ],
    "sg:phone":"+1 931 645 2888",
    "sg:postcode":"37040",
    "sg:province":"TN",
    "wof:name":"Dollar General",
    "wof:placetype":"venue"
},
  "geometry": {"coordinates":[-87.317727,36.624977],"type":"Point"}
}