{
  "type": "Feature",
  "properties": {
    "iso:country":"US",
    "sg:address":"20166 Clarkrange Hwy",
    "sg:city":"Monterey",
    "sg:classifiers":[
        {
            "category":"Home & Garden",
            "subcategory":"Garden Supply",
            "type":"Retail Goods"
        }
    ],
    "sg:phone":"+1 615 451 2874",
    "sg:postcode":"38574",
    "sg:province":"TN",
    "sg:tags":[
        "center"
    ],
    "wof:name":"Twelve Corners Nursery",
    "wof:placetype":"venue"
},
  "geometry": {"coordinates":[-85.174363,36.12061],"type":"Point"}
}