{
  "type": "Feature",
  "properties": {
    "iso:country":"US",
    "sg:address":"1715 Lynn St",
    "sg:city":"Tazewell",
    "sg:classifiers":[
        {
            "category":"Professional",
            "subcategory":"Business Services",
            "type":"Services"
        }
    ],
    "sg:phone":"+1 423 626 0363",
    "sg:postcode":"37879",
    "sg:province":"TN",
    "wof:name":"Turner Music",
    "wof:placetype":"venue"
},
  "geometry": {"coordinates":[-83.579921,36.457145],"type":"Point"}
}