{
  "type": "Feature",
  "properties": {
    "addr:full":"3211 Peoples St Johnson City TN 37604",
    "addr:housenumber":"3211",
    "addr:postcode":"37604",
    "addr:street":"Peoples St",
    "iso:country":"US",
    "sg:address":"3211 Peoples St",
    "sg:city":"Johnson City",
    "sg:classifiers":[
        {
            "category":"Home & Garden",
            "subcategory":"Home Furnishings",
            "type":"Retail Goods"
        }
    ],
    "sg:phone":"+1 423 915 0424",
    "sg:postcode":"37604",
    "sg:province":"TN",
    "wof:name":"Bed Bath & Beyond Inc",
    "wof:placetype":"venue"
},
  "geometry": {"coordinates":[-82.401242,36.346678],"type":"Point"}
}