{
  "type": "Feature",
  "properties": {
    "addr:full":"102 Indian Lake Rd Hendersonville TN 37075",
    "addr:housenumber":"102",
    "addr:postcode":"37075",
    "addr:street":"Indian Lake Rd",
    "iso:country":"US",
    "sg:address":"102 Indian Lake Rd",
    "sg:city":"Hendersonville",
    "sg:classifiers":[
        {
            "category":"Education",
            "subcategory":"School",
            "type":"Public Place"
        }
    ],
    "sg:phone":"+1 615 264 6085",
    "sg:postcode":"37075",
    "sg:province":"TN",
    "wof:name":"EB Wilson Night HS",
    "wof:placetype":"venue"
},
  "geometry": {"coordinates":[-86.604904,36.307178],"type":"Point"}
}