{
  "type": "Feature",
  "properties": {
    "iso:country":"US",
    "sg:address":"201 Mill Ave",
    "sg:city":"Hohenwald",
    "sg:classifiers":[
        {
            "category":"Building & Trades",
            "subcategory":"Equipment Rental",
            "type":"Services"
        }
    ],
    "sg:phone":"+1 931 796 5963",
    "sg:postcode":"38462",
    "sg:province":"TN",
    "sg:tags":[
        "hardware",
        "material",
        "lumber"
    ],
    "wof:name":"True Value",
    "wof:placetype":"venue"
},
  "geometry": {"coordinates":[-87.549539,35.545797],"type":"Point"}
}