{
  "type": "Feature",
  "properties": {
    "iso:country":"US",
    "sg:address":"5340 Ringgold Rd",
    "sg:city":"Chattanooga",
    "sg:classifiers":[
        {
            "category":"Personal",
            "subcategory":"Hair Removal",
            "type":"Services"
        }
    ],
    "sg:phone":"+1 423 894 3882",
    "sg:postcode":"37412",
    "sg:province":"TN",
    "sg:tags":[
        "management",
        "planning",
        "investment",
        "estate"
    ],
    "wof:name":"Cox Financial Centers Inc",
    "wof:placetype":"venue"
},
  "geometry": {"coordinates":[-85.233847,34.994917],"type":"Point"}
}