{
  "type": "Feature",
  "properties": {
    "iso:country":"US",
    "sg:address":"985 Cordova Station Ave",
    "sg:city":"Cordova",
    "sg:classifiers":[
        {
            "category":"Banks & Credit Unions",
            "subcategory":"Investment Brokerage",
            "type":"Services"
        },
        {
            "category":"Professional",
            "subcategory":"Management & Consulting",
            "type":"Services"
        }
    ],
    "sg:phone":"+1 901 737 6737",
    "sg:postcode":"38018",
    "sg:province":"TN",
    "sg:tags":[
        "consultant",
        "planning",
        "financial"
    ],
    "wof:name":"Mainstreet Financial Group",
    "wof:placetype":"venue"
},
  "geometry": {"coordinates":[-89.788599,35.1538],"type":"Point"}
}