{
  "type": "Feature",
  "properties": {
    "addr:full":"5495 Winchester Rd Memphis TN 38115",
    "addr:housenumber":"5495",
    "addr:postcode":"38115",
    "addr:street":"Winchester Rd",
    "iso:country":"US",
    "sg:address":"5495 Winchester Rd",
    "sg:city":"Memphis",
    "sg:classifiers":[
        {
            "category":"Personal",
            "subcategory":"Beauty Salon",
            "type":"Services"
        }
    ],
    "sg:phone":"+1 901 367 0616",
    "sg:postcode":"38115",
    "sg:province":"TN",
    "wof:name":"Du/Ba-Mer",
    "wof:placetype":"venue"
},
  "geometry": {"coordinates":[-89.87888,35.050316],"type":"Point"}
}