{
  "type": "Feature",
  "properties": {
    "addr:full":"3162 Hwy 79 Indian Mound TN 37079",
    "addr:housenumber":"3162",
    "addr:postcode":"37079",
    "addr:street":"Hwy 79",
    "iso:country":"US",
    "sg:address":"3162 Hwy 79",
    "sg:city":"Indian Mound",
    "sg:classifiers":[
        {
            "category":"Shopping",
            "subcategory":"Bicycles & Sporting Goods",
            "type":"Retail Goods"
        }
    ],
    "sg:phone":"+1 931 232 6648",
    "sg:postcode":"37079",
    "sg:province":"TN",
    "sg:tags":[
        "bait",
        "fishing"
    ],
    "wof:name":"J T's Bait & Tackle",
    "wof:placetype":"venue"
},
  "geometry": {"coordinates":[-87.660549,36.546962],"type":"Point"}
}