{
  "type": "Feature",
  "properties": {
    "iso:country":"US",
    "sg:address":"6775 Clinton Hwy",
    "sg:city":"Knoxville",
    "sg:classifiers":[
        {
            "category":"Restaurant",
            "type":"Food & Drink"
        }
    ],
    "sg:phone":"+1 865 947 8990",
    "sg:postcode":"37912",
    "sg:province":"TN",
    "sg:tags":[
        "eating"
    ],
    "wof:name":"Taco Bell",
    "wof:placetype":"venue"
},
  "geometry": {"coordinates":[-84.02788700000001,36.007122],"type":"Point"}
}