{
  "type": "Feature",
  "properties": {
    "iso:country":"US",
    "sg:address":"15164 Highland Dr",
    "sg:city":"Mc Kenzie",
    "sg:classifiers":[
        {
            "category":"Retail",
            "subcategory":"Laundry & Dry Cleaning",
            "type":"Services"
        }
    ],
    "sg:phone":"+1 731 352 4864",
    "sg:postcode":"38201",
    "sg:province":"TN",
    "sg:tags":[
        "cleaners",
        "rug",
        "carpet"
    ],
    "wof:name":"Spotless Carpet Cleaners",
    "wof:placetype":"venue"
},
  "geometry": {"coordinates":[-88.520741,36.120824],"type":"Point"}
}