{
  "type": "Feature",
  "properties": {
    "iso:country":"US",
    "sg:address":"107 US Hwy 641 N",
    "sg:city":"Camden",
    "sg:classifiers":[
        {
            "category":"Manufacturing",
            "subcategory":"Jewelry",
            "type":"Manufacturing & Wholesale Goods"
        }
    ],
    "sg:phone":"+1 731 584 4613",
    "sg:postcode":"38320",
    "sg:province":"TN",
    "wof:name":"American Shell Co",
    "wof:placetype":"venue"
},
  "geometry": {"coordinates":[-88.11511299999999,36.056259],"type":"Point"}
}