{
  "type": "Feature",
  "properties": {
    "iso:country":"US",
    "sg:address":"70 Holmes Mill Rd",
    "sg:city":"Huntingdon",
    "sg:classifiers":[
        {
            "category":"Real Estate",
            "subcategory":"Real Estate Operator",
            "type":"Services"
        }
    ],
    "sg:phone":"+1 731 986 2125",
    "sg:postcode":"38344",
    "sg:province":"TN",
    "sg:tags":[
        "apartment"
    ],
    "wof:name":"Cedar Country Estate",
    "wof:placetype":"venue"
},
  "geometry": {"coordinates":[-88.40168199999999,36.023587],"type":"Point"}
}