{
  "type": "Feature",
  "properties": {
    "iso:country":"US",
    "sg:address":"4215 Wallace Ln",
    "sg:city":"Nashville",
    "sg:classifiers":[
        {
            "category":"Professional",
            "subcategory":"Art Services",
            "type":"Services"
        }
    ],
    "sg:phone":"+1 615 783 0093",
    "sg:postcode":"37215",
    "sg:province":"TN",
    "sg:tags":[
        "commercial",
        "design"
    ],
    "sg:website":"www.ourdesignsinc.com",
    "wof:name":"Our Designs Inc",
    "wof:placetype":"venue"
},
  "geometry": {"coordinates":[-86.833974,36.102379],"type":"Point"}
}