{
  "type": "Feature",
  "properties": {
    "addr:full":"3939 Bethel Rd Pulaski TN 38478",
    "addr:housenumber":"3939",
    "addr:postcode":"38478",
    "addr:street":"Bethel Rd",
    "iso:country":"US",
    "sg:address":"3939 Bethel Rd",
    "sg:city":"Pulaski",
    "sg:classifiers":[
        {
            "category":"Manufacturing",
            "subcategory":"Food",
            "type":"Manufacturing & Wholesale Goods"
        }
    ],
    "sg:phone":"+1 931 363 7708",
    "sg:postcode":"38478",
    "sg:province":"TN",
    "sg:tags":[
        "popcorn",
        "supply"
    ],
    "wof:name":"Merritt Pop Popcorn Co",
    "wof:placetype":"venue"
},
  "geometry": {"coordinates":[-87.038466,35.114701],"type":"Point"}
}