{
  "type": "Feature",
  "properties": {
    "iso:country":"US",
    "sg:address":"724 W Market St",
    "sg:city":"Bolivar",
    "sg:classifiers":[
        {
            "category":"Banks & Credit Unions",
            "subcategory":"Bank",
            "type":"Services"
        }
    ],
    "sg:phone":"+1 731 658 2536",
    "sg:postcode":"38008",
    "sg:province":"TN",
    "sg:tags":[
        "state",
        "commercial",
        "loan",
        "broker"
    ],
    "sg:website":"www.bankofbolivar.com",
    "wof:name":"Bank Of Bolivar",
    "wof:placetype":"venue"
},
  "geometry": {"coordinates":[-88.99629299999999,35.256442],"type":"Point"}
}