{
  "type": "Feature",
  "properties": {
    "addr:full":"307 N Main St Dickson TN 37055",
    "addr:housenumber":"307",
    "addr:postcode":"37055",
    "addr:street":"N Main St",
    "iso:country":"US",
    "sg:address":"307 N Main St",
    "sg:city":"Dickson",
    "sg:classifiers":[
        {
            "category":"Sports & Exercise",
            "subcategory":"Gym",
            "type":"Entertainment"
        }
    ],
    "sg:phone":"+1 615 446 4949",
    "sg:postcode":"37055",
    "sg:province":"TN",
    "sg:tags":[
        "fitness",
        "physical",
        "facility"
    ],
    "wof:name":"United Figure Salon",
    "wof:placetype":"venue"
},
  "geometry": {"coordinates":[-87.38432299999999,36.07925],"type":"Point"}
}