{
  "type": "Feature",
  "properties": {
    "addr:full":"320 S Walnut Bend Rd Cordova TN 38018",
    "addr:housenumber":"320",
    "addr:postcode":"38018",
    "addr:street":"S Walnut Bend Rd",
    "iso:country":"US",
    "sg:address":"320 S Walnut Bend Rd",
    "sg:city":"Cordova",
    "sg:classifiers":[
        {
            "category":"Health Services",
            "subcategory":"Nursing And Care Facility",
            "type":"Services"
        }
    ],
    "sg:phone":"+1 901 385 2221",
    "sg:postcode":"38018",
    "sg:province":"TN",
    "sg:tags":[
        "hospice"
    ],
    "sg:website":"www.hospicesouth.com",
    "wof:name":"Hospice USA LLC",
    "wof:placetype":"venue"
},
  "geometry": {"coordinates":[-89.79850399999999,35.121658],"type":"Point"}
}