{
  "type": "Feature",
  "properties": {
    "iso:country":"US",
    "sg:address":"3411 Vinewood Dr",
    "sg:city":"Chattanooga",
    "sg:classifiers":[
        {
            "category":"Food & Beverages",
            "subcategory":"Groceries & Convenience Stores",
            "type":"Retail Goods"
        }
    ],
    "sg:phone":"+1 423 629 9788",
    "sg:postcode":"37406",
    "sg:province":"TN",
    "wof:name":"Golden Gallon",
    "wof:placetype":"venue"
},
  "geometry": {"coordinates":[-85.23970199999999,35.076613],"type":"Point"}
}