{
  "type": "Feature",
  "properties": {
    "iso:country":"US",
    "sg:address":"266 Donavon Dr",
    "sg:city":"Mc Minnville",
    "sg:classifiers":[
        {
            "category":"Shopping",
            "subcategory":"Jewelry",
            "type":"Retail Goods"
        }
    ],
    "sg:phone":"+1 931 815 8860",
    "sg:postcode":"37110",
    "sg:province":"TN",
    "sg:tags":[
        "jeweler"
    ],
    "wof:name":"Beedz & Treasurers Jewelry Co",
    "wof:placetype":"venue"
},
  "geometry": {"coordinates":[-85.825597,35.681445],"type":"Point"}
}