{
  "type": "Feature",
  "properties": {
    "iso:country":"US",
    "sg:address":"2297 Kingtown Rd",
    "sg:city":"Winfield",
    "sg:classifiers":[
        {
            "category":"Freight",
            "type":"Transportation"
        }
    ],
    "sg:phone":"+1 423 569 3307",
    "sg:postcode":"37892",
    "sg:province":"TN",
    "sg:tags":[
        "hauling",
        "trucking"
    ],
    "wof:name":"Garner Trucking Inc",
    "wof:placetype":"venue"
},
  "geometry": {"coordinates":[-84.459795,36.571969],"type":"Point"}
}