{
  "type": "Feature",
  "properties": {
    "addr:full":"2500 Hwy 31 W White House TN 37188",
    "addr:housenumber":"2500",
    "addr:postcode":"37188",
    "addr:street":"Hwy 31 W",
    "iso:country":"US",
    "sg:address":"2500 Hwy 31 W",
    "sg:city":"White House",
    "sg:classifiers":[
        {
            "category":"Food & Beverages",
            "subcategory":"Groceries & Convenience Stores",
            "type":"Retail Goods"
        }
    ],
    "sg:phone":"+1 615 672 3589",
    "sg:postcode":"37188",
    "sg:province":"TN",
    "sg:tags":[
        "station",
        "gasoline"
    ],
    "wof:name":"Super Stop Market",
    "wof:placetype":"venue"
},
  "geometry": {"coordinates":[-86.679717,36.440522],"type":"Point"}
}