{
  "type": "Feature",
  "properties": {
    "iso:country":"US",
    "sg:address":"2615 Jefferson St",
    "sg:city":"Nashville",
    "sg:classifiers":[
        {
            "category":"Restaurant",
            "type":"Food & Drink"
        }
    ],
    "sg:phone":"+1 615 321 1181",
    "sg:postcode":"37208",
    "sg:province":"TN",
    "wof:name":"One Brew Sports Bar & Grill",
    "wof:placetype":"venue"
},
  "geometry": {"coordinates":[-86.81692700000001,36.168122],"type":"Point"}
}