{
  "type": "Feature",
  "properties": {
    "iso:country":"US",
    "sg:address":"880 Joe Sanderlin Rd",
    "sg:city":"Stanton",
    "sg:classifiers":[
        {
            "category":"Farming",
            "subcategory":"Farm",
            "type":"Manufacturing & Wholesale Goods"
        }
    ],
    "sg:phone":"+1 731 548 6736",
    "sg:postcode":"38069",
    "sg:province":"TN",
    "sg:tags":[
        "farmer"
    ],
    "wof:name":"Marvin T Sanderlin",
    "wof:placetype":"venue"
},
  "geometry": {"coordinates":[-89.349216,35.462084],"type":"Point"}
}