{
  "type": "Feature",
  "properties": {
    "iso:country":"US",
    "sg:address":"1269 Marlin Rd",
    "sg:city":"Memphis",
    "sg:classifiers":[
        {
            "category":"Personal",
            "subcategory":"Beauty Salon",
            "type":"Services"
        }
    ],
    "sg:phone":"+1 901 398 0346",
    "sg:postcode":"38116",
    "sg:province":"TN",
    "sg:tags":[
        "shop"
    ],
    "wof:name":"De Choix Lecheveux",
    "wof:placetype":"venue"
},
  "geometry": {"coordinates":[-90.02112,35.034137],"type":"Point"}
}