{
  "type": "Feature",
  "properties": {
    "iso:country":"US",
    "sg:address":"191 Russell St",
    "sg:city":"Paris",
    "sg:classifiers":[
        {
            "category":"Professional",
            "type":"Services"
        }
    ],
    "sg:phone":"+1 731 644 3243",
    "sg:postcode":"38242",
    "sg:province":"TN",
    "sg:tags":[
        "establishment"
    ],
    "wof:name":"Showtime Enterprises",
    "wof:placetype":"venue"
},
  "geometry": {"coordinates":[-88.317818,36.283236],"type":"Point"}
}