{
  "type": "Feature",
  "properties": {
    "iso:country":"US",
    "sg:address":"213 E Main St",
    "sg:city":"Johnson City",
    "sg:classifiers":[
        {
            "category":"Shopping",
            "subcategory":"Books",
            "type":"Retail Goods"
        }
    ],
    "sg:phone":"+1 423 929 0317",
    "sg:postcode":"37604",
    "sg:province":"TN",
    "sg:tags":[
        "store"
    ],
    "wof:name":"Atomik Comiks",
    "wof:placetype":"venue"
},
  "geometry": {"coordinates":[-82.352664,36.316405],"type":"Point"}
}