{
  "type": "Feature",
  "properties": {
    "iso:country":"US",
    "sg:address":"4440 Rucker Christiana Rd",
    "sg:city":"Christiana",
    "sg:classifiers":[
        {
            "category":"Autos & Motor Vehicles",
            "subcategory":"Auto Supplies",
            "type":"Retail Goods"
        }
    ],
    "sg:phone":"+1 615 890 6497",
    "sg:postcode":"37037",
    "sg:province":"TN",
    "sg:tags":[
        "equipment",
        "racing",
        "car",
        "automobile"
    ],
    "wof:name":"Firestorm Racing",
    "wof:placetype":"venue"
},
  "geometry": {"coordinates":[-86.38320299999999,35.746204],"type":"Point"}
}