{
  "type": "Feature",
  "properties": {
    "iso:country":"US",
    "sg:address":"202 S Russell St",
    "sg:city":"Portland",
    "sg:classifiers":[
        {
            "category":"Personal",
            "subcategory":"Beauty Salon",
            "type":"Services"
        }
    ],
    "sg:phone":"+1 615 323 0073",
    "sg:postcode":"37148",
    "sg:province":"TN",
    "wof:name":"Yolanda's Hair Care & Design",
    "wof:placetype":"venue"
},
  "geometry": {"coordinates":[-86.512326,36.579813],"type":"Point"}
}