{
  "type": "Feature",
  "properties": {
    "iso:country":"US",
    "sg:address":"1901 E 29th St",
    "sg:city":"Chattanooga",
    "sg:classifiers":[
        {
            "category":"Freight",
            "type":"Transportation"
        }
    ],
    "sg:phone":"+1 423 622 4749",
    "sg:postcode":"37407",
    "sg:province":"TN",
    "sg:tags":[
        "trucking"
    ],
    "wof:name":"Rock Creek Logistics LLC",
    "wof:placetype":"venue"
},
  "geometry": {"coordinates":[-85.28703299999999,35.010799],"type":"Point"}
}