{
  "type": "Feature",
  "properties": {
    "addr:full":"370 Fountain River Dr Memphis TN 38120",
    "addr:housenumber":"370",
    "addr:postcode":"38120",
    "addr:street":"Fountain River Dr",
    "iso:country":"US",
    "sg:address":"370 Fountain River Dr",
    "sg:city":"Memphis",
    "sg:classifiers":[
        {
            "category":"Professional",
            "subcategory":"Engineering",
            "type":"Services"
        }
    ],
    "sg:phone":"+1 901 763 1785",
    "sg:postcode":"38120",
    "sg:province":"TN",
    "wof:name":"Bmb Engineering",
    "wof:placetype":"venue"
},
  "geometry": {"coordinates":[-89.876136,35.142418],"type":"Point"}
}