{
  "type": "Feature",
  "properties": {
    "iso:country":"US",
    "sg:address":"420 E Reelfoot Ave",
    "sg:city":"Union City",
    "sg:classifiers":[
        {
            "category":"Food & Beverages",
            "subcategory":"Groceries & Convenience Stores",
            "type":"Retail Goods"
        }
    ],
    "sg:phone":"+1 731 885 1692",
    "sg:postcode":"38261",
    "sg:province":"TN",
    "wof:name":"Maverick",
    "wof:placetype":"venue"
},
  "geometry": {"coordinates":[-89.05684100000001,36.414384],"type":"Point"}
}