{
  "type": "Feature",
  "properties": {
    "iso:country":"US",
    "sg:address":"485 Stevens Rd",
    "sg:city":"Jefferson City",
    "sg:classifiers":[
        {
            "category":"Organizations",
            "subcategory":"Religious Organization",
            "type":"Services"
        }
    ],
    "sg:phone":"+1 865 475 3911",
    "sg:postcode":"37760",
    "sg:province":"TN",
    "wof:name":"Faithful Missionary Baptist",
    "wof:placetype":"venue"
},
  "geometry": {"coordinates":[-83.48665,36.096168],"type":"Point"}
}