{
  "type": "Feature",
  "properties": {
    "addr:full":"367 Spencer Rd Mc Minnville TN 37110",
    "addr:housenumber":"367",
    "addr:postcode":"37110",
    "addr:street":"Spencer Rd",
    "iso:country":"US",
    "sg:address":"367 Spencer Rd",
    "sg:city":"Mc Minnville",
    "sg:classifiers":[
        {
            "category":"Home & Garden",
            "subcategory":"Garden Supply",
            "type":"Retail Goods"
        }
    ],
    "sg:phone":"+1 931 668 1590",
    "sg:postcode":"37110",
    "sg:province":"TN",
    "sg:tags":[
        "nurseryman"
    ],
    "wof:name":"Middle Tenn Nursery Ctr",
    "wof:placetype":"venue"
},
  "geometry": {"coordinates":[-85.70184399999999,35.713397],"type":"Point"}
}