{
  "type": "Feature",
  "properties": {
    "iso:country":"US",
    "sg:address":"7417 Kingston Pike",
    "sg:city":"Knoxville",
    "sg:classifiers":[
        {
            "category":"Professional",
            "subcategory":"Lawyer & Legal Services",
            "type":"Services"
        }
    ],
    "sg:phone":"+1 865 584 8620",
    "sg:postcode":"37919",
    "sg:province":"TN",
    "sg:tags":[
        "attorney"
    ],
    "wof:name":"Loring Justice",
    "wof:placetype":"venue"
},
  "geometry": {"coordinates":[-84.03354899999999,35.929554],"type":"Point"}
}