{
  "type": "Feature",
  "properties": {
    "iso:country":"US",
    "sg:address":"2814 Montvale Rd",
    "sg:city":"Maryville",
    "sg:classifiers":[
        {
            "category":"Building & Trades",
            "subcategory":"Electrical",
            "type":"Services"
        }
    ],
    "sg:phone":"+1 865 380 0432",
    "sg:postcode":"37803",
    "sg:province":"TN",
    "sg:tags":[
        "work",
        "electrical"
    ],
    "wof:name":"Wilburn Quality Heating & AC",
    "wof:placetype":"venue"
},
  "geometry": {"coordinates":[-83.96676100000001,35.705662],"type":"Point"}
}