{
  "type": "Feature",
  "properties": {
    "iso:country":"US",
    "sg:address":"161 4th Ave N",
    "sg:city":"Nashville",
    "sg:classifiers":[
        {
            "category":"Insurance",
            "subcategory":"Health Insurance",
            "type":"Services"
        }
    ],
    "sg:phone":"+1 615 259 6000",
    "sg:postcode":"37219",
    "sg:province":"TN",
    "sg:tags":[
        "carrier"
    ],
    "wof:name":"Tourists Information",
    "wof:placetype":"venue"
},
  "geometry": {"coordinates":[-86.777923,36.161952],"type":"Point"}
}