{
  "type": "Feature",
  "properties": {
    "addr:full":"660 Horace Crow Dr Clarksville TN 37043",
    "addr:housenumber":"660",
    "addr:postcode":"37043",
    "addr:street":"Horace Crow Dr",
    "iso:country":"US",
    "sg:address":"660 Horace Crow Dr",
    "sg:city":"Clarksville",
    "sg:classifiers":[
        {
            "category":"Professional",
            "subcategory":"Business Services",
            "type":"Services"
        }
    ],
    "sg:phone":"+1 931 647 3299",
    "sg:postcode":"37043",
    "sg:province":"TN",
    "wof:name":"Tactronics",
    "wof:placetype":"venue"
},
  "geometry": {"coordinates":[-87.318618,36.504333],"type":"Point"}
}