{
  "type": "Feature",
  "properties": {
    "iso:country":"US",
    "sg:address":"4087 Viscount Ave",
    "sg:city":"Memphis",
    "sg:classifiers":[
        {
            "category":"Professional",
            "subcategory":"Engineering",
            "type":"Services"
        },
        {
            "category":"Home & Garden",
            "subcategory":"Building Materials",
            "type":"Retail Goods"
        },
        {
            "category":"Building & Trades",
            "subcategory":"Construction",
            "type":"Services"
        }
    ],
    "sg:phone":"+1 901 745 4500",
    "sg:postcode":"38118",
    "sg:province":"TN",
    "sg:tags":[
        "system",
        "specialty",
        "heating",
        "contractor",
        "equipment",
        "air conditioning"
    ],
    "sg:website":"http://find.trane.com/tcs-dealer-419347?utm_source=YP&utm_medium=banner&utm_campaign=TL",
    "wof:name":"Helpco Services, Inc",
    "wof:placetype":"venue"
},
  "geometry": {"coordinates":[-89.927117,35.048835],"type":"Point"}
}