{
  "type": "Feature",
  "properties": {
    "iso:country":"US",
    "sg:address":"1911 Congress Pkwy NW",
    "sg:city":"Athens",
    "sg:classifiers":[
        {
            "category":"Health Services",
            "subcategory":"Doctor",
            "type":"Services"
        }
    ],
    "sg:phone":"+1 423 745 2630",
    "sg:postcode":"37303",
    "sg:province":"TN",
    "sg:tags":[
        "dentist"
    ],
    "wof:name":"Dogwood Dental Care",
    "wof:placetype":"venue"
},
  "geometry": {"coordinates":[-84.630437,35.445298],"type":"Point"}
}