{
  "type": "Feature",
  "properties": {
    "addr:full":"2006 21st Ave S Nashville TN 37212",
    "addr:housenumber":"2006",
    "addr:postcode":"37212",
    "addr:street":"21St Ave S",
    "iso:country":"US",
    "sg:address":"2006 21st Ave S",
    "sg:city":"Nashville",
    "sg:classifiers":[
        {
            "category":"Health Services",
            "subcategory":"Doctor",
            "type":"Services"
        }
    ],
    "sg:phone":"+1 615 383 4440",
    "sg:postcode":"37212",
    "sg:province":"TN",
    "sg:tags":[
        "dentist"
    ],
    "wof:name":"Mitchell Wright DDS",
    "wof:placetype":"venue"
},
  "geometry": {"coordinates":[-86.801376,36.131828],"type":"Point"}
}