{
  "type": "Feature",
  "properties": {
    "iso:country":"US",
    "sg:address":"900 Airport Rd",
    "sg:city":"Chattanooga",
    "sg:classifiers":[
        {
            "category":"Building & Trades",
            "subcategory":"Electrical",
            "type":"Services"
        }
    ],
    "sg:phone":"+1 423 855 4307",
    "sg:postcode":"37421",
    "sg:province":"TN",
    "sg:tags":[
        "electrical",
        "contractor"
    ],
    "wof:name":"Rievley Electric Co Inc",
    "wof:placetype":"venue"
},
  "geometry": {"coordinates":[-85.19460599999999,35.031974],"type":"Point"}
}