{
  "type": "Feature",
  "properties": {
    "iso:country":"US",
    "sg:address":"8370 Mitchell Mill Rd",
    "sg:city":"Ooltewah",
    "sg:classifiers":[
        {
            "category":"Recreation",
            "type":"Entertainment"
        }
    ],
    "sg:phone":"+1 423 238 5692",
    "sg:postcode":"37363",
    "sg:province":"TN",
    "sg:tags":[
        "club",
        "membership"
    ],
    "wof:name":"Mill Run Pool & Club House",
    "wof:placetype":"venue"
},
  "geometry": {"coordinates":[-85.066086,35.090927],"type":"Point"}
}