{
  "type": "Feature",
  "properties": {
    "addr:full":"3968 Jackson Ave Memphis TN 38128",
    "addr:housenumber":"3968",
    "addr:postcode":"38128",
    "addr:street":"Jackson Ave",
    "iso:country":"US",
    "sg:address":"3968 Jackson Ave",
    "sg:city":"Memphis",
    "sg:classifiers":[
        {
            "category":"Food & Beverages",
            "subcategory":"Groceries & Convenience Stores",
            "type":"Retail Goods"
        }
    ],
    "sg:phone":"+1 901 377 0578",
    "sg:postcode":"38128",
    "sg:province":"TN",
    "wof:name":"Super Mercado El Rey",
    "wof:placetype":"venue"
},
  "geometry": {"coordinates":[-89.931045,35.185366],"type":"Point"}
}