{
  "type": "Feature",
  "properties": {
    "iso:country":"US",
    "sg:address":"4372 Kerwin Dr",
    "sg:city":"Memphis",
    "sg:classifiers":[
        {
            "category":"Professional",
            "subcategory":"Business Services",
            "type":"Services"
        }
    ],
    "sg:phone":"+1 901 876 5390",
    "sg:postcode":"38128",
    "sg:province":"TN",
    "sg:tags":[
        "planning",
        "financial"
    ],
    "wof:name":"Image Productions",
    "wof:placetype":"venue"
},
  "geometry": {"coordinates":[-89.93441900000001,35.245107],"type":"Point"}
}