{
  "type": "Feature",
  "properties": {
    "iso:country":"US",
    "sg:address":"200 Shelby St",
    "sg:city":"Kingsport",
    "sg:classifiers":[
        {
            "category":"Government",
            "subcategory":"Court House",
            "type":"Public Place"
        }
    ],
    "sg:phone":"+1 423 224 1730",
    "sg:postcode":"37660",
    "sg:province":"TN",
    "sg:tags":[
        "county"
    ],
    "wof:name":"Sullivan County Juvenile Court",
    "wof:placetype":"venue"
},
  "geometry": {"coordinates":[-82.686088,36.539212],"type":"Point"}
}