{
  "type": "Feature",
  "properties": {
    "iso:country":"US",
    "sg:address":"2749 E Center St",
    "sg:city":"Kingsport",
    "sg:classifiers":[
        {
            "category":"Personal",
            "subcategory":"Beauty Salon",
            "type":"Services"
        }
    ],
    "sg:phone":"+1 423 246 1044",
    "sg:postcode":"37664",
    "sg:province":"TN",
    "wof:name":"Bangs Hair Studio",
    "wof:placetype":"venue"
},
  "geometry": {"coordinates":[-82.51575099999999,36.533789],"type":"Point"}
}