{
  "type": "Feature",
  "properties": {
    "iso:country":"US",
    "sg:address":"2745 Getwell Rd",
    "sg:city":"Memphis",
    "sg:classifiers":[
        {
            "category":"Retail",
            "subcategory":"Self-service Laundry",
            "type":"Services"
        }
    ],
    "sg:phone":"+1 901 365 2465",
    "sg:postcode":"38118",
    "sg:province":"TN",
    "wof:name":"Getwell Coin Laundry",
    "wof:placetype":"venue"
},
  "geometry": {"coordinates":[-89.931856,35.073777],"type":"Point"}
}