{
  "type": "Feature",
  "properties": {
    "iso:country":"US",
    "sg:address":"350 W Race St",
    "sg:city":"Kingston",
    "sg:classifiers":[
        {
            "category":"Retail",
            "subcategory":"Funeral Services",
            "type":"Services"
        }
    ],
    "sg:phone":"+1 865 376 6531",
    "sg:postcode":"37763",
    "sg:province":"TN",
    "sg:tags":[
        "director"
    ],
    "wof:name":"Kyker Funeral Home",
    "wof:placetype":"venue"
},
  "geometry": {"coordinates":[-84.524818,35.879204],"type":"Point"}
}