{
  "type": "Feature",
  "properties": {
    "iso:country":"US",
    "sg:address":"309 Commerce St",
    "sg:city":"Kingsport",
    "sg:classifiers":[
        {
            "category":"Professional",
            "subcategory":"Art Services",
            "type":"Services"
        }
    ],
    "sg:phone":"+1 423 246 6751",
    "sg:postcode":"37660",
    "sg:province":"TN",
    "sg:tags":[
        "graphic",
        "designer"
    ],
    "wof:name":"Steadman Designs",
    "wof:placetype":"venue"
},
  "geometry": {"coordinates":[-82.558538,36.547091],"type":"Point"}
}