{
  "type": "Feature",
  "properties": {
    "addr:full":"5963 Nature Ln Knoxville TN 37912",
    "addr:housenumber":"5963",
    "addr:postcode":"37912",
    "addr:street":"Nature Ln",
    "iso:country":"US",
    "sg:address":"5963 Nature Ln",
    "sg:city":"Knoxville",
    "sg:classifiers":[
        {
            "category":"Building & Trades",
            "subcategory":"Plumbing",
            "type":"Services"
        }
    ],
    "sg:phone":"+1 865 556 1560",
    "sg:postcode":"37912",
    "sg:province":"TN",
    "sg:tags":[
        "conditioning",
        "air",
        "system",
        "contractor"
    ],
    "wof:name":"O'Dells Heating & Cooling",
    "wof:placetype":"venue"
},
  "geometry": {"coordinates":[-83.976765,36.022887],"type":"Point"}
}