{
  "type": "Feature",
  "properties": {
    "addr:full":"6000 State Hwy 100 Nashville TN 37205",
    "addr:housenumber":"6000",
    "addr:postcode":"37205",
    "addr:street":"State Hwy 100",
    "iso:country":"US",
    "sg:address":"6000 State Hwy 100",
    "sg:city":"Nashville",
    "sg:classifiers":[
        {
            "category":"Personal",
            "subcategory":"Beauty Salon",
            "type":"Services"
        }
    ],
    "sg:phone":"+1 615 352 3545",
    "sg:postcode":"37205",
    "sg:province":"TN",
    "wof:name":"Escape Day Spa & Salon",
    "wof:placetype":"venue"
},
  "geometry": {"coordinates":[-86.86953,36.103725],"type":"Point"}
}