{
  "type": "Feature",
  "properties": {
    "iso:country":"US",
    "sg:address":"719 E Center St",
    "sg:city":"Kingsport",
    "sg:classifiers":[
        {
            "category":"Donuts",
            "subcategory":"None",
            "type":"Food & Drink"
        }
    ],
    "sg:phone":"+1 423 245 2441",
    "sg:postcode":"37660",
    "sg:province":"TN",
    "sg:tags":[
        "shop"
    ],
    "sg:website":"http://www.krispykreme.com/",
    "wof:name":"Krispy Kreme",
    "wof:placetype":"venue"
},
  "geometry": {"coordinates":[-82.553848,36.544182],"type":"Point"}
}