{
  "type": "Feature",
  "properties": {
    "iso:country":"US",
    "sg:address":"1948 Springcroft Dr",
    "sg:city":"Franklin",
    "sg:classifiers":[
        {
            "category":"Professional",
            "type":"Services"
        }
    ],
    "sg:phone":"+1 615 778 0606",
    "sg:postcode":"37027",
    "sg:province":"TN",
    "wof:name":"Techwood Hill",
    "wof:placetype":"venue"
},
  "geometry": {"coordinates":[-86.75232699999999,35.923673],"type":"Point"}
}