{
  "type": "Feature",
  "properties": {
    "iso:country":"US",
    "sg:address":"3461 E Raines Rd",
    "sg:city":"Memphis",
    "sg:classifiers":[
        {
            "category":"Freight",
            "type":"Transportation"
        },
        {
            "category":"Shopping",
            "subcategory":"Stationery & Office Supplies",
            "type":"Retail Goods"
        }
    ],
    "sg:phone":"+1 901 365 3100",
    "sg:postcode":"38118",
    "sg:province":"TN",
    "sg:tags":[
        "general"
    ],
    "sg:website":"www.averydennison.com",
    "wof:name":"Avery Dennison Corporation",
    "wof:placetype":"venue"
},
  "geometry": {"coordinates":[-89.947473,35.037547],"type":"Point"}
}