{
  "type": "Feature",
  "properties": {
    "iso:country":"US",
    "sg:address":"7964 Spot Light Rd",
    "sg:city":"Lyles",
    "sg:classifiers":[
        {
            "category":"Utilities",
            "subcategory":"Water",
            "type":"Services"
        }
    ],
    "sg:phone":"+1 931 670 3957",
    "sg:postcode":"37098",
    "sg:province":"TN",
    "sg:tags":[
        "company",
        "sewage"
    ],
    "wof:name":"Bon Aqua & Lyles Utility Dist",
    "wof:placetype":"venue"
},
  "geometry": {"coordinates":[-87.331175,35.915777],"type":"Point"}
}