{
  "type": "Feature",
  "properties": {
    "iso:country":"US",
    "sg:address":"590 Midway St",
    "sg:city":"Lewisburg",
    "sg:classifiers":[
        {
            "category":"Wholesale",
            "subcategory":"Durable Goods & Equipment",
            "type":"Manufacturing & Wholesale Goods"
        }
    ],
    "sg:phone":"+1 931 359 3743",
    "sg:postcode":"37091",
    "sg:province":"TN",
    "sg:tags":[
        "fire",
        "extinguisher"
    ],
    "wof:name":"Squad 1",
    "wof:placetype":"venue"
},
  "geometry": {"coordinates":[-86.802556,35.443901],"type":"Point"}
}