{
  "type": "Feature",
  "properties": {
    "iso:country":"US",
    "sg:address":"613 Parkway",
    "sg:city":"Sevierville",
    "sg:classifiers":[
        {
            "category":"Restaurant",
            "type":"Food & Drink"
        }
    ],
    "sg:phone":"+1 865 453 8001",
    "sg:postcode":"37862",
    "sg:province":"TN",
    "sg:tags":[
        "eating"
    ],
    "wof:name":"Pizza Hut",
    "wof:placetype":"venue"
},
  "geometry": {"coordinates":[-83.566068,35.860143],"type":"Point"}
}