{
  "type": "Feature",
  "properties": {
    "iso:country":"US",
    "sg:address":"400 W Morelia Ave",
    "sg:city":"Knoxville",
    "sg:classifiers":[
        {
            "category":"Insurance",
            "subcategory":"Life Insurance",
            "type":"Services"
        }
    ],
    "sg:phone":"+1 865 521 0966",
    "sg:postcode":"37917",
    "sg:province":"TN",
    "sg:tags":[
        "carrier"
    ],
    "wof:name":"Rsig",
    "wof:placetype":"venue"
},
  "geometry": {"coordinates":[-83.94375700000001,35.98959],"type":"Point"}
}