{
  "type": "Feature",
  "properties": {
    "addr:full":"313 N Mount Juliet Rd Mt Juliet TN 37122",
    "addr:housenumber":"313",
    "addr:postcode":"37122",
    "addr:street":"N Mount Juliet Rd",
    "iso:country":"US",
    "sg:address":"313 N Mount Juliet Rd",
    "sg:city":"Mt Juliet",
    "sg:classifiers":[
        {
            "category":"Professional",
            "type":"Services"
        }
    ],
    "sg:phone":"+1 615 758 3825",
    "sg:postcode":"37122",
    "sg:province":"TN",
    "wof:name":"Lighthouse Family Svc Inc",
    "wof:placetype":"venue"
},
  "geometry": {"coordinates":[-86.512804,36.176258],"type":"Point"}
}