{
  "type": "Feature",
  "properties": {
    "iso:country":"US",
    "sg:address":"434 W 1st North St",
    "sg:city":"Morristown",
    "sg:classifiers":[
        {
            "category":"Restaurant",
            "type":"Food & Drink"
        }
    ],
    "sg:menulink":"http://www.allmenus.com/tn/morristown/246252-krystal/menu/",
    "sg:phone":"+1 423 587 3367",
    "sg:postcode":"37814",
    "sg:province":"TN",
    "sg:tags":[
        "burger",
        "american"
    ],
    "wof:name":"Krystal",
    "wof:placetype":"venue"
},
  "geometry": {"coordinates":[-83.297104,36.212499],"type":"Point"}
}