{
  "type": "Feature",
  "properties": {
    "iso:country":"US",
    "sg:address":"5487 Courtland Rd",
    "sg:city":"Springfield",
    "sg:classifiers":[
        {
            "category":"Manufacturing",
            "subcategory":"Metals",
            "type":"Manufacturing & Wholesale Goods"
        }
    ],
    "sg:phone":"+1 615 430 7763",
    "sg:postcode":"37172",
    "sg:province":"TN",
    "sg:tags":[
        "coating"
    ],
    "wof:name":"Steel Blast Shot Blasting",
    "wof:placetype":"venue"
},
  "geometry": {"coordinates":[-86.838232,36.455296],"type":"Point"}
}