{
  "type": "Feature",
  "properties": {
    "iso:country":"US",
    "sg:address":"7130 Beacon Ln",
    "sg:city":"Chattanooga",
    "sg:classifiers":[
        {
            "category":"Health Services",
            "subcategory":"Doctor",
            "type":"Services"
        }
    ],
    "sg:phone":"+1 423 894 3866",
    "sg:postcode":"37421",
    "sg:province":"TN",
    "sg:tags":[
        "medical"
    ],
    "wof:name":"Isg",
    "wof:placetype":"venue"
},
  "geometry": {"coordinates":[-85.165531,35.01936],"type":"Point"}
}