{
  "type": "Feature",
  "properties": {
    "iso:country":"US",
    "sg:address":"3130 State Hwy 100 E",
    "sg:city":"Decaturville",
    "sg:classifiers":[
        {
            "category":"Restaurant",
            "type":"Food & Drink"
        }
    ],
    "sg:phone":"+1 731 852 4559",
    "sg:postcode":"38329",
    "sg:province":"TN",
    "sg:tags":[
        "eating"
    ],
    "wof:name":"Broadway Farms Restaurant",
    "wof:placetype":"venue"
},
  "geometry": {"coordinates":[-88.067182,35.580935],"type":"Point"}
}