{
  "type": "Feature",
  "properties": {
    "addr:full":"2617 Sequoya Trce Murfreesboro TN 37127",
    "addr:housenumber":"2617",
    "addr:postcode":"37127",
    "addr:street":"Sequoya Trce",
    "iso:country":"US",
    "sg:address":"2617 Sequoya Trce",
    "sg:city":"Murfreesboro",
    "sg:classifiers":[
        {
            "category":"Home & Garden",
            "subcategory":"Mobile Homes",
            "type":"Retail Goods"
        }
    ],
    "sg:phone":"+1 931 680 9779",
    "sg:postcode":"37127",
    "sg:province":"TN",
    "wof:name":"American Value Homes Inc",
    "wof:placetype":"venue"
},
  "geometry": {"coordinates":[-86.396505,35.79578],"type":"Point"}
}