{
  "type": "Feature",
  "properties": {
    "iso:country":"US",
    "sg:address":"125 Enon Springs Rd E",
    "sg:city":"Smyrna",
    "sg:classifiers":[
        {
            "category":"Personal",
            "subcategory":"Beauty Salon",
            "type":"Services"
        }
    ],
    "sg:phone":"+1 615 223 6703",
    "sg:postcode":"37167",
    "sg:province":"TN",
    "wof:name":"Beautiful Hair Salon & Day Spa",
    "wof:placetype":"venue"
},
  "geometry": {"coordinates":[-86.476581,35.972484],"type":"Point"}
}