{
  "type": "Feature",
  "properties": {
    "iso:country":"US",
    "sg:address":"4767 Highway 58",
    "sg:city":"Chattanooga",
    "sg:classifiers":[
        {
            "category":"Personal",
            "subcategory":"Tanning Parlor",
            "type":"Services"
        },
        {
            "category":"Personal",
            "subcategory":"Nail Salon",
            "type":"Services"
        }
    ],
    "sg:phone":"+1 423 296 0105",
    "sg:postcode":"37416",
    "sg:province":"TN",
    "wof:name":"Susie's Nails & Tanning",
    "wof:placetype":"venue"
},
  "geometry": {"coordinates":[-85.189464,35.087704],"type":"Point"}
}