{
  "type": "Feature",
  "properties": {
    "iso:country":"US",
    "sg:address":"4547 Millbranch Rd",
    "sg:city":"Memphis",
    "sg:classifiers":[
        {
            "category":"Personal",
            "subcategory":"Beauty Salon",
            "type":"Services"
        }
    ],
    "sg:phone":"+1 901 348 6777",
    "sg:postcode":"38116",
    "sg:province":"TN",
    "wof:name":"Healthy Hair Is Beautiful Hair",
    "wof:placetype":"venue"
},
  "geometry": {"coordinates":[-90.007606,35.023436],"type":"Point"}
}