{
  "type": "Feature",
  "properties": {
    "iso:country":"US",
    "sg:address":"103 N Sugar Hollow Rd",
    "sg:city":"Morristown",
    "sg:classifiers":[
        {
            "category":"Wholesale",
            "subcategory":"Hardware",
            "type":"Manufacturing & Wholesale Goods"
        }
    ],
    "sg:phone":"+1 423 581 0500",
    "sg:postcode":"37814",
    "sg:province":"TN",
    "sg:tags":[
        "heating",
        "air",
        "s",
        "electrical",
        "conditioning",
        "plumbing"
    ],
    "wof:name":"Modern Supply Co",
    "wof:placetype":"venue"
},
  "geometry": {"coordinates":[-83.344031,36.19696],"type":"Point"}
}