{
  "type": "Feature",
  "properties": {
    "addr:full":"1340 Walker School Rd Maryville TN 37803",
    "addr:housenumber":"1340",
    "addr:postcode":"37803",
    "addr:street":"Walker School Rd",
    "iso:country":"US",
    "sg:address":"1340 Walker School Rd",
    "sg:city":"Maryville",
    "sg:classifiers":[
        {
            "category":"Autos & Motor Vehicles",
            "subcategory":"Automobile Sales",
            "type":"Retail Goods"
        }
    ],
    "sg:phone":"+1 865 984 5793",
    "sg:postcode":"37803",
    "sg:province":"TN",
    "sg:tags":[
        "classic"
    ],
    "wof:name":"Times Past Classic & Muscle",
    "wof:placetype":"venue"
},
  "geometry": {"coordinates":[-84.034735,35.657519],"type":"Point"}
}