{
  "type": "Feature",
  "properties": {
    "iso:country":"US",
    "sg:address":"1649 Cumberland Ave",
    "sg:city":"Knoxville",
    "sg:classifiers":[
        {
            "category":"Shopping",
            "subcategory":"Books",
            "type":"Retail Goods"
        }
    ],
    "sg:phone":"+1 865 525 7336",
    "sg:postcode":"37916",
    "sg:province":"TN",
    "wof:name":"Campus Bookstore 145",
    "wof:placetype":"venue"
},
  "geometry": {"coordinates":[-83.931552,35.956967],"type":"Point"}
}