{
  "type": "Feature",
  "properties": {
    "addr:full":"2122 21st Ave S Nashville TN 37212",
    "addr:housenumber":"2122",
    "addr:postcode":"37212",
    "addr:street":"21St Ave S",
    "iso:country":"US",
    "sg:address":"2122 21st Ave S",
    "sg:city":"Nashville",
    "sg:classifiers":[
        {
            "category":"Real Estate",
            "subcategory":"Real Estate Agent",
            "type":"Services"
        }
    ],
    "sg:phone":"+1 615 297 3574",
    "sg:postcode":"37212",
    "sg:province":"TN",
    "sg:website":"www.harpeth.com",
    "wof:name":"Harpeth Co Realtors",
    "wof:placetype":"venue"
},
  "geometry": {"coordinates":[-86.801863,36.130491],"type":"Point"}
}