{
  "type": "Feature",
  "properties": {
    "iso:country":"US",
    "sg:address":"572 Bent Tree Dr",
    "sg:city":"Crossville",
    "sg:classifiers":[
        {
            "category":"Wholesale",
            "subcategory":"Medical Equipment & Supplies",
            "type":"Manufacturing & Wholesale Goods"
        }
    ],
    "sg:phone":"+1 931 788 1646",
    "sg:postcode":"38555",
    "sg:province":"TN",
    "sg:tags":[
        "x",
        "apparatus"
    ],
    "wof:name":"Sells X-Ray Co",
    "wof:placetype":"venue"
},
  "geometry": {"coordinates":[-85.070088,35.913329],"type":"Point"}
}