{
  "type": "Feature",
  "properties": {
    "iso:country":"US",
    "sg:address":"2400 Nolensville Pike",
    "sg:city":"Nashville",
    "sg:classifiers":[
        {
            "category":"Autos & Motor Vehicles",
            "subcategory":"Automobile Sales",
            "type":"Retail Goods"
        }
    ],
    "sg:phone":"+1 615 832 8842",
    "sg:postcode":"37211",
    "sg:province":"TN",
    "sg:tags":[
        "car",
        "used",
        "dealer"
    ],
    "wof:name":"Swaney Signature Cars Inc",
    "wof:placetype":"venue"
},
  "geometry": {"coordinates":[-86.749262,36.119112],"type":"Point"}
}