{
  "type": "Feature",
  "properties": {
    "iso:country":"US",
    "sg:address":"1997 US Hwy 45W Byp",
    "sg:city":"Trenton",
    "sg:classifiers":[
        {
            "category":"Home & Garden",
            "subcategory":"Carpets & Floor Coverings",
            "type":"Retail Goods"
        }
    ],
    "sg:phone":"+1 731 855 9041",
    "sg:postcode":"38382",
    "sg:province":"TN",
    "wof:name":"Sewell Carpet",
    "wof:placetype":"venue"
},
  "geometry": {"coordinates":[-88.92982499999999,35.970214],"type":"Point"}
}