{
  "type": "Feature",
  "properties": {
    "iso:country":"US",
    "sg:address":"939 4th Ave S",
    "sg:city":"Nashville",
    "sg:classifiers":[
        {
            "category":"Retail",
            "subcategory":"Repair Shop",
            "type":"Services"
        }
    ],
    "sg:phone":"+1 615 726 5282",
    "sg:postcode":"37210",
    "sg:province":"TN",
    "wof:name":"Quality Welding Equipment Svc",
    "wof:placetype":"venue"
},
  "geometry": {"coordinates":[-86.770596,36.150709],"type":"Point"}
}