{
  "type": "Feature",
  "properties": {
    "addr:full":"9125 Cross Park Dr NW Knoxville TN 37923",
    "addr:housenumber":"9125",
    "addr:postcode":"37923",
    "addr:street":"Cross Park Dr Nw",
    "iso:country":"US",
    "sg:address":"9125 Cross Park Dr NW",
    "sg:city":"Knoxville",
    "sg:classifiers":[
        {
            "category":"Professional",
            "subcategory":"Accounting & Tax Preparation",
            "type":"Services"
        }
    ],
    "sg:phone":"+1 865 694 4008",
    "sg:postcode":"37923",
    "sg:province":"TN",
    "wof:name":"Lattimore Black Morgan Cain PC",
    "wof:placetype":"venue"
},
  "geometry": {"coordinates":[-84.090605,35.921245],"type":"Point"}
}