{
  "type": "Feature",
  "properties": {
    "iso:country":"US",
    "sg:address":"225 Becklea Dr",
    "sg:city":"Madison",
    "sg:classifiers":[
        {
            "category":"Retail",
            "subcategory":"Auto Repair",
            "type":"Services"
        }
    ],
    "sg:phone":"+1 615 868 2314",
    "sg:postcode":"37115",
    "sg:province":"TN",
    "sg:tags":[
        "wrecker"
    ],
    "wof:name":"Jenkins Towing & Hauling",
    "wof:placetype":"venue"
},
  "geometry": {"coordinates":[-86.69995400000001,36.269231],"type":"Point"}
}