{
  "type": "Feature",
  "properties": {
    "iso:country":"US",
    "sg:address":"385 2nd Ave",
    "sg:city":"Dayton",
    "sg:classifiers":[
        {
            "category":"Professional",
            "type":"Services"
        }
    ],
    "sg:phone":"+1 423 570 0042",
    "sg:postcode":"37321",
    "sg:province":"TN",
    "wof:name":"Southern Supervision Svc",
    "wof:placetype":"venue"
},
  "geometry": {"coordinates":[-85.013242,35.494618],"type":"Point"}
}