{
  "type": "Feature",
  "properties": {
    "iso:country":"US",
    "sg:address":"160 Claude Simmons Rd",
    "sg:city":"Johnson City",
    "sg:classifiers":[
        {
            "category":"Professional",
            "type":"Services"
        }
    ],
    "sg:phone":"+1 423 753 3934",
    "sg:postcode":"37604",
    "sg:province":"TN",
    "wof:name":"B & B Williams Family LP",
    "wof:placetype":"venue"
},
  "geometry": {"coordinates":[-82.434093,36.315875],"type":"Point"}
}