{
  "type": "Feature",
  "properties": {
    "addr:full":"2850 Little Chuckey Rd Mosheim TN 37818",
    "addr:housenumber":"2850",
    "addr:postcode":"37818",
    "addr:street":"Little Chuckey Rd",
    "iso:country":"US",
    "sg:address":"2850 Little Chuckey Rd",
    "sg:city":"Mosheim",
    "sg:classifiers":[
        {
            "category":"Shopping",
            "subcategory":"Gifts & Souvenirs",
            "type":"Retail Goods"
        }
    ],
    "sg:phone":"+1 423 422 9522",
    "sg:postcode":"37818",
    "sg:province":"TN",
    "wof:name":"Amy Jones",
    "wof:placetype":"venue"
},
  "geometry": {"coordinates":[-82.989762,36.141962],"type":"Point"}
}