{
  "type": "Feature",
  "properties": {
    "iso:country":"US",
    "sg:address":"1838 Big Chiefs Skyview Dr",
    "sg:city":"Sevierville",
    "sg:classifiers":[
        {
            "category":"Shopping",
            "subcategory":"Used Merchandise",
            "type":"Retail Goods"
        }
    ],
    "sg:phone":"+1 865 428 0536",
    "sg:postcode":"37876",
    "sg:province":"TN",
    "wof:name":"Memory Lane Antique Mall Inc",
    "wof:placetype":"venue"
},
  "geometry": {"coordinates":[-83.685199,35.933172],"type":"Point"}
}