{
  "type": "Feature",
  "properties": {
    "iso:country":"US",
    "sg:address":"7039 Maynardville Pike",
    "sg:city":"Knoxville",
    "sg:classifiers":[
        {
            "category":"Professional",
            "subcategory":"Business Services",
            "type":"Services"
        },
        {
            "category":"Building & Trades",
            "subcategory":"Plumbing",
            "type":"Services"
        }
    ],
    "sg:phone":"+1 865 922 5754",
    "sg:postcode":"37918",
    "sg:province":"TN",
    "sg:tags":[
        "repair",
        "balancing",
        "air"
    ],
    "wof:name":"United Testing & Balancing Inc",
    "wof:placetype":"venue"
},
  "geometry": {"coordinates":[-83.927832,36.076135],"type":"Point"}
}