{
  "type": "Feature",
  "properties": {
    "addr:full":"1334 Shagbark Trl Murfreesboro TN 37130",
    "addr:housenumber":"1334",
    "addr:postcode":"37130",
    "addr:street":"Shagbark Trl",
    "iso:country":"US",
    "sg:address":"1334 Shagbark Trl",
    "sg:city":"Murfreesboro",
    "sg:classifiers":[
        {
            "category":"Shopping",
            "type":"Retail Goods"
        }
    ],
    "sg:phone":"+1 615 890 2150",
    "sg:postcode":"37130",
    "sg:province":"TN",
    "sg:tags":[
        "merchandise"
    ],
    "wof:name":"Picture Perfect",
    "wof:placetype":"venue"
},
  "geometry": {"coordinates":[-86.364081,35.879782],"type":"Point"}
}