{
  "type": "Feature",
  "properties": {
    "addr:full":"1124 N Gateway Ave Rockwood TN 37854",
    "addr:housenumber":"1124",
    "addr:postcode":"37854",
    "addr:street":"N Gateway Ave",
    "iso:country":"US",
    "sg:address":"1124 N Gateway Ave",
    "sg:city":"Rockwood",
    "sg:classifiers":[
        {
            "category":"Sports & Exercise",
            "subcategory":"Gym",
            "type":"Entertainment"
        }
    ],
    "sg:phone":"+1 865 354 4644",
    "sg:postcode":"37854",
    "sg:province":"TN",
    "sg:tags":[
        "club",
        "health",
        "studio",
        "gymnasium"
    ],
    "wof:name":"Curves",
    "wof:placetype":"venue"
},
  "geometry": {"coordinates":[-84.66839,35.878814],"type":"Point"}
}