{
  "type": "Feature",
  "properties": {
    "iso:country":"US",
    "sg:address":"8390 US-51 N",
    "sg:city":"Millington",
    "sg:classifiers":[
        {
            "category":"Deli",
            "type":"Food & Drink"
        }
    ],
    "sg:menulink":"http://www.allmenus.com/tn/millington/93114-mcalisters-deli/menu/",
    "sg:phone":"+1 901 872 1983",
    "sg:postcode":"38053",
    "sg:province":"TN",
    "sg:tags":[
        "wrap",
        "american",
        "sandwich"
    ],
    "wof:name":"Mcalister's Deli",
    "wof:placetype":"venue"
},
  "geometry": {"coordinates":[-89.895821,35.355519],"type":"Point"}
}