{
  "type": "Feature",
  "properties": {
    "iso:country":"US",
    "sg:address":"690 Old Chattanooga Pike SW",
    "sg:city":"Cleveland",
    "sg:classifiers":[
        {
            "category":"Social Services",
            "subcategory":"Child Care",
            "type":"Services"
        }
    ],
    "sg:phone":"+1 423 614 0199",
    "sg:postcode":"37311",
    "sg:province":"TN",
    "wof:name":"Signal CENTERS/Ucp",
    "wof:placetype":"venue"
},
  "geometry": {"coordinates":[-84.89581200000001,35.133358],"type":"Point"}
}