{
  "type": "Feature",
  "properties": {
    "iso:country":"US",
    "sg:address":"710 S Jefferson Ave",
    "sg:city":"Cookeville",
    "sg:classifiers":[
        {
            "category":"Real Estate",
            "subcategory":"Real Estate Agent",
            "type":"Services"
        }
    ],
    "sg:phone":"+1 931 979 2171",
    "sg:postcode":"38501",
    "sg:province":"TN",
    "wof:name":"American Way",
    "wof:placetype":"venue"
},
  "geometry": {"coordinates":[-85.500803,36.146016],"type":"Point"}
}