{
  "type": "Feature",
  "properties": {
    "addr:full":"7501 Francis Ferry Rd Rock Island TN 38581",
    "addr:housenumber":"7501",
    "addr:postcode":"38581",
    "addr:street":"Francis Ferry Rd",
    "iso:country":"US",
    "sg:address":"7501 Francis Ferry Rd",
    "sg:city":"Rock Island",
    "sg:classifiers":[
        {
            "category":"Manufacturing",
            "subcategory":"Tools & Machinery",
            "type":"Manufacturing & Wholesale Goods"
        }
    ],
    "sg:phone":"+1 931 686 9300",
    "sg:postcode":"38581",
    "sg:province":"TN",
    "sg:tags":[
        "die",
        "maker"
    ],
    "wof:name":"Boles Tool Inc",
    "wof:placetype":"venue"
},
  "geometry": {"coordinates":[-85.70288499999999,35.799128],"type":"Point"}
}