{
  "type": "Feature",
  "properties": {
    "iso:country":"US",
    "sg:address":"3285 Kings Arms St",
    "sg:city":"Memphis",
    "sg:classifiers":[
        {
            "category":"Professional",
            "subcategory":"Management & Consulting",
            "type":"Services"
        }
    ],
    "sg:phone":"+1 901 547 1312",
    "sg:postcode":"38115",
    "sg:province":"TN",
    "wof:name":"Joy Jones Realty Wanda J Gordo",
    "wof:placetype":"venue"
},
  "geometry": {"coordinates":[-89.87724799999999,35.06053],"type":"Point"}
}