{
  "type": "Feature",
  "properties": {
    "iso:country":"US",
    "sg:address":"215 W Commerce St",
    "sg:city":"Lewisburg",
    "sg:classifiers":[
        {
            "category":"Shopping",
            "subcategory":"Computers & Home Electronics",
            "type":"Retail Goods"
        }
    ],
    "sg:phone":"+1 931 270 7557",
    "sg:postcode":"37091",
    "sg:province":"TN",
    "wof:name":"Computer Tutor Plus",
    "wof:placetype":"venue"
},
  "geometry": {"coordinates":[-86.78917,35.449045],"type":"Point"}
}