{
  "type": "Feature",
  "properties": {
    "addr:full":"2201 Murfreesboro Pike B203 Nashville TN 37217",
    "addr:housenumber":"2201",
    "addr:postcode":"37217",
    "addr:street":"Murfreesboro Pike",
    "iso:country":"US",
    "sg:address":"2201 Murfreesboro Pike B203",
    "sg:city":"Nashville",
    "sg:classifiers":[
        {
            "category":"Professional",
            "subcategory":"Detective & Security Services",
            "type":"Services"
        }
    ],
    "sg:phone":"+1 615 346 9390",
    "sg:postcode":"37217",
    "sg:province":"TN",
    "sg:tags":[
        "car",
        "armored",
        "private",
        "investigator"
    ],
    "wof:name":"Broadsword Security Group",
    "wof:placetype":"venue"
},
  "geometry": {"coordinates":[-86.651093,36.09095],"type":"Point"}
}