{
  "type": "Feature",
  "properties": {
    "addr:full":"2611 S Mendenhall Rd Memphis TN 38115",
    "addr:housenumber":"2611",
    "addr:postcode":"38115",
    "addr:street":"S Mendenhall Rd",
    "iso:country":"US",
    "sg:address":"2611 S Mendenhall Rd",
    "sg:city":"Memphis",
    "sg:classifiers":[
        {
            "category":"Shopping",
            "subcategory":"Hobbies, Toys, & Games",
            "type":"Retail Goods"
        },
        {
            "category":"Recreation",
            "subcategory":"Gun Range",
            "type":"Entertainment"
        }
    ],
    "sg:phone":"+1 901 370 5600",
    "sg:postcode":"38115",
    "sg:province":"TN",
    "sg:tags":[
        "safety",
        "instruction",
        "marksmanship",
        "gunsmith"
    ],
    "sg:website":"http://www.rangemaster.com",
    "wof:name":"RangeMaster",
    "wof:placetype":"venue"
},
  "geometry": {"coordinates":[-89.884867,35.077957],"type":"Point"}
}