{
  "type": "Feature",
  "properties": {
    "iso:country":"US",
    "sg:address":"202 Forrest Lawn Dr",
    "sg:city":"Mount Juliet",
    "sg:classifiers":[
        {
            "category":"Real Estate",
            "subcategory":"Real Estate Agent",
            "type":"Services"
        }
    ],
    "sg:phone":"+1 615 754 2352",
    "sg:postcode":"37122",
    "sg:province":"TN",
    "wof:name":"Latham Appraisal Service",
    "wof:placetype":"venue"
},
  "geometry": {"coordinates":[-86.544842,36.21734],"type":"Point"}
}