{
  "type": "Feature",
  "properties": {
    "addr:full":"1029 John A Denie Rd Memphis TN 38134",
    "addr:housenumber":"1029",
    "addr:postcode":"38134",
    "addr:street":"John;Denie Rd",
    "iso:country":"US",
    "sg:address":"1029 John A Denie Rd",
    "sg:city":"Memphis",
    "sg:classifiers":[
        {
            "category":"Manufacturing",
            "subcategory":"Glass & Minerals",
            "type":"Manufacturing & Wholesale Goods"
        }
    ],
    "sg:phone":"+1 901 386 4499",
    "sg:postcode":"38134",
    "sg:province":"TN",
    "sg:tags":[
        "ready"
    ],
    "wof:name":"Memphis Ready Mix",
    "wof:placetype":"venue"
},
  "geometry": {"coordinates":[-89.864784,35.154099],"type":"Point"}
}