{
  "type": "Feature",
  "properties": {
    "iso:country":"US",
    "sg:address":"1640 Broadway St",
    "sg:city":"Dayton",
    "sg:classifiers":[
        {
            "category":"Manufacturing",
            "subcategory":"Retail Goods",
            "type":"Manufacturing & Wholesale Goods"
        }
    ],
    "sg:phone":"+1 423 775 1823",
    "sg:postcode":"37321",
    "sg:province":"TN",
    "sg:tags":[
        "manufacturer"
    ],
    "wof:name":"Robinson Manufacturing Wrhse",
    "wof:placetype":"venue"
},
  "geometry": {"coordinates":[-85.00145000000001,35.518816],"type":"Point"}
}