{
  "type": "Feature",
  "properties": {
    "iso:country":"US",
    "sg:address":"821 Loop Rd",
    "sg:city":"Knoxville",
    "sg:classifiers":[
        {
            "category":"Professional",
            "subcategory":"Lawyer & Legal Services",
            "type":"Services"
        }
    ],
    "sg:phone":"+1 865 966 2621",
    "sg:postcode":"37934",
    "sg:province":"TN",
    "wof:name":"Jeter Crolyn F Attorney At Law",
    "wof:placetype":"venue"
},
  "geometry": {"coordinates":[-84.141806,35.868659],"type":"Point"}
}