{
  "type": "Feature",
  "properties": {
    "addr:full":"559 E Main St Hendersonville TN 37075",
    "addr:housenumber":"559",
    "addr:postcode":"37075",
    "addr:street":"E Main St",
    "iso:country":"US",
    "sg:address":"559 E Main St",
    "sg:city":"Hendersonville",
    "sg:classifiers":[
        {
            "category":"Restaurant",
            "type":"Food & Drink"
        }
    ],
    "sg:menulink":"http://www.allmenus.com/tn/hendersonville/191676-sonic/menu/",
    "sg:phone":"+1 615 826 2135",
    "sg:postcode":"37075",
    "sg:province":"TN",
    "sg:tags":[
        "burger",
        "american"
    ],
    "wof:name":"Sonic",
    "wof:placetype":"venue"
},
  "geometry": {"coordinates":[-86.57445800000001,36.320945],"type":"Point"}
}