{
  "type": "Feature",
  "properties": {
    "iso:country":"US",
    "sg:address":"1304 E Grundy St",
    "sg:city":"Tullahoma",
    "sg:classifiers":[
        {
            "category":"Organizations",
            "subcategory":"Professional Association",
            "type":"Services"
        }
    ],
    "sg:phone":"+1 931 455 9704",
    "sg:postcode":"37388",
    "sg:province":"TN",
    "wof:name":"Tullahoma Fastpitch Assn",
    "wof:placetype":"venue"
},
  "geometry": {"coordinates":[-86.19471,35.372828],"type":"Point"}
}