{
  "type": "Feature",
  "properties": {
    "iso:country":"US",
    "sg:address":"3135 Harrison Pike",
    "sg:city":"Cleveland",
    "sg:classifiers":[
        {
            "category":"Building & Trades",
            "subcategory":"Electrical",
            "type":"Services"
        }
    ],
    "sg:phone":"+1 423 933 2174",
    "sg:postcode":"37311",
    "sg:province":"TN",
    "sg:tags":[
        "industrial",
        "electrician",
        "contractors-commercial",
        "electric"
    ],
    "wof:name":"Light'N Electric",
    "wof:placetype":"venue"
},
  "geometry": {"coordinates":[-84.93426700000001,35.185391],"type":"Point"}
}