{
  "type": "Feature",
  "properties": {
    "iso:country":"US",
    "sg:address":"8126 Timberstone Ln",
    "sg:city":"Powell",
    "sg:classifiers":[
        {
            "category":"Building & Trades",
            "subcategory":"Construction",
            "type":"Services"
        }
    ],
    "sg:phone":"+1 865 947 2234",
    "sg:postcode":"37849",
    "sg:province":"TN",
    "sg:tags":[
        "dock"
    ],
    "wof:name":"Lifetime Docks",
    "wof:placetype":"venue"
},
  "geometry": {"coordinates":[-84.0223,36.051144],"type":"Point"}
}