{
  "type": "Feature",
  "properties": {
    "iso:country":"US",
    "sg:address":"521 Mount Ida Pl",
    "sg:city":"Kingsport",
    "sg:classifiers":[
        {
            "category":"Building & Trades",
            "subcategory":"Plumbing",
            "type":"Services"
        }
    ],
    "sg:phone":"+1 423 378 4830",
    "sg:postcode":"37660",
    "sg:province":"TN",
    "sg:tags":[
        "contractor"
    ],
    "wof:name":"Cut Rate Plumbing",
    "wof:placetype":"venue"
},
  "geometry": {"coordinates":[-82.568944,36.556314],"type":"Point"}
}