{
  "type": "Feature",
  "properties": {
    "iso:country":"US",
    "sg:address":"2120 Utopia Ave",
    "sg:city":"Nashville",
    "sg:classifiers":[
        {
            "category":"Retail",
            "subcategory":"Auto Repair",
            "type":"Services"
        }
    ],
    "sg:phone":"+1 615 331 7155",
    "sg:postcode":"37211",
    "sg:province":"TN",
    "sg:tags":[
        "wrecker"
    ],
    "wof:name":"Chief Towing",
    "wof:placetype":"venue"
},
  "geometry": {"coordinates":[-86.756429,36.126875],"type":"Point"}
}