{
  "type": "Feature",
  "properties": {
    "addr:full":"4315 Harding Pike Nashville TN 37205",
    "addr:housenumber":"4315",
    "addr:postcode":"37205",
    "addr:street":"Harding Pike",
    "iso:country":"US",
    "sg:address":"4315 Harding Pike",
    "sg:city":"Nashville",
    "sg:classifiers":[
        {
            "category":"Banks & Credit Unions",
            "subcategory":"Bank",
            "type":"Services"
        }
    ],
    "sg:phone":"+1 615 748 2287",
    "sg:postcode":"37205",
    "sg:province":"TN",
    "wof:name":"AM South Bank",
    "wof:placetype":"venue"
},
  "geometry": {"coordinates":[-86.844741,36.127096],"type":"Point"}
}