{
  "type": "Feature",
  "properties": {
    "addr:full":"2329 Memorial Blvd Murfreesboro TN 37129",
    "addr:housenumber":"2329",
    "addr:postcode":"37129",
    "addr:street":"Memorial Blvd",
    "iso:country":"US",
    "sg:address":"2329 Memorial Blvd",
    "sg:city":"Murfreesboro",
    "sg:classifiers":[
        {
            "category":"Shopping",
            "subcategory":"Gifts & Souvenirs",
            "type":"Retail Goods"
        }
    ],
    "sg:phone":"+1 615 217 6025",
    "sg:postcode":"37129",
    "sg:province":"TN",
    "sg:tags":[
        "cards",
        "greeting"
    ],
    "wof:name":"Lisa's Hallmark Shop",
    "wof:placetype":"venue"
},
  "geometry": {"coordinates":[-86.39540599999999,35.854811],"type":"Point"}
}