{
  "type": "Feature",
  "properties": {
    "iso:country":"US",
    "sg:address":"1981 Cordes Rd",
    "sg:city":"Germantown",
    "sg:classifiers":[
        {
            "category":"Building & Trades",
            "subcategory":"Construction",
            "type":"Services"
        }
    ],
    "sg:phone":"+1 901 754 7164",
    "sg:postcode":"38139",
    "sg:province":"TN",
    "sg:tags":[
        "house"
    ],
    "wof:name":"Greg Bainer Construction",
    "wof:placetype":"venue"
},
  "geometry": {"coordinates":[-89.77678400000001,35.09509],"type":"Point"}
}