{
  "type": "Feature",
  "properties": {
    "addr:full":"6700 Ringgold Rd Chattanooga TN 37412",
    "addr:housenumber":"6700",
    "addr:postcode":"37412",
    "addr:street":"Ringgold Rd",
    "iso:country":"US",
    "sg:address":"6700 Ringgold Rd",
    "sg:city":"Chattanooga",
    "sg:classifiers":[
        {
            "category":"Railroad",
            "type":"Transportation"
        }
    ],
    "sg:phone":"+1 423 894 7297",
    "sg:postcode":"37412",
    "sg:province":"TN",
    "wof:name":"Norfolk Southern",
    "wof:placetype":"venue"
},
  "geometry": {"coordinates":[-85.203458,34.990071],"type":"Point"}
}