{
  "type": "Feature",
  "properties": {
    "iso:country":"US",
    "sg:address":"7218 River Run Dr",
    "sg:city":"Chattanooga",
    "sg:classifiers":[
        {
            "category":"Building & Trades",
            "subcategory":"Construction",
            "type":"Services"
        }
    ],
    "sg:phone":"+1 423 344 6869",
    "sg:postcode":"37416",
    "sg:province":"TN",
    "sg:tags":[
        "company"
    ],
    "wof:name":"N & N Construction Inc",
    "wof:placetype":"venue"
},
  "geometry": {"coordinates":[-85.15194200000001,35.145079],"type":"Point"}
}