{
  "type": "Feature",
  "properties": {
    "iso:country":"US",
    "sg:address":"275 Cumberland Cir",
    "sg:city":"Nashville",
    "sg:classifiers":[
        {
            "category":"Health Services",
            "subcategory":"Hospital",
            "type":"Services"
        },
        {
            "category":"Health Services",
            "subcategory":"Clinic",
            "type":"Services"
        }
    ],
    "sg:phone":"+1 615 726 3340",
    "sg:postcode":"37214",
    "sg:province":"TN",
    "sg:tags":[
        "medical",
        "mental"
    ],
    "sg:website":"www.mhc-tn.org",
    "wof:name":"Mental Health Cooperative Inc",
    "wof:placetype":"venue"
},
  "geometry": {"coordinates":[-86.667911,36.162408],"type":"Point"}
}