{
  "type": "Feature",
  "properties": {
    "addr:full":"121 N Spring St Mc Minnville TN 37110",
    "addr:housenumber":"121",
    "addr:postcode":"37110",
    "addr:street":"N Spring St",
    "iso:country":"US",
    "sg:address":"121 N Spring St",
    "sg:city":"Mc Minnville",
    "sg:classifiers":[
        {
            "category":"Shopping",
            "subcategory":"Computers & Home Electronics",
            "type":"Retail Goods"
        }
    ],
    "sg:phone":"+1 931 473 1039",
    "sg:postcode":"37110",
    "sg:province":"TN",
    "sg:tags":[
        "equipment",
        "dealer"
    ],
    "wof:name":"Computers Plus",
    "wof:placetype":"venue"
},
  "geometry": {"coordinates":[-85.771618,35.681792],"type":"Point"}
}