{
  "type": "Feature",
  "properties": {
    "iso:country":"US",
    "sg:address":"680 Winfield Dunn Pkwy",
    "sg:city":"Sevierville",
    "sg:classifiers":[
        {
            "category":"Travel",
            "subcategory":"Hotels & Motels",
            "type":"Entertainment"
        }
    ],
    "sg:phone":"+1 865 429 7797",
    "sg:postcode":"37876",
    "sg:province":"TN",
    "wof:name":"Country Hearth Inn",
    "wof:placetype":"venue"
},
  "geometry": {"coordinates":[-83.572744,35.883867],"type":"Point"}
}