{
  "type": "Feature",
  "properties": {
    "addr:full":"4730 Spottswood Ave Memphis TN 38117",
    "addr:postcode":"4730;38117",
    "addr:street":"Spottswood Ave",
    "iso:country":"US",
    "sg:address":"4730 Spottswood Ave",
    "sg:city":"Memphis",
    "sg:classifiers":[
        {
            "category":"Shopping",
            "type":"Retail Goods"
        }
    ],
    "sg:phone":"+1 901 683 5314",
    "sg:postcode":"38117",
    "sg:province":"TN",
    "sg:tags":[
        "cosmetic",
        "perfume"
    ],
    "sg:website":"www.merlenorman.com",
    "wof:name":"Merle Norman Cosmetics",
    "wof:placetype":"venue"
},
  "geometry": {"coordinates":[-89.904212,35.112087],"type":"Point"}
}