{
  "type": "Feature",
  "properties": {
    "addr:full":"6393 Poplar Ave Memphis TN 38119",
    "addr:housenumber":"6393",
    "addr:postcode":"38119",
    "addr:street":"Poplar Ave",
    "iso:country":"US",
    "sg:address":"6393 Poplar Ave",
    "sg:city":"Memphis",
    "sg:classifiers":[
        {
            "category":"Building & Trades",
            "subcategory":"Construction",
            "type":"Services"
        }
    ],
    "sg:phone":"+1 901 818 2415",
    "sg:postcode":"38119",
    "sg:province":"TN",
    "sg:tags":[
        "home",
        "builder"
    ],
    "wof:name":"Homes For Sale Magazine",
    "wof:placetype":"venue"
},
  "geometry": {"coordinates":[-89.848679,35.099836],"type":"Point"}
}