{
  "type": "Feature",
  "properties": {
    "addr:full":"830 Crescent Centre Dr Franklin TN 37067",
    "addr:housenumber":"830",
    "addr:postcode":"37067",
    "addr:street":"Crescent Centre Dr",
    "iso:country":"US",
    "sg:address":"830 Crescent Centre Dr",
    "sg:city":"Franklin",
    "sg:classifiers":[
        {
            "category":"Autos & Motor Vehicles",
            "subcategory":"Fuel & Gas Station",
            "type":"Retail Goods"
        }
    ],
    "sg:phone":"+1 615 771 6701",
    "sg:postcode":"37067",
    "sg:province":"TN",
    "sg:tags":[
        "oil"
    ],
    "sg:website":"www.delekus.com",
    "wof:name":"Delek US Holdings Inc",
    "wof:placetype":"venue"
},
  "geometry": {"coordinates":[-86.810503,35.943471],"type":"Point"}
}