{
  "type": "Feature",
  "properties": {
    "addr:full":"3537 Bethlehem Rd Union City TN 38261",
    "addr:housenumber":"3537",
    "addr:postcode":"38261",
    "addr:street":"Bethlehem Rd",
    "iso:country":"US",
    "sg:address":"3537 Bethlehem Rd",
    "sg:city":"Union City",
    "sg:classifiers":[
        {
            "category":"Farming",
            "subcategory":"Livestock Farm",
            "type":"Manufacturing & Wholesale Goods"
        }
    ],
    "sg:phone":"+1 731 885 7789",
    "sg:postcode":"38261",
    "sg:province":"TN",
    "sg:tags":[
        "equine"
    ],
    "wof:name":"Faulkner Farms",
    "wof:placetype":"venue"
},
  "geometry": {"coordinates":[-89.02482500000001,36.44383],"type":"Point"}
}