{
  "type": "Feature",
  "properties": {
    "iso:country":"US",
    "sg:address":"1293 Pee Dee Branch Rd",
    "sg:city":"Cottontown",
    "sg:classifiers":[
        {
            "category":"Building & Trades",
            "subcategory":"Construction",
            "type":"Services"
        }
    ],
    "sg:phone":"+1 615 672 2365",
    "sg:postcode":"37048",
    "sg:province":"TN",
    "sg:tags":[
        "excavation",
        "contractor"
    ],
    "wof:name":"Lempicki Excavating",
    "wof:placetype":"venue"
},
  "geometry": {"coordinates":[-86.603601,36.469733],"type":"Point"}
}