{
  "type": "Feature",
  "properties": {
    "addr:full":"429 Shelbyville Rd Knoxville TN 37922",
    "addr:housenumber":"429",
    "addr:postcode":"37922",
    "addr:street":"Shelbyville Rd",
    "iso:country":"US",
    "sg:address":"429 Shelbyville Rd",
    "sg:city":"Knoxville",
    "sg:classifiers":[
        {
            "category":"Banks & Credit Unions",
            "subcategory":"Investment Brokerage",
            "type":"Services"
        }
    ],
    "sg:phone":"+1 865 691 1119",
    "sg:postcode":"37922",
    "sg:province":"TN",
    "sg:tags":[
        "advisory",
        "financial"
    ],
    "wof:name":"LRM Partners",
    "wof:placetype":"venue"
},
  "geometry": {"coordinates":[-84.09511000000001,35.89576],"type":"Point"}
}