{
  "type": "Feature",
  "properties": {
    "iso:country":"US",
    "sg:address":"271 Blue Springs Rd",
    "sg:city":"Elizabethton",
    "sg:classifiers":[
        {
            "category":"Wholesale",
            "subcategory":"Hardware",
            "type":"Manufacturing & Wholesale Goods"
        }
    ],
    "sg:phone":"+1 423 474 2787",
    "sg:postcode":"37643",
    "sg:province":"TN",
    "wof:name":"Clean Air Consultants",
    "wof:placetype":"venue"
},
  "geometry": {"coordinates":[-82.14976,36.362236],"type":"Point"}
}