{
  "type": "Feature",
  "properties": {
    "iso:country":"US",
    "sg:address":"129 Luyben Hills Rd",
    "sg:city":"Kingston Springs",
    "sg:classifiers":[
        {
            "category":"Autos & Motor Vehicles",
            "subcategory":"Fuel & Gas Station",
            "type":"Retail Goods"
        }
    ],
    "sg:phone":"+1 615 952 2111",
    "sg:postcode":"37082",
    "sg:province":"TN",
    "sg:tags":[
        "station",
        "gasoline"
    ],
    "wof:name":"Sun and Service",
    "wof:placetype":"venue"
},
  "geometry": {"coordinates":[-87.09857700000001,36.083912],"type":"Point"}
}