{
  "type": "Feature",
  "properties": {
    "iso:country":"US",
    "sg:address":"1200 Water Plant Rd",
    "sg:city":"Ashland City",
    "sg:classifiers":[
        {
            "category":"Building & Trades",
            "subcategory":"Construction",
            "type":"Services"
        }
    ],
    "sg:phone":"+1 615 792 7196",
    "sg:postcode":"37015",
    "sg:province":"TN",
    "sg:tags":[
        "general",
        "contractor"
    ],
    "wof:name":"Terra Construction Co",
    "wof:placetype":"venue"
},
  "geometry": {"coordinates":[-87.049645,36.325535],"type":"Point"}
}