{
  "type": "Feature",
  "properties": {
    "iso:country":"US",
    "sg:address":"1595 Quarry Rd",
    "sg:city":"Mount Juliet",
    "sg:classifiers":[
        {
            "category":"Building & Trades",
            "subcategory":"Landscaping Services",
            "type":"Services"
        }
    ],
    "sg:phone":"+1 615 758 9008",
    "sg:postcode":"37122",
    "sg:province":"TN",
    "sg:tags":[
        "landscape"
    ],
    "wof:name":"Living Color",
    "wof:placetype":"venue"
},
  "geometry": {"coordinates":[-86.438682,36.209611],"type":"Point"}
}