{
  "type": "Feature",
  "properties": {
    "iso:country":"US",
    "sg:address":"2011 Church St",
    "sg:city":"Nashville",
    "sg:classifiers":[
        {
            "category":"Health Services",
            "subcategory":"Doctor",
            "type":"Services"
        }
    ],
    "sg:phone":"+1 615 284 7785",
    "sg:postcode":"37219",
    "sg:province":"TN",
    "sg:tags":[
        "physician",
        "surgeon"
    ],
    "wof:name":"Radiology Alliance",
    "wof:placetype":"venue"
},
  "geometry": {"coordinates":[-86.80249499999999,36.152489],"type":"Point"}
}