{
  "type": "Feature",
  "properties": {
    "addr:full":"7859 Farmington Blvd Germantown TN 38138",
    "addr:housenumber":"7859",
    "addr:postcode":"38138",
    "addr:street":"Farmington Blvd",
    "iso:country":"US",
    "sg:address":"7859 Farmington Blvd",
    "sg:city":"Germantown",
    "sg:classifiers":[
        {
            "category":"Shopping",
            "subcategory":"Clothing, Apparel, & Fashions",
            "type":"Retail Goods"
        }
    ],
    "sg:phone":"+1 901 754 0018",
    "sg:postcode":"38138",
    "sg:province":"TN",
    "sg:tags":[
        "garment"
    ],
    "wof:name":"Seriously Fun Apparel",
    "wof:placetype":"venue"
},
  "geometry": {"coordinates":[-89.802021,35.095496],"type":"Point"}
}