{
  "type": "Feature",
  "properties": {
    "iso:country":"US",
    "sg:address":"1458 Boyds Creek Hwy",
    "sg:city":"Seymour",
    "sg:classifiers":[
        {
            "category":"Personal",
            "type":"Services"
        }
    ],
    "sg:phone":"+1 865 556 4696",
    "sg:postcode":"37865",
    "sg:province":"TN",
    "sg:tags":[
        "therapist",
        "massage"
    ],
    "wof:name":"Nu Weigh LLC",
    "wof:placetype":"venue"
},
  "geometry": {"coordinates":[-83.714567,35.894784],"type":"Point"}
}