{
  "type": "Feature",
  "properties": {
    "addr:full":"215 Emory Heights Rd Harriman TN 37748",
    "addr:housenumber":"215",
    "addr:postcode":"37748",
    "addr:street":"Emory Heights Rd",
    "iso:country":"US",
    "sg:address":"215 Emory Heights Rd",
    "sg:city":"Harriman",
    "sg:classifiers":[
        {
            "category":"Manufacturing",
            "subcategory":"Jewelry",
            "type":"Manufacturing & Wholesale Goods"
        }
    ],
    "sg:phone":"+1 865 882 8973",
    "sg:postcode":"37748",
    "sg:province":"TN",
    "sg:tags":[
        "precious",
        "metal",
        "mfg"
    ],
    "wof:name":"Silver Treasures",
    "wof:placetype":"venue"
},
  "geometry": {"coordinates":[-84.534919,35.927781],"type":"Point"}
}