{
  "type": "Feature",
  "properties": {
    "iso:country":"US",
    "sg:address":"489 Russell Rd",
    "sg:city":"Jackson",
    "sg:classifiers":[
        {
            "category":"Professional",
            "type":"Services"
        }
    ],
    "sg:phone":"+1 731 660 3004",
    "sg:postcode":"38301",
    "sg:province":"TN",
    "wof:name":"African Mission",
    "wof:placetype":"venue"
},
  "geometry": {"coordinates":[-88.839055,35.641331],"type":"Point"}
}