{
  "type": "Feature",
  "properties": {
    "iso:country":"US",
    "sg:address":"8418 Orchard Hill Dr",
    "sg:city":"Germantown",
    "sg:classifiers":[
        {
            "category":"Banks & Credit Unions",
            "subcategory":"Investment Brokerage",
            "type":"Services"
        }
    ],
    "sg:phone":"+1 901 759 3767",
    "sg:postcode":"38138",
    "sg:province":"TN",
    "wof:name":"Hank Hill Investment Co Inc",
    "wof:placetype":"venue"
},
  "geometry": {"coordinates":[-89.782111,35.078858],"type":"Point"}
}