{
  "type": "Feature",
  "properties": {
    "iso:country":"US",
    "sg:address":"2000 Warfield Dr",
    "sg:city":"Nashville",
    "sg:classifiers":[
        {
            "category":"Real Estate",
            "subcategory":"Real Estate Agent",
            "type":"Services"
        }
    ],
    "sg:phone":"+1 615 385 3525",
    "sg:postcode":"37215",
    "sg:province":"TN",
    "sg:tags":[
        "manager"
    ],
    "wof:name":"Fulcher Realty Co",
    "wof:placetype":"venue"
},
  "geometry": {"coordinates":[-86.81522699999999,36.102731],"type":"Point"}
}