{
  "type": "Feature",
  "properties": {
    "iso:country":"US",
    "sg:address":"106 W Court Sq",
    "sg:city":"Waverly",
    "sg:classifiers":[
        {
            "category":"Cinema",
            "subcategory":"Movie Theater",
            "type":"Entertainment"
        }
    ],
    "sg:phone":"+1 931 296 4500",
    "sg:postcode":"37185",
    "sg:province":"TN",
    "wof:name":"Mi-De-Ga Theatre",
    "wof:placetype":"venue"
},
  "geometry": {"coordinates":[-87.794954,36.082689],"type":"Point"}
}