{
  "type": "Feature",
  "properties": {
    "iso:country":"US",
    "sg:address":"829 Myrtle St",
    "sg:city":"Kingsport",
    "sg:classifiers":[
        {
            "category":"Personal",
            "subcategory":"Beauty Salon",
            "type":"Services"
        }
    ],
    "sg:phone":"+1 423 791 3974",
    "sg:postcode":"37660",
    "sg:province":"TN",
    "sg:tags":[
        "treatment",
        "skin"
    ],
    "wof:name":"Sole",
    "wof:placetype":"venue"
},
  "geometry": {"coordinates":[-82.54869100000001,36.543265],"type":"Point"}
}