{
  "type": "Feature",
  "properties": {
    "iso:country":"US",
    "sg:address":"3890 Hixson Pike",
    "sg:city":"Chattanooga",
    "sg:classifiers":[
        {
            "category":"Banks & Credit Unions",
            "subcategory":"Investment Brokerage",
            "type":"Services"
        }
    ],
    "sg:phone":"+1 423 332 4773",
    "sg:postcode":"37415",
    "sg:province":"TN",
    "sg:tags":[
        "advisory",
        "financial"
    ],
    "wof:name":"Raymond James Financial Svc",
    "wof:placetype":"venue"
},
  "geometry": {"coordinates":[-85.266074,35.11233],"type":"Point"}
}