{
  "type": "Feature",
  "properties": {
    "iso:country":"US",
    "sg:address":"2490 E Andrew Johnson Hwy",
    "sg:city":"Greeneville",
    "sg:classifiers":[
        {
            "category":"Autos & Motor Vehicles",
            "subcategory":"Fuel & Gas Station",
            "type":"Retail Goods"
        },
        {
            "category":"Food & Beverages",
            "subcategory":"Groceries & Convenience Stores",
            "type":"Retail Goods"
        }
    ],
    "sg:phone":"+1 423 638 2726",
    "sg:postcode":"37745",
    "sg:province":"TN",
    "wof:name":"Roadrunner Markets Inc",
    "wof:placetype":"venue"
},
  "geometry": {"coordinates":[-82.779906,36.178702],"type":"Point"}
}