{
  "type": "Feature",
  "properties": {
    "iso:country":"US",
    "sg:address":"38 Steeplechase Dr",
    "sg:city":"Jackson",
    "sg:classifiers":[
        {
            "category":"Restaurant",
            "type":"Food & Drink"
        }
    ],
    "sg:phone":"+1 731 668 2452",
    "sg:postcode":"38305",
    "sg:province":"TN",
    "sg:tags":[
        "seasoning",
        "caterer"
    ],
    "wof:name":"Cajun Country Seasoning Co",
    "wof:placetype":"venue"
},
  "geometry": {"coordinates":[-88.849486,35.688296],"type":"Point"}
}