{
  "type": "Feature",
  "properties": {
    "iso:country":"US",
    "sg:address":"6672 Morgan County Hwy",
    "sg:city":"Lancing",
    "sg:classifiers":[
        {
            "category":"Wholesale",
            "subcategory":"Auto Parts",
            "type":"Manufacturing & Wholesale Goods"
        }
    ],
    "sg:phone":"+1 423 628 5431",
    "sg:postcode":"37770",
    "sg:province":"TN",
    "sg:tags":[
        "used"
    ],
    "wof:name":"Thunder Ridge Used Parts",
    "wof:placetype":"venue"
},
  "geometry": {"coordinates":[-84.660085,36.180153],"type":"Point"}
}