{
  "type": "Feature",
  "properties": {
    "iso:country":"US",
    "sg:address":"160 Kirby Dr",
    "sg:city":"Portland",
    "sg:classifiers":[
        {
            "category":"Manufacturing",
            "subcategory":"Metals",
            "type":"Manufacturing & Wholesale Goods"
        }
    ],
    "sg:phone":"+1 615 325 9224",
    "sg:postcode":"37148",
    "sg:province":"TN",
    "sg:tags":[
        "steel"
    ],
    "sg:website":"www.imperialgroup.com",
    "wof:name":"Imperial Fabricating Of TN",
    "wof:placetype":"venue"
},
  "geometry": {"coordinates":[-86.520831,36.603477],"type":"Point"}
}