{
  "type": "Feature",
  "properties": {
    "addr:full":"2886 S Rutherford Blvd Murfreesboro TN 37130",
    "addr:housenumber":"2886",
    "addr:postcode":"37130",
    "addr:street":"S Rutherford Blvd",
    "iso:country":"US",
    "sg:address":"2886 S Rutherford Blvd",
    "sg:city":"Murfreesboro",
    "sg:classifiers":[
        {
            "category":"Banks & Credit Unions",
            "subcategory":"Bank",
            "type":"Services"
        }
    ],
    "sg:phone":"+1 615 217 4311",
    "sg:postcode":"37130",
    "sg:province":"TN",
    "sg:tags":[
        "cashing",
        "check"
    ],
    "wof:name":"Check Advance",
    "wof:placetype":"venue"
},
  "geometry": {"coordinates":[-86.39538400000001,35.819073],"type":"Point"}
}