{
  "type": "Feature",
  "properties": {
    "addr:full":"66 E Mallory Ave Memphis TN 38109",
    "addr:housenumber":"66",
    "addr:postcode":"38109",
    "addr:street":"E Mallory Ave",
    "iso:country":"US",
    "sg:address":"66 E Mallory Ave",
    "sg:city":"Memphis",
    "sg:classifiers":[
        {
            "category":"Organizations",
            "subcategory":"Religious Organization",
            "type":"Services"
        }
    ],
    "sg:phone":"+1 901 948 1122",
    "sg:postcode":"38109",
    "sg:province":"TN",
    "sg:tags":[
        "church"
    ],
    "wof:name":"Faith Temple Church Of God",
    "wof:placetype":"venue"
},
  "geometry": {"coordinates":[-90.06300899999999,35.086639],"type":"Point"}
}