{
  "type": "Feature",
  "properties": {
    "iso:country":"US",
    "sg:address":"2704 Belmont Blvd",
    "sg:city":"Nashville",
    "sg:classifiers":[
        {
            "category":"Real Estate",
            "subcategory":"Architect",
            "type":"Services"
        }
    ],
    "sg:phone":"+1 615 385 1363",
    "sg:postcode":"37212",
    "sg:province":"TN",
    "wof:name":"David Kidd",
    "wof:placetype":"venue"
},
  "geometry": {"coordinates":[-86.794631,36.122432],"type":"Point"}
}