{
  "type": "Feature",
  "properties": {
    "iso:country":"US",
    "sg:address":"3606 Hamilton Church Rd",
    "sg:city":"Antioch",
    "sg:classifiers":[
        {
            "category":"Food & Beverages",
            "subcategory":"Groceries & Convenience Stores",
            "type":"Retail Goods"
        }
    ],
    "sg:phone":"+1 615 641 5675",
    "sg:postcode":"37013",
    "sg:province":"TN",
    "wof:name":"Sunrise Market",
    "wof:placetype":"venue"
},
  "geometry": {"coordinates":[-86.584414,36.055623],"type":"Point"}
}