{
  "type": "Feature",
  "properties": {
    "iso:country":"US",
    "sg:address":"1930 Memorial Blvd",
    "sg:city":"Murfreesboro",
    "sg:classifiers":[
        {
            "category":"Arena",
            "subcategory":"Sports Club",
            "type":"Entertainment"
        }
    ],
    "sg:phone":"+1 615 893 2011",
    "sg:postcode":"37129",
    "sg:province":"TN",
    "sg:tags":[
        "soccer"
    ],
    "wof:name":"Murfreesboro Soccer Club",
    "wof:placetype":"venue"
},
  "geometry": {"coordinates":[-86.395959,35.853852],"type":"Point"}
}