{
  "type": "Feature",
  "properties": {
    "iso:country":"US",
    "sg:address":"200 24th Ave S",
    "sg:city":"Nashville",
    "sg:classifiers":[
        {
            "category":"Organizations",
            "subcategory":"Religious Organization",
            "type":"Services"
        }
    ],
    "sg:phone":"+1 615 322 4783",
    "sg:postcode":"37212",
    "sg:province":"TN",
    "sg:tags":[
        "church"
    ],
    "wof:name":"Saint Augustine's Chapel",
    "wof:placetype":"venue"
},
  "geometry": {"coordinates":[-86.804918,36.1458],"type":"Point"}
}