{
  "type": "Feature",
  "properties": {
    "addr:full":"24 Pepper Ridge Ct Johnson City TN 37615",
    "addr:housenumber":"24",
    "addr:postcode":"37615",
    "addr:street":"Pepper Ridge Ct",
    "iso:country":"US",
    "sg:address":"24 Pepper Ridge Ct",
    "sg:city":"Johnson City",
    "sg:classifiers":[
        {
            "category":"Organizations",
            "subcategory":"Community Association",
            "type":"Services"
        }
    ],
    "sg:phone":"+1 423 854 8971",
    "sg:postcode":"37615",
    "sg:province":"TN",
    "sg:tags":[
        "condominium"
    ],
    "wof:name":"Pepper Ridge Court Condo",
    "wof:placetype":"venue"
},
  "geometry": {"coordinates":[-82.41378899999999,36.397391],"type":"Point"}
}