{
  "type": "Feature",
  "properties": {
    "iso:country":"US",
    "sg:address":"1045 Rule Hollow Rd",
    "sg:city":"Sevierville",
    "sg:classifiers":[
        {
            "category":"Retail",
            "subcategory":"Auto Repair",
            "type":"Services"
        }
    ],
    "sg:phone":"+1 865 429 5742",
    "sg:postcode":"37876",
    "sg:province":"TN",
    "sg:tags":[
        "repairing",
        "automobile",
        "general"
    ],
    "wof:name":"Rule Hollow Automotive LLC",
    "wof:placetype":"venue"
},
  "geometry": {"coordinates":[-83.621788,35.880276],"type":"Point"}
}