{
  "type": "Feature",
  "properties": {
    "addr:full":"3359 Winbrook Dr Memphis TN 38116",
    "addr:housenumber":"3359",
    "addr:postcode":"38116",
    "addr:street":"Winbrook Dr",
    "iso:country":"US",
    "sg:address":"3359 Winbrook Dr",
    "sg:city":"Memphis",
    "sg:classifiers":[
        {
            "category":"Transit Center",
            "subcategory":"Freight",
            "type":"Transportation"
        }
    ],
    "sg:phone":"+1 901 332 1600",
    "sg:postcode":"38116",
    "sg:province":"TN",
    "sg:tags":[
        "air",
        "cargo",
        "express",
        "package"
    ],
    "wof:name":"Pilot Air Freight",
    "wof:placetype":"venue"
},
  "geometry": {"coordinates":[-89.997603,35.056818],"type":"Point"}
}