{
  "type": "Feature",
  "properties": {
    "addr:full":"285 Fellers Cove Mosheim TN 37818",
    "addr:housenumber":"285",
    "addr:postcode":"37818",
    "addr:street":"Fellers Cove",
    "iso:country":"US",
    "sg:address":"285 Fellers Cove",
    "sg:city":"Mosheim",
    "sg:classifiers":[
        {
            "category":"Building & Trades",
            "subcategory":"Cleaning & Sanitation",
            "type":"Services"
        }
    ],
    "sg:phone":"+1 423 422 0077",
    "sg:postcode":"37818",
    "sg:province":"TN",
    "sg:tags":[
        "house"
    ],
    "wof:name":"White Orchid Cleaning",
    "wof:placetype":"venue"
},
  "geometry": {"coordinates":[-82.955417,36.2101],"type":"Point"}
}