{
  "type": "Feature",
  "properties": {
    "addr:full":"516 Stone Gate Pl Brentwood TN 37027",
    "addr:housenumber":"516",
    "addr:postcode":"37027",
    "addr:street":"Stone Gate Pl",
    "iso:country":"US",
    "sg:address":"516 Stone Gate Pl",
    "sg:city":"Brentwood",
    "sg:classifiers":[
        {
            "category":"Banks & Credit Unions",
            "subcategory":"Bank",
            "type":"Services"
        }
    ],
    "sg:phone":"+1 615 377 4686",
    "sg:postcode":"37027",
    "sg:province":"TN",
    "sg:tags":[
        "broker",
        "mortgage"
    ],
    "wof:name":"Smp Financial LLC",
    "wof:placetype":"venue"
},
  "geometry": {"coordinates":[-86.77181299999999,36.048473],"type":"Point"}
}