{
  "type": "Feature",
  "properties": {
    "iso:country":"US",
    "sg:address":"3303 Shiloh Ridge Rd",
    "sg:city":"Corinth",
    "sg:classifiers":[
        {
            "category":"Recreation",
            "type":"Entertainment"
        }
    ],
    "sg:phone":"+1 662 287 5669",
    "sg:postcode":"38834",
    "sg:province":"TN",
    "sg:tags":[
        "course",
        "golf"
    ],
    "wof:name":"Discount Golf",
    "wof:placetype":"venue"
},
  "geometry": {"coordinates":[-88.484848,34.962706],"type":"Point"}
}