{
  "type": "Feature",
  "properties": {
    "iso:country":"US",
    "sg:address":"9620 Clovercroft Rd",
    "sg:city":"Nolensville",
    "sg:classifiers":[
        {
            "category":"Professional",
            "subcategory":"Management & Consulting",
            "type":"Services"
        }
    ],
    "sg:phone":"+1 615 776 5346",
    "sg:postcode":"37135",
    "sg:province":"TN",
    "sg:tags":[
        "marketing"
    ],
    "wof:name":"Innovative Marketing",
    "wof:placetype":"venue"
},
  "geometry": {"coordinates":[-86.70857100000001,35.937856],"type":"Point"}
}