{
  "type": "Feature",
  "properties": {
    "iso:country":"US",
    "sg:address":"1615 Marsden Ave",
    "sg:city":"Nashville",
    "sg:classifiers":[
        {
            "category":"Social Services",
            "subcategory":"Child Care",
            "type":"Services"
        }
    ],
    "sg:phone":"+1 615 226 9677",
    "sg:postcode":"37216",
    "sg:province":"TN",
    "sg:tags":[
        "day"
    ],
    "wof:name":"Maxine's Child Care",
    "wof:placetype":"venue"
},
  "geometry": {"coordinates":[-86.723523,36.201299],"type":"Point"}
}