{
  "type": "Feature",
  "properties": {
    "iso:country":"US",
    "sg:address":"1421 Osborne St",
    "sg:city":"Humboldt",
    "sg:classifiers":[
        {
            "category":"Government",
            "subcategory":"Office",
            "type":"Public Place"
        }
    ],
    "sg:phone":"+1 731 784 9551",
    "sg:postcode":"38343",
    "sg:province":"TN",
    "sg:tags":[
        "village"
    ],
    "wof:name":"Humboldt General Sessions Ct",
    "wof:placetype":"venue"
},
  "geometry": {"coordinates":[-88.91685099999999,35.821531],"type":"Point"}
}