{
  "type": "Feature",
  "properties": {
    "addr:full":"224 Spring St Jonesborough TN 37659",
    "addr:housenumber":"224",
    "addr:postcode":"37659",
    "addr:street":"Spring St",
    "iso:country":"US",
    "sg:address":"224 Spring St",
    "sg:city":"Jonesborough",
    "sg:classifiers":[
        {
            "category":"Shopping",
            "subcategory":"Used Merchandise",
            "type":"Retail Goods"
        }
    ],
    "sg:phone":"+1 423 913 0575",
    "sg:postcode":"37659",
    "sg:province":"TN",
    "sg:tags":[
        "book",
        "rare",
        "dealer"
    ],
    "wof:name":"Mulberry Corner Used & Rare",
    "wof:placetype":"venue"
},
  "geometry": {"coordinates":[-82.467406,36.293086],"type":"Point"}
}