{
  "type": "Feature",
  "properties": {
    "iso:country":"US",
    "sg:address":"122 Wexler St",
    "sg:city":"Kingsport",
    "sg:classifiers":[
        {
            "category":"Building & Trades",
            "subcategory":"Construction",
            "type":"Services"
        }
    ],
    "sg:phone":"+1 423 246 8151",
    "sg:postcode":"37660",
    "sg:province":"TN",
    "sg:tags":[
        "general",
        "contractor"
    ],
    "sg:website":"www.irby.com",
    "wof:name":"Stuart C Irby Co",
    "wof:placetype":"venue"
},
  "geometry": {"coordinates":[-82.556945,36.542272],"type":"Point"}
}