{
  "type": "Feature",
  "properties": {
    "iso:country":"US",
    "sg:address":"2960 Foster Creighton Dr",
    "sg:city":"Nashville",
    "sg:classifiers":[
        {
            "category":"Professional",
            "subcategory":"Testing Lab",
            "type":"Services"
        }
    ],
    "sg:phone":"+1 615 726 0177",
    "sg:postcode":"37204",
    "sg:province":"TN",
    "sg:tags":[
        "laboratory"
    ],
    "sg:website":"www.testamericainc.com",
    "wof:name":"Testamerica Inc",
    "wof:placetype":"venue"
},
  "geometry": {"coordinates":[-86.754105,36.105637],"type":"Point"}
}