{
  "type": "Feature",
  "properties": {
    "iso:country":"US",
    "sg:address":"1051 Indian Mountain Rd",
    "sg:city":"Jellico",
    "sg:classifiers":[
        {
            "category":"Shopping",
            "subcategory":"Computers & Home Electronics",
            "type":"Retail Goods"
        }
    ],
    "sg:phone":"+1 423 784 4903",
    "sg:postcode":"37762",
    "sg:province":"TN",
    "wof:name":"Tech World",
    "wof:placetype":"venue"
},
  "geometry": {"coordinates":[-84.15653,36.570541],"type":"Point"}
}