{
  "type": "Feature",
  "properties": {
    "iso:country":"US",
    "sg:address":"411 Princeton Rd",
    "sg:city":"Johnson City",
    "sg:classifiers":[
        {
            "category":"Health Services",
            "subcategory":"Doctor",
            "type":"Services"
        }
    ],
    "sg:phone":"+1 423 282 6613",
    "sg:postcode":"37601",
    "sg:province":"TN",
    "sg:tags":[
        "dentist"
    ],
    "wof:name":"Larry E Denny DMD",
    "wof:placetype":"venue"
},
  "geometry": {"coordinates":[-82.369353,36.353756],"type":"Point"}
}