{
  "type": "Feature",
  "properties": {
    "iso:country":"US",
    "sg:address":"807 Old Airport Rd",
    "sg:city":"Bristol",
    "sg:classifiers":[
        {
            "category":"Building & Trades",
            "subcategory":"Construction",
            "type":"Services"
        }
    ],
    "sg:phone":"+1 276 669 1391",
    "sg:postcode":"24201",
    "sg:province":"TN",
    "sg:tags":[
        "excavation",
        "contractor"
    ],
    "wof:name":"Finney & Finney Construction",
    "wof:placetype":"venue"
},
  "geometry": {"coordinates":[-82.123648,36.624424],"type":"Point"}
}