{
  "type": "Feature",
  "properties": {
    "iso:country":"US",
    "sg:address":"655 Riverside Dr",
    "sg:city":"Memphis",
    "sg:classifiers":[
        {
            "category":"Building & Trades",
            "subcategory":"Cleaning & Sanitation",
            "type":"Services"
        }
    ],
    "sg:phone":"+1 901 523 9627",
    "sg:postcode":"38103",
    "sg:province":"TN",
    "sg:tags":[
        "janitor"
    ],
    "wof:name":"Sterling Enterprises",
    "wof:placetype":"venue"
},
  "geometry": {"coordinates":[-90.066917,35.130233],"type":"Point"}
}