{
  "type": "Feature",
  "properties": {
    "iso:country":"US",
    "sg:address":"2799 Broad Ave",
    "sg:city":"Memphis",
    "sg:classifiers":[
        {
            "category":"Wholesale",
            "subcategory":"Electrical",
            "type":"Manufacturing & Wholesale Goods"
        }
    ],
    "sg:phone":"+1 901 324 7089",
    "sg:postcode":"38112",
    "sg:province":"TN",
    "sg:tags":[
        "control",
        "equipment",
        "security",
        "monitoring",
        "system"
    ],
    "sg:website":"http://www.atwec.com",
    "wof:name":"Advanced Security",
    "wof:placetype":"venue"
},
  "geometry": {"coordinates":[-89.968019,35.147219],"type":"Point"}
}