{
  "type": "Feature",
  "properties": {
    "addr:full":"435 Gould Dr Cookeville TN 38506",
    "addr:housenumber":"435",
    "addr:postcode":"38506",
    "addr:street":"Gould Dr",
    "iso:country":"US",
    "sg:address":"435 Gould Dr",
    "sg:city":"Cookeville",
    "sg:classifiers":[
        {
            "category":"Social Services",
            "type":"Services"
        }
    ],
    "sg:phone":"+1 931 432 5981",
    "sg:postcode":"38506",
    "sg:province":"TN",
    "wof:name":"ARC Diversified Industries",
    "wof:placetype":"venue"
},
  "geometry": {"coordinates":[-85.53322199999999,36.131022],"type":"Point"}
}