{
  "type": "Feature",
  "properties": {
    "iso:country":"US",
    "sg:address":"238 Airways Blvd",
    "sg:city":"Jackson",
    "sg:classifiers":[
        {
            "category":"Real Estate",
            "subcategory":"Real Estate Operator",
            "type":"Services"
        }
    ],
    "sg:phone":"+1 731 427 0324",
    "sg:postcode":"38301",
    "sg:province":"TN",
    "sg:tags":[
        "building",
        "apartment"
    ],
    "wof:name":"Poplar Plaza Apartments",
    "wof:placetype":"venue"
},
  "geometry": {"coordinates":[-88.82928200000001,35.616226],"type":"Point"}
}