{
  "type": "Feature",
  "properties": {
    "addr:full":"118 Glass St Jackson TN 38301",
    "addr:housenumber":"118",
    "addr:postcode":"38301",
    "addr:street":"Glass St",
    "iso:country":"US",
    "sg:address":"118 Glass St",
    "sg:city":"Jackson",
    "sg:classifiers":[
        {
            "category":"Health Services",
            "subcategory":"Nursing And Care Facility",
            "type":"Services"
        }
    ],
    "sg:phone":"+1 731 424 2951",
    "sg:postcode":"38301",
    "sg:province":"TN",
    "sg:tags":[
        "home",
        "convalescent"
    ],
    "wof:name":"Mission Convalescent Home",
    "wof:placetype":"venue"
},
  "geometry": {"coordinates":[-88.79885299999999,35.628213],"type":"Point"}
}