{
  "type": "Feature",
  "properties": {
    "addr:full":"2150 Amnicola Hwy Chattanooga TN 37406",
    "addr:housenumber":"2150",
    "addr:postcode":"37406",
    "addr:street":"Amnicola Hwy",
    "iso:country":"US",
    "sg:address":"2150 Amnicola Hwy",
    "sg:city":"Chattanooga",
    "sg:classifiers":[
        {
            "category":"Banks & Credit Unions",
            "subcategory":"Investment Brokerage",
            "type":"Services"
        }
    ],
    "sg:phone":"+1 423 698 8210",
    "sg:postcode":"37406",
    "sg:province":"TN",
    "wof:name":"Southeastern Investment Inc",
    "wof:placetype":"venue"
},
  "geometry": {"coordinates":[-85.271202,35.06837],"type":"Point"}
}