{
  "type": "Feature",
  "properties": {
    "addr:full":"727 S Highland St Memphis TN 38111",
    "addr:housenumber":"727",
    "addr:postcode":"38111",
    "addr:street":"S Highland St",
    "iso:country":"US",
    "sg:address":"727 S Highland St",
    "sg:city":"Memphis",
    "sg:classifiers":[
        {
            "category":"Fast Food",
            "type":"Food & Drink"
        },
        {
            "category":"Restaurant",
            "type":"Food & Drink"
        }
    ],
    "sg:phone":"+1 901 452 6937",
    "sg:postcode":"38111",
    "sg:province":"TN",
    "sg:tags":[
        "hot",
        "hamburger",
        "dog"
    ],
    "wof:name":"Checkers",
    "wof:placetype":"venue"
},
  "geometry": {"coordinates":[-89.94589000000001,35.111581],"type":"Point"}
}