{
  "type": "Feature",
  "properties": {
    "iso:country":"US",
    "sg:address":"1305 Murfreesboro Pike",
    "sg:city":"Nashville",
    "sg:classifiers":[
        {
            "category":"Real Estate",
            "subcategory":"Real Estate Agent",
            "type":"Services"
        }
    ],
    "sg:phone":"+1 615 385 9010",
    "sg:postcode":"37217",
    "sg:province":"TN",
    "wof:name":"The Realty Association",
    "wof:placetype":"venue"
},
  "geometry": {"coordinates":[-86.69939100000001,36.117513],"type":"Point"}
}