{
  "type": "Feature",
  "properties": {
    "iso:country":"US",
    "sg:address":"17 Hollis Hollow Rd",
    "sg:city":"Loretto",
    "sg:classifiers":[
        {
            "category":"Building & Trades",
            "subcategory":"Landscaping Services",
            "type":"Services"
        }
    ],
    "sg:phone":"+1 931 853 6844",
    "sg:postcode":"38469",
    "sg:province":"TN",
    "sg:tags":[
        "tree"
    ],
    "wof:name":"Hollis Professional Tree Serv",
    "wof:placetype":"venue"
},
  "geometry": {"coordinates":[-87.438744,35.098525],"type":"Point"}
}