{
  "type": "Feature",
  "properties": {
    "addr:full":"4121 Hillsboro Pike Nashville TN 37215",
    "addr:housenumber":"4121",
    "addr:postcode":"37215",
    "addr:street":"Hillsboro Pike",
    "iso:country":"US",
    "sg:address":"4121 Hillsboro Pike",
    "sg:city":"Nashville",
    "sg:classifiers":[
        {
            "category":"Retail",
            "subcategory":"Laundry & Dry Cleaning",
            "type":"Services"
        }
    ],
    "sg:phone":"+1 615 292 0510",
    "sg:postcode":"37215",
    "sg:province":"TN",
    "wof:name":"Heritage Cleaners",
    "wof:placetype":"venue"
},
  "geometry": {"coordinates":[-86.818589,36.10118],"type":"Point"}
}