{
  "type": "Feature",
  "properties": {
    "iso:country":"US",
    "sg:address":"700 Roberts Cir",
    "sg:city":"Lenoir City",
    "sg:classifiers":[
        {
            "category":"Building & Trades",
            "subcategory":"Construction",
            "type":"Services"
        }
    ],
    "sg:phone":"+1 865 776 0925",
    "sg:postcode":"37772",
    "sg:province":"TN",
    "sg:tags":[
        "general",
        "contractor"
    ],
    "wof:name":"Whitworth Drywall",
    "wof:placetype":"venue"
},
  "geometry": {"coordinates":[-84.24799299999999,35.835045],"type":"Point"}
}