{
  "type": "Feature",
  "properties": {
    "iso:country":"US",
    "sg:address":"319 Cross Timbers Dr",
    "sg:city":"Nashville",
    "sg:classifiers":[
        {
            "category":"Communications",
            "subcategory":"Film & Video Production",
            "type":"Services"
        },
        {
            "category":"Arts & Performance",
            "subcategory":"Theater",
            "type":"Entertainment"
        }
    ],
    "sg:phone":"+1 615 662 6393",
    "sg:postcode":"37221",
    "sg:province":"TN",
    "sg:tags":[
        "theatrical",
        "animated"
    ],
    "wof:name":"Candle Moon",
    "wof:placetype":"venue"
},
  "geometry": {"coordinates":[-86.93841,36.083091],"type":"Point"}
}