{
  "type": "Feature",
  "properties": {
    "addr:full":"52 Timber Creek Dr Cordova TN 38018",
    "addr:housenumber":"52",
    "addr:postcode":"38018",
    "addr:street":"Timber Creek Dr",
    "iso:country":"US",
    "sg:address":"52 Timber Creek Dr",
    "sg:city":"Cordova",
    "sg:classifiers":[
        {
            "category":"Professional",
            "subcategory":"Management & Consulting",
            "type":"Services"
        }
    ],
    "sg:phone":"+1 901 683 4320",
    "sg:postcode":"38018",
    "sg:province":"TN",
    "sg:tags":[
        "consultant",
        "business"
    ],
    "wof:name":"Centre Group",
    "wof:placetype":"venue"
},
  "geometry": {"coordinates":[-89.794988,35.12778],"type":"Point"}
}