{
  "type": "Feature",
  "properties": {
    "iso:country":"US",
    "sg:address":"4621 Marshall Dr",
    "sg:city":"Knoxville",
    "sg:classifiers":[
        {
            "category":"Building & Trades",
            "subcategory":"Plumbing",
            "type":"Services"
        }
    ],
    "sg:phone":"+1 865 925 8233",
    "sg:postcode":"37918",
    "sg:province":"TN",
    "sg:tags":[
        "conditioning",
        "air",
        "system",
        "contractor"
    ],
    "wof:name":"Comfort Heating & Air",
    "wof:placetype":"venue"
},
  "geometry": {"coordinates":[-83.91577700000001,36.081758],"type":"Point"}
}