{
  "type": "Feature",
  "properties": {
    "addr:full":"621 Rivergate Meadows Dr Goodlettsville TN 37072",
    "addr:housenumber":"621",
    "addr:postcode":"37072",
    "addr:street":"Rivergate Meadows Dr",
    "iso:country":"US",
    "sg:address":"621 Rivergate Meadows Dr",
    "sg:city":"Goodlettsville",
    "sg:classifiers":[
        {
            "category":"Travel",
            "subcategory":"Hotels & Motels",
            "type":"Entertainment"
        }
    ],
    "sg:phone":"+1 615 448 2100",
    "sg:postcode":"37072",
    "sg:province":"TN",
    "wof:name":"Comfort Suites",
    "wof:placetype":"venue"
},
  "geometry": {"coordinates":[-86.70886900000001,36.297574],"type":"Point"}
}