{
  "type": "Feature",
  "properties": {
    "iso:country":"US",
    "sg:address":"4200 State Hwy 12 N",
    "sg:city":"Ashland City",
    "sg:classifiers":[
        {
            "category":"Food & Beverages",
            "subcategory":"Groceries & Convenience Stores",
            "type":"Retail Goods"
        }
    ],
    "sg:phone":"+1 615 307 4466",
    "sg:postcode":"37015",
    "sg:province":"TN",
    "wof:name":"Henrietta Shop Rite",
    "wof:placetype":"venue"
},
  "geometry": {"coordinates":[-87.20384300000001,36.406686],"type":"Point"}
}