{
  "type": "Feature",
  "properties": {
    "iso:country":"US",
    "sg:address":"1201 16th Ave S",
    "sg:city":"Nashville",
    "sg:classifiers":[
        {
            "category":"Building & Trades",
            "subcategory":"Construction",
            "type":"Services"
        }
    ],
    "sg:phone":"+1 615 321 2037",
    "sg:postcode":"37212",
    "sg:province":"TN",
    "sg:tags":[
        "property",
        "school",
        "management",
        "for"
    ],
    "wof:name":"School Facility Management LLC",
    "wof:placetype":"venue"
},
  "geometry": {"coordinates":[-86.79364099999999,36.140741],"type":"Point"}
}