{
  "type": "Feature",
  "properties": {
    "addr:full":"104 W Main St Mc Minnville TN 37110",
    "addr:housenumber":"104",
    "addr:postcode":"37110",
    "addr:street":"W Main St",
    "iso:country":"US",
    "sg:address":"104 W Main St",
    "sg:city":"Mc Minnville",
    "sg:classifiers":[
        {
            "category":"Shopping",
            "subcategory":"Used Merchandise",
            "type":"Retail Goods"
        }
    ],
    "sg:phone":"+1 931 507 7700",
    "sg:postcode":"37110",
    "sg:province":"TN",
    "sg:tags":[
        "antique"
    ],
    "wof:name":"Victorian Rose Antiques",
    "wof:placetype":"venue"
},
  "geometry": {"coordinates":[-85.774393,35.681464],"type":"Point"}
}