{
  "type": "Feature",
  "properties": {
    "iso:country":"US",
    "sg:address":"4120 Elizabeth Dr",
    "sg:city":"Mount Juliet",
    "sg:classifiers":[
        {
            "category":"Building & Trades",
            "subcategory":"Construction",
            "type":"Services"
        }
    ],
    "sg:phone":"+1 615 453 9651",
    "sg:postcode":"37122",
    "sg:province":"TN",
    "sg:tags":[
        "contractor"
    ],
    "wof:name":"American Roof Design LLC",
    "wof:placetype":"venue"
},
  "geometry": {"coordinates":[-86.51084299999999,36.113593],"type":"Point"}
}