{
  "type": "Feature",
  "properties": {
    "addr:full":"658 W Mitchell Rd Memphis TN 38109",
    "addr:housenumber":"658",
    "addr:postcode":"38109",
    "addr:street":"W Mitchell Rd",
    "iso:country":"US",
    "sg:address":"658 W Mitchell Rd",
    "sg:city":"Memphis",
    "sg:classifiers":[
        {
            "category":"Education",
            "subcategory":"School",
            "type":"Public Place"
        }
    ],
    "sg:phone":"+1 901 416 8174",
    "sg:postcode":"38109",
    "sg:province":"TN",
    "sg:tags":[
        "high"
    ],
    "sg:website":"http://www.whitehaven95.com",
    "wof:name":"Mitchell High School",
    "wof:placetype":"venue"
},
  "geometry": {"coordinates":[-90.085948,35.055943],"type":"Point"}
}