{
  "type": "Feature",
  "properties": {
    "iso:country":"US",
    "sg:address":"1103 Bowmantown Rd",
    "sg:city":"Limestone",
    "sg:classifiers":[
        {
            "category":"Organizations",
            "subcategory":"Religious Organization",
            "type":"Services"
        }
    ],
    "sg:phone":"+1 423 257 5205",
    "sg:postcode":"37681",
    "sg:province":"TN",
    "sg:tags":[
        "church"
    ],
    "wof:name":"Oakland Presbyterian Church",
    "wof:placetype":"venue"
},
  "geometry": {"coordinates":[-82.62699000000001,36.26606],"type":"Point"}
}