{
  "type": "Feature",
  "properties": {
    "iso:country":"US",
    "sg:address":"744 S Willow Ave",
    "sg:city":"Cookeville",
    "sg:classifiers":[
        {
            "category":"Banks & Credit Unions",
            "subcategory":"Bank",
            "type":"Services"
        }
    ],
    "sg:phone":"+1 931 528 0138",
    "sg:postcode":"38501",
    "sg:province":"TN",
    "sg:website":"www.communitybankotc.com",
    "wof:name":"Community Bank Of Cookeville",
    "wof:placetype":"venue"
},
  "geometry": {"coordinates":[-85.51986100000001,36.147691],"type":"Point"}
}