{
  "type": "Feature",
  "properties": {
    "addr:full":"3835 Knight Rd Memphis TN 38118",
    "addr:housenumber":"3835",
    "addr:postcode":"38118",
    "addr:street":"Knight Rd",
    "iso:country":"US",
    "sg:address":"3835 Knight Rd",
    "sg:city":"Memphis",
    "sg:classifiers":[
        {
            "category":"Food & Beverages",
            "subcategory":"Specialty",
            "type":"Retail Goods"
        }
    ],
    "sg:phone":"+1 901 794 1925",
    "sg:postcode":"38118",
    "sg:province":"TN",
    "sg:tags":[
        "water",
        "bulk",
        "company"
    ],
    "wof:name":"D S Waters",
    "wof:placetype":"venue"
},
  "geometry": {"coordinates":[-89.91127400000001,35.044112],"type":"Point"}
}