{
  "type": "Feature",
  "properties": {
    "iso:country":"US",
    "sg:address":"25 Burnley Rd",
    "sg:city":"Hartsville",
    "sg:classifiers":[
        {
            "category":"Building & Trades",
            "subcategory":"Construction",
            "type":"Services"
        }
    ],
    "sg:phone":"+1 615 374 0606",
    "sg:postcode":"37074",
    "sg:province":"TN",
    "sg:tags":[
        "piping",
        "contractor"
    ],
    "wof:name":"Universal Piping Inc",
    "wof:placetype":"venue"
},
  "geometry": {"coordinates":[-86.197253,36.360364],"type":"Point"}
}