{
  "type": "Feature",
  "properties": {
    "iso:country":"US",
    "sg:address":"874 Union Ave",
    "sg:city":"Memphis",
    "sg:classifiers":[
        {
            "category":"Manufacturing",
            "subcategory":"Chemicals & Compounds",
            "type":"Manufacturing & Wholesale Goods"
        }
    ],
    "sg:phone":"+1 901 448 6027",
    "sg:postcode":"38103",
    "sg:province":"TN",
    "sg:tags":[
        "pharmaceutical"
    ],
    "wof:name":"Pharmaceutical Department",
    "wof:placetype":"venue"
},
  "geometry": {"coordinates":[-90.03171,35.138437],"type":"Point"}
}