{
  "type": "Feature",
  "properties": {
    "iso:country":"US",
    "sg:address":"2345 Howard Rd",
    "sg:city":"Germantown",
    "sg:classifiers":[
        {
            "category":"Professional",
            "subcategory":"Business Services",
            "type":"Services"
        }
    ],
    "sg:phone":"+1 901 754 7221",
    "sg:postcode":"38138",
    "sg:province":"TN",
    "wof:name":"Afterglow",
    "wof:placetype":"venue"
},
  "geometry": {"coordinates":[-89.819472,35.084371],"type":"Point"}
}