{
  "type": "Feature",
  "properties": {
    "iso:country":"US",
    "sg:address":"621 Baton Rouge Ct",
    "sg:city":"Hermitage",
    "sg:classifiers":[
        {
            "category":"Shopping",
            "subcategory":"Music",
            "type":"Retail Goods"
        }
    ],
    "sg:phone":"+1 615 885 8000",
    "sg:postcode":"37076",
    "sg:province":"TN",
    "sg:tags":[
        "compact",
        "record",
        "disc",
        "tape"
    ],
    "sg:website":"www.gospelgallery.com",
    "wof:name":"Gospel Gallery",
    "wof:placetype":"venue"
},
  "geometry": {"coordinates":[-86.60453800000001,36.200979],"type":"Point"}
}