{
  "type": "Feature",
  "properties": {
    "iso:country":"US",
    "sg:address":"4552 Chapman Hwy",
    "sg:city":"Knoxville",
    "sg:classifiers":[
        {
            "category":"Banks & Credit Unions",
            "subcategory":"Bank",
            "type":"Services"
        }
    ],
    "sg:phone":"+1 865 579 3412",
    "sg:postcode":"37920",
    "sg:province":"TN",
    "sg:tags":[
        "other",
        "plan",
        "card"
    ],
    "wof:name":"Compucredit",
    "wof:placetype":"venue"
},
  "geometry": {"coordinates":[-83.902962,35.932224],"type":"Point"}
}