{
  "type": "Feature",
  "properties": {
    "addr:full":"1654 Ferrells Branch Rd Beechgrove TN 37018",
    "addr:housenumber":"1654",
    "addr:postcode":"37018",
    "addr:street":"Ferrells Branch Rd",
    "iso:country":"US",
    "sg:address":"1654 Ferrells Branch Rd",
    "sg:city":"Beechgrove",
    "sg:classifiers":[
        {
            "category":"Building & Trades",
            "subcategory":"Construction",
            "type":"Services"
        }
    ],
    "sg:phone":"+1 931 394 2492",
    "sg:postcode":"37018",
    "sg:province":"TN",
    "sg:tags":[
        "general",
        "contractor"
    ],
    "wof:name":"Lesco Builders Inc",
    "wof:placetype":"venue"
},
  "geometry": {"coordinates":[-86.17518,35.620815],"type":"Point"}
}