{
  "type": "Feature",
  "properties": {
    "iso:country":"US",
    "sg:address":"124 N Hills Dr",
    "sg:city":"Mc Minnville",
    "sg:classifiers":[
        {
            "category":"Wholesale",
            "subcategory":"Plants",
            "type":"Manufacturing & Wholesale Goods"
        }
    ],
    "sg:phone":"+1 931 473 5046",
    "sg:postcode":"37110",
    "sg:province":"TN",
    "sg:tags":[
        "supply"
    ],
    "wof:name":"Don Basham Nursery",
    "wof:placetype":"venue"
},
  "geometry": {"coordinates":[-85.789669,35.701482],"type":"Point"}
}