{
  "type": "Feature",
  "properties": {
    "iso:country":"US",
    "sg:address":"1560 S Maple Ave",
    "sg:city":"Cookeville",
    "sg:classifiers":[
        {
            "category":"Wholesale",
            "subcategory":"Books, Periodicals, & Newspapers",
            "type":"Manufacturing & Wholesale Goods"
        }
    ],
    "sg:phone":"+1 931 526 8860",
    "sg:postcode":"38506",
    "sg:province":"TN",
    "sg:tags":[
        "magazine",
        "retailer"
    ],
    "wof:name":"Austin Prdicals Satellite Agcy",
    "wof:placetype":"venue"
},
  "geometry": {"coordinates":[-85.493599,36.118696],"type":"Point"}
}