{
  "type": "Feature",
  "properties": {
    "addr:full":"1204 Newmans Trl Hendersonville TN 37075",
    "addr:housenumber":"1204",
    "addr:postcode":"37075",
    "addr:street":"Newmans Trl",
    "iso:country":"US",
    "sg:address":"1204 Newmans Trl",
    "sg:city":"Hendersonville",
    "sg:classifiers":[
        {
            "category":"Professional",
            "subcategory":"Computer Services",
            "type":"Services"
        }
    ],
    "sg:phone":"+1 615 824 6261",
    "sg:postcode":"37075",
    "sg:province":"TN",
    "sg:tags":[
        "datum"
    ],
    "wof:name":"Transverse Networks",
    "wof:placetype":"venue"
},
  "geometry": {"coordinates":[-86.599003,36.385079],"type":"Point"}
}