{
  "type": "Feature",
  "properties": {
    "iso:country":"US",
    "sg:address":"2232 Pete Mitchell Rd",
    "sg:city":"Germantown",
    "sg:classifiers":[
        {
            "category":"Manufacturing",
            "subcategory":"Printing",
            "type":"Manufacturing & Wholesale Goods"
        }
    ],
    "sg:phone":"+1 901 757 0225",
    "sg:postcode":"38138",
    "sg:province":"TN",
    "sg:tags":[
        "publishing"
    ],
    "wof:name":"American Publishing Inc",
    "wof:placetype":"venue"
},
  "geometry": {"coordinates":[-89.802984,35.088653],"type":"Point"}
}