{
  "type": "Feature",
  "properties": {
    "iso:country":"US",
    "sg:address":"2292 Peres Ave",
    "sg:city":"Memphis",
    "sg:classifiers":[
        {
            "category":"Retail",
            "subcategory":"Auto Repair",
            "type":"Services"
        }
    ],
    "sg:phone":"+1 901 725 8991",
    "sg:postcode":"38108",
    "sg:province":"TN",
    "sg:tags":[
        "repairing",
        "automobile"
    ],
    "wof:name":"Humphrey's Automotive Hobbies",
    "wof:placetype":"venue"
},
  "geometry": {"coordinates":[-89.980673,35.175182],"type":"Point"}
}