{
  "type": "Feature",
  "properties": {
    "addr:full":"7821 Corryton Luttrell Rd Corryton TN 37721",
    "addr:housenumber":"7821",
    "addr:postcode":"37721",
    "addr:street":"Corryton Luttrell Rd",
    "iso:country":"US",
    "sg:address":"7821 Corryton Luttrell Rd",
    "sg:city":"Corryton",
    "sg:classifiers":[
        {
            "category":"Home & Garden",
            "subcategory":"Garden Supply",
            "type":"Retail Goods"
        }
    ],
    "sg:phone":"+1 865 687 3770",
    "sg:postcode":"37721",
    "sg:province":"TN",
    "sg:tags":[
        "nurseryman"
    ],
    "wof:name":"Oakes Daylilies",
    "wof:placetype":"venue"
},
  "geometry": {"coordinates":[-83.78017699999999,36.157011],"type":"Point"}
}