{
  "type": "Feature",
  "properties": {
    "iso:country":"US",
    "sg:address":"933 W Old Hickory Blvd",
    "sg:city":"Madison",
    "sg:classifiers":[
        {
            "category":"Bus Charters",
            "type":"Transportation"
        },
        {
            "category":"Autos & Motor Vehicles",
            "subcategory":"Recreational Vehicle Sales",
            "type":"Retail Goods"
        }
    ],
    "sg:phone":"+1 615 860 9485",
    "sg:postcode":"37115",
    "sg:province":"TN",
    "sg:tags":[
        "home",
        "rental",
        "lease"
    ],
    "sg:website":"www.staleycoach.com",
    "wof:name":"Staley Coach",
    "wof:placetype":"venue"
},
  "geometry": {"coordinates":[-86.748907,36.267829],"type":"Point"}
}