{
  "type": "Feature",
  "properties": {
    "addr:full":"7211 Wellington Dr Knoxville TN 37919",
    "addr:housenumber":"7211",
    "addr:postcode":"37919",
    "addr:street":"Wellington Dr",
    "iso:country":"US",
    "sg:address":"7211 Wellington Dr",
    "sg:city":"Knoxville",
    "sg:classifiers":[
        {
            "category":"Health Services",
            "subcategory":"Doctor",
            "type":"Services"
        }
    ],
    "sg:phone":"+1 865 588 8005",
    "sg:postcode":"37919",
    "sg:province":"TN",
    "sg:tags":[
        "physician",
        "surgeon"
    ],
    "wof:name":"Summit Urgent Care Clinic",
    "wof:placetype":"venue"
},
  "geometry": {"coordinates":[-84.026867,35.930624],"type":"Point"}
}