{
  "type": "Feature",
  "properties": {
    "iso:country":"US",
    "sg:address":"1633 Lisalynn Dr",
    "sg:city":"Hixson",
    "sg:classifiers":[
        {
            "category":"Shopping",
            "type":"Retail Goods"
        }
    ],
    "sg:phone":"+1 423 847 9956",
    "sg:postcode":"37343",
    "sg:province":"TN",
    "sg:tags":[
        "candle"
    ],
    "wof:name":"Chattanooga Candle Co",
    "wof:placetype":"venue"
},
  "geometry": {"coordinates":[-85.18845899999999,35.19798],"type":"Point"}
}