{
  "type": "Feature",
  "properties": {
    "addr:full":"1513 McCallie Ferry Rd Soddy Daisy TN 37379",
    "addr:housenumber":"1513",
    "addr:postcode":"37379",
    "addr:street":"Mccallie Ferry Rd",
    "iso:country":"US",
    "sg:address":"1513 McCallie Ferry Rd",
    "sg:city":"Soddy Daisy",
    "sg:classifiers":[
        {
            "category":"Building & Trades",
            "subcategory":"Construction",
            "type":"Services"
        }
    ],
    "sg:phone":"+1 423 332 7300",
    "sg:postcode":"37379",
    "sg:province":"TN",
    "sg:tags":[
        "concrete",
        "contractor"
    ],
    "wof:name":"Concrete Doctor",
    "wof:placetype":"venue"
},
  "geometry": {"coordinates":[-85.080821,35.337358],"type":"Point"}
}