{
  "type": "Feature",
  "properties": {
    "addr:full":"1649 Fort Campbell Blvd Clarksville TN 37042",
    "addr:housenumber":"1649",
    "addr:postcode":"37042",
    "addr:street":"Fort Campbell Blvd",
    "iso:country":"US",
    "sg:address":"1649 Fort Campbell Blvd",
    "sg:city":"Clarksville",
    "sg:classifiers":[
        {
            "category":"Restaurant",
            "type":"Food & Drink"
        }
    ],
    "sg:menulink":"http://www.allmenus.com/tn/clarksville/84313-papa-johns-pizza/menu/",
    "sg:phone":"+1 931 552 7776",
    "sg:postcode":"37042",
    "sg:province":"TN",
    "sg:tags":[
        "american",
        "pizza"
    ],
    "wof:name":"Papa John's Pizza",
    "wof:placetype":"venue"
},
  "geometry": {"coordinates":[-87.408615,36.578691],"type":"Point"}
}