{
  "type": "Feature",
  "properties": {
    "iso:country":"US",
    "sg:address":"9495 Macon Rd",
    "sg:city":"Cordova",
    "sg:classifiers":[
        {
            "category":"Building & Trades",
            "subcategory":"Landscaping Services",
            "type":"Services"
        }
    ],
    "sg:phone":"+1 901 759 9302",
    "sg:postcode":"38016",
    "sg:province":"TN",
    "wof:name":"Ewing Sod Farm",
    "wof:placetype":"venue"
},
  "geometry": {"coordinates":[-89.747829,35.163531],"type":"Point"}
}