{
  "type": "Feature",
  "properties": {
    "iso:country":"US",
    "sg:address":"343 Ellis Ave",
    "sg:city":"Maryville",
    "sg:classifiers":[
        {
            "category":"Education",
            "subcategory":"Special Training",
            "type":"Public Place"
        }
    ],
    "sg:phone":"+1 865 984 6500",
    "sg:postcode":"37804",
    "sg:province":"TN",
    "sg:tags":[
        "program"
    ],
    "wof:name":"Southern Empowerment Project",
    "wof:placetype":"venue"
},
  "geometry": {"coordinates":[-83.967685,35.756366],"type":"Point"}
}