{
  "type": "Feature",
  "properties": {
    "iso:country":"US",
    "sg:address":"6620 Winchester Rd",
    "sg:city":"Memphis",
    "sg:classifiers":[
        {
            "category":"Shopping",
            "subcategory":"Music",
            "type":"Retail Goods"
        }
    ],
    "sg:phone":"+1 901 794 0883",
    "sg:postcode":"38115",
    "sg:province":"TN",
    "wof:name":"Pop Tunes",
    "wof:placetype":"venue"
},
  "geometry": {"coordinates":[-89.84363,35.049582],"type":"Point"}
}