{
  "type": "Feature",
  "properties": {
    "iso:country":"US",
    "sg:address":"5602 W Jefferson Pike",
    "sg:city":"Murfreesboro",
    "sg:classifiers":[
        {
            "category":"Retail",
            "subcategory":"Auto Repair",
            "type":"Services"
        }
    ],
    "sg:phone":"+1 615 459 0110",
    "sg:postcode":"37129",
    "sg:province":"TN",
    "sg:tags":[
        "transmission"
    ],
    "wof:name":"Elite Transmission",
    "wof:placetype":"venue"
},
  "geometry": {"coordinates":[-86.40628599999999,35.977748],"type":"Point"}
}