{
  "type": "Feature",
  "properties": {
    "addr:full":"643 Brochardt Blvd Knoxville TN 37934",
    "addr:housenumber":"643",
    "addr:postcode":"37934",
    "addr:street":"Brochardt Blvd",
    "iso:country":"US",
    "sg:address":"643 Brochardt Blvd",
    "sg:city":"Knoxville",
    "sg:classifiers":[
        {
            "category":"Professional",
            "subcategory":"Management & Consulting",
            "type":"Services"
        }
    ],
    "sg:phone":"+1 865 966 6607",
    "sg:postcode":"37934",
    "sg:province":"TN",
    "sg:tags":[
        "business"
    ],
    "wof:name":"Golf Science Consulting",
    "wof:placetype":"venue"
},
  "geometry": {"coordinates":[-84.213657,35.878921],"type":"Point"}
}