{
  "type": "Feature",
  "properties": {
    "iso:country":"US",
    "sg:address":"183 Underwood Rd",
    "sg:city":"Mc Minnville",
    "sg:classifiers":[
        {
            "category":"Organizations",
            "subcategory":"Religious Organization",
            "type":"Services"
        }
    ],
    "sg:phone":"+1 931 473 2712",
    "sg:postcode":"37110",
    "sg:province":"TN",
    "wof:name":"Chrch Jesus Chrst Lttr Day STS",
    "wof:placetype":"venue"
},
  "geometry": {"coordinates":[-85.79806000000001,35.699482],"type":"Point"}
}