{
  "type": "Feature",
  "properties": {
    "iso:country":"US",
    "sg:address":"15 Water Tank Rd",
    "sg:city":"Summertown",
    "sg:classifiers":[
        {
            "category":"Government",
            "subcategory":"Office",
            "type":"Public Place"
        }
    ],
    "sg:phone":"+1 931 964 4315",
    "sg:postcode":"38483",
    "sg:province":"TN",
    "sg:tags":[
        "govt",
        "city"
    ],
    "wof:name":"Summertown Utility District",
    "wof:placetype":"venue"
},
  "geometry": {"coordinates":[-87.305432,35.43713],"type":"Point"}
}