{
  "type": "Feature",
  "properties": {
    "iso:country":"US",
    "sg:address":"541 Laurel Park Dr",
    "sg:city":"Nashville",
    "sg:classifiers":[
        {
            "category":"Wholesale",
            "subcategory":"Seafood",
            "type":"Manufacturing & Wholesale Goods"
        }
    ],
    "sg:phone":"+1 615 352 5128",
    "sg:postcode":"37205",
    "sg:province":"TN",
    "wof:name":"Dhi International Inc",
    "wof:placetype":"venue"
},
  "geometry": {"coordinates":[-86.893642,36.083283],"type":"Point"}
}