{
  "type": "Feature",
  "properties": {
    "iso:country":"US",
    "sg:address":"401 Gate City Hwy",
    "sg:city":"Bristol",
    "sg:classifiers":[
        {
            "category":"Insurance",
            "subcategory":"Insurance Agent",
            "type":"Services"
        }
    ],
    "sg:phone":"+1 276 466 5521",
    "sg:postcode":"24201",
    "sg:province":"TN",
    "wof:name":"Allstate Insurance",
    "wof:placetype":"venue"
},
  "geometry": {"coordinates":[-82.21580299999999,36.599154],"type":"Point"}
}