{
  "type": "Feature",
  "properties": {
    "addr:full":"1805 Titus Rd Memphis TN 38111",
    "addr:housenumber":"1805",
    "addr:postcode":"38111",
    "addr:street":"Titus Rd",
    "iso:country":"US",
    "sg:address":"1805 Titus Rd",
    "sg:city":"Memphis",
    "sg:classifiers":[
        {
            "category":"Personal",
            "subcategory":"Beauty Salon",
            "type":"Services"
        }
    ],
    "sg:phone":"+1 901 743 4555",
    "sg:postcode":"38111",
    "sg:province":"TN",
    "wof:name":"Abigail's Beauty Salon",
    "wof:placetype":"venue"
},
  "geometry": {"coordinates":[-89.927238,35.082196],"type":"Point"}
}