{
  "type": "Feature",
  "properties": {
    "iso:country":"US",
    "sg:address":"1165 Bates Anderson Rd",
    "sg:city":"Rives",
    "sg:classifiers":[
        {
            "category":"Wholesale",
            "subcategory":"Scrap",
            "type":"Manufacturing & Wholesale Goods"
        }
    ],
    "sg:phone":"+1 731 536 4958",
    "sg:postcode":"38253",
    "sg:province":"TN",
    "sg:tags":[
        "material"
    ],
    "wof:name":"Younger & Sons Salvage",
    "wof:placetype":"venue"
},
  "geometry": {"coordinates":[-89.11900199999999,36.307273],"type":"Point"}
}