{
  "type": "Feature",
  "properties": {
    "addr:full":"1701 Mallory Ln Brentwood TN 37027",
    "addr:housenumber":"1701",
    "addr:postcode":"37027",
    "addr:street":"Mallory Ln",
    "iso:country":"US",
    "sg:address":"1701 Mallory Ln",
    "sg:city":"Brentwood",
    "sg:classifiers":[
        {
            "category":"Shopping",
            "subcategory":"Books",
            "type":"Retail Goods"
        }
    ],
    "sg:phone":"+1 615 377 9979",
    "sg:postcode":"37027",
    "sg:province":"TN",
    "sg:tags":[
        "store"
    ],
    "wof:name":"Barnes & Noble",
    "wof:placetype":"venue"
},
  "geometry": {"coordinates":[-86.81361800000001,35.966544],"type":"Point"}
}