{
  "type": "Feature",
  "properties": {
    "iso:country":"US",
    "sg:address":"210 W Harper Ave",
    "sg:city":"Maryville",
    "sg:classifiers":[
        {
            "category":"Banks & Credit Unions",
            "subcategory":"Bank",
            "type":"Services"
        }
    ],
    "sg:phone":"+1 865 982 3100",
    "sg:postcode":"37801",
    "sg:province":"TN",
    "sg:tags":[
        "loan",
        "company"
    ],
    "wof:name":"World Finance Corporation",
    "wof:placetype":"venue"
},
  "geometry": {"coordinates":[-83.972503,35.755496],"type":"Point"}
}