{
  "type": "Feature",
  "properties": {
    "iso:country":"US",
    "sg:address":"276 S Crest Rd",
    "sg:city":"Chattanooga",
    "sg:classifiers":[
        {
            "category":"Home & Garden",
            "subcategory":"Building Materials",
            "type":"Retail Goods"
        },
        {
            "category":"Building & Trades",
            "subcategory":"Construction",
            "type":"Services"
        }
    ],
    "sg:phone":"+1 423 629 9829",
    "sg:postcode":"37404",
    "sg:province":"TN",
    "sg:tags":[
        "fence-sales",
        "fence",
        "contractor"
    ],
    "wof:name":"Southern Fencing Co",
    "wof:placetype":"venue"
},
  "geometry": {"coordinates":[-85.26849,35.012748],"type":"Point"}
}