{
  "type": "Feature",
  "properties": {
    "iso:country":"US",
    "sg:address":"5022 Yale Rd",
    "sg:city":"Memphis",
    "sg:classifiers":[
        {
            "category":"Real Estate",
            "subcategory":"Real Estate Operator",
            "type":"Services"
        }
    ],
    "sg:phone":"+1 901 386 3538",
    "sg:postcode":"38128",
    "sg:province":"TN",
    "sg:tags":[
        "building",
        "apartment"
    ],
    "wof:name":"Raleigh Village Apartments",
    "wof:placetype":"venue"
},
  "geometry": {"coordinates":[-89.895999,35.221402],"type":"Point"}
}