{
  "type": "Feature",
  "properties": {
    "iso:country":"US",
    "sg:address":"819 Depot St",
    "sg:city":"Paris",
    "sg:classifiers":[
        {
            "category":"Bars & Pubs",
            "type":"Food & Drink"
        }
    ],
    "sg:phone":"+1 731 642 5461",
    "sg:postcode":"38242",
    "sg:province":"TN",
    "sg:tags":[
        "drinking"
    ],
    "wof:name":"Toy's Tavern",
    "wof:placetype":"venue"
},
  "geometry": {"coordinates":[-88.33456200000001,36.303986],"type":"Point"}
}