{
  "type": "Feature",
  "properties": {
    "iso:country":"US",
    "sg:address":"100 Madison St",
    "sg:city":"Shelbyville",
    "sg:classifiers":[
        {
            "category":"Shopping",
            "subcategory":"Pharmacy",
            "type":"Retail Goods"
        }
    ],
    "sg:phone":"+1 931 684 0280",
    "sg:postcode":"37160",
    "sg:province":"TN",
    "sg:tags":[
        "photofinishing",
        "laboratory"
    ],
    "wof:name":"Eckerd",
    "wof:placetype":"venue"
},
  "geometry": {"coordinates":[-86.458162,35.488958],"type":"Point"}
}