{
  "type": "Feature",
  "properties": {
    "iso:country":"US",
    "sg:address":"812 Bradley Pl",
    "sg:city":"Hermitage",
    "sg:classifiers":[
        {
            "category":"Shopping",
            "subcategory":"Discount & Variety Stores",
            "type":"Retail Goods"
        },
        {
            "category":"Shopping",
            "subcategory":"Catalog Store",
            "type":"Retail Goods"
        }
    ],
    "sg:phone":"+1 615 902 9877",
    "sg:postcode":"37076",
    "sg:province":"TN",
    "sg:tags":[
        "mail",
        "sales",
        "order"
    ],
    "wof:name":"G C's Gifts & Treasures",
    "wof:placetype":"venue"
},
  "geometry": {"coordinates":[-86.60211,36.197716],"type":"Point"}
}