{
  "type": "Feature",
  "properties": {
    "iso:country":"US",
    "sg:address":"7415 Gum Puckett Rd",
    "sg:city":"Murfreesboro",
    "sg:classifiers":[
        {
            "category":"Building & Trades",
            "subcategory":"Construction",
            "type":"Services"
        }
    ],
    "sg:phone":"+1 615 895 2927",
    "sg:postcode":"37127",
    "sg:province":"TN",
    "sg:tags":[
        "dry wall",
        "contractor"
    ],
    "wof:name":"David Robinson Drywall",
    "wof:placetype":"venue"
},
  "geometry": {"coordinates":[-86.272096,35.767974],"type":"Point"}
}