{
  "type": "Feature",
  "properties": {
    "iso:country":"US",
    "sg:address":"2248 Howell Ave",
    "sg:city":"Memphis",
    "sg:classifiers":[
        {
            "category":"Real Estate",
            "subcategory":"Real Estate Operator",
            "type":"Services"
        }
    ],
    "sg:phone":"+1 901 272 7946",
    "sg:postcode":"38108",
    "sg:province":"TN",
    "sg:tags":[
        "building",
        "apartment"
    ],
    "wof:name":"Howell Garden Apartments",
    "wof:placetype":"venue"
},
  "geometry": {"coordinates":[-89.983403,35.167336],"type":"Point"}
}