{
  "type": "Feature",
  "properties": {
    "addr:full":"3964 Jackson Ave Memphis TN 38128",
    "addr:housenumber":"3964",
    "addr:postcode":"38128",
    "addr:street":"Jackson Ave",
    "iso:country":"US",
    "sg:address":"3964 Jackson Ave",
    "sg:city":"Memphis",
    "sg:classifiers":[
        {
            "category":"Building & Trades",
            "subcategory":"Equipment Rental",
            "type":"Services"
        }
    ],
    "sg:phone":"+1 901 380 1622",
    "sg:postcode":"38128",
    "sg:province":"TN",
    "sg:tags":[
        "leasing",
        "furniture"
    ],
    "wof:name":"Staton's Rental",
    "wof:placetype":"venue"
},
  "geometry": {"coordinates":[-89.931023,35.185399],"type":"Point"}
}