{
  "type": "Feature",
  "properties": {
    "addr:full":"86 N Front St Memphis TN 38103",
    "addr:housenumber":"86",
    "addr:postcode":"38103",
    "addr:street":"N Front St",
    "iso:country":"US",
    "sg:address":"86 N Front St",
    "sg:city":"Memphis",
    "sg:classifiers":[
        {
            "category":"Parking",
            "type":"Transportation"
        }
    ],
    "sg:phone":"+1 901 521 1271",
    "sg:postcode":"38103",
    "sg:province":"TN",
    "sg:tags":[
        "garage"
    ],
    "wof:name":"Central Parking Systems",
    "wof:placetype":"venue"
},
  "geometry": {"coordinates":[-90.052954,35.148227],"type":"Point"}
}