{
  "type": "Feature",
  "properties": {
    "iso:country":"US",
    "sg:address":"5275 Fort Henry Dr",
    "sg:city":"Kingsport",
    "sg:classifiers":[
        {
            "category":"Personal",
            "subcategory":"Beauty Salon",
            "type":"Services"
        }
    ],
    "sg:phone":"+1 423 239 7868",
    "sg:postcode":"37663",
    "sg:province":"TN",
    "wof:name":"Deanna's Hair Shack",
    "wof:placetype":"venue"
},
  "geometry": {"coordinates":[-82.473086,36.460029],"type":"Point"}
}