{
  "type": "Feature",
  "properties": {
    "addr:full":"2211 Lake Springs Ln Cordova TN 38016",
    "addr:housenumber":"2211",
    "addr:postcode":"38016",
    "addr:street":"Lake Springs Ln",
    "iso:country":"US",
    "sg:address":"2211 Lake Springs Ln",
    "sg:city":"Cordova",
    "sg:classifiers":[
        {
            "category":"Building & Trades",
            "subcategory":"Electrical",
            "type":"Services"
        }
    ],
    "sg:phone":"+1 901 383 6930",
    "sg:postcode":"38016",
    "sg:province":"TN",
    "sg:tags":[
        "electrical",
        "contractor"
    ],
    "wof:name":"Les Electric",
    "wof:placetype":"venue"
},
  "geometry": {"coordinates":[-89.766856,35.18542],"type":"Point"}
}