{
  "type": "Feature",
  "properties": {
    "addr:full":"366 W Main St Hendersonville TN 37075",
    "addr:housenumber":"366",
    "addr:postcode":"37075",
    "addr:street":"W Main St",
    "iso:country":"US",
    "sg:address":"366 W Main St",
    "sg:city":"Hendersonville",
    "sg:classifiers":[
        {
            "category":"Retail",
            "subcategory":"Laundry & Dry Cleaning",
            "type":"Services"
        }
    ],
    "sg:phone":"+1 615 822 2450",
    "sg:postcode":"37075",
    "sg:province":"TN",
    "sg:tags":[
        "cleaners"
    ],
    "wof:name":"Fluff Cleaners Inc",
    "wof:placetype":"venue"
},
  "geometry": {"coordinates":[-86.62832299999999,36.303032],"type":"Point"}
}