{
  "type": "Feature",
  "properties": {
    "iso:country":"US",
    "sg:address":"1734 Southwind Dr",
    "sg:city":"Nashville",
    "sg:classifiers":[
        {
            "category":"Retail",
            "subcategory":"Repair Shop",
            "type":"Services"
        }
    ],
    "sg:phone":"+1 615 365 9923",
    "sg:postcode":"37217",
    "sg:province":"TN",
    "wof:name":"Lagnappe",
    "wof:placetype":"venue"
},
  "geometry": {"coordinates":[-86.664434,36.099367],"type":"Point"}
}