{
  "type": "Feature",
  "properties": {
    "addr:full":"443 W Sullivan St Kingsport TN 37660",
    "addr:housenumber":"443",
    "addr:postcode":"37660",
    "addr:street":"W Sullivan St",
    "iso:country":"US",
    "sg:address":"443 W Sullivan St",
    "sg:city":"Kingsport",
    "sg:classifiers":[
        {
            "category":"Food & Beverages",
            "subcategory":"Groceries & Convenience Stores",
            "type":"Retail Goods"
        }
    ],
    "sg:phone":"+1 423 245 3748",
    "sg:postcode":"37660",
    "sg:province":"TN",
    "sg:tags":[
        "grocer"
    ],
    "wof:name":"White's Fresh Foods",
    "wof:placetype":"venue"
},
  "geometry": {"coordinates":[-82.561599,36.552082],"type":"Point"}
}