{
  "type": "Feature",
  "properties": {
    "addr:full":"130 W Poplar Ave Collierville TN 38017",
    "addr:housenumber":"130",
    "addr:postcode":"38017",
    "addr:street":"W Poplar Ave",
    "iso:country":"US",
    "sg:address":"130 W Poplar Ave",
    "sg:city":"Collierville",
    "sg:classifiers":[
        {
            "category":"Restaurant",
            "type":"Food & Drink"
        }
    ],
    "sg:menulink":"http://www.allmenus.com/tn/collierville/33309-spr:-sekisui-pacific-rim/menu/",
    "sg:phone":"+1 901 850 8423",
    "sg:postcode":"38017",
    "sg:province":"TN",
    "sg:tags":[
        "japanese",
        "asian"
    ],
    "wof:name":"SPR: Sekisui Pacific Rim",
    "wof:placetype":"venue"
},
  "geometry": {"coordinates":[-89.66666600000001,35.04551],"type":"Point"}
}