{
  "type": "Feature",
  "properties": {
    "addr:full":"9908 Kingston Pike Knoxville TN 37922",
    "addr:housenumber":"9908",
    "addr:postcode":"37922",
    "addr:street":"Kingston Pike",
    "iso:country":"US",
    "sg:address":"9908 Kingston Pike",
    "sg:city":"Knoxville",
    "sg:classifiers":[
        {
            "category":"Place Of Worship",
            "subcategory":"Church",
            "type":"Public Place"
        },
        {
            "category":"Place Of Worship",
            "type":"Public Place"
        }
    ],
    "sg:phone":"+1 865 693 0353",
    "sg:postcode":"37922",
    "sg:province":"TN",
    "sg:tags":[
        "churches-united",
        "methodist"
    ],
    "sg:website":"http://www.cclive.org",
    "wof:name":"Cokesbury United Methodist Church",
    "wof:placetype":"venue"
},
  "geometry": {"coordinates":[-84.111531,35.905345],"type":"Point"}
}