{
  "type": "Feature",
  "properties": {
    "iso:country":"US",
    "sg:address":"5251 State Hwy 153",
    "sg:city":"Hixson",
    "sg:classifiers":[
        {
            "category":"Restaurant",
            "type":"Food & Drink"
        }
    ],
    "sg:phone":"+1 423 877 0941",
    "sg:postcode":"37343",
    "sg:province":"TN",
    "sg:tags":[
        "eating"
    ],
    "wof:name":"Subway",
    "wof:placetype":"venue"
},
  "geometry": {"coordinates":[-85.241623,35.126256],"type":"Point"}
}