{
  "type": "Feature",
  "properties": {
    "iso:country":"US",
    "sg:address":"878 New Hope Rd SE",
    "sg:city":"Cleveland",
    "sg:classifiers":[
        {
            "category":"Wholesale",
            "subcategory":"Machinery & Supplies",
            "type":"Manufacturing & Wholesale Goods"
        }
    ],
    "sg:phone":"+1 423 479 1214",
    "sg:postcode":"37323",
    "sg:province":"TN",
    "wof:name":"Craigs Farm Parts",
    "wof:placetype":"venue"
},
  "geometry": {"coordinates":[-84.811665,35.106931],"type":"Point"}
}