{
  "type": "Feature",
  "properties": {
    "iso:country":"US",
    "sg:address":"1406 McCalla Ave",
    "sg:city":"Knoxville",
    "sg:classifiers":[
        {
            "category":"Restaurant",
            "type":"Food & Drink"
        }
    ],
    "sg:phone":"+1 865 524 3288",
    "sg:postcode":"37915",
    "sg:province":"TN",
    "sg:tags":[
        "delicatessen"
    ],
    "wof:name":"Kesha's Market Deli & Lounge",
    "wof:placetype":"venue"
},
  "geometry": {"coordinates":[-83.90904399999999,35.975522],"type":"Point"}
}