{
  "type": "Feature",
  "properties": {
    "iso:country":"US",
    "sg:address":"6955 Charlotte Pike",
    "sg:city":"Nashville",
    "sg:classifiers":[
        {
            "category":"Food & Beverages",
            "subcategory":"Groceries & Convenience Stores",
            "type":"Retail Goods"
        }
    ],
    "sg:phone":"+1 615 352 7060",
    "sg:postcode":"37209",
    "sg:province":"TN",
    "wof:name":"Daily's",
    "wof:placetype":"venue"
},
  "geometry": {"coordinates":[-86.90303400000001,36.129446],"type":"Point"}
}