{
  "type": "Feature",
  "properties": {
    "addr:full":"820 S Main Ave Dyersburg TN 38024",
    "addr:housenumber":"820",
    "addr:postcode":"38024",
    "addr:street":"S Main Ave",
    "iso:country":"US",
    "sg:address":"820 S Main Ave",
    "sg:city":"Dyersburg",
    "sg:classifiers":[
        {
            "category":"Retail",
            "subcategory":"Repair Shop",
            "type":"Services"
        }
    ],
    "sg:phone":"+1 731 285 0685",
    "sg:postcode":"38024",
    "sg:province":"TN",
    "wof:name":"Toombs Upholstery Shop",
    "wof:placetype":"venue"
},
  "geometry": {"coordinates":[-89.391744,36.018556],"type":"Point"}
}