{
  "type": "Feature",
  "properties": {
    "addr:full":"9631 Rhodes Rd Bon Aqua TN 37025",
    "addr:housenumber":"9631",
    "addr:postcode":"37025",
    "addr:street":"Rhodes Rd",
    "iso:country":"US",
    "sg:address":"9631 Rhodes Rd",
    "sg:city":"Bon Aqua",
    "sg:classifiers":[
        {
            "category":"Building & Trades",
            "subcategory":"Landscaping Services",
            "type":"Services"
        }
    ],
    "sg:phone":"+1 931 670 4241",
    "sg:postcode":"37025",
    "sg:province":"TN",
    "sg:tags":[
        "lawn",
        "maintenance",
        "grounds"
    ],
    "wof:name":"Lawn Helpers",
    "wof:placetype":"venue"
},
  "geometry": {"coordinates":[-87.237672,35.908484],"type":"Point"}
}