{
  "type": "Feature",
  "properties": {
    "addr:full":"3983 Nolensville Pike Nashville TN 37211",
    "addr:housenumber":"3983",
    "addr:postcode":"37211",
    "addr:street":"Nolensville Pike",
    "iso:country":"US",
    "sg:address":"3983 Nolensville Pike",
    "sg:city":"Nashville",
    "sg:classifiers":[
        {
            "category":"Shopping",
            "subcategory":"Computers & Home Electronics",
            "type":"Retail Goods"
        }
    ],
    "sg:phone":"+1 615 832 0124",
    "sg:postcode":"37211",
    "sg:province":"TN",
    "sg:tags":[
        "equipment",
        "consumer",
        "electronic",
        "supply"
    ],
    "wof:name":"Radio Shack",
    "wof:placetype":"venue"
},
  "geometry": {"coordinates":[-86.72922800000001,36.085855],"type":"Point"}
}