{
  "type": "Feature",
  "properties": {
    "iso:country":"US",
    "sg:address":"215 S Water Ave",
    "sg:city":"Gallatin",
    "sg:classifiers":[
        {
            "category":"Arts & Performance",
            "subcategory":"Theater",
            "type":"Entertainment"
        }
    ],
    "sg:phone":"+1 615 452 9755",
    "sg:postcode":"37066",
    "sg:province":"TN",
    "sg:tags":[
        "group"
    ],
    "wof:name":"Balloons Clowns & Magic",
    "wof:placetype":"venue"
},
  "geometry": {"coordinates":[-86.445443,36.386015],"type":"Point"}
}