{
  "type": "Feature",
  "properties": {
    "iso:country":"US",
    "sg:address":"1400 Hazelwood Dr",
    "sg:city":"Smyrna",
    "sg:classifiers":[
        {
            "category":"Professional",
            "subcategory":"Employment Agencies",
            "type":"Services"
        }
    ],
    "sg:phone":"+1 615 220 9399",
    "sg:postcode":"37167",
    "sg:province":"TN",
    "sg:tags":[
        "opportunity"
    ],
    "wof:name":"Instaff Personnel",
    "wof:placetype":"venue"
},
  "geometry": {"coordinates":[-86.520673,35.958947],"type":"Point"}
}