{
  "type": "Feature",
  "properties": {
    "iso:country":"US",
    "sg:address":"3369 Acree St",
    "sg:city":"Memphis",
    "sg:classifiers":[
        {
            "category":"Building & Trades",
            "subcategory":"Plumbing",
            "type":"Services"
        }
    ],
    "sg:phone":"+1 901 385 2640",
    "sg:postcode":"38134",
    "sg:province":"TN",
    "sg:tags":[
        "contractor"
    ],
    "wof:name":"J G Herndon",
    "wof:placetype":"venue"
},
  "geometry": {"coordinates":[-89.860568,35.217467],"type":"Point"}
}