{
  "type": "Feature",
  "properties": {
    "iso:country":"US",
    "sg:address":"110 N Main St",
    "sg:city":"Collierville",
    "sg:classifiers":[
        {
            "category":"Wholesale",
            "subcategory":"Apparel",
            "type":"Manufacturing & Wholesale Goods"
        }
    ],
    "sg:phone":"+1 901 850 3451",
    "sg:postcode":"38017",
    "sg:province":"TN",
    "sg:tags":[
        "fur"
    ],
    "wof:name":"Springer's Antiques & Intrs",
    "wof:placetype":"venue"
},
  "geometry": {"coordinates":[-89.66422799999999,35.04293],"type":"Point"}
}