{
  "type": "Feature",
  "properties": {
    "addr:full":"1425 Old Rives Rd Union City TN 38261",
    "addr:housenumber":"1425",
    "addr:postcode":"38261",
    "addr:street":"Old Rives Rd",
    "iso:country":"US",
    "sg:address":"1425 Old Rives Rd",
    "sg:city":"Union City",
    "sg:classifiers":[
        {
            "category":"Wholesale",
            "subcategory":"Auto Parts",
            "type":"Manufacturing & Wholesale Goods"
        }
    ],
    "sg:phone":"+1 731 885 5463",
    "sg:postcode":"38261",
    "sg:province":"TN",
    "wof:name":"NAPA Auto Parts",
    "wof:placetype":"venue"
},
  "geometry": {"coordinates":[-89.071502,36.415175],"type":"Point"}
}