{
  "type": "Feature",
  "properties": {
    "addr:full":"1801 W End Ave Nashville TN 37240",
    "addr:housenumber":"1801",
    "addr:postcode":"37240",
    "addr:street":"W End Ave",
    "iso:country":"US",
    "sg:address":"1801 W End Ave",
    "sg:city":"Nashville",
    "sg:classifiers":[
        {
            "category":"Insurance",
            "subcategory":"Insurance Agent",
            "type":"Services"
        }
    ],
    "sg:phone":"+1 615 322 1600",
    "sg:postcode":"37240",
    "sg:province":"TN",
    "wof:name":"Aetna",
    "wof:placetype":"venue"
},
  "geometry": {"coordinates":[-86.79745,36.1523],"type":"Point"}
}