{
  "type": "Feature",
  "properties": {
    "addr:full":"1048 Old Pinnacle Rd Joelton TN 37080",
    "addr:housenumber":"1048",
    "addr:postcode":"37080",
    "addr:street":"Old Pinnacle Rd",
    "iso:country":"US",
    "sg:address":"1048 Old Pinnacle Rd",
    "sg:city":"Joelton",
    "sg:classifiers":[
        {
            "category":"Manufacturing",
            "subcategory":"Printing",
            "type":"Manufacturing & Wholesale Goods"
        }
    ],
    "sg:phone":"+1 615 746 3342",
    "sg:postcode":"37080",
    "sg:province":"TN",
    "sg:tags":[
        "book"
    ],
    "wof:name":"Old Pinnacle Publishing",
    "wof:placetype":"venue"
},
  "geometry": {"coordinates":[-86.926599,36.330794],"type":"Point"}
}