{
  "type": "Feature",
  "properties": {
    "iso:country":"US",
    "sg:address":"3081 US Hwy 11E",
    "sg:city":"Strawberry Plns",
    "sg:classifiers":[
        {
            "category":"Education",
            "subcategory":"School",
            "type":"Public Place"
        }
    ],
    "sg:phone":"+1 865 933 5313",
    "sg:postcode":"37871",
    "sg:province":"TN",
    "wof:name":"Rush Strong School",
    "wof:placetype":"venue"
},
  "geometry": {"coordinates":[-83.690558,36.05861],"type":"Point"}
}