{
  "type": "Feature",
  "properties": {
    "iso:country":"US",
    "sg:address":"1027 Columbia Ave",
    "sg:city":"Franklin",
    "sg:classifiers":[
        {
            "category":"Professional",
            "subcategory":"Management & Consulting",
            "type":"Services"
        }
    ],
    "sg:phone":"+1 615 599 0130",
    "sg:postcode":"37064",
    "sg:province":"TN",
    "sg:tags":[
        "business"
    ],
    "wof:name":"Automotive Consultants LLC",
    "wof:placetype":"venue"
},
  "geometry": {"coordinates":[-86.872767,35.918768],"type":"Point"}
}