{
  "type": "Feature",
  "properties": {
    "addr:full":"1413 Cline St NW Knoxville TN 37921",
    "addr:housenumber":"1413",
    "addr:postcode":"37921",
    "addr:street":"Cline St Nw",
    "iso:country":"US",
    "sg:address":"1413 Cline St NW",
    "sg:city":"Knoxville",
    "sg:classifiers":[
        {
            "category":"Wholesale",
            "subcategory":"Electrical",
            "type":"Manufacturing & Wholesale Goods"
        }
    ],
    "sg:phone":"+1 865 525 2308",
    "sg:postcode":"37921",
    "sg:province":"TN",
    "sg:tags":[
        "communication",
        "radio",
        "system"
    ],
    "sg:website":"www.mssenger.com",
    "wof:name":"Central Communications",
    "wof:placetype":"venue"
},
  "geometry": {"coordinates":[-83.93444700000001,35.981296],"type":"Point"}
}