{
  "type": "Feature",
  "properties": {
    "addr:full":"3625 Maynardville Hwy Maynardville TN 37807",
    "addr:housenumber":"3625",
    "addr:postcode":"37807",
    "addr:street":"Maynardville Hwy",
    "iso:country":"US",
    "sg:address":"3625 Maynardville Hwy",
    "sg:city":"Maynardville",
    "sg:classifiers":[
        {
            "category":"Autos & Motor Vehicles",
            "subcategory":"Auto Supplies",
            "type":"Retail Goods"
        }
    ],
    "sg:phone":"+1 865 992 9040",
    "sg:postcode":"37807",
    "sg:province":"TN",
    "wof:name":"Body Panels Plus",
    "wof:placetype":"venue"
},
  "geometry": {"coordinates":[-83.816273,36.241722],"type":"Point"}
}