{
  "type": "Feature",
  "properties": {
    "iso:country":"US",
    "sg:address":"1759 W Hwy 25-70",
    "sg:city":"New Market",
    "sg:classifiers":[
        {
            "category":"Wholesale",
            "subcategory":"Auto Parts",
            "type":"Manufacturing & Wholesale Goods"
        }
    ],
    "sg:phone":"+1 865 484 1944",
    "sg:postcode":"37820",
    "sg:province":"TN",
    "sg:tags":[
        "used"
    ],
    "wof:name":"Performance Parts & Sales",
    "wof:placetype":"venue"
},
  "geometry": {"coordinates":[-83.56168599999999,36.021081],"type":"Point"}
}