{
  "type": "Feature",
  "properties": {
    "iso:country":"US",
    "sg:address":"7525 Maynardville Pike",
    "sg:city":"Knoxville",
    "sg:classifiers":[
        {
            "category":"Wholesale",
            "subcategory":"Hardware",
            "type":"Manufacturing & Wholesale Goods"
        },
        {
            "category":"Home & Garden",
            "subcategory":"Garden Supply",
            "type":"Retail Goods"
        },
        {
            "category":"Retail",
            "subcategory":"Repair Shop",
            "type":"Services"
        }
    ],
    "sg:phone":"+1 865 922 9811",
    "sg:postcode":"37938",
    "sg:province":"TN",
    "sg:tags":[
        "renting",
        "lawn",
        "outdoor",
        "power",
        "landscaping",
        "equipment-sales",
        "equipment",
        "saw"
    ],
    "sg:website":"http://www.stihlusa.com/",
    "wof:name":"Hutton Hardware and Hobbies Inc.",
    "wof:placetype":"venue"
},
  "geometry": {"coordinates":[-83.92162999999999,36.090003],"type":"Point"}
}