{
  "type": "Feature",
  "properties": {
    "iso:country":"US",
    "sg:address":"4353 Walnut Hill Dr",
    "sg:city":"Memphis",
    "sg:classifiers":[
        {
            "category":"Shopping",
            "subcategory":"Florist",
            "type":"Retail Goods"
        }
    ],
    "sg:phone":"+1 901 348 9883",
    "sg:postcode":"38109",
    "sg:province":"TN",
    "wof:name":"Futrell Florist",
    "wof:placetype":"venue"
},
  "geometry": {"coordinates":[-90.045089,35.029711],"type":"Point"}
}