{
  "type": "Feature",
  "properties": {
    "addr:full":"357 Dover Rd Clarksville TN 37042",
    "addr:housenumber":"357",
    "addr:postcode":"37042",
    "addr:street":"Dover Rd",
    "iso:country":"US",
    "sg:address":"357 Dover Rd",
    "sg:city":"Clarksville",
    "sg:classifiers":[
        {
            "category":"Health Services",
            "subcategory":"Doctor",
            "type":"Services"
        }
    ],
    "sg:phone":"+1 931 645 2469",
    "sg:postcode":"37042",
    "sg:province":"TN",
    "sg:tags":[
        "dentist"
    ],
    "wof:name":"Linn Norfleet III DDS",
    "wof:placetype":"venue"
},
  "geometry": {"coordinates":[-87.406115,36.550484],"type":"Point"}
}