{
  "type": "Feature",
  "properties": {
    "addr:full":"616 E Lane St Shelbyville TN 37160",
    "addr:housenumber":"616",
    "addr:postcode":"37160",
    "addr:street":"E Lane",
    "iso:country":"US",
    "sg:address":"616 E Lane St",
    "sg:city":"Shelbyville",
    "sg:classifiers":[
        {
            "category":"Personal",
            "subcategory":"Beauty Salon",
            "type":"Services"
        }
    ],
    "sg:phone":"+1 931 684 5155",
    "sg:postcode":"37160",
    "sg:province":"TN",
    "sg:tags":[
        "shop"
    ],
    "wof:name":"Hair Company",
    "wof:placetype":"venue"
},
  "geometry": {"coordinates":[-86.44493,35.485933],"type":"Point"}
}