{
  "type": "Feature",
  "properties": {
    "iso:country":"US",
    "sg:address":"1815 Avon Rd",
    "sg:city":"Murfreesboro",
    "sg:classifiers":[
        {
            "category":"Professional",
            "subcategory":"Management & Consulting",
            "type":"Services"
        }
    ],
    "sg:phone":"+1 615 896 5290",
    "sg:postcode":"37129",
    "sg:province":"TN",
    "wof:name":"Miller Christiana Cemetery",
    "wof:placetype":"venue"
},
  "geometry": {"coordinates":[-86.418547,35.882515],"type":"Point"}
}