{
  "type": "Feature",
  "properties": {
    "iso:country":"US",
    "sg:address":"185 S Center St",
    "sg:city":"Collierville",
    "sg:classifiers":[
        {
            "category":"Professional",
            "type":"Services"
        }
    ],
    "sg:phone":"+1 901 850 3962",
    "sg:postcode":"38017",
    "sg:province":"TN",
    "sg:tags":[
        "establishment"
    ],
    "wof:name":"Careercurrnacy",
    "wof:placetype":"venue"
},
  "geometry": {"coordinates":[-89.665795,35.041206],"type":"Point"}
}