{
  "type": "Feature",
  "properties": {
    "iso:country":"US",
    "sg:address":"1109 Farris Dr",
    "sg:city":"Knoxville",
    "sg:classifiers":[
        {
            "category":"Building & Trades",
            "subcategory":"Landscaping Services",
            "type":"Services"
        }
    ],
    "sg:phone":"+1 865 688 0633",
    "sg:postcode":"37912",
    "sg:province":"TN",
    "sg:tags":[
        "landscape"
    ],
    "wof:name":"A A A Egle Ldscp Lwncare HM RE",
    "wof:placetype":"venue"
},
  "geometry": {"coordinates":[-83.976276,35.999013],"type":"Point"}
}