{
  "type": "Feature",
  "properties": {
    "iso:country":"US",
    "sg:address":"2510 Peres Ave",
    "sg:city":"Memphis",
    "sg:classifiers":[
        {
            "category":"Building & Trades",
            "subcategory":"Cleaning & Sanitation",
            "type":"Services"
        }
    ],
    "sg:phone":"+1 901 458 4558",
    "sg:postcode":"38108",
    "sg:province":"TN",
    "sg:tags":[
        "janitor"
    ],
    "wof:name":"WIL Clean Enterprise",
    "wof:placetype":"venue"
},
  "geometry": {"coordinates":[-89.97294599999999,35.17782],"type":"Point"}
}