{
  "type": "Feature",
  "properties": {
    "iso:country":"US",
    "sg:address":"6348 Bardstown Rd",
    "sg:city":"Memphis",
    "sg:classifiers":[
        {
            "category":"Banks & Credit Unions",
            "subcategory":"Investment Brokerage",
            "type":"Services"
        }
    ],
    "sg:phone":"+1 901 382 0509",
    "sg:postcode":"38134",
    "sg:province":"TN",
    "sg:tags":[
        "advisory",
        "financial"
    ],
    "wof:name":"Lee's Marketing Concepts",
    "wof:placetype":"venue"
},
  "geometry": {"coordinates":[-89.849478,35.208155],"type":"Point"}
}