{
  "type": "Feature",
  "properties": {
    "addr:full":"1216 Dickerson Rd Goodlettsville TN 37072",
    "addr:housenumber":"1216",
    "addr:postcode":"37072",
    "addr:street":"Dickerson Rd",
    "iso:country":"US",
    "sg:address":"1216 Dickerson Rd",
    "sg:city":"Goodlettsville",
    "sg:classifiers":[
        {
            "category":"Building & Trades",
            "subcategory":"Construction",
            "type":"Services"
        }
    ],
    "sg:phone":"+1 615 456 3492",
    "sg:postcode":"37072",
    "sg:province":"TN",
    "sg:tags":[
        "roofing",
        "contractor"
    ],
    "wof:name":"J & J Roofing & Remodeling",
    "wof:placetype":"venue"
},
  "geometry": {"coordinates":[-86.724689,36.296814],"type":"Point"}
}