{
  "type": "Feature",
  "properties": {
    "iso:country":"US",
    "sg:address":"60 Fairfield Ave",
    "sg:city":"Nashville",
    "sg:classifiers":[
        {
            "category":"Education",
            "subcategory":"School",
            "type":"Public Place"
        }
    ],
    "sg:phone":"+1 615 291 6400",
    "sg:postcode":"37210",
    "sg:province":"TN",
    "wof:name":"Napier Elementary School",
    "wof:placetype":"venue"
},
  "geometry": {"coordinates":[-86.75739799999999,36.149077],"type":"Point"}
}