{
  "type": "Feature",
  "properties": {
    "iso:country":"US",
    "sg:address":"201 Center Park Dr",
    "sg:city":"Knoxville",
    "sg:classifiers":[
        {
            "category":"Health Services",
            "subcategory":"Clinic",
            "type":"Services"
        }
    ],
    "sg:phone":"+1 865 966 2273",
    "sg:postcode":"37922",
    "sg:province":"TN",
    "sg:tags":[
        "home"
    ],
    "wof:name":"Home Care Equipment",
    "wof:placetype":"venue"
},
  "geometry": {"coordinates":[-84.121267,35.907169],"type":"Point"}
}