{
  "type": "Feature",
  "properties": {
    "iso:country":"US",
    "sg:address":"189 W University Pkwy",
    "sg:city":"Jackson",
    "sg:classifiers":[
        {
            "category":"Restaurant",
            "type":"Food & Drink"
        }
    ],
    "sg:phone":"+1 731 664 6150",
    "sg:postcode":"38305",
    "sg:province":"TN",
    "sg:website":"www.popeyes.com",
    "wof:name":"Popeye's Chicken & Biscuits",
    "wof:placetype":"venue"
},
  "geometry": {"coordinates":[-88.83745999999999,35.696147],"type":"Point"}
}