{
  "type": "Feature",
  "properties": {
    "iso:country":"US",
    "sg:address":"1660 Locke Rd",
    "sg:city":"Millington",
    "sg:classifiers":[
        {
            "category":"Real Estate",
            "subcategory":"Developer",
            "type":"Services"
        }
    ],
    "sg:phone":"+1 901 876 6063",
    "sg:postcode":"38053",
    "sg:province":"TN",
    "sg:tags":[
        "development",
        "land"
    ],
    "wof:name":"Negelein Development and Cnstr",
    "wof:placetype":"venue"
},
  "geometry": {"coordinates":[-90.00724099999999,35.301974],"type":"Point"}
}