{
  "type": "Feature",
  "properties": {
    "iso:country":"US",
    "sg:address":"3101 Charlotte Ave",
    "sg:city":"Nashville",
    "sg:classifiers":[
        {
            "category":"Retail",
            "subcategory":"Laundry & Dry Cleaning",
            "type":"Services"
        }
    ],
    "sg:phone":"+1 615 320 5575",
    "sg:postcode":"37209",
    "sg:province":"TN",
    "sg:tags":[
        "linen",
        "supply"
    ],
    "sg:website":"www.nationallinen.com",
    "wof:name":"National Linen & Uniform Svc",
    "wof:placetype":"venue"
},
  "geometry": {"coordinates":[-86.822525,36.153038],"type":"Point"}
}