{
  "type": "Feature",
  "properties": {
    "iso:country":"US",
    "sg:address":"108 Polk Rd",
    "sg:city":"Dyersburg",
    "sg:classifiers":[
        {
            "category":"Building & Trades",
            "subcategory":"Landscaping Services",
            "type":"Services"
        }
    ],
    "sg:phone":"+1 731 285 2150",
    "sg:postcode":"38024",
    "sg:province":"TN",
    "wof:name":"Allens Mowing Service",
    "wof:placetype":"venue"
},
  "geometry": {"coordinates":[-89.262552,36.027032],"type":"Point"}
}