{
  "type": "Feature",
  "properties": {
    "iso:country":"US",
    "sg:address":"608 S James Campbell Blvd",
    "sg:city":"Columbia",
    "sg:classifiers":[
        {
            "category":"Wholesale",
            "subcategory":"Machinery & Supplies",
            "type":"Manufacturing & Wholesale Goods"
        }
    ],
    "sg:phone":"+1 931 490 9777",
    "sg:postcode":"38401",
    "sg:province":"TN",
    "sg:tags":[
        "equipment",
        "establishment"
    ],
    "wof:name":"Hair City Beauty Supply",
    "wof:placetype":"venue"
},
  "geometry": {"coordinates":[-87.051905,35.593191],"type":"Point"}
}