{
  "type": "Feature",
  "properties": {
    "iso:country":"US",
    "sg:address":"9330 Park West Blvd",
    "sg:city":"Knoxville",
    "sg:classifiers":[
        {
            "category":"Health Services",
            "subcategory":"Doctor",
            "type":"Services"
        }
    ],
    "sg:phone":"+1 865 560 0703",
    "sg:postcode":"37923",
    "sg:province":"TN",
    "sg:tags":[
        "physician",
        "surgeon"
    ],
    "wof:name":"Southeast Gynecologic Oncology",
    "wof:placetype":"venue"
},
  "geometry": {"coordinates":[-84.100858,35.917849],"type":"Point"}
}