{
  "type": "Feature",
  "properties": {
    "iso:country":"US",
    "sg:address":"932 Buffalo Trl",
    "sg:city":"Morristown",
    "sg:classifiers":[
        {
            "category":"Retail",
            "subcategory":"Auto Repair",
            "type":"Services"
        }
    ],
    "sg:phone":"+1 423 581 2670",
    "sg:postcode":"37814",
    "sg:province":"TN",
    "sg:tags":[
        "repairing",
        "automobile",
        "radiator"
    ],
    "wof:name":"King's Radiator Shop",
    "wof:placetype":"venue"
},
  "geometry": {"coordinates":[-83.296357,36.223249],"type":"Point"}
}