{
  "type": "Feature",
  "properties": {
    "iso:country":"US",
    "sg:address":"212 N Boyers Ave",
    "sg:city":"Gallatin",
    "sg:classifiers":[
        {
            "category":"Real Estate",
            "subcategory":"Real Estate Operator",
            "type":"Services"
        }
    ],
    "sg:phone":"+1 615 451 9008",
    "sg:postcode":"37066",
    "sg:province":"TN",
    "sg:tags":[
        "building",
        "apartment"
    ],
    "wof:name":"Crestwood Towers",
    "wof:placetype":"venue"
},
  "geometry": {"coordinates":[-86.445319,36.391171],"type":"Point"}
}