{
  "type": "Feature",
  "properties": {
    "iso:country":"US",
    "sg:address":"1118 Johns Branch Rd",
    "sg:city":"Gatlinburg",
    "sg:classifiers":[
        {
            "category":"Professional",
            "subcategory":"Business Services",
            "type":"Services"
        }
    ],
    "sg:phone":"+1 865 430 9038",
    "sg:postcode":"37738",
    "sg:province":"TN",
    "wof:name":"Tin Man",
    "wof:placetype":"venue"
},
  "geometry": {"coordinates":[-83.45922299999999,35.745487],"type":"Point"}
}