{
  "type": "Feature",
  "properties": {
    "addr:full":"2078 York Ave Memphis TN 38104",
    "addr:housenumber":"2078",
    "addr:postcode":"38104",
    "addr:street":"York Ave",
    "iso:country":"US",
    "sg:address":"2078 York Ave",
    "sg:city":"Memphis",
    "sg:classifiers":[
        {
            "category":"Manufacturing",
            "subcategory":"Printing",
            "type":"Manufacturing & Wholesale Goods"
        }
    ],
    "sg:phone":"+1 901 276 6912",
    "sg:postcode":"38104",
    "sg:province":"TN",
    "sg:tags":[
        "printer"
    ],
    "sg:website":"www.blueprinters.com",
    "wof:name":"Blueprint Specialties",
    "wof:placetype":"venue"
},
  "geometry": {"coordinates":[-89.99118,35.125158],"type":"Point"}
}