{
  "type": "Feature",
  "properties": {
    "addr:full":"625 Apple Blossom Ln Morristown TN 37814",
    "addr:housenumber":"625",
    "addr:postcode":"37814",
    "addr:street":"Apple Blossom Ln",
    "iso:country":"US",
    "sg:address":"625 Apple Blossom Ln",
    "sg:city":"Morristown",
    "sg:classifiers":[
        {
            "category":"Restaurant",
            "type":"Food & Drink"
        }
    ],
    "sg:phone":"+1 423 318 0066",
    "sg:postcode":"37814",
    "sg:province":"TN",
    "sg:tags":[
        "eating"
    ],
    "wof:name":"Gourmet Artiste Catrg & Fd Svc",
    "wof:placetype":"venue"
},
  "geometry": {"coordinates":[-83.25705499999999,36.232887],"type":"Point"}
}