{
  "type": "Feature",
  "properties": {
    "iso:country":"US",
    "sg:address":"101 E Stratton Ave",
    "sg:city":"Monterey",
    "sg:classifiers":[
        {
            "category":"Autos & Motor Vehicles",
            "subcategory":"Fuel & Gas Station",
            "type":"Retail Goods"
        }
    ],
    "sg:phone":"+1 931 839 3568",
    "sg:postcode":"38574",
    "sg:province":"TN",
    "sg:tags":[
        "oil"
    ],
    "wof:name":"BP Market",
    "wof:placetype":"venue"
},
  "geometry": {"coordinates":[-85.272091,36.144849],"type":"Point"}
}