{
  "type": "Feature",
  "properties": {
    "iso:country":"US",
    "sg:address":"4521 Trousdale Dr",
    "sg:city":"Nashville",
    "sg:classifiers":[
        {
            "category":"Real Estate",
            "subcategory":"Real Estate Agent",
            "type":"Services"
        }
    ],
    "sg:phone":"+1 615 333 9500",
    "sg:postcode":"37220",
    "sg:province":"TN",
    "sg:tags":[
        "investment"
    ],
    "wof:name":"Mertech Development Corp",
    "wof:placetype":"venue"
},
  "geometry": {"coordinates":[-86.754525,36.086095],"type":"Point"}
}