{
  "type": "Feature",
  "properties": {
    "addr:full":"766 S Highland St Memphis TN 38111",
    "addr:housenumber":"766",
    "addr:postcode":"38111",
    "addr:street":"S Highland St",
    "iso:country":"US",
    "sg:address":"766 S Highland St",
    "sg:city":"Memphis",
    "sg:classifiers":[
        {
            "category":"Organizations",
            "subcategory":"Non-profit Organization",
            "type":"Services"
        }
    ],
    "sg:phone":"+1 901 323 2211",
    "sg:postcode":"38111",
    "sg:province":"TN",
    "wof:name":"YWCA",
    "wof:placetype":"venue"
},
  "geometry": {"coordinates":[-89.94587,35.110323],"type":"Point"}
}