{
  "type": "Feature",
  "properties": {
    "iso:country":"US",
    "sg:address":"337 McClures Bend Ln",
    "sg:city":"Carthage",
    "sg:classifiers":[
        {
            "category":"Autos & Motor Vehicles",
            "subcategory":"Auto Supplies",
            "type":"Retail Goods"
        }
    ],
    "sg:phone":"+1 615 774 3230",
    "sg:postcode":"37030",
    "sg:province":"TN",
    "sg:tags":[
        "tire"
    ],
    "wof:name":"Powell's Tire Store",
    "wof:placetype":"venue"
},
  "geometry": {"coordinates":[-85.90265,36.284352],"type":"Point"}
}