{
  "type": "Feature",
  "properties": {
    "addr:full":"1184 Channel Ave Memphis TN 38113",
    "addr:housenumber":"1184",
    "addr:postcode":"38113",
    "addr:street":"Channel Ave",
    "iso:country":"US",
    "sg:address":"1184 Channel Ave",
    "sg:city":"Memphis",
    "sg:classifiers":[
        {
            "category":"Manufacturing",
            "subcategory":"Textiles",
            "type":"Manufacturing & Wholesale Goods"
        }
    ],
    "sg:phone":"+1 901 948 4469",
    "sg:postcode":"38113",
    "sg:province":"TN",
    "sg:tags":[
        "processing",
        "cotton"
    ],
    "wof:name":"Jones Fiber Products",
    "wof:placetype":"venue"
},
  "geometry": {"coordinates":[-90.094375,35.104075],"type":"Point"}
}