{
  "type": "Feature",
  "properties": {
    "iso:country":"US",
    "sg:address":"240 Rockland Rd",
    "sg:city":"Hendersonville",
    "sg:classifiers":[
        {
            "category":"Professional",
            "type":"Services"
        }
    ],
    "sg:phone":"+1 615 822 4549",
    "sg:postcode":"37075",
    "sg:province":"TN",
    "wof:name":"David Lovell P H D",
    "wof:placetype":"venue"
},
  "geometry": {"coordinates":[-86.63944499999999,36.300962],"type":"Point"}
}