{
  "type": "Feature",
  "properties": {
    "addr:full":"3451 Austin Peay Hwy Memphis TN 38135",
    "addr:housenumber":"3451",
    "addr:postcode":"38135",
    "addr:street":"Austin Peay Hwy",
    "iso:country":"US",
    "sg:address":"3451 Austin Peay Hwy",
    "sg:city":"Memphis",
    "sg:classifiers":[
        {
            "category":"Personal",
            "subcategory":"Beauty Salon",
            "type":"Services"
        }
    ],
    "sg:phone":"+1 901 379 0055",
    "sg:postcode":"38135",
    "sg:province":"TN",
    "sg:tags":[
        "shop"
    ],
    "wof:name":"Hair Inc III",
    "wof:placetype":"venue"
},
  "geometry": {"coordinates":[-89.910364,35.220028],"type":"Point"}
}