{
  "type": "Feature",
  "properties": {
    "iso:country":"US",
    "sg:address":"535 Love Rd",
    "sg:city":"Friendsville",
    "sg:classifiers":[
        {
            "category":"Retail",
            "subcategory":"Auto Repair",
            "type":"Services"
        }
    ],
    "sg:phone":"+1 865 995 2071",
    "sg:postcode":"37737",
    "sg:province":"TN",
    "sg:tags":[
        "automotive",
        "wrecker",
        "general"
    ],
    "wof:name":"Bill's Bug Shop Auto Repairing",
    "wof:placetype":"venue"
},
  "geometry": {"coordinates":[-84.139199,35.743597],"type":"Point"}
}