{
  "type": "Feature",
  "properties": {
    "addr:full":"600 Athens Pike Etowah TN 37331",
    "addr:housenumber":"600",
    "addr:postcode":"37331",
    "addr:street":"Athens Pike",
    "iso:country":"US",
    "sg:address":"600 Athens Pike",
    "sg:city":"Etowah",
    "sg:classifiers":[
        {
            "category":"Organizations",
            "subcategory":"Community Association",
            "type":"Services"
        }
    ],
    "sg:phone":"+1 423 263 2966",
    "sg:postcode":"37331",
    "sg:province":"TN",
    "wof:name":"Interntnal Assn of Lions Clubs",
    "wof:placetype":"venue"
},
  "geometry": {"coordinates":[-84.52732899999999,35.338163],"type":"Point"}
}