{
  "type": "Feature",
  "properties": {
    "addr:full":"113 23rd Ave N Nashville TN 37203",
    "addr:housenumber":"113",
    "addr:postcode":"37203",
    "addr:street":"23Rd Ave N",
    "iso:country":"US",
    "sg:address":"113 23rd Ave N",
    "sg:city":"Nashville",
    "sg:classifiers":[
        {
            "category":"Health Services",
            "subcategory":"Doctor",
            "type":"Services"
        }
    ],
    "sg:phone":"+1 615 829 8158",
    "sg:postcode":"37203",
    "sg:province":"TN",
    "sg:tags":[
        "dentist",
        "dentists-pediatric",
        "dentistry"
    ],
    "sg:website":"http://www.realpagessites.com/creativedentistrypc",
    "wof:name":"Creative Dentistry PC",
    "wof:placetype":"venue"
},
  "geometry": {"coordinates":[-86.805348,36.1499],"type":"Point"}
}