{
  "type": "Feature",
  "properties": {
    "iso:country":"US",
    "sg:address":"2579 N 9th Ave",
    "sg:city":"Humboldt",
    "sg:classifiers":[
        {
            "category":"Manufacturing",
            "subcategory":"Metals",
            "type":"Manufacturing & Wholesale Goods"
        }
    ],
    "sg:phone":"+1 731 784 6401",
    "sg:postcode":"38343",
    "sg:province":"TN",
    "sg:tags":[
        "fabrication",
        "welding"
    ],
    "wof:name":"J & S Welding Machine Service",
    "wof:placetype":"venue"
},
  "geometry": {"coordinates":[-88.92184399999999,35.837331],"type":"Point"}
}