{
  "type": "Feature",
  "properties": {
    "iso:country":"US",
    "sg:address":"6475 Fairview Rd",
    "sg:city":"Hixson",
    "sg:classifiers":[
        {
            "category":"Manufacturing",
            "subcategory":"Textiles",
            "type":"Manufacturing & Wholesale Goods"
        }
    ],
    "sg:phone":"+1 423 842 4264",
    "sg:postcode":"37343",
    "sg:province":"TN",
    "wof:name":"Danny Smith Sales Inc",
    "wof:placetype":"venue"
},
  "geometry": {"coordinates":[-85.19483700000001,35.149147],"type":"Point"}
}