{
  "type": "Feature",
  "properties": {
    "iso:country":"US",
    "sg:address":"8213 Daisy Dallas Rd",
    "sg:city":"Hixson",
    "sg:classifiers":[
        {
            "category":"Retail",
            "subcategory":"Auto Repair",
            "type":"Services"
        }
    ],
    "sg:phone":"+1 423 843 0304",
    "sg:postcode":"37343",
    "sg:province":"TN",
    "sg:tags":[
        "body"
    ],
    "wof:name":"North Hixson Collision Center",
    "wof:placetype":"venue"
},
  "geometry": {"coordinates":[-85.15998999999999,35.201975],"type":"Point"}
}