{
  "type": "Feature",
  "properties": {
    "iso:country":"US",
    "sg:address":"923 Indian Creek Rd",
    "sg:city":"Cumberland Furnace",
    "sg:classifiers":[
        {
            "category":"Retail",
            "subcategory":"Animal Services",
            "type":"Services"
        }
    ],
    "sg:phone":"+1 931 387 4942",
    "sg:postcode":"37051",
    "sg:province":"TN",
    "wof:name":"C&L Stables",
    "wof:placetype":"venue"
},
  "geometry": {"coordinates":[-87.404507,36.330757],"type":"Point"}
}