{
  "type": "Feature",
  "properties": {
    "iso:country":"US",
    "sg:address":"3666 Sweethome Rd",
    "sg:city":"Ashland City",
    "sg:classifiers":[
        {
            "category":"Restaurant",
            "type":"Food & Drink"
        }
    ],
    "sg:phone":"+1 615 643 4302",
    "sg:postcode":"37015",
    "sg:province":"TN",
    "wof:name":"Highway 41 Cafe",
    "wof:placetype":"venue"
},
  "geometry": {"coordinates":[-87.07414300000001,36.360266],"type":"Point"}
}