{
  "type": "Feature",
  "properties": {
    "iso:country":"US",
    "sg:address":"3343 Perimeter Hill Dr",
    "sg:city":"Nashville",
    "sg:classifiers":[
        {
            "category":"Insurance",
            "subcategory":"Insurance Agent",
            "type":"Services"
        }
    ],
    "sg:phone":"+1 615 831 5003",
    "sg:postcode":"37211",
    "sg:province":"TN",
    "wof:name":"Brooke Insurance",
    "wof:placetype":"venue"
},
  "geometry": {"coordinates":[-86.693163,36.08483],"type":"Point"}
}