{
  "type": "Feature",
  "properties": {
    "iso:country":"US",
    "sg:address":"321 W Market St",
    "sg:city":"Bolivar",
    "sg:classifiers":[
        {
            "category":"Home & Garden",
            "subcategory":"Furniture",
            "type":"Retail Goods"
        }
    ],
    "sg:phone":"+1 731 658 9250",
    "sg:postcode":"38008",
    "sg:province":"TN",
    "sg:tags":[
        "appliance"
    ],
    "wof:name":"Freeman Furniture",
    "wof:placetype":"venue"
},
  "geometry": {"coordinates":[-88.991381,35.256177],"type":"Point"}
}