{
  "type": "Feature",
  "properties": {
    "iso:country":"US",
    "sg:address":"8214 Old Pond Creek Rd",
    "sg:city":"Pegram",
    "sg:classifiers":[
        {
            "category":"Communications",
            "subcategory":"Radio Station",
            "type":"Services"
        }
    ],
    "sg:phone":"+1 615 352 1569",
    "sg:postcode":"37143",
    "sg:province":"TN",
    "sg:tags":[
        "broadcast"
    ],
    "wof:name":"W Y Y B FM",
    "wof:placetype":"venue"
},
  "geometry": {"coordinates":[-86.986006,36.130116],"type":"Point"}
}