{
  "type": "Feature",
  "properties": {
    "iso:country":"US",
    "sg:address":"2003 Gallatin Pike N",
    "sg:city":"Madison",
    "sg:classifiers":[
        {
            "category":"Real Estate",
            "subcategory":"Developer",
            "type":"Services"
        }
    ],
    "sg:phone":"+1 615 859 6103",
    "sg:postcode":"37115",
    "sg:province":"TN",
    "sg:tags":[
        "broker"
    ],
    "wof:name":"Action Investment Realtors",
    "wof:placetype":"venue"
},
  "geometry": {"coordinates":[-86.694368,36.301143],"type":"Point"}
}