{
  "type": "Feature",
  "properties": {
    "iso:country":"US",
    "sg:address":"1602 Polkwright Ln",
    "sg:city":"Knoxville",
    "sg:classifiers":[
        {
            "category":"Building & Trades",
            "subcategory":"Landscaping Services",
            "type":"Services"
        }
    ],
    "sg:phone":"+1 865 588 3020",
    "sg:postcode":"37919",
    "sg:province":"TN",
    "wof:name":"Patterson Landscape",
    "wof:placetype":"venue"
},
  "geometry": {"coordinates":[-83.995435,35.908925],"type":"Point"}
}