{
  "type": "Feature",
  "properties": {
    "iso:country":"US",
    "sg:address":"658 Semmes St",
    "sg:city":"Memphis",
    "sg:classifiers":[
        {
            "category":"Social Services",
            "subcategory":"Child Care",
            "type":"Services"
        }
    ],
    "sg:phone":"+1 901 458 4077",
    "sg:postcode":"38111",
    "sg:province":"TN",
    "sg:tags":[
        "day"
    ],
    "wof:name":"All About Kids",
    "wof:placetype":"venue"
},
  "geometry": {"coordinates":[-89.961123,35.115449],"type":"Point"}
}