{
  "type": "Feature",
  "properties": {
    "iso:country":"US",
    "sg:address":"730 Airport Rd",
    "sg:city":"Sparta",
    "sg:classifiers":[
        {
            "category":"Autos & Motor Vehicles",
            "subcategory":"Automobile Sales",
            "type":"Retail Goods"
        }
    ],
    "sg:phone":"+1 931 738 3939",
    "sg:postcode":"38583",
    "sg:province":"TN",
    "sg:tags":[
        "aircraft"
    ],
    "wof:name":"Bill Austin Aircraft & Yacht",
    "wof:placetype":"venue"
},
  "geometry": {"coordinates":[-85.52558999999999,36.055551],"type":"Point"}
}