{
  "type": "Feature",
  "properties": {
    "addr:full":"2638 Parkway Pigeon Forge TN 37863",
    "addr:housenumber":"2638",
    "addr:postcode":"37863",
    "addr:street":"Parkway",
    "iso:country":"US",
    "sg:address":"2638 Parkway",
    "sg:city":"Pigeon Forge",
    "sg:classifiers":[
        {
            "category":"Professional",
            "type":"Services"
        }
    ],
    "sg:phone":"+1 865 906 9088",
    "sg:postcode":"37863",
    "sg:province":"TN",
    "sg:tags":[
        "establishment"
    ],
    "wof:name":"Tyme Traveler",
    "wof:placetype":"venue"
},
  "geometry": {"coordinates":[-83.57462700000001,35.803493],"type":"Point"}
}