{
  "type": "Feature",
  "properties": {
    "iso:country":"US",
    "sg:address":"1440 Falcon Dr SE",
    "sg:city":"Cleveland",
    "sg:classifiers":[
        {
            "category":"Retail",
            "subcategory":"Auto Repair",
            "type":"Services"
        }
    ],
    "sg:phone":"+1 423 472 3857",
    "sg:postcode":"37323",
    "sg:province":"TN",
    "sg:tags":[
        "general"
    ],
    "wof:name":"Family Tire & Auto Service",
    "wof:placetype":"venue"
},
  "geometry": {"coordinates":[-84.87196900000001,35.112181],"type":"Point"}
}