{
  "type": "Feature",
  "properties": {
    "iso:country":"US",
    "sg:address":"403 Cambridge Rd",
    "sg:city":"Lebanon",
    "sg:classifiers":[
        {
            "category":"Food & Beverages",
            "subcategory":"Groceries & Convenience Stores",
            "type":"Retail Goods"
        }
    ],
    "sg:phone":"+1 615 444 1279",
    "sg:postcode":"37087",
    "sg:province":"TN",
    "wof:name":"Tennessee Flea Market",
    "wof:placetype":"venue"
},
  "geometry": {"coordinates":[-86.361831,36.219493],"type":"Point"}
}