{
  "type": "Feature",
  "properties": {
    "addr:full":"4312 Ringgold Rd Chattanooga TN 37412",
    "addr:housenumber":"4312",
    "addr:postcode":"37412",
    "addr:street":"Ringgold Rd",
    "iso:country":"US",
    "sg:address":"4312 Ringgold Rd",
    "sg:city":"Chattanooga",
    "sg:classifiers":[
        {
            "category":"Manufacturing",
            "subcategory":"Paper Products",
            "type":"Manufacturing & Wholesale Goods"
        },
        {
            "category":"Shopping",
            "subcategory":"Gifts & Souvenirs",
            "type":"Retail Goods"
        }
    ],
    "sg:phone":"+1 423 629 2300",
    "sg:postcode":"37412",
    "sg:province":"TN",
    "sg:tags":[
        "stationery",
        "announcement",
        "invitation",
        "mfg"
    ],
    "wof:name":"D's What When & Where",
    "wof:placetype":"venue"
},
  "geometry": {"coordinates":[-85.239931,34.996182],"type":"Point"}
}