{
  "type": "Feature",
  "properties": {
    "iso:country":"US",
    "sg:address":"215 Baker Rd",
    "sg:city":"Huntingdon",
    "sg:classifiers":[
        {
            "category":"Communications",
            "subcategory":"Radio Station",
            "type":"Services"
        }
    ],
    "sg:phone":"+1 731 986 0242",
    "sg:postcode":"38344",
    "sg:province":"TN",
    "sg:tags":[
        "company",
        "broadcasting"
    ],
    "wof:name":"WVHR",
    "wof:placetype":"venue"
},
  "geometry": {"coordinates":[-88.463909,35.951131],"type":"Point"}
}