{
  "type": "Feature",
  "properties": {
    "addr:full":"14905 Lebanon Rd Old Hickory TN 37138",
    "addr:housenumber":"14905",
    "addr:postcode":"37138",
    "addr:street":"Lebanon Rd",
    "iso:country":"US",
    "sg:address":"14905 Lebanon Rd",
    "sg:city":"Old Hickory",
    "sg:classifiers":[
        {
            "category":"Building & Trades",
            "subcategory":"Construction",
            "type":"Services"
        }
    ],
    "sg:phone":"+1 615 754 8619",
    "sg:postcode":"37138",
    "sg:province":"TN",
    "sg:tags":[
        "hanging",
        "painter",
        "contractor"
    ],
    "wof:name":"Paradign Painting LLC",
    "wof:placetype":"venue"
},
  "geometry": {"coordinates":[-86.575292,36.218479],"type":"Point"}
}