{
  "type": "Feature",
  "properties": {
    "iso:country":"US",
    "sg:address":"1701 18th Ave S",
    "sg:city":"Nashville",
    "sg:classifiers":[
        {
            "category":"Professional",
            "subcategory":"Management & Consulting",
            "type":"Services"
        }
    ],
    "sg:phone":"+1 615 460 9898",
    "sg:postcode":"37212",
    "sg:province":"TN",
    "wof:name":"Sandra W Churchill",
    "wof:placetype":"venue"
},
  "geometry": {"coordinates":[-86.797067,36.136516],"type":"Point"}
}