{
  "type": "Feature",
  "properties": {
    "iso:country":"US",
    "sg:address":"1911 McDade Ln",
    "sg:city":"Chattanooga",
    "sg:classifiers":[
        {
            "category":"Banks & Credit Unions",
            "subcategory":"Financial Services",
            "type":"Services"
        }
    ],
    "sg:phone":"+1 423 265 7575",
    "sg:postcode":"37405",
    "sg:province":"TN",
    "sg:tags":[
        "trust",
        "investment",
        "real estate"
    ],
    "wof:name":"Nancy LP",
    "wof:placetype":"venue"
},
  "geometry": {"coordinates":[-85.289732,35.082706],"type":"Point"}
}