{
  "type": "Feature",
  "properties": {
    "iso:country":"US",
    "sg:address":"1437 Norris Rd",
    "sg:city":"Memphis",
    "sg:classifiers":[
        {
            "category":"Organizations",
            "subcategory":"Religious Organization",
            "type":"Services"
        }
    ],
    "sg:phone":"+1 901 942 0847",
    "sg:postcode":"38106",
    "sg:province":"TN",
    "wof:name":"Norris Ave Missionary Baptist",
    "wof:placetype":"venue"
},
  "geometry": {"coordinates":[-90.0159,35.083212],"type":"Point"}
}