{
  "type": "Feature",
  "properties": {
    "iso:country":"US",
    "sg:address":"630 S Church St",
    "sg:city":"Murfreesboro",
    "sg:classifiers":[
        {
            "category":"Professional",
            "subcategory":"Accounting & Tax Preparation",
            "type":"Services"
        }
    ],
    "sg:phone":"+1 615 895 4681",
    "sg:postcode":"37130",
    "sg:province":"TN",
    "sg:tags":[
        "accountant"
    ],
    "wof:name":"Sutton & Co Pllc",
    "wof:placetype":"venue"
},
  "geometry": {"coordinates":[-86.39242299999999,35.839774],"type":"Point"}
}