{
  "type": "Feature",
  "properties": {
    "iso:country":"US",
    "sg:address":"104 Flint Rd",
    "sg:city":"Oak Ridge",
    "sg:classifiers":[
        {
            "category":"Manufacturing",
            "subcategory":"Tools & Machinery",
            "type":"Manufacturing & Wholesale Goods"
        }
    ],
    "sg:phone":"+1 865 482 7648",
    "sg:postcode":"37830",
    "sg:province":"TN",
    "sg:tags":[
        "machine",
        "shop"
    ],
    "wof:name":"Atomic City Tool Co",
    "wof:placetype":"venue"
},
  "geometry": {"coordinates":[-84.23621799999999,36.017187],"type":"Point"}
}