{
  "type": "Feature",
  "properties": {
    "iso:country":"US",
    "sg:address":"223 W Sherrod Ave",
    "sg:city":"Covington",
    "sg:classifiers":[
        {
            "category":"Building & Trades",
            "subcategory":"Landscaping Services",
            "type":"Services"
        }
    ],
    "sg:phone":"+1 901 476 5032",
    "sg:postcode":"38019",
    "sg:province":"TN",
    "sg:tags":[
        "landscape"
    ],
    "wof:name":"Barry Myers & Son Landscaping",
    "wof:placetype":"venue"
},
  "geometry": {"coordinates":[-89.647008,35.557778],"type":"Point"}
}