{
  "type": "Feature",
  "properties": {
    "iso:country":"US",
    "sg:address":"359 Twin Oaks Ct",
    "sg:city":"Kingston Springs",
    "sg:classifiers":[
        {
            "category":"Building & Trades",
            "subcategory":"Construction",
            "type":"Services"
        }
    ],
    "sg:phone":"+1 615 952 9211",
    "sg:postcode":"37082",
    "sg:province":"TN",
    "sg:tags":[
        "house"
    ],
    "wof:name":"Horizon Home Improvements",
    "wof:placetype":"venue"
},
  "geometry": {"coordinates":[-87.089523,36.102281],"type":"Point"}
}