{
  "type": "Feature",
  "properties": {
    "iso:country":"US",
    "sg:address":"1476 Toms Creek Rd",
    "sg:city":"Del Rio",
    "sg:classifiers":[
        {
            "category":"Food & Beverages",
            "subcategory":"Groceries & Convenience Stores",
            "type":"Retail Goods"
        }
    ],
    "sg:phone":"+1 423 487 0536",
    "sg:postcode":"37727",
    "sg:province":"TN",
    "wof:name":"Market America Inc",
    "wof:placetype":"venue"
},
  "geometry": {"coordinates":[-83.01570100000001,35.855721],"type":"Point"}
}