{
  "type": "Feature",
  "properties": {
    "addr:full":"403 Lyons Head Dr Knoxville TN 37919",
    "addr:housenumber":"403",
    "addr:postcode":"37919",
    "addr:street":"Lyons Head Dr",
    "iso:country":"US",
    "sg:address":"403 Lyons Head Dr",
    "sg:city":"Knoxville",
    "sg:classifiers":[
        {
            "category":"Real Estate",
            "subcategory":"Real Estate Operator",
            "type":"Services"
        }
    ],
    "sg:phone":"+1 865 588 1011",
    "sg:postcode":"37919",
    "sg:province":"TN",
    "sg:tags":[
        "building",
        "nonresidential"
    ],
    "wof:name":"Albers Properties LLC",
    "wof:placetype":"venue"
},
  "geometry": {"coordinates":[-83.982715,35.936888],"type":"Point"}
}