{
  "type": "Feature",
  "properties": {
    "iso:country":"US",
    "sg:address":"1105 Broadway St",
    "sg:city":"New Johnsonville",
    "sg:classifiers":[
        {
            "category":"Bars & Pubs",
            "type":"Food & Drink"
        }
    ],
    "sg:phone":"+1 931 535 3686",
    "sg:postcode":"37134",
    "sg:province":"TN",
    "sg:tags":[
        "drinking"
    ],
    "wof:name":"Montana",
    "wof:placetype":"venue"
},
  "geometry": {"coordinates":[-87.94080099999999,36.034276],"type":"Point"}
}