{
  "type": "Feature",
  "properties": {
    "addr:full":"805 S Northshore Dr Knoxville TN 37919",
    "addr:housenumber":"805",
    "addr:postcode":"37919",
    "addr:street":"S Northshore Dr",
    "iso:country":"US",
    "sg:address":"805 S Northshore Dr",
    "sg:city":"Knoxville",
    "sg:classifiers":[
        {
            "category":"Organizations",
            "subcategory":"Religious Organization",
            "type":"Services"
        }
    ],
    "sg:phone":"+1 865 584 3307",
    "sg:postcode":"37919",
    "sg:province":"TN",
    "sg:tags":[
        "church"
    ],
    "wof:name":"Diocese Of Knoxville",
    "wof:placetype":"venue"
},
  "geometry": {"coordinates":[-83.99943399999999,35.926436],"type":"Point"}
}