{
  "type": "Feature",
  "properties": {
    "iso:country":"US",
    "sg:address":"1650 N Plantation Dr",
    "sg:city":"Cookeville",
    "sg:classifiers":[
        {
            "category":"Building & Trades",
            "subcategory":"Construction",
            "type":"Services"
        }
    ],
    "sg:phone":"+1 931 252 0299",
    "sg:postcode":"38506",
    "sg:province":"TN",
    "sg:tags":[
        "restoration",
        "cleaning",
        "patio",
        "deck"
    ],
    "wof:name":"Ace Pressure Cleaning",
    "wof:placetype":"venue"
},
  "geometry": {"coordinates":[-85.42664600000001,36.185044],"type":"Point"}
}