{
  "type": "Feature",
  "properties": {
    "iso:country":"US",
    "sg:address":"3601 Barron Ave",
    "sg:city":"Memphis",
    "sg:classifiers":[
        {
            "category":"Social Services",
            "subcategory":"Child Care",
            "type":"Services"
        }
    ],
    "sg:phone":"+1 901 452 0576",
    "sg:postcode":"38111",
    "sg:province":"TN",
    "sg:tags":[
        "day"
    ],
    "wof:name":"Quality United Assoc Learning",
    "wof:placetype":"venue"
},
  "geometry": {"coordinates":[-89.943078,35.097251],"type":"Point"}
}