{
  "type": "Feature",
  "properties": {
    "iso:country":"US",
    "sg:address":"1529 Pactolas Rd",
    "sg:city":"Johnson City",
    "sg:classifiers":[
        {
            "category":"Retail",
            "subcategory":"Car Wash",
            "type":"Services"
        }
    ],
    "sg:phone":"+1 423 926 2776",
    "sg:postcode":"37604",
    "sg:province":"TN",
    "sg:tags":[
        "carwash"
    ],
    "wof:name":"Wash-Rite Car Wash",
    "wof:placetype":"venue"
},
  "geometry": {"coordinates":[-82.381569,36.323423],"type":"Point"}
}