{
  "type": "Feature",
  "properties": {
    "iso:country":"US",
    "sg:address":"1150 Rocky Mound Rd",
    "sg:city":"Westmoreland",
    "sg:classifiers":[
        {
            "category":"Shopping",
            "type":"Retail Goods"
        }
    ],
    "sg:phone":"+1 615 644 5205",
    "sg:postcode":"37186",
    "sg:province":"TN",
    "sg:tags":[
        "plant",
        "flower",
        "tree",
        "artificial"
    ],
    "wof:name":"Westside Designs",
    "wof:placetype":"venue"
},
  "geometry": {"coordinates":[-86.181483,36.547562],"type":"Point"}
}