{
  "type": "Feature",
  "properties": {
    "iso:country":"US",
    "sg:address":"100 Tulsa Rd",
    "sg:city":"Oak Ridge",
    "sg:classifiers":[
        {
            "category":"Social Services",
            "type":"Services"
        }
    ],
    "sg:phone":"+1 865 483 7422",
    "sg:postcode":"37830",
    "sg:province":"TN",
    "sg:tags":[
        "individual",
        "family"
    ],
    "wof:name":"Area Counseling Service",
    "wof:placetype":"venue"
},
  "geometry": {"coordinates":[-84.263739,36.007985],"type":"Point"}
}