{
  "type": "Feature",
  "properties": {
    "iso:country":"US",
    "sg:address":"7348 E Brainerd Rd",
    "sg:city":"Chattanooga",
    "sg:classifiers":[
        {
            "category":"Insurance",
            "subcategory":"Insurance Agent",
            "type":"Services"
        }
    ],
    "sg:phone":"+1 423 894 0360",
    "sg:postcode":"37421",
    "sg:province":"TN",
    "sg:tags":[
        "auto"
    ],
    "sg:website":"http://www.erieinsurance.com/?utm_source=yp&utm_medium=cpc&utm_campaign=ck_yp",
    "wof:name":"CORNERSTONE INSURANCE GRP, INC",
    "wof:placetype":"venue"
},
  "geometry": {"coordinates":[-85.16454400000001,35.015831],"type":"Point"}
}