{
  "type": "Feature",
  "properties": {
    "addr:full":"420 W Walnut St Johnson City TN 37604",
    "addr:housenumber":"420",
    "addr:postcode":"37604",
    "addr:street":"W Walnut St",
    "iso:country":"US",
    "sg:address":"420 W Walnut St",
    "sg:city":"Johnson City",
    "sg:classifiers":[
        {
            "category":"Shopping",
            "subcategory":"Used Merchandise",
            "type":"Retail Goods"
        }
    ],
    "sg:phone":"+1 423 975 7883",
    "sg:postcode":"37604",
    "sg:province":"TN",
    "sg:tags":[
        "book",
        "rare",
        "dealer"
    ],
    "wof:name":"Olde Book Place",
    "wof:placetype":"venue"
},
  "geometry": {"coordinates":[-82.355188,36.311484],"type":"Point"}
}