{
  "type": "Feature",
  "properties": {
    "addr:full":"1247 Emerald Forest Ln Powell TN 37849",
    "addr:housenumber":"1247",
    "addr:postcode":"37849",
    "addr:street":"Emerald Forest Ln",
    "iso:country":"US",
    "sg:address":"1247 Emerald Forest Ln",
    "sg:city":"Powell",
    "sg:classifiers":[
        {
            "category":"Building & Trades",
            "subcategory":"Landscaping Services",
            "type":"Services"
        }
    ],
    "sg:phone":"+1 865 947 5287",
    "sg:postcode":"37849",
    "sg:province":"TN",
    "sg:tags":[
        "lawn",
        "garden"
    ],
    "wof:name":"Emerald Garden & Ldscpg Design",
    "wof:placetype":"venue"
},
  "geometry": {"coordinates":[-84.027824,36.039017],"type":"Point"}
}