{
  "type": "Feature",
  "properties": {
    "iso:country":"US",
    "sg:address":"935 N Wilcox Dr",
    "sg:city":"Kingsport",
    "sg:classifiers":[
        {
            "category":"Restaurant",
            "type":"Food & Drink"
        }
    ],
    "sg:phone":"+1 423 247 8182",
    "sg:postcode":"37660",
    "sg:province":"TN",
    "wof:name":"Golden Dragon Chinese Rstrnt",
    "wof:placetype":"venue"
},
  "geometry": {"coordinates":[-82.54756399999999,36.538814],"type":"Point"}
}