{
  "type": "Feature",
  "properties": {
    "iso:country":"US",
    "sg:address":"1717 J P Hennessy Dr",
    "sg:city":"La Vergne",
    "sg:classifiers":[
        {
            "category":"Freight",
            "type":"Transportation"
        }
    ],
    "sg:phone":"+1 615 501 0182",
    "sg:postcode":"37086",
    "sg:province":"TN",
    "sg:tags":[
        "warehouse"
    ],
    "wof:name":"Palm Commodities",
    "wof:placetype":"venue"
},
  "geometry": {"coordinates":[-86.60014,36.015848],"type":"Point"}
}