{
  "type": "Feature",
  "properties": {
    "iso:country":"US",
    "sg:address":"1000 Riverfront Pkwy",
    "sg:city":"Chattanooga",
    "sg:classifiers":[
        {
            "category":"Professional",
            "subcategory":"Computer Services",
            "type":"Services"
        }
    ],
    "sg:phone":"+1 423 267 0588",
    "sg:postcode":"37402",
    "sg:province":"TN",
    "sg:tags":[
        "consultant",
        "designer"
    ],
    "wof:name":"SRC Network & Software",
    "wof:placetype":"venue"
},
  "geometry": {"coordinates":[-85.322282,35.046819],"type":"Point"}
}