{
  "type": "Feature",
  "properties": {
    "addr:full":"6420 Bresslyn Ct Nashville TN 37205",
    "addr:housenumber":"6420",
    "addr:postcode":"37205",
    "addr:street":"Bresslyn Ct",
    "iso:country":"US",
    "sg:address":"6420 Bresslyn Ct",
    "sg:city":"Nashville",
    "sg:classifiers":[
        {
            "category":"Home & Garden",
            "subcategory":"Building Materials",
            "type":"Retail Goods"
        },
        {
            "category":"Home & Garden",
            "subcategory":"Furniture",
            "type":"Retail Goods"
        }
    ],
    "sg:phone":"+1 615 269 3502",
    "sg:postcode":"37205",
    "sg:province":"TN",
    "sg:tags":[
        "kitchen",
        "equipment",
        "custom",
        "cabinetry",
        "cabinet"
    ],
    "wof:name":"Kitchen Designs Cabinetry LLC",
    "wof:placetype":"venue"
},
  "geometry": {"coordinates":[-86.896692,36.108066],"type":"Point"}
}