{
  "type": "Feature",
  "properties": {
    "iso:country":"US",
    "sg:address":"211 E Blount Ave",
    "sg:city":"Knoxville",
    "sg:classifiers":[
        {
            "category":"Health Services",
            "subcategory":"Doctor",
            "type":"Services"
        }
    ],
    "sg:phone":"+1 865 971 6843",
    "sg:postcode":"37920",
    "sg:province":"TN",
    "sg:tags":[
        "physician",
        "surgeon"
    ],
    "wof:name":"Knoxville Emergency Physicians",
    "wof:placetype":"venue"
},
  "geometry": {"coordinates":[-83.91395199999999,35.955954],"type":"Point"}
}