{
  "type": "Feature",
  "properties": {
    "addr:full":"2125 Kingston Hwy Kingston TN 37763",
    "addr:housenumber":"2125",
    "addr:postcode":"37763",
    "addr:street":"Kingston Hwy",
    "iso:country":"US",
    "sg:address":"2125 Kingston Hwy",
    "sg:city":"Kingston",
    "sg:classifiers":[
        {
            "category":"Retail",
            "subcategory":"Auto Repair",
            "type":"Services"
        }
    ],
    "sg:phone":"+1 865 376 4792",
    "sg:postcode":"37763",
    "sg:province":"TN",
    "sg:tags":[
        "automotive"
    ],
    "wof:name":"Trews Wrecker Service Inc",
    "wof:placetype":"venue"
},
  "geometry": {"coordinates":[-84.47489299999999,35.857395],"type":"Point"}
}