{
  "type": "Feature",
  "properties": {
    "iso:country":"US",
    "sg:address":"2125 Kingston Hwy",
    "sg:city":"Kingston",
    "sg:classifiers":[
        {
            "category":"Retail",
            "subcategory":"Auto Repair",
            "type":"Services"
        }
    ],
    "sg:phone":"+1 865 376 4792",
    "sg:postcode":"37763",
    "sg:province":"TN",
    "sg:tags":[
        "automotive"
    ],
    "wof:name":"Trews Wrecker Service Inc",
    "wof:placetype":"venue"
},
  "geometry": {"coordinates":[-84.47489299999999,35.857395],"type":"Point"}
}