{
  "type": "Feature",
  "properties": {
    "iso:country":"US",
    "sg:address":"2193 Freemont Rd",
    "sg:city":"Memphis",
    "sg:classifiers":[
        {
            "category":"Freight",
            "type":"Transportation"
        }
    ],
    "sg:phone":"+1 901 744 7441",
    "sg:postcode":"38114",
    "sg:province":"TN",
    "sg:tags":[
        "operator",
        "local",
        "trucking"
    ],
    "wof:name":"Freemont Trucking LLC",
    "wof:placetype":"venue"
},
  "geometry": {"coordinates":[-89.989385,35.092533],"type":"Point"}
}