{
  "type": "Feature",
  "properties": {
    "addr:full":"4770 Centerline Dr Knoxville TN 37917",
    "addr:postcode":"4770;37917",
    "addr:street":"Centerline Dr",
    "iso:country":"US",
    "sg:address":"4770 Centerline Dr",
    "sg:city":"Knoxville",
    "sg:classifiers":[
        {
            "category":"Autos & Motor Vehicles",
            "subcategory":"Auto Supplies",
            "type":"Retail Goods"
        }
    ],
    "sg:phone":"+1 865 673 8779",
    "sg:postcode":"37917",
    "sg:province":"TN",
    "sg:tags":[
        "repair",
        "r",
        "general",
        "automotive"
    ],
    "wof:name":"Pep Boys",
    "wof:placetype":"venue"
},
  "geometry": {"coordinates":[-83.884028,36.029331],"type":"Point"}
}