{
  "type": "Feature",
  "properties": {
    "iso:country":"US",
    "sg:address":"3625 Roy Messer Hwy",
    "sg:city":"White Pine",
    "sg:classifiers":[
        {
            "category":"Food & Beverages",
            "subcategory":"Groceries & Convenience Stores",
            "type":"Retail Goods"
        },
        {
            "category":"Autos & Motor Vehicles",
            "subcategory":"Fuel & Gas Station",
            "type":"Retail Goods"
        }
    ],
    "sg:phone":"+1 865 674 0185",
    "sg:postcode":"37890",
    "sg:province":"TN",
    "sg:tags":[
        "station",
        "gasoline"
    ],
    "wof:name":"Fastop Food Mart 4",
    "wof:placetype":"venue"
},
  "geometry": {"coordinates":[-83.33233799999999,36.107367],"type":"Point"}
}