{
  "type": "Feature",
  "properties": {
    "addr:full":"250 Layne Rd Soddy Daisy TN 37379",
    "addr:housenumber":"250",
    "addr:postcode":"37379",
    "addr:street":"Layne Rd",
    "iso:country":"US",
    "sg:address":"250 Layne Rd",
    "sg:city":"Soddy Daisy",
    "sg:classifiers":[
        {
            "category":"Arena",
            "subcategory":"Sports Club",
            "type":"Entertainment"
        }
    ],
    "sg:phone":"+1 423 842 2763",
    "sg:postcode":"37379",
    "sg:province":"TN",
    "sg:tags":[
        "manager",
        "recruiter",
        "promoter"
    ],
    "wof:name":"Special Olympics",
    "wof:placetype":"venue"
},
  "geometry": {"coordinates":[-85.23021799999999,35.223064],"type":"Point"}
}