{
  "type": "Feature",
  "properties": {
    "iso:country":"US",
    "sg:address":"5656 Clovermeade Dr",
    "sg:city":"Brentwood",
    "sg:classifiers":[
        {
            "category":"Professional",
            "type":"Services"
        }
    ],
    "sg:phone":"+1 615 370 1512",
    "sg:postcode":"37027",
    "sg:province":"TN",
    "wof:name":"Professional Removal Serv",
    "wof:placetype":"venue"
},
  "geometry": {"coordinates":[-86.75905899999999,36.033684],"type":"Point"}
}