{
  "type": "Feature",
  "properties": {
    "addr:full":"773 Brethren Church Rd Jonesborough TN 37659",
    "addr:housenumber":"773",
    "addr:postcode":"37659",
    "addr:street":"Church Rd",
    "iso:country":"US",
    "sg:address":"773 Brethren Church Rd",
    "sg:city":"Jonesborough",
    "sg:classifiers":[
        {
            "category":"Organizations",
            "subcategory":"Religious Organization",
            "type":"Services"
        }
    ],
    "sg:phone":"+1 423 753 3437",
    "sg:postcode":"37659",
    "sg:province":"TN",
    "wof:name":"Pleasant Vly Church Brethern",
    "wof:placetype":"venue"
},
  "geometry": {"coordinates":[-82.511244,36.347812],"type":"Point"}
}