{
  "type": "Feature",
  "properties": {
    "iso:country":"US",
    "sg:address":"235 Floyd Dr",
    "sg:city":"Lewisburg",
    "sg:classifiers":[
        {
            "category":"Real Estate",
            "subcategory":"Real Estate Agent",
            "type":"Services"
        }
    ],
    "sg:phone":"+1 931 270 7424",
    "sg:postcode":"37091",
    "sg:province":"TN",
    "wof:name":"Richardson Properties Inc",
    "wof:placetype":"venue"
},
  "geometry": {"coordinates":[-86.811694,35.454203],"type":"Point"}
}