{
  "type": "Feature",
  "properties": {
    "iso:country":"US",
    "sg:address":"5523 Misty Valley Dr",
    "sg:city":"Ooltewah",
    "sg:classifiers":[
        {
            "category":"Real Estate",
            "subcategory":"Real Estate Operator",
            "type":"Services"
        }
    ],
    "sg:phone":"+1 423 396 5451",
    "sg:postcode":"37363",
    "sg:province":"TN",
    "sg:tags":[
        "building",
        "nonresidential"
    ],
    "wof:name":"Goldmine Properties LLC",
    "wof:placetype":"venue"
},
  "geometry": {"coordinates":[-85.032065,35.068068],"type":"Point"}
}