{
  "type": "Feature",
  "properties": {
    "addr:full":"3333 Hanna Dr Memphis TN 38128",
    "addr:housenumber":"3333",
    "addr:postcode":"38128",
    "addr:street":"Hanna Dr",
    "iso:country":"US",
    "sg:address":"3333 Hanna Dr",
    "sg:city":"Memphis",
    "sg:classifiers":[
        {
            "category":"Organizations",
            "subcategory":"Non-profit Organization",
            "type":"Services"
        }
    ],
    "sg:phone":"+1 901 382 7410",
    "sg:postcode":"38128",
    "sg:province":"TN",
    "sg:tags":[
        "disability"
    ],
    "wof:name":"Shelby Residential & Vctnl",
    "wof:placetype":"venue"
},
  "geometry": {"coordinates":[-89.92213599999999,35.216606],"type":"Point"}
}