{
  "type": "Feature",
  "properties": {
    "iso:country":"US",
    "sg:address":"406 Acorn Ct",
    "sg:city":"Smyrna",
    "sg:classifiers":[
        {
            "category":"Professional",
            "subcategory":"Management & Consulting",
            "type":"Services"
        }
    ],
    "sg:phone":"+1 615 355 4073",
    "sg:postcode":"37167",
    "sg:province":"TN",
    "sg:tags":[
        "engineering"
    ],
    "wof:name":"Sandra M Johnson Owner",
    "wof:placetype":"venue"
},
  "geometry": {"coordinates":[-86.52591,35.962591],"type":"Point"}
}