{
  "type": "Feature",
  "properties": {
    "iso:country":"US",
    "sg:address":"1750 Madison Ave",
    "sg:city":"Memphis",
    "sg:classifiers":[
        {
            "category":"Health Services",
            "subcategory":"Doctor",
            "type":"Services"
        }
    ],
    "sg:phone":"+1 901 722 8598",
    "sg:postcode":"38104",
    "sg:province":"TN",
    "sg:tags":[
        "medical"
    ],
    "wof:name":"Tharps Optical Goods",
    "wof:placetype":"venue"
},
  "geometry": {"coordinates":[-90.00291,35.138136],"type":"Point"}
}