{
  "type": "Feature",
  "properties": {
    "iso:country":"US",
    "sg:address":"1019 N Idlewild St",
    "sg:city":"Memphis",
    "sg:classifiers":[
        {
            "category":"Education",
            "subcategory":"Special Training",
            "type":"Public Place"
        }
    ],
    "sg:phone":"+1 901 921 7300",
    "sg:postcode":"38107",
    "sg:province":"TN",
    "sg:tags":[
        "seminar",
        "speaking"
    ],
    "wof:name":"San Ten Ventures",
    "wof:placetype":"venue"
},
  "geometry": {"coordinates":[-89.997319,35.164645],"type":"Point"}
}