{
  "type": "Feature",
  "properties": {
    "iso:country":"US",
    "sg:address":"325 Slayton Dr",
    "sg:city":"Madison",
    "sg:classifiers":[
        {
            "category":"Organizations",
            "subcategory":"Religious Organization",
            "type":"Services"
        }
    ],
    "sg:phone":"+1 615 868 1564",
    "sg:postcode":"37115",
    "sg:province":"TN",
    "sg:tags":[
        "church"
    ],
    "wof:name":"Jehovah's Witnesses-Madison",
    "wof:placetype":"venue"
},
  "geometry": {"coordinates":[-86.715175,36.280195],"type":"Point"}
}