{
  "type": "Feature",
  "properties": {
    "iso:country":"US",
    "sg:address":"5196 Buffalo Valley Rd",
    "sg:city":"Cookeville",
    "sg:classifiers":[
        {
            "category":"Home & Garden",
            "subcategory":"Building Materials",
            "type":"Retail Goods"
        }
    ],
    "sg:phone":"+1 931 858 2218",
    "sg:postcode":"38501",
    "sg:province":"TN",
    "sg:tags":[
        "type",
        "door"
    ],
    "wof:name":"Allied Door",
    "wof:placetype":"venue"
},
  "geometry": {"coordinates":[-85.60927100000001,36.149184],"type":"Point"}
}