{
  "type": "Feature",
  "properties": {
    "iso:country":"US",
    "sg:address":"3104 N Mount Juliet Rd",
    "sg:city":"Mt Juliet",
    "sg:classifiers":[
        {
            "category":"Insurance",
            "subcategory":"Insurance Agent",
            "type":"Services"
        }
    ],
    "sg:phone":"+1 615 773 8545",
    "sg:postcode":"37122",
    "sg:province":"TN",
    "wof:name":"Forward Financial & Ins Svc",
    "wof:placetype":"venue"
},
  "geometry": {"coordinates":[-86.51593699999999,36.214989],"type":"Point"}
}