{
  "type": "Feature",
  "properties": {
    "addr:full":"2005 Dunaway Rd Selmer TN 38375",
    "addr:housenumber":"2005",
    "addr:postcode":"38375",
    "addr:street":"Dunaway Rd",
    "iso:country":"US",
    "sg:address":"2005 Dunaway Rd",
    "sg:city":"Selmer",
    "sg:classifiers":[
        {
            "category":"Wholesale",
            "subcategory":"Machinery & Supplies",
            "type":"Manufacturing & Wholesale Goods"
        }
    ],
    "sg:phone":"+1 731 645 5058",
    "sg:postcode":"38375",
    "sg:province":"TN",
    "sg:tags":[
        "truck"
    ],
    "wof:name":"Grimes Equipment & Repair",
    "wof:placetype":"venue"
},
  "geometry": {"coordinates":[-88.66865799999999,35.130166],"type":"Point"}
}