{
  "type": "Feature",
  "properties": {
    "addr:full":"310 Tellico St S Madisonville TN 37354",
    "addr:housenumber":"310",
    "addr:postcode":"37354",
    "addr:street":"Tellico St S",
    "iso:country":"US",
    "sg:address":"310 Tellico St S",
    "sg:city":"Madisonville",
    "sg:classifiers":[
        {
            "category":"Government",
            "subcategory":"Office",
            "type":"Public Place"
        }
    ],
    "sg:phone":"+1 423 420 1885",
    "sg:postcode":"37354",
    "sg:province":"TN",
    "sg:tags":[
        "management"
    ],
    "wof:name":"Envirnment Cnsrvtion Tenn Dept",
    "wof:placetype":"venue"
},
  "geometry": {"coordinates":[-84.362889,35.519512],"type":"Point"}
}