{
  "type": "Feature",
  "properties": {
    "addr:full":"3615 3rd Ave Chattanooga TN 37407",
    "addr:housenumber":"3615",
    "addr:postcode":"37407",
    "addr:street":"3Rd Ave",
    "iso:country":"US",
    "sg:address":"3615 3rd Ave",
    "sg:city":"Chattanooga",
    "sg:classifiers":[
        {
            "category":"Retail",
            "subcategory":"Auto Repair",
            "type":"Services"
        }
    ],
    "sg:phone":"+1 423 867 5423",
    "sg:postcode":"37407",
    "sg:province":"TN",
    "sg:tags":[
        "wrecker"
    ],
    "wof:name":"United Wrecker",
    "wof:placetype":"venue"
},
  "geometry": {"coordinates":[-85.289805,35.001368],"type":"Point"}
}