{
  "type": "Feature",
  "properties": {
    "addr:full":"1440 E Shelby Dr Memphis TN 38116",
    "addr:housenumber":"1440",
    "addr:postcode":"38116",
    "addr:street":"E Shelby Dr",
    "iso:country":"US",
    "sg:address":"1440 E Shelby Dr",
    "sg:city":"Memphis",
    "sg:classifiers":[
        {
            "category":"Health Services",
            "subcategory":"Doctor",
            "type":"Services"
        }
    ],
    "sg:phone":"+1 901 346 1171",
    "sg:postcode":"38116",
    "sg:province":"TN",
    "sg:tags":[
        "dentist",
        "general",
        "dentistry"
    ],
    "wof:name":"Dean Johnson DDS",
    "wof:placetype":"venue"
},
  "geometry": {"coordinates":[-90.01649,35.020962],"type":"Point"}
}