{
  "type": "Feature",
  "properties": {
    "iso:country":"US",
    "sg:address":"1010 Dobbins St",
    "sg:city":"Paris",
    "sg:classifiers":[
        {
            "category":"Retail",
            "subcategory":"Repair Shop",
            "type":"Services"
        }
    ],
    "sg:phone":"+1 731 642 0211",
    "sg:postcode":"38242",
    "sg:province":"TN",
    "sg:tags":[
        "lining",
        "coating",
        "tank"
    ],
    "wof:name":"Tank Lining Of Paris Inc",
    "wof:placetype":"venue"
},
  "geometry": {"coordinates":[-88.34113600000001,36.297266],"type":"Point"}
}