{
  "type": "Feature",
  "properties": {
    "iso:country":"US",
    "sg:address":"5251 State Hwy 153",
    "sg:city":"Hixson",
    "sg:classifiers":[
        {
            "category":"Shopping",
            "type":"Retail Goods"
        }
    ],
    "sg:phone":"+1 423 344 9781",
    "sg:postcode":"37343",
    "sg:province":"TN",
    "sg:tags":[
        "pet",
        "food",
        "supply"
    ],
    "wof:name":"Happy Whiskers Cookie Co LLC",
    "wof:placetype":"venue"
},
  "geometry": {"coordinates":[-85.241623,35.126256],"type":"Point"}
}