{
  "type": "Feature",
  "properties": {
    "addr:full":"5605 Little Debbie Pkwy Ooltewah TN 37363",
    "addr:housenumber":"5605",
    "addr:postcode":"37363",
    "addr:street":"Little Debbie Pkwy",
    "iso:country":"US",
    "sg:address":"5605 Little Debbie Pkwy",
    "sg:city":"Ooltewah",
    "sg:classifiers":[
        {
            "category":"Restaurant",
            "type":"Food & Drink"
        }
    ],
    "sg:menulink":"http://www.allmenus.com/tn/ooltewah/214943-burger-king/menu/",
    "sg:phone":"+1 423 238 7035",
    "sg:postcode":"37363",
    "sg:province":"TN",
    "sg:tags":[
        "burger",
        "american"
    ],
    "wof:name":"Burger King",
    "wof:placetype":"venue"
},
  "geometry": {"coordinates":[-85.064328,35.084099],"type":"Point"}
}