{
  "type": "Feature",
  "properties": {
    "iso:country":"US",
    "sg:address":"334 Fountain View Cir",
    "sg:city":"Alcoa",
    "sg:classifiers":[
        {
            "category":"Restaurant",
            "type":"Food & Drink"
        }
    ],
    "sg:menulink":"http://www.allmenus.com/tn/maryville-alcoa/10417-texas-roadhouse/menu/",
    "sg:phone":"+1 865 984 4140",
    "sg:postcode":"37701",
    "sg:province":"TN",
    "sg:tags":[
        "american",
        "steakhouse"
    ],
    "wof:name":"Texas Roadhouse",
    "wof:placetype":"venue"
},
  "geometry": {"coordinates":[-83.988975,35.785089],"type":"Point"}
}