{
  "type": "Feature",
  "properties": {
    "iso:country":"US",
    "sg:address":"237 N Main St",
    "sg:city":"Ripley",
    "sg:classifiers":[
        {
            "category":"Retail",
            "subcategory":"Auto Repair",
            "type":"Services"
        }
    ],
    "sg:phone":"+1 731 635 3071",
    "sg:postcode":"38063",
    "sg:province":"TN",
    "sg:tags":[
        "repairing",
        "automobile",
        "radiator"
    ],
    "wof:name":"Halliburton's Radiator Svc",
    "wof:placetype":"venue"
},
  "geometry": {"coordinates":[-89.526718,35.752925],"type":"Point"}
}