{
  "type": "Feature",
  "properties": {
    "iso:country":"US",
    "sg:address":"125 Walnut St",
    "sg:city":"Memphis",
    "sg:classifiers":[
        {
            "category":"Building & Trades",
            "subcategory":"Construction",
            "type":"Services"
        }
    ],
    "sg:phone":"+1 901 759 7927",
    "sg:postcode":"38126",
    "sg:province":"TN",
    "sg:tags":[
        "house"
    ],
    "wof:name":"On Call Home Improvements",
    "wof:placetype":"venue"
},
  "geometry": {"coordinates":[-90.034947,35.137672],"type":"Point"}
}