{
  "type": "Feature",
  "properties": {
    "iso:country":"US",
    "sg:address":"3369 Anes Station Rd",
    "sg:city":"Lewisburg",
    "sg:classifiers":[
        {
            "category":"Farming",
            "subcategory":"Fish & Marine Products",
            "type":"Manufacturing & Wholesale Goods"
        }
    ],
    "sg:phone":"+1 931 359 9885",
    "sg:postcode":"37091",
    "sg:province":"TN",
    "sg:tags":[
        "preserves",
        "fishing",
        "hunting"
    ],
    "wof:name":"King Brothers Hunting Preserve",
    "wof:placetype":"venue"
},
  "geometry": {"coordinates":[-86.72666099999999,35.546613],"type":"Point"}
}