{
  "type": "Feature",
  "properties": {
    "addr:full":"4220 Dayton Blvd Chattanooga TN 37415",
    "addr:housenumber":"4220",
    "addr:postcode":"37415",
    "addr:street":"Dayton Blvd",
    "iso:country":"US",
    "sg:address":"4220 Dayton Blvd",
    "sg:city":"Chattanooga",
    "sg:classifiers":[
        {
            "category":"Utilities",
            "subcategory":"Telephone",
            "type":"Services"
        }
    ],
    "sg:phone":"+1 423 877 6020",
    "sg:postcode":"37415",
    "sg:province":"TN",
    "sg:tags":[
        "communications"
    ],
    "wof:name":"True Register",
    "wof:placetype":"venue"
},
  "geometry": {"coordinates":[-85.286383,35.123513],"type":"Point"}
}