{
  "type": "Feature",
  "properties": {
    "iso:country":"US",
    "sg:address":"16601 Cainsville Rd",
    "sg:city":"Lascassas",
    "sg:classifiers":[
        {
            "category":"Freight",
            "type":"Transportation"
        }
    ],
    "sg:phone":"+1 615 273 2748",
    "sg:postcode":"37085",
    "sg:province":"TN",
    "wof:name":"Earp Transportation",
    "wof:placetype":"venue"
},
  "geometry": {"coordinates":[-86.24957999999999,35.982771],"type":"Point"}
}