{
  "type": "Feature",
  "properties": {
    "iso:country":"US",
    "sg:address":"2503 N 16th St",
    "sg:city":"Nashville",
    "sg:classifiers":[
        {
            "category":"Organizations",
            "subcategory":"Non-profit Organization",
            "type":"Services"
        }
    ],
    "sg:phone":"+1 615 876 9489",
    "sg:postcode":"37206",
    "sg:province":"TN",
    "sg:tags":[
        "agency",
        "social"
    ],
    "wof:name":"National Empowerment Women Inc",
    "wof:placetype":"venue"
},
  "geometry": {"coordinates":[-86.737297,36.19542],"type":"Point"}
}