{
  "type": "Feature",
  "properties": {
    "iso:country":"US",
    "sg:address":"1763 Peabody Ave",
    "sg:city":"Memphis",
    "sg:classifiers":[
        {
            "category":"Building & Trades",
            "subcategory":"Cleaning & Sanitation",
            "type":"Services"
        }
    ],
    "sg:phone":"+1 901 488 8440",
    "sg:postcode":"38104",
    "sg:province":"TN",
    "sg:tags":[
        "maintenance"
    ],
    "wof:name":"JM Services",
    "wof:placetype":"venue"
},
  "geometry": {"coordinates":[-90.001446,35.131934],"type":"Point"}
}