{
  "type": "Feature",
  "properties": {
    "addr:full":"322 Tillery Rd Knoxville TN 37912",
    "addr:housenumber":"322",
    "addr:postcode":"37912",
    "addr:street":"Tillery Rd",
    "iso:country":"US",
    "sg:address":"322 Tillery Rd",
    "sg:city":"Knoxville",
    "sg:classifiers":[
        {
            "category":"Retail",
            "subcategory":"Auto Repair",
            "type":"Services"
        }
    ],
    "sg:phone":"+1 865 689 7143",
    "sg:postcode":"37912",
    "sg:province":"TN",
    "sg:tags":[
        "repairing",
        "automobile"
    ],
    "wof:name":"Lee's Specialtee LLC",
    "wof:placetype":"venue"
},
  "geometry": {"coordinates":[-83.96517799999999,36.00079],"type":"Point"}
}