{
  "type": "Feature",
  "properties": {
    "iso:country":"US",
    "sg:address":"969 Shag Rag Rd",
    "sg:city":"Cookeville",
    "sg:classifiers":[
        {
            "category":"Shopping",
            "type":"Retail Goods"
        }
    ],
    "sg:phone":"+1 931 520 7711",
    "sg:postcode":"38506",
    "sg:province":"TN",
    "sg:tags":[
        "merchandise"
    ],
    "wof:name":"Cumberland Collection",
    "wof:placetype":"venue"
},
  "geometry": {"coordinates":[-85.48203700000001,36.190825],"type":"Point"}
}