{
  "type": "Feature",
  "properties": {
    "iso:country":"US",
    "sg:address":"516 Tennessee St",
    "sg:city":"Memphis",
    "sg:classifiers":[
        {
            "category":"Professional",
            "subcategory":"Business Services",
            "type":"Services"
        },
        {
            "category":"Education",
            "subcategory":"Special Training",
            "type":"Public Place"
        }
    ],
    "sg:phone":"+1 901 767 0000",
    "sg:postcode":"38103",
    "sg:province":"TN",
    "sg:tags":[
        "motion",
        "consulting",
        "pic"
    ],
    "sg:website":"www.uslearning.com",
    "wof:name":"Don Hutson Organization",
    "wof:placetype":"venue"
},
  "geometry": {"coordinates":[-90.062484,35.133417],"type":"Point"}
}