{
  "type": "Feature",
  "properties": {
    "addr:full":"412 6th St Bristol TN 37620",
    "addr:housenumber":"412",
    "addr:postcode":"37620",
    "addr:street":"6Th St",
    "iso:country":"US",
    "sg:address":"412 6th St",
    "sg:city":"Bristol",
    "sg:classifiers":[
        {
            "category":"Restaurant",
            "type":"Food & Drink"
        }
    ],
    "sg:phone":"+1 423 968 9099",
    "sg:postcode":"37620",
    "sg:province":"TN",
    "sg:tags":[
        "drinking",
        "eating"
    ],
    "sg:website":"www.thetroutdale.com",
    "wof:name":"Troutdale Dining Room",
    "wof:placetype":"venue"
},
  "geometry": {"coordinates":[-82.183564,36.590671],"type":"Point"}
}