{
  "type": "Feature",
  "properties": {
    "addr:full":"1350 Wildersville Rd Wildersville TN 38388",
    "addr:housenumber":"1350",
    "addr:postcode":"38388",
    "addr:street":"Wildersville Rd",
    "iso:country":"US",
    "sg:address":"1350 Wildersville Rd",
    "sg:city":"Wildersville",
    "sg:classifiers":[
        {
            "category":"Food & Beverages",
            "subcategory":"Groceries & Convenience Stores",
            "type":"Retail Goods"
        }
    ],
    "sg:phone":"+1 731 967 3803",
    "sg:postcode":"38388",
    "sg:province":"TN",
    "wof:name":"This & That",
    "wof:placetype":"venue"
},
  "geometry": {"coordinates":[-88.37304,35.784387],"type":"Point"}
}