{
  "type": "Feature",
  "properties": {
    "addr:full":"1754 Clark Rd Scotts Hill TN 38374",
    "addr:housenumber":"1754",
    "addr:postcode":"38374",
    "addr:street":"Clark Rd",
    "iso:country":"US",
    "sg:address":"1754 Clark Rd",
    "sg:city":"Scotts Hill",
    "sg:classifiers":[
        {
            "category":"Manufacturing",
            "subcategory":"Metals",
            "type":"Manufacturing & Wholesale Goods"
        }
    ],
    "sg:phone":"+1 731 549 3821",
    "sg:postcode":"38374",
    "sg:province":"TN",
    "sg:tags":[
        "die",
        "mfg",
        "nonferrous"
    ],
    "wof:name":"Tennessee Valley Bullets",
    "wof:placetype":"venue"
},
  "geometry": {"coordinates":[-88.194412,35.453337],"type":"Point"}
}