{
  "type": "Feature",
  "properties": {
    "addr:full":"417 N Main St Jamestown TN 38556",
    "addr:housenumber":"417",
    "addr:postcode":"38556",
    "addr:street":"N Main St",
    "iso:country":"US",
    "sg:address":"417 N Main St",
    "sg:city":"Jamestown",
    "sg:classifiers":[
        {
            "category":"Restaurant",
            "type":"Food & Drink"
        }
    ],
    "sg:phone":"+1 931 752 8991",
    "sg:postcode":"38556",
    "sg:province":"TN",
    "wof:name":"El Rey Azteca Mexican Rstrnt",
    "wof:placetype":"venue"
},
  "geometry": {"coordinates":[-84.93536899999999,36.434168],"type":"Point"}
}