{
  "type": "Feature",
  "properties": {
    "iso:country":"US",
    "sg:address":"304 W Church St",
    "sg:city":"Lewisburg",
    "sg:classifiers":[
        {
            "category":"Banks & Credit Unions",
            "subcategory":"Bank",
            "type":"Services"
        }
    ],
    "sg:phone":"+1 931 359 3551",
    "sg:postcode":"37091",
    "sg:province":"TN",
    "wof:name":"Kenneth Phelps & Assoc",
    "wof:placetype":"venue"
},
  "geometry": {"coordinates":[-86.791562,35.450318],"type":"Point"}
}