{
  "type": "Feature",
  "properties": {
    "addr:full":"177 Belle Forest Cir Nashville TN 37221",
    "addr:housenumber":"177",
    "addr:postcode":"37221",
    "addr:street":"Belle Forest Cir",
    "iso:country":"US",
    "sg:address":"177 Belle Forest Cir",
    "sg:city":"Nashville",
    "sg:classifiers":[
        {
            "category":"Organizations",
            "subcategory":"Professional Association",
            "type":"Services"
        }
    ],
    "sg:phone":"+1 615 662 2737",
    "sg:postcode":"37221",
    "sg:province":"TN",
    "sg:tags":[
        "chambers",
        "business",
        "commerce"
    ],
    "wof:name":"Bellevue Chamber Of Commerce",
    "wof:placetype":"venue"
},
  "geometry": {"coordinates":[-86.92411300000001,36.075442],"type":"Point"}
}