{
  "type": "Feature",
  "properties": {
    "iso:country":"US",
    "sg:address":"4523 Haverty Dr",
    "sg:city":"Knoxville",
    "sg:classifiers":[
        {
            "category":"Professional",
            "subcategory":"Advertising",
            "type":"Services"
        }
    ],
    "sg:phone":"+1 865 693 4139",
    "sg:postcode":"37931",
    "sg:province":"TN",
    "sg:tags":[
        "agency"
    ],
    "wof:name":"Reiff Advertising & Design",
    "wof:placetype":"venue"
},
  "geometry": {"coordinates":[-84.050422,35.992862],"type":"Point"}
}