{
  "type": "Feature",
  "properties": {
    "iso:country":"US",
    "sg:address":"114 N Cason Ave",
    "sg:city":"Henderson",
    "sg:classifiers":[
        {
            "category":"Professional",
            "subcategory":"Business Services",
            "type":"Services"
        }
    ],
    "sg:phone":"+1 731 989 2525",
    "sg:postcode":"38340",
    "sg:province":"TN",
    "sg:tags":[
        "embroidery"
    ],
    "wof:name":"Sew Happy",
    "wof:placetype":"venue"
},
  "geometry": {"coordinates":[-88.640503,35.440336],"type":"Point"}
}