{
  "type": "Feature",
  "properties": {
    "iso:country":"US",
    "sg:address":"6712 Kingston Pike",
    "sg:city":"Knoxville",
    "sg:classifiers":[
        {
            "category":"Insurance",
            "subcategory":"Insurance Agent",
            "type":"Services"
        }
    ],
    "sg:phone":"+1 865 584 2196",
    "sg:postcode":"37919",
    "sg:province":"TN",
    "wof:name":"Professional Insurance Conslnt",
    "wof:placetype":"venue"
},
  "geometry": {"coordinates":[-84.016312,35.932284],"type":"Point"}
}