{
  "type": "Feature",
  "properties": {
    "iso:country":"US",
    "sg:address":"10385 Long Rd",
    "sg:city":"Arlington",
    "sg:classifiers":[
        {
            "category":"Retail",
            "subcategory":"Repair Shop",
            "type":"Services"
        }
    ],
    "sg:phone":"+1 901 867 7300",
    "sg:postcode":"38002",
    "sg:province":"TN",
    "sg:tags":[
        "blacksmith"
    ],
    "wof:name":"Ironwood LLC",
    "wof:placetype":"venue"
},
  "geometry": {"coordinates":[-89.69774700000001,35.302217],"type":"Point"}
}