{
  "type": "Feature",
  "properties": {
    "iso:country":"US",
    "sg:address":"375 W Church Ave",
    "sg:city":"Medina",
    "sg:classifiers":[
        {
            "category":"Personal",
            "subcategory":"Beauty Salon",
            "type":"Services"
        }
    ],
    "sg:phone":"+1 731 783 1601",
    "sg:postcode":"38355",
    "sg:province":"TN",
    "wof:name":"Allusions Salon",
    "wof:placetype":"venue"
},
  "geometry": {"coordinates":[-88.78055999999999,35.801916],"type":"Point"}
}