{
  "type": "Feature",
  "properties": {
    "iso:country":"US",
    "sg:address":"1095 Neill Cemetery Dr",
    "sg:city":"Savannah",
    "sg:classifiers":[
        {
            "category":"Professional",
            "type":"Services"
        }
    ],
    "sg:phone":"+1 731 925 6489",
    "sg:postcode":"38372",
    "sg:province":"TN",
    "wof:name":"Melinda R Jones",
    "wof:placetype":"venue"
},
  "geometry": {"coordinates":[-88.186031,35.210714],"type":"Point"}
}