{
  "type": "Feature",
  "properties": {
    "addr:full":"214 Centerview Dr Brentwood TN 37027",
    "addr:housenumber":"214",
    "addr:postcode":"37027",
    "addr:street":"Centerview Dr",
    "iso:country":"US",
    "sg:address":"214 Centerview Dr",
    "sg:city":"Brentwood",
    "sg:classifiers":[
        {
            "category":"Insurance",
            "subcategory":"Hazard Insurance",
            "type":"Services"
        },
        {
            "category":"Insurance",
            "subcategory":"Insurance Agent",
            "type":"Services"
        }
    ],
    "sg:phone":"+1 615 377 0019",
    "sg:postcode":"37027",
    "sg:province":"TN",
    "sg:tags":[
        "carrier"
    ],
    "wof:name":"Wausau Insurance Companies",
    "wof:placetype":"venue"
},
  "geometry": {"coordinates":[-86.786991,36.030933],"type":"Point"}
}