{
  "type": "Feature",
  "properties": {
    "iso:country":"US",
    "sg:address":"240 W Central Ave",
    "sg:city":"La Follette",
    "sg:classifiers":[
        {
            "category":"Shopping",
            "type":"Retail Goods"
        },
        {
            "category":"Wholesale",
            "subcategory":"Home Furnishings",
            "type":"Manufacturing & Wholesale Goods"
        }
    ],
    "sg:phone":"+1 423 563 0080",
    "sg:postcode":"37766",
    "sg:province":"TN",
    "sg:tags":[
        "picture",
        "frame",
        "art"
    ],
    "wof:name":"Perfect Image",
    "wof:placetype":"venue"
},
  "geometry": {"coordinates":[-84.12445700000001,36.379377],"type":"Point"}
}