{
  "type": "Feature",
  "properties": {
    "iso:country":"US",
    "sg:address":"313 S Murray St",
    "sg:city":"Gainesboro",
    "sg:classifiers":[
        {
            "category":"Organizations",
            "subcategory":"Religious Organization",
            "type":"Services"
        }
    ],
    "sg:phone":"+1 931 268 9828",
    "sg:postcode":"38562",
    "sg:province":"TN",
    "sg:tags":[
        "church"
    ],
    "wof:name":"Church Of Christ",
    "wof:placetype":"venue"
},
  "geometry": {"coordinates":[-85.65688,36.353477],"type":"Point"}
}