{
  "type": "Feature",
  "properties": {
    "addr:full":"3641 Hixson Pike Chattanooga TN 37415",
    "addr:housenumber":"3641",
    "addr:postcode":"37415",
    "addr:street":"Hixson Pike",
    "iso:country":"US",
    "sg:address":"3641 Hixson Pike",
    "sg:city":"Chattanooga",
    "sg:classifiers":[
        {
            "category":"Manufacturing",
            "subcategory":"Printing",
            "type":"Manufacturing & Wholesale Goods"
        }
    ],
    "sg:phone":"+1 423 842 9290",
    "sg:postcode":"37415",
    "sg:province":"TN",
    "sg:tags":[
        "screen"
    ],
    "sg:website":"www.bcgrafx.net",
    "wof:name":"B C Graphics",
    "wof:placetype":"venue"
},
  "geometry": {"coordinates":[-85.271798,35.108125],"type":"Point"}
}