{
  "type": "Feature",
  "properties": {
    "iso:country":"US",
    "sg:address":"562 S Water Ave",
    "sg:city":"Gallatin",
    "sg:classifiers":[
        {
            "category":"Restaurant",
            "type":"Food & Drink"
        }
    ],
    "sg:phone":"+1 615 230 8335",
    "sg:postcode":"37066",
    "sg:province":"TN",
    "wof:name":"Menells At Fitzgerald Manor",
    "wof:placetype":"venue"
},
  "geometry": {"coordinates":[-86.443319,36.380321],"type":"Point"}
}