{
  "type": "Feature",
  "properties": {
    "addr:full":"6600 Charlotte Pike Nashville TN 37209",
    "addr:housenumber":"6600",
    "addr:postcode":"37209",
    "addr:street":"Charlotte Pike",
    "iso:country":"US",
    "sg:address":"6600 Charlotte Pike",
    "sg:city":"Nashville",
    "sg:classifiers":[
        {
            "category":"Restaurant",
            "type":"Food & Drink"
        }
    ],
    "sg:phone":"+1 615 354 0470",
    "sg:postcode":"37209",
    "sg:province":"TN",
    "wof:name":"Mc Donald's",
    "wof:placetype":"venue"
},
  "geometry": {"coordinates":[-86.88124500000001,36.138529],"type":"Point"}
}