{
  "type": "Feature",
  "properties": {
    "addr:full":"120 Franklin Rd Brentwood TN 37027",
    "addr:housenumber":"120",
    "addr:postcode":"37027",
    "addr:street":"Franklin Rd",
    "iso:country":"US",
    "sg:address":"120 Franklin Rd",
    "sg:city":"Brentwood",
    "sg:classifiers":[
        {
            "category":"Retail",
            "subcategory":"Auto Repair",
            "type":"Services"
        }
    ],
    "sg:phone":"+1 615 371 5371",
    "sg:postcode":"37027",
    "sg:province":"TN",
    "sg:tags":[
        "automobile",
        "lubrication"
    ],
    "wof:name":"Valvoline Instant Oil Change",
    "wof:placetype":"venue"
},
  "geometry": {"coordinates":[-86.78750100000001,36.035289],"type":"Point"}
}