{
  "type": "Feature",
  "properties": {
    "iso:country":"US",
    "sg:address":"625 Morrison Springs Rd",
    "sg:city":"Chattanooga",
    "sg:classifiers":[
        {
            "category":"Health Services",
            "subcategory":"Doctor",
            "type":"Services"
        }
    ],
    "sg:phone":"+1 423 855 5550",
    "sg:postcode":"37415",
    "sg:province":"TN",
    "sg:tags":[
        "dentist"
    ],
    "sg:website":"www.easttnfacialsurgery.com",
    "wof:name":"East Tn Facial Surgery Inc",
    "wof:placetype":"venue"
},
  "geometry": {"coordinates":[-85.301136,35.124333],"type":"Point"}
}