{
  "type": "Feature",
  "properties": {
    "addr:full":"121 W Market St Dyersburg TN 38024",
    "addr:housenumber":"121",
    "addr:postcode":"38024",
    "addr:street":"W Market St",
    "iso:country":"US",
    "sg:address":"121 W Market St",
    "sg:city":"Dyersburg",
    "sg:classifiers":[
        {
            "category":"Social Services",
            "type":"Services"
        }
    ],
    "sg:phone":"+1 731 287 8100",
    "sg:postcode":"38024",
    "sg:province":"TN",
    "sg:tags":[
        "counselor",
        "marriage",
        "family"
    ],
    "wof:name":"Here's Hope Counseling",
    "wof:placetype":"venue"
},
  "geometry": {"coordinates":[-89.38667599999999,36.031927],"type":"Point"}
}