{
  "type": "Feature",
  "properties": {
    "addr:full":"8542 Shady Trail Cv Cordova TN 38018",
    "addr:housenumber":"8542",
    "addr:postcode":"38018",
    "addr:street":"Shady Trail Cv",
    "iso:country":"US",
    "sg:address":"8542 Shady Trail Cv",
    "sg:city":"Cordova",
    "sg:classifiers":[
        {
            "category":"Shopping",
            "subcategory":"Hobbies, Toys, & Games",
            "type":"Retail Goods"
        },
        {
            "category":"Recreation",
            "subcategory":"Gun Range",
            "type":"Entertainment"
        }
    ],
    "sg:phone":"+1 901 755 4196",
    "sg:postcode":"38018",
    "sg:province":"TN",
    "sg:tags":[
        "safety",
        "instruction",
        "marksmanship",
        "gunsmith"
    ],
    "wof:name":"Haddon Hill",
    "wof:placetype":"venue"
},
  "geometry": {"coordinates":[-89.777889,35.122172],"type":"Point"}
}