{
  "type": "Feature",
  "properties": {
    "iso:country":"US",
    "sg:address":"5403 Hixson Pike",
    "sg:city":"Hixson",
    "sg:classifiers":[
        {
            "category":"Retail",
            "subcategory":"Laundry & Dry Cleaning",
            "type":"Services"
        }
    ],
    "sg:phone":"+1 423 842 5880",
    "sg:postcode":"37343",
    "sg:province":"TN",
    "sg:tags":[
        "cleaners",
        "rug",
        "carpet"
    ],
    "wof:name":"A 1 Carpet Cleaning & Repairs",
    "wof:placetype":"venue"
},
  "geometry": {"coordinates":[-85.229792,35.142272],"type":"Point"}
}