{
  "type": "Feature",
  "properties": {
    "addr:full":"159 Mall Circle Dr Murfreesboro TN 37129",
    "addr:housenumber":"159",
    "addr:postcode":"37129",
    "addr:street":"Mall Circle Dr",
    "iso:country":"US",
    "sg:address":"159 Mall Circle Dr",
    "sg:city":"Murfreesboro",
    "sg:classifiers":[
        {
            "category":"Shopping",
            "subcategory":"Discount & Variety Stores",
            "type":"Retail Goods"
        }
    ],
    "sg:phone":"+1 615 896 8863",
    "sg:postcode":"37129",
    "sg:province":"TN",
    "sg:tags":[
        "merchandise",
        "general"
    ],
    "wof:name":"CD Warehouse",
    "wof:placetype":"venue"
},
  "geometry": {"coordinates":[-86.420784,35.846971],"type":"Point"}
}