{
  "type": "Feature",
  "properties": {
    "iso:country":"US",
    "sg:address":"4156 Flynns Creek Rd",
    "sg:city":"Gainesboro",
    "sg:classifiers":[
        {
            "category":"Organizations",
            "subcategory":"Religious Organization",
            "type":"Services"
        }
    ],
    "sg:phone":"+1 931 268 4336",
    "sg:postcode":"38562",
    "sg:province":"TN",
    "wof:name":"Crossroads Baptist Church",
    "wof:placetype":"venue"
},
  "geometry": {"coordinates":[-85.615076,36.247814],"type":"Point"}
}