{
  "type": "Feature",
  "properties": {
    "iso:country":"US",
    "sg:address":"4203 Faithway Dr",
    "sg:city":"Murfreesboro",
    "sg:classifiers":[
        {
            "category":"Retail",
            "subcategory":"Repair Shop",
            "type":"Services"
        }
    ],
    "sg:phone":"+1 615 890 0243",
    "sg:postcode":"37128",
    "sg:province":"TN",
    "wof:name":"MB Commerical Cleaning",
    "wof:placetype":"venue"
},
  "geometry": {"coordinates":[-86.474013,35.823862],"type":"Point"}
}