{
  "type": "Feature",
  "properties": {
    "iso:country":"US",
    "sg:address":"620 Mall Blvd",
    "sg:city":"Dyersburg",
    "sg:classifiers":[
        {
            "category":"Shopping",
            "subcategory":"Jewelry",
            "type":"Retail Goods"
        }
    ],
    "sg:phone":"+1 731 287 1189",
    "sg:postcode":"38024",
    "sg:province":"TN",
    "sg:tags":[
        "jeweler"
    ],
    "wof:name":"Jewelry Jungle",
    "wof:placetype":"venue"
},
  "geometry": {"coordinates":[-89.392889,36.06458],"type":"Point"}
}