{
  "type": "Feature",
  "properties": {
    "iso:country":"US",
    "sg:address":"813 Brentwood Dr",
    "sg:city":"Maryville",
    "sg:classifiers":[
        {
            "category":"Wholesale",
            "subcategory":"Construction Materials",
            "type":"Manufacturing & Wholesale Goods"
        },
        {
            "category":"Shopping",
            "type":"Retail Goods"
        }
    ],
    "sg:phone":"+1 865 380 0506",
    "sg:postcode":"37804",
    "sg:province":"TN",
    "sg:tags":[
        "consultant",
        "product",
        "wood",
        "lumber"
    ],
    "wof:name":"Wood Drops Inc",
    "wof:placetype":"venue"
},
  "geometry": {"coordinates":[-83.944704,35.768816],"type":"Point"}
}