{
  "type": "Feature",
  "properties": {
    "iso:country":"US",
    "sg:address":"515 N Highland St",
    "sg:city":"Memphis",
    "sg:classifiers":[
        {
            "category":"Health Services",
            "subcategory":"Health Practitioner",
            "type":"Services"
        }
    ],
    "sg:phone":"+1 901 323 9986",
    "sg:postcode":"38122",
    "sg:province":"TN",
    "sg:tags":[
        "acupuncture",
        "holistic"
    ],
    "wof:name":"Dr Ly Acupuncture Integrative Medicine",
    "wof:placetype":"venue"
},
  "geometry": {"coordinates":[-89.94462300000001,35.146112],"type":"Point"}
}