{
  "type": "Feature",
  "properties": {
    "iso:country":"US",
    "sg:address":"1225 Everett Ave",
    "sg:city":"Maryville",
    "sg:classifiers":[
        {
            "category":"Real Estate",
            "subcategory":"Surveying",
            "type":"Services"
        }
    ],
    "sg:phone":"+1 865 254 1316",
    "sg:postcode":"37804",
    "sg:province":"TN",
    "sg:tags":[
        "surveyor"
    ],
    "wof:name":"Apex Land Surveying",
    "wof:placetype":"venue"
},
  "geometry": {"coordinates":[-83.958822,35.763652],"type":"Point"}
}