{
  "type": "Feature",
  "properties": {
    "iso:country":"US",
    "sg:address":"1305 Decatur Pike",
    "sg:city":"Athens",
    "sg:classifiers":[
        {
            "category":"Banks & Credit Unions",
            "subcategory":"Bank",
            "type":"Services"
        }
    ],
    "sg:phone":"+1 423 745 8246",
    "sg:postcode":"37303",
    "sg:province":"TN",
    "sg:tags":[
        "state",
        "commercial"
    ],
    "sg:website":"www.mybankconnection.com",
    "wof:name":"Bank Of Athens",
    "wof:placetype":"venue"
},
  "geometry": {"coordinates":[-84.61534399999999,35.448765],"type":"Point"}
}