{
  "type": "Feature",
  "properties": {
    "addr:full":"320 N Main St Greeneville TN 37745",
    "addr:housenumber":"320",
    "addr:postcode":"37745",
    "addr:street":"N Main St",
    "iso:country":"US",
    "sg:address":"320 N Main St",
    "sg:city":"Greeneville",
    "sg:classifiers":[
        {
            "category":"Wholesale",
            "subcategory":"Furniture",
            "type":"Manufacturing & Wholesale Goods"
        }
    ],
    "sg:phone":"+1 423 638 9677",
    "sg:postcode":"37745",
    "sg:province":"TN",
    "sg:tags":[
        "manufacture",
        "independent",
        "for",
        "rep",
        "also",
        "operate"
    ],
    "wof:name":"Azaleas",
    "wof:placetype":"venue"
},
  "geometry": {"coordinates":[-82.82779499999999,36.168501],"type":"Point"}
}