{
  "type": "Feature",
  "properties": {
    "addr:full":"1339 State Hwy 13 S Waverly TN 37185",
    "addr:housenumber":"1339",
    "addr:postcode":"37185",
    "addr:street":"State Hwy 13 S",
    "iso:country":"US",
    "sg:address":"1339 State Hwy 13 S",
    "sg:city":"Waverly",
    "sg:classifiers":[
        {
            "category":"Real Estate",
            "subcategory":"Developer",
            "type":"Services"
        }
    ],
    "sg:phone":"+1 931 296 4284",
    "sg:postcode":"37185",
    "sg:province":"TN",
    "sg:tags":[
        "cemetery"
    ],
    "wof:name":"Ferbie L Hicks Family Cemetery",
    "wof:placetype":"venue"
},
  "geometry": {"coordinates":[-87.79404,36.07633],"type":"Point"}
}