{
  "type": "Feature",
  "properties": {
    "addr:full":"9326 Seasons Dr Chattanooga TN 37421",
    "addr:postcode":"9326;37421",
    "addr:street":"Seasons Dr",
    "iso:country":"US",
    "sg:address":"9326 Seasons Dr",
    "sg:city":"Chattanooga",
    "sg:classifiers":[
        {
            "category":"Real Estate",
            "subcategory":"Real Estate Services",
            "type":"Services"
        },
        {
            "category":"Real Estate",
            "subcategory":"Real Estate Agent",
            "type":"Services"
        }
    ],
    "sg:phone":"+1 423 894 9602",
    "sg:postcode":"37421",
    "sg:province":"TN",
    "sg:tags":[
        "management"
    ],
    "wof:name":"Jackson Pam Real Estate",
    "wof:placetype":"venue"
},
  "geometry": {"coordinates":[-85.108789,35.006198],"type":"Point"}
}