{
  "type": "Feature",
  "properties": {
    "addr:full":"2100 S Lee Hwy Cleveland TN 37311",
    "addr:housenumber":"2100",
    "addr:postcode":"37311",
    "addr:street":"S Lee Hwy",
    "iso:country":"US",
    "sg:address":"2100 S Lee Hwy",
    "sg:city":"Cleveland",
    "sg:classifiers":[
        {
            "category":"Retail",
            "subcategory":"Auto Repair",
            "type":"Services"
        }
    ],
    "sg:phone":"+1 423 476 9227",
    "sg:postcode":"37311",
    "sg:province":"TN",
    "sg:tags":[
        "repairing",
        "automobile"
    ],
    "wof:name":"Bud's Auto Svc",
    "wof:placetype":"venue"
},
  "geometry": {"coordinates":[-84.90573000000001,35.151807],"type":"Point"}
}