{
  "type": "Feature",
  "properties": {
    "addr:full":"525 W Hillwood Dr Nashville TN 37205",
    "addr:housenumber":"525",
    "addr:postcode":"37205",
    "addr:street":"W Hillwood Dr",
    "iso:country":"US",
    "sg:address":"525 W Hillwood Dr",
    "sg:city":"Nashville",
    "sg:classifiers":[
        {
            "category":"Professional",
            "type":"Services"
        }
    ],
    "sg:phone":"+1 615 356 5090",
    "sg:postcode":"37205",
    "sg:province":"TN",
    "wof:name":"Bluemillion Co",
    "wof:placetype":"venue"
},
  "geometry": {"coordinates":[-86.88126699999999,36.130144],"type":"Point"}
}