{
  "type": "Feature",
  "properties": {
    "iso:country":"US",
    "sg:address":"97 Milan Hwy",
    "sg:city":"Milan",
    "sg:classifiers":[
        {
            "category":"Organizations",
            "subcategory":"Religious Organization",
            "type":"Services"
        }
    ],
    "sg:phone":"+1 731 783 3222",
    "sg:postcode":"38358",
    "sg:province":"TN",
    "sg:tags":[
        "baptist",
        "church"
    ],
    "wof:name":"First Baptist Church",
    "wof:placetype":"venue"
},
  "geometry": {"coordinates":[-88.76515999999999,35.819317],"type":"Point"}
}