{
  "type": "Feature",
  "properties": {
    "addr:full":"203 Sparta St Mc Minnville TN 37110",
    "addr:housenumber":"203",
    "addr:postcode":"37110",
    "addr:street":"Sparta St",
    "iso:country":"US",
    "sg:address":"203 Sparta St",
    "sg:city":"Mc Minnville",
    "sg:classifiers":[
        {
            "category":"Autos & Motor Vehicles",
            "subcategory":"Fuel & Gas Station",
            "type":"Retail Goods"
        }
    ],
    "sg:phone":"+1 931 473 2923",
    "sg:postcode":"37110",
    "sg:province":"TN",
    "sg:tags":[
        "oil"
    ],
    "wof:name":"Amoco Downtown Svc Inc",
    "wof:placetype":"venue"
},
  "geometry": {"coordinates":[-85.769443,35.682417],"type":"Point"}
}