{
  "type": "Feature",
  "properties": {
    "iso:country":"US",
    "sg:address":"513 Fernwood Dr",
    "sg:city":"Kingsport",
    "sg:classifiers":[
        {
            "category":"Manufacturing",
            "subcategory":"Wood Products",
            "type":"Manufacturing & Wholesale Goods"
        }
    ],
    "sg:phone":"+1 423 239 8567",
    "sg:postcode":"37663",
    "sg:province":"TN",
    "sg:tags":[
        "mfg"
    ],
    "wof:name":"N Wood Notes",
    "wof:placetype":"venue"
},
  "geometry": {"coordinates":[-82.498271,36.490581],"type":"Point"}
}