{
  "type": "Feature",
  "properties": {
    "addr:full":"507 Heather Pl Nashville TN 37204",
    "addr:housenumber":"507",
    "addr:postcode":"37204",
    "addr:street":"Heather Pl",
    "iso:country":"US",
    "sg:address":"507 Heather Pl",
    "sg:city":"Nashville",
    "sg:classifiers":[
        {
            "category":"Wholesale",
            "subcategory":"Furniture",
            "type":"Manufacturing & Wholesale Goods"
        }
    ],
    "sg:phone":"+1 615 397 1217",
    "sg:postcode":"37204",
    "sg:province":"TN",
    "wof:name":"R & M Furniture Transport",
    "wof:placetype":"venue"
},
  "geometry": {"coordinates":[-86.76281400000001,36.112857],"type":"Point"}
}