{
  "type": "Feature",
  "properties": {
    "iso:country":"US",
    "sg:address":"2473 Rocky Fork Rd",
    "sg:city":"Nolensville",
    "sg:classifiers":[
        {
            "category":"Professional",
            "subcategory":"Business Services",
            "type":"Services"
        }
    ],
    "sg:phone":"+1 615 776 2060",
    "sg:postcode":"37135",
    "sg:province":"TN",
    "sg:tags":[
        "recording",
        "studio"
    ],
    "sg:website":"www.billwencepromotions.com",
    "wof:name":"Bill Wence Promotions",
    "wof:placetype":"venue"
},
  "geometry": {"coordinates":[-86.627759,35.947491],"type":"Point"}
}