{
  "type": "Feature",
  "properties": {
    "addr:full":"4649 Kirby Pkwy Memphis TN 38141",
    "addr:housenumber":"4649",
    "addr:postcode":"38141",
    "addr:street":"Kirby Pkwy",
    "iso:country":"US",
    "sg:address":"4649 Kirby Pkwy",
    "sg:city":"Memphis",
    "sg:classifiers":[
        {
            "category":"Insurance",
            "subcategory":"Insurance Agent",
            "type":"Services"
        }
    ],
    "sg:phone":"+1 901 365 7690",
    "sg:postcode":"38141",
    "sg:province":"TN",
    "wof:name":"L & M Sise & Assoc",
    "wof:placetype":"venue"
},
  "geometry": {"coordinates":[-89.84876199999999,35.021784],"type":"Point"}
}