{
  "type": "Feature",
  "properties": {
    "addr:full":"6075 Winchester Rd Memphis TN 38115",
    "addr:housenumber":"6075",
    "addr:postcode":"38115",
    "addr:street":"Winchester Rd",
    "iso:country":"US",
    "sg:address":"6075 Winchester Rd",
    "sg:city":"Memphis",
    "sg:classifiers":[
        {
            "category":"Retail",
            "subcategory":"Repair Shop",
            "type":"Services"
        }
    ],
    "sg:phone":"+1 901 542 0202",
    "sg:postcode":"38115",
    "sg:province":"TN",
    "sg:tags":[
        "watch"
    ],
    "wof:name":"Treasure Time",
    "wof:placetype":"venue"
},
  "geometry": {"coordinates":[-89.85878599999999,35.049739],"type":"Point"}
}