{
  "type": "Feature",
  "properties": {
    "iso:country":"US",
    "sg:address":"2640 Upper Middle Creek Rd",
    "sg:city":"Sevierville",
    "sg:classifiers":[
        {
            "category":"Shopping",
            "subcategory":"Used Merchandise",
            "type":"Retail Goods"
        }
    ],
    "sg:phone":"+1 865 429 9886",
    "sg:postcode":"37876",
    "sg:province":"TN",
    "sg:tags":[
        "book",
        "rare",
        "dealer"
    ],
    "wof:name":"Book Heaven",
    "wof:placetype":"venue"
},
  "geometry": {"coordinates":[-83.45862200000001,35.80641],"type":"Point"}
}