{
  "type": "Feature",
  "properties": {
    "iso:country":"US",
    "sg:address":"106 S Center St",
    "sg:city":"Covington",
    "sg:classifiers":[
        {
            "category":"Home & Garden",
            "subcategory":"Hardware",
            "type":"Retail Goods"
        }
    ],
    "sg:phone":"+1 901 476 8296",
    "sg:postcode":"38017",
    "sg:province":"TN",
    "wof:name":"Covington Hardware",
    "wof:placetype":"venue"
},
  "geometry": {"coordinates":[-89.665627,35.041828],"type":"Point"}
}