{
  "type": "Feature",
  "properties": {
    "addr:full":"93 N Ocoee St Cleveland TN 37311",
    "addr:housenumber":"93",
    "addr:postcode":"37311",
    "addr:street":"N Ocoee St",
    "iso:country":"US",
    "sg:address":"93 N Ocoee St",
    "sg:city":"Cleveland",
    "sg:classifiers":[
        {
            "category":"Banks & Credit Unions",
            "subcategory":"Bank",
            "type":"Services"
        }
    ],
    "sg:phone":"+1 423 559 7532",
    "sg:postcode":"37311",
    "sg:province":"TN",
    "sg:website":"www.suntrust.com",
    "wof:name":"Sun Trust Bank",
    "wof:placetype":"venue"
},
  "geometry": {"coordinates":[-84.876009,35.159322],"type":"Point"}
}