{
  "type": "Feature",
  "properties": {
    "addr:full":"6546 Winchester Rd Memphis TN 38115",
    "addr:housenumber":"6546",
    "addr:postcode":"38115",
    "addr:street":"Winchester Rd",
    "iso:country":"US",
    "sg:address":"6546 Winchester Rd",
    "sg:city":"Memphis",
    "sg:classifiers":[
        {
            "category":"Restaurant",
            "type":"Food & Drink"
        }
    ],
    "sg:phone":"+1 901 363 3234",
    "sg:postcode":"38115",
    "sg:province":"TN",
    "sg:tags":[
        "eating"
    ],
    "wof:name":"Hardees",
    "wof:placetype":"venue"
},
  "geometry": {"coordinates":[-89.84498600000001,35.049607],"type":"Point"}
}