{
  "type": "Feature",
  "properties": {
    "iso:country":"US",
    "sg:address":"504 Autumn Springs Ct",
    "sg:city":"Franklin",
    "sg:classifiers":[
        {
            "category":"Professional",
            "subcategory":"Employment Agencies",
            "type":"Services"
        }
    ],
    "sg:phone":"+1 615 771 6835",
    "sg:postcode":"37067",
    "sg:province":"TN",
    "sg:tags":[
        "consultant",
        "search",
        "executive"
    ],
    "wof:name":"Strands Three Partners",
    "wof:placetype":"venue"
},
  "geometry": {"coordinates":[-86.827955,35.94882],"type":"Point"}
}