{
  "type": "Feature",
  "properties": {
    "iso:country":"US",
    "sg:address":"2955 Oakleigh Ln",
    "sg:city":"Germantown",
    "sg:classifiers":[
        {
            "category":"Banks & Credit Unions",
            "subcategory":"Investment Brokerage",
            "type":"Services"
        }
    ],
    "sg:phone":"+1 901 737 4243",
    "sg:postcode":"38138",
    "sg:province":"TN",
    "sg:tags":[
        "management"
    ],
    "wof:name":"KANE Investments",
    "wof:placetype":"venue"
},
  "geometry": {"coordinates":[-89.778364,35.068149],"type":"Point"}
}