{
  "type": "Feature",
  "properties": {
    "iso:country":"US",
    "sg:address":"110 S Park St",
    "sg:city":"Hohenwald",
    "sg:classifiers":[
        {
            "category":"Social Services",
            "subcategory":"Child Care",
            "type":"Services"
        }
    ],
    "sg:phone":"+1 931 796 7559",
    "sg:postcode":"38462",
    "sg:province":"TN",
    "sg:website":"www.hohenwald.org",
    "wof:name":"Hohenwald Church Of Christ",
    "wof:placetype":"venue"
},
  "geometry": {"coordinates":[-87.55255200000001,35.545733],"type":"Point"}
}