{
  "type": "Feature",
  "properties": {
    "addr:full":"1435 E Pkwy Gatlinburg TN 37738",
    "addr:housenumber":"1435",
    "addr:postcode":"37738",
    "addr:street":"E Pkwy",
    "iso:country":"US",
    "sg:address":"1435 E Pkwy",
    "sg:city":"Gatlinburg",
    "sg:classifiers":[
        {
            "category":"Shopping",
            "subcategory":"Gifts & Souvenirs",
            "type":"Retail Goods"
        }
    ],
    "sg:phone":"+1 865 430 4683",
    "sg:postcode":"37738",
    "sg:province":"TN",
    "sg:tags":[
        "shop"
    ],
    "wof:name":"Reigning Animal Crafts",
    "wof:placetype":"venue"
},
  "geometry": {"coordinates":[-83.46105,35.727755],"type":"Point"}
}