{
  "type": "Feature",
  "properties": {
    "iso:country":"US",
    "sg:address":"105 Creekside Ln",
    "sg:city":"Brentwood",
    "sg:classifiers":[
        {
            "category":"Restaurant",
            "type":"Food & Drink"
        }
    ],
    "sg:phone":"+1 615 371 9699",
    "sg:postcode":"37034",
    "sg:province":"TN",
    "sg:tags":[
        "shop",
        "coffee"
    ],
    "wof:name":"Starbucks",
    "wof:placetype":"venue"
},
  "geometry": {"coordinates":[-86.604884,35.620967],"type":"Point"}
}