{
  "type": "Feature",
  "properties": {
    "addr:full":"404 Camilla Ln Lebanon TN 37087",
    "addr:housenumber":"404",
    "addr:postcode":"37087",
    "addr:street":"Camilla Ln",
    "iso:country":"US",
    "sg:address":"404 Camilla Ln",
    "sg:city":"Lebanon",
    "sg:classifiers":[
        {
            "category":"Personal",
            "type":"Services"
        }
    ],
    "sg:phone":"+1 615 444 2712",
    "sg:postcode":"37087",
    "sg:province":"TN",
    "wof:name":"Weekend Handyman",
    "wof:placetype":"venue"
},
  "geometry": {"coordinates":[-86.283843,36.219921],"type":"Point"}
}