{
  "type": "Feature",
  "properties": {
    "iso:country":"US",
    "sg:address":"1105 S Walnut Ave",
    "sg:city":"Cookeville",
    "sg:classifiers":[
        {
            "category":"Professional",
            "subcategory":"Management & Consulting",
            "type":"Services"
        }
    ],
    "sg:phone":"+1 931 646 7100",
    "sg:postcode":"38501",
    "sg:province":"TN",
    "sg:tags":[
        "party",
        "quality",
        "third",
        "assurance"
    ],
    "wof:name":"Q S G",
    "wof:placetype":"venue"
},
  "geometry": {"coordinates":[-85.50858100000001,36.136955],"type":"Point"}
}