{
  "type": "Feature",
  "properties": {
    "iso:country":"US",
    "sg:address":"3300 W Market St",
    "sg:city":"Johnson City",
    "sg:classifiers":[
        {
            "category":"Shopping",
            "type":"Retail Goods"
        }
    ],
    "sg:phone":"+1 423 928 3307",
    "sg:postcode":"37604",
    "sg:province":"TN",
    "sg:tags":[
        "trophy",
        "medal",
        "award"
    ],
    "wof:name":"Quality Trophy & Engraving",
    "wof:placetype":"venue"
},
  "geometry": {"coordinates":[-82.41384600000001,36.312055],"type":"Point"}
}