{
  "type": "Feature",
  "properties": {
    "iso:country":"US",
    "sg:address":"9113 Lynwood Ln",
    "sg:city":"Rockford",
    "sg:classifiers":[
        {
            "category":"Professional",
            "subcategory":"Business Services",
            "type":"Services"
        }
    ],
    "sg:phone":"+1 865 983 8278",
    "sg:postcode":"37853",
    "sg:province":"TN",
    "wof:name":"Impact Associates Inc",
    "wof:placetype":"venue"
},
  "geometry": {"coordinates":[-83.878719,35.845147],"type":"Point"}
}