{
  "type": "Feature",
  "properties": {
    "iso:country":"US",
    "sg:address":"17165 US Hwy 70",
    "sg:city":"Huntingdon",
    "sg:classifiers":[
        {
            "category":"Social Services",
            "subcategory":"Child Care",
            "type":"Services"
        }
    ],
    "sg:phone":"+1 731 986 2250",
    "sg:postcode":"38344",
    "sg:province":"TN",
    "wof:name":"Sunny Slope Day Care Ctr",
    "wof:placetype":"venue"
},
  "geometry": {"coordinates":[-88.453,35.974135],"type":"Point"}
}