{
  "type": "Feature",
  "properties": {
    "addr:full":"5380 State Hwy 226 Savannah TN 38372",
    "addr:housenumber":"5380",
    "addr:postcode":"38372",
    "addr:street":"State Hwy 226",
    "iso:country":"US",
    "sg:address":"5380 State Hwy 226",
    "sg:city":"Savannah",
    "sg:classifiers":[
        {
            "category":"Retail",
            "subcategory":"Repair Shop",
            "type":"Services"
        }
    ],
    "sg:phone":"+1 731 925 2847",
    "sg:postcode":"38372",
    "sg:province":"TN",
    "sg:tags":[
        "welding"
    ],
    "wof:name":"Savannah Fabricating & Machine",
    "wof:placetype":"venue"
},
  "geometry": {"coordinates":[-88.203761,35.204064],"type":"Point"}
}