{
  "type": "Feature",
  "properties": {
    "addr:full":"1400 N Highland Ave Jackson TN 38301",
    "addr:housenumber":"1400",
    "addr:postcode":"38301",
    "addr:street":"N Highland Ave",
    "iso:country":"US",
    "sg:address":"1400 N Highland Ave",
    "sg:city":"Jackson",
    "sg:classifiers":[
        {
            "category":"Autos & Motor Vehicles",
            "subcategory":"Fuel & Gas Station",
            "type":"Retail Goods"
        }
    ],
    "sg:phone":"+1 731 422 4268",
    "sg:postcode":"38301",
    "sg:province":"TN",
    "sg:tags":[
        "oil"
    ],
    "wof:name":"Highland Park Exxon",
    "wof:placetype":"venue"
},
  "geometry": {"coordinates":[-88.823956,35.637575],"type":"Point"}
}