{
  "type": "Feature",
  "properties": {
    "addr:full":"8012 Brooks Chapel Rd Brentwood TN 37027",
    "addr:housenumber":"8012",
    "addr:postcode":"37027",
    "addr:street":"Brooks Chapel Rd",
    "iso:country":"US",
    "sg:address":"8012 Brooks Chapel Rd",
    "sg:city":"Brentwood",
    "sg:classifiers":[
        {
            "category":"Real Estate",
            "subcategory":"Real Estate Agent",
            "type":"Services"
        }
    ],
    "sg:phone":"+1 615 376 6011",
    "sg:postcode":"37027",
    "sg:province":"TN",
    "wof:name":"Tn Real Estate Elctronic",
    "wof:placetype":"venue"
},
  "geometry": {"coordinates":[-86.78581800000001,36.036254],"type":"Point"}
}