{
  "type": "Feature",
  "properties": {
    "addr:full":"1601 W Reelfoot Ave Union City TN 38261",
    "addr:housenumber":"1601",
    "addr:postcode":"38261",
    "addr:street":"W Reelfoot Ave",
    "iso:country":"US",
    "sg:address":"1601 W Reelfoot Ave",
    "sg:city":"Union City",
    "sg:classifiers":[
        {
            "category":"Cinema",
            "subcategory":"Movie Rental",
            "type":"Entertainment"
        }
    ],
    "sg:phone":"+1 731 884 0565",
    "sg:postcode":"38261",
    "sg:province":"TN",
    "sg:tags":[
        "video",
        "tape"
    ],
    "wof:name":"Movie Gallery",
    "wof:placetype":"venue"
},
  "geometry": {"coordinates":[-89.077659,36.412657],"type":"Point"}
}