{
  "type": "Feature",
  "properties": {
    "addr:full":"101 Lea Ave Nashville TN 37210",
    "addr:housenumber":"101",
    "addr:postcode":"37210",
    "addr:street":"Lea Ave",
    "iso:country":"US",
    "sg:address":"101 Lea Ave",
    "sg:city":"Nashville",
    "sg:classifiers":[
        {
            "category":"Social Services",
            "type":"Services"
        }
    ],
    "sg:phone":"+1 615 726 1065",
    "sg:postcode":"37210",
    "sg:province":"TN",
    "sg:tags":[
        "senior",
        "citizen"
    ],
    "sg:website":"www.perennialservices.com",
    "wof:name":"Perennial Services Network",
    "wof:placetype":"venue"
},
  "geometry": {"coordinates":[-86.771096,36.155626],"type":"Point"}
}