{
  "type": "Feature",
  "properties": {
    "iso:country":"US",
    "sg:address":"11 Abingdon Ct",
    "sg:city":"Brentwood",
    "sg:classifiers":[
        {
            "category":"Professional",
            "subcategory":"Business Services",
            "type":"Services"
        }
    ],
    "sg:phone":"+1 615 507 1579",
    "sg:postcode":"37027",
    "sg:province":"TN",
    "wof:name":"Huff Recording Inc",
    "wof:placetype":"venue"
},
  "geometry": {"coordinates":[-86.770455,36.047267],"type":"Point"}
}