{
  "type": "Feature",
  "properties": {
    "iso:country":"US",
    "sg:address":"6621 Benjestown Rd",
    "sg:city":"Millington",
    "sg:classifiers":[
        {
            "category":"Wholesale",
            "subcategory":"Medical Equipment & Supplies",
            "type":"Manufacturing & Wholesale Goods"
        }
    ],
    "sg:phone":"+1 901 353 3361",
    "sg:postcode":"38053",
    "sg:province":"TN",
    "sg:tags":[
        "surgical",
        "appliance"
    ],
    "wof:name":"Surgical Implant Co Inc",
    "wof:placetype":"venue"
},
  "geometry": {"coordinates":[-90.04347199999999,35.307171],"type":"Point"}
}