{
  "type": "Feature",
  "properties": {
    "addr:full":"885 Island Rd Bristol TN 24201",
    "addr:housenumber":"885",
    "addr:postcode":"24201",
    "addr:street":"Island Rd",
    "iso:country":"US",
    "sg:address":"885 Island Rd",
    "sg:city":"Bristol",
    "sg:classifiers":[
        {
            "category":"Manufacturing",
            "subcategory":"Signs",
            "type":"Manufacturing & Wholesale Goods"
        }
    ],
    "sg:phone":"+1 276 669 7254",
    "sg:postcode":"24201",
    "sg:province":"TN",
    "sg:tags":[
        "specialty",
        "mfg"
    ],
    "wof:name":"Hardin Sign Company",
    "wof:placetype":"venue"
},
  "geometry": {"coordinates":[-82.219273,36.605917],"type":"Point"}
}