{
  "type": "Feature",
  "properties": {
    "addr:full":"1836 Hwy 70 Kingston Springs TN 37082",
    "addr:housenumber":"1836",
    "addr:postcode":"37082",
    "addr:street":"Hwy 70",
    "iso:country":"US",
    "sg:address":"1836 Hwy 70",
    "sg:city":"Kingston Springs",
    "sg:classifiers":[
        {
            "category":"Organizations",
            "subcategory":"Religious Organization",
            "type":"Services"
        }
    ],
    "sg:phone":"+1 615 446 4575",
    "sg:postcode":"37082",
    "sg:province":"TN",
    "sg:tags":[
        "church"
    ],
    "wof:name":"Shacklett Church Of Christ",
    "wof:placetype":"venue"
},
  "geometry": {"coordinates":[-87.138141,36.119688],"type":"Point"}
}