{
  "type": "Feature",
  "properties": {
    "addr:full":"9022 Telecom Dr Milan TN 38358",
    "addr:postcode":"9022;38358",
    "addr:street":"Telecom Dr",
    "iso:country":"US",
    "sg:address":"9022 Telecom Dr",
    "sg:city":"Milan",
    "sg:classifiers":[
        {
            "category":"Professional",
            "type":"Services"
        }
    ],
    "sg:phone":"+1 731 686 2737",
    "sg:postcode":"38358",
    "sg:province":"TN",
    "wof:name":"Glenda Faye Houston",
    "wof:placetype":"venue"
},
  "geometry": {"coordinates":[-88.75775899999999,35.88971],"type":"Point"}
}