{
  "type": "Feature",
  "properties": {
    "iso:country":"US",
    "sg:address":"540 New Salem Rd",
    "sg:city":"Murfreesboro",
    "sg:classifiers":[
        {
            "category":"Travel",
            "subcategory":"Hotels & Motels",
            "type":"Entertainment"
        }
    ],
    "sg:phone":"+1 615 849 4084",
    "sg:postcode":"37129",
    "sg:province":"TN",
    "sg:tags":[
        "operation"
    ],
    "wof:name":"Premier Hospitality",
    "wof:placetype":"venue"
},
  "geometry": {"coordinates":[-86.408287,35.842731],"type":"Point"}
}