{
  "type": "Feature",
  "properties": {
    "iso:country":"US",
    "sg:address":"6747 Bauxhall Dr",
    "sg:city":"Germantown",
    "sg:classifiers":[
        {
            "category":"Professional",
            "subcategory":"Management & Consulting",
            "type":"Services"
        }
    ],
    "sg:phone":"+1 901 755 9285",
    "sg:postcode":"38138",
    "sg:province":"TN",
    "sg:tags":[
        "business"
    ],
    "wof:name":"H H & Associates LLC",
    "wof:placetype":"venue"
},
  "geometry": {"coordinates":[-89.83755600000001,35.096115],"type":"Point"}
}