{
  "type": "Feature",
  "properties": {
    "iso:country":"US",
    "sg:address":"114 Hilltop Dr",
    "sg:city":"Shelbyville",
    "sg:classifiers":[
        {
            "category":"Food & Beverages",
            "subcategory":"Specialty",
            "type":"Retail Goods"
        }
    ],
    "sg:phone":"+1 931 680 0356",
    "sg:postcode":"37160",
    "sg:province":"TN",
    "wof:name":"Wallace & Associates",
    "wof:placetype":"venue"
},
  "geometry": {"coordinates":[-86.470269,35.457249],"type":"Point"}
}