{
  "type": "Feature",
  "properties": {
    "iso:country":"US",
    "sg:address":"850 Matthew Ct",
    "sg:city":"Kingston Springs",
    "sg:classifiers":[
        {
            "category":"Professional",
            "subcategory":"Business Services",
            "type":"Services"
        }
    ],
    "sg:phone":"+1 615 952 5843",
    "sg:postcode":"37082",
    "sg:province":"TN",
    "wof:name":"Texpatriate",
    "wof:placetype":"venue"
},
  "geometry": {"coordinates":[-87.133488,36.071098],"type":"Point"}
}