{
  "type": "Feature",
  "properties": {
    "iso:country":"US",
    "sg:address":"587 S 4th St",
    "sg:city":"Memphis",
    "sg:classifiers":[
        {
            "category":"Organizations",
            "subcategory":"Religious Organization",
            "type":"Services"
        }
    ],
    "sg:phone":"+1 901 946 7104",
    "sg:postcode":"38126",
    "sg:province":"TN",
    "wof:name":"General Assembly of Christn Ch",
    "wof:placetype":"venue"
},
  "geometry": {"coordinates":[-90.050516,35.130484],"type":"Point"}
}