{
  "type": "Feature",
  "properties": {
    "iso:country":"US",
    "sg:address":"158 Luna St",
    "sg:city":"Decaturville",
    "sg:classifiers":[
        {
            "category":"Government",
            "subcategory":"Office",
            "type":"Public Place"
        }
    ],
    "sg:phone":"+1 731 852 4822",
    "sg:postcode":"38329",
    "sg:province":"TN",
    "sg:tags":[
        "county",
        "program"
    ],
    "wof:name":"Decatur Solid Waste",
    "wof:placetype":"venue"
},
  "geometry": {"coordinates":[-88.117062,35.58467],"type":"Point"}
}