{
  "type": "Feature",
  "properties": {
    "addr:full":"506 S Harrison St Knoxville TN 37914",
    "addr:housenumber":"506",
    "addr:postcode":"37914",
    "addr:street":"S Harrison St",
    "iso:country":"US",
    "sg:address":"506 S Harrison St",
    "sg:city":"Knoxville",
    "sg:classifiers":[
        {
            "category":"Restaurant",
            "type":"Food & Drink"
        }
    ],
    "sg:phone":"+1 865 522 0872",
    "sg:postcode":"37914",
    "sg:province":"TN",
    "wof:name":"Maxxs Deli",
    "wof:placetype":"venue"
},
  "geometry": {"coordinates":[-83.887755,35.984822],"type":"Point"}
}