{
  "type": "Feature",
  "properties": {
    "iso:country":"US",
    "sg:address":"26 N Main St",
    "sg:city":"Memphis",
    "sg:classifiers":[
        {
            "category":"Shopping",
            "subcategory":"Clothing, Apparel, & Fashions",
            "type":"Retail Goods"
        }
    ],
    "sg:phone":"+1 901 888 2099",
    "sg:postcode":"38103",
    "sg:province":"TN",
    "sg:tags":[
        "hat"
    ],
    "wof:name":"Mister Hats",
    "wof:placetype":"venue"
},
  "geometry": {"coordinates":[-90.052454,35.1459],"type":"Point"}
}