{
  "type": "Feature",
  "properties": {
    "iso:country":"US",
    "sg:address":"2103 Forest Dr",
    "sg:city":"Gray",
    "sg:classifiers":[
        {
            "category":"Health Services",
            "subcategory":"Doctor",
            "type":"Services"
        }
    ],
    "sg:phone":"+1 423 477 2885",
    "sg:postcode":"37615",
    "sg:province":"TN",
    "sg:tags":[
        "physician",
        "surgeon",
        "medical"
    ],
    "sg:website":"www.beansprouts.com",
    "wof:name":"Gray Station Primary Care",
    "wof:placetype":"venue"
},
  "geometry": {"coordinates":[-82.473991,36.410737],"type":"Point"}
}