{
  "type": "Feature",
  "properties": {
    "iso:country":"US",
    "sg:address":"222 2nd Ave N",
    "sg:city":"Nashville",
    "sg:classifiers":[
        {
            "category":"Utilities",
            "subcategory":"Mobile Phone",
            "type":"Services"
        }
    ],
    "sg:phone":"+1 615 345 4700",
    "sg:postcode":"37201",
    "sg:province":"TN",
    "sg:tags":[
        "communication",
        "radiotelephone",
        "merchandise"
    ],
    "wof:name":"Sprint",
    "wof:placetype":"venue"
},
  "geometry": {"coordinates":[-86.77642899999999,36.163869],"type":"Point"}
}