{
  "type": "Feature",
  "properties": {
    "addr:full":"6296 Quince Rd Memphis TN 38119",
    "addr:housenumber":"6296",
    "addr:postcode":"38119",
    "addr:street":"Quince Rd",
    "iso:country":"US",
    "sg:address":"6296 Quince Rd",
    "sg:city":"Memphis",
    "sg:classifiers":[
        {
            "category":"Communications",
            "subcategory":"Film & Video Production",
            "type":"Services"
        }
    ],
    "sg:phone":"+1 901 374 0680",
    "sg:postcode":"38119",
    "sg:province":"TN",
    "sg:tags":[
        "taping"
    ],
    "wof:name":"Robin Scott Enterprises",
    "wof:placetype":"venue"
},
  "geometry": {"coordinates":[-89.852075,35.082406],"type":"Point"}
}