{
  "type": "Feature",
  "properties": {
    "iso:country":"US",
    "sg:address":"4970 Raleigh Lagrange Rd # 1",
    "sg:city":"Memphis",
    "sg:classifiers":[
        {
            "category":"Real Estate",
            "subcategory":"Real Estate Services",
            "type":"Services"
        },
        {
            "category":"Banks & Credit Unions",
            "subcategory":"Financial Services",
            "type":"Services"
        }
    ],
    "sg:phone":"+1 901 383 2810",
    "sg:postcode":"38128",
    "sg:province":"TN",
    "sg:tags":[
        "loan",
        "mortgage"
    ],
    "wof:name":"Advanced Trust Mortgage",
    "wof:placetype":"venue"
},
  "geometry": {"coordinates":[-89.89808600000001,35.194492],"type":"Point"}
}