{
  "type": "Feature",
  "properties": {
    "iso:country":"US",
    "sg:address":"111 Union Valley Rd",
    "sg:city":"Oak Ridge",
    "sg:classifiers":[
        {
            "category":"Professional",
            "subcategory":"Engineering",
            "type":"Services"
        }
    ],
    "sg:phone":"+1 865 483 8622",
    "sg:postcode":"37830",
    "sg:province":"TN",
    "wof:name":"Foster Wheeler",
    "wof:placetype":"venue"
},
  "geometry": {"coordinates":[-84.22801200000001,35.998771],"type":"Point"}
}