{
  "type": "Feature",
  "properties": {
    "iso:country":"US",
    "sg:address":"3308 Wilkinson Pike",
    "sg:city":"Maryville",
    "sg:classifiers":[
        {
            "category":"Personal",
            "subcategory":"Beauty Salon",
            "type":"Services"
        }
    ],
    "sg:phone":"+1 865 983 2777",
    "sg:postcode":"37803",
    "sg:province":"TN",
    "sg:tags":[
        "manicuring"
    ],
    "wof:name":"Bremon's Nail Salon",
    "wof:placetype":"venue"
},
  "geometry": {"coordinates":[-83.92043200000001,35.71399],"type":"Point"}
}