{
  "type": "Feature",
  "properties": {
    "iso:country":"US",
    "sg:address":"66 N Main St",
    "sg:city":"Memphis",
    "sg:classifiers":[
        {
            "category":"Government",
            "subcategory":"Court House",
            "type":"Public Place"
        }
    ],
    "sg:phone":"+1 901 523 0159",
    "sg:postcode":"38103",
    "sg:province":"TN",
    "sg:tags":[
        "justice"
    ],
    "wof:name":"Court Square Center",
    "wof:placetype":"venue"
},
  "geometry": {"coordinates":[-90.052104,35.146935],"type":"Point"}
}