{
  "type": "Feature",
  "properties": {
    "iso:country":"US",
    "sg:address":"1022 Jones Blvd",
    "sg:city":"Murfreesboro",
    "sg:classifiers":[
        {
            "category":"Building & Trades",
            "subcategory":"Cleaning & Sanitation",
            "type":"Services"
        }
    ],
    "sg:phone":"+1 615 895 7238",
    "sg:postcode":"37129",
    "sg:province":"TN",
    "sg:tags":[
        "maintenance"
    ],
    "wof:name":"Yaninas Cleaning Services",
    "wof:placetype":"venue"
},
  "geometry": {"coordinates":[-86.400054,35.858952],"type":"Point"}
}