{
  "type": "Feature",
  "properties": {
    "addr:full":"3320 Perimeter Hill Dr Nashville TN 37211",
    "addr:housenumber":"3320",
    "addr:postcode":"37211",
    "addr:street":"Perimeter Hill Dr",
    "iso:country":"US",
    "sg:address":"3320 Perimeter Hill Dr",
    "sg:city":"Nashville",
    "sg:classifiers":[
        {
            "category":"Banks & Credit Unions",
            "subcategory":"Investment Brokerage",
            "type":"Services"
        }
    ],
    "sg:phone":"+1 615 333 6343",
    "sg:postcode":"37211",
    "sg:province":"TN",
    "sg:tags":[
        "retirement",
        "planning"
    ],
    "wof:name":"Paper Industry Union Mgmt",
    "wof:placetype":"venue"
},
  "geometry": {"coordinates":[-86.691581,36.08488],"type":"Point"}
}