{
  "type": "Feature",
  "properties": {
    "iso:country":"US",
    "sg:address":"4 Worth Cir",
    "sg:city":"Johnson City",
    "sg:classifiers":[
        {
            "category":"Retail",
            "subcategory":"Laundry & Dry Cleaning",
            "type":"Services"
        }
    ],
    "sg:phone":"+1 423 610 7172",
    "sg:postcode":"37601",
    "sg:province":"TN",
    "sg:tags":[
        "cleaners",
        "rug",
        "carpet"
    ],
    "sg:website":"www.vortexdrying.com",
    "wof:name":"East Tennessee Restorations",
    "wof:placetype":"venue"
},
  "geometry": {"coordinates":[-82.367014,36.352161],"type":"Point"}
}