{
  "type": "Feature",
  "properties": {
    "iso:country":"US",
    "sg:address":"2049 Nashville Hwy",
    "sg:city":"Columbia",
    "sg:classifiers":[
        {
            "category":"Wholesale",
            "subcategory":"Electrical",
            "type":"Manufacturing & Wholesale Goods"
        }
    ],
    "sg:phone":"+1 931 381 3322",
    "sg:postcode":"38401",
    "sg:province":"TN",
    "sg:tags":[
        "equipment",
        "electronic"
    ],
    "wof:name":"Sct Systems",
    "wof:placetype":"venue"
},
  "geometry": {"coordinates":[-86.997947,35.681606],"type":"Point"}
}