{
  "type": "Feature",
  "properties": {
    "addr:full":"2100 Hamilton Place Blvd Chattanooga TN 37421",
    "addr:housenumber":"2100",
    "addr:postcode":"37421",
    "addr:street":"Hamilton Place Blvd",
    "iso:country":"US",
    "sg:address":"2100 Hamilton Place Blvd",
    "sg:city":"Chattanooga",
    "sg:classifiers":[
        {
            "category":"Shopping",
            "subcategory":"Clothing, Apparel, & Fashions",
            "type":"Retail Goods"
        }
    ],
    "sg:phone":"+1 423 899 7437",
    "sg:postcode":"37421",
    "sg:province":"TN",
    "sg:tags":[
        "item",
        "boutique"
    ],
    "wof:name":"Claire's Boutique",
    "wof:placetype":"venue"
},
  "geometry": {"coordinates":[-85.161187,35.036544],"type":"Point"}
}