{
  "type": "Feature",
  "properties": {
    "iso:country":"US",
    "sg:address":"4327 Elvis Presley Blvd",
    "sg:city":"Memphis",
    "sg:classifiers":[
        {
            "category":"Organizations",
            "subcategory":"Religious Organization",
            "type":"Services"
        }
    ],
    "sg:phone":"+1 901 332 5723",
    "sg:postcode":"38116",
    "sg:province":"TN",
    "sg:tags":[
        "school",
        "church"
    ],
    "wof:name":"Eternal Mercy Lutheran Church",
    "wof:placetype":"venue"
},
  "geometry": {"coordinates":[-90.025248,35.030294],"type":"Point"}
}