{
  "type": "Feature",
  "properties": {
    "iso:country":"US",
    "sg:address":"19 Sweet Springs Rd",
    "sg:city":"Kelso",
    "sg:classifiers":[
        {
            "category":"Manufacturing",
            "subcategory":"Tools & Machinery",
            "type":"Manufacturing & Wholesale Goods"
        }
    ],
    "sg:phone":"+1 931 937 8438",
    "sg:postcode":"37348",
    "sg:province":"TN",
    "sg:tags":[
        "machine",
        "shop"
    ],
    "wof:name":"Billy's Machine Shop",
    "wof:placetype":"venue"
},
  "geometry": {"coordinates":[-86.481672,35.102442],"type":"Point"}
}