{
  "type": "Feature",
  "properties": {
    "addr:full":"2799 Bransford Ave Nashville TN 37204",
    "addr:housenumber":"2799",
    "addr:postcode":"37204",
    "addr:street":"Bransford Ave",
    "iso:country":"US",
    "sg:address":"2799 Bransford Ave",
    "sg:city":"Nashville",
    "sg:classifiers":[
        {
            "category":"Professional",
            "subcategory":"Management & Consulting",
            "type":"Services"
        }
    ],
    "sg:phone":"+1 615 385 5355",
    "sg:postcode":"37204",
    "sg:province":"TN",
    "sg:tags":[
        "business"
    ],
    "wof:name":"M W C America",
    "wof:placetype":"venue"
},
  "geometry": {"coordinates":[-86.766246,36.117605],"type":"Point"}
}