{
  "type": "Feature",
  "properties": {
    "iso:country":"US",
    "sg:address":"1298 N Highland Ave",
    "sg:city":"Jackson",
    "sg:classifiers":[
        {
            "category":"Health Services",
            "subcategory":"Chiropractor",
            "type":"Services"
        }
    ],
    "sg:phone":"+1 731 422 6761",
    "sg:postcode":"38301",
    "sg:province":"TN",
    "wof:name":"Vitale Chiropractic",
    "wof:placetype":"venue"
},
  "geometry": {"coordinates":[-88.820105,35.635644],"type":"Point"}
}