{
  "type": "Feature",
  "properties": {
    "iso:country":"US",
    "sg:address":"1061 Cosby Hwy",
    "sg:city":"Newport",
    "sg:classifiers":[
        {
            "category":"Personal",
            "subcategory":"Beauty Salon",
            "type":"Services"
        }
    ],
    "sg:phone":"+1 423 613 4449",
    "sg:postcode":"37821",
    "sg:province":"TN",
    "sg:tags":[
        "shop"
    ],
    "wof:name":"Q Nails",
    "wof:placetype":"venue"
},
  "geometry": {"coordinates":[-83.207708,35.943944],"type":"Point"}
}