{
  "type": "Feature",
  "properties": {
    "iso:country":"US",
    "sg:address":"115 E Main St",
    "sg:city":"Lebanon",
    "sg:classifiers":[
        {
            "category":"Professional",
            "subcategory":"Lawyer & Legal Services",
            "type":"Services"
        }
    ],
    "sg:phone":"+1 615 444 4740",
    "sg:postcode":"37087",
    "sg:province":"TN",
    "sg:tags":[
        "attorney"
    ],
    "wof:name":"Christensen Legal Svc",
    "wof:placetype":"venue"
},
  "geometry": {"coordinates":[-86.290626,36.207998],"type":"Point"}
}