{
  "type": "Feature",
  "properties": {
    "iso:country":"US",
    "sg:address":"1201 Hilton Rd",
    "sg:city":"Knoxville",
    "sg:classifiers":[
        {
            "category":"Retail",
            "subcategory":"Repair Shop",
            "type":"Services"
        },
        {
            "category":"Manufacturing",
            "subcategory":"Electronics",
            "type":"Manufacturing & Wholesale Goods"
        }
    ],
    "sg:phone":"+1 865 558 5770",
    "sg:postcode":"37921",
    "sg:province":"TN",
    "sg:tags":[
        "equipment",
        "home",
        "mfg",
        "communication"
    ],
    "wof:name":"Advanced Sound X",
    "wof:placetype":"venue"
},
  "geometry": {"coordinates":[-84.002612,35.954435],"type":"Point"}
}