{
  "type": "Feature",
  "properties": {
    "iso:country":"US",
    "sg:address":"555 Hwy 25 W",
    "sg:city":"Castalian Spgs",
    "sg:classifiers":[
        {
            "category":"Autos & Motor Vehicles",
            "subcategory":"Automobile Sales",
            "type":"Retail Goods"
        }
    ],
    "sg:phone":"+1 615 374 9900",
    "sg:postcode":"37031",
    "sg:province":"TN",
    "sg:tags":[
        "car",
        "dealer"
    ],
    "wof:name":"Cross Roads Motors",
    "wof:placetype":"venue"
},
  "geometry": {"coordinates":[-86.261582,36.388857],"type":"Point"}
}