{
  "type": "Feature",
  "properties": {
    "addr:full":"120 Broad St Kingsport TN 37660",
    "addr:housenumber":"120",
    "addr:postcode":"37660",
    "addr:street":"Broad St",
    "iso:country":"US",
    "sg:address":"120 Broad St",
    "sg:city":"Kingsport",
    "sg:classifiers":[
        {
            "category":"Personal",
            "subcategory":"Beauty Salon",
            "type":"Services"
        }
    ],
    "sg:phone":"+1 423 245 2006",
    "sg:postcode":"37660",
    "sg:province":"TN",
    "wof:name":"Spa Difference Day Spa",
    "wof:placetype":"venue"
},
  "geometry": {"coordinates":[-82.561894,36.545233],"type":"Point"}
}