{
  "type": "Feature",
  "properties": {
    "iso:country":"US",
    "sg:address":"3582 Kings Rd",
    "sg:city":"Chattanooga",
    "sg:classifiers":[
        {
            "category":"Building & Trades",
            "subcategory":"Construction",
            "type":"Services"
        }
    ],
    "sg:phone":"+1 423 622 0313",
    "sg:postcode":"37416",
    "sg:province":"TN",
    "sg:tags":[
        "wallpaper"
    ],
    "wof:name":"Carter Wall Design",
    "wof:placetype":"venue"
},
  "geometry": {"coordinates":[-85.205994,35.097187],"type":"Point"}
}