{
  "type": "Feature",
  "properties": {
    "iso:country":"US",
    "sg:address":"117 Auto Dr",
    "sg:city":"Maryville",
    "sg:classifiers":[
        {
            "category":"Utilities",
            "subcategory":"Refuse",
            "type":"Services"
        }
    ],
    "sg:phone":"+1 865 856 8676",
    "sg:postcode":"37801",
    "sg:province":"TN",
    "sg:tags":[
        "system",
        "business"
    ],
    "wof:name":"Maryville Waste Oil Products",
    "wof:placetype":"venue"
},
  "geometry": {"coordinates":[-84.115892,35.651316],"type":"Point"}
}