{
  "type": "Feature",
  "properties": {
    "addr:full":"820 Crossland Ave Clarksville TN 37040",
    "addr:housenumber":"820",
    "addr:postcode":"37040",
    "addr:street":"Crossland Ave",
    "iso:country":"US",
    "sg:address":"820 Crossland Ave",
    "sg:city":"Clarksville",
    "sg:classifiers":[
        {
            "category":"Autos & Motor Vehicles",
            "subcategory":"Automobile Sales",
            "type":"Retail Goods"
        }
    ],
    "sg:phone":"+1 931 647 8732",
    "sg:postcode":"37040",
    "sg:province":"TN",
    "sg:tags":[
        "car",
        "used",
        "dealer"
    ],
    "wof:name":"Terrell's Auto Sales",
    "wof:placetype":"venue"
},
  "geometry": {"coordinates":[-87.347982,36.519802],"type":"Point"}
}