{
  "type": "Feature",
  "properties": {
    "iso:country":"US",
    "sg:address":"4030 Lamar Ave",
    "sg:city":"Memphis",
    "sg:classifiers":[
        {
            "category":"Travel",
            "subcategory":"Hotels & Motels",
            "type":"Entertainment"
        }
    ],
    "sg:phone":"+1 901 362 5700",
    "sg:postcode":"38118",
    "sg:province":"TN",
    "sg:tags":[
        "operation"
    ],
    "wof:name":"Budget Inn",
    "wof:placetype":"venue"
},
  "geometry": {"coordinates":[-89.930528,35.055651],"type":"Point"}
}