{
  "type": "Feature",
  "properties": {
    "addr:full":"527 W Broadway Ave Maryville TN 37801",
    "addr:housenumber":"527",
    "addr:postcode":"37801",
    "addr:street":"W Broadway Ave",
    "iso:country":"US",
    "sg:address":"527 W Broadway Ave",
    "sg:city":"Maryville",
    "sg:classifiers":[
        {
            "category":"Food & Beverages",
            "subcategory":"Groceries & Convenience Stores",
            "type":"Retail Goods"
        }
    ],
    "sg:phone":"+1 865 681 1346",
    "sg:postcode":"37801",
    "sg:province":"TN",
    "wof:name":"Mr Gas",
    "wof:placetype":"venue"
},
  "geometry": {"coordinates":[-83.97655399999999,35.751026],"type":"Point"}
}