{
  "type": "Feature",
  "properties": {
    "iso:country":"US",
    "sg:address":"119 Sycamore St",
    "sg:city":"Whiteville",
    "sg:classifiers":[
        {
            "category":"Retail",
            "subcategory":"Laundry & Dry Cleaning",
            "type":"Services"
        }
    ],
    "sg:phone":"+1 731 254 8461",
    "sg:postcode":"38075",
    "sg:province":"TN",
    "sg:tags":[
        "drycleaning",
        "plant",
        "agent",
        "garment"
    ],
    "wof:name":"Whiteville Cleaners",
    "wof:placetype":"venue"
},
  "geometry": {"coordinates":[-89.150702,35.325594],"type":"Point"}
}