{
  "type": "Feature",
  "properties": {
    "addr:full":"117 Lee Parkway Dr Chattanooga TN 37421",
    "addr:housenumber":"117",
    "addr:postcode":"37421",
    "addr:street":"Lee Parkway Dr",
    "iso:country":"US",
    "sg:address":"117 Lee Parkway Dr",
    "sg:city":"Chattanooga",
    "sg:classifiers":[
        {
            "category":"Professional",
            "subcategory":"Advertising",
            "type":"Services"
        }
    ],
    "sg:phone":"+1 423 643 2200",
    "sg:postcode":"37421",
    "sg:province":"TN",
    "sg:tags":[
        "agency",
        "specialty"
    ],
    "sg:website":"http://www.watsonadvertising.com",
    "wof:name":"Watson Advertising",
    "wof:placetype":"venue"
},
  "geometry": {"coordinates":[-85.16177399999999,35.04714],"type":"Point"}
}