{
  "type": "Feature",
  "properties": {
    "addr:full":"7124 Burkesville Hwy Celina TN 38551",
    "addr:housenumber":"7124",
    "addr:postcode":"38551",
    "addr:street":"Burkesville Hwy",
    "iso:country":"US",
    "sg:address":"7124 Burkesville Hwy",
    "sg:city":"Celina",
    "sg:classifiers":[
        {
            "category":"Travel",
            "subcategory":"Hotels & Motels",
            "type":"Entertainment"
        }
    ],
    "sg:phone":"+1 931 243 3053",
    "sg:postcode":"38551",
    "sg:province":"TN",
    "sg:tags":[
        "operation"
    ],
    "wof:name":"Pea Ridge Haven Rentals",
    "wof:placetype":"venue"
},
  "geometry": {"coordinates":[-85.42131500000001,36.613397],"type":"Point"}
}