{
  "type": "Feature",
  "properties": {
    "iso:country":"US",
    "sg:address":"2104 Madison Ave",
    "sg:city":"Memphis",
    "sg:classifiers":[
        {
            "category":"Professional",
            "subcategory":"Management & Consulting",
            "type":"Services"
        },
        {
            "category":"Restaurant",
            "type":"Food & Drink"
        }
    ],
    "sg:phone":"+1 901 278 0087",
    "sg:postcode":"38104",
    "sg:province":"TN",
    "wof:name":"Roma Pomodori Inc",
    "wof:placetype":"venue"
},
  "geometry": {"coordinates":[-89.99114400000001,35.136825],"type":"Point"}
}