{
  "type": "Feature",
  "properties": {
    "iso:country":"US",
    "sg:address":"478 Timmons St",
    "sg:city":"Nashville",
    "sg:classifiers":[
        {
            "category":"Retail",
            "subcategory":"Repair Shop",
            "type":"Services"
        }
    ],
    "sg:phone":"+1 615 474 7814",
    "sg:postcode":"37211",
    "sg:province":"TN",
    "sg:tags":[
        "lock",
        "locksmith"
    ],
    "wof:name":"A Plus A Locksmith",
    "wof:placetype":"venue"
},
  "geometry": {"coordinates":[-86.74431,36.107494],"type":"Point"}
}