{
  "type": "Feature",
  "properties": {
    "iso:country":"US",
    "sg:address":"33 Shadow Lawn Dr",
    "sg:city":"Jackson",
    "sg:classifiers":[
        {
            "category":"Retail",
            "subcategory":"Repair Shop",
            "type":"Services"
        }
    ],
    "sg:phone":"+1 731 424 9610",
    "sg:postcode":"38301",
    "sg:province":"TN",
    "sg:tags":[
        "clocks",
        "parts"
    ],
    "wof:name":"Alan Mcleary Clock Repair Co",
    "wof:placetype":"venue"
},
  "geometry": {"coordinates":[-88.838228,35.634882],"type":"Point"}
}