{
  "type": "Feature",
  "properties": {
    "addr:full":"2711 Knott Rd NW Knoxville TN 37921",
    "addr:housenumber":"2711",
    "addr:postcode":"37921",
    "addr:street":"Knott Rd Nw",
    "iso:country":"US",
    "sg:address":"2711 Knott Rd NW",
    "sg:city":"Knoxville",
    "sg:classifiers":[
        {
            "category":"Freight",
            "type":"Transportation"
        }
    ],
    "sg:phone":"+1 865 588 6499",
    "sg:postcode":"37921",
    "sg:province":"TN",
    "sg:tags":[
        "dry",
        "distance",
        "hauler",
        "long",
        "trucking",
        "bulk"
    ],
    "sg:website":"www.kenanadvantagegroup.com",
    "wof:name":"Kenan Transport Company",
    "wof:placetype":"venue"
},
  "geometry": {"coordinates":[-84.00394799999999,35.965562],"type":"Point"}
}