{
  "type": "Feature",
  "properties": {
    "iso:country":"US",
    "sg:address":"514 Walker St NW",
    "sg:city":"Knoxville",
    "sg:classifiers":[
        {
            "category":"Shopping",
            "subcategory":"Bicycles & Sporting Goods",
            "type":"Retail Goods"
        }
    ],
    "sg:phone":"+1 865 525 4606",
    "sg:postcode":"37919",
    "sg:province":"TN",
    "sg:tags":[
        "specialized"
    ],
    "wof:name":"Earth Traverse Outfitters",
    "wof:placetype":"venue"
},
  "geometry": {"coordinates":[-83.963691,35.955373],"type":"Point"}
}