{
  "type": "Feature",
  "properties": {
    "addr:full":"3904 October Woods Dr Antioch TN 37013",
    "addr:housenumber":"3904",
    "addr:postcode":"37013",
    "addr:street":"October Woods Dr",
    "iso:country":"US",
    "sg:address":"3904 October Woods Dr",
    "sg:city":"Antioch",
    "sg:classifiers":[
        {
            "category":"Real Estate",
            "subcategory":"Real Estate Agent",
            "type":"Services"
        }
    ],
    "sg:phone":"+1 615 941 1718",
    "sg:postcode":"37013",
    "sg:province":"TN",
    "wof:name":"Lifestyles Sales/October Woods",
    "wof:placetype":"venue"
},
  "geometry": {"coordinates":[-86.623453,36.009182],"type":"Point"}
}