{
  "type": "Feature",
  "properties": {
    "addr:full":"1040 Ladys Way Newport TN 37821",
    "addr:housenumber":"1040",
    "addr:postcode":"37821",
    "addr:street":"Ladys Way",
    "iso:country":"US",
    "sg:address":"1040 Ladys Way",
    "sg:city":"Newport",
    "sg:classifiers":[
        {
            "category":"Farming",
            "subcategory":"Farm",
            "type":"Manufacturing & Wholesale Goods"
        }
    ],
    "sg:phone":"+1 423 623 2260",
    "sg:postcode":"37821",
    "sg:province":"TN",
    "sg:tags":[
        "crop",
        "general"
    ],
    "wof:name":"Robert Tucker",
    "wof:placetype":"venue"
},
  "geometry": {"coordinates":[-83.15639299999999,35.952859],"type":"Point"}
}