{
  "type": "Feature",
  "properties": {
    "addr:full":"1829 E Brooks Rd Memphis TN 38116",
    "addr:housenumber":"1829",
    "addr:postcode":"38116",
    "addr:street":"E Brooks Rd",
    "iso:country":"US",
    "sg:address":"1829 E Brooks Rd",
    "sg:city":"Memphis",
    "sg:classifiers":[
        {
            "category":"Freight",
            "type":"Transportation"
        }
    ],
    "sg:phone":"+1 901 346 4700",
    "sg:postcode":"38116",
    "sg:province":"TN",
    "sg:tags":[
        "trucking"
    ],
    "wof:name":"C & J Enterprise",
    "wof:placetype":"venue"
},
  "geometry": {"coordinates":[-90.002387,35.060826],"type":"Point"}
}