{
  "type": "Feature",
  "properties": {
    "iso:country":"US",
    "sg:address":"2690 Asheville Hwy",
    "sg:city":"Greeneville",
    "sg:classifiers":[
        {
            "category":"Retail",
            "subcategory":"Repair Shop",
            "type":"Services"
        }
    ],
    "sg:phone":"+1 423 638 2579",
    "sg:postcode":"37743",
    "sg:province":"TN",
    "sg:tags":[
        "engine",
        "machine"
    ],
    "wof:name":"Myers Engine & Machine Shop",
    "wof:placetype":"venue"
},
  "geometry": {"coordinates":[-82.865206,36.116561],"type":"Point"}
}