{
  "type": "Feature",
  "properties": {
    "iso:country":"US",
    "sg:address":"103 Arcaro Pl",
    "sg:city":"Brentwood",
    "sg:classifiers":[
        {
            "category":"Real Estate",
            "subcategory":"Real Estate Operator",
            "type":"Services"
        }
    ],
    "sg:phone":"+1 615 376 9299",
    "sg:postcode":"37027",
    "sg:province":"TN",
    "sg:tags":[
        "property",
        "lessor"
    ],
    "wof:name":"Elsie Shoup Farm",
    "wof:placetype":"venue"
},
  "geometry": {"coordinates":[-86.814762,36.037964],"type":"Point"}
}