{
  "type": "Feature",
  "properties": {
    "addr:full":"3457 Lamar Ave Memphis TN 38118",
    "addr:housenumber":"3457",
    "addr:postcode":"38118",
    "addr:street":"Lamar Ave",
    "iso:country":"US",
    "sg:address":"3457 Lamar Ave",
    "sg:city":"Memphis",
    "sg:classifiers":[
        {
            "category":"Real Estate",
            "subcategory":"Real Estate Agent",
            "type":"Services"
        }
    ],
    "sg:phone":"+1 901 795 7592",
    "sg:postcode":"38118",
    "sg:province":"TN",
    "sg:tags":[
        "agency",
        "rental"
    ],
    "wof:name":"Grand Rental Station",
    "wof:placetype":"venue"
},
  "geometry": {"coordinates":[-89.94875500000001,35.074317],"type":"Point"}
}