{
  "type": "Feature",
  "properties": {
    "addr:full":"5705 Stage Rd Memphis TN 38134",
    "addr:housenumber":"5705",
    "addr:postcode":"38134",
    "addr:street":"Stage Rd",
    "iso:country":"US",
    "sg:address":"5705 Stage Rd",
    "sg:city":"Memphis",
    "sg:classifiers":[
        {
            "category":"Professional",
            "subcategory":"Credit Reporting & Collection",
            "type":"Services"
        }
    ],
    "sg:phone":"+1 901 575 3393",
    "sg:postcode":"38134",
    "sg:province":"TN",
    "sg:tags":[
        "agency"
    ],
    "sg:website":"www.collectmore.net",
    "wof:name":"Arco Collection Co",
    "wof:placetype":"venue"
},
  "geometry": {"coordinates":[-89.871371,35.204129],"type":"Point"}
}