{
  "type": "Feature",
  "properties": {
    "iso:country":"US",
    "sg:address":"1902 Columbia Ave",
    "sg:city":"Franklin",
    "sg:classifiers":[
        {
            "category":"Building & Trades",
            "subcategory":"Construction",
            "type":"Services"
        }
    ],
    "sg:phone":"+1 615 791 0093",
    "sg:postcode":"37064",
    "sg:province":"TN",
    "sg:tags":[
        "builder",
        "operative"
    ],
    "wof:name":"Cameron Motors",
    "wof:placetype":"venue"
},
  "geometry": {"coordinates":[-86.876272,35.898677],"type":"Point"}
}