{
  "type": "Feature",
  "properties": {
    "iso:country":"US",
    "sg:address":"514 Tyrone Dr",
    "sg:city":"Mount Juliet",
    "sg:classifiers":[
        {
            "category":"Real Estate",
            "subcategory":"Real Estate Agent",
            "type":"Services"
        }
    ],
    "sg:phone":"+1 615 758 6486",
    "sg:postcode":"37122",
    "sg:province":"TN",
    "wof:name":"Billy R Medley",
    "wof:placetype":"venue"
},
  "geometry": {"coordinates":[-86.534646,36.248205],"type":"Point"}
}