{
  "type": "Feature",
  "properties": {
    "iso:country":"US",
    "sg:address":"4766 Tuggle Rd",
    "sg:city":"Memphis",
    "sg:classifiers":[
        {
            "category":"Building & Trades",
            "subcategory":"Construction",
            "type":"Services"
        }
    ],
    "sg:phone":"+1 901 794 2090",
    "sg:postcode":"38118",
    "sg:province":"TN",
    "sg:tags":[
        "paving",
        "contractor"
    ],
    "wof:name":"APAC Tennessee Inc",
    "wof:placetype":"venue"
},
  "geometry": {"coordinates":[-89.8886,35.018771],"type":"Point"}
}