{
  "type": "Feature",
  "properties": {
    "addr:full":"101 US Hwy 51 S Covington TN 38019",
    "addr:housenumber":"101",
    "addr:postcode":"38019",
    "addr:street":"Us Hwy 51 S",
    "iso:country":"US",
    "sg:address":"101 US Hwy 51 S",
    "sg:city":"Covington",
    "sg:classifiers":[
        {
            "category":"Autos & Motor Vehicles",
            "subcategory":"Automobile Sales",
            "type":"Retail Goods"
        }
    ],
    "sg:phone":"+1 901 476 7505",
    "sg:postcode":"38019",
    "sg:province":"TN",
    "sg:tags":[
        "car",
        "dealer"
    ],
    "wof:name":"Quality Used Cars",
    "wof:placetype":"venue"
},
  "geometry": {"coordinates":[-89.64979099999999,35.563815],"type":"Point"}
}