{
  "type": "Feature",
  "properties": {
    "addr:full":"4655 Nolensville Pike Nashville TN 37211",
    "addr:housenumber":"4655",
    "addr:postcode":"37211",
    "addr:street":"Nolensville Pike",
    "iso:country":"US",
    "sg:address":"4655 Nolensville Pike",
    "sg:city":"Nashville",
    "sg:classifiers":[
        {
            "category":"Health Services",
            "subcategory":"Health Practitioner",
            "type":"Services"
        }
    ],
    "sg:phone":"+1 615 781 1224",
    "sg:postcode":"37211",
    "sg:province":"TN",
    "sg:tags":[
        "acupuncture"
    ],
    "wof:name":"Dr Lu Acupunture PC",
    "wof:placetype":"venue"
},
  "geometry": {"coordinates":[-86.71911,36.068207],"type":"Point"}
}