{
  "type": "Feature",
  "properties": {
    "iso:country":"US",
    "sg:address":"202 N Cumberland St",
    "sg:city":"Lebanon",
    "sg:classifiers":[
        {
            "category":"Retail",
            "subcategory":"Auto Repair",
            "type":"Services"
        }
    ],
    "sg:phone":"+1 615 444 1588",
    "sg:postcode":"37087",
    "sg:province":"TN",
    "sg:tags":[
        "repairing",
        "automobile"
    ],
    "wof:name":"Midas Auto Svc Experts",
    "wof:placetype":"venue"
},
  "geometry": {"coordinates":[-86.290803,36.210373],"type":"Point"}
}