{
  "type": "Feature",
  "properties": {
    "iso:country":"US",
    "sg:address":"8115 Kerry Dr",
    "sg:city":"Cordova",
    "sg:classifiers":[
        {
            "category":"Professional",
            "subcategory":"Detective & Security Services",
            "type":"Services"
        }
    ],
    "sg:phone":"+1 901 753 1633",
    "sg:postcode":"38018",
    "sg:province":"TN",
    "sg:tags":[
        "system"
    ],
    "wof:name":"Shadow Access System",
    "wof:placetype":"venue"
},
  "geometry": {"coordinates":[-89.791873,35.138571],"type":"Point"}
}