{
  "type": "Feature",
  "properties": {
    "iso:country":"US",
    "sg:address":"111 Bosley Springs Rd",
    "sg:city":"Nashville",
    "sg:classifiers":[
        {
            "category":"Banks & Credit Unions",
            "subcategory":"Bank",
            "type":"Services"
        }
    ],
    "sg:phone":"+1 615 292 7928",
    "sg:postcode":"37205",
    "sg:province":"TN",
    "sg:website":"www.stthomascu.org",
    "wof:name":"St Thomas Hospital Empl CU",
    "wof:placetype":"venue"
},
  "geometry": {"coordinates":[-86.84428200000001,36.127712],"type":"Point"}
}