{
  "type": "Feature",
  "properties": {
    "addr:full":"150 Commerce St Kingsport TN 37660",
    "addr:housenumber":"150",
    "addr:postcode":"37660",
    "addr:street":"Commerce St",
    "iso:country":"US",
    "sg:address":"150 Commerce St",
    "sg:city":"Kingsport",
    "sg:classifiers":[
        {
            "category":"Wholesale",
            "subcategory":"Electrical",
            "type":"Manufacturing & Wholesale Goods"
        }
    ],
    "sg:phone":"+1 423 246 4716",
    "sg:postcode":"37660",
    "sg:province":"TN",
    "sg:tags":[
        "electronic",
        "contractor"
    ],
    "wof:name":"Ideacom Technologies Inc",
    "wof:placetype":"venue"
},
  "geometry": {"coordinates":[-82.353571,36.317571],"type":"Point"}
}