{
  "type": "Feature",
  "properties": {
    "addr:full":"942 Fred Hill Rd Sparta TN 38583",
    "addr:housenumber":"942",
    "addr:postcode":"38583",
    "addr:street":"Fred Hill Rd",
    "iso:country":"US",
    "sg:address":"942 Fred Hill Rd",
    "sg:city":"Sparta",
    "sg:classifiers":[
        {
            "category":"Autos & Motor Vehicles",
            "subcategory":"Recreational Vehicle Sales",
            "type":"Retail Goods"
        }
    ],
    "sg:phone":"+1 931 739 9275",
    "sg:postcode":"38583",
    "sg:province":"TN",
    "sg:tags":[
        "travel",
        "trailer"
    ],
    "wof:name":"Sparta Trailer World",
    "wof:placetype":"venue"
},
  "geometry": {"coordinates":[-85.49435,35.921119],"type":"Point"}
}