{
  "type": "Feature",
  "properties": {
    "iso:country":"US",
    "sg:address":"600 Stills Rd",
    "sg:city":"Greeneville",
    "sg:classifiers":[
        {
            "category":"Organizations",
            "subcategory":"Religious Organization",
            "type":"Services"
        }
    ],
    "sg:phone":"+1 423 798 0898",
    "sg:postcode":"37743",
    "sg:province":"TN",
    "sg:tags":[
        "church"
    ],
    "wof:name":"Still Water Church",
    "wof:placetype":"venue"
},
  "geometry": {"coordinates":[-82.890733,36.086166],"type":"Point"}
}