{
  "type": "Feature",
  "properties": {
    "iso:country":"US",
    "sg:address":"109 S McCrary St",
    "sg:city":"Woodbury",
    "sg:classifiers":[
        {
            "category":"Government",
            "subcategory":"Office",
            "type":"Public Place"
        }
    ],
    "sg:phone":"+1 615 563 4321",
    "sg:postcode":"37190",
    "sg:province":"TN",
    "sg:tags":[
        "federal"
    ],
    "wof:name":"US Consolidated Farm Svc Agcy",
    "wof:placetype":"venue"
},
  "geometry": {"coordinates":[-86.068755,35.827439],"type":"Point"}
}