{
  "type": "Feature",
  "properties": {
    "iso:country":"US",
    "sg:address":"133 East Dr",
    "sg:city":"Hendersonville",
    "sg:classifiers":[
        {
            "category":"Professional",
            "subcategory":"Business Services",
            "type":"Services"
        }
    ],
    "sg:phone":"+1 615 822 0766",
    "sg:postcode":"37075",
    "sg:province":"TN",
    "wof:name":"Manning & Associates Inc",
    "wof:placetype":"venue"
},
  "geometry": {"coordinates":[-86.590107,36.283044],"type":"Point"}
}