{
  "type": "Feature",
  "properties": {
    "iso:country":"US",
    "sg:address":"3009 Greenline Rd",
    "sg:city":"Johnson City",
    "sg:classifiers":[
        {
            "category":"Restaurant",
            "type":"Food & Drink"
        }
    ],
    "sg:phone":"+1 423 283 0666",
    "sg:postcode":"37604",
    "sg:province":"TN",
    "sg:tags":[
        "eating"
    ],
    "wof:name":"China Chef Chinese Restaurant",
    "wof:placetype":"venue"
},
  "geometry": {"coordinates":[-82.397423,36.351353],"type":"Point"}
}