{
  "type": "Feature",
  "properties": {
    "iso:country":"US",
    "sg:address":"4785 State Hwy 58",
    "sg:city":"Chattanooga",
    "sg:classifiers":[
        {
            "category":"Sports & Exercise",
            "subcategory":"Gym",
            "type":"Entertainment"
        }
    ],
    "sg:phone":"+1 423 490 0009",
    "sg:postcode":"37416",
    "sg:province":"TN",
    "sg:tags":[
        "fitness",
        "physical",
        "facility"
    ],
    "wof:name":"Virginia Moss Co",
    "wof:placetype":"venue"
},
  "geometry": {"coordinates":[-85.189717,35.087606],"type":"Point"}
}