{
  "type": "Feature",
  "properties": {
    "iso:country":"US",
    "sg:address":"1330 Cason Ln",
    "sg:city":"Murfreesboro",
    "sg:classifiers":[
        {
            "category":"Education",
            "subcategory":"School",
            "type":"Public Place"
        }
    ],
    "sg:phone":"+1 615 898 7145",
    "sg:postcode":"37128",
    "sg:province":"TN",
    "wof:name":"Cason Lane Academy",
    "wof:placetype":"venue"
},
  "geometry": {"coordinates":[-86.44355400000001,35.82189],"type":"Point"}
}