{
  "type": "Feature",
  "properties": {
    "iso:country":"US",
    "sg:address":"820 Templeton Dr",
    "sg:city":"Nashville",
    "sg:classifiers":[
        {
            "category":"Retail",
            "subcategory":"Animal Services",
            "type":"Services"
        }
    ],
    "sg:phone":"+1 615 352 0843",
    "sg:postcode":"37205",
    "sg:province":"TN",
    "sg:tags":[
        "pet",
        "breeder"
    ],
    "wof:name":"Shadowland Australian Shepherd",
    "wof:placetype":"venue"
},
  "geometry": {"coordinates":[-86.891969,36.132676],"type":"Point"}
}