{
  "type": "Feature",
  "properties": {
    "iso:country":"US",
    "sg:address":"2408 Bella Vista Ln",
    "sg:city":"Knoxville",
    "sg:classifiers":[
        {
            "category":"Building & Trades",
            "subcategory":"Plumbing",
            "type":"Services"
        }
    ],
    "sg:phone":"+1 865 740 7821",
    "sg:postcode":"37914",
    "sg:province":"TN",
    "sg:tags":[
        "plumbing",
        "contractor"
    ],
    "wof:name":"Plumber's R Us",
    "wof:placetype":"venue"
},
  "geometry": {"coordinates":[-83.746019,35.970749],"type":"Point"}
}