{
  "type": "Feature",
  "properties": {
    "addr:full":"200 Dodge Dr Nashville TN 37210",
    "addr:housenumber":"200",
    "addr:postcode":"37210",
    "addr:street":"Dodge Dr",
    "iso:country":"US",
    "sg:address":"200 Dodge Dr",
    "sg:city":"Nashville",
    "sg:classifiers":[
        {
            "category":"Social Services",
            "subcategory":"Child Care",
            "type":"Services"
        }
    ],
    "sg:phone":"+1 615 254 6474",
    "sg:postcode":"37210",
    "sg:province":"TN",
    "sg:tags":[
        "day"
    ],
    "wof:name":"Miss Lndas Pre-School Day Care",
    "wof:placetype":"venue"
},
  "geometry": {"coordinates":[-86.7299,36.124635],"type":"Point"}
}