{
  "type": "Feature",
  "properties": {
    "iso:country":"US",
    "sg:address":"2966 Austin Peay Hwy",
    "sg:city":"Memphis",
    "sg:classifiers":[
        {
            "category":"Retail",
            "subcategory":"Auto Repair",
            "type":"Services"
        }
    ],
    "sg:phone":"+1 954 491 3800",
    "sg:postcode":"38128",
    "sg:province":"TN",
    "sg:tags":[
        "wholesale",
        "radio",
        "au",
        "automotive"
    ],
    "wof:name":"Gold Coast Autotronics Inc",
    "wof:placetype":"venue"
},
  "geometry": {"coordinates":[-89.921436,35.20742],"type":"Point"}
}