{
  "type": "Feature",
  "properties": {
    "iso:country":"US",
    "sg:address":"1889 Chester Harris Rd",
    "sg:city":"Woodlawn",
    "sg:classifiers":[
        {
            "category":"Wholesale",
            "subcategory":"Sporting Goods",
            "type":"Manufacturing & Wholesale Goods"
        },
        {
            "category":"Wholesale",
            "subcategory":"Non-durable Goods",
            "type":"Manufacturing & Wholesale Goods"
        }
    ],
    "sg:phone":"+1 931 920 2941",
    "sg:postcode":"37191",
    "sg:province":"TN",
    "sg:tags":[
        "bait",
        "fishing"
    ],
    "wof:name":"Bowles Wholesale Bait Inc",
    "wof:placetype":"venue"
},
  "geometry": {"coordinates":[-87.47881,36.47632],"type":"Point"}
}