{
  "type": "Feature",
  "properties": {
    "iso:country":"US",
    "sg:address":"147 Bill Buck Ln",
    "sg:city":"Gainesboro",
    "sg:classifiers":[
        {
            "category":"Farming",
            "subcategory":"Farm & Veterinary Services",
            "type":"Manufacturing & Wholesale Goods"
        }
    ],
    "sg:phone":"+1 931 268 0819",
    "sg:postcode":"38562",
    "sg:province":"TN",
    "sg:tags":[
        "livestock"
    ],
    "wof:name":"Billy C Buck",
    "wof:placetype":"venue"
},
  "geometry": {"coordinates":[-85.557535,36.43587],"type":"Point"}
}