{
  "type": "Feature",
  "properties": {
    "iso:country":"US",
    "sg:address":"2205 Oasis Ln",
    "sg:city":"Kingsport",
    "sg:classifiers":[
        {
            "category":"Recreation",
            "subcategory":"Arcade",
            "type":"Entertainment"
        }
    ],
    "sg:phone":"+1 423 245 3890",
    "sg:postcode":"37660",
    "sg:province":"TN",
    "sg:tags":[
        "device",
        "operator",
        "amusement"
    ],
    "wof:name":"B & S Amusement",
    "wof:placetype":"venue"
},
  "geometry": {"coordinates":[-82.574387,36.506283],"type":"Point"}
}