{
  "type": "Feature",
  "properties": {
    "addr:full":"9736 Dayton Pike Soddy Daisy TN 37379",
    "addr:housenumber":"9736",
    "addr:postcode":"37379",
    "addr:street":"Dayton Pike",
    "iso:country":"US",
    "sg:address":"9736 Dayton Pike",
    "sg:city":"Soddy Daisy",
    "sg:classifiers":[
        {
            "category":"Health Services",
            "subcategory":"Doctor",
            "type":"Services"
        }
    ],
    "sg:phone":"+1 423 332 8222",
    "sg:postcode":"37379",
    "sg:province":"TN",
    "sg:tags":[
        "physician",
        "surgeon",
        "medical"
    ],
    "wof:name":"Complete Eye Care PC",
    "wof:placetype":"venue"
},
  "geometry": {"coordinates":[-85.189517,35.244605],"type":"Point"}
}