{
  "type": "Feature",
  "properties": {
    "addr:full":"347 Berry Branch Rd Mountain City TN 37683",
    "addr:housenumber":"347",
    "addr:postcode":"37683",
    "addr:street":"Berry Branch Rd",
    "iso:country":"US",
    "sg:address":"347 Berry Branch Rd",
    "sg:city":"Mountain City",
    "sg:classifiers":[
        {
            "category":"Organizations",
            "subcategory":"Community Association",
            "type":"Services"
        }
    ],
    "sg:phone":"+1 423 727 8062",
    "sg:postcode":"37683",
    "sg:province":"TN",
    "wof:name":"International Assoc of LI",
    "wof:placetype":"venue"
},
  "geometry": {"coordinates":[-81.83246200000001,36.495618],"type":"Point"}
}