{
  "type": "Feature",
  "properties": {
    "addr:full":"510 W Main St Greeneville TN 37743",
    "addr:housenumber":"510",
    "addr:postcode":"37743",
    "addr:street":"W Main St",
    "iso:country":"US",
    "sg:address":"510 W Main St",
    "sg:city":"Greeneville",
    "sg:classifiers":[
        {
            "category":"Professional",
            "subcategory":"Secretarial Services",
            "type":"Services"
        }
    ],
    "sg:phone":"+1 423 639 0254",
    "sg:postcode":"37743",
    "sg:province":"TN",
    "sg:tags":[
        "reporting"
    ],
    "wof:name":"Star Enterprises",
    "wof:placetype":"venue"
},
  "geometry": {"coordinates":[-82.83738700000001,36.158702],"type":"Point"}
}