{
  "type": "Feature",
  "properties": {
    "iso:country":"US",
    "sg:address":"1880 Leo Baker Rd",
    "sg:city":"Ashland City",
    "sg:classifiers":[
        {
            "category":"Farming",
            "subcategory":"Nursery",
            "type":"Manufacturing & Wholesale Goods"
        }
    ],
    "sg:phone":"+1 615 307 3596",
    "sg:postcode":"37015",
    "sg:province":"TN",
    "sg:tags":[
        "ornamental",
        "tobacco",
        "beef",
        "farm",
        "crop",
        "field",
        "cattle"
    ],
    "wof:name":"Charles Head Farms",
    "wof:placetype":"venue"
},
  "geometry": {"coordinates":[-87.145852,36.403925],"type":"Point"}
}