{
  "type": "Feature",
  "properties": {
    "iso:country":"US",
    "sg:address":"14981 US Hwy 431",
    "sg:city":"Hazel Green",
    "sg:classifiers":[
        {
            "category":"Recreation",
            "type":"Entertainment"
        }
    ],
    "sg:phone":"+1 256 828 1921",
    "sg:postcode":"35750",
    "sg:province":"TN",
    "sg:tags":[
        "instruction",
        "gymnastic"
    ],
    "wof:name":"North Alabama Cheernastics",
    "wof:placetype":"venue"
},
  "geometry": {"coordinates":[-86.570808,34.955701],"type":"Point"}
}