{
  "type": "Feature",
  "properties": {
    "iso:country":"US",
    "sg:address":"1714 General George Patton Dr",
    "sg:city":"Brentwood",
    "sg:classifiers":[
        {
            "category":"Freight",
            "type":"Transportation"
        }
    ],
    "sg:phone":"+1 615 371 8030",
    "sg:postcode":"37027",
    "sg:province":"TN",
    "sg:tags":[
        "commercial",
        "storage",
        "general"
    ],
    "wof:name":"Brentwood Self Storage",
    "wof:placetype":"venue"
},
  "geometry": {"coordinates":[-86.820843,35.965528],"type":"Point"}
}