{
  "type": "Feature",
  "properties": {
    "iso:country":"US",
    "sg:address":"330 Polly Rd",
    "sg:city":"Pulaski",
    "sg:classifiers":[
        {
            "category":"Building & Trades",
            "subcategory":"Plumbing",
            "type":"Services"
        }
    ],
    "sg:phone":"+1 931 363 6628",
    "sg:postcode":"38478",
    "sg:province":"TN",
    "sg:tags":[
        "conditioning",
        "contractor",
        "system",
        "air"
    ],
    "wof:name":"Commercial One Heating & Coolg",
    "wof:placetype":"venue"
},
  "geometry": {"coordinates":[-86.96623,35.124751],"type":"Point"}
}