{
  "type": "Feature",
  "properties": {
    "iso:country":"US",
    "sg:address":"2912 Pleasant Grove Pl SW",
    "sg:city":"Cleveland",
    "sg:classifiers":[
        {
            "category":"Building & Trades",
            "subcategory":"Construction",
            "type":"Services"
        }
    ],
    "sg:phone":"+1 423 478 5254",
    "sg:postcode":"37311",
    "sg:province":"TN",
    "sg:tags":[
        "downspouts",
        "gutter"
    ],
    "wof:name":"Streamline Seamless Guttering",
    "wof:placetype":"venue"
},
  "geometry": {"coordinates":[-84.91740299999999,35.150507],"type":"Point"}
}