{
  "type": "Feature",
  "properties": {
    "iso:country":"US",
    "sg:address":"3552 Talahi Dr SW",
    "sg:city":"Knoxville",
    "sg:classifiers":[
        {
            "category":"Retail",
            "subcategory":"Repair Shop",
            "type":"Services"
        }
    ],
    "sg:phone":"+1 865 659 2077",
    "sg:postcode":"37919",
    "sg:province":"TN",
    "sg:tags":[
        "repairing",
        "piano",
        "refinishing"
    ],
    "wof:name":"Seven Takvoryan",
    "wof:placetype":"venue"
},
  "geometry": {"coordinates":[-83.957166,35.935746],"type":"Point"}
}