{
  "type": "Feature",
  "properties": {
    "iso:country":"US",
    "sg:address":"1401 Poplar Ln",
    "sg:city":"Nashville",
    "sg:classifiers":[
        {
            "category":"Professional",
            "type":"Services"
        }
    ],
    "sg:phone":"+1 615 259 5121",
    "sg:postcode":"37210",
    "sg:province":"TN",
    "sg:website":"www.ashleysling.com",
    "wof:name":"Ashley Sling Inc",
    "wof:placetype":"venue"
},
  "geometry": {"coordinates":[-86.72614799999999,36.141505],"type":"Point"}
}