{
  "type": "Feature",
  "properties": {
    "iso:country":"US",
    "sg:address":"402 Kelly Hills Rd",
    "sg:city":"Sevierville",
    "sg:classifiers":[
        {
            "category":"Building & Trades",
            "subcategory":"Construction",
            "type":"Services"
        }
    ],
    "sg:phone":"+1 865 453 1611",
    "sg:postcode":"37876",
    "sg:province":"TN",
    "sg:tags":[
        "concrete",
        "pumping",
        "contractor"
    ],
    "wof:name":"Volunteer Concrete Pumping",
    "wof:placetype":"venue"
},
  "geometry": {"coordinates":[-83.42440499999999,35.892354],"type":"Point"}
}