{
  "type": "Feature",
  "properties": {
    "iso:country":"US",
    "sg:address":"1843 Air Lane Dr",
    "sg:city":"Nashville",
    "sg:classifiers":[
        {
            "category":"Real Estate",
            "subcategory":"Architect",
            "type":"Services"
        }
    ],
    "sg:phone":"+1 615 254 7590",
    "sg:postcode":"37210",
    "sg:province":"TN",
    "sg:website":"www.archaffinc.com",
    "wof:name":"Architectural Affiliates",
    "wof:placetype":"venue"
},
  "geometry": {"coordinates":[-86.697191,36.14787],"type":"Point"}
}