{
  "type": "Feature",
  "properties": {
    "addr:full":"239 Adams Ave Memphis TN 38103",
    "addr:housenumber":"239",
    "addr:postcode":"38103",
    "addr:street":"Adams Ave",
    "iso:country":"US",
    "sg:address":"239 Adams Ave",
    "sg:city":"Memphis",
    "sg:classifiers":[
        {
            "category":"Professional",
            "subcategory":"Lawyer & Legal Services",
            "type":"Services"
        }
    ],
    "sg:phone":"+1 901 525 0257",
    "sg:postcode":"38103",
    "sg:province":"TN",
    "sg:tags":[
        "attorney",
        "practice"
    ],
    "sg:website":"http://www.memphisattorney.com",
    "wof:name":"Field, Roscoe Law Office Of",
    "wof:placetype":"venue"
},
  "geometry": {"coordinates":[-90.04693,35.146928],"type":"Point"}
}