{
  "type": "Feature",
  "properties": {
    "addr:full":"7734 Castlehill Ct Powell TN 37849",
    "addr:housenumber":"7734",
    "addr:postcode":"37849",
    "addr:street":"Castlehill Ct",
    "iso:country":"US",
    "sg:address":"7734 Castlehill Ct",
    "sg:city":"Powell",
    "sg:classifiers":[
        {
            "category":"Autos & Motor Vehicles",
            "subcategory":"Auto Supplies",
            "type":"Retail Goods"
        }
    ],
    "sg:phone":"+1 865 805 3966",
    "sg:postcode":"37849",
    "sg:province":"TN",
    "wof:name":"Super Grip Industrial Tire",
    "wof:placetype":"venue"
},
  "geometry": {"coordinates":[-84.036777,36.028911],"type":"Point"}
}