{
  "type": "Feature",
  "properties": {
    "iso:country":"US",
    "sg:address":"3505 Nolensville Pike",
    "sg:city":"Nashville",
    "sg:classifiers":[
        {
            "category":"Health Services",
            "subcategory":"Doctor",
            "type":"Services"
        }
    ],
    "sg:phone":"+1 615 781 8272",
    "sg:postcode":"37211",
    "sg:province":"TN",
    "wof:name":"Bright Judith S Ms DDS",
    "wof:placetype":"venue"
},
  "geometry": {"coordinates":[-86.73901499999999,36.098584],"type":"Point"}
}