{
  "type": "Feature",
  "properties": {
    "iso:country":"US",
    "sg:address":"2093 Thomas Rd",
    "sg:city":"Memphis",
    "sg:classifiers":[
        {
            "category":"Building & Trades",
            "subcategory":"Construction",
            "type":"Services"
        }
    ],
    "sg:phone":"+1 901 373 5394",
    "sg:postcode":"38134",
    "sg:province":"TN",
    "sg:tags":[
        "fire",
        "restoration",
        "damage"
    ],
    "sg:website":"www.pdrestoration.com",
    "wof:name":"Paul Davis Restoration",
    "wof:placetype":"venue"
},
  "geometry": {"coordinates":[-89.88768399999999,35.185147],"type":"Point"}
}