{
  "type": "Feature",
  "properties": {
    "iso:country":"US",
    "sg:address":"4566 Old Manchester Hwy",
    "sg:city":"Tullahoma",
    "sg:classifiers":[
        {
            "category":"Organizations",
            "subcategory":"Religious Organization",
            "type":"Services"
        }
    ],
    "sg:phone":"+1 931 455 1737",
    "sg:postcode":"37388",
    "sg:province":"TN",
    "sg:tags":[
        "church"
    ],
    "wof:name":"Hickerson Station Chr-Christ",
    "wof:placetype":"venue"
},
  "geometry": {"coordinates":[-86.14066200000001,35.400545],"type":"Point"}
}