{
  "type": "Feature",
  "properties": {
    "iso:country":"US",
    "sg:address":"732 Elm St",
    "sg:city":"Martin",
    "sg:classifiers":[
        {
            "category":"Retail",
            "subcategory":"Auto Repair",
            "type":"Services"
        }
    ],
    "sg:phone":"+1 731 587 5200",
    "sg:postcode":"38237",
    "sg:province":"TN",
    "sg:tags":[
        "repairing",
        "automobile"
    ],
    "wof:name":"E & C Garage",
    "wof:placetype":"venue"
},
  "geometry": {"coordinates":[-88.85332099999999,36.334092],"type":"Point"}
}