{
  "type": "Feature",
  "properties": {
    "addr:full":"3974 Sulphur Spring Branch Rd Columbia TN 38401",
    "addr:housenumber":"3974",
    "addr:postcode":"38401",
    "addr:street":"Sulphur Spring Branch Rd",
    "iso:country":"US",
    "sg:address":"3974 Sulphur Spring Branch Rd",
    "sg:city":"Columbia",
    "sg:classifiers":[
        {
            "category":"Building & Trades",
            "subcategory":"Construction",
            "type":"Services"
        }
    ],
    "sg:phone":"+1 615 790 7085",
    "sg:postcode":"38401",
    "sg:province":"TN",
    "sg:tags":[
        "ceiling"
    ],
    "wof:name":"Advanced Acoustic",
    "wof:placetype":"venue"
},
  "geometry": {"coordinates":[-87.04914100000001,35.789348],"type":"Point"}
}