{
  "type": "Feature",
  "properties": {
    "iso:country":"US",
    "sg:address":"1300 Latta St",
    "sg:city":"Chattanooga",
    "sg:classifiers":[
        {
            "category":"Shopping",
            "type":"Retail Goods"
        },
        {
            "category":"Building & Trades",
            "subcategory":"Equipment Rental",
            "type":"Services"
        }
    ],
    "sg:phone":"+1 423 624 2070",
    "sg:postcode":"37406",
    "sg:province":"TN",
    "sg:tags":[
        "party",
        "wedding",
        "supply"
    ],
    "wof:name":"Show Time Event Rentals Inc",
    "wof:placetype":"venue"
},
  "geometry": {"coordinates":[-85.265203,35.069364],"type":"Point"}
}