{
  "type": "Feature",
  "properties": {
    "iso:country":"US",
    "sg:address":"219 W Main St",
    "sg:city":"Murfreesboro",
    "sg:classifiers":[
        {
            "category":"Shopping",
            "type":"Retail Goods"
        }
    ],
    "sg:phone":"+1 615 895 2301",
    "sg:postcode":"37129",
    "sg:province":"TN",
    "sg:tags":[
        "equipment",
        "care",
        "health",
        "home"
    ],
    "sg:website":"www.musiccitymedical.com",
    "wof:name":"Music City Medical Supply",
    "wof:placetype":"venue"
},
  "geometry": {"coordinates":[-86.39369600000001,35.846119],"type":"Point"}
}