{
  "type": "Feature",
  "properties": {
    "iso:country":"US",
    "sg:address":"3406 Bedford Ln",
    "sg:city":"Germantown",
    "sg:classifiers":[
        {
            "category":"Insurance",
            "subcategory":"Insurance Agent",
            "type":"Services"
        }
    ],
    "sg:phone":"+1 901 854 7323",
    "sg:postcode":"38139",
    "sg:province":"TN",
    "wof:name":"David Burch",
    "wof:placetype":"venue"
},
  "geometry": {"coordinates":[-89.73809799999999,35.056182],"type":"Point"}
}