{
  "type": "Feature",
  "properties": {
    "addr:full":"49 Conrad Dr Jackson TN 38305",
    "addr:housenumber":"49",
    "addr:postcode":"38305",
    "addr:street":"Conrad Dr",
    "iso:country":"US",
    "sg:address":"49 Conrad Dr",
    "sg:city":"Jackson",
    "sg:classifiers":[
        {
            "category":"Health Services",
            "subcategory":"Clinic",
            "type":"Services"
        }
    ],
    "sg:phone":"+1 731 668 7061",
    "sg:postcode":"38305",
    "sg:province":"TN",
    "sg:tags":[
        "specialty",
        "outpatient"
    ],
    "wof:name":"Impact Centers Inc",
    "wof:placetype":"venue"
},
  "geometry": {"coordinates":[-88.849288,35.645521],"type":"Point"}
}