{
  "type": "Feature",
  "properties": {
    "iso:country":"US",
    "sg:address":"10133 Sherrill Blvd",
    "sg:city":"Knoxville",
    "sg:classifiers":[
        {
            "category":"Professional",
            "subcategory":"Engineering",
            "type":"Services"
        }
    ],
    "sg:phone":"+1 865 637 2810",
    "sg:postcode":"37932",
    "sg:province":"TN",
    "sg:tags":[
        "engineer"
    ],
    "wof:name":"Barge Waggoner Sumner & Cannon",
    "wof:placetype":"venue"
},
  "geometry": {"coordinates":[-84.12246,35.916563],"type":"Point"}
}