{
  "type": "Feature",
  "properties": {
    "addr:full":"1669 Kirby Pkwy Memphis TN 38120",
    "addr:housenumber":"1669",
    "addr:postcode":"38120",
    "addr:street":"Kirby Pkwy",
    "iso:country":"US",
    "sg:address":"1669 Kirby Pkwy",
    "sg:city":"Memphis",
    "sg:classifiers":[
        {
            "category":"Wholesale",
            "subcategory":"Stationery",
            "type":"Manufacturing & Wholesale Goods"
        }
    ],
    "sg:phone":"+1 901 753 8161",
    "sg:postcode":"38120",
    "sg:province":"TN",
    "sg:tags":[
        "supply",
        "f",
        "manifold",
        "business",
        "mfg"
    ],
    "wof:name":"Moore North America",
    "wof:placetype":"venue"
},
  "geometry": {"coordinates":[-89.84136700000001,35.103397],"type":"Point"}
}