{
  "type": "Feature",
  "properties": {
    "addr:full":"1910 Decherd Blvd Decherd TN 37324",
    "addr:housenumber":"1910",
    "addr:postcode":"37324",
    "addr:street":"Decherd Blvd",
    "iso:country":"US",
    "sg:address":"1910 Decherd Blvd",
    "sg:city":"Decherd",
    "sg:classifiers":[
        {
            "category":"Banks & Credit Unions",
            "subcategory":"Bank",
            "type":"Services"
        }
    ],
    "sg:phone":"+1 931 967 5516",
    "sg:postcode":"37324",
    "sg:province":"TN",
    "sg:website":"www.usbank.com",
    "wof:name":"US Bank",
    "wof:placetype":"venue"
},
  "geometry": {"coordinates":[-86.09412399999999,35.207405],"type":"Point"}
}