{
  "type": "Feature",
  "properties": {
    "addr:full":"3801 Sevierville Pike Knoxville TN 37920",
    "addr:housenumber":"3801",
    "addr:postcode":"37920",
    "addr:street":"Sevierville Pike",
    "iso:country":"US",
    "sg:address":"3801 Sevierville Pike",
    "sg:city":"Knoxville",
    "sg:classifiers":[
        {
            "category":"Personal",
            "subcategory":"Beauty Salon",
            "type":"Services"
        }
    ],
    "sg:phone":"+1 865 577 0414",
    "sg:postcode":"37920",
    "sg:province":"TN",
    "wof:name":"Casual Cuts & Styles",
    "wof:placetype":"venue"
},
  "geometry": {"coordinates":[-83.88827999999999,35.944532],"type":"Point"}
}