{
  "type": "Feature",
  "properties": {
    "addr:full":"601 Mayes Pl Columbia TN 38401",
    "addr:housenumber":"601",
    "addr:postcode":"38401",
    "addr:street":"Mayes Pl",
    "iso:country":"US",
    "sg:address":"601 Mayes Pl",
    "sg:city":"Columbia",
    "sg:classifiers":[
        {
            "category":"Professional",
            "subcategory":"Business Services",
            "type":"Services"
        }
    ],
    "sg:phone":"+1 931 381 9374",
    "sg:postcode":"38401",
    "sg:province":"TN",
    "sg:tags":[
        "interior",
        "consultant",
        "design",
        "decorator"
    ],
    "wof:name":"Interiors Inc",
    "wof:placetype":"venue"
},
  "geometry": {"coordinates":[-87.038185,35.61818],"type":"Point"}
}