{
  "type": "Feature",
  "properties": {
    "iso:country":"US",
    "sg:address":"525 E Main St",
    "sg:city":"Jackson",
    "sg:classifiers":[
        {
            "category":"Social Services",
            "subcategory":"Child Care",
            "type":"Services"
        }
    ],
    "sg:phone":"+1 731 422 4253",
    "sg:postcode":"38301",
    "sg:province":"TN",
    "sg:tags":[
        "day"
    ],
    "wof:name":"Kids Village Learning Center",
    "wof:placetype":"venue"
},
  "geometry": {"coordinates":[-88.813205,35.614224],"type":"Point"}
}