{
  "type": "Feature",
  "properties": {
    "iso:country":"US",
    "sg:address":"20515 E Main St",
    "sg:city":"Huntingdon",
    "sg:classifiers":[
        {
            "category":"Banks & Credit Unions",
            "subcategory":"Bank",
            "type":"Services"
        }
    ],
    "sg:phone":"+1 731 209 1640",
    "sg:postcode":"38344",
    "sg:province":"TN",
    "wof:name":"Carroll Bank & Trust",
    "wof:placetype":"venue"
},
  "geometry": {"coordinates":[-88.408801,36.006259],"type":"Point"}
}