{
  "type": "Feature",
  "properties": {
    "addr:full":"7154 Oak Ridge Hwy Knoxville TN 37931",
    "addr:housenumber":"7154",
    "addr:postcode":"37931",
    "addr:street":"Oak Ridge Hwy",
    "iso:country":"US",
    "sg:address":"7154 Oak Ridge Hwy",
    "sg:city":"Knoxville",
    "sg:classifiers":[
        {
            "category":"Retail",
            "subcategory":"Car Wash",
            "type":"Services"
        }
    ],
    "sg:phone":"+1 865 769 4070",
    "sg:postcode":"37931",
    "sg:province":"TN",
    "sg:tags":[
        "polishing",
        "washing"
    ],
    "wof:name":"Express Shine Auto Wash",
    "wof:placetype":"venue"
},
  "geometry": {"coordinates":[-84.074595,35.990042],"type":"Point"}
}