{
  "type": "Feature",
  "properties": {
    "iso:country":"US",
    "sg:address":"7053 Germantown Trl",
    "sg:city":"Memphis",
    "sg:classifiers":[
        {
            "category":"Building & Trades",
            "subcategory":"Construction",
            "type":"Services"
        }
    ],
    "sg:phone":"+1 901 751 6606",
    "sg:postcode":"38125",
    "sg:province":"TN",
    "sg:tags":[
        "system",
        "specialty",
        "heating",
        "contractor",
        "air conditioning"
    ],
    "wof:name":"M&W Heating And Air Conditioning",
    "wof:placetype":"venue"
},
  "geometry": {"coordinates":[-89.827815,35.012238],"type":"Point"}
}