{
  "type": "Feature",
  "properties": {
    "addr:full":"9047 Executive Park Dr NW Knoxville TN 37923",
    "addr:housenumber":"9047",
    "addr:postcode":"37923",
    "addr:street":"Executive Park Dr Nw",
    "iso:country":"US",
    "sg:address":"9047 Executive Park Dr NW",
    "sg:city":"Knoxville",
    "sg:classifiers":[
        {
            "category":"Professional",
            "subcategory":"Research",
            "type":"Services"
        }
    ],
    "sg:phone":"+1 865 694 9099",
    "sg:postcode":"37923",
    "sg:province":"TN",
    "sg:tags":[
        "integrator",
        "optical",
        "inspection",
        "system"
    ],
    "wof:name":"Act",
    "wof:placetype":"venue"
},
  "geometry": {"coordinates":[-84.085826,35.921139],"type":"Point"}
}