{
  "type": "Feature",
  "properties": {
    "addr:full":"1664 Hampshire Pike Columbia TN 38401",
    "addr:housenumber":"1664",
    "addr:postcode":"38401",
    "addr:street":"Hampshire Pike",
    "iso:country":"US",
    "sg:address":"1664 Hampshire Pike",
    "sg:city":"Columbia",
    "sg:classifiers":[
        {
            "category":"Communications",
            "type":"Services"
        }
    ],
    "sg:phone":"+1 931 381 5755",
    "sg:postcode":"38401",
    "sg:province":"TN",
    "wof:name":"Communication Workers",
    "wof:placetype":"venue"
},
  "geometry": {"coordinates":[-87.101097,35.618674],"type":"Point"}
}