{
  "type": "Feature",
  "properties": {
    "addr:full":"2226 Grassy Branch Rd Sevierville TN 37876",
    "addr:housenumber":"2226",
    "addr:postcode":"37876",
    "addr:street":"Grassy Branch Rd",
    "iso:country":"US",
    "sg:address":"2226 Grassy Branch Rd",
    "sg:city":"Sevierville",
    "sg:classifiers":[
        {
            "category":"Organizations",
            "subcategory":"Religious Organization",
            "type":"Services"
        }
    ],
    "sg:phone":"+1 865 453 2633",
    "sg:postcode":"37876",
    "sg:province":"TN",
    "sg:tags":[
        "church"
    ],
    "wof:name":"Zion Grove Baptist Church",
    "wof:placetype":"venue"
},
  "geometry": {"coordinates":[-83.437652,35.763142],"type":"Point"}
}