{
  "type": "Feature",
  "properties": {
    "iso:country":"US",
    "sg:address":"72 Myrick Rd",
    "sg:city":"Flintville",
    "sg:classifiers":[
        {
            "category":"Freight",
            "type":"Transportation"
        }
    ],
    "sg:phone":"+1 931 937 7502",
    "sg:postcode":"37335",
    "sg:province":"TN",
    "sg:tags":[
        "operator",
        "local",
        "trucking"
    ],
    "wof:name":"Richard & Nicoles Trucking",
    "wof:placetype":"venue"
},
  "geometry": {"coordinates":[-86.402861,35.078878],"type":"Point"}
}