{
  "type": "Feature",
  "properties": {
    "addr:full":"603 Englewood Rd Madisonville TN 37354",
    "addr:housenumber":"603",
    "addr:postcode":"37354",
    "addr:street":"Englewood Rd",
    "iso:country":"US",
    "sg:address":"603 Englewood Rd",
    "sg:city":"Madisonville",
    "sg:classifiers":[
        {
            "category":"Shopping",
            "subcategory":"Used Merchandise",
            "type":"Retail Goods"
        }
    ],
    "sg:phone":"+1 423 442 2964",
    "sg:postcode":"37354",
    "sg:province":"TN",
    "sg:tags":[
        "shop",
        "consignment"
    ],
    "wof:name":"Kid's & More",
    "wof:placetype":"venue"
},
  "geometry": {"coordinates":[-84.369996,35.512812],"type":"Point"}
}