{
  "type": "Feature",
  "properties": {
    "addr:full":"6074 Hwy 31 W Portland TN 37148",
    "addr:housenumber":"6074",
    "addr:postcode":"37148",
    "addr:street":"Hwy 31 W",
    "iso:country":"US",
    "sg:address":"6074 Hwy 31 W",
    "sg:city":"Portland",
    "sg:classifiers":[
        {
            "category":"Professional",
            "type":"Services"
        }
    ],
    "sg:phone":"+1 615 325 5900",
    "sg:postcode":"37148",
    "sg:province":"TN",
    "wof:name":"Warren Exploration",
    "wof:placetype":"venue"
},
  "geometry": {"coordinates":[-86.567425,36.627326],"type":"Point"}
}