{
  "type": "Feature",
  "properties": {
    "iso:country":"US",
    "sg:address":"125 Belle Forest Cir",
    "sg:city":"Nashville",
    "sg:classifiers":[
        {
            "category":"Professional",
            "subcategory":"Business Services",
            "type":"Services"
        }
    ],
    "sg:phone":"+1 615 662 4811",
    "sg:postcode":"37221",
    "sg:province":"TN",
    "wof:name":"Sws Sales LLC",
    "wof:placetype":"venue"
},
  "geometry": {"coordinates":[-86.921812,36.076768],"type":"Point"}
}