{
  "type": "Feature",
  "properties": {
    "iso:country":"US",
    "sg:address":"113 W Main St",
    "sg:city":"Waverly",
    "sg:classifiers":[
        {
            "category":"Food & Beverages",
            "subcategory":"Groceries & Convenience Stores",
            "type":"Retail Goods"
        }
    ],
    "sg:phone":"+1 931 296 1457",
    "sg:postcode":"37185",
    "sg:province":"TN",
    "wof:name":"Jds Market Inc",
    "wof:placetype":"venue"
},
  "geometry": {"coordinates":[-87.79549900000001,36.083346],"type":"Point"}
}