{
  "type": "Feature",
  "properties": {
    "addr:full":"918 Buchanan St Nashville TN 37208",
    "addr:housenumber":"918",
    "addr:postcode":"37208",
    "addr:street":"Buchanan St",
    "iso:country":"US",
    "sg:address":"918 Buchanan St",
    "sg:city":"Nashville",
    "sg:classifiers":[
        {
            "category":"Shopping",
            "subcategory":"Discount & Variety Stores",
            "type":"Retail Goods"
        }
    ],
    "sg:phone":"+1 615 244 7222",
    "sg:postcode":"37208",
    "sg:province":"TN",
    "sg:tags":[
        "merchandise",
        "general"
    ],
    "wof:name":"Dollar Mania Of Nashville",
    "wof:placetype":"venue"
},
  "geometry": {"coordinates":[-86.802915,36.180534],"type":"Point"}
}