{
  "type": "Feature",
  "properties": {
    "addr:full":"800 Longview Rd NW Knoxville TN 37919",
    "addr:housenumber":"800",
    "addr:postcode":"37919",
    "addr:street":"Longview Rd Nw",
    "iso:country":"US",
    "sg:address":"800 Longview Rd NW",
    "sg:city":"Knoxville",
    "sg:classifiers":[
        {
            "category":"Real Estate",
            "subcategory":"Real Estate Operator",
            "type":"Services"
        }
    ],
    "sg:phone":"+1 865 584 8571",
    "sg:postcode":"37919",
    "sg:province":"TN",
    "sg:tags":[
        "building",
        "nonresidential"
    ],
    "wof:name":"Crestridge Apartments",
    "wof:placetype":"venue"
},
  "geometry": {"coordinates":[-83.984651,35.946719],"type":"Point"}
}