{
  "type": "Feature",
  "properties": {
    "iso:country":"US",
    "sg:address":"2800 S Mendenhall Rd",
    "sg:city":"Memphis",
    "sg:classifiers":[
        {
            "category":"Professional",
            "type":"Services"
        }
    ],
    "sg:phone":"+1 901 360 0065",
    "sg:postcode":"38115",
    "sg:province":"TN",
    "wof:name":"Step 6 Revive",
    "wof:placetype":"venue"
},
  "geometry": {"coordinates":[-89.885024,35.073704],"type":"Point"}
}