{
  "type": "Feature",
  "properties": {
    "addr:full":"335 E Main St Red Boiling Spgs TN 37150",
    "addr:housenumber":"335",
    "addr:postcode":"37150",
    "addr:street":"E Main St",
    "iso:country":"US",
    "sg:address":"335 E Main St",
    "sg:city":"Red Boiling Spgs",
    "sg:classifiers":[
        {
            "category":"Education",
            "subcategory":"Library",
            "type":"Public Place"
        }
    ],
    "sg:phone":"+1 615 699 3701",
    "sg:postcode":"37150",
    "sg:province":"TN",
    "wof:name":"Red Boiling Springs Library",
    "wof:placetype":"venue"
},
  "geometry": {"coordinates":[-85.847903,36.530568],"type":"Point"}
}