{
  "type": "Feature",
  "properties": {
    "addr:full":"2003 Hickory Valley Rd Chattanooga TN 37421",
    "addr:housenumber":"2003",
    "addr:postcode":"37421",
    "addr:street":"Hickory Valley Rd",
    "iso:country":"US",
    "sg:address":"2003 Hickory Valley Rd",
    "sg:city":"Chattanooga",
    "sg:classifiers":[
        {
            "category":"Social Services",
            "subcategory":"Child Care",
            "type":"Services"
        }
    ],
    "sg:phone":"+1 423 400 4210",
    "sg:postcode":"37421",
    "sg:province":"TN",
    "sg:tags":[
        "day"
    ],
    "wof:name":"Systems In Hitek Learning",
    "wof:placetype":"venue"
},
  "geometry": {"coordinates":[-85.170457,35.038648],"type":"Point"}
}