{
  "type": "Feature",
  "properties": {
    "addr:full":"40 S Main St Lexington TN 38351",
    "addr:housenumber":"40",
    "addr:postcode":"38351",
    "addr:street":"S Main St",
    "iso:country":"US",
    "sg:address":"40 S Main St",
    "sg:city":"Lexington",
    "sg:classifiers":[
        {
            "category":"Shopping",
            "subcategory":"Clothing, Apparel, & Fashions",
            "type":"Retail Goods"
        }
    ],
    "sg:phone":"+1 731 968 3351",
    "sg:postcode":"38351",
    "sg:province":"TN",
    "sg:tags":[
        "family"
    ],
    "wof:name":"Davis Dry Goods Company",
    "wof:placetype":"venue"
},
  "geometry": {"coordinates":[-88.39256899999999,35.648535],"type":"Point"}
}