{
  "type": "Feature",
  "properties": {
    "addr:full":"1001 Rialto Rd Covington TN 38019",
    "addr:housenumber":"1001",
    "addr:postcode":"38019",
    "addr:street":"Rialto Rd",
    "iso:country":"US",
    "sg:address":"1001 Rialto Rd",
    "sg:city":"Covington",
    "sg:classifiers":[
        {
            "category":"Wholesale",
            "subcategory":"Stationery",
            "type":"Manufacturing & Wholesale Goods"
        }
    ],
    "sg:phone":"+1 901 476 4087",
    "sg:postcode":"38019",
    "sg:province":"TN",
    "sg:tags":[
        "business",
        "form",
        "system"
    ],
    "wof:name":"R R Donnelley & Sons Co",
    "wof:placetype":"venue"
},
  "geometry": {"coordinates":[-89.605892,35.59993],"type":"Point"}
}