{
  "type": "Feature",
  "properties": {
    "iso:country":"US",
    "sg:address":"630 Harwood Cove",
    "sg:city":"Memphis",
    "sg:classifiers":[
        {
            "category":"Professional",
            "subcategory":"Business Services",
            "type":"Services"
        }
    ],
    "sg:phone":"+1 901 761 3177",
    "sg:postcode":"38120",
    "sg:province":"TN",
    "wof:name":"Savories O Simple",
    "wof:placetype":"venue"
},
  "geometry": {"coordinates":[-89.86826,35.115943],"type":"Point"}
}