{
  "type": "Feature",
  "properties": {
    "iso:country":"US",
    "sg:address":"1016 W Main St",
    "sg:city":"Lebanon",
    "sg:classifiers":[
        {
            "category":"Retail",
            "subcategory":"Photofinishing",
            "type":"Services"
        }
    ],
    "sg:phone":"+1 615 444 5758",
    "sg:postcode":"37087",
    "sg:province":"TN",
    "sg:tags":[
        "laboratory"
    ],
    "wof:name":"Custom Color 1-Hour Lab",
    "wof:placetype":"venue"
},
  "geometry": {"coordinates":[-86.313705,36.210915],"type":"Point"}
}