{
  "type": "Feature",
  "properties": {
    "addr:full":"7112 Florence Rd Smyrna TN 37167",
    "addr:housenumber":"7112",
    "addr:postcode":"37167",
    "addr:street":"Florence Rd",
    "iso:country":"US",
    "sg:address":"7112 Florence Rd",
    "sg:city":"Smyrna",
    "sg:classifiers":[
        {
            "category":"Manufacturing",
            "subcategory":"Tools & Machinery",
            "type":"Manufacturing & Wholesale Goods"
        }
    ],
    "sg:phone":"+1 615 459 6921",
    "sg:postcode":"37167",
    "sg:province":"TN",
    "sg:tags":[
        "machine",
        "shop"
    ],
    "wof:name":"Tangent Industries",
    "wof:placetype":"venue"
},
  "geometry": {"coordinates":[-86.47112199999999,35.951485],"type":"Point"}
}