{
  "type": "Feature",
  "properties": {
    "iso:country":"US",
    "sg:address":"1241 Ridge Cir",
    "sg:city":"Joelton",
    "sg:classifiers":[
        {
            "category":"Manufacturing",
            "subcategory":"Building Materials",
            "type":"Manufacturing & Wholesale Goods"
        }
    ],
    "sg:phone":"+1 615 746 0200",
    "sg:postcode":"37080",
    "sg:province":"TN",
    "sg:tags":[
        "mfg",
        "wood",
        "kitchen",
        "cabinet"
    ],
    "wof:name":"Phoenix Design",
    "wof:placetype":"venue"
},
  "geometry": {"coordinates":[-86.94172,36.361464],"type":"Point"}
}