{
  "type": "Feature",
  "properties": {
    "iso:country":"US",
    "sg:address":"5751 Peavine Rd",
    "sg:city":"Crossville",
    "sg:classifiers":[
        {
            "category":"Restaurant",
            "type":"Food & Drink"
        }
    ],
    "sg:phone":"+1 931 459 2026",
    "sg:postcode":"38571",
    "sg:province":"TN",
    "sg:tags":[
        "parlor",
        "ice",
        "cream"
    ],
    "wof:name":"Custard Cabin",
    "wof:placetype":"venue"
},
  "geometry": {"coordinates":[-84.90653,36.008442],"type":"Point"}
}