{
  "type": "Feature",
  "properties": {
    "iso:country":"US",
    "sg:address":"255 Bethelem Rd",
    "sg:city":"Copperhill",
    "sg:classifiers":[
        {
            "category":"Professional",
            "subcategory":"Computer Services",
            "type":"Services"
        }
    ],
    "sg:phone":"+1 404 312 7864",
    "sg:postcode":"37317",
    "sg:province":"NC",
    "sg:tags":[
        "prepackaged",
        "software"
    ],
    "wof:name":"Cabin In Sky Systems",
    "wof:placetype":"venue"
},
  "geometry": {"coordinates":[-84.335987,35.045539],"type":"Point"}
}