{
  "type": "Feature",
  "properties": {
    "addr:full":"1215 S Main Ave Dyersburg TN 38024",
    "addr:housenumber":"1215",
    "addr:postcode":"38024",
    "addr:street":"S Main Ave",
    "iso:country":"US",
    "sg:address":"1215 S Main Ave",
    "sg:city":"Dyersburg",
    "sg:classifiers":[
        {
            "category":"Wholesale",
            "subcategory":"Groceries",
            "type":"Manufacturing & Wholesale Goods"
        }
    ],
    "sg:phone":"+1 731 288 0792",
    "sg:postcode":"38024",
    "sg:province":"TN",
    "sg:tags":[
        "baker"
    ],
    "wof:name":"Flowers Baking Co",
    "wof:placetype":"venue"
},
  "geometry": {"coordinates":[-89.395753,36.011205],"type":"Point"}
}