{
  "type": "Feature",
  "properties": {
    "addr:full":"2595 E Hwy 25-70 Dandridge TN 37725",
    "addr:housenumber":"2595",
    "addr:postcode":"25-70;37725",
    "addr:street":"E Hwy",
    "iso:country":"US",
    "sg:address":"2595 E Hwy 25-70",
    "sg:city":"Dandridge",
    "sg:classifiers":[
        {
            "category":"Freight",
            "type":"Transportation"
        }
    ],
    "sg:phone":"+1 865 397 0022",
    "sg:postcode":"37725",
    "sg:province":"TN",
    "wof:name":"Aaron Self Storage & U-Haul",
    "wof:placetype":"venue"
},
  "geometry": {"coordinates":[-83.28446099999999,35.987205],"type":"Point"}
}