{
  "type": "Feature",
  "properties": {
    "iso:country":"US",
    "sg:address":"875 Parson Forest Cove",
    "sg:city":"Cordova",
    "sg:classifiers":[
        {
            "category":"Manufacturing",
            "subcategory":"Jewelry",
            "type":"Manufacturing & Wholesale Goods"
        }
    ],
    "sg:phone":"+1 901 309 8992",
    "sg:postcode":"38018",
    "sg:province":"TN",
    "sg:tags":[
        "precious",
        "metal",
        "mfg"
    ],
    "wof:name":"OH Baby Bracelets",
    "wof:placetype":"venue"
},
  "geometry": {"coordinates":[-89.785996,35.149269],"type":"Point"}
}