{
  "type": "Feature",
  "properties": {
    "addr:full":"4841 Prairie Plains Rd Hillsboro TN 37342",
    "addr:housenumber":"4841",
    "addr:postcode":"37342",
    "addr:street":"Prairie Plains Rd",
    "iso:country":"US",
    "sg:address":"4841 Prairie Plains Rd",
    "sg:city":"Hillsboro",
    "sg:classifiers":[
        {
            "category":"Organizations",
            "subcategory":"Religious Organization",
            "type":"Services"
        }
    ],
    "sg:phone":"+1 931 596 2754",
    "sg:postcode":"37342",
    "sg:province":"TN",
    "sg:tags":[
        "church"
    ],
    "wof:name":"Prairie Plains Church-Christ",
    "wof:placetype":"venue"
},
  "geometry": {"coordinates":[-85.968012,35.341264],"type":"Point"}
}