{
  "type": "Feature",
  "properties": {
    "iso:country":"US",
    "sg:address":"617 S Orleans St",
    "sg:city":"Memphis",
    "sg:classifiers":[
        {
            "category":"Recreation",
            "type":"Entertainment"
        }
    ],
    "sg:phone":"+1 901 527 3620",
    "sg:postcode":"38126",
    "sg:province":"TN",
    "sg:tags":[
        "parks"
    ],
    "wof:name":"Memphis Park Commission LE",
    "wof:placetype":"venue"
},
  "geometry": {"coordinates":[-90.040083,35.130191],"type":"Point"}
}