{
  "type": "Feature",
  "properties": {
    "iso:country":"US",
    "sg:address":"205 N College St",
    "sg:city":"Greeneville",
    "sg:classifiers":[
        {
            "category":"Real Estate",
            "subcategory":"Real Estate Operator",
            "type":"Services"
        }
    ],
    "sg:phone":"+1 423 638 3481",
    "sg:postcode":"37745",
    "sg:province":"TN",
    "sg:tags":[
        "building",
        "nonresidential"
    ],
    "wof:name":"Little Theatre of Greeneville",
    "wof:placetype":"venue"
},
  "geometry": {"coordinates":[-82.827995,36.165171],"type":"Point"}
}