{
  "type": "Feature",
  "properties": {
    "iso:country":"US",
    "sg:address":"795 Tanglewood St",
    "sg:city":"Memphis",
    "sg:classifiers":[
        {
            "category":"Professional",
            "subcategory":"Lawyer & Legal Services",
            "type":"Services"
        }
    ],
    "sg:phone":"+1 901 276 6364",
    "sg:postcode":"38104",
    "sg:province":"TN",
    "sg:tags":[
        "attorney"
    ],
    "wof:name":"William Mason",
    "wof:placetype":"venue"
},
  "geometry": {"coordinates":[-89.993396,35.124395],"type":"Point"}
}