{
  "type": "Feature",
  "properties": {
    "addr:full":"100 E Court Sq Trenton TN 38382",
    "addr:housenumber":"100",
    "addr:postcode":"38382",
    "addr:street":"E Court Sq",
    "iso:country":"US",
    "sg:address":"100 E Court Sq",
    "sg:city":"Trenton",
    "sg:classifiers":[
        {
            "category":"Real Estate",
            "subcategory":"Real Estate Agent",
            "type":"Services"
        }
    ],
    "sg:phone":"+1 731 855 4585",
    "sg:postcode":"38382",
    "sg:province":"TN",
    "wof:name":"Patterson RE & Auctn Co",
    "wof:placetype":"venue"
},
  "geometry": {"coordinates":[-88.94168500000001,35.980754],"type":"Point"}
}