{
  "type": "Feature",
  "properties": {
    "iso:country":"US",
    "sg:address":"5727 Summer Trees Dr",
    "sg:city":"Memphis",
    "sg:classifiers":[
        {
            "category":"Real Estate",
            "subcategory":"Real Estate Agent",
            "type":"Services"
        },
        {
            "category":"Professional",
            "subcategory":"Business Services",
            "type":"Services"
        }
    ],
    "sg:phone":"+1 901 388 3768",
    "sg:postcode":"38134",
    "sg:province":"TN",
    "sg:tags":[
        "appraiser"
    ],
    "wof:name":"Real Estate Loan Svcs of Tenn",
    "wof:placetype":"venue"
},
  "geometry": {"coordinates":[-89.871667,35.165337],"type":"Point"}
}