{
  "type": "Feature",
  "properties": {
    "addr:full":"5105 Charlotte Pike Nashville TN 37209",
    "addr:housenumber":"5105",
    "addr:postcode":"37209",
    "addr:street":"Charlotte Pike",
    "iso:country":"US",
    "sg:address":"5105 Charlotte Pike",
    "sg:city":"Nashville",
    "sg:classifiers":[
        {
            "category":"Education",
            "subcategory":"School",
            "type":"Public Place"
        }
    ],
    "sg:phone":"+1 615 269 0568",
    "sg:postcode":"37209",
    "sg:province":"TN",
    "wof:name":"St Ann School",
    "wof:placetype":"venue"
},
  "geometry": {"coordinates":[-86.848614,36.151896],"type":"Point"}
}