{
  "type": "Feature",
  "properties": {
    "iso:country":"US",
    "sg:address":"1350 Ridgecrest Dr",
    "sg:city":"Seymour",
    "sg:classifiers":[
        {
            "category":"Bus Charters",
            "type":"Transportation"
        }
    ],
    "sg:phone":"+1 865 579 0872",
    "sg:postcode":"37865",
    "sg:province":"TN",
    "sg:tags":[
        "local"
    ],
    "wof:name":"Whitted Bus Lines",
    "wof:placetype":"venue"
},
  "geometry": {"coordinates":[-83.73329099999999,35.902578],"type":"Point"}
}