{
  "type": "Feature",
  "properties": {
    "addr:full":"1007 Old US Hwy 127 S Jamestown TN 38556",
    "addr:housenumber":"1007",
    "addr:postcode":"38556",
    "addr:street":"Old Us Hwy 127 S",
    "iso:country":"US",
    "sg:address":"1007 Old US Hwy 127 S",
    "sg:city":"Jamestown",
    "sg:classifiers":[
        {
            "category":"Autos & Motor Vehicles",
            "subcategory":"Motorcycle Sales",
            "type":"Retail Goods"
        }
    ],
    "sg:phone":"+1 931 879 0225",
    "sg:postcode":"38556",
    "sg:province":"TN",
    "sg:tags":[
        "scooter"
    ],
    "wof:name":"Garys Cycle Shop",
    "wof:placetype":"venue"
},
  "geometry": {"coordinates":[-84.935802,36.414519],"type":"Point"}
}