{
  "type": "Feature",
  "properties": {
    "addr:full":"738 English Mountain Rd Newport TN 37821",
    "addr:housenumber":"738",
    "addr:postcode":"37821",
    "addr:street":"English Mountain Rd",
    "iso:country":"US",
    "sg:address":"738 English Mountain Rd",
    "sg:city":"Newport",
    "sg:classifiers":[
        {
            "category":"Recreation",
            "type":"Entertainment"
        }
    ],
    "sg:phone":"+1 423 623 5274",
    "sg:postcode":"37821",
    "sg:province":"TN",
    "wof:name":"English Mountain Llama Treks",
    "wof:placetype":"venue"
},
  "geometry": {"coordinates":[-83.252944,35.909646],"type":"Point"}
}