{
  "type": "Feature",
  "properties": {
    "iso:country":"US",
    "sg:address":"4340 Stage Rd",
    "sg:city":"Memphis",
    "sg:classifiers":[
        {
            "category":"Retail",
            "subcategory":"Auto Repair",
            "type":"Services"
        }
    ],
    "sg:phone":"+1 901 373 1872",
    "sg:postcode":"38128",
    "sg:province":"TN",
    "sg:tags":[
        "body",
        "repairing",
        "painting",
        "automobile"
    ],
    "wof:name":"Auto Paint Specialists",
    "wof:placetype":"venue"
},
  "geometry": {"coordinates":[-89.91861,35.20536],"type":"Point"}
}