{
  "type": "Feature",
  "properties": {
    "iso:country":"US",
    "sg:address":"1415 Stuart St",
    "sg:city":"Chattanooga",
    "sg:classifiers":[
        {
            "category":"Professional",
            "subcategory":"Engineering",
            "type":"Services"
        }
    ],
    "sg:phone":"+1 423 648 2288",
    "sg:postcode":"37406",
    "sg:province":"TN",
    "sg:tags":[
        "machinery"
    ],
    "wof:name":"Intech Automation",
    "wof:placetype":"venue"
},
  "geometry": {"coordinates":[-85.26031,35.075587],"type":"Point"}
}