{
  "type": "Feature",
  "properties": {
    "iso:country":"US",
    "sg:address":"820 Lafolette Dr",
    "sg:city":"Maryville",
    "sg:classifiers":[
        {
            "category":"Professional",
            "subcategory":"Business Services",
            "type":"Services"
        }
    ],
    "sg:phone":"+1 865 984 0075",
    "sg:postcode":"37801",
    "sg:province":"TN",
    "sg:tags":[
        "packaging"
    ],
    "wof:name":"Bag N Time",
    "wof:placetype":"venue"
},
  "geometry": {"coordinates":[-84.06500800000001,35.707547],"type":"Point"}
}