{
  "type": "Feature",
  "properties": {
    "addr:full":"9301 Lee Hwy Ooltewah TN 37363",
    "addr:housenumber":"9301",
    "addr:postcode":"37363",
    "addr:street":"Lee Hwy",
    "iso:country":"US",
    "sg:address":"9301 Lee Hwy",
    "sg:city":"Ooltewah",
    "sg:classifiers":[
        {
            "category":"Autos & Motor Vehicles",
            "subcategory":"Automobile Sales",
            "type":"Retail Goods"
        }
    ],
    "sg:phone":"+1 423 238 5969",
    "sg:postcode":"37363",
    "sg:province":"TN",
    "sg:tags":[
        "car",
        "dealer"
    ],
    "wof:name":"Ooltewah Auto Brokers",
    "wof:placetype":"venue"
},
  "geometry": {"coordinates":[-85.058487,35.082829],"type":"Point"}
}