{
  "type": "Feature",
  "properties": {
    "addr:full":"2014 Beechwood Ave Nashville TN 37212",
    "addr:housenumber":"2014",
    "addr:postcode":"37212",
    "addr:street":"Beechwood Ave",
    "iso:country":"US",
    "sg:address":"2014 Beechwood Ave",
    "sg:city":"Nashville",
    "sg:classifiers":[
        {
            "category":"Shopping",
            "subcategory":"Music",
            "type":"Retail Goods"
        }
    ],
    "sg:phone":"+1 615 385 3640",
    "sg:postcode":"37212",
    "sg:province":"TN",
    "wof:name":"Amy Shreve",
    "wof:placetype":"venue"
},
  "geometry": {"coordinates":[-86.80372,36.127073],"type":"Point"}
}