{
  "type": "Feature",
  "properties": {
    "iso:country":"US",
    "sg:address":"2240 Oakleaf Dr",
    "sg:city":"Franklin",
    "sg:classifiers":[
        {
            "category":"Education",
            "subcategory":"Dance Studio",
            "type":"Public Place"
        }
    ],
    "sg:phone":"+1 615 790 8945",
    "sg:postcode":"37064",
    "sg:province":"TN",
    "wof:name":"Fiesta Dance Studios Inc",
    "wof:placetype":"venue"
},
  "geometry": {"coordinates":[-86.87544800000001,35.877866],"type":"Point"}
}