{
  "type": "Feature",
  "properties": {
    "iso:country":"US",
    "sg:address":"460 Grove Rd",
    "sg:city":"Benton",
    "sg:classifiers":[
        {
            "category":"Manufacturing",
            "subcategory":"Retail Goods",
            "type":"Manufacturing & Wholesale Goods"
        }
    ],
    "sg:phone":"+1 423 338 1258",
    "sg:postcode":"37307",
    "sg:province":"TN",
    "sg:tags":[
        "product",
        "mfg"
    ],
    "wof:name":"Clayco Industries",
    "wof:placetype":"venue"
},
  "geometry": {"coordinates":[-84.633039,35.187054],"type":"Point"}
}