{
  "type": "Feature",
  "properties": {
    "iso:country":"US",
    "sg:address":"534 Dudala Cir",
    "sg:city":"Loudon",
    "sg:classifiers":[
        {
            "category":"Professional",
            "subcategory":"Business Services",
            "type":"Services"
        }
    ],
    "sg:phone":"+1 865 408 2611",
    "sg:postcode":"37774",
    "sg:province":"TN",
    "wof:name":"Barnett Enterprises Inc",
    "wof:placetype":"venue"
},
  "geometry": {"coordinates":[-84.265698,35.661083],"type":"Point"}
}