{
  "type": "Feature",
  "properties": {
    "addr:full":"2864 Elm Hill Pike Nashville TN 37214",
    "addr:housenumber":"2864",
    "addr:postcode":"37214",
    "addr:street":"Elm Hill Pike",
    "iso:country":"US",
    "sg:address":"2864 Elm Hill Pike",
    "sg:city":"Nashville",
    "sg:classifiers":[
        {
            "category":"Organizations",
            "subcategory":"Community Association",
            "type":"Services"
        }
    ],
    "sg:phone":"+1 615 889 9318",
    "sg:postcode":"37214",
    "sg:province":"TN",
    "sg:tags":[
        "military"
    ],
    "wof:name":"American Legion",
    "wof:placetype":"venue"
},
  "geometry": {"coordinates":[-86.663201,36.147827],"type":"Point"}
}