{
  "type": "Feature",
  "properties": {
    "addr:full":"2633 Altruria Rd Memphis TN 38134",
    "addr:housenumber":"2633",
    "addr:postcode":"38134",
    "addr:street":"Altruria Rd",
    "iso:country":"US",
    "sg:address":"2633 Altruria Rd",
    "sg:city":"Memphis",
    "sg:classifiers":[
        {
            "category":"Shopping",
            "subcategory":"Musical Instruments",
            "type":"Retail Goods"
        }
    ],
    "sg:phone":"+1 901 388 1290",
    "sg:postcode":"38134",
    "sg:province":"TN",
    "sg:tags":[
        "music",
        "dealer"
    ],
    "wof:name":"Cross Way Music Publishing",
    "wof:placetype":"venue"
},
  "geometry": {"coordinates":[-89.84959600000001,35.194288],"type":"Point"}
}