{
  "type": "Feature",
  "properties": {
    "addr:full":"220 Crossings Pl Antioch TN 37013",
    "addr:housenumber":"220",
    "addr:postcode":"37013",
    "addr:street":"Crossings Pl",
    "iso:country":"US",
    "sg:address":"220 Crossings Pl",
    "sg:city":"Antioch",
    "sg:classifiers":[
        {
            "category":"Autos & Motor Vehicles",
            "subcategory":"Fuel & Gas Station",
            "type":"Retail Goods"
        }
    ],
    "sg:phone":"+1 615 717 0020",
    "sg:postcode":"37013",
    "sg:province":"TN",
    "sg:tags":[
        "station",
        "gasoline"
    ],
    "wof:name":"Mountain View Shell",
    "wof:placetype":"venue"
},
  "geometry": {"coordinates":[-86.646806,36.043951],"type":"Point"}
}