{
  "type": "Feature",
  "properties": {
    "iso:country":"US",
    "sg:address":"726 US Hwy 51 N",
    "sg:city":"Covington",
    "sg:classifiers":[
        {
            "category":"Insurance",
            "subcategory":"Insurance Agent",
            "type":"Services"
        }
    ],
    "sg:phone":"+1 901 475 4414",
    "sg:postcode":"38019",
    "sg:province":"TN",
    "wof:name":"Acceptance Insurance Agency",
    "wof:placetype":"venue"
},
  "geometry": {"coordinates":[-89.645329,35.572458],"type":"Point"}
}