{
  "type": "Feature",
  "properties": {
    "iso:country":"US",
    "sg:address":"120 Woodlawn Ave",
    "sg:city":"Newport",
    "sg:classifiers":[
        {
            "category":"Retail",
            "subcategory":"Auto Repair",
            "type":"Services"
        }
    ],
    "sg:phone":"+1 423 625 8009",
    "sg:postcode":"37821",
    "sg:province":"TN",
    "sg:tags":[
        "automotive",
        "glass",
        "replacement"
    ],
    "wof:name":"Affordable Auto Glass",
    "wof:placetype":"venue"
},
  "geometry": {"coordinates":[-83.188436,35.966364],"type":"Point"}
}