{
  "type": "Feature",
  "properties": {
    "addr:full":"12330 State Hwy 13 S Hurricane Mills TN 37078",
    "addr:housenumber":"12330",
    "addr:postcode":"37078",
    "addr:street":"State Hwy 13 S;Mills",
    "iso:country":"US",
    "sg:address":"12330 State Hwy 13 S",
    "sg:city":"Hurricane Mills",
    "sg:classifiers":[
        {
            "category":"Building & Trades",
            "subcategory":"Construction",
            "type":"Services"
        }
    ],
    "sg:phone":"+1 931 296 9459",
    "sg:postcode":"37078",
    "sg:province":"TN",
    "sg:tags":[
        "house"
    ],
    "wof:name":"Buffalo Log Homes",
    "wof:placetype":"venue"
},
  "geometry": {"coordinates":[-87.78269400000001,35.908486],"type":"Point"}
}