{
  "type": "Feature",
  "properties": {
    "iso:country":"US",
    "sg:address":"507 Donelson Pike",
    "sg:city":"Nashville",
    "sg:classifiers":[
        {
            "category":"Shopping",
            "subcategory":"Used Merchandise",
            "type":"Retail Goods"
        }
    ],
    "sg:phone":"+1 615 885 1448",
    "sg:postcode":"37214",
    "sg:province":"TN",
    "sg:tags":[
        "pawnbroker"
    ],
    "wof:name":"Donelson Jewelry & Loan LLC",
    "wof:placetype":"venue"
},
  "geometry": {"coordinates":[-86.666224,36.148309],"type":"Point"}
}