{
  "type": "Feature",
  "properties": {
    "addr:full":"110 Young Rd Linden TN 37090",
    "addr:housenumber":"110",
    "addr:postcode":"37090",
    "addr:street":"Young Rd",
    "iso:country":"US",
    "sg:address":"110 Young Rd",
    "sg:city":"Linden",
    "sg:classifiers":[
        {
            "category":"Professional",
            "type":"Services"
        }
    ],
    "sg:phone":"+1 931 589 3121",
    "sg:postcode":"37090",
    "sg:province":"TN",
    "sg:tags":[
        "establishment"
    ],
    "wof:name":"Untangled",
    "wof:placetype":"venue"
},
  "geometry": {"coordinates":[-86.21358499999999,36.127783],"type":"Point"}
}