{
  "type": "Feature",
  "properties": {
    "iso:country":"US",
    "sg:address":"1522 Cherokee Trl",
    "sg:city":"Knoxville",
    "sg:classifiers":[
        {
            "category":"Government",
            "subcategory":"Office",
            "type":"Public Place"
        }
    ],
    "sg:phone":"+1 865 546 9221",
    "sg:postcode":"37920",
    "sg:province":"TN",
    "wof:name":"East Tennessee Regional Ofc",
    "wof:placetype":"venue"
},
  "geometry": {"coordinates":[-83.939263,35.93547],"type":"Point"}
}