{
  "type": "Feature",
  "properties": {
    "iso:country":"US",
    "sg:address":"3105 Chairman Dr",
    "sg:city":"Memphis",
    "sg:classifiers":[
        {
            "category":"Organizations",
            "subcategory":"Religious Organization",
            "type":"Services"
        }
    ],
    "sg:phone":"+1 901 395 0023",
    "sg:postcode":"38131",
    "sg:province":"TN",
    "wof:name":"Watchman Ministries",
    "wof:placetype":"venue"
},
  "geometry": {"coordinates":[-89.99243800000001,35.064111],"type":"Point"}
}