{
  "type": "Feature",
  "properties": {
    "iso:country":"US",
    "sg:address":"301 S Main St",
    "sg:city":"Dickson",
    "sg:classifiers":[
        {
            "category":"Professional",
            "subcategory":"Management & Consulting",
            "type":"Services"
        }
    ],
    "sg:phone":"+1 615 446 7908",
    "sg:postcode":"37055",
    "sg:province":"TN",
    "sg:tags":[
        "construction"
    ],
    "wof:name":"HDH Mgmt Corp Constr Mgmt",
    "wof:placetype":"venue"
},
  "geometry": {"coordinates":[-87.39131399999999,36.074124],"type":"Point"}
}