{
  "type": "Feature",
  "properties": {
    "iso:country":"US",
    "sg:address":"1465 Rhea Branch Rd",
    "sg:city":"Ethridge",
    "sg:classifiers":[
        {
            "category":"Building & Trades",
            "subcategory":"Construction",
            "type":"Services"
        }
    ],
    "sg:phone":"+1 931 424 9995",
    "sg:postcode":"38478",
    "sg:province":"TN",
    "sg:tags":[
        "home",
        "work",
        "new",
        "concrete"
    ],
    "wof:name":"Dickey Concrete and Cnstr",
    "wof:placetype":"venue"
},
  "geometry": {"coordinates":[-87.166633,35.338979],"type":"Point"}
}