{
  "type": "Feature",
  "properties": {
    "addr:full":"700 Drexel St Nashville TN 37203",
    "addr:housenumber":"700",
    "addr:postcode":"37203",
    "addr:street":"Drexel St",
    "iso:country":"US",
    "sg:address":"700 Drexel St",
    "sg:city":"Nashville",
    "sg:classifiers":[
        {
            "category":"Home & Garden",
            "subcategory":"Building Materials",
            "type":"Retail Goods"
        },
        {
            "category":"Manufacturing",
            "subcategory":"Chemicals & Compounds",
            "type":"Manufacturing & Wholesale Goods"
        }
    ],
    "sg:phone":"+1 615 726 3142",
    "sg:postcode":"37203",
    "sg:province":"TN",
    "sg:tags":[
        "paint"
    ],
    "wof:name":"Sherwin-Williams Paints",
    "wof:placetype":"venue"
},
  "geometry": {"coordinates":[-86.77843300000001,36.152792],"type":"Point"}
}