{
  "type": "Feature",
  "properties": {
    "iso:country":"US",
    "sg:address":"4900 Hixson Pike",
    "sg:city":"Hixson",
    "sg:classifiers":[
        {
            "category":"Shopping",
            "type":"Retail Goods"
        },
        {
            "category":"Shopping",
            "subcategory":"Optical Goods",
            "type":"Retail Goods"
        }
    ],
    "sg:phone":"+1 423 875 3108",
    "sg:postcode":"37343",
    "sg:province":"TN",
    "sg:tags":[
        "sun",
        "goggles",
        "sunglasses",
        "accessory"
    ],
    "wof:name":"Sunglass Hut 73",
    "wof:placetype":"venue"
},
  "geometry": {"coordinates":[-85.246241,35.129001],"type":"Point"}
}