{
  "type": "Feature",
  "properties": {
    "addr:full":"3903 Volunteer Dr Chattanooga TN 37416",
    "addr:housenumber":"3903",
    "addr:postcode":"37416",
    "addr:street":"Volunteer Dr",
    "iso:country":"US",
    "sg:address":"3903 Volunteer Dr",
    "sg:city":"Chattanooga",
    "sg:classifiers":[
        {
            "category":"Home & Garden",
            "subcategory":"Building Materials",
            "type":"Retail Goods"
        }
    ],
    "sg:phone":"+1 423 899 1245",
    "sg:postcode":"37416",
    "sg:province":"TN",
    "sg:tags":[
        "glass",
        "window",
        "plate"
    ],
    "sg:website":"www.pilkington.com",
    "wof:name":"Pilkington North America",
    "wof:placetype":"venue"
},
  "geometry": {"coordinates":[-85.202066,35.073549],"type":"Point"}
}