{
  "type": "Feature",
  "properties": {
    "iso:country":"US",
    "sg:address":"2107 Arrow Ct",
    "sg:city":"Murfreesboro",
    "sg:classifiers":[
        {
            "category":"Manufacturing",
            "subcategory":"Apparel",
            "type":"Manufacturing & Wholesale Goods"
        }
    ],
    "sg:phone":"+1 615 867 5080",
    "sg:postcode":"37127",
    "sg:province":"TN",
    "wof:name":"A Sport Seam",
    "wof:placetype":"venue"
},
  "geometry": {"coordinates":[-86.352537,35.819653],"type":"Point"}
}