{
  "type": "Feature",
  "properties": {
    "addr:full":"2490 Middle Creek Rd Pigeon Forge TN 37863",
    "addr:housenumber":"2490",
    "addr:postcode":"37863",
    "addr:street":"Middle Creek Rd",
    "iso:country":"US",
    "sg:address":"2490 Middle Creek Rd",
    "sg:city":"Pigeon Forge",
    "sg:classifiers":[
        {
            "category":"Retail",
            "subcategory":"Auto Repair",
            "type":"Services"
        }
    ],
    "sg:phone":"+1 865 453 4300",
    "sg:postcode":"37863",
    "sg:province":"TN",
    "sg:tags":[
        "general"
    ],
    "wof:name":"Jim Kings Auto Repair",
    "wof:placetype":"venue"
},
  "geometry": {"coordinates":[-83.543919,35.796976],"type":"Point"}
}