{
  "type": "Feature",
  "properties": {
    "addr:full":"736 Horn Springs Rd Lebanon TN 37087",
    "addr:housenumber":"736",
    "addr:postcode":"37087",
    "addr:street":"Horn Springs Rd",
    "iso:country":"US",
    "sg:address":"736 Horn Springs Rd",
    "sg:city":"Lebanon",
    "sg:classifiers":[
        {
            "category":"Professional",
            "subcategory":"Business Services",
            "type":"Services"
        }
    ],
    "sg:phone":"+1 615 584 4709",
    "sg:postcode":"37087",
    "sg:province":"TN",
    "wof:name":"Britt Enterprise",
    "wof:placetype":"venue"
},
  "geometry": {"coordinates":[-86.363686,36.250302],"type":"Point"}
}