{
  "type": "Feature",
  "properties": {
    "iso:country":"US",
    "sg:address":"3560 Holt's Church Rd",
    "sg:city":"Morristown",
    "sg:classifiers":[
        {
            "category":"Organizations",
            "subcategory":"Religious Organization",
            "type":"Services"
        }
    ],
    "sg:phone":"+1 423 581 6945",
    "sg:postcode":"37814",
    "sg:province":"TN",
    "sg:tags":[
        "church"
    ],
    "wof:name":"Holts Baptist Church",
    "wof:placetype":"venue"
},
  "geometry": {"coordinates":[-83.36479,36.249998],"type":"Point"}
}