{
  "type": "Feature",
  "properties": {
    "iso:country":"US",
    "sg:address":"5016 Rossville Blvd",
    "sg:city":"Chattanooga",
    "sg:classifiers":[
        {
            "category":"Banks & Credit Unions",
            "subcategory":"Bank",
            "type":"Services"
        }
    ],
    "sg:phone":"+1 423 867 3278",
    "sg:postcode":"37407",
    "sg:province":"TN",
    "sg:tags":[
        "depository",
        "banking"
    ],
    "wof:name":"Signature Cash Advance",
    "wof:placetype":"venue"
},
  "geometry": {"coordinates":[-85.286879,34.98501],"type":"Point"}
}