{
  "type": "Feature",
  "properties": {
    "iso:country":"US",
    "sg:address":"2109 Piney Grove Church Rd",
    "sg:city":"Knoxville",
    "sg:classifiers":[
        {
            "category":"Organizations",
            "subcategory":"Religious Organization",
            "type":"Services"
        }
    ],
    "sg:phone":"+1 865 691 1260",
    "sg:postcode":"37909",
    "sg:province":"TN",
    "sg:tags":[
        "church"
    ],
    "wof:name":"Piney Grove Baptist Church",
    "wof:placetype":"venue"
},
  "geometry": {"coordinates":[-84.04383300000001,35.960991],"type":"Point"}
}