{
  "type": "Feature",
  "properties": {
    "iso:country":"US",
    "sg:address":"1322 Second Ln",
    "sg:city":"Sevierville",
    "sg:classifiers":[
        {
            "category":"Organizations",
            "subcategory":"Religious Organization",
            "type":"Services"
        }
    ],
    "sg:phone":"+1 865 453 4010",
    "sg:postcode":"37876",
    "sg:province":"TN",
    "wof:name":"Green Acres Baptist Churc",
    "wof:placetype":"venue"
},
  "geometry": {"coordinates":[-83.538831,35.943781],"type":"Point"}
}