{
  "type": "Feature",
  "properties": {
    "iso:country":"US",
    "sg:address":"711 Stone Blvd",
    "sg:city":"Tullahoma",
    "sg:classifiers":[
        {
            "category":"Organizations",
            "subcategory":"Religious Organization",
            "type":"Services"
        }
    ],
    "sg:phone":"+1 931 455 8629",
    "sg:postcode":"37388",
    "sg:province":"TN",
    "sg:tags":[
        "church"
    ],
    "wof:name":"Church Of The Nazarene",
    "wof:placetype":"venue"
},
  "geometry": {"coordinates":[-86.231971,35.363231],"type":"Point"}
}