{
  "type": "Feature",
  "properties": {
    "iso:country":"US",
    "sg:address":"4190 State Rte 100 W",
    "sg:city":"Henderson",
    "sg:classifiers":[
        {
            "category":"Real Estate",
            "subcategory":"Real Estate Operator",
            "type":"Services"
        }
    ],
    "sg:phone":"+1 731 989 4586",
    "sg:postcode":"38340",
    "sg:province":"TN",
    "sg:tags":[
        "property",
        "lessor"
    ],
    "wof:name":"Victor Graves",
    "wof:placetype":"venue"
},
  "geometry": {"coordinates":[-88.708714,35.411431],"type":"Point"}
}