{
  "type": "Feature",
  "properties": {
    "addr:full":"4159 Ringgold Rd Chattanooga TN 37412",
    "addr:housenumber":"4159",
    "addr:postcode":"37412",
    "addr:street":"Ringgold Rd",
    "iso:country":"US",
    "sg:address":"4159 Ringgold Rd",
    "sg:city":"Chattanooga",
    "sg:classifiers":[
        {
            "category":"Wholesale",
            "subcategory":"Chemicals & Plastics",
            "type":"Manufacturing & Wholesale Goods"
        }
    ],
    "sg:phone":"+1 423 624 0920",
    "sg:postcode":"37412",
    "sg:province":"TN",
    "sg:tags":[
        "explosive"
    ],
    "wof:name":"Energetics Materials Mgmt",
    "wof:placetype":"venue"
},
  "geometry": {"coordinates":[-85.243206,34.997272],"type":"Point"}
}