{
  "type": "Feature",
  "properties": {
    "addr:full":"5407 S Lamont Rd Springfield TN 37172",
    "addr:housenumber":"5407",
    "addr:postcode":"37172",
    "addr:street":"S Lamont Rd",
    "iso:country":"US",
    "sg:address":"5407 S Lamont Rd",
    "sg:city":"Springfield",
    "sg:classifiers":[
        {
            "category":"Wholesale",
            "subcategory":"Plants",
            "type":"Manufacturing & Wholesale Goods"
        }
    ],
    "sg:phone":"+1 615 654 3569",
    "sg:postcode":"37172",
    "sg:province":"TN",
    "wof:name":"Fishers Greenhouse",
    "wof:placetype":"venue"
},
  "geometry": {"coordinates":[-86.762703,36.595075],"type":"Point"}
}