{
  "type": "Feature",
  "properties": {
    "iso:country":"US",
    "sg:address":"4638 Talley Rd",
    "sg:city":"Millington",
    "sg:classifiers":[
        {
            "category":"Professional",
            "subcategory":"Business Services",
            "type":"Services"
        }
    ],
    "sg:phone":"+1 901 872 4638",
    "sg:postcode":"38053",
    "sg:province":"TN",
    "sg:tags":[
        "consultant",
        "coach"
    ],
    "wof:name":"Ninja Store",
    "wof:placetype":"venue"
},
  "geometry": {"coordinates":[-89.908714,35.344236],"type":"Point"}
}