{
  "type": "Feature",
  "properties": {
    "addr:full":"2235 Covington Pike Memphis TN 38128",
    "addr:housenumber":"2235",
    "addr:postcode":"38128",
    "addr:street":"Covington Pike",
    "iso:country":"US",
    "sg:address":"2235 Covington Pike",
    "sg:city":"Memphis",
    "sg:classifiers":[
        {
            "category":"Retail",
            "subcategory":"Auto Rental",
            "type":"Services"
        }
    ],
    "sg:phone":"+1 901 368 1444",
    "sg:postcode":"38128",
    "sg:province":"TN",
    "sg:tags":[
        "renting",
        "automobile"
    ],
    "wof:name":"Access Car Rental",
    "wof:placetype":"venue"
},
  "geometry": {"coordinates":[-89.89623,35.18665],"type":"Point"}
}