{
  "type": "Feature",
  "properties": {
    "addr:full":"1828 Airbase Rd Louisville TN 37777",
    "addr:housenumber":"1828",
    "addr:postcode":"37777",
    "addr:street":"Airbase Rd",
    "iso:country":"US",
    "sg:address":"1828 Airbase Rd",
    "sg:city":"Louisville",
    "sg:classifiers":[
        {
            "category":"Banks & Credit Unions",
            "subcategory":"Bank",
            "type":"Services"
        }
    ],
    "sg:phone":"+1 865 970 7283",
    "sg:postcode":"37777",
    "sg:province":"TN",
    "sg:tags":[
        "federal"
    ],
    "wof:name":"ETMA Federal Credit Union",
    "wof:placetype":"venue"
},
  "geometry": {"coordinates":[-83.98364100000001,35.829103],"type":"Point"}
}