{
  "type": "Feature",
  "properties": {
    "addr:full":"2001 Genco Dr Cookeville TN 38506",
    "addr:housenumber":"2001",
    "addr:postcode":"38506",
    "addr:street":"Genco Dr",
    "iso:country":"US",
    "sg:address":"2001 Genco Dr",
    "sg:city":"Cookeville",
    "sg:classifiers":[
        {
            "category":"Manufacturing",
            "subcategory":"Metals",
            "type":"Manufacturing & Wholesale Goods"
        }
    ],
    "sg:phone":"+1 931 528 5574",
    "sg:postcode":"38506",
    "sg:province":"TN",
    "sg:tags":[
        "treating",
        "heat",
        "stampings",
        "mfg"
    ],
    "wof:name":"Genco Stamping & Manufacturing",
    "wof:placetype":"venue"
},
  "geometry": {"coordinates":[-85.46477299999999,36.189624],"type":"Point"}
}