{
  "type": "Feature",
  "properties": {
    "iso:country":"US",
    "sg:address":"1533 Amherst Rd",
    "sg:city":"Knoxville",
    "sg:classifiers":[
        {
            "category":"Communications",
            "subcategory":"Television Station",
            "type":"Services"
        }
    ],
    "sg:phone":"+1 865 693 1020",
    "sg:postcode":"37909",
    "sg:province":"TN",
    "sg:tags":[
        "broadcast",
        "radio"
    ],
    "wof:name":"Wmyu FM",
    "wof:placetype":"venue"
},
  "geometry": {"coordinates":[-84.01225,35.952747],"type":"Point"}
}