{
  "type": "Feature",
  "properties": {
    "iso:country":"US",
    "sg:address":"4697 Alamo Gadsden Rd",
    "sg:city":"Gadsden",
    "sg:classifiers":[
        {
            "category":"Manufacturing",
            "subcategory":"Glass & Minerals",
            "type":"Manufacturing & Wholesale Goods"
        }
    ],
    "sg:phone":"+1 731 696 3066",
    "sg:postcode":"38337",
    "sg:province":"TN",
    "sg:tags":[
        "concrete",
        "product",
        "mfg"
    ],
    "wof:name":"1st Impressions USA Inc",
    "wof:placetype":"venue"
},
  "geometry": {"coordinates":[-89.01743399999999,35.786871],"type":"Point"}
}