{
  "type": "Feature",
  "properties": {
    "addr:full":"927 Oglewood Ave NE Knoxville TN 37917",
    "addr:housenumber":"927",
    "addr:postcode":"37917",
    "addr:street":"Oglewood Ave Ne",
    "iso:country":"US",
    "sg:address":"927 Oglewood Ave NE",
    "sg:city":"Knoxville",
    "sg:classifiers":[
        {
            "category":"Education",
            "subcategory":"School",
            "type":"Public Place"
        }
    ],
    "sg:phone":"+1 865 594 8500",
    "sg:postcode":"37917",
    "sg:province":"TN",
    "wof:name":"Christenberry Elementary Schl",
    "wof:placetype":"venue"
},
  "geometry": {"coordinates":[-83.928867,35.995435],"type":"Point"}
}