{
  "type": "Feature",
  "properties": {
    "iso:country":"US",
    "sg:address":"508 Taylor St",
    "sg:city":"Brownsville",
    "sg:classifiers":[
        {
            "category":"Social Services",
            "subcategory":"Child Care",
            "type":"Services"
        }
    ],
    "sg:phone":"+1 731 779 3124",
    "sg:postcode":"38012",
    "sg:province":"TN",
    "sg:tags":[
        "day"
    ],
    "wof:name":"Samanthas Child Care",
    "wof:placetype":"venue"
},
  "geometry": {"coordinates":[-89.26976500000001,35.587786],"type":"Point"}
}