{
  "type": "Feature",
  "properties": {
    "addr:full":"147 4th Ave N Nashville TN 37219",
    "addr:housenumber":"147",
    "addr:postcode":"37219",
    "addr:street":"4Th Ave N",
    "iso:country":"US",
    "sg:address":"147 4th Ave N",
    "sg:city":"Nashville",
    "sg:classifiers":[
        {
            "category":"Parking",
            "type":"Transportation"
        }
    ],
    "sg:phone":"+1 615 742 0087",
    "sg:postcode":"37219",
    "sg:province":"TN",
    "sg:tags":[
        "garage"
    ],
    "wof:name":"CENTRAL Parking",
    "wof:placetype":"venue"
},
  "geometry": {"coordinates":[-86.778054,36.16215],"type":"Point"}
}