{
  "type": "Feature",
  "properties": {
    "iso:country":"US",
    "sg:address":"1000 W Main St",
    "sg:city":"Decherd",
    "sg:classifiers":[
        {
            "category":"Retail",
            "subcategory":"Auto Repair",
            "type":"Services"
        }
    ],
    "sg:phone":"+1 931 968 4948",
    "sg:postcode":"37324",
    "sg:province":"TN",
    "sg:tags":[
        "wrecker"
    ],
    "wof:name":"Ikard Towing",
    "wof:placetype":"venue"
},
  "geometry": {"coordinates":[-86.08701499999999,35.206673],"type":"Point"}
}