{
  "type": "Feature",
  "properties": {
    "iso:country":"US",
    "sg:address":"2851 Shelby St",
    "sg:city":"Bartlett",
    "sg:classifiers":[
        {
            "category":"Real Estate",
            "subcategory":"Real Estate Agent",
            "type":"Services"
        }
    ],
    "sg:phone":"+1 901 383 7377",
    "sg:postcode":"38134",
    "sg:province":"TN",
    "sg:tags":[
        "management"
    ],
    "wof:name":"Micro Management",
    "wof:placetype":"venue"
},
  "geometry": {"coordinates":[-89.874441,35.203042],"type":"Point"}
}