{
  "type": "Feature",
  "properties": {
    "iso:country":"US",
    "sg:address":"988 Oak Ridge Tpke",
    "sg:city":"Oak Ridge",
    "sg:classifiers":[
        {
            "category":"Health Services",
            "subcategory":"Medical Lab",
            "type":"Services"
        }
    ],
    "sg:phone":"+1 865 482 4028",
    "sg:postcode":"37830",
    "sg:province":"TN",
    "sg:tags":[
        "laboratory"
    ],
    "sg:website":"www.vdcor.com",
    "wof:name":"Vascular Diagnostics Ctr",
    "wof:placetype":"venue"
},
  "geometry": {"coordinates":[-84.24391799999999,36.023536],"type":"Point"}
}