{
  "type": "Feature",
  "properties": {
    "iso:country":"US",
    "sg:address":"173 Moore Rd",
    "sg:city":"Jonesborough",
    "sg:classifiers":[
        {
            "category":"Real Estate",
            "subcategory":"Real Estate Agent",
            "type":"Services"
        }
    ],
    "sg:phone":"+1 423 913 3885",
    "sg:postcode":"37659",
    "sg:province":"TN",
    "wof:name":"White's Star Realty",
    "wof:placetype":"venue"
},
  "geometry": {"coordinates":[-82.508639,36.357231],"type":"Point"}
}