{
  "type": "Feature",
  "properties": {
    "addr:full":"421 Cedar Grove Rd Johnson City TN 37601",
    "addr:housenumber":"421",
    "addr:postcode":"37601",
    "addr:street":"Cedar Grove Rd",
    "iso:country":"US",
    "sg:address":"421 Cedar Grove Rd",
    "sg:city":"Johnson City",
    "sg:classifiers":[
        {
            "category":"Building & Trades",
            "subcategory":"Construction",
            "type":"Services"
        }
    ],
    "sg:phone":"+1 423 926 5344",
    "sg:postcode":"37601",
    "sg:province":"TN",
    "sg:tags":[
        "painting",
        "painter",
        "contractor"
    ],
    "wof:name":"Massey Brothers Painting Inc",
    "wof:placetype":"venue"
},
  "geometry": {"coordinates":[-82.318417,36.308565],"type":"Point"}
}