{
  "type": "Feature",
  "properties": {
    "iso:country":"US",
    "sg:address":"1201 Riverfront Pkwy",
    "sg:city":"Chattanooga",
    "sg:classifiers":[
        {
            "category":"Professional",
            "subcategory":"Engineering",
            "type":"Services"
        }
    ],
    "sg:phone":"+1 423 752 2387",
    "sg:postcode":"37408",
    "sg:province":"TN",
    "wof:name":"Apcompower Inc",
    "wof:placetype":"venue"
},
  "geometry": {"coordinates":[-85.320744,35.043122],"type":"Point"}
}