{
  "type": "Feature",
  "properties": {
    "iso:country":"US",
    "sg:address":"112 Randy Rd",
    "sg:city":"Madison",
    "sg:classifiers":[
        {
            "category":"Shopping",
            "subcategory":"Hobbies, Toys, & Games",
            "type":"Retail Goods"
        }
    ],
    "sg:phone":"+1 615 868 5279",
    "sg:postcode":"37115",
    "sg:province":"TN",
    "wof:name":"Des Artworks",
    "wof:placetype":"venue"
},
  "geometry": {"coordinates":[-86.691946,36.257465],"type":"Point"}
}