{
  "type": "Feature",
  "properties": {
    "iso:country":"US",
    "sg:address":"189 Graylynn Dr",
    "sg:city":"Nashville",
    "sg:classifiers":[
        {
            "category":"Banks & Credit Unions",
            "subcategory":"Bank",
            "type":"Services"
        }
    ],
    "sg:phone":"+1 615 902 9600",
    "sg:postcode":"37214",
    "sg:province":"TN",
    "sg:tags":[
        "loan",
        "real estate"
    ],
    "wof:name":"Gateway Financial Group",
    "wof:placetype":"venue"
},
  "geometry": {"coordinates":[-86.674351,36.169635],"type":"Point"}
}