{
  "type": "Feature",
  "properties": {
    "iso:country":"US",
    "sg:address":"1600 N Jackson St",
    "sg:city":"Tullahoma",
    "sg:classifiers":[
        {
            "category":"Shopping",
            "subcategory":"Department Store",
            "type":"Retail Goods"
        }
    ],
    "sg:phone":"+1 931 455 0074",
    "sg:postcode":"37388",
    "sg:province":"TN",
    "wof:name":"J C Penney Co",
    "wof:placetype":"venue"
},
  "geometry": {"coordinates":[-86.226783,35.378771],"type":"Point"}
}