{
  "type": "Feature",
  "properties": {
    "iso:country":"US",
    "sg:address":"400 S Charles G Seivers Blvd",
    "sg:city":"Clinton",
    "sg:classifiers":[
        {
            "category":"Organizations",
            "subcategory":"Religious Organization",
            "type":"Services"
        }
    ],
    "sg:phone":"+1 865 457 8777",
    "sg:postcode":"37716",
    "sg:province":"TN",
    "sg:tags":[
        "church"
    ],
    "wof:name":"Clinton Christian Church",
    "wof:placetype":"venue"
},
  "geometry": {"coordinates":[-84.137214,36.093325],"type":"Point"}
}