{
  "type": "Feature",
  "properties": {
    "addr:full":"309 W Morford St Mc Minnville TN 37110",
    "addr:housenumber":"309",
    "addr:postcode":"37110",
    "addr:street":"W Morford St",
    "iso:country":"US",
    "sg:address":"309 W Morford St",
    "sg:city":"Mc Minnville",
    "sg:classifiers":[
        {
            "category":"Personal",
            "subcategory":"Beauty Salon",
            "type":"Services"
        }
    ],
    "sg:phone":"+1 931 473 2824",
    "sg:postcode":"37110",
    "sg:province":"TN",
    "sg:tags":[
        "shop",
        "manicuring"
    ],
    "wof:name":"Universal Nails",
    "wof:placetype":"venue"
},
  "geometry": {"coordinates":[-85.778589,35.682603],"type":"Point"}
}