{
  "type": "Feature",
  "properties": {
    "iso:country":"US",
    "sg:address":"112 Midtown Ct",
    "sg:city":"Hendersonville",
    "sg:classifiers":[
        {
            "category":"Building & Trades",
            "subcategory":"Cleaning & Sanitation",
            "type":"Services"
        }
    ],
    "sg:phone":"+1 615 822 6882",
    "sg:postcode":"37075",
    "sg:province":"TN",
    "sg:tags":[
        "maintenance"
    ],
    "wof:name":"Kleanway Systems",
    "wof:placetype":"venue"
},
  "geometry": {"coordinates":[-86.634378,36.304361],"type":"Point"}
}