{
  "type": "Feature",
  "properties": {
    "addr:full":"4186 Locust Ridge Rd Sevierville TN 37876",
    "addr:housenumber":"4186",
    "addr:postcode":"37876",
    "addr:street":"Locust Ridge Rd",
    "iso:country":"US",
    "sg:address":"4186 Locust Ridge Rd",
    "sg:city":"Sevierville",
    "sg:classifiers":[
        {
            "category":"Personal",
            "type":"Services"
        }
    ],
    "sg:phone":"+1 865 774 0078",
    "sg:postcode":"37876",
    "sg:province":"TN",
    "wof:name":"Gold & Tan Tanning Salon",
    "wof:placetype":"venue"
},
  "geometry": {"coordinates":[-83.391454,35.800488],"type":"Point"}
}