{
  "type": "Feature",
  "properties": {
    "iso:country":"US",
    "sg:address":"3070 Saint Elmo Ave",
    "sg:city":"Chattanooga",
    "sg:classifiers":[
        {
            "category":"Manufacturing",
            "subcategory":"Printing",
            "type":"Manufacturing & Wholesale Goods"
        }
    ],
    "sg:phone":"+1 423 266 3532",
    "sg:postcode":"37408",
    "sg:province":"TN",
    "sg:tags":[
        "printer"
    ],
    "wof:name":"Image Works",
    "wof:placetype":"venue"
},
  "geometry": {"coordinates":[-85.32041599999999,35.022161],"type":"Point"}
}