{
  "type": "Feature",
  "properties": {
    "iso:country":"US",
    "sg:address":"7710 Lantana Rd",
    "sg:city":"Crossville",
    "sg:classifiers":[
        {
            "category":"Building & Trades",
            "subcategory":"Landscaping Services",
            "type":"Services"
        }
    ],
    "sg:phone":"+1 931 788 2083",
    "sg:postcode":"38572",
    "sg:province":"TN",
    "wof:name":"Wood Lawn Service",
    "wof:placetype":"venue"
},
  "geometry": {"coordinates":[-85.126721,35.846038],"type":"Point"}
}