{
  "type": "Feature",
  "properties": {
    "addr:full":"3014 Bristol Hwy Johnson City TN 37601",
    "addr:housenumber":"3014",
    "addr:postcode":"37601",
    "addr:street":"Bristol Hwy",
    "iso:country":"US",
    "sg:address":"3014 Bristol Hwy",
    "sg:city":"Johnson City",
    "sg:classifiers":[
        {
            "category":"Home & Garden",
            "subcategory":"Household Appliances",
            "type":"Retail Goods"
        }
    ],
    "sg:phone":"+1 423 926 1417",
    "sg:postcode":"37601",
    "sg:province":"TN",
    "sg:tags":[
        "machine",
        "quilting"
    ],
    "sg:website":"www.somewheresewing.com",
    "wof:name":"Somewhere Sewing",
    "wof:placetype":"venue"
},
  "geometry": {"coordinates":[-82.38409900000001,36.360397],"type":"Point"}
}