{
  "type": "Feature",
  "properties": {
    "iso:country":"US",
    "sg:address":"1812 E 12th St",
    "sg:city":"Chattanooga",
    "sg:classifiers":[
        {
            "category":"Organizations",
            "subcategory":"Religious Organization",
            "type":"Services"
        }
    ],
    "sg:phone":"+1 423 622 4120",
    "sg:postcode":"37404",
    "sg:province":"TN",
    "wof:name":"Foster Ezell",
    "wof:placetype":"venue"
},
  "geometry": {"coordinates":[-85.278805,35.028379],"type":"Point"}
}