{
  "type": "Feature",
  "properties": {
    "iso:country":"US",
    "sg:address":"5891 Taft Hwy",
    "sg:city":"Signal Mountain",
    "sg:classifiers":[
        {
            "category":"Autos & Motor Vehicles",
            "subcategory":"Automobile Sales",
            "type":"Retail Goods"
        }
    ],
    "sg:phone":"+1 423 886 7489",
    "sg:postcode":"37377",
    "sg:province":"TN",
    "sg:tags":[
        "car",
        "dealer"
    ],
    "wof:name":"Southwest Co",
    "wof:placetype":"venue"
},
  "geometry": {"coordinates":[-85.35114299999999,35.188037],"type":"Point"}
}