{
  "type": "Feature",
  "properties": {
    "iso:country":"US",
    "sg:address":"456 Lindsay Mill Cir",
    "sg:city":"Lake City",
    "sg:classifiers":[
        {
            "category":"Building & Trades",
            "subcategory":"Cleaning & Sanitation",
            "type":"Services"
        }
    ],
    "sg:phone":"+1 865 637 1817",
    "sg:postcode":"37769",
    "sg:province":"TN",
    "sg:tags":[
        "maintenance"
    ],
    "wof:name":"Professional Chimney Sweeps",
    "wof:placetype":"venue"
},
  "geometry": {"coordinates":[-84.150819,36.260186],"type":"Point"}
}