{
  "type": "Feature",
  "properties": {
    "addr:full":"811 W Main St Waverly TN 37185",
    "addr:housenumber":"811",
    "addr:postcode":"37185",
    "addr:street":"W Main St",
    "iso:country":"US",
    "sg:address":"811 W Main St",
    "sg:city":"Waverly",
    "sg:classifiers":[
        {
            "category":"Health Services",
            "subcategory":"Nursing And Care Facility",
            "type":"Services"
        }
    ],
    "sg:phone":"+1 931 296 4131",
    "sg:postcode":"37185",
    "sg:province":"TN",
    "sg:tags":[
        "intermediate"
    ],
    "wof:name":"Magnolia Place Assisted Living",
    "wof:placetype":"venue"
},
  "geometry": {"coordinates":[-87.82104099999999,36.08179],"type":"Point"}
}