{
  "type": "Feature",
  "properties": {
    "iso:country":"US",
    "sg:address":"1807 Quinn Rd",
    "sg:city":"Collierville",
    "sg:classifiers":[
        {
            "category":"Building & Trades",
            "subcategory":"Landscaping Services",
            "type":"Services"
        }
    ],
    "sg:phone":"+1 901 854 2646",
    "sg:postcode":"38017",
    "sg:province":"TN",
    "sg:tags":[
        "landscape",
        "contractor"
    ],
    "sg:website":"www.agriscapes.com",
    "wof:name":"Agriscapes LLC",
    "wof:placetype":"venue"
},
  "geometry": {"coordinates":[-89.661835,34.995649],"type":"Point"}
}