{
  "type": "Feature",
  "properties": {
    "iso:country":"US",
    "sg:address":"4441 S 3rd St",
    "sg:city":"Memphis",
    "sg:classifiers":[
        {
            "category":"Shopping",
            "subcategory":"Department Store",
            "type":"Retail Goods"
        }
    ],
    "sg:phone":"+1 901 785 9302",
    "sg:postcode":"38109",
    "sg:province":"TN",
    "wof:name":"Bargain Center USA",
    "wof:placetype":"venue"
},
  "geometry": {"coordinates":[-90.081283,35.027548],"type":"Point"}
}