{
  "type": "Feature",
  "properties": {
    "iso:country":"US",
    "sg:address":"267 Stonecrossing Dr",
    "sg:city":"Clarksville",
    "sg:classifiers":[
        {
            "category":"Banks & Credit Unions",
            "subcategory":"Bank",
            "type":"Services"
        }
    ],
    "sg:phone":"+1 931 920 2252",
    "sg:postcode":"37042",
    "sg:province":"TN",
    "sg:tags":[
        "mortgage",
        "loan",
        "broker",
        "real estate"
    ],
    "sg:website":"www.anchormortgage.com",
    "wof:name":"Anchor Mortgage Inc",
    "wof:placetype":"venue"
},
  "geometry": {"coordinates":[-87.39355500000001,36.585931],"type":"Point"}
}