{
  "type": "Feature",
  "properties": {
    "iso:country":"US",
    "sg:address":"5290 Brantford Ave",
    "sg:city":"Memphis",
    "sg:classifiers":[
        {
            "category":"Professional",
            "type":"Services"
        }
    ],
    "sg:phone":"+1 901 761 9845",
    "sg:postcode":"38120",
    "sg:province":"TN",
    "wof:name":"Bullshooters",
    "wof:placetype":"venue"
},
  "geometry": {"coordinates":[-89.887531,35.118668],"type":"Point"}
}