{
  "type": "Feature",
  "properties": {
    "iso:country":"US",
    "sg:address":"724 Bacon Trl",
    "sg:city":"Chattanooga",
    "sg:classifiers":[
        {
            "category":"Organizations",
            "subcategory":"Community Association",
            "type":"Services"
        }
    ],
    "sg:phone":"+1 423 629 5037",
    "sg:postcode":"37412",
    "sg:province":"TN",
    "wof:name":"Belvoir Hills Estates",
    "wof:placetype":"venue"
},
  "geometry": {"coordinates":[-85.246431,35.009497],"type":"Point"}
}