{
  "type": "Feature",
  "properties": {
    "iso:country":"US",
    "sg:address":"30 Trezevant Hwy",
    "sg:city":"Bradford",
    "sg:classifiers":[
        {
            "category":"Building & Trades",
            "subcategory":"Construction",
            "type":"Services"
        }
    ],
    "sg:phone":"+1 731 742 2476",
    "sg:postcode":"38316",
    "sg:province":"TN",
    "sg:tags":[
        "contractor"
    ],
    "wof:name":"Tennessee Volunteer Siding Co",
    "wof:placetype":"venue"
},
  "geometry": {"coordinates":[-88.792182,36.0799],"type":"Point"}
}