{
  "type": "Feature",
  "properties": {
    "iso:country":"US",
    "sg:address":"865 W Trinity Ln",
    "sg:city":"Nashville",
    "sg:classifiers":[
        {
            "category":"Wholesale",
            "subcategory":"Scrap",
            "type":"Manufacturing & Wholesale Goods"
        }
    ],
    "sg:phone":"+1 615 255 7617",
    "sg:postcode":"37207",
    "sg:province":"TN",
    "sg:tags":[
        "material"
    ],
    "wof:name":"Abernathy Salvage",
    "wof:placetype":"venue"
},
  "geometry": {"coordinates":[-86.79773400000001,36.207202],"type":"Point"}
}