{
  "type": "Feature",
  "properties": {
    "iso:country":"US",
    "sg:address":"1128 New Hampshire Ave",
    "sg:city":"Bristol",
    "sg:classifiers":[
        {
            "category":"Organizations",
            "subcategory":"Religious Organization",
            "type":"Services"
        }
    ],
    "sg:phone":"+1 276 669 0473",
    "sg:postcode":"24201",
    "sg:province":"TN",
    "sg:tags":[
        "church"
    ],
    "wof:name":"Covenant Fellowship Chr Of God",
    "wof:placetype":"venue"
},
  "geometry": {"coordinates":[-82.164931,36.602759],"type":"Point"}
}