{
  "type": "Feature",
  "properties": {
    "iso:country":"US",
    "sg:address":"2119 Gunbarrel Rd",
    "sg:city":"Chattanooga",
    "sg:classifiers":[
        {
            "category":"Restaurant",
            "type":"Food & Drink"
        }
    ],
    "sg:menulink":"http://www.allmenus.com/tn/chattanooga/99549-logans-roadhouse/menu/",
    "sg:phone":"+1 423 499 4339",
    "sg:postcode":"37421",
    "sg:province":"TN",
    "sg:tags":[
        "american"
    ],
    "wof:name":"Logan's Roadhouse",
    "wof:placetype":"venue"
},
  "geometry": {"coordinates":[-85.153126,35.035536],"type":"Point"}
}