{
  "type": "Feature",
  "properties": {
    "iso:country":"US",
    "sg:address":"39 Smith Ave",
    "sg:city":"Hohenwald",
    "sg:classifiers":[
        {
            "category":"Government",
            "subcategory":"Office",
            "type":"Public Place"
        }
    ],
    "sg:phone":"+1 931 796 2939",
    "sg:postcode":"38462",
    "sg:province":"TN",
    "sg:tags":[
        "county"
    ],
    "wof:name":"Lewis County Soil Conservation",
    "wof:placetype":"venue"
},
  "geometry": {"coordinates":[-87.55278300000001,35.551089],"type":"Point"}
}