{
  "type": "Feature",
  "properties": {
    "addr:full":"14805 Hickory Creek Rd Lenoir City TN 37771",
    "addr:housenumber":"14805",
    "addr:postcode":"37771",
    "addr:street":"Hickory Creek Rd",
    "iso:country":"US",
    "sg:address":"14805 Hickory Creek Rd",
    "sg:city":"Lenoir City",
    "sg:classifiers":[
        {
            "category":"Autos & Motor Vehicles",
            "subcategory":"Automobile Sales",
            "type":"Retail Goods"
        }
    ],
    "sg:phone":"+1 865 986 7700",
    "sg:postcode":"37771",
    "sg:province":"TN",
    "sg:tags":[
        "car",
        "used",
        "dealer"
    ],
    "wof:name":"American Truck and Trailer",
    "wof:placetype":"venue"
},
  "geometry": {"coordinates":[-84.254576,35.866331],"type":"Point"}
}