{
  "type": "Feature",
  "properties": {
    "addr:full":"1522 Decatur Pike Athens TN 37303",
    "addr:housenumber":"1522",
    "addr:postcode":"37303",
    "addr:street":"Decatur Pike",
    "iso:country":"US",
    "sg:address":"1522 Decatur Pike",
    "sg:city":"Athens",
    "sg:classifiers":[
        {
            "category":"Food & Beverages",
            "subcategory":"Specialty",
            "type":"Retail Goods"
        }
    ],
    "sg:phone":"+1 423 745 9511",
    "sg:postcode":"37303",
    "sg:province":"TN",
    "sg:tags":[
        "health",
        "diet"
    ],
    "wof:name":"Rightway Natural Foods",
    "wof:placetype":"venue"
},
  "geometry": {"coordinates":[-84.622016,35.450469],"type":"Point"}
}