{
  "type": "Feature",
  "properties": {
    "iso:country":"US",
    "sg:address":"2439 Peres Ave",
    "sg:city":"Memphis",
    "sg:classifiers":[
        {
            "category":"Organizations",
            "subcategory":"Religious Organization",
            "type":"Services"
        }
    ],
    "sg:phone":"+1 901 324 0631",
    "sg:postcode":"38108",
    "sg:province":"TN",
    "sg:tags":[
        "church"
    ],
    "wof:name":"United Fellowship MB Church",
    "wof:placetype":"venue"
},
  "geometry": {"coordinates":[-89.976022,35.176629],"type":"Point"}
}