{
  "type": "Feature",
  "properties": {
    "iso:country":"US",
    "sg:address":"2572 Treace Rd",
    "sg:city":"Hornbeak",
    "sg:classifiers":[
        {
            "category":"Wholesale",
            "subcategory":"Auto Parts",
            "type":"Manufacturing & Wholesale Goods"
        }
    ],
    "sg:phone":"+1 731 538 2204",
    "sg:postcode":"38232",
    "sg:province":"TN",
    "sg:tags":[
        "automobile",
        "rebuilt"
    ],
    "wof:name":"Shawtown Auto Salvage",
    "wof:placetype":"venue"
},
  "geometry": {"coordinates":[-89.303275,36.420524],"type":"Point"}
}