{
  "type": "Feature",
  "properties": {
    "addr:full":"6705 Kingston Pike Knoxville TN 37919",
    "addr:housenumber":"6705",
    "addr:postcode":"37919",
    "addr:street":"Kingston Pike",
    "iso:country":"US",
    "sg:address":"6705 Kingston Pike",
    "sg:city":"Knoxville",
    "sg:classifiers":[
        {
            "category":"Wholesale",
            "subcategory":"Electrical",
            "type":"Manufacturing & Wholesale Goods"
        }
    ],
    "sg:phone":"+1 865 212 4991",
    "sg:postcode":"37919",
    "sg:province":"TN",
    "sg:tags":[
        "radio"
    ],
    "wof:name":"Wireless Image LLC",
    "wof:placetype":"venue"
},
  "geometry": {"coordinates":[-84.013193,35.931947],"type":"Point"}
}