{
  "type": "Feature",
  "properties": {
    "iso:country":"US",
    "sg:address":"418 E Central Ave",
    "sg:city":"Jamestown",
    "sg:classifiers":[
        {
            "category":"Shopping",
            "subcategory":"Florist",
            "type":"Retail Goods"
        }
    ],
    "sg:phone":"+1 931 879 7718",
    "sg:postcode":"38556",
    "sg:province":"TN",
    "wof:name":"Fentress County Florist",
    "wof:placetype":"venue"
},
  "geometry": {"coordinates":[-84.92663899999999,36.427172],"type":"Point"}
}