{
  "type": "Feature",
  "properties": {
    "iso:country":"US",
    "sg:address":"120 Rosebank Ave",
    "sg:city":"Nashville",
    "sg:classifiers":[
        {
            "category":"Home & Garden",
            "subcategory":"Carpets & Floor Coverings",
            "type":"Retail Goods"
        }
    ],
    "sg:phone":"+1 615 650 8455",
    "sg:postcode":"37206",
    "sg:province":"TN",
    "sg:tags":[
        "tile",
        "design"
    ],
    "wof:name":"T M Setter Tile & Marble",
    "wof:placetype":"venue"
},
  "geometry": {"coordinates":[-86.72900300000001,36.187453],"type":"Point"}
}