{
  "type": "Feature",
  "properties": {
    "iso:country":"US",
    "sg:address":"2837 S Commerce Rd",
    "sg:city":"Watertown",
    "sg:classifiers":[
        {
            "category":"Farming",
            "subcategory":"Dairy Farm",
            "type":"Manufacturing & Wholesale Goods"
        }
    ],
    "sg:phone":"+1 615 237 3407",
    "sg:postcode":"37184",
    "sg:province":"TN",
    "wof:name":"J&R Farm",
    "wof:placetype":"venue"
},
  "geometry": {"coordinates":[-86.110983,36.132988],"type":"Point"}
}