{
  "type": "Feature",
  "properties": {
    "iso:country":"US",
    "sg:address":"146 Volunteer Dr",
    "sg:city":"Elizabethton",
    "sg:classifiers":[
        {
            "category":"Building & Trades",
            "subcategory":"Construction",
            "type":"Services"
        }
    ],
    "sg:phone":"+1 423 542 6817",
    "sg:postcode":"37643",
    "sg:province":"TN",
    "sg:tags":[
        "painter"
    ],
    "wof:name":"Volunteer Painting & Sndblstng",
    "wof:placetype":"venue"
},
  "geometry": {"coordinates":[-82.215783,36.36909],"type":"Point"}
}