{
  "type": "Feature",
  "properties": {
    "addr:full":"2313 Hampton Ave Nashville TN 37215",
    "addr:housenumber":"2313",
    "addr:postcode":"37215",
    "addr:street":"Hampton Ave",
    "iso:country":"US",
    "sg:address":"2313 Hampton Ave",
    "sg:city":"Nashville",
    "sg:classifiers":[
        {
            "category":"Professional",
            "subcategory":"Business Services",
            "type":"Services"
        }
    ],
    "sg:phone":"+1 615 292 4180",
    "sg:postcode":"37215",
    "sg:province":"TN",
    "wof:name":"Van Slyke Family Partnership",
    "wof:placetype":"venue"
},
  "geometry": {"coordinates":[-86.826561,36.117361],"type":"Point"}
}