{
  "type": "Feature",
  "properties": {
    "addr:full":"6174 State Hwy 88 Maury City TN 38040",
    "addr:housenumber":"6174",
    "addr:postcode":"38040",
    "addr:street":"State Hwy 88 Maury",
    "iso:country":"US",
    "sg:address":"6174 State Hwy 88",
    "sg:city":"Maury City",
    "sg:classifiers":[
        {
            "category":"Building & Trades",
            "subcategory":"Landscaping Services",
            "type":"Services"
        }
    ],
    "sg:phone":"+1 731 656 2205",
    "sg:postcode":"38040",
    "sg:province":"TN",
    "sg:tags":[
        "mowing"
    ],
    "wof:name":"J R Mowing Co",
    "wof:placetype":"venue"
},
  "geometry": {"coordinates":[-89.48886299999999,35.909731],"type":"Point"}
}