{
  "type": "Feature",
  "properties": {
    "iso:country":"US",
    "sg:address":"6145 Temple Star Rd",
    "sg:city":"Kingsport",
    "sg:classifiers":[
        {
            "category":"Professional",
            "type":"Services"
        }
    ],
    "sg:phone":"+1 423 349 4051",
    "sg:postcode":"37660",
    "sg:province":"TN",
    "sg:tags":[
        "establishment"
    ],
    "wof:name":"Redwood Toxicology",
    "wof:placetype":"venue"
},
  "geometry": {"coordinates":[-82.624199,36.467903],"type":"Point"}
}