{
  "type": "Feature",
  "properties": {
    "addr:full":"100 Hunters Ct Tullahoma TN 37388",
    "addr:housenumber":"100",
    "addr:postcode":"37388",
    "addr:street":"Hunters Ct",
    "iso:country":"US",
    "sg:address":"100 Hunters Ct",
    "sg:city":"Tullahoma",
    "sg:classifiers":[
        {
            "category":"Health Services",
            "subcategory":"Health Practitioner",
            "type":"Services"
        }
    ],
    "sg:phone":"+1 931 455 1980",
    "sg:postcode":"37388",
    "sg:province":"TN",
    "sg:tags":[
        "therapist",
        "physical"
    ],
    "wof:name":"Results Physiotherapy",
    "wof:placetype":"venue"
},
  "geometry": {"coordinates":[-86.23011700000001,35.415232],"type":"Point"}
}