{
  "type": "Feature",
  "properties": {
    "iso:country":"US",
    "sg:address":"29 Franwood Cove",
    "sg:city":"Jackson",
    "sg:classifiers":[
        {
            "category":"Building & Trades",
            "subcategory":"Construction",
            "type":"Services"
        }
    ],
    "sg:phone":"+1 731 661 0994",
    "sg:postcode":"38301",
    "sg:province":"TN",
    "sg:tags":[
        "house"
    ],
    "wof:name":"McKown Renovations",
    "wof:placetype":"venue"
},
  "geometry": {"coordinates":[-88.84405,35.646196],"type":"Point"}
}