{
  "type": "Feature",
  "properties": {
    "iso:country":"US",
    "sg:address":"7815 Kingston Pike",
    "sg:city":"Knoxville",
    "sg:classifiers":[
        {
            "category":"Health Services",
            "subcategory":"Clinic",
            "type":"Services"
        }
    ],
    "sg:phone":"+1 865 692 0383",
    "sg:postcode":"37919",
    "sg:province":"TN",
    "wof:name":"Team Health",
    "wof:placetype":"venue"
},
  "geometry": {"coordinates":[-84.04217300000001,35.926937],"type":"Point"}
}