{
  "type": "Feature",
  "properties": {
    "addr:full":"2601 Farms Cir Woodlawn TN 37191",
    "addr:housenumber":"2601",
    "addr:postcode":"37191",
    "addr:street":"Farms Cir",
    "iso:country":"US",
    "sg:address":"2601 Farms Cir",
    "sg:city":"Woodlawn",
    "sg:classifiers":[
        {
            "category":"Real Estate",
            "subcategory":"Developer",
            "type":"Services"
        }
    ],
    "sg:phone":"+1 931 645 1896",
    "sg:postcode":"37191",
    "sg:province":"TN",
    "sg:tags":[
        "cemetery"
    ],
    "wof:name":"Woodlawn Park Parent Club",
    "wof:placetype":"venue"
},
  "geometry": {"coordinates":[-87.51863899999999,36.532301],"type":"Point"}
}