{
  "type": "Feature",
  "properties": {
    "iso:country":"US",
    "sg:address":"1822 Hollywood Dr",
    "sg:city":"Jackson",
    "sg:classifiers":[
        {
            "category":"Freight",
            "type":"Transportation"
        }
    ],
    "sg:phone":"+1 731 668 9221",
    "sg:postcode":"38305",
    "sg:province":"TN",
    "sg:tags":[
        "carrier",
        "motor"
    ],
    "sg:website":"www.myyellowfreight.com",
    "wof:name":"Yellow Transportation Inc",
    "wof:placetype":"venue"
},
  "geometry": {"coordinates":[-88.859994,35.645494],"type":"Point"}
}