{
  "type": "Feature",
  "properties": {
    "addr:full":"501 E Race St Kingston TN 37763",
    "addr:housenumber":"501",
    "addr:postcode":"37763",
    "addr:street":"E Race St",
    "iso:country":"US",
    "sg:address":"501 E Race St",
    "sg:city":"Kingston",
    "sg:classifiers":[
        {
            "category":"Organizations",
            "subcategory":"Religious Organization",
            "type":"Services"
        }
    ],
    "sg:phone":"+1 865 376 3723",
    "sg:postcode":"37763",
    "sg:province":"TN",
    "wof:name":"Foursquare Gospel Church",
    "wof:placetype":"venue"
},
  "geometry": {"coordinates":[-84.513125,35.869654],"type":"Point"}
}