{
  "type": "Feature",
  "properties": {
    "addr:full":"3044 Winfield Dunn Pkwy Kodak TN 37764",
    "addr:housenumber":"3044",
    "addr:postcode":"37764",
    "addr:street":"Winfield Dunn Pkwy",
    "iso:country":"US",
    "sg:address":"3044 Winfield Dunn Pkwy",
    "sg:city":"Kodak",
    "sg:classifiers":[
        {
            "category":"Shopping",
            "type":"Retail Goods"
        }
    ],
    "sg:phone":"+1 865 933 9115",
    "sg:postcode":"37764",
    "sg:province":"TN",
    "sg:tags":[
        "outdoor",
        "lighting",
        "specialty"
    ],
    "sg:website":"www.countrychristmasonline.com",
    "wof:name":"Country Christmas",
    "wof:placetype":"venue"
},
  "geometry": {"coordinates":[-83.595944,35.964476],"type":"Point"}
}