{
  "type": "Feature",
  "properties": {
    "iso:country":"US",
    "sg:address":"303 Wilton Springs Rd",
    "sg:city":"Newport",
    "sg:classifiers":[
        {
            "category":"Home & Garden",
            "subcategory":"Hardware",
            "type":"Retail Goods"
        }
    ],
    "sg:phone":"+1 423 623 9777",
    "sg:postcode":"37821",
    "sg:province":"TN",
    "sg:tags":[
        "station",
        "gasoline",
        "store",
        "variety"
    ],
    "wof:name":"Wilton Springs Hardware LLC",
    "wof:placetype":"venue"
},
  "geometry": {"coordinates":[-83.206845,35.876856],"type":"Point"}
}