{
  "type": "Feature",
  "properties": {
    "iso:country":"US",
    "sg:address":"153 Space Park S",
    "sg:city":"Nashville",
    "sg:classifiers":[
        {
            "category":"Building & Trades",
            "subcategory":"Equipment Rental",
            "type":"Services"
        }
    ],
    "sg:phone":"+1 615 834 7655",
    "sg:postcode":"37211",
    "sg:province":"TN",
    "sg:tags":[
        "material"
    ],
    "wof:name":"Ames Taping Tool Systems Inc",
    "wof:placetype":"venue"
},
  "geometry": {"coordinates":[-86.70662900000001,36.098702],"type":"Point"}
}