{
  "type": "Feature",
  "properties": {
    "addr:full":"9205 San Jose Ln Knoxville TN 37922",
    "addr:housenumber":"9205",
    "addr:postcode":"37922",
    "addr:street":"San Jose Ln",
    "iso:country":"US",
    "sg:address":"9205 San Jose Ln",
    "sg:city":"Knoxville",
    "sg:classifiers":[
        {
            "category":"Shopping",
            "subcategory":"Hobbies, Toys, & Games",
            "type":"Retail Goods"
        }
    ],
    "sg:phone":"+1 865 690 7769",
    "sg:postcode":"37922",
    "sg:province":"TN",
    "wof:name":"Painting Etc",
    "wof:placetype":"venue"
},
  "geometry": {"coordinates":[-84.061526,35.873602],"type":"Point"}
}