{
  "type": "Feature",
  "properties": {
    "iso:country":"US",
    "sg:address":"8658 Rosemark Rd",
    "sg:city":"Millington",
    "sg:classifiers":[
        {
            "category":"Organizations",
            "subcategory":"Religious Organization",
            "type":"Services"
        }
    ],
    "sg:phone":"+1 901 829 4105",
    "sg:postcode":"38053",
    "sg:province":"TN",
    "wof:name":"Richland Assc Refmd Pres CHR",
    "wof:placetype":"venue"
},
  "geometry": {"coordinates":[-89.77138600000001,35.368974],"type":"Point"}
}