{
  "type": "Feature",
  "properties": {
    "iso:country":"US",
    "sg:address":"802 Park Meadow",
    "sg:city":"Halls",
    "sg:classifiers":[
        {
            "category":"Government",
            "subcategory":"Office",
            "type":"Public Place"
        }
    ],
    "sg:phone":"+1 901 325 7800",
    "sg:postcode":"38040",
    "sg:province":"TN",
    "sg:tags":[
        "housing",
        "program"
    ],
    "wof:name":"Wesley Pk Madows Elderly Hsing",
    "wof:placetype":"venue"
},
  "geometry": {"coordinates":[-89.40831900000001,35.88356],"type":"Point"}
}