{
  "type": "Feature",
  "properties": {
    "addr:full":"3404 W End Ave Nashville TN 37203",
    "addr:housenumber":"3404",
    "addr:postcode":"37203",
    "addr:street":"W End Ave",
    "iso:country":"US",
    "sg:address":"3404 W End Ave",
    "sg:city":"Nashville",
    "sg:classifiers":[
        {
            "category":"Insurance",
            "subcategory":"Insurance Agent",
            "type":"Services"
        }
    ],
    "sg:phone":"+1 615 298 4110",
    "sg:postcode":"37203",
    "sg:province":"TN",
    "wof:name":"Allstate",
    "wof:placetype":"venue"
},
  "geometry": {"coordinates":[-86.82053500000001,36.138106],"type":"Point"}
}