{
  "type": "Feature",
  "properties": {
    "iso:country":"US",
    "sg:address":"110 Miller Plz",
    "sg:city":"Ashland City",
    "sg:classifiers":[
        {
            "category":"Building & Trades",
            "subcategory":"Cleaning & Sanitation",
            "type":"Services"
        }
    ],
    "sg:phone":"+1 615 792 9410",
    "sg:postcode":"37015",
    "sg:province":"TN",
    "sg:tags":[
        "maintenance"
    ],
    "wof:name":"Norm Ragan Maintenance",
    "wof:placetype":"venue"
},
  "geometry": {"coordinates":[-87.054055,36.269415],"type":"Point"}
}