{
  "type": "Feature",
  "properties": {
    "iso:country":"US",
    "sg:address":"2134 Amnicola Hwy",
    "sg:city":"Chattanooga",
    "sg:classifiers":[
        {
            "category":"Wholesale",
            "subcategory":"Machinery & Supplies",
            "type":"Manufacturing & Wholesale Goods"
        }
    ],
    "sg:phone":"+1 423 622 8008",
    "sg:postcode":"37406",
    "sg:province":"TN",
    "sg:tags":[
        "janitor"
    ],
    "sg:website":"www.aptcommerce.com",
    "wof:name":"American Paper & Twine Co",
    "wof:placetype":"venue"
},
  "geometry": {"coordinates":[-85.270799,35.06891],"type":"Point"}
}