{
  "type": "Feature",
  "properties": {
    "addr:full":"9100 Heritage Dr Brentwood TN 37027",
    "addr:housenumber":"9100",
    "addr:postcode":"37027",
    "addr:street":"Heritage Dr",
    "iso:country":"US",
    "sg:address":"9100 Heritage Dr",
    "sg:city":"Brentwood",
    "sg:classifiers":[
        {
            "category":"Real Estate",
            "subcategory":"Real Estate Operator",
            "type":"Services"
        }
    ],
    "sg:phone":"+1 615 370 8001",
    "sg:postcode":"37027",
    "sg:province":"TN",
    "sg:tags":[
        "building",
        "nonresidential"
    ],
    "wof:name":"Lesley Properties Inc",
    "wof:placetype":"venue"
},
  "geometry": {"coordinates":[-86.770714,36.004882],"type":"Point"}
}