{
  "type": "Feature",
  "properties": {
    "iso:country":"US",
    "sg:address":"1154 Park Ave",
    "sg:city":"Murfreesboro",
    "sg:classifiers":[
        {
            "category":"Organizations",
            "subcategory":"Religious Organization",
            "type":"Services"
        }
    ],
    "sg:phone":"+1 615 893 5683",
    "sg:postcode":"37129",
    "sg:province":"TN",
    "sg:tags":[
        "church"
    ],
    "wof:name":"Victory Christian Ctr",
    "wof:placetype":"venue"
},
  "geometry": {"coordinates":[-86.397724,35.831354],"type":"Point"}
}