{
  "type": "Feature",
  "properties": {
    "iso:country":"US",
    "sg:address":"5744 E Shelby Dr",
    "sg:city":"Memphis",
    "sg:classifiers":[
        {
            "category":"Manufacturing",
            "subcategory":"Signs",
            "type":"Manufacturing & Wholesale Goods"
        }
    ],
    "sg:phone":"+1 901 794 7894",
    "sg:postcode":"38141",
    "sg:province":"TN",
    "sg:tags":[
        "advertising",
        "specialty"
    ],
    "wof:name":"Ark Designs",
    "wof:placetype":"venue"
},
  "geometry": {"coordinates":[-89.872156,35.020404],"type":"Point"}
}