{
  "type": "Feature",
  "properties": {
    "iso:country":"US",
    "sg:address":"3673 Hillridge St",
    "sg:city":"Memphis",
    "sg:classifiers":[
        {
            "category":"Professional",
            "type":"Services"
        }
    ],
    "sg:phone":"+1 901 210 3807",
    "sg:postcode":"38109",
    "sg:province":"TN",
    "wof:name":"Frank D Originals",
    "wof:placetype":"venue"
},
  "geometry": {"coordinates":[-90.054303,35.049783],"type":"Point"}
}