{
  "type": "Feature",
  "properties": {
    "addr:full":"191 Cardwell Dr Tazewell TN 37879",
    "addr:housenumber":"191",
    "addr:postcode":"37879",
    "addr:street":"Cardwell Dr",
    "iso:country":"US",
    "sg:address":"191 Cardwell Dr",
    "sg:city":"Tazewell",
    "sg:classifiers":[
        {
            "category":"Autos & Motor Vehicles",
            "subcategory":"Automobile Sales",
            "type":"Retail Goods"
        }
    ],
    "sg:phone":"+1 423 626 9977",
    "sg:postcode":"37879",
    "sg:province":"TN",
    "sg:tags":[
        "coin",
        "laundry"
    ],
    "wof:name":"Hill Top Laundry",
    "wof:placetype":"venue"
},
  "geometry": {"coordinates":[-83.601777,36.487178],"type":"Point"}
}