{
  "type": "Feature",
  "properties": {
    "iso:country":"US",
    "sg:address":"1260 Savannah Hwy",
    "sg:city":"Waynesboro",
    "sg:classifiers":[
        {
            "category":"Professional",
            "subcategory":"Detective & Security Services",
            "type":"Services"
        }
    ],
    "sg:phone":"+1 931 722 6311",
    "sg:postcode":"38485",
    "sg:province":"TN",
    "sg:tags":[
        "car"
    ],
    "wof:name":"American Investigations",
    "wof:placetype":"venue"
},
  "geometry": {"coordinates":[-87.832021,35.295742],"type":"Point"}
}