{
  "type": "Feature",
  "properties": {
    "addr:full":"2008 Remke Ave Lawrenceburg TN 38464",
    "addr:housenumber":"2008",
    "addr:postcode":"38464",
    "addr:street":"Remke Ave",
    "iso:country":"US",
    "sg:address":"2008 Remke Ave",
    "sg:city":"Lawrenceburg",
    "sg:classifiers":[
        {
            "category":"Government",
            "subcategory":"Office",
            "type":"Public Place"
        }
    ],
    "sg:phone":"+1 931 762 3505",
    "sg:postcode":"38464",
    "sg:province":"TN",
    "sg:tags":[
        "govt",
        "city"
    ],
    "wof:name":"Water & Sewer Dept",
    "wof:placetype":"venue"
},
  "geometry": {"coordinates":[-87.329842,35.264649],"type":"Point"}
}