{
  "type": "Feature",
  "properties": {
    "iso:country":"US",
    "sg:address":"424 Spring St",
    "sg:city":"Monteagle",
    "sg:classifiers":[
        {
            "category":"Building & Trades",
            "subcategory":"Plumbing",
            "type":"Services"
        }
    ],
    "sg:phone":"+1 931 924 3570",
    "sg:postcode":"37356",
    "sg:province":"TN",
    "sg:tags":[
        "plumbing",
        "contractor"
    ],
    "wof:name":"Preferred Plumbing Repair Hm",
    "wof:placetype":"venue"
},
  "geometry": {"coordinates":[-85.833646,35.237786],"type":"Point"}
}