{
  "type": "Feature",
  "properties": {
    "addr:full":"1506 Compton Ave Memphis TN 38106",
    "addr:housenumber":"1506",
    "addr:postcode":"38106",
    "addr:street":"Compton Ave",
    "iso:country":"US",
    "sg:address":"1506 Compton Ave",
    "sg:city":"Memphis",
    "sg:classifiers":[
        {
            "category":"Professional",
            "subcategory":"Management & Consulting",
            "type":"Services"
        }
    ],
    "sg:phone":"+1 901 774 7866",
    "sg:postcode":"38106",
    "sg:province":"TN",
    "sg:tags":[
        "investigating",
        "training"
    ],
    "wof:name":"M S & Associates",
    "wof:placetype":"venue"
},
  "geometry": {"coordinates":[-90.013608,35.078902],"type":"Point"}
}