{
  "type": "Feature",
  "properties": {
    "iso:country":"US",
    "sg:address":"251 Curtis Rd SE",
    "sg:city":"Cleveland",
    "sg:classifiers":[
        {
            "category":"Retail",
            "subcategory":"Auto Repair",
            "type":"Services"
        }
    ],
    "sg:phone":"+1 423 339 1097",
    "sg:postcode":"37323",
    "sg:province":"TN",
    "sg:tags":[
        "repairing",
        "automobile"
    ],
    "wof:name":"Automotive AC & Svc",
    "wof:placetype":"venue"
},
  "geometry": {"coordinates":[-84.900531,35.003469],"type":"Point"}
}