{
  "type": "Feature",
  "properties": {
    "addr:full":"1406 Tusculum Blvd Greeneville TN 37745",
    "addr:housenumber":"1406",
    "addr:postcode":"37745",
    "addr:street":"Tusculum Blvd",
    "iso:country":"US",
    "sg:address":"1406 Tusculum Blvd",
    "sg:city":"Greeneville",
    "sg:classifiers":[
        {
            "category":"Health Services",
            "subcategory":"Doctor",
            "type":"Services"
        }
    ],
    "sg:phone":"+1 423 639 9993",
    "sg:postcode":"37745",
    "sg:province":"TN",
    "sg:tags":[
        "physician",
        "surgeon"
    ],
    "wof:name":"Mountain Surgical",
    "wof:placetype":"venue"
},
  "geometry": {"coordinates":[-82.791099,36.175056],"type":"Point"}
}