{
  "type": "Feature",
  "properties": {
    "iso:country":"US",
    "sg:address":"101 E Blount Ave",
    "sg:city":"Knoxville",
    "sg:classifiers":[
        {
            "category":"Health Services",
            "subcategory":"Doctor",
            "type":"Services"
        }
    ],
    "sg:phone":"+1 865 632 5699",
    "sg:postcode":"37920",
    "sg:province":"TN",
    "sg:tags":[
        "physician",
        "surgeon"
    ],
    "wof:name":"Surgical Consultants-Knoxville",
    "wof:placetype":"venue"
},
  "geometry": {"coordinates":[-83.915117,35.955366],"type":"Point"}
}