{
  "type": "Feature",
  "properties": {
    "iso:country":"US",
    "sg:address":"615 Franklin Limestone Rd",
    "sg:city":"Nashville",
    "sg:classifiers":[
        {
            "category":"Freight",
            "type":"Transportation"
        }
    ],
    "sg:phone":"+1 615 399 7013",
    "sg:postcode":"37217",
    "sg:province":"TN",
    "sg:tags":[
        "trucking"
    ],
    "wof:name":"Big M Trucking",
    "wof:placetype":"venue"
},
  "geometry": {"coordinates":[-86.66118400000001,36.090054],"type":"Point"}
}