{
  "type": "Feature",
  "properties": {
    "iso:country":"US",
    "sg:address":"8996 Ellington Way",
    "sg:city":"Chattanooga",
    "sg:classifiers":[
        {
            "category":"Insurance",
            "subcategory":"Insurance Agent",
            "type":"Services"
        }
    ],
    "sg:phone":"+1 423 855 2111",
    "sg:postcode":"37421",
    "sg:province":"TN",
    "sg:tags":[
        "processing"
    ],
    "wof:name":"Erie Insurance Claims",
    "wof:placetype":"venue"
},
  "geometry": {"coordinates":[-85.123375,35.011898],"type":"Point"}
}