{
  "type": "Feature",
  "properties": {
    "iso:country":"US",
    "sg:address":"2855 Lamb Pl",
    "sg:city":"Memphis",
    "sg:classifiers":[
        {
            "category":"Restaurant",
            "type":"Food & Drink"
        }
    ],
    "sg:phone":"+1 901 362 9691",
    "sg:postcode":"38118",
    "sg:province":"TN",
    "sg:tags":[
        "patent",
        "canned",
        "eating",
        "specialty",
        "mfg"
    ],
    "wof:name":"Panchos Companies",
    "wof:placetype":"venue"
},
  "geometry": {"coordinates":[-89.962073,35.071903],"type":"Point"}
}