{
  "type": "Feature",
  "properties": {
    "iso:country":"US",
    "sg:address":"127 Bank St",
    "sg:city":"Tellico Plains",
    "sg:classifiers":[
        {
            "category":"Restaurant",
            "type":"Food & Drink"
        }
    ],
    "sg:menulink":"http://www.allmenus.com/tn/tellico-plains/155010-hardees/menu/",
    "sg:phone":"+1 423 253 3350",
    "sg:postcode":"37385",
    "sg:province":"TN",
    "sg:tags":[
        "burger",
        "american"
    ],
    "wof:name":"Hardee's",
    "wof:placetype":"venue"
},
  "geometry": {"coordinates":[-84.30150999999999,35.36845],"type":"Point"}
}