{
  "type": "Feature",
  "properties": {
    "iso:country":"US",
    "sg:address":"1868 Old Boones Creek Rd",
    "sg:city":"Gray",
    "sg:classifiers":[
        {
            "category":"Retail",
            "subcategory":"Repair Shop",
            "type":"Services"
        },
        {
            "category":"Building & Trades",
            "subcategory":"Construction",
            "type":"Services"
        }
    ],
    "sg:phone":"+1 423 753 6696",
    "sg:postcode":"37615",
    "sg:province":"TN",
    "sg:tags":[
        "sink",
        "bathtub",
        "refinishing",
        "contractor"
    ],
    "wof:name":"Color-All",
    "wof:placetype":"venue"
},
  "geometry": {"coordinates":[-82.444125,36.349874],"type":"Point"}
}