{
  "type": "Feature",
  "properties": {
    "iso:country":"US",
    "sg:address":"455 Hannings Ln",
    "sg:city":"Martin",
    "sg:classifiers":[
        {
            "category":"Organizations",
            "subcategory":"Non-profit Organization",
            "type":"Services"
        }
    ],
    "sg:phone":"+1 731 587 3851",
    "sg:postcode":"38237",
    "sg:province":"TN",
    "sg:tags":[
        "development",
        "community"
    ],
    "wof:name":"C D S",
    "wof:placetype":"venue"
},
  "geometry": {"coordinates":[-88.86956600000001,36.337566],"type":"Point"}
}