{
  "type": "Feature",
  "properties": {
    "iso:country":"US",
    "sg:address":"121 Tooweka Cir",
    "sg:city":"Loudon",
    "sg:classifiers":[
        {
            "category":"Building & Trades",
            "subcategory":"Construction",
            "type":"Services"
        }
    ],
    "sg:phone":"+1 865 637 5969",
    "sg:postcode":"37774",
    "sg:province":"TN",
    "sg:tags":[
        "consulting",
        "business",
        "contractor"
    ],
    "wof:name":"C & R Roofing Co",
    "wof:placetype":"venue"
},
  "geometry": {"coordinates":[-84.253435,35.689167],"type":"Point"}
}