{
  "type": "Feature",
  "properties": {
    "iso:country":"US",
    "sg:address":"208 Bellwood Cir",
    "sg:city":"Dickson",
    "sg:classifiers":[
        {
            "category":"Organizations",
            "subcategory":"Membership Organization",
            "type":"Services"
        }
    ],
    "sg:phone":"+1 615 446 7855",
    "sg:postcode":"37055",
    "sg:province":"TN",
    "wof:name":"Tennessee Archaeological Trust",
    "wof:placetype":"venue"
},
  "geometry": {"coordinates":[-87.35414400000001,36.080981],"type":"Point"}
}