{
  "type": "Feature",
  "properties": {
    "addr:full":"9450 S Northshore Dr Knoxville TN 37922",
    "addr:housenumber":"9450",
    "addr:postcode":"37922",
    "addr:street":"S Northshore Dr",
    "iso:country":"US",
    "sg:address":"9450 S Northshore Dr",
    "sg:city":"Knoxville",
    "sg:classifiers":[
        {
            "category":"Restaurant",
            "type":"Food & Drink"
        }
    ],
    "sg:menulink":"http://www.allmenus.com/tn/knoxville/140336-subway/menu/",
    "sg:phone":"+1 865 531 3010",
    "sg:postcode":"37922",
    "sg:province":"TN",
    "sg:tags":[
        "american",
        "sandwich"
    ],
    "wof:name":"Subway",
    "wof:placetype":"venue"
},
  "geometry": {"coordinates":[-84.06183,35.86503],"type":"Point"}
}