{
  "type": "Feature",
  "properties": {
    "iso:country":"US",
    "sg:address":"2845 Lebanon Pike",
    "sg:city":"Nashville",
    "sg:classifiers":[
        {
            "category":"Autos & Motor Vehicles",
            "subcategory":"Automobile Sales",
            "type":"Retail Goods"
        }
    ],
    "sg:phone":"+1 615 883 4400",
    "sg:postcode":"37214",
    "sg:province":"TN",
    "sg:tags":[
        "car",
        "used",
        "dealer"
    ],
    "wof:name":"World Class Sales",
    "wof:placetype":"venue"
},
  "geometry": {"coordinates":[-86.65876299999999,36.167719],"type":"Point"}
}