{
  "type": "Feature",
  "properties": {
    "iso:country":"US",
    "sg:address":"900 S Willow Ave",
    "sg:city":"Cookeville",
    "sg:classifiers":[
        {
            "category":"Professional",
            "type":"Services"
        }
    ],
    "sg:phone":"+1 931 808 8592",
    "sg:postcode":"38501",
    "sg:province":"TN",
    "wof:name":"Product Action Internatio",
    "wof:placetype":"venue"
},
  "geometry": {"coordinates":[-85.52404199999999,36.143721],"type":"Point"}
}