{
  "type": "Feature",
  "properties": {
    "addr:full":"323 Mohawk Valley Rd Monroe TN 38573",
    "addr:housenumber":"323",
    "addr:postcode":"38573",
    "addr:street":"Mohawk Valley Rd",
    "iso:country":"US",
    "sg:address":"323 Mohawk Valley Rd",
    "sg:city":"Monroe",
    "sg:classifiers":[
        {
            "category":"Building & Trades",
            "subcategory":"Construction",
            "type":"Services"
        }
    ],
    "sg:phone":"+1 931 823 4305",
    "sg:postcode":"38573",
    "sg:province":"TN",
    "sg:tags":[
        "downspouts",
        "gutter"
    ],
    "wof:name":"Gutter Max Gutter",
    "wof:placetype":"venue"
},
  "geometry": {"coordinates":[-85.269463,36.519707],"type":"Point"}
}