{
  "type": "Feature",
  "properties": {
    "addr:full":"7905 Boone Trce Nashville TN 37221",
    "addr:housenumber":"7905",
    "addr:postcode":"37221",
    "addr:street":"Boone Trce",
    "iso:country":"US",
    "sg:address":"7905 Boone Trce",
    "sg:city":"Nashville",
    "sg:classifiers":[
        {
            "category":"Retail",
            "subcategory":"Auto Repair",
            "type":"Services"
        }
    ],
    "sg:phone":"+1 615 292 4955",
    "sg:postcode":"37221",
    "sg:province":"TN",
    "sg:tags":[
        "repairing",
        "automobile"
    ],
    "wof:name":"Andys Auto Svc",
    "wof:placetype":"venue"
},
  "geometry": {"coordinates":[-87.014765,36.084177],"type":"Point"}
}