{
  "type": "Feature",
  "properties": {
    "iso:country":"US",
    "sg:address":"704 Cedar Ln",
    "sg:city":"Tullahoma",
    "sg:classifiers":[
        {
            "category":"Personal",
            "subcategory":"Beauty Salon",
            "type":"Services"
        }
    ],
    "sg:phone":"+1 931 393 0333",
    "sg:postcode":"37388",
    "sg:province":"TN",
    "sg:tags":[
        "shop"
    ],
    "wof:name":"Christy's Creative Cuts",
    "wof:placetype":"venue"
},
  "geometry": {"coordinates":[-86.225086,35.365095],"type":"Point"}
}