{
  "type": "Feature",
  "properties": {
    "addr:full":"136 Frierson St Brentwood TN 37027",
    "addr:housenumber":"136",
    "addr:postcode":"37027",
    "addr:street":"Frierson St",
    "iso:country":"US",
    "sg:address":"136 Frierson St",
    "sg:city":"Brentwood",
    "sg:classifiers":[
        {
            "category":"Organizations",
            "subcategory":"Religious Organization",
            "type":"Services"
        }
    ],
    "sg:phone":"+1 615 373 1565",
    "sg:postcode":"37027",
    "sg:province":"TN",
    "wof:name":"Mt Lebanon Mssnry Bapt Chrch",
    "wof:placetype":"venue"
},
  "geometry": {"coordinates":[-86.78393800000001,36.034139],"type":"Point"}
}