{
  "type": "Feature",
  "properties": {
    "iso:country":"US",
    "sg:address":"150 Kraft St",
    "sg:city":"Clarksville",
    "sg:classifiers":[
        {
            "category":"Professional",
            "subcategory":"Business Services",
            "type":"Services"
        }
    ],
    "sg:phone":"+1 931 647 4468",
    "sg:postcode":"37040",
    "sg:province":"TN",
    "sg:tags":[
        "auctioneer"
    ],
    "wof:name":"Bellamy Auction & Real Estate",
    "wof:placetype":"venue"
},
  "geometry": {"coordinates":[-87.340377,36.539374],"type":"Point"}
}