{
  "type": "Feature",
  "properties": {
    "iso:country":"US",
    "sg:address":"915 Hickory Oaks Cir",
    "sg:city":"Collierville",
    "sg:classifiers":[
        {
            "category":"Building & Trades",
            "subcategory":"Construction",
            "type":"Services"
        }
    ],
    "sg:phone":"+1 901 853 5155",
    "sg:postcode":"38017",
    "sg:province":"TN",
    "sg:tags":[
        "spa",
        "hot",
        "tub",
        "pool",
        "swimming"
    ],
    "sg:website":"http://www.poolsunlimited.com",
    "wof:name":"Pools Unlimited Inc",
    "wof:placetype":"venue"
},
  "geometry": {"coordinates":[-89.701364,35.065012],"type":"Point"}
}