{
  "type": "Feature",
  "properties": {
    "addr:full":"8849 Dayton Pike Soddy Daisy TN 37379",
    "addr:housenumber":"8849",
    "addr:postcode":"37379",
    "addr:street":"Dayton Pike",
    "iso:country":"US",
    "sg:address":"8849 Dayton Pike",
    "sg:city":"Soddy Daisy",
    "sg:classifiers":[
        {
            "category":"Autos & Motor Vehicles",
            "subcategory":"Automobile Sales",
            "type":"Retail Goods"
        }
    ],
    "sg:phone":"+1 423 332 2861",
    "sg:postcode":"37379",
    "sg:province":"TN",
    "sg:tags":[
        "car",
        "used",
        "dealer"
    ],
    "wof:name":"Clyde's Used Cars",
    "wof:placetype":"venue"
},
  "geometry": {"coordinates":[-85.21672700000001,35.225162],"type":"Point"}
}