{
  "type": "Feature",
  "properties": {
    "iso:country":"US",
    "sg:address":"3434 Woodmont Blvd",
    "sg:city":"Nashville",
    "sg:classifiers":[
        {
            "category":"Professional",
            "subcategory":"Management & Consulting",
            "type":"Services"
        }
    ],
    "sg:phone":"+1 615 385 9206",
    "sg:postcode":"37215",
    "sg:province":"TN",
    "sg:tags":[
        "business"
    ],
    "wof:name":"Edmund B Fitzgerald",
    "wof:placetype":"venue"
},
  "geometry": {"coordinates":[-86.824855,36.115252],"type":"Point"}
}