{
  "type": "Feature",
  "properties": {
    "iso:country":"US",
    "sg:address":"4406 Malone Rd",
    "sg:city":"Memphis",
    "sg:classifiers":[
        {
            "category":"Professional",
            "type":"Services"
        }
    ],
    "sg:phone":"+1 901 383 2300",
    "sg:postcode":"38118",
    "sg:province":"TN",
    "sg:tags":[
        "establishment"
    ],
    "wof:name":"Vance & Richards Office Rcrds",
    "wof:placetype":"venue"
},
  "geometry": {"coordinates":[-89.91916999999999,35.027631],"type":"Point"}
}