{
  "type": "Feature",
  "properties": {
    "iso:country":"US",
    "sg:address":"2250 E Court St",
    "sg:city":"Dyersburg",
    "sg:classifiers":[
        {
            "category":"Organizations",
            "subcategory":"Religious Organization",
            "type":"Services"
        }
    ],
    "sg:phone":"+1 731 285 9849",
    "sg:postcode":"38024",
    "sg:province":"TN",
    "sg:tags":[
        "church"
    ],
    "wof:name":"Church Of Jesus Christ",
    "wof:placetype":"venue"
},
  "geometry": {"coordinates":[-89.35405,36.024828],"type":"Point"}
}