{
  "type": "Feature",
  "properties": {
    "iso:country":"US",
    "sg:address":"145 Logan St",
    "sg:city":"Jellico",
    "sg:classifiers":[
        {
            "category":"Social Services",
            "subcategory":"Child Care",
            "type":"Services"
        }
    ],
    "sg:phone":"+1 423 784 5302",
    "sg:postcode":"37762",
    "sg:province":"TN",
    "sg:tags":[
        "day"
    ],
    "wof:name":"Jellico Learning Center",
    "wof:placetype":"venue"
},
  "geometry": {"coordinates":[-84.13073300000001,36.585532],"type":"Point"}
}