{
  "type": "Feature",
  "properties": {
    "addr:full":"207 E Main St Johnson City TN 37604",
    "addr:housenumber":"207",
    "addr:postcode":"37604",
    "addr:street":"E Main St",
    "iso:country":"US",
    "sg:address":"207 E Main St",
    "sg:city":"Johnson City",
    "sg:classifiers":[
        {
            "category":"Social Services",
            "type":"Services"
        }
    ],
    "sg:phone":"+1 423 282 0223",
    "sg:postcode":"37604",
    "sg:province":"TN",
    "sg:tags":[
        "counseling"
    ],
    "wof:name":"Cathlyn C Cannon",
    "wof:placetype":"venue"
},
  "geometry": {"coordinates":[-82.352585,36.316433],"type":"Point"}
}