{
  "type": "Feature",
  "properties": {
    "iso:country":"US",
    "sg:address":"101 J E B Ct",
    "sg:city":"Smyrna",
    "sg:classifiers":[
        {
            "category":"Building & Trades",
            "subcategory":"Plumbing",
            "type":"Services"
        }
    ],
    "sg:phone":"+1 615 355 4420",
    "sg:postcode":"37167",
    "sg:province":"TN",
    "sg:tags":[
        "contractor"
    ],
    "wof:name":"Chandler Plumbing",
    "wof:placetype":"venue"
},
  "geometry": {"coordinates":[-86.508298,35.942476],"type":"Point"}
}