{
  "type": "Feature",
  "properties": {
    "addr:full":"237 N Lindell St Martin TN 38237",
    "addr:housenumber":"237",
    "addr:postcode":"38237",
    "addr:street":"N Lindell St",
    "iso:country":"US",
    "sg:address":"237 N Lindell St",
    "sg:city":"Martin",
    "sg:classifiers":[
        {
            "category":"Health Services",
            "subcategory":"Health Practitioner",
            "type":"Services"
        }
    ],
    "sg:phone":"+1 731 587 3422",
    "sg:postcode":"38237",
    "sg:province":"TN",
    "sg:tags":[
        "therapist",
        "physical"
    ],
    "wof:name":"Sideline Physical Therapy",
    "wof:placetype":"venue"
},
  "geometry": {"coordinates":[-88.849165,36.350664],"type":"Point"}
}