{
  "type": "Feature",
  "properties": {
    "iso:country":"US",
    "sg:address":"5748 Rayben Cir",
    "sg:city":"Memphis",
    "sg:classifiers":[
        {
            "category":"Professional",
            "subcategory":"Accounting & Tax Preparation",
            "type":"Services"
        }
    ],
    "sg:phone":"+1 901 795 5555",
    "sg:postcode":"38115",
    "sg:province":"TN",
    "sg:tags":[
        "accountant"
    ],
    "wof:name":"C R Fuller CPA PC",
    "wof:placetype":"venue"
},
  "geometry": {"coordinates":[-89.871746,35.073879],"type":"Point"}
}