{
  "type": "Feature",
  "properties": {
    "iso:country":"US",
    "sg:address":"2726 Island Home Blvd",
    "sg:city":"Knoxville",
    "sg:classifiers":[
        {
            "category":"Government",
            "subcategory":"Office",
            "type":"Public Place"
        }
    ],
    "sg:phone":"+1 865 579 3099",
    "sg:postcode":"37920",
    "sg:province":"TN",
    "sg:tags":[
        "state",
        "program"
    ],
    "wof:name":"Education Dept",
    "wof:placetype":"venue"
},
  "geometry": {"coordinates":[-83.880048,35.959189],"type":"Point"}
}