{
  "type": "Feature",
  "properties": {
    "addr:full":"1907 Gallatin Pike N Madison TN 37115",
    "addr:housenumber":"1907",
    "addr:postcode":"37115",
    "addr:street":"Gallatin Pike N",
    "iso:country":"US",
    "sg:address":"1907 Gallatin Pike N",
    "sg:city":"Madison",
    "sg:classifiers":[
        {
            "category":"Coffee & Tea",
            "type":"Food & Drink"
        }
    ],
    "sg:menulink":"http://www.allmenus.com/tn/nashville/115198-starbucks-coffee/menu/",
    "sg:phone":"+1 615 855 6814",
    "sg:postcode":"37115",
    "sg:province":"TN",
    "sg:tags":[
        "american"
    ],
    "wof:name":"Starbucks Coffee",
    "wof:placetype":"venue"
},
  "geometry": {"coordinates":[-86.695989,36.300165],"type":"Point"}
}