{
  "type": "Feature",
  "properties": {
    "addr:full":"1206 Marsh Rd Hixson TN 37343",
    "addr:housenumber":"1206",
    "addr:postcode":"37343",
    "addr:street":"Marsh Rd",
    "iso:country":"US",
    "sg:address":"1206 Marsh Rd",
    "sg:city":"Hixson",
    "sg:classifiers":[
        {
            "category":"Building & Trades",
            "subcategory":"Landscaping Services",
            "type":"Services"
        }
    ],
    "sg:phone":"+1 423 870 5570",
    "sg:postcode":"37343",
    "sg:province":"TN",
    "wof:name":"Yardboys Landscaping",
    "wof:placetype":"venue"
},
  "geometry": {"coordinates":[-85.23922899999999,35.151692],"type":"Point"}
}