{
  "type": "Feature",
  "properties": {
    "addr:full":"5708 Brainerd Rd Chattanooga TN 37411",
    "addr:postcode":"5708;37411",
    "addr:street":"Brainerd Rd",
    "iso:country":"US",
    "sg:address":"5708 Brainerd Rd",
    "sg:city":"Chattanooga",
    "sg:classifiers":[
        {
            "category":"Professional",
            "subcategory":"Detective & Security Services",
            "type":"Services"
        }
    ],
    "sg:phone":"+1 423 894 5248",
    "sg:postcode":"37411",
    "sg:province":"TN",
    "sg:tags":[
        "guard",
        "patrol"
    ],
    "sg:website":"www.pinkertons.com",
    "wof:name":"Securitas Security Svc USA Inc",
    "wof:placetype":"venue"
},
  "geometry": {"coordinates":[-85.21408099999999,35.011575],"type":"Point"}
}