{
  "type": "Feature",
  "properties": {
    "iso:country":"US",
    "sg:address":"475 Shadowtown Rd",
    "sg:city":"Blountville",
    "sg:classifiers":[
        {
            "category":"Personal",
            "subcategory":"Beauty Salon",
            "type":"Services"
        }
    ],
    "sg:phone":"+1 423 323 8583",
    "sg:postcode":"37617",
    "sg:province":"TN",
    "sg:tags":[
        "shop"
    ],
    "wof:name":"Jans Beauty Shop",
    "wof:placetype":"venue"
},
  "geometry": {"coordinates":[-82.400738,36.529423],"type":"Point"}
}