{
  "type": "Feature",
  "properties": {
    "addr:full":"3367 Cedar Fork Rd Tazewell TN 37879",
    "addr:housenumber":"3367",
    "addr:postcode":"37879",
    "addr:street":"Cedar Fork Rd",
    "iso:country":"US",
    "sg:address":"3367 Cedar Fork Rd",
    "sg:city":"Tazewell",
    "sg:classifiers":[
        {
            "category":"Food & Beverages",
            "subcategory":"Groceries & Convenience Stores",
            "type":"Retail Goods"
        }
    ],
    "sg:phone":"+1 423 626 9911",
    "sg:postcode":"37879",
    "sg:province":"TN",
    "sg:tags":[
        "gasoline"
    ],
    "wof:name":"Cedar Fork Market",
    "wof:placetype":"venue"
},
  "geometry": {"coordinates":[-83.47218100000001,36.521567],"type":"Point"}
}