{
  "type": "Feature",
  "properties": {
    "iso:country":"US",
    "sg:address":"1303 E Wood St",
    "sg:city":"Paris",
    "sg:classifiers":[
        {
            "category":"Restaurant",
            "type":"Food & Drink"
        }
    ],
    "sg:menulink":"http://www.allmenus.com/tn/paris/100999-captain-ds-seafood/menu/",
    "sg:phone":"+1 731 642 6614",
    "sg:postcode":"38242",
    "sg:province":"TN",
    "sg:tags":[
        "seafood",
        "american"
    ],
    "wof:name":"Captain D's Seafood",
    "wof:placetype":"venue"
},
  "geometry": {"coordinates":[-88.30016999999999,36.305895],"type":"Point"}
}