{
  "type": "Feature",
  "properties": {
    "addr:full":"5697 Tatumville Rd Newbern TN 38059",
    "addr:housenumber":"5697",
    "addr:postcode":"38059",
    "addr:street":"Tatumville Rd",
    "iso:country":"US",
    "sg:address":"5697 Tatumville Rd",
    "sg:city":"Newbern",
    "sg:classifiers":[
        {
            "category":"Building & Trades",
            "subcategory":"Construction",
            "type":"Services"
        }
    ],
    "sg:phone":"+1 731 627 9958",
    "sg:postcode":"38059",
    "sg:province":"TN",
    "sg:tags":[
        "house"
    ],
    "wof:name":"Taylor Remodeling",
    "wof:placetype":"venue"
},
  "geometry": {"coordinates":[-89.183727,36.105677],"type":"Point"}
}