{
  "type": "Feature",
  "properties": {
    "iso:country":"US",
    "sg:address":"1845 Moriah Woods Blvd",
    "sg:city":"Memphis",
    "sg:classifiers":[
        {
            "category":"Professional",
            "subcategory":"Computer Services",
            "type":"Services"
        }
    ],
    "sg:phone":"+1 901 795 6511",
    "sg:postcode":"38117",
    "sg:province":"TN",
    "sg:tags":[
        "isp",
        "provider",
        "internet"
    ],
    "wof:name":"Dreamsites Net",
    "wof:placetype":"venue"
},
  "geometry": {"coordinates":[-89.898505,35.082801],"type":"Point"}
}