{
  "type": "Feature",
  "properties": {
    "iso:country":"US",
    "sg:address":"2210 River Rd",
    "sg:city":"Clarksville",
    "sg:classifiers":[
        {
            "category":"Organizations",
            "subcategory":"Community Association",
            "type":"Services"
        }
    ],
    "sg:phone":"+1 931 221 0510",
    "sg:postcode":"37040",
    "sg:province":"TN",
    "sg:tags":[
        "club"
    ],
    "wof:name":"R J Potter 48 Club",
    "wof:placetype":"venue"
},
  "geometry": {"coordinates":[-87.383146,36.459906],"type":"Point"}
}