{
  "type": "Feature",
  "properties": {
    "addr:full":"7030 Gamble Rd Birchwood TN 37308",
    "addr:housenumber":"7030",
    "addr:postcode":"37308",
    "addr:street":"Gamble Rd",
    "iso:country":"US",
    "sg:address":"7030 Gamble Rd",
    "sg:city":"Birchwood",
    "sg:classifiers":[
        {
            "category":"Farming",
            "subcategory":"Livestock Farm",
            "type":"Manufacturing & Wholesale Goods"
        }
    ],
    "sg:phone":"+1 423 344 6743",
    "sg:postcode":"37308",
    "sg:province":"TN",
    "sg:tags":[
        "beef",
        "feedlot",
        "cattle"
    ],
    "wof:name":"Leroy Holder Construction Co",
    "wof:placetype":"venue"
},
  "geometry": {"coordinates":[-85.02275899999999,35.265198],"type":"Point"}
}