{
  "type": "Feature",
  "properties": {
    "iso:country":"US",
    "sg:address":"1204 Debbie Ln",
    "sg:city":"Hixson",
    "sg:classifiers":[
        {
            "category":"Building & Trades",
            "subcategory":"Construction",
            "type":"Services"
        }
    ],
    "sg:phone":"+1 423 362 0794",
    "sg:postcode":"37343",
    "sg:province":"TN",
    "sg:tags":[
        "roofing",
        "contractor"
    ],
    "wof:name":"Combs Roofing",
    "wof:placetype":"venue"
},
  "geometry": {"coordinates":[-85.205572,35.183709],"type":"Point"}
}