{
  "type": "Feature",
  "properties": {
    "iso:country":"US",
    "sg:address":"715 Rison St",
    "sg:city":"Paris",
    "sg:classifiers":[
        {
            "category":"Retail",
            "subcategory":"Auto Repair",
            "type":"Services"
        }
    ],
    "sg:phone":"+1 731 642 8789",
    "sg:postcode":"38242",
    "sg:province":"TN",
    "sg:tags":[
        "repairing",
        "automobile"
    ],
    "wof:name":"Tharpe Auto Repair",
    "wof:placetype":"venue"
},
  "geometry": {"coordinates":[-88.336673,36.311372],"type":"Point"}
}