{
  "type": "Feature",
  "properties": {
    "addr:full":"80 Stuart Loop Somerville TN 38068",
    "addr:housenumber":"80",
    "addr:postcode":"38068",
    "addr:street":"Stuart Loop",
    "iso:country":"US",
    "sg:address":"80 Stuart Loop",
    "sg:city":"Somerville",
    "sg:classifiers":[
        {
            "category":"Professional",
            "type":"Services"
        }
    ],
    "sg:phone":"+1 901 277 2413",
    "sg:postcode":"38068",
    "sg:province":"TN",
    "wof:name":"R & A Lumper Svc",
    "wof:placetype":"venue"
},
  "geometry": {"coordinates":[-89.356437,35.21681],"type":"Point"}
}