{
  "type": "Feature",
  "properties": {
    "addr:full":"1489 Hwy 49 W Ashland City TN 37015",
    "addr:housenumber":"1489",
    "addr:postcode":"37015",
    "addr:street":"Hwy 49 W Ashland",
    "iso:country":"US",
    "sg:address":"1489 Hwy 49 W",
    "sg:city":"Ashland City",
    "sg:classifiers":[
        {
            "category":"Manufacturing",
            "subcategory":"Electronics",
            "type":"Manufacturing & Wholesale Goods"
        }
    ],
    "sg:phone":"+1 615 792 0480",
    "sg:postcode":"37015",
    "sg:province":"TN",
    "sg:tags":[
        "prerecorded",
        "durable",
        "mfg"
    ],
    "wof:name":"Dixiraks Records & Tapes",
    "wof:placetype":"venue"
},
  "geometry": {"coordinates":[-87.082714,36.272065],"type":"Point"}
}