{
  "type": "Feature",
  "properties": {
    "iso:country":"US",
    "sg:address":"901 N Roan St",
    "sg:city":"Johnson City",
    "sg:classifiers":[
        {
            "category":"Banks & Credit Unions",
            "subcategory":"Investment Brokerage",
            "type":"Services"
        }
    ],
    "sg:phone":"+1 423 928 8361",
    "sg:postcode":"37601",
    "sg:province":"TN",
    "sg:tags":[
        "stock",
        "bond"
    ],
    "wof:name":"Raymond James Financial Svc",
    "wof:placetype":"venue"
},
  "geometry": {"coordinates":[-82.35887700000001,36.323052],"type":"Point"}
}