{
  "type": "Feature",
  "properties": {
    "addr:full":"921 de Armond Ln Maryville TN 37804",
    "addr:housenumber":"921",
    "addr:postcode":"37804",
    "addr:street":"De Armond Ln",
    "iso:country":"US",
    "sg:address":"921 de Armond Ln",
    "sg:city":"Maryville",
    "sg:classifiers":[
        {
            "category":"Wholesale",
            "subcategory":"Non-durable Goods",
            "type":"Manufacturing & Wholesale Goods"
        }
    ],
    "sg:phone":"+1 865 977 7754",
    "sg:postcode":"37804",
    "sg:province":"TN",
    "sg:tags":[
        "tropical",
        "fish"
    ],
    "wof:name":"Wildwood Fisheries",
    "wof:placetype":"venue"
},
  "geometry": {"coordinates":[-83.90599,35.797326],"type":"Point"}
}