{
  "type": "Feature",
  "properties": {
    "iso:country":"US",
    "sg:address":"1283 Murfreesboro Pike",
    "sg:city":"Nashville",
    "sg:classifiers":[
        {
            "category":"Professional",
            "subcategory":"Management & Consulting",
            "type":"Services"
        },
        {
            "category":"Real Estate",
            "subcategory":"Real Estate Operator",
            "type":"Services"
        }
    ],
    "sg:phone":"+1 615 366 5569",
    "sg:postcode":"37217",
    "sg:province":"TN",
    "sg:tags":[
        "building",
        "parks"
    ],
    "wof:name":"Airway Plaza",
    "wof:placetype":"venue"
},
  "geometry": {"coordinates":[-86.701939,36.119476],"type":"Point"}
}