{
  "type": "Feature",
  "properties": {
    "iso:country":"US",
    "sg:address":"1610 Weaver Pike",
    "sg:city":"Bristol",
    "sg:classifiers":[
        {
            "category":"Shopping",
            "subcategory":"Clothing, Apparel, & Fashions",
            "type":"Retail Goods"
        }
    ],
    "sg:phone":"+1 423 652 2677",
    "sg:postcode":"37620",
    "sg:province":"TN",
    "wof:name":"Mels Bargain Shop",
    "wof:placetype":"venue"
},
  "geometry": {"coordinates":[-82.17635799999999,36.57231],"type":"Point"}
}