{
  "type": "Feature",
  "properties": {
    "iso:country":"US",
    "sg:address":"189 Clayton Hollow Ln",
    "sg:city":"Rock Island",
    "sg:classifiers":[
        {
            "category":"Retail",
            "subcategory":"Repair Shop",
            "type":"Services"
        }
    ],
    "sg:phone":"+1 931 686 9009",
    "sg:postcode":"38581",
    "sg:province":"TN",
    "sg:tags":[
        "welding"
    ],
    "wof:name":"Rock Island Mfg",
    "wof:placetype":"venue"
},
  "geometry": {"coordinates":[-85.66116700000001,35.810089],"type":"Point"}
}