{
  "type": "Feature",
  "properties": {
    "addr:full":"5201 Bobby Hicks Hwy Johnson City TN 37615",
    "addr:housenumber":"5201",
    "addr:postcode":"37615",
    "addr:street":"Bobby Hicks Hwy",
    "iso:country":"US",
    "sg:address":"5201 Bobby Hicks Hwy",
    "sg:city":"Johnson City",
    "sg:classifiers":[
        {
            "category":"Restaurant",
            "type":"Food & Drink"
        }
    ],
    "sg:phone":"+1 423 467 0025",
    "sg:postcode":"37615",
    "sg:province":"TN",
    "wof:name":"Taco Bell",
    "wof:placetype":"venue"
},
  "geometry": {"coordinates":[-82.471784,36.41306],"type":"Point"}
}