{
  "type": "Feature",
  "properties": {
    "iso:country":"US",
    "sg:address":"391 E Big Springs Rd",
    "sg:city":"Lawrenceburg",
    "sg:classifiers":[
        {
            "category":"Wholesale",
            "subcategory":"Office Equipment",
            "type":"Manufacturing & Wholesale Goods"
        }
    ],
    "sg:phone":"+1 931 762 7897",
    "sg:postcode":"38464",
    "sg:province":"TN",
    "sg:tags":[
        "machine",
        "duplicating",
        "copying"
    ],
    "wof:name":"Hobbs Office Machines",
    "wof:placetype":"venue"
},
  "geometry": {"coordinates":[-87.428022,35.325538],"type":"Point"}
}