{
  "type": "Feature",
  "properties": {
    "addr:full":"4111 Auster Cove Memphis TN 38125",
    "addr:housenumber":"4111",
    "addr:postcode":"38125",
    "addr:street":"Auster Cove",
    "iso:country":"US",
    "sg:address":"4111 Auster Cove",
    "sg:city":"Memphis",
    "sg:classifiers":[
        {
            "category":"Professional",
            "type":"Services"
        }
    ],
    "sg:phone":"+1 901 309 1050",
    "sg:postcode":"38125",
    "sg:province":"TN",
    "sg:tags":[
        "establishment"
    ],
    "wof:name":"I'Care 24 Hr Inc",
    "wof:placetype":"venue"
},
  "geometry": {"coordinates":[-89.819273,35.036303],"type":"Point"}
}