{
  "type": "Feature",
  "properties": {
    "iso:country":"US",
    "sg:address":"1916 Edgewood Ave",
    "sg:city":"Knoxville",
    "sg:classifiers":[
        {
            "category":"Social Services",
            "subcategory":"Child Care",
            "type":"Services"
        }
    ],
    "sg:phone":"+1 865 524 9999",
    "sg:postcode":"37917",
    "sg:province":"TN",
    "sg:tags":[
        "day"
    ],
    "wof:name":"Mertties Little Merrigolds",
    "wof:placetype":"venue"
},
  "geometry": {"coordinates":[-83.918916,36.001632],"type":"Point"}
}