{
  "type": "Feature",
  "properties": {
    "iso:country":"US",
    "sg:address":"1121 Riverwood Pl",
    "sg:city":"Clarksville",
    "sg:classifiers":[
        {
            "category":"Professional",
            "subcategory":"Computer Services",
            "type":"Services"
        }
    ],
    "sg:phone":"+1 931 920 2963",
    "sg:postcode":"37040",
    "sg:province":"TN",
    "sg:tags":[
        "installer",
        "network"
    ],
    "wof:name":"Johnson Interprises",
    "wof:placetype":"venue"
},
  "geometry": {"coordinates":[-87.364296,36.506434],"type":"Point"}
}