{
  "type": "Feature",
  "properties": {
    "iso:country":"US",
    "sg:address":"2612 Woodcliff Dr",
    "sg:city":"Memphis",
    "sg:classifiers":[
        {
            "category":"Personal",
            "subcategory":"Beauty Salon",
            "type":"Services"
        }
    ],
    "sg:phone":"+1 901 353 8776",
    "sg:postcode":"38127",
    "sg:province":"TN",
    "wof:name":"Hair N More",
    "wof:placetype":"venue"
},
  "geometry": {"coordinates":[-89.97720099999999,35.203689],"type":"Point"}
}