{
  "type": "Feature",
  "properties": {
    "addr:full":"1241 Volunteer Pkwy Bristol TN 37620",
    "addr:housenumber":"1241",
    "addr:postcode":"37620",
    "addr:street":"Volunteer Pkwy",
    "iso:country":"US",
    "sg:address":"1241 Volunteer Pkwy",
    "sg:city":"Bristol",
    "sg:classifiers":[
        {
            "category":"Professional",
            "subcategory":"Testing Lab",
            "type":"Services"
        }
    ],
    "sg:phone":"+1 423 764 2150",
    "sg:postcode":"37620",
    "sg:province":"TN",
    "sg:tags":[
        "laboratory"
    ],
    "wof:name":"Redwood Toxicology",
    "wof:placetype":"venue"
},
  "geometry": {"coordinates":[-82.202225,36.566136],"type":"Point"}
}