{
  "type": "Feature",
  "properties": {
    "iso:country":"US",
    "sg:address":"611 E Lytle St",
    "sg:city":"Murfreesboro",
    "sg:classifiers":[
        {
            "category":"Sports & Exercise",
            "subcategory":"Gym",
            "type":"Entertainment"
        }
    ],
    "sg:phone":"+1 615 896 0290",
    "sg:postcode":"37130",
    "sg:province":"TN",
    "sg:tags":[
        "fitness",
        "physical",
        "facility"
    ],
    "wof:name":"Pace Center",
    "wof:placetype":"venue"
},
  "geometry": {"coordinates":[-86.381124,35.847131],"type":"Point"}
}