{
  "type": "Feature",
  "properties": {
    "iso:country":"US",
    "sg:address":"517 Foxcroft Cir",
    "sg:city":"Franklin",
    "sg:classifiers":[
        {
            "category":"Autos & Motor Vehicles",
            "subcategory":"Fuel & Gas Station",
            "type":"Retail Goods"
        }
    ],
    "sg:phone":"+1 615 794 8128",
    "sg:postcode":"37067",
    "sg:province":"TN",
    "sg:tags":[
        "station",
        "gasoline"
    ],
    "wof:name":"BP",
    "wof:placetype":"venue"
},
  "geometry": {"coordinates":[-86.836344,35.932698],"type":"Point"}
}