{
  "type": "Feature",
  "properties": {
    "iso:country":"US",
    "sg:address":"8557 Munford Giltedge Rd",
    "sg:city":"Burlison",
    "sg:classifiers":[
        {
            "category":"Building & Trades",
            "subcategory":"Construction",
            "type":"Services"
        }
    ],
    "sg:phone":"+1 901 476 7444",
    "sg:postcode":"38015",
    "sg:province":"TN",
    "sg:tags":[
        "residential"
    ],
    "wof:name":"Hunter Construction",
    "wof:placetype":"venue"
},
  "geometry": {"coordinates":[-89.82302,35.544695],"type":"Point"}
}