{
  "type": "Feature",
  "properties": {
    "iso:country":"US",
    "sg:address":"9632 E Brainerd Rd",
    "sg:city":"Chattanooga",
    "sg:classifiers":[
        {
            "category":"Place Of Worship",
            "subcategory":"Church",
            "type":"Public Place"
        },
        {
            "category":"Place Of Worship",
            "type":"Public Place"
        }
    ],
    "sg:phone":"+1 423 892 3027",
    "sg:postcode":"37421",
    "sg:province":"TN",
    "sg:tags":[
        "churches-presbyterian",
        "churches-presbyterian-arp",
        "christ",
        "churches-community"
    ],
    "wof:name":"Cornerstone Community Church",
    "wof:placetype":"venue"
},
  "geometry": {"coordinates":[-85.09701,35.000631],"type":"Point"}
}