{
  "type": "Feature",
  "properties": {
    "iso:country":"US",
    "sg:address":"3922 Thomas Russell Rd",
    "sg:city":"South Fulton",
    "sg:classifiers":[
        {
            "category":"Shopping",
            "type":"Retail Goods"
        }
    ],
    "sg:phone":"+1 731 479 2278",
    "sg:postcode":"38257",
    "sg:province":"TN",
    "sg:tags":[
        "merchandise"
    ],
    "wof:name":"Possums A&W Shop",
    "wof:placetype":"venue"
},
  "geometry": {"coordinates":[-88.88484099999999,36.454926],"type":"Point"}
}