{
  "type": "Feature",
  "properties": {
    "addr:full":"9052 Middlebrook Pike Knoxville TN 37923",
    "addr:housenumber":"9052",
    "addr:postcode":"37923",
    "addr:street":"Middlebrook Pike",
    "iso:country":"US",
    "sg:address":"9052 Middlebrook Pike",
    "sg:city":"Knoxville",
    "sg:classifiers":[
        {
            "category":"Building & Trades",
            "subcategory":"Construction",
            "type":"Services"
        }
    ],
    "sg:phone":"+1 865 690 6681",
    "sg:postcode":"37923",
    "sg:province":"TN",
    "sg:tags":[
        "residence",
        "for",
        "family",
        "contractor"
    ],
    "wof:name":"Walt Dickson Construction Co",
    "wof:placetype":"venue"
},
  "geometry": {"coordinates":[-84.084566,35.94349],"type":"Point"}
}