{
  "type": "Feature",
  "properties": {
    "iso:country":"US",
    "sg:address":"3105 Dickerson Pike",
    "sg:city":"Nashville",
    "sg:classifiers":[
        {
            "category":"Food & Beverages",
            "subcategory":"Groceries & Convenience Stores",
            "type":"Retail Goods"
        }
    ],
    "sg:phone":"+1 615 228 0926",
    "sg:postcode":"37207",
    "sg:province":"TN",
    "sg:tags":[
        "grocer"
    ],
    "sg:website":"www.hghill.com",
    "wof:name":"H G Hill Food Store",
    "wof:placetype":"venue"
},
  "geometry": {"coordinates":[-86.758956,36.231283],"type":"Point"}
}