{
  "type": "Feature",
  "properties": {
    "addr:full":"2601 Glass St Chattanooga TN 37406",
    "addr:housenumber":"2601",
    "addr:postcode":"37406",
    "addr:street":"Glass St",
    "iso:country":"US",
    "sg:address":"2601 Glass St",
    "sg:city":"Chattanooga",
    "sg:classifiers":[
        {
            "category":"Personal",
            "subcategory":"Barber",
            "type":"Services"
        }
    ],
    "sg:phone":"+1 423 698 0767",
    "sg:postcode":"37406",
    "sg:province":"TN",
    "sg:tags":[
        "shop"
    ],
    "wof:name":"Progress",
    "wof:placetype":"venue"
},
  "geometry": {"coordinates":[-85.24593299999999,35.066431],"type":"Point"}
}