{
  "type": "Feature",
  "properties": {
    "iso:country":"US",
    "sg:address":"236 McGavock Pike",
    "sg:city":"Nashville",
    "sg:classifiers":[
        {
            "category":"Home & Garden",
            "subcategory":"Building Materials",
            "type":"Retail Goods"
        }
    ],
    "sg:phone":"+1 615 889 2426",
    "sg:postcode":"37214",
    "sg:province":"TN",
    "wof:name":"Intrepid Studios",
    "wof:placetype":"venue"
},
  "geometry": {"coordinates":[-86.68056199999999,36.165875],"type":"Point"}
}