{
  "type": "Feature",
  "properties": {
    "iso:country":"US",
    "sg:address":"661 Mays Chapel Rd",
    "sg:city":"Mount Juliet",
    "sg:classifiers":[
        {
            "category":"Organizations",
            "subcategory":"Religious Organization",
            "type":"Services"
        }
    ],
    "sg:phone":"+1 615 754 4426",
    "sg:postcode":"37122",
    "sg:province":"TN",
    "wof:name":"Mays Chapel Baptist Church",
    "wof:placetype":"venue"
},
  "geometry": {"coordinates":[-86.47464600000001,36.247788],"type":"Point"}
}