{
  "type": "Feature",
  "properties": {
    "iso:country":"US",
    "sg:address":"460 Medon Malesus Rd",
    "sg:city":"Medon",
    "sg:classifiers":[
        {
            "category":"Organizations",
            "subcategory":"Religious Organization",
            "type":"Services"
        }
    ],
    "sg:phone":"+1 731 427 5673",
    "sg:postcode":"38356",
    "sg:province":"TN",
    "sg:tags":[
        "church"
    ],
    "wof:name":"Saint Paul Baptist Church",
    "wof:placetype":"venue"
},
  "geometry": {"coordinates":[-88.8254,35.502964],"type":"Point"}
}