{
  "type": "Feature",
  "properties": {
    "addr:full":"8902 Forest Ridge Cove Cordova TN 38018",
    "addr:housenumber":"8902",
    "addr:postcode":"38018",
    "addr:street":"Forest Ridge Cove",
    "iso:country":"US",
    "sg:address":"8902 Forest Ridge Cove",
    "sg:city":"Cordova",
    "sg:classifiers":[
        {
            "category":"Professional",
            "subcategory":"Management & Consulting",
            "type":"Services"
        }
    ],
    "sg:phone":"+1 901 755 3587",
    "sg:postcode":"38018",
    "sg:province":"TN",
    "sg:tags":[
        "consultant"
    ],
    "wof:name":"Mid South Medical Mgmt Cnsltng",
    "wof:placetype":"venue"
},
  "geometry": {"coordinates":[-89.765624,35.114247],"type":"Point"}
}