{
  "type": "Feature",
  "properties": {
    "addr:full":"1031 N Washington St Tullahoma TN 37388",
    "addr:housenumber":"1031",
    "addr:postcode":"37388",
    "addr:street":"N Washington St",
    "iso:country":"US",
    "sg:address":"1031 N Washington St",
    "sg:city":"Tullahoma",
    "sg:classifiers":[
        {
            "category":"Organizations",
            "subcategory":"Religious Organization",
            "type":"Services"
        }
    ],
    "sg:phone":"+1 931 455 8660",
    "sg:postcode":"37388",
    "sg:province":"TN",
    "wof:name":"Christ Rock Intl",
    "wof:placetype":"venue"
},
  "geometry": {"coordinates":[-86.21744099999999,35.373962],"type":"Point"}
}