{
  "type": "Feature",
  "properties": {
    "iso:country":"US",
    "sg:address":"310 S Mount Pleasant Rd",
    "sg:city":"Collierville",
    "sg:classifiers":[
        {
            "category":"Building & Trades",
            "subcategory":"Construction",
            "type":"Services"
        }
    ],
    "sg:phone":"+1 901 853 2790",
    "sg:postcode":"38017",
    "sg:province":"TN",
    "sg:tags":[
        "contractor"
    ],
    "wof:name":"Mississippi Limestone Corp",
    "wof:placetype":"venue"
},
  "geometry": {"coordinates":[-89.660555,35.037491],"type":"Point"}
}