{
  "type": "Feature",
  "properties": {
    "iso:country":"US",
    "sg:address":"9181 Hunter Valley Ln",
    "sg:city":"Knoxville",
    "sg:classifiers":[
        {
            "category":"Wholesale",
            "subcategory":"Groceries",
            "type":"Manufacturing & Wholesale Goods"
        }
    ],
    "sg:phone":"+1 865 531 3400",
    "sg:postcode":"37922",
    "sg:province":"TN",
    "sg:tags":[
        "product",
        "dairy",
        "dried",
        "milk"
    ],
    "wof:name":"Tedford/Tellico Inc",
    "wof:placetype":"venue"
},
  "geometry": {"coordinates":[-84.058707,35.861342],"type":"Point"}
}