{
  "type": "Feature",
  "properties": {
    "iso:country":"US",
    "sg:address":"4727 Pleasant Run Rd",
    "sg:city":"Memphis",
    "sg:classifiers":[
        {
            "category":"Retail",
            "subcategory":"Auto Rental",
            "type":"Services"
        }
    ],
    "sg:phone":"+1 901 375 1884",
    "sg:postcode":"38118",
    "sg:province":"TN",
    "sg:tags":[
        "trailer",
        "lease"
    ],
    "wof:name":"GE",
    "wof:placetype":"venue"
},
  "geometry": {"coordinates":[-89.90194099999999,35.016544],"type":"Point"}
}