{
  "type": "Feature",
  "properties": {
    "iso:country":"US",
    "sg:address":"777 Ranch Way",
    "sg:city":"Sevierville",
    "sg:classifiers":[
        {
            "category":"Farming",
            "subcategory":"Farm",
            "type":"Manufacturing & Wholesale Goods"
        }
    ],
    "sg:phone":"+1 865 774 1999",
    "sg:postcode":"37862",
    "sg:province":"TN",
    "sg:tags":[
        "crop",
        "general"
    ],
    "wof:name":"Utopia Frms Rdiscovery Program",
    "wof:placetype":"venue"
},
  "geometry": {"coordinates":[-83.60298,35.842237],"type":"Point"}
}