{
  "type": "Feature",
  "properties": {
    "iso:country":"US",
    "sg:address":"193 Blair Rd",
    "sg:city":"Carthage",
    "sg:classifiers":[
        {
            "category":"Government",
            "subcategory":"Office",
            "type":"Public Place"
        }
    ],
    "sg:phone":"+1 615 735 0109",
    "sg:postcode":"37167",
    "sg:province":"TN",
    "sg:tags":[
        "executive"
    ],
    "wof:name":"Sewer Trtmnt Gordonsville Cy",
    "wof:placetype":"venue"
},
  "geometry": {"coordinates":[-86.576223,35.967532],"type":"Point"}
}