{
  "type": "Feature",
  "properties": {
    "iso:country":"US",
    "sg:address":"7525 Twining Dr",
    "sg:city":"Knoxville",
    "sg:classifiers":[
        {
            "category":"Professional",
            "type":"Services"
        }
    ],
    "sg:phone":"+1 865 769 5266",
    "sg:postcode":"37919",
    "sg:province":"TN",
    "wof:name":"Creative Network Alliance Inc",
    "wof:placetype":"venue"
},
  "geometry": {"coordinates":[-84.035803,35.917481],"type":"Point"}
}