{
  "type": "Feature",
  "properties": {
    "iso:country":"US",
    "sg:address":"1498 Union Ave",
    "sg:city":"Memphis",
    "sg:classifiers":[
        {
            "category":"Utilities",
            "subcategory":"Mobile Phone",
            "type":"Services"
        }
    ],
    "sg:phone":"+1 901 725 2200",
    "sg:postcode":"38104",
    "sg:province":"TN",
    "sg:tags":[
        "telephone",
        "cellular"
    ],
    "wof:name":"T-Mobile",
    "wof:placetype":"venue"
},
  "geometry": {"coordinates":[-90.010733,35.136332],"type":"Point"}
}