{
  "type": "Feature",
  "properties": {
    "iso:country":"US",
    "sg:address":"1737 Lochearn Rd",
    "sg:city":"Memphis",
    "sg:classifiers":[
        {
            "category":"Building & Trades",
            "subcategory":"Plumbing",
            "type":"Services"
        }
    ],
    "sg:phone":"+1 901 332 1449",
    "sg:postcode":"38116",
    "sg:province":"TN",
    "sg:tags":[
        "plumbing",
        "contractor"
    ],
    "wof:name":"Krag Plumbing Company Inc",
    "wof:placetype":"venue"
},
  "geometry": {"coordinates":[-90.006112,35.057257],"type":"Point"}
}