{
  "type": "Feature",
  "properties": {
    "iso:country":"US",
    "sg:address":"506 Jordan Rd",
    "sg:city":"Franklin",
    "sg:classifiers":[
        {
            "category":"Organizations",
            "subcategory":"Religious Organization",
            "type":"Services"
        }
    ],
    "sg:phone":"+1 615 790 0106",
    "sg:postcode":"37067",
    "sg:province":"TN",
    "sg:tags":[
        "church"
    ],
    "wof:name":"Faith Community Of Faith Chr",
    "wof:placetype":"venue"
},
  "geometry": {"coordinates":[-86.840496,35.931937],"type":"Point"}
}