{
  "type": "Feature",
  "properties": {
    "addr:full":"10049 Rolling Wind Dr Soddy Daisy TN 37379",
    "addr:housenumber":"10049",
    "addr:postcode":"37379",
    "addr:street":"Rolling Wind Dr",
    "iso:country":"US",
    "sg:address":"10049 Rolling Wind Dr",
    "sg:city":"Soddy Daisy",
    "sg:classifiers":[
        {
            "category":"Real Estate",
            "subcategory":"Real Estate Operator",
            "type":"Services"
        }
    ],
    "sg:phone":"+1 423 842 3558",
    "sg:postcode":"37379",
    "sg:province":"TN",
    "sg:tags":[
        "building",
        "nonresidential"
    ],
    "wof:name":"Caro Tenn Properties LLC",
    "wof:placetype":"venue"
},
  "geometry": {"coordinates":[-85.120285,35.225234],"type":"Point"}
}