{
  "type": "Feature",
  "properties": {
    "iso:country":"US",
    "sg:address":"3019 Sanders Dr",
    "sg:city":"Knoxville",
    "sg:classifiers":[
        {
            "category":"Health Services",
            "subcategory":"Doctor",
            "type":"Services"
        }
    ],
    "sg:phone":"+1 865 688 4112",
    "sg:postcode":"37918",
    "sg:province":"TN",
    "wof:name":"Major J T DDS",
    "wof:placetype":"venue"
},
  "geometry": {"coordinates":[-83.92368999999999,36.027343],"type":"Point"}
}