{
  "type": "Feature",
  "properties": {
    "iso:country":"US",
    "sg:address":"920 E Chester St",
    "sg:city":"Jackson",
    "sg:classifiers":[
        {
            "category":"Shopping",
            "subcategory":"Clothing, Apparel, & Fashions",
            "type":"Retail Goods"
        }
    ],
    "sg:phone":"+1 731 423 1017",
    "sg:postcode":"38301",
    "sg:province":"TN",
    "wof:name":"Men of Excellence Now Inc",
    "wof:placetype":"venue"
},
  "geometry": {"coordinates":[-88.799741,35.611941],"type":"Point"}
}