{
  "type": "Feature",
  "properties": {
    "addr:full":"1350 Shirley Myers Way Sevierville TN 37862",
    "addr:housenumber":"1350",
    "addr:postcode":"37862",
    "addr:street":"Shirley Myers Way",
    "iso:country":"US",
    "sg:address":"1350 Shirley Myers Way",
    "sg:city":"Sevierville",
    "sg:classifiers":[
        {
            "category":"Building & Trades",
            "subcategory":"Cleaning & Sanitation",
            "type":"Services"
        },
        {
            "category":"Building & Trades",
            "subcategory":"Construction",
            "type":"Services"
        }
    ],
    "sg:phone":"+1 865 453 4103",
    "sg:postcode":"37862",
    "sg:province":"TN",
    "sg:tags":[
        "fireplace",
        "chimney",
        "contractor"
    ],
    "wof:name":"Old Smokey Chimney Sweeps Inc",
    "wof:placetype":"venue"
},
  "geometry": {"coordinates":[-83.582469,35.759817],"type":"Point"}
}