{
  "type": "Feature",
  "properties": {
    "iso:country":"US",
    "sg:address":"1727 Elm Hill Pike",
    "sg:city":"Nashville",
    "sg:classifiers":[
        {
            "category":"Restaurant",
            "type":"Food & Drink"
        }
    ],
    "sg:phone":"+1 615 231 2528",
    "sg:postcode":"37210",
    "sg:province":"TN",
    "sg:tags":[
        "eating"
    ],
    "wof:name":"Shoneys 1655",
    "wof:placetype":"venue"
},
  "geometry": {"coordinates":[-86.712709,36.144598],"type":"Point"}
}