{
  "type": "Feature",
  "properties": {
    "addr:full":"2153 Gallatin Pike N Madison TN 37115",
    "addr:housenumber":"2153",
    "addr:postcode":"37115",
    "addr:street":"Gallatin Pike N",
    "iso:country":"US",
    "sg:address":"2153 Gallatin Pike N",
    "sg:city":"Madison",
    "sg:classifiers":[
        {
            "category":"Organizations",
            "subcategory":"Community Association",
            "type":"Services"
        }
    ],
    "sg:phone":"+1 615 859 8400",
    "sg:postcode":"37115",
    "sg:province":"TN",
    "sg:tags":[
        "club"
    ],
    "wof:name":"AAA Insurance",
    "wof:placetype":"venue"
},
  "geometry": {"coordinates":[-86.68983900000001,36.304179],"type":"Point"}
}