{
  "type": "Feature",
  "properties": {
    "addr:full":"525 Keller St Bolivar TN 38008",
    "addr:housenumber":"525",
    "addr:postcode":"38008",
    "addr:street":"Keller St",
    "iso:country":"US",
    "sg:address":"525 Keller St",
    "sg:city":"Bolivar",
    "sg:classifiers":[
        {
            "category":"Professional",
            "type":"Services"
        }
    ],
    "sg:phone":"+1 731 658 9223",
    "sg:postcode":"38008",
    "sg:province":"TN",
    "sg:tags":[
        "establishment"
    ],
    "wof:name":"T Mc Clellan Dog",
    "wof:placetype":"venue"
},
  "geometry": {"coordinates":[-88.992346,35.26216],"type":"Point"}
}