{
  "type": "Feature",
  "properties": {
    "addr:full":"3529 Brainerd Rd Chattanooga TN 37411",
    "addr:housenumber":"3529",
    "addr:postcode":"37411",
    "addr:street":"Brainerd Rd",
    "iso:country":"US",
    "sg:address":"3529 Brainerd Rd",
    "sg:city":"Chattanooga",
    "sg:classifiers":[
        {
            "category":"Insurance",
            "subcategory":"Insurance Agent",
            "type":"Services"
        }
    ],
    "sg:phone":"+1 423 622 1534",
    "sg:postcode":"37411",
    "sg:province":"TN",
    "wof:name":"Edward Rust",
    "wof:placetype":"venue"
},
  "geometry": {"coordinates":[-85.246662,35.024353],"type":"Point"}
}