{
  "type": "Feature",
  "properties": {
    "addr:full":"2011 Julie Dr Mt Juliet TN 37122",
    "addr:housenumber":"2011",
    "addr:postcode":"37122",
    "addr:street":"Julie Dr",
    "iso:country":"US",
    "sg:address":"2011 Julie Dr",
    "sg:city":"Mt Juliet",
    "sg:classifiers":[
        {
            "category":"Professional",
            "subcategory":"Business Services",
            "type":"Services"
        },
        {
            "category":"Manufacturing",
            "subcategory":"Apparel",
            "type":"Manufacturing & Wholesale Goods"
        }
    ],
    "sg:phone":"+1 615 773 5169",
    "sg:postcode":"37122",
    "sg:province":"TN",
    "sg:tags":[
        "embroidery"
    ],
    "wof:name":"Threadheadz Embroidery Works",
    "wof:placetype":"venue"
},
  "geometry": {"coordinates":[-86.523444,36.196656],"type":"Point"}
}