{
  "type": "Feature",
  "properties": {
    "iso:country":"US",
    "sg:address":"130 Richardson St",
    "sg:city":"Smyrna",
    "sg:classifiers":[
        {
            "category":"Social Services",
            "type":"Services"
        }
    ],
    "sg:phone":"+1 615 355 0697",
    "sg:postcode":"37167",
    "sg:province":"TN",
    "wof:name":"Smyrna Lavergne Food Bank",
    "wof:placetype":"venue"
},
  "geometry": {"coordinates":[-86.52524099999999,35.983667],"type":"Point"}
}