{
  "type": "Feature",
  "properties": {
    "iso:country":"US",
    "sg:address":"2208 Tuckaleechee Pike",
    "sg:city":"Maryville",
    "sg:classifiers":[
        {
            "category":"Organizations",
            "subcategory":"Religious Organization",
            "type":"Services"
        }
    ],
    "sg:phone":"+1 865 982 8530",
    "sg:postcode":"37803",
    "sg:province":"TN",
    "wof:name":"Grandview Baptist Church",
    "wof:placetype":"venue"
},
  "geometry": {"coordinates":[-83.93582499999999,35.752248],"type":"Point"}
}