{
  "type": "Feature",
  "properties": {
    "iso:country":"US",
    "sg:address":"421 N Broadway",
    "sg:city":"Portland",
    "sg:classifiers":[
        {
            "category":"Health Services",
            "subcategory":"Doctor",
            "type":"Services"
        }
    ],
    "sg:phone":"+1 615 325 6030",
    "sg:postcode":"37148",
    "sg:province":"TN",
    "sg:tags":[
        "physician",
        "surgeon"
    ],
    "wof:name":"Portland Family Practice",
    "wof:placetype":"venue"
},
  "geometry": {"coordinates":[-86.518556,36.585058],"type":"Point"}
}