{
  "type": "Feature",
  "properties": {
    "iso:country":"US",
    "sg:address":"403 McFarland St",
    "sg:city":"Morristown",
    "sg:classifiers":[
        {
            "category":"Wholesale",
            "subcategory":"Medical Equipment & Supplies",
            "type":"Manufacturing & Wholesale Goods"
        }
    ],
    "sg:phone":"+1 423 581 8110",
    "sg:postcode":"37814",
    "sg:province":"TN",
    "sg:tags":[
        "physician",
        "surgeon"
    ],
    "wof:name":"Beneficial Home Medical Equip",
    "wof:placetype":"venue"
},
  "geometry": {"coordinates":[-83.30319900000001,36.212487],"type":"Point"}
}