{
  "type": "Feature",
  "properties": {
    "addr:full":"2747 Buckner Ln Thompsons Sta TN 37179",
    "addr:housenumber":"2747",
    "addr:postcode":"37179",
    "addr:street":"Buckner Ln",
    "iso:country":"US",
    "sg:address":"2747 Buckner Ln",
    "sg:city":"Thompsons Sta",
    "sg:classifiers":[
        {
            "category":"Building & Trades",
            "subcategory":"Landscaping Services",
            "type":"Services"
        }
    ],
    "sg:phone":"+1 615 791 1506",
    "sg:postcode":"37179",
    "sg:province":"TN",
    "sg:tags":[
        "lawn",
        "maintenance",
        "grounds"
    ],
    "wof:name":"Redman Lawn Care",
    "wof:placetype":"venue"
},
  "geometry": {"coordinates":[-86.87989899999999,35.775564],"type":"Point"}
}