{
  "type": "Feature",
  "properties": {
    "iso:country":"US",
    "sg:address":"350 N Mount Juliet Rd",
    "sg:city":"Mount Juliet",
    "sg:classifiers":[
        {
            "category":"Bars & Pubs",
            "type":"Food & Drink"
        },
        {
            "category":"Restaurant",
            "type":"Food & Drink"
        }
    ],
    "sg:menulink":"http://www.allmenus.com/tn/mount-juliet/222967-cracker-barrel-old-country-store/menu/",
    "sg:phone":"+1 615 754 8300",
    "sg:postcode":"37122",
    "sg:province":"TN",
    "sg:tags":[
        "american",
        "southern"
    ],
    "wof:name":"Cracker Barrel Old Country Store",
    "wof:placetype":"venue"
},
  "geometry": {"coordinates":[-86.512924,36.176019],"type":"Point"}
}