{
  "type": "Feature",
  "properties": {
    "iso:country":"US",
    "sg:address":"6625 Maynardville Pike",
    "sg:city":"Knoxville",
    "sg:classifiers":[
        {
            "category":"Restaurant",
            "type":"Food & Drink"
        }
    ],
    "sg:phone":"+1 865 922 3354",
    "sg:postcode":"37918",
    "sg:province":"TN",
    "sg:tags":[
        "delicatessen"
    ],
    "wof:name":"Time Out Deli",
    "wof:placetype":"venue"
},
  "geometry": {"coordinates":[-83.926579,36.066735],"type":"Point"}
}