{
  "type": "Feature",
  "properties": {
    "iso:country":"US",
    "sg:address":"4707 S 3rd St",
    "sg:city":"Memphis",
    "sg:classifiers":[
        {
            "category":"Food & Beverages",
            "subcategory":"Liquor & Beverages",
            "type":"Retail Goods"
        }
    ],
    "sg:phone":"+1 901 785 5660",
    "sg:postcode":"38109",
    "sg:province":"TN",
    "sg:tags":[
        "alcoholic"
    ],
    "wof:name":"Coda Liquor Store",
    "wof:placetype":"venue"
},
  "geometry": {"coordinates":[-90.08845700000001,35.02029],"type":"Point"}
}