{
  "type": "Feature",
  "properties": {
    "iso:country":"US",
    "sg:address":"739 Bluff City Hwy",
    "sg:city":"Bristol",
    "sg:classifiers":[
        {
            "category":"Professional",
            "subcategory":"Management & Consulting",
            "type":"Services"
        }
    ],
    "sg:phone":"+1 423 274 9458",
    "sg:postcode":"37620",
    "sg:province":"TN",
    "sg:tags":[
        "consultant",
        "business"
    ],
    "sg:website":"www.chipthomasconsulting.com",
    "wof:name":"Chip Thomas Consulting",
    "wof:placetype":"venue"
},
  "geometry": {"coordinates":[-82.198909,36.564949],"type":"Point"}
}