{
  "type": "Feature",
  "properties": {
    "addr:full":"552 Roosevelt Ave Madison TN 37115",
    "addr:housenumber":"552",
    "addr:postcode":"37115",
    "addr:street":"Roosevelt Ave",
    "iso:country":"US",
    "sg:address":"552 Roosevelt Ave",
    "sg:city":"Madison",
    "sg:classifiers":[
        {
            "category":"Personal",
            "subcategory":"Beauty Salon",
            "type":"Services"
        }
    ],
    "sg:phone":"+1 615 860 7023",
    "sg:postcode":"37115",
    "sg:province":"TN",
    "sg:tags":[
        "shop"
    ],
    "wof:name":"Bridgets Hair",
    "wof:placetype":"venue"
},
  "geometry": {"coordinates":[-86.69862500000001,36.271017],"type":"Point"}
}