{
  "type": "Feature",
  "properties": {
    "iso:country":"US",
    "sg:address":"8296 Shallow Rock Cove",
    "sg:city":"Cordova",
    "sg:classifiers":[
        {
            "category":"Utilities",
            "subcategory":"Telephone",
            "type":"Services"
        }
    ],
    "sg:phone":"+1 901 757 6289",
    "sg:postcode":"38016",
    "sg:province":"TN",
    "sg:tags":[
        "company"
    ],
    "wof:name":"Bellsouth",
    "wof:placetype":"venue"
},
  "geometry": {"coordinates":[-89.78711699999999,35.166133],"type":"Point"}
}