{
  "type": "Feature",
  "properties": {
    "iso:country":"US",
    "sg:address":"110 Spring St",
    "sg:city":"Spencer",
    "sg:classifiers":[
        {
            "category":"Autos & Motor Vehicles",
            "subcategory":"Fuel & Gas Station",
            "type":"Retail Goods"
        }
    ],
    "sg:phone":"+1 931 946 2565",
    "sg:postcode":"38583",
    "sg:province":"TN",
    "sg:tags":[
        "oil"
    ],
    "wof:name":"Hitchcock's 111 Shell",
    "wof:placetype":"venue"
},
  "geometry": {"coordinates":[-85.474244,35.934984],"type":"Point"}
}