{
  "type": "Feature",
  "properties": {
    "iso:country":"US",
    "sg:address":"1018 W Trinity Ln",
    "sg:city":"Nashville",
    "sg:classifiers":[
        {
            "category":"Restaurant",
            "type":"Food & Drink"
        }
    ],
    "sg:phone":"+1 615 259 2350",
    "sg:postcode":"37218",
    "sg:province":"TN",
    "sg:tags":[
        "eating"
    ],
    "wof:name":"Team Ice Cream",
    "wof:placetype":"venue"
},
  "geometry": {"coordinates":[-86.816728,36.204611],"type":"Point"}
}