{
  "type": "Feature",
  "properties": {
    "iso:country":"US",
    "sg:address":"200 Dogwood Ter",
    "sg:city":"Lenoir City",
    "sg:classifiers":[
        {
            "category":"Real Estate",
            "subcategory":"Real Estate Operator",
            "type":"Services"
        }
    ],
    "sg:phone":"+1 865 986 0280",
    "sg:postcode":"37771",
    "sg:province":"TN",
    "sg:tags":[
        "building",
        "apartment"
    ],
    "wof:name":"Wood Properties Management Inc",
    "wof:placetype":"venue"
},
  "geometry": {"coordinates":[-84.27814100000001,35.804682],"type":"Point"}
}