{
  "type": "Feature",
  "properties": {
    "iso:country":"US",
    "sg:address":"604 Churchill Rd",
    "sg:city":"Knoxville",
    "sg:classifiers":[
        {
            "category":"Manufacturing",
            "subcategory":"Printing",
            "type":"Manufacturing & Wholesale Goods"
        }
    ],
    "sg:phone":"+1 865 693 2703",
    "sg:postcode":"37909",
    "sg:province":"TN",
    "sg:tags":[
        "publishing"
    ],
    "wof:name":"Private Sector Ent",
    "wof:placetype":"venue"
},
  "geometry": {"coordinates":[-84.044224,35.935456],"type":"Point"}
}