{
  "type": "Feature",
  "properties": {
    "addr:full":"709 Congress Pkwy NW Athens TN 37303",
    "addr:housenumber":"709",
    "addr:postcode":"37303",
    "addr:street":"Congress Pkwy Nw",
    "iso:country":"US",
    "sg:address":"709 Congress Pkwy NW",
    "sg:city":"Athens",
    "sg:classifiers":[
        {
            "category":"Retail",
            "subcategory":"Repair Shop",
            "type":"Services"
        }
    ],
    "sg:phone":"+1 423 745 8347",
    "sg:postcode":"37303",
    "sg:province":"TN",
    "sg:tags":[
        "household",
        "appliance"
    ],
    "wof:name":"Vac-N-Stitch",
    "wof:placetype":"venue"
},
  "geometry": {"coordinates":[-84.614379,35.459512],"type":"Point"}
}