{
  "type": "Feature",
  "properties": {
    "addr:full":"537 Market St Chattanooga TN 37402",
    "addr:housenumber":"537",
    "addr:postcode":"37402",
    "addr:street":"Market St",
    "iso:country":"US",
    "sg:address":"537 Market St",
    "sg:city":"Chattanooga",
    "sg:classifiers":[
        {
            "category":"Professional",
            "subcategory":"Employment Agencies",
            "type":"Services"
        }
    ],
    "sg:phone":"+1 423 265 6522",
    "sg:postcode":"37402",
    "sg:province":"TN",
    "sg:tags":[
        "opportunity"
    ],
    "wof:name":"Accountemps",
    "wof:placetype":"venue"
},
  "geometry": {"coordinates":[-85.30963300000001,35.050146],"type":"Point"}
}