{
  "type": "Feature",
  "properties": {
    "addr:full":"1170 Topside Rd Louisville TN 37777",
    "addr:housenumber":"1170",
    "addr:postcode":"37777",
    "addr:street":"Topside Rd",
    "iso:country":"US",
    "sg:address":"1170 Topside Rd",
    "sg:city":"Louisville",
    "sg:classifiers":[
        {
            "category":"Wholesale",
            "subcategory":"Machinery & Supplies",
            "type":"Manufacturing & Wholesale Goods"
        }
    ],
    "sg:phone":"+1 865 970 9290",
    "sg:postcode":"37777",
    "sg:province":"TN",
    "sg:tags":[
        "equipment",
        "pneumatic",
        "component"
    ],
    "sg:website":"www.drain-all.com",
    "wof:name":"Drain-All Inc",
    "wof:placetype":"venue"
},
  "geometry": {"coordinates":[-83.966536,35.86226],"type":"Point"}
}