{
  "type": "Feature",
  "properties": {
    "addr:full":"849 Sunny Acres Dr Crossville TN 38555",
    "addr:housenumber":"849",
    "addr:postcode":"38555",
    "addr:street":"Sunny Acres Dr",
    "iso:country":"US",
    "sg:address":"849 Sunny Acres Dr",
    "sg:city":"Crossville",
    "sg:classifiers":[
        {
            "category":"Restaurant",
            "type":"Food & Drink"
        }
    ],
    "sg:phone":"+1 931 484 5402",
    "sg:postcode":"38555",
    "sg:province":"TN",
    "sg:tags":[
        "caterer"
    ],
    "wof:name":"Wheeler Girls Home Catering",
    "wof:placetype":"venue"
},
  "geometry": {"coordinates":[-84.914253,35.908909],"type":"Point"}
}