{
  "type": "Feature",
  "properties": {
    "iso:country":"US",
    "sg:address":"2200 Democrat Rd",
    "sg:city":"Memphis",
    "sg:classifiers":[
        {
            "category":"Shopping",
            "subcategory":"Computers & Home Electronics",
            "type":"Retail Goods"
        }
    ],
    "sg:phone":"+1 901 340 0059",
    "sg:postcode":"38118",
    "sg:province":"TN",
    "sg:tags":[
        "satellite",
        "installation",
        "sales",
        "system"
    ],
    "wof:name":"A Nova Communications",
    "wof:placetype":"venue"
},
  "geometry": {"coordinates":[-89.992808,35.068869],"type":"Point"}
}