{
  "type": "Feature",
  "properties": {
    "iso:country":"US",
    "sg:address":"1520 Lookout Ave",
    "sg:city":"Memphis",
    "sg:classifiers":[
        {
            "category":"Autos & Motor Vehicles",
            "subcategory":"Auto Supplies",
            "type":"Retail Goods"
        }
    ],
    "sg:phone":"+1 901 212 9095",
    "sg:postcode":"38127",
    "sg:province":"TN",
    "sg:tags":[
        "body",
        "shop",
        "equipment",
        "automobile"
    ],
    "wof:name":"Muckey's Repair & Supply",
    "wof:placetype":"venue"
},
  "geometry": {"coordinates":[-90.014281,35.204307],"type":"Point"}
}