{
  "type": "Feature",
  "properties": {
    "iso:country":"US",
    "sg:address":"223 Mayfield Dr",
    "sg:city":"Elizabethton",
    "sg:classifiers":[
        {
            "category":"Professional",
            "type":"Services"
        }
    ],
    "sg:phone":"+1 423 543 4632",
    "sg:postcode":"37643",
    "sg:province":"TN",
    "wof:name":"Glasurebusiness / Bob Gla",
    "wof:placetype":"venue"
},
  "geometry": {"coordinates":[-82.17134799999999,36.366077],"type":"Point"}
}