{
  "type": "Feature",
  "properties": {
    "iso:country":"US",
    "sg:address":"2144 Pine Meade Rd",
    "sg:city":"Knoxville",
    "sg:classifiers":[
        {
            "category":"Professional",
            "type":"Services"
        }
    ],
    "sg:phone":"+1 865 693 3345",
    "sg:postcode":"37923",
    "sg:province":"TN",
    "wof:name":"Teno and Ayers PC",
    "wof:placetype":"venue"
},
  "geometry": {"coordinates":[-84.05849600000001,35.954274],"type":"Point"}
}