{
  "type": "Feature",
  "properties": {
    "addr:full":"303 Glenrose Ave Nashville TN 37210",
    "addr:housenumber":"303",
    "addr:postcode":"37210",
    "addr:street":"Glenrose Ave",
    "iso:country":"US",
    "sg:address":"303 Glenrose Ave",
    "sg:city":"Nashville",
    "sg:classifiers":[
        {
            "category":"Restaurant",
            "type":"Food & Drink"
        }
    ],
    "sg:phone":"+1 615 255 9347",
    "sg:postcode":"37210",
    "sg:province":"TN",
    "sg:tags":[
        "school",
        "cafeteria",
        "operates"
    ],
    "sg:website":"www.pcconline.com",
    "wof:name":"Pioneer College Caterers Inc",
    "wof:placetype":"venue"
},
  "geometry": {"coordinates":[-86.745959,36.125554],"type":"Point"}
}