{
  "type": "Feature",
  "properties": {
    "addr:full":"3655 Knight Rd Memphis TN 38118",
    "addr:housenumber":"3655",
    "addr:postcode":"38118",
    "addr:street":"Knight Rd",
    "iso:country":"US",
    "sg:address":"3655 Knight Rd",
    "sg:city":"Memphis",
    "sg:classifiers":[
        {
            "category":"Wholesale",
            "subcategory":"Stationery",
            "type":"Manufacturing & Wholesale Goods"
        }
    ],
    "sg:phone":"+1 901 566 2530",
    "sg:postcode":"38118",
    "sg:province":"TN",
    "sg:tags":[
        "product",
        "paper"
    ],
    "wof:name":"Amcor Sunclipse North America",
    "wof:placetype":"venue"
},
  "geometry": {"coordinates":[-89.910962,35.050589],"type":"Point"}
}