{
  "type": "Feature",
  "properties": {
    "iso:country":"US",
    "sg:address":"229 N Main St",
    "sg:city":"Greeneville",
    "sg:classifiers":[
        {
            "category":"Education",
            "subcategory":"Library",
            "type":"Public Place"
        }
    ],
    "sg:phone":"+1 423 638 9866",
    "sg:postcode":"37745",
    "sg:province":"TN",
    "wof:name":"Cox T Elmore Historical",
    "wof:placetype":"venue"
},
  "geometry": {"coordinates":[-82.82920300000001,36.166248],"type":"Point"}
}