{
  "type": "Feature",
  "properties": {
    "iso:country":"US",
    "sg:address":"5294 Cottonwood Rd",
    "sg:city":"Memphis",
    "sg:classifiers":[
        {
            "category":"Banks & Credit Unions",
            "subcategory":"Investment Brokerage",
            "type":"Services"
        }
    ],
    "sg:phone":"+1 901 795 6401",
    "sg:postcode":"38118",
    "sg:province":"TN",
    "sg:tags":[
        "consultant",
        "planning",
        "financial"
    ],
    "wof:name":"Financial Institutional Ntwrk",
    "wof:placetype":"venue"
},
  "geometry": {"coordinates":[-89.88564100000001,35.06896],"type":"Point"}
}