{
  "type": "Feature",
  "properties": {
    "addr:full":"7513 Halls View Rd Knoxville TN 37938",
    "addr:housenumber":"7513",
    "addr:postcode":"37938",
    "addr:street":"Halls View Rd",
    "iso:country":"US",
    "sg:address":"7513 Halls View Rd",
    "sg:city":"Knoxville",
    "sg:classifiers":[
        {
            "category":"Retail",
            "subcategory":"Auto Repair",
            "type":"Services"
        }
    ],
    "sg:phone":"+1 865 922 0789",
    "sg:postcode":"37938",
    "sg:province":"TN",
    "sg:tags":[
        "body"
    ],
    "wof:name":"Pioneer Lines & Letters",
    "wof:placetype":"venue"
},
  "geometry": {"coordinates":[-83.937679,36.08405],"type":"Point"}
}