{
  "type": "Feature",
  "properties": {
    "iso:country":"US",
    "sg:address":"2668 S Harper Rd",
    "sg:city":"Corinth",
    "sg:classifiers":[
        {
            "category":"Shopping",
            "subcategory":"Pharmacy",
            "type":"Retail Goods"
        }
    ],
    "sg:phone":"+1 662 665 9660",
    "sg:postcode":"38834",
    "sg:province":"TN",
    "wof:name":"Urgent Care Pharmacy",
    "wof:placetype":"venue"
},
  "geometry": {"coordinates":[-88.53254800000001,34.90889],"type":"Point"}
}