{
  "type": "Feature",
  "properties": {
    "iso:country":"US",
    "sg:address":"515 N Highland St",
    "sg:city":"Memphis",
    "sg:classifiers":[
        {
            "category":"Health Services",
            "subcategory":"Doctor",
            "type":"Services"
        }
    ],
    "sg:phone":"+1 901 323 1200",
    "sg:postcode":"38122",
    "sg:province":"TN",
    "sg:tags":[
        "physician",
        "family",
        "medical",
        "practice",
        "surgeons",
        "medicine",
        "surgeon"
    ],
    "wof:name":"Dan P Marshall Md",
    "wof:placetype":"venue"
},
  "geometry": {"coordinates":[-89.94462300000001,35.146112],"type":"Point"}
}