{
  "type": "Feature",
  "properties": {
    "iso:country":"US",
    "sg:address":"327 Tennessee Ave",
    "sg:city":"Etowah",
    "sg:classifiers":[
        {
            "category":"Restaurant",
            "type":"Food & Drink"
        }
    ],
    "sg:phone":"+1 423 263 0053",
    "sg:postcode":"37331",
    "sg:province":"TN",
    "sg:tags":[
        "eating"
    ],
    "wof:name":"Shellys Diner",
    "wof:placetype":"venue"
},
  "geometry": {"coordinates":[-84.522397,35.328883],"type":"Point"}
}