{
  "type": "Feature",
  "properties": {
    "iso:country":"US",
    "sg:address":"228 Stokes Ln",
    "sg:city":"Gainesboro",
    "sg:classifiers":[
        {
            "category":"Organizations",
            "subcategory":"Religious Organization",
            "type":"Services"
        }
    ],
    "sg:phone":"+1 931 268 6459",
    "sg:postcode":"38562",
    "sg:province":"TN",
    "sg:tags":[
        "church"
    ],
    "wof:name":"Jehovahs Witness Church",
    "wof:placetype":"venue"
},
  "geometry": {"coordinates":[-85.732962,36.338206],"type":"Point"}
}