{
  "type": "Feature",
  "properties": {
    "addr:full":"6236 Stage Rd Memphis TN 38134",
    "addr:housenumber":"6236",
    "addr:postcode":"38134",
    "addr:street":"Stage Rd",
    "iso:country":"US",
    "sg:address":"6236 Stage Rd",
    "sg:city":"Memphis",
    "sg:phone":"+1 901 380 0174",
    "sg:postcode":"38134",
    "sg:province":"TN",
    "wof:name":"Global Service Assoc Inc",
    "wof:placetype":"venue"
},
  "geometry": {"coordinates":[-89.855862,35.204651],"type":"Point"}
}