{
  "type": "Feature",
  "properties": {
    "iso:country":"US",
    "sg:address":"551 Springplace Rd",
    "sg:city":"Lewisburg",
    "sg:classifiers":[
        {
            "category":"Manufacturing",
            "subcategory":"Retail Goods",
            "type":"Manufacturing & Wholesale Goods"
        }
    ],
    "sg:phone":"+1 931 359 1583",
    "sg:postcode":"37091",
    "sg:province":"TN",
    "sg:tags":[
        "pencil"
    ],
    "sg:website":"www.sanfordcorp.com",
    "wof:name":"Sanford LP",
    "wof:placetype":"venue"
},
  "geometry": {"coordinates":[-86.78091000000001,35.442971],"type":"Point"}
}