{
  "type": "Feature",
  "properties": {
    "iso:country":"US",
    "sg:address":"904 Tellico St S",
    "sg:city":"Madisonville",
    "sg:classifiers":[
        {
            "category":"Banks & Credit Unions",
            "subcategory":"Bank",
            "type":"Services"
        }
    ],
    "sg:phone":"+1 423 420 3323",
    "sg:postcode":"37354",
    "sg:province":"TN",
    "wof:name":"Peoples Bank Of East Tennessee",
    "wof:placetype":"venue"
},
  "geometry": {"coordinates":[-84.362611,35.512753],"type":"Point"}
}