{
  "type": "Feature",
  "properties": {
    "addr:full":"121 Gallatin Pike N Madison TN 37115",
    "addr:housenumber":"121",
    "addr:postcode":"37115",
    "addr:street":"Gallatin Pike N",
    "iso:country":"US",
    "sg:address":"121 Gallatin Pike N",
    "sg:city":"Madison",
    "sg:classifiers":[
        {
            "category":"Professional",
            "subcategory":"Employment Agencies",
            "type":"Services"
        }
    ],
    "sg:phone":"+1 615 865 9099",
    "sg:postcode":"37115",
    "sg:province":"TN",
    "sg:tags":[
        "help",
        "supply"
    ],
    "wof:name":"Cumberland Labor Inc",
    "wof:placetype":"venue"
},
  "geometry": {"coordinates":[-86.711485,36.264487],"type":"Point"}
}