{
  "type": "Feature",
  "properties": {
    "iso:country":"US",
    "sg:address":"5105 Greenleaf Dr",
    "sg:city":"Nashville",
    "sg:classifiers":[
        {
            "category":"Real Estate",
            "subcategory":"Real Estate Operator",
            "type":"Services"
        }
    ],
    "sg:phone":"+1 615 331 3096",
    "sg:postcode":"37211",
    "sg:province":"TN",
    "sg:tags":[
        "building",
        "apartment"
    ],
    "wof:name":"Mc Murray Manor Annex",
    "wof:placetype":"venue"
},
  "geometry": {"coordinates":[-86.71935000000001,36.058459],"type":"Point"}
}