{
  "type": "Feature",
  "properties": {
    "addr:full":"2109 Abbott Martin Rd Nashville TN 37215",
    "addr:housenumber":"2109",
    "addr:postcode":"37215",
    "addr:street":"Abbott Martin Rd",
    "iso:country":"US",
    "sg:address":"2109 Abbott Martin Rd",
    "sg:city":"Nashville",
    "sg:classifiers":[
        {
            "category":"Restaurant",
            "type":"Food & Drink"
        }
    ],
    "sg:menulink":"http://www.allmenus.com/tn/nashville/85736-dominos-pizza/menu/",
    "sg:phone":"+1 615 383 3030",
    "sg:postcode":"37215",
    "sg:province":"TN",
    "sg:tags":[
        "american",
        "wing",
        "pizza"
    ],
    "wof:name":"Domino's Pizza",
    "wof:placetype":"venue"
},
  "geometry": {"coordinates":[-86.815707,36.105689],"type":"Point"}
}