{
  "type": "Feature",
  "properties": {
    "addr:full":"212 E Broad St Livingston TN 38570",
    "addr:housenumber":"212",
    "addr:postcode":"38570",
    "addr:street":"E Broad St",
    "iso:country":"US",
    "sg:address":"212 E Broad St",
    "sg:city":"Livingston",
    "sg:classifiers":[
        {
            "category":"Mining & Drilling",
            "type":"Manufacturing & Wholesale Goods"
        }
    ],
    "sg:phone":"+1 931 823 7582",
    "sg:postcode":"38570",
    "sg:province":"TN",
    "sg:tags":[
        "exploration"
    ],
    "wof:name":"Bottom Line Oil & Gas LLC",
    "wof:placetype":"venue"
},
  "geometry": {"coordinates":[-85.318911,36.384395],"type":"Point"}
}