{
  "type": "Feature",
  "properties": {
    "iso:country":"US",
    "sg:address":"146 E Chickasaw Pkwy",
    "sg:city":"Memphis",
    "sg:classifiers":[
        {
            "category":"Professional",
            "type":"Services"
        }
    ],
    "sg:phone":"+1 901 458 0202",
    "sg:postcode":"38111",
    "sg:province":"TN",
    "wof:name":"Equipoise Fund",
    "wof:placetype":"venue"
},
  "geometry": {"coordinates":[-89.961611,35.126883],"type":"Point"}
}