{
  "type": "Feature",
  "properties": {
    "iso:country":"US",
    "sg:address":"1808 W End Ave",
    "sg:city":"Nashville",
    "sg:classifiers":[
        {
            "category":"Manufacturing",
            "subcategory":"Printing",
            "type":"Manufacturing & Wholesale Goods"
        }
    ],
    "sg:phone":"+1 615 320 1000",
    "sg:postcode":"37203",
    "sg:province":"TN",
    "sg:tags":[
        "multimedia"
    ],
    "wof:name":"Idream Multimedia Inc",
    "wof:placetype":"venue"
},
  "geometry": {"coordinates":[-86.797392,36.152422],"type":"Point"}
}