{
  "type": "Feature",
  "properties": {
    "addr:full":"515 Lee Rd Cottontown TN 37048",
    "addr:housenumber":"515",
    "addr:postcode":"37048",
    "addr:street":"Lee Rd",
    "iso:country":"US",
    "sg:address":"515 Lee Rd",
    "sg:city":"Cottontown",
    "sg:classifiers":[
        {
            "category":"Building & Trades",
            "subcategory":"Construction",
            "type":"Services"
        }
    ],
    "sg:phone":"+1 615 672 9355",
    "sg:postcode":"37048",
    "sg:province":"TN",
    "sg:tags":[
        "house"
    ],
    "wof:name":"Berry Patch Landscaping",
    "wof:placetype":"venue"
},
  "geometry": {"coordinates":[-86.63624299999999,36.496664],"type":"Point"}
}