{
  "type": "Feature",
  "properties": {
    "iso:country":"US",
    "sg:address":"1700 Kirby St",
    "sg:city":"Springfield",
    "sg:classifiers":[
        {
            "category":"Restaurant",
            "type":"Food & Drink"
        }
    ],
    "sg:phone":"+1 615 384 1463",
    "sg:postcode":"37172",
    "sg:province":"TN",
    "wof:name":"Porky's",
    "wof:placetype":"venue"
},
  "geometry": {"coordinates":[-86.87996,36.49694],"type":"Point"}
}