{
  "type": "Feature",
  "properties": {
    "addr:full":"2803 E Oakland Ave Johnson City TN 37601",
    "addr:housenumber":"2803",
    "addr:postcode":"37601",
    "addr:street":"E Oakland Ave",
    "iso:country":"US",
    "sg:address":"2803 E Oakland Ave",
    "sg:city":"Johnson City",
    "sg:classifiers":[
        {
            "category":"Retail",
            "subcategory":"Animal Services",
            "type":"Services"
        }
    ],
    "sg:phone":"+1 423 928 2121",
    "sg:postcode":"37601",
    "sg:province":"TN",
    "sg:tags":[
        "pet",
        "grooming",
        "washing"
    ],
    "wof:name":"Personal Touch Pet Grooming",
    "wof:placetype":"venue"
},
  "geometry": {"coordinates":[-82.374076,36.359345],"type":"Point"}
}