{
  "type": "Feature",
  "properties": {
    "iso:country":"US",
    "sg:address":"420 E Bernard Ave",
    "sg:city":"Greeneville",
    "sg:classifiers":[
        {
            "category":"Shopping",
            "subcategory":"Florist",
            "type":"Retail Goods"
        }
    ],
    "sg:phone":"+1 423 638 3009",
    "sg:postcode":"37745",
    "sg:province":"TN",
    "wof:name":"Scott's Florist",
    "wof:placetype":"venue"
},
  "geometry": {"coordinates":[-82.816149,36.164226],"type":"Point"}
}