{
  "type": "Feature",
  "properties": {
    "iso:country":"US",
    "sg:address":"640 Morrison Springs Rd",
    "sg:city":"Chattanooga",
    "sg:classifiers":[
        {
            "category":"Government",
            "subcategory":"Office",
            "type":"Public Place"
        }
    ],
    "sg:phone":"+1 423 874 1900",
    "sg:postcode":"37415",
    "sg:province":"TN",
    "sg:tags":[
        "school"
    ],
    "wof:name":"Red Bank High School",
    "wof:placetype":"venue"
},
  "geometry": {"coordinates":[-85.30430699999999,35.124832],"type":"Point"}
}