{
  "type": "Feature",
  "properties": {
    "iso:country":"US",
    "sg:address":"2865 Rudder Rd",
    "sg:city":"Memphis",
    "sg:classifiers":[
        {
            "category":"Military Area",
            "subcategory":"Coast Guard Base",
            "type":"Public Place"
        }
    ],
    "sg:phone":"+1 901 363 0377",
    "sg:postcode":"38118",
    "sg:province":"TN",
    "sg:tags":[
        "meter"
    ],
    "sg:website":"http://www.tristatemeter.com",
    "wof:name":"Tri State Meter and Regulator Services",
    "wof:placetype":"venue"
},
  "geometry": {"coordinates":[-89.96783499999999,35.039308],"type":"Point"}
}