{
  "type": "Feature",
  "properties": {
    "addr:full":"2935 Lakeland Hills Dr Arlington TN 38002",
    "addr:housenumber":"2935",
    "addr:postcode":"38002",
    "addr:street":"Lakeland Hills Dr",
    "iso:country":"US",
    "sg:address":"2935 Lakeland Hills Dr",
    "sg:city":"Arlington",
    "sg:classifiers":[
        {
            "category":"Social Services",
            "subcategory":"Child Care",
            "type":"Services"
        }
    ],
    "sg:phone":"+1 901 382 0013",
    "sg:postcode":"38002",
    "sg:province":"TN",
    "sg:tags":[
        "center",
        "day"
    ],
    "wof:name":"Funtime Learning Center",
    "wof:placetype":"venue"
},
  "geometry": {"coordinates":[-89.739422,35.205994],"type":"Point"}
}