{
  "type": "Feature",
  "properties": {
    "iso:country":"US",
    "sg:address":"4350 Elvis Presley Blvd",
    "sg:city":"Memphis",
    "sg:classifiers":[
        {
            "category":"Building & Trades",
            "subcategory":"Locksmith",
            "type":"Services"
        }
    ],
    "sg:phone":"+1 901 248 0212",
    "sg:postcode":"38116",
    "sg:province":"TN",
    "sg:tags":[
        "lock",
        "industrial",
        "key",
        "locksmiths-commercial"
    ],
    "wof:name":"247 Memphis Lock And Key",
    "wof:placetype":"venue"
},
  "geometry": {"coordinates":[-90.025177,35.029762],"type":"Point"}
}