{
  "type": "Feature",
  "properties": {
    "addr:full":"104 Todd Ln Madison TN 37110",
    "addr:housenumber":"104",
    "addr:postcode":"37110",
    "addr:street":"Todd Ln",
    "iso:country":"US",
    "sg:address":"104 Todd Ln",
    "sg:city":"Madison",
    "sg:classifiers":[
        {
            "category":"Professional",
            "subcategory":"Business Services",
            "type":"Services"
        }
    ],
    "sg:phone":"+1 615 859 7613",
    "sg:postcode":"37110",
    "sg:province":"TN",
    "wof:name":"Patients Accounts",
    "wof:placetype":"venue"
},
  "geometry": {"coordinates":[-85.857275,35.625993],"type":"Point"}
}