{
  "type": "Feature",
  "properties": {
    "iso:country":"US",
    "sg:address":"1480 Fox Ford Rd",
    "sg:city":"Greeneville",
    "sg:classifiers":[
        {
            "category":"Wholesale",
            "subcategory":"Non-durable Goods",
            "type":"Manufacturing & Wholesale Goods"
        },
        {
            "category":"Manufacturing",
            "subcategory":"Printing",
            "type":"Manufacturing & Wholesale Goods"
        }
    ],
    "sg:phone":"+1 423 639 0064",
    "sg:postcode":"37743",
    "sg:province":"TN",
    "sg:tags":[
        "screen"
    ],
    "wof:name":"Fran Ellis & Associates",
    "wof:placetype":"venue"
},
  "geometry": {"coordinates":[-82.796469,36.094585],"type":"Point"}
}