{
  "type": "Feature",
  "properties": {
    "addr:full":"718 Mount Moriah Rd Memphis TN 38117",
    "addr:housenumber":"718",
    "addr:postcode":"38117",
    "addr:street":"Mount Moriah Rd",
    "iso:country":"US",
    "sg:address":"718 Mount Moriah Rd",
    "sg:city":"Memphis",
    "sg:phone":"+1 901 761 2750",
    "sg:postcode":"38117",
    "sg:province":"TN",
    "sg:tags":[
        "lubricant"
    ],
    "wof:name":"Traxit North America",
    "wof:placetype":"venue"
},
  "geometry": {"coordinates":[-89.895127,35.111843],"type":"Point"}
}