{
  "type": "Feature",
  "properties": {
    "iso:country":"US",
    "sg:address":"65 Stonebridge Blvd",
    "sg:city":"Jackson",
    "sg:classifiers":[
        {
            "category":"Professional",
            "subcategory":"Lawyer & Legal Services",
            "type":"Services"
        }
    ],
    "sg:phone":"+1 731 668 4878",
    "sg:postcode":"38305",
    "sg:province":"TN",
    "sg:tags":[
        "attorney"
    ],
    "wof:name":"Jeffrey A Garrety Law Offices",
    "wof:placetype":"venue"
},
  "geometry": {"coordinates":[-88.853067,35.675851],"type":"Point"}
}