{
  "type": "Feature",
  "properties": {
    "iso:country":"US",
    "sg:address":"330 Green Trail Cove",
    "sg:city":"Cordova",
    "sg:classifiers":[
        {
            "category":"Building & Trades",
            "subcategory":"Construction",
            "type":"Services"
        }
    ],
    "sg:phone":"+1 901 850 9500",
    "sg:postcode":"38018",
    "sg:province":"TN",
    "sg:tags":[
        "contractor"
    ],
    "wof:name":"Cordova Plastering Inc",
    "wof:placetype":"venue"
},
  "geometry": {"coordinates":[-89.775593,35.120519],"type":"Point"}
}