{
  "type": "Feature",
  "properties": {
    "addr:full":"1719 Gallatin Pike N Madison TN 37115",
    "addr:housenumber":"1719",
    "addr:postcode":"37115",
    "addr:street":"Gallatin Pike N",
    "iso:country":"US",
    "sg:address":"1719 Gallatin Pike N",
    "sg:city":"Madison",
    "sg:classifiers":[
        {
            "category":"Health Services",
            "subcategory":"Doctor",
            "type":"Services"
        }
    ],
    "sg:phone":"+1 615 870 0143",
    "sg:postcode":"37115",
    "sg:province":"TN",
    "sg:tags":[
        "clinic"
    ],
    "sg:website":"www.ohplus.com",
    "wof:name":"Occupational Health & Rehab",
    "wof:placetype":"venue"
},
  "geometry": {"coordinates":[-86.700896,36.294777],"type":"Point"}
}