{
  "type": "Feature",
  "properties": {
    "addr:full":"880 Blueberry Hill Rd Dayton TN 37321",
    "addr:housenumber":"880",
    "addr:postcode":"37321",
    "addr:street":"Blueberry Hill Rd",
    "iso:country":"US",
    "sg:address":"880 Blueberry Hill Rd",
    "sg:city":"Dayton",
    "sg:classifiers":[
        {
            "category":"Building & Trades",
            "subcategory":"Construction",
            "type":"Services"
        }
    ],
    "sg:phone":"+1 423 775 0376",
    "sg:postcode":"37321",
    "sg:province":"TN",
    "sg:tags":[
        "contractor"
    ],
    "wof:name":"K & S Siding & Guttering",
    "wof:placetype":"venue"
},
  "geometry": {"coordinates":[-84.98844699999999,35.506217],"type":"Point"}
}