{
  "type": "Feature",
  "properties": {
    "addr:full":"119 Cima Dr Goodlettsville TN 37072",
    "addr:housenumber":"119",
    "addr:postcode":"37072",
    "addr:street":"Cima Dr",
    "iso:country":"US",
    "sg:address":"119 Cima Dr",
    "sg:city":"Goodlettsville",
    "sg:classifiers":[
        {
            "category":"Professional",
            "subcategory":"Accounting & Tax Preparation",
            "type":"Services"
        }
    ],
    "sg:phone":"+1 615 859 0446",
    "sg:postcode":"37072",
    "sg:province":"TN",
    "wof:name":"Darrel E Tongate CPA",
    "wof:placetype":"venue"
},
  "geometry": {"coordinates":[-86.713976,36.309364],"type":"Point"}
}