{
  "type": "Feature",
  "properties": {
    "addr:city":"Chattanooga",
    "addr:full":"400 Chestnut St Chattanooga, Tn 37402",
    "addr:house_number":"400",
    "addr:housenumber":"400",
    "addr:phone":"+1 423-265-3247",
    "addr:postcode":"37402",
    "addr:road":"Chestnut St",
    "addr:state":"TN",
    "addr:street":"Chestnut St",
    "iso:country":"US",
    "sg:address":"400 Chestnut St",
    "sg:city":"Chattanooga",
    "sg:classifiers":[
        {
            "category":"Museum",
            "type":"Entertainment"
        }
    ],
    "sg:phone":"+1 423 265 3247",
    "sg:postcode":"37402",
    "sg:province":"TN",
    "sg:tags":[
        "gallery"
    ],
    "wof:airports":[
        102533789
    ],
    "wof:name":"Chattanooga Regional History",
    "wof:placetype":"venue"
},
  "geometry": {"coordinates":[-85.31122000000001,35.05111],"type":"Point"}
}