{
  "type": "Feature",
  "properties": {
    "iso:country":"US",
    "sg:address":"400 Chestnut St",
    "sg:city":"Chattanooga",
    "sg:classifiers":[
        {
            "category":"Museum",
            "type":"Entertainment"
        }
    ],
    "sg:phone":"+1 423 265 3247",
    "sg:postcode":"37402",
    "sg:province":"TN",
    "sg:tags":[
        "gallery"
    ],
    "wof:name":"Chattnoga Rgnal History Museum",
    "wof:placetype":"venue"
},
  "geometry": {"coordinates":[-85.311775,35.052212],"type":"Point"}
}