{
  "type": "Feature",
  "properties": {
    "addr:full":"1100 Orleans Dr Knoxville TN 37919",
    "addr:housenumber":"1100",
    "addr:postcode":"37919",
    "addr:street":"Orleans Dr",
    "iso:country":"US",
    "sg:address":"1100 Orleans Dr",
    "sg:city":"Knoxville",
    "sg:classifiers":[
        {
            "category":"Travel",
            "subcategory":"Hotels & Motels",
            "type":"Entertainment"
        }
    ],
    "sg:phone":"+1 865 588 8844",
    "sg:postcode":"37919",
    "sg:province":"TN",
    "sg:tags":[
        "membership",
        "lodging"
    ],
    "wof:name":"Westlands Condos Security Offi",
    "wof:placetype":"venue"
},
  "geometry": {"coordinates":[-83.999771,35.918665],"type":"Point"}
}