{
  "type": "Feature",
  "properties": {
    "iso:country":"US",
    "sg:address":"1332 Hotwater Rd",
    "sg:city":"Soddy Daisy",
    "sg:classifiers":[
        {
            "category":"Professional",
            "type":"Services"
        }
    ],
    "sg:phone":"+1 423 332 4403",
    "sg:postcode":"37379",
    "sg:province":"TN",
    "wof:name":"Raymond Millsaps",
    "wof:placetype":"venue"
},
  "geometry": {"coordinates":[-85.199167,35.277179],"type":"Point"}
}