{
  "type": "Feature",
  "properties": {
    "iso:country":"US",
    "sg:address":"2043 N Broadway St",
    "sg:city":"Knoxville",
    "sg:classifiers":[
        {
            "category":"Shopping",
            "subcategory":"Discount & Variety Stores",
            "type":"Retail Goods"
        }
    ],
    "sg:phone":"+1 865 523 2540",
    "sg:postcode":"37917",
    "sg:province":"TN",
    "wof:name":"Dollar General",
    "wof:placetype":"venue"
},
  "geometry": {"coordinates":[-83.920224,35.991982],"type":"Point"}
}