{
  "type": "Feature",
  "properties": {
    "addr:full":"1205 Repass Dr SW Knoxville TN 37920",
    "addr:housenumber":"1205",
    "addr:postcode":"37920",
    "addr:street":"Repass Dr Sw",
    "iso:country":"US",
    "sg:address":"1205 Repass Dr SW",
    "sg:city":"Knoxville",
    "sg:classifiers":[
        {
            "category":"Retail",
            "subcategory":"Laundry & Dry Cleaning",
            "type":"Services"
        }
    ],
    "sg:phone":"+1 865 573 4741",
    "sg:postcode":"37920",
    "sg:province":"TN",
    "sg:tags":[
        "cleaners",
        "rug",
        "carpet"
    ],
    "wof:name":"Pro Clean Carpet Care",
    "wof:placetype":"venue"
},
  "geometry": {"coordinates":[-83.92729300000001,35.931443],"type":"Point"}
}