{
  "type": "Feature",
  "properties": {
    "iso:country":"US",
    "sg:address":"371 E Tri County Blvd",
    "sg:city":"Oliver Springs",
    "sg:classifiers":[
        {
            "category":"Autos & Motor Vehicles",
            "subcategory":"Auto Supplies",
            "type":"Retail Goods"
        }
    ],
    "sg:phone":"+1 865 435 7788",
    "sg:postcode":"37840",
    "sg:province":"TN",
    "sg:tags":[
        "automobile",
        "parts"
    ],
    "wof:name":"Vann's Auto Parts",
    "wof:placetype":"venue"
},
  "geometry": {"coordinates":[-84.33187700000001,36.036051],"type":"Point"}
}