{
  "type": "Feature",
  "properties": {
    "addr:full":"4012 Tea Garden Way Antioch TN 37013",
    "addr:housenumber":"4012",
    "addr:postcode":"37013",
    "addr:street":"Tea Garden Way",
    "iso:country":"US",
    "sg:address":"4012 Tea Garden Way",
    "sg:city":"Antioch",
    "sg:classifiers":[
        {
            "category":"Building & Trades",
            "subcategory":"Construction",
            "type":"Services"
        }
    ],
    "sg:phone":"+1 615 367 0001",
    "sg:postcode":"37013",
    "sg:province":"TN",
    "sg:tags":[
        "specializing",
        "gutter",
        "contractor"
    ],
    "wof:name":"Gutter Topper Of Nashville",
    "wof:placetype":"venue"
},
  "geometry": {"coordinates":[-86.611869,36.065412],"type":"Point"}
}