{
  "type": "Feature",
  "properties": {
    "addr:full":"166 Poplar Ave Memphis TN 38103",
    "addr:housenumber":"166",
    "addr:postcode":"38103",
    "addr:street":"Poplar Ave",
    "iso:country":"US",
    "sg:address":"166 Poplar Ave",
    "sg:city":"Memphis",
    "sg:classifiers":[
        {
            "category":"Social Services",
            "subcategory":"Child Care",
            "type":"Services"
        }
    ],
    "sg:phone":"+1 901 525 5619",
    "sg:postcode":"38103",
    "sg:province":"TN",
    "sg:tags":[
        "organization",
        "religious",
        "day"
    ],
    "wof:name":"First Presbyterian Church",
    "wof:placetype":"venue"
},
  "geometry": {"coordinates":[-90.049313,35.149844],"type":"Point"}
}