{
  "type": "Feature",
  "properties": {
    "addr:full":"120 E Hill Ave Knoxville TN 37902",
    "addr:housenumber":"120",
    "addr:postcode":"37902",
    "addr:street":"E Hill Ave",
    "iso:country":"US",
    "sg:address":"120 E Hill Ave",
    "sg:city":"Knoxville",
    "sg:classifiers":[
        {
            "category":"Education",
            "subcategory":"College",
            "type":"Public Place"
        }
    ],
    "sg:phone":"+1 865 974 2779",
    "sg:postcode":"37902",
    "sg:province":"TN",
    "sg:tags":[
        "university"
    ],
    "wof:name":"College of Engineering",
    "wof:placetype":"venue"
},
  "geometry": {"coordinates":[-83.913589,35.961794],"type":"Point"}
}