{
  "type": "Feature",
  "properties": {
    "addr:full":"911 Tennessee Blvd Lebanon TN 37087",
    "addr:housenumber":"911",
    "addr:postcode":"37087",
    "addr:street":"Tennessee Blvd",
    "iso:country":"US",
    "sg:address":"911 Tennessee Blvd",
    "sg:city":"Lebanon",
    "sg:classifiers":[
        {
            "category":"Wholesale",
            "subcategory":"Hardware",
            "type":"Manufacturing & Wholesale Goods"
        }
    ],
    "sg:phone":"+1 615 444 8647",
    "sg:postcode":"37087",
    "sg:province":"TN",
    "sg:tags":[
        "conditioning",
        "air",
        "heating",
        "supply"
    ],
    "wof:name":"C C Dickson Co",
    "wof:placetype":"venue"
},
  "geometry": {"coordinates":[-86.271181,36.203056],"type":"Point"}
}