{
  "type": "Feature",
  "properties": {
    "addr:full":"206 Cedar Creek Rd Gray TN 37615",
    "addr:housenumber":"206",
    "addr:postcode":"37615",
    "addr:street":"Cedar Creek Rd",
    "iso:country":"US",
    "sg:address":"206 Cedar Creek Rd",
    "sg:city":"Gray",
    "sg:classifiers":[
        {
            "category":"Home & Garden",
            "subcategory":"Building Materials",
            "type":"Retail Goods"
        },
        {
            "category":"Professional",
            "type":"Services"
        }
    ],
    "sg:phone":"+1 423 477 3139",
    "sg:postcode":"37615",
    "sg:province":"TN",
    "sg:tags":[
        "glass",
        "leaded"
    ],
    "wof:name":"Glass Castle",
    "wof:placetype":"venue"
},
  "geometry": {"coordinates":[-82.449501,36.434877],"type":"Point"}
}