{
  "type": "Feature",
  "properties": {
    "iso:country":"US",
    "sg:address":"2730 Kanasita Dr",
    "sg:city":"Hixson",
    "sg:classifiers":[
        {
            "category":"Manufacturing",
            "subcategory":"Metals",
            "type":"Manufacturing & Wholesale Goods"
        }
    ],
    "sg:phone":"+1 423 870 9441",
    "sg:postcode":"37343",
    "sg:province":"TN",
    "sg:tags":[
        "chemical",
        "etching"
    ],
    "wof:name":"Eci",
    "wof:placetype":"venue"
},
  "geometry": {"coordinates":[-85.229124,35.132894],"type":"Point"}
}