{
  "type": "Feature",
  "properties": {
    "iso:country":"US",
    "sg:address":"850 S White Station Rd",
    "sg:city":"Memphis",
    "sg:classifiers":[
        {
            "category":"Professional",
            "subcategory":"Business Services",
            "type":"Services"
        }
    ],
    "sg:phone":"+1 901 767 8616",
    "sg:postcode":"38117",
    "sg:province":"TN",
    "sg:tags":[
        "interior",
        "consultant",
        "design",
        "decorator"
    ],
    "wof:name":"Jill Hertz Interior Design",
    "wof:placetype":"venue"
},
  "geometry": {"coordinates":[-89.889707,35.107104],"type":"Point"}
}