{
  "type": "Feature",
  "properties": {
    "addr:full":"1036 Waller Rd Brentwood TN 37027",
    "addr:housenumber":"1036",
    "addr:postcode":"37027",
    "addr:street":"Waller Rd",
    "iso:country":"US",
    "sg:address":"1036 Waller Rd",
    "sg:city":"Brentwood",
    "sg:classifiers":[
        {
            "category":"Shopping",
            "subcategory":"Books",
            "type":"Retail Goods"
        }
    ],
    "sg:phone":"+1 615 776 2240",
    "sg:postcode":"37027",
    "sg:province":"TN",
    "wof:name":"Blue Sky Books",
    "wof:placetype":"venue"
},
  "geometry": {"coordinates":[-86.69623199999999,35.990305],"type":"Point"}
}