{
  "type": "Feature",
  "properties": {
    "addr:full":"3421 Austin Peay Hwy Memphis TN 38135",
    "addr:housenumber":"3421",
    "addr:postcode":"38135",
    "addr:street":"Austin Peay Hwy",
    "iso:country":"US",
    "sg:address":"3421 Austin Peay Hwy",
    "sg:city":"Memphis",
    "sg:classifiers":[
        {
            "category":"Wholesale",
            "subcategory":"Machinery & Supplies",
            "type":"Manufacturing & Wholesale Goods"
        }
    ],
    "sg:phone":"+1 901 382 8828",
    "sg:postcode":"38135",
    "sg:province":"TN",
    "sg:tags":[
        "shop",
        "equipment",
        "salon",
        "barber",
        "beauty"
    ],
    "wof:name":"Sally Beauty Supply 246",
    "wof:placetype":"venue"
},
  "geometry": {"coordinates":[-89.911519,35.218805],"type":"Point"}
}