{
  "type": "Feature",
  "properties": {
    "iso:country":"US",
    "sg:address":"4421 Murphy Rd",
    "sg:city":"Nashville",
    "sg:classifiers":[
        {
            "category":"Food & Beverages",
            "subcategory":"Groceries & Convenience Stores",
            "type":"Retail Goods"
        }
    ],
    "sg:phone":"+1 615 269 8730",
    "sg:postcode":"37209",
    "sg:province":"TN",
    "wof:name":"Jack's Market",
    "wof:placetype":"venue"
},
  "geometry": {"coordinates":[-86.840099,36.14091],"type":"Point"}
}