{
  "type": "Feature",
  "properties": {
    "iso:country":"US",
    "sg:address":"3428 Winfield Dunn Pkwy",
    "sg:city":"Kodak",
    "sg:classifiers":[
        {
            "category":"Wholesale",
            "subcategory":"Toys & Hobbies",
            "type":"Manufacturing & Wholesale Goods"
        },
        {
            "category":"Food & Beverages",
            "subcategory":"Groceries & Convenience Stores",
            "type":"Retail Goods"
        }
    ],
    "sg:phone":"+1 865 933 1264",
    "sg:postcode":"37764",
    "sg:province":"TN",
    "sg:tags":[
        "chemical",
        "preparation",
        "firework",
        "mfg"
    ],
    "wof:name":"Fireworks Supermarkets",
    "wof:placetype":"venue"
},
  "geometry": {"coordinates":[-83.602841,35.972422],"type":"Point"}
}