{
  "type": "Feature",
  "properties": {
    "addr:full":"75 Michael Ln Ripley TN 38063",
    "addr:housenumber":"75",
    "addr:postcode":"38063",
    "addr:street":"Michael Ln",
    "iso:country":"US",
    "sg:address":"75 Michael Ln",
    "sg:city":"Ripley",
    "sg:classifiers":[
        {
            "category":"Professional",
            "type":"Services"
        }
    ],
    "sg:phone":"+1 731 221 8864",
    "sg:postcode":"38063",
    "sg:province":"TN",
    "wof:name":"Devora K Brown",
    "wof:placetype":"venue"
},
  "geometry": {"coordinates":[-89.54483500000001,35.82011],"type":"Point"}
}