{
  "type": "Feature",
  "properties": {
    "iso:country":"US",
    "sg:address":"3630 E Raines Rd",
    "sg:city":"Memphis",
    "sg:classifiers":[
        {
            "category":"Manufacturing",
            "subcategory":"Printing",
            "type":"Manufacturing & Wholesale Goods"
        }
    ],
    "sg:phone":"+1 901 366 6502",
    "sg:postcode":"38118",
    "sg:province":"TN",
    "sg:tags":[
        "periodical"
    ],
    "wof:name":"RR Donaly Logistics",
    "wof:placetype":"venue"
},
  "geometry": {"coordinates":[-89.94272100000001,35.036993],"type":"Point"}
}