{
  "type": "Feature",
  "properties": {
    "iso:country":"US",
    "sg:address":"100 N Main St",
    "sg:city":"Dickson",
    "sg:classifiers":[
        {
            "category":"Professional",
            "subcategory":"Advertising",
            "type":"Services"
        }
    ],
    "sg:phone":"+1 615 740 9543",
    "sg:postcode":"37055",
    "sg:province":"TN",
    "sg:tags":[
        "representative"
    ],
    "wof:name":"Shopping News Dickson County",
    "wof:placetype":"venue"
},
  "geometry": {"coordinates":[-87.386909,36.077435],"type":"Point"}
}