{
  "type": "Feature",
  "properties": {
    "addr:full":"3850 N Berlinwood Cove Memphis TN 38133",
    "addr:housenumber":"3850",
    "addr:postcode":"38133",
    "addr:street":"N Berlinwood Cove",
    "iso:country":"US",
    "sg:address":"3850 N Berlinwood Cove",
    "sg:city":"Memphis",
    "sg:classifiers":[
        {
            "category":"Retail",
            "subcategory":"Repair Shop",
            "type":"Services"
        }
    ],
    "sg:phone":"+1 901 382 0799",
    "sg:postcode":"38133",
    "sg:province":"TN",
    "sg:tags":[
        "equipment",
        "electronic",
        "supply"
    ],
    "sg:website":"www.bits-pos.com",
    "wof:name":"Bartlett Info Tech Svc",
    "wof:placetype":"venue"
},
  "geometry": {"coordinates":[-89.76759800000001,35.228814],"type":"Point"}
}