{
  "type": "Feature",
  "properties": {
    "iso:country":"US",
    "sg:address":"1211 Dodds Ave",
    "sg:city":"Chattanooga",
    "sg:classifiers":[
        {
            "category":"Organizations",
            "subcategory":"Community Association",
            "type":"Services"
        }
    ],
    "sg:phone":"+1 423 629 5831",
    "sg:postcode":"37404",
    "sg:province":"TN",
    "sg:tags":[
        "fraternal"
    ],
    "wof:name":"Elks Lodge",
    "wof:placetype":"venue"
},
  "geometry": {"coordinates":[-85.26838100000001,35.024184],"type":"Point"}
}