{
  "type": "Feature",
  "properties": {
    "iso:country":"US",
    "sg:address":"145 Lou Monta Way",
    "sg:city":"Oakland",
    "sg:classifiers":[
        {
            "category":"Real Estate",
            "subcategory":"Developer",
            "type":"Services"
        }
    ],
    "sg:phone":"+1 901 465 1901",
    "sg:postcode":"38060",
    "sg:province":"TN",
    "sg:website":"www.loumontahills.com",
    "wof:name":"Lou Monta Development Corp Co",
    "wof:placetype":"venue"
},
  "geometry": {"coordinates":[-89.44570400000001,35.219054],"type":"Point"}
}