{
  "type": "Feature",
  "properties": {
    "iso:country":"US",
    "sg:address":"5400 Poplar Ave",
    "sg:city":"Memphis",
    "sg:classifiers":[
        {
            "category":"Insurance",
            "subcategory":"Insurance Agent",
            "type":"Services"
        }
    ],
    "sg:phone":"+1 901 761 6108",
    "sg:postcode":"38119",
    "sg:province":"TN",
    "wof:name":"Prudential Insurance Co",
    "wof:placetype":"venue"
},
  "geometry": {"coordinates":[-89.879896,35.106394],"type":"Point"}
}