{
  "type": "Feature",
  "properties": {
    "iso:country":"US",
    "sg:address":"2000 Old Gallatin Rd",
    "sg:city":"Portland",
    "sg:classifiers":[
        {
            "category":"Shopping",
            "subcategory":"Used Merchandise",
            "type":"Retail Goods"
        }
    ],
    "sg:phone":"+1 615 451 6885",
    "sg:postcode":"37148",
    "sg:province":"TN",
    "sg:tags":[
        "house",
        "mail"
    ],
    "wof:name":"Grendels Cave",
    "wof:placetype":"venue"
},
  "geometry": {"coordinates":[-86.46896599999999,36.485351],"type":"Point"}
}