{
  "type": "Feature",
  "properties": {
    "iso:country":"US",
    "sg:address":"653 Mimosa Dr",
    "sg:city":"Cleveland",
    "sg:classifiers":[
        {
            "category":"Personal",
            "subcategory":"Beauty Salon",
            "type":"Services"
        }
    ],
    "sg:phone":"+1 423 478 5080",
    "sg:postcode":"37312",
    "sg:province":"TN",
    "sg:tags":[
        "shop"
    ],
    "wof:name":"Style Masters",
    "wof:placetype":"venue"
},
  "geometry": {"coordinates":[-84.85493,35.201588],"type":"Point"}
}