{
  "type": "Feature",
  "properties": {
    "iso:country":"US",
    "sg:address":"1544 Madison Ave",
    "sg:city":"Memphis",
    "sg:classifiers":[
        {
            "category":"Government",
            "subcategory":"Police Station",
            "type":"Public Place"
        }
    ],
    "sg:phone":"+1 901 274 1338",
    "sg:postcode":"38104",
    "sg:province":"TN",
    "sg:tags":[
        "department"
    ],
    "wof:name":"Memphis Police Dept",
    "wof:placetype":"venue"
},
  "geometry": {"coordinates":[-90.010713,35.13847],"type":"Point"}
}