{
  "type": "Feature",
  "properties": {
    "addr:full":"701 Cherokee Blvd Chattanooga TN 37405",
    "addr:housenumber":"701",
    "addr:postcode":"37405",
    "addr:street":"Cherokee Blvd",
    "iso:country":"US",
    "sg:address":"701 Cherokee Blvd",
    "sg:city":"Chattanooga",
    "sg:classifiers":[
        {
            "category":"Organizations",
            "subcategory":"Non-profit Organization",
            "type":"Services"
        },
        {
            "category":"Social Services",
            "type":"Services"
        }
    ],
    "sg:phone":"+1 423 267 5383",
    "sg:postcode":"37405",
    "sg:province":"TN",
    "sg:tags":[
        "welfare"
    ],
    "sg:website":"www.firstthings.org",
    "wof:name":"First Things First Corp",
    "wof:placetype":"venue"
},
  "geometry": {"coordinates":[-85.31902100000001,35.072711],"type":"Point"}
}