{
  "type": "Feature",
  "properties": {
    "iso:country":"US",
    "sg:address":"2 Northgate Park",
    "sg:city":"Chattanooga",
    "sg:classifiers":[
        {
            "category":"Banks & Credit Unions",
            "subcategory":"Bank",
            "type":"Services"
        }
    ],
    "sg:phone":"+1 423 877 8821",
    "sg:postcode":"37415",
    "sg:province":"TN",
    "sg:tags":[
        "financing"
    ],
    "wof:name":"Citi Financial Auto Credit Inc",
    "wof:placetype":"venue"
},
  "geometry": {"coordinates":[-85.237217,35.133289],"type":"Point"}
}