{
  "type": "Feature",
  "properties": {
    "iso:country":"US",
    "sg:address":"1723 Cumberland Ave",
    "sg:city":"Knoxville",
    "sg:classifiers":[
        {
            "category":"Shopping",
            "subcategory":"Bicycles & Sporting Goods",
            "type":"Retail Goods"
        }
    ],
    "sg:phone":"+1 865 523 0045",
    "sg:postcode":"37916",
    "sg:province":"TN",
    "sg:tags":[
        "equipment",
        "skateboard"
    ],
    "sg:website":"www.plutosports.com",
    "wof:name":"Pluto Sports",
    "wof:placetype":"venue"
},
  "geometry": {"coordinates":[-83.932665,35.956535],"type":"Point"}
}