{
  "type": "Feature",
  "properties": {
    "iso:country":"US",
    "sg:address":"2991 Lamar Ave",
    "sg:city":"Memphis",
    "sg:classifiers":[
        {
            "category":"Retail",
            "subcategory":"Self-service Laundry",
            "type":"Services"
        }
    ],
    "sg:phone":"+1 901 745 3341",
    "sg:postcode":"38114",
    "sg:province":"TN",
    "sg:tags":[
        "operated",
        "coin"
    ],
    "wof:name":"Laundromax",
    "wof:placetype":"venue"
},
  "geometry": {"coordinates":[-89.96357500000001,35.08715],"type":"Point"}
}