{
  "type": "Feature",
  "properties": {
    "iso:country":"US",
    "sg:address":"216 State St",
    "sg:city":"Jackson",
    "sg:classifiers":[
        {
            "category":"Home & Garden",
            "subcategory":"Building Materials",
            "type":"Retail Goods"
        }
    ],
    "sg:phone":"+1 731 427 3500",
    "sg:postcode":"38301",
    "sg:province":"TN",
    "sg:tags":[
        "door"
    ],
    "wof:name":"Parker Bros Door Hangers Inc",
    "wof:placetype":"venue"
},
  "geometry": {"coordinates":[-88.835077,35.615459],"type":"Point"}
}