{
  "type": "Feature",
  "properties": {
    "iso:country":"US",
    "sg:address":"214 Bridge St",
    "sg:city":"Franklin",
    "sg:classifiers":[
        {
            "category":"Professional",
            "type":"Services"
        }
    ],
    "sg:phone":"+1 615 595 8585",
    "sg:postcode":"37064",
    "sg:province":"TN",
    "sg:website":"www.taylormadesmiles.com",
    "wof:name":"Taylor Made Smiles",
    "wof:placetype":"venue"
},
  "geometry": {"coordinates":[-86.868905,35.92736],"type":"Point"}
}