{
  "type": "Feature",
  "properties": {
    "addr:full":"8874 Kingston Pike Knoxville TN 37923",
    "addr:housenumber":"8874",
    "addr:postcode":"37923",
    "addr:street":"Kingston Pike",
    "iso:country":"US",
    "sg:address":"8874 Kingston Pike",
    "sg:city":"Knoxville",
    "sg:classifiers":[
        {
            "category":"Health Services",
            "subcategory":"Doctor",
            "type":"Services"
        }
    ],
    "sg:phone":"+1 865 691 2330",
    "sg:postcode":"37923",
    "sg:province":"TN",
    "sg:tags":[
        "dentist"
    ],
    "wof:name":"Associated Dental Professional",
    "wof:placetype":"venue"
},
  "geometry": {"coordinates":[-84.078868,35.913879],"type":"Point"}
}