{
  "type": "Feature",
  "properties": {
    "addr:full":"1714 Rubio St Chattanooga TN 37406",
    "addr:housenumber":"1714",
    "addr:postcode":"37406",
    "addr:street":"Rubio St",
    "iso:country":"US",
    "sg:address":"1714 Rubio St",
    "sg:city":"Chattanooga",
    "sg:classifiers":[
        {
            "category":"Organizations",
            "subcategory":"Religious Organization",
            "type":"Services"
        }
    ],
    "sg:phone":"+1 423 629 0740",
    "sg:postcode":"37406",
    "sg:province":"TN",
    "sg:tags":[
        "church"
    ],
    "wof:name":"Zion Hill Missionary Baptist",
    "wof:placetype":"venue"
},
  "geometry": {"coordinates":[-85.267579,35.054122],"type":"Point"}
}