{
  "type": "Feature",
  "properties": {
    "iso:country":"US",
    "sg:address":"2616 Old Hwy 25 E",
    "sg:city":"Morristown",
    "sg:classifiers":[
        {
            "category":"Building & Trades",
            "subcategory":"Plumbing",
            "type":"Services"
        }
    ],
    "sg:phone":"+1 423 586 5666",
    "sg:postcode":"37813",
    "sg:province":"TN",
    "sg:tags":[
        "heating",
        "contractor"
    ],
    "wof:name":"A-Z Sheet Metal",
    "wof:placetype":"venue"
},
  "geometry": {"coordinates":[-83.283711,36.185661],"type":"Point"}
}