{
  "type": "Feature",
  "properties": {
    "addr:full":"3619 Nolensville Pike Nashville TN 37211",
    "addr:housenumber":"3619",
    "addr:postcode":"37211",
    "addr:street":"Nolensville Pike",
    "iso:country":"US",
    "sg:address":"3619 Nolensville Pike",
    "sg:city":"Nashville",
    "sg:classifiers":[
        {
            "category":"Banks & Credit Unions",
            "subcategory":"Bank",
            "type":"Services"
        }
    ],
    "sg:phone":"+1 615 228 6260",
    "sg:postcode":"37211",
    "sg:province":"TN",
    "sg:tags":[
        "cashing",
        "check"
    ],
    "wof:name":"A-1 Check Cashing",
    "wof:placetype":"venue"
},
  "geometry": {"coordinates":[-86.73848,36.097739],"type":"Point"}
}