{
  "type": "Feature",
  "properties": {
    "addr:full":"7445 Lakeview Dr Nashville TN 37209",
    "addr:housenumber":"7445",
    "addr:postcode":"37209",
    "addr:street":"Lakeview Dr",
    "iso:country":"US",
    "sg:address":"7445 Lakeview Dr",
    "sg:city":"Nashville",
    "sg:classifiers":[
        {
            "category":"Real Estate",
            "subcategory":"Real Estate Agent",
            "type":"Services"
        }
    ],
    "sg:phone":"+1 615 352 5725",
    "sg:postcode":"37209",
    "sg:province":"TN",
    "wof:name":"Phillips Auction & Realty",
    "wof:placetype":"venue"
},
  "geometry": {"coordinates":[-86.963442,36.153523],"type":"Point"}
}