{
  "type": "Feature",
  "properties": {
    "iso:country":"US",
    "sg:address":"1404 Towson Dr",
    "sg:city":"Columbia",
    "sg:classifiers":[
        {
            "category":"Professional",
            "type":"Services"
        }
    ],
    "sg:phone":"+1 931 388 2161",
    "sg:postcode":"38401",
    "sg:province":"TN",
    "wof:name":"National Society of Daugh",
    "wof:placetype":"venue"
},
  "geometry": {"coordinates":[-87.087276,35.585279],"type":"Point"}
}