{
  "type": "Feature",
  "properties": {
    "addr:full":"4907 French Rd Knoxville TN 37920",
    "addr:housenumber":"4907",
    "addr:postcode":"37920",
    "addr:street":"French Rd",
    "iso:country":"US",
    "sg:address":"4907 French Rd",
    "sg:city":"Knoxville",
    "sg:classifiers":[
        {
            "category":"Manufacturing",
            "subcategory":"Printing",
            "type":"Manufacturing & Wholesale Goods"
        }
    ],
    "sg:phone":"+1 865 573 5501",
    "sg:postcode":"37920",
    "sg:province":"TN",
    "sg:tags":[
        "publishing"
    ],
    "wof:name":"Pennco",
    "wof:placetype":"venue"
},
  "geometry": {"coordinates":[-83.797246,35.944263],"type":"Point"}
}