{
  "type": "Feature",
  "properties": {
    "iso:country":"US",
    "sg:address":"36 Bazeberry Rd",
    "sg:city":"Cordova",
    "sg:classifiers":[
        {
            "category":"Health Services",
            "subcategory":"Doctor",
            "type":"Services"
        }
    ],
    "sg:phone":"+1 901 737 4102",
    "sg:postcode":"38018",
    "sg:province":"TN",
    "sg:tags":[
        "physician",
        "surgeon"
    ],
    "wof:name":"Leona De Mere-Dwyer MD",
    "wof:placetype":"venue"
},
  "geometry": {"coordinates":[-89.758807,35.126486],"type":"Point"}
}