{
  "type": "Feature",
  "properties": {
    "iso:country":"US",
    "sg:address":"124 Glancy St",
    "sg:city":"Goodlettsville",
    "sg:classifiers":[
        {
            "category":"Shopping",
            "type":"Retail Goods"
        }
    ],
    "sg:phone":"+1 615 851 3901",
    "sg:postcode":"37072",
    "sg:province":"TN",
    "sg:tags":[
        "hearing",
        "equipment",
        "supply",
        "impaired"
    ],
    "wof:name":"Tennessee Hearing Instrument",
    "wof:placetype":"venue"
},
  "geometry": {"coordinates":[-86.704894,36.296754],"type":"Point"}
}