{
  "type": "Feature",
  "properties": {
    "iso:country":"US",
    "sg:address":"4319 Saundersville Rd",
    "sg:city":"Old Hickory",
    "sg:classifiers":[
        {
            "category":"Organizations",
            "subcategory":"Religious Organization",
            "type":"Services"
        }
    ],
    "sg:phone":"+1 615 847 3274",
    "sg:postcode":"37138",
    "sg:province":"TN",
    "wof:name":"Lakeview Baptist Church",
    "wof:placetype":"venue"
},
  "geometry": {"coordinates":[-86.58958199999999,36.22916],"type":"Point"}
}