{
  "type": "Feature",
  "properties": {
    "iso:country":"US",
    "sg:address":"200 Main Ave N",
    "sg:city":"Fayetteville",
    "sg:classifiers":[
        {
            "category":"Retail",
            "subcategory":"Laundry & Dry Cleaning",
            "type":"Services"
        }
    ],
    "sg:phone":"+1 931 433 2442",
    "sg:postcode":"37334",
    "sg:province":"TN",
    "sg:tags":[
        "drycleaning",
        "plant",
        "power",
        "cleaners"
    ],
    "wof:name":"Five Star Laundry and Cleaners",
    "wof:placetype":"venue"
},
  "geometry": {"coordinates":[-86.57032599999999,35.153931],"type":"Point"}
}