{
  "type": "Feature",
  "properties": {
    "iso:country":"US",
    "sg:address":"35 County Farm Rd",
    "sg:city":"Manchester",
    "sg:classifiers":[
        {
            "category":"Building & Trades",
            "subcategory":"Plumbing",
            "type":"Services"
        }
    ],
    "sg:phone":"+1 931 728 7144",
    "sg:postcode":"37355",
    "sg:province":"TN",
    "sg:tags":[
        "contractor"
    ],
    "wof:name":"C&S Heating & Air",
    "wof:placetype":"venue"
},
  "geometry": {"coordinates":[-86.134995,35.514638],"type":"Point"}
}