{
  "type": "Feature",
  "properties": {
    "addr:full":"908 E Center St Kingsport TN 37660",
    "addr:housenumber":"908",
    "addr:postcode":"37660",
    "addr:street":"E Center St",
    "iso:country":"US",
    "sg:address":"908 E Center St",
    "sg:city":"Kingsport",
    "sg:classifiers":[
        {
            "category":"Wholesale",
            "subcategory":"Durable Goods & Equipment",
            "type":"Manufacturing & Wholesale Goods"
        }
    ],
    "sg:phone":"+1 423 246 7800",
    "sg:postcode":"37660",
    "sg:province":"TN",
    "sg:tags":[
        "representative",
        "manufacturer"
    ],
    "wof:name":"Collings-Parker Assoc Inc",
    "wof:placetype":"venue"
},
  "geometry": {"coordinates":[-82.550822,36.543511],"type":"Point"}
}