{
  "type": "Feature",
  "properties": {
    "addr:full":"313 Jenso Dr NW Knoxville TN 37912",
    "addr:housenumber":"313",
    "addr:postcode":"37912",
    "addr:street":"Jenso Dr Nw",
    "iso:country":"US",
    "sg:address":"313 Jenso Dr NW",
    "sg:city":"Knoxville",
    "sg:classifiers":[
        {
            "category":"Professional",
            "type":"Services"
        }
    ],
    "sg:phone":"+1 865 689 1994",
    "sg:postcode":"37912",
    "sg:province":"TN",
    "sg:tags":[
        "establishment"
    ],
    "wof:name":"Municipal Equipment Inc",
    "wof:placetype":"venue"
},
  "geometry": {"coordinates":[-83.96275,35.999809],"type":"Point"}
}