{
  "type": "Feature",
  "properties": {
    "iso:country":"US",
    "sg:address":"186 Carronbridge Way",
    "sg:city":"Franklin",
    "sg:classifiers":[
        {
            "category":"Professional",
            "type":"Services"
        }
    ],
    "sg:phone":"+1 615 771 7747",
    "sg:postcode":"37067",
    "sg:province":"TN",
    "sg:tags":[
        "establishment"
    ],
    "wof:name":"Enclave The At Carronbridge",
    "wof:placetype":"venue"
},
  "geometry": {"coordinates":[-86.80165599999999,35.941874],"type":"Point"}
}