{
  "type": "Feature",
  "properties": {
    "iso:country":"US",
    "sg:address":"2036 US Hwy 25W",
    "sg:city":"Jellico",
    "sg:classifiers":[
        {
            "category":"Shopping",
            "subcategory":"Gifts & Souvenirs",
            "type":"Retail Goods"
        }
    ],
    "sg:phone":"+1 423 784 6131",
    "sg:postcode":"37762",
    "sg:province":"TN",
    "wof:name":"Frontier House Texaco LLC",
    "wof:placetype":"venue"
},
  "geometry": {"coordinates":[-84.10731199999999,36.57997],"type":"Point"}
}