{
  "type": "Feature",
  "properties": {
    "iso:country":"US",
    "sg:address":"184 Joy Ln",
    "sg:city":"Jacksboro",
    "sg:classifiers":[
        {
            "category":"Wholesale",
            "subcategory":"Vending Machines",
            "type":"Manufacturing & Wholesale Goods"
        }
    ],
    "sg:phone":"+1 423 562 1122",
    "sg:postcode":"37757",
    "sg:province":"TN",
    "sg:tags":[
        "operator"
    ],
    "wof:name":"Dewitts Vending",
    "wof:placetype":"venue"
},
  "geometry": {"coordinates":[-84.152619,36.323376],"type":"Point"}
}