{
  "type": "Feature",
  "properties": {
    "iso:country":"US",
    "sg:address":"384 Carriage House Dr",
    "sg:city":"Jackson",
    "sg:classifiers":[
        {
            "category":"Banks & Credit Unions",
            "subcategory":"Investment Brokerage",
            "type":"Services"
        }
    ],
    "sg:phone":"+1 731 554 2423",
    "sg:postcode":"38305",
    "sg:province":"TN",
    "wof:name":"Chad Wilson Investment Pro",
    "wof:placetype":"venue"
},
  "geometry": {"coordinates":[-88.843799,35.666479],"type":"Point"}
}