{
  "type": "Feature",
  "properties": {
    "addr:full":"1210 Mineral Wells Ave Paris TN 38242",
    "addr:housenumber":"1210",
    "addr:postcode":"38242",
    "addr:street":"Mineral Wells Ave",
    "iso:country":"US",
    "sg:address":"1210 Mineral Wells Ave",
    "sg:city":"Paris",
    "sg:classifiers":[
        {
            "category":"Professional",
            "subcategory":"Accounting & Tax Preparation",
            "type":"Services"
        }
    ],
    "sg:phone":"+1 731 642 8570",
    "sg:postcode":"38242",
    "sg:province":"TN",
    "sg:tags":[
        "return",
        "filing"
    ],
    "wof:name":"Jackson Hewitt Tax Svc",
    "wof:placetype":"venue"
},
  "geometry": {"coordinates":[-88.307367,36.283415],"type":"Point"}
}