{
  "type": "Feature",
  "properties": {
    "iso:country":"US",
    "sg:address":"1030 Madison Creek Rd",
    "sg:city":"Goodlettsville",
    "sg:classifiers":[
        {
            "category":"Professional",
            "subcategory":"Accounting & Tax Preparation",
            "type":"Services"
        }
    ],
    "sg:phone":"+1 615 855 2368",
    "sg:postcode":"37072",
    "sg:province":"TN",
    "sg:tags":[
        "keeping",
        "book"
    ],
    "wof:name":"Cindy Bean Tax Service",
    "wof:placetype":"venue"
},
  "geometry": {"coordinates":[-86.682177,36.345201],"type":"Point"}
}