{
  "type": "Feature",
  "properties": {
    "iso:country":"US",
    "sg:address":"9747 Waycross Cir",
    "sg:city":"Ooltewah",
    "sg:classifiers":[
        {
            "category":"Retail",
            "subcategory":"Repair Shop",
            "type":"Services"
        },
        {
            "category":"Retail",
            "subcategory":"Laundry & Dry Cleaning",
            "type":"Services"
        }
    ],
    "sg:phone":"+1 423 893 7144",
    "sg:postcode":"37363",
    "sg:province":"TN",
    "sg:tags":[
        "cleaners",
        "rug",
        "carpet"
    ],
    "wof:name":"A Power Clean Inc",
    "wof:placetype":"venue"
},
  "geometry": {"coordinates":[-85.093819,35.003104],"type":"Point"}
}