{
  "type": "Feature",
  "properties": {
    "iso:country":"US",
    "sg:address":"1917 Hackworth St",
    "sg:city":"Nashville",
    "sg:phone":"+1 615 256 7176",
    "sg:postcode":"37210",
    "sg:province":"TN",
    "sg:tags":[
        "gas"
    ],
    "sg:website":"www.suburbanpropane.com",
    "wof:name":"Suburban Propane",
    "wof:placetype":"venue"
},
  "geometry": {"coordinates":[-86.750016,36.137007],"type":"Point"}
}