{
  "type": "Feature",
  "properties": {
    "addr:full":"497 Lenoir Rd Kingsport TN 37660",
    "addr:housenumber":"497",
    "addr:postcode":"37660",
    "addr:street":"Lenoir Rd",
    "iso:country":"US",
    "sg:address":"497 Lenoir Rd",
    "sg:city":"Kingsport",
    "sg:classifiers":[
        {
            "category":"Social Services",
            "subcategory":"Child Care",
            "type":"Services"
        }
    ],
    "sg:phone":"+1 423 288 9116",
    "sg:postcode":"37660",
    "sg:province":"TN",
    "sg:tags":[
        "day"
    ],
    "wof:name":"Small World Preschool Daycare",
    "wof:placetype":"venue"
},
  "geometry": {"coordinates":[-82.497142,36.567647],"type":"Point"}
}