{
  "type": "Feature",
  "properties": {
    "iso:country":"US",
    "sg:address":"153 Ocala Dr",
    "sg:city":"Antioch",
    "sg:classifiers":[
        {
            "category":"Building & Trades",
            "subcategory":"Construction",
            "type":"Services"
        }
    ],
    "sg:phone":"+1 615 445 3148",
    "sg:postcode":"37013",
    "sg:province":"TN",
    "sg:tags":[
        "house"
    ],
    "wof:name":"Shadday Ft Construction Co",
    "wof:placetype":"venue"
},
  "geometry": {"coordinates":[-86.693072,36.049918],"type":"Point"}
}