{
  "type": "Feature",
  "properties": {
    "iso:country":"US",
    "sg:address":"318 Belltown Rd",
    "sg:city":"Copperhill",
    "sg:classifiers":[
        {
            "category":"Freight",
            "type":"Transportation"
        }
    ],
    "sg:phone":"+1 423 496 1242",
    "sg:postcode":"37317",
    "sg:province":"NC",
    "sg:tags":[
        "commercial",
        "storage"
    ],
    "wof:name":"Belltown Mini Storage & Garage",
    "wof:placetype":"venue"
},
  "geometry": {"coordinates":[-84.36824,34.998002],"type":"Point"}
}