{
  "type": "Feature",
  "properties": {
    "iso:country":"US",
    "sg:address":"2280 Beckwith Rd",
    "sg:city":"Mount Juliet",
    "sg:classifiers":[
        {
            "category":"Utilities",
            "subcategory":"Electric",
            "type":"Services"
        }
    ],
    "sg:phone":"+1 615 758 2908",
    "sg:postcode":"37122",
    "sg:province":"TN",
    "wof:name":"T V A-Wilson 500 Substation",
    "wof:placetype":"venue"
},
  "geometry": {"coordinates":[-86.46168900000001,36.206452],"type":"Point"}
}