{
  "type": "Feature",
  "properties": {
    "addr:full":"353 Lucy Ave Memphis TN 38106",
    "addr:housenumber":"353",
    "addr:postcode":"38106",
    "addr:street":"Lucy Ave",
    "iso:country":"US",
    "sg:address":"353 Lucy Ave",
    "sg:city":"Memphis",
    "sg:classifiers":[
        {
            "category":"Organizations",
            "subcategory":"Religious Organization",
            "type":"Services"
        }
    ],
    "sg:phone":"+1 901 947 1879",
    "sg:postcode":"38106",
    "sg:province":"TN",
    "wof:name":"Fletcher Memorial Cmnty Church",
    "wof:placetype":"venue"
},
  "geometry": {"coordinates":[-90.051329,35.114078],"type":"Point"}
}