{
  "type": "Feature",
  "properties": {
    "addr:full":"813 Ava Dr Kingsport TN 37663",
    "addr:housenumber":"813",
    "addr:postcode":"37663",
    "addr:street":"Ava Dr",
    "iso:country":"US",
    "sg:address":"813 Ava Dr",
    "sg:city":"Kingsport",
    "sg:classifiers":[
        {
            "category":"Professional",
            "subcategory":"Art Services",
            "type":"Services"
        }
    ],
    "sg:phone":"+1 423 239 5010",
    "sg:postcode":"37663",
    "sg:province":"TN",
    "sg:tags":[
        "commercial",
        "graphic",
        "design",
        "designer"
    ],
    "wof:name":"Outside The Box",
    "wof:placetype":"venue"
},
  "geometry": {"coordinates":[-82.489896,36.487921],"type":"Point"}
}