{
  "type": "Feature",
  "properties": {
    "iso:country":"US",
    "sg:address":"1537 Fort Campbell Blvd",
    "sg:city":"Clarksville",
    "sg:classifiers":[
        {
            "category":"Bars & Pubs",
            "type":"Food & Drink"
        }
    ],
    "sg:phone":"+1 931 647 0377",
    "sg:postcode":"37042",
    "sg:province":"TN",
    "sg:tags":[
        "lounge",
        "cocktail"
    ],
    "wof:name":"Seoul Lounge",
    "wof:placetype":"venue"
},
  "geometry": {"coordinates":[-87.405815,36.571223],"type":"Point"}
}