{
  "type": "Feature",
  "properties": {
    "addr:full":"2709 Rifle Range Rd Knoxville TN 37918",
    "addr:housenumber":"2709",
    "addr:postcode":"37918",
    "addr:street":"Rifle Range Rd",
    "iso:country":"US",
    "sg:address":"2709 Rifle Range Rd",
    "sg:city":"Knoxville",
    "sg:classifiers":[
        {
            "category":"Building & Trades",
            "subcategory":"Construction",
            "type":"Services"
        }
    ],
    "sg:phone":"+1 865 688 9474",
    "sg:postcode":"37918",
    "sg:province":"TN",
    "sg:tags":[
        "special",
        "contractor"
    ],
    "wof:name":"Bryants Seal Coating Striping",
    "wof:placetype":"venue"
},
  "geometry": {"coordinates":[-83.940652,36.049436],"type":"Point"}
}