{
  "type": "Feature",
  "properties": {
    "iso:country":"US",
    "sg:address":"356 Chickasaw Land Cove",
    "sg:city":"Collierville",
    "sg:classifiers":[
        {
            "category":"Manufacturing",
            "subcategory":"Printing",
            "type":"Manufacturing & Wholesale Goods"
        }
    ],
    "sg:phone":"+1 901 850 5900",
    "sg:postcode":"38017",
    "sg:province":"TN",
    "sg:tags":[
        "poster"
    ],
    "sg:website":"www.yourcustomposter.com",
    "wof:name":"Express Digital Images",
    "wof:placetype":"venue"
},
  "geometry": {"coordinates":[-89.681473,35.006909],"type":"Point"}
}