{
  "type": "Feature",
  "properties": {
    "addr:full":"31 Edenwold Rd Madison TN 37115",
    "addr:housenumber":"31",
    "addr:postcode":"37115",
    "addr:street":"Edenwold Rd",
    "iso:country":"US",
    "sg:address":"31 Edenwold Rd",
    "sg:city":"Madison",
    "sg:classifiers":[
        {
            "category":"Manufacturing",
            "subcategory":"Food",
            "type":"Manufacturing & Wholesale Goods"
        }
    ],
    "sg:phone":"+1 615 868 6923",
    "sg:postcode":"37115",
    "sg:province":"TN",
    "sg:tags":[
        "product",
        "petroleum",
        "mfg"
    ],
    "wof:name":"Griffin Industries-Kentucky",
    "wof:placetype":"venue"
},
  "geometry": {"coordinates":[-86.693708,36.288698],"type":"Point"}
}