{
  "type": "Feature",
  "properties": {
    "addr:full":"100 Briar Creek Rd Williamsburg TN 40769",
    "addr:housenumber":"100",
    "addr:postcode":"40769",
    "addr:street":"Briar Creek Rd",
    "iso:country":"US",
    "sg:address":"100 Briar Creek Rd",
    "sg:city":"Williamsburg",
    "sg:classifiers":[
        {
            "category":"Government",
            "subcategory":"Office",
            "type":"Public Place"
        }
    ],
    "sg:phone":"+1 606 549 3047",
    "sg:postcode":"40769",
    "sg:province":"TN",
    "sg:tags":[
        "county"
    ],
    "wof:name":"Whitley County Conservation",
    "wof:placetype":"venue"
},
  "geometry": {"coordinates":[-84.207251,36.706663],"type":"Point"}
}