{
  "type": "Feature",
  "properties": {
    "iso:country":"US",
    "sg:address":"6064 New Nashville Hwy",
    "sg:city":"Murfreesboro",
    "sg:classifiers":[
        {
            "category":"Retail",
            "subcategory":"Auto Repair",
            "type":"Services"
        }
    ],
    "sg:phone":"+1 615 896 7297",
    "sg:postcode":"37129",
    "sg:province":"TN",
    "sg:tags":[
        "muffler",
        "exhaust",
        "system"
    ],
    "wof:name":"Ray's Custom Exhaust Shop",
    "wof:placetype":"venue"
},
  "geometry": {"coordinates":[-86.471115,35.927834],"type":"Point"}
}