{
  "type": "Feature",
  "properties": {
    "iso:country":"US",
    "sg:address":"110 W Gage Ave",
    "sg:city":"Memphis",
    "sg:classifiers":[
        {
            "category":"Real Estate",
            "subcategory":"Real Estate Services",
            "type":"Services"
        },
        {
            "category":"Real Estate",
            "subcategory":"Real Estate Agent",
            "type":"Services"
        }
    ],
    "sg:phone":"+1 901 942 5683",
    "sg:postcode":"38109",
    "sg:province":"TN",
    "sg:tags":[
        "management"
    ],
    "wof:name":"Ncgowan & Shays Real Estate",
    "wof:placetype":"venue"
},
  "geometry": {"coordinates":[-90.065966,35.087709],"type":"Point"}
}