{
  "type": "Feature",
  "properties": {
    "iso:country":"US",
    "sg:address":"2361 Ketchum Rd",
    "sg:city":"Memphis",
    "sg:classifiers":[
        {
            "category":"Food & Beverages",
            "subcategory":"Groceries & Convenience Stores",
            "type":"Retail Goods"
        }
    ],
    "sg:phone":"+1 901 743 1145",
    "sg:postcode":"38114",
    "sg:province":"TN",
    "wof:name":"KWIK-Chek Food Store",
    "wof:placetype":"venue"
},
  "geometry": {"coordinates":[-89.984009,35.07928],"type":"Point"}
}