{
  "type": "Feature",
  "properties": {
    "iso:country":"US",
    "sg:address":"1105 Temple St",
    "sg:city":"Greeneville",
    "sg:classifiers":[
        {
            "category":"Home & Garden",
            "subcategory":"Household Appliances",
            "type":"Retail Goods"
        }
    ],
    "sg:phone":"+1 423 638 2864",
    "sg:postcode":"37745",
    "sg:province":"TN",
    "sg:tags":[
        "cleaning",
        "vacuum"
    ],
    "wof:name":"Filter Queen",
    "wof:placetype":"venue"
},
  "geometry": {"coordinates":[-82.805819,36.168904],"type":"Point"}
}