{
  "type": "Feature",
  "properties": {
    "addr:full":"2637 Decherd Blvd Winchester TN 37398",
    "addr:housenumber":"2637",
    "addr:postcode":"37398",
    "addr:street":"Decherd Blvd",
    "iso:country":"US",
    "sg:address":"2637 Decherd Blvd",
    "sg:city":"Winchester",
    "sg:classifiers":[
        {
            "category":"Food & Beverages",
            "subcategory":"Specialty",
            "type":"Retail Goods"
        }
    ],
    "sg:phone":"+1 931 962 4462",
    "sg:postcode":"37398",
    "sg:province":"TN",
    "wof:name":"GNC",
    "wof:placetype":"venue"
},
  "geometry": {"coordinates":[-86.10289400000001,35.221925],"type":"Point"}
}