{
  "type": "Feature",
  "properties": {
    "iso:country":"US",
    "sg:address":"107 Ashley Dr",
    "sg:city":"Goodlettsville",
    "sg:classifiers":[
        {
            "category":"Building & Trades",
            "subcategory":"Plumbing",
            "type":"Services"
        }
    ],
    "sg:phone":"+1 615 400 3168",
    "sg:postcode":"37072",
    "sg:province":"TN",
    "sg:tags":[
        "contractor"
    ],
    "wof:name":"Celsius LLC",
    "wof:placetype":"venue"
},
  "geometry": {"coordinates":[-86.694314,36.326596],"type":"Point"}
}