{
  "type": "Feature",
  "properties": {
    "iso:country":"US",
    "sg:address":"163 Medina Hwy",
    "sg:city":"Humboldt",
    "sg:classifiers":[
        {
            "category":"Retail",
            "subcategory":"Portrait Studio",
            "type":"Services"
        }
    ],
    "sg:phone":"+1 731 784 7422",
    "sg:postcode":"38343",
    "sg:province":"TN",
    "sg:tags":[
        "photo"
    ],
    "wof:name":"Fisher Photography",
    "wof:placetype":"venue"
},
  "geometry": {"coordinates":[-88.865618,35.814324],"type":"Point"}
}