{
  "type": "Feature",
  "properties": {
    "iso:country":"US",
    "sg:address":"8115 E Brainerd Rd",
    "sg:city":"Chattanooga",
    "sg:classifiers":[
        {
            "category":"Wholesale",
            "subcategory":"Poultry",
            "type":"Manufacturing & Wholesale Goods"
        }
    ],
    "sg:phone":"+1 423 664 2449",
    "sg:postcode":"37421",
    "sg:province":"TN",
    "wof:name":"Lawrence Wholesale",
    "wof:placetype":"venue"
},
  "geometry": {"coordinates":[-85.14944,35.004024],"type":"Point"}
}