{
  "type": "Feature",
  "properties": {
    "addr:full":"216 W Market St Somerville TN 38068",
    "addr:housenumber":"216",
    "addr:postcode":"38068",
    "addr:street":"W Market St",
    "iso:country":"US",
    "sg:address":"216 W Market St",
    "sg:city":"Somerville",
    "sg:classifiers":[
        {
            "category":"Education",
            "subcategory":"Library",
            "type":"Public Place"
        }
    ],
    "sg:phone":"+1 901 465 5248",
    "sg:postcode":"38068",
    "sg:province":"TN",
    "wof:name":"Somerville Fayette County Lib",
    "wof:placetype":"venue"
},
  "geometry": {"coordinates":[-89.35148100000001,35.244426],"type":"Point"}
}