{
  "type": "Feature",
  "properties": {
    "iso:country":"US",
    "sg:address":"560 Sims Springs Rd",
    "sg:city":"Lewisburg",
    "sg:classifiers":[
        {
            "category":"Professional",
            "type":"Services"
        }
    ],
    "sg:phone":"+1 931 684 2482",
    "sg:postcode":"37091",
    "sg:province":"TN",
    "wof:name":"Christy Warner",
    "wof:placetype":"venue"
},
  "geometry": {"coordinates":[-86.62294199999999,35.513304],"type":"Point"}
}