{
  "type": "Feature",
  "properties": {
    "addr:full":"1508 Gallatin Ave Nashville TN 37206",
    "addr:housenumber":"1508",
    "addr:postcode":"37206",
    "addr:street":"Gallatin Ave",
    "iso:country":"US",
    "sg:address":"1508 Gallatin Ave",
    "sg:city":"Nashville",
    "sg:classifiers":[
        {
            "category":"Retail",
            "subcategory":"Portrait Studio",
            "type":"Services"
        }
    ],
    "sg:phone":"+1 615 870 1289",
    "sg:postcode":"37206",
    "sg:province":"TN",
    "sg:tags":[
        "photographer"
    ],
    "wof:name":"Olan Mills Portrait Studio",
    "wof:placetype":"venue"
},
  "geometry": {"coordinates":[-86.743263,36.194942],"type":"Point"}
}