{
  "type": "Feature",
  "properties": {
    "iso:country":"US",
    "sg:address":"1109 Almaville Rd",
    "sg:city":"Smyrna",
    "sg:classifiers":[
        {
            "category":"Building & Trades",
            "subcategory":"Construction",
            "type":"Services"
        }
    ],
    "sg:phone":"+1 615 223 0917",
    "sg:postcode":"37167",
    "sg:province":"TN",
    "sg:tags":[
        "house"
    ],
    "wof:name":"J D H Interiors",
    "wof:placetype":"venue"
},
  "geometry": {"coordinates":[-86.57114900000001,35.884061],"type":"Point"}
}