{
  "type": "Feature",
  "properties": {
    "iso:country":"US",
    "sg:address":"6586 Burkitt Rd",
    "sg:city":"Antioch",
    "sg:classifiers":[
        {
            "category":"Building & Trades",
            "subcategory":"Electrical",
            "type":"Services"
        }
    ],
    "sg:phone":"+1 615 941 1615",
    "sg:postcode":"37013",
    "sg:province":"TN",
    "sg:tags":[
        "electric",
        "contractor"
    ],
    "wof:name":"Mc Clanahan Electric",
    "wof:placetype":"venue"
},
  "geometry": {"coordinates":[-86.638806,35.990042],"type":"Point"}
}