{
  "type": "Feature",
  "properties": {
    "iso:country":"US",
    "sg:address":"5590 S York Hwy",
    "sg:city":"Grimsley",
    "sg:classifiers":[
        {
            "category":"Shopping",
            "subcategory":"Bicycles & Sporting Goods",
            "type":"Retail Goods"
        }
    ],
    "sg:phone":"+1 931 863 4991",
    "sg:postcode":"38553",
    "sg:province":"TN",
    "wof:name":"Cumberland Paintball Sports",
    "wof:placetype":"venue"
},
  "geometry": {"coordinates":[-84.99787999999999,36.248283],"type":"Point"}
}