{
  "type": "Feature",
  "properties": {
    "addr:full":"9417 Bennie Ln Ooltewah TN 37363",
    "addr:housenumber":"9417",
    "addr:postcode":"37363",
    "addr:street":"Bennie Ln",
    "iso:country":"US",
    "sg:address":"9417 Bennie Ln",
    "sg:city":"Ooltewah",
    "sg:classifiers":[
        {
            "category":"Shopping",
            "subcategory":"Bicycles & Sporting Goods",
            "type":"Retail Goods"
        }
    ],
    "sg:phone":"+1 423 892 8306",
    "sg:postcode":"37363",
    "sg:province":"TN",
    "sg:tags":[
        "equipment",
        "playground"
    ],
    "wof:name":"Backyard Playground",
    "wof:placetype":"venue"
},
  "geometry": {"coordinates":[-85.08472399999999,35.04218],"type":"Point"}
}