{
  "type": "Feature",
  "properties": {
    "iso:country":"US",
    "sg:address":"8957 Grey Mountain Dr",
    "sg:city":"Ooltewah",
    "sg:classifiers":[
        {
            "category":"Professional",
            "subcategory":"Accounting & Tax Preparation",
            "type":"Services"
        }
    ],
    "sg:phone":"+1 423 396 9996",
    "sg:postcode":"37363",
    "sg:province":"TN",
    "sg:tags":[
        "accountant",
        "public",
        "accountants-certified"
    ],
    "wof:name":"William P Elliott Cpa Pc",
    "wof:placetype":"venue"
},
  "geometry": {"coordinates":[-85.028351,35.069884],"type":"Point"}
}