{
  "type": "Feature",
  "properties": {
    "addr:full":"146 Stoddert St Jackson TN 38301",
    "addr:housenumber":"146",
    "addr:postcode":"38301",
    "addr:street":"Stoddert St",
    "iso:country":"US",
    "sg:address":"146 Stoddert St",
    "sg:city":"Jackson",
    "sg:classifiers":[
        {
            "category":"Organizations",
            "subcategory":"Religious Organization",
            "type":"Services"
        }
    ],
    "sg:phone":"+1 731 423 5418",
    "sg:postcode":"38301",
    "sg:province":"TN",
    "wof:name":"Pentecstal Church Jesus Christ",
    "wof:placetype":"venue"
},
  "geometry": {"coordinates":[-88.809924,35.617221],"type":"Point"}
}