{
  "type": "Feature",
  "properties": {
    "addr:full":"11402 Hardin Valley Rd Knoxville TN 37932",
    "addr:housenumber":"11402",
    "addr:postcode":"37932",
    "addr:street":"Hardin Valley Rd",
    "iso:country":"US",
    "sg:address":"11402 Hardin Valley Rd",
    "sg:city":"Knoxville",
    "sg:classifiers":[
        {
            "category":"Organizations",
            "subcategory":"Religious Organization",
            "type":"Services"
        }
    ],
    "sg:phone":"+1 865 693 0080",
    "sg:postcode":"37932",
    "sg:province":"TN",
    "wof:name":"Marietta Cmbrland Prsbt Church",
    "wof:placetype":"venue"
},
  "geometry": {"coordinates":[-84.180933,35.933192],"type":"Point"}
}