{
  "type": "Feature",
  "properties": {
    "iso:country":"US",
    "sg:address":"10915 Hardin Valley Rd",
    "sg:city":"Knoxville",
    "sg:classifiers":[
        {
            "category":"Education",
            "subcategory":"Special Training",
            "type":"Public Place"
        }
    ],
    "sg:phone":"+1 865 694 6752",
    "sg:postcode":"37932",
    "sg:province":"TN",
    "sg:tags":[
        "tutoring"
    ],
    "wof:name":"GED Testing",
    "wof:placetype":"venue"
},
  "geometry": {"coordinates":[-84.161542,35.946232],"type":"Point"}
}