{
  "type": "Feature",
  "properties": {
    "addr:full":"405 Monroe Ave Memphis TN 38103",
    "addr:housenumber":"405",
    "addr:postcode":"38103",
    "addr:street":"Monroe Ave",
    "iso:country":"US",
    "sg:address":"405 Monroe Ave",
    "sg:city":"Memphis",
    "sg:classifiers":[
        {
            "category":"Retail",
            "subcategory":"Auto Repair",
            "type":"Services"
        }
    ],
    "sg:phone":"+1 901 527 6000",
    "sg:postcode":"38103",
    "sg:province":"TN",
    "sg:tags":[
        "body",
        "painting",
        "repairing",
        "automobile"
    ],
    "wof:name":"Gilbert Buddy Auto Center",
    "wof:placetype":"venue"
},
  "geometry": {"coordinates":[-90.043437,35.141592],"type":"Point"}
}