{
  "type": "Feature",
  "properties": {
    "addr:full":"188 Vann Dr Jackson TN 38305",
    "addr:housenumber":"188",
    "addr:postcode":"38305",
    "addr:street":"Vann Dr",
    "iso:country":"US",
    "sg:address":"188 Vann Dr",
    "sg:city":"Jackson",
    "sg:classifiers":[
        {
            "category":"Bars & Pubs",
            "type":"Food & Drink"
        },
        {
            "category":"Restaurant",
            "type":"Food & Drink"
        }
    ],
    "sg:menulink":"http://www.allmenus.com/tn/jackson/34483-cracker-barrel-old-country-store/menu/",
    "sg:phone":"+1 731 664 1028",
    "sg:postcode":"38305",
    "sg:province":"TN",
    "sg:tags":[
        "american",
        "southern"
    ],
    "wof:name":"Cracker Barrel Old Country Store",
    "wof:placetype":"venue"
},
  "geometry": {"coordinates":[-88.834982,35.6712],"type":"Point"}
}