{
  "type": "Feature",
  "properties": {
    "iso:country":"US",
    "sg:address":"5169 Holloway Rd",
    "sg:city":"Union City",
    "sg:classifiers":[
        {
            "category":"Manufacturing",
            "subcategory":"Lumber",
            "type":"Manufacturing & Wholesale Goods"
        }
    ],
    "sg:phone":"+1 731 538 2469",
    "sg:postcode":"38261",
    "sg:province":"TN",
    "sg:tags":[
        "sawmill"
    ],
    "wof:name":"Roberson Brothers Sawmill Inc",
    "wof:placetype":"venue"
},
  "geometry": {"coordinates":[-89.282906,36.475064],"type":"Point"}
}