{
  "type": "Feature",
  "properties": {
    "iso:country":"US",
    "sg:address":"9452 US Hwy 641 N",
    "sg:city":"Puryear",
    "sg:classifiers":[
        {
            "category":"Freight",
            "type":"Transportation"
        }
    ],
    "sg:phone":"+1 731 247 5871",
    "sg:postcode":"38251",
    "sg:province":"TN",
    "sg:tags":[
        "trucking"
    ],
    "wof:name":"Pittman Trucking Co",
    "wof:placetype":"venue"
},
  "geometry": {"coordinates":[-88.33247799999999,36.437537],"type":"Point"}
}