{
  "type": "Feature",
  "properties": {
    "iso:country":"US",
    "sg:address":"4727 Brainerd Rd",
    "sg:city":"Chattanooga",
    "sg:classifiers":[
        {
            "category":"Health Services",
            "subcategory":"Doctor",
            "type":"Services"
        }
    ],
    "sg:phone":"+1 423 624 8217",
    "sg:postcode":"37411",
    "sg:province":"TN",
    "sg:tags":[
        "dentist"
    ],
    "wof:name":"Stephen M Sawrie DDS",
    "wof:placetype":"venue"
},
  "geometry": {"coordinates":[-85.22994300000001,35.013761],"type":"Point"}
}