{
  "type": "Feature",
  "properties": {
    "addr:full":"3391 Castleman St Memphis TN 38118",
    "addr:housenumber":"3391",
    "addr:postcode":"38118",
    "addr:street":"Castleman St",
    "iso:country":"US",
    "sg:address":"3391 Castleman St",
    "sg:city":"Memphis",
    "sg:classifiers":[
        {
            "category":"Recreation",
            "type":"Entertainment"
        }
    ],
    "sg:phone":"+1 901 794 5045",
    "sg:postcode":"38118",
    "sg:province":"TN",
    "sg:tags":[
        "tennis",
        "court"
    ],
    "wof:name":"Wooddale Tennis Ctr",
    "wof:placetype":"venue"
},
  "geometry": {"coordinates":[-89.890827,35.05671],"type":"Point"}
}