{
  "type": "Feature",
  "properties": {
    "iso:country":"US",
    "sg:address":"212 E Cedar St",
    "sg:city":"Goodlettsville",
    "sg:classifiers":[
        {
            "category":"Manufacturing",
            "subcategory":"Metals",
            "type":"Manufacturing & Wholesale Goods"
        }
    ],
    "sg:phone":"+1 615 790 6580",
    "sg:postcode":"37072",
    "sg:province":"TN",
    "sg:tags":[
        "caster",
        "glide"
    ],
    "wof:name":"Casters Corp",
    "wof:placetype":"venue"
},
  "geometry": {"coordinates":[-86.70917,36.324274],"type":"Point"}
}