{
  "type": "Feature",
  "properties": {
    "addr:full":"306 S Bellevue Blvd Memphis TN 38104",
    "addr:housenumber":"306",
    "addr:postcode":"38104",
    "addr:street":"S Bellevue Blvd",
    "iso:country":"US",
    "sg:address":"306 S Bellevue Blvd",
    "sg:city":"Memphis",
    "sg:classifiers":[
        {
            "category":"Education",
            "subcategory":"School",
            "type":"Public Place"
        }
    ],
    "sg:phone":"+1 901 722 4500",
    "sg:postcode":"38104",
    "sg:province":"TN",
    "sg:tags":[
        "executive"
    ],
    "wof:name":"Central High School",
    "wof:placetype":"venue"
},
  "geometry": {"coordinates":[-90.02069,35.13441],"type":"Point"}
}