{
  "type": "Feature",
  "properties": {
    "iso:country":"US",
    "sg:address":"601 Sherwood Dr",
    "sg:city":"Union City",
    "sg:classifiers":[
        {
            "category":"Shopping",
            "subcategory":"Shoes",
            "type":"Retail Goods"
        }
    ],
    "sg:phone":"+1 731 885 5885",
    "sg:postcode":"38261",
    "sg:province":"TN",
    "wof:name":"Bass Shoe Factory Outlet",
    "wof:placetype":"venue"
},
  "geometry": {"coordinates":[-89.050468,36.443132],"type":"Point"}
}