{
  "type": "Feature",
  "properties": {
    "iso:country":"US",
    "sg:address":"1584 Galloway Ave",
    "sg:city":"Memphis",
    "sg:classifiers":[
        {
            "category":"Professional",
            "subcategory":"Art Services",
            "type":"Services"
        }
    ],
    "sg:phone":"+1 901 272 3548",
    "sg:postcode":"38112",
    "sg:province":"TN",
    "sg:tags":[
        "photography",
        "videography",
        "photographers-portrait"
    ],
    "wof:name":"Jay Adkins Photography",
    "wof:placetype":"venue"
},
  "geometry": {"coordinates":[-90.00626,35.151182],"type":"Point"}
}