{
  "type": "Feature",
  "properties": {
    "iso:country":"US",
    "sg:address":"301 Ducktown Rd",
    "sg:city":"Limestone",
    "sg:classifiers":[
        {
            "category":"Farming",
            "subcategory":"Farm",
            "type":"Manufacturing & Wholesale Goods"
        }
    ],
    "sg:phone":"+1 423 753 6891",
    "sg:postcode":"37681",
    "sg:province":"TN",
    "sg:tags":[
        "crop",
        "general"
    ],
    "wof:name":"Fanny Slagle",
    "wof:placetype":"venue"
},
  "geometry": {"coordinates":[-82.63194799999999,36.332135],"type":"Point"}
}