{
  "type": "Feature",
  "properties": {
    "addr:full":"1005 Dr D B Todd Jr Blvd Nashville TN 37208",
    "addr:housenumber":"1005",
    "addr:postcode":"37208",
    "addr:street":"Dr D;Jr Blvd",
    "iso:country":"US",
    "sg:address":"1005 Dr D B Todd Jr Blvd",
    "sg:city":"Nashville",
    "sg:classifiers":[
        {
            "category":"Health Services",
            "subcategory":"Doctor",
            "type":"Services"
        }
    ],
    "sg:phone":"+1 615 327 5531",
    "sg:postcode":"37208",
    "sg:province":"TN",
    "sg:tags":[
        "physician",
        "surgeon"
    ],
    "wof:name":"Susan L Gillespie MD",
    "wof:placetype":"venue"
},
  "geometry": {"coordinates":[-86.805662,36.166952],"type":"Point"}
}