{
  "type": "Feature",
  "properties": {
    "iso:country":"US",
    "sg:address":"1414 Edgehill Ave",
    "sg:city":"Nashville",
    "sg:classifiers":[
        {
            "category":"Education",
            "subcategory":"Special Training",
            "type":"Public Place"
        }
    ],
    "sg:phone":"+1 615 255 8355",
    "sg:postcode":"37212",
    "sg:province":"TN",
    "sg:tags":[
        "instruction",
        "music"
    ],
    "wof:name":"W O Smith Music School",
    "wof:placetype":"venue"
},
  "geometry": {"coordinates":[-86.79055,36.143143],"type":"Point"}
}