{
  "type": "Feature",
  "properties": {
    "addr:full":"908 Old McGinley Dr Maryville TN 37803",
    "addr:housenumber":"908",
    "addr:postcode":"37803",
    "addr:street":"Old Mcginley Dr",
    "iso:country":"US",
    "sg:address":"908 Old McGinley Dr",
    "sg:city":"Maryville",
    "sg:classifiers":[
        {
            "category":"Retail",
            "subcategory":"Car Wash",
            "type":"Services"
        }
    ],
    "sg:phone":"+1 865 680 2026",
    "sg:postcode":"37803",
    "sg:province":"TN",
    "sg:tags":[
        "automobile",
        "detail",
        "clean"
    ],
    "wof:name":"Vickie's Detailing Svc",
    "wof:placetype":"venue"
},
  "geometry": {"coordinates":[-83.90915099999999,35.731881],"type":"Point"}
}