{
  "type": "Feature",
  "properties": {
    "addr:full":"2033 Lafayette Rd Red Boiling Spgs TN 37150",
    "addr:housenumber":"2033",
    "addr:postcode":"37150",
    "iso:country":"US",
    "sg:address":"2033 Lafayette Rd",
    "sg:city":"Red Boiling Spgs",
    "sg:classifiers":[
        {
            "category":"Personal",
            "subcategory":"Beauty Salon",
            "type":"Services"
        }
    ],
    "sg:phone":"+1 615 699 4101",
    "sg:postcode":"37150",
    "sg:province":"TN",
    "wof:name":"New Designs Hair Salon",
    "wof:placetype":"venue"
},
  "geometry": {"coordinates":[-85.88386199999999,36.522444],"type":"Point"}
}