{
  "type": "Feature",
  "properties": {
    "iso:country":"US",
    "sg:address":"4011 Kellys Ferry Rd",
    "sg:city":"Chattanooga",
    "sg:classifiers":[
        {
            "category":"Professional",
            "type":"Services"
        }
    ],
    "sg:phone":"+1 423 825 1529",
    "sg:postcode":"37419",
    "sg:province":"TN",
    "wof:name":"C&Rss Co",
    "wof:placetype":"venue"
},
  "geometry": {"coordinates":[-85.388734,35.024785],"type":"Point"}
}