{
  "type": "Feature",
  "properties": {
    "iso:country":"US",
    "sg:address":"3201 Kinross Ave",
    "sg:city":"Nashville",
    "sg:classifiers":[
        {
            "category":"Manufacturing",
            "subcategory":"Apparel",
            "type":"Manufacturing & Wholesale Goods"
        }
    ],
    "sg:phone":"+1 615 331 9157",
    "sg:postcode":"37211",
    "sg:province":"TN",
    "sg:tags":[
        "trouser",
        "mfg"
    ],
    "wof:name":"Just Boys",
    "wof:placetype":"venue"
},
  "geometry": {"coordinates":[-86.73358899999999,36.103077],"type":"Point"}
}