{
  "type": "Feature",
  "properties": {
    "iso:country":"US",
    "sg:address":"971 Pineville Rd",
    "sg:city":"Chattanooga",
    "sg:classifiers":[
        {
            "category":"Wholesale",
            "subcategory":"Machinery & Supplies",
            "type":"Manufacturing & Wholesale Goods"
        }
    ],
    "sg:phone":"+1 423 267 9223",
    "sg:postcode":"37405",
    "sg:province":"TN",
    "sg:tags":[
        "equipment",
        "industrial"
    ],
    "wof:name":"OEM Products",
    "wof:placetype":"venue"
},
  "geometry": {"coordinates":[-85.32953999999999,35.072137],"type":"Point"}
}