{
  "type": "Feature",
  "properties": {
    "addr:full":"21 Covington St Clarksville TN 37040",
    "addr:housenumber":"21",
    "addr:postcode":"37040",
    "addr:street":"Covington St",
    "iso:country":"US",
    "sg:address":"21 Covington St",
    "sg:city":"Clarksville",
    "sg:classifiers":[
        {
            "category":"Retail",
            "subcategory":"Repair Shop",
            "type":"Services"
        }
    ],
    "sg:phone":"+1 931 647 2088",
    "sg:postcode":"37040",
    "sg:province":"TN",
    "sg:tags":[
        "taxidermist"
    ],
    "wof:name":"B & J Mounting Svc",
    "wof:placetype":"venue"
},
  "geometry": {"coordinates":[-87.317077,36.563458],"type":"Point"}
}