{
  "type": "Feature",
  "properties": {
    "addr:full":"1169 Duncan Rd Manchester TN 37355",
    "addr:housenumber":"1169",
    "addr:postcode":"37355",
    "addr:street":"Duncan Rd",
    "iso:country":"US",
    "sg:address":"1169 Duncan Rd",
    "sg:city":"Manchester",
    "sg:phone":"+1 931 728 5408",
    "sg:postcode":"37355",
    "sg:province":"TN",
    "sg:tags":[
        "farm",
        "corn",
        "soybean"
    ],
    "wof:name":"Kelly Duncan",
    "wof:placetype":"venue"
},
  "geometry": {"coordinates":[-86.091165,35.595884],"type":"Point"}
}