{
  "type": "Feature",
  "properties": {
    "iso:country":"US",
    "sg:address":"1 Poplar St",
    "sg:city":"Munford",
    "sg:classifiers":[
        {
            "category":"Social Services",
            "type":"Services"
        }
    ],
    "sg:phone":"+1 901 837 9876",
    "sg:postcode":"38030",
    "sg:province":"TN",
    "sg:tags":[
        "youth",
        "organization",
        "center"
    ],
    "wof:name":"Munford Youth Sports",
    "wof:placetype":"venue"
},
  "geometry": {"coordinates":[-89.48199099999999,36.035685],"type":"Point"}
}