{
  "type": "Feature",
  "properties": {
    "iso:country":"US",
    "sg:address":"2801 Wilma Rudolph Blvd",
    "sg:city":"Clarksville",
    "sg:classifiers":[
        {
            "category":"Insurance",
            "subcategory":"Insurance Agent",
            "type":"Services"
        }
    ],
    "sg:phone":"+1 931 542 0310",
    "sg:postcode":"37040",
    "sg:province":"TN",
    "wof:name":"Military Benefit Assn",
    "wof:placetype":"venue"
},
  "geometry": {"coordinates":[-87.293587,36.588066],"type":"Point"}
}