{
  "type": "Feature",
  "properties": {
    "iso:country":"US",
    "sg:address":"1401 E 14th St",
    "sg:city":"Chattanooga",
    "sg:classifiers":[
        {
            "category":"Manufacturing",
            "subcategory":"Tools & Machinery",
            "type":"Manufacturing & Wholesale Goods"
        }
    ],
    "sg:phone":"+1 423 622 2685",
    "sg:postcode":"37404",
    "sg:province":"TN",
    "sg:tags":[
        "machine",
        "mfg"
    ],
    "wof:name":"Coin Wrap Inc",
    "wof:placetype":"venue"
},
  "geometry": {"coordinates":[-85.286361,35.029413],"type":"Point"}
}