{
  "type": "Feature",
  "properties": {
    "addr:full":"4081 Riverdale Rd Ste 103 Memphis TN 38115",
    "addr:housenumber":"4081",
    "addr:postcode":"38115",
    "addr:street":"Riverdale Rd Ste 103",
    "iso:country":"US",
    "sg:address":"4081 Riverdale Rd Ste 103",
    "sg:city":"Memphis",
    "sg:classifiers":[
        {
            "category":"Insurance",
            "subcategory":"Hazard Insurance",
            "type":"Services"
        },
        {
            "category":"Insurance",
            "subcategory":"Insurance Agent",
            "type":"Services"
        },
        {
            "category":"Insurance",
            "subcategory":"Life Insurance",
            "type":"Services"
        },
        {
            "category":"Insurance",
            "subcategory":"Title Insurance",
            "type":"Services"
        }
    ],
    "sg:phone":"+1 901 794 0706",
    "sg:postcode":"38115",
    "sg:province":"TN",
    "sg:tags":[
        "auto",
        "homeowner"
    ],
    "sg:website":"http://www.nationwide.com/agent/Memphis-TENNESSEE-insurance-agent/stacey-collins/office.html",
    "wof:name":"Stacey D Collins - Nationwide Insurance",
    "wof:placetype":"venue"
},
  "geometry": {"coordinates":[-89.831413,35.036348],"type":"Point"}
}