{
  "type": "Feature",
  "properties": {
    "iso:country":"US",
    "sg:address":"4777 Andrew Jackson Pkwy",
    "sg:city":"Hermitage",
    "sg:classifiers":[
        {
            "category":"Health Services",
            "subcategory":"Doctor",
            "type":"Services"
        }
    ],
    "sg:phone":"+1 615 883 2331",
    "sg:postcode":"37076",
    "sg:province":"TN",
    "sg:tags":[
        "physician",
        "surgeon"
    ],
    "wof:name":"Columbia Physician Svc",
    "wof:placetype":"venue"
},
  "geometry": {"coordinates":[-86.597488,36.221382],"type":"Point"}
}