{
  "type": "Feature",
  "properties": {
    "addr:full":"531 Henley St Knoxville TN 37902",
    "addr:housenumber":"531",
    "addr:postcode":"37902",
    "addr:street":"Henley St",
    "iso:country":"US",
    "sg:address":"531 Henley St",
    "sg:city":"Knoxville",
    "sg:classifiers":[
        {
            "category":"Social Services",
            "type":"Services"
        }
    ],
    "sg:phone":"+1 865 594 6054",
    "sg:postcode":"37902",
    "sg:province":"TN",
    "wof:name":"Rehabilitation Services",
    "wof:placetype":"venue"
},
  "geometry": {"coordinates":[-83.92251,35.963225],"type":"Point"}
}