{
  "type": "Feature",
  "properties": {
    "iso:country":"US",
    "sg:address":"5959 Shallowford Rd",
    "sg:city":"Chattanooga",
    "sg:classifiers":[
        {
            "category":"Wholesale",
            "subcategory":"Hardware",
            "type":"Manufacturing & Wholesale Goods"
        }
    ],
    "sg:phone":"+1 423 553 8854",
    "sg:postcode":"37421",
    "sg:province":"TN",
    "sg:tags":[
        "hardware-wholesale",
        "manufacturer"
    ],
    "sg:website":"http://www.hydraulic-supply.com",
    "wof:name":"Aero Hardware",
    "wof:placetype":"venue"
},
  "geometry": {"coordinates":[-85.19376699999999,35.054679],"type":"Point"}
}