{
  "type": "Feature",
  "properties": {
    "iso:country":"US",
    "sg:address":"607 S Cannon Blvd",
    "sg:city":"Shelbyville",
    "sg:classifiers":[
        {
            "category":"Autos & Motor Vehicles",
            "subcategory":"Fuel & Gas Station",
            "type":"Retail Goods"
        }
    ],
    "sg:phone":"+1 931 684 1174",
    "sg:postcode":"37160",
    "sg:province":"TN",
    "sg:tags":[
        "oil"
    ],
    "wof:name":"Boyce Phillips 66",
    "wof:placetype":"venue"
},
  "geometry": {"coordinates":[-86.465592,35.476463],"type":"Point"}
}