{
  "type": "Feature",
  "properties": {
    "iso:country":"US",
    "sg:address":"1106 Crossing Way",
    "sg:city":"Cleveland",
    "sg:classifiers":[
        {
            "category":"Organizations",
            "subcategory":"Religious Organization",
            "type":"Services"
        }
    ],
    "sg:phone":"+1 423 472 8103",
    "sg:postcode":"37312",
    "sg:province":"TN",
    "wof:name":"Pine Hill Church of God",
    "wof:placetype":"venue"
},
  "geometry": {"coordinates":[-84.87074200000001,35.222729],"type":"Point"}
}