{
  "type": "Feature",
  "properties": {
    "addr:full":"1705 S Highland Ave Jackson TN 38301",
    "addr:housenumber":"1705",
    "addr:postcode":"38301",
    "addr:street":"S Highland Ave",
    "iso:country":"US",
    "sg:address":"1705 S Highland Ave",
    "sg:city":"Jackson",
    "sg:classifiers":[
        {
            "category":"Restaurant",
            "type":"Food & Drink"
        }
    ],
    "sg:menulink":"http://www.allmenus.com/tn/jackson/85665-dominos-pizza/menu/",
    "sg:phone":"+1 731 935 2425",
    "sg:postcode":"38301",
    "sg:province":"TN",
    "sg:tags":[
        "american",
        "wing",
        "pizza"
    ],
    "wof:name":"Domino's Pizza",
    "wof:placetype":"venue"
},
  "geometry": {"coordinates":[-88.814874,35.563379],"type":"Point"}
}