{
  "type": "Feature",
  "properties": {
    "addr:full":"2614 Hillsboro Rd Brentwood TN 37027",
    "addr:housenumber":"2614",
    "addr:postcode":"37027",
    "addr:street":"Hillsboro Rd",
    "iso:country":"US",
    "sg:address":"2614 Hillsboro Rd",
    "sg:city":"Brentwood",
    "sg:classifiers":[
        {
            "category":"Health Services",
            "subcategory":"Clinic",
            "type":"Services"
        }
    ],
    "sg:phone":"+1 615 383 6272",
    "sg:postcode":"37027",
    "sg:province":"TN",
    "wof:name":"Maxim Healthcare Svc Inc",
    "wof:placetype":"venue"
},
  "geometry": {"coordinates":[-86.888238,36.016872],"type":"Point"}
}