{
  "type": "Feature",
  "properties": {
    "iso:country":"US",
    "sg:address":"300 N Fairmont Ave",
    "sg:city":"Morristown",
    "sg:classifiers":[
        {
            "category":"Retail",
            "subcategory":"Self-service Laundry",
            "type":"Services"
        }
    ],
    "sg:phone":"+1 423 581 8189",
    "sg:postcode":"37814",
    "sg:province":"TN",
    "sg:tags":[
        "coin"
    ],
    "wof:name":"Crescent Center Laundromat",
    "wof:placetype":"venue"
},
  "geometry": {"coordinates":[-83.308207,36.208372],"type":"Point"}
}