{
  "type": "Feature",
  "properties": {
    "addr:full":"811 Mount Vernon Ave Chattanooga TN 37405",
    "addr:housenumber":"811",
    "addr:postcode":"37405",
    "addr:street":"Mount Vernon Ave",
    "iso:country":"US",
    "sg:address":"811 Mount Vernon Ave",
    "sg:city":"Chattanooga",
    "sg:classifiers":[
        {
            "category":"Professional",
            "subcategory":"Art Services",
            "type":"Services"
        }
    ],
    "sg:phone":"+1 423 756 4290",
    "sg:postcode":"37405",
    "sg:province":"TN",
    "sg:tags":[
        "commercial",
        "graphic",
        "design"
    ],
    "wof:name":"T G Covers",
    "wof:placetype":"venue"
},
  "geometry": {"coordinates":[-85.297021,35.075788],"type":"Point"}
}