{
  "type": "Feature",
  "properties": {
    "addr:full":"1672 E Alcy Rd Memphis TN 38114",
    "addr:housenumber":"1672",
    "addr:postcode":"38114",
    "addr:street":"E Alcy Rd",
    "iso:country":"US",
    "sg:address":"1672 E Alcy Rd",
    "sg:city":"Memphis",
    "sg:classifiers":[
        {
            "category":"Food & Beverages",
            "subcategory":"Groceries & Convenience Stores",
            "type":"Retail Goods"
        }
    ],
    "sg:phone":"+1 901 942 9564",
    "sg:postcode":"38114",
    "sg:province":"TN",
    "sg:tags":[
        "grocer"
    ],
    "wof:name":"Alcy Market",
    "wof:placetype":"venue"
},
  "geometry": {"coordinates":[-90.00610500000001,35.077816],"type":"Point"}
}