{
  "type": "Feature",
  "properties": {
    "addr:full":"1225 Parkway Sevierville TN 37862",
    "addr:housenumber":"1225",
    "addr:postcode":"37862",
    "addr:street":"Parkway",
    "iso:country":"US",
    "sg:address":"1225 Parkway",
    "sg:city":"Sevierville",
    "sg:classifiers":[
        {
            "category":"Building & Trades",
            "subcategory":"Construction",
            "type":"Services"
        }
    ],
    "sg:phone":"+1 865 429 0721",
    "sg:postcode":"37862",
    "sg:province":"TN",
    "sg:tags":[
        "home",
        "builder"
    ],
    "wof:name":"C & B Construction",
    "wof:placetype":"venue"
},
  "geometry": {"coordinates":[-83.570357,35.845585],"type":"Point"}
}