{
  "type": "Feature",
  "properties": {
    "iso:country":"US",
    "sg:address":"2850 Austin Peay Hwy",
    "sg:city":"Memphis",
    "sg:classifiers":[
        {
            "category":"Home & Garden",
            "subcategory":"Furniture",
            "type":"Retail Goods"
        }
    ],
    "sg:phone":"+1 901 383 4676",
    "sg:postcode":"38128",
    "sg:province":"TN",
    "sg:tags":[
        "store"
    ],
    "wof:name":"Room To Room Furniture",
    "wof:placetype":"venue"
},
  "geometry": {"coordinates":[-89.92205800000001,35.203098],"type":"Point"}
}