{
  "type": "Feature",
  "properties": {
    "iso:country":"US",
    "sg:address":"2695 Boones Creek Rd",
    "sg:city":"Johnson City",
    "sg:classifiers":[
        {
            "category":"Food & Beverages",
            "subcategory":"Groceries & Convenience Stores",
            "type":"Retail Goods"
        }
    ],
    "sg:phone":"+1 423 610 0485",
    "sg:postcode":"37615",
    "sg:province":"TN",
    "wof:name":"Roadrunner",
    "wof:placetype":"venue"
},
  "geometry": {"coordinates":[-82.427752,36.374282],"type":"Point"}
}