{
  "type": "Feature",
  "properties": {
    "addr:full":"9390 Old Brownsville Rd Arlington TN 38002",
    "addr:housenumber":"9390",
    "addr:postcode":"38002",
    "addr:street":"Old Brownsville Rd",
    "iso:country":"US",
    "sg:address":"9390 Old Brownsville Rd",
    "sg:city":"Arlington",
    "sg:classifiers":[
        {
            "category":"Professional",
            "subcategory":"Engineering",
            "type":"Services"
        }
    ],
    "sg:phone":"+1 901 867 4021",
    "sg:postcode":"38002",
    "sg:province":"TN",
    "sg:tags":[
        "engineer"
    ],
    "wof:name":"One Light Group Inc",
    "wof:placetype":"venue"
},
  "geometry": {"coordinates":[-89.74865699999999,35.265882],"type":"Point"}
}