{
  "type": "Feature",
  "properties": {
    "iso:country":"US",
    "sg:address":"581 Club Tower Cove",
    "sg:city":"Memphis",
    "sg:classifiers":[
        {
            "category":"Wholesale",
            "subcategory":"Electrical",
            "type":"Manufacturing & Wholesale Goods"
        }
    ],
    "sg:phone":"+1 901 458 9840",
    "sg:postcode":"38111",
    "sg:province":"TN",
    "sg:tags":[
        "product",
        "ergonomic"
    ],
    "wof:name":"Ergonomic Solutions",
    "wof:placetype":"venue"
},
  "geometry": {"coordinates":[-89.954954,35.115715],"type":"Point"}
}