{
  "type": "Feature",
  "properties": {
    "iso:country":"US",
    "sg:address":"10000 Kingston Pike",
    "sg:city":"Knoxville",
    "sg:classifiers":[
        {
            "category":"Insurance",
            "subcategory":"Insurance Agent",
            "type":"Services"
        }
    ],
    "sg:phone":"+1 865 692 2244",
    "sg:postcode":"37922",
    "sg:province":"TN",
    "wof:name":"ISG Auto Insurance",
    "wof:placetype":"venue"
},
  "geometry": {"coordinates":[-84.116906,35.903643],"type":"Point"}
}