{
  "type": "Feature",
  "properties": {
    "iso:country":"US",
    "sg:address":"905 S Castle St",
    "sg:city":"Knoxville",
    "sg:classifiers":[
        {
            "category":"Professional",
            "subcategory":"Management & Consulting",
            "type":"Services"
        }
    ],
    "sg:phone":"+1 865 974 4422",
    "sg:postcode":"37914",
    "sg:province":"TN",
    "wof:name":"Construction Resource Analysis",
    "wof:placetype":"venue"
},
  "geometry": {"coordinates":[-83.876802,35.985869],"type":"Point"}
}