{
  "type": "Feature",
  "properties": {
    "iso:country":"US",
    "sg:address":"3851 Katelyns Ln",
    "sg:city":"Sevierville",
    "sg:classifiers":[
        {
            "category":"Travel",
            "subcategory":"Travel Agent",
            "type":"Entertainment"
        }
    ],
    "sg:phone":"+1 865 428 1105",
    "sg:postcode":"37876",
    "sg:province":"TN",
    "sg:tags":[
        "operator",
        "tour"
    ],
    "wof:name":"Black Bear Tours Inc",
    "wof:placetype":"venue"
},
  "geometry": {"coordinates":[-83.462535,35.782391],"type":"Point"}
}