{
  "type": "Feature",
  "properties": {
    "iso:country":"US",
    "sg:address":"1740 N Germantown Pkwy",
    "sg:city":"Cordova",
    "sg:classifiers":[
        {
            "category":"Building & Trades",
            "subcategory":"Construction",
            "type":"Services"
        }
    ],
    "sg:phone":"+1 901 624 7753",
    "sg:postcode":"38016",
    "sg:province":"TN",
    "sg:tags":[
        "tile",
        "dealer"
    ],
    "wof:name":"Tile House",
    "wof:placetype":"venue"
},
  "geometry": {"coordinates":[-89.792843,35.172675],"type":"Point"}
}