{
  "type": "Feature",
  "properties": {
    "addr:full":"2103 Country Club Dr Tullahoma TN 37388",
    "addr:housenumber":"2103",
    "addr:postcode":"37388",
    "addr:street":"Country Club Dr",
    "iso:country":"US",
    "sg:address":"2103 Country Club Dr",
    "sg:city":"Tullahoma",
    "sg:classifiers":[
        {
            "category":"Shopping",
            "type":"Retail Goods"
        }
    ],
    "sg:phone":"+1 931 455 6669",
    "sg:postcode":"37388",
    "sg:province":"TN",
    "sg:tags":[
        "merchandise"
    ],
    "wof:name":"Squad 1 Extinguishers",
    "wof:placetype":"venue"
},
  "geometry": {"coordinates":[-86.21686200000001,35.395305],"type":"Point"}
}