{
  "type": "Feature",
  "properties": {
    "iso:country":"US",
    "sg:address":"5983 Apple Tree Dr",
    "sg:city":"Memphis",
    "sg:classifiers":[
        {
            "category":"Health Services",
            "subcategory":"Doctor",
            "type":"Services"
        }
    ],
    "sg:phone":"+1 901 363 1945",
    "sg:postcode":"38115",
    "sg:province":"TN",
    "sg:tags":[
        "physician",
        "surgeon"
    ],
    "wof:name":"Advanced Primary Care Inc",
    "wof:placetype":"venue"
},
  "geometry": {"coordinates":[-89.85977699999999,35.070549],"type":"Point"}
}