{
  "type": "Feature",
  "properties": {
    "iso:country":"US",
    "sg:address":"5299 Mendenhall Park Pl",
    "sg:city":"Memphis",
    "sg:classifiers":[
        {
            "category":"Manufacturing",
            "subcategory":"Printing",
            "type":"Manufacturing & Wholesale Goods"
        }
    ],
    "sg:phone":"+1 901 360 0056",
    "sg:postcode":"38115",
    "sg:province":"TN",
    "sg:tags":[
        "commercial"
    ],
    "wof:name":"Ink Alley Printing",
    "wof:placetype":"venue"
},
  "geometry": {"coordinates":[-89.887514,35.043526],"type":"Point"}
}