{
  "type": "Feature",
  "properties": {
    "addr:full":"4340 Pippin Rd Cookeville TN 38501",
    "addr:postcode":"4340;38501",
    "addr:street":"Pippin Rd",
    "iso:country":"US",
    "sg:address":"4340 Pippin Rd",
    "sg:city":"Cookeville",
    "sg:classifiers":[
        {
            "category":"Travel",
            "subcategory":"Travel Agent",
            "type":"Entertainment"
        }
    ],
    "sg:phone":"+1 931 372 8989",
    "sg:postcode":"38501",
    "sg:province":"TN",
    "sg:tags":[
        "operator",
        "tour",
        "agency"
    ],
    "wof:name":"Carefree Tours",
    "wof:placetype":"venue"
},
  "geometry": {"coordinates":[-85.59827900000001,36.222359],"type":"Point"}
}