{
  "type": "Feature",
  "properties": {
    "addr:full":"57 Germantown Court  Suite 300 Memphis TN 38018",
    "addr:housenumber":"57",
    "addr:postcode":"38018",
    "addr:street":"Germantown Court Suite 300",
    "iso:country":"US",
    "sg:address":"57 Germantown Court  Suite 300",
    "sg:city":"Memphis",
    "sg:classifiers":[
        {
            "category":"Professional",
            "subcategory":"Computer Services",
            "type":"Services"
        }
    ],
    "sg:phone":"+1 901 767 1850",
    "sg:postcode":"38018",
    "sg:province":"TN",
    "wof:name":"Aegis InterWorld",
    "wof:placetype":"venue"
},
  "geometry": {"coordinates":[-89.79538599999999,35.129826],"type":"Point"}
}