{
  "type": "Feature",
  "properties": {
    "iso:country":"US",
    "sg:address":"2615 Chase Ln",
    "sg:city":"Murfreesboro",
    "sg:classifiers":[
        {
            "category":"Building & Trades",
            "subcategory":"Construction",
            "type":"Services"
        }
    ],
    "sg:phone":"+1 615 217 9636",
    "sg:postcode":"37130",
    "sg:province":"TN",
    "sg:tags":[
        "house"
    ],
    "wof:name":"Mullen Construction",
    "wof:placetype":"venue"
},
  "geometry": {"coordinates":[-86.373389,35.893725],"type":"Point"}
}