{
  "type": "Feature",
  "properties": {
    "addr:full":"705 Forrest Ave Mc Kenzie TN 38201",
    "addr:housenumber":"705",
    "addr:postcode":"38201",
    "addr:street":"Forrest Ave Mc",
    "iso:country":"US",
    "sg:address":"705 Forrest Ave",
    "sg:city":"Mc Kenzie",
    "sg:classifiers":[
        {
            "category":"Real Estate",
            "subcategory":"Real Estate Agent",
            "type":"Services"
        }
    ],
    "sg:phone":"+1 731 352 5971",
    "sg:postcode":"38201",
    "sg:province":"TN",
    "wof:name":"Hodges Rental Properties",
    "wof:placetype":"venue"
},
  "geometry": {"coordinates":[-88.506517,36.132435],"type":"Point"}
}