{
  "type": "Feature",
  "properties": {
    "iso:country":"US",
    "sg:address":"2454 Nashville Hwy",
    "sg:city":"Mc Minnville",
    "sg:classifiers":[
        {
            "category":"Building & Trades",
            "subcategory":"Construction",
            "type":"Services"
        }
    ],
    "sg:phone":"+1 931 668 2298",
    "sg:postcode":"37110",
    "sg:province":"TN",
    "sg:tags":[
        "roofing",
        "contractor"
    ],
    "sg:website":"www.porter-roofing.com",
    "wof:name":"Porter Roofing Contractors Inc",
    "wof:placetype":"venue"
},
  "geometry": {"coordinates":[-85.81214900000001,35.695808],"type":"Point"}
}