{
  "type": "Feature",
  "properties": {
    "iso:country":"US",
    "sg:address":"4093 Maumee St",
    "sg:city":"Memphis",
    "sg:classifiers":[
        {
            "category":"Manufacturing",
            "subcategory":"Printing",
            "type":"Manufacturing & Wholesale Goods"
        }
    ],
    "sg:phone":"+1 901 785 9376",
    "sg:postcode":"38109",
    "sg:province":"TN",
    "sg:tags":[
        "lithographing",
        "ink"
    ],
    "wof:name":"Ink Forever",
    "wof:placetype":"venue"
},
  "geometry": {"coordinates":[-90.10475599999999,35.038023],"type":"Point"}
}