{
  "type": "Feature",
  "properties": {
    "addr:full":"2022 Euclid Ave Bristol TN 24201",
    "addr:housenumber":"2022",
    "addr:postcode":"24201",
    "addr:street":"Euclid Ave",
    "iso:country":"US",
    "sg:address":"2022 Euclid Ave",
    "sg:city":"Bristol",
    "sg:classifiers":[
        {
            "category":"Health Services",
            "subcategory":"Chiropractor",
            "type":"Services"
        }
    ],
    "sg:phone":"+1 276 466 3012",
    "sg:postcode":"24201",
    "sg:province":"TN",
    "wof:name":"Morenings Chiropractic",
    "wof:placetype":"venue"
},
  "geometry": {"coordinates":[-82.205426,36.597676],"type":"Point"}
}