{
  "type": "Feature",
  "properties": {
    "addr:full":"620 W Main St Hendersonville TN 37075",
    "addr:housenumber":"620",
    "addr:postcode":"37075",
    "addr:street":"W Main St",
    "iso:country":"US",
    "sg:address":"620 W Main St",
    "sg:city":"Hendersonville",
    "sg:classifiers":[
        {
            "category":"Personal",
            "subcategory":"Beauty Salon",
            "type":"Services"
        }
    ],
    "sg:phone":"+1 615 826 5808",
    "sg:postcode":"37075",
    "sg:province":"TN",
    "sg:tags":[
        "shop"
    ],
    "wof:name":"Speed Cuts",
    "wof:placetype":"venue"
},
  "geometry": {"coordinates":[-86.638868,36.302962],"type":"Point"}
}