{
  "type": "Feature",
  "properties": {
    "iso:country":"US",
    "sg:address":"4334 Castle Ave",
    "sg:city":"Memphis",
    "sg:classifiers":[
        {
            "category":"Professional",
            "type":"Services"
        }
    ],
    "sg:phone":"+1 901 683 8672",
    "sg:postcode":"38122",
    "sg:province":"TN",
    "wof:name":"Donovan Laprett",
    "wof:placetype":"venue"
},
  "geometry": {"coordinates":[-89.917981,35.152547],"type":"Point"}
}