{
  "type": "Feature",
  "properties": {
    "addr:full":"1073 W Van Hook St Milan TN 38358",
    "addr:housenumber":"1073",
    "addr:postcode":"38358",
    "addr:street":"W Van Hook St",
    "iso:country":"US",
    "sg:address":"1073 W Van Hook St",
    "sg:city":"Milan",
    "sg:classifiers":[
        {
            "category":"Travel",
            "subcategory":"Hotels & Motels",
            "type":"Entertainment"
        }
    ],
    "sg:phone":"+1 731 686 7575",
    "sg:postcode":"38358",
    "sg:province":"TN",
    "wof:name":"Budget Inn",
    "wof:placetype":"venue"
},
  "geometry": {"coordinates":[-88.75680699999999,35.914302],"type":"Point"}
}