{
  "type": "Feature",
  "properties": {
    "iso:country":"US",
    "sg:address":"11001 Twin Harbour Dr",
    "sg:city":"Knoxville",
    "sg:classifiers":[
        {
            "category":"Local Transit",
            "type":"Transportation"
        }
    ],
    "sg:phone":"+1 865 671 0141",
    "sg:postcode":"37934",
    "sg:province":"TN",
    "sg:tags":[
        "passenger"
    ],
    "wof:name":"Hilton Transportation",
    "wof:placetype":"venue"
},
  "geometry": {"coordinates":[-84.133836,35.870283],"type":"Point"}
}