{
  "type": "Feature",
  "properties": {
    "addr:full":"4313 Genny Lynn Dr Knoxville TN 37918",
    "addr:housenumber":"4313",
    "addr:postcode":"37918",
    "addr:street":"Genny Lynn Dr",
    "iso:country":"US",
    "sg:address":"4313 Genny Lynn Dr",
    "sg:city":"Knoxville",
    "sg:classifiers":[
        {
            "category":"Freight",
            "type":"Transportation"
        }
    ],
    "sg:phone":"+1 865 689 6655",
    "sg:postcode":"37918",
    "sg:province":"TN",
    "sg:tags":[
        "broker",
        "trucking"
    ],
    "wof:name":"Anmark Traqnsportation",
    "wof:placetype":"venue"
},
  "geometry": {"coordinates":[-83.91392999999999,36.063947],"type":"Point"}
}