{
  "type": "Feature",
  "properties": {
    "iso:country":"US",
    "sg:address":"31 Rimfire Dr",
    "sg:city":"Beechgrove",
    "sg:classifiers":[
        {
            "category":"Restaurant",
            "type":"Food & Drink"
        }
    ],
    "sg:phone":"+1 931 394 3030",
    "sg:postcode":"37018",
    "sg:province":"TN",
    "sg:tags":[
        "cafe"
    ],
    "wof:name":"Who Do Cafe",
    "wof:placetype":"venue"
},
  "geometry": {"coordinates":[-86.13208400000001,35.643859],"type":"Point"}
}