{
  "type": "Feature",
  "properties": {
    "addr:full":"1723 William Blount Dr Maryville TN 37801",
    "addr:housenumber":"1723",
    "addr:postcode":"37801",
    "addr:street":"William Blount Dr",
    "iso:country":"US",
    "sg:address":"1723 William Blount Dr",
    "sg:city":"Maryville",
    "sg:classifiers":[
        {
            "category":"Organizations",
            "subcategory":"Religious Organization",
            "type":"Services"
        }
    ],
    "sg:phone":"+1 865 982 4901",
    "sg:postcode":"37801",
    "sg:province":"TN",
    "sg:tags":[
        "church"
    ],
    "sg:website":"www.firstapostolic.org",
    "wof:name":"First Apostolic Church",
    "wof:placetype":"venue"
},
  "geometry": {"coordinates":[-84.044399,35.753235],"type":"Point"}
}