{
  "type": "Feature",
  "properties": {
    "iso:country":"US",
    "sg:address":"211 Highland Sq",
    "sg:city":"Crossville",
    "sg:classifiers":[
        {
            "category":"Restaurant",
            "type":"Food & Drink"
        }
    ],
    "sg:phone":"+1 931 456 0533",
    "sg:postcode":"38555",
    "sg:province":"TN",
    "sg:tags":[
        "pizza"
    ],
    "wof:name":"Little Caesars Pizza",
    "wof:placetype":"venue"
},
  "geometry": {"coordinates":[-85.04478,35.958056],"type":"Point"}
}