{
  "type": "Feature",
  "properties": {
    "iso:country":"US",
    "sg:address":"6906 Bordeaux Ln",
    "sg:city":"Memphis",
    "sg:classifiers":[
        {
            "category":"Retail",
            "subcategory":"Auto Rental",
            "type":"Services"
        }
    ],
    "sg:phone":"+1 901 795 3684",
    "sg:postcode":"38141",
    "sg:province":"TN",
    "sg:tags":[
        "trailer",
        "utility"
    ],
    "wof:name":"McKinney Exchange Trucking",
    "wof:placetype":"venue"
},
  "geometry": {"coordinates":[-89.83144,35.024413],"type":"Point"}
}