{
  "type": "Feature",
  "properties": {
    "iso:country":"US",
    "sg:address":"615 Potomac Pl",
    "sg:city":"Smyrna",
    "sg:classifiers":[
        {
            "category":"Arts & Performance",
            "subcategory":"Theater",
            "type":"Entertainment"
        }
    ],
    "sg:phone":"+1 615 361 1810",
    "sg:postcode":"37167",
    "sg:province":"TN",
    "sg:tags":[
        "theatrical"
    ],
    "wof:name":"G S F & Associates Inc",
    "wof:placetype":"venue"
},
  "geometry": {"coordinates":[-86.55766800000001,35.977104],"type":"Point"}
}