{
  "type": "Feature",
  "properties": {
    "addr:full":"2820 Media Dr Knoxville TN 37914",
    "addr:housenumber":"2820",
    "addr:postcode":"37914",
    "addr:street":"Media Dr",
    "iso:country":"US",
    "sg:address":"2820 Media Dr",
    "sg:city":"Knoxville",
    "sg:classifiers":[
        {
            "category":"Manufacturing",
            "subcategory":"Tools & Machinery",
            "type":"Manufacturing & Wholesale Goods"
        }
    ],
    "sg:phone":"+1 865 546 4208",
    "sg:postcode":"37914",
    "sg:province":"TN",
    "sg:tags":[
        "razor",
        "mfg",
        "bladed",
        "blade",
        "hand",
        "shaving"
    ],
    "wof:name":"American Safety Razor Company",
    "wof:placetype":"venue"
},
  "geometry": {"coordinates":[-83.827569,35.958777],"type":"Point"}
}