{
  "type": "Feature",
  "properties": {
    "iso:country":"US",
    "sg:address":"301 E Central St",
    "sg:city":"Trenton",
    "sg:classifiers":[
        {
            "category":"Social Services",
            "subcategory":"Child Care",
            "type":"Services"
        }
    ],
    "sg:phone":"+1 731 855 0577",
    "sg:postcode":"38382",
    "sg:province":"TN",
    "sg:tags":[
        "day"
    ],
    "wof:name":"Central Street Connection",
    "wof:placetype":"venue"
},
  "geometry": {"coordinates":[-88.93940499999999,35.982504],"type":"Point"}
}