{
  "type": "Feature",
  "properties": {
    "iso:country":"US",
    "sg:address":"9025 Highway 64",
    "sg:city":"Arlington",
    "sg:phone":"+1 901 381 9065",
    "sg:postcode":"38002",
    "sg:province":"TN",
    "sg:website":"http://www.schnucks.com",
    "wof:name":"Schnuck Markets, Inc",
    "wof:placetype":"venue"
},
  "geometry": {"coordinates":[-89.761831,35.204497],"type":"Point"}
}