{
  "type": "Feature",
  "properties": {
    "iso:country":"US",
    "sg:address":"305 Highwood Ct",
    "sg:city":"Knoxville",
    "sg:classifiers":[
        {
            "category":"Building & Trades",
            "subcategory":"Landscaping Services",
            "type":"Services"
        }
    ],
    "sg:phone":"+1 865 573 4650",
    "sg:postcode":"37920",
    "sg:province":"TN",
    "wof:name":"Silver Creek Landscaping",
    "wof:placetype":"venue"
},
  "geometry": {"coordinates":[-83.910431,35.947453],"type":"Point"}
}