{
  "type": "Feature",
  "properties": {
    "iso:country":"US",
    "sg:address":"1280 Rocky Hill Rd",
    "sg:city":"Knoxville",
    "sg:classifiers":[
        {
            "category":"Manufacturing",
            "subcategory":"Printing",
            "type":"Manufacturing & Wholesale Goods"
        }
    ],
    "sg:phone":"+1 865 691 5141",
    "sg:postcode":"37919",
    "sg:province":"TN",
    "sg:tags":[
        "commercial"
    ],
    "wof:name":"Label Industries LLC",
    "wof:placetype":"venue"
},
  "geometry": {"coordinates":[-84.020793,35.90505],"type":"Point"}
}