{
  "type": "Feature",
  "properties": {
    "addr:full":"311 Gallatin Ave Nashville TN 37206",
    "addr:housenumber":"311",
    "addr:postcode":"37206",
    "addr:street":"Gallatin Ave",
    "iso:country":"US",
    "sg:address":"311 Gallatin Ave",
    "sg:city":"Nashville",
    "sg:classifiers":[
        {
            "category":"Restaurant",
            "type":"Food & Drink"
        }
    ],
    "sg:phone":"+1 615 226 2930",
    "sg:postcode":"37206",
    "sg:province":"TN",
    "wof:name":"Mrs Winners Chicken & Biscuits",
    "wof:placetype":"venue"
},
  "geometry": {"coordinates":[-86.75029600000001,36.179217],"type":"Point"}
}