{
  "type": "Feature",
  "properties": {
    "iso:country":"US",
    "sg:address":"304 S Lowry St Ste A",
    "sg:city":"Smyrna",
    "sg:classifiers":[
        {
            "category":"Professional",
            "subcategory":"Lawyer & Legal Services",
            "type":"Services"
        }
    ],
    "sg:phone":"+1 615 459 2527",
    "sg:postcode":"37167",
    "sg:province":"TN",
    "sg:tags":[
        "attorney",
        "practice"
    ],
    "wof:name":"Bolin & Ward Attorneys At Law",
    "wof:placetype":"venue"
},
  "geometry": {"coordinates":[-86.511619,35.974096],"type":"Point"}
}