{
  "type": "Feature",
  "properties": {
    "iso:country":"US",
    "sg:address":"6325 Bresslyn Rd",
    "sg:city":"Nashville",
    "sg:classifiers":[
        {
            "category":"Building & Trades",
            "subcategory":"Construction",
            "type":"Services"
        }
    ],
    "sg:phone":"+1 615 353 1738",
    "sg:postcode":"37205",
    "sg:province":"TN",
    "sg:tags":[
        "contractor"
    ],
    "wof:name":"Bill Hancock Construction Inc",
    "wof:placetype":"venue"
},
  "geometry": {"coordinates":[-86.892577,36.108599],"type":"Point"}
}