{
  "type": "Feature",
  "properties": {
    "addr:full":"322 Nancy Lynn Ln Knoxville TN 37919",
    "addr:housenumber":"322",
    "addr:postcode":"37919",
    "addr:street":"Nancy Lynn Ln",
    "iso:country":"US",
    "sg:address":"322 Nancy Lynn Ln",
    "sg:city":"Knoxville",
    "sg:classifiers":[
        {
            "category":"Professional",
            "subcategory":"Lawyer & Legal Services",
            "type":"Services"
        }
    ],
    "sg:phone":"+1 865 594 6519",
    "sg:postcode":"37919",
    "sg:province":"TN",
    "wof:name":"Tennessee Safety Department",
    "wof:placetype":"venue"
},
  "geometry": {"coordinates":[-84.00948699999999,35.92637],"type":"Point"}
}