{
  "type": "Feature",
  "properties": {
    "addr:full":"8719 Kingston Pike Knoxville TN 37923",
    "addr:housenumber":"8719",
    "addr:postcode":"37923",
    "addr:street":"Kingston Pike",
    "iso:country":"US",
    "sg:address":"8719 Kingston Pike",
    "sg:city":"Knoxville",
    "sg:classifiers":[
        {
            "category":"Home & Garden",
            "subcategory":"Carpets & Floor Coverings",
            "type":"Retail Goods"
        }
    ],
    "sg:phone":"+1 865 523 0731",
    "sg:postcode":"37923",
    "sg:province":"TN",
    "sg:tags":[
        "dealer",
        "rug"
    ],
    "wof:name":"Home Choice",
    "wof:placetype":"venue"
},
  "geometry": {"coordinates":[-84.073425,35.91748],"type":"Point"}
}