{
  "type": "Feature",
  "properties": {
    "iso:country":"US",
    "sg:address":"8206 Jackman Rd",
    "sg:city":"Joelton",
    "sg:classifiers":[
        {
            "category":"Building & Trades",
            "subcategory":"Construction",
            "type":"Services"
        }
    ],
    "sg:phone":"+1 615 876 0328",
    "sg:postcode":"37080",
    "sg:province":"TN",
    "sg:tags":[
        "house"
    ],
    "wof:name":"Michael Norris Home Improvemen",
    "wof:placetype":"venue"
},
  "geometry": {"coordinates":[-86.87713599999999,36.360844],"type":"Point"}
}