{
  "type": "Feature",
  "properties": {
    "iso:country":"US",
    "sg:address":"3716 E Stone Dr",
    "sg:city":"Kingsport",
    "sg:classifiers":[
        {
            "category":"Wholesale",
            "subcategory":"Medical Equipment & Supplies",
            "type":"Manufacturing & Wholesale Goods"
        }
    ],
    "sg:phone":"+1 423 392 9900",
    "sg:postcode":"37660",
    "sg:province":"TN",
    "sg:tags":[
        "physician",
        "surgeon"
    ],
    "wof:name":"Holland Medical Equipment",
    "wof:placetype":"venue"
},
  "geometry": {"coordinates":[-82.43656900000001,36.572177],"type":"Point"}
}