{
  "type": "Feature",
  "properties": {
    "addr:full":"32 W Gage Ave Memphis TN 38109",
    "addr:housenumber":"32",
    "addr:postcode":"38109",
    "addr:street":"W Gage Ave",
    "iso:country":"US",
    "sg:address":"32 W Gage Ave",
    "sg:city":"Memphis",
    "sg:classifiers":[
        {
            "category":"Organizations",
            "subcategory":"Religious Organization",
            "type":"Services"
        }
    ],
    "sg:phone":"+1 901 946 4800",
    "sg:postcode":"38109",
    "sg:province":"TN",
    "wof:name":"Solemn Assembly",
    "wof:placetype":"venue"
},
  "geometry": {"coordinates":[-90.064241,35.087737],"type":"Point"}
}