{
  "type": "Feature",
  "properties": {
    "iso:country":"US",
    "sg:address":"724 Taylor Rd",
    "sg:city":"Knoxville",
    "sg:classifiers":[
        {
            "category":"Real Estate",
            "subcategory":"Architect",
            "type":"Services"
        }
    ],
    "sg:phone":"+1 865 573 1148",
    "sg:postcode":"37920",
    "sg:province":"TN",
    "sg:tags":[
        "architectural"
    ],
    "wof:name":"Johnson Len & Associates",
    "wof:placetype":"venue"
},
  "geometry": {"coordinates":[-83.893636,35.938622],"type":"Point"}
}