{
  "type": "Feature",
  "properties": {
    "addr:full":"5160 Old Kentucky Rd Morristown TN 37814",
    "addr:housenumber":"5160",
    "addr:postcode":"37814",
    "addr:street":"Old Kentucky Rd",
    "iso:country":"US",
    "sg:address":"5160 Old Kentucky Rd",
    "sg:city":"Morristown",
    "sg:classifiers":[
        {
            "category":"Retail",
            "subcategory":"Auto Repair",
            "type":"Services"
        }
    ],
    "sg:phone":"+1 423 587 6781",
    "sg:postcode":"37814",
    "sg:province":"TN",
    "sg:tags":[
        "general"
    ],
    "wof:name":"Complete Automotive Repair Svc",
    "wof:placetype":"venue"
},
  "geometry": {"coordinates":[-83.223354,36.251743],"type":"Point"}
}