{
  "type": "Feature",
  "properties": {
    "addr:full":"238 S Washington St Ripley TN 38063",
    "addr:housenumber":"238",
    "addr:postcode":"38063",
    "addr:street":"S Washington St",
    "iso:country":"US",
    "sg:address":"238 S Washington St",
    "sg:city":"Ripley",
    "sg:classifiers":[
        {
            "category":"Food & Beverages",
            "subcategory":"Groceries & Convenience Stores",
            "type":"Retail Goods"
        }
    ],
    "sg:phone":"+1 731 635 4663",
    "sg:postcode":"38063",
    "sg:province":"TN",
    "wof:name":"Little General Store 3",
    "wof:placetype":"venue"
},
  "geometry": {"coordinates":[-89.53663,35.743922],"type":"Point"}
}