{
  "type": "Feature",
  "properties": {
    "iso:country":"US",
    "sg:address":"2636 E Magnolia Ave",
    "sg:city":"Knoxville",
    "sg:classifiers":[
        {
            "category":"Manufacturing",
            "subcategory":"Printing",
            "type":"Manufacturing & Wholesale Goods"
        }
    ],
    "sg:phone":"+1 865 546 9574",
    "sg:postcode":"37914",
    "sg:province":"TN",
    "sg:tags":[
        "lithographic",
        "commercial"
    ],
    "wof:name":"TNT Digital Printing",
    "wof:placetype":"venue"
},
  "geometry": {"coordinates":[-83.892736,35.987786],"type":"Point"}
}