{
  "type": "Feature",
  "properties": {
    "addr:full":"2176 Hillsboro Rd Franklin TN 37069",
    "addr:housenumber":"2176",
    "addr:postcode":"37069",
    "addr:street":"Hillsboro Rd",
    "iso:country":"US",
    "sg:address":"2176 Hillsboro Rd",
    "sg:city":"Franklin",
    "sg:classifiers":[
        {
            "category":"Restaurant",
            "type":"Food & Drink"
        }
    ],
    "sg:phone":"+1 615 591 2223",
    "sg:postcode":"37069",
    "sg:province":"TN",
    "sg:tags":[
        "eating"
    ],
    "wof:name":"Great Wall Of China",
    "wof:placetype":"venue"
},
  "geometry": {"coordinates":[-86.890762,35.987925],"type":"Point"}
}