{
  "type": "Feature",
  "properties": {
    "iso:country":"US",
    "sg:address":"27 Joyce Dr",
    "sg:city":"Jackson",
    "sg:classifiers":[
        {
            "category":"Building & Trades",
            "subcategory":"Landscaping Services",
            "type":"Services"
        }
    ],
    "sg:phone":"+1 731 424 1933",
    "sg:postcode":"38305",
    "sg:province":"TN",
    "wof:name":"Brads Lawn Services",
    "wof:placetype":"venue"
},
  "geometry": {"coordinates":[-88.80710999999999,35.68187],"type":"Point"}
}