{
  "type": "Feature",
  "properties": {
    "iso:country":"US",
    "sg:address":"7362 Nolensville Rd",
    "sg:city":"Nolensville",
    "sg:classifiers":[
        {
            "category":"Shopping",
            "subcategory":"Florist",
            "type":"Retail Goods"
        }
    ],
    "sg:phone":"+1 615 776 5372",
    "sg:postcode":"37135",
    "sg:province":"TN",
    "sg:tags":[
        "plant"
    ],
    "wof:name":"Tant's Plants",
    "wof:placetype":"venue"
},
  "geometry": {"coordinates":[-86.664344,35.943678],"type":"Point"}
}