{
  "type": "Feature",
  "properties": {
    "iso:country":"US",
    "sg:address":"4022 Gamaliel Rd",
    "sg:city":"Red Boiling Springs",
    "sg:classifiers":[
        {
            "category":"Farming",
            "subcategory":"Poultry Farm",
            "type":"Manufacturing & Wholesale Goods"
        }
    ],
    "sg:phone":"+1 615 699 3766",
    "sg:postcode":"37150",
    "sg:province":"TN",
    "sg:tags":[
        "hatchery"
    ],
    "wof:name":"Kathy H Brown",
    "wof:placetype":"venue"
},
  "geometry": {"coordinates":[-85.822057,36.597783],"type":"Point"}
}