{
  "type": "Feature",
  "properties": {
    "iso:country":"US",
    "sg:address":"105 W 1st Ave",
    "sg:city":"Oneida",
    "sg:classifiers":[
        {
            "category":"Personal",
            "subcategory":"Beauty Salon",
            "type":"Services"
        }
    ],
    "sg:phone":"+1 423 569 8860",
    "sg:postcode":"37841",
    "sg:province":"TN",
    "wof:name":"Beverly's Hair Care",
    "wof:placetype":"venue"
},
  "geometry": {"coordinates":[-84.516593,36.499811],"type":"Point"}
}