{
  "type": "Feature",
  "properties": {
    "iso:country":"US",
    "sg:address":"2559 Berryhill Rd",
    "sg:city":"Cordova",
    "sg:classifiers":[
        {
            "category":"Professional",
            "subcategory":"Management & Consulting",
            "type":"Services"
        }
    ],
    "sg:phone":"+1 901 372 8381",
    "sg:postcode":"38016",
    "sg:province":"TN",
    "sg:tags":[
        "business"
    ],
    "wof:name":"Commercial Turf Equipment",
    "wof:placetype":"venue"
},
  "geometry": {"coordinates":[-89.75903700000001,35.195294],"type":"Point"}
}