{
  "type": "Feature",
  "properties": {
    "iso:country":"US",
    "sg:address":"855 Hickory Oaks Cir",
    "sg:city":"Collierville",
    "sg:classifiers":[
        {
            "category":"Banks & Credit Unions",
            "subcategory":"Investment Brokerage",
            "type":"Services"
        },
        {
            "category":"Professional",
            "subcategory":"Management & Consulting",
            "type":"Services"
        }
    ],
    "sg:phone":"+1 901 861 3074",
    "sg:postcode":"38017",
    "sg:province":"TN",
    "sg:tags":[
        "consultant",
        "planning",
        "financial"
    ],
    "wof:name":"Insurance Benefits Consulting",
    "wof:placetype":"venue"
},
  "geometry": {"coordinates":[-89.70172100000001,35.063226],"type":"Point"}
}