{
  "type": "Feature",
  "properties": {
    "addr:full":"2149 Harbor Ave Memphis TN 38113",
    "addr:housenumber":"2149",
    "addr:postcode":"38113",
    "addr:street":"Harbor Ave",
    "iso:country":"US",
    "sg:address":"2149 Harbor Ave",
    "sg:city":"Memphis",
    "sg:classifiers":[
        {
            "category":"Manufacturing",
            "subcategory":"Tools & Machinery",
            "type":"Manufacturing & Wholesale Goods"
        }
    ],
    "sg:phone":"+1 901 948 3372",
    "sg:postcode":"38113",
    "sg:province":"TN",
    "sg:tags":[
        "physician",
        "surgeon"
    ],
    "wof:name":"Glaxosmithkline",
    "wof:placetype":"venue"
},
  "geometry": {"coordinates":[-90.112801,35.096268],"type":"Point"}
}