{
  "type": "Feature",
  "properties": {
    "iso:country":"US",
    "sg:address":"1861 Lenow Rd",
    "sg:city":"Cordova",
    "sg:classifiers":[
        {
            "category":"Building & Trades",
            "subcategory":"Landscaping Services",
            "type":"Services"
        }
    ],
    "sg:phone":"+1 901 751 8528",
    "sg:postcode":"38016",
    "sg:province":"TN",
    "sg:tags":[
        "landscape",
        "contractor"
    ],
    "wof:name":"Earth & Turf",
    "wof:placetype":"venue"
},
  "geometry": {"coordinates":[-89.737425,35.179402],"type":"Point"}
}