{
  "type": "Feature",
  "properties": {
    "iso:country":"US",
    "sg:address":"9333 Park West Blvd",
    "sg:city":"Knoxville",
    "sg:classifiers":[
        {
            "category":"Health Services",
            "subcategory":"Doctor",
            "type":"Services"
        }
    ],
    "sg:phone":"+1 865 531 4658",
    "sg:postcode":"37923",
    "sg:province":"TN",
    "sg:tags":[
        "medical"
    ],
    "wof:name":"Ojeda Gabriel A MD",
    "wof:placetype":"venue"
},
  "geometry": {"coordinates":[-84.100866,35.918001],"type":"Point"}
}