{
  "type": "Feature",
  "properties": {
    "iso:country":"US",
    "sg:address":"5272 E Andrew Johnson Hwy",
    "sg:city":"Russellville",
    "sg:classifiers":[
        {
            "category":"Restaurant",
            "type":"Food & Drink"
        }
    ],
    "sg:phone":"+1 423 587 3778",
    "sg:postcode":"37860",
    "sg:province":"TN",
    "sg:tags":[
        "pizza",
        "italian"
    ],
    "sg:website":"http://www.pizzaplusinc.com",
    "wof:name":"Pizza Plus Of Morristown",
    "wof:placetype":"venue"
},
  "geometry": {"coordinates":[-83.219255,36.24628],"type":"Point"}
}