{
  "type": "Feature",
  "properties": {
    "addr:full":"7455 Cainsville Pike Lascassas TN 37085",
    "addr:housenumber":"7455",
    "addr:postcode":"37085",
    "addr:street":"Cainsville Pike",
    "iso:country":"US",
    "sg:address":"7455 Cainsville Pike",
    "sg:city":"Lascassas",
    "sg:classifiers":[
        {
            "category":"Utilities",
            "subcategory":"Sewage",
            "type":"Services"
        }
    ],
    "sg:phone":"+1 615 399 8377",
    "sg:postcode":"37085",
    "sg:province":"TN",
    "sg:tags":[
        "equipment",
        "treatment"
    ],
    "wof:name":"Specialized Operations Svc Inc",
    "wof:placetype":"venue"
},
  "geometry": {"coordinates":[-86.269547,35.929996],"type":"Point"}
}