{
  "type": "Feature",
  "properties": {
    "addr:full":"4111 S Creek Rd Chattanooga TN 37406",
    "addr:housenumber":"4111",
    "addr:postcode":"37406",
    "addr:street":"S Creek Rd",
    "iso:country":"US",
    "sg:address":"4111 S Creek Rd",
    "sg:city":"Chattanooga",
    "sg:classifiers":[
        {
            "category":"Professional",
            "type":"Services"
        }
    ],
    "sg:phone":"+1 423 698 2281",
    "sg:postcode":"37406",
    "sg:province":"TN",
    "sg:tags":[
        "establishment"
    ],
    "wof:name":"SKJ LLC",
    "wof:placetype":"venue"
},
  "geometry": {"coordinates":[-85.24187499999999,35.093596],"type":"Point"}
}