{
  "type": "Feature",
  "properties": {
    "iso:country":"US",
    "sg:address":"415 W 7th St",
    "sg:city":"Columbia",
    "sg:classifiers":[
        {
            "category":"Banks & Credit Unions",
            "subcategory":"Investment Brokerage",
            "type":"Services"
        }
    ],
    "sg:phone":"+1 931 381 0523",
    "sg:postcode":"38401",
    "sg:province":"TN",
    "sg:tags":[
        "stock",
        "bond"
    ],
    "wof:name":"Edward Jones Co",
    "wof:placetype":"venue"
},
  "geometry": {"coordinates":[-87.040764,35.615481],"type":"Point"}
}