{
  "type": "Feature",
  "properties": {
    "iso:country":"US",
    "sg:address":"5715 Old Tazewell Pike NE",
    "sg:city":"Knoxville",
    "sg:classifiers":[
        {
            "category":"Organizations",
            "subcategory":"Labor Organization",
            "type":"Services"
        }
    ],
    "sg:phone":"+1 865 687 6272",
    "sg:postcode":"37918",
    "sg:province":"TN",
    "wof:name":"Bricklayer's Local",
    "wof:placetype":"venue"
},
  "geometry": {"coordinates":[-83.879601,36.074064],"type":"Point"}
}