{
  "type": "Feature",
  "properties": {
    "addr:full":"6113 Sherwood Dr Chattanooga TN 37412",
    "addr:housenumber":"6113",
    "addr:postcode":"37412",
    "addr:street":"Sherwood Dr",
    "iso:country":"US",
    "sg:address":"6113 Sherwood Dr",
    "sg:city":"Chattanooga",
    "sg:classifiers":[
        {
            "category":"Building & Trades",
            "subcategory":"Cleaning & Sanitation",
            "type":"Services"
        }
    ],
    "sg:phone":"+1 423 894 9458",
    "sg:postcode":"37412",
    "sg:province":"TN",
    "sg:tags":[
        "property",
        "maintenance"
    ],
    "wof:name":"Pinnacle Property Maintenance",
    "wof:placetype":"venue"
},
  "geometry": {"coordinates":[-85.21653499999999,34.996685],"type":"Point"}
}