{
  "type": "Feature",
  "properties": {
    "iso:country":"US",
    "sg:address":"2225 Hillsboro Blvd",
    "sg:city":"Manchester",
    "sg:classifiers":[
        {
            "category":"Professional",
            "subcategory":"Management & Consulting",
            "type":"Services"
        },
        {
            "category":"Professional",
            "subcategory":"Employment Agencies",
            "type":"Services"
        }
    ],
    "sg:phone":"+1 931 723 7810",
    "sg:postcode":"37355",
    "sg:province":"TN",
    "sg:tags":[
        "personnel",
        "supply",
        "help",
        "consultant"
    ],
    "wof:name":"USA Staffing",
    "wof:placetype":"venue"
},
  "geometry": {"coordinates":[-86.056911,35.459409],"type":"Point"}
}