{
  "type": "Feature",
  "properties": {
    "addr:full":"200 Shelby St Kingsport TN 37660",
    "addr:housenumber":"200",
    "addr:postcode":"37660",
    "addr:street":"Shelby St",
    "iso:country":"US",
    "sg:address":"200 Shelby St",
    "sg:city":"Kingsport",
    "sg:classifiers":[
        {
            "category":"Social Services",
            "type":"Services"
        }
    ],
    "sg:phone":"+1 423 245 8640",
    "sg:postcode":"37660",
    "sg:province":"TN",
    "sg:tags":[
        "notification",
        "emergency"
    ],
    "wof:name":"Sullivan County Emergency Svc",
    "wof:placetype":"venue"
},
  "geometry": {"coordinates":[-82.686088,36.539212],"type":"Point"}
}