{
  "type": "Feature",
  "properties": {
    "iso:country":"US",
    "sg:address":"551 Oak St",
    "sg:city":"Chattanooga",
    "sg:classifiers":[
        {
            "category":"Health Services",
            "subcategory":"Doctor",
            "type":"Services"
        }
    ],
    "sg:phone":"+1 423 265 2455",
    "sg:postcode":"37403",
    "sg:province":"TN",
    "sg:tags":[
        "commercial",
        "outpatient",
        "psychiatric",
        "treatment",
        "real estate"
    ],
    "wof:name":"Psychtric Group of Chttnoga PC",
    "wof:placetype":"venue"
},
  "geometry": {"coordinates":[-85.302262,35.047405],"type":"Point"}
}