{
  "type": "Feature",
  "properties": {
    "iso:country":"US",
    "sg:address":"1024 N Division St",
    "sg:city":"Union City",
    "sg:classifiers":[
        {
            "category":"Building & Trades",
            "subcategory":"Construction",
            "type":"Services"
        }
    ],
    "sg:phone":"+1 731 885 6490",
    "sg:postcode":"38261",
    "sg:province":"TN",
    "sg:tags":[
        "general",
        "contractor"
    ],
    "wof:name":"B & B General Contractor",
    "wof:placetype":"venue"
},
  "geometry": {"coordinates":[-89.05334000000001,36.434275],"type":"Point"}
}