{
  "type": "Feature",
  "properties": {
    "iso:country":"US",
    "sg:address":"3074 Charity Ln",
    "sg:city":"Hazel Green",
    "sg:classifiers":[
        {
            "category":"Personal",
            "subcategory":"Beauty Salon",
            "type":"Services"
        }
    ],
    "sg:phone":"+1 256 828 7041",
    "sg:postcode":"35750",
    "sg:province":"TN",
    "sg:tags":[
        "shop"
    ],
    "wof:name":"Kathy's Cut-N-Curl",
    "wof:placetype":"venue"
},
  "geometry": {"coordinates":[-86.693169,34.947946],"type":"Point"}
}