{
  "type": "Feature",
  "properties": {
    "iso:country":"US",
    "sg:address":"5738 Nanjack Cir",
    "sg:city":"Memphis",
    "sg:classifiers":[
        {
            "category":"Personal",
            "subcategory":"Adult",
            "type":"Services"
        }
    ],
    "sg:phone":"+1 901 365 7900",
    "sg:postcode":"38115",
    "sg:province":"TN",
    "sg:tags":[
        "escort"
    ],
    "wof:name":"Apris",
    "wof:placetype":"venue"
},
  "geometry": {"coordinates":[-89.87207100000001,35.073318],"type":"Point"}
}