{
  "type": "Feature",
  "properties": {
    "iso:country":"US",
    "sg:address":"808 Kensington Dr",
    "sg:city":"Nashville",
    "sg:classifiers":[
        {
            "category":"Building & Trades",
            "subcategory":"Cleaning & Sanitation",
            "type":"Services"
        }
    ],
    "sg:phone":"+1 615 419 6258",
    "sg:postcode":"37216",
    "sg:province":"TN",
    "sg:tags":[
        "janitor"
    ],
    "wof:name":"Best Bet Janitorial Svc",
    "wof:placetype":"venue"
},
  "geometry": {"coordinates":[-86.733321,36.238043],"type":"Point"}
}