{
  "type": "Feature",
  "properties": {
    "iso:country":"US",
    "sg:address":"2415 McCallie Ave",
    "sg:city":"Chattanooga",
    "sg:classifiers":[
        {
            "category":"Health Services",
            "subcategory":"Doctor",
            "type":"Services"
        }
    ],
    "sg:phone":"+1 423 697 2055",
    "sg:postcode":"37404",
    "sg:province":"TN",
    "sg:tags":[
        "physician",
        "surgeon"
    ],
    "wof:name":"Tn Valley Occupational Health",
    "wof:placetype":"venue"
},
  "geometry": {"coordinates":[-85.26599299999999,35.032675],"type":"Point"}
}