{
  "type": "Feature",
  "properties": {
    "addr:full":"2406 Elm Hill Pike Nashville TN 37214",
    "addr:housenumber":"2406",
    "addr:postcode":"37214",
    "addr:street":"Elm Hill Pike",
    "iso:country":"US",
    "sg:address":"2406 Elm Hill Pike",
    "sg:city":"Nashville",
    "sg:classifiers":[
        {
            "category":"Food & Beverages",
            "subcategory":"Groceries & Convenience Stores",
            "type":"Retail Goods"
        }
    ],
    "sg:phone":"+1 615 889 3326",
    "sg:postcode":"37214",
    "sg:province":"TN",
    "wof:name":"Mapco Express",
    "wof:placetype":"venue"
},
  "geometry": {"coordinates":[-86.683977,36.153135],"type":"Point"}
}