{
  "type": "Feature",
  "properties": {
    "iso:country":"US",
    "sg:address":"7325 Braden Rd",
    "sg:city":"Arlington",
    "sg:classifiers":[
        {
            "category":"Professional",
            "subcategory":"Business Services",
            "type":"Services"
        }
    ],
    "sg:phone":"+1 901 465 1920",
    "sg:postcode":"38002",
    "sg:province":"TN",
    "wof:name":"BLT Express LLC",
    "wof:placetype":"venue"
},
  "geometry": {"coordinates":[-89.581868,35.275807],"type":"Point"}
}