{
  "type": "Feature",
  "properties": {
    "addr:full":"353 Washington College Station Rd Limestone TN 37681",
    "addr:housenumber":"353",
    "addr:postcode":"37681",
    "addr:street":"Washington College Station Rd",
    "iso:country":"US",
    "sg:address":"353 Washington College Station Rd",
    "sg:city":"Limestone",
    "sg:classifiers":[
        {
            "category":"Freight",
            "type":"Transportation"
        }
    ],
    "sg:phone":"+1 423 257 6877",
    "sg:postcode":"37681",
    "sg:province":"TN",
    "sg:tags":[
        "trucking"
    ],
    "wof:name":"Mc Curry's Trucking",
    "wof:placetype":"venue"
},
  "geometry": {"coordinates":[-82.587045,36.244896],"type":"Point"}
}