{
  "type": "Feature",
  "properties": {
    "addr:full":"2501 Park Plz Nashville TN 37203",
    "addr:housenumber":"2501",
    "addr:postcode":"37203",
    "addr:street":"Park Plz",
    "iso:country":"US",
    "sg:address":"2501 Park Plz",
    "sg:city":"Nashville",
    "sg:classifiers":[
        {
            "category":"Utilities",
            "subcategory":"Telephone",
            "type":"Services"
        }
    ],
    "sg:phone":"+1 615 344 5288",
    "sg:postcode":"37203",
    "sg:province":"TN",
    "wof:name":"Southwestern Bell Telephone LP",
    "wof:placetype":"venue"
},
  "geometry": {"coordinates":[-86.816754,36.150736],"type":"Point"}
}