{
  "type": "Feature",
  "properties": {
    "iso:country":"US",
    "sg:address":"6105 Preservation Dr",
    "sg:city":"Chattanooga",
    "sg:classifiers":[
        {
            "category":"Professional",
            "subcategory":"Engineering",
            "type":"Services"
        }
    ],
    "sg:phone":"+1 423 664 4411",
    "sg:postcode":"37416",
    "sg:province":"TN",
    "wof:name":"Western Anatec Inc",
    "wof:placetype":"venue"
},
  "geometry": {"coordinates":[-85.18792,35.075575],"type":"Point"}
}