{
  "type": "Feature",
  "properties": {
    "iso:country":"US",
    "sg:address":"1959 Fort Campbell Blvd",
    "sg:city":"Clarksville",
    "sg:classifiers":[
        {
            "category":"Freight",
            "type":"Transportation"
        }
    ],
    "sg:phone":"+1 931 648 4945",
    "sg:postcode":"37042",
    "sg:province":"TN",
    "sg:tags":[
        "commercial",
        "storage",
        "special",
        "general"
    ],
    "wof:name":"Ringgold Mini Storage",
    "wof:placetype":"venue"
},
  "geometry": {"coordinates":[-87.416563,36.592314],"type":"Point"}
}