{
  "type": "Feature",
  "properties": {
    "iso:country":"US",
    "sg:address":"35 Seaton Loop",
    "sg:city":"Adamsville",
    "sg:classifiers":[
        {
            "category":"Autos & Motor Vehicles",
            "subcategory":"Automobile Sales",
            "type":"Retail Goods"
        }
    ],
    "sg:phone":"+1 731 632 5104",
    "sg:postcode":"38310",
    "sg:province":"TN",
    "sg:tags":[
        "used"
    ],
    "wof:name":"Crump Auto Sales",
    "wof:placetype":"venue"
},
  "geometry": {"coordinates":[-88.338756,35.22439],"type":"Point"}
}