{
  "type": "Feature",
  "properties": {
    "iso:country":"US",
    "sg:address":"345 Self Hollow Rd",
    "sg:city":"Rockford",
    "sg:classifiers":[
        {
            "category":"Retail",
            "subcategory":"Repair Shop",
            "type":"Services"
        }
    ],
    "sg:phone":"+1 865 984 5960",
    "sg:postcode":"37853",
    "sg:province":"TN",
    "sg:tags":[
        "refrigeration",
        "electrical"
    ],
    "wof:name":"Dailey Appliance Service",
    "wof:placetype":"venue"
},
  "geometry": {"coordinates":[-83.92941399999999,35.834569],"type":"Point"}
}