{
  "type": "Feature",
  "properties": {
    "iso:country":"US",
    "sg:address":"4798 Summer Ave",
    "sg:city":"Memphis",
    "sg:classifiers":[
        {
            "category":"Wholesale",
            "subcategory":"Electrical",
            "type":"Manufacturing & Wholesale Goods"
        }
    ],
    "sg:phone":"+1 901 682 2426",
    "sg:postcode":"38122",
    "sg:province":"TN",
    "sg:tags":[
        "lighting",
        "fixture"
    ],
    "wof:name":"Lighting Inc",
    "wof:placetype":"venue"
},
  "geometry": {"coordinates":[-89.8991,35.148597],"type":"Point"}
}