{
  "type": "Feature",
  "properties": {
    "iso:country":"US",
    "sg:address":"53 Tremont Pl",
    "sg:city":"Bristol",
    "sg:classifiers":[
        {
            "category":"Building & Trades",
            "subcategory":"Construction",
            "type":"Services"
        }
    ],
    "sg:phone":"+1 423 764 1435",
    "sg:postcode":"37620",
    "sg:province":"TN",
    "sg:tags":[
        "house",
        "siding",
        "contractor"
    ],
    "wof:name":"C & S Home Improvements",
    "wof:placetype":"venue"
},
  "geometry": {"coordinates":[-82.183168,36.573075],"type":"Point"}
}