{
  "type": "Feature",
  "properties": {
    "iso:country":"US",
    "sg:address":"1510 Hamilton Ave",
    "sg:city":"Chattanooga",
    "sg:classifiers":[
        {
            "category":"Education",
            "subcategory":"School",
            "type":"Public Place"
        }
    ],
    "sg:phone":"+1 423 757 4756",
    "sg:postcode":"37405",
    "sg:province":"TN",
    "wof:name":"Head Start",
    "wof:placetype":"venue"
},
  "geometry": {"coordinates":[-85.307249,35.079085],"type":"Point"}
}