{
  "type": "Feature",
  "properties": {
    "iso:country":"US",
    "sg:address":"119 N 3rd St",
    "sg:city":"Clarksville",
    "sg:classifiers":[
        {
            "category":"Government",
            "subcategory":"Office",
            "type":"Public Place"
        }
    ],
    "sg:phone":"+1 931 648 5516",
    "sg:postcode":"37040",
    "sg:province":"TN",
    "sg:tags":[
        "state",
        "resource"
    ],
    "wof:name":"Department Of Children's Svc",
    "wof:placetype":"venue"
},
  "geometry": {"coordinates":[-87.357894,36.528145],"type":"Point"}
}