{
  "type": "Feature",
  "properties": {
    "addr:full":"220 S Peters Rd Knoxville TN 37923",
    "addr:housenumber":"220",
    "addr:postcode":"37923",
    "addr:street":"S Peters Rd",
    "iso:country":"US",
    "sg:address":"220 S Peters Rd",
    "sg:city":"Knoxville",
    "sg:classifiers":[
        {
            "category":"Insurance",
            "subcategory":"Insurance Agent",
            "type":"Services"
        }
    ],
    "sg:phone":"+1 865 693 7676",
    "sg:postcode":"37923",
    "sg:province":"TN",
    "wof:name":"Allstate",
    "wof:placetype":"venue"
},
  "geometry": {"coordinates":[-84.079525,35.909323],"type":"Point"}
}