{
  "type": "Feature",
  "properties": {
    "addr:full":"13145 State Hwy 69A Big Sandy TN 38221",
    "addr:housenumber":"13145",
    "addr:postcode":"38221",
    "addr:street":"State Hwy 69A",
    "iso:country":"US",
    "sg:address":"13145 State Hwy 69A",
    "sg:city":"Big Sandy",
    "sg:classifiers":[
        {
            "category":"Autos & Motor Vehicles",
            "subcategory":"Boat Sales",
            "type":"Retail Goods"
        }
    ],
    "sg:phone":"+1 731 593 1148",
    "sg:postcode":"38221",
    "sg:province":"TN",
    "wof:name":"Big Sandy Auto & Mar Sls & Svc",
    "wof:placetype":"venue"
},
  "geometry": {"coordinates":[-88.085341,36.228156],"type":"Point"}
}