{
  "type": "Feature",
  "properties": {
    "addr:full":"1132 Snowdon Dr NE Knoxville TN 37912",
    "addr:housenumber":"1132",
    "addr:postcode":"37912",
    "addr:street":"Snowdon Dr Ne",
    "iso:country":"US",
    "sg:address":"1132 Snowdon Dr NE",
    "sg:city":"Knoxville",
    "sg:classifiers":[
        {
            "category":"Mining & Drilling",
            "type":"Manufacturing & Wholesale Goods"
        }
    ],
    "sg:phone":"+1 865 687 3926",
    "sg:postcode":"37912",
    "sg:province":"TN",
    "sg:tags":[
        "stone"
    ],
    "wof:name":"Stone Northern",
    "wof:placetype":"venue"
},
  "geometry": {"coordinates":[-83.962041,36.033361],"type":"Point"}
}