{
  "type": "Feature",
  "properties": {
    "iso:country":"US",
    "sg:address":"241 Old Humboldt Rd",
    "sg:city":"Jackson",
    "sg:classifiers":[
        {
            "category":"Building & Trades",
            "subcategory":"Construction",
            "type":"Services"
        }
    ],
    "sg:phone":"+1 731 664 6648",
    "sg:postcode":"38305",
    "sg:province":"TN",
    "sg:tags":[
        "residential"
    ],
    "wof:name":"Cross Creek Partners",
    "wof:placetype":"venue"
},
  "geometry": {"coordinates":[-88.84004299999999,35.686749],"type":"Point"}
}