{
  "type": "Feature",
  "properties": {
    "iso:country":"US",
    "sg:address":"9840 Hwy 641 S",
    "sg:city":"Holladay",
    "sg:classifiers":[
        {
            "category":"Building & Trades",
            "subcategory":"Construction",
            "type":"Services"
        }
    ],
    "sg:phone":"+1 731 584 5054",
    "sg:postcode":"38341",
    "sg:province":"TN",
    "sg:tags":[
        "excavating",
        "contractor"
    ],
    "wof:name":"Ken Love Excavating Inc",
    "wof:placetype":"venue"
},
  "geometry": {"coordinates":[-88.103504,35.916007],"type":"Point"}
}