{
  "type": "Feature",
  "properties": {
    "iso:country":"US",
    "sg:address":"9111 Cross Park Dr NW",
    "sg:city":"Knoxville",
    "sg:classifiers":[
        {
            "category":"Education",
            "subcategory":"Vocational School",
            "type":"Public Place"
        }
    ],
    "sg:phone":"+1 865 691 1515",
    "sg:postcode":"37923",
    "sg:province":"TN",
    "sg:tags":[
        "training",
        "computer"
    ],
    "sg:website":"www.nhknoxville.com",
    "wof:name":"New Horizons Computer Learning",
    "wof:placetype":"venue"
},
  "geometry": {"coordinates":[-84.091486,35.920967],"type":"Point"}
}