{
  "type": "Feature",
  "properties": {
    "addr:full":"197 Welch Rd Nashville TN 37211",
    "addr:housenumber":"197",
    "addr:postcode":"37211",
    "addr:street":"Welch Rd",
    "iso:country":"US",
    "sg:address":"197 Welch Rd",
    "sg:city":"Nashville",
    "sg:classifiers":[
        {
            "category":"Real Estate",
            "subcategory":"Real Estate Agent",
            "type":"Services"
        }
    ],
    "sg:phone":"+1 615 333 4629",
    "sg:postcode":"37211",
    "sg:province":"TN",
    "sg:tags":[
        "inspection"
    ],
    "wof:name":"Davidson Home Examination",
    "wof:placetype":"venue"
},
  "geometry": {"coordinates":[-86.717324,36.081071],"type":"Point"}
}