{
  "type": "Feature",
  "properties": {
    "addr:full":"707 Main St Nashville TN 37206",
    "addr:housenumber":"707",
    "addr:postcode":"37206",
    "addr:street":"Main St",
    "iso:country":"US",
    "sg:address":"707 Main St",
    "sg:city":"Nashville",
    "sg:classifiers":[
        {
            "category":"Shopping",
            "subcategory":"Clothing, Apparel, & Fashions",
            "type":"Retail Goods"
        }
    ],
    "sg:phone":"+1 615 822 6973",
    "sg:postcode":"37206",
    "sg:province":"TN",
    "sg:tags":[
        "alteration"
    ],
    "wof:name":"Hendersonville Alterations",
    "wof:placetype":"venue"
},
  "geometry": {"coordinates":[-86.759378,36.175216],"type":"Point"}
}