{
  "type": "Feature",
  "properties": {
    "iso:country":"US",
    "sg:address":"806 E Main St",
    "sg:city":"Henderson",
    "sg:classifiers":[
        {
            "category":"Restaurant",
            "type":"Food & Drink"
        }
    ],
    "sg:phone":"+1 731 989 3490",
    "sg:postcode":"38340",
    "sg:province":"TN",
    "sg:tags":[
        "eating"
    ],
    "wof:name":"Snookum's Beef House",
    "wof:placetype":"venue"
},
  "geometry": {"coordinates":[-88.617093,35.445178],"type":"Point"}
}