{
  "type": "Feature",
  "properties": {
    "iso:country":"US",
    "sg:address":"935 Edgehill Ave",
    "sg:city":"Nashville",
    "sg:classifiers":[
        {
            "category":"Social Services",
            "type":"Services"
        }
    ],
    "sg:phone":"+1 615 256 5108",
    "sg:postcode":"37203",
    "sg:province":"TN",
    "sg:tags":[
        "center",
        "community"
    ],
    "wof:name":"Edgehill Center Inc",
    "wof:placetype":"venue"
},
  "geometry": {"coordinates":[-86.78188900000001,36.141969],"type":"Point"}
}