{
  "type": "Feature",
  "properties": {
    "addr:full":"359 W Main St Alamo TN 38001",
    "addr:housenumber":"359",
    "addr:postcode":"38001",
    "addr:street":"W Main St",
    "iso:country":"US",
    "sg:address":"359 W Main St",
    "sg:city":"Alamo",
    "sg:classifiers":[
        {
            "category":"Wholesale",
            "subcategory":"Farm Supplies",
            "type":"Manufacturing & Wholesale Goods"
        }
    ],
    "sg:phone":"+1 731 696 5527",
    "sg:postcode":"38001",
    "sg:province":"TN",
    "wof:name":"Mid South Farmers Co-Op",
    "wof:placetype":"venue"
},
  "geometry": {"coordinates":[-89.13046300000001,35.785315],"type":"Point"}
}