{
  "type": "Feature",
  "properties": {
    "iso:country":"US",
    "sg:address":"8640 Dayton Pike",
    "sg:city":"Soddy Daisy",
    "sg:classifiers":[
        {
            "category":"Food & Beverages",
            "subcategory":"Groceries & Convenience Stores",
            "type":"Retail Goods"
        }
    ],
    "sg:phone":"+1 423 332 6943",
    "sg:postcode":"37379",
    "sg:province":"TN",
    "sg:tags":[
        "station",
        "gas"
    ],
    "wof:name":"Golden Gallon 181",
    "wof:placetype":"venue"
},
  "geometry": {"coordinates":[-85.22136500000001,35.221819],"type":"Point"}
}