{
  "type": "Feature",
  "properties": {
    "addr:full":"7039 Maynardville Pike Knoxville TN 37918",
    "addr:housenumber":"7039",
    "addr:postcode":"37918",
    "addr:street":"Maynardville Pike",
    "iso:country":"US",
    "sg:address":"7039 Maynardville Pike",
    "sg:city":"Knoxville",
    "sg:classifiers":[
        {
            "category":"Insurance",
            "subcategory":"Insurance Agent",
            "type":"Services"
        }
    ],
    "sg:phone":"+1 865 922 4663",
    "sg:postcode":"37918",
    "sg:province":"TN",
    "wof:name":"Allstate",
    "wof:placetype":"venue"
},
  "geometry": {"coordinates":[-83.927832,36.076135],"type":"Point"}
}