{
  "type": "Feature",
  "properties": {
    "iso:country":"US",
    "sg:address":"56 Airport Rd",
    "sg:city":"Milan",
    "sg:classifiers":[
        {
            "category":"Airport",
            "type":"Transportation"
        }
    ],
    "sg:phone":"+1 731 723 9596",
    "sg:postcode":"38358",
    "sg:province":"TN",
    "wof:name":"Gibson County Airport",
    "wof:placetype":"venue"
},
  "geometry": {"coordinates":[-88.850357,35.938634],"type":"Point"}
}