{
  "type": "Feature",
  "properties": {
    "iso:country":"US",
    "sg:address":"2581 Forge Ridge Rd",
    "sg:city":"Harrogate",
    "sg:classifiers":[
        {
            "category":"Autos & Motor Vehicles",
            "subcategory":"Auto Supplies",
            "type":"Retail Goods"
        }
    ],
    "sg:phone":"+1 423 869 5377",
    "sg:postcode":"37752",
    "sg:province":"TN",
    "sg:tags":[
        "equipment",
        "racing",
        "car",
        "automobile"
    ],
    "wof:name":"Flying B Hot Rods Inc",
    "wof:placetype":"venue"
},
  "geometry": {"coordinates":[-83.587261,36.576346],"type":"Point"}
}