{
  "type": "Feature",
  "properties": {
    "iso:country":"US",
    "sg:address":"4621 State Hwy 58",
    "sg:city":"Chattanooga",
    "sg:classifiers":[
        {
            "category":"Utilities",
            "subcategory":"Mobile Phone",
            "type":"Services"
        }
    ],
    "sg:phone":"+1 423 485 1100",
    "sg:postcode":"37416",
    "sg:province":"TN",
    "sg:tags":[
        "repair",
        "beeper"
    ],
    "wof:name":"Satellite Page Inc",
    "wof:placetype":"venue"
},
  "geometry": {"coordinates":[-85.192387,35.086071],"type":"Point"}
}