{
  "type": "Feature",
  "properties": {
    "iso:country":"US",
    "sg:address":"109 Lane Pkwy",
    "sg:city":"Shelbyville",
    "sg:classifiers":[
        {
            "category":"Government",
            "subcategory":"Police Station",
            "type":"Public Place"
        }
    ],
    "sg:phone":"+1 931 684 8787",
    "sg:postcode":"37160",
    "sg:province":"TN",
    "sg:tags":[
        "department"
    ],
    "wof:name":"Shelbyville Police Chief",
    "wof:placetype":"venue"
},
  "geometry": {"coordinates":[-86.464191,35.485397],"type":"Point"}
}