{
  "type": "Feature",
  "properties": {
    "iso:country":"US",
    "sg:address":"875 Linden Ave",
    "sg:city":"Memphis",
    "sg:classifiers":[
        {
            "category":"Real Estate",
            "subcategory":"Real Estate Operator",
            "type":"Services"
        }
    ],
    "sg:phone":"+1 901 521 1828",
    "sg:postcode":"38126",
    "sg:province":"TN",
    "sg:tags":[
        "building",
        "apartment"
    ],
    "wof:name":"Independent Apartments Inc",
    "wof:placetype":"venue"
},
  "geometry": {"coordinates":[-90.03127000000001,35.135198],"type":"Point"}
}