{
  "type": "Feature",
  "properties": {
    "iso:country":"US",
    "sg:address":"5670 Palestine Rd",
    "sg:city":"Henry",
    "sg:classifiers":[
        {
            "category":"Retail",
            "subcategory":"Repair Shop",
            "type":"Services"
        }
    ],
    "sg:phone":"+1 731 243 2640",
    "sg:postcode":"38231",
    "sg:province":"TN",
    "wof:name":"Swareys Enterprises",
    "wof:placetype":"venue"
},
  "geometry": {"coordinates":[-88.42424800000001,36.244728],"type":"Point"}
}