{
  "type": "Feature",
  "properties": {
    "addr:full":"408 Madison St Clarksville TN 37040",
    "addr:housenumber":"408",
    "addr:postcode":"37040",
    "addr:street":"Madison St",
    "iso:country":"US",
    "sg:address":"408 Madison St",
    "sg:city":"Clarksville",
    "sg:classifiers":[
        {
            "category":"Organizations",
            "subcategory":"Religious Organization",
            "type":"Services"
        }
    ],
    "sg:phone":"+1 931 645 5781",
    "sg:postcode":"37040",
    "sg:province":"TN",
    "sg:tags":[
        "church"
    ],
    "sg:website":"www.clcelca.org",
    "wof:name":"Christ Lutheran Church-Elca",
    "wof:placetype":"venue"
},
  "geometry": {"coordinates":[-87.355299,36.525696],"type":"Point"}
}