{
  "type": "Feature",
  "properties": {
    "iso:country":"US",
    "sg:address":"511 Courtland St",
    "sg:city":"Murfreesboro",
    "sg:classifiers":[
        {
            "category":"Arts & Performance",
            "subcategory":"Theater",
            "type":"Entertainment"
        }
    ],
    "sg:phone":"+1 615 217 0648",
    "sg:postcode":"37130",
    "sg:province":"TN",
    "sg:tags":[
        "group"
    ],
    "wof:name":"Kustom Home Entertainment",
    "wof:placetype":"venue"
},
  "geometry": {"coordinates":[-86.38716100000001,35.850784],"type":"Point"}
}