{
  "type": "Feature",
  "properties": {
    "addr:full":"719 Thompson Ln Ste 100 Nashville TN 37204",
    "addr:housenumber":"719",
    "addr:postcode":"37204",
    "addr:street":"Thompson Ln Ste 100",
    "iso:country":"US",
    "sg:address":"719 Thompson Ln Ste 100",
    "sg:city":"Nashville",
    "sg:classifiers":[
        {
            "category":"Shopping",
            "subcategory":"Department Store",
            "type":"Retail Goods"
        }
    ],
    "sg:phone":"+1 615 386 0023",
    "sg:postcode":"37204",
    "sg:province":"TN",
    "wof:name":"Off Fifth",
    "wof:placetype":"venue"
},
  "geometry": {"coordinates":[-86.76531199999999,36.112129],"type":"Point"}
}