{
  "type": "Feature",
  "properties": {
    "addr:full":"4115 Ringgold Rd Chattanooga TN 37412",
    "addr:housenumber":"4115",
    "addr:postcode":"37412",
    "addr:street":"Ringgold Rd",
    "iso:country":"US",
    "sg:address":"4115 Ringgold Rd",
    "sg:city":"Chattanooga",
    "sg:classifiers":[
        {
            "category":"Shopping",
            "subcategory":"Discount & Variety Stores",
            "type":"Retail Goods"
        }
    ],
    "sg:phone":"+1 423 698 2573",
    "sg:postcode":"37412",
    "sg:province":"TN",
    "sg:tags":[
        "merchandise",
        "general"
    ],
    "wof:name":"Merchandise Outlet",
    "wof:placetype":"venue"
},
  "geometry": {"coordinates":[-85.246207,34.997547],"type":"Point"}
}