{
  "type": "Feature",
  "properties": {
    "addr:full":"1202 Murfreesboro Rd Franklin TN 37064",
    "addr:housenumber":"1202",
    "addr:postcode":"37064",
    "addr:street":"Murfreesboro Rd",
    "iso:country":"US",
    "sg:address":"1202 Murfreesboro Rd",
    "sg:city":"Franklin",
    "sg:classifiers":[
        {
            "category":"Food & Beverages",
            "subcategory":"Groceries & Convenience Stores",
            "type":"Retail Goods"
        }
    ],
    "sg:phone":"+1 615 791 6259",
    "sg:postcode":"37064",
    "sg:province":"TN",
    "sg:tags":[
        "grocer"
    ],
    "wof:name":"Bi-Lo",
    "wof:placetype":"venue"
},
  "geometry": {"coordinates":[-86.831491,35.91562],"type":"Point"}
}