{
  "type": "Feature",
  "properties": {
    "iso:country":"US",
    "sg:address":"200 E Main St",
    "sg:city":"Brownsville",
    "sg:classifiers":[
        {
            "category":"Shopping",
            "subcategory":"Pharmacy",
            "type":"Retail Goods"
        }
    ],
    "sg:phone":"+1 731 772 5466",
    "sg:postcode":"38012",
    "sg:province":"TN",
    "sg:tags":[
        "drug",
        "store"
    ],
    "wof:name":"Super D Express",
    "wof:placetype":"venue"
},
  "geometry": {"coordinates":[-89.25975,35.593674],"type":"Point"}
}