{
  "type": "Feature",
  "properties": {
    "iso:country":"US",
    "sg:address":"512 E Stone Dr",
    "sg:city":"Kingsport",
    "sg:classifiers":[
        {
            "category":"Autos & Motor Vehicles",
            "subcategory":"Automobile Sales",
            "type":"Retail Goods"
        }
    ],
    "sg:phone":"+1 423 378 3418",
    "sg:postcode":"37660",
    "sg:province":"TN",
    "sg:tags":[
        "car",
        "used",
        "dealer"
    ],
    "wof:name":"Wade's Motors",
    "wof:placetype":"venue"
},
  "geometry": {"coordinates":[-82.542698,36.55866],"type":"Point"}
}