{
  "type": "Feature",
  "properties": {
    "addr:full":"317 Main St Franklin TN 37064",
    "addr:housenumber":"317",
    "addr:postcode":"37064",
    "addr:street":"Main St",
    "iso:country":"US",
    "sg:address":"317 Main St",
    "sg:city":"Franklin",
    "sg:classifiers":[
        {
            "category":"Wholesale",
            "subcategory":"Non-durable Goods",
            "type":"Manufacturing & Wholesale Goods"
        }
    ],
    "sg:phone":"+1 615 791 7895",
    "sg:postcode":"37064",
    "sg:province":"TN",
    "sg:tags":[
        "religious"
    ],
    "wof:name":"Evangecube International",
    "wof:placetype":"venue"
},
  "geometry": {"coordinates":[-86.86924999999999,35.924951],"type":"Point"}
}