{
  "type": "Feature",
  "properties": {
    "iso:country":"US",
    "sg:address":"603 N 22nd Ave",
    "sg:city":"Humboldt",
    "sg:classifiers":[
        {
            "category":"Autos & Motor Vehicles",
            "subcategory":"Automobile Sales",
            "type":"Retail Goods"
        }
    ],
    "sg:phone":"+1 731 784 2002",
    "sg:postcode":"38343",
    "sg:province":"TN",
    "sg:tags":[
        "used"
    ],
    "wof:name":"Gary Caraway Motor Co",
    "wof:placetype":"venue"
},
  "geometry": {"coordinates":[-88.907382,35.826374],"type":"Point"}
}