{
  "type": "Feature",
  "properties": {
    "addr:full":"3302 Elam Rd Murfreesboro TN 37127",
    "addr:housenumber":"3302",
    "addr:postcode":"37127",
    "addr:street":"Elam Rd",
    "iso:country":"US",
    "sg:address":"3302 Elam Rd",
    "sg:city":"Murfreesboro",
    "sg:classifiers":[
        {
            "category":"Farming",
            "subcategory":"Livestock Farm",
            "type":"Manufacturing & Wholesale Goods"
        }
    ],
    "sg:phone":"+1 615 896 2216",
    "sg:postcode":"37127",
    "sg:province":"TN",
    "sg:tags":[
        "beef",
        "feedlot",
        "cattle"
    ],
    "wof:name":"Elam Farms",
    "wof:placetype":"venue"
},
  "geometry": {"coordinates":[-86.376413,35.783291],"type":"Point"}
}