{
  "type": "Feature",
  "properties": {
    "iso:country":"US",
    "sg:address":"204 Creek Trl",
    "sg:city":"Columbia",
    "sg:classifiers":[
        {
            "category":"Shopping",
            "type":"Retail Goods"
        }
    ],
    "sg:phone":"+1 615 944 5777",
    "sg:postcode":"38401",
    "sg:province":"TN",
    "sg:tags":[
        "pet",
        "shop"
    ],
    "wof:name":"Authentic New Wave",
    "wof:placetype":"venue"
},
  "geometry": {"coordinates":[-87.02286599999999,35.642131],"type":"Point"}
}