{
  "type": "Feature",
  "properties": {
    "addr:full":"650 25th St NW Cleveland TN 37311",
    "addr:housenumber":"650",
    "addr:postcode":"37311",
    "addr:street":"25Th St Nw",
    "iso:country":"US",
    "sg:address":"650 25th St NW",
    "sg:city":"Cleveland",
    "sg:classifiers":[
        {
            "category":"Banks & Credit Unions",
            "subcategory":"Bank",
            "type":"Services"
        }
    ],
    "sg:phone":"+1 423 559 0911",
    "sg:postcode":"37311",
    "sg:province":"TN",
    "sg:tags":[
        "mortgage",
        "loan",
        "broker",
        "real estate"
    ],
    "wof:name":"Capital Home Equity",
    "wof:placetype":"venue"
},
  "geometry": {"coordinates":[-84.871832,35.181819],"type":"Point"}
}