{
  "type": "Feature",
  "properties": {
    "iso:country":"US",
    "sg:address":"430 W Adams St",
    "sg:city":"Woodbury",
    "sg:classifiers":[
        {
            "category":"Restaurant",
            "type":"Food & Drink"
        }
    ],
    "sg:phone":"+1 615 563 2583",
    "sg:postcode":"37190",
    "sg:province":"TN",
    "sg:tags":[
        "eating"
    ],
    "wof:name":"Woodbury Cafeteria",
    "wof:placetype":"venue"
},
  "geometry": {"coordinates":[-86.072357,35.820823],"type":"Point"}
}