{
  "type": "Feature",
  "properties": {
    "addr:full":"1412 Hardwood Trl Cordova TN 38016",
    "addr:housenumber":"1412",
    "addr:postcode":"38016",
    "addr:street":"Hardwood Trl",
    "iso:country":"US",
    "sg:address":"1412 Hardwood Trl",
    "sg:city":"Cordova",
    "sg:classifiers":[
        {
            "category":"Shopping",
            "subcategory":"Clothing, Apparel, & Fashions",
            "type":"Retail Goods"
        }
    ],
    "sg:phone":"+1 901 634 4655",
    "sg:postcode":"38016",
    "sg:province":"TN",
    "wof:name":"Change of Seasons",
    "wof:placetype":"venue"
},
  "geometry": {"coordinates":[-89.786023,35.164258],"type":"Point"}
}