{
  "type": "Feature",
  "properties": {
    "iso:country":"US",
    "sg:address":"9222 Old State Hwy 13",
    "sg:city":"Hurricane Mills",
    "sg:classifiers":[
        {
            "category":"Building & Trades",
            "subcategory":"Construction",
            "type":"Services"
        }
    ],
    "sg:phone":"+1 931 296 4661",
    "sg:postcode":"37078",
    "sg:province":"TN",
    "sg:tags":[
        "commercial"
    ],
    "wof:name":"Davis Construction",
    "wof:placetype":"venue"
},
  "geometry": {"coordinates":[-87.836386,35.930676],"type":"Point"}
}