{
  "type": "Feature",
  "properties": {
    "iso:country":"US",
    "sg:address":"1613 Buchanan St",
    "sg:city":"Nashville",
    "sg:classifiers":[
        {
            "category":"Food & Beverages",
            "subcategory":"Liquor & Beverages",
            "type":"Retail Goods"
        }
    ],
    "sg:phone":"+1 615 400 4191",
    "sg:postcode":"37208",
    "sg:province":"TN",
    "wof:name":"Northside Liquor Store",
    "wof:placetype":"venue"
},
  "geometry": {"coordinates":[-86.81036,36.179974],"type":"Point"}
}