{
  "type": "Feature",
  "properties": {
    "iso:country":"US",
    "sg:address":"505 Indian Lake Rd",
    "sg:city":"Hendersonville",
    "sg:classifiers":[
        {
            "category":"Shopping",
            "type":"Retail Goods"
        }
    ],
    "sg:phone":"+1 615 826 6055",
    "sg:postcode":"37075",
    "sg:province":"TN",
    "sg:tags":[
        "merchandise"
    ],
    "wof:name":"Nextel",
    "wof:placetype":"venue"
},
  "geometry": {"coordinates":[-86.585705,36.271438],"type":"Point"}
}