{
  "type": "Feature",
  "properties": {
    "iso:country":"US",
    "sg:address":"1330 Cedar Ln",
    "sg:city":"Tullahoma",
    "sg:classifiers":[
        {
            "category":"Health Services",
            "subcategory":"Doctor",
            "type":"Services"
        }
    ],
    "sg:phone":"+1 931 393 3366",
    "sg:postcode":"37388",
    "sg:province":"TN",
    "sg:tags":[
        "physician",
        "surgeon"
    ],
    "wof:name":"Rimda Gupta MD",
    "wof:placetype":"venue"
},
  "geometry": {"coordinates":[-86.232789,35.376711],"type":"Point"}
}