{
  "type": "Feature",
  "properties": {
    "iso:country":"US",
    "sg:address":"100 N Main St",
    "sg:city":"Memphis",
    "sg:classifiers":[
        {
            "category":"Professional",
            "subcategory":"Lawyer & Legal Services",
            "type":"Services"
        }
    ],
    "sg:phone":"+1 901 525 6804",
    "sg:postcode":"38103",
    "sg:province":"TN",
    "sg:tags":[
        "attorney"
    ],
    "wof:name":"Weiss Miller & Weiss",
    "wof:placetype":"venue"
},
  "geometry": {"coordinates":[-90.051801,35.147461],"type":"Point"}
}