{
  "type": "Feature",
  "properties": {
    "addr:full":"944 Battery Ln Nashville TN 37220",
    "addr:housenumber":"944",
    "addr:postcode":"37220",
    "addr:street":"Battery Ln",
    "iso:country":"US",
    "sg:address":"944 Battery Ln",
    "sg:city":"Nashville",
    "sg:classifiers":[
        {
            "category":"Professional",
            "subcategory":"Business Services",
            "type":"Services"
        }
    ],
    "sg:phone":"+1 615 383 8274",
    "sg:postcode":"37220",
    "sg:province":"TN",
    "wof:name":"Mark Adkison",
    "wof:placetype":"venue"
},
  "geometry": {"coordinates":[-86.790808,36.08838],"type":"Point"}
}