{
  "type": "Feature",
  "properties": {
    "addr:full":"8930 Snowhill Rd Ooltewah TN 37363",
    "addr:postcode":"8930;37363",
    "addr:street":"Snowhill Rd",
    "iso:country":"US",
    "sg:address":"8930 Snowhill Rd",
    "sg:city":"Ooltewah",
    "sg:classifiers":[
        {
            "category":"Professional",
            "subcategory":"Business Services",
            "type":"Services"
        }
    ],
    "sg:phone":"+1 423 344 0651",
    "sg:postcode":"37363",
    "sg:province":"TN",
    "wof:name":"Advantage Home Inspection Inc",
    "wof:placetype":"venue"
},
  "geometry": {"coordinates":[-85.052273,35.176596],"type":"Point"}
}