{
  "type": "Feature",
  "properties": {
    "addr:full":"149 Wallace Rd Luttrell TN 37779",
    "addr:housenumber":"149",
    "addr:postcode":"37779",
    "addr:street":"Wallace Rd",
    "iso:country":"US",
    "sg:address":"149 Wallace Rd",
    "sg:city":"Luttrell",
    "sg:classifiers":[
        {
            "category":"Government",
            "subcategory":"Office",
            "type":"Public Place"
        }
    ],
    "sg:phone":"+1 865 278 4007",
    "sg:postcode":"37779",
    "sg:province":"TN",
    "sg:tags":[
        "county",
        "program"
    ],
    "wof:name":"Union County Solid Waste Auth",
    "wof:placetype":"venue"
},
  "geometry": {"coordinates":[-83.798087,36.184946],"type":"Point"}
}