{
  "type": "Feature",
  "properties": {
    "iso:country":"US",
    "sg:address":"644 Trevor Dr",
    "sg:city":"Kingsport",
    "sg:classifiers":[
        {
            "category":"Professional",
            "type":"Services"
        }
    ],
    "sg:phone":"+1 423 378 5268",
    "sg:postcode":"37660",
    "sg:province":"TN",
    "wof:name":"Gary Lark",
    "wof:placetype":"venue"
},
  "geometry": {"coordinates":[-82.54650100000001,36.580954],"type":"Point"}
}