{
  "type": "Feature",
  "properties": {
    "iso:country":"US",
    "sg:address":"1266 Getwell Rd",
    "sg:city":"Memphis",
    "sg:classifiers":[
        {
            "category":"Shopping",
            "subcategory":"Clothing, Apparel, & Fashions",
            "type":"Retail Goods"
        }
    ],
    "sg:phone":"+1 901 744 8944",
    "sg:postcode":"38111",
    "sg:province":"TN",
    "sg:tags":[
        "uniform"
    ],
    "wof:name":"Uniform Outlet",
    "wof:placetype":"venue"
},
  "geometry": {"coordinates":[-89.930831,35.098048],"type":"Point"}
}