{
  "type": "Feature",
  "properties": {
    "iso:country":"US",
    "sg:address":"400 Squirrel Hollow Dr",
    "sg:city":"Linden",
    "sg:classifiers":[
        {
            "category":"Restaurant",
            "type":"Food & Drink"
        }
    ],
    "sg:phone":"+1 931 589 2921",
    "sg:postcode":"37096",
    "sg:province":"TN",
    "wof:name":"B & H Drive Inn",
    "wof:placetype":"venue"
},
  "geometry": {"coordinates":[-87.866632,35.592821],"type":"Point"}
}