{
  "type": "Feature",
  "properties": {
    "iso:country":"US",
    "sg:address":"7723 Clinton Hwy",
    "sg:city":"Powell",
    "sg:classifiers":[
        {
            "category":"Retail",
            "subcategory":"Auto Repair",
            "type":"Services"
        }
    ],
    "sg:phone":"+1 865 938 2950",
    "sg:postcode":"37849",
    "sg:province":"TN",
    "sg:tags":[
        "repairing",
        "automobile"
    ],
    "wof:name":"Denton's Garage",
    "wof:placetype":"venue"
},
  "geometry": {"coordinates":[-84.059212,36.024209],"type":"Point"}
}