{
  "type": "Feature",
  "properties": {
    "iso:country":"US",
    "sg:address":"830 Crescent Centre Dr",
    "sg:city":"Franklin",
    "sg:classifiers":[
        {
            "category":"Manufacturing",
            "subcategory":"Metals",
            "type":"Manufacturing & Wholesale Goods"
        }
    ],
    "sg:phone":"+1 615 771 4360",
    "sg:postcode":"37067",
    "sg:province":"TN",
    "sg:tags":[
        "wire"
    ],
    "sg:website":"www.fujikura.com",
    "wof:name":"Fujikura America Inc",
    "wof:placetype":"venue"
},
  "geometry": {"coordinates":[-86.810503,35.943471],"type":"Point"}
}