{
  "type": "Feature",
  "properties": {
    "iso:country":"US",
    "sg:address":"350 Woodbird Pl",
    "sg:city":"Paris",
    "sg:classifiers":[
        {
            "category":"Personal",
            "subcategory":"Beauty Salon",
            "type":"Services"
        }
    ],
    "sg:phone":"+1 731 642 4701",
    "sg:postcode":"38242",
    "sg:province":"TN",
    "wof:name":"Theresa's Nails & Tanning Sln",
    "wof:placetype":"venue"
},
  "geometry": {"coordinates":[-88.222616,36.226328],"type":"Point"}
}