{
  "type": "Feature",
  "properties": {
    "addr:full":"2711 Murfreesboro Pike Antioch TN 37013",
    "addr:housenumber":"2711",
    "addr:postcode":"37013",
    "addr:street":"Murfreesboro Pike",
    "iso:country":"US",
    "sg:address":"2711 Murfreesboro Pike",
    "sg:city":"Antioch",
    "sg:classifiers":[
        {
            "category":"Banks & Credit Unions",
            "subcategory":"Bank",
            "type":"Services"
        }
    ],
    "sg:phone":"+1 615 366 9366",
    "sg:postcode":"37013",
    "sg:province":"TN",
    "sg:tags":[
        "mortgage"
    ],
    "wof:name":"Amrc",
    "wof:placetype":"venue"
},
  "geometry": {"coordinates":[-86.63265199999999,36.068711],"type":"Point"}
}