{
  "type": "Feature",
  "properties": {
    "iso:country":"US",
    "sg:address":"841 E Raines Rd",
    "sg:city":"Memphis",
    "sg:classifiers":[
        {
            "category":"Real Estate",
            "subcategory":"Real Estate Services",
            "type":"Services"
        },
        {
            "category":"Banks & Credit Unions",
            "subcategory":"Financial Services",
            "type":"Services"
        }
    ],
    "sg:phone":"+1 901 396 5000",
    "sg:postcode":"38116",
    "sg:province":"TN",
    "sg:tags":[
        "loan",
        "processing"
    ],
    "wof:name":"Midamerica Mortgage Co",
    "wof:placetype":"venue"
},
  "geometry": {"coordinates":[-90.03559300000001,35.035312],"type":"Point"}
}