{
  "type": "Feature",
  "properties": {
    "iso:country":"US",
    "sg:address":"3357 Tyree Springs Rd",
    "sg:city":"Hendersonville",
    "sg:classifiers":[
        {
            "category":"Professional",
            "subcategory":"Computer Services",
            "type":"Services"
        }
    ],
    "sg:phone":"+1 615 822 5400",
    "sg:postcode":"37075",
    "sg:province":"TN",
    "sg:tags":[
        "home",
        "consulting",
        "page",
        "dev",
        "internet"
    ],
    "wof:name":"Web Host Now",
    "wof:placetype":"venue"
},
  "geometry": {"coordinates":[-86.644161,36.413537],"type":"Point"}
}