{
  "type": "Feature",
  "properties": {
    "addr:full":"522 Chickamauga Ave NE Knoxville TN 37917",
    "addr:housenumber":"522",
    "addr:postcode":"37917",
    "addr:street":"Chickamauga Ave Ne",
    "iso:country":"US",
    "sg:address":"522 Chickamauga Ave NE",
    "sg:city":"Knoxville",
    "sg:classifiers":[
        {
            "category":"Building & Trades",
            "subcategory":"Plumbing",
            "type":"Services"
        }
    ],
    "sg:phone":"+1 865 523 2612",
    "sg:postcode":"37917",
    "sg:province":"TN",
    "sg:tags":[
        "sheet",
        "work",
        "metal",
        "contractor"
    ],
    "wof:name":"Superior Sheet Metal Fab",
    "wof:placetype":"venue"
},
  "geometry": {"coordinates":[-83.937506,35.999779],"type":"Point"}
}