{
  "type": "Feature",
  "properties": {
    "iso:country":"US",
    "sg:address":"1134 N Gateway Ave",
    "sg:city":"Rockwood",
    "sg:classifiers":[
        {
            "category":"Shopping",
            "subcategory":"Shoes",
            "type":"Retail Goods"
        }
    ],
    "sg:phone":"+1 865 354 3756",
    "sg:postcode":"37854",
    "sg:province":"TN",
    "sg:website":"www.shoeshow.com",
    "wof:name":"Shoe Show",
    "wof:placetype":"venue"
},
  "geometry": {"coordinates":[-84.66837099999999,35.878826],"type":"Point"}
}