{
  "type": "Feature",
  "properties": {
    "iso:country":"US",
    "sg:address":"11316 Lebanon Rd",
    "sg:city":"Mount Juliet",
    "sg:classifiers":[
        {
            "category":"Health Services",
            "subcategory":"Doctor",
            "type":"Services"
        }
    ],
    "sg:phone":"+1 615 754 2444",
    "sg:postcode":"37122",
    "sg:province":"TN",
    "wof:name":"Stephen A Foster DDS",
    "wof:placetype":"venue"
},
  "geometry": {"coordinates":[-86.515259,36.23086],"type":"Point"}
}