{
  "type": "Feature",
  "properties": {
    "iso:country":"US",
    "sg:address":"4320 Kenilwood Dr",
    "sg:city":"Nashville",
    "sg:classifiers":[
        {
            "category":"Retail",
            "subcategory":"Auto Rental",
            "type":"Services"
        }
    ],
    "sg:phone":"+1 615 833 3989",
    "sg:postcode":"37204",
    "sg:province":"TN",
    "sg:tags":[
        "renting",
        "truck",
        "leasing"
    ],
    "wof:name":"U-Haul Co",
    "wof:placetype":"venue"
},
  "geometry": {"coordinates":[-86.76217699999999,36.092152],"type":"Point"}
}