{
  "type": "Feature",
  "properties": {
    "iso:country":"US",
    "sg:address":"3544 Cummings Hwy",
    "sg:city":"Chattanooga",
    "sg:classifiers":[
        {
            "category":"Utilities",
            "subcategory":"Mobile Phone",
            "type":"Services"
        }
    ],
    "sg:phone":"+1 423 822 9638",
    "sg:postcode":"37419",
    "sg:province":"TN",
    "sg:tags":[
        "telephone",
        "cellular"
    ],
    "wof:name":"IPT Cellular Inc",
    "wof:placetype":"venue"
},
  "geometry": {"coordinates":[-85.375477,35.018839],"type":"Point"}
}