{
  "type": "Feature",
  "properties": {
    "iso:country":"US",
    "sg:address":"301 Washington Ave",
    "sg:city":"Memphis",
    "sg:classifiers":[
        {
            "category":"Professional",
            "subcategory":"Business Services",
            "type":"Services"
        }
    ],
    "sg:phone":"+1 901 527 8377",
    "sg:postcode":"38103",
    "sg:province":"TN",
    "sg:tags":[
        "recording",
        "studio"
    ],
    "wof:name":"Hypnotize Minds",
    "wof:placetype":"venue"
},
  "geometry": {"coordinates":[-90.04566800000001,35.147613],"type":"Point"}
}