{
  "type": "Feature",
  "properties": {
    "addr:full":"1927 Bay Pointe Dr Hixson TN 37343",
    "addr:housenumber":"1927",
    "addr:postcode":"37343",
    "addr:street":"Bay Pointe Dr",
    "iso:country":"US",
    "sg:address":"1927 Bay Pointe Dr",
    "sg:city":"Hixson",
    "sg:classifiers":[
        {
            "category":"Professional",
            "subcategory":"Business Services",
            "type":"Services"
        }
    ],
    "sg:phone":"+1 423 843 1821",
    "sg:postcode":"37343",
    "sg:province":"TN",
    "sg:tags":[
        "interior",
        "consultant",
        "design",
        "decorator"
    ],
    "wof:name":"Designs By Peggy Violette",
    "wof:placetype":"venue"
},
  "geometry": {"coordinates":[-85.18475599999999,35.145224],"type":"Point"}
}