{
  "type": "Feature",
  "properties": {
    "iso:country":"US",
    "sg:address":"6006 Sweetbriar Cv",
    "sg:city":"Memphis",
    "sg:classifiers":[
        {
            "category":"Personal",
            "type":"Services"
        },
        {
            "category":"Health Services",
            "subcategory":"Health Practitioner",
            "type":"Services"
        }
    ],
    "sg:phone":"+1 901 683 8200",
    "sg:postcode":"38120",
    "sg:province":"TN",
    "sg:tags":[
        "control",
        "weight",
        "consultant",
        "program",
        "fitness"
    ],
    "sg:website":"http://www.jennycraig.com",
    "wof:name":"Jenny Craig",
    "wof:placetype":"venue"
},
  "geometry": {"coordinates":[-89.861006,35.120559],"type":"Point"}
}