{
  "type": "Feature",
  "properties": {
    "addr:full":"430 Peach St Selmer TN 38375",
    "addr:housenumber":"430",
    "addr:postcode":"38375",
    "addr:street":"Peach St",
    "iso:country":"US",
    "sg:address":"430 Peach St",
    "sg:city":"Selmer",
    "sg:classifiers":[
        {
            "category":"Food & Beverages",
            "subcategory":"Groceries & Convenience Stores",
            "type":"Retail Goods"
        }
    ],
    "sg:phone":"+1 731 645 1022",
    "sg:postcode":"38375",
    "sg:province":"TN",
    "wof:name":"Quick Stop",
    "wof:placetype":"venue"
},
  "geometry": {"coordinates":[-88.59956099999999,35.177047],"type":"Point"}
}