{
  "type": "Feature",
  "properties": {
    "iso:country":"US",
    "sg:address":"1064 Mulberry St",
    "sg:city":"Loudon",
    "sg:classifiers":[
        {
            "category":"Retail",
            "subcategory":"Auto Repair",
            "type":"Services"
        }
    ],
    "sg:phone":"+1 865 458 2900",
    "sg:postcode":"37774",
    "sg:province":"TN",
    "sg:tags":[
        "exhaust"
    ],
    "wof:name":"Proformance Muffler Shop",
    "wof:placetype":"venue"
},
  "geometry": {"coordinates":[-84.348947,35.730668],"type":"Point"}
}