{
  "type": "Feature",
  "properties": {
    "iso:country":"US",
    "sg:address":"1310 Getwell Rd",
    "sg:city":"Memphis",
    "sg:classifiers":[
        {
            "category":"Banks & Credit Unions",
            "subcategory":"Bank",
            "type":"Services"
        }
    ],
    "sg:phone":"+1 901 743 3233",
    "sg:postcode":"38111",
    "sg:province":"TN",
    "sg:tags":[
        "loan"
    ],
    "wof:name":"Money Mart",
    "wof:placetype":"venue"
},
  "geometry": {"coordinates":[-89.930874,35.096343],"type":"Point"}
}