{
  "type": "Feature",
  "properties": {
    "iso:country":"US",
    "sg:address":"112 E Fowlkes St",
    "sg:city":"Franklin",
    "sg:classifiers":[
        {
            "category":"Insurance",
            "subcategory":"Insurance Agent",
            "type":"Services"
        }
    ],
    "sg:phone":"+1 615 794 6636",
    "sg:postcode":"37064",
    "sg:province":"TN",
    "wof:name":"American Benefits Co",
    "wof:placetype":"venue"
},
  "geometry": {"coordinates":[-86.872271,35.91796],"type":"Point"}
}