{
  "type": "Feature",
  "properties": {
    "iso:country":"US",
    "sg:address":"8512 Kingston Pike",
    "sg:city":"Knoxville",
    "sg:classifiers":[
        {
            "category":"Food & Beverages",
            "subcategory":"Groceries & Convenience Stores",
            "type":"Retail Goods"
        }
    ],
    "sg:phone":"+1 865 560 5511",
    "sg:postcode":"37919",
    "sg:province":"TN",
    "wof:name":"Kenjo",
    "wof:placetype":"venue"
},
  "geometry": {"coordinates":[-84.060074,35.922712],"type":"Point"}
}