{
  "type": "Feature",
  "properties": {
    "iso:country":"US",
    "sg:address":"5616 Rich Rd",
    "sg:city":"Memphis",
    "sg:classifiers":[
        {
            "category":"Real Estate",
            "subcategory":"Real Estate Operator",
            "type":"Services"
        }
    ],
    "sg:phone":"+1 901 763 4874",
    "sg:postcode":"38120",
    "sg:province":"TN",
    "sg:tags":[
        "building",
        "nonresidential"
    ],
    "wof:name":"Thomas M Tucker",
    "wof:placetype":"venue"
},
  "geometry": {"coordinates":[-89.87405800000001,35.134915],"type":"Point"}
}