{
  "type": "Feature",
  "properties": {
    "addr:full":"617 Woodbury Hwy Manchester TN 37355",
    "addr:housenumber":"617",
    "addr:postcode":"37355",
    "addr:street":"Woodbury Hwy",
    "iso:country":"US",
    "sg:address":"617 Woodbury Hwy",
    "sg:city":"Manchester",
    "sg:classifiers":[
        {
            "category":"Local Transit",
            "type":"Transportation"
        }
    ],
    "sg:phone":"+1 931 728 6348",
    "sg:postcode":"37355",
    "sg:province":"TN",
    "wof:name":"Greyhound Bus Lines",
    "wof:placetype":"venue"
},
  "geometry": {"coordinates":[-86.087216,35.497049],"type":"Point"}
}