{
  "type": "Feature",
  "properties": {
    "addr:full":"336 Bell Rd Nashville TN 37217",
    "addr:housenumber":"336",
    "addr:postcode":"37217",
    "addr:street":"Bell Rd",
    "iso:country":"US",
    "sg:address":"336 Bell Rd",
    "sg:city":"Nashville",
    "sg:classifiers":[
        {
            "category":"Shopping",
            "subcategory":"Gifts & Souvenirs",
            "type":"Retail Goods"
        }
    ],
    "sg:phone":"+1 615 399 7732",
    "sg:postcode":"37217",
    "sg:province":"TN",
    "sg:tags":[
        "announcement",
        "invitation"
    ],
    "wof:name":"Aard Yart",
    "wof:placetype":"venue"
},
  "geometry": {"coordinates":[-86.634423,36.077765],"type":"Point"}
}