{
  "type": "Feature",
  "properties": {
    "addr:full":"80 Humphreys Center Memphis TN 38120",
    "addr:housenumber":"80",
    "addr:postcode":"38120",
    "addr:street":"Humphreys Center",
    "iso:country":"US",
    "sg:address":"80 Humphreys Center",
    "sg:city":"Memphis",
    "sg:classifiers":[
        {
            "category":"Health Services",
            "subcategory":"Doctor",
            "type":"Services"
        }
    ],
    "sg:phone":"+1 901 747 3066",
    "sg:postcode":"38120",
    "sg:province":"TN",
    "sg:tags":[
        "medical"
    ],
    "wof:name":"Cardiovascular Surgery Clinic",
    "wof:placetype":"venue"
},
  "geometry": {"coordinates":[-89.85728400000001,35.128288],"type":"Point"}
}