{
  "type": "Feature",
  "properties": {
    "addr:full":"239 Cason Ln Murfreesboro TN 37128",
    "addr:housenumber":"239",
    "addr:postcode":"37128",
    "addr:street":"Cason Ln",
    "iso:country":"US",
    "sg:address":"239 Cason Ln",
    "sg:city":"Murfreesboro",
    "sg:classifiers":[
        {
            "category":"Restaurant",
            "type":"Food & Drink"
        }
    ],
    "sg:menulink":"http://www.allmenus.com/tn/murfreesboro/100986-captain-ds-seafood/menu/",
    "sg:phone":"+1 615 907 0727",
    "sg:postcode":"37128",
    "sg:province":"TN",
    "sg:tags":[
        "seafood",
        "american"
    ],
    "wof:name":"Captain D's Seafood",
    "wof:placetype":"venue"
},
  "geometry": {"coordinates":[-86.440001,35.842632],"type":"Point"}
}