{
  "type": "Feature",
  "properties": {
    "iso:country":"US",
    "sg:address":"338 New Byhalia Rd",
    "sg:city":"Collierville",
    "sg:classifiers":[
        {
            "category":"Wholesale",
            "subcategory":"Stationery",
            "type":"Manufacturing & Wholesale Goods"
        }
    ],
    "sg:phone":"+1 901 850 7880",
    "sg:postcode":"38017",
    "sg:province":"TN",
    "sg:tags":[
        "supply"
    ],
    "wof:name":"Forms Management Co",
    "wof:placetype":"venue"
},
  "geometry": {"coordinates":[-89.688198,35.050084],"type":"Point"}
}