{
  "type": "Feature",
  "properties": {
    "addr:full":"1240 Vernon Cove Memphis TN 38122",
    "addr:housenumber":"1240",
    "addr:postcode":"38122",
    "addr:street":"Vernon Cove",
    "iso:country":"US",
    "sg:address":"1240 Vernon Cove",
    "sg:city":"Memphis",
    "sg:classifiers":[
        {
            "category":"Retail",
            "subcategory":"Laundry & Dry Cleaning",
            "type":"Services"
        }
    ],
    "sg:phone":"+1 901 482 5326",
    "sg:postcode":"38122",
    "sg:province":"TN",
    "sg:tags":[
        "cleaners",
        "rug",
        "carpet"
    ],
    "wof:name":"A Mid-South Carpet Care",
    "wof:placetype":"venue"
},
  "geometry": {"coordinates":[-89.929953,35.164582],"type":"Point"}
}