{
  "type": "Feature",
  "properties": {
    "addr:full":"3013 Riverside Dr Chattanooga TN 37406",
    "addr:housenumber":"3013",
    "addr:postcode":"37406",
    "addr:street":"Riverside Dr",
    "iso:country":"US",
    "sg:address":"3013 Riverside Dr",
    "sg:city":"Chattanooga",
    "sg:classifiers":[
        {
            "category":"Building & Trades",
            "subcategory":"Plumbing",
            "type":"Services"
        }
    ],
    "sg:phone":"+1 423 622 4395",
    "sg:postcode":"37406",
    "sg:province":"TN",
    "sg:tags":[
        "plumber",
        "industrial",
        "contractors-commercial"
    ],
    "wof:name":"Plumbers And Steamfitters Local 43",
    "wof:placetype":"venue"
},
  "geometry": {"coordinates":[-85.258472,35.074991],"type":"Point"}
}