{
  "type": "Feature",
  "properties": {
    "iso:country":"US",
    "sg:address":"180 Talmeda Rd",
    "sg:city":"Oak Ridge",
    "sg:classifiers":[
        {
            "category":"Banks & Credit Unions",
            "subcategory":"Financial Services",
            "type":"Services"
        }
    ],
    "sg:phone":"+1 865 482 4626",
    "sg:postcode":"37830",
    "sg:province":"TN",
    "sg:tags":[
        "franchising"
    ],
    "wof:name":"Simply Soup Inc",
    "wof:placetype":"venue"
},
  "geometry": {"coordinates":[-84.23905600000001,36.026862],"type":"Point"}
}