{
  "type": "Feature",
  "properties": {
    "iso:country":"US",
    "sg:address":"500 Unaka Way St",
    "sg:city":"Erwin",
    "sg:classifiers":[
        {
            "category":"Arena",
            "subcategory":"Sports Club",
            "type":"Entertainment"
        }
    ],
    "sg:phone":"+1 423 743 1626",
    "sg:postcode":"37650",
    "sg:province":"TN",
    "wof:name":"Unicoi County High School",
    "wof:placetype":"venue"
},
  "geometry": {"coordinates":[-82.41310799999999,36.137039],"type":"Point"}
}