{
  "type": "Feature",
  "properties": {
    "addr:full":"414 Brick Church Park Dr Nashville TN 37207",
    "addr:housenumber":"414",
    "addr:postcode":"37207",
    "addr:street":"Brick Church Park Dr",
    "iso:country":"US",
    "sg:address":"414 Brick Church Park Dr",
    "sg:city":"Nashville",
    "sg:classifiers":[
        {
            "category":"Wholesale",
            "subcategory":"Construction Materials",
            "type":"Manufacturing & Wholesale Goods"
        }
    ],
    "sg:phone":"+1 615 650 3357",
    "sg:postcode":"37207",
    "sg:province":"TN",
    "sg:tags":[
        "building"
    ],
    "sg:website":"www.primesourcebp.com",
    "wof:name":"Primesource",
    "wof:placetype":"venue"
},
  "geometry": {"coordinates":[-86.7859,36.224876],"type":"Point"}
}