{
  "type": "Feature",
  "properties": {
    "iso:country":"US",
    "sg:address":"4725 Adams Rd",
    "sg:city":"Hixson",
    "sg:classifiers":[
        {
            "category":"Retail",
            "subcategory":"Auto Repair",
            "type":"Services"
        }
    ],
    "sg:phone":"+1 423 870 2184",
    "sg:postcode":"37343",
    "sg:province":"TN",
    "sg:tags":[
        "general"
    ],
    "wof:name":"Automotive Systems",
    "wof:placetype":"venue"
},
  "geometry": {"coordinates":[-85.233425,35.134489],"type":"Point"}
}