{
  "type": "Feature",
  "properties": {
    "addr:full":"4786 State Hwy 58 Chattanooga TN 37416",
    "addr:housenumber":"4786",
    "addr:postcode":"37416",
    "addr:street":"State Hwy 58",
    "iso:country":"US",
    "sg:address":"4786 State Hwy 58",
    "sg:city":"Chattanooga",
    "sg:classifiers":[
        {
            "category":"Restaurant",
            "type":"Food & Drink"
        }
    ],
    "sg:phone":"+1 423 899 6118",
    "sg:postcode":"37416",
    "sg:province":"TN",
    "sg:tags":[
        "fast",
        "chain"
    ],
    "wof:name":"Taco Bell",
    "wof:placetype":"venue"
},
  "geometry": {"coordinates":[-85.18961899999999,35.087493],"type":"Point"}
}