{
  "type": "Feature",
  "properties": {
    "addr:full":"1011 Main St N Carthage TN 37030",
    "addr:housenumber":"1011",
    "addr:postcode":"37030",
    "addr:street":"Main St N",
    "iso:country":"US",
    "sg:address":"1011 Main St N",
    "sg:city":"Carthage",
    "sg:classifiers":[
        {
            "category":"Insurance",
            "subcategory":"Insurance Agent",
            "type":"Services"
        }
    ],
    "sg:phone":"+1 615 735 1812",
    "sg:postcode":"37030",
    "sg:province":"TN",
    "wof:name":"State Farm Insurance",
    "wof:placetype":"venue"
},
  "geometry": {"coordinates":[-85.95775999999999,36.269682],"type":"Point"}
}