{
  "type": "Feature",
  "properties": {
    "addr:full":"113 Elliott Cir Oak Ridge TN 37830",
    "addr:housenumber":"113",
    "addr:postcode":"37830",
    "addr:street":"Elliott Cir",
    "iso:country":"US",
    "sg:address":"113 Elliott Cir",
    "sg:city":"Oak Ridge",
    "sg:classifiers":[
        {
            "category":"Professional",
            "subcategory":"Computer Services",
            "type":"Services"
        }
    ],
    "sg:phone":"+1 865 483 8971",
    "sg:postcode":"37830",
    "sg:province":"TN",
    "sg:tags":[
        "datum"
    ],
    "wof:name":"Young Etheridge",
    "wof:placetype":"venue"
},
  "geometry": {"coordinates":[-84.218361,36.054386],"type":"Point"}
}