{
  "type": "Feature",
  "properties": {
    "iso:country":"US",
    "sg:address":"2510 Eugenia Ave",
    "sg:city":"Nashville",
    "sg:classifiers":[
        {
            "category":"Home & Garden",
            "subcategory":"Household Appliances",
            "type":"Retail Goods"
        },
        {
            "category":"Building & Trades",
            "subcategory":"Cleaning & Sanitation",
            "type":"Services"
        },
        {
            "category":"Building & Trades",
            "subcategory":"Construction",
            "type":"Services"
        }
    ],
    "sg:phone":"+1 615 244 9520",
    "sg:postcode":"37211",
    "sg:province":"TN",
    "sg:tags":[
        "repair",
        "dishwashing",
        "duct",
        "system",
        "specialty",
        "machine",
        "heating",
        "contractor",
        "air conditioning"
    ],
    "sg:website":"http://www.copelandandson.com",
    "wof:name":"Copeland & Son Air Conditioning & Heating Service Inc",
    "wof:placetype":"venue"
},
  "geometry": {"coordinates":[-86.75458500000001,36.116235],"type":"Point"}
}