{
  "type": "Feature",
  "properties": {
    "iso:country":"US",
    "sg:address":"8099 Moores Ln",
    "sg:city":"Brentwood",
    "sg:classifiers":[
        {
            "category":"Home & Garden",
            "subcategory":"Furniture",
            "type":"Retail Goods"
        }
    ],
    "sg:phone":"+1 615 690 4444",
    "sg:postcode":"37027",
    "sg:province":"TN",
    "wof:name":"Ashley Furniture Homestore",
    "wof:placetype":"venue"
},
  "geometry": {"coordinates":[-86.79902199999999,35.965586],"type":"Point"}
}