{
  "type": "Feature",
  "properties": {
    "iso:country":"US",
    "sg:address":"102 Beauregard St",
    "sg:city":"Smyrna",
    "sg:classifiers":[
        {
            "category":"Real Estate",
            "subcategory":"Real Estate Agent",
            "type":"Services"
        }
    ],
    "sg:phone":"+1 615 459 2197",
    "sg:postcode":"37167",
    "sg:province":"TN",
    "sg:tags":[
        "authorities",
        "housing"
    ],
    "wof:name":"Wherry Housing Co-Op",
    "wof:placetype":"venue"
},
  "geometry": {"coordinates":[-86.494776,36.006772],"type":"Point"}
}