{
  "type": "Feature",
  "properties": {
    "iso:country":"US",
    "sg:address":"55 Music Sq W",
    "sg:city":"Nashville",
    "sg:classifiers":[
        {
            "category":"Communications",
            "subcategory":"Radio Station",
            "type":"Services"
        }
    ],
    "sg:phone":"+1 615 664 2400",
    "sg:postcode":"37203",
    "sg:province":"TN",
    "sg:tags":[
        "company",
        "broadcasting"
    ],
    "wof:name":"WNRQ",
    "wof:placetype":"venue"
},
  "geometry": {"coordinates":[-86.793833,36.147082],"type":"Point"}
}