{
  "type": "Feature",
  "properties": {
    "iso:country":"US",
    "sg:address":"2 Bobbitt Rd",
    "sg:city":"Humboldt",
    "sg:classifiers":[
        {
            "category":"Retail",
            "subcategory":"Portrait Studio",
            "type":"Services"
        }
    ],
    "sg:phone":"+1 731 686 0867",
    "sg:postcode":"38317",
    "sg:province":"TN",
    "sg:tags":[
        "photo"
    ],
    "wof:name":"Strayhorn Photography",
    "wof:placetype":"venue"
},
  "geometry": {"coordinates":[-88.32011,36.035726],"type":"Point"}
}