{
  "type": "Feature",
  "properties": {
    "iso:country":"US",
    "sg:address":"1770 Cub Creek Hall Rd",
    "sg:city":"Parsons",
    "sg:classifiers":[
        {
            "category":"Retail",
            "subcategory":"Repair Shop",
            "type":"Services"
        }
    ],
    "sg:phone":"+1 731 847 6816",
    "sg:postcode":"38363",
    "sg:province":"TN",
    "sg:tags":[
        "welding"
    ],
    "wof:name":"Welding Shop",
    "wof:placetype":"venue"
},
  "geometry": {"coordinates":[-88.13605800000001,35.720347],"type":"Point"}
}