{
  "type": "Feature",
  "properties": {
    "addr:full":"750 E Main St Chattanooga TN 37408",
    "addr:housenumber":"750",
    "addr:postcode":"37408",
    "addr:street":"E Main St",
    "iso:country":"US",
    "sg:address":"750 E Main St",
    "sg:city":"Chattanooga",
    "sg:classifiers":[
        {
            "category":"Utilities",
            "subcategory":"Telephone",
            "type":"Services"
        }
    ],
    "sg:phone":"+1 423 756 5803",
    "sg:postcode":"37408",
    "sg:province":"TN",
    "sg:tags":[
        "communications"
    ],
    "wof:name":"MCI",
    "wof:placetype":"venue"
},
  "geometry": {"coordinates":[-85.297607,35.032365],"type":"Point"}
}