{
  "type": "Feature",
  "properties": {
    "iso:country":"US",
    "sg:address":"610 Church St",
    "sg:city":"Nashville",
    "sg:classifiers":[
        {
            "category":"Retail",
            "subcategory":"Auto Repair",
            "type":"Services"
        }
    ],
    "sg:phone":"+1 615 661 5400",
    "sg:postcode":"37203",
    "sg:province":"TN",
    "sg:tags":[
        "repairing",
        "automobile"
    ],
    "wof:name":"American Tire",
    "wof:placetype":"venue"
},
  "geometry": {"coordinates":[-86.781982,36.162533],"type":"Point"}
}