{
  "type": "Feature",
  "properties": {
    "iso:country":"US",
    "sg:address":"2222 Cedar St",
    "sg:city":"Mc Kenzie",
    "sg:classifiers":[
        {
            "category":"Retail",
            "subcategory":"Laundry & Dry Cleaning",
            "type":"Services"
        }
    ],
    "sg:phone":"+1 731 352 2335",
    "sg:postcode":"38201",
    "sg:province":"TN",
    "sg:tags":[
        "cleaner"
    ],
    "wof:name":"One Hour Wardrobe Cleaners",
    "wof:placetype":"venue"
},
  "geometry": {"coordinates":[-88.515677,36.131014],"type":"Point"}
}