{
  "type": "Feature",
  "properties": {
    "iso:country":"US",
    "sg:address":"51 Glendale Rd",
    "sg:city":"Newbern",
    "sg:classifiers":[
        {
            "category":"Shopping",
            "type":"Retail Goods"
        }
    ],
    "sg:phone":"+1 731 627 1010",
    "sg:postcode":"38059",
    "sg:province":"TN",
    "sg:tags":[
        "equipment",
        "irrigation",
        "system"
    ],
    "wof:name":"Mid-Valley Irrigation Inc",
    "wof:placetype":"venue"
},
  "geometry": {"coordinates":[-89.33250200000001,36.167399],"type":"Point"}
}