{
  "type": "Feature",
  "properties": {
    "addr:full":"549 Armstrong Dr Kingsport TN 37660",
    "addr:housenumber":"549",
    "addr:postcode":"37660",
    "addr:street":"Armstrong Dr",
    "iso:country":"US",
    "sg:address":"549 Armstrong Dr",
    "sg:city":"Kingsport",
    "sg:classifiers":[
        {
            "category":"Retail",
            "subcategory":"Auto Repair",
            "type":"Services"
        }
    ],
    "sg:phone":"+1 423 288 4181",
    "sg:postcode":"37660",
    "sg:province":"TN",
    "sg:tags":[
        "repairing",
        "automobile"
    ],
    "wof:name":"Friendly Auto Svc",
    "wof:placetype":"venue"
},
  "geometry": {"coordinates":[-82.50703300000001,36.566319],"type":"Point"}
}