{
  "type": "Feature",
  "properties": {
    "iso:country":"US",
    "sg:address":"2106 Chota Rd",
    "sg:city":"Maryville",
    "sg:classifiers":[
        {
            "category":"Building & Trades",
            "subcategory":"Construction",
            "type":"Services"
        }
    ],
    "sg:phone":"+1 865 984 0264",
    "sg:postcode":"37803",
    "sg:province":"TN",
    "sg:tags":[
        "excavation",
        "contractor"
    ],
    "wof:name":"Kagleys Excavating",
    "wof:placetype":"venue"
},
  "geometry": {"coordinates":[-84.038222,35.622666],"type":"Point"}
}