{
  "type": "Feature",
  "properties": {
    "iso:country":"US",
    "sg:address":"101 Dogwood Dr",
    "sg:city":"Athens",
    "sg:classifiers":[
        {
            "category":"Shopping",
            "subcategory":"Clothing, Apparel, & Fashions",
            "type":"Retail Goods"
        }
    ],
    "sg:phone":"+1 423 746 2553",
    "sg:postcode":"37303",
    "sg:province":"TN",
    "sg:tags":[
        "infant",
        "wear"
    ],
    "wof:name":"Brenda's Ballet Boutique",
    "wof:placetype":"venue"
},
  "geometry": {"coordinates":[-84.60939500000001,35.439522],"type":"Point"}
}