{
  "type": "Feature",
  "properties": {
    "addr:full":"3074 Covington Pike Memphis TN 38128",
    "addr:housenumber":"3074",
    "addr:postcode":"38128",
    "addr:street":"Covington Pike",
    "iso:country":"US",
    "sg:address":"3074 Covington Pike",
    "sg:city":"Memphis",
    "sg:classifiers":[
        {
            "category":"Banks & Credit Unions",
            "subcategory":"Bank",
            "type":"Services"
        }
    ],
    "sg:phone":"+1 901 937 7655",
    "sg:postcode":"38128",
    "sg:province":"TN",
    "wof:name":"L G & W Federal Credit Union",
    "wof:placetype":"venue"
},
  "geometry": {"coordinates":[-89.894565,35.209395],"type":"Point"}
}