{
  "type": "Feature",
  "properties": {
    "iso:country":"US",
    "sg:address":"7990 Trinity Rd",
    "sg:city":"Cordova",
    "sg:classifiers":[
        {
            "category":"Real Estate",
            "subcategory":"Architect",
            "type":"Services"
        }
    ],
    "sg:phone":"+1 901 844 7990",
    "sg:postcode":"38018",
    "sg:province":"TN",
    "sg:tags":[
        "building",
        "designer",
        "architectural"
    ],
    "wof:name":"Gardo Design Group LLC",
    "wof:placetype":"venue"
},
  "geometry": {"coordinates":[-89.79667499999999,35.142342],"type":"Point"}
}