{
  "type": "Feature",
  "properties": {
    "iso:country":"US",
    "sg:address":"959 Milam Branch Rd",
    "sg:city":"Centerville",
    "sg:classifiers":[
        {
            "category":"Farming",
            "subcategory":"Livestock Farm",
            "type":"Manufacturing & Wholesale Goods"
        }
    ],
    "sg:phone":"+1 931 729 3263",
    "sg:postcode":"37033",
    "sg:province":"TN",
    "sg:tags":[
        "beef",
        "feedlot",
        "cattle"
    ],
    "wof:name":"Louise Campbell",
    "wof:placetype":"venue"
},
  "geometry": {"coordinates":[-87.565275,35.715619],"type":"Point"}
}