{
  "type": "Feature",
  "properties": {
    "iso:country":"US",
    "sg:address":"429 N Broadway",
    "sg:city":"Portland",
    "sg:classifiers":[
        {
            "category":"Personal",
            "subcategory":"Beauty Salon",
            "type":"Services"
        }
    ],
    "sg:phone":"+1 615 325 9255",
    "sg:postcode":"37148",
    "sg:province":"TN",
    "sg:tags":[
        "shop"
    ],
    "wof:name":"Professional Images Salon",
    "wof:placetype":"venue"
},
  "geometry": {"coordinates":[-86.51840900000001,36.58492],"type":"Point"}
}