{
  "type": "Feature",
  "properties": {
    "iso:country":"US",
    "sg:address":"391 Rivers Edge Ln",
    "sg:city":"Sparta",
    "sg:classifiers":[
        {
            "category":"Real Estate",
            "subcategory":"Real Estate Agent",
            "type":"Services"
        }
    ],
    "sg:phone":"+1 931 788 3885",
    "sg:postcode":"38583",
    "sg:province":"TN",
    "wof:name":"Roger Vanrekom Real Esta",
    "wof:placetype":"venue"
},
  "geometry": {"coordinates":[-85.215738,35.882921],"type":"Point"}
}