{
  "type": "Feature",
  "properties": {
    "addr:full":"2400 Buena Vista Pike Nashville TN 37218",
    "addr:housenumber":"2400",
    "addr:postcode":"37218",
    "addr:street":"Buena Vista Pike",
    "iso:country":"US",
    "sg:address":"2400 Buena Vista Pike",
    "sg:city":"Nashville",
    "sg:classifiers":[
        {
            "category":"Shopping",
            "subcategory":"Clothing, Apparel, & Fashions",
            "type":"Retail Goods"
        }
    ],
    "sg:phone":"+1 615 243 6185",
    "sg:postcode":"37218",
    "sg:province":"TN",
    "wof:name":"New York Enterprise",
    "wof:placetype":"venue"
},
  "geometry": {"coordinates":[-86.823128,36.200894],"type":"Point"}
}