{
  "type": "Feature",
  "properties": {
    "addr:full":"1864 Winchester Rd Memphis TN 38116",
    "addr:housenumber":"1864",
    "addr:postcode":"38116",
    "addr:street":"Winchester Rd",
    "iso:country":"US",
    "sg:address":"1864 Winchester Rd",
    "sg:city":"Memphis",
    "sg:classifiers":[
        {
            "category":"Shopping",
            "subcategory":"Beauty & Cosmetics",
            "type":"Retail Goods"
        }
    ],
    "sg:phone":"+1 901 345 2397",
    "sg:postcode":"38116",
    "sg:province":"TN",
    "sg:tags":[
        "supply"
    ],
    "wof:name":"3217 Winchester Load",
    "wof:placetype":"venue"
},
  "geometry": {"coordinates":[-89.999127,35.05359],"type":"Point"}
}