{
  "type": "Feature",
  "properties": {
    "iso:country":"US",
    "sg:address":"18019 US Hwy 41",
    "sg:city":"Chattanooga",
    "sg:classifiers":[
        {
            "category":"Professional",
            "type":"Services"
        }
    ],
    "sg:phone":"+1 423 821 2876",
    "sg:postcode":"37419",
    "sg:province":"TN",
    "wof:name":"Massengale Family Ltd Partnr",
    "wof:placetype":"venue"
},
  "geometry": {"coordinates":[-85.483428,35.047498],"type":"Point"}
}