{
  "type": "Feature",
  "properties": {
    "iso:country":"US",
    "sg:address":"210 S Main St",
    "sg:city":"Shelbyville",
    "sg:classifiers":[
        {
            "category":"Wholesale",
            "subcategory":"Furniture",
            "type":"Manufacturing & Wholesale Goods"
        },
        {
            "category":"Home & Garden",
            "subcategory":"Furniture",
            "type":"Retail Goods"
        }
    ],
    "sg:phone":"+1 931 685 4357",
    "sg:postcode":"37160",
    "sg:province":"TN",
    "sg:tags":[
        "stationery",
        "who"
    ],
    "wof:name":"Southern Office Systems",
    "wof:placetype":"venue"
},
  "geometry": {"coordinates":[-86.460187,35.4817],"type":"Point"}
}