{
  "type": "Feature",
  "properties": {
    "iso:country":"US",
    "sg:address":"6363 Stage Rd",
    "sg:city":"Memphis",
    "sg:classifiers":[
        {
            "category":"Health Services",
            "subcategory":"Doctor",
            "type":"Services"
        }
    ],
    "sg:phone":"+1 901 386 5757",
    "sg:postcode":"38134",
    "sg:province":"TN",
    "wof:name":"Parrish Dental Office",
    "wof:placetype":"venue"
},
  "geometry": {"coordinates":[-89.850999,35.204688],"type":"Point"}
}