{
  "type": "Feature",
  "properties": {
    "iso:country":"US",
    "sg:address":"1315 D'Ann Dr",
    "sg:city":"Murfreesboro",
    "sg:classifiers":[
        {
            "category":"Building & Trades",
            "subcategory":"Cleaning & Sanitation",
            "type":"Services"
        }
    ],
    "sg:phone":"+1 615 849 3864",
    "sg:postcode":"37129",
    "sg:province":"TN",
    "sg:tags":[
        "maintenance"
    ],
    "wof:name":"Dan Daves Cleaning Services",
    "wof:placetype":"venue"
},
  "geometry": {"coordinates":[-86.402801,35.887898],"type":"Point"}
}