{
  "type": "Feature",
  "properties": {
    "iso:country":"US",
    "sg:address":"9502 Middlebrook Pike",
    "sg:city":"Knoxville",
    "sg:classifiers":[
        {
            "category":"Recreation",
            "type":"Entertainment"
        }
    ],
    "sg:phone":"+1 865 694 3093",
    "sg:postcode":"37931",
    "sg:province":"TN",
    "wof:name":"Wesco Racing",
    "wof:placetype":"venue"
},
  "geometry": {"coordinates":[-84.112773,35.946939],"type":"Point"}
}