{
  "type": "Feature",
  "properties": {
    "addr:full":"5403 Western Ave Knoxville TN 37921",
    "addr:housenumber":"5403",
    "addr:postcode":"37921",
    "addr:street":"Western Ave",
    "iso:country":"US",
    "sg:address":"5403 Western Ave",
    "sg:city":"Knoxville",
    "sg:classifiers":[
        {
            "category":"Shopping",
            "subcategory":"Department Store",
            "type":"Retail Goods"
        }
    ],
    "sg:phone":"+1 865 558 3045",
    "sg:postcode":"37921",
    "sg:province":"TN",
    "sg:tags":[
        "shop"
    ],
    "wof:name":"Classy Image",
    "wof:placetype":"venue"
},
  "geometry": {"coordinates":[-84.008331,35.97599],"type":"Point"}
}