{
  "type": "Feature",
  "properties": {
    "iso:country":"US",
    "sg:address":"638 Fitzhugh Blvd",
    "sg:city":"Smyrna",
    "sg:classifiers":[
        {
            "category":"Professional",
            "type":"Services"
        }
    ],
    "sg:phone":"+1 615 459 3039",
    "sg:postcode":"37167",
    "sg:province":"TN",
    "sg:tags":[
        "establishment"
    ],
    "wof:name":"United Defense LTD",
    "wof:placetype":"venue"
},
  "geometry": {"coordinates":[-86.51047699999999,36.016265],"type":"Point"}
}