{
  "type": "Feature",
  "properties": {
    "iso:country":"US",
    "sg:address":"3085 Stage Post Dr",
    "sg:city":"Memphis",
    "sg:classifiers":[
        {
            "category":"Building & Trades",
            "subcategory":"Construction",
            "type":"Services"
        }
    ],
    "sg:phone":"+1 901 372 5766",
    "sg:postcode":"38133",
    "sg:province":"TN",
    "sg:tags":[
        "contractor",
        "industrial",
        "general",
        "nonresidential"
    ],
    "wof:name":"Venture Construction Company",
    "wof:placetype":"venue"
},
  "geometry": {"coordinates":[-89.80230899999999,35.209887],"type":"Point"}
}