{
  "type": "Feature",
  "properties": {
    "iso:country":"US",
    "sg:address":"6300 US Hwy 641 N",
    "sg:city":"Puryear",
    "sg:classifiers":[
        {
            "category":"Shopping",
            "subcategory":"Clothing, Apparel, & Fashions",
            "type":"Retail Goods"
        }
    ],
    "sg:phone":"+1 731 642 0404",
    "sg:postcode":"38251",
    "sg:province":"TN",
    "wof:name":"Paris Tailoring Shop",
    "wof:placetype":"venue"
},
  "geometry": {"coordinates":[-88.333475,36.394364],"type":"Point"}
}