{
  "type": "Feature",
  "properties": {
    "iso:country":"US",
    "sg:address":"4315 S 3rd St",
    "sg:city":"Memphis",
    "sg:classifiers":[
        {
            "category":"Food & Beverages",
            "subcategory":"Groceries & Convenience Stores",
            "type":"Retail Goods"
        }
    ],
    "sg:phone":"+1 901 789 6788",
    "sg:postcode":"38109",
    "sg:province":"TN",
    "wof:name":"Robinson Food Market",
    "wof:placetype":"venue"
},
  "geometry": {"coordinates":[-90.078419,35.030313],"type":"Point"}
}