{
  "type": "Feature",
  "properties": {
    "iso:country":"US",
    "sg:address":"4101 US Hwy 411",
    "sg:city":"Ocoee",
    "sg:classifiers":[
        {
            "category":"Food & Beverages",
            "subcategory":"Groceries & Convenience Stores",
            "type":"Retail Goods"
        }
    ],
    "sg:phone":"+1 423 338 0122",
    "sg:postcode":"37361",
    "sg:province":"TN",
    "wof:name":"Favorite Market",
    "wof:placetype":"venue"
},
  "geometry": {"coordinates":[-84.715704,35.130078],"type":"Point"}
}