{
  "type": "Feature",
  "properties": {
    "addr:full":"1108 E Main St Union City TN 38261",
    "addr:housenumber":"1108",
    "addr:postcode":"38261",
    "addr:street":"E Main St",
    "iso:country":"US",
    "sg:address":"1108 E Main St",
    "sg:city":"Union City",
    "sg:classifiers":[
        {
            "category":"Shopping",
            "type":"Retail Goods"
        }
    ],
    "sg:phone":"+1 731 885 5269",
    "sg:postcode":"38261",
    "sg:province":"TN",
    "sg:tags":[
        "cosmetic",
        "perfume"
    ],
    "wof:name":"Kat's Beauty Zone",
    "wof:placetype":"venue"
},
  "geometry": {"coordinates":[-89.04497499999999,36.425086],"type":"Point"}
}