{
  "type": "Feature",
  "properties": {
    "addr:full":"5651 Frist Blvd Ste 213 Hermitage TN 37076",
    "addr:housenumber":"5651",
    "addr:postcode":"37076",
    "addr:street":"Frist Blvd Ste 213",
    "iso:country":"US",
    "sg:address":"5651 Frist Blvd Ste 213",
    "sg:city":"Hermitage",
    "sg:classifiers":[
        {
            "category":"Health Services",
            "subcategory":"Doctor",
            "type":"Services"
        }
    ],
    "sg:phone":"+1 615 883 9988",
    "sg:postcode":"37076",
    "sg:province":"TN",
    "sg:tags":[
        "physician",
        "family",
        "gynecology",
        "practice",
        "surgeons",
        "obstetrics",
        "medicine",
        "surgeon"
    ],
    "wof:name":"Moody Samantha",
    "wof:placetype":"venue"
},
  "geometry": {"coordinates":[-86.606003,36.17812],"type":"Point"}
}