{
  "type": "Feature",
  "properties": {
    "addr:full":"1407 Bunker Hill Rd Cookeville TN 38506",
    "addr:housenumber":"1407",
    "addr:postcode":"38506",
    "addr:street":"Bunker Hill Rd",
    "iso:country":"US",
    "sg:address":"1407 Bunker Hill Rd",
    "sg:city":"Cookeville",
    "sg:classifiers":[
        {
            "category":"Retail",
            "subcategory":"Self-service Laundry",
            "type":"Services"
        }
    ],
    "sg:phone":"+1 931 528 8687",
    "sg:postcode":"38506",
    "sg:province":"TN",
    "sg:tags":[
        "coin"
    ],
    "wof:name":"Handymart Laundry",
    "wof:placetype":"venue"
},
  "geometry": {"coordinates":[-85.51122100000001,36.125686],"type":"Point"}
}