{
  "type": "Feature",
  "properties": {
    "iso:country":"US",
    "sg:address":"439 Barbara Ln",
    "sg:city":"Eads",
    "sg:classifiers":[
        {
            "category":"Home & Garden",
            "subcategory":"Furniture",
            "type":"Retail Goods"
        }
    ],
    "sg:phone":"+1 901 726 1413",
    "sg:postcode":"38028",
    "sg:province":"TN",
    "sg:tags":[
        "mexican",
        "importer",
        "novelty"
    ],
    "wof:name":"Su Casa Imports",
    "wof:placetype":"venue"
},
  "geometry": {"coordinates":[-89.68992,35.113526],"type":"Point"}
}