{
  "type": "Feature",
  "properties": {
    "iso:country":"US",
    "sg:address":"1177 Dave Huddleston Rd",
    "sg:city":"Cookeville",
    "sg:classifiers":[
        {
            "category":"Manufacturing",
            "subcategory":"Tools & Machinery",
            "type":"Manufacturing & Wholesale Goods"
        }
    ],
    "sg:phone":"+1 931 526 7914",
    "sg:postcode":"38501",
    "sg:province":"TN",
    "sg:tags":[
        "designed",
        "built"
    ],
    "wof:name":"Complete Control Systems",
    "wof:placetype":"venue"
},
  "geometry": {"coordinates":[-85.51325,36.221114],"type":"Point"}
}