{
  "type": "Feature",
  "properties": {
    "addr:full":"622 Belgium Dr Hermitage TN 37076",
    "addr:housenumber":"622",
    "addr:postcode":"37076",
    "addr:street":"Belgium Dr",
    "iso:country":"US",
    "sg:address":"622 Belgium Dr",
    "sg:city":"Hermitage",
    "sg:classifiers":[
        {
            "category":"Professional",
            "subcategory":"Business Services",
            "type":"Services"
        }
    ],
    "sg:phone":"+1 615 885 8672",
    "sg:postcode":"37076",
    "sg:province":"TN",
    "wof:name":"Right On Time Documents",
    "wof:placetype":"venue"
},
  "geometry": {"coordinates":[-86.597239,36.202904],"type":"Point"}
}