{
  "type": "Feature",
  "properties": {
    "iso:country":"US",
    "sg:address":"112 Pine Grove Way",
    "sg:city":"Maryville",
    "sg:classifiers":[
        {
            "category":"Organizations",
            "subcategory":"Religious Organization",
            "type":"Services"
        }
    ],
    "sg:phone":"+1 865 982 8241",
    "sg:postcode":"37801",
    "sg:province":"TN",
    "wof:name":"Meadowbrook Christian Church",
    "wof:placetype":"venue"
},
  "geometry": {"coordinates":[-84.050529,35.722956],"type":"Point"}
}