{
  "type": "Feature",
  "properties": {
    "iso:country":"US",
    "sg:address":"808 Appomattox Pl",
    "sg:city":"Franklin",
    "sg:classifiers":[
        {
            "category":"Shopping",
            "subcategory":"Used Merchandise",
            "type":"Retail Goods"
        }
    ],
    "sg:phone":"+1 615 591 0644",
    "sg:postcode":"37064",
    "sg:province":"TN",
    "sg:tags":[
        "antique"
    ],
    "wof:name":"Cinnamon Hill Antiques Inc",
    "wof:placetype":"venue"
},
  "geometry": {"coordinates":[-86.855934,35.91253],"type":"Point"}
}