{
  "type": "Feature",
  "properties": {
    "iso:country":"US",
    "sg:address":"1993 Neal Rd",
    "sg:city":"Belvidere",
    "sg:classifiers":[
        {
            "category":"Building & Trades",
            "subcategory":"Construction",
            "type":"Services"
        }
    ],
    "sg:phone":"+1 931 968 1024",
    "sg:postcode":"37306",
    "sg:province":"TN",
    "sg:tags":[
        "hanging",
        "contractor"
    ],
    "wof:name":"R&S Painting",
    "wof:placetype":"venue"
},
  "geometry": {"coordinates":[-86.28450100000001,35.151579],"type":"Point"}
}