{
  "type": "Feature",
  "properties": {
    "addr:full":"2605 N Broadway St Knoxville TN 37917",
    "addr:housenumber":"2605",
    "addr:postcode":"37917",
    "addr:street":"N Broadway St",
    "iso:country":"US",
    "sg:address":"2605 N Broadway St",
    "sg:city":"Knoxville",
    "sg:classifiers":[
        {
            "category":"Building & Trades",
            "subcategory":"Equipment Rental",
            "type":"Services"
        }
    ],
    "sg:phone":"+1 865 544 1135",
    "sg:postcode":"37917",
    "sg:province":"TN",
    "sg:tags":[
        "leasing",
        "furniture"
    ],
    "wof:name":"Aaron's Rental Purchase",
    "wof:placetype":"venue"
},
  "geometry": {"coordinates":[-83.923693,35.996608],"type":"Point"}
}