{
  "type": "Feature",
  "properties": {
    "addr:full":"104 Martin Dr Hendersonville TN 37075",
    "addr:housenumber":"104",
    "addr:postcode":"37075",
    "addr:street":"Martin Dr",
    "iso:country":"US",
    "sg:address":"104 Martin Dr",
    "sg:city":"Hendersonville",
    "sg:classifiers":[
        {
            "category":"Organizations",
            "subcategory":"Non-profit Organization",
            "type":"Services"
        }
    ],
    "sg:phone":"+1 615 264 2927",
    "sg:postcode":"37075",
    "sg:province":"TN",
    "sg:tags":[
        "fund",
        "counselor",
        "raising"
    ],
    "wof:name":"Little Lamb's",
    "wof:placetype":"venue"
},
  "geometry": {"coordinates":[-86.602593,36.299563],"type":"Point"}
}