{
  "type": "Feature",
  "properties": {
    "iso:country":"US",
    "sg:address":"539 W Commerce St",
    "sg:city":"Lewisburg",
    "sg:classifiers":[
        {
            "category":"Home & Garden",
            "subcategory":"Furniture",
            "type":"Retail Goods"
        }
    ],
    "sg:phone":"+1 931 270 6046",
    "sg:postcode":"37091",
    "sg:province":"TN",
    "wof:name":"Blackwell Furniture",
    "wof:placetype":"venue"
},
  "geometry": {"coordinates":[-86.794932,35.449511],"type":"Point"}
}