{
  "type": "Feature",
  "properties": {
    "iso:country":"US",
    "sg:address":"111 Moffitt St",
    "sg:city":"Mc Minnville",
    "sg:classifiers":[
        {
            "category":"Manufacturing",
            "subcategory":"Tools & Machinery",
            "type":"Manufacturing & Wholesale Goods"
        }
    ],
    "sg:phone":"+1 931 474 7550",
    "sg:postcode":"37110",
    "sg:province":"TN",
    "sg:tags":[
        "instrument",
        "surgical",
        "apparatus",
        "mfg"
    ],
    "wof:name":"Vilex Inc",
    "wof:placetype":"venue"
},
  "geometry": {"coordinates":[-85.76234599999999,35.687605],"type":"Point"}
}