{
  "type": "Feature",
  "properties": {
    "iso:country":"US",
    "sg:address":"6159 Georgetown Rd NW",
    "sg:city":"Cleveland",
    "sg:classifiers":[
        {
            "category":"Professional",
            "subcategory":"Business Services",
            "type":"Services"
        }
    ],
    "sg:phone":"+1 423 478 0007",
    "sg:postcode":"37312",
    "sg:province":"TN",
    "sg:tags":[
        "interior",
        "designer"
    ],
    "wof:name":"Storm Interiors",
    "wof:placetype":"venue"
},
  "geometry": {"coordinates":[-84.901177,35.251583],"type":"Point"}
}