{
  "type": "Feature",
  "properties": {
    "iso:country":"US",
    "sg:address":"1329 Gunbarrel Rd",
    "sg:city":"Chattanooga",
    "sg:classifiers":[
        {
            "category":"Professional",
            "subcategory":"Art Services",
            "type":"Services"
        }
    ],
    "sg:phone":"+1 423 855 9720",
    "sg:postcode":"37421",
    "sg:province":"TN",
    "sg:tags":[
        "commercial",
        "design"
    ],
    "wof:name":"Wallace Braud",
    "wof:placetype":"venue"
},
  "geometry": {"coordinates":[-85.16522399999999,35.012464],"type":"Point"}
}