{
  "type": "Feature",
  "properties": {
    "iso:country":"US",
    "sg:address":"107 Flenniken Ave",
    "sg:city":"Knoxville",
    "sg:classifiers":[
        {
            "category":"Professional",
            "type":"Services"
        }
    ],
    "sg:phone":"+1 865 403 1384",
    "sg:postcode":"37920",
    "sg:province":"TN",
    "sg:tags":[
        "establishment"
    ],
    "wof:name":"Verandas On Flenniken",
    "wof:placetype":"venue"
},
  "geometry": {"coordinates":[-83.912943,35.939757],"type":"Point"}
}