{
  "type": "Feature",
  "properties": {
    "iso:country":"US",
    "sg:address":"3975 Vantech Dr",
    "sg:city":"Memphis",
    "sg:classifiers":[
        {
            "category":"Shopping",
            "subcategory":"Optical Goods",
            "type":"Retail Goods"
        }
    ],
    "sg:phone":"+1 901 794 3890",
    "sg:postcode":"38115",
    "sg:province":"TN",
    "sg:tags":[
        "sun",
        "goggles",
        "sunglasses"
    ],
    "sg:website":"www.olympicoptical.com",
    "wof:name":"Olympic Optical Co",
    "wof:placetype":"venue"
},
  "geometry": {"coordinates":[-89.88696,35.039956],"type":"Point"}
}