{
  "type": "Feature",
  "properties": {
    "iso:country":"US",
    "sg:address":"3025 Zeb Warren Rd",
    "sg:city":"Cookeville",
    "sg:classifiers":[
        {
            "category":"Building & Trades",
            "subcategory":"Construction",
            "type":"Services"
        }
    ],
    "sg:phone":"+1 931 252 1529",
    "sg:postcode":"38506",
    "sg:province":"TN",
    "sg:tags":[
        "concrete",
        "pumping"
    ],
    "wof:name":"Concrete Pumping Svc",
    "wof:placetype":"venue"
},
  "geometry": {"coordinates":[-85.452225,36.251004],"type":"Point"}
}