{
  "type": "Feature",
  "properties": {
    "iso:country":"US",
    "sg:address":"1165 Rayner St",
    "sg:city":"Memphis",
    "sg:classifiers":[
        {
            "category":"Retail",
            "subcategory":"Pet Boarding",
            "type":"Services"
        }
    ],
    "sg:phone":"+1 901 726 1354",
    "sg:postcode":"38106",
    "sg:province":"TN",
    "sg:tags":[
        "kennel"
    ],
    "wof:name":"William Carroll Boarding Facility",
    "wof:placetype":"venue"
},
  "geometry": {"coordinates":[-90.012019,35.114433],"type":"Point"}
}