{
  "type": "Feature",
  "properties": {
    "iso:country":"US",
    "sg:address":"870 Winfield Dunn Pkwy",
    "sg:city":"Sevierville",
    "sg:classifiers":[
        {
            "category":"Recreation",
            "type":"Entertainment"
        }
    ],
    "sg:phone":"+1 865 774 7071",
    "sg:postcode":"37876",
    "sg:province":"TN",
    "sg:tags":[
        "tours",
        "sightseeing"
    ],
    "wof:name":"MTO Tour & Receptive",
    "wof:placetype":"venue"
},
  "geometry": {"coordinates":[-83.576937,35.888726],"type":"Point"}
}