{
  "type": "Feature",
  "properties": {
    "addr:full":"925 S Church St Murfreesboro TN 37130",
    "addr:housenumber":"925",
    "addr:postcode":"37130",
    "addr:street":"S Church St",
    "iso:country":"US",
    "sg:address":"925 S Church St",
    "sg:city":"Murfreesboro",
    "sg:classifiers":[
        {
            "category":"Professional",
            "subcategory":"Advertising",
            "type":"Services"
        }
    ],
    "sg:phone":"+1 615 324 6400",
    "sg:postcode":"37130",
    "sg:province":"TN",
    "sg:tags":[
        "guide"
    ],
    "sg:website":"www.yellowbookusa.com",
    "wof:name":"Yellow Book USA",
    "wof:placetype":"venue"
},
  "geometry": {"coordinates":[-86.39316599999999,35.834025],"type":"Point"}
}