{
  "type": "Feature",
  "properties": {
    "iso:country":"US",
    "sg:address":"253 N Main St",
    "sg:city":"Oneida",
    "sg:classifiers":[
        {
            "category":"Shopping",
            "subcategory":"Florist",
            "type":"Retail Goods"
        }
    ],
    "sg:phone":"+1 423 569 2085",
    "sg:postcode":"37841",
    "sg:province":"TN",
    "wof:name":"Milford's Flower Shop",
    "wof:placetype":"venue"
},
  "geometry": {"coordinates":[-84.51348900000001,36.504843],"type":"Point"}
}