{
  "type": "Feature",
  "properties": {
    "iso:country":"US",
    "sg:address":"100 Hermitage Dr",
    "sg:city":"Tullahoma",
    "sg:classifiers":[
        {
            "category":"Health Services",
            "subcategory":"Health Practitioner",
            "type":"Services"
        }
    ],
    "sg:phone":"+1 931 393 2151",
    "sg:postcode":"37388",
    "sg:province":"TN",
    "wof:name":"Waterscmpbll Spch & Lngge Pthl",
    "wof:placetype":"venue"
},
  "geometry": {"coordinates":[-86.23391100000001,35.340098],"type":"Point"}
}