{
  "type": "Feature",
  "properties": {
    "addr:full":"430 Outlet Village Blvd Lebanon TN 37090",
    "addr:housenumber":"430",
    "addr:postcode":"37090",
    "addr:street":"Outlet Village Blvd",
    "iso:country":"US",
    "sg:address":"430 Outlet Village Blvd",
    "sg:city":"Lebanon",
    "sg:classifiers":[
        {
            "category":"Home & Garden",
            "subcategory":"Home Furnishings",
            "type":"Retail Goods"
        }
    ],
    "sg:phone":"+1 615 453 7648",
    "sg:postcode":"37090",
    "sg:province":"TN",
    "sg:tags":[
        "glassware",
        "chinaware"
    ],
    "wof:name":"Pfaltzgraff Factory Store",
    "wof:placetype":"venue"
},
  "geometry": {"coordinates":[-86.30332900000001,36.178423],"type":"Point"}
}