{
  "type": "Feature",
  "properties": {
    "iso:country":"US",
    "sg:address":"101 Center Rd",
    "sg:city":"Madisonville",
    "sg:classifiers":[
        {
            "category":"Government",
            "subcategory":"Office",
            "type":"Public Place"
        }
    ],
    "sg:phone":"+1 423 442 1373",
    "sg:postcode":"37354",
    "sg:province":"TN",
    "sg:tags":[
        "village"
    ],
    "wof:name":"Madisonville Animal Shelter",
    "wof:placetype":"venue"
},
  "geometry": {"coordinates":[-84.35438499999999,35.467922],"type":"Point"}
}