{
  "type": "Feature",
  "properties": {
    "addr:full":"620 Market St SW Knoxville TN 37902",
    "addr:housenumber":"620",
    "addr:postcode":"37902",
    "addr:street":"Market St Sw",
    "iso:country":"US",
    "sg:address":"620 Market St SW",
    "sg:city":"Knoxville",
    "sg:classifiers":[
        {
            "category":"Professional",
            "subcategory":"Lawyer & Legal Services",
            "type":"Services"
        }
    ],
    "sg:phone":"+1 865 523 2000",
    "sg:postcode":"37902",
    "sg:province":"TN",
    "sg:tags":[
        "attorney"
    ],
    "wof:name":"Morton & Morton",
    "wof:placetype":"venue"
},
  "geometry": {"coordinates":[-83.918307,35.963248],"type":"Point"}
}