{
  "type": "Feature",
  "properties": {
    "addr:full":"9102 Finney Point Rd Ooltewah TN 37363",
    "addr:housenumber":"9102",
    "addr:postcode":"37363",
    "addr:street":"Finney Point Rd",
    "iso:country":"US",
    "sg:address":"9102 Finney Point Rd",
    "sg:city":"Ooltewah",
    "sg:classifiers":[
        {
            "category":"Building & Trades",
            "subcategory":"Equipment Rental",
            "type":"Services"
        }
    ],
    "sg:phone":"+1 423 892 1209",
    "sg:postcode":"37363",
    "sg:province":"TN",
    "sg:tags":[
        "crane"
    ],
    "wof:name":"Sterchi Steel Constructors",
    "wof:placetype":"venue"
},
  "geometry": {"coordinates":[-85.074383,35.073812],"type":"Point"}
}