{
  "type": "Feature",
  "properties": {
    "addr:full":"1230 West Ave Crossville TN 38555",
    "addr:housenumber":"1230",
    "addr:postcode":"38555",
    "addr:street":"West Ave",
    "iso:country":"US",
    "sg:address":"1230 West Ave",
    "sg:city":"Crossville",
    "sg:classifiers":[
        {
            "category":"Shopping",
            "type":"Retail Goods"
        }
    ],
    "sg:phone":"+1 931 484 4879",
    "sg:postcode":"38555",
    "sg:province":"TN",
    "sg:tags":[
        "outdoor"
    ],
    "wof:name":"Plateau Outdoors",
    "wof:placetype":"venue"
},
  "geometry": {"coordinates":[-85.040359,35.957432],"type":"Point"}
}