{
  "type": "Feature",
  "properties": {
    "addr:full":"3748 Townes Ave Memphis TN 38122",
    "addr:postcode":"3748;38122",
    "addr:street":"Townes Ave",
    "iso:country":"US",
    "sg:address":"3748 Townes Ave",
    "sg:city":"Memphis",
    "sg:classifiers":[
        {
            "category":"Food & Beverages",
            "subcategory":"Groceries & Convenience Stores",
            "type":"Retail Goods"
        }
    ],
    "sg:phone":"+1 901 458 3530",
    "sg:postcode":"38122",
    "sg:province":"TN",
    "sg:tags":[
        "grocer"
    ],
    "wof:name":"Rod's Grocery",
    "wof:placetype":"venue"
},
  "geometry": {"coordinates":[-89.93792500000001,35.171669],"type":"Point"}
}