{
  "type": "Feature",
  "properties": {
    "iso:country":"US",
    "sg:address":"101 Main St",
    "sg:city":"Lynchburg",
    "sg:classifiers":[
        {
            "category":"Organizations",
            "subcategory":"Community Association",
            "type":"Services"
        }
    ],
    "sg:phone":"+1 931 759 4509",
    "sg:postcode":"37352",
    "sg:province":"TN",
    "sg:tags":[
        "fraternal"
    ],
    "wof:name":"Farris Creek Lodge",
    "wof:placetype":"venue"
},
  "geometry": {"coordinates":[-86.371793,35.282821],"type":"Point"}
}