{
  "type": "Feature",
  "properties": {
    "iso:country":"US",
    "sg:address":"355 E Broadway St",
    "sg:city":"Newport",
    "sg:classifiers":[
        {
            "category":"Real Estate",
            "subcategory":"Real Estate Agent",
            "type":"Services"
        }
    ],
    "sg:phone":"+1 423 623 9990",
    "sg:postcode":"37821",
    "sg:province":"TN",
    "wof:name":"State Appraisal Office",
    "wof:placetype":"venue"
},
  "geometry": {"coordinates":[-83.18400699999999,35.966637],"type":"Point"}
}