{
  "type": "Feature",
  "properties": {
    "iso:country":"US",
    "sg:address":"65 N Star Dr",
    "sg:city":"Jackson",
    "sg:classifiers":[
        {
            "category":"Building & Trades",
            "subcategory":"Construction",
            "type":"Services"
        }
    ],
    "sg:phone":"+1 731 668 8288",
    "sg:postcode":"38305",
    "sg:province":"TN",
    "sg:tags":[
        "tile",
        "dealer"
    ],
    "wof:name":"Smith's Floor Covering",
    "wof:placetype":"venue"
},
  "geometry": {"coordinates":[-88.854282,35.705017],"type":"Point"}
}