{
  "type": "Feature",
  "properties": {
    "addr:full":"7704 Canyon Dr Chattanooga TN 37416",
    "addr:housenumber":"7704",
    "addr:postcode":"37416",
    "addr:street":"Canyon Dr",
    "iso:country":"US",
    "sg:address":"7704 Canyon Dr",
    "sg:city":"Chattanooga",
    "sg:classifiers":[
        {
            "category":"Education",
            "subcategory":"Special Training",
            "type":"Public Place"
        }
    ],
    "sg:phone":"+1 423 503 5405",
    "sg:postcode":"37416",
    "sg:province":"TN",
    "sg:tags":[
        "dance",
        "distribution",
        "production",
        "music",
        "arts"
    ],
    "wof:name":"Innerprize Productions",
    "wof:placetype":"venue"
},
  "geometry": {"coordinates":[-85.175802,35.074807],"type":"Point"}
}