{
  "type": "Feature",
  "properties": {
    "iso:country":"US",
    "sg:address":"995 S Shady St",
    "sg:city":"Mountain City",
    "sg:classifiers":[
        {
            "category":"Food & Beverages",
            "subcategory":"Groceries & Convenience Stores",
            "type":"Retail Goods"
        }
    ],
    "sg:phone":"+1 423 727 6911",
    "sg:postcode":"37683",
    "sg:province":"TN",
    "wof:name":"Citgo",
    "wof:placetype":"venue"
},
  "geometry": {"coordinates":[-81.801765,36.465543],"type":"Point"}
}