{
  "type": "Feature",
  "properties": {
    "iso:country":"US",
    "sg:address":"2272 N Roan St",
    "sg:city":"Johnson City",
    "sg:classifiers":[
        {
            "category":"Organizations",
            "subcategory":"Religious Organization",
            "type":"Services"
        }
    ],
    "sg:phone":"+1 423 928 8191",
    "sg:postcode":"37601",
    "sg:province":"TN",
    "wof:name":"True Life Ministries",
    "wof:placetype":"venue"
},
  "geometry": {"coordinates":[-82.376926,36.344508],"type":"Point"}
}