{
  "type": "Feature",
  "properties": {
    "addr:full":"1214 Gadd Rd Hixson TN 37343",
    "addr:housenumber":"1214",
    "addr:postcode":"37343",
    "addr:street":"Gadd Rd",
    "iso:country":"US",
    "sg:address":"1214 Gadd Rd",
    "sg:city":"Hixson",
    "sg:classifiers":[
        {
            "category":"Retail",
            "subcategory":"Laundry & Dry Cleaning",
            "type":"Services"
        }
    ],
    "sg:phone":"+1 423 876 8462",
    "sg:postcode":"37343",
    "sg:province":"TN",
    "wof:name":"Budget Carpet Cleaning",
    "wof:placetype":"venue"
},
  "geometry": {"coordinates":[-85.245965,35.142426],"type":"Point"}
}