{
  "type": "Feature",
  "properties": {
    "addr:full":"626 Gallatin Pike S Madison TN 37115",
    "addr:housenumber":"626",
    "addr:postcode":"37115",
    "addr:street":"Gallatin Pike",
    "iso:country":"US",
    "sg:address":"626 Gallatin Pike S",
    "sg:city":"Madison",
    "sg:classifiers":[
        {
            "category":"Insurance",
            "subcategory":"Insurance Agent",
            "type":"Services"
        }
    ],
    "sg:phone":"+1 615 860 3600",
    "sg:postcode":"37115",
    "sg:province":"TN",
    "wof:name":"State Farm Insurance",
    "wof:placetype":"venue"
},
  "geometry": {"coordinates":[-86.71418799999999,36.256449],"type":"Point"}
}