{
  "type": "Feature",
  "properties": {
    "iso:country":"US",
    "sg:address":"1515 S Lee Hwy",
    "sg:city":"Cleveland",
    "sg:classifiers":[
        {
            "category":"Building & Trades",
            "subcategory":"Pest Control",
            "type":"Services"
        }
    ],
    "sg:phone":"+1 423 476 6000",
    "sg:postcode":"37311",
    "sg:province":"TN",
    "wof:name":"David Mayfield Pest Control",
    "wof:placetype":"venue"
},
  "geometry": {"coordinates":[-84.896545,35.152572],"type":"Point"}
}