{
  "type": "Feature",
  "properties": {
    "iso:country":"US",
    "sg:address":"2614 Foster Ave",
    "sg:city":"Nashville",
    "sg:classifiers":[
        {
            "category":"Organizations",
            "subcategory":"Religious Organization",
            "type":"Services"
        }
    ],
    "sg:phone":"+1 615 833 4422",
    "sg:postcode":"37210",
    "sg:province":"TN",
    "sg:tags":[
        "church"
    ],
    "wof:name":"Foster Avenue Church Of Christ",
    "wof:placetype":"venue"
},
  "geometry": {"coordinates":[-86.743557,36.11577],"type":"Point"}
}