{
  "type": "Feature",
  "properties": {
    "iso:country":"US",
    "sg:address":"1601 E Broadway Ave",
    "sg:city":"Maryville",
    "sg:classifiers":[
        {
            "category":"Organizations",
            "subcategory":"Religious Organization",
            "type":"Services"
        }
    ],
    "sg:phone":"+1 865 984 4001",
    "sg:postcode":"37804",
    "sg:province":"TN",
    "wof:name":"Impact Fellowship",
    "wof:placetype":"venue"
},
  "geometry": {"coordinates":[-83.95784399999999,35.771169],"type":"Point"}
}