{
  "type": "Feature",
  "properties": {
    "addr:full":"6424 Hixson Pike Hixson TN 37343",
    "addr:housenumber":"6424",
    "addr:postcode":"37343",
    "addr:street":"Hixson Pike",
    "iso:country":"US",
    "sg:address":"6424 Hixson Pike",
    "sg:city":"Hixson",
    "sg:classifiers":[
        {
            "category":"Organizations",
            "subcategory":"Religious Organization",
            "type":"Services"
        }
    ],
    "sg:phone":"+1 423 842 6515",
    "sg:postcode":"37343",
    "sg:province":"TN",
    "sg:tags":[
        "church"
    ],
    "wof:name":"Hixson Seventh Day Adventist",
    "wof:placetype":"venue"
},
  "geometry": {"coordinates":[-85.196617,35.156646],"type":"Point"}
}