{
  "type": "Feature",
  "properties": {
    "iso:country":"US",
    "sg:address":"4615 Mill Branch Ln",
    "sg:city":"Knoxville",
    "sg:classifiers":[
        {
            "category":"Home & Garden",
            "subcategory":"Furniture",
            "type":"Retail Goods"
        }
    ],
    "sg:phone":"+1 865 922 6458",
    "sg:postcode":"37938",
    "sg:province":"TN",
    "sg:tags":[
        "mattress"
    ],
    "wof:name":"Smokey Mountain Mattress",
    "wof:placetype":"venue"
},
  "geometry": {"coordinates":[-83.91956399999999,36.093638],"type":"Point"}
}