{
  "type": "Feature",
  "properties": {
    "addr:full":"4108 Brown Gap Rd Knoxville TN 37918",
    "addr:housenumber":"4108",
    "addr:postcode":"37918",
    "addr:street":"Brown Gap Rd",
    "iso:country":"US",
    "sg:address":"4108 Brown Gap Rd",
    "sg:city":"Knoxville",
    "sg:classifiers":[
        {
            "category":"Building & Trades",
            "subcategory":"Construction",
            "type":"Services"
        }
    ],
    "sg:phone":"+1 865 687 2043",
    "sg:postcode":"37918",
    "sg:province":"TN",
    "sg:tags":[
        "house",
        "remodeling",
        "general"
    ],
    "wof:name":"Tommy Johnson",
    "wof:placetype":"venue"
},
  "geometry": {"coordinates":[-83.92115800000001,36.059288],"type":"Point"}
}