{
  "type": "Feature",
  "properties": {
    "iso:country":"US",
    "sg:address":"3310 Greenway Dr",
    "sg:city":"Knoxville",
    "sg:classifiers":[
        {
            "category":"Building & Trades",
            "subcategory":"Construction",
            "type":"Services"
        }
    ],
    "sg:phone":"+1 865 687 3400",
    "sg:postcode":"37918",
    "sg:province":"TN",
    "sg:tags":[
        "clearing",
        "land",
        "leveling"
    ],
    "sg:website":"www.wolftreeinc.com",
    "wof:name":"Wolf Tree Experts Inc",
    "wof:placetype":"venue"
},
  "geometry": {"coordinates":[-83.90888099999999,36.027294],"type":"Point"}
}