{
  "type": "Feature",
  "properties": {
    "iso:country":"US",
    "sg:address":"1835 Court Ave",
    "sg:city":"Germantown",
    "sg:classifiers":[
        {
            "category":"Professional",
            "type":"Services"
        }
    ],
    "sg:phone":"+1 901 755 0747",
    "sg:postcode":"38104",
    "sg:province":"TN",
    "sg:tags":[
        "arts",
        "artist"
    ],
    "wof:name":"De Lira's Design",
    "wof:placetype":"venue"
},
  "geometry": {"coordinates":[-89.99813399999999,35.138664],"type":"Point"}
}