{
  "type": "Feature",
  "properties": {
    "iso:country":"US",
    "sg:address":"304 Cedar Glen Cir",
    "sg:city":"Chattanooga",
    "sg:classifiers":[
        {
            "category":"Professional",
            "subcategory":"Management & Consulting",
            "type":"Services"
        }
    ],
    "sg:phone":"+1 423 296 6492",
    "sg:postcode":"37412",
    "sg:province":"TN",
    "sg:tags":[
        "personnel",
        "consultant"
    ],
    "wof:name":"R K Consulting Group",
    "wof:placetype":"venue"
},
  "geometry": {"coordinates":[-85.190138,35.000407],"type":"Point"}
}