{
  "type": "Feature",
  "properties": {
    "addr:full":"1000 Eastern Star Rd Kingsport TN 37663",
    "addr:housenumber":"1000",
    "addr:postcode":"37663",
    "addr:street":"Eastern Star Rd",
    "iso:country":"US",
    "sg:address":"1000 Eastern Star Rd",
    "sg:city":"Kingsport",
    "sg:classifiers":[
        {
            "category":"Wholesale",
            "subcategory":"Durable Goods & Equipment",
            "type":"Manufacturing & Wholesale Goods"
        }
    ],
    "sg:phone":"+1 423 349 6640",
    "sg:postcode":"37663",
    "sg:province":"TN",
    "wof:name":"Teamair Distributors",
    "wof:placetype":"venue"
},
  "geometry": {"coordinates":[-82.52025,36.451202],"type":"Point"}
}