{
  "type": "Feature",
  "properties": {
    "iso:country":"US",
    "sg:address":"1553 Willow Grove Hwy",
    "sg:city":"Monroe",
    "sg:classifiers":[
        {
            "category":"Wholesale",
            "subcategory":"Electrical",
            "type":"Manufacturing & Wholesale Goods"
        }
    ],
    "sg:phone":"+1 931 823 2052",
    "sg:postcode":"38573",
    "sg:province":"TN",
    "sg:tags":[
        "electric",
        "motor"
    ],
    "wof:name":"Sells Electric Motor Shop",
    "wof:placetype":"venue"
},
  "geometry": {"coordinates":[-85.278951,36.482427],"type":"Point"}
}