{
  "type": "Feature",
  "properties": {
    "iso:country":"US",
    "sg:address":"409 Dunailie Dr",
    "sg:city":"Nashville",
    "sg:classifiers":[
        {
            "category":"Retail",
            "subcategory":"Laundry & Dry Cleaning",
            "type":"Services"
        }
    ],
    "sg:phone":"+1 615 361 0988",
    "sg:postcode":"37217",
    "sg:province":"TN",
    "sg:tags":[
        "cleaner",
        "operated",
        "dryer",
        "laundries-self",
        "washer",
        "coin"
    ],
    "wof:name":"Clean World Laundromat",
    "wof:placetype":"venue"
},
  "geometry": {"coordinates":[-86.702124,36.115085],"type":"Point"}
}