{
  "type": "Feature",
  "properties": {
    "iso:country":"US",
    "sg:address":"392 Haw Ridge Dock Rd",
    "sg:city":"Piney Flats",
    "sg:classifiers":[
        {
            "category":"Professional",
            "type":"Services"
        }
    ],
    "sg:phone":"+1 423 538 0105",
    "sg:postcode":"37686",
    "sg:province":"TN",
    "wof:name":"Customer Service Center",
    "wof:placetype":"venue"
},
  "geometry": {"coordinates":[-82.38979999999999,36.459747],"type":"Point"}
}