{
  "type": "Feature",
  "properties": {
    "iso:country":"US",
    "sg:address":"6675 Cloverport Rd",
    "sg:city":"Toone",
    "sg:classifiers":[
        {
            "category":"Home & Garden",
            "subcategory":"Building Materials",
            "type":"Retail Goods"
        }
    ],
    "sg:phone":"+1 731 659 2228",
    "sg:postcode":"38381",
    "sg:province":"TN",
    "sg:tags":[
        "door"
    ],
    "wof:name":"Joyner Glass",
    "wof:placetype":"venue"
},
  "geometry": {"coordinates":[-88.996757,35.36716],"type":"Point"}
}