{
  "type": "Feature",
  "properties": {
    "iso:country":"US",
    "sg:address":"926 E Sevier Ave",
    "sg:city":"Kingsport",
    "sg:classifiers":[
        {
            "category":"Restaurant",
            "type":"Food & Drink"
        }
    ],
    "sg:phone":"+1 423 246 7435",
    "sg:postcode":"37660",
    "sg:province":"TN",
    "sg:tags":[
        "eating"
    ],
    "wof:name":"Plays Los Cabos",
    "wof:placetype":"venue"
},
  "geometry": {"coordinates":[-82.549132,36.541663],"type":"Point"}
}