{
  "type": "Feature",
  "properties": {
    "iso:country":"US",
    "sg:address":"35 Hailey Rd",
    "sg:city":"Savannah",
    "sg:classifiers":[
        {
            "category":"Food & Beverages",
            "subcategory":"Groceries & Convenience Stores",
            "type":"Retail Goods"
        }
    ],
    "sg:phone":"+1 731 925 2661",
    "sg:postcode":"38392",
    "sg:province":"TN",
    "wof:name":"Druckers General Store",
    "wof:placetype":"venue"
},
  "geometry": {"coordinates":[-88.983337,35.444313],"type":"Point"}
}