{
  "type": "Feature",
  "properties": {
    "addr:full":"2511 Sevier Ave Knoxville TN 37920",
    "addr:housenumber":"2511",
    "addr:postcode":"37920",
    "addr:street":"Sevier Ave",
    "iso:country":"US",
    "sg:address":"2511 Sevier Ave",
    "sg:city":"Knoxville",
    "sg:classifiers":[
        {
            "category":"Restaurant",
            "type":"Food & Drink"
        }
    ],
    "sg:phone":"+1 865 524 9171",
    "sg:postcode":"37920",
    "sg:province":"TN",
    "sg:tags":[
        "delicatessen"
    ],
    "wof:name":"Bubba's Country Deli",
    "wof:placetype":"venue"
},
  "geometry": {"coordinates":[-83.897408,35.956666],"type":"Point"}
}