{
  "type": "Feature",
  "properties": {
    "iso:country":"US",
    "sg:address":"101 N Spring St",
    "sg:city":"Mc Minnville",
    "sg:classifiers":[
        {
            "category":"Real Estate",
            "subcategory":"Real Estate Agent",
            "type":"Services"
        }
    ],
    "sg:phone":"+1 931 473 1357",
    "sg:postcode":"37110",
    "sg:province":"TN",
    "sg:tags":[
        "appraiser"
    ],
    "wof:name":"J L Stiles & Assoc",
    "wof:placetype":"venue"
},
  "geometry": {"coordinates":[-85.77152,35.681954],"type":"Point"}
}