{
  "type": "Feature",
  "properties": {
    "iso:country":"US",
    "sg:address":"908 Conference Dr",
    "sg:city":"Goodlettsville",
    "sg:classifiers":[
        {
            "category":"Restaurant",
            "type":"Food & Drink"
        }
    ],
    "sg:menulink":"http://www.allmenus.com/tn/nashville/210232-kabuto/menu/",
    "sg:phone":"+1 615 851 4004",
    "sg:postcode":"37072",
    "sg:province":"TN",
    "sg:tags":[
        "japanese",
        "asian"
    ],
    "wof:name":"Kabuto",
    "wof:placetype":"venue"
},
  "geometry": {"coordinates":[-86.701176,36.32322],"type":"Point"}
}