{
  "type": "Feature",
  "properties": {
    "addr:full":"5006 N Broadway St Knoxville TN 37918",
    "addr:housenumber":"5006",
    "addr:postcode":"37918",
    "addr:street":"N Broadway St",
    "iso:country":"US",
    "sg:address":"5006 N Broadway St",
    "sg:city":"Knoxville",
    "sg:classifiers":[
        {
            "category":"Shopping",
            "subcategory":"Pharmacy",
            "type":"Retail Goods"
        }
    ],
    "sg:phone":"+1 865 688 0179",
    "sg:postcode":"37918",
    "sg:province":"TN",
    "sg:tags":[
        "photofinishing",
        "laboratory"
    ],
    "sg:website":"www.walgreens.com",
    "wof:name":"Walgreens",
    "wof:placetype":"venue"
},
  "geometry": {"coordinates":[-83.929548,36.03145],"type":"Point"}
}