{
  "type": "Feature",
  "properties": {
    "iso:country":"US",
    "sg:address":"243 Mayland Loop",
    "sg:city":"Crossville",
    "sg:classifiers":[
        {
            "category":"Building & Trades",
            "subcategory":"Landscaping Services",
            "type":"Services"
        }
    ],
    "sg:phone":"+1 931 277 5507",
    "sg:postcode":"38571",
    "sg:province":"TN",
    "sg:tags":[
        "tree"
    ],
    "wof:name":"D & K Stump Busters",
    "wof:placetype":"venue"
},
  "geometry": {"coordinates":[-85.198414,36.047697],"type":"Point"}
}