{
  "type": "Feature",
  "properties": {
    "iso:country":"US",
    "sg:address":"1113 Murfreesboro Rd",
    "sg:city":"Franklin",
    "sg:classifiers":[
        {
            "category":"Shopping",
            "subcategory":"Crafts & Fabrics",
            "type":"Retail Goods"
        }
    ],
    "sg:phone":"+1 615 794 0469",
    "sg:postcode":"37064",
    "sg:province":"TN",
    "sg:tags":[
        "shop"
    ],
    "sg:website":"www.hancockfabrics.com",
    "wof:name":"Hancock Fabrics",
    "wof:placetype":"venue"
},
  "geometry": {"coordinates":[-86.83639100000001,35.916156],"type":"Point"}
}