{
  "type": "Feature",
  "properties": {
    "iso:country":"US",
    "sg:address":"2069 Harbert Ave",
    "sg:city":"Memphis",
    "sg:classifiers":[
        {
            "category":"Building & Trades",
            "subcategory":"Landscaping Services",
            "type":"Services"
        }
    ],
    "sg:phone":"+1 901 238 5574",
    "sg:postcode":"38104",
    "sg:province":"TN",
    "sg:tags":[
        "tree"
    ],
    "wof:name":"Ben's Tree Svc Inc",
    "wof:placetype":"venue"
},
  "geometry": {"coordinates":[-89.99281499999999,35.129274],"type":"Point"}
}