{
  "type": "Feature",
  "properties": {
    "iso:country":"US",
    "sg:address":"832 Wedgewood Ave",
    "sg:city":"Nashville",
    "sg:classifiers":[
        {
            "category":"Health Services",
            "subcategory":"Nursing And Care Facility",
            "type":"Services"
        }
    ],
    "sg:phone":"+1 615 383 4006",
    "sg:postcode":"37203",
    "sg:province":"TN",
    "sg:tags":[
        "skilled"
    ],
    "wof:name":"Lakeshore Wedgewood",
    "wof:placetype":"venue"
},
  "geometry": {"coordinates":[-86.780659,36.134373],"type":"Point"}
}