{
  "type": "Feature",
  "properties": {
    "iso:country":"US",
    "sg:address":"5211 Hixson Pike",
    "sg:city":"Hixson",
    "sg:classifiers":[
        {
            "category":"Retail",
            "subcategory":"Laundry & Dry Cleaning",
            "type":"Services"
        }
    ],
    "sg:phone":"+1 423 875 4201",
    "sg:postcode":"37343",
    "sg:province":"TN",
    "sg:tags":[
        "drycleaning",
        "plant"
    ],
    "wof:name":"Kleen-A-Matic",
    "wof:placetype":"venue"
},
  "geometry": {"coordinates":[-85.235208,35.138851],"type":"Point"}
}