{
  "type": "Feature",
  "properties": {
    "iso:country":"US",
    "sg:address":"2968 E Old Ashland City Rd",
    "sg:city":"Clarksville",
    "sg:classifiers":[
        {
            "category":"Building & Trades",
            "subcategory":"Plumbing",
            "type":"Services"
        }
    ],
    "sg:phone":"+1 931 552 5555",
    "sg:postcode":"37043",
    "sg:province":"TN",
    "sg:tags":[
        "plumbing",
        "contractor"
    ],
    "wof:name":"Mac Plumbing",
    "wof:placetype":"venue"
},
  "geometry": {"coordinates":[-87.27290600000001,36.496156],"type":"Point"}
}