{
  "type": "Feature",
  "properties": {
    "iso:country":"US",
    "sg:address":"4605 Lyons View Pike",
    "sg:city":"Knoxville",
    "sg:classifiers":[
        {
            "category":"Building & Trades",
            "subcategory":"Cleaning & Sanitation",
            "type":"Services"
        }
    ],
    "sg:phone":"+1 865 588 1115",
    "sg:postcode":"37919",
    "sg:province":"TN",
    "sg:tags":[
        "polishing",
        "waxing",
        "floor"
    ],
    "wof:name":"S & R Cleaning Svc",
    "wof:placetype":"venue"
},
  "geometry": {"coordinates":[-83.97912700000001,35.940506],"type":"Point"}
}