{
  "type": "Feature",
  "properties": {
    "iso:country":"US",
    "sg:address":"228 Copley Branch Rd",
    "sg:city":"Butler",
    "sg:classifiers":[
        {
            "category":"Manufacturing",
            "subcategory":"Lumber",
            "type":"Manufacturing & Wholesale Goods"
        }
    ],
    "sg:phone":"+1 423 768 3992",
    "sg:postcode":"37640",
    "sg:province":"TN",
    "sg:tags":[
        "logging"
    ],
    "wof:name":"Robinson Logging Inc",
    "wof:placetype":"venue"
},
  "geometry": {"coordinates":[-82.022341,36.365683],"type":"Point"}
}