{
  "type": "Feature",
  "properties": {
    "iso:country":"US",
    "sg:address":"351 State Hwy 100",
    "sg:city":"Centerville",
    "sg:classifiers":[
        {
            "category":"Building & Trades",
            "subcategory":"Pest Control",
            "type":"Services"
        }
    ],
    "sg:phone":"+1 931 729 3940",
    "sg:postcode":"37033",
    "sg:province":"TN",
    "wof:name":"All-Pest Termite & Pest Cntrl",
    "wof:placetype":"venue"
},
  "geometry": {"coordinates":[-87.450498,35.787594],"type":"Point"}
}