{
  "type": "Feature",
  "properties": {
    "iso:country":"US",
    "sg:address":"4191 Stinking Creek Rd",
    "sg:city":"Pioneer",
    "sg:classifiers":[
        {
            "category":"Government",
            "subcategory":"Office",
            "type":"Public Place"
        }
    ],
    "sg:phone":"+1 423 784 3636",
    "sg:postcode":"37847",
    "sg:province":"TN",
    "sg:tags":[
        "county",
        "program"
    ],
    "wof:name":"Campbell County Sanitation",
    "wof:placetype":"venue"
},
  "geometry": {"coordinates":[-84.237837,36.441095],"type":"Point"}
}