{
  "type": "Feature",
  "properties": {
    "iso:country":"US",
    "sg:address":"6771 E Shelby Dr",
    "sg:city":"Memphis",
    "sg:classifiers":[
        {
            "category":"Shopping",
            "subcategory":"Music",
            "type":"Retail Goods"
        }
    ],
    "sg:phone":"+1 901 366 0095",
    "sg:postcode":"38118",
    "sg:province":"TN",
    "sg:tags":[
        "video",
        "disc",
        "tape",
        "cassette"
    ],
    "wof:name":"Cinemagic Video",
    "wof:placetype":"venue"
},
  "geometry": {"coordinates":[-89.839877,35.020382],"type":"Point"}
}