{
  "type": "Feature",
  "properties": {
    "addr:full":"6643 Hwy 52 W Lafayette TN 37083",
    "addr:housenumber":"6643",
    "addr:postcode":"37083",
    "addr:street":"Hwy 52 W",
    "iso:country":"US",
    "sg:address":"6643 Hwy 52 W",
    "sg:city":"Lafayette",
    "sg:classifiers":[
        {
            "category":"Building & Trades",
            "subcategory":"Landscaping Services",
            "type":"Services"
        }
    ],
    "sg:phone":"+1 615 688 3775",
    "sg:postcode":"37083",
    "sg:province":"TN",
    "sg:tags":[
        "lawn",
        "maintenance",
        "grounds"
    ],
    "wof:name":"Kittrell's Mowing",
    "wof:placetype":"venue"
},
  "geometry": {"coordinates":[-86.136336,36.52054],"type":"Point"}
}