{
  "type": "Feature",
  "properties": {
    "addr:full":"1000 N Liberty Hill Rd Morristown TN 37814",
    "addr:housenumber":"1000",
    "addr:postcode":"37814",
    "addr:street":"N Liberty Hill Rd",
    "iso:country":"US",
    "sg:address":"1000 N Liberty Hill Rd",
    "sg:city":"Morristown",
    "sg:classifiers":[
        {
            "category":"Building & Trades",
            "subcategory":"Construction",
            "type":"Services"
        }
    ],
    "sg:phone":"+1 423 581 9458",
    "sg:postcode":"37814",
    "sg:province":"TN",
    "sg:tags":[
        "contractor"
    ],
    "wof:name":"H 20 Pruf Systems",
    "wof:placetype":"venue"
},
  "geometry": {"coordinates":[-83.27745400000001,36.227578],"type":"Point"}
}