{
  "type": "Feature",
  "properties": {
    "addr:full":"111 Hospitality Blvd Manchester TN 37355",
    "addr:housenumber":"111",
    "addr:postcode":"37355",
    "addr:street":"Hospitality Blvd",
    "iso:country":"US",
    "sg:address":"111 Hospitality Blvd",
    "sg:city":"Manchester",
    "sg:classifiers":[
        {
            "category":"Travel",
            "subcategory":"Hotels & Motels",
            "type":"Entertainment"
        }
    ],
    "sg:phone":"+1 931 728 9383",
    "sg:postcode":"37355",
    "sg:province":"TN",
    "sg:website":"www.holidayinn.com",
    "wof:name":"Holiday Inn Express-Conf Ctr",
    "wof:placetype":"venue"
},
  "geometry": {"coordinates":[-86.04854899999999,35.45773],"type":"Point"}
}