{
  "type": "Feature",
  "properties": {
    "iso:country":"US",
    "sg:address":"2 Glen Abbey",
    "sg:city":"Nashville",
    "sg:classifiers":[
        {
            "category":"Building & Trades",
            "subcategory":"Construction",
            "type":"Services"
        }
    ],
    "sg:phone":"+1 615 221 9737",
    "sg:postcode":"37215",
    "sg:province":"TN",
    "sg:tags":[
        "glass",
        "door",
        "sales"
    ],
    "wof:name":"Brandon Door & Glass LLC",
    "wof:placetype":"venue"
},
  "geometry": {"coordinates":[-86.826848,36.053971],"type":"Point"}
}