{
  "type": "Feature",
  "properties": {
    "addr:full":"7257 Bonnyshire Dr Chattanooga TN 37416",
    "addr:housenumber":"7257",
    "addr:postcode":"37416",
    "addr:street":"Bonnyshire Dr",
    "iso:country":"US",
    "sg:address":"7257 Bonnyshire Dr",
    "sg:city":"Chattanooga",
    "sg:classifiers":[
        {
            "category":"Home & Garden",
            "subcategory":"Building Materials",
            "type":"Retail Goods"
        }
    ],
    "sg:phone":"+1 423 855 4108",
    "sg:postcode":"37416",
    "sg:province":"TN",
    "sg:website":"http://www.interiortrimandsupply.com",
    "wof:name":"Interior Trim & Supply Inc",
    "wof:placetype":"venue"
},
  "geometry": {"coordinates":[-85.164945,35.069015],"type":"Point"}
}