{
  "type": "Feature",
  "properties": {
    "addr:full":"3006 E Oakland Ave Johnson City TN 37601",
    "addr:housenumber":"3006",
    "addr:postcode":"37601",
    "addr:street":"E Oakland Ave",
    "iso:country":"US",
    "sg:address":"3006 E Oakland Ave",
    "sg:city":"Johnson City",
    "sg:classifiers":[
        {
            "category":"Building & Trades",
            "subcategory":"Construction",
            "type":"Services"
        }
    ],
    "sg:phone":"+1 423 282 6611",
    "sg:postcode":"37601",
    "sg:province":"TN",
    "sg:tags":[
        "merchandise",
        "contractor"
    ],
    "wof:name":"Thouin Enterprises",
    "wof:placetype":"venue"
},
  "geometry": {"coordinates":[-82.38134599999999,36.360401],"type":"Point"}
}