{
  "type": "Feature",
  "properties": {
    "iso:country":"US",
    "sg:address":"2233 Hwy 75",
    "sg:city":"Blountville",
    "sg:classifiers":[
        {
            "category":"Wholesale",
            "subcategory":"Machinery & Supplies",
            "type":"Manufacturing & Wholesale Goods"
        }
    ],
    "sg:phone":"+1 423 279 7220",
    "sg:postcode":"37617",
    "sg:province":"TN",
    "sg:tags":[
        "equipment",
        "industrial",
        "cleaning",
        "bu"
    ],
    "wof:name":"Just Clean",
    "wof:placetype":"venue"
},
  "geometry": {"coordinates":[-82.40665300000001,36.494136],"type":"Point"}
}