{
  "type": "Feature",
  "properties": {
    "iso:country":"US",
    "sg:address":"8802 Pine Ridge Rd",
    "sg:city":"Ooltewah",
    "sg:classifiers":[
        {
            "category":"Real Estate",
            "subcategory":"Real Estate Agent",
            "type":"Services"
        }
    ],
    "sg:phone":"+1 423 892 6169",
    "sg:postcode":"37363",
    "sg:province":"TN",
    "wof:name":"Amicus LLC",
    "wof:placetype":"venue"
},
  "geometry": {"coordinates":[-85.08693,35.036869],"type":"Point"}
}