{
  "type": "Feature",
  "properties": {
    "iso:country":"US",
    "sg:address":"200 S Main St",
    "sg:city":"Bolivar",
    "sg:classifiers":[
        {
            "category":"Home & Garden",
            "subcategory":"Household Appliances",
            "type":"Retail Goods"
        }
    ],
    "sg:phone":"+1 731 658 3193",
    "sg:postcode":"38008",
    "sg:province":"TN",
    "sg:tags":[
        "electronics",
        "consumer"
    ],
    "wof:name":"Wheeler Radio & TV Service",
    "wof:placetype":"venue"
},
  "geometry": {"coordinates":[-88.987876,35.255385],"type":"Point"}
}