{
  "type": "Feature",
  "properties": {
    "addr:full":"782 Old Hickory Blvd Brentwood TN 37027",
    "addr:housenumber":"782",
    "addr:postcode":"37027",
    "addr:street":"Old Hickory Blvd",
    "iso:country":"US",
    "sg:address":"782 Old Hickory Blvd",
    "sg:city":"Brentwood",
    "sg:classifiers":[
        {
            "category":"Food & Beverages",
            "subcategory":"Specialty",
            "type":"Retail Goods"
        }
    ],
    "sg:phone":"+1 615 221 9909",
    "sg:postcode":"37027",
    "sg:province":"TN",
    "sg:tags":[
        "health",
        "diet"
    ],
    "wof:name":"GNC",
    "wof:placetype":"venue"
},
  "geometry": {"coordinates":[-86.78258099999999,36.038996],"type":"Point"}
}