{
  "type": "Feature",
  "properties": {
    "addr:full":"4909 Ball Rd Knoxville TN 37931",
    "addr:housenumber":"4909",
    "addr:postcode":"37931",
    "addr:street":"Ball Rd",
    "iso:country":"US",
    "sg:address":"4909 Ball Rd",
    "sg:city":"Knoxville",
    "sg:classifiers":[
        {
            "category":"Freight",
            "type":"Transportation"
        }
    ],
    "sg:phone":"+1 865 330 3555",
    "sg:postcode":"37931",
    "sg:province":"TN",
    "sg:tags":[
        "general"
    ],
    "wof:name":"Western Avenue Mini Storage",
    "wof:placetype":"venue"
},
  "geometry": {"coordinates":[-84.059168,35.987049],"type":"Point"}
}