{
  "type": "Feature",
  "properties": {
    "addr:full":"900 Georgia Ave Chattanooga TN 37402",
    "addr:housenumber":"900",
    "addr:postcode":"37402",
    "addr:street":"Georgia Ave",
    "iso:country":"US",
    "sg:address":"900 Georgia Ave",
    "sg:city":"Chattanooga",
    "sg:classifiers":[
        {
            "category":"Social Services",
            "type":"Services"
        }
    ],
    "sg:phone":"+1 423 752 5193",
    "sg:postcode":"37402",
    "sg:province":"TN",
    "sg:tags":[
        "probation"
    ],
    "wof:name":"US Probation & Parole Office",
    "wof:placetype":"venue"
},
  "geometry": {"coordinates":[-85.30885000000001,35.044709],"type":"Point"}
}