{
  "type": "Feature",
  "properties": {
    "addr:full":"3171 Standard Dr Memphis TN 38111",
    "addr:housenumber":"3171",
    "addr:postcode":"38111",
    "addr:street":"Standard Dr",
    "iso:country":"US",
    "sg:address":"3171 Standard Dr",
    "sg:city":"Memphis",
    "sg:classifiers":[
        {
            "category":"Building & Trades",
            "subcategory":"Construction",
            "type":"Services"
        }
    ],
    "sg:phone":"+1 901 744 7385",
    "sg:postcode":"38111",
    "sg:province":"TN",
    "sg:tags":[
        "nonresidential"
    ],
    "wof:name":"Powers Construction Co",
    "wof:placetype":"venue"
},
  "geometry": {"coordinates":[-89.956197,35.097322],"type":"Point"}
}