{
  "type": "Feature",
  "properties": {
    "addr:full":"167 8th Ave N Nashville TN 37203",
    "addr:housenumber":"167",
    "addr:postcode":"37203",
    "addr:street":"8Th Ave N",
    "iso:country":"US",
    "sg:address":"167 8th Ave N",
    "sg:city":"Nashville",
    "sg:classifiers":[
        {
            "category":"Restaurant",
            "type":"Food & Drink"
        }
    ],
    "sg:phone":"+1 615 244 2229",
    "sg:postcode":"37203",
    "sg:province":"TN",
    "sg:tags":[
        "caterer"
    ],
    "wof:name":"Catering Unlimited Inc",
    "wof:placetype":"venue"
},
  "geometry": {"coordinates":[-86.782363,36.159385],"type":"Point"}
}