{
  "type": "Feature",
  "properties": {
    "iso:country":"US",
    "sg:address":"320 Troy Cir SW",
    "sg:city":"Knoxville",
    "sg:classifiers":[
        {
            "category":"Building & Trades",
            "subcategory":"Construction",
            "type":"Services"
        }
    ],
    "sg:phone":"+1 865 794 5465",
    "sg:postcode":"37919",
    "sg:province":"TN",
    "sg:tags":[
        "roofing",
        "contractor"
    ],
    "wof:name":"John Heithcock & Son Roofing",
    "wof:placetype":"venue"
},
  "geometry": {"coordinates":[-84.004564,35.927206],"type":"Point"}
}