{
  "type": "Feature",
  "properties": {
    "iso:country":"US",
    "sg:address":"6031 Knight Arnold Rd Exd",
    "sg:city":"Memphis",
    "sg:classifiers":[
        {
            "category":"Professional",
            "type":"Services"
        }
    ],
    "sg:phone":"+1 901 795 0903",
    "sg:postcode":"38115",
    "sg:province":"TN",
    "sg:tags":[
        "establishment"
    ],
    "wof:name":"Margarita Candy",
    "wof:placetype":"venue"
},
  "geometry": {"coordinates":[-89.865312,35.060646],"type":"Point"}
}