{
  "type": "Feature",
  "properties": {
    "iso:country":"US",
    "sg:address":"222 S 16th St",
    "sg:city":"Nashville",
    "sg:classifiers":[
        {
            "category":"Taxi",
            "type":"Transportation"
        }
    ],
    "sg:phone":"+1 615 256 8294",
    "sg:postcode":"37206",
    "sg:province":"TN",
    "sg:tags":[
        "taxicab"
    ],
    "wof:name":"A Absolute Taxi",
    "wof:placetype":"venue"
},
  "geometry": {"coordinates":[-86.742407,36.174165],"type":"Point"}
}