{
  "type": "Feature",
  "properties": {
    "addr:full":"1105 W Lincoln St Tullahoma TN 37388",
    "addr:housenumber":"1105",
    "addr:postcode":"37388",
    "addr:street":"W Lincoln St",
    "iso:country":"US",
    "sg:address":"1105 W Lincoln St",
    "sg:city":"Tullahoma",
    "sg:classifiers":[
        {
            "category":"Organizations",
            "subcategory":"Religious Organization",
            "type":"Services"
        }
    ],
    "sg:phone":"+1 931 455 2984",
    "sg:postcode":"37388",
    "sg:province":"TN",
    "sg:tags":[
        "personal"
    ],
    "wof:name":"First Assembly of God Inc",
    "wof:placetype":"venue"
},
  "geometry": {"coordinates":[-86.22676,35.353362],"type":"Point"}
}