{
  "type": "Feature",
  "properties": {
    "iso:country":"US",
    "sg:address":"4091 Summer Ave",
    "sg:city":"Memphis",
    "sg:classifiers":[
        {
            "category":"Shopping",
            "subcategory":"Clothing, Apparel, & Fashions",
            "type":"Retail Goods"
        }
    ],
    "sg:phone":"+1 901 458 2330",
    "sg:postcode":"38122",
    "sg:province":"TN",
    "sg:tags":[
        "western"
    ],
    "wof:name":"LA Herradura",
    "wof:placetype":"venue"
},
  "geometry": {"coordinates":[-89.924263,35.14897],"type":"Point"}
}