{
  "type": "Feature",
  "properties": {
    "iso:country":"US",
    "sg:address":"175 S 3rd St",
    "sg:city":"Selmer",
    "sg:classifiers":[
        {
            "category":"Insurance",
            "subcategory":"Insurance Agent",
            "type":"Services"
        }
    ],
    "sg:phone":"+1 731 645 4827",
    "sg:postcode":"38375",
    "sg:province":"TN",
    "wof:name":"United Insurance Company Amer",
    "wof:placetype":"venue"
},
  "geometry": {"coordinates":[-88.593925,35.169841],"type":"Point"}
}