{
  "type": "Feature",
  "properties": {
    "iso:country":"US",
    "sg:address":"8893 Wenham Cove E",
    "sg:city":"Cordova",
    "sg:classifiers":[
        {
            "category":"Health Services",
            "subcategory":"Medical Lab",
            "type":"Services"
        }
    ],
    "sg:phone":"+1 901 753 8519",
    "sg:postcode":"38016",
    "sg:province":"TN",
    "sg:tags":[
        "laboratory",
        "dental"
    ],
    "wof:name":"Griggs Dental Laboratory",
    "wof:placetype":"venue"
},
  "geometry": {"coordinates":[-89.768399,35.173815],"type":"Point"}
}