{
  "type": "Feature",
  "properties": {
    "iso:country":"US",
    "sg:address":"5326 Solitaire Way",
    "sg:city":"Memphis",
    "sg:classifiers":[
        {
            "category":"Building & Trades",
            "subcategory":"Landscaping Services",
            "type":"Services"
        }
    ],
    "sg:phone":"+1 901 289 6325",
    "sg:postcode":"38109",
    "sg:province":"TN",
    "sg:tags":[
        "lawn"
    ],
    "wof:name":"Gillespies Lawn Service",
    "wof:placetype":"venue"
},
  "geometry": {"coordinates":[-90.090152,35.003406],"type":"Point"}
}