{
  "type": "Feature",
  "properties": {
    "iso:country":"US",
    "sg:address":"603 Calderwood Hwy",
    "sg:city":"Maryville",
    "sg:classifiers":[
        {
            "category":"Building & Trades",
            "subcategory":"Plumbing",
            "type":"Services"
        }
    ],
    "sg:phone":"+1 865 982 4544",
    "sg:postcode":"37801",
    "sg:province":"TN",
    "sg:tags":[
        "contractor"
    ],
    "wof:name":"Stanley Best Heating & AC",
    "wof:placetype":"venue"
},
  "geometry": {"coordinates":[-84.041065,35.68051],"type":"Point"}
}