{
  "type": "Feature",
  "properties": {
    "addr:full":"10099 Gordon St Soddy Daisy TN 37379",
    "addr:housenumber":"10099",
    "addr:postcode":"37379",
    "addr:street":"Gordon St",
    "iso:country":"US",
    "sg:address":"10099 Gordon St",
    "sg:city":"Soddy Daisy",
    "sg:classifiers":[
        {
            "category":"Building & Trades",
            "subcategory":"Construction",
            "type":"Services"
        }
    ],
    "sg:phone":"+1 423 332 1832",
    "sg:postcode":"37379",
    "sg:province":"TN",
    "sg:tags":[
        "house"
    ],
    "wof:name":"DC Remodeling",
    "wof:placetype":"venue"
},
  "geometry": {"coordinates":[-85.156701,35.240679],"type":"Point"}
}