{
  "type": "Feature",
  "properties": {
    "iso:country":"US",
    "sg:address":"6300 Baileyton Rd",
    "sg:city":"Greeneville",
    "sg:classifiers":[
        {
            "category":"Organizations",
            "subcategory":"Religious Organization",
            "type":"Services"
        }
    ],
    "sg:phone":"+1 423 639 5555",
    "sg:postcode":"37745",
    "sg:province":"TN",
    "sg:tags":[
        "church"
    ],
    "wof:name":"Gospel Way Independent Baptist",
    "wof:placetype":"venue"
},
  "geometry": {"coordinates":[-82.82793100000001,36.252963],"type":"Point"}
}