{
  "type": "Feature",
  "properties": {
    "iso:country":"US",
    "sg:address":"3747 Colvett Rd",
    "sg:city":"Alamo",
    "sg:classifiers":[
        {
            "category":"Retail",
            "subcategory":"Repair Shop",
            "type":"Services"
        }
    ],
    "sg:phone":"+1 731 677 3027",
    "sg:postcode":"38001",
    "sg:province":"TN",
    "sg:tags":[
        "welding"
    ],
    "wof:name":"G V's Welding Fabricating",
    "wof:placetype":"venue"
},
  "geometry": {"coordinates":[-89.13614699999999,35.863254],"type":"Point"}
}