{
  "type": "Feature",
  "properties": {
    "iso:country":"US",
    "sg:address":"18 Peachtree St",
    "sg:city":"Nashville",
    "sg:classifiers":[
        {
            "category":"Professional",
            "type":"Services"
        }
    ],
    "sg:phone":"+1 615 331 6135",
    "sg:postcode":"37210",
    "sg:province":"TN",
    "wof:name":"Allie Cunningham",
    "wof:placetype":"venue"
},
  "geometry": {"coordinates":[-86.732361,36.119341],"type":"Point"}
}