{
  "type": "Feature",
  "properties": {
    "iso:country":"US",
    "sg:address":"3331 Millbranch Rd",
    "sg:city":"Memphis",
    "sg:classifiers":[
        {
            "category":"Freight",
            "type":"Transportation"
        }
    ],
    "sg:phone":"+1 901 344 0100",
    "sg:postcode":"38116",
    "sg:province":"TN",
    "wof:name":"Air Serv Corp",
    "wof:placetype":"venue"
},
  "geometry": {"coordinates":[-90.007324,35.060625],"type":"Point"}
}