{
  "type": "Feature",
  "properties": {
    "iso:country":"US",
    "sg:address":"2551 Buffalo Trl",
    "sg:city":"Morristown",
    "sg:classifiers":[
        {
            "category":"Autos & Motor Vehicles",
            "subcategory":"Automobile Sales",
            "type":"Retail Goods"
        }
    ],
    "sg:phone":"+1 423 317 7132",
    "sg:postcode":"37814",
    "sg:province":"TN",
    "sg:tags":[
        "car",
        "dealer"
    ],
    "wof:name":"B & B Auto Sales Inc",
    "wof:placetype":"venue"
},
  "geometry": {"coordinates":[-83.284463,36.247288],"type":"Point"}
}