{
  "type": "Feature",
  "properties": {
    "iso:country":"US",
    "sg:address":"1114 17th Ave S",
    "sg:city":"Nashville",
    "sg:classifiers":[
        {
            "category":"Professional",
            "subcategory":"Lawyer & Legal Services",
            "type":"Services"
        }
    ],
    "sg:phone":"+1 615 329 9455",
    "sg:postcode":"37212",
    "sg:province":"TN",
    "sg:tags":[
        "attorney"
    ],
    "wof:name":"J Rush Hicks Law Office",
    "wof:placetype":"venue"
},
  "geometry": {"coordinates":[-86.794026,36.145434],"type":"Point"}
}