{
  "type": "Feature",
  "properties": {
    "iso:country":"US",
    "sg:address":"826 Hills Creek Rd",
    "sg:city":"Mc Minnville",
    "sg:classifiers":[
        {
            "category":"Wholesale",
            "subcategory":"Plants",
            "type":"Manufacturing & Wholesale Goods"
        }
    ],
    "sg:phone":"+1 931 668 8071",
    "sg:postcode":"37110",
    "sg:province":"TN",
    "sg:website":"www.hillscreeknursery.com",
    "wof:name":"Hill's Creek Nursery",
    "wof:placetype":"venue"
},
  "geometry": {"coordinates":[-85.69922200000001,35.580373],"type":"Point"}
}