{
  "type": "Feature",
  "properties": {
    "iso:country":"US",
    "sg:address":"721 Myatt Dr",
    "sg:city":"Madison",
    "sg:classifiers":[
        {
            "category":"Cinema",
            "subcategory":"Movie Theater",
            "type":"Entertainment"
        }
    ],
    "sg:phone":"+1 615 860 7686",
    "sg:postcode":"37115",
    "sg:province":"TN",
    "wof:name":"Wynnsong 10",
    "wof:placetype":"venue"
},
  "geometry": {"coordinates":[-86.696782,36.294326],"type":"Point"}
}