{
  "type": "Feature",
  "properties": {
    "addr:full":"3101 Palmer Place Dr Lebanon TN 37090",
    "addr:housenumber":"3101",
    "addr:postcode":"37090",
    "addr:street":"Palmer Place Dr",
    "iso:country":"US",
    "sg:address":"3101 Palmer Place Dr",
    "sg:city":"Lebanon",
    "sg:classifiers":[
        {
            "category":"Professional",
            "subcategory":"Business Services",
            "type":"Services"
        }
    ],
    "sg:phone":"+1 615 444 2614",
    "sg:postcode":"37090",
    "sg:province":"TN",
    "sg:tags":[
        "interior",
        "consultant",
        "design",
        "decorator"
    ],
    "wof:name":"Kristina's Interiors",
    "wof:placetype":"venue"
},
  "geometry": {"coordinates":[-86.382667,36.206313],"type":"Point"}
}