{
  "type": "Feature",
  "properties": {
    "iso:country":"US",
    "sg:address":"4212 Keith Rd",
    "sg:city":"Springfield",
    "sg:classifiers":[
        {
            "category":"Building & Trades",
            "subcategory":"Electrical",
            "type":"Services"
        }
    ],
    "sg:phone":"+1 615 384 2106",
    "sg:postcode":"37172",
    "sg:province":"TN",
    "sg:tags":[
        "electrical",
        "contractor"
    ],
    "wof:name":"C J Electric",
    "wof:placetype":"venue"
},
  "geometry": {"coordinates":[-86.773382,36.531891],"type":"Point"}
}