{
  "type": "Feature",
  "properties": {
    "iso:country":"US",
    "sg:address":"167 Cadillac Ln",
    "sg:city":"Mc Minnville",
    "sg:classifiers":[
        {
            "category":"Government",
            "subcategory":"Office",
            "type":"Public Place"
        }
    ],
    "sg:phone":"+1 931 668 9073",
    "sg:postcode":"37110",
    "sg:province":"TN",
    "sg:tags":[
        "state",
        "program"
    ],
    "wof:name":"Drivers License Ctr",
    "wof:placetype":"venue"
},
  "geometry": {"coordinates":[-85.74423400000001,35.703169],"type":"Point"}
}