{
  "type": "Feature",
  "properties": {
    "iso:country":"US",
    "sg:address":"7203 US Hwy 11 E",
    "sg:city":"Lenoir City",
    "sg:classifiers":[
        {
            "category":"Building & Trades",
            "subcategory":"Plumbing",
            "type":"Services"
        }
    ],
    "sg:phone":"+1 865 986 7307",
    "sg:postcode":"37772",
    "sg:province":"TN",
    "sg:tags":[
        "plumbing",
        "contractor"
    ],
    "wof:name":"Turn Key Plumbing & Constr Inc",
    "wof:placetype":"venue"
},
  "geometry": {"coordinates":[-84.25203999999999,35.824389],"type":"Point"}
}