{
  "type": "Feature",
  "properties": {
    "addr:full":"221 E Main St Hendersonville TN 37075",
    "addr:housenumber":"221",
    "addr:postcode":"37075",
    "addr:street":"E Main St",
    "iso:country":"US",
    "sg:address":"221 E Main St",
    "sg:city":"Hendersonville",
    "sg:classifiers":[
        {
            "category":"Banks & Credit Unions",
            "subcategory":"Bank",
            "type":"Services"
        }
    ],
    "sg:phone":"+1 615 822 3024",
    "sg:postcode":"37075",
    "sg:province":"TN",
    "wof:name":"National Bank Of Commerce",
    "wof:placetype":"venue"
},
  "geometry": {"coordinates":[-86.60472900000001,36.308257],"type":"Point"}
}