{
  "type": "Feature",
  "properties": {
    "addr:full":"640 Rock Springs Rd Kingsport TN 37664",
    "addr:housenumber":"640",
    "addr:postcode":"37664",
    "addr:street":"Rock Springs Rd",
    "iso:country":"US",
    "sg:address":"640 Rock Springs Rd",
    "sg:city":"Kingsport",
    "sg:classifiers":[
        {
            "category":"Social Services",
            "subcategory":"Adult Care",
            "type":"Services"
        }
    ],
    "sg:phone":"+1 423 239 8803",
    "sg:postcode":"37664",
    "sg:province":"TN",
    "sg:tags":[
        "living",
        "assisted",
        "facility"
    ],
    "wof:name":"Remington House",
    "wof:placetype":"venue"
},
  "geometry": {"coordinates":[-82.529954,36.48678],"type":"Point"}
}