{
  "type": "Feature",
  "properties": {
    "addr:full":"892 4th St Crossville TN 38555",
    "addr:housenumber":"892",
    "addr:postcode":"38555",
    "addr:street":"4Th St",
    "iso:country":"US",
    "sg:address":"892 4th St",
    "sg:city":"Crossville",
    "sg:classifiers":[
        {
            "category":"Retail",
            "subcategory":"Repair Shop",
            "type":"Services"
        }
    ],
    "sg:phone":"+1 931 484 7228",
    "sg:postcode":"38555",
    "sg:province":"TN",
    "sg:tags":[
        "upholsterer"
    ],
    "wof:name":"Plateau Upholstery",
    "wof:placetype":"venue"
},
  "geometry": {"coordinates":[-85.039941,35.9419],"type":"Point"}
}