{
  "type": "Feature",
  "properties": {
    "iso:country":"US",
    "sg:address":"601 N Church St",
    "sg:city":"Livingston",
    "sg:classifiers":[
        {
            "category":"Personal",
            "subcategory":"Barber",
            "type":"Services"
        }
    ],
    "sg:phone":"+1 931 823 8622",
    "sg:postcode":"38570",
    "sg:province":"TN",
    "wof:name":"Misenhimer Barber Shop",
    "wof:placetype":"venue"
},
  "geometry": {"coordinates":[-85.324513,36.389867],"type":"Point"}
}