{
  "type": "Feature",
  "properties": {
    "iso:country":"US",
    "sg:address":"3645 Cato Ct",
    "sg:city":"Memphis",
    "sg:classifiers":[
        {
            "category":"Shopping",
            "subcategory":"Used Merchandise",
            "type":"Retail Goods"
        }
    ],
    "sg:phone":"+1 901 785 1015",
    "sg:postcode":"38109",
    "sg:province":"TN",
    "sg:tags":[
        "antique"
    ],
    "wof:name":"Martin's Antiques",
    "wof:placetype":"venue"
},
  "geometry": {"coordinates":[-90.06766399999999,35.049119],"type":"Point"}
}