{
  "type": "Feature",
  "properties": {
    "iso:country":"US",
    "sg:address":"5100 State Hwy 58",
    "sg:city":"Chattanooga",
    "sg:classifiers":[
        {
            "category":"Autos & Motor Vehicles",
            "subcategory":"Motorcycle Sales",
            "type":"Retail Goods"
        }
    ],
    "sg:phone":"+1 423 892 0619",
    "sg:postcode":"37416",
    "sg:province":"TN",
    "sg:tags":[
        "scooter"
    ],
    "wof:name":"Cripple Creek Cycles & Leather",
    "wof:placetype":"venue"
},
  "geometry": {"coordinates":[-85.17230000000001,35.097829],"type":"Point"}
}