{
  "type": "Feature",
  "properties": {
    "iso:country":"US",
    "sg:address":"6513 Kingston Pike",
    "sg:city":"Knoxville",
    "sg:classifiers":[
        {
            "category":"Utilities",
            "subcategory":"Mobile Phone",
            "type":"Services"
        }
    ],
    "sg:phone":"+1 865 584 2355",
    "sg:postcode":"37919",
    "sg:province":"TN",
    "sg:tags":[
        "communication",
        "radiotelephone",
        "merchandise"
    ],
    "wof:name":"Verizon",
    "wof:placetype":"venue"
},
  "geometry": {"coordinates":[-84.012502,35.931941],"type":"Point"}
}