{
  "type": "Feature",
  "properties": {
    "iso:country":"US",
    "sg:address":"140 S Headden Dr",
    "sg:city":"Ridgely",
    "sg:classifiers":[
        {
            "category":"Health Services",
            "subcategory":"Doctor",
            "type":"Services"
        }
    ],
    "sg:phone":"+1 731 264 9944",
    "sg:postcode":"38080",
    "sg:province":"TN",
    "sg:tags":[
        "physician",
        "surgeon"
    ],
    "wof:name":"Lake County Internal Medicine",
    "wof:placetype":"venue"
},
  "geometry": {"coordinates":[-89.478082,36.263537],"type":"Point"}
}