{
  "type": "Feature",
  "properties": {
    "iso:country":"US",
    "sg:address":"318 Ridgefields Rd",
    "sg:city":"Kingsport",
    "sg:classifiers":[
        {
            "category":"Restaurant",
            "type":"Food & Drink"
        }
    ],
    "sg:phone":"+1 423 612 1775",
    "sg:postcode":"37660",
    "sg:province":"TN",
    "wof:name":"Texas Smoke House Inc",
    "wof:placetype":"venue"
},
  "geometry": {"coordinates":[-82.591548,36.549073],"type":"Point"}
}