{
  "type": "Feature",
  "properties": {
    "iso:country":"US",
    "sg:address":"5062 Lakeview Dr",
    "sg:city":"Nashville",
    "sg:classifiers":[
        {
            "category":"Restaurant",
            "type":"Food & Drink"
        }
    ],
    "sg:phone":"+1 615 661 7981",
    "sg:postcode":"37220",
    "sg:province":"TN",
    "sg:tags":[
        "eating"
    ],
    "wof:name":"Call In Kettle Black Music",
    "wof:placetype":"venue"
},
  "geometry": {"coordinates":[-86.79920300000001,36.06884],"type":"Point"}
}