{
  "type": "Feature",
  "properties": {
    "iso:country":"US",
    "sg:address":"930 Kerr Ave",
    "sg:city":"Memphis",
    "sg:classifiers":[
        {
            "category":"Food & Beverages",
            "subcategory":"Liquor & Beverages",
            "type":"Retail Goods"
        }
    ],
    "sg:phone":"+1 901 948 0052",
    "sg:postcode":"38106",
    "sg:province":"TN",
    "wof:name":"Big Lee's Liquor's",
    "wof:placetype":"venue"
},
  "geometry": {"coordinates":[-90.03245200000001,35.107094],"type":"Point"}
}