{
  "type": "Feature",
  "properties": {
    "iso:country":"US",
    "sg:address":"615 Co Rd 319",
    "sg:city":"Niota",
    "sg:classifiers":[
        {
            "category":"Shopping",
            "subcategory":"Jewelry",
            "type":"Retail Goods"
        }
    ],
    "sg:phone":"+1 423 568 2934",
    "sg:postcode":"37826",
    "sg:province":"TN",
    "wof:name":"Jewelry By Design",
    "wof:placetype":"venue"
},
  "geometry": {"coordinates":[-84.54485099999999,35.556934],"type":"Point"}
}