{
  "type": "Feature",
  "properties": {
    "addr:full":"2335 Charleston Gift Rd Covington TN 38019",
    "addr:housenumber":"2335",
    "addr:postcode":"38019",
    "addr:street":"Charleston Gift Rd",
    "iso:country":"US",
    "sg:address":"2335 Charleston Gift Rd",
    "sg:city":"Covington",
    "sg:classifiers":[
        {
            "category":"Retail",
            "subcategory":"Animal Services",
            "type":"Services"
        }
    ],
    "sg:phone":"+1 901 353 7575",
    "sg:postcode":"38019",
    "sg:province":"TN",
    "wof:name":"Dyson Training and Breeding",
    "wof:placetype":"venue"
},
  "geometry": {"coordinates":[-89.53297000000001,35.526891],"type":"Point"}
}