{
  "type": "Feature",
  "properties": {
    "iso:country":"US",
    "sg:address":"5390 Greystone Rd",
    "sg:city":"Greeneville",
    "sg:classifiers":[
        {
            "category":"Food & Beverages",
            "subcategory":"Groceries & Convenience Stores",
            "type":"Retail Goods"
        }
    ],
    "sg:phone":"+1 423 639 3962",
    "sg:postcode":"37743",
    "sg:province":"TN",
    "sg:tags":[
        "grocer"
    ],
    "wof:name":"Hopson's Grocery",
    "wof:placetype":"venue"
},
  "geometry": {"coordinates":[-82.704801,36.102534],"type":"Point"}
}