{
  "type": "Feature",
  "properties": {
    "iso:country":"US",
    "sg:address":"12240 Channel Point Dr",
    "sg:city":"Knoxville",
    "sg:classifiers":[
        {
            "category":"Building & Trades",
            "subcategory":"Construction",
            "type":"Services"
        }
    ],
    "sg:phone":"+1 865 966 8419",
    "sg:postcode":"37922",
    "sg:province":"TN",
    "sg:tags":[
        "designer",
        "dealer",
        "pool",
        "swimming"
    ],
    "wof:name":"Pro Pools",
    "wof:placetype":"venue"
},
  "geometry": {"coordinates":[-84.148015,35.81129],"type":"Point"}
}