{
  "type": "Feature",
  "properties": {
    "iso:country":"US",
    "sg:address":"2103 Maryville Pike",
    "sg:city":"Knoxville",
    "sg:classifiers":[
        {
            "category":"Retail",
            "subcategory":"Auto Repair",
            "type":"Services"
        }
    ],
    "sg:phone":"+1 865 573 2688",
    "sg:postcode":"37920",
    "sg:province":"TN",
    "sg:tags":[
        "body"
    ],
    "wof:name":"Allen Enterprise",
    "wof:placetype":"venue"
},
  "geometry": {"coordinates":[-83.936942,35.913733],"type":"Point"}
}