{
  "type": "Feature",
  "properties": {
    "iso:country":"US",
    "sg:address":"920 Indian Mound Rd",
    "sg:city":"Indian Mound",
    "sg:classifiers":[
        {
            "category":"Freight",
            "type":"Transportation"
        }
    ],
    "sg:phone":"+1 931 232 8784",
    "sg:postcode":"37079",
    "sg:province":"TN",
    "sg:tags":[
        "trucking"
    ],
    "wof:name":"L & P Trucking",
    "wof:placetype":"venue"
},
  "geometry": {"coordinates":[-87.72383000000001,36.522969],"type":"Point"}
}