{
  "type": "Feature",
  "properties": {
    "addr:full":"29 Lincoln Rd Fayetteville TN 37334",
    "addr:housenumber":"29",
    "addr:postcode":"37334",
    "addr:street":"Lincoln Rd",
    "iso:country":"US",
    "sg:address":"29 Lincoln Rd",
    "sg:city":"Fayetteville",
    "sg:classifiers":[
        {
            "category":"Manufacturing",
            "subcategory":"Tools & Machinery",
            "type":"Manufacturing & Wholesale Goods"
        }
    ],
    "sg:phone":"+1 931 433 5845",
    "sg:postcode":"37334",
    "sg:province":"TN",
    "sg:tags":[
        "industrial",
        "mfg"
    ],
    "wof:name":"Wright Machine Shop",
    "wof:placetype":"venue"
},
  "geometry": {"coordinates":[-86.571331,35.021719],"type":"Point"}
}