{
  "type": "Feature",
  "properties": {
    "iso:country":"US",
    "sg:address":"6618 Kingston Pike",
    "sg:city":"Knoxville",
    "sg:classifiers":[
        {
            "category":"Utilities",
            "subcategory":"Mobile Phone",
            "type":"Services"
        }
    ],
    "sg:phone":"+1 865 588 4049",
    "sg:postcode":"37919",
    "sg:province":"TN",
    "sg:tags":[
        "telephone",
        "cellular"
    ],
    "wof:name":"Cellular Express",
    "wof:placetype":"venue"
},
  "geometry": {"coordinates":[-84.009193,35.931847],"type":"Point"}
}