{
  "type": "Feature",
  "properties": {
    "iso:country":"US",
    "sg:address":"405 W Gaines St",
    "sg:city":"Lawrenceburg",
    "sg:classifiers":[
        {
            "category":"Food & Beverages",
            "subcategory":"Bakery",
            "type":"Retail Goods"
        }
    ],
    "sg:phone":"+1 931 766 4000",
    "sg:postcode":"38464",
    "sg:province":"TN",
    "sg:tags":[
        "doughnut"
    ],
    "wof:name":"Dreamin Donuts",
    "wof:placetype":"venue"
},
  "geometry": {"coordinates":[-87.340326,35.243612],"type":"Point"}
}