{
  "type": "Feature",
  "properties": {
    "iso:country":"US",
    "sg:address":"414 Oakcrest Rd NE",
    "sg:city":"Knoxville",
    "sg:classifiers":[
        {
            "category":"Professional",
            "subcategory":"Computer Services",
            "type":"Services"
        }
    ],
    "sg:phone":"+1 865 688 4890",
    "sg:postcode":"37912",
    "sg:province":"TN",
    "sg:tags":[
        "related"
    ],
    "wof:name":"Myers Computing",
    "wof:placetype":"venue"
},
  "geometry": {"coordinates":[-83.974515,36.01993],"type":"Point"}
}