{
  "type": "Feature",
  "properties": {
    "addr:full":"1833 King College Rd Bristol TN 37620",
    "addr:housenumber":"1833",
    "addr:postcode":"37620",
    "addr:street":"King College Rd",
    "iso:country":"US",
    "sg:address":"1833 King College Rd",
    "sg:city":"Bristol",
    "sg:classifiers":[
        {
            "category":"Building & Trades",
            "subcategory":"Plumbing",
            "type":"Services"
        }
    ],
    "sg:phone":"+1 423 878 6022",
    "sg:postcode":"37620",
    "sg:province":"TN",
    "sg:tags":[
        "repair",
        "contractor"
    ],
    "wof:name":"Associate Plumbing",
    "wof:placetype":"venue"
},
  "geometry": {"coordinates":[-82.142252,36.585048],"type":"Point"}
}