{
  "type": "Feature",
  "properties": {
    "iso:country":"US",
    "sg:address":"122 Stephanie Dr",
    "sg:city":"Clarksville",
    "sg:classifiers":[
        {
            "category":"Communications",
            "subcategory":"Radio Station",
            "type":"Services"
        }
    ],
    "sg:phone":"+1 931 206 8648",
    "sg:postcode":"37042",
    "sg:province":"TN",
    "sg:tags":[
        "religious"
    ],
    "wof:name":"William Peer",
    "wof:placetype":"venue"
},
  "geometry": {"coordinates":[-87.40046100000001,36.553829],"type":"Point"}
}