{
  "type": "Feature",
  "properties": {
    "iso:country":"US",
    "sg:address":"2203 Stones River Rd",
    "sg:city":"Woodbury",
    "sg:classifiers":[
        {
            "category":"Wholesale",
            "subcategory":"Jewelry",
            "type":"Manufacturing & Wholesale Goods"
        }
    ],
    "sg:phone":"+1 615 563 5449",
    "sg:postcode":"37190",
    "sg:province":"TN",
    "sg:tags":[
        "stone"
    ],
    "wof:name":"Bourgeois Assoc",
    "wof:placetype":"venue"
},
  "geometry": {"coordinates":[-85.996865,35.831804],"type":"Point"}
}