{
  "type": "Feature",
  "properties": {
    "iso:country":"US",
    "sg:address":"5 W Norris Rd",
    "sg:city":"Norris",
    "sg:classifiers":[
        {
            "category":"Education",
            "subcategory":"School",
            "type":"Public Place"
        }
    ],
    "sg:phone":"+1 865 494 7171",
    "sg:postcode":"37828",
    "sg:province":"TN",
    "wof:name":"Norris Middle School",
    "wof:placetype":"venue"
},
  "geometry": {"coordinates":[-84.07211599999999,36.193627],"type":"Point"}
}