{
  "type": "Feature",
  "properties": {
    "iso:country":"US",
    "sg:address":"114 Donnelly St",
    "sg:city":"Mountain City",
    "sg:classifiers":[
        {
            "category":"Government",
            "subcategory":"Fire Station",
            "type":"Public Place"
        }
    ],
    "sg:phone":"+1 423 727 6754",
    "sg:postcode":"37683",
    "sg:province":"TN",
    "sg:tags":[
        "department"
    ],
    "wof:name":"Mountain City Fire Dept",
    "wof:placetype":"venue"
},
  "geometry": {"coordinates":[-81.80542199999999,36.473759],"type":"Point"}
}