{
  "type": "Feature",
  "properties": {
    "addr:full":"1822 Maggie St Maryville TN 37803",
    "addr:housenumber":"1822",
    "addr:postcode":"37803",
    "addr:street":"Maggie St",
    "iso:country":"US",
    "sg:address":"1822 Maggie St",
    "sg:city":"Maryville",
    "sg:classifiers":[
        {
            "category":"Personal",
            "subcategory":"Beauty Salon",
            "type":"Services"
        }
    ],
    "sg:phone":"+1 865 681 6146",
    "sg:postcode":"37803",
    "sg:province":"TN",
    "sg:tags":[
        "shop",
        "trade",
        "contractor"
    ],
    "wof:name":"Solar Tamers",
    "wof:placetype":"venue"
},
  "geometry": {"coordinates":[-83.97457199999999,35.725211],"type":"Point"}
}