{
  "type": "Feature",
  "properties": {
    "iso:country":"US",
    "sg:address":"211 S Main St",
    "sg:city":"Covington",
    "sg:classifiers":[
        {
            "category":"Organizations",
            "subcategory":"Religious Organization",
            "type":"Services"
        }
    ],
    "sg:phone":"+1 901 476 2489",
    "sg:postcode":"38019",
    "sg:province":"TN",
    "sg:tags":[
        "church"
    ],
    "sg:website":"www.fbccovington.org",
    "wof:name":"First Baptist Church",
    "wof:placetype":"venue"
},
  "geometry": {"coordinates":[-89.646368,35.56368],"type":"Point"}
}