{
  "type": "Feature",
  "properties": {
    "iso:country":"US",
    "sg:address":"908 Rutherford Pointe Cir",
    "sg:city":"La Vergne",
    "sg:classifiers":[
        {
            "category":"Building & Trades",
            "subcategory":"Construction",
            "type":"Services"
        }
    ],
    "sg:phone":"+1 615 573 3095",
    "sg:postcode":"37086",
    "sg:province":"TN",
    "sg:tags":[
        "removal",
        "wallpaper",
        "contractor"
    ],
    "wof:name":"Randy Blankenship Paint & Wall",
    "wof:placetype":"venue"
},
  "geometry": {"coordinates":[-86.56763100000001,36.020279],"type":"Point"}
}