{
  "type": "Feature",
  "properties": {
    "iso:country":"US",
    "sg:address":"5900 E Holmes Rd",
    "sg:city":"Memphis",
    "sg:classifiers":[
        {
            "category":"Utilities",
            "subcategory":"Telephone",
            "type":"Services"
        }
    ],
    "sg:phone":"+1 901 255 5280",
    "sg:postcode":"38141",
    "sg:province":"TN",
    "sg:tags":[
        "communication"
    ],
    "wof:name":"Elx Distribution",
    "wof:placetype":"venue"
},
  "geometry": {"coordinates":[-89.868036,35.005905],"type":"Point"}
}