{
  "type": "Feature",
  "properties": {
    "addr:full":"138 Vann Dr Jackson TN 38305",
    "addr:housenumber":"138",
    "addr:postcode":"38305",
    "addr:street":"Vann Dr",
    "iso:country":"US",
    "sg:address":"138 Vann Dr",
    "sg:city":"Jackson",
    "sg:classifiers":[
        {
            "category":"Wholesale",
            "subcategory":"Office Equipment",
            "type":"Manufacturing & Wholesale Goods"
        },
        {
            "category":"Shopping",
            "type":"Retail Goods"
        }
    ],
    "sg:phone":"+1 731 660 3301",
    "sg:postcode":"38305",
    "sg:province":"TN",
    "sg:tags":[
        "machine",
        "merchandise",
        "duplicating",
        "copying",
        "furniture"
    ],
    "sg:website":"www.deximaging.com",
    "wof:name":"Dex Imaging",
    "wof:placetype":"venue"
},
  "geometry": {"coordinates":[-88.83568,35.670677],"type":"Point"}
}