{
  "type": "Feature",
  "properties": {
    "addr:full":"147 Lakeview Cir Clinton TN 37716",
    "addr:housenumber":"147",
    "addr:postcode":"37716",
    "addr:street":"Lakeview Cir",
    "iso:country":"US",
    "sg:address":"147 Lakeview Cir",
    "sg:city":"Clinton",
    "sg:classifiers":[
        {
            "category":"Building & Trades",
            "subcategory":"Construction",
            "type":"Services"
        }
    ],
    "sg:phone":"+1 865 481 3861",
    "sg:postcode":"37716",
    "sg:province":"TN",
    "sg:tags":[
        "painter"
    ],
    "wof:name":"Dwight Marlow Decorating Contr",
    "wof:placetype":"venue"
},
  "geometry": {"coordinates":[-84.161362,36.022881],"type":"Point"}
}