{
  "type": "Feature",
  "properties": {
    "iso:country":"US",
    "sg:address":"2115 White Rd",
    "sg:city":"Waynesboro",
    "sg:classifiers":[
        {
            "category":"Organizations",
            "subcategory":"Religious Organization",
            "type":"Services"
        }
    ],
    "sg:phone":"+1 931 722 3453",
    "sg:postcode":"38485",
    "sg:province":"TN",
    "sg:tags":[
        "church"
    ],
    "wof:name":"Highland Church Of Christ",
    "wof:placetype":"venue"
},
  "geometry": {"coordinates":[-87.792278,35.425051],"type":"Point"}
}