{
  "type": "Feature",
  "properties": {
    "addr:full":"611 Haggard Dr Sevierville TN 37876",
    "addr:housenumber":"611",
    "addr:postcode":"37876",
    "addr:street":"Haggard Dr",
    "iso:country":"US",
    "sg:address":"611 Haggard Dr",
    "sg:city":"Sevierville",
    "sg:classifiers":[
        {
            "category":"Building & Trades",
            "subcategory":"Construction",
            "type":"Services"
        }
    ],
    "sg:phone":"+1 865 429 4356",
    "sg:postcode":"37876",
    "sg:province":"TN",
    "sg:tags":[
        "contractor"
    ],
    "wof:name":"Eds Drywall",
    "wof:placetype":"venue"
},
  "geometry": {"coordinates":[-83.55937299999999,35.918636],"type":"Point"}
}