{
  "type": "Feature",
  "properties": {
    "iso:country":"US",
    "sg:address":"10 Trenton Hwy",
    "sg:city":"Dyer",
    "sg:classifiers":[
        {
            "category":"Building & Trades",
            "subcategory":"Construction",
            "type":"Services"
        }
    ],
    "sg:phone":"+1 731 855 1441",
    "sg:postcode":"38330",
    "sg:province":"TN",
    "sg:tags":[
        "utility",
        "contractor"
    ],
    "wof:name":"Gibson County Utility District",
    "wof:placetype":"venue"
},
  "geometry": {"coordinates":[-88.974033,36.039731],"type":"Point"}
}