{
  "type": "Feature",
  "properties": {
    "iso:country":"US",
    "sg:address":"844 Norwalk Dr",
    "sg:city":"Nashville",
    "sg:classifiers":[
        {
            "category":"Building & Trades",
            "subcategory":"Electrical",
            "type":"Services"
        }
    ],
    "sg:phone":"+1 615 885 6457",
    "sg:postcode":"37214",
    "sg:province":"TN",
    "sg:tags":[
        "electrical",
        "contractor"
    ],
    "wof:name":"KG Electrical & Wiring",
    "wof:placetype":"venue"
},
  "geometry": {"coordinates":[-86.62954000000001,36.147293],"type":"Point"}
}