{
  "type": "Feature",
  "properties": {
    "addr:full":"2123 Fernwood Dr Nashville TN 37216",
    "addr:housenumber":"2123",
    "addr:postcode":"37216",
    "addr:street":"Fernwood Dr",
    "iso:country":"US",
    "sg:address":"2123 Fernwood Dr",
    "sg:city":"Nashville",
    "sg:classifiers":[
        {
            "category":"Freight",
            "type":"Transportation"
        }
    ],
    "sg:phone":"+1 615 227 1192",
    "sg:postcode":"37216",
    "sg:province":"TN",
    "sg:tags":[
        "mover"
    ],
    "wof:name":"Pro Movers",
    "wof:placetype":"venue"
},
  "geometry": {"coordinates":[-86.712371,36.202666],"type":"Point"}
}