{
  "type": "Feature",
  "properties": {
    "iso:country":"US",
    "sg:address":"191 Tanner Rd",
    "sg:city":"Brighton",
    "sg:classifiers":[
        {
            "category":"Building & Trades",
            "subcategory":"Plumbing",
            "type":"Services"
        }
    ],
    "sg:phone":"+1 901 262 6901",
    "sg:postcode":"38011",
    "sg:province":"TN",
    "sg:tags":[
        "conditioning",
        "air",
        "system",
        "contractor"
    ],
    "wof:name":"Lippard Heating & Air",
    "wof:placetype":"venue"
},
  "geometry": {"coordinates":[-89.672641,35.40202],"type":"Point"}
}