{
  "type": "Feature",
  "properties": {
    "iso:country":"US",
    "sg:address":"730 Oakview Loop",
    "sg:city":"Bolivar",
    "sg:classifiers":[
        {
            "category":"Banks & Credit Unions",
            "subcategory":"Financial Services",
            "type":"Services"
        }
    ],
    "sg:phone":"+1 731 658 2974",
    "sg:postcode":"38008",
    "sg:province":"TN",
    "sg:tags":[
        "investment",
        "closed"
    ],
    "wof:name":"Ray Investments",
    "wof:placetype":"venue"
},
  "geometry": {"coordinates":[-89.002881,35.226731],"type":"Point"}
}