{
  "type": "Feature",
  "properties": {
    "iso:country":"US",
    "sg:address":"915 Center Point Rd",
    "sg:city":"Mason",
    "sg:classifiers":[
        {
            "category":"Health Services",
            "subcategory":"Health Practitioner",
            "type":"Services"
        }
    ],
    "sg:phone":"+1 901 867 7125",
    "sg:postcode":"38049",
    "sg:province":"TN",
    "sg:tags":[
        "midwife"
    ],
    "wof:name":"Chosen Births Midwifery",
    "wof:placetype":"venue"
},
  "geometry": {"coordinates":[-89.602862,35.329675],"type":"Point"}
}