{
  "type": "Feature",
  "properties": {
    "iso:country":"US",
    "sg:address":"633 Laurels Rd",
    "sg:city":"Johnson City",
    "sg:classifiers":[
        {
            "category":"Shopping",
            "subcategory":"Clothing, Apparel, & Fashions",
            "type":"Retail Goods"
        }
    ],
    "sg:phone":"+1 423 926 9518",
    "sg:postcode":"37601",
    "sg:province":"TN",
    "sg:tags":[
        "wear"
    ],
    "wof:name":"Earls Mens Shop",
    "wof:placetype":"venue"
},
  "geometry": {"coordinates":[-82.284678,36.260992],"type":"Point"}
}