{
  "type": "Feature",
  "properties": {
    "addr:full":"4028 Lebanon Pike Hermitage TN 37076",
    "addr:housenumber":"4028",
    "addr:postcode":"37076",
    "addr:street":"Lebanon Pike",
    "iso:country":"US",
    "sg:address":"4028 Lebanon Pike",
    "sg:city":"Hermitage",
    "sg:classifiers":[
        {
            "category":"Wholesale",
            "subcategory":"Jewelry",
            "type":"Manufacturing & Wholesale Goods"
        }
    ],
    "sg:phone":"+1 615 874 0900",
    "sg:postcode":"37076",
    "sg:province":"TN",
    "sg:tags":[
        "stone"
    ],
    "wof:name":"Wholesale Jewelers",
    "wof:placetype":"venue"
},
  "geometry": {"coordinates":[-86.621714,36.195718],"type":"Point"}
}