{
  "type": "Feature",
  "properties": {
    "addr:full":"3909 Saint Elmo Ave Chattanooga TN 37409",
    "addr:housenumber":"3909",
    "addr:postcode":"37409",
    "addr:street":"Saint Elmo Ave",
    "iso:country":"US",
    "sg:address":"3909 Saint Elmo Ave",
    "sg:city":"Chattanooga",
    "sg:classifiers":[
        {
            "category":"Retail",
            "subcategory":"Repair Shop",
            "type":"Services"
        }
    ],
    "sg:phone":"+1 423 821 2703",
    "sg:postcode":"37409",
    "sg:province":"TN",
    "sg:tags":[
        "clocks",
        "parts"
    ],
    "sg:website":"www.clockandwatch.com",
    "wof:name":"Clock Works & Vintage Watches",
    "wof:placetype":"venue"
},
  "geometry": {"coordinates":[-85.328439,35.009999],"type":"Point"}
}