{
  "type": "Feature",
  "properties": {
    "iso:country":"US",
    "sg:address":"198 Adams Ave",
    "sg:city":"Memphis",
    "sg:classifiers":[
        {
            "category":"Landmark",
            "subcategory":"Historic",
            "type":"Public Place"
        },
        {
            "category":"Landmark",
            "subcategory":"Tourist Information",
            "type":"Public Place"
        },
        {
            "category":"Government",
            "subcategory":"Office",
            "type":"Public Place"
        }
    ],
    "sg:phone":"+1 901 526 4464",
    "sg:postcode":"38103",
    "sg:province":"TN",
    "sg:tags":[
        "attraction",
        "township",
        "government-city",
        "historical",
        "village"
    ],
    "wof:name":"Magevney House The",
    "wof:placetype":"venue"
},
  "geometry": {"coordinates":[-90.048478,35.147356],"type":"Point"}
}