{
  "type": "Feature",
  "properties": {
    "addr:full":"114 N Cliff Ln Chattanooga TN 37415",
    "addr:housenumber":"114",
    "addr:postcode":"37415",
    "addr:street":"N Cliff Ln",
    "iso:country":"US",
    "sg:address":"114 N Cliff Ln",
    "sg:city":"Chattanooga",
    "sg:classifiers":[
        {
            "category":"Real Estate",
            "subcategory":"Real Estate Agent",
            "type":"Services"
        }
    ],
    "sg:phone":"+1 423 756 7635",
    "sg:postcode":"37415",
    "sg:province":"TN",
    "wof:name":"Business Broker Associates",
    "wof:placetype":"venue"
},
  "geometry": {"coordinates":[-85.27288799999999,35.129289],"type":"Point"}
}