{
  "type": "Feature",
  "properties": {
    "addr:full":"74 Bonwood Dr Jackson TN 38301",
    "addr:housenumber":"74",
    "addr:postcode":"38301",
    "addr:street":"Bonwood Dr",
    "iso:country":"US",
    "sg:address":"74 Bonwood Dr",
    "sg:city":"Jackson",
    "sg:classifiers":[
        {
            "category":"Manufacturing",
            "subcategory":"Rubber & Plastics",
            "type":"Manufacturing & Wholesale Goods"
        }
    ],
    "sg:phone":"+1 731 423 0810",
    "sg:postcode":"38301",
    "sg:province":"TN",
    "sg:website":"www.atlantisplastics.com",
    "wof:name":"Atlantis Plastics Inc",
    "wof:placetype":"venue"
},
  "geometry": {"coordinates":[-88.820195,35.554111],"type":"Point"}
}