{
  "type": "Feature",
  "properties": {
    "addr:full":"8808 Fuller Rd Chattanooga TN 37421",
    "addr:housenumber":"8808",
    "addr:postcode":"37421",
    "addr:street":"Fuller Rd",
    "iso:country":"US",
    "sg:address":"8808 Fuller Rd",
    "sg:city":"Chattanooga",
    "sg:classifiers":[
        {
            "category":"Insurance",
            "subcategory":"Insurance Agent",
            "type":"Services"
        }
    ],
    "sg:phone":"+1 423 855 0758",
    "sg:postcode":"37421",
    "sg:province":"TN",
    "wof:name":"C G Mc Cullough & ASSOC LLC",
    "wof:placetype":"venue"
},
  "geometry": {"coordinates":[-85.131154,35.000687],"type":"Point"}
}