{
  "type": "Feature",
  "properties": {
    "iso:country":"US",
    "sg:address":"658 Stratford Rd",
    "sg:city":"Memphis",
    "sg:classifiers":[
        {
            "category":"Food & Beverages",
            "subcategory":"Groceries & Convenience Stores",
            "type":"Retail Goods"
        }
    ],
    "sg:phone":"+1 901 682 5215",
    "sg:postcode":"38122",
    "sg:province":"TN",
    "wof:name":"Save Time Drive-In Grocery",
    "wof:placetype":"venue"
},
  "geometry": {"coordinates":[-89.906043,35.149883],"type":"Point"}
}