{
  "type": "Feature",
  "properties": {
    "addr:full":"485 Dry Creek Rd Jonesborough TN 37659",
    "addr:housenumber":"485",
    "addr:postcode":"37659",
    "addr:street":"Dry Creek Rd",
    "iso:country":"US",
    "sg:address":"485 Dry Creek Rd",
    "sg:city":"Jonesborough",
    "sg:classifiers":[
        {
            "category":"Manufacturing",
            "subcategory":"Lumber",
            "type":"Manufacturing & Wholesale Goods"
        }
    ],
    "sg:phone":"+1 423 753 4011",
    "sg:postcode":"37659",
    "sg:province":"TN",
    "sg:tags":[
        "government"
    ],
    "sg:website":"www.state.tn.us",
    "wof:name":"Forestry Division",
    "wof:placetype":"venue"
},
  "geometry": {"coordinates":[-82.427036,36.204485],"type":"Point"}
}