{
  "type": "Feature",
  "properties": {
    "addr:full":"129 City St Huntingdon TN 38320",
    "addr:housenumber":"129",
    "addr:postcode":"38320",
    "addr:street":"City St",
    "iso:country":"US",
    "sg:address":"129 City St",
    "sg:city":"Huntingdon",
    "sg:classifiers":[
        {
            "category":"Personal",
            "subcategory":"Beauty Salon",
            "type":"Services"
        }
    ],
    "sg:phone":"+1 731 986 4030",
    "sg:postcode":"38320",
    "sg:province":"TN",
    "sg:tags":[
        "shop"
    ],
    "wof:name":"Perfect Hair and Nails",
    "wof:placetype":"venue"
},
  "geometry": {"coordinates":[-88.084812,36.061732],"type":"Point"}
}