{
  "type": "Feature",
  "properties": {
    "addr:full":"107 Heady Dr Nashville TN 37205",
    "addr:housenumber":"107",
    "addr:postcode":"37205",
    "addr:street":"Heady Dr",
    "iso:country":"US",
    "sg:address":"107 Heady Dr",
    "sg:city":"Nashville",
    "sg:classifiers":[
        {
            "category":"Restaurant",
            "type":"Food & Drink"
        }
    ],
    "sg:phone":"+1 615 352 0296",
    "sg:postcode":"37205",
    "sg:province":"TN",
    "sg:tags":[
        "caterer"
    ],
    "wof:name":"Something Special",
    "wof:placetype":"venue"
},
  "geometry": {"coordinates":[-86.87048799999999,36.098178],"type":"Point"}
}