{
  "type": "Feature",
  "properties": {
    "addr:full":"2100 Hamilton Place Blvd Chattanooga TN 37421",
    "addr:housenumber":"2100",
    "addr:postcode":"37421",
    "addr:street":"Hamilton Place Blvd",
    "iso:country":"US",
    "sg:address":"2100 Hamilton Place Blvd",
    "sg:city":"Chattanooga",
    "sg:classifiers":[
        {
            "category":"Manufacturing",
            "subcategory":"Tools & Machinery",
            "type":"Manufacturing & Wholesale Goods"
        }
    ],
    "sg:phone":"+1 423 892 8510",
    "sg:postcode":"37421",
    "sg:province":"TN",
    "sg:tags":[
        "surgical",
        "mfg"
    ],
    "sg:website":"www.miracle-ear.com",
    "wof:name":"Miracle-Ear",
    "wof:placetype":"venue"
},
  "geometry": {"coordinates":[-85.161187,35.036544],"type":"Point"}
}