{
  "type": "Feature",
  "properties": {
    "iso:country":"US",
    "sg:address":"576 Country Club Ln",
    "sg:city":"Memphis",
    "sg:classifiers":[
        {
            "category":"Professional",
            "subcategory":"Business Services",
            "type":"Services"
        }
    ],
    "sg:phone":"+1 901 452 4315",
    "sg:postcode":"38111",
    "sg:province":"TN",
    "sg:tags":[
        "interior",
        "designer"
    ],
    "wof:name":"Lary-Vanlandingham",
    "wof:placetype":"venue"
},
  "geometry": {"coordinates":[-89.957483,35.115967],"type":"Point"}
}