{
  "type": "Feature",
  "properties": {
    "iso:country":"US",
    "sg:address":"601 Fugate Rd",
    "sg:city":"Del Rio",
    "sg:classifiers":[
        {
            "category":"Real Estate",
            "subcategory":"Real Estate Agent",
            "type":"Services"
        }
    ],
    "sg:phone":"+1 423 623 8899",
    "sg:postcode":"37727",
    "sg:province":"TN",
    "wof:name":"Keys Island Realty",
    "wof:placetype":"venue"
},
  "geometry": {"coordinates":[-82.993472,35.916996],"type":"Point"}
}