{
  "type": "Feature",
  "properties": {
    "iso:country":"US",
    "sg:address":"2706 W Linden Ave",
    "sg:city":"Nashville",
    "sg:classifiers":[
        {
            "category":"Manufacturing",
            "subcategory":"Metals",
            "type":"Manufacturing & Wholesale Goods"
        }
    ],
    "sg:phone":"+1 615 383 8980",
    "sg:postcode":"37212",
    "sg:province":"TN",
    "sg:tags":[
        "brass",
        "foundry",
        "bronze"
    ],
    "wof:name":"House Of Beauregard",
    "wof:placetype":"venue"
},
  "geometry": {"coordinates":[-86.810512,36.128322],"type":"Point"}
}