{
  "type": "Feature",
  "properties": {
    "iso:country":"US",
    "sg:address":"7065 Moores Ln",
    "sg:city":"Brentwood",
    "sg:classifiers":[
        {
            "category":"Professional",
            "subcategory":"Advertising",
            "type":"Services"
        },
        {
            "category":"Wholesale",
            "subcategory":"Non-durable Goods",
            "type":"Manufacturing & Wholesale Goods"
        }
    ],
    "sg:phone":"+1 615 309 8089",
    "sg:postcode":"37027",
    "sg:province":"TN",
    "sg:tags":[
        "product",
        "promotional"
    ],
    "wof:name":"Tom A Promotions",
    "wof:placetype":"venue"
},
  "geometry": {"coordinates":[-86.821483,35.970467],"type":"Point"}
}