{
  "type": "Feature",
  "properties": {
    "iso:country":"US",
    "sg:address":"4121 Pepperwood Dr",
    "sg:city":"Antioch",
    "sg:classifiers":[
        {
            "category":"Building & Trades",
            "subcategory":"Cleaning & Sanitation",
            "type":"Services"
        }
    ],
    "sg:phone":"+1 615 641 9357",
    "sg:postcode":"37013",
    "sg:province":"TN",
    "sg:tags":[
        "janitor"
    ],
    "wof:name":"Majoh Enterprises",
    "wof:placetype":"venue"
},
  "geometry": {"coordinates":[-86.580691,36.040451],"type":"Point"}
}