{
  "type": "Feature",
  "properties": {
    "iso:country":"US",
    "sg:address":"3234 Wears Valley Rd",
    "sg:city":"Sevierville",
    "sg:classifiers":[
        {
            "category":"Shopping",
            "subcategory":"Used Merchandise",
            "type":"Retail Goods"
        }
    ],
    "sg:phone":"+1 865 453 5294",
    "sg:postcode":"37862",
    "sg:province":"TN",
    "sg:tags":[
        "antique"
    ],
    "wof:name":"Wears Valley Antique & Craft",
    "wof:placetype":"venue"
},
  "geometry": {"coordinates":[-83.637462,35.725574],"type":"Point"}
}