{
  "type": "Feature",
  "properties": {
    "iso:country":"US",
    "sg:address":"21058 River Canyon Rd",
    "sg:city":"Chattanooga",
    "sg:classifiers":[
        {
            "category":"Real Estate",
            "subcategory":"Real Estate Agent",
            "type":"Services"
        }
    ],
    "sg:phone":"+1 423 886 6130",
    "sg:postcode":"37405",
    "sg:province":"TN",
    "wof:name":"Vacation Rentals",
    "wof:placetype":"venue"
},
  "geometry": {"coordinates":[-85.390959,35.124358],"type":"Point"}
}