{
  "type": "Feature",
  "properties": {
    "iso:country":"US",
    "sg:address":"2117 Gallatin Pike N",
    "sg:city":"Madison",
    "sg:classifiers":[
        {
            "category":"Shopping",
            "subcategory":"Stationery & Office Supplies",
            "type":"Retail Goods"
        }
    ],
    "sg:phone":"+1 615 859 0038",
    "sg:postcode":"37115",
    "sg:province":"TN",
    "wof:name":"Office Max",
    "wof:placetype":"venue"
},
  "geometry": {"coordinates":[-86.69230899999999,36.302485],"type":"Point"}
}