{
  "type": "Feature",
  "properties": {
    "addr:full":"1235 Riverside Blvd Memphis TN 38106",
    "addr:housenumber":"1235",
    "addr:postcode":"38106",
    "addr:street":"Riverside Blvd",
    "iso:country":"US",
    "sg:address":"1235 Riverside Blvd",
    "sg:city":"Memphis",
    "sg:classifiers":[
        {
            "category":"Building & Trades",
            "subcategory":"Construction",
            "type":"Services"
        }
    ],
    "sg:phone":"+1 901 566 9097",
    "sg:postcode":"38106",
    "sg:province":"TN",
    "sg:tags":[
        "restoration",
        "preservation"
    ],
    "wof:name":"AAA Restoration Svc Inc",
    "wof:placetype":"venue"
},
  "geometry": {"coordinates":[-90.07422,35.113479],"type":"Point"}
}