{
  "type": "Feature",
  "properties": {
    "iso:country":"US",
    "sg:address":"4770 Navy Rd",
    "sg:city":"Millington",
    "sg:classifiers":[
        {
            "category":"Utilities",
            "subcategory":"Telephone",
            "type":"Services"
        }
    ],
    "sg:phone":"+1 901 829 4262",
    "sg:postcode":"38053",
    "sg:province":"TN",
    "sg:tags":[
        "company"
    ],
    "wof:name":"Millington Telephone Co Repair",
    "wof:placetype":"venue"
},
  "geometry": {"coordinates":[-89.903896,35.341443],"type":"Point"}
}