{
  "type": "Feature",
  "properties": {
    "iso:country":"US",
    "sg:address":"2134 N Locust Ave",
    "sg:city":"Lawrenceburg",
    "sg:classifiers":[
        {
            "category":"Shopping",
            "type":"Retail Goods"
        }
    ],
    "sg:phone":"+1 931 766 0484",
    "sg:postcode":"38464",
    "sg:province":"TN",
    "sg:tags":[
        "merchandise"
    ],
    "wof:name":"Daly Communications",
    "wof:placetype":"venue"
},
  "geometry": {"coordinates":[-87.320792,35.269318],"type":"Point"}
}