{
  "type": "Feature",
  "properties": {
    "addr:full":"101 Valley Ct Oak Ridge TN 37830",
    "addr:housenumber":"101",
    "addr:postcode":"37830",
    "addr:street":"Valley Ct",
    "iso:country":"US",
    "sg:address":"101 Valley Ct",
    "sg:city":"Oak Ridge",
    "sg:classifiers":[
        {
            "category":"Professional",
            "type":"Services"
        },
        {
            "category":"Home & Garden",
            "subcategory":"Furniture",
            "type":"Retail Goods"
        }
    ],
    "sg:phone":"+1 865 481 8275",
    "sg:postcode":"37830",
    "sg:province":"TN",
    "sg:tags":[
        "equipment",
        "kitchen",
        "cabinet"
    ],
    "wof:name":"Built Right Surfaces",
    "wof:placetype":"venue"
},
  "geometry": {"coordinates":[-84.232631,35.997779],"type":"Point"}
}