{
  "type": "Feature",
  "properties": {
    "iso:country":"US",
    "sg:address":"102 Williams Ct",
    "sg:city":"Tullahoma",
    "sg:classifiers":[
        {
            "category":"Health Services",
            "subcategory":"Clinic",
            "type":"Services"
        }
    ],
    "sg:phone":"+1 931 455 4442",
    "sg:postcode":"37388",
    "sg:province":"TN",
    "sg:tags":[
        "home",
        "care"
    ],
    "wof:name":"Respiratory At Home Corp",
    "wof:placetype":"venue"
},
  "geometry": {"coordinates":[-86.229544,35.344653],"type":"Point"}
}