{
  "type": "Feature",
  "properties": {
    "iso:country":"US",
    "sg:address":"20 Airport Rd",
    "sg:city":"Lexington",
    "sg:classifiers":[
        {
            "category":"Building & Trades",
            "subcategory":"Construction",
            "type":"Services"
        }
    ],
    "sg:phone":"+1 731 968 8002",
    "sg:postcode":"38351",
    "sg:province":"TN",
    "sg:tags":[
        "carpentry",
        "contractor"
    ],
    "wof:name":"FIC Woodworks",
    "wof:placetype":"venue"
},
  "geometry": {"coordinates":[-88.38252900000001,35.654317],"type":"Point"}
}