{
  "type": "Feature",
  "properties": {
    "iso:country":"US",
    "sg:address":"7003 Chadwick Dr",
    "sg:city":"Brentwood",
    "sg:classifiers":[
        {
            "category":"Wholesale",
            "subcategory":"Electrical",
            "type":"Manufacturing & Wholesale Goods"
        }
    ],
    "sg:phone":"+1 615 661 0083",
    "sg:postcode":"37027",
    "sg:province":"TN",
    "sg:tags":[
        "generator"
    ],
    "wof:name":"Integrated Power Systems Inc",
    "wof:placetype":"venue"
},
  "geometry": {"coordinates":[-86.787055,36.030872],"type":"Point"}
}