{
  "type": "Feature",
  "properties": {
    "iso:country":"US",
    "sg:address":"711 Main St",
    "sg:city":"Nashville",
    "sg:classifiers":[
        {
            "category":"Building & Trades",
            "subcategory":"Construction",
            "type":"Services"
        }
    ],
    "sg:phone":"+1 615 254 6512",
    "sg:postcode":"37206",
    "sg:province":"TN",
    "sg:tags":[
        "general",
        "industrial",
        "commercial",
        "contractor"
    ],
    "sg:website":"www.hardcastleconstruction.com",
    "wof:name":"Hardcastle Construction Co",
    "wof:placetype":"venue"
},
  "geometry": {"coordinates":[-86.759449,36.175182],"type":"Point"}
}