{
  "type": "Feature",
  "properties": {
    "addr:full":"100 Walters Ct Nashville TN 37218",
    "addr:housenumber":"100",
    "addr:postcode":"37218",
    "addr:street":"Walters Ct",
    "iso:country":"US",
    "sg:address":"100 Walters Ct",
    "sg:city":"Nashville",
    "sg:classifiers":[
        {
            "category":"Professional",
            "type":"Services"
        }
    ],
    "sg:phone":"+1 615 346 9207",
    "sg:postcode":"37218",
    "sg:province":"TN",
    "wof:name":"Nationwide Loss Mitigation",
    "wof:placetype":"venue"
},
  "geometry": {"coordinates":[-86.83485899999999,36.210678],"type":"Point"}
}