{
  "type": "Feature",
  "properties": {
    "iso:country":"US",
    "sg:address":"309 S Lindell St",
    "sg:city":"Martin",
    "sg:classifiers":[
        {
            "category":"Shopping",
            "type":"Retail Goods"
        }
    ],
    "sg:phone":"+1 731 588 1295",
    "sg:postcode":"38237",
    "sg:province":"TN",
    "sg:tags":[
        "telephone",
        "cellular"
    ],
    "wof:name":"Cellular Communications-Martin",
    "wof:placetype":"venue"
},
  "geometry": {"coordinates":[-88.850531,36.343376],"type":"Point"}
}