{
  "type": "Feature",
  "properties": {
    "iso:country":"US",
    "sg:address":"8152 W Andrew Johnson Hwy",
    "sg:city":"Mosheim",
    "sg:classifiers":[
        {
            "category":"Banks & Credit Unions",
            "subcategory":"Bank",
            "type":"Services"
        }
    ],
    "sg:phone":"+1 423 798 2261",
    "sg:postcode":"37818",
    "sg:province":"TN",
    "wof:name":"First Tennessee Bank",
    "wof:placetype":"venue"
},
  "geometry": {"coordinates":[-82.93910200000001,36.186425],"type":"Point"}
}