{
  "type": "Feature",
  "properties": {
    "iso:country":"US",
    "sg:address":"6001 Chapman Hwy",
    "sg:city":"Knoxville",
    "sg:classifiers":[
        {
            "category":"Retail",
            "subcategory":"Auto Repair",
            "type":"Services"
        }
    ],
    "sg:phone":"+1 865 573 1650",
    "sg:postcode":"37920",
    "sg:province":"TN",
    "sg:tags":[
        "repairing",
        "automobile"
    ],
    "wof:name":"Oliver's Auto Ctr",
    "wof:placetype":"venue"
},
  "geometry": {"coordinates":[-83.87656,35.921251],"type":"Point"}
}