{
  "type": "Feature",
  "properties": {
    "iso:country":"US",
    "sg:address":"4230 Harding Pl",
    "sg:city":"Nashville",
    "sg:classifiers":[
        {
            "category":"Shopping",
            "subcategory":"Pharmacy",
            "type":"Retail Goods"
        }
    ],
    "sg:phone":"+1 615 386 6371",
    "sg:postcode":"37205",
    "sg:province":"TN",
    "wof:name":"St Thomas Radio Pharmacy",
    "wof:placetype":"venue"
},
  "geometry": {"coordinates":[-86.848949,36.093198],"type":"Point"}
}