{
  "type": "Feature",
  "properties": {
    "iso:country":"US",
    "sg:address":"185 N Church Ave",
    "sg:city":"Dyersburg",
    "sg:classifiers":[
        {
            "category":"Professional",
            "subcategory":"Accounting & Tax Preparation",
            "type":"Services"
        }
    ],
    "sg:phone":"+1 731 285 7900",
    "sg:postcode":"38024",
    "sg:province":"TN",
    "sg:tags":[
        "accountant"
    ],
    "sg:website":"www.atacpa.net",
    "wof:name":"Alexander Thompson Arnold Pllc",
    "wof:placetype":"venue"
},
  "geometry": {"coordinates":[-89.387939,36.033145],"type":"Point"}
}