{
  "type": "Feature",
  "properties": {
    "iso:country":"US",
    "sg:address":"404 S Cedar Ave",
    "sg:city":"South Pittsburg",
    "sg:classifiers":[
        {
            "category":"Banks & Credit Unions",
            "subcategory":"Bank",
            "type":"Services"
        }
    ],
    "sg:phone":"+1 423 837 7178",
    "sg:postcode":"37380",
    "sg:province":"TN",
    "wof:name":"Citizens State Bank",
    "wof:placetype":"venue"
},
  "geometry": {"coordinates":[-85.705916,35.010776],"type":"Point"}
}