{
  "type": "Feature",
  "properties": {
    "addr:full":"893 S 3rd St Memphis TN 38106",
    "addr:housenumber":"893",
    "addr:postcode":"38106",
    "addr:street":"S 3Rd St",
    "iso:country":"US",
    "sg:address":"893 S 3rd St",
    "sg:city":"Memphis",
    "sg:classifiers":[
        {
            "category":"Utilities",
            "subcategory":"Recycling",
            "type":"Services"
        }
    ],
    "sg:phone":"+1 901 942 3100",
    "sg:postcode":"38106",
    "sg:province":"TN",
    "wof:name":"Thecyberyard Com Inc",
    "wof:placetype":"venue"
},
  "geometry": {"coordinates":[-90.054998,35.12302],"type":"Point"}
}