{
  "type": "Feature",
  "properties": {
    "addr:full":"8001 State Hwy 104 Cordova TN 38024",
    "addr:housenumber":"8001",
    "addr:postcode":"38024",
    "addr:street":"State Hwy 104",
    "iso:country":"US",
    "sg:address":"8001 State Hwy 104",
    "sg:city":"Cordova",
    "sg:classifiers":[
        {
            "category":"Banks & Credit Unions",
            "subcategory":"Investment Brokerage",
            "type":"Services"
        }
    ],
    "sg:phone":"+1 901 759 0037",
    "sg:postcode":"38024",
    "sg:province":"TN",
    "sg:tags":[
        "consultant",
        "planning",
        "financial"
    ],
    "sg:website":"www.raymondjames.com",
    "wof:name":"Raymond James Financial Svc",
    "wof:placetype":"venue"
},
  "geometry": {"coordinates":[-89.249793,36.028082],"type":"Point"}
}