{
  "type": "Feature",
  "properties": {
    "iso:country":"US",
    "sg:address":"120 W Lincoln St",
    "sg:city":"Tullahoma",
    "sg:classifiers":[
        {
            "category":"Professional",
            "subcategory":"Computer Services",
            "type":"Services"
        }
    ],
    "sg:phone":"+1 931 454 1706",
    "sg:postcode":"37388",
    "sg:province":"TN",
    "sg:tags":[
        "prepackaged",
        "software"
    ],
    "wof:name":"Red Hat Software",
    "wof:placetype":"venue"
},
  "geometry": {"coordinates":[-86.210712,35.362088],"type":"Point"}
}