{
  "type": "Feature",
  "properties": {
    "iso:country":"US",
    "sg:address":"1611 Bagwell Ave",
    "sg:city":"Hixson",
    "sg:classifiers":[
        {
            "category":"Professional",
            "subcategory":"Employment Agencies",
            "type":"Services"
        }
    ],
    "sg:phone":"+1 423 240 3116",
    "sg:postcode":"37343",
    "sg:province":"TN",
    "sg:tags":[
        "help",
        "contractor"
    ],
    "wof:name":"Innovative Answers",
    "wof:placetype":"venue"
},
  "geometry": {"coordinates":[-85.247463,35.121496],"type":"Point"}
}