{
  "type": "Feature",
  "properties": {
    "iso:country":"US",
    "sg:address":"1429 State Hwy 100",
    "sg:city":"Centerville",
    "sg:classifiers":[
        {
            "category":"Professional",
            "subcategory":"Business Services",
            "type":"Services"
        }
    ],
    "sg:phone":"+1 931 729 4867",
    "sg:postcode":"37033",
    "sg:province":"TN",
    "wof:name":"Glenda F Teet",
    "wof:placetype":"venue"
},
  "geometry": {"coordinates":[-87.436572,35.826486],"type":"Point"}
}