{
  "type": "Feature",
  "properties": {
    "iso:country":"US",
    "sg:address":"2731 Donna Ave",
    "sg:city":"Memphis",
    "sg:classifiers":[
        {
            "category":"Real Estate",
            "subcategory":"Real Estate Agent",
            "type":"Services"
        }
    ],
    "sg:phone":"+1 901 744 0038",
    "sg:postcode":"38114",
    "sg:province":"TN",
    "wof:name":"Tracey Meadows Realtor",
    "wof:placetype":"venue"
},
  "geometry": {"coordinates":[-89.971964,35.087827],"type":"Point"}
}