{
  "type": "Feature",
  "properties": {
    "iso:country":"US",
    "sg:address":"711 K St",
    "sg:city":"Greeneville",
    "sg:classifiers":[
        {
            "category":"Health Services",
            "subcategory":"Doctor",
            "type":"Services"
        }
    ],
    "sg:phone":"+1 423 638 3571",
    "sg:postcode":"37745",
    "sg:province":"TN",
    "wof:name":"Williams James Ronnie DDS",
    "wof:placetype":"venue"
},
  "geometry": {"coordinates":[-82.817453,36.16194],"type":"Point"}
}