{
  "type": "Feature",
  "properties": {
    "iso:country":"US",
    "sg:address":"4591 Baptist Ridge Rd",
    "sg:city":"Hilham",
    "sg:classifiers":[
        {
            "category":"Restaurant",
            "type":"Food & Drink"
        }
    ],
    "sg:phone":"+1 931 243 2786",
    "sg:postcode":"38568",
    "sg:province":"TN",
    "sg:tags":[
        "eating"
    ],
    "wof:name":"Gone Country",
    "wof:placetype":"venue"
},
  "geometry": {"coordinates":[-85.523565,36.483842],"type":"Point"}
}