{
  "type": "Feature",
  "properties": {
    "iso:country":"US",
    "sg:address":"4900 Bill Jones Rd",
    "sg:city":"Apison",
    "sg:classifiers":[
        {
            "category":"Manufacturing",
            "subcategory":"Rubber & Plastics",
            "type":"Manufacturing & Wholesale Goods"
        }
    ],
    "sg:phone":"+1 423 236 5100",
    "sg:postcode":"37302",
    "sg:province":"TN",
    "sg:tags":[
        "windows",
        "mfg",
        "vinyl",
        "storm",
        "replacement"
    ],
    "wof:name":"Hullco Inc",
    "wof:placetype":"venue"
},
  "geometry": {"coordinates":[-85.024412,35.022355],"type":"Point"}
}