{
  "type": "Feature",
  "properties": {
    "addr:full":"705 Ledford Dr Nashville TN 37207",
    "addr:housenumber":"705",
    "addr:postcode":"37207",
    "addr:street":"Ledford Dr",
    "iso:country":"US",
    "sg:address":"705 Ledford Dr",
    "sg:city":"Nashville",
    "sg:classifiers":[
        {
            "category":"Professional",
            "subcategory":"Business Services",
            "type":"Services"
        }
    ],
    "sg:phone":"+1 615 227 6388",
    "sg:postcode":"37207",
    "sg:province":"TN",
    "wof:name":"Barnett 24 Hour Worldwide Bond",
    "wof:placetype":"venue"
},
  "geometry": {"coordinates":[-86.808323,36.213938],"type":"Point"}
}