{
  "type": "Feature",
  "properties": {
    "iso:country":"US",
    "sg:address":"421 S Main St",
    "sg:city":"Crossville",
    "sg:classifiers":[
        {
            "category":"Health Services",
            "subcategory":"Doctor",
            "type":"Services"
        }
    ],
    "sg:phone":"+1 931 484 7276",
    "sg:postcode":"38555",
    "sg:province":"TN",
    "sg:tags":[
        "medical"
    ],
    "wof:name":"He Is Now Part A Hosp Group",
    "wof:placetype":"venue"
},
  "geometry": {"coordinates":[-85.022848,35.94263],"type":"Point"}
}