{
  "type": "Feature",
  "properties": {
    "iso:country":"US",
    "sg:address":"820 Woodsmoke Cir",
    "sg:city":"Knoxville",
    "sg:classifiers":[
        {
            "category":"Organizations",
            "subcategory":"Community Association",
            "type":"Services"
        }
    ],
    "sg:phone":"+1 865 675 1407",
    "sg:postcode":"37934",
    "sg:province":"TN",
    "wof:name":"Woodchase II Homeowners Assn",
    "wof:placetype":"venue"
},
  "geometry": {"coordinates":[-84.195143,35.891902],"type":"Point"}
}