{
  "type": "Feature",
  "properties": {
    "iso:country":"US",
    "sg:address":"1108 Dutch Valley Dr",
    "sg:city":"Knoxville",
    "sg:classifiers":[
        {
            "category":"Building & Trades",
            "subcategory":"Construction",
            "type":"Services"
        }
    ],
    "sg:phone":"+1 865 281 9196",
    "sg:postcode":"37918",
    "sg:province":"TN",
    "sg:tags":[
        "masonry",
        "contractor"
    ],
    "wof:name":"Wasco Inc",
    "wof:placetype":"venue"
},
  "geometry": {"coordinates":[-83.950733,36.006817],"type":"Point"}
}