{
  "type": "Feature",
  "properties": {
    "iso:country":"US",
    "sg:address":"535 Mainstream Dr",
    "sg:city":"Nashville",
    "sg:classifiers":[
        {
            "category":"Utilities",
            "subcategory":"Mobile Phone",
            "type":"Services"
        },
        {
            "category":"Utilities",
            "subcategory":"Telephone",
            "type":"Services"
        }
    ],
    "sg:phone":"+1 615 627 3000",
    "sg:postcode":"37228",
    "sg:province":"TN",
    "sg:tags":[
        "wireless",
        "communications",
        "company"
    ],
    "sg:website":"www.xspedius.com",
    "wof:name":"Xspedius Communications LLC",
    "wof:placetype":"venue"
},
  "geometry": {"coordinates":[-86.810559,36.200067],"type":"Point"}
}