{
  "type": "Feature",
  "properties": {
    "addr:full":"1673 US Hwy 51 Bus Dyersburg TN 38024",
    "addr:housenumber":"1673",
    "addr:postcode":"38024",
    "addr:street":"Us Hwy 51 Bus",
    "iso:country":"US",
    "sg:address":"1673 US Hwy 51 Bus",
    "sg:city":"Dyersburg",
    "sg:classifiers":[
        {
            "category":"Restaurant",
            "type":"Food & Drink"
        }
    ],
    "sg:phone":"+1 731 286 5576",
    "sg:postcode":"38024",
    "sg:province":"TN",
    "sg:tags":[
        "eating"
    ],
    "wof:name":"Stein Low Ctrg Wdding Planners",
    "wof:placetype":"venue"
},
  "geometry": {"coordinates":[-89.37162600000001,36.04718],"type":"Point"}
}