{
  "type": "Feature",
  "properties": {
    "iso:country":"US",
    "sg:address":"3118 Kingsgate Ave",
    "sg:city":"Memphis",
    "sg:classifiers":[
        {
            "category":"Social Services",
            "subcategory":"Child Care",
            "type":"Services"
        }
    ],
    "sg:phone":"+1 901 363 1029",
    "sg:postcode":"38118",
    "sg:province":"TN",
    "sg:tags":[
        "day"
    ],
    "wof:name":"Kids Kreation Home Daycare",
    "wof:placetype":"venue"
},
  "geometry": {"coordinates":[-89.960443,35.038009],"type":"Point"}
}