{
  "type": "Feature",
  "properties": {
    "addr:full":"4831 Nolensville Pike Nashville TN 37211",
    "addr:housenumber":"4831",
    "addr:postcode":"37211",
    "addr:street":"Nolensville Pike",
    "iso:country":"US",
    "sg:address":"4831 Nolensville Pike",
    "sg:city":"Nashville",
    "sg:classifiers":[
        {
            "category":"Restaurant",
            "type":"Food & Drink"
        },
        {
            "category":"Ice Cream",
            "type":"Food & Drink"
        }
    ],
    "sg:menulink":"http://www.allmenus.com/tn/nashville/192755-dairy-queen/menu/",
    "sg:phone":"+1 615 831 5600",
    "sg:postcode":"37211",
    "sg:province":"TN",
    "sg:tags":[
        "burger",
        "american",
        "ice",
        "cream"
    ],
    "wof:name":"Dairy Queen",
    "wof:placetype":"venue"
},
  "geometry": {"coordinates":[-86.717735,36.064439],"type":"Point"}
}