{
  "type": "Feature",
  "properties": {
    "addr:full":"102 Fairways Blvd S Tullahoma TN 37388",
    "addr:housenumber":"102",
    "addr:postcode":"37388",
    "addr:street":"Fairways Blvd S",
    "iso:country":"US",
    "sg:address":"102 Fairways Blvd S",
    "sg:city":"Tullahoma",
    "sg:classifiers":[
        {
            "category":"Professional",
            "subcategory":"Employment Agencies",
            "type":"Services"
        }
    ],
    "sg:phone":"+1 931 454 0408",
    "sg:postcode":"37388",
    "sg:province":"TN",
    "sg:tags":[
        "help",
        "supply"
    ],
    "wof:name":"Upgrade Stffing Spcialists LLC",
    "wof:placetype":"venue"
},
  "geometry": {"coordinates":[-86.216911,35.387054],"type":"Point"}
}