{
  "type": "Feature",
  "properties": {
    "iso:country":"US",
    "sg:address":"2700 Getwell Rd",
    "sg:city":"Memphis",
    "sg:classifiers":[
        {
            "category":"Retail",
            "subcategory":"Storage",
            "type":"Services"
        }
    ],
    "sg:phone":"+1 901 881 8167",
    "sg:postcode":"38118",
    "sg:province":"TN",
    "sg:tags":[
        "self",
        "recreational",
        "commercial",
        "campers-storage",
        "vehicle",
        "household"
    ],
    "sg:website":"http://www.watsontaylorselfstorage.com/self_storage/Memphis_TN/watson__taylor_self_storage",
    "wof:name":"Watson & Taylor Self Storage",
    "wof:placetype":"venue"
},
  "geometry": {"coordinates":[-89.931635,35.075456],"type":"Point"}
}