{
  "type": "Feature",
  "properties": {
    "iso:country":"US",
    "sg:address":"105 Southside Park Dr",
    "sg:city":"Lebanon",
    "sg:classifiers":[
        {
            "category":"Manufacturing",
            "subcategory":"Tools & Machinery",
            "type":"Manufacturing & Wholesale Goods"
        }
    ],
    "sg:phone":"+1 615 444 1740",
    "sg:postcode":"37090",
    "sg:province":"TN",
    "sg:tags":[
        "die",
        "maker"
    ],
    "wof:name":"Gibson Broach & Tool Co",
    "wof:placetype":"venue"
},
  "geometry": {"coordinates":[-86.30308100000001,36.171453],"type":"Point"}
}