{
  "type": "Feature",
  "properties": {
    "addr:full":"1922 Pendleton St Memphis TN 38114",
    "addr:housenumber":"1922",
    "addr:postcode":"38114",
    "addr:street":"Pendleton St",
    "iso:country":"US",
    "sg:address":"1922 Pendleton St",
    "sg:city":"Memphis",
    "sg:classifiers":[
        {
            "category":"Organizations",
            "subcategory":"Community Association",
            "type":"Services"
        }
    ],
    "sg:phone":"+1 901 745 2748",
    "sg:postcode":"38114",
    "sg:province":"TN",
    "sg:tags":[
        "club",
        "private"
    ],
    "wof:name":"Memphis Redliners",
    "wof:placetype":"venue"
},
  "geometry": {"coordinates":[-89.970291,35.092766],"type":"Point"}
}