{
  "type": "Feature",
  "properties": {
    "iso:country":"US",
    "sg:address":"5307 Collingwood Rd",
    "sg:city":"Memphis",
    "sg:classifiers":[
        {
            "category":"Professional",
            "type":"Services"
        }
    ],
    "sg:phone":"+1 901 767 1633",
    "sg:postcode":"38117",
    "sg:province":"TN",
    "sg:tags":[
        "establishment"
    ],
    "wof:name":"Ipass",
    "wof:placetype":"venue"
},
  "geometry": {"coordinates":[-89.88606799999999,35.124725],"type":"Point"}
}