{
  "type": "Feature",
  "properties": {
    "addr:full":"5007 Mountview Pl Brentwood TN 37027",
    "addr:housenumber":"5007",
    "addr:postcode":"37027",
    "addr:street":"Mountview Pl",
    "iso:country":"US",
    "sg:address":"5007 Mountview Pl",
    "sg:city":"Brentwood",
    "sg:classifiers":[
        {
            "category":"Shopping",
            "subcategory":"Crafts & Fabrics",
            "type":"Retail Goods"
        }
    ],
    "sg:phone":"+1 615 377 0211",
    "sg:postcode":"37027",
    "sg:province":"TN",
    "sg:tags":[
        "sewing"
    ],
    "wof:name":"Joy of Needle Point",
    "wof:placetype":"venue"
},
  "geometry": {"coordinates":[-86.81166,35.998954],"type":"Point"}
}