{
  "type": "Feature",
  "properties": {
    "addr:full":"618 Grassmere Park Drive, Suite 20 Nashville TN 37211-3677",
    "addr:housenumber":"618;20",
    "addr:postcode":"37211-3677",
    "addr:street":"Grassmere Park Drive Suite",
    "iso:country":"US",
    "sg:address":"618 Grassmere Park Drive, Suite 20",
    "sg:city":"Nashville",
    "sg:classifiers":[
        {
            "category":"Professional",
            "subcategory":"Computer Services",
            "type":"Services"
        }
    ],
    "sg:postcode":"37211-3677",
    "sg:province":"TN",
    "wof:name":"Meretek Diagnostics",
    "wof:placetype":"venue"
},
  "geometry": {"coordinates":[-86.74915799999999,36.0889],"type":"Point"}
}