{
  "type": "Feature",
  "properties": {
    "iso:country":"US",
    "sg:address":"209 Turkey Creek Rd",
    "sg:city":"Carthage",
    "sg:classifiers":[
        {
            "category":"Building & Trades",
            "subcategory":"Construction",
            "type":"Services"
        }
    ],
    "sg:phone":"+1 615 735 1832",
    "sg:postcode":"37030",
    "sg:province":"TN",
    "sg:tags":[
        "utility",
        "contractor"
    ],
    "wof:name":"Cordell Hull Utility District",
    "wof:placetype":"venue"
},
  "geometry": {"coordinates":[-85.952241,36.30464],"type":"Point"}
}