{
  "type": "Feature",
  "properties": {
    "iso:country":"US",
    "sg:address":"1713 Doningham Dr",
    "sg:city":"Knoxville",
    "sg:classifiers":[
        {
            "category":"Shopping",
            "subcategory":"Bicycles & Sporting Goods",
            "type":"Retail Goods"
        }
    ],
    "sg:phone":"+1 865 254 6363",
    "sg:postcode":"37918",
    "sg:province":"TN",
    "wof:name":"Pups Pro Shop",
    "wof:placetype":"venue"
},
  "geometry": {"coordinates":[-83.953118,36.034523],"type":"Point"}
}