{
  "type": "Feature",
  "properties": {
    "iso:country":"US",
    "sg:address":"480 Old Collierville Arlington Rd",
    "sg:city":"Collierville",
    "sg:classifiers":[
        {
            "category":"Building & Trades",
            "subcategory":"Construction",
            "type":"Services"
        }
    ],
    "sg:phone":"+1 901 351 8449",
    "sg:postcode":"38017",
    "sg:province":"TN",
    "wof:name":"Mccall & Mccall Constr Co",
    "wof:placetype":"venue"
},
  "geometry": {"coordinates":[-89.653218,35.052925],"type":"Point"}
}