{
  "type": "Feature",
  "properties": {
    "iso:country":"US",
    "sg:address":"1454 Bowman Rd",
    "sg:city":"Hixson",
    "sg:classifiers":[
        {
            "category":"Professional",
            "subcategory":"Business Services",
            "type":"Services"
        }
    ],
    "sg:phone":"+1 423 847 1532",
    "sg:postcode":"37343",
    "sg:province":"TN",
    "wof:name":"Landscape & Design",
    "wof:placetype":"venue"
},
  "geometry": {"coordinates":[-85.194456,35.205231],"type":"Point"}
}