{
  "type": "Feature",
  "properties": {
    "addr:full":"234 Tyson Ave Paris TN 38242",
    "addr:housenumber":"234",
    "addr:postcode":"38242",
    "addr:street":"Tyson Ave",
    "iso:country":"US",
    "sg:address":"234 Tyson Ave",
    "sg:city":"Paris",
    "sg:classifiers":[
        {
            "category":"Building & Trades",
            "subcategory":"Plumbing",
            "type":"Services"
        }
    ],
    "sg:phone":"+1 731 642 1403",
    "sg:postcode":"38242",
    "sg:province":"TN",
    "sg:tags":[
        "conditioning",
        "air",
        "system",
        "contractor"
    ],
    "wof:name":"Custom Heating & Cooling",
    "wof:placetype":"venue"
},
  "geometry": {"coordinates":[-88.310689,36.298439],"type":"Point"}
}