{
  "type": "Feature",
  "properties": {
    "iso:country":"US",
    "sg:address":"310 Trails Cir",
    "sg:city":"Nashville",
    "sg:classifiers":[
        {
            "category":"Wholesale",
            "subcategory":"Chemicals & Plastics",
            "type":"Manufacturing & Wholesale Goods"
        }
    ],
    "sg:phone":"+1 615 391 1625",
    "sg:postcode":"37214",
    "sg:province":"TN",
    "wof:name":"Uniform Color Company",
    "wof:placetype":"venue"
},
  "geometry": {"coordinates":[-86.625697,36.147255],"type":"Point"}
}