{
  "type": "Feature",
  "properties": {
    "iso:country":"US",
    "sg:address":"6301 Old Rutledge Pike",
    "sg:city":"Knoxville",
    "sg:classifiers":[
        {
            "category":"Manufacturing",
            "subcategory":"Tools & Machinery",
            "type":"Manufacturing & Wholesale Goods"
        }
    ],
    "sg:phone":"+1 865 546 1414",
    "sg:postcode":"37924",
    "sg:province":"TN",
    "sg:tags":[
        "contractor"
    ],
    "sg:website":"www.stowerscat.com",
    "wof:name":"Stowers Machinery Corp",
    "wof:placetype":"venue"
},
  "geometry": {"coordinates":[-83.838528,36.027638],"type":"Point"}
}