{
  "type": "Feature",
  "properties": {
    "addr:full":"3405 Hackberry Rd Knoxville TN 37931",
    "addr:housenumber":"3405",
    "addr:postcode":"37931",
    "addr:street":"Hackberry Rd",
    "iso:country":"US",
    "sg:address":"3405 Hackberry Rd",
    "sg:city":"Knoxville",
    "sg:classifiers":[
        {
            "category":"Building & Trades",
            "subcategory":"Landscaping Services",
            "type":"Services"
        }
    ],
    "sg:phone":"+1 865 454 6331",
    "sg:postcode":"37931",
    "sg:province":"TN",
    "sg:tags":[
        "landscape",
        "contractor"
    ],
    "wof:name":"Earthscapes",
    "wof:placetype":"venue"
},
  "geometry": {"coordinates":[-84.057485,35.987269],"type":"Point"}
}