{
  "type": "Feature",
  "properties": {
    "iso:country":"US",
    "sg:address":"5027 Hixson Pike",
    "sg:city":"Hixson",
    "sg:classifiers":[
        {
            "category":"Freight",
            "type":"Transportation"
        }
    ],
    "sg:phone":"+1 423 648 7867",
    "sg:postcode":"37343",
    "sg:province":"TN",
    "sg:tags":[
        "commercial",
        "storage"
    ],
    "wof:name":"Prostorage At East Brainerd",
    "wof:placetype":"venue"
},
  "geometry": {"coordinates":[-85.242535,35.133221],"type":"Point"}
}