{
  "type": "Feature",
  "properties": {
    "addr:full":"5040 Sanderlin Ave Memphis TN 38117",
    "addr:housenumber":"5040",
    "addr:postcode":"38117",
    "addr:street":"Sanderlin Ave",
    "iso:country":"US",
    "sg:address":"5040 Sanderlin Ave",
    "sg:city":"Memphis",
    "sg:classifiers":[
        {
            "category":"Home & Garden",
            "subcategory":"Carpets & Floor Coverings",
            "type":"Retail Goods"
        }
    ],
    "sg:phone":"+1 901 818 6878",
    "sg:postcode":"38117",
    "sg:province":"TN",
    "sg:tags":[
        "oriental",
        "rug"
    ],
    "wof:name":"S V Kish Oriental Rugs Inc",
    "wof:placetype":"venue"
},
  "geometry": {"coordinates":[-89.894031,35.11725],"type":"Point"}
}