{
  "type": "Feature",
  "properties": {
    "iso:country":"US",
    "sg:address":"205 S Jackson St",
    "sg:city":"Tullahoma",
    "sg:classifiers":[
        {
            "category":"Health Services",
            "subcategory":"Doctor",
            "type":"Services"
        }
    ],
    "sg:phone":"+1 931 455 0146",
    "sg:postcode":"37388",
    "sg:province":"TN",
    "wof:name":"J Randll N Smth DDS Rchrd D",
    "wof:placetype":"venue"
},
  "geometry": {"coordinates":[-86.21040499999999,35.360689],"type":"Point"}
}