{
  "type": "Feature",
  "properties": {
    "addr:full":"2571 Fite Rd Memphis TN 38127",
    "addr:housenumber":"2571",
    "addr:postcode":"38127",
    "addr:street":"Fite Rd",
    "iso:country":"US",
    "sg:address":"2571 Fite Rd",
    "sg:city":"Memphis",
    "sg:classifiers":[
        {
            "category":"Manufacturing",
            "subcategory":"Chemicals & Compounds",
            "type":"Manufacturing & Wholesale Goods"
        }
    ],
    "sg:phone":"+1 901 353 7100",
    "sg:postcode":"38127",
    "sg:province":"TN",
    "sg:website":"www.dupont.com",
    "wof:name":"Du Pont De Nemours EI & Co",
    "wof:placetype":"venue"
},
  "geometry": {"coordinates":[-89.978273,35.272005],"type":"Point"}
}