{
  "type": "Feature",
  "properties": {
    "iso:country":"US",
    "sg:address":"57 Hebbertsburg Rd",
    "sg:city":"Crab Orchard",
    "sg:classifiers":[
        {
            "category":"Shopping",
            "type":"Retail Goods"
        }
    ],
    "sg:phone":"+1 931 456 9934",
    "sg:postcode":"37723",
    "sg:province":"TN",
    "sg:tags":[
        "refinishing",
        "furniture"
    ],
    "wof:name":"Second Chance",
    "wof:placetype":"venue"
},
  "geometry": {"coordinates":[-84.877861,35.909988],"type":"Point"}
}