{
  "type": "Feature",
  "properties": {
    "addr:full":"115 N Fairmont Ave Morristown TN 37814",
    "addr:housenumber":"115",
    "addr:postcode":"37814",
    "addr:street":"N Fairmont Ave",
    "iso:country":"US",
    "sg:address":"115 N Fairmont Ave",
    "sg:city":"Morristown",
    "sg:classifiers":[
        {
            "category":"Manufacturing",
            "subcategory":"Tools & Machinery",
            "type":"Manufacturing & Wholesale Goods"
        }
    ],
    "sg:phone":"+1 423 587 3050",
    "sg:postcode":"37814",
    "sg:province":"TN",
    "sg:tags":[
        "industrial",
        "mfg"
    ],
    "wof:name":"Thompson Machine Works",
    "wof:placetype":"venue"
},
  "geometry": {"coordinates":[-83.30767,36.207458],"type":"Point"}
}