{
  "type": "Feature",
  "properties": {
    "iso:country":"US",
    "sg:address":"1800 Wayne Rd",
    "sg:city":"Savannah",
    "sg:classifiers":[
        {
            "category":"Shopping",
            "subcategory":"Computers & Home Electronics",
            "type":"Retail Goods"
        }
    ],
    "sg:phone":"+1 731 925 0146",
    "sg:postcode":"38372",
    "sg:province":"TN",
    "sg:tags":[
        "game",
        "video"
    ],
    "sg:website":"www.gamestop.com",
    "wof:name":"Gamestop",
    "wof:placetype":"venue"
},
  "geometry": {"coordinates":[-88.234133,35.227537],"type":"Point"}
}