{
  "type": "Feature",
  "properties": {
    "addr:full":"801 Hangar Ln Nashville TN 37217",
    "addr:housenumber":"801",
    "addr:postcode":"37217",
    "addr:street":"Hangar Ln",
    "iso:country":"US",
    "sg:address":"801 Hangar Ln",
    "sg:city":"Nashville",
    "sg:classifiers":[
        {
            "category":"Airport",
            "type":"Transportation"
        }
    ],
    "sg:phone":"+1 615 365 0089",
    "sg:postcode":"37217",
    "sg:province":"TN",
    "sg:tags":[
        "aircraft",
        "maintenance"
    ],
    "wof:name":"Merlin's Avionics Svc",
    "wof:placetype":"venue"
},
  "geometry": {"coordinates":[-86.677516,36.115547],"type":"Point"}
}