{
  "type": "Feature",
  "properties": {
    "addr:full":"2195 S Germantown Rd Germantown TN 38138",
    "addr:housenumber":"2195",
    "addr:postcode":"38138",
    "addr:street":"S Germantown Rd",
    "iso:country":"US",
    "sg:address":"2195 S Germantown Rd",
    "sg:city":"Germantown",
    "sg:classifiers":[
        {
            "category":"Organizations",
            "subcategory":"Professional Association",
            "type":"Services"
        }
    ],
    "sg:phone":"+1 901 755 1200",
    "sg:postcode":"38138",
    "sg:province":"TN",
    "sg:tags":[
        "chamber",
        "commerce"
    ],
    "wof:name":"Germantown Chamber Of Commerce",
    "wof:placetype":"venue"
},
  "geometry": {"coordinates":[-89.80929999999999,35.091789],"type":"Point"}
}