{
  "type": "Feature",
  "properties": {
    "iso:country":"US",
    "sg:address":"103 Meadow St",
    "sg:city":"Old Hickory",
    "sg:classifiers":[
        {
            "category":"Building & Trades",
            "subcategory":"Construction",
            "type":"Services"
        }
    ],
    "sg:phone":"+1 615 847 3660",
    "sg:postcode":"37138",
    "sg:province":"TN",
    "sg:tags":[
        "house"
    ],
    "wof:name":"Precision Home Improvement",
    "wof:placetype":"venue"
},
  "geometry": {"coordinates":[-86.640603,36.241484],"type":"Point"}
}