{
  "type": "Feature",
  "properties": {
    "addr:full":"7114 Winchester Rd Memphis TN 38125",
    "addr:housenumber":"7114",
    "addr:postcode":"38125",
    "addr:street":"Winchester Rd",
    "iso:country":"US",
    "sg:address":"7114 Winchester Rd",
    "sg:city":"Memphis",
    "sg:classifiers":[
        {
            "category":"Home & Garden",
            "subcategory":"Household Appliances",
            "type":"Retail Goods"
        },
        {
            "category":"Autos & Motor Vehicles",
            "subcategory":"Auto Supplies",
            "type":"Retail Goods"
        },
        {
            "category":"Shopping",
            "subcategory":"Computers & Home Electronics",
            "type":"Retail Goods"
        },
        {
            "category":"Wholesale",
            "subcategory":"Computers",
            "type":"Manufacturing & Wholesale Goods"
        }
    ],
    "sg:phone":"+1 901 754 0652",
    "sg:postcode":"38125",
    "sg:province":"TN",
    "sg:tags":[
        "stereo",
        "theater",
        "automobile",
        "television",
        "system",
        "equipment",
        "radio",
        "major",
        "consumer",
        "store"
    ],
    "sg:website":"http://www.bestbuy.com/",
    "wof:name":"Best Buy",
    "wof:placetype":"venue"
},
  "geometry": {"coordinates":[-89.825974,35.049016],"type":"Point"}
}