{
  "type": "Feature",
  "properties": {
    "addr:full":"8142 Tamarack Rd Knoxville TN 37919",
    "addr:housenumber":"8142",
    "addr:postcode":"37919",
    "addr:street":"Tamarack Rd",
    "iso:country":"US",
    "sg:address":"8142 Tamarack Rd",
    "sg:city":"Knoxville",
    "sg:classifiers":[
        {
            "category":"Professional",
            "subcategory":"Business Services",
            "type":"Services"
        }
    ],
    "sg:phone":"+1 865 539 0465",
    "sg:postcode":"37919",
    "sg:province":"TN",
    "sg:tags":[
        "engineering",
        "fabrication"
    ],
    "wof:name":"Combined Technologies Inc",
    "wof:placetype":"venue"
},
  "geometry": {"coordinates":[-84.02596200000001,35.897686],"type":"Point"}
}