{
  "type": "Feature",
  "properties": {
    "iso:country":"US",
    "sg:address":"99 E Tennessee Ave",
    "sg:city":"Oak Ridge",
    "sg:classifiers":[
        {
            "category":"Food & Beverages",
            "subcategory":"Groceries & Convenience Stores",
            "type":"Retail Goods"
        }
    ],
    "sg:phone":"+1 865 482 5640",
    "sg:postcode":"37830",
    "sg:province":"TN",
    "sg:tags":[
        "deli"
    ],
    "wof:name":"Tim's Market & Deli",
    "wof:placetype":"venue"
},
  "geometry": {"coordinates":[-84.237011,36.029665],"type":"Point"}
}