{
  "type": "Feature",
  "properties": {
    "addr:full":"12834 Paris St Huntingdon TN 38344",
    "addr:postcode":"12834;38344",
    "addr:street":"St",
    "iso:country":"US",
    "sg:address":"12834 Paris St",
    "sg:city":"Huntingdon",
    "sg:classifiers":[
        {
            "category":"Home & Garden",
            "subcategory":"Household Appliances",
            "type":"Retail Goods"
        },
        {
            "category":"Home & Garden",
            "subcategory":"Furniture",
            "type":"Retail Goods"
        }
    ],
    "sg:phone":"+1 731 986 9588",
    "sg:postcode":"38344",
    "sg:province":"TN",
    "wof:name":"Jordans Auction & Trading Post",
    "wof:placetype":"venue"
},
  "geometry": {"coordinates":[-88.428116,36.00185],"type":"Point"}
}