{
  "type": "Feature",
  "properties": {
    "iso:country":"US",
    "sg:address":"107 Music City Cir",
    "sg:city":"Nashville",
    "sg:classifiers":[
        {
            "category":"Shopping",
            "subcategory":"Clothing, Apparel, & Fashions",
            "type":"Retail Goods"
        }
    ],
    "sg:phone":"+1 615 885 2005",
    "sg:postcode":"37214",
    "sg:province":"TN",
    "wof:name":"Cintas Corp",
    "wof:placetype":"venue"
},
  "geometry": {"coordinates":[-86.69681,36.222991],"type":"Point"}
}