{
  "type": "Feature",
  "properties": {
    "iso:country":"US",
    "sg:address":"7172 Volendam Cv",
    "sg:city":"Memphis",
    "sg:classifiers":[
        {
            "category":"Government",
            "subcategory":"Office",
            "type":"Public Place"
        }
    ],
    "sg:phone":"+1 901 383 8071",
    "sg:postcode":"38133",
    "sg:province":"TN",
    "sg:tags":[
        "government-united",
        "state"
    ],
    "wof:name":"Tanner, John",
    "wof:placetype":"venue"
},
  "geometry": {"coordinates":[-89.823151,35.201615],"type":"Point"}
}