{
  "type": "Feature",
  "properties": {
    "iso:country":"US",
    "sg:address":"9051 Executive Park Dr",
    "sg:city":"Knoxville",
    "sg:classifiers":[
        {
            "category":"Professional",
            "subcategory":"Testing Lab",
            "type":"Services"
        }
    ],
    "sg:phone":"+1 865 769 1301",
    "sg:postcode":"37923",
    "sg:province":"TN",
    "sg:tags":[
        "laboratory"
    ],
    "wof:name":"Absoutely Certain DNA",
    "wof:placetype":"venue"
},
  "geometry": {"coordinates":[-84.085616,35.921194],"type":"Point"}
}