{
  "type": "Feature",
  "properties": {
    "addr:full":"1935 Hamer Rd Dyersburg TN 38024",
    "addr:housenumber":"1935",
    "addr:postcode":"38024",
    "addr:street":"Hamer Rd",
    "iso:country":"US",
    "sg:address":"1935 Hamer Rd",
    "sg:city":"Dyersburg",
    "sg:classifiers":[
        {
            "category":"Restaurant",
            "type":"Food & Drink"
        }
    ],
    "sg:phone":"+1 731 287 8196",
    "sg:postcode":"38024",
    "sg:province":"TN",
    "sg:tags":[
        "eating"
    ],
    "wof:name":"Tonys Ice",
    "wof:placetype":"venue"
},
  "geometry": {"coordinates":[-89.362816,36.110949],"type":"Point"}
}