{
  "type": "Feature",
  "properties": {
    "addr:full":"833 Sylvan Dr Chattanooga TN 37411",
    "addr:housenumber":"833",
    "addr:postcode":"37411",
    "addr:street":"Sylvan Dr",
    "iso:country":"US",
    "sg:address":"833 Sylvan Dr",
    "sg:city":"Chattanooga",
    "sg:classifiers":[
        {
            "category":"Building & Trades",
            "subcategory":"Construction",
            "type":"Services"
        }
    ],
    "sg:phone":"+1 423 622 8319",
    "sg:postcode":"37411",
    "sg:province":"TN",
    "sg:tags":[
        "housing"
    ],
    "wof:name":"N T S Builders",
    "wof:placetype":"venue"
},
  "geometry": {"coordinates":[-85.233119,35.036439],"type":"Point"}
}