{
  "type": "Feature",
  "properties": {
    "addr:full":"1225 Columbia Ave Franklin TN 37064",
    "addr:housenumber":"1225",
    "addr:postcode":"37064",
    "addr:street":"Columbia Ave",
    "iso:country":"US",
    "sg:address":"1225 Columbia Ave",
    "sg:city":"Franklin",
    "sg:classifiers":[
        {
            "category":"Restaurant",
            "type":"Food & Drink"
        }
    ],
    "sg:menulink":"http://www.allmenus.com/tn/franklin/85649-dominos-pizza/menu/",
    "sg:phone":"+1 615 790 8855",
    "sg:postcode":"37064",
    "sg:province":"TN",
    "sg:tags":[
        "american",
        "wing",
        "pizza"
    ],
    "wof:name":"Domino's Pizza",
    "wof:placetype":"venue"
},
  "geometry": {"coordinates":[-86.87303799999999,35.9158],"type":"Point"}
}