{
  "type": "Feature",
  "properties": {
    "iso:country":"US",
    "sg:address":"449 US Hwy 72",
    "sg:city":"Collierville",
    "sg:classifiers":[
        {
            "category":"Organizations",
            "subcategory":"Religious Organization",
            "type":"Services"
        }
    ],
    "sg:phone":"+1 901 854 2216",
    "sg:postcode":"38017",
    "sg:province":"TN",
    "sg:tags":[
        "church"
    ],
    "wof:name":"Greater Works Deliverance",
    "wof:placetype":"venue"
},
  "geometry": {"coordinates":[-89.676832,35.045729],"type":"Point"}
}