{
  "type": "Feature",
  "properties": {
    "iso:country":"US",
    "sg:address":"191 Crab Apple Ln",
    "sg:city":"Crossville",
    "sg:classifiers":[
        {
            "category":"Building & Trades",
            "subcategory":"Construction",
            "type":"Services"
        }
    ],
    "sg:phone":"+1 931 484 2593",
    "sg:postcode":"38555",
    "sg:province":"TN",
    "sg:tags":[
        "housing"
    ],
    "wof:name":"L & J Construction",
    "wof:placetype":"venue"
},
  "geometry": {"coordinates":[-84.973866,35.90357],"type":"Point"}
}