{
  "type": "Feature",
  "properties": {
    "addr:full":"101 Creekside Xing Brentwood TN 37027",
    "addr:housenumber":"101",
    "addr:postcode":"37027",
    "addr:street":"Creekside Xing",
    "iso:country":"US",
    "sg:address":"101 Creekside Xing",
    "sg:city":"Brentwood",
    "sg:classifiers":[
        {
            "category":"Restaurant",
            "type":"Food & Drink"
        }
    ],
    "sg:menulink":"http://www.allmenus.com/tn/nashville/95696-pei-wei/menu/",
    "sg:phone":"+1 615 514 4990",
    "sg:postcode":"37027",
    "sg:province":"TN",
    "sg:tags":[
        "chinese",
        "vietnamese",
        "japanese",
        "asian",
        "korean",
        "thai"
    ],
    "wof:name":"Pei Wei",
    "wof:placetype":"venue"
},
  "geometry": {"coordinates":[-86.797791,36.037774],"type":"Point"}
}