{
  "type": "Feature",
  "properties": {
    "iso:country":"US",
    "sg:address":"8427 Ashley Oak Way",
    "sg:city":"Knoxville",
    "sg:classifiers":[
        {
            "category":"Banks & Credit Unions",
            "subcategory":"Financial Services",
            "type":"Services"
        }
    ],
    "sg:phone":"+1 865 604 5366",
    "sg:postcode":"37923",
    "sg:province":"TN",
    "sg:tags":[
        "investor"
    ],
    "wof:name":"Medtek Investment",
    "wof:placetype":"venue"
},
  "geometry": {"coordinates":[-84.055862,35.893853],"type":"Point"}
}