{
  "type": "Feature",
  "properties": {
    "iso:country":"US",
    "sg:address":"9408 Sarasota Dr NW",
    "sg:city":"Knoxville",
    "sg:classifiers":[
        {
            "category":"Recreation",
            "type":"Entertainment"
        }
    ],
    "sg:phone":"+1 865 690 4145",
    "sg:postcode":"37923",
    "sg:province":"TN",
    "wof:name":"Tennessee Valley Cat Fanciers",
    "wof:placetype":"venue"
},
  "geometry": {"coordinates":[-84.099569,35.929059],"type":"Point"}
}