{
  "type": "Feature",
  "properties": {
    "addr:full":"2761 Sullins St SW Knoxville TN 37919",
    "addr:housenumber":"2761",
    "addr:postcode":"37919",
    "addr:street":"Sullins St Sw",
    "iso:country":"US",
    "sg:address":"2761 Sullins St SW",
    "sg:city":"Knoxville",
    "sg:classifiers":[
        {
            "category":"Professional",
            "type":"Services"
        }
    ],
    "sg:phone":"+1 865 219 4877",
    "sg:postcode":"37919",
    "sg:province":"TN",
    "sg:tags":[
        "establishment"
    ],
    "wof:name":"Propage",
    "wof:placetype":"venue"
},
  "geometry": {"coordinates":[-83.948949,35.952352],"type":"Point"}
}