{
  "type": "Feature",
  "properties": {
    "addr:full":"470 Wooten Rd Clarksville TN 37042",
    "addr:housenumber":"470",
    "addr:postcode":"37042",
    "addr:street":"Wooten Rd",
    "iso:country":"US",
    "sg:address":"470 Wooten Rd",
    "sg:city":"Clarksville",
    "sg:classifiers":[
        {
            "category":"Wholesale",
            "subcategory":"Durable Goods & Equipment",
            "type":"Manufacturing & Wholesale Goods"
        }
    ],
    "sg:phone":"+1 931 648 2183",
    "sg:postcode":"37042",
    "sg:province":"TN",
    "sg:tags":[
        "fire",
        "extinguisher",
        "business"
    ],
    "wof:name":"Queen City Fire Equipment Co",
    "wof:placetype":"venue"
},
  "geometry": {"coordinates":[-87.43259999999999,36.524863],"type":"Point"}
}