{
  "type": "Feature",
  "properties": {
    "iso:country":"US",
    "sg:address":"224 Jackson Meadows Dr",
    "sg:city":"Hermitage",
    "sg:classifiers":[
        {
            "category":"Shopping",
            "subcategory":"Hobbies, Toys, & Games",
            "type":"Retail Goods"
        }
    ],
    "sg:phone":"+1 615 883 9313",
    "sg:postcode":"37076",
    "sg:province":"TN",
    "sg:tags":[
        "mfg"
    ],
    "wof:name":"A Teddy Bear Close",
    "wof:placetype":"venue"
},
  "geometry": {"coordinates":[-86.599817,36.21794],"type":"Point"}
}