{
  "type": "Feature",
  "properties": {
    "addr:full":"915 Harpeth Valley Pl Nashville TN 37221",
    "addr:housenumber":"915",
    "addr:postcode":"37221",
    "addr:street":"Harpeth Valley Pl",
    "iso:country":"US",
    "sg:address":"915 Harpeth Valley Pl",
    "sg:city":"Nashville",
    "sg:classifiers":[
        {
            "category":"Insurance",
            "subcategory":"Insurance Agent",
            "type":"Services"
        }
    ],
    "sg:phone":"+1 615 662 1551",
    "sg:postcode":"37221",
    "sg:province":"TN",
    "wof:name":"State Farm Insurance",
    "wof:placetype":"venue"
},
  "geometry": {"coordinates":[-86.95687100000001,36.083216],"type":"Point"}
}