{
  "type": "Feature",
  "properties": {
    "iso:country":"US",
    "sg:address":"9606 Thornberry Dr",
    "sg:city":"Ooltewah",
    "sg:classifiers":[
        {
            "category":"Real Estate",
            "subcategory":"Real Estate Operator",
            "type":"Services"
        }
    ],
    "sg:phone":"+1 423 875 2247",
    "sg:postcode":"37363",
    "sg:province":"TN",
    "sg:tags":[
        "building",
        "nonresidential"
    ],
    "wof:name":"Star Properties",
    "wof:placetype":"venue"
},
  "geometry": {"coordinates":[-85.073229,35.037859],"type":"Point"}
}