{
  "type": "Feature",
  "properties": {
    "addr:full":"149 N Main St Clinton TN 37716",
    "addr:housenumber":"149",
    "addr:postcode":"37716",
    "addr:street":"N Main St",
    "iso:country":"US",
    "sg:address":"149 N Main St",
    "sg:city":"Clinton",
    "sg:classifiers":[
        {
            "category":"Professional",
            "subcategory":"Lawyer & Legal Services",
            "type":"Services"
        }
    ],
    "sg:phone":"+1 865 457 5640",
    "sg:postcode":"37716",
    "sg:province":"TN",
    "sg:tags":[
        "attorney"
    ],
    "sg:website":"www.attorneygeneral.org",
    "wof:name":"District Attorney General",
    "wof:placetype":"venue"
},
  "geometry": {"coordinates":[-84.13299499999999,36.100763],"type":"Point"}
}