{
  "type": "Feature",
  "properties": {
    "addr:full":"263 Buffalo Rd Clinton TN 37716",
    "addr:housenumber":"263",
    "addr:postcode":"37716",
    "addr:street":"Buffalo Rd",
    "iso:country":"US",
    "sg:address":"263 Buffalo Rd",
    "sg:city":"Clinton",
    "sg:classifiers":[
        {
            "category":"Organizations",
            "subcategory":"Religious Organization",
            "type":"Services"
        }
    ],
    "sg:phone":"+1 865 494 0565",
    "sg:postcode":"37716",
    "sg:province":"TN",
    "wof:name":"Tennessee Dst of Wsleya Church",
    "wof:placetype":"venue"
},
  "geometry": {"coordinates":[-84.073446,36.157543],"type":"Point"}
}