{
  "type": "Feature",
  "properties": {
    "iso:country":"US",
    "sg:address":"200 River Hills Dr",
    "sg:city":"Nashville",
    "sg:classifiers":[
        {
            "category":"Wholesale",
            "subcategory":"Medical Equipment & Supplies",
            "type":"Manufacturing & Wholesale Goods"
        }
    ],
    "sg:phone":"+1 615 883 9090",
    "sg:postcode":"37210",
    "sg:province":"TN",
    "sg:tags":[
        "physician",
        "surgeon"
    ],
    "sg:website":"www.ssiultra.com",
    "wof:name":"Specialty Surgical Instrmnttn",
    "wof:placetype":"venue"
},
  "geometry": {"coordinates":[-86.71755400000001,36.16298],"type":"Point"}
}