{
  "type": "Feature",
  "properties": {
    "iso:country":"US",
    "sg:address":"609 W Irish St",
    "sg:city":"Greeneville",
    "sg:classifiers":[
        {
            "category":"Wholesale",
            "subcategory":"Farm Supplies",
            "type":"Manufacturing & Wholesale Goods"
        }
    ],
    "sg:phone":"+1 423 639 0161",
    "sg:postcode":"37743",
    "sg:province":"TN",
    "wof:name":"F & M Farm Supply",
    "wof:placetype":"venue"
},
  "geometry": {"coordinates":[-82.838703,36.160287],"type":"Point"}
}