{
  "type": "Feature",
  "properties": {
    "iso:country":"US",
    "sg:address":"2617 Elvis Presley Blvd",
    "sg:city":"Memphis",
    "sg:classifiers":[
        {
            "category":"Food & Beverages",
            "subcategory":"Liquor & Beverages",
            "type":"Retail Goods"
        }
    ],
    "sg:phone":"+1 901 948 1508",
    "sg:postcode":"38116",
    "sg:province":"TN",
    "sg:tags":[
        "alcoholic"
    ],
    "wof:name":"Cattaneos Liquor Store",
    "wof:placetype":"venue"
},
  "geometry": {"coordinates":[-90.020775,35.073272],"type":"Point"}
}