{
  "type": "Feature",
  "properties": {
    "iso:country":"US",
    "sg:address":"38 Music Sq E",
    "sg:city":"Nashville",
    "sg:classifiers":[
        {
            "category":"Retail",
            "subcategory":"Photofinishing",
            "type":"Services"
        }
    ],
    "sg:phone":"+1 615 242 1883",
    "sg:postcode":"37203",
    "sg:province":"TN",
    "sg:tags":[
        "photo",
        "finishing"
    ],
    "sg:website":"www.starphotoservice.com",
    "wof:name":"Star Photo Svc",
    "wof:placetype":"venue"
},
  "geometry": {"coordinates":[-86.79209,36.148795],"type":"Point"}
}