{
  "type": "Feature",
  "properties": {
    "iso:country":"US",
    "sg:address":"1304 Riverside Dr",
    "sg:city":"Old Hickory",
    "sg:classifiers":[
        {
            "category":"Professional",
            "subcategory":"Management & Consulting",
            "type":"Services"
        }
    ],
    "sg:phone":"+1 615 847 8483",
    "sg:postcode":"37138",
    "sg:province":"TN",
    "sg:tags":[
        "business"
    ],
    "wof:name":"Access America",
    "wof:placetype":"venue"
},
  "geometry": {"coordinates":[-86.642759,36.256408],"type":"Point"}
}