{
  "type": "Feature",
  "properties": {
    "iso:country":"US",
    "sg:address":"2208 Gallatin Pike N",
    "sg:city":"Madison",
    "sg:classifiers":[
        {
            "category":"Home & Garden",
            "subcategory":"Furniture",
            "type":"Retail Goods"
        }
    ],
    "sg:phone":"+1 615 851 2541",
    "sg:postcode":"37115",
    "sg:province":"TN",
    "wof:name":"Havertys Rivergate",
    "wof:placetype":"venue"
},
  "geometry": {"coordinates":[-86.684504,36.307374],"type":"Point"}
}