{
  "type": "Feature",
  "properties": {
    "addr:full":"1176 Main St Wartburg TN 37887",
    "addr:housenumber":"1176",
    "addr:postcode":"37887",
    "addr:street":"Main St",
    "iso:country":"US",
    "sg:address":"1176 Main St",
    "sg:city":"Wartburg",
    "sg:classifiers":[
        {
            "category":"Utilities",
            "subcategory":"Telephone",
            "type":"Services"
        }
    ],
    "sg:phone":"+1 423 346 6085",
    "sg:postcode":"37887",
    "sg:province":"TN",
    "sg:tags":[
        "company"
    ],
    "wof:name":"American Telephone Exchange",
    "wof:placetype":"venue"
},
  "geometry": {"coordinates":[-84.584435,36.099381],"type":"Point"}
}