{
  "type": "Feature",
  "properties": {
    "iso:country":"US",
    "sg:address":"105 Church St",
    "sg:city":"Loretto",
    "sg:classifiers":[
        {
            "category":"Shopping",
            "subcategory":"Pharmacy",
            "type":"Retail Goods"
        }
    ],
    "sg:phone":"+1 931 853 5910",
    "sg:postcode":"38469",
    "sg:province":"TN",
    "wof:name":"Loretto Drugs",
    "wof:placetype":"venue"
},
  "geometry": {"coordinates":[-87.440034,35.076494],"type":"Point"}
}