{
  "type": "Feature",
  "properties": {
    "iso:country":"US",
    "sg:address":"420 W Church Ave",
    "sg:city":"Knoxville",
    "sg:classifiers":[
        {
            "category":"Shopping",
            "type":"Retail Goods"
        }
    ],
    "sg:phone":"+1 865 522 8484",
    "sg:postcode":"37902",
    "sg:province":"TN",
    "sg:tags":[
        "merchandise"
    ],
    "wof:name":"Back Room Gallery",
    "wof:placetype":"venue"
},
  "geometry": {"coordinates":[-83.919073,35.962662],"type":"Point"}
}