{
  "type": "Feature",
  "properties": {
    "addr:full":"771 Haystack Ln Antioch TN 37013",
    "addr:housenumber":"771",
    "addr:postcode":"37013",
    "addr:street":"Haystack Ln",
    "iso:country":"US",
    "sg:address":"771 Haystack Ln",
    "sg:city":"Antioch",
    "sg:classifiers":[
        {
            "category":"Taxi",
            "type":"Transportation"
        }
    ],
    "sg:phone":"+1 615 506 3086",
    "sg:postcode":"37013",
    "sg:province":"TN",
    "sg:tags":[
        "taxicab"
    ],
    "wof:name":"Allied Cab",
    "wof:placetype":"venue"
},
  "geometry": {"coordinates":[-86.684831,36.071509],"type":"Point"}
}