{
  "type": "Feature",
  "properties": {
    "iso:country":"US",
    "sg:address":"2394 Wildwood Rd",
    "sg:city":"Maryville",
    "sg:classifiers":[
        {
            "category":"Building & Trades",
            "subcategory":"Construction",
            "type":"Services"
        }
    ],
    "sg:phone":"+1 865 982 8011",
    "sg:postcode":"37804",
    "sg:province":"TN",
    "sg:tags":[
        "excavating",
        "land",
        "for",
        "clearing",
        "contractor",
        "trenching"
    ],
    "wof:name":"Sam C Franklin & Son Inc",
    "wof:placetype":"venue"
},
  "geometry": {"coordinates":[-83.943342,35.784283],"type":"Point"}
}