{
  "type": "Feature",
  "properties": {
    "addr:full":"650 State Hwy 100 Centerville TN 37033",
    "addr:housenumber":"650",
    "addr:postcode":"37033",
    "addr:street":"State Hwy 100",
    "iso:country":"US",
    "sg:address":"650 State Hwy 100",
    "sg:city":"Centerville",
    "sg:classifiers":[
        {
            "category":"Shopping",
            "subcategory":"Pharmacy",
            "type":"Retail Goods"
        }
    ],
    "sg:phone":"+1 931 729 5005",
    "sg:postcode":"37033",
    "sg:province":"TN",
    "wof:name":"Rite Aid Pharmacy",
    "wof:placetype":"venue"
},
  "geometry": {"coordinates":[-87.437938,35.799746],"type":"Point"}
}