{
  "type": "Feature",
  "properties": {
    "iso:country":"US",
    "sg:address":"5433 Nolensville Pike",
    "sg:city":"Nashville",
    "sg:classifiers":[
        {
            "category":"Shopping",
            "subcategory":"Discount & Variety Stores",
            "type":"Retail Goods"
        }
    ],
    "sg:phone":"+1 615 333 0973",
    "sg:postcode":"37211",
    "sg:province":"TN",
    "sg:tags":[
        "merchandise",
        "general"
    ],
    "wof:name":"Dollar General",
    "wof:placetype":"venue"
},
  "geometry": {"coordinates":[-86.714057,36.050182],"type":"Point"}
}