{
  "type": "Feature",
  "properties": {
    "iso:country":"US",
    "sg:address":"7700 Poplar Ave",
    "sg:city":"Germantown",
    "sg:classifiers":[
        {
            "category":"Real Estate",
            "subcategory":"Real Estate Agent",
            "type":"Services"
        }
    ],
    "sg:phone":"+1 901 754 0800",
    "sg:postcode":"38138",
    "sg:province":"TN",
    "wof:name":"Crye-Leike Realtors",
    "wof:placetype":"venue"
},
  "geometry": {"coordinates":[-89.80566899999999,35.091306],"type":"Point"}
}