{
  "type": "Feature",
  "properties": {
    "iso:country":"US",
    "sg:address":"5284 Whitworth Rd",
    "sg:city":"Memphis",
    "sg:classifiers":[
        {
            "category":"Retail",
            "subcategory":"Repair Shop",
            "type":"Services"
        }
    ],
    "sg:phone":"+1 901 346 0114",
    "sg:postcode":"38116",
    "sg:province":"TN",
    "wof:name":"JWS Cleaning",
    "wof:placetype":"venue"
},
  "geometry": {"coordinates":[-90.015601,35.004874],"type":"Point"}
}