{
  "type": "Feature",
  "properties": {
    "iso:country":"US",
    "sg:address":"801 Pine St",
    "sg:city":"Chattanooga",
    "sg:classifiers":[
        {
            "category":"Health Services",
            "subcategory":"Doctor",
            "type":"Services"
        }
    ],
    "sg:phone":"+1 423 755 5600",
    "sg:postcode":"37402",
    "sg:province":"TN",
    "sg:tags":[
        "organization",
        "maintenance"
    ],
    "wof:name":"Volunteer State Health Plan",
    "wof:placetype":"venue"
},
  "geometry": {"coordinates":[-85.31258699999999,35.046624],"type":"Point"}
}