{
  "type": "Feature",
  "properties": {
    "iso:country":"US",
    "sg:address":"8185 Londonberry Rd",
    "sg:city":"Nashville",
    "sg:classifiers":[
        {
            "category":"Home & Garden",
            "subcategory":"Carpets & Floor Coverings",
            "type":"Retail Goods"
        }
    ],
    "sg:phone":"+1 615 673 6344",
    "sg:postcode":"37221",
    "sg:province":"TN",
    "wof:name":"Carpet Source",
    "wof:placetype":"venue"
},
  "geometry": {"coordinates":[-86.976681,36.06316],"type":"Point"}
}