{
  "type": "Feature",
  "properties": {
    "iso:country":"US",
    "sg:address":"235 Germantown Bend Cove",
    "sg:city":"Cordova",
    "sg:classifiers":[
        {
            "category":"Professional",
            "subcategory":"Management & Consulting",
            "type":"Services"
        }
    ],
    "sg:phone":"+1 901 757 8195",
    "sg:postcode":"38018",
    "sg:province":"TN",
    "sg:tags":[
        "consultant",
        "security",
        "system"
    ],
    "wof:name":"Alarm Co",
    "wof:placetype":"venue"
},
  "geometry": {"coordinates":[-89.798243,35.123916],"type":"Point"}
}