{
  "type": "Feature",
  "properties": {
    "iso:country":"US",
    "sg:address":"8344 Savannah Ln E",
    "sg:city":"Ooltewah",
    "sg:classifiers":[
        {
            "category":"Utilities",
            "subcategory":"Fuel Oil & Lpg",
            "type":"Services"
        }
    ],
    "sg:phone":"+1 423 344 7019",
    "sg:postcode":"37363",
    "sg:province":"TN",
    "sg:tags":[
        "dealer"
    ],
    "wof:name":"Cumberland Mountain Firewood",
    "wof:placetype":"venue"
},
  "geometry": {"coordinates":[-85.059062,35.158156],"type":"Point"}
}