{
  "type": "Feature",
  "properties": {
    "addr:full":"3571 Lamar Ave Memphis TN 38118",
    "addr:housenumber":"3571",
    "addr:postcode":"38118",
    "addr:street":"Lamar Ave",
    "iso:country":"US",
    "sg:address":"3571 Lamar Ave",
    "sg:city":"Memphis",
    "sg:classifiers":[
        {
            "category":"Restaurant",
            "type":"Food & Drink"
        }
    ],
    "sg:phone":"+1 901 794 1254",
    "sg:postcode":"38118",
    "sg:province":"TN",
    "sg:tags":[
        "chicken"
    ],
    "wof:name":"Pirtles Fried Chkn Carry-Out",
    "wof:placetype":"venue"
},
  "geometry": {"coordinates":[-89.893967,35.015251],"type":"Point"}
}