{
  "type": "Feature",
  "properties": {
    "iso:country":"US",
    "sg:address":"1678 Kindra Ct",
    "sg:city":"Brentwood",
    "sg:classifiers":[
        {
            "category":"Wholesale",
            "subcategory":"Groceries",
            "type":"Manufacturing & Wholesale Goods"
        }
    ],
    "sg:phone":"+1 615 376 6150",
    "sg:postcode":"37027",
    "sg:province":"TN",
    "wof:name":"Dr Ffeines Beans",
    "wof:placetype":"venue"
},
  "geometry": {"coordinates":[-86.757475,35.961506],"type":"Point"}
}