{
  "type": "Feature",
  "properties": {
    "iso:country":"US",
    "sg:address":"169 Belle Forest Cir",
    "sg:city":"Nashville",
    "sg:classifiers":[
        {
            "category":"Insurance",
            "subcategory":"Insurance Agent",
            "type":"Services"
        }
    ],
    "sg:phone":"+1 615 673 8466",
    "sg:postcode":"37221",
    "sg:province":"TN",
    "wof:name":"Shelter Insurance",
    "wof:placetype":"venue"
},
  "geometry": {"coordinates":[-86.92387100000001,36.075728],"type":"Point"}
}