{
  "type": "Feature",
  "properties": {
    "iso:country":"US",
    "sg:address":"2304 E Reelfoot Ave",
    "sg:city":"Union City",
    "sg:classifiers":[
        {
            "category":"Building & Trades",
            "subcategory":"Construction",
            "type":"Services"
        }
    ],
    "sg:phone":"+1 731 886 0019",
    "sg:postcode":"38261",
    "sg:province":"TN",
    "sg:tags":[
        "maintenance",
        "contractor"
    ],
    "wof:name":"Maintenance Professional",
    "wof:placetype":"venue"
},
  "geometry": {"coordinates":[-89.017358,36.411503],"type":"Point"}
}