{
  "type": "Feature",
  "properties": {
    "iso:country":"US",
    "sg:address":"3814 Cleghorn Ave",
    "sg:city":"Nashville",
    "sg:classifiers":[
        {
            "category":"Manufacturing",
            "subcategory":"Retail Goods",
            "type":"Manufacturing & Wholesale Goods"
        }
    ],
    "sg:phone":"+1 615 298 4444",
    "sg:postcode":"37215",
    "sg:province":"TN",
    "sg:tags":[
        "manufacturer"
    ],
    "sg:website":"www.williamfmiller.com",
    "wof:name":"William F Miller & Assoc",
    "wof:placetype":"venue"
},
  "geometry": {"coordinates":[-86.81940400000001,36.106946],"type":"Point"}
}