{
  "type": "Feature",
  "properties": {
    "iso:country":"US",
    "sg:address":"4726 Nolensville Pike",
    "sg:city":"Nashville",
    "sg:classifiers":[
        {
            "category":"Restaurant",
            "type":"Food & Drink"
        }
    ],
    "sg:phone":"+1 615 834 9988",
    "sg:postcode":"37211",
    "sg:province":"TN",
    "sg:tags":[
        "eating"
    ],
    "wof:name":"International Ballroom",
    "wof:placetype":"venue"
},
  "geometry": {"coordinates":[-86.71817,36.067126],"type":"Point"}
}