{
  "type": "Feature",
  "properties": {
    "addr:full":"721 S Everett High Rd Maryville TN 37804",
    "addr:housenumber":"721",
    "addr:postcode":"37804",
    "addr:street":"S Everett High Rd",
    "iso:country":"US",
    "sg:address":"721 S Everett High Rd",
    "sg:city":"Maryville",
    "sg:classifiers":[
        {
            "category":"Organizations",
            "subcategory":"Religious Organization",
            "type":"Services"
        }
    ],
    "sg:phone":"+1 865 981 2033",
    "sg:postcode":"37804",
    "sg:province":"TN",
    "wof:name":"Unity Christian Church",
    "wof:placetype":"venue"
},
  "geometry": {"coordinates":[-83.952068,35.763117],"type":"Point"}
}