{
  "type": "Feature",
  "properties": {
    "iso:country":"US",
    "sg:address":"5869 Almaville Rd",
    "sg:city":"Smyrna",
    "sg:classifiers":[
        {
            "category":"Professional",
            "type":"Services"
        }
    ],
    "sg:phone":"+1 615 893 5977",
    "sg:postcode":"37167",
    "sg:province":"TN",
    "wof:name":"Royal Glen Step Service",
    "wof:placetype":"venue"
},
  "geometry": {"coordinates":[-86.529932,35.9362],"type":"Point"}
}