{
  "type": "Feature",
  "properties": {
    "iso:country":"US",
    "sg:address":"14550 Natchez Trace Rd",
    "sg:city":"Lexington",
    "sg:classifiers":[
        {
            "category":"Building & Trades",
            "subcategory":"Construction",
            "type":"Services"
        }
    ],
    "sg:phone":"+1 731 968 7255",
    "sg:postcode":"38351",
    "sg:province":"TN",
    "sg:tags":[
        "carpentry",
        "contractor"
    ],
    "wof:name":"Maness Woodworks",
    "wof:placetype":"venue"
},
  "geometry": {"coordinates":[-88.363952,35.697184],"type":"Point"}
}