{
  "type": "Feature",
  "properties": {
    "addr:full":"21 Ridge Ln Lawrenceburg TN 38464",
    "addr:housenumber":"21",
    "addr:postcode":"38464",
    "addr:street":"Ridge Ln",
    "iso:country":"US",
    "sg:address":"21 Ridge Ln",
    "sg:city":"Lawrenceburg",
    "sg:classifiers":[
        {
            "category":"Building & Trades",
            "subcategory":"Construction",
            "type":"Services"
        }
    ],
    "sg:phone":"+1 931 766 2253",
    "sg:postcode":"38464",
    "sg:province":"TN",
    "sg:tags":[
        "house"
    ],
    "wof:name":"Price Mobile Home Parts & Svc",
    "wof:placetype":"venue"
},
  "geometry": {"coordinates":[-87.39308200000001,35.216403],"type":"Point"}
}