{
  "type": "Feature",
  "properties": {
    "iso:country":"US",
    "sg:address":"594 Pickens Rd",
    "sg:city":"Mason",
    "sg:classifiers":[
        {
            "category":"Professional",
            "subcategory":"Management & Consulting",
            "type":"Services"
        }
    ],
    "sg:phone":"+1 901 476 7171",
    "sg:postcode":"38049",
    "sg:province":"TN",
    "sg:tags":[
        "agricultural",
        "consultant"
    ],
    "wof:name":"BFAA",
    "wof:placetype":"venue"
},
  "geometry": {"coordinates":[-89.574147,35.478024],"type":"Point"}
}