{
  "type": "Feature",
  "properties": {
    "iso:country":"US",
    "sg:address":"416 E Eh Crump Blvd",
    "sg:city":"Memphis",
    "sg:classifiers":[
        {
            "category":"Banks & Credit Unions",
            "subcategory":"Financial Services",
            "type":"Services"
        }
    ],
    "sg:phone":"+1 901 948 7407",
    "sg:postcode":"38126",
    "sg:province":"TN",
    "sg:tags":[
        "cashing",
        "check"
    ],
    "wof:name":"Check Advance/National Check Cashing",
    "wof:placetype":"venue"
},
  "geometry": {"coordinates":[-90.047527,35.124416],"type":"Point"}
}