{
  "type": "Feature",
  "properties": {
    "iso:country":"US",
    "sg:address":"3465 Austin Peay Hwy",
    "sg:city":"Memphis",
    "sg:classifiers":[
        {
            "category":"Wholesale",
            "subcategory":"Groceries",
            "type":"Manufacturing & Wholesale Goods"
        }
    ],
    "sg:phone":"+1 901 380 5550",
    "sg:postcode":"38135",
    "sg:province":"TN",
    "sg:tags":[
        "general"
    ],
    "wof:name":"Save-A-Lot",
    "wof:placetype":"venue"
},
  "geometry": {"coordinates":[-89.91069299999999,35.219623],"type":"Point"}
}