{
  "type": "Feature",
  "properties": {
    "iso:country":"US",
    "sg:address":"109 2nd Ave N",
    "sg:city":"Nashville",
    "sg:classifiers":[
        {
            "category":"Restaurant",
            "type":"Food & Drink"
        }
    ],
    "sg:phone":"+1 615 244 7900",
    "sg:postcode":"37201",
    "sg:province":"TN",
    "sg:tags":[
        "japanese"
    ],
    "sg:website":"http://www.ichibanusa.com",
    "wof:name":"Ichiban Japanese Restaurant",
    "wof:placetype":"venue"
},
  "geometry": {"coordinates":[-86.77530299999999,36.162125],"type":"Point"}
}