{
  "type": "Feature",
  "properties": {
    "iso:country":"US",
    "sg:address":"3003 Dickerson Pike",
    "sg:city":"Nashville",
    "sg:phone":"+1 615 226 6424",
    "sg:postcode":"37207",
    "sg:province":"TN",
    "sg:tags":[
        "material",
        "fixture",
        "display"
    ],
    "sg:website":"www.mmstorefixtures.com",
    "wof:name":"Murdock Mendelsohn Co Inc",
    "wof:placetype":"venue"
},
  "geometry": {"coordinates":[-86.760238,36.225536],"type":"Point"}
}