{
  "type": "Feature",
  "properties": {
    "iso:country":"US",
    "sg:address":"102 A Dr",
    "sg:city":"Madisonville",
    "sg:classifiers":[
        {
            "category":"Real Estate",
            "subcategory":"Real Estate Agent",
            "type":"Services"
        }
    ],
    "sg:phone":"+1 423 442 5701",
    "sg:postcode":"37354",
    "sg:province":"TN",
    "wof:name":"Tennessee Valley Appraisal Svc",
    "wof:placetype":"venue"
},
  "geometry": {"coordinates":[-84.303342,35.610721],"type":"Point"}
}