{
  "type": "Feature",
  "properties": {
    "addr:full":"1013 W Sullivan St Kingsport TN 37660",
    "addr:housenumber":"1013",
    "addr:postcode":"37660",
    "addr:street":"W Sullivan St",
    "iso:country":"US",
    "sg:address":"1013 W Sullivan St",
    "sg:city":"Kingsport",
    "sg:classifiers":[
        {
            "category":"Building & Trades",
            "subcategory":"Construction",
            "type":"Services"
        }
    ],
    "sg:phone":"+1 423 392 0705",
    "sg:postcode":"37660",
    "sg:province":"TN",
    "sg:tags":[
        "cabinet",
        "maker",
        "contractor"
    ],
    "wof:name":"Armstrong Cabinet & Repair",
    "wof:placetype":"venue"
},
  "geometry": {"coordinates":[-82.569033,36.556168],"type":"Point"}
}