{
  "type": "Feature",
  "properties": {
    "iso:country":"US",
    "sg:address":"6927 Wood Rd",
    "sg:city":"Corryton",
    "sg:classifiers":[
        {
            "category":"Organizations",
            "subcategory":"Religious Organization",
            "type":"Services"
        }
    ],
    "sg:phone":"+1 865 922 2716",
    "sg:postcode":"37721",
    "sg:province":"TN",
    "sg:tags":[
        "clergy"
    ],
    "wof:name":"Glenn T Kitts",
    "wof:placetype":"venue"
},
  "geometry": {"coordinates":[-83.896193,36.140238],"type":"Point"}
}