{
  "type": "Feature",
  "properties": {
    "addr:full":"1000 S Cooper St Memphis TN 38104",
    "addr:housenumber":"1000",
    "addr:postcode":"38104",
    "addr:street":"S Cooper St",
    "iso:country":"US",
    "sg:address":"1000 S Cooper St",
    "sg:city":"Memphis",
    "sg:classifiers":[
        {
            "category":"Health Services",
            "subcategory":"Clinic",
            "type":"Services"
        },
        {
            "category":"Health Services",
            "subcategory":"Health Practitioner",
            "type":"Services"
        }
    ],
    "sg:phone":"+1 901 682 8874",
    "sg:postcode":"38104",
    "sg:province":"TN",
    "sg:tags":[
        "home",
        "midwife",
        "care"
    ],
    "wof:name":"Home Birth Midwifery Service",
    "wof:placetype":"venue"
},
  "geometry": {"coordinates":[-89.99108099999999,35.118082],"type":"Point"}
}