{
  "type": "Feature",
  "properties": {
    "iso:country":"US",
    "sg:address":"1307 Long Hunter Ln",
    "sg:city":"Nashville",
    "sg:classifiers":[
        {
            "category":"Arts & Performance",
            "subcategory":"Theater",
            "type":"Entertainment"
        }
    ],
    "sg:phone":"+1 615 399 7054",
    "sg:postcode":"37217",
    "sg:province":"TN",
    "sg:tags":[
        "group"
    ],
    "wof:name":"Art Fegan Entertainment Inc",
    "wof:placetype":"venue"
},
  "geometry": {"coordinates":[-86.642786,36.09284],"type":"Point"}
}