{
  "type": "Feature",
  "properties": {
    "iso:country":"US",
    "sg:address":"561 Forest Retreat Rd",
    "sg:city":"Hendersonville",
    "sg:classifiers":[
        {
            "category":"Building & Trades",
            "subcategory":"Plumbing",
            "type":"Services"
        }
    ],
    "sg:phone":"+1 615 824 5507",
    "sg:postcode":"37075",
    "sg:province":"TN",
    "sg:tags":[
        "plumbing",
        "contractor"
    ],
    "wof:name":"Wayne Owens Plumbing",
    "wof:placetype":"venue"
},
  "geometry": {"coordinates":[-86.642585,36.333071],"type":"Point"}
}