{
  "type": "Feature",
  "properties": {
    "addr:full":"555 New Salem Rd Murfreesboro TN 37129",
    "addr:housenumber":"555",
    "addr:postcode":"37129",
    "addr:street":"New Salem Rd",
    "iso:country":"US",
    "sg:address":"555 New Salem Rd",
    "sg:city":"Murfreesboro",
    "sg:classifiers":[
        {
            "category":"Utilities",
            "subcategory":"Electric",
            "type":"Services"
        }
    ],
    "sg:phone":"+1 615 890 9762",
    "sg:postcode":"37129",
    "sg:province":"TN",
    "sg:tags":[
        "company"
    ],
    "sg:website":"www.mtemc.com",
    "wof:name":"Middle Tennessee Electric Corp",
    "wof:placetype":"venue"
},
  "geometry": {"coordinates":[-86.408168,35.842517],"type":"Point"}
}