{
  "type": "Feature",
  "properties": {
    "iso:country":"US",
    "sg:address":"302 Roscoe St",
    "sg:city":"Goodlettsville",
    "sg:classifiers":[
        {
            "category":"Building & Trades",
            "subcategory":"Plumbing",
            "type":"Services"
        }
    ],
    "sg:phone":"+1 615 855 3030",
    "sg:postcode":"37072",
    "sg:province":"TN",
    "sg:tags":[
        "conditioning",
        "contractor",
        "system",
        "air"
    ],
    "wof:name":"Alpha & Omega Heating & Air",
    "wof:placetype":"venue"
},
  "geometry": {"coordinates":[-86.708099,36.31728],"type":"Point"}
}