{
  "type": "Feature",
  "properties": {
    "iso:country":"US",
    "sg:address":"605 8th Ave S",
    "sg:city":"Nashville",
    "sg:classifiers":[
        {
            "category":"Restaurant",
            "type":"Food & Drink"
        }
    ],
    "sg:phone":"+1 615 256 4455",
    "sg:postcode":"37204",
    "sg:province":"TN",
    "sg:tags":[
        "eating"
    ],
    "wof:name":"Arnold's Country Kitchen",
    "wof:placetype":"venue"
},
  "geometry": {"coordinates":[-86.77932199999999,36.151316],"type":"Point"}
}