{
  "type": "Feature",
  "properties": {
    "addr:full":"4495 Hunters Point Pike Lebanon TN 37087",
    "addr:housenumber":"4495",
    "addr:postcode":"37087",
    "addr:street":"Hunters Point Pike",
    "iso:country":"US",
    "sg:address":"4495 Hunters Point Pike",
    "sg:city":"Lebanon",
    "sg:classifiers":[
        {
            "category":"Retail",
            "subcategory":"Auto Repair",
            "type":"Services"
        }
    ],
    "sg:phone":"+1 615 822 8677",
    "sg:postcode":"37087",
    "sg:province":"TN",
    "sg:tags":[
        "body"
    ],
    "wof:name":"Chuck Bennett Upholstery",
    "wof:placetype":"venue"
},
  "geometry": {"coordinates":[-86.278266,36.274309],"type":"Point"}
}