{
  "type": "Feature",
  "properties": {
    "iso:country":"US",
    "sg:address":"706 E Lake Ave",
    "sg:city":"Celina",
    "sg:classifiers":[
        {
            "category":"Professional",
            "type":"Services"
        },
        {
            "category":"Retail",
            "subcategory":"Auto Repair",
            "type":"Services"
        }
    ],
    "sg:phone":"+1 931 243 2244",
    "sg:postcode":"38551",
    "sg:province":"TN",
    "sg:tags":[
        "repairing",
        "automobile",
        "establishment"
    ],
    "wof:name":"Ferrell's Autoworks Automo0",
    "wof:placetype":"venue"
},
  "geometry": {"coordinates":[-85.496223,36.550093],"type":"Point"}
}