{
  "type": "Feature",
  "properties": {
    "addr:full":"269 Delta Rd Memphis TN 38109",
    "addr:housenumber":"269",
    "addr:postcode":"38109",
    "addr:street":"Delta Rd",
    "iso:country":"US",
    "sg:address":"269 Delta Rd",
    "sg:city":"Memphis",
    "sg:classifiers":[
        {
            "category":"Real Estate",
            "subcategory":"Real Estate Services",
            "type":"Services"
        },
        {
            "category":"Real Estate",
            "subcategory":"Real Estate Agent",
            "type":"Services"
        }
    ],
    "sg:phone":"+1 901 789 5057",
    "sg:postcode":"38109",
    "sg:province":"TN",
    "sg:tags":[
        "buyer",
        "broker"
    ],
    "wof:name":"Reed & Assoc",
    "wof:placetype":"venue"
},
  "geometry": {"coordinates":[-90.073151,35.018162],"type":"Point"}
}