{
  "type": "Feature",
  "properties": {
    "addr:full":"5035 US Hwy 70 E Brownsville TN 38012",
    "addr:housenumber":"5035",
    "addr:postcode":"38012",
    "addr:street":"Us Hwy 70 E",
    "iso:country":"US",
    "sg:address":"5035 US Hwy 70 E",
    "sg:city":"Brownsville",
    "sg:classifiers":[
        {
            "category":"Building & Trades",
            "subcategory":"Construction",
            "type":"Services"
        }
    ],
    "sg:phone":"+1 731 772 5390",
    "sg:postcode":"38012",
    "sg:province":"TN",
    "sg:tags":[
        "house"
    ],
    "wof:name":"H F Construction",
    "wof:placetype":"venue"
},
  "geometry": {"coordinates":[-89.17322900000001,35.591167],"type":"Point"}
}