{
  "type": "Feature",
  "properties": {
    "iso:country":"US",
    "sg:address":"3872 Elvis Presley Blvd",
    "sg:city":"Memphis",
    "sg:classifiers":[
        {
            "category":"Social Services",
            "subcategory":"Child Care",
            "type":"Services"
        }
    ],
    "sg:phone":"+1 901 396 2354",
    "sg:postcode":"38116",
    "sg:province":"TN",
    "wof:name":"Precious Joy Childcare Ctr",
    "wof:placetype":"venue"
},
  "geometry": {"coordinates":[-90.02503400000001,35.043704],"type":"Point"}
}