{
  "type": "Feature",
  "properties": {
    "iso:country":"US",
    "sg:address":"390 River Rock Ln",
    "sg:city":"Midway",
    "sg:phone":"+1 423 235 2652",
    "sg:postcode":"37809",
    "sg:province":"TN",
    "sg:tags":[
        "farm",
        "tobacco"
    ],
    "wof:name":"Shelton Farm",
    "wof:placetype":"venue"
},
  "geometry": {"coordinates":[-83.091826,36.110887],"type":"Point"}
}