{
  "type": "Feature",
  "properties": {
    "iso:country":"US",
    "sg:address":"189 Cottonwood Dr",
    "sg:city":"Franklin",
    "sg:classifiers":[
        {
            "category":"Wholesale",
            "subcategory":"Machinery & Supplies",
            "type":"Manufacturing & Wholesale Goods"
        }
    ],
    "sg:phone":"+1 615 599 3100",
    "sg:postcode":"37069",
    "sg:province":"TN",
    "sg:tags":[
        "equipment",
        "industrial"
    ],
    "wof:name":"Plageman Associates",
    "wof:placetype":"venue"
},
  "geometry": {"coordinates":[-86.910577,35.970721],"type":"Point"}
}