{
  "type": "Feature",
  "properties": {
    "iso:country":"US",
    "sg:address":"10267 Kingston Pike",
    "sg:city":"Knoxville",
    "sg:classifiers":[
        {
            "category":"Professional",
            "subcategory":"Lawyer & Legal Services",
            "type":"Services"
        }
    ],
    "sg:phone":"+1 865 694 7999",
    "sg:postcode":"37922",
    "sg:province":"TN",
    "sg:tags":[
        "attorney"
    ],
    "wof:name":"Klein & Assoc Attorneys At Law",
    "wof:placetype":"venue"
},
  "geometry": {"coordinates":[-84.124973,35.900792],"type":"Point"}
}