{
  "type": "Feature",
  "properties": {
    "iso:country":"US",
    "sg:address":"6301 Lonas Dr",
    "sg:city":"Knoxville",
    "sg:classifiers":[
        {
            "category":"Food & Beverages",
            "subcategory":"Groceries & Convenience Stores",
            "type":"Retail Goods"
        }
    ],
    "sg:phone":"+1 865 584 9814",
    "sg:postcode":"37909",
    "sg:province":"TN",
    "sg:tags":[
        "grocer"
    ],
    "wof:name":"Weigel's Farm Store",
    "wof:placetype":"venue"
},
  "geometry": {"coordinates":[-84.01108499999999,35.941362],"type":"Point"}
}