{
  "type": "Feature",
  "properties": {
    "addr:full":"244 Crabtree Rd Crossville TN 38571",
    "addr:housenumber":"244",
    "addr:postcode":"38571",
    "addr:street":"Crabtree Rd",
    "iso:country":"US",
    "sg:address":"244 Crabtree Rd",
    "sg:city":"Crossville",
    "sg:classifiers":[
        {
            "category":"Organizations",
            "subcategory":"Religious Organization",
            "type":"Services"
        }
    ],
    "sg:phone":"+1 931 456 8684",
    "sg:postcode":"38571",
    "sg:province":"TN",
    "wof:name":"Love Free Will Baptist Church",
    "wof:placetype":"venue"
},
  "geometry": {"coordinates":[-85.01624099999999,35.985161],"type":"Point"}
}