{
  "type": "Feature",
  "properties": {
    "iso:country":"US",
    "sg:address":"2156 N Highland Ave",
    "sg:city":"Jackson",
    "sg:classifiers":[
        {
            "category":"Professional",
            "subcategory":"Lawyer & Legal Services",
            "type":"Services"
        }
    ],
    "sg:phone":"+1 731 664 7529",
    "sg:postcode":"38305",
    "sg:province":"TN",
    "sg:tags":[
        "attorney"
    ],
    "wof:name":"Smith Law Firm",
    "wof:placetype":"venue"
},
  "geometry": {"coordinates":[-88.828226,35.660913],"type":"Point"}
}