{
  "type": "Feature",
  "properties": {
    "iso:country":"US",
    "sg:address":"3140 E Andrew Johnson Hwy",
    "sg:city":"Greeneville",
    "sg:classifiers":[
        {
            "category":"Cafe",
            "type":"Food & Drink"
        }
    ],
    "sg:menulink":"http://www.allmenus.com/tn/greeneville/146715-fatz-cafe/menu/",
    "sg:phone":"+1 423 787 9090",
    "sg:postcode":"37745",
    "sg:province":"TN",
    "sg:tags":[
        "american"
    ],
    "wof:name":"Fatz Cafe",
    "wof:placetype":"venue"
},
  "geometry": {"coordinates":[-82.76878600000001,36.183443],"type":"Point"}
}