{
  "type": "Feature",
  "properties": {
    "addr:full":"2646 Byington Solway Rd Knoxville TN 37931",
    "addr:housenumber":"2646",
    "addr:postcode":"37931",
    "addr:street":"Byington Solway Rd",
    "iso:country":"US",
    "sg:address":"2646 Byington Solway Rd",
    "sg:city":"Knoxville",
    "sg:classifiers":[
        {
            "category":"Home & Garden",
            "subcategory":"Building Materials",
            "type":"Retail Goods"
        }
    ],
    "sg:phone":"+1 865 691 4152",
    "sg:postcode":"37931",
    "sg:province":"TN",
    "wof:name":"C-K Supply",
    "wof:placetype":"venue"
},
  "geometry": {"coordinates":[-84.12406900000001,35.968534],"type":"Point"}
}