{
  "type": "Feature",
  "properties": {
    "addr:full":"7051 Wikle Rd W Brentwood TN 37027",
    "addr:postcode":"7051;37027",
    "addr:street":"Wikle Rd W",
    "iso:country":"US",
    "sg:address":"7051 Wikle Rd W",
    "sg:city":"Brentwood",
    "sg:classifiers":[
        {
            "category":"Recreation",
            "type":"Entertainment"
        }
    ],
    "sg:phone":"+1 615 373 3996",
    "sg:postcode":"37027",
    "sg:province":"TN",
    "wof:name":"New Moon Stables",
    "wof:placetype":"venue"
},
  "geometry": {"coordinates":[-86.80342,35.984298],"type":"Point"}
}