{
  "type": "Feature",
  "properties": {
    "addr:full":"168 W Broad St Cookeville TN 38501",
    "addr:housenumber":"168",
    "addr:postcode":"38501",
    "addr:street":"W Broad St",
    "iso:country":"US",
    "sg:address":"168 W Broad St",
    "sg:city":"Cookeville",
    "sg:classifiers":[
        {
            "category":"Personal",
            "subcategory":"Beauty Salon",
            "type":"Services"
        }
    ],
    "sg:phone":"+1 931 528 6318",
    "sg:postcode":"38501",
    "sg:province":"TN",
    "sg:tags":[
        "shop"
    ],
    "wof:name":"Xanadu Hair Creations",
    "wof:placetype":"venue"
},
  "geometry": {"coordinates":[-85.50961700000001,36.16463],"type":"Point"}
}