{
  "type": "Feature",
  "properties": {
    "iso:country":"US",
    "sg:address":"220 E End Dr",
    "sg:city":"Savannah",
    "sg:classifiers":[
        {
            "category":"Manufacturing",
            "subcategory":"Tools & Machinery",
            "type":"Manufacturing & Wholesale Goods"
        }
    ],
    "sg:phone":"+1 731 925 6752",
    "sg:postcode":"38372",
    "sg:province":"TN",
    "sg:tags":[
        "machine",
        "shop"
    ],
    "wof:name":"Garner Tool & Die",
    "wof:placetype":"venue"
},
  "geometry": {"coordinates":[-88.218884,35.227588],"type":"Point"}
}