{
  "type": "Feature",
  "properties": {
    "iso:country":"US",
    "sg:address":"3580 N Mount Juliet Rd",
    "sg:city":"Mt Juliet",
    "sg:classifiers":[
        {
            "category":"Professional",
            "type":"Services"
        }
    ],
    "sg:phone":"+1 615 758 4888",
    "sg:postcode":"37122",
    "sg:province":"TN",
    "sg:tags":[
        "establishment"
    ],
    "wof:name":"Lyttle Fox Therapy",
    "wof:placetype":"venue"
},
  "geometry": {"coordinates":[-86.515162,36.220163],"type":"Point"}
}