{
  "type": "Feature",
  "properties": {
    "addr:full":"4710 Nolensville Pike Nashville TN 37211",
    "addr:housenumber":"4710",
    "addr:postcode":"37211",
    "addr:street":"Nolensville Pike",
    "iso:country":"US",
    "sg:address":"4710 Nolensville Pike",
    "sg:city":"Nashville",
    "sg:classifiers":[
        {
            "category":"Retail",
            "subcategory":"Repair Shop",
            "type":"Services"
        }
    ],
    "sg:phone":"+1 615 781 6148",
    "sg:postcode":"37211",
    "sg:province":"TN",
    "sg:tags":[
        "engine",
        "building"
    ],
    "wof:name":"Performance Engineering",
    "wof:placetype":"venue"
},
  "geometry": {"coordinates":[-86.717996,36.066863],"type":"Point"}
}