{
  "type": "Feature",
  "properties": {
    "iso:country":"US",
    "sg:address":"7400 Sawyer Ln",
    "sg:city":"Knoxville",
    "sg:classifiers":[
        {
            "category":"Restaurant",
            "type":"Food & Drink"
        }
    ],
    "sg:phone":"+1 865 932 0636",
    "sg:postcode":"37924",
    "sg:province":"TN",
    "sg:tags":[
        "eating"
    ],
    "sg:website":"www.outback.com",
    "wof:name":"Outback Steakhouse",
    "wof:placetype":"venue"
},
  "geometry": {"coordinates":[-83.771107,36.004712],"type":"Point"}
}