{
  "type": "Feature",
  "properties": {
    "addr:full":"99 N Main St Memphis TN 38103",
    "addr:housenumber":"99",
    "addr:postcode":"38103",
    "addr:street":"N Main St",
    "iso:country":"US",
    "sg:address":"99 N Main St",
    "sg:city":"Memphis",
    "sg:classifiers":[
        {
            "category":"Real Estate",
            "subcategory":"Real Estate Services",
            "type":"Services"
        }
    ],
    "sg:phone":"+1 866 308 3041",
    "sg:postcode":"38103",
    "sg:province":"TN",
    "sg:tags":[
        "apartment",
        "management",
        "rental",
        "finder"
    ],
    "wof:name":"The Renaissance",
    "wof:placetype":"venue"
},
  "geometry": {"coordinates":[-90.051807,35.147678],"type":"Point"}
}