{
  "type": "Feature",
  "properties": {
    "addr:full":"4791 Bolen Huse Rd Memphis TN 38128",
    "addr:housenumber":"4791",
    "addr:postcode":"38128",
    "addr:street":"Bolen Huse Rd",
    "iso:country":"US",
    "sg:address":"4791 Bolen Huse Rd",
    "sg:city":"Memphis",
    "sg:classifiers":[
        {
            "category":"Government",
            "subcategory":"Office",
            "type":"Public Place"
        }
    ],
    "sg:phone":"+1 901 385 1419",
    "sg:postcode":"38128",
    "sg:province":"TN",
    "sg:tags":[
        "township",
        "government-city",
        "village"
    ],
    "wof:name":"City Of Memphis",
    "wof:placetype":"venue"
},
  "geometry": {"coordinates":[-89.909536,35.261586],"type":"Point"}
}