{
  "type": "Feature",
  "properties": {
    "iso:country":"US",
    "sg:address":"3155 Given Ave",
    "sg:city":"Memphis",
    "sg:classifiers":[
        {
            "category":"Professional",
            "subcategory":"Computer Services",
            "type":"Services"
        },
        {
            "category":"Manufacturing",
            "subcategory":"Printing",
            "type":"Manufacturing & Wholesale Goods"
        }
    ],
    "sg:phone":"+1 901 949 6969",
    "sg:postcode":"38112",
    "sg:province":"TN",
    "sg:tags":[
        "multimedia",
        "datum"
    ],
    "wof:name":"South Coast Multimedia",
    "wof:placetype":"venue"
},
  "geometry": {"coordinates":[-89.953481,35.157365],"type":"Point"}
}