{
  "type": "Feature",
  "properties": {
    "addr:full":"2018 Black Valley Rd Sneedville TN 37869",
    "addr:housenumber":"2018",
    "addr:postcode":"37869",
    "addr:street":"Black Valley Rd",
    "iso:country":"US",
    "sg:address":"2018 Black Valley Rd",
    "sg:city":"Sneedville",
    "sg:classifiers":[
        {
            "category":"Personal",
            "subcategory":"Beauty Salon",
            "type":"Services"
        }
    ],
    "sg:phone":"+1 423 733 2356",
    "sg:postcode":"37869",
    "sg:province":"TN",
    "wof:name":"Deannas Hair Salon",
    "wof:placetype":"venue"
},
  "geometry": {"coordinates":[-83.339026,36.50906],"type":"Point"}
}