{
  "type": "Feature",
  "properties": {
    "iso:country":"US",
    "sg:address":"208 3rd Ave N",
    "sg:city":"Nashville",
    "sg:classifiers":[
        {
            "category":"Professional",
            "subcategory":"Lawyer & Legal Services",
            "type":"Services"
        }
    ],
    "sg:phone":"+1 615 227 1213",
    "sg:postcode":"37201",
    "sg:province":"TN",
    "sg:tags":[
        "attorney"
    ],
    "wof:name":"Robert Greene Attorney",
    "wof:placetype":"venue"
},
  "geometry": {"coordinates":[-86.77714899999999,36.163452],"type":"Point"}
}