{
  "type": "Feature",
  "properties": {
    "addr:full":"5000 American Way Memphis TN 38118",
    "addr:housenumber":"5000",
    "addr:postcode":"38118",
    "addr:street":"American Way",
    "iso:country":"US",
    "sg:address":"5000 American Way",
    "sg:city":"Memphis",
    "sg:classifiers":[
        {
            "category":"Utilities",
            "subcategory":"Telephone",
            "type":"Services"
        }
    ],
    "sg:phone":"+1 770 604 6208",
    "sg:postcode":"38118",
    "sg:province":"TN",
    "sg:tags":[
        "communications"
    ],
    "wof:name":"Cingular Wireless",
    "wof:placetype":"venue"
},
  "geometry": {"coordinates":[-89.89196699999999,35.076782],"type":"Point"}
}