{
  "type": "Feature",
  "properties": {
    "iso:country":"US",
    "sg:address":"1251 Thrasher Pike",
    "sg:city":"Hixson",
    "sg:classifiers":[
        {
            "category":"Wholesale",
            "subcategory":"Non-durable Goods",
            "type":"Manufacturing & Wholesale Goods"
        }
    ],
    "sg:phone":"+1 423 843 0270",
    "sg:postcode":"37343",
    "sg:province":"TN",
    "sg:tags":[
        "merchandise",
        "general"
    ],
    "wof:name":"Hixson Wholesale Products",
    "wof:placetype":"venue"
},
  "geometry": {"coordinates":[-85.210876,35.203659],"type":"Point"}
}