{
  "type": "Feature",
  "properties": {
    "iso:country":"US",
    "sg:address":"13230 Hwy 51 S",
    "sg:city":"Atoka",
    "sg:classifiers":[
        {
            "category":"Shopping",
            "type":"Retail Goods"
        }
    ],
    "sg:phone":"+1 901 837 3300",
    "sg:postcode":"38004",
    "sg:province":"TN",
    "sg:tags":[
        "picture",
        "frame"
    ],
    "wof:name":"Friends Custom Frames & Gifts",
    "wof:placetype":"venue"
},
  "geometry": {"coordinates":[-89.811575,35.426589],"type":"Point"}
}