{
  "type": "Feature",
  "properties": {
    "addr:full":"145 Lyle Ln Nashville TN 37210",
    "addr:housenumber":"145",
    "addr:postcode":"37210",
    "addr:street":"Lyle Ln",
    "iso:country":"US",
    "sg:address":"145 Lyle Ln",
    "sg:city":"Nashville",
    "sg:classifiers":[
        {
            "category":"Home & Garden",
            "subcategory":"Home Furnishings",
            "type":"Retail Goods"
        },
        {
            "category":"Home & Garden",
            "subcategory":"Furniture",
            "type":"Retail Goods"
        }
    ],
    "sg:phone":"+1 615 256 6865",
    "sg:postcode":"37210",
    "sg:province":"TN",
    "sg:tags":[
        "equipment-household",
        "refacing",
        "resurfacing",
        "cabinet",
        "cabinets-refinishing",
        "kitchen"
    ],
    "wof:name":"Supreme Kitchens Inc",
    "wof:placetype":"venue"
},
  "geometry": {"coordinates":[-86.737161,36.127643],"type":"Point"}
}