{
  "type": "Feature",
  "properties": {
    "addr:full":"309 Elm Hill Dr Clinton TN 37716",
    "addr:housenumber":"309",
    "addr:postcode":"37716",
    "addr:street":"Elm Hill Dr",
    "iso:country":"US",
    "sg:address":"309 Elm Hill Dr",
    "sg:city":"Clinton",
    "sg:classifiers":[
        {
            "category":"Professional",
            "subcategory":"Engineering",
            "type":"Services"
        }
    ],
    "sg:phone":"+1 865 457 6335",
    "sg:postcode":"37716",
    "sg:province":"TN",
    "sg:tags":[
        "consultant",
        "management"
    ],
    "wof:name":"Creative Concepts",
    "wof:placetype":"venue"
},
  "geometry": {"coordinates":[-84.170565,36.068593],"type":"Point"}
}