{
  "type": "Feature",
  "properties": {
    "iso:country":"US",
    "sg:address":"6329 Sam Smith Rd",
    "sg:city":"Birchwood",
    "sg:classifiers":[
        {
            "category":"Professional",
            "type":"Services"
        }
    ],
    "sg:phone":"+1 423 961 2423",
    "sg:postcode":"37308",
    "sg:province":"TN",
    "wof:name":"Vincent E Campbell",
    "wof:placetype":"venue"
},
  "geometry": {"coordinates":[-84.99316,35.332225],"type":"Point"}
}