{
  "type": "Feature",
  "properties": {
    "iso:country":"US",
    "sg:address":"114 Burrum Dr",
    "sg:city":"Shelbyville",
    "sg:classifiers":[
        {
            "category":"Professional",
            "subcategory":"Lawyer & Legal Services",
            "type":"Services"
        }
    ],
    "sg:phone":"+1 931 684 7115",
    "sg:postcode":"37160",
    "sg:province":"TN",
    "sg:tags":[
        "attorney"
    ],
    "wof:name":"James R Nance",
    "wof:placetype":"venue"
},
  "geometry": {"coordinates":[-86.471688,35.470982],"type":"Point"}
}