{
  "type": "Feature",
  "properties": {
    "iso:country":"US",
    "sg:address":"126 Remington Dr",
    "sg:city":"Lascassas",
    "sg:classifiers":[
        {
            "category":"Manufacturing",
            "subcategory":"Toys & Sporting Goods",
            "type":"Manufacturing & Wholesale Goods"
        }
    ],
    "sg:phone":"+1 615 849 9819",
    "sg:postcode":"37085",
    "sg:province":"TN",
    "sg:tags":[
        "mfg"
    ],
    "wof:name":"Pucketts Sports Connection",
    "wof:placetype":"venue"
},
  "geometry": {"coordinates":[-86.305257,35.932676],"type":"Point"}
}