{
  "type": "Feature",
  "properties": {
    "iso:country":"US",
    "sg:address":"40 White Bridge Pike",
    "sg:city":"Nashville",
    "sg:classifiers":[
        {
            "category":"Restaurant",
            "type":"Food & Drink"
        }
    ],
    "sg:phone":"+1 615 356 6600",
    "sg:postcode":"37205",
    "sg:province":"TN",
    "sg:tags":[
        "japanese"
    ],
    "wof:name":"Ben Kays Japanese Restaurant",
    "wof:placetype":"venue"
},
  "geometry": {"coordinates":[-86.85328800000001,36.12874],"type":"Point"}
}