{
  "type": "Feature",
  "properties": {
    "iso:country":"US",
    "sg:address":"5567 Southern Winds Dr",
    "sg:city":"Arlington",
    "sg:classifiers":[
        {
            "category":"Professional",
            "subcategory":"Management & Consulting",
            "type":"Services"
        }
    ],
    "sg:phone":"+1 901 867 0659",
    "sg:postcode":"38002",
    "sg:province":"TN",
    "sg:tags":[
        "consultant"
    ],
    "wof:name":"World Class Consulting Inc",
    "wof:placetype":"venue"
},
  "geometry": {"coordinates":[-89.652675,35.278069],"type":"Point"}
}