{
  "type": "Feature",
  "properties": {
    "addr:full":"985 Oak Ridge Tpke Oak Ridge TN 37830",
    "addr:housenumber":"985",
    "addr:postcode":"37830",
    "addr:street":"Oak Ridge Tpke",
    "iso:country":"US",
    "sg:address":"985 Oak Ridge Tpke",
    "sg:city":"Oak Ridge",
    "sg:classifiers":[
        {
            "category":"Health Services",
            "subcategory":"Podiatrist",
            "type":"Services"
        }
    ],
    "sg:phone":"+1 865 482 3441",
    "sg:postcode":"37830",
    "sg:province":"TN",
    "wof:name":"Advanced Foot Care Tennessee",
    "wof:placetype":"venue"
},
  "geometry": {"coordinates":[-84.243531,36.023665],"type":"Point"}
}