{
  "type": "Feature",
  "properties": {
    "addr:full":"315 Cypress Glen Dr Mount Juliet TN 37122",
    "addr:housenumber":"315",
    "addr:postcode":"37122",
    "addr:street":"Cypress Glen Dr",
    "iso:country":"US",
    "sg:address":"315 Cypress Glen Dr",
    "sg:city":"Mount Juliet",
    "sg:classifiers":[
        {
            "category":"Organizations",
            "subcategory":"Professional Association",
            "type":"Services"
        }
    ],
    "sg:phone":"+1 615 758 0913",
    "sg:postcode":"37122",
    "sg:province":"TN",
    "sg:tags":[
        "mail",
        "business",
        "house"
    ],
    "wof:name":"Elvis Presley Memorial Soc",
    "wof:placetype":"venue"
},
  "geometry": {"coordinates":[-86.50539000000001,36.227889],"type":"Point"}
}