{
  "type": "Feature",
  "properties": {
    "addr:full":"1342 Hardwood Trl Cordova TN 38016",
    "addr:housenumber":"1342",
    "addr:postcode":"38016",
    "addr:street":"Hardwood Trl",
    "iso:country":"US",
    "sg:address":"1342 Hardwood Trl",
    "sg:city":"Cordova",
    "sg:classifiers":[
        {
            "category":"Sports & Exercise",
            "subcategory":"Race Track",
            "type":"Entertainment"
        }
    ],
    "sg:phone":"+1 901 754 7088",
    "sg:postcode":"38016",
    "sg:province":"TN",
    "sg:tags":[
        "racing",
        "operation",
        "including"
    ],
    "wof:name":"Tri Star Racing Inc",
    "wof:placetype":"venue"
},
  "geometry": {"coordinates":[-89.78925700000001,35.162132],"type":"Point"}
}