{
  "type": "Feature",
  "properties": {
    "iso:country":"US",
    "sg:address":"113 N 1st St",
    "sg:city":"Pulaski",
    "sg:classifiers":[
        {
            "category":"Real Estate",
            "subcategory":"Real Estate Agent",
            "type":"Services"
        }
    ],
    "sg:phone":"+1 931 363 2644",
    "sg:postcode":"38478",
    "sg:province":"TN",
    "sg:website":"www.frg1.com",
    "wof:name":"First Realty Group",
    "wof:placetype":"venue"
},
  "geometry": {"coordinates":[-87.030475,35.199933],"type":"Point"}
}