{
  "type": "Feature",
  "properties": {
    "iso:country":"US",
    "sg:address":"225 Co Rd 401",
    "sg:city":"Madisonville",
    "sg:classifiers":[
        {
            "category":"Utilities",
            "subcategory":"Refuse",
            "type":"Services"
        }
    ],
    "sg:phone":"+1 423 744 9368",
    "sg:postcode":"37354",
    "sg:province":"TN",
    "sg:tags":[
        "garbage",
        "collection"
    ],
    "wof:name":"K & N Disposal",
    "wof:placetype":"venue"
},
  "geometry": {"coordinates":[-84.485731,35.49912],"type":"Point"}
}