{
  "type": "Feature",
  "properties": {
    "iso:country":"US",
    "sg:address":"1432 Pig Path Rd",
    "sg:city":"Rockwood",
    "sg:classifiers":[
        {
            "category":"Freight",
            "type":"Transportation"
        }
    ],
    "sg:phone":"+1 865 354 4646",
    "sg:postcode":"37854",
    "sg:province":"TN",
    "sg:tags":[
        "distance",
        "long",
        "trucking"
    ],
    "wof:name":"Jr Bells Trucking",
    "wof:placetype":"venue"
},
  "geometry": {"coordinates":[-84.745243,35.88895],"type":"Point"}
}