{
  "type": "Feature",
  "properties": {
    "iso:country":"US",
    "sg:address":"1989 Saint John Ave",
    "sg:city":"Dyersburg",
    "sg:classifiers":[
        {
            "category":"Retail",
            "subcategory":"Auto Repair",
            "type":"Services"
        }
    ],
    "sg:phone":"+1 731 285 8028",
    "sg:postcode":"38024",
    "sg:province":"TN",
    "sg:tags":[
        "automotive",
        "general"
    ],
    "wof:name":"J L Truck Trailer Repair Inc",
    "wof:placetype":"venue"
},
  "geometry": {"coordinates":[-89.361165,36.054274],"type":"Point"}
}