{
  "type": "Feature",
  "properties": {
    "addr:full":"5560 Pleasant View Rd Memphis TN 38134",
    "addr:housenumber":"5560",
    "addr:postcode":"38134",
    "addr:street":"Pleasant View Rd",
    "iso:country":"US",
    "sg:address":"5560 Pleasant View Rd",
    "sg:city":"Memphis",
    "sg:classifiers":[
        {
            "category":"Professional",
            "subcategory":"Engineering",
            "type":"Services"
        }
    ],
    "sg:phone":"+1 901 388 4466",
    "sg:postcode":"38134",
    "sg:province":"TN",
    "sg:tags":[
        "contract"
    ],
    "wof:name":"M A P S",
    "wof:placetype":"venue"
},
  "geometry": {"coordinates":[-89.874482,35.173431],"type":"Point"}
}