{
  "type": "Feature",
  "properties": {
    "iso:country":"US",
    "sg:address":"202 N Palisades Dr",
    "sg:city":"Signal Mountain",
    "sg:classifiers":[
        {
            "category":"Restaurant",
            "type":"Food & Drink"
        }
    ],
    "sg:phone":"+1 423 886 7476",
    "sg:postcode":"37377",
    "sg:province":"TN",
    "sg:tags":[
        "eating"
    ],
    "wof:name":"Suck Creek Country Club",
    "wof:placetype":"venue"
},
  "geometry": {"coordinates":[-85.340997,35.114396],"type":"Point"}
}