{
  "type": "Feature",
  "properties": {
    "iso:country":"US",
    "sg:address":"2831 Dogwood Pl",
    "sg:city":"Nashville",
    "sg:classifiers":[
        {
            "category":"Shopping",
            "subcategory":"Musical Instruments",
            "type":"Retail Goods"
        }
    ],
    "sg:phone":"+1 615 269 8682",
    "sg:postcode":"37204",
    "sg:province":"TN",
    "sg:tags":[
        "motion",
        "production"
    ],
    "wof:name":"Songs For The Planet Inc",
    "wof:placetype":"venue"
},
  "geometry": {"coordinates":[-86.764762,36.113812],"type":"Point"}
}