{
  "type": "Feature",
  "properties": {
    "iso:country":"US",
    "sg:address":"352 Gimlet Rd",
    "sg:city":"Fayetteville",
    "sg:classifiers":[
        {
            "category":"Organizations",
            "subcategory":"Religious Organization",
            "type":"Services"
        }
    ],
    "sg:phone":"+1 931 433 8417",
    "sg:postcode":"37334",
    "sg:province":"TN",
    "sg:tags":[
        "church"
    ],
    "wof:name":"Stony Point Church Of Christ",
    "wof:placetype":"venue"
},
  "geometry": {"coordinates":[-86.500477,35.268269],"type":"Point"}
}