{
  "type": "Feature",
  "properties": {
    "addr:full":"10319 Cogdill Rd Knoxville TN 37932",
    "addr:postcode":"10319;37932",
    "addr:street":"Cogdill Rd",
    "iso:country":"US",
    "sg:address":"10319 Cogdill Rd",
    "sg:city":"Knoxville",
    "sg:classifiers":[
        {
            "category":"Building & Trades",
            "subcategory":"Construction",
            "type":"Services"
        }
    ],
    "sg:phone":"+1 865 966 7311",
    "sg:postcode":"37932",
    "sg:province":"TN",
    "sg:tags":[
        "general",
        "contractor"
    ],
    "wof:name":"Baseline Sports Construction",
    "wof:placetype":"venue"
},
  "geometry": {"coordinates":[-84.130346,35.911933],"type":"Point"}
}