{
  "type": "Feature",
  "properties": {
    "addr:full":"1350 Murfreesboro Pike Nashville TN 37217",
    "addr:housenumber":"1350",
    "addr:postcode":"37217",
    "addr:street":"Murfreesboro Pike",
    "iso:country":"US",
    "sg:address":"1350 Murfreesboro Pike",
    "sg:city":"Nashville",
    "sg:classifiers":[
        {
            "category":"Manufacturing",
            "subcategory":"Printing",
            "type":"Manufacturing & Wholesale Goods"
        }
    ],
    "sg:phone":"+1 615 843 1627",
    "sg:postcode":"37217",
    "sg:province":"TN",
    "sg:tags":[
        "printer",
        "form"
    ],
    "wof:name":"Tennessee Printing & Forms",
    "wof:placetype":"venue"
},
  "geometry": {"coordinates":[-86.694517,36.115296],"type":"Point"}
}