{
  "type": "Feature",
  "properties": {
    "iso:country":"US",
    "sg:address":"108 Memorial Dr",
    "sg:city":"Goodlettsville",
    "sg:classifiers":[
        {
            "category":"Organizations",
            "subcategory":"Community Association",
            "type":"Services"
        }
    ],
    "sg:phone":"+1 615 859 2214",
    "sg:postcode":"37072",
    "sg:province":"TN",
    "wof:name":"Goodlettsville Masonic Lodge",
    "wof:placetype":"venue"
},
  "geometry": {"coordinates":[-86.71320799999999,36.321152],"type":"Point"}
}