{
  "type": "Feature",
  "properties": {
    "iso:country":"US",
    "sg:address":"2122 N Locust Ave",
    "sg:city":"Lawrenceburg",
    "sg:classifiers":[
        {
            "category":"Autos & Motor Vehicles",
            "subcategory":"Automobile Sales",
            "type":"Retail Goods"
        }
    ],
    "sg:phone":"+1 931 762 2299",
    "sg:postcode":"38464",
    "sg:province":"TN",
    "sg:tags":[
        "car",
        "dealer"
    ],
    "sg:website":"www.heritageautomotivecenter.com",
    "wof:name":"Heritage Automotive Ctr Inc",
    "wof:placetype":"venue"
},
  "geometry": {"coordinates":[-87.320537,35.269793],"type":"Point"}
}