{
  "type": "Feature",
  "properties": {
    "iso:country":"US",
    "sg:address":"45 Reeder Ave",
    "sg:city":"Munford",
    "sg:classifiers":[
        {
            "category":"Restaurant",
            "type":"Food & Drink"
        }
    ],
    "sg:phone":"+1 901 837 0668",
    "sg:postcode":"38058",
    "sg:province":"TN",
    "sg:tags":[
        "cafe"
    ],
    "wof:name":"Cafe On The Corner",
    "wof:placetype":"venue"
},
  "geometry": {"coordinates":[-89.811059,35.454879],"type":"Point"}
}