{
  "type": "Feature",
  "properties": {
    "addr:full":"2878 Bartlett Rd Memphis TN 38134",
    "addr:housenumber":"2878",
    "addr:postcode":"38134",
    "addr:street":"Bartlett Rd",
    "iso:country":"US",
    "sg:address":"2878 Bartlett Rd",
    "sg:city":"Memphis",
    "sg:classifiers":[
        {
            "category":"Retail",
            "subcategory":"Auto Repair",
            "type":"Services"
        }
    ],
    "sg:phone":"+1 901 386 4755",
    "sg:postcode":"38134",
    "sg:province":"TN",
    "sg:tags":[
        "engines-rebuild",
        "exchange",
        "automobile",
        "brake",
        "equipment-service",
        "diagnostic",
        "air conditioning"
    ],
    "sg:website":"http://www.wggarage.com",
    "wof:name":"Warr & Geurin Garage",
    "wof:placetype":"venue"
},
  "geometry": {"coordinates":[-89.868551,35.203325],"type":"Point"}
}