{
  "type": "Feature",
  "properties": {
    "iso:country":"US",
    "sg:address":"474 S Main St",
    "sg:city":"Memphis",
    "sg:classifiers":[
        {
            "category":"Government",
            "subcategory":"Office",
            "type":"Public Place"
        }
    ],
    "sg:phone":"+1 901 527 1400",
    "sg:postcode":"38103",
    "sg:province":"TN",
    "sg:tags":[
        "township",
        "government-city",
        "village"
    ],
    "sg:website":"http://www.memphislibrary.org",
    "wof:name":"General Services Dept",
    "wof:placetype":"venue"
},
  "geometry": {"coordinates":[-90.058907,35.134499],"type":"Point"}
}