{
  "type": "Feature",
  "properties": {
    "addr:full":"2441 Old Fort Pkwy Murfreesboro TN 37128",
    "addr:housenumber":"2441",
    "addr:postcode":"37128",
    "addr:street":"Old Fort Pkwy",
    "iso:country":"US",
    "sg:address":"2441 Old Fort Pkwy",
    "sg:city":"Murfreesboro",
    "sg:classifiers":[
        {
            "category":"Professional",
            "subcategory":"Computer Services",
            "type":"Services"
        }
    ],
    "sg:phone":"+1 615 596 3444",
    "sg:postcode":"37128",
    "sg:province":"TN",
    "sg:tags":[
        "repair"
    ],
    "sg:website":"www.servicetech.com",
    "wof:name":"SERVICETECH.COM",
    "wof:placetype":"venue"
},
  "geometry": {"coordinates":[-86.44750500000001,35.844944],"type":"Point"}
}