{
  "type": "Feature",
  "properties": {
    "addr:full":"114 G B Plunk Rd Adamsville TN 38375",
    "addr:housenumber":"114",
    "addr:postcode":"38375",
    "addr:street":"G B Plunk Rd",
    "iso:country":"US",
    "sg:address":"114 G B Plunk Rd",
    "sg:city":"Adamsville",
    "sg:classifiers":[
        {
            "category":"Organizations",
            "subcategory":"Religious Organization",
            "type":"Services"
        }
    ],
    "sg:phone":"+1 731 632 0300",
    "sg:postcode":"38375",
    "sg:province":"TN",
    "wof:name":"Clear Creek Baptist Church",
    "wof:placetype":"venue"
},
  "geometry": {"coordinates":[-88.52403099999999,35.222932],"type":"Point"}
}