{
  "type": "Feature",
  "properties": {
    "iso:country":"US",
    "sg:address":"308 US Hwy 25E Scn",
    "sg:city":"Tazewell",
    "sg:classifiers":[
        {
            "category":"Autos & Motor Vehicles",
            "subcategory":"Automobile Sales",
            "type":"Retail Goods"
        }
    ],
    "sg:phone":"+1 423 626 4114",
    "sg:postcode":"37879",
    "sg:province":"TN",
    "sg:tags":[
        "car",
        "dealer"
    ],
    "wof:name":"Hobart's Cars",
    "wof:placetype":"venue"
},
  "geometry": {"coordinates":[-83.567921,36.447946],"type":"Point"}
}