{
  "type": "Feature",
  "properties": {
    "addr:full":"949 W Outer Dr Oak Ridge TN 37830",
    "addr:housenumber":"949",
    "addr:postcode":"37830",
    "addr:street":"W Outer Dr",
    "iso:country":"US",
    "sg:address":"949 W Outer Dr",
    "sg:city":"Oak Ridge",
    "sg:classifiers":[
        {
            "category":"Organizations",
            "subcategory":"Non-profit Organization",
            "type":"Services"
        }
    ],
    "sg:phone":"+1 865 539 6155",
    "sg:postcode":"37830",
    "sg:province":"TN",
    "wof:name":"Friends Of Haw Ridge Park Inc",
    "wof:placetype":"venue"
},
  "geometry": {"coordinates":[-84.325457,36.002783],"type":"Point"}
}