{
  "type": "Feature",
  "properties": {
    "iso:country":"US",
    "sg:address":"106 S Liberty St",
    "sg:city":"Jackson",
    "sg:classifiers":[
        {
            "category":"Professional",
            "subcategory":"Lawyer & Legal Services",
            "type":"Services"
        }
    ],
    "sg:phone":"+1 731 424 6211",
    "sg:postcode":"38301",
    "sg:province":"TN",
    "sg:tags":[
        "attorney"
    ],
    "wof:name":"Waldrop & Hall",
    "wof:placetype":"venue"
},
  "geometry": {"coordinates":[-88.818197,35.613482],"type":"Point"}
}