{
  "type": "Feature",
  "properties": {
    "iso:country":"US",
    "sg:address":"3 Tom Carroll Rd",
    "sg:city":"Summertown",
    "sg:classifiers":[
        {
            "category":"Farming",
            "subcategory":"Livestock Farm",
            "type":"Manufacturing & Wholesale Goods"
        }
    ],
    "sg:phone":"+1 931 964 2622",
    "sg:postcode":"38483",
    "sg:province":"TN",
    "sg:tags":[
        "beef",
        "feedlot",
        "cattle"
    ],
    "wof:name":"Carrolls Cow & Fish Farm",
    "wof:placetype":"venue"
},
  "geometry": {"coordinates":[-87.438343,35.434943],"type":"Point"}
}