{
  "type": "Feature",
  "properties": {
    "iso:country":"US",
    "sg:address":"1230 S Ellington Pkwy",
    "sg:city":"Lewisburg",
    "sg:classifiers":[
        {
            "category":"Real Estate",
            "subcategory":"Real Estate Operator",
            "type":"Services"
        }
    ],
    "sg:phone":"+1 931 359 6735",
    "sg:postcode":"37091",
    "sg:province":"TN",
    "sg:tags":[
        "apartment"
    ],
    "wof:name":"Pinewood Place Apartments",
    "wof:placetype":"venue"
},
  "geometry": {"coordinates":[-86.790088,35.429352],"type":"Point"}
}