{
  "type": "Feature",
  "properties": {
    "addr:full":"130 Bethlehem Church Rd Madisonville TN 37354",
    "addr:housenumber":"130",
    "addr:postcode":"37354",
    "addr:street":"Bethlehem Church Rd",
    "iso:country":"US",
    "sg:address":"130 Bethlehem Church Rd",
    "sg:city":"Madisonville",
    "sg:classifiers":[
        {
            "category":"Organizations",
            "subcategory":"Religious Organization",
            "type":"Services"
        }
    ],
    "sg:phone":"+1 423 442 1311",
    "sg:postcode":"37354",
    "sg:province":"TN",
    "wof:name":"Bethlehem Baptist Church",
    "wof:placetype":"venue"
},
  "geometry": {"coordinates":[-84.34957199999999,35.440037],"type":"Point"}
}