{
  "type": "Feature",
  "properties": {
    "iso:country":"US",
    "sg:address":"909 Fairfield Rd",
    "sg:city":"Westmoreland",
    "sg:classifiers":[
        {
            "category":"Organizations",
            "subcategory":"Religious Organization",
            "type":"Services"
        }
    ],
    "sg:phone":"+1 615 888 9938",
    "sg:postcode":"37186",
    "sg:province":"TN",
    "sg:tags":[
        "church"
    ],
    "wof:name":"Fairfield United Methodist Chr",
    "wof:placetype":"venue"
},
  "geometry": {"coordinates":[-86.344876,36.619744],"type":"Point"}
}