{
  "type": "Feature",
  "properties": {
    "iso:country":"US",
    "sg:address":"120 Administration Rd",
    "sg:city":"Oak Ridge",
    "sg:classifiers":[
        {
            "category":"Professional",
            "subcategory":"Detective & Security Services",
            "type":"Services"
        }
    ],
    "sg:phone":"+1 865 482 0440",
    "sg:postcode":"37830",
    "sg:province":"TN",
    "sg:tags":[
        "line",
        "full",
        "agency"
    ],
    "wof:name":"Pinnacle Investigation",
    "wof:placetype":"venue"
},
  "geometry": {"coordinates":[-84.238146,36.024545],"type":"Point"}
}