{
  "type": "Feature",
  "properties": {
    "addr:full":"1344 Old Hickory Blvd Brentwood TN 37027",
    "addr:housenumber":"1344",
    "addr:postcode":"37027",
    "addr:street":"Old Hickory Blvd",
    "iso:country":"US",
    "sg:address":"1344 Old Hickory Blvd",
    "sg:city":"Brentwood",
    "sg:classifiers":[
        {
            "category":"Real Estate",
            "subcategory":"Real Estate Operator",
            "type":"Services"
        }
    ],
    "sg:phone":"+1 615 661 9941",
    "sg:postcode":"37027",
    "sg:province":"TN",
    "sg:tags":[
        "building",
        "nonresidential"
    ],
    "wof:name":"Reynolds Property and Dev LLC",
    "wof:placetype":"venue"
},
  "geometry": {"coordinates":[-86.82444,36.041907],"type":"Point"}
}