{
  "type": "Feature",
  "properties": {
    "addr:full":"1056 Fredericksburg Cove Collierville TN 38017",
    "addr:housenumber":"1056",
    "addr:postcode":"38017",
    "addr:street":"Fredericksburg Cove",
    "iso:country":"US",
    "sg:address":"1056 Fredericksburg Cove",
    "sg:city":"Collierville",
    "sg:classifiers":[
        {
            "category":"Manufacturing",
            "subcategory":"Paper Products",
            "type":"Manufacturing & Wholesale Goods"
        }
    ],
    "sg:phone":"+1 901 854 8497",
    "sg:postcode":"38017",
    "sg:province":"TN",
    "sg:tags":[
        "mill"
    ],
    "wof:name":"Doodle Bug Prints",
    "wof:placetype":"venue"
},
  "geometry": {"coordinates":[-89.666479,35.069235],"type":"Point"}
}