{
  "type": "Feature",
  "properties": {
    "addr:full":"1925 Euclid Ave Bristol TN 24201",
    "addr:housenumber":"1925",
    "addr:postcode":"24201",
    "addr:street":"Euclid Ave",
    "iso:country":"US",
    "sg:address":"1925 Euclid Ave",
    "sg:city":"Bristol",
    "sg:classifiers":[
        {
            "category":"Utilities",
            "subcategory":"Fuel Oil & Lpg",
            "type":"Services"
        }
    ],
    "sg:phone":"+1 276 669 1521",
    "sg:postcode":"24201",
    "sg:province":"TN",
    "sg:tags":[
        "dealer"
    ],
    "wof:name":"J R Bob Smith Oil Co Inc",
    "wof:placetype":"venue"
},
  "geometry": {"coordinates":[-82.203473,36.598582],"type":"Point"}
}