{
  "type": "Feature",
  "properties": {
    "iso:country":"US",
    "sg:address":"413 4th Ave",
    "sg:city":"Fayetteville",
    "sg:classifiers":[
        {
            "category":"Building & Trades",
            "subcategory":"Electrical",
            "type":"Services"
        }
    ],
    "sg:phone":"+1 931 433 8756",
    "sg:postcode":"37334",
    "sg:province":"TN",
    "sg:tags":[
        "electric",
        "contractor"
    ],
    "wof:name":"Bevels Plumbing & Electric",
    "wof:placetype":"venue"
},
  "geometry": {"coordinates":[-86.583912,35.156793],"type":"Point"}
}