{
  "type": "Feature",
  "properties": {
    "iso:country":"US",
    "sg:address":"103 Whispering Hills Dr",
    "sg:city":"Jackson",
    "sg:classifiers":[
        {
            "category":"Real Estate",
            "subcategory":"Real Estate Agent",
            "type":"Services"
        }
    ],
    "sg:phone":"+1 731 661 0577",
    "sg:postcode":"38305",
    "sg:province":"TN",
    "wof:name":"Sivart Realty",
    "wof:placetype":"venue"
},
  "geometry": {"coordinates":[-88.904691,35.683212],"type":"Point"}
}