{
  "type": "Feature",
  "properties": {
    "iso:country":"US",
    "sg:address":"402 Bna Dr",
    "sg:city":"Nashville",
    "sg:classifiers":[
        {
            "category":"Insurance",
            "subcategory":"Insurance Agent",
            "type":"Services"
        }
    ],
    "sg:phone":"+1 615 366 7660",
    "sg:postcode":"37217",
    "sg:province":"TN",
    "wof:name":"Broadspire Services Inc",
    "wof:placetype":"venue"
},
  "geometry": {"coordinates":[-86.697726,36.139008],"type":"Point"}
}