{
  "type": "Feature",
  "properties": {
    "addr:full":"3892 Knight Arnold Rd Memphis TN 38118",
    "addr:housenumber":"3892",
    "addr:postcode":"38118",
    "addr:street":"Knight Arnold Rd",
    "iso:country":"US",
    "sg:address":"3892 Knight Arnold Rd",
    "sg:city":"Memphis",
    "sg:classifiers":[
        {
            "category":"Organizations",
            "subcategory":"Religious Organization",
            "type":"Services"
        }
    ],
    "sg:phone":"+1 901 368 6195",
    "sg:postcode":"38118",
    "sg:province":"TN",
    "sg:tags":[
        "church"
    ],
    "wof:name":"New Wright Chapel",
    "wof:placetype":"venue"
},
  "geometry": {"coordinates":[-89.932982,35.06497],"type":"Point"}
}