{
  "type": "Feature",
  "properties": {
    "iso:country":"US",
    "sg:address":"3218 Chestnut Hill Rd",
    "sg:city":"Dandridge",
    "sg:classifiers":[
        {
            "category":"Manufacturing",
            "subcategory":"Metals",
            "type":"Manufacturing & Wholesale Goods"
        }
    ],
    "sg:phone":"+1 865 509 7544",
    "sg:postcode":"37725",
    "sg:province":"TN",
    "sg:tags":[
        "container",
        "mfg"
    ],
    "wof:name":"Ball Corporation",
    "wof:placetype":"venue"
},
  "geometry": {"coordinates":[-83.348766,35.929401],"type":"Point"}
}