{
  "type": "Feature",
  "properties": {
    "addr:full":"410 Outlet Village Blvd Lebanon TN 37090",
    "addr:housenumber":"410",
    "addr:postcode":"37090",
    "addr:street":"Outlet Village Blvd",
    "iso:country":"US",
    "sg:address":"410 Outlet Village Blvd",
    "sg:city":"Lebanon",
    "sg:classifiers":[
        {
            "category":"Shopping",
            "subcategory":"Luggage & Leather Goods",
            "type":"Retail Goods"
        }
    ],
    "sg:phone":"+1 615 443 3688",
    "sg:postcode":"37090",
    "sg:province":"TN",
    "wof:name":"Coach Store",
    "wof:placetype":"venue"
},
  "geometry": {"coordinates":[-86.303394,36.178433],"type":"Point"}
}