{
  "type": "Feature",
  "properties": {
    "iso:country":"US",
    "sg:address":"1111 Lakeview Dr",
    "sg:city":"Franklin",
    "sg:classifiers":[
        {
            "category":"Banks & Credit Unions",
            "subcategory":"Bank",
            "type":"Services"
        }
    ],
    "sg:phone":"+1 615 591 2528",
    "sg:postcode":"37067",
    "sg:province":"TN",
    "sg:tags":[
        "loan",
        "real estate"
    ],
    "wof:name":"Quality Mortgage Svc",
    "wof:placetype":"venue"
},
  "geometry": {"coordinates":[-86.82489200000001,35.920396],"type":"Point"}
}