{
  "type": "Feature",
  "properties": {
    "iso:country":"US",
    "sg:address":"640 W Main St",
    "sg:city":"Murfreesboro",
    "sg:classifiers":[
        {
            "category":"Social Services",
            "subcategory":"Child Care",
            "type":"Services"
        },
        {
            "category":"Social Services",
            "type":"Services"
        }
    ],
    "sg:phone":"+1 615 896 7016",
    "sg:postcode":"37129",
    "sg:province":"TN",
    "sg:tags":[
        "shelter",
        "day",
        "homeless"
    ],
    "wof:name":"Room In The Inn Day Shelter",
    "wof:placetype":"venue"
},
  "geometry": {"coordinates":[-86.400435,35.84695],"type":"Point"}
}