{
  "type": "Feature",
  "properties": {
    "iso:country":"US",
    "sg:address":"1768 W Northfield Blvd",
    "sg:city":"Murfreesboro",
    "sg:classifiers":[
        {
            "category":"Manufacturing",
            "subcategory":"Apparel",
            "type":"Manufacturing & Wholesale Goods"
        }
    ],
    "sg:phone":"+1 615 895 8310",
    "sg:postcode":"37129",
    "sg:province":"TN",
    "sg:website":"www.embroidme-murfreesboro.com",
    "wof:name":"Embroidme",
    "wof:placetype":"venue"
},
  "geometry": {"coordinates":[-86.411759,35.871865],"type":"Point"}
}