{
  "type": "Feature",
  "properties": {
    "addr:full":"2010 E Broadway Ave Maryville TN 37804",
    "addr:housenumber":"2010",
    "addr:postcode":"37804",
    "addr:street":"E Broadway Ave",
    "iso:country":"US",
    "sg:address":"2010 E Broadway Ave",
    "sg:city":"Maryville",
    "sg:classifiers":[
        {
            "category":"Restaurant",
            "type":"Food & Drink"
        }
    ],
    "sg:menulink":"http://www.allmenus.com/tn/maryville-alcoa/191790-sonic/menu/",
    "sg:phone":"+1 865 977 8135",
    "sg:postcode":"37804",
    "sg:province":"TN",
    "sg:tags":[
        "burger",
        "american"
    ],
    "wof:name":"Sonic",
    "wof:placetype":"venue"
},
  "geometry": {"coordinates":[-83.953019,35.776254],"type":"Point"}
}