{
  "type": "Feature",
  "properties": {
    "addr:full":"311 Ebenezer Rd Knoxville TN 37923",
    "addr:housenumber":"311",
    "addr:postcode":"37923",
    "addr:street":"Ebenezer Rd",
    "iso:country":"US",
    "sg:address":"311 Ebenezer Rd",
    "sg:city":"Knoxville",
    "sg:classifiers":[
        {
            "category":"Professional",
            "subcategory":"Business Services",
            "type":"Services"
        }
    ],
    "sg:phone":"+1 865 531 6222",
    "sg:postcode":"37923",
    "sg:province":"TN",
    "sg:tags":[
        "call",
        "center"
    ],
    "wof:name":"Priority Communications",
    "wof:placetype":"venue"
},
  "geometry": {"coordinates":[-84.074116,35.906135],"type":"Point"}
}