{
  "type": "Feature",
  "properties": {
    "iso:country":"US",
    "sg:address":"3564 Dickerson Pike",
    "sg:city":"Nashville",
    "sg:classifiers":[
        {
            "category":"Freight",
            "type":"Transportation"
        }
    ],
    "sg:phone":"+1 615 865 6212",
    "sg:postcode":"37207",
    "sg:province":"TN",
    "sg:tags":[
        "general"
    ],
    "wof:name":"Merchants Metals",
    "wof:placetype":"venue"
},
  "geometry": {"coordinates":[-86.757752,36.253111],"type":"Point"}
}