{
  "type": "Feature",
  "properties": {
    "iso:country":"US",
    "sg:address":"114 Fairbanks Rd",
    "sg:city":"Oak Ridge",
    "sg:classifiers":[
        {
            "category":"Shopping",
            "subcategory":"Computers & Home Electronics",
            "type":"Retail Goods"
        }
    ],
    "sg:phone":"+1 865 482 6024",
    "sg:postcode":"37830",
    "sg:province":"TN",
    "sg:tags":[
        "product",
        "tobacco"
    ],
    "wof:name":"National Electronics",
    "wof:placetype":"venue"
},
  "geometry": {"coordinates":[-84.22760599999999,36.030947],"type":"Point"}
}