{
  "type": "Feature",
  "properties": {
    "iso:country":"US",
    "sg:address":"636 N Fox Chase Cove",
    "sg:city":"Collierville",
    "sg:classifiers":[
        {
            "category":"Manufacturing",
            "subcategory":"Food",
            "type":"Manufacturing & Wholesale Goods"
        }
    ],
    "sg:phone":"+1 901 861 0988",
    "sg:postcode":"38017",
    "sg:province":"TN",
    "sg:tags":[
        "frozen",
        "fresh",
        "mfg",
        "citrus",
        "juice"
    ],
    "wof:name":"Tropicana",
    "wof:placetype":"venue"
},
  "geometry": {"coordinates":[-89.68226,35.055644],"type":"Point"}
}