{
  "type": "Feature",
  "properties": {
    "iso:country":"US",
    "sg:address":"1324 Elm Hill Pike",
    "sg:city":"Nashville",
    "sg:classifiers":[
        {
            "category":"Building & Trades",
            "subcategory":"Construction",
            "type":"Services"
        }
    ],
    "sg:phone":"+1 615 782 2940",
    "sg:postcode":"37210",
    "sg:province":"TN",
    "sg:tags":[
        "maintenance",
        "contractor"
    ],
    "wof:name":"NPS Energy Svc Inc",
    "wof:placetype":"venue"
},
  "geometry": {"coordinates":[-86.729133,36.143863],"type":"Point"}
}