{
  "type": "Feature",
  "properties": {
    "iso:country":"US",
    "sg:address":"130 Serral Dr",
    "sg:city":"Greeneville",
    "sg:classifiers":[
        {
            "category":"Government",
            "subcategory":"Office",
            "type":"Public Place"
        }
    ],
    "sg:phone":"+1 423 639 4465",
    "sg:postcode":"37745",
    "sg:province":"TN",
    "wof:name":"Children Services Dept",
    "wof:placetype":"venue"
},
  "geometry": {"coordinates":[-82.76634300000001,36.18897],"type":"Point"}
}