{
  "type": "Feature",
  "properties": {
    "iso:country":"US",
    "sg:address":"7324 Noah Reid Rd",
    "sg:city":"Chattanooga",
    "sg:classifiers":[
        {
            "category":"Organizations",
            "subcategory":"Religious Organization",
            "type":"Services"
        }
    ],
    "sg:phone":"+1 423 499 1990",
    "sg:postcode":"37421",
    "sg:province":"TN",
    "sg:website":"www.precept.org",
    "wof:name":"How Can I Live",
    "wof:placetype":"venue"
},
  "geometry": {"coordinates":[-85.176559,35.062014],"type":"Point"}
}