{
  "type": "Feature",
  "properties": {
    "iso:country":"US",
    "sg:address":"1094 S Highland Ave",
    "sg:city":"Jackson",
    "sg:classifiers":[
        {
            "category":"Retail",
            "subcategory":"Auto Repair",
            "type":"Services"
        }
    ],
    "sg:phone":"+1 731 427 4824",
    "sg:postcode":"38301",
    "sg:province":"TN",
    "sg:tags":[
        "body"
    ],
    "wof:name":"Thompsons Body Shop",
    "wof:placetype":"venue"
},
  "geometry": {"coordinates":[-88.81420300000001,35.591231],"type":"Point"}
}