{
  "type": "Feature",
  "properties": {
    "iso:country":"US",
    "sg:address":"901 College St",
    "sg:city":"Knoxville",
    "sg:classifiers":[
        {
            "category":"Education",
            "subcategory":"College",
            "type":"Public Place"
        }
    ],
    "sg:phone":"+1 865 524 6511",
    "sg:postcode":"37921",
    "sg:province":"TN",
    "wof:name":"Knoxville College",
    "wof:placetype":"venue"
},
  "geometry": {"coordinates":[-83.94087500000001,35.970312],"type":"Point"}
}