{
  "type": "Feature",
  "properties": {
    "addr:full":"7528 Nashville Hwy Dowelltown TN 37059",
    "addr:housenumber":"7528",
    "addr:postcode":"37059",
    "addr:street":"Nashville Hwy",
    "iso:country":"US",
    "sg:address":"7528 Nashville Hwy",
    "sg:city":"Dowelltown",
    "sg:classifiers":[
        {
            "category":"Building & Trades",
            "subcategory":"Construction",
            "type":"Services"
        }
    ],
    "sg:phone":"+1 615 536 5523",
    "sg:postcode":"37059",
    "sg:province":"TN",
    "sg:tags":[
        "general",
        "contractor"
    ],
    "wof:name":"Steve Mathis Backhoe Svc",
    "wof:placetype":"venue"
},
  "geometry": {"coordinates":[-85.89306999999999,35.998678],"type":"Point"}
}