{
  "type": "Feature",
  "properties": {
    "addr:full":"2238 Joe Stephens Rd Morristown TN 37814",
    "addr:housenumber":"2238",
    "addr:postcode":"37814",
    "addr:street":"Joe Stephens Rd",
    "iso:country":"US",
    "sg:address":"2238 Joe Stephens Rd",
    "sg:city":"Morristown",
    "sg:classifiers":[
        {
            "category":"Manufacturing",
            "subcategory":"Printing",
            "type":"Manufacturing & Wholesale Goods"
        }
    ],
    "sg:phone":"+1 423 581 4603",
    "sg:postcode":"37814",
    "sg:province":"TN",
    "sg:tags":[
        "publishing"
    ],
    "wof:name":"Cox Networking",
    "wof:placetype":"venue"
},
  "geometry": {"coordinates":[-83.36088100000001,36.22944],"type":"Point"}
}