{
  "type": "Feature",
  "properties": {
    "iso:country":"US",
    "sg:address":"55 Richie Way",
    "sg:city":"Hornsby",
    "sg:classifiers":[
        {
            "category":"Building & Trades",
            "subcategory":"Landscaping Services",
            "type":"Services"
        }
    ],
    "sg:phone":"+1 731 658 9633",
    "sg:postcode":"38044",
    "sg:province":"TN",
    "wof:name":"L McMahan Trucking",
    "wof:placetype":"venue"
},
  "geometry": {"coordinates":[-88.801945,35.194142],"type":"Point"}
}