{
  "type": "Feature",
  "properties": {
    "iso:country":"US",
    "sg:address":"2967 Milkyway Cove",
    "sg:city":"Memphis",
    "sg:classifiers":[
        {
            "category":"Professional",
            "subcategory":"Management & Consulting",
            "type":"Services"
        }
    ],
    "sg:phone":"+1 901 382 8115",
    "sg:postcode":"38134",
    "sg:province":"TN",
    "sg:tags":[
        "consultant"
    ],
    "wof:name":"Cancer Consultants",
    "wof:placetype":"venue"
},
  "geometry": {"coordinates":[-89.844128,35.207294],"type":"Point"}
}