{
  "type": "Feature",
  "properties": {
    "addr:full":"985 Reddoch Cove Memphis TN 38119",
    "addr:housenumber":"985",
    "addr:postcode":"38119",
    "addr:street":"Reddoch Cove",
    "iso:country":"US",
    "sg:address":"985 Reddoch Cove",
    "sg:city":"Memphis",
    "sg:classifiers":[
        {
            "category":"Building & Trades",
            "subcategory":"Construction",
            "type":"Services"
        }
    ],
    "sg:phone":"+1 901 761 4113",
    "sg:postcode":"38119",
    "sg:province":"TN",
    "sg:tags":[
        "house"
    ],
    "wof:name":"Duke John Inc",
    "wof:placetype":"venue"
},
  "geometry": {"coordinates":[-89.879975,35.105699],"type":"Point"}
}