{
  "type": "Feature",
  "properties": {
    "iso:country":"US",
    "sg:address":"312 Mc Brien Rd",
    "sg:city":"Chattanooga",
    "sg:classifiers":[
        {
            "category":"Shopping",
            "type":"Retail Goods"
        }
    ],
    "sg:phone":"+1 423 954 9899",
    "sg:postcode":"37411",
    "sg:province":"TN",
    "sg:tags":[
        "merchandise"
    ],
    "wof:name":"Angels Pampered Pets",
    "wof:placetype":"venue"
},
  "geometry": {"coordinates":[-85.226654,35.005441],"type":"Point"}
}