{
  "type": "Feature",
  "properties": {
    "addr:full":"404 Elysian Fields Rd Nashville TN 37211",
    "addr:housenumber":"404",
    "addr:postcode":"37211",
    "addr:street":"Elysian Fields Rd",
    "iso:country":"US",
    "sg:address":"404 Elysian Fields Rd",
    "sg:city":"Nashville",
    "sg:classifiers":[
        {
            "category":"Restaurant",
            "type":"Food & Drink"
        }
    ],
    "sg:phone":"+1 615 831 3944",
    "sg:postcode":"37211",
    "sg:province":"TN",
    "wof:name":"Elysian Inn",
    "wof:placetype":"venue"
},
  "geometry": {"coordinates":[-86.73378599999999,36.084965],"type":"Point"}
}