{
  "type": "Feature",
  "properties": {
    "iso:country":"US",
    "sg:address":"392 Gilley Rd",
    "sg:city":"Mount Juliet",
    "sg:classifiers":[
        {
            "category":"Retail",
            "subcategory":"Repair Shop",
            "type":"Services"
        }
    ],
    "sg:phone":"+1 615 758 8092",
    "sg:postcode":"37122",
    "sg:province":"TN",
    "wof:name":"Flag Star Repair & Maintenace",
    "wof:placetype":"venue"
},
  "geometry": {"coordinates":[-86.48764300000001,36.277775],"type":"Point"}
}