{
  "type": "Feature",
  "properties": {
    "iso:country":"US",
    "sg:address":"237 Harvey Rd",
    "sg:city":"Kingston",
    "sg:classifiers":[
        {
            "category":"Farming",
            "subcategory":"Livestock Farm",
            "type":"Manufacturing & Wholesale Goods"
        }
    ],
    "sg:phone":"+1 865 376 4100",
    "sg:postcode":"37763",
    "sg:province":"TN",
    "sg:tags":[
        "specialty",
        "animal"
    ],
    "sg:website":"www.tigerhaven.org",
    "wof:name":"Tiger Haven Inc",
    "wof:placetype":"venue"
},
  "geometry": {"coordinates":[-84.402193,35.81426],"type":"Point"}
}