{
  "type": "Feature",
  "properties": {
    "addr:full":"2000 Seven Oaks Dr Morristown TN 37814",
    "addr:housenumber":"2000",
    "addr:postcode":"37814",
    "addr:street":"Seven Oaks Dr",
    "iso:country":"US",
    "sg:address":"2000 Seven Oaks Dr",
    "sg:city":"Morristown",
    "sg:classifiers":[
        {
            "category":"Building & Trades",
            "subcategory":"Landscaping Services",
            "type":"Services"
        }
    ],
    "sg:phone":"+1 423 587 5530",
    "sg:postcode":"37814",
    "sg:province":"TN",
    "wof:name":"Eversles Lawn Trctr Fncing Svc",
    "wof:placetype":"venue"
},
  "geometry": {"coordinates":[-83.39961,36.190963],"type":"Point"}
}