{
  "type": "Feature",
  "properties": {
    "addr:full":"5954 Dayton Mountain Hwy Dayton TN 37321",
    "addr:housenumber":"5954",
    "addr:postcode":"37321",
    "addr:street":"Dayton Mountain Hwy",
    "iso:country":"US",
    "sg:address":"5954 Dayton Mountain Hwy",
    "sg:city":"Dayton",
    "sg:classifiers":[
        {
            "category":"Home & Garden",
            "subcategory":"Garden Supply",
            "type":"Retail Goods"
        }
    ],
    "sg:phone":"+1 423 775 7063",
    "sg:postcode":"37321",
    "sg:province":"TN",
    "sg:tags":[
        "repair"
    ],
    "wof:name":"Eds Repairs",
    "wof:placetype":"venue"
},
  "geometry": {"coordinates":[-85.068268,35.545924],"type":"Point"}
}