{
  "type": "Feature",
  "properties": {
    "addr:full":"2221 Poplar Ave Memphis TN 38104",
    "addr:housenumber":"2221",
    "addr:postcode":"38104",
    "addr:street":"Poplar Ave",
    "iso:country":"US",
    "sg:address":"2221 Poplar Ave",
    "sg:city":"Memphis",
    "sg:classifiers":[
        {
            "category":"Organizations",
            "subcategory":"Membership Organization",
            "type":"Services"
        }
    ],
    "sg:phone":"+1 901 276 6748",
    "sg:postcode":"38104",
    "sg:province":"TN",
    "wof:name":"Filipino American Association",
    "wof:placetype":"venue"
},
  "geometry": {"coordinates":[-89.98502999999999,35.141168],"type":"Point"}
}