{
  "type": "Feature",
  "properties": {
    "iso:country":"US",
    "sg:address":"4125 New Allen Rd",
    "sg:city":"Memphis",
    "sg:classifiers":[
        {
            "category":"Social Services",
            "subcategory":"Child Care",
            "type":"Services"
        }
    ],
    "sg:phone":"+1 901 353 5975",
    "sg:postcode":"38128",
    "sg:province":"TN",
    "sg:tags":[
        "day"
    ],
    "wof:name":"La Petite Academy Inc",
    "wof:placetype":"venue"
},
  "geometry": {"coordinates":[-89.946889,35.242683],"type":"Point"}
}