{
  "type": "Feature",
  "properties": {
    "iso:country":"US",
    "sg:address":"3203 Coleman Rd",
    "sg:city":"Memphis",
    "sg:classifiers":[
        {
            "category":"Restaurant",
            "type":"Food & Drink"
        }
    ],
    "sg:phone":"+1 901 266 0153",
    "sg:postcode":"38128",
    "sg:province":"TN",
    "wof:name":"El Pacifico",
    "wof:placetype":"venue"
},
  "geometry": {"coordinates":[-89.915257,35.212592],"type":"Point"}
}