{
  "type": "Feature",
  "properties": {
    "addr:full":"5665 E Raines Rd Memphis TN 38115",
    "addr:housenumber":"5665",
    "addr:postcode":"38115",
    "addr:street":"E Raines Rd",
    "iso:country":"US",
    "sg:address":"5665 E Raines Rd",
    "sg:city":"Memphis",
    "sg:classifiers":[
        {
            "category":"Wholesale",
            "subcategory":"Machinery & Supplies",
            "type":"Manufacturing & Wholesale Goods"
        }
    ],
    "sg:phone":"+1 901 366 1842",
    "sg:postcode":"38115",
    "sg:province":"TN",
    "sg:tags":[
        "truck"
    ],
    "wof:name":"Lift Truck Svc & Rentals",
    "wof:placetype":"venue"
},
  "geometry": {"coordinates":[-89.87450699999999,35.034767],"type":"Point"}
}