{
  "type": "Feature",
  "properties": {
    "iso:country":"US",
    "sg:address":"1581 Overton Park Ave",
    "sg:city":"Memphis",
    "sg:classifiers":[
        {
            "category":"Shopping",
            "type":"Retail Goods"
        }
    ],
    "sg:phone":"+1 901 276 7515",
    "sg:postcode":"38112",
    "sg:province":"TN",
    "sg:tags":[
        "art",
        "gallery",
        "dealer"
    ],
    "wof:name":"Diane's Art Gift & Home",
    "wof:placetype":"venue"
},
  "geometry": {"coordinates":[-90.00743,35.148727],"type":"Point"}
}