{
  "type": "Feature",
  "properties": {
    "iso:country":"US",
    "sg:address":"205 N Claybrook St",
    "sg:city":"Memphis",
    "sg:classifiers":[
        {
            "category":"Education",
            "subcategory":"Special Training",
            "type":"Public Place"
        }
    ],
    "sg:phone":"+1 901 416 2216",
    "sg:postcode":"38104",
    "sg:province":"TN",
    "sg:tags":[
        "center"
    ],
    "wof:name":"Memphis City Sch Board - Edu",
    "wof:placetype":"venue"
},
  "geometry": {"coordinates":[-90.01718700000001,35.144564],"type":"Point"}
}