{
  "type": "Feature",
  "properties": {
    "addr:full":"4325 Grand Ave Chattanooga TN 37410",
    "addr:housenumber":"4325",
    "addr:postcode":"37410",
    "addr:street":"Grand Ave",
    "iso:country":"US",
    "sg:address":"4325 Grand Ave",
    "sg:city":"Chattanooga",
    "sg:classifiers":[
        {
            "category":"Organizations",
            "subcategory":"Religious Organization",
            "type":"Services"
        }
    ],
    "sg:phone":"+1 423 825 6530",
    "sg:postcode":"37410",
    "sg:province":"TN",
    "wof:name":"Friendship Primitive Baptist",
    "wof:placetype":"venue"
},
  "geometry": {"coordinates":[-85.320249,35.00232],"type":"Point"}
}