{
  "type": "Feature",
  "properties": {
    "iso:country":"US",
    "sg:address":"3913 Western Ave",
    "sg:city":"Knoxville",
    "sg:classifiers":[
        {
            "category":"Restaurant",
            "type":"Food & Drink"
        }
    ],
    "sg:phone":"+1 865 524 9456",
    "sg:postcode":"37921",
    "sg:province":"TN",
    "sg:tags":[
        "eating"
    ],
    "wof:name":"Tracy's Restaurant",
    "wof:placetype":"venue"
},
  "geometry": {"coordinates":[-83.976122,35.97442],"type":"Point"}
}