{
  "type": "Feature",
  "properties": {
    "iso:country":"US",
    "sg:address":"8191 Rebecca Woods Dr",
    "sg:city":"Arlington",
    "sg:classifiers":[
        {
            "category":"Professional",
            "subcategory":"Computer Services",
            "type":"Services"
        }
    ],
    "sg:phone":"+1 901 373 3132",
    "sg:postcode":"38002",
    "sg:province":"TN",
    "sg:tags":[
        "programing",
        "custom"
    ],
    "wof:name":"Ensemble Corporation",
    "wof:placetype":"venue"
},
  "geometry": {"coordinates":[-89.788291,35.254278],"type":"Point"}
}