{
  "type": "Feature",
  "properties": {
    "iso:country":"US",
    "sg:address":"4235 Old State Rd",
    "sg:city":"Hampshire",
    "sg:classifiers":[
        {
            "category":"Education",
            "subcategory":"School",
            "type":"Public Place"
        }
    ],
    "sg:phone":"+1 931 285 2300",
    "sg:postcode":"38461",
    "sg:province":"TN",
    "wof:name":"Hampshire School",
    "wof:placetype":"venue"
},
  "geometry": {"coordinates":[-87.28945,35.595465],"type":"Point"}
}