{
  "type": "Feature",
  "properties": {
    "addr:full":"240 College Ave Lawrenceburg TN 38464",
    "addr:housenumber":"240",
    "addr:postcode":"38464",
    "addr:street":"College Ave",
    "iso:country":"US",
    "sg:address":"240 College Ave",
    "sg:city":"Lawrenceburg",
    "sg:classifiers":[
        {
            "category":"Education",
            "subcategory":"School",
            "type":"Public Place"
        }
    ],
    "sg:phone":"+1 931 766 0442",
    "sg:postcode":"38464",
    "sg:province":"TN",
    "wof:name":"Old Public School",
    "wof:placetype":"venue"
},
  "geometry": {"coordinates":[-87.330147,35.237729],"type":"Point"}
}