{
  "type": "Feature",
  "properties": {
    "iso:country":"US",
    "sg:address":"83 Tinker Hill Rd",
    "sg:city":"Jackson",
    "sg:classifiers":[
        {
            "category":"Freight",
            "type":"Transportation"
        }
    ],
    "sg:phone":"+1 731 661 0196",
    "sg:postcode":"38305",
    "sg:province":"TN",
    "sg:tags":[
        "operator",
        "local",
        "trucking"
    ],
    "wof:name":"J & K Trucking LLC",
    "wof:placetype":"venue"
},
  "geometry": {"coordinates":[-88.83245599999999,35.659004],"type":"Point"}
}