{
  "type": "Feature",
  "properties": {
    "iso:country":"US",
    "sg:address":"3019 Scenic Hwy",
    "sg:city":"Memphis",
    "sg:classifiers":[
        {
            "category":"Organizations",
            "subcategory":"Labor Organization",
            "type":"Services"
        }
    ],
    "sg:phone":"+1 901 357 2257",
    "sg:postcode":"38128",
    "sg:province":"TN",
    "wof:name":"Russ Callison",
    "wof:placetype":"venue"
},
  "geometry": {"coordinates":[-89.962982,35.201768],"type":"Point"}
}