{
  "type": "Feature",
  "properties": {
    "iso:country":"US",
    "sg:address":"1445 Airport Rd",
    "sg:city":"Gallatin",
    "sg:classifiers":[
        {
            "category":"Airport",
            "type":"Transportation"
        }
    ],
    "sg:phone":"+1 615 451 7337",
    "sg:postcode":"37066",
    "sg:province":"TN",
    "sg:tags":[
        "aircraft",
        "storage"
    ],
    "wof:name":"Nashville Air",
    "wof:placetype":"venue"
},
  "geometry": {"coordinates":[-86.43185200000001,36.375609],"type":"Point"}
}