{
  "type": "Feature",
  "properties": {
    "addr:full":"2608 Avery Ave Memphis TN 38112",
    "addr:housenumber":"2608",
    "addr:postcode":"38112",
    "addr:street":"Avery Ave",
    "iso:country":"US",
    "sg:address":"2608 Avery Ave",
    "sg:city":"Memphis",
    "sg:classifiers":[
        {
            "category":"Banks & Credit Unions",
            "subcategory":"Bank",
            "type":"Services"
        }
    ],
    "sg:phone":"+1 901 321 1200",
    "sg:postcode":"38112",
    "sg:province":"TN",
    "sg:website":"http://www.cityofmemphiscu.org",
    "wof:name":"Memphis City Government",
    "wof:placetype":"venue"
},
  "geometry": {"coordinates":[-89.97421300000001,35.130862],"type":"Point"}
}