{
  "type": "Feature",
  "properties": {
    "iso:country":"US",
    "sg:address":"4295 Cromwell Rd",
    "sg:city":"Chattanooga",
    "sg:classifiers":[
        {
            "category":"Retail",
            "subcategory":"Funeral Services",
            "type":"Services"
        }
    ],
    "sg:phone":"+1 423 499 4430",
    "sg:postcode":"37421",
    "sg:province":"TN",
    "sg:tags":[
        "consulting",
        "referral"
    ],
    "wof:name":"Advanced Planning Associates",
    "wof:placetype":"venue"
},
  "geometry": {"coordinates":[-85.198635,35.066118],"type":"Point"}
}