{
  "type": "Feature",
  "properties": {
    "iso:country":"US",
    "sg:address":"1079 Dove Rd",
    "sg:city":"Rock Island",
    "sg:classifiers":[
        {
            "category":"Home & Garden",
            "subcategory":"Garden Supply",
            "type":"Retail Goods"
        }
    ],
    "sg:phone":"+1 931 686 2612",
    "sg:postcode":"38581",
    "sg:province":"TN",
    "wof:name":"Rigsby Nursery & Landscaping",
    "wof:placetype":"venue"
},
  "geometry": {"coordinates":[-85.662481,35.807153],"type":"Point"}
}