{
  "type": "Feature",
  "properties": {
    "addr:full":"1545 Ridgemont Dr La Vergne TN 37086",
    "addr:housenumber":"1545",
    "addr:postcode":"37086",
    "addr:street":"Ridgemont Dr",
    "iso:country":"US",
    "sg:address":"1545 Ridgemont Dr",
    "sg:city":"La Vergne",
    "sg:classifiers":[
        {
            "category":"Professional",
            "subcategory":"Management & Consulting",
            "type":"Services"
        }
    ],
    "sg:phone":"+1 615 287 0866",
    "sg:postcode":"37086",
    "sg:province":"TN",
    "sg:tags":[
        "consultant"
    ],
    "wof:name":"LDA Consulting",
    "wof:placetype":"venue"
},
  "geometry": {"coordinates":[-86.54442,36.001096],"type":"Point"}
}