{
  "type": "Feature",
  "properties": {
    "iso:country":"US",
    "sg:address":"6398 US Hwy 41 A",
    "sg:city":"Pleasant View",
    "sg:classifiers":[
        {
            "category":"Real Estate",
            "subcategory":"Real Estate Agent",
            "type":"Services"
        }
    ],
    "sg:phone":"+1 615 746 0005",
    "sg:postcode":"37146",
    "sg:province":"TN",
    "wof:name":"Stephen Carr & Assoc Inc",
    "wof:placetype":"venue"
},
  "geometry": {"coordinates":[-87.029546,36.398908],"type":"Point"}
}