{
  "type": "Feature",
  "properties": {
    "iso:country":"US",
    "sg:address":"2835 E Wood St",
    "sg:city":"Paris",
    "sg:classifiers":[
        {
            "category":"Utilities",
            "subcategory":"Mobile Phone",
            "type":"Services"
        },
        {
            "category":"Wholesale",
            "subcategory":"Electrical",
            "type":"Manufacturing & Wholesale Goods"
        }
    ],
    "sg:phone":"+1 731 644 9378",
    "sg:postcode":"38242",
    "sg:province":"TN",
    "sg:tags":[
        "communication",
        "telephone",
        "cellular",
        "equipment"
    ],
    "wof:name":"Tennessee West Communications",
    "wof:placetype":"venue"
},
  "geometry": {"coordinates":[-88.269984,36.324999],"type":"Point"}
}