{
  "type": "Feature",
  "properties": {
    "addr:full":"1007 N Main St Bolivar TN 38008",
    "addr:housenumber":"1007",
    "addr:postcode":"38008",
    "addr:street":"N Main St Bolivar",
    "iso:country":"US",
    "sg:address":"1007 N Main St",
    "sg:city":"Bolivar",
    "sg:classifiers":[
        {
            "category":"Autos & Motor Vehicles",
            "subcategory":"Fuel & Gas Station",
            "type":"Retail Goods"
        }
    ],
    "sg:phone":"+1 731 658 5988",
    "sg:postcode":"38008",
    "sg:province":"TN",
    "sg:tags":[
        "oil"
    ],
    "wof:name":"Houston's Bp",
    "wof:placetype":"venue"
},
  "geometry": {"coordinates":[-88.97844600000001,35.27287],"type":"Point"}
}