{
  "type": "Feature",
  "properties": {
    "addr:full":"2025 Todds Dr Kingsport TN 37660",
    "addr:housenumber":"2025",
    "addr:postcode":"37660",
    "addr:street":"Todds Dr",
    "iso:country":"US",
    "sg:address":"2025 Todds Dr",
    "sg:city":"Kingsport",
    "sg:classifiers":[
        {
            "category":"Organizations",
            "subcategory":"Membership Organization",
            "type":"Services"
        }
    ],
    "sg:phone":"+1 423 246 1802",
    "sg:postcode":"37660",
    "sg:province":"TN",
    "sg:website":"www.madd.org",
    "wof:name":"Mothers Against Drunk Driving",
    "wof:placetype":"venue"
},
  "geometry": {"coordinates":[-82.58711700000001,36.563009],"type":"Point"}
}