{
  "type": "Feature",
  "properties": {
    "iso:country":"US",
    "sg:address":"1339 Dunlop Ln",
    "sg:city":"Clarksville",
    "sg:classifiers":[
        {
            "category":"Professional",
            "type":"Services"
        }
    ],
    "sg:phone":"+1 931 648 3180",
    "sg:postcode":"37043",
    "sg:province":"TN",
    "wof:name":"Richard Moseley",
    "wof:placetype":"venue"
},
  "geometry": {"coordinates":[-87.251491,36.578323],"type":"Point"}
}