{
  "type": "Feature",
  "properties": {
    "iso:country":"US",
    "sg:address":"314 Fox Rd",
    "sg:city":"Knoxville",
    "sg:classifiers":[
        {
            "category":"Professional",
            "subcategory":"Management & Consulting",
            "type":"Services"
        }
    ],
    "sg:phone":"+1 865 470 0765",
    "sg:postcode":"37922",
    "sg:province":"TN",
    "sg:tags":[
        "business"
    ],
    "wof:name":"Knxnet Co",
    "wof:placetype":"venue"
},
  "geometry": {"coordinates":[-84.114514,35.897462],"type":"Point"}
}