{
  "type": "Feature",
  "properties": {
    "iso:country":"US",
    "sg:address":"1482 Monroe Ave",
    "sg:city":"Memphis",
    "sg:classifiers":[
        {
            "category":"Professional",
            "subcategory":"Lawyer & Legal Services",
            "type":"Services"
        }
    ],
    "sg:phone":"+1 901 521 9888",
    "sg:postcode":"38104",
    "sg:province":"TN",
    "sg:tags":[
        "attorney"
    ],
    "wof:name":"Walter Buford",
    "wof:placetype":"venue"
},
  "geometry": {"coordinates":[-90.012151,35.137398],"type":"Point"}
}