{
  "type": "Feature",
  "properties": {
    "iso:country":"US",
    "sg:address":"30 Market Sq SW",
    "sg:city":"Knoxville",
    "sg:classifiers":[
        {
            "category":"Real Estate",
            "subcategory":"Architect",
            "type":"Services"
        }
    ],
    "sg:phone":"+1 865 546 8232",
    "sg:postcode":"37902",
    "sg:province":"TN",
    "wof:name":"Architects Weeks Ambrose Inc",
    "wof:placetype":"venue"
},
  "geometry": {"coordinates":[-83.919738,35.96559],"type":"Point"}
}