{
  "type": "Feature",
  "properties": {
    "addr:full":"6116 Shallowford Rd Chattanooga TN 37421",
    "addr:housenumber":"6116",
    "addr:postcode":"37421",
    "addr:street":"Shallowford Rd",
    "iso:country":"US",
    "sg:address":"6116 Shallowford Rd",
    "sg:city":"Chattanooga",
    "sg:classifiers":[
        {
            "category":"Health Services",
            "subcategory":"Hospital",
            "type":"Services"
        },
        {
            "category":"Health Services",
            "subcategory":"Clinic",
            "type":"Services"
        }
    ],
    "sg:phone":"+1 423 892 5059",
    "sg:postcode":"37421",
    "sg:province":"TN",
    "sg:tags":[
        "home",
        "specialty"
    ],
    "wof:name":"Hospice Care Of East Tennessee",
    "wof:placetype":"venue"
},
  "geometry": {"coordinates":[-85.183331,35.053197],"type":"Point"}
}