{
  "type": "Feature",
  "properties": {
    "iso:country":"US",
    "sg:address":"10700 Old Cox Pike",
    "sg:city":"Bon Aqua",
    "sg:classifiers":[
        {
            "category":"Building & Trades",
            "subcategory":"Construction",
            "type":"Services"
        }
    ],
    "sg:phone":"+1 931 670 6225",
    "sg:postcode":"37025",
    "sg:province":"TN",
    "sg:tags":[
        "concrete",
        "contractor"
    ],
    "wof:name":"Anderson Concrete Finishing",
    "wof:placetype":"venue"
},
  "geometry": {"coordinates":[-87.21475700000001,35.940339],"type":"Point"}
}