{
  "type": "Feature",
  "properties": {
    "iso:country":"US",
    "sg:address":"2631 Davies Plantation Rd",
    "sg:city":"Cordova",
    "sg:classifiers":[
        {
            "category":"Utilities",
            "subcategory":"Telephone",
            "type":"Services"
        }
    ],
    "sg:phone":"+1 901 382 5966",
    "sg:postcode":"38016",
    "sg:province":"TN",
    "sg:tags":[
        "communication",
        "isp",
        "provider",
        "internet"
    ],
    "wof:name":"M2 Hosts Web Design & Hosting",
    "wof:placetype":"venue"
},
  "geometry": {"coordinates":[-89.74610699999999,35.1974],"type":"Point"}
}