{
  "type": "Feature",
  "properties": {
    "iso:country":"US",
    "sg:address":"65 Blythe St",
    "sg:city":"Savannah",
    "sg:classifiers":[
        {
            "category":"Building & Trades",
            "subcategory":"Construction",
            "type":"Services"
        }
    ],
    "sg:phone":"+1 731 926 2307",
    "sg:postcode":"38372",
    "sg:province":"TN",
    "sg:tags":[
        "excavating",
        "contractor"
    ],
    "wof:name":"Cromwell Excavating",
    "wof:placetype":"venue"
},
  "geometry": {"coordinates":[-88.234184,35.201576],"type":"Point"}
}