{
  "type": "Feature",
  "properties": {
    "addr:full":"3915 Air Park St Memphis TN 38118",
    "addr:housenumber":"3915",
    "addr:postcode":"38118",
    "addr:street":"Air Park St",
    "iso:country":"US",
    "sg:address":"3915 Air Park St",
    "sg:city":"Memphis",
    "sg:classifiers":[
        {
            "category":"Manufacturing",
            "subcategory":"Chemicals & Compounds",
            "type":"Manufacturing & Wholesale Goods"
        }
    ],
    "sg:phone":"+1 901 363 4340",
    "sg:postcode":"38118",
    "sg:province":"TN",
    "sg:tags":[
        "inorganic",
        "industrial"
    ],
    "sg:website":"www.deltaforemost.com",
    "wof:name":"Delta Foremost Chemical Corp",
    "wof:placetype":"venue"
},
  "geometry": {"coordinates":[-89.931314,35.042666],"type":"Point"}
}