{
  "type": "Feature",
  "properties": {
    "addr:full":"451 Sequoyah Dr Newport TN 37821",
    "addr:housenumber":"451",
    "addr:postcode":"37821",
    "addr:street":"Sequoyah Dr",
    "iso:country":"US",
    "sg:address":"451 Sequoyah Dr",
    "sg:city":"Newport",
    "sg:classifiers":[
        {
            "category":"Personal",
            "type":"Services"
        }
    ],
    "sg:phone":"+1 423 625 0435",
    "sg:postcode":"37821",
    "sg:province":"TN",
    "wof:name":"Total Body Massage",
    "wof:placetype":"venue"
},
  "geometry": {"coordinates":[-83.19568599999999,35.947604],"type":"Point"}
}