{
  "type": "Feature",
  "properties": {
    "iso:country":"US",
    "sg:address":"3354 Winbrook Dr",
    "sg:city":"Memphis",
    "sg:classifiers":[
        {
            "category":"Wholesale",
            "subcategory":"Machinery & Supplies",
            "type":"Manufacturing & Wholesale Goods"
        },
        {
            "category":"Wholesale",
            "subcategory":"Durable Goods & Equipment",
            "type":"Manufacturing & Wholesale Goods"
        }
    ],
    "sg:phone":"+1 901 346 4433",
    "sg:postcode":"38116",
    "sg:province":"TN",
    "sg:tags":[
        "abrasive",
        "tool",
        "importer",
        "file"
    ],
    "sg:website":"www.fedfile.com",
    "wof:name":"Federal File Co Inc",
    "wof:placetype":"venue"
},
  "geometry": {"coordinates":[-89.99721599999999,35.058926],"type":"Point"}
}