{
  "type": "Feature",
  "properties": {
    "iso:country":"US",
    "sg:address":"408 Parkside Cir",
    "sg:city":"Lebanon",
    "sg:classifiers":[
        {
            "category":"Freight",
            "type":"Transportation"
        }
    ],
    "sg:phone":"+1 615 443 1721",
    "sg:postcode":"37087",
    "sg:province":"TN",
    "sg:tags":[
        "operator",
        "local",
        "trucking"
    ],
    "wof:name":"Pfingsten Trucking",
    "wof:placetype":"venue"
},
  "geometry": {"coordinates":[-86.28506,36.194791],"type":"Point"}
}