{
  "type": "Feature",
  "properties": {
    "addr:full":"130 Hillcrest Dr Clarksville TN 37043",
    "addr:housenumber":"130",
    "addr:postcode":"37043",
    "addr:street":"Hillcrest Dr",
    "iso:country":"US",
    "sg:address":"130 Hillcrest Dr",
    "sg:city":"Clarksville",
    "sg:classifiers":[
        {
            "category":"Professional",
            "subcategory":"Management & Consulting",
            "type":"Services"
        }
    ],
    "sg:phone":"+1 931 503 0697",
    "sg:postcode":"37043",
    "sg:province":"TN",
    "wof:name":"Big Bear Management",
    "wof:placetype":"venue"
},
  "geometry": {"coordinates":[-87.30443200000001,36.515163],"type":"Point"}
}