{
  "type": "Feature",
  "properties": {
    "iso:country":"US",
    "sg:address":"1339 Ski Mountain Rd",
    "sg:city":"Gatlinburg",
    "sg:classifiers":[
        {
            "category":"Recreation",
            "subcategory":"Amusement Park",
            "type":"Entertainment"
        }
    ],
    "sg:phone":"+1 865 430 7555",
    "sg:postcode":"37738",
    "sg:province":"TN",
    "wof:name":"Del Gatlin Games",
    "wof:placetype":"venue"
},
  "geometry": {"coordinates":[-83.560384,35.703024],"type":"Point"}
}