{
  "type": "Feature",
  "properties": {
    "addr:full":"1598 Crestview Dr Madison TN 37115",
    "addr:housenumber":"1598",
    "addr:postcode":"37115",
    "addr:street":"Crestview Dr",
    "iso:country":"US",
    "sg:address":"1598 Crestview Dr",
    "sg:city":"Madison",
    "sg:classifiers":[
        {
            "category":"Health Services",
            "subcategory":"Health Practitioner",
            "type":"Services"
        }
    ],
    "sg:phone":"+1 615 860 3852",
    "sg:postcode":"37115",
    "sg:province":"TN",
    "wof:name":"Christian Psychological &",
    "wof:placetype":"venue"
},
  "geometry": {"coordinates":[-86.70576,36.291537],"type":"Point"}
}