{
  "type": "Feature",
  "properties": {
    "addr:full":"11010 Summerhouse Way Knoxville TN 37931",
    "addr:housenumber":"11010",
    "addr:postcode":"37931",
    "addr:street":"Summerhouse Way",
    "iso:country":"US",
    "sg:address":"11010 Summerhouse Way",
    "sg:city":"Knoxville",
    "sg:classifiers":[
        {
            "category":"Real Estate",
            "subcategory":"Real Estate Agent",
            "type":"Services"
        }
    ],
    "sg:phone":"+1 865 927 0091",
    "sg:postcode":"37931",
    "sg:province":"TN",
    "sg:tags":[
        "appraiser"
    ],
    "wof:name":"Browning Appraisal Group",
    "wof:placetype":"venue"
},
  "geometry": {"coordinates":[-84.18877999999999,35.973131],"type":"Point"}
}