{
  "type": "Feature",
  "properties": {
    "iso:country":"US",
    "sg:address":"2417 W End Ave",
    "sg:city":"Nashville",
    "sg:classifiers":[
        {
            "category":"Government",
            "subcategory":"Office",
            "type":"Public Place"
        }
    ],
    "sg:phone":"+1 615 343 2563",
    "sg:postcode":"37203",
    "sg:province":"TN",
    "sg:tags":[
        "educational",
        "program",
        "administrative"
    ],
    "wof:name":"Tennessee Holocaust Commission",
    "wof:placetype":"venue"
},
  "geometry": {"coordinates":[-86.806471,36.147928],"type":"Point"}
}