{
  "type": "Feature",
  "properties": {
    "iso:country":"US",
    "sg:address":"1141 Shelton Ave",
    "sg:city":"Nashville",
    "sg:classifiers":[
        {
            "category":"Shopping",
            "subcategory":"Computers & Home Electronics",
            "type":"Retail Goods"
        }
    ],
    "sg:phone":"+1 615 255 3990",
    "sg:postcode":"37216",
    "sg:province":"TN",
    "sg:tags":[
        "audio"
    ],
    "wof:name":"Rag X Visual Arts Agency",
    "wof:placetype":"venue"
},
  "geometry": {"coordinates":[-86.72934100000001,36.209326],"type":"Point"}
}