{
  "type": "Feature",
  "properties": {
    "addr:full":"71 Fesslers Ln Nashville TN 37210",
    "addr:housenumber":"71",
    "addr:postcode":"37210",
    "addr:street":"Fesslers Ln",
    "iso:country":"US",
    "sg:address":"71 Fesslers Ln",
    "sg:city":"Nashville",
    "sg:classifiers":[
        {
            "category":"Retail",
            "subcategory":"Laundry & Dry Cleaning",
            "type":"Services"
        }
    ],
    "sg:phone":"+1 615 255 0535",
    "sg:postcode":"37210",
    "sg:province":"TN",
    "sg:tags":[
        "industrial",
        "towel",
        "uniform",
        "supply"
    ],
    "wof:name":"Unifirst",
    "wof:placetype":"venue"
},
  "geometry": {"coordinates":[-86.74355,36.155445],"type":"Point"}
}