{
  "type": "Feature",
  "properties": {
    "addr:full":"100 Winners Cir N Ste 158 Brentwood TN 37027",
    "addr:housenumber":"100",
    "addr:postcode":"37027",
    "addr:street":"Winners Cir N Ste 158",
    "iso:country":"US",
    "sg:address":"100 Winners Cir N Ste 158",
    "sg:city":"Brentwood",
    "sg:classifiers":[
        {
            "category":"Manufacturing",
            "subcategory":"Food",
            "type":"Manufacturing & Wholesale Goods"
        }
    ],
    "sg:phone":"+1 615 383 5001",
    "sg:postcode":"37027",
    "sg:province":"TN",
    "sg:tags":[
        "product",
        "processing"
    ],
    "wof:name":"Dixie Lily Foods",
    "wof:placetype":"venue"
},
  "geometry": {"coordinates":[-86.80806699999999,36.036839],"type":"Point"}
}