{
  "type": "Feature",
  "properties": {
    "iso:country":"US",
    "sg:address":"178 Pickens Bridge Rd",
    "sg:city":"Gray",
    "sg:classifiers":[
        {
            "category":"Organizations",
            "subcategory":"Religious Organization",
            "type":"Services"
        }
    ],
    "sg:phone":"+1 423 282 0018",
    "sg:postcode":"37615",
    "sg:province":"TN",
    "sg:tags":[
        "church"
    ],
    "wof:name":"Calvary Church Outreach Mnstry",
    "wof:placetype":"venue"
},
  "geometry": {"coordinates":[-82.40671500000001,36.390663],"type":"Point"}
}