{
  "type": "Feature",
  "properties": {
    "iso:country":"US",
    "sg:address":"2702 Greystone Rd",
    "sg:city":"Nashville",
    "sg:classifiers":[
        {
            "category":"Real Estate",
            "subcategory":"Real Estate Agent",
            "type":"Services"
        }
    ],
    "sg:phone":"+1 615 292 8200",
    "sg:postcode":"37204",
    "sg:province":"TN",
    "wof:name":"Paramount Properties",
    "wof:placetype":"venue"
},
  "geometry": {"coordinates":[-86.76824000000001,36.118955],"type":"Point"}
}