{
  "type": "Feature",
  "properties": {
    "iso:country":"US",
    "sg:address":"535 W Main St",
    "sg:city":"Rogersville",
    "sg:classifiers":[
        {
            "category":"Retail",
            "subcategory":"Auto Repair",
            "type":"Services"
        }
    ],
    "sg:phone":"+1 423 272 3263",
    "sg:postcode":"37857",
    "sg:province":"TN",
    "sg:tags":[
        "repairing",
        "automobile",
        "general"
    ],
    "wof:name":"Glenn's Auto Repair",
    "wof:placetype":"venue"
},
  "geometry": {"coordinates":[-83.012199,36.404506],"type":"Point"}
}