{
  "type": "Feature",
  "properties": {
    "addr:full":"4284 Summer Ave Memphis TN 38122",
    "addr:housenumber":"4284",
    "addr:postcode":"38122",
    "addr:street":"Summer Ave",
    "iso:country":"US",
    "sg:address":"4284 Summer Ave",
    "sg:city":"Memphis",
    "sg:classifiers":[
        {
            "category":"Shopping",
            "subcategory":"Clothing, Apparel, & Fashions",
            "type":"Retail Goods"
        }
    ],
    "sg:phone":"+1 901 818 0333",
    "sg:postcode":"38122",
    "sg:province":"TN",
    "sg:website":"www.rainbowshops.com",
    "wof:name":"Rainbow",
    "wof:placetype":"venue"
},
  "geometry": {"coordinates":[-89.914736,35.148931],"type":"Point"}
}