{
  "type": "Feature",
  "properties": {
    "iso:country":"US",
    "sg:address":"120 S 14th Ave",
    "sg:city":"Humboldt",
    "sg:classifiers":[
        {
            "category":"Personal",
            "subcategory":"Beauty Salon",
            "type":"Services"
        }
    ],
    "sg:phone":"+1 731 824 0028",
    "sg:postcode":"38343",
    "sg:province":"TN",
    "wof:name":"A KUT Above Full Svc Salon",
    "wof:placetype":"venue"
},
  "geometry": {"coordinates":[-88.91710999999999,35.819694],"type":"Point"}
}