{
  "type": "Feature",
  "properties": {
    "iso:country":"US",
    "sg:address":"2700 S Roan St",
    "sg:city":"Johnson City",
    "sg:classifiers":[
        {
            "category":"Professional",
            "subcategory":"Employment Agencies",
            "type":"Services"
        }
    ],
    "sg:phone":"+1 423 928 3005",
    "sg:postcode":"37601",
    "sg:province":"TN",
    "sg:tags":[
        "help",
        "contractor"
    ],
    "sg:website":"www.laborfinders.com",
    "wof:name":"Labor Finders",
    "wof:placetype":"venue"
},
  "geometry": {"coordinates":[-82.32928,36.292141],"type":"Point"}
}