{
  "type": "Feature",
  "properties": {
    "addr:full":"600 Henley St Knoxville TN 37902",
    "addr:housenumber":"600",
    "addr:postcode":"37902",
    "addr:street":"Henley St",
    "iso:country":"US",
    "sg:address":"600 Henley St",
    "sg:city":"Knoxville",
    "sg:classifiers":[
        {
            "category":"Sports & Exercise",
            "subcategory":"Bowling",
            "type":"Entertainment"
        }
    ],
    "sg:phone":"+1 865 974 5301",
    "sg:postcode":"37902",
    "sg:province":"TN",
    "sg:tags":[
        "center"
    ],
    "wof:name":"Centre Thomson Bowling",
    "wof:placetype":"venue"
},
  "geometry": {"coordinates":[-83.92159100000001,35.96176],"type":"Point"}
}