{
  "type": "Feature",
  "properties": {
    "addr:full":"266 Morrison St Gallatin TN 37066",
    "addr:housenumber":"266",
    "addr:postcode":"37066",
    "addr:street":"Morrison St",
    "iso:country":"US",
    "sg:address":"266 Morrison St",
    "sg:city":"Gallatin",
    "sg:classifiers":[
        {
            "category":"Organizations",
            "subcategory":"Community Association",
            "type":"Services"
        }
    ],
    "sg:phone":"+1 615 230 3007",
    "sg:postcode":"37066",
    "sg:province":"TN",
    "sg:tags":[
        "military"
    ],
    "wof:name":"Veterans House Vfw & Vietnam",
    "wof:placetype":"venue"
},
  "geometry": {"coordinates":[-86.437488,36.384949],"type":"Point"}
}