{
  "type": "Feature",
  "properties": {
    "iso:country":"US",
    "sg:address":"29 Ridgecrest Rd",
    "sg:city":"Jackson",
    "sg:classifiers":[
        {
            "category":"Manufacturing",
            "subcategory":"Metals",
            "type":"Manufacturing & Wholesale Goods"
        }
    ],
    "sg:phone":"+1 731 668 8105",
    "sg:postcode":"38305",
    "sg:province":"TN",
    "sg:tags":[
        "coating"
    ],
    "wof:name":"PPG Porter Paints",
    "wof:placetype":"venue"
},
  "geometry": {"coordinates":[-88.827504,35.667567],"type":"Point"}
}