{
  "type": "Feature",
  "properties": {
    "iso:country":"US",
    "sg:address":"5724 Summer Trees Dr",
    "sg:city":"Memphis",
    "sg:classifiers":[
        {
            "category":"Government",
            "subcategory":"Office",
            "type":"Public Place"
        }
    ],
    "sg:phone":"+1 901 372 7962",
    "sg:postcode":"38134",
    "sg:province":"TN",
    "sg:tags":[
        "environmental",
        "consulting"
    ],
    "wof:name":"Petroleom Partners",
    "wof:placetype":"venue"
},
  "geometry": {"coordinates":[-89.871611,35.165502],"type":"Point"}
}