{
  "type": "Feature",
  "properties": {
    "iso:country":"US",
    "sg:address":"2006 Johnson Industrial Blvd",
    "sg:city":"Nolensville",
    "sg:classifiers":[
        {
            "category":"Social Services",
            "subcategory":"Child Care",
            "type":"Services"
        }
    ],
    "sg:phone":"+1 615 776 7462",
    "sg:postcode":"37135",
    "sg:province":"TN",
    "sg:tags":[
        "day"
    ],
    "wof:name":"Open House Learning Center",
    "wof:placetype":"venue"
},
  "geometry": {"coordinates":[-86.666312,35.956756],"type":"Point"}
}