{
  "type": "Feature",
  "properties": {
    "addr:full":"829 Bob Kirby Rd Knoxville TN 37923",
    "addr:housenumber":"829",
    "addr:postcode":"37923",
    "addr:street":"Bob Kirby Rd",
    "iso:country":"US",
    "sg:address":"829 Bob Kirby Rd",
    "sg:city":"Knoxville",
    "sg:classifiers":[
        {
            "category":"Building & Trades",
            "subcategory":"Electrical",
            "type":"Services"
        }
    ],
    "sg:phone":"+1 865 690 3710",
    "sg:postcode":"37923",
    "sg:province":"TN",
    "sg:tags":[
        "electrical",
        "contractor"
    ],
    "wof:name":"Halcomb Electric",
    "wof:placetype":"venue"
},
  "geometry": {"coordinates":[-84.116668,35.929909],"type":"Point"}
}