{
  "type": "Feature",
  "properties": {
    "iso:country":"US",
    "sg:address":"305 Hwy 31",
    "sg:city":"Mooresburg",
    "sg:classifiers":[
        {
            "category":"Building & Trades",
            "subcategory":"Construction",
            "type":"Services"
        }
    ],
    "sg:phone":"+1 423 272 2375",
    "sg:postcode":"37811",
    "sg:province":"TN",
    "sg:tags":[
        "general",
        "contractor"
    ],
    "wof:name":"Burwill Construction",
    "wof:placetype":"venue"
},
  "geometry": {"coordinates":[-83.22825,36.345847],"type":"Point"}
}