{
  "type": "Feature",
  "properties": {
    "iso:country":"US",
    "sg:address":"757 Sundial Ln",
    "sg:city":"Seymour",
    "sg:classifiers":[
        {
            "category":"Building & Trades",
            "subcategory":"Construction",
            "type":"Services"
        }
    ],
    "sg:phone":"+1 865 577 8555",
    "sg:postcode":"37865",
    "sg:province":"TN",
    "sg:tags":[
        "hanging",
        "contractor"
    ],
    "wof:name":"Claytons Painting Co",
    "wof:placetype":"venue"
},
  "geometry": {"coordinates":[-83.75222100000001,35.888597],"type":"Point"}
}