{
  "type": "Feature",
  "properties": {
    "addr:full":"586 Airways Blvd Jackson TN 38301",
    "addr:housenumber":"586",
    "addr:postcode":"38301",
    "addr:street":"Airways Blvd",
    "iso:country":"US",
    "sg:address":"586 Airways Blvd",
    "sg:city":"Jackson",
    "sg:classifiers":[
        {
            "category":"Real Estate",
            "subcategory":"Real Estate Agent",
            "type":"Services"
        }
    ],
    "sg:phone":"+1 731 664 3184",
    "sg:postcode":"38301",
    "sg:province":"TN",
    "wof:name":"Elsebae Realty Inc",
    "wof:placetype":"venue"
},
  "geometry": {"coordinates":[-88.84478,35.617625],"type":"Point"}
}