{
  "type": "Feature",
  "properties": {
    "iso:country":"US",
    "sg:address":"6551 Hwy 104 E",
    "sg:city":"Dyersburg",
    "sg:classifiers":[
        {
            "category":"Food & Beverages",
            "subcategory":"Groceries & Convenience Stores",
            "type":"Retail Goods"
        }
    ],
    "sg:phone":"+1 731 285 9076",
    "sg:postcode":"38024",
    "sg:province":"TN",
    "wof:name":"B & B Market",
    "wof:placetype":"venue"
},
  "geometry": {"coordinates":[-89.264611,36.02554],"type":"Point"}
}