{
  "type": "Feature",
  "properties": {
    "iso:country":"US",
    "sg:address":"2929 Cliffside Rd",
    "sg:city":"Kingsport",
    "sg:classifiers":[
        {
            "category":"Taxi",
            "type":"Transportation"
        }
    ],
    "sg:phone":"+1 423 246 2412",
    "sg:postcode":"37664",
    "sg:province":"TN",
    "sg:tags":[
        "cab"
    ],
    "wof:name":"Clemons Cab & Limousine Svc",
    "wof:placetype":"venue"
},
  "geometry": {"coordinates":[-82.52181,36.516408],"type":"Point"}
}