{
  "type": "Feature",
  "properties": {
    "addr:full":"1087 Dancyville Rd Stanton TN 38069",
    "addr:housenumber":"1087",
    "addr:postcode":"38069",
    "addr:street":"Dancyville Rd",
    "iso:country":"US",
    "sg:address":"1087 Dancyville Rd",
    "sg:city":"Stanton",
    "sg:classifiers":[
        {
            "category":"Professional",
            "type":"Services"
        }
    ],
    "sg:phone":"+1 901 335 2703",
    "sg:postcode":"38069",
    "sg:province":"TN",
    "wof:name":"Pentz Trimming",
    "wof:placetype":"venue"
},
  "geometry": {"coordinates":[-89.331778,35.432911],"type":"Point"}
}