{
  "type": "Feature",
  "properties": {
    "iso:country":"US",
    "sg:address":"923 E College St",
    "sg:city":"Pulaski",
    "sg:classifiers":[
        {
            "category":"Manufacturing",
            "subcategory":"Lumber",
            "type":"Manufacturing & Wholesale Goods"
        }
    ],
    "sg:phone":"+1 931 424 4009",
    "sg:postcode":"38478",
    "sg:province":"TN",
    "sg:tags":[
        "government"
    ],
    "sg:website":"www.state.tn.us",
    "wof:name":"Forestry Div",
    "wof:placetype":"venue"
},
  "geometry": {"coordinates":[-87.01732,35.194059],"type":"Point"}
}