{
  "type": "Feature",
  "properties": {
    "addr:full":"6597 Clarksville Pike Joelton TN 37080",
    "addr:housenumber":"6597",
    "addr:postcode":"37080",
    "addr:street":"Clarksville Pike",
    "iso:country":"US",
    "sg:address":"6597 Clarksville Pike",
    "sg:city":"Joelton",
    "sg:classifiers":[
        {
            "category":"Bars & Pubs",
            "type":"Food & Drink"
        }
    ],
    "sg:phone":"+1 615 299 8053",
    "sg:postcode":"37080",
    "sg:province":"TN",
    "wof:name":"Mike's Place",
    "wof:placetype":"venue"
},
  "geometry": {"coordinates":[-86.910771,36.322959],"type":"Point"}
}