{
  "type": "Feature",
  "properties": {
    "addr:full":"33 Clairpointe Cove Jackson TN 38305",
    "addr:housenumber":"33",
    "addr:postcode":"38305",
    "addr:street":"Clairpointe Cove",
    "iso:country":"US",
    "sg:address":"33 Clairpointe Cove",
    "sg:city":"Jackson",
    "sg:classifiers":[
        {
            "category":"Building & Trades",
            "subcategory":"Construction",
            "type":"Services"
        }
    ],
    "sg:phone":"+1 731 424 6823",
    "sg:postcode":"38305",
    "sg:province":"TN",
    "sg:tags":[
        "contractor"
    ],
    "wof:name":"Gutter Pro LLC",
    "wof:placetype":"venue"
},
  "geometry": {"coordinates":[-88.78425900000001,35.695066],"type":"Point"}
}