{
  "type": "Feature",
  "properties": {
    "iso:country":"US",
    "sg:address":"104 S Magnolia St",
    "sg:city":"Maryville",
    "sg:classifiers":[
        {
            "category":"Shopping",
            "subcategory":"Books",
            "type":"Retail Goods"
        }
    ],
    "sg:phone":"+1 865 983 1545",
    "sg:postcode":"37803",
    "sg:province":"TN",
    "sg:tags":[
        "used",
        "merchandise"
    ],
    "wof:name":"Cover To Cover",
    "wof:placetype":"venue"
},
  "geometry": {"coordinates":[-83.98134400000001,35.747291],"type":"Point"}
}