{
  "type": "Feature",
  "properties": {
    "iso:country":"US",
    "sg:address":"731 Old Hwy 70",
    "sg:city":"Harriman",
    "sg:classifiers":[
        {
            "category":"Building & Trades",
            "subcategory":"Construction",
            "type":"Services"
        }
    ],
    "sg:phone":"+1 865 882 6552",
    "sg:postcode":"37748",
    "sg:province":"TN",
    "sg:tags":[
        "paving",
        "contractor"
    ],
    "wof:name":"Holder's Paving & Excavating",
    "wof:placetype":"venue"
},
  "geometry": {"coordinates":[-84.575371,35.87051],"type":"Point"}
}