{
  "type": "Feature",
  "properties": {
    "iso:country":"US",
    "sg:address":"1009 Mount Lebanon Rd",
    "sg:city":"Maryville",
    "sg:classifiers":[
        {
            "category":"Government",
            "subcategory":"Office",
            "type":"Public Place"
        }
    ],
    "sg:phone":"+1 865 681 8059",
    "sg:postcode":"37804",
    "sg:province":"TN",
    "sg:tags":[
        "village"
    ],
    "wof:name":"City Of Alcoa",
    "wof:placetype":"venue"
},
  "geometry": {"coordinates":[-83.91588299999999,35.794646],"type":"Point"}
}