{
  "type": "Feature",
  "properties": {
    "addr:full":"224 State Hwy 107 Jonesborough TN 37659",
    "addr:housenumber":"224",
    "addr:postcode":"37659",
    "addr:street":"State Hwy 107",
    "iso:country":"US",
    "sg:address":"224 State Hwy 107",
    "sg:city":"Jonesborough",
    "sg:classifiers":[
        {
            "category":"Farming",
            "subcategory":"Farm",
            "type":"Manufacturing & Wholesale Goods"
        }
    ],
    "sg:phone":"+1 423 913 2900",
    "sg:postcode":"37659",
    "sg:province":"TN",
    "wof:name":"Smith Farms & Produce",
    "wof:placetype":"venue"
},
  "geometry": {"coordinates":[-82.4701,36.20407],"type":"Point"}
}