{
  "type": "Feature",
  "properties": {
    "addr:full":"1804 Trace Creek Rd Hohenwald TN 38462",
    "addr:housenumber":"1804",
    "addr:postcode":"38462",
    "addr:street":"Trace Creek Rd",
    "iso:country":"US",
    "sg:address":"1804 Trace Creek Rd",
    "sg:city":"Hohenwald",
    "sg:classifiers":[
        {
            "category":"Professional",
            "subcategory":"Management & Consulting",
            "type":"Services"
        }
    ],
    "sg:phone":"+1 931 796 0796",
    "sg:postcode":"38462",
    "sg:province":"TN",
    "sg:tags":[
        "small",
        "support",
        "computer",
        "business"
    ],
    "wof:name":"TCS",
    "wof:placetype":"venue"
},
  "geometry": {"coordinates":[-87.62628100000001,35.477975],"type":"Point"}
}