{
  "type": "Feature",
  "properties": {
    "addr:full":"502 Hwy 70 Pegram TN 37143",
    "addr:housenumber":"502",
    "addr:postcode":"37143",
    "addr:street":"Hwy 70 Pegram",
    "iso:country":"US",
    "sg:address":"502 Hwy 70",
    "sg:city":"Pegram",
    "sg:classifiers":[
        {
            "category":"Government",
            "subcategory":"Post Office",
            "type":"Public Place"
        }
    ],
    "sg:phone":"+1 615 646 6886",
    "sg:postcode":"37143",
    "sg:province":"TN",
    "wof:name":"US Post Office",
    "wof:placetype":"venue"
},
  "geometry": {"coordinates":[-87.05289,36.101625],"type":"Point"}
}