{
  "type": "Feature",
  "properties": {
    "iso:country":"US",
    "sg:address":"209 N College St",
    "sg:city":"Greeneville",
    "sg:classifiers":[
        {
            "category":"Health Services",
            "subcategory":"Doctor",
            "type":"Services"
        },
        {
            "category":"Health Services",
            "subcategory":"Medical Lab",
            "type":"Services"
        }
    ],
    "sg:phone":"+1 423 639 5781",
    "sg:postcode":"37745",
    "sg:province":"TN",
    "sg:tags":[
        "physician",
        "surgeon",
        "pathology",
        "laboratory"
    ],
    "wof:name":"Greeneville Pathology Assoc PC",
    "wof:placetype":"venue"
},
  "geometry": {"coordinates":[-82.828243,36.164669],"type":"Point"}
}