{
  "type": "Feature",
  "properties": {
    "addr:full":"106 E Fort St Manchester TN 37355",
    "addr:housenumber":"106",
    "addr:postcode":"37355",
    "addr:street":"E Fort St",
    "iso:country":"US",
    "sg:address":"106 E Fort St",
    "sg:city":"Manchester",
    "sg:classifiers":[
        {
            "category":"Utilities",
            "subcategory":"Fuel Oil & Lpg",
            "type":"Services"
        }
    ],
    "sg:phone":"+1 931 728 7817",
    "sg:postcode":"37355",
    "sg:province":"TN",
    "sg:tags":[
        "liquefied",
        "household",
        "gas",
        "appliance",
        "petroleum"
    ],
    "wof:name":"Henley Propane Gas Co",
    "wof:placetype":"venue"
},
  "geometry": {"coordinates":[-86.088193,35.483528],"type":"Point"}
}