{
  "type": "Feature",
  "properties": {
    "iso:country":"US",
    "sg:address":"708 N Church St",
    "sg:city":"Livingston",
    "sg:classifiers":[
        {
            "category":"Real Estate",
            "subcategory":"Surveying",
            "type":"Services"
        }
    ],
    "sg:phone":"+1 931 823 5903",
    "sg:postcode":"38570",
    "sg:province":"TN",
    "sg:tags":[
        "surveyor"
    ],
    "wof:name":"A B & D Surveying",
    "wof:placetype":"venue"
},
  "geometry": {"coordinates":[-85.32515600000001,36.391171],"type":"Point"}
}