{
  "type": "Feature",
  "properties": {
    "iso:country":"US",
    "sg:address":"204 Mtcs Dr",
    "sg:city":"Murfreesboro",
    "sg:classifiers":[
        {
            "category":"Social Services",
            "subcategory":"Child Care",
            "type":"Services"
        }
    ],
    "sg:phone":"+1 615 895 5050",
    "sg:postcode":"37129",
    "sg:province":"TN",
    "sg:tags":[
        "day"
    ],
    "wof:name":"Parker House Child Care Center",
    "wof:placetype":"venue"
},
  "geometry": {"coordinates":[-86.38800500000001,35.871047],"type":"Point"}
}