{
  "type": "Feature",
  "properties": {
    "iso:country":"US",
    "sg:address":"1163 State Hwy 49",
    "sg:city":"Erin",
    "sg:classifiers":[
        {
            "category":"Communications",
            "type":"Services"
        }
    ],
    "sg:phone":"+1 931 721 4019",
    "sg:postcode":"37061",
    "sg:province":"TN",
    "sg:tags":[
        "call",
        "emergency"
    ],
    "wof:name":"E-911 Central Communication",
    "wof:placetype":"venue"
},
  "geometry": {"coordinates":[-87.732157,36.320466],"type":"Point"}
}