{
  "type": "Feature",
  "properties": {
    "addr:full":"108 Pebble Brook Dr Murfreesboro TN 37127",
    "addr:housenumber":"108",
    "addr:postcode":"37127",
    "addr:street":"Pebble Brook Dr",
    "iso:country":"US",
    "sg:address":"108 Pebble Brook Dr",
    "sg:city":"Murfreesboro",
    "sg:classifiers":[
        {
            "category":"Building & Trades",
            "subcategory":"Construction",
            "type":"Services"
        }
    ],
    "sg:phone":"+1 615 893 3622",
    "sg:postcode":"37127",
    "sg:province":"TN",
    "sg:tags":[
        "roofing",
        "siding",
        "work"
    ],
    "wof:name":"Candy Rody Strombeck",
    "wof:placetype":"venue"
},
  "geometry": {"coordinates":[-86.33275399999999,35.801584],"type":"Point"}
}