{
  "type": "Feature",
  "properties": {
    "iso:country":"US",
    "sg:address":"4901 State Hwy 49 W",
    "sg:city":"Vanleer",
    "sg:classifiers":[
        {
            "category":"Food & Beverages",
            "subcategory":"Groceries & Convenience Stores",
            "type":"Retail Goods"
        },
        {
            "category":"Food & Beverages",
            "subcategory":"Specialty",
            "type":"Retail Goods"
        }
    ],
    "sg:phone":"+1 615 763 2929",
    "sg:postcode":"37181",
    "sg:province":"TN",
    "sg:tags":[
        "market"
    ],
    "wof:name":"Johnson's Market",
    "wof:placetype":"venue"
},
  "geometry": {"coordinates":[-87.445228,36.236009],"type":"Point"}
}