{
  "type": "Feature",
  "properties": {
    "iso:country":"US",
    "sg:address":"745 N Mendenhall Rd",
    "sg:city":"Memphis",
    "sg:classifiers":[
        {
            "category":"Building & Trades",
            "subcategory":"Construction",
            "type":"Services"
        }
    ],
    "sg:phone":"+1 901 230 7578",
    "sg:postcode":"38122",
    "sg:province":"TN",
    "sg:tags":[
        "roofing",
        "commercial"
    ],
    "wof:name":"Top Choice Roofs LLC",
    "wof:placetype":"venue"
},
  "geometry": {"coordinates":[-89.897857,35.151686],"type":"Point"}
}