{
  "type": "Feature",
  "properties": {
    "iso:country":"US",
    "sg:address":"129 Miller Dr",
    "sg:city":"La Vergne",
    "sg:classifiers":[
        {
            "category":"Retail",
            "subcategory":"Repair Shop",
            "type":"Services"
        }
    ],
    "sg:phone":"+1 615 793 6727",
    "sg:postcode":"37086",
    "sg:province":"TN",
    "sg:tags":[
        "welding"
    ],
    "wof:name":"Brown Welding & Repair Service",
    "wof:placetype":"venue"
},
  "geometry": {"coordinates":[-86.551643,36.006597],"type":"Point"}
}