{
  "type": "Feature",
  "properties": {
    "iso:country":"US",
    "sg:address":"3352 Old Airport Rd",
    "sg:city":"White Pine",
    "sg:classifiers":[
        {
            "category":"Professional",
            "subcategory":"Management & Consulting",
            "type":"Services"
        }
    ],
    "sg:phone":"+1 865 674 2246",
    "sg:postcode":"37890",
    "sg:province":"TN",
    "sg:tags":[
        "business"
    ],
    "wof:name":"Your Business Assistant",
    "wof:placetype":"venue"
},
  "geometry": {"coordinates":[-83.27069899999999,36.088819],"type":"Point"}
}