{
  "type": "Feature",
  "properties": {
    "iso:country":"US",
    "sg:address":"104 Thrasher Pike",
    "sg:city":"Soddy Daisy",
    "sg:classifiers":[
        {
            "category":"Restaurant",
            "type":"Food & Drink"
        }
    ],
    "sg:phone":"+1 423 843 3888",
    "sg:postcode":"37379",
    "sg:province":"TN",
    "wof:name":"Idell's Diner",
    "wof:placetype":"venue"
},
  "geometry": {"coordinates":[-85.22757300000001,35.215751],"type":"Point"}
}