{
  "type": "Feature",
  "properties": {
    "iso:country":"US",
    "sg:address":"823 Joy St",
    "sg:city":"Paris",
    "sg:classifiers":[
        {
            "category":"Personal",
            "subcategory":"Beauty Salon",
            "type":"Services"
        }
    ],
    "sg:phone":"+1 731 642 5100",
    "sg:postcode":"38242",
    "sg:province":"TN",
    "sg:tags":[
        "shop"
    ],
    "wof:name":"Monicas Beautique",
    "wof:placetype":"venue"
},
  "geometry": {"coordinates":[-88.312789,36.295915],"type":"Point"}
}