{
  "type": "Feature",
  "properties": {
    "addr:full":"604 S Gay St Knoxville TN 37902",
    "addr:housenumber":"604",
    "addr:postcode":"37902",
    "addr:street":"S Gay St",
    "iso:country":"US",
    "sg:address":"604 S Gay St",
    "sg:city":"Knoxville",
    "sg:classifiers":[
        {
            "category":"Cinema",
            "subcategory":"Movie Theater",
            "type":"Entertainment"
        }
    ],
    "sg:phone":"+1 865 637 6307",
    "sg:postcode":"37902",
    "sg:province":"TN",
    "wof:name":"Living Arts For Students",
    "wof:placetype":"venue"
},
  "geometry": {"coordinates":[-83.917428,35.963933],"type":"Point"}
}