{
  "type": "Feature",
  "properties": {
    "addr:full":"2227 Henpeck Ln Franklin TN 37064",
    "addr:housenumber":"2227",
    "addr:postcode":"37064",
    "addr:street":"Henpeck Ln",
    "iso:country":"US",
    "sg:address":"2227 Henpeck Ln",
    "sg:city":"Franklin",
    "sg:classifiers":[
        {
            "category":"Organizations",
            "subcategory":"Religious Organization",
            "type":"Services"
        }
    ],
    "sg:phone":"+1 615 300 8888",
    "sg:postcode":"37064",
    "sg:province":"TN",
    "wof:name":"We Can Do That",
    "wof:placetype":"venue"
},
  "geometry": {"coordinates":[-86.877325,35.873491],"type":"Point"}
}