{
  "type": "Feature",
  "properties": {
    "iso:country":"US",
    "sg:address":"100 Cindy Cir",
    "sg:city":"Tullahoma",
    "sg:classifiers":[
        {
            "category":"Government",
            "subcategory":"Office",
            "type":"Public Place"
        }
    ],
    "sg:phone":"+1 931 455 5870",
    "sg:postcode":"37388",
    "sg:province":"TN",
    "sg:tags":[
        "course",
        "golf"
    ],
    "wof:name":"Arnold Afb Golf Course",
    "wof:placetype":"venue"
},
  "geometry": {"coordinates":[-86.279977,35.281695],"type":"Point"}
}