{
  "type": "Feature",
  "properties": {
    "iso:country":"US",
    "sg:address":"730 Arlington Ave",
    "sg:city":"Jackson",
    "sg:classifiers":[
        {
            "category":"Sports & Exercise",
            "subcategory":"Bowling",
            "type":"Entertainment"
        }
    ],
    "sg:phone":"+1 731 422 6666",
    "sg:postcode":"38301",
    "sg:province":"TN",
    "sg:tags":[
        "center"
    ],
    "wof:name":"Classic Bowl",
    "wof:placetype":"venue"
},
  "geometry": {"coordinates":[-88.836382,35.626366],"type":"Point"}
}