{
  "type": "Feature",
  "properties": {
    "iso:country":"US",
    "sg:address":"128 Franklin Rd",
    "sg:city":"Brentwood",
    "sg:classifiers":[
        {
            "category":"Retail",
            "subcategory":"Laundry & Dry Cleaning",
            "type":"Services"
        }
    ],
    "sg:phone":"+1 615 373 3600",
    "sg:postcode":"37027",
    "sg:province":"TN",
    "sg:tags":[
        "cleaners"
    ],
    "wof:name":"Carriage House Cleaners",
    "wof:placetype":"venue"
},
  "geometry": {"coordinates":[-86.787626,36.035019],"type":"Point"}
}