{
  "type": "Feature",
  "properties": {
    "addr:full":"35 Castlegate Dr Jackson TN 38305",
    "addr:housenumber":"35",
    "addr:postcode":"38305",
    "addr:street":"Castlegate Dr",
    "iso:country":"US",
    "sg:address":"35 Castlegate Dr",
    "sg:city":"Jackson",
    "sg:classifiers":[
        {
            "category":"Professional",
            "subcategory":"Business Services",
            "type":"Services"
        }
    ],
    "sg:phone":"+1 731 217 5135",
    "sg:postcode":"38305",
    "sg:province":"TN",
    "wof:name":"Personal Space",
    "wof:placetype":"venue"
},
  "geometry": {"coordinates":[-88.776263,35.697412],"type":"Point"}
}