{
  "type": "Feature",
  "properties": {
    "addr:full":"3313 E Stone Dr Kingsport TN 37660",
    "addr:housenumber":"3313",
    "addr:postcode":"37660",
    "addr:street":"E Stone Dr",
    "iso:country":"US",
    "sg:address":"3313 E Stone Dr",
    "sg:city":"Kingsport",
    "sg:classifiers":[
        {
            "category":"Retail",
            "subcategory":"Auto Repair",
            "type":"Services"
        }
    ],
    "sg:phone":"+1 423 288 0200",
    "sg:postcode":"37660",
    "sg:province":"TN",
    "sg:tags":[
        "general"
    ],
    "wof:name":"Perfect Finish",
    "wof:placetype":"venue"
},
  "geometry": {"coordinates":[-82.458078,36.563647],"type":"Point"}
}