{
  "type": "Feature",
  "properties": {
    "addr:full":"8739 Horton Hwy College Grove TN 37046",
    "addr:housenumber":"8739",
    "addr:postcode":"37046",
    "addr:street":"Horton Hwy College Grove",
    "iso:country":"US",
    "sg:address":"8739 Horton Hwy",
    "sg:city":"College Grove",
    "sg:classifiers":[
        {
            "category":"Retail",
            "subcategory":"Auto Repair",
            "type":"Services"
        }
    ],
    "sg:phone":"+1 615 368 3000",
    "sg:postcode":"37046",
    "sg:province":"TN",
    "sg:tags":[
        "automobile",
        "customizing"
    ],
    "wof:name":"Hot Rods & Threads LLC",
    "wof:placetype":"venue"
},
  "geometry": {"coordinates":[-86.67690399999999,35.785634],"type":"Point"}
}