{
  "type": "Feature",
  "properties": {
    "iso:country":"US",
    "sg:address":"4901 Montvale Rd",
    "sg:city":"Maryville",
    "sg:classifiers":[
        {
            "category":"Social Services",
            "type":"Services"
        }
    ],
    "sg:phone":"+1 865 984 5519",
    "sg:postcode":"37803",
    "sg:province":"TN",
    "sg:tags":[
        "organization",
        "welfare"
    ],
    "sg:website":"www.campmontvale.org",
    "wof:name":"YMCA",
    "wof:placetype":"venue"
},
  "geometry": {"coordinates":[-83.960576,35.641182],"type":"Point"}
}