{
  "type": "Feature",
  "properties": {
    "addr:full":"2147 Pulaski Hwy Lawrenceburg TN 38464",
    "addr:housenumber":"2147",
    "addr:postcode":"38464",
    "addr:street":"Pulaski Hwy",
    "iso:country":"US",
    "sg:address":"2147 Pulaski Hwy",
    "sg:city":"Lawrenceburg",
    "sg:classifiers":[
        {
            "category":"Wholesale",
            "subcategory":"Medical Equipment & Supplies",
            "type":"Manufacturing & Wholesale Goods"
        }
    ],
    "sg:phone":"+1 931 766 5888",
    "sg:postcode":"38464",
    "sg:province":"TN",
    "sg:tags":[
        "physician",
        "surgeon"
    ],
    "wof:name":"Orange Medical",
    "wof:placetype":"venue"
},
  "geometry": {"coordinates":[-87.300448,35.237341],"type":"Point"}
}