{
  "type": "Feature",
  "properties": {
    "iso:country":"US",
    "sg:address":"11025 Matthew Rd",
    "sg:city":"Soddy Daisy",
    "sg:classifiers":[
        {
            "category":"Organizations",
            "subcategory":"Religious Organization",
            "type":"Services"
        }
    ],
    "sg:phone":"+1 423 332 7416",
    "sg:postcode":"37379",
    "sg:province":"TN",
    "sg:tags":[
        "church"
    ],
    "wof:name":"Good Shepherd Outreach Mnstry",
    "wof:placetype":"venue"
},
  "geometry": {"coordinates":[-85.167485,35.277435],"type":"Point"}
}