{
  "type": "Feature",
  "properties": {
    "addr:full":"715 N Main St Columbia TN 38401",
    "addr:housenumber":"715",
    "addr:postcode":"38401",
    "addr:street":"N Main St",
    "iso:country":"US",
    "sg:address":"715 N Main St",
    "sg:city":"Columbia",
    "sg:classifiers":[
        {
            "category":"Building & Trades",
            "subcategory":"Construction",
            "type":"Services"
        }
    ],
    "sg:phone":"+1 931 328 0091",
    "sg:postcode":"38401",
    "sg:province":"TN",
    "sg:tags":[
        "contractor"
    ],
    "wof:name":"Nehemiah Builders",
    "wof:placetype":"venue"
},
  "geometry": {"coordinates":[-87.033739,35.616075],"type":"Point"}
}