{
  "type": "Feature",
  "properties": {
    "iso:country":"US",
    "sg:address":"6634 Winchester Rd",
    "sg:city":"Memphis",
    "sg:classifiers":[
        {
            "category":"Utilities",
            "subcategory":"Mobile Phone",
            "type":"Services"
        },
        {
            "category":"Shopping",
            "subcategory":"Mobile Phones",
            "type":"Retail Goods"
        }
    ],
    "sg:phone":"+1 901 433 3389",
    "sg:postcode":"38115",
    "sg:province":"TN",
    "sg:tags":[
        "supply",
        "communication",
        "telephone",
        "wireless",
        "equipment",
        "cellular"
    ],
    "sg:website":"http://www.mycricket.com",
    "wof:name":"Cricket Wireless - Cotton Plant",
    "wof:placetype":"venue"
},
  "geometry": {"coordinates":[-89.84133300000001,35.049455],"type":"Point"}
}