{
  "type": "Feature",
  "properties": {
    "iso:country":"US",
    "sg:address":"1404 Airways Blvd",
    "sg:city":"Memphis",
    "sg:classifiers":[
        {
            "category":"Restaurant",
            "type":"Food & Drink"
        }
    ],
    "sg:phone":"+1 901 828 3676",
    "sg:postcode":"38114",
    "sg:province":"TN",
    "sg:tags":[
        "eating"
    ],
    "wof:name":"Bynum's Bar-B-Q",
    "wof:placetype":"venue"
},
  "geometry": {"coordinates":[-89.98500799999999,35.107101],"type":"Point"}
}