{
  "type": "Feature",
  "properties": {
    "addr:full":"3439 Heckle Ave Memphis TN 38111",
    "addr:housenumber":"3439",
    "addr:postcode":"38111",
    "addr:street":"Heckle Ave",
    "iso:country":"US",
    "sg:address":"3439 Heckle Ave",
    "sg:city":"Memphis",
    "sg:classifiers":[
        {
            "category":"Personal",
            "type":"Services"
        }
    ],
    "sg:phone":"+1 901 743 4881",
    "sg:postcode":"38111",
    "sg:province":"TN",
    "wof:name":"Elegance of Earth",
    "wof:placetype":"venue"
},
  "geometry": {"coordinates":[-89.945278,35.091578],"type":"Point"}
}