{
  "type": "Feature",
  "properties": {
    "iso:country":"US",
    "sg:address":"4007 Blanchard",
    "sg:city":"Chattanooga",
    "sg:classifiers":[
        {
            "category":"Building & Trades",
            "subcategory":"Construction",
            "type":"Services"
        }
    ],
    "sg:phone":"+1 423 622 7630",
    "sg:postcode":"37411",
    "sg:province":"TN",
    "sg:tags":[
        "housing"
    ],
    "wof:name":"Dale Barkubein General Contr",
    "wof:placetype":"venue"
},
  "geometry": {"coordinates":[-85.22991,35.034048],"type":"Point"}
}