{
  "type": "Feature",
  "properties": {
    "addr:full":"710 S 1st St Nashville TN 37213",
    "addr:housenumber":"710",
    "addr:postcode":"37213",
    "addr:street":"S 1St St",
    "iso:country":"US",
    "sg:address":"710 S 1st St",
    "sg:city":"Nashville",
    "sg:classifiers":[
        {
            "category":"Retail",
            "subcategory":"Auto Rental",
            "type":"Services"
        }
    ],
    "sg:phone":"+1 615 726 8677",
    "sg:postcode":"37213",
    "sg:province":"TN",
    "sg:tags":[
        "truck",
        "leasing"
    ],
    "wof:name":"Penske",
    "wof:placetype":"venue"
},
  "geometry": {"coordinates":[-86.76848699999999,36.162389],"type":"Point"}
}