{
  "type": "Feature",
  "properties": {
    "iso:country":"US",
    "sg:address":"2822 Calhoun Ave",
    "sg:city":"Chattanooga",
    "sg:classifiers":[
        {
            "category":"Autos & Motor Vehicles",
            "subcategory":"Auto Supplies",
            "type":"Retail Goods"
        }
    ],
    "sg:phone":"+1 423 624 1100",
    "sg:postcode":"37407",
    "sg:province":"TN",
    "sg:tags":[
        "accessories-wholesale",
        "automobile",
        "part",
        "parts",
        "manufacturer"
    ],
    "wof:name":"Tennessee Automotive Parts",
    "wof:placetype":"venue"
},
  "geometry": {"coordinates":[-85.295514,35.013778],"type":"Point"}
}