{
  "type": "Feature",
  "properties": {
    "iso:country":"US",
    "sg:address":"6590 State Line Rd",
    "sg:city":"Memphis",
    "sg:classifiers":[
        {
            "category":"Organizations",
            "subcategory":"Religious Organization",
            "type":"Services"
        }
    ],
    "sg:phone":"+1 901 363 9133",
    "sg:postcode":"38141",
    "sg:province":"TN",
    "sg:tags":[
        "church"
    ],
    "wof:name":"Hunters Run Church Of Christ",
    "wof:placetype":"venue"
},
  "geometry": {"coordinates":[-89.84032500000001,34.994517],"type":"Point"}
}