{
  "type": "Feature",
  "properties": {
    "iso:country":"US",
    "sg:address":"620 Monte Carlo Dr",
    "sg:city":"Antioch",
    "sg:classifiers":[
        {
            "category":"Shopping",
            "subcategory":"Clothing, Apparel, & Fashions",
            "type":"Retail Goods"
        }
    ],
    "sg:phone":"+1 615 333 9244",
    "sg:postcode":"37013",
    "sg:province":"TN",
    "wof:name":"Big Rick Fashion",
    "wof:placetype":"venue"
},
  "geometry": {"coordinates":[-86.70912,36.035375],"type":"Point"}
}