{
  "type": "Feature",
  "properties": {
    "iso:country":"US",
    "sg:address":"6518 Hixson Pike",
    "sg:city":"Hixson",
    "sg:classifiers":[
        {
            "category":"Retail",
            "subcategory":"Repair Shop",
            "type":"Services"
        }
    ],
    "sg:phone":"+1 423 842 6395",
    "sg:postcode":"37343",
    "sg:province":"TN",
    "sg:tags":[
        "boat",
        "motor"
    ],
    "sg:website":"www.franklinmarine.com",
    "wof:name":"Franklin Marine Inc",
    "wof:placetype":"venue"
},
  "geometry": {"coordinates":[-85.194222,35.159095],"type":"Point"}
}