{
  "type": "Feature",
  "properties": {
    "addr:full":"691 E Main St Hendersonville TN 37075",
    "addr:housenumber":"691",
    "addr:postcode":"37075",
    "addr:street":"E Main St",
    "iso:country":"US",
    "sg:address":"691 E Main St",
    "sg:city":"Hendersonville",
    "sg:classifiers":[
        {
            "category":"Building & Trades",
            "subcategory":"Construction",
            "type":"Services"
        }
    ],
    "sg:phone":"+1 615 822 2577",
    "sg:postcode":"37075",
    "sg:province":"TN",
    "sg:tags":[
        "home",
        "builder"
    ],
    "wof:name":"David Weekley Homes",
    "wof:placetype":"venue"
},
  "geometry": {"coordinates":[-86.568083,36.323862],"type":"Point"}
}