{
  "type": "Feature",
  "properties": {
    "iso:country":"US",
    "sg:address":"2923 State Hwy 109",
    "sg:city":"Lebanon",
    "sg:classifiers":[
        {
            "category":"Home & Garden",
            "subcategory":"Home Furnishings",
            "type":"Retail Goods"
        }
    ],
    "sg:phone":"+1 615 443 5173",
    "sg:postcode":"37090",
    "sg:province":"TN",
    "sg:tags":[
        "pottery"
    ],
    "wof:name":"All American Pottery Studio",
    "wof:placetype":"venue"
},
  "geometry": {"coordinates":[-86.425297,36.223384],"type":"Point"}
}