{
  "type": "Feature",
  "properties": {
    "iso:country":"US",
    "sg:address":"3582 Ellenview Cove N",
    "sg:city":"Memphis",
    "sg:classifiers":[
        {
            "category":"Professional",
            "subcategory":"Detective & Security Services",
            "type":"Services"
        }
    ],
    "sg:phone":"+1 901 372 0900",
    "sg:postcode":"38133",
    "sg:province":"TN",
    "wof:name":"Cornerstone Protective Svc",
    "wof:placetype":"venue"
},
  "geometry": {"coordinates":[-89.81645899999999,35.222948],"type":"Point"}
}