{
  "type": "Feature",
  "properties": {
    "addr:full":"3959 Dayton Blvd Chattanooga TN 37415",
    "addr:housenumber":"3959",
    "addr:postcode":"37415",
    "addr:street":"Dayton Blvd",
    "iso:country":"US",
    "sg:address":"3959 Dayton Blvd",
    "sg:city":"Chattanooga",
    "sg:classifiers":[
        {
            "category":"Professional",
            "subcategory":"Lawyer & Legal Services",
            "type":"Services"
        }
    ],
    "sg:phone":"+1 423 876 0081",
    "sg:postcode":"37415",
    "sg:province":"TN",
    "wof:name":"Robbie L McLean",
    "wof:placetype":"venue"
},
  "geometry": {"coordinates":[-85.288821,35.120664],"type":"Point"}
}