{
  "type": "Feature",
  "properties": {
    "addr:full":"9 Dixon Springs Hwy Carthage TN 37030",
    "addr:housenumber":"9",
    "addr:postcode":"37030",
    "addr:street":"Dixon Springs Hwy",
    "iso:country":"US",
    "sg:address":"9 Dixon Springs Hwy",
    "sg:city":"Carthage",
    "sg:classifiers":[
        {
            "category":"Organizations",
            "subcategory":"Religious Organization",
            "type":"Services"
        }
    ],
    "sg:phone":"+1 615 735 8476",
    "sg:postcode":"37030",
    "sg:province":"TN",
    "sg:tags":[
        "church"
    ],
    "wof:name":"God's Way Community Church",
    "wof:placetype":"venue"
},
  "geometry": {"coordinates":[-85.956345,36.264452],"type":"Point"}
}