{
  "type": "Feature",
  "properties": {
    "iso:country":"US",
    "sg:address":"132 England Dr",
    "sg:city":"Clinton",
    "sg:classifiers":[
        {
            "category":"Food & Beverages",
            "subcategory":"Specialty",
            "type":"Retail Goods"
        }
    ],
    "sg:phone":"+1 865 435 1452",
    "sg:postcode":"37716",
    "sg:province":"TN",
    "sg:tags":[
        "farm",
        "herb",
        "field",
        "crop",
        "supply"
    ],
    "wof:name":"Erin's Meadow Herb Farm",
    "wof:placetype":"venue"
},
  "geometry": {"coordinates":[-84.25828,36.047802],"type":"Point"}
}