{
  "type": "Feature",
  "properties": {
    "addr:full":"5940 State Hwy 58 Harrison TN 37341",
    "addr:housenumber":"5940",
    "addr:postcode":"37341",
    "addr:street":"State Hwy 58",
    "iso:country":"US",
    "sg:address":"5940 State Hwy 58",
    "sg:city":"Harrison",
    "sg:classifiers":[
        {
            "category":"Shopping",
            "subcategory":"Discount & Variety Stores",
            "type":"Retail Goods"
        },
        {
            "category":"Shopping",
            "subcategory":"Department Store",
            "type":"Retail Goods"
        }
    ],
    "sg:phone":"+1 423 326 3666",
    "sg:postcode":"37341",
    "sg:province":"TN",
    "wof:name":"Family Dollar Stores",
    "wof:placetype":"venue"
},
  "geometry": {"coordinates":[-85.128839,35.11474],"type":"Point"}
}