{
  "type": "Feature",
  "properties": {
    "iso:country":"US",
    "sg:address":"8439 Falcon Dr",
    "sg:city":"Knoxville",
    "sg:classifiers":[
        {
            "category":"Building & Trades",
            "subcategory":"Electrical",
            "type":"Services"
        }
    ],
    "sg:phone":"+1 865 693 6368",
    "sg:postcode":"37923",
    "sg:province":"TN",
    "sg:tags":[
        "electrical",
        "contractor"
    ],
    "wof:name":"R & B Electric",
    "wof:placetype":"venue"
},
  "geometry": {"coordinates":[-84.06331,35.939113],"type":"Point"}
}