{
  "type": "Feature",
  "properties": {
    "addr:full":"4530 Poplar Ave. Memphis TN 38117",
    "addr:housenumber":"4530",
    "addr:postcode":"38117",
    "addr:street":"Poplar Ave.",
    "iso:country":"US",
    "sg:address":"4530 Poplar Ave.",
    "sg:city":"Memphis",
    "sg:classifiers":[
        {
            "category":"Shopping",
            "subcategory":"Clothing, Apparel, & Fashions",
            "type":"Retail Goods"
        },
        {
            "category":"Shopping",
            "subcategory":"Bicycles & Sporting Goods",
            "type":"Retail Goods"
        },
        {
            "category":"Shopping",
            "subcategory":"Shoes",
            "type":"Retail Goods"
        }
    ],
    "sg:phone":"+1 901 761 0078",
    "sg:postcode":"38117",
    "sg:province":"TN",
    "sg:tags":[
        "apparel",
        "sportswear",
        "racing",
        "store",
        "merchandise"
    ],
    "sg:website":"http://www.fleetfeetmemphis.com",
    "wof:name":"Fleet Feet Sports",
    "wof:placetype":"venue"
},
  "geometry": {"coordinates":[-89.911033,35.117962],"type":"Point"}
}