{
  "type": "Feature",
  "properties": {
    "iso:country":"US",
    "sg:address":"2016 8th Ave S",
    "sg:city":"Nashville",
    "sg:classifiers":[
        {
            "category":"Professional",
            "subcategory":"Lawyer & Legal Services",
            "type":"Services"
        }
    ],
    "sg:phone":"+1 615 297 5900",
    "sg:postcode":"37204",
    "sg:province":"TN",
    "wof:name":"Herbison John Law Offices",
    "wof:placetype":"venue"
},
  "geometry": {"coordinates":[-86.779173,36.132643],"type":"Point"}
}