{
  "type": "Feature",
  "properties": {
    "addr:full":"60 Parris Ave Nashville TN 37210",
    "addr:housenumber":"60",
    "addr:postcode":"37210",
    "addr:street":"Parris Ave",
    "iso:country":"US",
    "sg:address":"60 Parris Ave",
    "sg:city":"Nashville",
    "sg:classifiers":[
        {
            "category":"Professional",
            "subcategory":"Management & Consulting",
            "type":"Services"
        }
    ],
    "sg:phone":"+1 615 254 3867",
    "sg:postcode":"37210",
    "sg:province":"TN",
    "sg:tags":[
        "party",
        "planning"
    ],
    "wof:name":"Fun Services",
    "wof:placetype":"venue"
},
  "geometry": {"coordinates":[-86.747912,36.141357],"type":"Point"}
}