{
  "type": "Feature",
  "properties": {
    "addr:full":"7208 Bethel Rd Goodlettsville TN 37072",
    "addr:housenumber":"7208",
    "addr:postcode":"37072",
    "addr:street":"Bethel Rd",
    "iso:country":"US",
    "sg:address":"7208 Bethel Rd",
    "sg:city":"Goodlettsville",
    "sg:classifiers":[
        {
            "category":"Manufacturing",
            "subcategory":"Tools & Machinery",
            "type":"Manufacturing & Wholesale Goods"
        }
    ],
    "sg:phone":"+1 615 643 1133",
    "sg:postcode":"37072",
    "sg:province":"TN",
    "sg:tags":[
        "metalworking",
        "mfg"
    ],
    "wof:name":"Highland Rim Machine Co",
    "wof:placetype":"venue"
},
  "geometry": {"coordinates":[-86.72300300000001,36.417691],"type":"Point"}
}