{
  "type": "Feature",
  "properties": {
    "iso:country":"US",
    "sg:address":"1796 Lamar Ave",
    "sg:city":"Memphis",
    "sg:classifiers":[
        {
            "category":"Food & Beverages",
            "subcategory":"Groceries & Convenience Stores",
            "type":"Retail Goods"
        }
    ],
    "sg:phone":"+1 901 729 2831",
    "sg:postcode":"38114",
    "sg:province":"TN",
    "wof:name":"Corner Foodmart",
    "wof:placetype":"venue"
},
  "geometry": {"coordinates":[-90.002037,35.117219],"type":"Point"}
}