{
  "type": "Feature",
  "properties": {
    "iso:country":"US",
    "sg:address":"3325 State Hwy 109",
    "sg:city":"Lebanon",
    "sg:classifiers":[
        {
            "category":"Retail",
            "subcategory":"Auto Rental",
            "type":"Services"
        }
    ],
    "sg:phone":"+1 615 443 9002",
    "sg:postcode":"37090",
    "sg:province":"TN",
    "sg:tags":[
        "passenger",
        "car"
    ],
    "wof:name":"Americar Inc",
    "wof:placetype":"venue"
},
  "geometry": {"coordinates":[-86.42706,36.228108],"type":"Point"}
}