{
  "type": "Feature",
  "properties": {
    "iso:country":"US",
    "sg:address":"2936 Ashland City Rd",
    "sg:city":"Clarksville",
    "sg:classifiers":[
        {
            "category":"Manufacturing",
            "subcategory":"Tools & Machinery",
            "type":"Manufacturing & Wholesale Goods"
        }
    ],
    "sg:phone":"+1 931 358 5028",
    "sg:postcode":"37043",
    "sg:province":"TN",
    "sg:tags":[
        "machine",
        "mfg"
    ],
    "wof:name":"Simplex Time Recorder Co",
    "wof:placetype":"venue"
},
  "geometry": {"coordinates":[-87.263824,36.487557],"type":"Point"}
}