{
  "type": "Feature",
  "properties": {
    "addr:full":"5075 Columbia Pike Spring Hill TN 37174",
    "addr:housenumber":"5075",
    "addr:postcode":"37174",
    "addr:street":"Columbia Pike",
    "iso:country":"US",
    "sg:address":"5075 Columbia Pike",
    "sg:city":"Spring Hill",
    "sg:classifiers":[
        {
            "category":"Food & Beverages",
            "subcategory":"Specialty",
            "type":"Retail Goods"
        }
    ],
    "sg:phone":"+1 615 302 0392",
    "sg:postcode":"37174",
    "sg:province":"TN",
    "sg:tags":[
        "health",
        "diet"
    ],
    "wof:name":"Naturals Wellness Store",
    "wof:placetype":"venue"
},
  "geometry": {"coordinates":[-86.882077,35.837502],"type":"Point"}
}