{
  "type": "Feature",
  "properties": {
    "iso:country":"US",
    "sg:address":"34 Volner Rd",
    "sg:city":"Decaturville",
    "sg:classifiers":[
        {
            "category":"Manufacturing",
            "subcategory":"Metals",
            "type":"Manufacturing & Wholesale Goods"
        }
    ],
    "sg:phone":"+1 731 852 4818",
    "sg:postcode":"38329",
    "sg:province":"TN",
    "sg:tags":[
        "machine",
        "screw",
        "product"
    ],
    "wof:name":"Martin Machine Works",
    "wof:placetype":"venue"
},
  "geometry": {"coordinates":[-88.219359,35.514129],"type":"Point"}
}