{
  "type": "Feature",
  "properties": {
    "addr:full":"4777 State Hwy 58 Chattanooga TN 37416",
    "addr:housenumber":"4777",
    "addr:postcode":"37416",
    "addr:street":"State Hwy 58",
    "iso:country":"US",
    "sg:address":"4777 State Hwy 58",
    "sg:city":"Chattanooga",
    "sg:classifiers":[
        {
            "category":"Shopping",
            "subcategory":"Used Merchandise",
            "type":"Retail Goods"
        }
    ],
    "sg:phone":"+1 423 499 4984",
    "sg:postcode":"37416",
    "sg:province":"TN",
    "wof:name":"Puttin On Ritz Resale Shop",
    "wof:placetype":"venue"
},
  "geometry": {"coordinates":[-85.189455,35.087763],"type":"Point"}
}