{
  "type": "Feature",
  "properties": {
    "iso:country":"US",
    "sg:address":"3491 Poplar Ave",
    "sg:city":"Memphis",
    "sg:classifiers":[
        {
            "category":"Restaurant",
            "type":"Food & Drink"
        }
    ],
    "sg:phone":"+1 901 452 9848",
    "sg:postcode":"38111",
    "sg:province":"TN",
    "sg:tags":[
        "mexican"
    ],
    "wof:name":"Lahacienda Mexican Restaurant",
    "wof:placetype":"venue"
},
  "geometry": {"coordinates":[-89.945369,35.127843],"type":"Point"}
}