{
  "type": "Feature",
  "properties": {
    "iso:country":"US",
    "sg:address":"61 McLaughlin Dr",
    "sg:city":"Atoka",
    "sg:classifiers":[
        {
            "category":"Wholesale",
            "subcategory":"Drugs",
            "type":"Manufacturing & Wholesale Goods"
        }
    ],
    "sg:phone":"+1 901 840 3090",
    "sg:postcode":"38058",
    "sg:province":"TN",
    "sg:tags":[
        "pharmaceutical",
        "product"
    ],
    "wof:name":"Prime Care Pharmaceuticals",
    "wof:placetype":"venue"
},
  "geometry": {"coordinates":[-89.782779,35.449836],"type":"Point"}
}