{
  "type": "Feature",
  "properties": {
    "iso:country":"US",
    "sg:address":"460 Gentry Ln",
    "sg:city":"Bristol",
    "sg:classifiers":[
        {
            "category":"Professional",
            "subcategory":"Business Services",
            "type":"Services"
        }
    ],
    "sg:phone":"+1 423 968 1002",
    "sg:postcode":"37620",
    "sg:province":"TN",
    "wof:name":"Evermoore Farm",
    "wof:placetype":"venue"
},
  "geometry": {"coordinates":[-82.217354,36.545048],"type":"Point"}
}