{
  "type": "Feature",
  "properties": {
    "addr:full":"5910 Charlotte Pike Nashville TN 37209",
    "addr:housenumber":"5910",
    "addr:postcode":"37209",
    "addr:street":"Charlotte Pike",
    "iso:country":"US",
    "sg:address":"5910 Charlotte Pike",
    "sg:city":"Nashville",
    "sg:classifiers":[
        {
            "category":"Arts & Performance",
            "subcategory":"Theater",
            "type":"Entertainment"
        }
    ],
    "sg:phone":"+1 615 353 1152",
    "sg:postcode":"37209",
    "sg:province":"TN",
    "sg:tags":[
        "bureau"
    ],
    "wof:name":"AZN Sports & Entertainment",
    "wof:placetype":"venue"
},
  "geometry": {"coordinates":[-86.861619,36.149404],"type":"Point"}
}