{
  "type": "Feature",
  "properties": {
    "iso:country":"US",
    "sg:address":"441 Allied Dr",
    "sg:city":"Nashville",
    "sg:classifiers":[
        {
            "category":"Building & Trades",
            "subcategory":"Electrical",
            "type":"Services"
        }
    ],
    "sg:phone":"+1 615 331 0007",
    "sg:postcode":"37211",
    "sg:province":"TN",
    "sg:tags":[
        "electric",
        "contractor"
    ],
    "sg:website":"www.harlan-electric.com",
    "wof:name":"Harlan Electric Co",
    "wof:placetype":"venue"
},
  "geometry": {"coordinates":[-86.740669,36.095703],"type":"Point"}
}