{
  "type": "Feature",
  "properties": {
    "iso:country":"US",
    "sg:address":"1131 Cedar Springs Rd SE",
    "sg:city":"Cleveland",
    "sg:classifiers":[
        {
            "category":"Building & Trades",
            "subcategory":"Plumbing",
            "type":"Services"
        }
    ],
    "sg:phone":"+1 423 479 7474",
    "sg:postcode":"37323",
    "sg:province":"TN",
    "sg:tags":[
        "system",
        "air conditioning",
        "contractor"
    ],
    "wof:name":"Wells' Plumbing",
    "wof:placetype":"venue"
},
  "geometry": {"coordinates":[-84.806715,35.05963],"type":"Point"}
}