{
  "type": "Feature",
  "properties": {
    "iso:country":"US",
    "sg:address":"4300 N Access Rd",
    "sg:city":"Chattanooga",
    "sg:classifiers":[
        {
            "category":"Wholesale",
            "subcategory":"Farm Supplies",
            "type":"Manufacturing & Wholesale Goods"
        }
    ],
    "sg:phone":"+1 423 877 3152",
    "sg:postcode":"37415",
    "sg:province":"TN",
    "sg:tags":[
        "feed"
    ],
    "wof:name":"Midwest Chattanooga",
    "wof:placetype":"venue"
},
  "geometry": {"coordinates":[-85.253463,35.11288],"type":"Point"}
}