{
  "type": "Feature",
  "properties": {
    "iso:country":"US",
    "sg:address":"158 Marne St",
    "sg:city":"Memphis",
    "sg:classifiers":[
        {
            "category":"Building & Trades",
            "subcategory":"Construction",
            "type":"Services"
        }
    ],
    "sg:phone":"+1 901 338 7055",
    "sg:postcode":"38111",
    "sg:province":"TN",
    "sg:tags":[
        "steel",
        "industrial",
        "erectors"
    ],
    "wof:name":"C S M",
    "wof:placetype":"venue"
},
  "geometry": {"coordinates":[-89.95563900000001,35.127439],"type":"Point"}
}