{
  "type": "Feature",
  "properties": {
    "addr:full":"8624 Bowles Rd Rockvale TN 37153",
    "addr:housenumber":"8624",
    "addr:postcode":"37153",
    "addr:street":"Bowles Rd",
    "iso:country":"US",
    "sg:address":"8624 Bowles Rd",
    "sg:city":"Rockvale",
    "sg:classifiers":[
        {
            "category":"Wholesale",
            "subcategory":"Groceries",
            "type":"Manufacturing & Wholesale Goods"
        }
    ],
    "sg:phone":"+1 615 274 2277",
    "sg:postcode":"37153",
    "sg:province":"TN",
    "sg:tags":[
        "food",
        "product"
    ],
    "wof:name":"Carl's All Purpose Seasoning",
    "wof:placetype":"venue"
},
  "geometry": {"coordinates":[-86.54651200000001,35.712807],"type":"Point"}
}