{
  "type": "Feature",
  "properties": {
    "iso:country":"US",
    "sg:address":"5115 Maryland Way",
    "sg:city":"Brentwood",
    "sg:classifiers":[
        {
            "category":"Social Services",
            "type":"Services"
        }
    ],
    "sg:phone":"+1 615 377 0777",
    "sg:postcode":"37027",
    "sg:province":"TN",
    "sg:tags":[
        "counseling"
    ],
    "wof:name":"Abundant Life Counseling Svc",
    "wof:placetype":"venue"
},
  "geometry": {"coordinates":[-86.799677,36.033329],"type":"Point"}
}