{
  "type": "Feature",
  "properties": {
    "iso:country":"US",
    "sg:address":"1017 Taft Ave",
    "sg:city":"Chattanooga",
    "sg:classifiers":[
        {
            "category":"Retail",
            "subcategory":"Auto Repair",
            "type":"Services"
        }
    ],
    "sg:phone":"+1 423 267 2256",
    "sg:postcode":"37408",
    "sg:province":"TN",
    "sg:tags":[
        "transmission",
        "automotive"
    ],
    "wof:name":"Johnson Williams Transmissions",
    "wof:placetype":"venue"
},
  "geometry": {"coordinates":[-85.298413,35.023587],"type":"Point"}
}