{
  "type": "Feature",
  "properties": {
    "iso:country":"US",
    "sg:address":"350 Donelson Dr",
    "sg:city":"Eads",
    "sg:classifiers":[
        {
            "category":"Retail",
            "subcategory":"Auto Repair",
            "type":"Services"
        }
    ],
    "sg:phone":"+1 901 465 5566",
    "sg:postcode":"38028",
    "sg:province":"TN",
    "sg:tags":[
        "body",
        "automobile",
        "painting"
    ],
    "wof:name":"Pritchett's Body Shop",
    "wof:placetype":"venue"
},
  "geometry": {"coordinates":[-89.567136,35.234554],"type":"Point"}
}