{
  "type": "Feature",
  "properties": {
    "iso:country":"US",
    "sg:address":"4466 Elvis Presley Blvd",
    "sg:city":"Memphis",
    "sg:classifiers":[
        {
            "category":"Building & Trades",
            "subcategory":"Construction",
            "type":"Services"
        }
    ],
    "sg:phone":"+1 901 398 8500",
    "sg:postcode":"38116",
    "sg:province":"TN",
    "sg:tags":[
        "contractor"
    ],
    "wof:name":"Brooks Carpet & Tile Svc",
    "wof:placetype":"venue"
},
  "geometry": {"coordinates":[-90.025109,35.026771],"type":"Point"}
}