{
  "type": "Feature",
  "properties": {
    "iso:country":"US",
    "sg:address":"1001 Lindsay St",
    "sg:city":"Chattanooga",
    "sg:classifiers":[
        {
            "category":"Government",
            "subcategory":"Office",
            "type":"Public Place"
        }
    ],
    "sg:phone":"+1 423 757 4811",
    "sg:postcode":"37402",
    "sg:province":"TN",
    "sg:tags":[
        "village"
    ],
    "wof:name":"Chattanooga Human Rights Dept",
    "wof:placetype":"venue"
},
  "geometry": {"coordinates":[-85.30771300000001,35.043817],"type":"Point"}
}