{
  "type": "Feature",
  "properties": {
    "iso:country":"US",
    "sg:address":"6302 Nashville Hwy",
    "sg:city":"Mc Minnville",
    "sg:classifiers":[
        {
            "category":"Home & Garden",
            "subcategory":"Garden Supply",
            "type":"Retail Goods"
        }
    ],
    "sg:phone":"+1 931 939 2047",
    "sg:postcode":"37110",
    "sg:province":"TN",
    "sg:tags":[
        "nurseryman"
    ],
    "wof:name":"A-1 Tree Farms",
    "wof:placetype":"venue"
},
  "geometry": {"coordinates":[-85.87874600000001,35.706022],"type":"Point"}
}