{
  "type": "Feature",
  "properties": {
    "iso:country":"US",
    "sg:address":"1308 E Spring St",
    "sg:city":"Cookeville",
    "sg:classifiers":[
        {
            "category":"Wholesale",
            "subcategory":"Hardware",
            "type":"Manufacturing & Wholesale Goods"
        }
    ],
    "sg:phone":"+1 931 372 8565",
    "sg:postcode":"38501",
    "sg:province":"TN",
    "sg:tags":[
        "fastener"
    ],
    "sg:website":"www.fastenal.com",
    "wof:name":"Fastenal Co",
    "wof:placetype":"venue"
},
  "geometry": {"coordinates":[-85.476467,36.15326],"type":"Point"}
}