{
  "type": "Feature",
  "properties": {
    "addr:full":"406 Union Ave SW Knoxville TN 37902",
    "addr:housenumber":"406",
    "addr:postcode":"37902",
    "addr:street":"Union Ave Sw",
    "iso:country":"US",
    "sg:address":"406 Union Ave SW",
    "sg:city":"Knoxville",
    "sg:classifiers":[
        {
            "category":"Banks & Credit Unions",
            "subcategory":"Bank",
            "type":"Services"
        }
    ],
    "sg:phone":"+1 865 541 6400",
    "sg:postcode":"37902",
    "sg:province":"TN",
    "sg:tags":[
        "development",
        "mortgage",
        "broker",
        "real estate"
    ],
    "wof:name":"Subsidiaryary Home Federal Bnk",
    "wof:placetype":"venue"
},
  "geometry": {"coordinates":[-83.91936099999999,35.964594],"type":"Point"}
}