{
  "type": "Feature",
  "properties": {
    "iso:country":"US",
    "sg:address":"145 State Hwy 120",
    "sg:city":"Franklin",
    "sg:classifiers":[
        {
            "category":"Building & Trades",
            "subcategory":"Equipment Rental",
            "type":"Services"
        }
    ],
    "sg:phone":"+1 615 599 1125",
    "sg:postcode":"37023",
    "sg:province":"TN",
    "sg:tags":[
        "disabled",
        "person",
        "supply"
    ],
    "wof:name":"Bios Of Tn LLC",
    "wof:placetype":"venue"
},
  "geometry": {"coordinates":[-87.72994199999999,36.564704],"type":"Point"}
}