{
  "type": "Feature",
  "properties": {
    "iso:country":"US",
    "sg:address":"1312 Stad Ave",
    "sg:city":"Union City",
    "sg:classifiers":[
        {
            "category":"Health Services",
            "subcategory":"Chiropractor",
            "type":"Services"
        }
    ],
    "sg:phone":"+1 731 885 2555",
    "sg:postcode":"38261",
    "sg:province":"TN",
    "wof:name":"Family Chiropractic Ctr",
    "wof:placetype":"venue"
},
  "geometry": {"coordinates":[-89.074557,36.412806],"type":"Point"}
}