{
  "type": "Feature",
  "properties": {
    "addr:full":"2243 Sweeney Ln Chapel Hill TN 37034",
    "addr:housenumber":"2243",
    "addr:postcode":"37034",
    "addr:street":"Sweeney Ln",
    "iso:country":"US",
    "sg:address":"2243 Sweeney Ln",
    "sg:city":"Chapel Hill",
    "sg:classifiers":[
        {
            "category":"Farming",
            "subcategory":"Dairy Farm",
            "type":"Manufacturing & Wholesale Goods"
        }
    ],
    "sg:phone":"+1 931 364 7634",
    "sg:postcode":"37034",
    "sg:province":"TN",
    "wof:name":"Tommy Roberson",
    "wof:placetype":"venue"
},
  "geometry": {"coordinates":[-86.71193700000001,35.67768],"type":"Point"}
}