{
  "type": "Feature",
  "properties": {
    "iso:country":"US",
    "sg:address":"3275 Newport Hwy",
    "sg:city":"Sevierville",
    "sg:classifiers":[
        {
            "category":"Social Services",
            "type":"Services"
        }
    ],
    "sg:phone":"+1 865 429 9583",
    "sg:postcode":"37876",
    "sg:province":"TN",
    "sg:tags":[
        "organization",
        "welfare"
    ],
    "wof:name":"Teen Volunteer Network",
    "wof:placetype":"venue"
},
  "geometry": {"coordinates":[-83.40875800000001,35.909693],"type":"Point"}
}