{
  "type": "Feature",
  "properties": {
    "iso:country":"US",
    "sg:address":"6216 Dayton Blvd",
    "sg:city":"Hixson",
    "sg:classifiers":[
        {
            "category":"Home & Garden",
            "subcategory":"Building Materials",
            "type":"Retail Goods"
        }
    ],
    "sg:phone":"+1 423 843 3737",
    "sg:postcode":"37343",
    "sg:province":"TN",
    "sg:tags":[
        "glass",
        "leaded"
    ],
    "wof:name":"Stained Glass Windows",
    "wof:placetype":"venue"
},
  "geometry": {"coordinates":[-85.250648,35.176733],"type":"Point"}
}