{
  "type": "Feature",
  "properties": {
    "iso:country":"US",
    "sg:address":"10 25th St NW",
    "sg:city":"Cleveland",
    "sg:classifiers":[
        {
            "category":"Home & Garden",
            "subcategory":"Carpets & Floor Coverings",
            "type":"Retail Goods"
        }
    ],
    "sg:phone":"+1 423 472 6248",
    "sg:postcode":"37311",
    "sg:province":"TN",
    "sg:tags":[
        "material",
        "rug"
    ],
    "wof:name":"Value Flooring",
    "wof:placetype":"venue"
},
  "geometry": {"coordinates":[-84.86449,35.178541],"type":"Point"}
}