{
  "type": "Feature",
  "properties": {
    "iso:country":"US",
    "sg:address":"112 Houston Ln",
    "sg:city":"Woodbury",
    "sg:classifiers":[
        {
            "category":"Professional",
            "type":"Services"
        }
    ],
    "sg:phone":"+1 615 563 8191",
    "sg:postcode":"37190",
    "sg:province":"TN",
    "wof:name":"Bob Stoetzel Consutling",
    "wof:placetype":"venue"
},
  "geometry": {"coordinates":[-86.059269,35.825369],"type":"Point"}
}