{
  "type": "Feature",
  "properties": {
    "iso:country":"US",
    "sg:address":"935 Mulberry St",
    "sg:city":"Loudon",
    "sg:classifiers":[
        {
            "category":"Personal",
            "subcategory":"Beauty Salon",
            "type":"Services"
        }
    ],
    "sg:phone":"+1 865 458 2649",
    "sg:postcode":"37774",
    "sg:province":"TN",
    "sg:tags":[
        "shop"
    ],
    "wof:name":"Sammies Beauty Shop",
    "wof:placetype":"venue"
},
  "geometry": {"coordinates":[-84.34689299999999,35.733059],"type":"Point"}
}