{
  "type": "Feature",
  "properties": {
    "iso:country":"US",
    "sg:address":"4650 Quality Dr",
    "sg:city":"Memphis",
    "sg:classifiers":[
        {
            "category":"Wholesale",
            "subcategory":"Non-durable Goods",
            "type":"Manufacturing & Wholesale Goods"
        }
    ],
    "sg:phone":"+1 901 333 0133",
    "sg:postcode":"38118",
    "sg:province":"TN",
    "sg:website":"www.creativecoop.com",
    "wof:name":"Creative Co-Op",
    "wof:placetype":"venue"
},
  "geometry": {"coordinates":[-89.90799800000001,35.025319],"type":"Point"}
}