{
  "type": "Feature",
  "properties": {
    "iso:country":"US",
    "sg:address":"4600 E Shelby Dr Ste 101",
    "sg:city":"Memphis",
    "sg:classifiers":[
        {
            "category":"Wholesale",
            "subcategory":"Medical Equipment & Supplies",
            "type":"Manufacturing & Wholesale Goods"
        }
    ],
    "sg:phone":"+1 901 433 1990",
    "sg:postcode":"38118",
    "sg:province":"TN",
    "sg:tags":[
        "device",
        "surgical",
        "orthopedic",
        "appliance",
        "prosthetic"
    ],
    "sg:website":"http://www.stealth-medical.com",
    "wof:name":"Orchid Stealth Coating",
    "wof:placetype":"venue"
},
  "geometry": {"coordinates":[-89.90920699999999,35.020642],"type":"Point"}
}