{
  "type": "Feature",
  "properties": {
    "iso:country":"US",
    "sg:address":"7712 US Hwy 64",
    "sg:city":"Oakland",
    "sg:classifiers":[
        {
            "category":"Organizations",
            "subcategory":"Religious Organization",
            "type":"Services"
        }
    ],
    "sg:phone":"+1 901 465 9095",
    "sg:postcode":"38060",
    "sg:province":"TN",
    "sg:tags":[
        "church"
    ],
    "wof:name":"Faith United Methodist Church",
    "wof:placetype":"venue"
},
  "geometry": {"coordinates":[-89.510848,35.228911],"type":"Point"}
}