{
  "type": "Feature",
  "properties": {
    "iso:country":"US",
    "sg:address":"1993 N Highland Ave",
    "sg:city":"Jackson",
    "sg:classifiers":[
        {
            "category":"Banks & Credit Unions",
            "subcategory":"Bank",
            "type":"Services"
        }
    ],
    "sg:phone":"+1 731 661 6950",
    "sg:postcode":"38305",
    "sg:province":"TN",
    "sg:tags":[
        "state",
        "commercial"
    ],
    "wof:name":"AmSouth",
    "wof:placetype":"venue"
},
  "geometry": {"coordinates":[-88.82790199999999,35.657008],"type":"Point"}
}