{
  "type": "Feature",
  "properties": {
    "iso:country":"US",
    "sg:address":"346 Fallen Oak Cir",
    "sg:city":"Seymour",
    "sg:classifiers":[
        {
            "category":"Professional",
            "type":"Services"
        }
    ],
    "sg:phone":"+1 865 577 6630",
    "sg:postcode":"37865",
    "sg:province":"TN",
    "sg:tags":[
        "establishment"
    ],
    "wof:name":"Triad Associates Inc",
    "wof:placetype":"venue"
},
  "geometry": {"coordinates":[-83.713634,35.892076],"type":"Point"}
}