{
  "type": "Feature",
  "properties": {
    "addr:full":"8204 Asheville Hwy Knoxville TN 37924",
    "addr:housenumber":"8204",
    "addr:postcode":"37924",
    "addr:street":"Asheville Hwy",
    "iso:country":"US",
    "sg:address":"8204 Asheville Hwy",
    "sg:city":"Knoxville",
    "sg:classifiers":[
        {
            "category":"Home & Garden",
            "subcategory":"Carpets & Floor Coverings",
            "type":"Retail Goods"
        }
    ],
    "sg:phone":"+1 865 932 1642",
    "sg:postcode":"37924",
    "sg:province":"TN",
    "sg:tags":[
        "dealer",
        "rug"
    ],
    "wof:name":"Abbey Carpet Of Knoxville",
    "wof:placetype":"venue"
},
  "geometry": {"coordinates":[-83.751546,36.023863],"type":"Point"}
}