{
  "type": "Feature",
  "properties": {
    "iso:country":"US",
    "sg:address":"1751 S Walker Rd",
    "sg:city":"Pleasant View",
    "sg:classifiers":[
        {
            "category":"Professional",
            "subcategory":"Computer Services",
            "type":"Services"
        }
    ],
    "sg:phone":"+1 615 746 4927",
    "sg:postcode":"37146",
    "sg:province":"TN",
    "sg:tags":[
        "datum"
    ],
    "wof:name":"Wrightrac Web Design",
    "wof:placetype":"venue"
},
  "geometry": {"coordinates":[-87.00256400000001,36.390881],"type":"Point"}
}