{
  "type": "Feature",
  "properties": {
    "iso:country":"US",
    "sg:address":"1875 N Commerce Rd",
    "sg:city":"Lebanon",
    "sg:classifiers":[
        {
            "category":"Retail",
            "subcategory":"Repair Shop",
            "type":"Services"
        }
    ],
    "sg:phone":"+1 615 449 0858",
    "sg:postcode":"37090",
    "sg:province":"TN",
    "sg:tags":[
        "welding"
    ],
    "wof:name":"Lebanon Ornamental Iron Svc",
    "wof:placetype":"venue"
},
  "geometry": {"coordinates":[-86.11291300000001,36.199292],"type":"Point"}
}