{
  "type": "Feature",
  "properties": {
    "iso:country":"US",
    "sg:address":"46 N Cooper St",
    "sg:city":"Memphis",
    "sg:classifiers":[
        {
            "category":"Professional",
            "subcategory":"Business Services",
            "type":"Services"
        }
    ],
    "sg:phone":"+1 901 726 1366",
    "sg:postcode":"38104",
    "sg:province":"TN",
    "sg:tags":[
        "appraiser"
    ],
    "wof:name":"Anthony Hill Appraisal Svc",
    "wof:placetype":"venue"
},
  "geometry": {"coordinates":[-89.98996,35.137753],"type":"Point"}
}