{
  "type": "Feature",
  "properties": {
    "addr:full":"2979 Egg Hill Rd Alamo TN 38001",
    "addr:postcode":"38001",
    "addr:street":"Egg Hill Rd",
    "iso:country":"US",
    "sg:address":"2979 Egg Hill Rd",
    "sg:city":"Alamo",
    "sg:classifiers":[
        {
            "category":"Banks & Credit Unions",
            "subcategory":"Financial Services",
            "type":"Services"
        }
    ],
    "sg:phone":"+1 731 696 5743",
    "sg:postcode":"38001",
    "sg:province":"TN",
    "sg:tags":[
        "investor"
    ],
    "wof:name":"Nance Investments LLC",
    "wof:placetype":"venue"
},
  "geometry": {"coordinates":[-89.14945,35.776987],"type":"Point"}
}