{
  "type": "Feature",
  "properties": {
    "iso:country":"US",
    "sg:address":"1709 Dry Gap Pike",
    "sg:city":"Knoxville",
    "sg:classifiers":[
        {
            "category":"Shopping",
            "subcategory":"Florist",
            "type":"Retail Goods"
        }
    ],
    "sg:phone":"+1 865 688 1968",
    "sg:postcode":"37918",
    "sg:province":"TN",
    "wof:name":"Elegant Touch Floral Gifts",
    "wof:placetype":"venue"
},
  "geometry": {"coordinates":[-83.970553,36.055852],"type":"Point"}
}