{
  "type": "Feature",
  "properties": {
    "addr:full":"2255 E Andrew Johnson Hwy Greeneville TN 37745",
    "addr:housenumber":"2255",
    "addr:postcode":"37745",
    "addr:street":"E Andrew Johnson Hwy",
    "iso:country":"US",
    "sg:address":"2255 E Andrew Johnson Hwy",
    "sg:city":"Greeneville",
    "sg:classifiers":[
        {
            "category":"Wholesale",
            "subcategory":"Electrical",
            "type":"Manufacturing & Wholesale Goods"
        }
    ],
    "sg:phone":"+1 423 798 0001",
    "sg:postcode":"37745",
    "sg:province":"TN",
    "sg:tags":[
        "alarm",
        "burglar",
        "system"
    ],
    "wof:name":"Advanced Security Concepts",
    "wof:placetype":"venue"
},
  "geometry": {"coordinates":[-82.783053,36.178409],"type":"Point"}
}