{
  "type": "Feature",
  "properties": {
    "iso:country":"US",
    "sg:address":"5002 Market Pl",
    "sg:city":"Mt Juliet",
    "sg:classifiers":[
        {
            "category":"Building & Trades",
            "subcategory":"Construction",
            "type":"Services"
        }
    ],
    "sg:phone":"+1 615 773 1931",
    "sg:postcode":"37122",
    "sg:province":"TN",
    "sg:tags":[
        "designer",
        "dealer",
        "pool",
        "swimming"
    ],
    "wof:name":"Roy Vaden Pools",
    "wof:placetype":"venue"
},
  "geometry": {"coordinates":[-86.53645299999999,36.233911],"type":"Point"}
}