{
  "type": "Feature",
  "properties": {
    "iso:country":"US",
    "sg:address":"115 Depot St",
    "sg:city":"Summertown",
    "sg:classifiers":[
        {
            "category":"Wholesale",
            "subcategory":"Computers",
            "type":"Manufacturing & Wholesale Goods"
        }
    ],
    "sg:phone":"+1 931 964 2660",
    "sg:postcode":"38483",
    "sg:province":"TN",
    "sg:tags":[
        "repair"
    ],
    "wof:name":"Southeastern Micro",
    "wof:placetype":"venue"
},
  "geometry": {"coordinates":[-87.29634,35.435154],"type":"Point"}
}