{
  "type": "Feature",
  "properties": {
    "iso:country":"US",
    "sg:address":"910 Chicken Rd",
    "sg:city":"Lebanon",
    "sg:classifiers":[
        {
            "category":"Building & Trades",
            "subcategory":"Construction",
            "type":"Services"
        }
    ],
    "sg:phone":"+1 615 449 7209",
    "sg:postcode":"37090",
    "sg:province":"TN",
    "sg:tags":[
        "house"
    ],
    "wof:name":"Oma Homes",
    "wof:placetype":"venue"
},
  "geometry": {"coordinates":[-86.315485,36.09848],"type":"Point"}
}