{
  "type": "Feature",
  "properties": {
    "iso:country":"US",
    "sg:address":"1384 Sand Creek Cove",
    "sg:city":"Cordova",
    "sg:classifiers":[
        {
            "category":"Building & Trades",
            "subcategory":"Landscaping Services",
            "type":"Services"
        }
    ],
    "sg:phone":"+1 901 309 3989",
    "sg:postcode":"38016",
    "sg:province":"TN",
    "sg:tags":[
        "landscape"
    ],
    "wof:name":"Dm Landscape",
    "wof:placetype":"venue"
},
  "geometry": {"coordinates":[-89.789039,35.162385],"type":"Point"}
}