{
  "type": "Feature",
  "properties": {
    "iso:country":"US",
    "sg:address":"4117 Cummings Hwy",
    "sg:city":"Chattanooga",
    "sg:classifiers":[
        {
            "category":"Building & Trades",
            "subcategory":"Construction",
            "type":"Services"
        }
    ],
    "sg:phone":"+1 423 821 7721",
    "sg:postcode":"37419",
    "sg:province":"TN",
    "sg:tags":[
        "general",
        "contractor"
    ],
    "wof:name":"Tristate Acoustics LLC",
    "wof:placetype":"venue"
},
  "geometry": {"coordinates":[-85.395059,35.02437],"type":"Point"}
}