{
  "type": "Feature",
  "properties": {
    "iso:country":"US",
    "sg:address":"2751 Commerce Dr NE",
    "sg:city":"Cleveland",
    "sg:classifiers":[
        {
            "category":"Banks & Credit Unions",
            "subcategory":"Bank",
            "type":"Services"
        }
    ],
    "sg:phone":"+1 423 479 2168",
    "sg:postcode":"37311",
    "sg:province":"TN",
    "wof:name":"Pathway Credit Union",
    "wof:placetype":"venue"
},
  "geometry": {"coordinates":[-84.85099,35.168638],"type":"Point"}
}