{
  "type": "Feature",
  "properties": {
    "iso:country":"US",
    "sg:address":"2305 N Highland Ave",
    "sg:city":"Jackson",
    "sg:classifiers":[
        {
            "category":"Autos & Motor Vehicles",
            "subcategory":"Fuel & Gas Station",
            "type":"Retail Goods"
        }
    ],
    "sg:phone":"+1 731 668 4582",
    "sg:postcode":"38305",
    "sg:province":"TN",
    "sg:tags":[
        "station",
        "gasoline",
        "oil"
    ],
    "wof:name":"Racetrac Service Station",
    "wof:placetype":"venue"
},
  "geometry": {"coordinates":[-88.829255,35.666985],"type":"Point"}
}