{
  "type": "Feature",
  "properties": {
    "iso:country":"US",
    "sg:address":"1404 Carter St",
    "sg:city":"Chattanooga",
    "sg:classifiers":[
        {
            "category":"Building & Trades",
            "subcategory":"Construction",
            "type":"Services"
        }
    ],
    "sg:phone":"+1 423 265 3693",
    "sg:postcode":"37402",
    "sg:province":"TN",
    "sg:tags":[
        "contractor",
        "mechanical"
    ],
    "wof:name":"Mechanical Contractor's Association",
    "wof:placetype":"venue"
},
  "geometry": {"coordinates":[-85.31472100000001,35.040125],"type":"Point"}
}