{
  "type": "Feature",
  "properties": {
    "addr:full":"106 Lee Carter Dr Johnson City TN 37601",
    "addr:housenumber":"106",
    "addr:postcode":"37601",
    "addr:street":"Lee Carter Dr",
    "iso:country":"US",
    "sg:address":"106 Lee Carter Dr",
    "sg:city":"Johnson City",
    "sg:classifiers":[
        {
            "category":"Building & Trades",
            "subcategory":"Construction",
            "type":"Services"
        }
    ],
    "sg:phone":"+1 423 610 0549",
    "sg:postcode":"37601",
    "sg:province":"TN",
    "sg:tags":[
        "residential"
    ],
    "wof:name":"Firm Foundation Cnstr LLC",
    "wof:placetype":"venue"
},
  "geometry": {"coordinates":[-82.387241,36.386229],"type":"Point"}
}