{
  "type": "Feature",
  "properties": {
    "iso:country":"US",
    "sg:address":"1905 Argo Ln",
    "sg:city":"Nashville",
    "sg:classifiers":[
        {
            "category":"Professional",
            "subcategory":"Management & Consulting",
            "type":"Services"
        }
    ],
    "sg:phone":"+1 615 331 4015",
    "sg:postcode":"37211",
    "sg:province":"TN",
    "sg:tags":[
        "marketing",
        "promotional"
    ],
    "wof:name":"Bcl Marketing & Consulting",
    "wof:placetype":"venue"
},
  "geometry": {"coordinates":[-86.727526,36.017752],"type":"Point"}
}