{
  "type": "Feature",
  "properties": {
    "iso:country":"US",
    "sg:address":"955 E Commerce St",
    "sg:city":"Lewisburg",
    "sg:classifiers":[
        {
            "category":"Building & Trades",
            "subcategory":"Landscaping Services",
            "type":"Services"
        }
    ],
    "sg:phone":"+1 931 276 2724",
    "sg:postcode":"37091",
    "sg:province":"TN",
    "sg:tags":[
        "tree"
    ],
    "wof:name":"Marshall County Tree Service",
    "wof:placetype":"venue"
},
  "geometry": {"coordinates":[-86.76934300000001,35.44374],"type":"Point"}
}