{
  "type": "Feature",
  "properties": {
    "iso:country":"US",
    "sg:address":"3377 Regal Dr",
    "sg:city":"Alcoa",
    "sg:classifiers":[
        {
            "category":"Retail",
            "subcategory":"Auto Repair",
            "type":"Services"
        }
    ],
    "sg:phone":"+1 865 970 2869",
    "sg:postcode":"37701",
    "sg:province":"TN",
    "sg:tags":[
        "body",
        "automobile",
        "painting"
    ],
    "wof:name":"Advantage Towing-West Chevy",
    "wof:placetype":"venue"
},
  "geometry": {"coordinates":[-83.970646,35.832262],"type":"Point"}
}