{
  "type": "Feature",
  "properties": {
    "iso:country":"US",
    "sg:address":"520 Big Horn Dr",
    "sg:city":"Old Hickory",
    "sg:classifiers":[
        {
            "category":"Building & Trades",
            "subcategory":"Construction",
            "type":"Services"
        }
    ],
    "sg:phone":"+1 615 773 1678",
    "sg:postcode":"37138",
    "sg:province":"TN",
    "sg:tags":[
        "hanging",
        "contractor"
    ],
    "wof:name":"David Roberts",
    "wof:placetype":"venue"
},
  "geometry": {"coordinates":[-86.579981,36.224103],"type":"Point"}
}