{
  "type": "Feature",
  "properties": {
    "addr:full":"230 Brooks Rd Atwood TN 38220",
    "addr:housenumber":"230",
    "addr:postcode":"38220",
    "addr:street":"Brooks Rd",
    "iso:country":"US",
    "sg:address":"230 Brooks Rd",
    "sg:city":"Atwood",
    "sg:phone":"+1 731 662 7692",
    "sg:postcode":"38220",
    "sg:province":"TN",
    "sg:tags":[
        "farm",
        "cotton"
    ],
    "wof:name":"Ricky Long Farms",
    "wof:placetype":"venue"
},
  "geometry": {"coordinates":[-88.68089000000001,35.973389],"type":"Point"}
}