{
  "type": "Feature",
  "properties": {
    "iso:country":"US",
    "sg:address":"2441 Old Fort Pkwy",
    "sg:city":"Murfreesboro",
    "sg:classifiers":[
        {
            "category":"Retail",
            "subcategory":"Laundry & Dry Cleaning",
            "type":"Services"
        }
    ],
    "sg:phone":"+1 615 867 3972",
    "sg:postcode":"37128",
    "sg:province":"TN",
    "sg:tags":[
        "drycleaning",
        "plant",
        "cleaners"
    ],
    "wof:name":"Crystal Cleaners 1",
    "wof:placetype":"venue"
},
  "geometry": {"coordinates":[-86.44750500000001,35.844944],"type":"Point"}
}