{
  "type": "Feature",
  "properties": {
    "addr:full":"1894 Edward Ave Memphis TN 38107",
    "addr:housenumber":"1894",
    "addr:postcode":"38107",
    "addr:street":"Edward Ave",
    "iso:country":"US",
    "sg:address":"1894 Edward Ave",
    "sg:city":"Memphis",
    "sg:classifiers":[
        {
            "category":"Organizations",
            "subcategory":"Membership Organization",
            "type":"Services"
        }
    ],
    "sg:phone":"+1 901 274 2614",
    "sg:postcode":"38107",
    "sg:province":"TN",
    "wof:name":"Global Employment Institute",
    "wof:placetype":"venue"
},
  "geometry": {"coordinates":[-89.99509999999999,35.167532],"type":"Point"}
}