{
  "type": "Feature",
  "properties": {
    "iso:country":"US",
    "sg:address":"1700 McCallie Ave",
    "sg:city":"Chattanooga",
    "sg:classifiers":[
        {
            "category":"Shopping",
            "type":"Retail Goods"
        }
    ],
    "sg:phone":"+1 423 622 2000",
    "sg:postcode":"37404",
    "sg:province":"TN",
    "sg:tags":[
        "merchandise"
    ],
    "wof:name":"Dynamic Prosthetic & Orthotic",
    "wof:placetype":"venue"
},
  "geometry": {"coordinates":[-85.27609699999999,35.036431],"type":"Point"}
}