{
  "type": "Feature",
  "properties": {
    "iso:country":"US",
    "sg:address":"1268 Market St",
    "sg:city":"Dayton",
    "sg:classifiers":[
        {
            "category":"Retail",
            "subcategory":"Auto Repair",
            "type":"Services"
        }
    ],
    "sg:phone":"+1 423 570 1926",
    "sg:postcode":"37321",
    "sg:province":"TN",
    "sg:tags":[
        "repairing",
        "automobile"
    ],
    "wof:name":"Fether Automotive",
    "wof:placetype":"venue"
},
  "geometry": {"coordinates":[-85.014589,35.492079],"type":"Point"}
}