{
  "type": "Feature",
  "properties": {
    "iso:country":"US",
    "sg:address":"8135 Chapel Hill Rd",
    "sg:city":"South Fulton",
    "sg:classifiers":[
        {
            "category":"Organizations",
            "subcategory":"Religious Organization",
            "type":"Services"
        }
    ],
    "sg:phone":"+1 731 479 3551",
    "sg:postcode":"38257",
    "sg:province":"TN",
    "sg:tags":[
        "church"
    ],
    "wof:name":"Johnsons Grove Baptist Church",
    "wof:placetype":"venue"
},
  "geometry": {"coordinates":[-88.900678,36.446189],"type":"Point"}
}