{
  "type": "Feature",
  "properties": {
    "iso:country":"US",
    "sg:address":"1634 NW Broad St",
    "sg:city":"Murfreesboro",
    "sg:classifiers":[
        {
            "category":"Autos & Motor Vehicles",
            "subcategory":"Automobile Sales",
            "type":"Retail Goods"
        }
    ],
    "sg:phone":"+1 615 895 2277",
    "sg:postcode":"37129",
    "sg:province":"TN",
    "sg:tags":[
        "used"
    ],
    "wof:name":"Crencor Leasing and Sales",
    "wof:placetype":"venue"
},
  "geometry": {"coordinates":[-86.420436,35.873443],"type":"Point"}
}