{
  "type": "Feature",
  "properties": {
    "addr:full":"214 W Main St Gallatin TN 37066",
    "addr:housenumber":"214",
    "addr:postcode":"37066",
    "addr:street":"W Main St",
    "iso:country":"US",
    "sg:address":"214 W Main St",
    "sg:city":"Gallatin",
    "sg:classifiers":[
        {
            "category":"Autos & Motor Vehicles",
            "subcategory":"Automobile Sales",
            "type":"Retail Goods"
        }
    ],
    "sg:phone":"+1 615 451 6800",
    "sg:postcode":"37066",
    "sg:province":"TN",
    "sg:tags":[
        "car",
        "dealer"
    ],
    "wof:name":"North Lake Bargain Ctr",
    "wof:placetype":"venue"
},
  "geometry": {"coordinates":[-86.449433,36.387609],"type":"Point"}
}