{
  "type": "Feature",
  "properties": {
    "iso:country":"US",
    "sg:address":"1260 Cherrydale Cove",
    "sg:city":"Memphis",
    "sg:classifiers":[
        {
            "category":"Wholesale",
            "subcategory":"Electrical",
            "type":"Manufacturing & Wholesale Goods"
        }
    ],
    "sg:phone":"+1 901 744 8589",
    "sg:postcode":"38111",
    "sg:province":"TN",
    "sg:tags":[
        "equipment"
    ],
    "wof:name":"Service Electric Company",
    "wof:placetype":"venue"
},
  "geometry": {"coordinates":[-89.917158,35.097575],"type":"Point"}
}