{
  "type": "Feature",
  "properties": {
    "iso:country":"US",
    "sg:address":"210 Williamson Dr",
    "sg:city":"Loudon",
    "sg:classifiers":[
        {
            "category":"Wholesale",
            "subcategory":"Metals & Minerals",
            "type":"Manufacturing & Wholesale Goods"
        }
    ],
    "sg:phone":"+1 865 458 1103",
    "sg:postcode":"37774",
    "sg:province":"TN",
    "sg:tags":[
        "sporting",
        "aluminum"
    ],
    "sg:website":"www.integrismetals.com",
    "wof:name":"Integris Metals Inc",
    "wof:placetype":"venue"
},
  "geometry": {"coordinates":[-84.312961,35.739772],"type":"Point"}
}