{
  "type": "Feature",
  "properties": {
    "addr:full":"107 Lexington Ave Lexington TN 38301",
    "addr:housenumber":"107",
    "addr:postcode":"38301",
    "addr:street":"Lexington Ave",
    "iso:country":"US",
    "sg:address":"107 Lexington Ave",
    "sg:city":"Lexington",
    "sg:classifiers":[
        {
            "category":"Health Services",
            "subcategory":"Optometrist",
            "type":"Services"
        }
    ],
    "sg:phone":"+1 731 968 2766",
    "sg:postcode":"38301",
    "sg:province":"TN",
    "wof:name":"Total Vision Inc",
    "wof:placetype":"venue"
},
  "geometry": {"coordinates":[-88.81204200000001,35.616401],"type":"Point"}
}