{
  "type": "Feature",
  "properties": {
    "iso:country":"US",
    "sg:address":"9960 Holly Grove Rd",
    "sg:city":"Cordova",
    "sg:classifiers":[
        {
            "category":"Sports & Exercise",
            "subcategory":"Race Track",
            "type":"Entertainment"
        }
    ],
    "sg:phone":"+1 901 758 2277",
    "sg:postcode":"38018",
    "sg:province":"TN",
    "sg:tags":[
        "operation",
        "racing",
        "or"
    ],
    "wof:name":"Jdh Motorsports",
    "wof:placetype":"venue"
},
  "geometry": {"coordinates":[-89.73041600000001,35.137388],"type":"Point"}
}