{
  "type": "Feature",
  "properties": {
    "addr:full":"4650 Ballard Slough Rd Covington TN 38015",
    "addr:housenumber":"4650",
    "addr:postcode":"38015",
    "addr:street":"Ballard Slough Rd",
    "iso:country":"US",
    "sg:address":"4650 Ballard Slough Rd",
    "sg:city":"Covington",
    "sg:classifiers":[
        {
            "category":"Organizations",
            "subcategory":"Religious Organization",
            "type":"Services"
        }
    ],
    "sg:phone":"+1 901 476 3227",
    "sg:postcode":"38015",
    "sg:province":"TN",
    "sg:tags":[
        "church"
    ],
    "wof:name":"Bright Hill Baptist Church",
    "wof:placetype":"venue"
},
  "geometry": {"coordinates":[-89.865641,35.555999],"type":"Point"}
}