{
  "type": "Feature",
  "properties": {
    "iso:country":"US",
    "sg:address":"236 Paragon Mills Rd",
    "sg:city":"Nashville",
    "sg:classifiers":[
        {
            "category":"Food & Beverages",
            "subcategory":"Groceries & Convenience Stores",
            "type":"Retail Goods"
        }
    ],
    "sg:phone":"+1 615 327 0817",
    "sg:postcode":"37211",
    "sg:province":"TN",
    "wof:name":"In & Out Market",
    "wof:placetype":"venue"
},
  "geometry": {"coordinates":[-86.70435999999999,36.086875],"type":"Point"}
}