{
  "type": "Feature",
  "properties": {
    "iso:country":"US",
    "sg:address":"1216 Lake Ridge Sq",
    "sg:city":"Johnson City",
    "sg:classifiers":[
        {
            "category":"Recreation",
            "type":"Entertainment"
        }
    ],
    "sg:phone":"+1 423 928 7270",
    "sg:postcode":"37601",
    "sg:province":"TN",
    "sg:tags":[
        "club",
        "membership"
    ],
    "wof:name":"Newcomers Club Johnson City",
    "wof:placetype":"venue"
},
  "geometry": {"coordinates":[-82.38410399999999,36.385105],"type":"Point"}
}