{
  "type": "Feature",
  "properties": {
    "iso:country":"US",
    "sg:address":"2588 Frayser Blvd",
    "sg:city":"Memphis",
    "sg:classifiers":[
        {
            "category":"Shopping",
            "subcategory":"Clothing, Apparel, & Fashions",
            "type":"Retail Goods"
        }
    ],
    "sg:phone":"+1 901 354 2777",
    "sg:postcode":"38127",
    "sg:province":"TN",
    "sg:website":"www.rainbowshops.com",
    "wof:name":"Rainbow",
    "wof:placetype":"venue"
},
  "geometry": {"coordinates":[-89.976726,35.220715],"type":"Point"}
}