{
  "type": "Feature",
  "properties": {
    "addr:full":"126 University St Martin TN 38237",
    "addr:housenumber":"126",
    "addr:postcode":"38237",
    "addr:street":"University St",
    "iso:country":"US",
    "sg:address":"126 University St",
    "sg:city":"Martin",
    "sg:classifiers":[
        {
            "category":"Banks & Credit Unions",
            "subcategory":"Bank",
            "type":"Services"
        }
    ],
    "sg:phone":"+1 731 587 9284",
    "sg:postcode":"38237",
    "sg:province":"TN",
    "wof:name":"First State Bank",
    "wof:placetype":"venue"
},
  "geometry": {"coordinates":[-88.85208,36.342157],"type":"Point"}
}