{
  "type": "Feature",
  "properties": {
    "addr:full":"307 S 2nd St Union City TN 38261",
    "addr:housenumber":"307",
    "addr:postcode":"38261",
    "addr:street":"S 2Nd St",
    "iso:country":"US",
    "sg:address":"307 S 2nd St",
    "sg:city":"Union City",
    "sg:classifiers":[
        {
            "category":"Insurance",
            "subcategory":"Insurance Agent",
            "type":"Services"
        }
    ],
    "sg:phone":"+1 731 885 3961",
    "sg:postcode":"38261",
    "sg:province":"TN",
    "wof:name":"BHD Insurance",
    "wof:placetype":"venue"
},
  "geometry": {"coordinates":[-89.058261,36.424419],"type":"Point"}
}