{
  "type": "Feature",
  "properties": {
    "iso:country":"US",
    "sg:address":"4530 Curve Nankipoo Rd",
    "sg:city":"Halls",
    "sg:classifiers":[
        {
            "category":"Building & Trades",
            "subcategory":"Electrical",
            "type":"Services"
        },
        {
            "category":"Building & Trades",
            "subcategory":"Plumbing",
            "type":"Services"
        }
    ],
    "sg:phone":"+1 731 836 3100",
    "sg:postcode":"38040",
    "sg:province":"TN",
    "sg:tags":[
        "electrical",
        "electric",
        "contractor"
    ],
    "wof:name":"Davis Heating Air and Electric",
    "wof:placetype":"venue"
},
  "geometry": {"coordinates":[-89.482395,35.854982],"type":"Point"}
}