{
  "type": "Feature",
  "properties": {
    "iso:country":"US",
    "sg:address":"7700 Noah Reid Rd",
    "sg:city":"Chattanooga",
    "sg:classifiers":[
        {
            "category":"Wholesale",
            "subcategory":"Non-durable Goods",
            "type":"Manufacturing & Wholesale Goods"
        }
    ],
    "sg:phone":"+1 423 855 1222",
    "sg:postcode":"37416",
    "sg:province":"TN",
    "sg:tags":[
        "advertising",
        "specialty"
    ],
    "wof:name":"Remainstobeseen",
    "wof:placetype":"venue"
},
  "geometry": {"coordinates":[-85.17171999999999,35.071836],"type":"Point"}
}