{
  "type": "Feature",
  "properties": {
    "iso:country":"US",
    "sg:address":"3119 Meadowside Ln",
    "sg:city":"Nashville",
    "sg:classifiers":[
        {
            "category":"Retail",
            "subcategory":"Repair Shop",
            "type":"Services"
        }
    ],
    "sg:phone":"+1 615 262 5292",
    "sg:postcode":"37207",
    "sg:province":"TN",
    "wof:name":"C Appleton Janitorl",
    "wof:placetype":"venue"
},
  "geometry": {"coordinates":[-86.777216,36.234696],"type":"Point"}
}