{
  "type": "Feature",
  "properties": {
    "iso:country":"US",
    "sg:address":"813 Airways Blvd",
    "sg:city":"Jackson",
    "sg:classifiers":[
        {
            "category":"Autos & Motor Vehicles",
            "subcategory":"Automobile Sales",
            "type":"Retail Goods"
        }
    ],
    "sg:phone":"+1 731 427 1333",
    "sg:postcode":"38301",
    "sg:province":"TN",
    "sg:tags":[
        "car",
        "dealer"
    ],
    "wof:name":"Powell Auto Sales",
    "wof:placetype":"venue"
},
  "geometry": {"coordinates":[-88.866865,35.618599],"type":"Point"}
}