{
  "type": "Feature",
  "properties": {
    "iso:country":"US",
    "sg:address":"196 Povo Rd",
    "sg:city":"Madisonville",
    "sg:classifiers":[
        {
            "category":"Building & Trades",
            "subcategory":"Construction",
            "type":"Services"
        }
    ],
    "sg:phone":"+1 423 442 3970",
    "sg:postcode":"37354",
    "sg:province":"TN",
    "sg:tags":[
        "contractor"
    ],
    "wof:name":"Stalens Guttering",
    "wof:placetype":"venue"
},
  "geometry": {"coordinates":[-84.346817,35.515045],"type":"Point"}
}