{
  "type": "Feature",
  "properties": {
    "addr:full":"4415 Nolensville Pike Nashville TN 37211",
    "addr:housenumber":"4415",
    "addr:postcode":"37211",
    "addr:street":"Nolensville Pike",
    "iso:country":"US",
    "sg:address":"4415 Nolensville Pike",
    "sg:city":"Nashville",
    "sg:classifiers":[
        {
            "category":"Retail",
            "subcategory":"Auto Repair",
            "type":"Services"
        }
    ],
    "sg:phone":"+1 615 834 2645",
    "sg:postcode":"37211",
    "sg:province":"TN",
    "sg:tags":[
        "body",
        "automotive",
        "painting",
        "automobile"
    ],
    "wof:name":"Paint and Body Perfectors",
    "wof:placetype":"venue"
},
  "geometry": {"coordinates":[-86.724492,36.073353],"type":"Point"}
}