{
  "type": "Feature",
  "properties": {
    "addr:full":"9 Music Sq E Nashville TN 37203",
    "addr:housenumber":"9",
    "addr:postcode":"37203",
    "addr:street":"Music Sq E",
    "iso:country":"US",
    "sg:address":"9 Music Sq E",
    "sg:city":"Nashville",
    "sg:classifiers":[
        {
            "category":"Professional",
            "type":"Services"
        }
    ],
    "sg:phone":"+1 615 252 8232",
    "sg:postcode":"37203",
    "sg:province":"TN",
    "sg:tags":[
        "establishment"
    ],
    "wof:name":"Briggs & Assoc",
    "wof:placetype":"venue"
},
  "geometry": {"coordinates":[-86.79177300000001,36.151491],"type":"Point"}
}