{
  "type": "Feature",
  "properties": {
    "addr:full":"571 Erin Dr Memphis TN 38117",
    "addr:housenumber":"571",
    "addr:postcode":"38117",
    "addr:street":"Erin Dr",
    "iso:country":"US",
    "sg:address":"571 Erin Dr",
    "sg:city":"Memphis",
    "sg:classifiers":[
        {
            "category":"Shopping",
            "subcategory":"Shoes",
            "type":"Retail Goods"
        }
    ],
    "sg:phone":"+1 901 761 0078",
    "sg:postcode":"38117",
    "sg:province":"TN",
    "wof:name":"Fleet Feet Sports",
    "wof:placetype":"venue"
},
  "geometry": {"coordinates":[-89.898854,35.11577],"type":"Point"}
}