{
  "type": "Feature",
  "properties": {
    "iso:country":"US",
    "sg:address":"3816 Brainerd Rd",
    "sg:city":"Chattanooga",
    "sg:classifiers":[
        {
            "category":"Restaurant",
            "type":"Food & Drink"
        }
    ],
    "sg:phone":"+1 423 624 0034",
    "sg:postcode":"37411",
    "sg:province":"TN",
    "sg:tags":[
        "eating"
    ],
    "wof:name":"Mayos Clinic",
    "wof:placetype":"venue"
},
  "geometry": {"coordinates":[-85.24287699999999,35.022632],"type":"Point"}
}