{
  "type": "Feature",
  "properties": {
    "addr:full":"2460 E 5th Ave Knoxville TN 37917",
    "addr:housenumber":"2460",
    "addr:postcode":"37917",
    "addr:street":"E 5Th Ave",
    "iso:country":"US",
    "sg:address":"2460 E 5th Ave",
    "sg:city":"Knoxville",
    "sg:classifiers":[
        {
            "category":"Real Estate",
            "subcategory":"Real Estate Operator",
            "type":"Services"
        }
    ],
    "sg:phone":"+1 865 546 5812",
    "sg:postcode":"37917",
    "sg:province":"TN",
    "sg:tags":[
        "building",
        "apartment"
    ],
    "wof:name":"Pleasantree Apartments",
    "wof:placetype":"venue"
},
  "geometry": {"coordinates":[-83.898304,35.984716],"type":"Point"}
}