{
  "type": "Feature",
  "properties": {
    "iso:country":"US",
    "sg:address":"905 Providence Blvd",
    "sg:city":"Clarksville",
    "sg:classifiers":[
        {
            "category":"Travel",
            "subcategory":"Hotels & Motels",
            "type":"Entertainment"
        }
    ],
    "sg:phone":"+1 931 552 4526",
    "sg:postcode":"37042",
    "sg:province":"TN",
    "sg:tags":[
        "operation"
    ],
    "wof:name":"Bon Aire Motel",
    "wof:placetype":"venue"
},
  "geometry": {"coordinates":[-87.38760000000001,36.55109],"type":"Point"}
}