{
  "type": "Feature",
  "properties": {
    "iso:country":"US",
    "sg:address":"160 White Bridge Pike",
    "sg:city":"Nashville",
    "sg:classifiers":[
        {
            "category":"Professional",
            "type":"Services"
        }
    ],
    "sg:phone":"+1 615 353 2512",
    "sg:postcode":"37209",
    "sg:province":"TN",
    "sg:tags":[
        "establishment"
    ],
    "wof:name":"Admin",
    "wof:placetype":"venue"
},
  "geometry": {"coordinates":[-86.85765600000001,36.137778],"type":"Point"}
}