{
  "type": "Feature",
  "properties": {
    "addr:full":"30 Bridge St Big Sandy TN 38221",
    "addr:housenumber":"30",
    "addr:postcode":"38221",
    "addr:street":"Bridge St",
    "iso:country":"US",
    "sg:address":"30 Bridge St",
    "sg:city":"Big Sandy",
    "sg:classifiers":[
        {
            "category":"Government",
            "subcategory":"Office",
            "type":"Public Place"
        }
    ],
    "sg:phone":"+1 731 593 5753",
    "sg:postcode":"38221",
    "sg:province":"TN",
    "sg:tags":[
        "village"
    ],
    "wof:name":"City Garage",
    "wof:placetype":"venue"
},
  "geometry": {"coordinates":[-88.086083,36.235728],"type":"Point"}
}