{
  "type": "Feature",
  "properties": {
    "iso:country":"US",
    "sg:address":"370 9th St SE",
    "sg:city":"Cleveland",
    "sg:classifiers":[
        {
            "category":"Home & Garden",
            "subcategory":"Furniture",
            "type":"Retail Goods"
        }
    ],
    "sg:phone":"+1 423 961 7243",
    "sg:postcode":"37311",
    "sg:province":"TN",
    "sg:tags":[
        "store"
    ],
    "sg:website":"http://www.catnapper.com",
    "wof:name":"Cleveland Chair",
    "wof:placetype":"venue"
},
  "geometry": {"coordinates":[-84.8753,35.151959],"type":"Point"}
}