{
  "type": "Feature",
  "properties": {
    "iso:country":"US",
    "sg:address":"168 Randolph Rd",
    "sg:city":"Oak Ridge",
    "sg:classifiers":[
        {
            "category":"Shopping",
            "subcategory":"Used Merchandise",
            "type":"Retail Goods"
        }
    ],
    "sg:phone":"+1 865 483 7070",
    "sg:postcode":"37830",
    "sg:province":"TN",
    "wof:name":"Just US",
    "wof:placetype":"venue"
},
  "geometry": {"coordinates":[-84.26734399999999,36.013943],"type":"Point"}
}