{
  "type": "Feature",
  "properties": {
    "iso:country":"US",
    "sg:address":"658 Gists Creek Rd",
    "sg:city":"Sevierville",
    "sg:classifiers":[
        {
            "category":"Retail",
            "subcategory":"Auto Repair",
            "type":"Services"
        }
    ],
    "sg:phone":"+1 865 774 1407",
    "sg:postcode":"37876",
    "sg:province":"TN",
    "sg:tags":[
        "repairing",
        "automobile"
    ],
    "wof:name":"Eagle Automotive",
    "wof:placetype":"venue"
},
  "geometry": {"coordinates":[-83.609243,35.88748],"type":"Point"}
}