{
  "type": "Feature",
  "properties": {
    "iso:country":"US",
    "sg:address":"127 Cosby Park Rd",
    "sg:city":"Cosby",
    "sg:classifiers":[
        {
            "category":"Government",
            "subcategory":"Office",
            "type":"Public Place"
        }
    ],
    "sg:phone":"+1 423 487 5418",
    "sg:postcode":"37722",
    "sg:province":"TN",
    "wof:name":"District Ranger",
    "wof:placetype":"venue"
},
  "geometry": {"coordinates":[-83.21240299999999,35.768714],"type":"Point"}
}