{
  "type": "Feature",
  "properties": {
    "iso:country":"US",
    "sg:address":"6010 Rutledge Pike",
    "sg:city":"Knoxville",
    "sg:classifiers":[
        {
            "category":"Food & Beverages",
            "subcategory":"Groceries & Convenience Stores",
            "type":"Retail Goods"
        }
    ],
    "sg:phone":"+1 865 546 9887",
    "sg:postcode":"37924",
    "sg:province":"TN",
    "wof:name":"John Sevier Market",
    "wof:placetype":"venue"
},
  "geometry": {"coordinates":[-83.845506,36.03226],"type":"Point"}
}