{
  "type": "Feature",
  "properties": {
    "iso:country":"US",
    "sg:address":"1035 Dr D B Todd Jr Blvd",
    "sg:city":"Nashville",
    "sg:classifiers":[
        {
            "category":"Health Services",
            "subcategory":"Doctor",
            "type":"Services"
        }
    ],
    "sg:phone":"+1 615 329 9013",
    "sg:postcode":"37208",
    "sg:province":"TN",
    "sg:tags":[
        "dentist"
    ],
    "wof:name":"J W King Jr DDS",
    "wof:placetype":"venue"
},
  "geometry": {"coordinates":[-86.80688499999999,36.170097],"type":"Point"}
}