{
  "type": "Feature",
  "properties": {
    "iso:country":"US",
    "sg:address":"355 School House Rd",
    "sg:city":"Robbins",
    "sg:classifiers":[
        {
            "category":"Education",
            "subcategory":"School",
            "type":"Public Place"
        }
    ],
    "sg:phone":"+1 423 627 4354",
    "sg:postcode":"37852",
    "sg:province":"TN",
    "wof:name":"Robbins Elementary School",
    "wof:placetype":"venue"
},
  "geometry": {"coordinates":[-84.58595699999999,36.352156],"type":"Point"}
}