{
  "type": "Feature",
  "properties": {
    "iso:country":"US",
    "sg:address":"5548 W Shady Trl",
    "sg:city":"Old Hickory",
    "sg:classifiers":[
        {
            "category":"Shopping",
            "subcategory":"Music",
            "type":"Retail Goods"
        }
    ],
    "sg:phone":"+1 615 754 7439",
    "sg:postcode":"37138",
    "sg:province":"TN",
    "sg:tags":[
        "compact",
        "record",
        "disc",
        "tape"
    ],
    "wof:name":"Center Hill Records",
    "wof:placetype":"venue"
},
  "geometry": {"coordinates":[-86.569801,36.236076],"type":"Point"}
}