{
  "type": "Feature",
  "properties": {
    "addr:full":"2485 Parkway Pl Memphis TN 38112",
    "addr:housenumber":"2485",
    "addr:postcode":"38112",
    "addr:street":"Parkway Pl",
    "iso:country":"US",
    "sg:address":"2485 Parkway Pl",
    "sg:city":"Memphis",
    "sg:classifiers":[
        {
            "category":"Food & Beverages",
            "subcategory":"Groceries & Convenience Stores",
            "type":"Retail Goods"
        }
    ],
    "sg:phone":"+1 901 323 2060",
    "sg:postcode":"38112",
    "sg:province":"TN",
    "sg:tags":[
        "automotive"
    ],
    "wof:name":"Big Bear Towing",
    "wof:placetype":"venue"
},
  "geometry": {"coordinates":[-89.976557,35.148843],"type":"Point"}
}