{
  "type": "Feature",
  "properties": {
    "iso:country":"US",
    "sg:address":"4445 Louise Rd",
    "sg:city":"Cumberland Furn",
    "sg:classifiers":[
        {
            "category":"Organizations",
            "subcategory":"Religious Organization",
            "type":"Services"
        }
    ],
    "sg:phone":"+1 931 387 2231",
    "sg:postcode":"37051",
    "sg:province":"TN",
    "sg:tags":[
        "church"
    ],
    "wof:name":"Lone Oak Baptist Church",
    "wof:placetype":"venue"
},
  "geometry": {"coordinates":[-87.395359,36.382345],"type":"Point"}
}