{
  "type": "Feature",
  "properties": {
    "addr:full":"900 Stratford Cir NW Cleveland TN 37312",
    "addr:housenumber":"900",
    "addr:postcode":"37312",
    "addr:street":"Stratford Cir Nw",
    "iso:country":"US",
    "sg:address":"900 Stratford Cir NW",
    "sg:city":"Cleveland",
    "sg:classifiers":[
        {
            "category":"Autos & Motor Vehicles",
            "subcategory":"Fuel & Gas Station",
            "type":"Retail Goods"
        }
    ],
    "sg:phone":"+1 423 478 3265",
    "sg:postcode":"37312",
    "sg:province":"TN",
    "sg:tags":[
        "store"
    ],
    "wof:name":"Dalton Pike Mart",
    "wof:placetype":"venue"
},
  "geometry": {"coordinates":[-84.858659,35.209187],"type":"Point"}
}