{
  "type": "Feature",
  "properties": {
    "addr:full":"906 State Hwy 1 Gatlinburg TN 37771",
    "addr:housenumber":"906",
    "addr:postcode":"37771",
    "addr:street":"State Hwy 1",
    "iso:country":"US",
    "sg:address":"906 State Hwy 1",
    "sg:city":"Gatlinburg",
    "sg:classifiers":[
        {
            "category":"Real Estate",
            "subcategory":"Architect",
            "type":"Services"
        }
    ],
    "sg:phone":"+1 865 436 9436",
    "sg:postcode":"37771",
    "sg:province":"TN",
    "wof:name":"Trotter & Assoc Architect",
    "wof:placetype":"venue"
},
  "geometry": {"coordinates":[-84.32639399999999,35.835183],"type":"Point"}
}