{
  "type": "Feature",
  "properties": {
    "iso:country":"US",
    "sg:address":"515 Alexandria Dr",
    "sg:city":"Collierville",
    "sg:classifiers":[
        {
            "category":"Real Estate",
            "subcategory":"Architect",
            "type":"Services"
        }
    ],
    "sg:phone":"+1 901 854 9500",
    "sg:postcode":"38017",
    "sg:province":"TN",
    "sg:tags":[
        "architectural"
    ],
    "wof:name":"Cornerstone Designs Inc",
    "wof:placetype":"venue"
},
  "geometry": {"coordinates":[-89.649895,35.071696],"type":"Point"}
}