{
  "type": "Feature",
  "properties": {
    "iso:country":"US",
    "sg:address":"680 Oakleaf Office Ln",
    "sg:city":"Memphis",
    "sg:classifiers":[
        {
            "category":"Professional",
            "subcategory":"Detective & Security Services",
            "type":"Services"
        }
    ],
    "sg:phone":"+1 901 767 8787",
    "sg:postcode":"38117",
    "sg:province":"TN",
    "sg:tags":[
        "system"
    ],
    "wof:name":"ADT Security Systems Inc",
    "wof:placetype":"venue"
},
  "geometry": {"coordinates":[-89.906046,35.112639],"type":"Point"}
}