{
  "type": "Feature",
  "properties": {
    "iso:country":"US",
    "sg:address":"3526 Parkway",
    "sg:city":"Pigeon Forge",
    "sg:classifiers":[
        {
            "category":"Professional",
            "type":"Services"
        }
    ],
    "sg:phone":"+1 865 908 2029",
    "sg:postcode":"37863",
    "sg:province":"TN",
    "wof:name":"Hollywood Connection",
    "wof:placetype":"venue"
},
  "geometry": {"coordinates":[-83.553218,35.785644],"type":"Point"}
}