{
  "type": "Feature",
  "properties": {
    "iso:country":"US",
    "sg:address":"8309 Asheville Hwy",
    "sg:city":"Knoxville",
    "sg:classifiers":[
        {
            "category":"Health Services",
            "subcategory":"Health Practitioner",
            "type":"Services"
        }
    ],
    "sg:phone":"+1 865 932 1334",
    "sg:postcode":"37924",
    "sg:province":"TN",
    "sg:tags":[
        "therapy",
        "physical"
    ],
    "wof:name":"Maximum Potential Therapies",
    "wof:placetype":"venue"
},
  "geometry": {"coordinates":[-83.748758,36.024291],"type":"Point"}
}