{
  "type": "Feature",
  "properties": {
    "addr:full":"4156 Macon Rd Memphis TN 38122",
    "addr:housenumber":"4156",
    "addr:postcode":"38122",
    "addr:street":"Macon Rd",
    "iso:country":"US",
    "sg:address":"4156 Macon Rd",
    "sg:city":"Memphis",
    "sg:classifiers":[
        {
            "category":"Building & Trades",
            "subcategory":"Construction",
            "type":"Services"
        }
    ],
    "sg:phone":"+1 901 458 7100",
    "sg:postcode":"38122",
    "sg:province":"TN",
    "sg:tags":[
        "general",
        "contractor"
    ],
    "wof:name":"Trowel Master Construction",
    "wof:placetype":"venue"
},
  "geometry": {"coordinates":[-89.921536,35.162198],"type":"Point"}
}