{
  "type": "Feature",
  "properties": {
    "iso:country":"US",
    "sg:address":"8113 Westland Dr",
    "sg:city":"Knoxville",
    "sg:classifiers":[
        {
            "category":"Professional",
            "subcategory":"Computer Services",
            "type":"Services"
        }
    ],
    "sg:phone":"+1 865 693 8905",
    "sg:postcode":"37919",
    "sg:province":"TN",
    "sg:tags":[
        "prepackaged",
        "software"
    ],
    "wof:name":"Ravine Software",
    "wof:placetype":"venue"
},
  "geometry": {"coordinates":[-84.043537,35.907408],"type":"Point"}
}