{
  "type": "Feature",
  "properties": {
    "iso:country":"US",
    "sg:address":"702 Vanderhorst Dr",
    "sg:city":"Nashville",
    "sg:classifiers":[
        {
            "category":"Building & Trades",
            "subcategory":"Cleaning & Sanitation",
            "type":"Services"
        }
    ],
    "sg:phone":"+1 615 228 7859",
    "sg:postcode":"37207",
    "sg:province":"TN",
    "sg:tags":[
        "paper",
        "janitorial",
        "supply"
    ],
    "wof:name":"Best Service Cleaning Co",
    "wof:placetype":"venue"
},
  "geometry": {"coordinates":[-86.81104999999999,36.217784],"type":"Point"}
}