{
  "type": "Feature",
  "properties": {
    "iso:country":"US",
    "sg:address":"790 G'Fellers Rd",
    "sg:city":"Chuckey",
    "sg:classifiers":[
        {
            "category":"Utilities",
            "type":"Services"
        }
    ],
    "sg:phone":"+1 423 257 8904",
    "sg:postcode":"37641",
    "sg:province":"TN",
    "sg:tags":[
        "sanitary"
    ],
    "wof:name":"East Tennessee Sweeping Svcs",
    "wof:placetype":"venue"
},
  "geometry": {"coordinates":[-82.695528,36.174632],"type":"Point"}
}