{
  "type": "Feature",
  "properties": {
    "iso:country":"US",
    "sg:address":"130 N Water Ave",
    "sg:city":"Gallatin",
    "sg:classifiers":[
        {
            "category":"Shopping",
            "subcategory":"Jewelry",
            "type":"Retail Goods"
        }
    ],
    "sg:phone":"+1 615 452 0688",
    "sg:postcode":"37066",
    "sg:province":"TN",
    "sg:tags":[
        "repair",
        "diamond",
        "watch"
    ],
    "wof:name":"Blue's Jewelry Store",
    "wof:placetype":"venue"
},
  "geometry": {"coordinates":[-86.44653700000001,36.388771],"type":"Point"}
}