{
  "type": "Feature",
  "properties": {
    "iso:country":"US",
    "sg:address":"630 Wilson Ave",
    "sg:city":"Tullahoma",
    "sg:classifiers":[
        {
            "category":"Social Services",
            "type":"Services"
        }
    ],
    "sg:phone":"+1 931 454 1912",
    "sg:postcode":"37388",
    "sg:province":"TN",
    "sg:tags":[
        "probation"
    ],
    "wof:name":"Adult Probation",
    "wof:placetype":"venue"
},
  "geometry": {"coordinates":[-86.224233,35.36568],"type":"Point"}
}