{
  "type": "Feature",
  "properties": {
    "addr:full":"2814 Dogwood Pl Nashville TN 37204",
    "addr:housenumber":"2814",
    "addr:postcode":"37204",
    "addr:street":"Dogwood Pl",
    "iso:country":"US",
    "sg:address":"2814 Dogwood Pl",
    "sg:city":"Nashville",
    "sg:classifiers":[
        {
            "category":"Professional",
            "subcategory":"Lawyer & Legal Services",
            "type":"Services"
        }
    ],
    "sg:phone":"+1 615 742 1304",
    "sg:postcode":"37204",
    "sg:province":"TN",
    "sg:tags":[
        "attorney"
    ],
    "wof:name":"Susan R Limor",
    "wof:placetype":"venue"
},
  "geometry": {"coordinates":[-86.76469400000001,36.113404],"type":"Point"}
}