{
  "type": "Feature",
  "properties": {
    "addr:full":"387 Bond Cemetery Rd Denmark TN 38391",
    "addr:housenumber":"387",
    "addr:postcode":"38391",
    "addr:street":"Bond Cemetery Rd",
    "iso:country":"US",
    "sg:address":"387 Bond Cemetery Rd",
    "sg:city":"Denmark",
    "sg:classifiers":[
        {
            "category":"Organizations",
            "subcategory":"Community Association",
            "type":"Services"
        }
    ],
    "sg:phone":"+1 731 422 3055",
    "sg:postcode":"38391",
    "sg:province":"TN",
    "wof:name":"Disabled American Veterans",
    "wof:placetype":"venue"
},
  "geometry": {"coordinates":[-89.034144,35.564172],"type":"Point"}
}