{
  "type": "Feature",
  "properties": {
    "iso:country":"US",
    "sg:address":"7257 Winchester Rd",
    "sg:city":"Memphis",
    "sg:classifiers":[
        {
            "category":"Building & Trades",
            "subcategory":"Equipment Rental",
            "type":"Services"
        }
    ],
    "sg:phone":"+1 866 871 1040",
    "sg:postcode":"38125",
    "sg:province":"TN",
    "sg:tags":[
        "preparation",
        "return",
        "tax"
    ],
    "sg:website":"http://www.libertytax.com/",
    "wof:name":"Liberty Tax Service",
    "wof:placetype":"venue"
},
  "geometry": {"coordinates":[-89.82141799999999,35.049015],"type":"Point"}
}