{
  "type": "Feature",
  "properties": {
    "iso:country":"US",
    "sg:address":"1432 US Hwy 51 N",
    "sg:city":"Covington",
    "sg:classifiers":[
        {
            "category":"Farming",
            "subcategory":"Farm & Veterinary Services",
            "type":"Manufacturing & Wholesale Goods"
        }
    ],
    "sg:phone":"+1 901 476 7088",
    "sg:postcode":"38019",
    "sg:province":"TN",
    "sg:tags":[
        "seed",
        "grain",
        "cleaning"
    ],
    "wof:name":"Southall's Seed Cleaner",
    "wof:placetype":"venue"
},
  "geometry": {"coordinates":[-89.631692,35.597481],"type":"Point"}
}