{
  "type": "Feature",
  "properties": {
    "iso:country":"US",
    "sg:address":"902 W Brow Rd",
    "sg:city":"Lookout Mountain",
    "sg:classifiers":[
        {
            "category":"Health Services",
            "subcategory":"Doctor",
            "type":"Services"
        }
    ],
    "sg:phone":"+1 423 821 7289",
    "sg:postcode":"37350",
    "sg:province":"TN",
    "wof:name":"Wayne E Tipps",
    "wof:placetype":"venue"
},
  "geometry": {"coordinates":[-85.345963,35.008038],"type":"Point"}
}