{
  "type": "Feature",
  "properties": {
    "iso:country":"US",
    "sg:address":"311 E Broadway St",
    "sg:city":"Newport",
    "sg:classifiers":[
        {
            "category":"Restaurant",
            "type":"Food & Drink"
        }
    ],
    "sg:phone":"+1 423 625 7701",
    "sg:postcode":"37821",
    "sg:province":"TN",
    "wof:name":"Kaupp Enterprises",
    "wof:placetype":"venue"
},
  "geometry": {"coordinates":[-83.18584199999999,35.966674],"type":"Point"}
}