{
  "type": "Feature",
  "properties": {
    "addr:full":"127 Hwy 52 W Lafayette TN 37083",
    "addr:housenumber":"127",
    "addr:postcode":"37083",
    "addr:street":"Hwy 52 W",
    "iso:country":"US",
    "sg:address":"127 Hwy 52 W",
    "sg:city":"Lafayette",
    "sg:classifiers":[
        {
            "category":"Manufacturing",
            "subcategory":"Buildings",
            "type":"Manufacturing & Wholesale Goods"
        }
    ],
    "sg:phone":"+1 615 666 2104",
    "sg:postcode":"37083",
    "sg:province":"TN",
    "sg:tags":[
        "prefab"
    ],
    "wof:name":"Carter Homes LLC",
    "wof:placetype":"venue"
},
  "geometry": {"coordinates":[-86.02745,36.517585],"type":"Point"}
}