{
  "type": "Feature",
  "properties": {
    "iso:country":"US",
    "sg:address":"33 Rebel Rd",
    "sg:city":"Jackson",
    "sg:classifiers":[
        {
            "category":"Restaurant",
            "type":"Food & Drink"
        }
    ],
    "sg:phone":"+1 731 423 0154",
    "sg:postcode":"38301",
    "sg:province":"TN",
    "sg:tags":[
        "eating"
    ],
    "wof:name":"Tonys Eat In/Carry Out",
    "wof:placetype":"venue"
},
  "geometry": {"coordinates":[-88.81341500000001,35.564685],"type":"Point"}
}