{
  "type": "Feature",
  "properties": {
    "iso:country":"US",
    "sg:address":"120 S Jefferson St",
    "sg:city":"Ripley",
    "sg:classifiers":[
        {
            "category":"Personal",
            "subcategory":"Beauty Salon",
            "type":"Services"
        }
    ],
    "sg:phone":"+1 731 635 0195",
    "sg:postcode":"38063",
    "sg:province":"TN",
    "sg:tags":[
        "shop"
    ],
    "wof:name":"Styles By Stephanie",
    "wof:placetype":"venue"
},
  "geometry": {"coordinates":[-89.53185999999999,35.742449],"type":"Point"}
}