{
  "type": "Feature",
  "properties": {
    "iso:country":"US",
    "sg:address":"1912 Creason Dr",
    "sg:city":"Maryville",
    "sg:classifiers":[
        {
            "category":"Retail",
            "subcategory":"Auto Repair",
            "type":"Services"
        }
    ],
    "sg:phone":"+1 865 681 2062",
    "sg:postcode":"37801",
    "sg:province":"TN",
    "sg:tags":[
        "body"
    ],
    "wof:name":"Leroy Long JRS Paint & Body",
    "wof:placetype":"venue"
},
  "geometry": {"coordinates":[-84.004296,35.739551],"type":"Point"}
}