{
  "type": "Feature",
  "properties": {
    "addr:full":"1424 Crescent Rd Loudon TN 37774",
    "addr:housenumber":"1424",
    "addr:postcode":"37774",
    "addr:street":"Crescent Rd",
    "iso:country":"US",
    "sg:address":"1424 Crescent Rd",
    "sg:city":"Loudon",
    "sg:classifiers":[
        {
            "category":"Organizations",
            "subcategory":"Religious Organization",
            "type":"Services"
        }
    ],
    "sg:phone":"+1 865 458 5781",
    "sg:postcode":"37774",
    "sg:province":"TN",
    "sg:tags":[
        "church"
    ],
    "wof:name":"East Hills Baptist Church",
    "wof:placetype":"venue"
},
  "geometry": {"coordinates":[-84.31928499999999,35.747925],"type":"Point"}
}