{
  "type": "Feature",
  "properties": {
    "addr:full":"6080 Shallowford Rd Chattanooga TN 37421",
    "addr:housenumber":"6080",
    "addr:postcode":"37421",
    "addr:street":"Shallowford Rd",
    "iso:country":"US",
    "sg:address":"6080 Shallowford Rd",
    "sg:city":"Chattanooga",
    "sg:classifiers":[
        {
            "category":"Utilities",
            "subcategory":"Electric",
            "type":"Services"
        }
    ],
    "sg:phone":"+1 423 756 2706",
    "sg:postcode":"37421",
    "sg:province":"TN",
    "sg:tags":[
        "company"
    ],
    "wof:name":"EPB Electric Power",
    "wof:placetype":"venue"
},
  "geometry": {"coordinates":[-85.184051,35.053357],"type":"Point"}
}