{
  "type": "Feature",
  "properties": {
    "iso:country":"US",
    "sg:address":"2845 Appling Way",
    "sg:city":"Memphis",
    "sg:classifiers":[
        {
            "category":"Autos & Motor Vehicles",
            "subcategory":"Auto Supplies",
            "type":"Retail Goods"
        }
    ],
    "sg:phone":"+1 901 388 1180",
    "sg:postcode":"38133",
    "sg:province":"TN",
    "sg:tags":[
        "automobile",
        "parts"
    ],
    "wof:name":"Union Auto Parts",
    "wof:placetype":"venue"
},
  "geometry": {"coordinates":[-89.810689,35.203065],"type":"Point"}
}