{
  "type": "Feature",
  "properties": {
    "iso:country":"US",
    "sg:address":"5101 Albert Dr",
    "sg:city":"Brentwood",
    "sg:classifiers":[
        {
            "category":"Building & Trades",
            "subcategory":"Construction",
            "type":"Services"
        }
    ],
    "sg:phone":"+1 615 377 2337",
    "sg:postcode":"37027",
    "sg:province":"TN",
    "sg:tags":[
        "hanging",
        "contractor"
    ],
    "wof:name":"Southeast Painting",
    "wof:placetype":"venue"
},
  "geometry": {"coordinates":[-86.81750099999999,35.988044],"type":"Point"}
}