{
  "type": "Feature",
  "properties": {
    "addr:full":"167 Webster Ave Memphis TN 38126",
    "addr:housenumber":"167",
    "addr:postcode":"38126",
    "addr:street":"Webster Ave",
    "iso:country":"US",
    "sg:address":"167 Webster Ave",
    "sg:city":"Memphis",
    "sg:classifiers":[
        {
            "category":"Retail",
            "subcategory":"Auto Repair",
            "type":"Services"
        }
    ],
    "sg:phone":"+1 901 527 4881",
    "sg:postcode":"38126",
    "sg:province":"TN",
    "sg:tags":[
        "repairing",
        "automobile"
    ],
    "wof:name":"Tri State Reconditioned Car",
    "wof:placetype":"venue"
},
  "geometry": {"coordinates":[-90.05787599999999,35.130349],"type":"Point"}
}