{
  "type": "Feature",
  "properties": {
    "addr:full":"39 Caradine Dr Jackson TN 38301",
    "addr:housenumber":"39",
    "addr:postcode":"38301",
    "addr:street":"Caradine Dr",
    "iso:country":"US",
    "sg:address":"39 Caradine Dr",
    "sg:city":"Jackson",
    "sg:classifiers":[
        {
            "category":"Organizations",
            "subcategory":"Religious Organization",
            "type":"Services"
        }
    ],
    "sg:phone":"+1 731 668 5399",
    "sg:postcode":"38301",
    "sg:province":"TN",
    "wof:name":"Bebe Stone Ministries",
    "wof:placetype":"venue"
},
  "geometry": {"coordinates":[-88.843796,35.643765],"type":"Point"}
}