{
  "type": "Feature",
  "properties": {
    "iso:country":"US",
    "sg:address":"19 Millsap Dr",
    "sg:city":"Jackson",
    "sg:classifiers":[
        {
            "category":"Freight",
            "type":"Transportation"
        }
    ],
    "sg:phone":"+1 731 935 2979",
    "sg:postcode":"38305",
    "sg:province":"TN",
    "sg:tags":[
        "operator",
        "trucking"
    ],
    "wof:name":"Two Sisters Inc",
    "wof:placetype":"venue"
},
  "geometry": {"coordinates":[-88.800912,35.692377],"type":"Point"}
}