{
  "type": "Feature",
  "properties": {
    "addr:full":"3946 Park Ave Memphis TN 38111",
    "addr:housenumber":"3946",
    "addr:postcode":"38111",
    "addr:street":"Park Ave",
    "iso:country":"US",
    "sg:address":"3946 Park Ave",
    "sg:city":"Memphis",
    "sg:classifiers":[
        {
            "category":"Wholesale",
            "subcategory":"Furniture",
            "type":"Manufacturing & Wholesale Goods"
        }
    ],
    "sg:phone":"+1 901 452 8433",
    "sg:postcode":"38111",
    "sg:province":"TN",
    "sg:tags":[
        "equipment-wholesale",
        "manufacturer"
    ],
    "wof:name":"Otter's Office Supplies",
    "wof:placetype":"venue"
},
  "geometry": {"coordinates":[-89.93108100000001,35.107517],"type":"Point"}
}