{
  "type": "Feature",
  "properties": {
    "iso:country":"US",
    "sg:address":"3759 Homewood Rd",
    "sg:city":"Memphis",
    "sg:classifiers":[
        {
            "category":"Manufacturing",
            "subcategory":"Motor Vehicles & Parts",
            "type":"Manufacturing & Wholesale Goods"
        },
        {
            "category":"Autos & Motor Vehicles",
            "subcategory":"Auto Supplies",
            "type":"Retail Goods"
        }
    ],
    "sg:phone":"+1 901 368 0305",
    "sg:postcode":"38118",
    "sg:province":"TN",
    "sg:tags":[
        "distributor",
        "motors-manufacturers",
        "electric",
        "motors-used"
    ],
    "wof:name":"Green Electric Motor Works",
    "wof:placetype":"venue"
},
  "geometry": {"coordinates":[-89.925825,35.04621],"type":"Point"}
}