{
  "type": "Feature",
  "properties": {
    "iso:country":"US",
    "sg:address":"1875 US Hwy 51 Bus",
    "sg:city":"Dyersburg",
    "sg:classifiers":[
        {
            "category":"Real Estate",
            "subcategory":"Real Estate Agent",
            "type":"Services"
        }
    ],
    "sg:phone":"+1 731 286 0555",
    "sg:postcode":"38024",
    "sg:province":"TN",
    "wof:name":"Dogwood Realty",
    "wof:placetype":"venue"
},
  "geometry": {"coordinates":[-89.368511,36.049292],"type":"Point"}
}