{
  "type": "Feature",
  "properties": {
    "addr:full":"7044 Northridge Dr Nashville TN 37221",
    "addr:housenumber":"7044",
    "addr:postcode":"37221",
    "addr:street":"Northridge Dr",
    "iso:country":"US",
    "sg:address":"7044 Northridge Dr",
    "sg:city":"Nashville",
    "sg:classifiers":[
        {
            "category":"Professional",
            "type":"Services"
        }
    ],
    "sg:phone":"+1 615 838 0502",
    "sg:postcode":"37221",
    "sg:province":"TN",
    "sg:tags":[
        "a",
        "song",
        "wholesale",
        "writer",
        "operates",
        "record",
        "as"
    ],
    "wof:name":"Lsr Records Inc",
    "wof:placetype":"venue"
},
  "geometry": {"coordinates":[-86.953231,36.061059],"type":"Point"}
}