{
  "type": "Feature",
  "properties": {
    "addr:full":"3939 Summer Ave Memphis TN 38122",
    "addr:housenumber":"3939",
    "addr:postcode":"38122",
    "addr:street":"Summer Ave",
    "iso:country":"US",
    "sg:address":"3939 Summer Ave",
    "sg:city":"Memphis",
    "sg:classifiers":[
        {
            "category":"Professional",
            "subcategory":"Employment Agencies",
            "type":"Services"
        }
    ],
    "sg:phone":"+1 901 323 7400",
    "sg:postcode":"38122",
    "sg:province":"TN",
    "sg:tags":[
        "help",
        "contractor"
    ],
    "wof:name":"Labor Finders",
    "wof:placetype":"venue"
},
  "geometry": {"coordinates":[-89.928725,35.149054],"type":"Point"}
}