{
  "type": "Feature",
  "properties": {
    "iso:country":"US",
    "sg:address":"5003 Bonnavista Dr",
    "sg:city":"Hermitage",
    "sg:classifiers":[
        {
            "category":"Building & Trades",
            "subcategory":"Construction",
            "type":"Services"
        }
    ],
    "sg:phone":"+1 615 419 0241",
    "sg:postcode":"37076",
    "sg:province":"TN",
    "sg:tags":[
        "painter"
    ],
    "wof:name":"True Colors Painting",
    "wof:placetype":"venue"
},
  "geometry": {"coordinates":[-86.633933,36.19912],"type":"Point"}
}