{
  "type": "Feature",
  "properties": {
    "iso:country":"US",
    "sg:address":"1500 E Reelfoot Ave",
    "sg:city":"Union City",
    "sg:classifiers":[
        {
            "category":"Food & Beverages",
            "subcategory":"Groceries & Convenience Stores",
            "type":"Retail Goods"
        }
    ],
    "sg:phone":"+1 731 885 1105",
    "sg:postcode":"38261",
    "sg:province":"TN",
    "wof:name":"3 J's Food Mart",
    "wof:placetype":"venue"
},
  "geometry": {"coordinates":[-89.04132199999999,36.413312],"type":"Point"}
}