{
  "type": "Feature",
  "properties": {
    "iso:country":"US",
    "sg:address":"3371 N Trezevant St",
    "sg:city":"Memphis",
    "sg:classifiers":[
        {
            "category":"Building & Trades",
            "subcategory":"Construction",
            "type":"Services"
        }
    ],
    "sg:phone":"+1 901 358 8875",
    "sg:postcode":"38127",
    "sg:province":"TN",
    "sg:tags":[
        "contractor",
        "painting",
        "hanging"
    ],
    "wof:name":"Greg S Custom Painting",
    "wof:placetype":"venue"
},
  "geometry": {"coordinates":[-89.978655,35.217775],"type":"Point"}
}