{
  "type": "Feature",
  "properties": {
    "addr:full":"918 Hillsboro Blvd Manchester TN 37355",
    "addr:housenumber":"918",
    "addr:postcode":"37355",
    "addr:street":"Hillsboro Blvd",
    "iso:country":"US",
    "sg:address":"918 Hillsboro Blvd",
    "sg:city":"Manchester",
    "sg:classifiers":[
        {
            "category":"Shopping",
            "subcategory":"Pharmacy",
            "type":"Retail Goods"
        }
    ],
    "sg:phone":"+1 931 728 6656",
    "sg:postcode":"37355",
    "sg:province":"TN",
    "wof:name":"Rite Aid Pharmacy",
    "wof:placetype":"venue"
},
  "geometry": {"coordinates":[-86.079256,35.474626],"type":"Point"}
}