{
  "type": "Feature",
  "properties": {
    "iso:country":"US",
    "sg:address":"214 Brisbane Rd",
    "sg:city":"Oak Ridge",
    "sg:classifiers":[
        {
            "category":"Manufacturing",
            "subcategory":"Printing",
            "type":"Manufacturing & Wholesale Goods"
        }
    ],
    "sg:phone":"+1 865 483 4789",
    "sg:postcode":"37830",
    "sg:province":"TN",
    "sg:tags":[
        "screen"
    ],
    "wof:name":"Knoxvegas Screen Printing",
    "wof:placetype":"venue"
},
  "geometry": {"coordinates":[-84.213807,36.041829],"type":"Point"}
}