{
  "type": "Feature",
  "properties": {
    "addr:full":"2177 Frayser Blvd Memphis TN 38127",
    "addr:housenumber":"2177",
    "addr:postcode":"38127",
    "addr:street":"Frayser Blvd",
    "iso:country":"US",
    "sg:address":"2177 Frayser Blvd",
    "sg:city":"Memphis",
    "sg:classifiers":[
        {
            "category":"Shopping",
            "subcategory":"Computers & Home Electronics",
            "type":"Retail Goods"
        }
    ],
    "sg:phone":"+1 901 353 9040",
    "sg:postcode":"38127",
    "sg:province":"TN",
    "sg:tags":[
        "television",
        "high",
        "stereophonic",
        "radio",
        "fidelity",
        "consumer"
    ],
    "wof:name":"Clay's Audio",
    "wof:placetype":"venue"
},
  "geometry": {"coordinates":[-89.990936,35.217093],"type":"Point"}
}