{
  "type": "Feature",
  "properties": {
    "iso:country":"US",
    "sg:address":"4709 Papermill Dr",
    "sg:city":"Knoxville",
    "sg:classifiers":[
        {
            "category":"Insurance",
            "subcategory":"Insurance Agent",
            "type":"Services"
        }
    ],
    "sg:phone":"+1 865 330 7600",
    "sg:postcode":"37909",
    "sg:province":"TN",
    "sg:tags":[
        "processing"
    ],
    "wof:name":"Sedgwick Claims Management Svc",
    "wof:placetype":"venue"
},
  "geometry": {"coordinates":[-83.989113,35.950162],"type":"Point"}
}