{
  "type": "Feature",
  "properties": {
    "iso:country":"US",
    "sg:address":"52 Concord Dr",
    "sg:city":"Jackson",
    "sg:classifiers":[
        {
            "category":"Sports & Exercise",
            "subcategory":"Golf",
            "type":"Entertainment"
        }
    ],
    "sg:phone":"+1 731 664 4653",
    "sg:postcode":"38305",
    "sg:province":"TN",
    "sg:tags":[
        "course"
    ],
    "wof:name":"Highland Green Golf Club",
    "wof:placetype":"venue"
},
  "geometry": {"coordinates":[-88.889568,35.687457],"type":"Point"}
}