{
  "type": "Feature",
  "properties": {
    "addr:full":"1388 N Hollywood St Memphis TN 38108",
    "addr:housenumber":"1388",
    "addr:postcode":"38108",
    "addr:street":"N Hollywood St",
    "iso:country":"US",
    "sg:address":"1388 N Hollywood St",
    "sg:city":"Memphis",
    "sg:classifiers":[
        {
            "category":"Restaurant",
            "type":"Food & Drink"
        }
    ],
    "sg:phone":"+1 901 327 9166",
    "sg:postcode":"38108",
    "sg:province":"TN",
    "wof:name":"Vic's Slap Yo Moma Wings",
    "wof:placetype":"venue"
},
  "geometry": {"coordinates":[-89.97537800000001,35.174019],"type":"Point"}
}