{
  "type": "Feature",
  "properties": {
    "addr:full":"574 Grand Oaks Dr Brentwood TN 37027",
    "addr:housenumber":"574",
    "addr:postcode":"37027",
    "addr:street":"Grand Oaks Dr",
    "iso:country":"US",
    "sg:address":"574 Grand Oaks Dr",
    "sg:city":"Brentwood",
    "sg:classifiers":[
        {
            "category":"Building & Trades",
            "subcategory":"Construction",
            "type":"Services"
        }
    ],
    "sg:phone":"+1 615 377 9106",
    "sg:postcode":"37027",
    "sg:province":"TN",
    "sg:tags":[
        "general",
        "contractor"
    ],
    "wof:name":"Cates Construction Co",
    "wof:placetype":"venue"
},
  "geometry": {"coordinates":[-86.83976,36.027478],"type":"Point"}
}