{
  "type": "Feature",
  "properties": {
    "addr:full":"525 Des Moines Dr Hermitage TN 37076",
    "addr:housenumber":"525",
    "addr:postcode":"37076",
    "addr:street":"Des Moines Dr",
    "iso:country":"US",
    "sg:address":"525 Des Moines Dr",
    "sg:city":"Hermitage",
    "sg:classifiers":[
        {
            "category":"Professional",
            "subcategory":"Secretarial Services",
            "type":"Services"
        }
    ],
    "sg:phone":"+1 615 889 2043",
    "sg:postcode":"37076",
    "sg:province":"TN",
    "sg:tags":[
        "reporting",
        "court"
    ],
    "wof:name":"Vicari Rosara-",
    "wof:placetype":"venue"
},
  "geometry": {"coordinates":[-86.602767,36.210173],"type":"Point"}
}