{
  "type": "Feature",
  "properties": {
    "iso:country":"US",
    "sg:address":"1015 S Cooper St",
    "sg:city":"Memphis",
    "sg:classifiers":[
        {
            "category":"Social Services",
            "type":"Services"
        }
    ],
    "sg:phone":"+1 901 721 5992",
    "sg:postcode":"38104",
    "sg:province":"TN",
    "sg:tags":[
        "info",
        "program",
        "referral"
    ],
    "wof:name":"Centenary Ministries Inc",
    "wof:placetype":"venue"
},
  "geometry": {"coordinates":[-89.991208,35.1185],"type":"Point"}
}