{
  "type": "Feature",
  "properties": {
    "iso:country":"US",
    "sg:address":"5520 N Suggs Dr",
    "sg:city":"Memphis",
    "sg:classifiers":[
        {
            "category":"Professional",
            "type":"Services"
        }
    ],
    "sg:phone":"+1 901 682 3432",
    "sg:postcode":"38120",
    "sg:province":"TN",
    "wof:name":"Manna of Memphis Inc",
    "wof:placetype":"venue"
},
  "geometry": {"coordinates":[-89.878653,35.113622],"type":"Point"}
}