{
  "type": "Feature",
  "properties": {
    "addr:full":"2532 Forestdale Ave Knoxville TN 37917",
    "addr:housenumber":"2532",
    "addr:postcode":"37917",
    "addr:street":"Forestdale Ave",
    "iso:country":"US",
    "sg:address":"2532 Forestdale Ave",
    "sg:city":"Knoxville",
    "sg:classifiers":[
        {
            "category":"Building & Trades",
            "subcategory":"Construction",
            "type":"Services"
        }
    ],
    "sg:phone":"+1 865 525 9226",
    "sg:postcode":"37917",
    "sg:province":"TN",
    "sg:tags":[
        "house"
    ],
    "wof:name":"Bush Entreprenuers",
    "wof:placetype":"venue"
},
  "geometry": {"coordinates":[-83.91184800000001,36.006393],"type":"Point"}
}