{
  "type": "Feature",
  "properties": {
    "iso:country":"US",
    "sg:address":"135 Pigeon Rd",
    "sg:city":"Cookeville",
    "sg:classifiers":[
        {
            "category":"Health Services",
            "subcategory":"Clinic",
            "type":"Services"
        }
    ],
    "sg:phone":"+1 931 525 1315",
    "sg:postcode":"38506",
    "sg:province":"TN",
    "sg:tags":[
        "specialty",
        "outpatient"
    ],
    "wof:name":"Therapy Solutions PC",
    "wof:placetype":"venue"
},
  "geometry": {"coordinates":[-85.508286,36.116646],"type":"Point"}
}