{
  "type": "Feature",
  "properties": {
    "addr:full":"5872 Advantage Cove Memphis TN 38141",
    "addr:housenumber":"5872",
    "addr:postcode":"38141",
    "addr:street":"Advantage Cove",
    "iso:country":"US",
    "sg:address":"5872 Advantage Cove",
    "sg:city":"Memphis",
    "sg:classifiers":[
        {
            "category":"Wholesale",
            "subcategory":"Stationery",
            "type":"Manufacturing & Wholesale Goods"
        }
    ],
    "sg:phone":"+1 901 542 0090",
    "sg:postcode":"38141",
    "sg:province":"TN",
    "sg:tags":[
        "go",
        "product",
        "paper"
    ],
    "sg:website":"www.aptcommerce.com",
    "wof:name":"American Paper & Twine Company",
    "wof:placetype":"venue"
},
  "geometry": {"coordinates":[-89.868106,35.016587],"type":"Point"}
}