{
  "type": "Feature",
  "properties": {
    "iso:country":"US",
    "sg:address":"7428 River Ridge Dr",
    "sg:city":"Chattanooga",
    "sg:classifiers":[
        {
            "category":"Professional",
            "subcategory":"Management & Consulting",
            "type":"Services"
        }
    ],
    "sg:phone":"+1 423 344 2463",
    "sg:postcode":"37416",
    "sg:province":"TN",
    "sg:tags":[
        "consultant",
        "business"
    ],
    "wof:name":"Dondero & Assoc Inc",
    "wof:placetype":"venue"
},
  "geometry": {"coordinates":[-85.151223,35.149685],"type":"Point"}
}