{
  "type": "Feature",
  "properties": {
    "addr:full":"294 Stott Ln Gatlinburg TN 37738",
    "addr:housenumber":"294",
    "addr:postcode":"37738",
    "addr:street":"Stott Ln",
    "iso:country":"US",
    "sg:address":"294 Stott Ln",
    "sg:city":"Gatlinburg",
    "sg:classifiers":[
        {
            "category":"Retail",
            "subcategory":"Auto Repair",
            "type":"Services"
        }
    ],
    "sg:phone":"+1 865 654 3392",
    "sg:postcode":"37738",
    "sg:province":"TN",
    "sg:tags":[
        "repairing",
        "automobile"
    ],
    "wof:name":"Ogle's Towing & Garage",
    "wof:placetype":"venue"
},
  "geometry": {"coordinates":[-83.45975,35.735376],"type":"Point"}
}