{
  "type": "Feature",
  "properties": {
    "iso:country":"US",
    "sg:address":"601 Carolina Ave",
    "sg:city":"Erwin",
    "sg:classifiers":[
        {
            "category":"Restaurant",
            "type":"Food & Drink"
        }
    ],
    "sg:phone":"+1 423 743 0025",
    "sg:postcode":"37650",
    "sg:province":"TN",
    "sg:tags":[
        "equipment",
        "eating",
        "supply"
    ],
    "wof:name":"A 1 Restaurant Equipments",
    "wof:placetype":"venue"
},
  "geometry": {"coordinates":[-82.41849499999999,36.135628],"type":"Point"}
}