{
  "type": "Feature",
  "properties": {
    "addr:full":"742 Mount Moriah Rd Memphis TN 38117",
    "addr:housenumber":"742",
    "addr:postcode":"38117",
    "addr:street":"Mount Moriah Rd",
    "iso:country":"US",
    "sg:address":"742 Mount Moriah Rd",
    "sg:city":"Memphis",
    "sg:classifiers":[
        {
            "category":"Home & Garden",
            "subcategory":"Garden Supply",
            "type":"Retail Goods"
        }
    ],
    "sg:phone":"+1 901 374 9964",
    "sg:postcode":"38117",
    "sg:province":"TN",
    "sg:tags":[
        "gift"
    ],
    "wof:name":"Urban Gardener",
    "wof:placetype":"venue"
},
  "geometry": {"coordinates":[-89.89522599999999,35.110839],"type":"Point"}
}