{
  "type": "Feature",
  "properties": {
    "addr:full":"2530 Bradford Hicks Dr Livingston TN 38570",
    "addr:housenumber":"2530",
    "addr:postcode":"38570",
    "addr:street":"Bradford Hicks Dr",
    "iso:country":"US",
    "sg:address":"2530 Bradford Hicks Dr",
    "sg:city":"Livingston",
    "sg:classifiers":[
        {
            "category":"Government",
            "subcategory":"Office",
            "type":"Public Place"
        }
    ],
    "sg:phone":"+1 931 823 5506",
    "sg:postcode":"38570",
    "sg:province":"TN",
    "sg:tags":[
        "farm",
        "agency"
    ],
    "wof:name":"Farm Service Agency",
    "wof:placetype":"venue"
},
  "geometry": {"coordinates":[-85.334514,36.389377],"type":"Point"}
}