{
  "type": "Feature",
  "properties": {
    "iso:country":"US",
    "sg:address":"28102 Clocktower Dr",
    "sg:city":"Franklin",
    "sg:classifiers":[
        {
            "category":"Retail",
            "subcategory":"Repair Shop",
            "type":"Services"
        }
    ],
    "sg:phone":"+1 615 969 9967",
    "sg:postcode":"37067",
    "sg:province":"TN",
    "sg:tags":[
        "equipment",
        "conditioning",
        "air"
    ],
    "wof:name":"Benso Air Conditioning",
    "wof:placetype":"venue"
},
  "geometry": {"coordinates":[-86.836327,35.94781],"type":"Point"}
}