{
  "type": "Feature",
  "properties": {
    "addr:full":"621 E Elmwood St Jefferson City TN 37760",
    "addr:housenumber":"621",
    "addr:postcode":"37760",
    "addr:street":"E Elmwood St",
    "iso:country":"US",
    "sg:address":"621 E Elmwood St",
    "sg:city":"Jefferson City",
    "sg:classifiers":[
        {
            "category":"Home & Garden",
            "subcategory":"Building Materials",
            "type":"Retail Goods"
        }
    ],
    "sg:phone":"+1 865 475 7679",
    "sg:postcode":"37760",
    "sg:province":"TN",
    "wof:name":"Watson & Co",
    "wof:placetype":"venue"
},
  "geometry": {"coordinates":[-83.489243,36.115305],"type":"Point"}
}