{
  "type": "Feature",
  "properties": {
    "iso:country":"US",
    "sg:address":"2999 Steeplegate Cove",
    "sg:city":"Germantown",
    "sg:classifiers":[
        {
            "category":"Professional",
            "subcategory":"Business Services",
            "type":"Services"
        }
    ],
    "sg:phone":"+1 901 624 0738",
    "sg:postcode":"38138",
    "sg:province":"TN",
    "sg:tags":[
        "interior",
        "design"
    ],
    "wof:name":"Pouffy Business",
    "wof:placetype":"venue"
},
  "geometry": {"coordinates":[-89.771506,35.065103],"type":"Point"}
}