{
  "type": "Feature",
  "properties": {
    "addr:full":"2242 Old Russellville Pike Clarksville TN 37040",
    "addr:housenumber":"2242",
    "addr:postcode":"37040",
    "addr:street":"Old Russellville Pike",
    "iso:country":"US",
    "sg:address":"2242 Old Russellville Pike",
    "sg:city":"Clarksville",
    "sg:classifiers":[
        {
            "category":"Freight",
            "type":"Transportation"
        }
    ],
    "sg:phone":"+1 931 552 6065",
    "sg:postcode":"37040",
    "sg:province":"TN",
    "sg:tags":[
        "trucking"
    ],
    "wof:name":"Ryan Phillippe",
    "wof:placetype":"venue"
},
  "geometry": {"coordinates":[-87.29992900000001,36.572017],"type":"Point"}
}