{
  "type": "Feature",
  "properties": {
    "addr:full":"215 W Market St Smithville TN 37166",
    "addr:housenumber":"215",
    "addr:postcode":"37166",
    "addr:street":"W Market St",
    "iso:country":"US",
    "sg:address":"215 W Market St",
    "sg:city":"Smithville",
    "sg:classifiers":[
        {
            "category":"Retail",
            "subcategory":"Auto Repair",
            "type":"Services"
        }
    ],
    "sg:phone":"+1 615 597 6909",
    "sg:postcode":"37166",
    "sg:province":"TN",
    "sg:tags":[
        "body",
        "automotive",
        "work",
        "painting",
        "collision"
    ],
    "wof:name":"Foutch Industries LLC",
    "wof:placetype":"venue"
},
  "geometry": {"coordinates":[-85.816039,35.960597],"type":"Point"}
}