{
  "type": "Feature",
  "properties": {
    "iso:country":"US",
    "sg:address":"2318 E Broadway Ave",
    "sg:city":"Maryville",
    "sg:classifiers":[
        {
            "category":"Autos & Motor Vehicles",
            "subcategory":"Auto Supplies",
            "type":"Retail Goods"
        }
    ],
    "sg:phone":"+1 865 983 0823",
    "sg:postcode":"37804",
    "sg:province":"TN",
    "wof:name":"Auto Clips & Fasteners",
    "wof:placetype":"venue"
},
  "geometry": {"coordinates":[-83.947395,35.784228],"type":"Point"}
}