{
  "type": "Feature",
  "properties": {
    "iso:country":"US",
    "sg:address":"3006 Pomo Cir",
    "sg:city":"Crossville",
    "sg:classifiers":[
        {
            "category":"Building & Trades",
            "subcategory":"Plumbing",
            "type":"Services"
        }
    ],
    "sg:phone":"+1 931 788 5938",
    "sg:postcode":"38572",
    "sg:province":"TN",
    "sg:tags":[
        "plumbing",
        "contractor"
    ],
    "wof:name":"A Plus Plumbing",
    "wof:placetype":"venue"
},
  "geometry": {"coordinates":[-85.045934,35.867408],"type":"Point"}
}