{
  "type": "Feature",
  "properties": {
    "iso:country":"US",
    "sg:address":"211 S Main St",
    "sg:city":"Gainesboro",
    "sg:classifiers":[
        {
            "category":"Manufacturing",
            "subcategory":"Printing",
            "type":"Manufacturing & Wholesale Goods"
        }
    ],
    "sg:phone":"+1 931 268 9725",
    "sg:postcode":"38562",
    "sg:province":"TN",
    "sg:tags":[
        "newspaper"
    ],
    "wof:name":"Jackson County Sentinel",
    "wof:placetype":"venue"
},
  "geometry": {"coordinates":[-85.65851499999999,36.354931],"type":"Point"}
}