{
  "type": "Feature",
  "properties": {
    "iso:country":"US",
    "sg:address":"133 Raleigh Rd",
    "sg:city":"Oak Ridge",
    "sg:classifiers":[
        {
            "category":"Organizations",
            "subcategory":"Labor Organization",
            "type":"Services"
        }
    ],
    "sg:phone":"+1 865 483 3745",
    "sg:postcode":"37830",
    "sg:province":"TN",
    "wof:name":"Paper Allied-Industrial Chemcl",
    "wof:placetype":"venue"
},
  "geometry": {"coordinates":[-84.26530700000001,36.013223],"type":"Point"}
}