{
  "type": "Feature",
  "properties": {
    "iso:country":"US",
    "sg:address":"947 Kirby Rd",
    "sg:city":"Mc Minnville",
    "sg:classifiers":[
        {
            "category":"Retail",
            "subcategory":"Auto Repair",
            "type":"Services"
        }
    ],
    "sg:phone":"+1 931 939 2086",
    "sg:postcode":"37110",
    "sg:province":"TN",
    "sg:tags":[
        "body",
        "automobile",
        "painting"
    ],
    "wof:name":"Gary's Body Shop",
    "wof:placetype":"venue"
},
  "geometry": {"coordinates":[-85.879364,35.748465],"type":"Point"}
}