{
  "type": "Feature",
  "properties": {
    "addr:full":"305 New Shackle Island Rd Hendersonville TN 37075",
    "addr:housenumber":"305",
    "addr:postcode":"37075",
    "addr:street":"New Shackle Island Rd",
    "iso:country":"US",
    "sg:address":"305 New Shackle Island Rd",
    "sg:city":"Hendersonville",
    "sg:classifiers":[
        {
            "category":"Restaurant",
            "type":"Food & Drink"
        }
    ],
    "sg:menulink":"http://www.allmenus.com/tn/hendersonville/203443-mcdonalds/menu/",
    "sg:phone":"+1 615 822 7169",
    "sg:postcode":"37075",
    "sg:province":"TN",
    "sg:tags":[
        "burger",
        "american"
    ],
    "wof:name":"McDonald's",
    "wof:placetype":"venue"
},
  "geometry": {"coordinates":[-86.62314600000001,36.321601],"type":"Point"}
}