{
  "type": "Feature",
  "properties": {
    "iso:country":"US",
    "sg:address":"1381 Kney St",
    "sg:city":"Memphis",
    "sg:classifiers":[
        {
            "category":"Organizations",
            "subcategory":"Religious Organization",
            "type":"Services"
        }
    ],
    "sg:phone":"+1 901 528 1500",
    "sg:postcode":"38107",
    "sg:province":"TN",
    "sg:tags":[
        "church"
    ],
    "wof:name":"Hope Evangelistic Chr-God",
    "wof:placetype":"venue"
},
  "geometry": {"coordinates":[-90.02223600000001,35.179018],"type":"Point"}
}