{
  "type": "Feature",
  "properties": {
    "addr:full":"2212 Nolensville Pike Nashville TN 37211",
    "addr:housenumber":"2212",
    "addr:postcode":"37211",
    "addr:street":"Nolensville Pike",
    "iso:country":"US",
    "sg:address":"2212 Nolensville Pike",
    "sg:city":"Nashville",
    "sg:classifiers":[
        {
            "category":"Restaurant",
            "type":"Food & Drink"
        }
    ],
    "sg:menulink":"http://www.allmenus.com/tn/nashville/203499-mcdonalds/menu/",
    "sg:phone":"+1 615 259 3912",
    "sg:postcode":"37211",
    "sg:province":"TN",
    "sg:tags":[
        "burger",
        "american"
    ],
    "wof:name":"McDonald's",
    "wof:placetype":"venue"
},
  "geometry": {"coordinates":[-86.75189399999999,36.124497],"type":"Point"}
}