{
  "type": "Feature",
  "properties": {
    "iso:country":"US",
    "sg:address":"250 S Indiana Ave",
    "sg:city":"La Follette",
    "sg:classifiers":[
        {
            "category":"Personal",
            "subcategory":"Beauty Salon",
            "type":"Services"
        }
    ],
    "sg:phone":"+1 423 566 3813",
    "sg:postcode":"37766",
    "sg:province":"TN",
    "sg:tags":[
        "shop"
    ],
    "wof:name":"Shear Designs Salon",
    "wof:placetype":"venue"
},
  "geometry": {"coordinates":[-84.11886,36.38159],"type":"Point"}
}