{
  "type": "Feature",
  "properties": {
    "iso:country":"US",
    "sg:address":"2413 Melbourne Dr",
    "sg:city":"Johnson City",
    "sg:classifiers":[
        {
            "category":"Building & Trades",
            "subcategory":"Construction",
            "type":"Services"
        }
    ],
    "sg:phone":"+1 423 791 3686",
    "sg:postcode":"37601",
    "sg:province":"TN",
    "sg:tags":[
        "home",
        "improvement"
    ],
    "wof:name":"Hampshire Home Repair",
    "wof:placetype":"venue"
},
  "geometry": {"coordinates":[-82.362686,36.355377],"type":"Point"}
}