{
  "type": "Feature",
  "properties": {
    "addr:full":"99 Circle Dr Lexington TN 38351",
    "addr:housenumber":"99",
    "addr:postcode":"38351",
    "addr:street":"Circle Dr",
    "iso:country":"US",
    "sg:address":"99 Circle Dr",
    "sg:city":"Lexington",
    "sg:classifiers":[
        {
            "category":"Shopping",
            "subcategory":"Clothing, Apparel, & Fashions",
            "type":"Retail Goods"
        }
    ],
    "sg:phone":"+1 731 968 2235",
    "sg:postcode":"38351",
    "sg:province":"TN",
    "sg:tags":[
        "lady"
    ],
    "wof:name":"Classic Creations Inc",
    "wof:placetype":"venue"
},
  "geometry": {"coordinates":[-88.389315,35.662103],"type":"Point"}
}