{
  "type": "Feature",
  "properties": {
    "addr:full":"2020 Gunbarrel Rd Chattanooga TN 37421",
    "addr:postcode":"37421",
    "addr:street":"2020 Gunbarrel Rd",
    "iso:country":"US",
    "sg:address":"2020 Gunbarrel Rd",
    "sg:city":"Chattanooga",
    "sg:classifiers":[
        {
            "category":"Fast Food",
            "type":"Food & Drink"
        },
        {
            "category":"Restaurant",
            "type":"Food & Drink"
        }
    ],
    "sg:phone":"+1 423 664 3500",
    "sg:postcode":"37421",
    "sg:province":"TN",
    "sg:tags":[
        "american"
    ],
    "sg:website":"http://www.fiveguys.com",
    "wof:name":"Five Guys Burgers & Fries",
    "wof:placetype":"venue"
},
  "geometry": {"coordinates":[-85.155179,35.030914],"type":"Point"}
}