{
  "type": "Feature",
  "properties": {
    "addr:full":"1640 Ridgeview St SE Cleveland TN 37323",
    "addr:housenumber":"1640",
    "addr:postcode":"37323",
    "addr:street":"Ridgeview St Se",
    "iso:country":"US",
    "sg:address":"1640 Ridgeview St SE",
    "sg:city":"Cleveland",
    "sg:classifiers":[
        {
            "category":"Real Estate",
            "subcategory":"Real Estate Agent",
            "type":"Services"
        }
    ],
    "sg:phone":"+1 423 472 7805",
    "sg:postcode":"37323",
    "sg:province":"TN",
    "sg:tags":[
        "inspection"
    ],
    "wof:name":"East Tennessee Home Inspection",
    "wof:placetype":"venue"
},
  "geometry": {"coordinates":[-84.85737,35.133856],"type":"Point"}
}