{
  "type": "Feature",
  "properties": {
    "iso:country":"US",
    "sg:address":"115 W Main St",
    "sg:city":"Waverly",
    "sg:classifiers":[
        {
            "category":"Organizations",
            "subcategory":"Religious Organization",
            "type":"Services"
        }
    ],
    "sg:phone":"+1 931 296 2611",
    "sg:postcode":"37185",
    "sg:province":"TN",
    "sg:tags":[
        "church"
    ],
    "wof:name":"Waverly United Methodist Chr",
    "wof:placetype":"venue"
},
  "geometry": {"coordinates":[-87.796678,36.083473],"type":"Point"}
}