{
  "type": "Feature",
  "properties": {
    "iso:country":"US",
    "sg:address":"1439 State Hwy 92",
    "sg:city":"Williamsburg",
    "sg:classifiers":[
        {
            "category":"Government",
            "subcategory":"Jail",
            "type":"Public Place"
        }
    ],
    "sg:phone":"+1 606 549 6013",
    "sg:postcode":"40769",
    "sg:province":"TN",
    "sg:tags":[
        "county",
        "govt",
        "institution"
    ],
    "wof:name":"Whitley County Jail",
    "wof:placetype":"venue"
},
  "geometry": {"coordinates":[-84.183789,36.727443],"type":"Point"}
}