{
  "type": "Feature",
  "properties": {
    "addr:full":"1204 Houston Levee Rd Cordova TN 38018",
    "addr:housenumber":"1204",
    "addr:postcode":"38018",
    "addr:street":"Houston Levee Rd",
    "iso:country":"US",
    "sg:address":"1204 Houston Levee Rd",
    "sg:city":"Cordova",
    "sg:classifiers":[
        {
            "category":"Restaurant",
            "type":"Food & Drink"
        }
    ],
    "sg:phone":"+1 901 752 6666",
    "sg:postcode":"38018",
    "sg:province":"TN",
    "sg:tags":[
        "eating"
    ],
    "wof:name":"Cordova Ridge Italian Cafe",
    "wof:placetype":"venue"
},
  "geometry": {"coordinates":[-89.72743199999999,35.159152],"type":"Point"}
}