{
  "type": "Feature",
  "properties": {
    "addr:full":"1247 Stonewall Jackson Dr Dandridge TN 37725",
    "addr:housenumber":"1247",
    "addr:postcode":"37725",
    "addr:street":"Stonewall Jackson Dr",
    "iso:country":"US",
    "sg:address":"1247 Stonewall Jackson Dr",
    "sg:city":"Dandridge",
    "sg:classifiers":[
        {
            "category":"Sports & Exercise",
            "subcategory":"Golf",
            "type":"Entertainment"
        }
    ],
    "sg:phone":"+1 865 397 2655",
    "sg:postcode":"37725",
    "sg:province":"TN",
    "sg:tags":[
        "course"
    ],
    "wof:name":"Patriot Hills Golf Club",
    "wof:placetype":"venue"
},
  "geometry": {"coordinates":[-83.405208,36.047323],"type":"Point"}
}