{
  "type": "Feature",
  "properties": {
    "iso:country":"US",
    "sg:address":"804 E Gibbs St",
    "sg:city":"Union City",
    "sg:classifiers":[
        {
            "category":"Organizations",
            "subcategory":"Religious Organization",
            "type":"Services"
        }
    ],
    "sg:phone":"+1 731 885 0312",
    "sg:postcode":"38261",
    "sg:province":"TN",
    "sg:tags":[
        "church"
    ],
    "wof:name":"Bethel Church Of God In Christ",
    "wof:placetype":"venue"
},
  "geometry": {"coordinates":[-89.047691,36.430444],"type":"Point"}
}