{
  "type": "Feature",
  "properties": {
    "addr:full":"686 Provine Ave Memphis TN 38126",
    "addr:housenumber":"686",
    "addr:postcode":"38126",
    "addr:street":"Provine Ave",
    "iso:country":"US",
    "sg:address":"686 Provine Ave",
    "sg:city":"Memphis",
    "sg:classifiers":[
        {
            "category":"Organizations",
            "subcategory":"Religious Organization",
            "type":"Services"
        }
    ],
    "sg:phone":"+1 901 948 1666",
    "sg:postcode":"38126",
    "sg:province":"TN",
    "sg:tags":[
        "church"
    ],
    "wof:name":"Greater Beulah Land MB Church",
    "wof:placetype":"venue"
},
  "geometry": {"coordinates":[-90.04020199999999,35.124189],"type":"Point"}
}