{
  "type": "Feature",
  "properties": {
    "addr:full":"609 Oak Harbor Cove Hermitage TN 37076",
    "addr:housenumber":"609",
    "addr:postcode":"37076",
    "addr:street":"Oak Harbor Cove",
    "iso:country":"US",
    "sg:address":"609 Oak Harbor Cove",
    "sg:city":"Hermitage",
    "sg:classifiers":[
        {
            "category":"Retail",
            "subcategory":"Repair Shop",
            "type":"Services"
        }
    ],
    "sg:phone":"+1 615 414 0813",
    "sg:postcode":"37076",
    "sg:province":"TN",
    "sg:tags":[
        "upholsterer"
    ],
    "wof:name":"C J's",
    "wof:placetype":"venue"
},
  "geometry": {"coordinates":[-86.587557,36.162478],"type":"Point"}
}