{
  "type": "Feature",
  "properties": {
    "iso:country":"US",
    "sg:address":"409 Enon Springs Rd E",
    "sg:city":"Smyrna",
    "sg:classifiers":[
        {
            "category":"Professional",
            "subcategory":"Business Services",
            "type":"Services"
        }
    ],
    "sg:phone":"+1 615 220 0749",
    "sg:postcode":"37167",
    "sg:province":"TN",
    "wof:name":"Mark Lindsey",
    "wof:placetype":"venue"
},
  "geometry": {"coordinates":[-86.49881499999999,35.973963],"type":"Point"}
}