{
  "type": "Feature",
  "properties": {
    "iso:country":"US",
    "sg:address":"3709 Lake Vista Dr",
    "sg:city":"Chattanooga",
    "sg:classifiers":[
        {
            "category":"Building & Trades",
            "subcategory":"Plumbing",
            "type":"Services"
        }
    ],
    "sg:phone":"+1 423 855 1972",
    "sg:postcode":"37416",
    "sg:province":"TN",
    "sg:tags":[
        "plumbing",
        "air",
        "heating",
        "contractor"
    ],
    "wof:name":"Custom Services Heating & AC",
    "wof:placetype":"venue"
},
  "geometry": {"coordinates":[-85.20449600000001,35.091491],"type":"Point"}
}