{
  "type": "Feature",
  "properties": {
    "iso:country":"US",
    "sg:address":"1045 Mullins Station Rd",
    "sg:city":"Memphis",
    "sg:classifiers":[
        {
            "category":"Utilities",
            "subcategory":"Telephone",
            "type":"Services"
        }
    ],
    "sg:phone":"+1 901 381 3987",
    "sg:postcode":"38134",
    "sg:province":"TN",
    "sg:tags":[
        "communications"
    ],
    "wof:name":"Invision Telecom",
    "wof:placetype":"venue"
},
  "geometry": {"coordinates":[-89.850883,35.156771],"type":"Point"}
}