{
  "type": "Feature",
  "properties": {
    "addr:full":"1075 E Van Hook St Milan TN 38358",
    "addr:housenumber":"1075",
    "addr:postcode":"38358",
    "addr:street":"E Van Hook St",
    "iso:country":"US",
    "sg:address":"1075 E Van Hook St",
    "sg:city":"Milan",
    "sg:classifiers":[
        {
            "category":"Social Services",
            "type":"Services"
        }
    ],
    "sg:phone":"+1 731 686 0851",
    "sg:postcode":"38358",
    "sg:province":"TN",
    "sg:tags":[
        "senior",
        "citizen"
    ],
    "wof:name":"Milan Senior Citizens Center",
    "wof:placetype":"venue"
},
  "geometry": {"coordinates":[-88.750339,35.918537],"type":"Point"}
}