{
  "type": "Feature",
  "properties": {
    "iso:country":"US",
    "sg:address":"903 Murfreesboro Rd",
    "sg:city":"Franklin",
    "sg:classifiers":[
        {
            "category":"Banks & Credit Unions",
            "subcategory":"Investment Brokerage",
            "type":"Services"
        }
    ],
    "sg:phone":"+1 615 614 0070",
    "sg:postcode":"37067",
    "sg:province":"TN",
    "sg:tags":[
        "consultant",
        "planning",
        "financial"
    ],
    "wof:name":"Monarch Advisory Group",
    "wof:placetype":"venue"
},
  "geometry": {"coordinates":[-86.84351700000001,35.917138],"type":"Point"}
}