{
  "type": "Feature",
  "properties": {
    "iso:country":"US",
    "sg:address":"4164 Minden Rd",
    "sg:city":"Memphis",
    "sg:classifiers":[
        {
            "category":"Professional",
            "subcategory":"Advertising",
            "type":"Services"
        }
    ],
    "sg:phone":"+1 901 323 4900",
    "sg:postcode":"38117",
    "sg:province":"TN",
    "sg:tags":[
        "counselor"
    ],
    "wof:name":"Counterpart Communication Dsgn",
    "wof:placetype":"venue"
},
  "geometry": {"coordinates":[-89.922499,35.138083],"type":"Point"}
}