{
  "type": "Feature",
  "properties": {
    "iso:country":"US",
    "sg:address":"2844 Logan St",
    "sg:city":"Nashville",
    "sg:classifiers":[
        {
            "category":"Professional",
            "subcategory":"Advertising",
            "type":"Services"
        }
    ],
    "sg:phone":"+1 615 263 1838",
    "sg:postcode":"37211",
    "sg:province":"TN",
    "wof:name":"TAPEONLINE.COM",
    "wof:placetype":"venue"
},
  "geometry": {"coordinates":[-86.741829,36.111947],"type":"Point"}
}