{
  "type": "Feature",
  "properties": {
    "addr:full":"11503 Chapman Hwy Seymour TN 37865",
    "addr:housenumber":"11503",
    "addr:postcode":"37865",
    "addr:street":"Chapman Hwy",
    "iso:country":"US",
    "sg:address":"11503 Chapman Hwy",
    "sg:city":"Seymour",
    "sg:classifiers":[
        {
            "category":"Personal",
            "subcategory":"Barber",
            "type":"Services"
        }
    ],
    "sg:phone":"+1 865 609 2739",
    "sg:postcode":"37865",
    "sg:province":"TN",
    "sg:tags":[
        "shop"
    ],
    "wof:name":"Cutting Crew",
    "wof:placetype":"venue"
},
  "geometry": {"coordinates":[-83.756635,35.870467],"type":"Point"}
}