{
  "type": "Feature",
  "properties": {
    "iso:country":"US",
    "sg:address":"801 Ashland St",
    "sg:city":"Hickman",
    "sg:classifiers":[
        {
            "category":"Shopping",
            "subcategory":"Used Merchandise",
            "type":"Retail Goods"
        }
    ],
    "sg:phone":"+1 270 236 6005",
    "sg:postcode":"42050",
    "sg:province":"TN",
    "sg:tags":[
        "shop",
        "thrift"
    ],
    "wof:name":"River Town Mission",
    "wof:placetype":"venue"
},
  "geometry": {"coordinates":[-89.201842,36.568112],"type":"Point"}
}