{
  "type": "Feature",
  "properties": {
    "iso:country":"US",
    "sg:address":"509 E Main St",
    "sg:city":"Kingsport",
    "sg:classifiers":[
        {
            "category":"Wholesale",
            "subcategory":"Machinery & Supplies",
            "type":"Manufacturing & Wholesale Goods"
        }
    ],
    "sg:phone":"+1 423 246 6178",
    "sg:postcode":"37660",
    "sg:province":"TN",
    "sg:tags":[
        "equipment",
        "industrial"
    ],
    "wof:name":"Air Products",
    "wof:placetype":"venue"
},
  "geometry": {"coordinates":[-82.557062,36.542153],"type":"Point"}
}