{
  "type": "Feature",
  "properties": {
    "iso:country":"US",
    "sg:address":"2060 Dandridge Ave SE",
    "sg:city":"Knoxville",
    "sg:classifiers":[
        {
            "category":"Shopping",
            "subcategory":"Gifts & Souvenirs",
            "type":"Retail Goods"
        }
    ],
    "sg:phone":"+1 865 546 0043",
    "sg:postcode":"37915",
    "sg:province":"TN",
    "wof:name":"Candys Gifts & Accessories",
    "wof:placetype":"venue"
},
  "geometry": {"coordinates":[-83.895205,35.972537],"type":"Point"}
}