{
  "type": "Feature",
  "properties": {
    "addr:full":"2310 N Germantown Pkwy Cordova TN 38016",
    "addr:housenumber":"2310",
    "addr:postcode":"38016",
    "addr:street":"N Germantown Pkwy",
    "iso:country":"US",
    "sg:address":"2310 N Germantown Pkwy",
    "sg:city":"Cordova",
    "sg:classifiers":[
        {
            "category":"Restaurant",
            "type":"Food & Drink"
        }
    ],
    "sg:phone":"+1 901 386 8020",
    "sg:postcode":"38016",
    "sg:province":"TN",
    "wof:name":"Teriyaki Express",
    "wof:placetype":"venue"
},
  "geometry": {"coordinates":[-89.792359,35.191173],"type":"Point"}
}