{
  "type": "Feature",
  "properties": {
    "iso:country":"US",
    "sg:address":"1630 Lynn Garden Dr",
    "sg:city":"Kingsport",
    "sg:classifiers":[
        {
            "category":"Autos & Motor Vehicles",
            "subcategory":"Automobile Sales",
            "type":"Retail Goods"
        },
        {
            "category":"Retail",
            "subcategory":"Auto Repair",
            "type":"Services"
        }
    ],
    "sg:phone":"+1 423 246 2206",
    "sg:postcode":"37665",
    "sg:province":"TN",
    "sg:tags":[
        "body",
        "used",
        "painting"
    ],
    "wof:name":"B & E Collision Ctr & Auto Sls",
    "wof:placetype":"venue"
},
  "geometry": {"coordinates":[-82.568234,36.581204],"type":"Point"}
}