{
  "type": "Feature",
  "properties": {
    "iso:country":"US",
    "sg:address":"108 Clairmont Dr",
    "sg:city":"Dickson",
    "sg:classifiers":[
        {
            "category":"Wholesale",
            "subcategory":"Electrical",
            "type":"Manufacturing & Wholesale Goods"
        }
    ],
    "sg:phone":"+1 615 441 4952",
    "sg:postcode":"37055",
    "sg:province":"TN",
    "sg:tags":[
        "control",
        "security",
        "system"
    ],
    "wof:name":"Elizabeth Hall Security",
    "wof:placetype":"venue"
},
  "geometry": {"coordinates":[-87.352428,36.085876],"type":"Point"}
}