{
  "type": "Feature",
  "properties": {
    "iso:country":"US",
    "sg:address":"1416 Silver St",
    "sg:city":"Memphis",
    "sg:classifiers":[
        {
            "category":"Real Estate",
            "subcategory":"Real Estate Operator",
            "type":"Services"
        }
    ],
    "sg:phone":"+1 901 775 0006",
    "sg:postcode":"38106",
    "sg:province":"TN",
    "sg:tags":[
        "building",
        "nonresidential"
    ],
    "wof:name":"A and J Properties",
    "wof:placetype":"venue"
},
  "geometry": {"coordinates":[-90.012326,35.109082],"type":"Point"}
}