{
  "type": "Feature",
  "properties": {
    "addr:full":"2347 Jones Bend Rd Louisville TN 37777",
    "addr:housenumber":"2347",
    "addr:postcode":"37777",
    "addr:street":"Jones Bend Rd",
    "iso:country":"US",
    "sg:address":"2347 Jones Bend Rd",
    "sg:city":"Louisville",
    "sg:classifiers":[
        {
            "category":"Health Services",
            "subcategory":"Hospital",
            "type":"Services"
        }
    ],
    "sg:phone":"+1 865 970 9800",
    "sg:postcode":"37777",
    "sg:province":"TN",
    "sg:tags":[
        "mental"
    ],
    "sg:website":"www.covenanthealth.com",
    "wof:name":"Mental Health Ctr-Knoxville",
    "wof:placetype":"venue"
},
  "geometry": {"coordinates":[-84.020731,35.871675],"type":"Point"}
}