{
  "type": "Feature",
  "properties": {
    "addr:full":"5616 Nolensville Pike Nashville TN 37211",
    "addr:housenumber":"5616",
    "addr:postcode":"37211",
    "addr:street":"Nolensville Pike",
    "iso:country":"US",
    "sg:address":"5616 Nolensville Pike",
    "sg:city":"Nashville",
    "sg:classifiers":[
        {
            "category":"Shopping",
            "subcategory":"Department Store",
            "type":"Retail Goods"
        }
    ],
    "sg:phone":"+1 615 833 1309",
    "sg:postcode":"37211",
    "sg:province":"TN",
    "sg:tags":[
        "shop"
    ],
    "wof:name":"Bargain Depot LLC",
    "wof:placetype":"venue"
},
  "geometry": {"coordinates":[-86.713213,36.045653],"type":"Point"}
}