{
  "type": "Feature",
  "properties": {
    "iso:country":"US",
    "sg:address":"2648 Wilma Rudolph Blvd",
    "sg:city":"Clarksville",
    "sg:classifiers":[
        {
            "category":"Shopping",
            "subcategory":"Clothing, Apparel, & Fashions",
            "type":"Retail Goods"
        }
    ],
    "sg:phone":"+1 931 551 3883",
    "sg:postcode":"37040",
    "sg:province":"TN",
    "sg:website":"www.catofashions.com",
    "wof:name":"Cato",
    "wof:placetype":"venue"
},
  "geometry": {"coordinates":[-87.297572,36.581831],"type":"Point"}
}