{
  "type": "Feature",
  "properties": {
    "iso:country":"US",
    "sg:address":"1702 Hollister Rd",
    "sg:city":"Signal Mountain",
    "sg:classifiers":[
        {
            "category":"Professional",
            "type":"Services"
        }
    ],
    "sg:phone":"+1 423 886 3044",
    "sg:postcode":"37377",
    "sg:province":"TN",
    "wof:name":"Stuart B & Freida A Miller",
    "wof:placetype":"venue"
},
  "geometry": {"coordinates":[-85.326224,35.17847],"type":"Point"}
}