{
  "type": "Feature",
  "properties": {
    "iso:country":"US",
    "sg:address":"3801 Old Hwy 31 E",
    "sg:city":"Westmoreland",
    "sg:classifiers":[
        {
            "category":"Food & Beverages",
            "subcategory":"Groceries & Convenience Stores",
            "type":"Retail Goods"
        }
    ],
    "sg:phone":"+1 615 644 2880",
    "sg:postcode":"37186",
    "sg:province":"TN",
    "wof:name":"Arlene's Mini Mart",
    "wof:placetype":"venue"
},
  "geometry": {"coordinates":[-86.260102,36.542213],"type":"Point"}
}