{
  "type": "Feature",
  "properties": {
    "iso:country":"US",
    "sg:address":"7657 US Hwy 70 S",
    "sg:city":"Nashville",
    "sg:classifiers":[
        {
            "category":"Shopping",
            "subcategory":"Hobbies, Toys, & Games",
            "type":"Retail Goods"
        }
    ],
    "sg:phone":"+1 615 646 3403",
    "sg:postcode":"37221",
    "sg:province":"TN",
    "sg:tags":[
        "craft",
        "supply"
    ],
    "wof:name":"Michaels Arts & Crafts Store",
    "wof:placetype":"venue"
},
  "geometry": {"coordinates":[-86.955536,36.080607],"type":"Point"}
}