{
  "type": "Feature",
  "properties": {
    "addr:full":"3801 Princeton Ave Nashville TN 37205",
    "addr:housenumber":"3801",
    "addr:postcode":"37205",
    "addr:street":"Princeton Ave",
    "iso:country":"US",
    "sg:address":"3801 Princeton Ave",
    "sg:city":"Nashville",
    "sg:classifiers":[
        {
            "category":"Professional",
            "subcategory":"Business Services",
            "type":"Services"
        }
    ],
    "sg:phone":"+1 615 385 3228",
    "sg:postcode":"37205",
    "sg:province":"TN",
    "sg:tags":[
        "optometry"
    ],
    "wof:name":"Chan L Webster Od",
    "wof:placetype":"venue"
},
  "geometry": {"coordinates":[-86.83376699999999,36.13578],"type":"Point"}
}