{
  "type": "Feature",
  "properties": {
    "addr:full":"4204 Erin Rd Mc Ewen TN 37101",
    "addr:housenumber":"4204",
    "addr:postcode":"37101",
    "addr:street":"Erin Rd",
    "iso:country":"US",
    "sg:address":"4204 Erin Rd",
    "sg:city":"Mc Ewen",
    "sg:classifiers":[
        {
            "category":"Wholesale",
            "subcategory":"Fruits & Vegetables",
            "type":"Manufacturing & Wholesale Goods"
        }
    ],
    "sg:phone":"+1 931 582 7676",
    "sg:postcode":"37101",
    "sg:province":"TN",
    "wof:name":"Tonis",
    "wof:placetype":"venue"
},
  "geometry": {"coordinates":[-87.659901,36.185463],"type":"Point"}
}