{
  "type": "Feature",
  "properties": {
    "iso:country":"US",
    "sg:address":"142 Chestnut Grove Rd",
    "sg:city":"Pulaski",
    "sg:classifiers":[
        {
            "category":"Professional",
            "subcategory":"Engineering",
            "type":"Services"
        }
    ],
    "sg:phone":"+1 931 363 7655",
    "sg:postcode":"38478",
    "sg:province":"TN",
    "wof:name":"Pjs Tool & Machine",
    "wof:placetype":"venue"
},
  "geometry": {"coordinates":[-87.12445200000001,35.170189],"type":"Point"}
}