{
  "type": "Feature",
  "properties": {
    "addr:full":"2506 Johnston St Knoxville TN 37921",
    "addr:housenumber":"2506",
    "addr:postcode":"37921",
    "addr:street":"Johnston St",
    "iso:country":"US",
    "sg:address":"2506 Johnston St",
    "sg:city":"Knoxville",
    "sg:classifiers":[
        {
            "category":"Manufacturing",
            "subcategory":"Paper Products",
            "type":"Manufacturing & Wholesale Goods"
        }
    ],
    "sg:phone":"+1 865 637 0145",
    "sg:postcode":"37921",
    "sg:province":"TN",
    "sg:website":"www.tamko.com",
    "wof:name":"Tamko Roofing Products Inc",
    "wof:placetype":"venue"
},
  "geometry": {"coordinates":[-83.950102,35.983874],"type":"Point"}
}