{
  "type": "Feature",
  "properties": {
    "iso:country":"US",
    "sg:address":"3874 Viscount Ave",
    "sg:city":"Memphis",
    "sg:classifiers":[
        {
            "category":"Professional",
            "type":"Services"
        }
    ],
    "sg:phone":"+1 901 795 8797",
    "sg:postcode":"38118",
    "sg:province":"TN",
    "sg:tags":[
        "establishment"
    ],
    "wof:name":"W G Flautt & Assoc",
    "wof:placetype":"venue"
},
  "geometry": {"coordinates":[-89.93382,35.048905],"type":"Point"}
}