{
  "type": "Feature",
  "properties": {
    "iso:country":"US",
    "sg:address":"1471 Calgy Dr",
    "sg:city":"Gallatin",
    "sg:classifiers":[
        {
            "category":"Arena",
            "subcategory":"Sports Club",
            "type":"Entertainment"
        }
    ],
    "sg:phone":"+1 615 206 6945",
    "sg:postcode":"37066",
    "sg:province":"TN",
    "sg:tags":[
        "manager",
        "recruiter",
        "promoter"
    ],
    "wof:name":"Southestern Athletics",
    "wof:placetype":"venue"
},
  "geometry": {"coordinates":[-86.44996399999999,36.343038],"type":"Point"}
}