{
  "type": "Feature",
  "properties": {
    "iso:country":"US",
    "sg:address":"2373 Unionville Deason Rd",
    "sg:city":"Bell Buckle",
    "sg:classifiers":[
        {
            "category":"Home & Garden",
            "subcategory":"Home Furnishings",
            "type":"Retail Goods"
        }
    ],
    "sg:phone":"+1 931 437 2148",
    "sg:postcode":"37020",
    "sg:province":"TN",
    "wof:name":"Sr Specialties",
    "wof:placetype":"venue"
},
  "geometry": {"coordinates":[-86.486825,35.603995],"type":"Point"}
}