{
  "type": "Feature",
  "properties": {
    "addr:full":"227 W Young High Pkwy Knoxville TN 37920",
    "addr:housenumber":"227",
    "addr:postcode":"37920",
    "addr:street":"W Young High Pkwy",
    "iso:country":"US",
    "sg:address":"227 W Young High Pkwy",
    "sg:city":"Knoxville",
    "sg:classifiers":[
        {
            "category":"Insurance",
            "subcategory":"Insurance Agent",
            "type":"Services"
        }
    ],
    "sg:phone":"+1 865 579 0400",
    "sg:postcode":"37920",
    "sg:province":"TN",
    "wof:name":"State Farm Insurance",
    "wof:placetype":"venue"
},
  "geometry": {"coordinates":[-83.907618,35.933508],"type":"Point"}
}