{
  "type": "Feature",
  "properties": {
    "iso:country":"US",
    "sg:address":"5700 Pleasant View Rd",
    "sg:city":"Memphis",
    "sg:classifiers":[
        {
            "category":"Professional",
            "subcategory":"Testing Lab",
            "type":"Services"
        }
    ],
    "sg:phone":"+1 901 373 6797",
    "sg:postcode":"38134",
    "sg:province":"TN",
    "sg:tags":[
        "laboratory"
    ],
    "wof:name":"Alpha Therapeutic Corp",
    "wof:placetype":"venue"
},
  "geometry": {"coordinates":[-89.87410800000001,35.173422],"type":"Point"}
}