{
  "type": "Feature",
  "properties": {
    "iso:country":"US",
    "sg:address":"128 Crockett Manor Dr",
    "sg:city":"Trenton",
    "sg:classifiers":[
        {
            "category":"Shopping",
            "subcategory":"Discount & Variety Stores",
            "type":"Retail Goods"
        },
        {
            "category":"Shopping",
            "subcategory":"Department Store",
            "type":"Retail Goods"
        }
    ],
    "sg:phone":"+1 731 855 0254",
    "sg:postcode":"38382",
    "sg:province":"TN",
    "wof:name":"Family Dollar Stores",
    "wof:placetype":"venue"
},
  "geometry": {"coordinates":[-88.92920700000001,35.966619],"type":"Point"}
}