{
  "type": "Feature",
  "properties": {
    "iso:country":"US",
    "sg:address":"8713 Ooltewah Georgetown Rd",
    "sg:city":"Ooltewah",
    "sg:classifiers":[
        {
            "category":"Building & Trades",
            "subcategory":"Plumbing",
            "type":"Services"
        }
    ],
    "sg:phone":"+1 423 326 1509",
    "sg:postcode":"37363",
    "sg:province":"TN",
    "sg:tags":[
        "conditioning",
        "air",
        "system",
        "contractor"
    ],
    "wof:name":"A & O Air Inc",
    "wof:placetype":"venue"
},
  "geometry": {"coordinates":[-85.03359399999999,35.164314],"type":"Point"}
}