{
  "type": "Feature",
  "properties": {
    "iso:country":"US",
    "sg:address":"882 N Hwy 45 W",
    "sg:city":"Union City",
    "sg:classifiers":[
        {
            "category":"Personal",
            "subcategory":"Barber",
            "type":"Services"
        }
    ],
    "sg:phone":"+1 731 536 5379",
    "sg:postcode":"38261",
    "sg:province":"TN",
    "wof:name":"Gentlemen's Choice Barber Shop",
    "wof:placetype":"venue"
},
  "geometry": {"coordinates":[-89.066986,36.356426],"type":"Point"}
}