{
  "type": "Feature",
  "properties": {
    "iso:country":"US",
    "sg:address":"10900 Melton View Ln",
    "sg:city":"Knoxville",
    "sg:classifiers":[
        {
            "category":"Professional",
            "subcategory":"Management & Consulting",
            "type":"Services"
        }
    ],
    "sg:phone":"+1 865 927 5876",
    "sg:postcode":"37931",
    "sg:province":"TN",
    "sg:tags":[
        "business"
    ],
    "wof:name":"McDowell Margaret Fowler",
    "wof:placetype":"venue"
},
  "geometry": {"coordinates":[-84.199838,35.974047],"type":"Point"}
}