{
  "type": "Feature",
  "properties": {
    "addr:full":"3435 Frayser Raleigh Rd Memphis TN 38128",
    "addr:housenumber":"3435",
    "addr:postcode":"38128",
    "addr:street":"Raleigh Rd",
    "iso:country":"US",
    "sg:address":"3435 Frayser Raleigh Rd",
    "sg:city":"Memphis",
    "sg:classifiers":[
        {
            "category":"Social Services",
            "subcategory":"Child Care",
            "type":"Services"
        }
    ],
    "sg:phone":"+1 901 386 1429",
    "sg:postcode":"38128",
    "sg:province":"TN",
    "wof:name":"Pyramid Quality Infant Care",
    "wof:placetype":"venue"
},
  "geometry": {"coordinates":[-89.947812,35.223505],"type":"Point"}
}