{
  "type": "Feature",
  "properties": {
    "iso:country":"US",
    "sg:address":"110 Katrina Ln",
    "sg:city":"Lafayette",
    "sg:classifiers":[
        {
            "category":"Freight",
            "type":"Transportation"
        }
    ],
    "sg:phone":"+1 615 666 8417",
    "sg:postcode":"37083",
    "sg:province":"TN",
    "sg:tags":[
        "carrier",
        "contract"
    ],
    "wof:name":"Ace Transport",
    "wof:placetype":"venue"
},
  "geometry": {"coordinates":[-86.056483,36.602589],"type":"Point"}
}