{
  "type": "Feature",
  "properties": {
    "iso:country":"US",
    "sg:address":"436 S Valley View Cir",
    "sg:city":"Kingsport",
    "sg:classifiers":[
        {
            "category":"Personal",
            "subcategory":"Beauty Salon",
            "type":"Services"
        }
    ],
    "sg:phone":"+1 423 247 7717",
    "sg:postcode":"37664",
    "sg:province":"TN",
    "wof:name":"Viola Making Waves",
    "wof:placetype":"venue"
},
  "geometry": {"coordinates":[-82.425603,36.536944],"type":"Point"}
}