{
  "type": "Feature",
  "properties": {
    "iso:country":"US",
    "sg:address":"25 Ingram Blvd",
    "sg:city":"La Vergne",
    "sg:classifiers":[
        {
            "category":"Building & Trades",
            "subcategory":"Construction",
            "type":"Services"
        }
    ],
    "sg:phone":"+1 615 831 3100",
    "sg:postcode":"37086",
    "sg:province":"TN",
    "sg:tags":[
        "concrete",
        "pumping"
    ],
    "wof:name":"Premier Concrete Pumping Inc",
    "wof:placetype":"venue"
},
  "geometry": {"coordinates":[-86.585853,35.998476],"type":"Point"}
}