{
  "type": "Feature",
  "properties": {
    "iso:country":"US",
    "sg:address":"523 Dawson Ln",
    "sg:city":"Lebanon",
    "sg:classifiers":[
        {
            "category":"Building & Trades",
            "subcategory":"Landscaping Services",
            "type":"Services"
        }
    ],
    "sg:phone":"+1 615 453 1354",
    "sg:postcode":"37087",
    "sg:province":"TN",
    "wof:name":"Everyday Lawn Care",
    "wof:placetype":"venue"
},
  "geometry": {"coordinates":[-86.31755,36.20411],"type":"Point"}
}