{
  "type": "Feature",
  "properties": {
    "addr:full":"1211 Getwell Rd Memphis TN 38111",
    "addr:housenumber":"1211",
    "addr:postcode":"38111",
    "addr:street":"Getwell Rd",
    "iso:country":"US",
    "sg:address":"1211 Getwell Rd",
    "sg:city":"Memphis",
    "sg:classifiers":[
        {
            "category":"Professional",
            "subcategory":"Employment Agencies",
            "type":"Services"
        }
    ],
    "sg:phone":"+1 901 452 5888",
    "sg:postcode":"38111",
    "sg:province":"TN",
    "wof:name":"Ready Staffing Network LLC",
    "wof:placetype":"venue"
},
  "geometry": {"coordinates":[-89.930961,35.0989],"type":"Point"}
}