{
  "type": "Feature",
  "properties": {
    "iso:country":"US",
    "sg:address":"841 US Hwy 25W",
    "sg:city":"Williamsburg",
    "sg:classifiers":[
        {
            "category":"Health Services",
            "subcategory":"Chiropractor",
            "type":"Services"
        }
    ],
    "sg:phone":"+1 606 549 0123",
    "sg:postcode":"40769",
    "sg:province":"TN",
    "wof:name":"Ho Medical & Chiropractic",
    "wof:placetype":"venue"
},
  "geometry": {"coordinates":[-84.157833,36.752829],"type":"Point"}
}