{
  "type": "Feature",
  "properties": {
    "addr:full":"145 Casteel Rd SE Cleveland TN 37323",
    "addr:housenumber":"145",
    "addr:postcode":"37323",
    "addr:street":"Casteel Rd Se",
    "iso:country":"US",
    "sg:address":"145 Casteel Rd SE",
    "sg:city":"Cleveland",
    "sg:classifiers":[
        {
            "category":"Real Estate",
            "subcategory":"Real Estate Agent",
            "type":"Services"
        }
    ],
    "sg:phone":"+1 423 614 7278",
    "sg:postcode":"37323",
    "sg:province":"TN",
    "wof:name":"Bill L Beck",
    "wof:placetype":"venue"
},
  "geometry": {"coordinates":[-84.802217,35.126734],"type":"Point"}
}