{
  "type": "Feature",
  "properties": {
    "iso:country":"US",
    "sg:address":"109 Cottonwood Dr",
    "sg:city":"Franklin",
    "sg:classifiers":[
        {
            "category":"Organizations",
            "subcategory":"Membership Organization",
            "type":"Services"
        }
    ],
    "sg:phone":"+1 615 794 4679",
    "sg:postcode":"37069",
    "sg:province":"TN",
    "wof:name":"Music City Masters Inc",
    "wof:placetype":"venue"
},
  "geometry": {"coordinates":[-86.900255,35.976889],"type":"Point"}
}