{
  "type": "Feature",
  "properties": {
    "iso:country":"US",
    "sg:address":"237 W Summer St",
    "sg:city":"Greeneville",
    "sg:classifiers":[
        {
            "category":"Insurance",
            "subcategory":"Insurance Agent",
            "type":"Services"
        }
    ],
    "sg:phone":"+1 423 639 5171",
    "sg:postcode":"37743",
    "sg:province":"TN",
    "wof:name":"Mc Inturff Milligan & Brooks",
    "wof:placetype":"venue"
},
  "geometry": {"coordinates":[-82.834986,36.163453],"type":"Point"}
}