{
  "type": "Feature",
  "properties": {
    "addr:full":"520 Old Hwy 68 Sweetwater TN 37874",
    "addr:housenumber":"520",
    "addr:postcode":"37874",
    "addr:street":"Old Hwy 68",
    "iso:country":"US",
    "sg:address":"520 Old Hwy 68",
    "sg:city":"Sweetwater",
    "sg:classifiers":[
        {
            "category":"Health Services",
            "subcategory":"Nursing And Care Facility",
            "type":"Services"
        }
    ],
    "sg:phone":"+1 423 337 5326",
    "sg:postcode":"37874",
    "sg:province":"TN",
    "sg:tags":[
        "home"
    ],
    "wof:name":"Wood Village",
    "wof:placetype":"venue"
},
  "geometry": {"coordinates":[-84.460347,35.59521],"type":"Point"}
}