{
  "type": "Feature",
  "properties": {
    "iso:country":"US",
    "sg:address":"2276 West St",
    "sg:city":"Germantown",
    "sg:classifiers":[
        {
            "category":"Recreation",
            "type":"Entertainment"
        }
    ],
    "sg:phone":"+1 901 757 7205",
    "sg:postcode":"38138",
    "sg:province":"TN",
    "sg:tags":[
        "executive"
    ],
    "wof:name":"Germantown Parks & Recreation",
    "wof:placetype":"venue"
},
  "geometry": {"coordinates":[-89.811604,35.087215],"type":"Point"}
}