{
  "type": "Feature",
  "properties": {
    "addr:full":"606 Arbor Lake Blvd Hermitage TN 37076",
    "addr:housenumber":"606",
    "addr:postcode":"37076",
    "addr:street":"Arbor Lake Blvd",
    "iso:country":"US",
    "sg:address":"606 Arbor Lake Blvd",
    "sg:city":"Hermitage",
    "sg:classifiers":[
        {
            "category":"Professional",
            "subcategory":"Management & Consulting",
            "type":"Services"
        }
    ],
    "sg:phone":"+1 615 889 4983",
    "sg:postcode":"37076",
    "sg:province":"TN",
    "sg:tags":[
        "business"
    ],
    "wof:name":"Totally Shagaedlic Consulting",
    "wof:placetype":"venue"
},
  "geometry": {"coordinates":[-86.597887,36.164058],"type":"Point"}
}