{
  "type": "Feature",
  "properties": {
    "addr:full":"2817 Azalea Pl Nashville TN 37204",
    "addr:housenumber":"2817",
    "addr:postcode":"37204",
    "addr:street":"Azalea Pl",
    "iso:country":"US",
    "sg:address":"2817 Azalea Pl",
    "sg:city":"Nashville",
    "sg:classifiers":[
        {
            "category":"Organizations",
            "subcategory":"Religious Organization",
            "type":"Services"
        }
    ],
    "sg:phone":"+1 615 383 2001",
    "sg:postcode":"37204",
    "sg:province":"TN",
    "wof:name":"Eckankar Center Of Nashville",
    "wof:placetype":"venue"
},
  "geometry": {"coordinates":[-86.76792399999999,36.116749],"type":"Point"}
}