{
  "type": "Feature",
  "properties": {
    "iso:country":"US",
    "sg:address":"9860 Highway 641 N",
    "sg:city":"Puryear",
    "sg:classifiers":[
        {
            "category":"Restaurant",
            "type":"Food & Drink"
        }
    ],
    "sg:menulink":"http://www.allmenus.com/tn/puryear/140341-subway/menu/",
    "sg:phone":"+1 731 247 3355",
    "sg:postcode":"38251",
    "sg:province":"TN",
    "sg:tags":[
        "american",
        "sandwich"
    ],
    "wof:name":"Subway",
    "wof:placetype":"venue"
},
  "geometry": {"coordinates":[-88.332266,36.443126],"type":"Point"}
}