{
  "type": "Feature",
  "properties": {
    "iso:country":"US",
    "sg:address":"19900 State Hwy 69",
    "sg:city":"Savannah",
    "sg:classifiers":[
        {
            "category":"Recreation",
            "type":"Entertainment"
        }
    ],
    "sg:phone":"+1 731 925 9266",
    "sg:postcode":"38372",
    "sg:province":"TN",
    "sg:tags":[
        "club",
        "membership"
    ],
    "wof:name":"R&G Hunting Club",
    "wof:placetype":"venue"
},
  "geometry": {"coordinates":[-88.23299400000001,35.186631],"type":"Point"}
}