{
  "type": "Feature",
  "properties": {
    "iso:country":"US",
    "sg:address":"105 Martin Rd",
    "sg:city":"Limestone",
    "sg:classifiers":[
        {
            "category":"Building & Trades",
            "subcategory":"Construction",
            "type":"Services"
        }
    ],
    "sg:phone":"+1 423 257 3789",
    "sg:postcode":"37681",
    "sg:province":"TN",
    "sg:tags":[
        "hanging",
        "contractor"
    ],
    "wof:name":"Gils Painting",
    "wof:placetype":"venue"
},
  "geometry": {"coordinates":[-82.65940500000001,36.278904],"type":"Point"}
}