{
  "type": "Feature",
  "properties": {
    "iso:country":"US",
    "sg:address":"430 Mountain View Rd",
    "sg:city":"Bluff City",
    "sg:classifiers":[
        {
            "category":"Real Estate",
            "subcategory":"Real Estate Operator",
            "type":"Services"
        }
    ],
    "sg:phone":"+1 423 764 9126",
    "sg:postcode":"37618",
    "sg:province":"TN",
    "sg:tags":[
        "mobile",
        "home",
        "community"
    ],
    "wof:name":"Mann Mobile Home Park",
    "wof:placetype":"venue"
},
  "geometry": {"coordinates":[-82.263294,36.44916],"type":"Point"}
}