{
  "type": "Feature",
  "properties": {
    "iso:country":"US",
    "sg:address":"6515 Currywood Dr",
    "sg:city":"Nashville",
    "sg:classifiers":[
        {
            "category":"Home & Garden",
            "subcategory":"Home Furnishings",
            "type":"Retail Goods"
        }
    ],
    "sg:phone":"+1 615 646 7299",
    "sg:postcode":"37205",
    "sg:province":"TN",
    "sg:tags":[
        "venetian",
        "blind"
    ],
    "wof:name":"Blind Man",
    "wof:placetype":"venue"
},
  "geometry": {"coordinates":[-86.89712900000001,36.112614],"type":"Point"}
}