{
  "type": "Feature",
  "properties": {
    "iso:country":"US",
    "sg:address":"8031 E Brainerd Rd",
    "sg:city":"Chattanooga",
    "sg:classifiers":[
        {
            "category":"Personal",
            "subcategory":"Barber",
            "type":"Services"
        }
    ],
    "sg:phone":"+1 423 894 6462",
    "sg:postcode":"37421",
    "sg:province":"TN",
    "sg:tags":[
        "shop"
    ],
    "wof:name":"Cawoods Barber Shop",
    "wof:placetype":"venue"
},
  "geometry": {"coordinates":[-85.150642,35.004322],"type":"Point"}
}