{
  "type": "Feature",
  "properties": {
    "iso:country":"US",
    "sg:address":"5555 N Lee Hwy",
    "sg:city":"Cleveland",
    "sg:classifiers":[
        {
            "category":"Home & Garden",
            "subcategory":"Building Materials",
            "type":"Retail Goods"
        }
    ],
    "sg:phone":"+1 423 559 5565",
    "sg:postcode":"37312",
    "sg:province":"TN",
    "sg:tags":[
        "windows"
    ],
    "wof:name":"Accurate Windows & Doors",
    "wof:placetype":"venue"
},
  "geometry": {"coordinates":[-84.82896,35.216941],"type":"Point"}
}