{
  "type": "Feature",
  "properties": {
    "iso:country":"US",
    "sg:address":"214 Heatherwood Ct",
    "sg:city":"Murfreesboro",
    "sg:classifiers":[
        {
            "category":"Professional",
            "subcategory":"Business Services",
            "type":"Services"
        }
    ],
    "sg:phone":"+1 615 494 0698",
    "sg:postcode":"37129",
    "sg:province":"TN",
    "wof:name":"Maraschiello Carolyn",
    "wof:placetype":"venue"
},
  "geometry": {"coordinates":[-86.48934300000001,35.889277],"type":"Point"}
}