{
  "type": "Feature",
  "properties": {
    "addr:full":"1947 Old Knoxville Hwy Sevierville TN 37876",
    "addr:housenumber":"1947",
    "addr:postcode":"37876",
    "addr:street":"Old Knoxville Hwy",
    "iso:country":"US",
    "sg:address":"1947 Old Knoxville Hwy",
    "sg:city":"Sevierville",
    "sg:classifiers":[
        {
            "category":"Building & Trades",
            "subcategory":"Landscaping Services",
            "type":"Services"
        }
    ],
    "sg:phone":"+1 865 428 6070",
    "sg:postcode":"37876",
    "sg:province":"TN",
    "sg:tags":[
        "excavation",
        "landscape",
        "contractor"
    ],
    "wof:name":"Oakhacen Cenort",
    "wof:placetype":"venue"
},
  "geometry": {"coordinates":[-83.60047,35.919487],"type":"Point"}
}