{
  "type": "Feature",
  "properties": {
    "iso:country":"US",
    "sg:address":"2855 Poplar Ave",
    "sg:city":"Memphis",
    "sg:classifiers":[
        {
            "category":"Restaurant",
            "type":"Food & Drink"
        }
    ],
    "sg:phone":"+1 901 323 0007",
    "sg:postcode":"38111",
    "sg:province":"TN",
    "sg:tags":[
        "style",
        "family"
    ],
    "sg:website":"http://www.ronniegrisantianadsons.com",
    "wof:name":"Ronnie Grisanti & Sons Restaurant",
    "wof:placetype":"venue"
},
  "geometry": {"coordinates":[-89.96613600000001,35.134459],"type":"Point"}
}