{
  "type": "Feature",
  "properties": {
    "iso:country":"US",
    "sg:address":"2415 E Broadway Ave",
    "sg:city":"Maryville",
    "sg:classifiers":[
        {
            "category":"Home & Garden",
            "subcategory":"Building Materials",
            "type":"Retail Goods"
        }
    ],
    "sg:phone":"+1 865 982 3151",
    "sg:postcode":"37804",
    "sg:province":"TN",
    "sg:tags":[
        "glass",
        "window",
        "plate"
    ],
    "wof:name":"3 T Glass Co",
    "wof:placetype":"venue"
},
  "geometry": {"coordinates":[-83.947153,35.786888],"type":"Point"}
}