{
  "type": "Feature",
  "properties": {
    "iso:country":"US",
    "sg:address":"1139 Nashville Hwy",
    "sg:city":"Lewisburg",
    "sg:classifiers":[
        {
            "category":"Sports & Exercise",
            "subcategory":"Gym",
            "type":"Entertainment"
        }
    ],
    "sg:phone":"+1 931 270 7833",
    "sg:postcode":"37091",
    "sg:province":"TN",
    "sg:tags":[
        "club",
        "health",
        "studio",
        "gymnasium"
    ],
    "wof:name":"Curves For Women",
    "wof:placetype":"venue"
},
  "geometry": {"coordinates":[-86.779437,35.463069],"type":"Point"}
}