{
  "type": "Feature",
  "properties": {
    "addr:full":"2823 Penn Meade Dr Nashville TN 37214",
    "addr:housenumber":"2823",
    "addr:postcode":"37214",
    "addr:street":"Penn Meade Dr",
    "iso:country":"US",
    "sg:address":"2823 Penn Meade Dr",
    "sg:city":"Nashville",
    "sg:classifiers":[
        {
            "category":"Building & Trades",
            "subcategory":"Construction",
            "type":"Services"
        }
    ],
    "sg:phone":"+1 615 391 4629",
    "sg:postcode":"37214",
    "sg:province":"TN",
    "sg:tags":[
        "home",
        "builder"
    ],
    "wof:name":"Fox Ridge Homes Inc",
    "wof:placetype":"venue"
},
  "geometry": {"coordinates":[-86.702145,36.239046],"type":"Point"}
}