{
  "type": "Feature",
  "properties": {
    "iso:country":"US",
    "sg:address":"902 S Holly St",
    "sg:city":"Monterey",
    "sg:classifiers":[
        {
            "category":"Restaurant",
            "type":"Food & Drink"
        }
    ],
    "sg:phone":"+1 931 839 3505",
    "sg:postcode":"38574",
    "sg:province":"TN",
    "sg:tags":[
        "eating"
    ],
    "wof:name":"Hardees",
    "wof:placetype":"venue"
},
  "geometry": {"coordinates":[-85.27585500000001,36.142105],"type":"Point"}
}