{
  "type": "Feature",
  "properties": {
    "addr:full":"861 Springfield Hwy Goodlettsville TN 37072",
    "addr:housenumber":"861",
    "addr:postcode":"37072",
    "addr:street":"Springfield Hwy",
    "iso:country":"US",
    "sg:address":"861 Springfield Hwy",
    "sg:city":"Goodlettsville",
    "sg:classifiers":[
        {
            "category":"Building & Trades",
            "subcategory":"Electrical",
            "type":"Services"
        }
    ],
    "sg:phone":"+1 615 859 0290",
    "sg:postcode":"37072",
    "sg:province":"TN",
    "sg:tags":[
        "electric",
        "contractor"
    ],
    "wof:name":"J H Electric Co",
    "wof:placetype":"venue"
},
  "geometry": {"coordinates":[-86.72526499999999,36.358135],"type":"Point"}
}