{
  "type": "Feature",
  "properties": {
    "iso:country":"US",
    "sg:address":"550 S Main St",
    "sg:city":"Sweetwater",
    "sg:classifiers":[
        {
            "category":"Banks & Credit Unions",
            "subcategory":"Bank",
            "type":"Services"
        }
    ],
    "sg:phone":"+1 423 337 5449",
    "sg:postcode":"37874",
    "sg:province":"TN",
    "sg:tags":[
        "depository",
        "banking"
    ],
    "wof:name":"C Moss Enterprises",
    "wof:placetype":"venue"
},
  "geometry": {"coordinates":[-84.468047,35.593193],"type":"Point"}
}