{
  "type": "Feature",
  "properties": {
    "iso:country":"US",
    "sg:address":"4152 Maplewood St",
    "sg:city":"Kingsport",
    "sg:classifiers":[
        {
            "category":"Organizations",
            "subcategory":"Religious Organization",
            "type":"Services"
        }
    ],
    "sg:phone":"+1 423 349 6288",
    "sg:postcode":"37660",
    "sg:province":"TN",
    "sg:website":"www.sullivanbaptist.org",
    "wof:name":"Sullivan Baptist Church",
    "wof:placetype":"venue"
},
  "geometry": {"coordinates":[-82.598251,36.477418],"type":"Point"}
}