{
  "type": "Feature",
  "properties": {
    "iso:country":"US",
    "sg:address":"3738 Dickerson Pike",
    "sg:city":"Nashville",
    "sg:classifiers":[
        {
            "category":"Wholesale",
            "subcategory":"Plants",
            "type":"Manufacturing & Wholesale Goods"
        },
        {
            "category":"Farming",
            "subcategory":"Nursery",
            "type":"Manufacturing & Wholesale Goods"
        }
    ],
    "sg:phone":"+1 615 333 3333",
    "sg:postcode":"37207",
    "sg:province":"TN",
    "sg:tags":[
        "ornamental",
        "tree"
    ],
    "sg:website":"www.southernnurseries.com",
    "wof:name":"Southern Nurseries Inc",
    "wof:placetype":"venue"
},
  "geometry": {"coordinates":[-86.757425,36.262911],"type":"Point"}
}