{
  "type": "Feature",
  "properties": {
    "addr:full":"315 W Broadway St Lenoir City TN 37771",
    "addr:housenumber":"315",
    "addr:postcode":"37771",
    "addr:street":"W Broadway St",
    "iso:country":"US",
    "sg:address":"315 W Broadway St",
    "sg:city":"Lenoir City",
    "sg:classifiers":[
        {
            "category":"Building & Trades",
            "subcategory":"Construction",
            "type":"Services"
        }
    ],
    "sg:phone":"+1 865 986 3313",
    "sg:postcode":"37771",
    "sg:province":"TN",
    "sg:tags":[
        "general",
        "contractor"
    ],
    "wof:name":"David Lee Construction",
    "wof:placetype":"venue"
},
  "geometry": {"coordinates":[-84.267979,35.789758],"type":"Point"}
}