{
  "type": "Feature",
  "properties": {
    "addr:full":"121 Factory St Rock Island TN 38581",
    "addr:housenumber":"121",
    "addr:postcode":"38581",
    "addr:street":"Factory St",
    "iso:country":"US",
    "sg:address":"121 Factory St",
    "sg:city":"Rock Island",
    "sg:classifiers":[
        {
            "category":"Manufacturing",
            "subcategory":"Metals",
            "type":"Manufacturing & Wholesale Goods"
        }
    ],
    "sg:phone":"+1 931 686 2538",
    "sg:postcode":"38581",
    "sg:province":"TN",
    "sg:tags":[
        "plating"
    ],
    "wof:name":"Duromatic Products Inc",
    "wof:placetype":"venue"
},
  "geometry": {"coordinates":[-85.63318099999999,35.768594],"type":"Point"}
}