{
  "type": "Feature",
  "properties": {
    "iso:country":"US",
    "sg:address":"4321 Whispering Bend Cove N",
    "sg:city":"Memphis",
    "sg:classifiers":[
        {
            "category":"Education",
            "subcategory":"Special Training",
            "type":"Public Place"
        }
    ],
    "sg:phone":"+1 901 737 2874",
    "sg:postcode":"38125",
    "sg:province":"TN",
    "sg:tags":[
        "educational"
    ],
    "wof:name":"TOUCH Inc",
    "wof:placetype":"venue"
},
  "geometry": {"coordinates":[-89.78982600000001,35.030034],"type":"Point"}
}