{
  "type": "Feature",
  "properties": {
    "iso:country":"US",
    "sg:address":"204 N Main St",
    "sg:city":"Dickson",
    "sg:classifiers":[
        {
            "category":"Real Estate",
            "subcategory":"Surveying",
            "type":"Services"
        }
    ],
    "sg:phone":"+1 615 740 7373",
    "sg:postcode":"37055",
    "sg:province":"TN",
    "sg:tags":[
        "surveyor"
    ],
    "wof:name":"Fowlkes Land Surveying Company",
    "wof:placetype":"venue"
},
  "geometry": {"coordinates":[-87.38552199999999,36.07855],"type":"Point"}
}