{
  "type": "Feature",
  "properties": {
    "iso:country":"US",
    "sg:address":"1200 Park Ave",
    "sg:city":"Murfreesboro",
    "sg:classifiers":[
        {
            "category":"Building & Trades",
            "subcategory":"Equipment Rental",
            "type":"Services"
        }
    ],
    "sg:phone":"+1 615 890 6277",
    "sg:postcode":"37129",
    "sg:province":"TN",
    "sg:tags":[
        "leasing"
    ],
    "wof:name":"Morris Leasing",
    "wof:placetype":"venue"
},
  "geometry": {"coordinates":[-86.397858,35.830509],"type":"Point"}
}