{
  "type": "Feature",
  "properties": {
    "iso:country":"US",
    "sg:address":"463 E Chester St",
    "sg:city":"Jackson",
    "sg:classifiers":[
        {
            "category":"Retail",
            "subcategory":"Car Wash",
            "type":"Services"
        }
    ],
    "sg:phone":"+1 731 423 8221",
    "sg:postcode":"38301",
    "sg:province":"TN",
    "sg:tags":[
        "carwash",
        "supply"
    ],
    "wof:name":"Millers Tire",
    "wof:placetype":"venue"
},
  "geometry": {"coordinates":[-88.81451300000001,35.612591],"type":"Point"}
}