{
  "type": "Feature",
  "properties": {
    "addr:full":"4510 Airport Hwy Louisville TN 37777",
    "addr:housenumber":"4510",
    "addr:postcode":"37777",
    "addr:street":"Airport Hwy",
    "iso:country":"US",
    "sg:address":"4510 Airport Hwy",
    "sg:city":"Louisville",
    "sg:classifiers":[
        {
            "category":"Food & Beverages",
            "subcategory":"Groceries & Convenience Stores",
            "type":"Retail Goods"
        }
    ],
    "sg:phone":"+1 865 681 3400",
    "sg:postcode":"37777",
    "sg:province":"TN",
    "wof:name":"Lakemont Market",
    "wof:placetype":"venue"
},
  "geometry": {"coordinates":[-83.95959999999999,35.859589],"type":"Point"}
}