{
  "type": "Feature",
  "properties": {
    "iso:country":"US",
    "sg:address":"2008 Post Rd",
    "sg:city":"Clarksville",
    "sg:classifiers":[
        {
            "category":"Arts & Performance",
            "subcategory":"Theater",
            "type":"Entertainment"
        }
    ],
    "sg:phone":"+1 931 552 3116",
    "sg:postcode":"37043",
    "sg:province":"TN",
    "sg:tags":[
        "musician"
    ],
    "wof:name":"Thomas A Faulkner",
    "wof:placetype":"venue"
},
  "geometry": {"coordinates":[-87.299001,36.519969],"type":"Point"}
}