{
  "type": "Feature",
  "properties": {
    "iso:country":"US",
    "sg:address":"2424 E Broadway Ave",
    "sg:city":"Maryville",
    "sg:classifiers":[
        {
            "category":"Food & Beverages",
            "subcategory":"Bakery",
            "type":"Retail Goods"
        }
    ],
    "sg:phone":"+1 865 983 7961",
    "sg:postcode":"37804",
    "sg:province":"TN",
    "sg:tags":[
        "baker"
    ],
    "wof:name":"Merita Thrift Store",
    "wof:placetype":"venue"
},
  "geometry": {"coordinates":[-83.947029,35.786644],"type":"Point"}
}