{
  "type": "Feature",
  "properties": {
    "iso:country":"US",
    "sg:address":"605 Eagle Ct",
    "sg:city":"La Vergne",
    "sg:classifiers":[
        {
            "category":"Professional",
            "subcategory":"Computer Services",
            "type":"Services"
        }
    ],
    "sg:phone":"+1 615 355 9812",
    "sg:postcode":"37086",
    "sg:province":"TN",
    "sg:tags":[
        "related"
    ],
    "wof:name":"Bob Lawler",
    "wof:placetype":"venue"
},
  "geometry": {"coordinates":[-86.545101,36.018622],"type":"Point"}
}