{
  "type": "Feature",
  "properties": {
    "addr:full":"1301 Hampshire Pike Columbia TN 38401",
    "addr:housenumber":"1301",
    "addr:postcode":"38401",
    "addr:street":"Hampshire Pike",
    "iso:country":"US",
    "sg:address":"1301 Hampshire Pike",
    "sg:city":"Columbia",
    "sg:classifiers":[
        {
            "category":"Education",
            "subcategory":"School",
            "type":"Public Place"
        }
    ],
    "sg:phone":"+1 931 388 3319",
    "sg:postcode":"38401",
    "sg:province":"TN",
    "wof:name":"Baker School",
    "wof:placetype":"venue"
},
  "geometry": {"coordinates":[-87.0792,35.619596],"type":"Point"}
}