{
  "type": "Feature",
  "properties": {
    "iso:country":"US",
    "sg:address":"1664 Tamarack Ln",
    "sg:city":"Germantown",
    "sg:classifiers":[
        {
            "category":"Professional",
            "subcategory":"Business Services",
            "type":"Services"
        }
    ],
    "sg:phone":"+1 901 754 1154",
    "sg:postcode":"38138",
    "sg:province":"TN",
    "wof:name":"Write Stuff",
    "wof:placetype":"venue"
},
  "geometry": {"coordinates":[-89.819013,35.102055],"type":"Point"}
}