{
  "type": "Feature",
  "properties": {
    "iso:country":"US",
    "sg:address":"2715 Whites Creek Pike # 175",
    "sg:city":"Nashville",
    "sg:classifiers":[
        {
            "category":"Personal",
            "subcategory":"Nail Salon",
            "type":"Services"
        }
    ],
    "sg:phone":"+1 615 473 4845",
    "sg:postcode":"37207",
    "sg:province":"TN",
    "wof:name":"Nails By Michele",
    "wof:placetype":"venue"
},
  "geometry": {"coordinates":[-86.803513,36.218201],"type":"Point"}
}