{
  "type": "Feature",
  "properties": {
    "addr:full":"260 N Bank St Oneida TN 37841",
    "addr:housenumber":"260",
    "addr:postcode":"37841",
    "addr:street":"N Bank St",
    "iso:country":"US",
    "sg:address":"260 N Bank St",
    "sg:city":"Oneida",
    "sg:classifiers":[
        {
            "category":"Wholesale",
            "subcategory":"Medical Equipment & Supplies",
            "type":"Manufacturing & Wholesale Goods"
        }
    ],
    "sg:phone":"+1 423 286 6464",
    "sg:postcode":"37841",
    "sg:province":"TN",
    "sg:tags":[
        "physician",
        "surgeon"
    ],
    "wof:name":"Renaissance Medical",
    "wof:placetype":"venue"
},
  "geometry": {"coordinates":[-84.51110799999999,36.504268],"type":"Point"}
}