{
  "type": "Feature",
  "properties": {
    "addr:full":"1725 W Broadway Ave Maryville TN 37801",
    "addr:housenumber":"1725",
    "addr:postcode":"37801",
    "addr:street":"W Broadway Ave",
    "iso:country":"US",
    "sg:address":"1725 W Broadway Ave",
    "sg:city":"Maryville",
    "sg:classifiers":[
        {
            "category":"Restaurant",
            "type":"Food & Drink"
        }
    ],
    "sg:menulink":"http://www.allmenus.com/tn/maryville-alcoa/116190-quiznos-sub/menu/",
    "sg:phone":"+1 865 983 0069",
    "sg:postcode":"37801",
    "sg:province":"TN",
    "sg:tags":[
        "wrap",
        "american",
        "sandwich"
    ],
    "wof:name":"Quiznos Sub",
    "wof:placetype":"venue"
},
  "geometry": {"coordinates":[-83.99316,35.735046],"type":"Point"}
}