{
  "type": "Feature",
  "properties": {
    "addr:full":"5108 Old Hickory Blvd Nashville TN 37218",
    "addr:housenumber":"5108",
    "addr:postcode":"37218",
    "addr:street":"Old Hickory Blvd",
    "iso:country":"US",
    "sg:address":"5108 Old Hickory Blvd",
    "sg:city":"Nashville",
    "sg:classifiers":[
        {
            "category":"Shopping",
            "subcategory":"Computers & Home Electronics",
            "type":"Retail Goods"
        }
    ],
    "sg:phone":"+1 615 846 1208",
    "sg:postcode":"37218",
    "sg:province":"TN",
    "sg:tags":[
        "equipment",
        "electronic",
        "supply"
    ],
    "wof:name":"Electronic Express",
    "wof:placetype":"venue"
},
  "geometry": {"coordinates":[-86.918676,36.215285],"type":"Point"}
}