{
  "type": "Feature",
  "properties": {
    "iso:country":"US",
    "sg:address":"350 Cedar Springs Rd SE",
    "sg:city":"Cleveland",
    "sg:classifiers":[
        {
            "category":"Building & Trades",
            "subcategory":"Cleaning & Sanitation",
            "type":"Services"
        }
    ],
    "sg:phone":"+1 423 479 4580",
    "sg:postcode":"37323",
    "sg:province":"TN",
    "sg:tags":[
        "janitor"
    ],
    "wof:name":"Cleveland Janitorial Svc",
    "wof:placetype":"venue"
},
  "geometry": {"coordinates":[-84.79435700000001,35.076711],"type":"Point"}
}