{
  "type": "Feature",
  "properties": {
    "iso:country":"US",
    "sg:address":"8245 Farmington Blvd",
    "sg:city":"Germantown",
    "sg:classifiers":[
        {
            "category":"Organizations",
            "subcategory":"Religious Organization",
            "type":"Services"
        }
    ],
    "sg:phone":"+1 901 754 2794",
    "sg:postcode":"38139",
    "sg:province":"TN",
    "sg:tags":[
        "school"
    ],
    "wof:name":"Farmington Presbt Kindergarten",
    "wof:placetype":"venue"
},
  "geometry": {"coordinates":[-89.788076,35.095105],"type":"Point"}
}