{
  "type": "Feature",
  "properties": {
    "addr:full":"430 Riverport Rd Kingsport TN 37660",
    "addr:housenumber":"430",
    "addr:postcode":"37660",
    "addr:street":"Riverport Rd",
    "iso:country":"US",
    "sg:address":"430 Riverport Rd",
    "sg:city":"Kingsport",
    "sg:classifiers":[
        {
            "category":"Real Estate",
            "subcategory":"Real Estate Operator",
            "type":"Services"
        }
    ],
    "sg:phone":"+1 423 247 2700",
    "sg:postcode":"37660",
    "sg:province":"TN",
    "sg:tags":[
        "property",
        "management"
    ],
    "wof:name":"Baysview LLC",
    "wof:placetype":"venue"
},
  "geometry": {"coordinates":[-82.574913,36.541202],"type":"Point"}
}