{
  "type": "Feature",
  "properties": {
    "iso:country":"US",
    "sg:address":"921 Murfreesboro Rd",
    "sg:city":"Lebanon",
    "sg:classifiers":[
        {
            "category":"Food & Beverages",
            "subcategory":"Specialty",
            "type":"Retail Goods"
        }
    ],
    "sg:phone":"+1 615 547 7060",
    "sg:postcode":"37090",
    "sg:province":"TN",
    "sg:tags":[
        "health",
        "diet"
    ],
    "wof:name":"Truckers Choice Wellness",
    "wof:placetype":"venue"
},
  "geometry": {"coordinates":[-86.300218,36.179481],"type":"Point"}
}