{
  "type": "Feature",
  "properties": {
    "iso:country":"US",
    "sg:address":"112 S Sycamore St",
    "sg:city":"Elizabethton",
    "sg:classifiers":[
        {
            "category":"Professional",
            "type":"Services"
        }
    ],
    "sg:phone":"+1 423 542 2167",
    "sg:postcode":"37643",
    "sg:province":"TN",
    "wof:name":"Brumit Kenneth Brumit",
    "wof:placetype":"venue"
},
  "geometry": {"coordinates":[-82.21439700000001,36.347462],"type":"Point"}
}