{
  "type": "Feature",
  "properties": {
    "iso:country":"US",
    "sg:address":"739 Humble Dr",
    "sg:city":"Cookeville",
    "sg:classifiers":[
        {
            "category":"Retail",
            "subcategory":"Auto Repair",
            "type":"Services"
        }
    ],
    "sg:phone":"+1 931 526 6214",
    "sg:postcode":"38501",
    "sg:province":"TN",
    "sg:tags":[
        "body"
    ],
    "wof:name":"Jones Auto Body",
    "wof:placetype":"venue"
},
  "geometry": {"coordinates":[-85.526287,36.142902],"type":"Point"}
}