{
  "type": "Feature",
  "properties": {
    "iso:country":"US",
    "sg:address":"1403 Tunnel Blvd",
    "sg:city":"Chattanooga",
    "sg:classifiers":[
        {
            "category":"Organizations",
            "subcategory":"Religious Organization",
            "type":"Services"
        }
    ],
    "sg:phone":"+1 423 698 3121",
    "sg:postcode":"37411",
    "sg:province":"TN",
    "wof:name":"Eastdale Vlg Comm Utd Meth CHR",
    "wof:placetype":"venue"
},
  "geometry": {"coordinates":[-85.237747,35.044544],"type":"Point"}
}