{
  "type": "Feature",
  "properties": {
    "addr:full":"3400 Berkshire Cir Johnson City TN 37604",
    "addr:housenumber":"3400",
    "addr:postcode":"37604",
    "addr:street":"Berkshire Cir",
    "iso:country":"US",
    "sg:address":"3400 Berkshire Cir",
    "sg:city":"Johnson City",
    "sg:classifiers":[
        {
            "category":"Insurance",
            "subcategory":"Insurance Agent",
            "type":"Services"
        }
    ],
    "sg:phone":"+1 423 282 5746",
    "sg:postcode":"37604",
    "sg:province":"TN",
    "wof:name":"John Abe Teague Ins Agncy",
    "wof:placetype":"venue"
},
  "geometry": {"coordinates":[-82.414435,36.347134],"type":"Point"}
}