{
  "type": "Feature",
  "properties": {
    "addr:full":"146 Space Park S Nashville TN 37211",
    "addr:postcode":"37211",
    "addr:street":"S",
    "iso:country":"US",
    "sg:address":"146 Space Park S",
    "sg:city":"Nashville",
    "sg:classifiers":[
        {
            "category":"Wholesale",
            "subcategory":"Machinery & Supplies",
            "type":"Manufacturing & Wholesale Goods"
        }
    ],
    "sg:phone":"+1 615 831 2891",
    "sg:postcode":"37211",
    "sg:province":"TN",
    "sg:tags":[
        "industrial"
    ],
    "wof:name":"Hazen Agency",
    "wof:placetype":"venue"
},
  "geometry": {"coordinates":[-86.706495,36.098774],"type":"Point"}
}