{
  "type": "Feature",
  "properties": {
    "iso:country":"US",
    "sg:address":"109 Saltwood Pl",
    "sg:city":"Hendersonville",
    "sg:classifiers":[
        {
            "category":"Professional",
            "type":"Services"
        }
    ],
    "sg:phone":"+1 615 824 2626",
    "sg:postcode":"37075",
    "sg:province":"TN",
    "wof:name":"Rmf Inc",
    "wof:placetype":"venue"
},
  "geometry": {"coordinates":[-86.58422299999999,36.283202],"type":"Point"}
}