{
  "type": "Feature",
  "properties": {
    "iso:country":"US",
    "sg:address":"4549 Raccoon Trl",
    "sg:city":"Hermitage",
    "sg:classifiers":[
        {
            "category":"Professional",
            "subcategory":"Research",
            "type":"Services"
        }
    ],
    "sg:phone":"+1 615 391 4758",
    "sg:postcode":"37076",
    "sg:province":"TN",
    "sg:tags":[
        "scientific"
    ],
    "wof:name":"Macias-Perez Ines",
    "wof:placetype":"venue"
},
  "geometry": {"coordinates":[-86.580338,36.192493],"type":"Point"}
}