{
  "type": "Feature",
  "properties": {
    "addr:full":"123 E Emory Rd Powell TN 37849",
    "addr:housenumber":"123",
    "addr:postcode":"37849",
    "addr:street":"E Emory Rd",
    "iso:country":"US",
    "sg:address":"123 E Emory Rd",
    "sg:city":"Powell",
    "sg:classifiers":[
        {
            "category":"Health Services",
            "subcategory":"Doctor",
            "type":"Services"
        }
    ],
    "sg:phone":"+1 865 938 1230",
    "sg:postcode":"37849",
    "sg:province":"TN",
    "wof:name":"Crumpton Reid DDS",
    "wof:placetype":"venue"
},
  "geometry": {"coordinates":[-84.008132,36.043524],"type":"Point"}
}