{
  "type": "Feature",
  "properties": {
    "addr:full":"2660 US Hwy 641 N Paris TN 38242",
    "addr:housenumber":"2660",
    "addr:postcode":"38242",
    "addr:street":"Us Hwy 641 N",
    "iso:country":"US",
    "sg:address":"2660 US Hwy 641 N",
    "sg:city":"Paris",
    "sg:classifiers":[
        {
            "category":"Building & Trades",
            "subcategory":"Plumbing",
            "type":"Services"
        }
    ],
    "sg:phone":"+1 731 644 1287",
    "sg:postcode":"38242",
    "sg:province":"TN",
    "sg:tags":[
        "contractor"
    ],
    "wof:name":"All Temp Services",
    "wof:placetype":"venue"
},
  "geometry": {"coordinates":[-88.32823399999999,36.338816],"type":"Point"}
}