{
  "type": "Feature",
  "properties": {
    "iso:country":"US",
    "sg:address":"4990 SE Tater Peeler Rd",
    "sg:city":"Lebanon",
    "sg:classifiers":[
        {
            "category":"Building & Trades",
            "subcategory":"Construction",
            "type":"Services"
        }
    ],
    "sg:phone":"+1 615 453 6892",
    "sg:postcode":"37090",
    "sg:province":"TN",
    "sg:tags":[
        "house",
        "general",
        "contractor"
    ],
    "wof:name":"Jackie Posey Construction LLC",
    "wof:placetype":"venue"
},
  "geometry": {"coordinates":[-86.277366,36.13688],"type":"Point"}
}