{
  "type": "Feature",
  "properties": {
    "iso:country":"US",
    "sg:address":"1148 Gilchrist Rd",
    "sg:city":"Adamsville",
    "sg:classifiers":[
        {
            "category":"Manufacturing",
            "subcategory":"Petroleum Products",
            "type":"Manufacturing & Wholesale Goods"
        },
        {
            "category":"Building & Trades",
            "subcategory":"Construction",
            "type":"Services"
        }
    ],
    "sg:phone":"+1 731 632 1900",
    "sg:postcode":"38310",
    "sg:province":"TN",
    "sg:tags":[
        "asphalt",
        "mfg"
    ],
    "wof:name":"Jones Bros Inc",
    "wof:placetype":"venue"
},
  "geometry": {"coordinates":[-88.403503,35.203584],"type":"Point"}
}