{
  "type": "Feature",
  "properties": {
    "iso:country":"US",
    "sg:address":"342 Troy Cir SW",
    "sg:city":"Knoxville",
    "sg:classifiers":[
        {
            "category":"Arts & Performance",
            "subcategory":"Theater",
            "type":"Entertainment"
        }
    ],
    "sg:phone":"+1 865 588 9848",
    "sg:postcode":"37919",
    "sg:province":"TN",
    "sg:tags":[
        "theatrical"
    ],
    "wof:name":"Thunderroad Production Svcs",
    "wof:placetype":"venue"
},
  "geometry": {"coordinates":[-84.00476500000001,35.927706],"type":"Point"}
}