{
  "type": "Feature",
  "properties": {
    "iso:country":"US",
    "sg:address":"607 Beechcroft Rd",
    "sg:city":"Spring Hill",
    "sg:phone":"+1 931 486 1161",
    "sg:postcode":"37174",
    "sg:province":"TN",
    "sg:tags":[
        "partition"
    ],
    "wof:name":"John W Mc Dougall Co",
    "wof:placetype":"venue"
},
  "geometry": {"coordinates":[-86.954013,35.752719],"type":"Point"}
}