{
  "type": "Feature",
  "properties": {
    "addr:full":"2517 Knob Creek Rd Johnson City TN 37604",
    "addr:housenumber":"2517",
    "addr:postcode":"37604",
    "addr:street":"Knob Creek Rd",
    "iso:country":"US",
    "sg:address":"2517 Knob Creek Rd",
    "sg:city":"Johnson City",
    "sg:classifiers":[
        {
            "category":"Professional",
            "subcategory":"Employment Agencies",
            "type":"Services"
        }
    ],
    "sg:phone":"+1 423 283 0360",
    "sg:postcode":"37604",
    "sg:province":"TN",
    "sg:tags":[
        "opportunity"
    ],
    "wof:name":"Atwork Personnel Svc",
    "wof:placetype":"venue"
},
  "geometry": {"coordinates":[-82.405479,36.342167],"type":"Point"}
}