{
  "type": "Feature",
  "properties": {
    "iso:country":"US",
    "sg:address":"2403 W Main St",
    "sg:city":"Union City",
    "sg:classifiers":[
        {
            "category":"Wholesale",
            "subcategory":"Machinery & Supplies",
            "type":"Manufacturing & Wholesale Goods"
        }
    ],
    "sg:phone":"+1 731 884 2868",
    "sg:postcode":"38261",
    "sg:province":"TN",
    "sg:tags":[
        "equipment",
        "welding"
    ],
    "wof:name":"Airgas Mid-South",
    "wof:placetype":"venue"
},
  "geometry": {"coordinates":[-89.087037,36.434911],"type":"Point"}
}