{
  "type": "Feature",
  "properties": {
    "iso:country":"US",
    "sg:address":"427 Park Village Rd",
    "sg:city":"Knoxville",
    "sg:classifiers":[
        {
            "category":"Manufacturing",
            "subcategory":"Food",
            "type":"Manufacturing & Wholesale Goods"
        }
    ],
    "sg:phone":"+1 865 690 4961",
    "sg:postcode":"37923",
    "sg:province":"TN",
    "sg:tags":[
        "mfg",
        "potato"
    ],
    "wof:name":"Keebler",
    "wof:placetype":"venue"
},
  "geometry": {"coordinates":[-84.08722,35.924039],"type":"Point"}
}