{
  "type": "Feature",
  "properties": {
    "iso:country":"US",
    "sg:address":"9041 Executive Park Dr",
    "sg:city":"Knoxville",
    "sg:classifiers":[
        {
            "category":"Professional",
            "subcategory":"Business Services",
            "type":"Services"
        }
    ],
    "sg:phone":"+1 865 546 2700",
    "sg:postcode":"37923",
    "sg:province":"TN",
    "sg:tags":[
        "appraiser"
    ],
    "sg:website":"www.holmesappraisals.com",
    "wof:name":"Holmes Appraisals",
    "wof:placetype":"venue"
},
  "geometry": {"coordinates":[-84.080641,35.922256],"type":"Point"}
}