{
  "type": "Feature",
  "properties": {
    "addr:full":"307 W Main St Livingston TN 38570",
    "addr:housenumber":"307",
    "addr:postcode":"38570",
    "addr:street":"W Main St",
    "iso:country":"US",
    "sg:address":"307 W Main St",
    "sg:city":"Livingston",
    "sg:classifiers":[
        {
            "category":"Professional",
            "subcategory":"Business Services",
            "type":"Services"
        }
    ],
    "sg:phone":"+1 931 403 2663",
    "sg:postcode":"38570",
    "sg:province":"TN",
    "wof:name":"Free Bird Bonding Co",
    "wof:placetype":"venue"
},
  "geometry": {"coordinates":[-85.324106,36.382745],"type":"Point"}
}