{
  "type": "Feature",
  "properties": {
    "iso:country":"US",
    "sg:address":"105 Bonnabrook Dr",
    "sg:city":"Hermitage",
    "sg:classifiers":[
        {
            "category":"Professional",
            "subcategory":"Research",
            "type":"Services"
        }
    ],
    "sg:phone":"+1 615 885 7432",
    "sg:postcode":"37076",
    "sg:province":"TN",
    "sg:tags":[
        "commercial",
        "physical"
    ],
    "wof:name":"P V & S",
    "wof:placetype":"venue"
},
  "geometry": {"coordinates":[-86.626474,36.192557],"type":"Point"}
}