{
  "type": "Feature",
  "properties": {
    "iso:country":"US",
    "sg:address":"2801 Columbine Pl",
    "sg:city":"Nashville",
    "sg:classifiers":[
        {
            "category":"Professional",
            "subcategory":"Lawyer & Legal Services",
            "type":"Services"
        }
    ],
    "sg:phone":"+1 615 783 0107",
    "sg:postcode":"37204",
    "sg:province":"TN",
    "sg:tags":[
        "attorney"
    ],
    "wof:name":"Steve Holzapfel",
    "wof:placetype":"venue"
},
  "geometry": {"coordinates":[-86.765473,36.115266],"type":"Point"}
}