{
  "type": "Feature",
  "properties": {
    "addr:full":"2400 Crestmoor Rd Nashville TN 37215",
    "addr:housenumber":"2400",
    "addr:postcode":"37215",
    "addr:street":"Crestmoor Rd",
    "iso:country":"US",
    "sg:address":"2400 Crestmoor Rd",
    "sg:city":"Nashville",
    "sg:classifiers":[
        {
            "category":"Restaurant",
            "type":"Food & Drink"
        }
    ],
    "sg:phone":"+1 615 386 7107",
    "sg:postcode":"37215",
    "sg:province":"TN",
    "sg:tags":[
        "parlor",
        "ice",
        "cream"
    ],
    "wof:name":"Dairy Queen",
    "wof:placetype":"venue"
},
  "geometry": {"coordinates":[-86.819481,36.109943],"type":"Point"}
}