{
  "type": "Feature",
  "properties": {
    "iso:country":"US",
    "sg:address":"1843 W Dumplin Valley Rd",
    "sg:city":"New Market",
    "sg:classifiers":[
        {
            "category":"Organizations",
            "subcategory":"Religious Organization",
            "type":"Services"
        }
    ],
    "sg:phone":"+1 865 397 2048",
    "sg:postcode":"37820",
    "sg:province":"TN",
    "wof:name":"Dumplin Baptist Church",
    "wof:placetype":"venue"
},
  "geometry": {"coordinates":[-83.558849,36.005214],"type":"Point"}
}