{
  "type": "Feature",
  "properties": {
    "iso:country":"US",
    "sg:address":"1619 Rossville Ave",
    "sg:city":"Chattanooga",
    "sg:classifiers":[
        {
            "category":"Manufacturing",
            "subcategory":"Apparel",
            "type":"Manufacturing & Wholesale Goods"
        }
    ],
    "sg:phone":"+1 423 267 1603",
    "sg:postcode":"37408",
    "sg:province":"TN",
    "sg:tags":[
        "textile",
        "product",
        "fabricated",
        "mfg"
    ],
    "wof:name":"Sunrider Supply Co",
    "wof:placetype":"venue"
},
  "geometry": {"coordinates":[-85.30487100000001,35.034301],"type":"Point"}
}