{
  "type": "Feature",
  "properties": {
    "iso:country":"US",
    "sg:address":"1589 Sparta St",
    "sg:city":"Mc Minnville",
    "sg:classifiers":[
        {
            "category":"Health Services",
            "subcategory":"Doctor",
            "type":"Services"
        }
    ],
    "sg:phone":"+1 931 815 9395",
    "sg:postcode":"37110",
    "sg:province":"TN",
    "sg:tags":[
        "physician",
        "surgeon"
    ],
    "wof:name":"Mc Minnville Pulmonary Med",
    "wof:placetype":"venue"
},
  "geometry": {"coordinates":[-85.74105900000001,35.69989],"type":"Point"}
}