{
  "type": "Feature",
  "properties": {
    "iso:country":"US",
    "sg:address":"5512 Ringgold Rd",
    "sg:city":"Chattanooga",
    "sg:classifiers":[
        {
            "category":"Communications",
            "subcategory":"Radio Station",
            "type":"Services"
        }
    ],
    "sg:phone":"+1 423 892 5172",
    "sg:postcode":"37412",
    "sg:province":"TN",
    "sg:tags":[
        "broadcast"
    ],
    "wof:name":"103 Request Line",
    "wof:placetype":"venue"
},
  "geometry": {"coordinates":[-85.227256,34.992447],"type":"Point"}
}