{
  "type": "Feature",
  "properties": {
    "addr:full":"2107 Chapman Hwy Knoxville TN 37920",
    "addr:housenumber":"2107",
    "addr:postcode":"37920",
    "addr:street":"Chapman Hwy",
    "iso:country":"US",
    "sg:address":"2107 Chapman Hwy",
    "sg:city":"Knoxville",
    "sg:classifiers":[
        {
            "category":"Autos & Motor Vehicles",
            "subcategory":"Fuel & Gas Station",
            "type":"Retail Goods"
        }
    ],
    "sg:phone":"+1 865 573 0629",
    "sg:postcode":"37920",
    "sg:province":"TN",
    "sg:tags":[
        "grocery",
        "station",
        "gasoline"
    ],
    "wof:name":"Amoco",
    "wof:placetype":"venue"
},
  "geometry": {"coordinates":[-83.915738,35.953339],"type":"Point"}
}