{
  "type": "Feature",
  "properties": {
    "addr:full":"2104 W Emory Rd Powell TN 37849",
    "addr:housenumber":"2104",
    "addr:postcode":"37849",
    "addr:street":"W Emory Rd",
    "iso:country":"US",
    "sg:address":"2104 W Emory Rd",
    "sg:city":"Powell",
    "sg:classifiers":[
        {
            "category":"Wholesale",
            "subcategory":"Machinery & Supplies",
            "type":"Manufacturing & Wholesale Goods"
        }
    ],
    "sg:phone":"+1 865 938 2076",
    "sg:postcode":"37849",
    "sg:province":"TN",
    "sg:tags":[
        "industrial"
    ],
    "wof:name":"Buds Mobile Home RPS & Svc",
    "wof:placetype":"venue"
},
  "geometry": {"coordinates":[-84.02999,36.029922],"type":"Point"}
}