{
  "type": "Feature",
  "properties": {
    "iso:country":"US",
    "sg:address":"9490 State Rte 22A S",
    "sg:city":"Enville",
    "sg:phone":"+1 731 688 5221",
    "sg:postcode":"38332",
    "sg:province":"TN",
    "sg:tags":[
        "farm",
        "soybean"
    ],
    "wof:name":"Oneal Farm",
    "wof:placetype":"venue"
},
  "geometry": {"coordinates":[-88.406409,35.385099],"type":"Point"}
}