{
  "type": "Feature",
  "properties": {
    "iso:country":"US",
    "sg:address":"520 E Iris Dr",
    "sg:city":"Nashville",
    "sg:classifiers":[
        {
            "category":"Social Services",
            "subcategory":"Child Care",
            "type":"Services"
        }
    ],
    "sg:phone":"+1 615 383 8845",
    "sg:postcode":"37204",
    "sg:province":"TN",
    "sg:tags":[
        "day"
    ],
    "wof:name":"Child Sensitive Communications",
    "wof:placetype":"venue"
},
  "geometry": {"coordinates":[-86.76402899999999,36.11529],"type":"Point"}
}