{
  "type": "Feature",
  "properties": {
    "iso:country":"US",
    "sg:address":"11606 Memphis Arlington Rd",
    "sg:city":"Arlington",
    "sg:classifiers":[
        {
            "category":"Manufacturing",
            "subcategory":"Tools & Machinery",
            "type":"Manufacturing & Wholesale Goods"
        }
    ],
    "sg:phone":"+1 901 867 7854",
    "sg:postcode":"38002",
    "sg:province":"TN",
    "wof:name":"Click Industries",
    "wof:placetype":"venue"
},
  "geometry": {"coordinates":[-89.675844,35.282396],"type":"Point"}
}