{
  "type": "Feature",
  "properties": {
    "iso:country":"US",
    "sg:address":"730 N Broadway St",
    "sg:city":"Knoxville",
    "sg:classifiers":[
        {
            "category":"Manufacturing",
            "subcategory":"Printing",
            "type":"Manufacturing & Wholesale Goods"
        }
    ],
    "sg:phone":"+1 865 525 0192",
    "sg:postcode":"37917",
    "sg:province":"TN",
    "sg:tags":[
        "commercial",
        "lithographic"
    ],
    "sg:website":"www.knoxvilleprinters.com",
    "wof:name":"Knoxville Printers & Publisher",
    "wof:placetype":"venue"
},
  "geometry": {"coordinates":[-83.92352700000001,35.97739],"type":"Point"}
}