{
  "type": "Feature",
  "properties": {
    "iso:country":"US",
    "sg:address":"4010 E Holmes Rd",
    "sg:city":"Memphis",
    "sg:classifiers":[
        {
            "category":"Professional",
            "type":"Services"
        }
    ],
    "sg:phone":"+1 901 363 7557",
    "sg:postcode":"38118",
    "sg:province":"TN",
    "sg:tags":[
        "establishment"
    ],
    "wof:name":"Sig Net 6",
    "wof:placetype":"venue"
},
  "geometry": {"coordinates":[-89.925569,35.006134],"type":"Point"}
}