{
  "type": "Feature",
  "properties": {
    "addr:full":"200 Roma Dr Crossville TN 38555",
    "addr:housenumber":"200",
    "addr:postcode":"38555",
    "addr:street":"Roma Dr",
    "iso:country":"US",
    "sg:address":"200 Roma Dr",
    "sg:city":"Crossville",
    "sg:classifiers":[
        {
            "category":"Mining & Drilling",
            "type":"Manufacturing & Wholesale Goods"
        }
    ],
    "sg:phone":"+1 931 484 6172",
    "sg:postcode":"38555",
    "sg:province":"TN",
    "sg:tags":[
        "perforating",
        "well",
        "oil",
        "logging"
    ],
    "wof:name":"Well Services Inc",
    "wof:placetype":"venue"
},
  "geometry": {"coordinates":[-85.040453,35.916585],"type":"Point"}
}