{
  "type": "Feature",
  "properties": {
    "addr:full":"10228 Technology Dr Knoxville TN 37932",
    "addr:housenumber":"10228",
    "addr:postcode":"37932",
    "addr:street":"Technology Dr",
    "iso:country":"US",
    "sg:address":"10228 Technology Dr",
    "sg:city":"Knoxville",
    "sg:classifiers":[
        {
            "category":"Professional",
            "subcategory":"Art Services",
            "type":"Services"
        }
    ],
    "sg:phone":"+1 865 675 6277",
    "sg:postcode":"37932",
    "sg:province":"TN",
    "sg:tags":[
        "map",
        "transit",
        "other",
        "design",
        "directional"
    ],
    "wof:name":"Smartmaps Inc",
    "wof:placetype":"venue"
},
  "geometry": {"coordinates":[-84.128056,35.919698],"type":"Point"}
}