{
  "type": "Feature",
  "properties": {
    "addr:full":"1336 Ryanwood Ave Memphis TN 38116",
    "addr:housenumber":"1336",
    "addr:postcode":"38116",
    "addr:street":"Ryanwood Ave",
    "iso:country":"US",
    "sg:address":"1336 Ryanwood Ave",
    "sg:city":"Memphis",
    "sg:classifiers":[
        {
            "category":"Professional",
            "subcategory":"Business Services",
            "type":"Services"
        }
    ],
    "sg:phone":"+1 901 398 0474",
    "sg:postcode":"38116",
    "sg:province":"TN",
    "wof:name":"Michael & Assoc CU",
    "wof:placetype":"venue"
},
  "geometry": {"coordinates":[-90.0213,34.998525],"type":"Point"}
}