{
  "type": "Feature",
  "properties": {
    "iso:country":"US",
    "sg:address":"1770 Kirby Pkwy",
    "sg:city":"Germantown",
    "sg:classifiers":[
        {
            "category":"Banks & Credit Unions",
            "subcategory":"Bank",
            "type":"Services"
        }
    ],
    "sg:phone":"+1 901 754 4475",
    "sg:postcode":"38120",
    "sg:province":"TN",
    "sg:tags":[
        "loan",
        "real estate"
    ],
    "wof:name":"GMAC Mortgage",
    "wof:placetype":"venue"
},
  "geometry": {"coordinates":[-89.839106,35.100451],"type":"Point"}
}