{
  "type": "Feature",
  "properties": {
    "iso:country":"US",
    "sg:address":"6708 Deane Hill Dr",
    "sg:city":"Knoxville",
    "sg:classifiers":[
        {
            "category":"Retail",
            "subcategory":"Laundry & Dry Cleaning",
            "type":"Services"
        }
    ],
    "sg:phone":"+1 865 691 9585",
    "sg:postcode":"37919",
    "sg:province":"TN",
    "wof:name":"Alterations Sales Etc",
    "wof:placetype":"venue"
},
  "geometry": {"coordinates":[-84.013846,35.928274],"type":"Point"}
}