{
  "type": "Feature",
  "properties": {
    "iso:country":"US",
    "sg:address":"305 1st Ave SE",
    "sg:city":"Winchester",
    "sg:classifiers":[
        {
            "category":"Real Estate",
            "subcategory":"Real Estate Services",
            "type":"Services"
        }
    ],
    "sg:phone":"+1 931 967 6100",
    "sg:postcode":"37398",
    "sg:province":"TN",
    "sg:tags":[
        "company",
        "title"
    ],
    "wof:name":"Sovereign Title & Escrow Co",
    "wof:placetype":"venue"
},
  "geometry": {"coordinates":[-86.109424,35.187656],"type":"Point"}
}