{
  "type": "Feature",
  "properties": {
    "iso:country":"US",
    "sg:address":"1407 E 5th Ave",
    "sg:city":"Knoxville",
    "sg:classifiers":[
        {
            "category":"Social Services",
            "type":"Services"
        }
    ],
    "sg:phone":"+1 865 522 4991",
    "sg:postcode":"37917",
    "sg:province":"TN",
    "sg:tags":[
        "organization",
        "welfare"
    ],
    "sg:website":"www.efeasttn.org",
    "wof:name":"Epilepsy Foundation Of E Tenn",
    "wof:placetype":"venue"
},
  "geometry": {"coordinates":[-83.910619,35.979043],"type":"Point"}
}