{
  "type": "Feature",
  "properties": {
    "iso:country":"US",
    "sg:address":"8920 Transport Ln",
    "sg:city":"Ooltewah",
    "sg:classifiers":[
        {
            "category":"Professional",
            "subcategory":"Management & Consulting",
            "type":"Services"
        }
    ],
    "sg:phone":"+1 423 238 5184",
    "sg:postcode":"37363",
    "sg:province":"TN",
    "sg:tags":[
        "financial"
    ],
    "wof:name":"Ach Commerce LLC",
    "wof:placetype":"venue"
},
  "geometry": {"coordinates":[-85.054643,35.104999],"type":"Point"}
}