{
  "type": "Feature",
  "properties": {
    "iso:country":"US",
    "sg:address":"528 Titan Ct",
    "sg:city":"Antioch",
    "sg:classifiers":[
        {
            "category":"Wholesale",
            "subcategory":"Toys & Hobbies",
            "type":"Manufacturing & Wholesale Goods"
        }
    ],
    "sg:phone":"+1 615 367 2771",
    "sg:postcode":"37013",
    "sg:province":"TN",
    "sg:tags":[
        "wholesaler"
    ],
    "wof:name":"G & M Wholesale",
    "wof:placetype":"venue"
},
  "geometry": {"coordinates":[-86.651408,36.085633],"type":"Point"}
}