{
  "type": "Feature",
  "properties": {
    "addr:full":"728 State Hwy 114 S Scotts Hill TN 38374",
    "addr:housenumber":"728",
    "addr:postcode":"38374",
    "addr:street":"State Hwy 114 S",
    "iso:country":"US",
    "sg:address":"728 State Hwy 114 S",
    "sg:city":"Scotts Hill",
    "sg:classifiers":[
        {
            "category":"Shopping",
            "subcategory":"Discount & Variety Stores",
            "type":"Retail Goods"
        }
    ],
    "sg:phone":"+1 731 549 2324",
    "sg:postcode":"38374",
    "sg:province":"TN",
    "wof:name":"Dollar General",
    "wof:placetype":"venue"
},
  "geometry": {"coordinates":[-88.250524,35.522882],"type":"Point"}
}