{
  "type": "Feature",
  "properties": {
    "iso:country":"US",
    "sg:address":"5353 Stuffel Rd",
    "sg:city":"Morristown",
    "sg:classifiers":[
        {
            "category":"Social Services",
            "subcategory":"Child Care",
            "type":"Services"
        }
    ],
    "sg:phone":"+1 423 587 9198",
    "sg:postcode":"37814",
    "sg:province":"TN",
    "sg:tags":[
        "day"
    ],
    "wof:name":"Dearings Family Care",
    "wof:placetype":"venue"
},
  "geometry": {"coordinates":[-83.23781700000001,36.262892],"type":"Point"}
}