{
  "type": "Feature",
  "properties": {
    "iso:country":"US",
    "sg:address":"153 Cedar Valley Rd",
    "sg:city":"Rogersville",
    "sg:classifiers":[
        {
            "category":"Wholesale",
            "subcategory":"Non-durable Goods",
            "type":"Manufacturing & Wholesale Goods"
        }
    ],
    "sg:phone":"+1 423 272 5093",
    "sg:postcode":"37857",
    "sg:province":"TN",
    "wof:name":"Wild Plum Hollow",
    "wof:placetype":"venue"
},
  "geometry": {"coordinates":[-83.043443,36.422383],"type":"Point"}
}