{
  "type": "Feature",
  "properties": {
    "iso:country":"US",
    "sg:address":"2321 N Meridian St",
    "sg:city":"Greenfield",
    "sg:classifiers":[
        {
            "category":"Shopping",
            "type":"Retail Goods"
        }
    ],
    "sg:phone":"+1 731 235 2293",
    "sg:postcode":"38230",
    "sg:province":"TN",
    "sg:tags":[
        "monument"
    ],
    "wof:name":"Greenfield Monument Works",
    "wof:placetype":"venue"
},
  "geometry": {"coordinates":[-88.803532,36.163059],"type":"Point"}
}