{
  "type": "Feature",
  "properties": {
    "addr:full":"808 Kirkwood Ave Nashville TN 37204",
    "addr:housenumber":"808",
    "addr:postcode":"37204",
    "addr:street":"Kirkwood Ave",
    "iso:country":"US",
    "sg:address":"808 Kirkwood Ave",
    "sg:city":"Nashville",
    "sg:classifiers":[
        {
            "category":"Health Services",
            "subcategory":"Doctor",
            "type":"Services"
        }
    ],
    "sg:phone":"+1 615 385 9744",
    "sg:postcode":"37204",
    "sg:province":"TN",
    "sg:tags":[
        "dentist"
    ],
    "wof:name":"All Care Dentistry",
    "wof:placetype":"venue"
},
  "geometry": {"coordinates":[-86.778336,36.121042],"type":"Point"}
}