{
  "type": "Feature",
  "properties": {
    "iso:country":"US",
    "sg:address":"732 Co Rd 130",
    "sg:city":"Athens",
    "sg:classifiers":[
        {
            "category":"Building & Trades",
            "subcategory":"Construction",
            "type":"Services"
        }
    ],
    "sg:phone":"+1 423 745 4067",
    "sg:postcode":"37303",
    "sg:province":"TN",
    "sg:tags":[
        "house"
    ],
    "wof:name":"Freeman Remodeling",
    "wof:placetype":"venue"
},
  "geometry": {"coordinates":[-84.685121,35.440197],"type":"Point"}
}