{
  "type": "Feature",
  "properties": {
    "iso:country":"US",
    "sg:address":"445 W Commerce St",
    "sg:city":"Lewisburg",
    "sg:classifiers":[
        {
            "category":"Food & Beverages",
            "subcategory":"Liquor & Beverages",
            "type":"Retail Goods"
        }
    ],
    "sg:phone":"+1 931 359 2397",
    "sg:postcode":"37091",
    "sg:province":"TN",
    "sg:tags":[
        "store"
    ],
    "wof:name":"West Side Liquor Store",
    "wof:placetype":"venue"
},
  "geometry": {"coordinates":[-86.79262199999999,35.449308],"type":"Point"}
}