{
  "type": "Feature",
  "properties": {
    "iso:country":"US",
    "sg:address":"1050 S Mount Juliet Rd",
    "sg:city":"Mt Juliet",
    "sg:classifiers":[
        {
            "category":"Building & Trades",
            "subcategory":"Construction",
            "type":"Services"
        }
    ],
    "sg:phone":"+1 615 754 6062",
    "sg:postcode":"37122",
    "sg:province":"TN",
    "sg:tags":[
        "home",
        "builder"
    ],
    "wof:name":"Fox Ridge Homes Inc",
    "wof:placetype":"venue"
},
  "geometry": {"coordinates":[-86.516153,36.156367],"type":"Point"}
}