{
  "type": "Feature",
  "properties": {
    "addr:full":"1500 Broadway Rd N Lexington TN 38351",
    "addr:housenumber":"1500",
    "addr:postcode":"38351",
    "addr:street":"Broadway Rd N",
    "iso:country":"US",
    "sg:address":"1500 Broadway Rd N",
    "sg:city":"Lexington",
    "sg:classifiers":[
        {
            "category":"Autos & Motor Vehicles",
            "subcategory":"Automobile Sales",
            "type":"Retail Goods"
        }
    ],
    "sg:phone":"+1 731 968 3321",
    "sg:postcode":"38351",
    "sg:province":"TN",
    "sg:tags":[
        "car",
        "dealer"
    ],
    "wof:name":"Rickett's Used Cars",
    "wof:placetype":"venue"
},
  "geometry": {"coordinates":[-88.46516699999999,35.655123],"type":"Point"}
}