{
  "type": "Feature",
  "properties": {
    "iso:country":"US",
    "sg:address":"434 Ikard Ln",
    "sg:city":"Decherd",
    "sg:classifiers":[
        {
            "category":"Manufacturing",
            "subcategory":"Glass & Minerals",
            "type":"Manufacturing & Wholesale Goods"
        }
    ],
    "sg:phone":"+1 931 967 6278",
    "sg:postcode":"37324",
    "sg:province":"TN",
    "sg:tags":[
        "product",
        "nonmetallic",
        "mfg"
    ],
    "wof:name":"Flogiston Foundry",
    "wof:placetype":"venue"
},
  "geometry": {"coordinates":[-85.92186,35.269938],"type":"Point"}
}