{
  "type": "Feature",
  "properties": {
    "iso:country":"US",
    "sg:address":"2400 Elvis Presley Blvd",
    "sg:city":"Memphis",
    "sg:classifiers":[
        {
            "category":"Retail",
            "subcategory":"Auto Repair",
            "type":"Services"
        }
    ],
    "sg:phone":"+1 901 774 8588",
    "sg:postcode":"38106",
    "sg:province":"TN",
    "sg:tags":[
        "general"
    ],
    "wof:name":"Quality Automotive Svc",
    "wof:placetype":"venue"
},
  "geometry": {"coordinates":[-90.01936000000001,35.078405],"type":"Point"}
}