{
  "type": "Feature",
  "properties": {
    "addr:full":"5210 Brainerd Rd Chattanooga TN 37411",
    "addr:postcode":"5210;37411",
    "addr:street":"Brainerd Rd",
    "iso:country":"US",
    "sg:address":"5210 Brainerd Rd",
    "sg:city":"Chattanooga",
    "sg:classifiers":[
        {
            "category":"Banks & Credit Unions",
            "subcategory":"Bank",
            "type":"Services"
        }
    ],
    "sg:phone":"+1 423 296 0415",
    "sg:postcode":"37411",
    "sg:province":"TN",
    "sg:tags":[
        "institution",
        "business"
    ],
    "wof:name":"Credit Central Inc",
    "wof:placetype":"venue"
},
  "geometry": {"coordinates":[-85.224667,35.01146],"type":"Point"}
}