{
  "type": "Feature",
  "properties": {
    "iso:country":"US",
    "sg:address":"1119 Davis Ave",
    "sg:city":"Morristown",
    "sg:classifiers":[
        {
            "category":"Organizations",
            "subcategory":"Religious Organization",
            "type":"Services"
        }
    ],
    "sg:phone":"+1 423 581 1115",
    "sg:postcode":"37814",
    "sg:province":"TN",
    "wof:name":"Abundant Life Church",
    "wof:placetype":"venue"
},
  "geometry": {"coordinates":[-83.295697,36.226231],"type":"Point"}
}