{
  "type": "Feature",
  "properties": {
    "addr:full":"5520 State Hwy 104 W Finley TN 38030",
    "addr:housenumber":"5520",
    "addr:postcode":"38030",
    "addr:street":"State Hwy 104 W",
    "iso:country":"US",
    "sg:address":"5520 State Hwy 104 W",
    "sg:city":"Finley",
    "sg:classifiers":[
        {
            "category":"Government",
            "subcategory":"Post Office",
            "type":"Public Place"
        }
    ],
    "sg:phone":"+1 731 285 8814",
    "sg:postcode":"38030",
    "sg:province":"TN",
    "wof:name":"US Post Office",
    "wof:placetype":"venue"
},
  "geometry": {"coordinates":[-89.48057900000001,36.035892],"type":"Point"}
}