{
  "type": "Feature",
  "properties": {
    "iso:country":"US",
    "sg:address":"1852 Lively Rd",
    "sg:city":"Maryville",
    "sg:classifiers":[
        {
            "category":"Professional",
            "subcategory":"Computer Services",
            "type":"Services"
        }
    ],
    "sg:phone":"+1 865 982 7628",
    "sg:postcode":"37801",
    "sg:province":"TN",
    "sg:tags":[
        "consultant",
        "designer"
    ],
    "wof:name":"Renegade Computer Systems",
    "wof:placetype":"venue"
},
  "geometry": {"coordinates":[-84.017397,35.7821],"type":"Point"}
}