{
  "type": "Feature",
  "properties": {
    "iso:country":"US",
    "sg:address":"212 S Main St",
    "sg:city":"Medina",
    "sg:classifiers":[
        {
            "category":"Food & Beverages",
            "subcategory":"Groceries & Convenience Stores",
            "type":"Retail Goods"
        }
    ],
    "sg:phone":"+1 731 783 0305",
    "sg:postcode":"38355",
    "sg:province":"TN",
    "wof:name":"Oasis Food Store",
    "wof:placetype":"venue"
},
  "geometry": {"coordinates":[-88.777179,35.80022],"type":"Point"}
}