{
  "type": "Feature",
  "properties": {
    "iso:country":"US",
    "sg:address":"129 Industrial Park Cir",
    "sg:city":"Livingston",
    "sg:classifiers":[
        {
            "category":"Mining & Drilling",
            "type":"Manufacturing & Wholesale Goods"
        }
    ],
    "sg:phone":"+1 931 403 2673",
    "sg:postcode":"38570",
    "sg:province":"TN",
    "sg:tags":[
        "extraction",
        "oil",
        "gas"
    ],
    "wof:name":"Basin Oil & Gas Corporation",
    "wof:placetype":"venue"
},
  "geometry": {"coordinates":[-85.331316,36.353232],"type":"Point"}
}