{
  "type": "Feature",
  "properties": {
    "iso:country":"US",
    "sg:address":"2007 E 27th St",
    "sg:city":"Chattanooga",
    "sg:classifiers":[
        {
            "category":"Organizations",
            "subcategory":"Religious Organization",
            "type":"Services"
        }
    ],
    "sg:phone":"+1 423 629 5821",
    "sg:postcode":"37407",
    "sg:province":"TN",
    "sg:tags":[
        "church"
    ],
    "wof:name":"Edgewood Baptist Church",
    "wof:placetype":"venue"
},
  "geometry": {"coordinates":[-85.28494600000001,35.012987],"type":"Point"}
}