{
  "type": "Feature",
  "properties": {
    "addr:full":"2525 Ashwood Ave Nashville TN 37212",
    "addr:housenumber":"2525",
    "addr:postcode":"37212",
    "addr:street":"Ashwood Ave",
    "iso:country":"US",
    "sg:address":"2525 Ashwood Ave",
    "sg:city":"Nashville",
    "sg:classifiers":[
        {
            "category":"Building & Trades",
            "subcategory":"Construction",
            "type":"Services"
        }
    ],
    "sg:phone":"+1 615 491 3403",
    "sg:postcode":"37212",
    "sg:province":"TN",
    "sg:tags":[
        "maker",
        "cabinet"
    ],
    "wof:name":"Carpenter's Shop",
    "wof:placetype":"venue"
},
  "geometry": {"coordinates":[-86.808995,36.130073],"type":"Point"}
}