{
  "type": "Feature",
  "properties": {
    "iso:country":"US",
    "sg:address":"4070 Elvis Presley Blvd",
    "sg:city":"Memphis",
    "sg:classifiers":[
        {
            "category":"Shopping",
            "subcategory":"Clothing, Apparel, & Fashions",
            "type":"Retail Goods"
        }
    ],
    "sg:phone":"+1 901 332 8722",
    "sg:postcode":"38116",
    "sg:province":"TN",
    "sg:tags":[
        "wear"
    ],
    "wof:name":"Martys Mens Store 3",
    "wof:placetype":"venue"
},
  "geometry": {"coordinates":[-90.025062,35.03848],"type":"Point"}
}