{
  "type": "Feature",
  "properties": {
    "addr:full":"885 Barron Rd Lewisburg TN 37091",
    "addr:housenumber":"885",
    "addr:postcode":"37091",
    "addr:street":"Barron Rd",
    "iso:country":"US",
    "sg:address":"885 Barron Rd",
    "sg:city":"Lewisburg",
    "sg:classifiers":[
        {
            "category":"Sports & Exercise",
            "subcategory":"Bowling",
            "type":"Entertainment"
        }
    ],
    "sg:phone":"+1 931 359 5449",
    "sg:postcode":"37091",
    "sg:province":"TN",
    "sg:tags":[
        "organization",
        "membership",
        "center"
    ],
    "wof:name":"Lewisburg Tenn Womens Bowling",
    "wof:placetype":"venue"
},
  "geometry": {"coordinates":[-86.805538,35.434522],"type":"Point"}
}