{
  "type": "Feature",
  "properties": {
    "iso:country":"US",
    "sg:address":"4801 N Broadway St",
    "sg:city":"Knoxville",
    "sg:classifiers":[
        {
            "category":"Food & Beverages",
            "subcategory":"Groceries & Convenience Stores",
            "type":"Retail Goods"
        }
    ],
    "sg:phone":"+1 865 688 6843",
    "sg:postcode":"37918",
    "sg:province":"TN",
    "wof:name":"Mr Zip Inc Of Tennessee",
    "wof:placetype":"venue"
},
  "geometry": {"coordinates":[-83.927182,36.026026],"type":"Point"}
}