{
  "type": "Feature",
  "properties": {
    "iso:country":"US",
    "sg:address":"173 Revilo Rd",
    "sg:city":"Leoma",
    "sg:classifiers":[
        {
            "category":"Building & Trades",
            "subcategory":"Construction",
            "type":"Services"
        }
    ],
    "sg:phone":"+1 931 852 4743",
    "sg:postcode":"38468",
    "sg:province":"TN",
    "sg:tags":[
        "concrete",
        "contractor"
    ],
    "wof:name":"L & L Concrete",
    "wof:placetype":"venue"
},
  "geometry": {"coordinates":[-87.27063200000001,35.143666],"type":"Point"}
}