{
  "type": "Feature",
  "properties": {
    "addr:full":"3137 Old Knoxville Hwy Maryville TN 37804",
    "addr:housenumber":"3137",
    "addr:postcode":"37804",
    "addr:street":"Old Knoxville Hwy",
    "iso:country":"US",
    "sg:address":"3137 Old Knoxville Hwy",
    "sg:city":"Maryville",
    "sg:classifiers":[
        {
            "category":"Organizations",
            "subcategory":"Religious Organization",
            "type":"Services"
        }
    ],
    "sg:phone":"+1 865 982 5280",
    "sg:postcode":"37804",
    "sg:province":"TN",
    "sg:tags":[
        "church"
    ],
    "wof:name":"Clark's Grove Cumberland",
    "wof:placetype":"venue"
},
  "geometry": {"coordinates":[-83.940061,35.806456],"type":"Point"}
}