{
  "type": "Feature",
  "properties": {
    "iso:country":"US",
    "sg:address":"605 Cumberland Dr",
    "sg:city":"Clarksville",
    "sg:classifiers":[
        {
            "category":"Bars & Pubs",
            "type":"Food & Drink"
        }
    ],
    "sg:phone":"+1 931 648 1896",
    "sg:postcode":"37040",
    "sg:province":"TN",
    "sg:tags":[
        "drinking"
    ],
    "wof:name":"Jerry's Friendly Tavern",
    "wof:placetype":"venue"
},
  "geometry": {"coordinates":[-87.352205,36.521405],"type":"Point"}
}