{
  "type": "Feature",
  "properties": {
    "iso:country":"US",
    "sg:address":"4424 Old French Rd",
    "sg:city":"Knoxville",
    "sg:classifiers":[
        {
            "category":"Shopping",
            "subcategory":"Photographic Equipment",
            "type":"Retail Goods"
        }
    ],
    "sg:phone":"+1 865 573 2468",
    "sg:postcode":"37920",
    "sg:province":"TN",
    "sg:tags":[
        "supply"
    ],
    "wof:name":"Substrata Camera Svc Inc",
    "wof:placetype":"venue"
},
  "geometry": {"coordinates":[-83.802475,35.951233],"type":"Point"}
}