{
  "type": "Feature",
  "properties": {
    "addr:full":"173 Bennett Dr Johnson City TN 37615",
    "addr:housenumber":"173",
    "addr:postcode":"37615",
    "addr:street":"Bennett Dr",
    "iso:country":"US",
    "sg:address":"173 Bennett Dr",
    "sg:city":"Johnson City",
    "sg:classifiers":[
        {
            "category":"Building & Trades",
            "subcategory":"Construction",
            "type":"Services"
        }
    ],
    "sg:phone":"+1 423 913 1004",
    "sg:postcode":"37615",
    "sg:province":"TN",
    "sg:tags":[
        "home",
        "builder"
    ],
    "wof:name":"Customized Homes Plans",
    "wof:placetype":"venue"
},
  "geometry": {"coordinates":[-82.403704,36.41968],"type":"Point"}
}