{
  "type": "Feature",
  "properties": {
    "iso:country":"US",
    "sg:address":"119 Pedigo Rd",
    "sg:city":"Madisonville",
    "sg:classifiers":[
        {
            "category":"Health Services",
            "subcategory":"Clinic",
            "type":"Services"
        }
    ],
    "sg:phone":"+1 423 442 5280",
    "sg:postcode":"37354",
    "sg:province":"TN",
    "wof:name":"Cherokee Health Systems",
    "wof:placetype":"venue"
},
  "geometry": {"coordinates":[-84.337755,35.535414],"type":"Point"}
}