{
  "type": "Feature",
  "properties": {
    "iso:country":"US",
    "sg:address":"423 Tremont Dr",
    "sg:city":"Murfreesboro",
    "sg:classifiers":[
        {
            "category":"Personal",
            "type":"Services"
        },
        {
            "category":"Personal",
            "subcategory":"Beauty Salon",
            "type":"Services"
        }
    ],
    "sg:phone":"+1 615 890 1555",
    "sg:postcode":"37130",
    "sg:province":"TN",
    "sg:tags":[
        "shop",
        "electrolysis"
    ],
    "wof:name":"Andrea Ross Electrologist",
    "wof:placetype":"venue"
},
  "geometry": {"coordinates":[-86.385997,35.833634],"type":"Point"}
}