{
  "type": "Feature",
  "properties": {
    "iso:country":"US",
    "sg:address":"305 Seaboard Ln",
    "sg:city":"Franklin",
    "sg:classifiers":[
        {
            "category":"Manufacturing",
            "subcategory":"Printing",
            "type":"Manufacturing & Wholesale Goods"
        }
    ],
    "sg:phone":"+1 615 236 8728",
    "sg:postcode":"37067",
    "sg:province":"TN",
    "sg:tags":[
        "newspaper",
        "lithographic",
        "commercial"
    ],
    "wof:name":"U S A Today",
    "wof:placetype":"venue"
},
  "geometry": {"coordinates":[-86.831058,35.949299],"type":"Point"}
}