{
  "type": "Feature",
  "properties": {
    "addr:full":"8901 Bluegrass Rd Knoxville TN 37922",
    "addr:housenumber":"8901",
    "addr:postcode":"37922",
    "addr:street":"Bluegrass Rd",
    "iso:country":"US",
    "sg:address":"8901 Bluegrass Rd",
    "sg:city":"Knoxville",
    "sg:classifiers":[
        {
            "category":"Education",
            "subcategory":"School",
            "type":"Public Place"
        }
    ],
    "sg:phone":"+1 865 539 7864",
    "sg:postcode":"37922",
    "sg:province":"TN",
    "sg:website":"www.knoxcountyschools.com",
    "wof:name":"Bluegrass School",
    "wof:placetype":"venue"
},
  "geometry": {"coordinates":[-84.06563800000001,35.876377],"type":"Point"}
}