{
  "type": "Feature",
  "properties": {
    "iso:country":"US",
    "sg:address":"517 Cumberland St W",
    "sg:city":"Cowan",
    "sg:classifiers":[
        {
            "category":"Personal",
            "subcategory":"Beauty Salon",
            "type":"Services"
        }
    ],
    "sg:phone":"+1 931 967 1991",
    "sg:postcode":"37318",
    "sg:province":"TN",
    "wof:name":"Shear Class Hair Design",
    "wof:placetype":"venue"
},
  "geometry": {"coordinates":[-86.025165,35.161995],"type":"Point"}
}