{
  "type": "Feature",
  "properties": {
    "addr:full":"1917 Brookside Ln Kingsport TN 37660",
    "addr:housenumber":"1917",
    "addr:postcode":"37660",
    "addr:street":"Brookside Ln",
    "iso:country":"US",
    "sg:address":"1917 Brookside Ln",
    "sg:city":"Kingsport",
    "sg:classifiers":[
        {
            "category":"Home & Garden",
            "subcategory":"Building Materials",
            "type":"Retail Goods"
        }
    ],
    "sg:phone":"+1 423 245 4559",
    "sg:postcode":"37660",
    "sg:province":"TN",
    "sg:tags":[
        "glass",
        "window",
        "plate"
    ],
    "wof:name":"Freeman Glass Svc",
    "wof:placetype":"venue"
},
  "geometry": {"coordinates":[-82.517657,36.556138],"type":"Point"}
}