{
  "type": "Feature",
  "properties": {
    "addr:full":"631 Nuckolls Rd Bolivar TN 38008",
    "addr:housenumber":"631",
    "addr:postcode":"38008",
    "addr:street":"Nuckolls Rd",
    "iso:country":"US",
    "sg:address":"631 Nuckolls Rd",
    "sg:city":"Bolivar",
    "sg:classifiers":[
        {
            "category":"Social Services",
            "subcategory":"Adult Care",
            "type":"Services"
        }
    ],
    "sg:phone":"+1 731 658 3313",
    "sg:postcode":"38008",
    "sg:province":"TN",
    "sg:tags":[
        "home",
        "residential"
    ],
    "wof:name":"Bolivar Assisted Care Living",
    "wof:placetype":"venue"
},
  "geometry": {"coordinates":[-89.000772,35.264893],"type":"Point"}
}