{
  "type": "Feature",
  "properties": {
    "iso:country":"US",
    "sg:address":"1603 James Blvd",
    "sg:city":"Signal Mountain",
    "sg:classifiers":[
        {
            "category":"Wholesale",
            "subcategory":"Durable Goods & Equipment",
            "type":"Manufacturing & Wholesale Goods"
        }
    ],
    "sg:phone":"+1 423 886 5577",
    "sg:postcode":"37377",
    "sg:province":"TN",
    "sg:tags":[
        "representative",
        "manufacturer"
    ],
    "wof:name":"G B Sisson Co",
    "wof:placetype":"venue"
},
  "geometry": {"coordinates":[-85.324548,35.147113],"type":"Point"}
}