{
  "type": "Feature",
  "properties": {
    "iso:country":"US",
    "sg:address":"2541 Georgetown Rd NW",
    "sg:city":"Cleveland",
    "sg:classifiers":[
        {
            "category":"Shopping",
            "subcategory":"Florist",
            "type":"Retail Goods"
        }
    ],
    "sg:phone":"+1 423 476 7524",
    "sg:postcode":"37311",
    "sg:province":"TN",
    "wof:name":"Jones Flower Shop",
    "wof:placetype":"venue"
},
  "geometry": {"coordinates":[-84.88535,35.190931],"type":"Point"}
}