{
  "type": "Feature",
  "properties": {
    "iso:country":"US",
    "sg:address":"735 Broad St",
    "sg:city":"Chattanooga",
    "sg:classifiers":[
        {
            "category":"Insurance",
            "subcategory":"Insurance Agent",
            "type":"Services"
        }
    ],
    "sg:phone":"+1 423 265 0005",
    "sg:postcode":"37402",
    "sg:province":"TN",
    "wof:name":"Prudential",
    "wof:placetype":"venue"
},
  "geometry": {"coordinates":[-85.310678,35.047527],"type":"Point"}
}