{
  "type": "Feature",
  "properties": {
    "iso:country":"US",
    "sg:address":"1302 Wayne Rd",
    "sg:city":"Savannah",
    "sg:classifiers":[
        {
            "category":"Personal",
            "subcategory":"Beauty Salon",
            "type":"Services"
        },
        {
            "category":"Shopping",
            "subcategory":"Clothing, Apparel, & Fashions",
            "type":"Retail Goods"
        }
    ],
    "sg:phone":"+1 731 925 2144",
    "sg:postcode":"38372",
    "sg:province":"TN",
    "wof:name":"Crystal's",
    "wof:placetype":"venue"
},
  "geometry": {"coordinates":[-88.2398,35.226927],"type":"Point"}
}