{
  "type": "Feature",
  "properties": {
    "addr:full":"7934 Donnybrook Dr Germantown TN 38138",
    "addr:housenumber":"7934",
    "addr:postcode":"38138",
    "addr:street":"Donnybrook Dr",
    "iso:country":"US",
    "sg:address":"7934 Donnybrook Dr",
    "sg:city":"Germantown",
    "sg:classifiers":[
        {
            "category":"Organizations",
            "subcategory":"Religious Organization",
            "type":"Services"
        }
    ],
    "sg:phone":"+1 901 753 7512",
    "sg:postcode":"38138",
    "sg:province":"TN",
    "sg:tags":[
        "church"
    ],
    "wof:name":"Church Of Jesus Christ",
    "wof:placetype":"venue"
},
  "geometry": {"coordinates":[-89.799342,35.088853],"type":"Point"}
}