{
  "type": "Feature",
  "properties": {
    "addr:full":"136 Timothy Rd Livingston TN 38541",
    "addr:housenumber":"136",
    "addr:postcode":"38541",
    "addr:street":"Timothy Rd",
    "iso:country":"US",
    "sg:address":"136 Timothy Rd",
    "sg:city":"Livingston",
    "sg:classifiers":[
        {
            "category":"Restaurant",
            "type":"Food & Drink"
        }
    ],
    "sg:phone":"+1 931 403 3388",
    "sg:postcode":"38541",
    "sg:province":"TN",
    "wof:name":"Lisa's Country Cooking Rstrnt",
    "wof:placetype":"venue"
},
  "geometry": {"coordinates":[-85.404967,36.489337],"type":"Point"}
}