{
  "type": "Feature",
  "properties": {
    "iso:country":"US",
    "sg:address":"1305 Rice Creek Rd",
    "sg:city":"Flag Pond",
    "sg:classifiers":[
        {
            "category":"Government",
            "subcategory":"Post Office",
            "type":"Public Place"
        }
    ],
    "sg:phone":"+1 423 743 5431",
    "sg:postcode":"37657",
    "sg:province":"TN",
    "wof:name":"US Post Office",
    "wof:placetype":"venue"
},
  "geometry": {"coordinates":[-82.601372,35.970555],"type":"Point"}
}