{
  "type": "Feature",
  "properties": {
    "iso:country":"US",
    "sg:address":"1314 Vollintine Ave",
    "sg:city":"Memphis",
    "sg:classifiers":[
        {
            "category":"Organizations",
            "subcategory":"Religious Organization",
            "type":"Services"
        }
    ],
    "sg:phone":"+1 901 278 7356",
    "sg:postcode":"38107",
    "sg:province":"TN",
    "sg:tags":[
        "church"
    ],
    "wof:name":"Klondike Church of Christ Inc",
    "wof:placetype":"venue"
},
  "geometry": {"coordinates":[-90.0138,35.165129],"type":"Point"}
}