{
  "type": "Feature",
  "properties": {
    "iso:country":"US",
    "sg:address":"700 Jearoldstown Rd",
    "sg:city":"Greeneville",
    "sg:classifiers":[
        {
            "category":"Food & Beverages",
            "subcategory":"Groceries & Convenience Stores",
            "type":"Retail Goods"
        }
    ],
    "sg:phone":"+1 423 234 0253",
    "sg:postcode":"37745",
    "sg:province":"TN",
    "wof:name":"Shilo Market",
    "wof:placetype":"venue"
},
  "geometry": {"coordinates":[-82.698482,36.357013],"type":"Point"}
}