{
  "type": "Feature",
  "properties": {
    "addr:full":"1921 S Court St Maryville TN 37803",
    "addr:housenumber":"1921",
    "addr:postcode":"37803",
    "addr:street":"S Court St",
    "iso:country":"US",
    "sg:address":"1921 S Court St",
    "sg:city":"Maryville",
    "sg:classifiers":[
        {
            "category":"Manufacturing",
            "subcategory":"Glass & Minerals",
            "type":"Manufacturing & Wholesale Goods"
        }
    ],
    "sg:phone":"+1 865 981 5760",
    "sg:postcode":"37803",
    "sg:province":"TN",
    "sg:tags":[
        "ready",
        "concrete",
        "mfg"
    ],
    "wof:name":"APAC",
    "wof:placetype":"venue"
},
  "geometry": {"coordinates":[-83.95222200000001,35.7356],"type":"Point"}
}