{
  "type": "Feature",
  "properties": {
    "iso:country":"US",
    "sg:address":"21190 E Main St",
    "sg:city":"Huntingdon",
    "sg:classifiers":[
        {
            "category":"Retail",
            "subcategory":"Funeral Services",
            "type":"Services"
        }
    ],
    "sg:phone":"+1 731 986 0500",
    "sg:postcode":"38344",
    "sg:province":"TN",
    "wof:name":"Chase Funeral Home",
    "wof:placetype":"venue"
},
  "geometry": {"coordinates":[-88.398669,36.009777],"type":"Point"}
}