{
  "type": "Feature",
  "properties": {
    "iso:country":"US",
    "sg:address":"123 Welch Ln",
    "sg:city":"New Tazewell",
    "sg:classifiers":[
        {
            "category":"Communications",
            "type":"Services"
        }
    ],
    "sg:phone":"+1 423 626 2662",
    "sg:postcode":"37825",
    "sg:province":"TN",
    "wof:name":"Lookout Towers",
    "wof:placetype":"venue"
},
  "geometry": {"coordinates":[-83.682396,36.45548],"type":"Point"}
}