{
  "type": "Feature",
  "properties": {
    "iso:country":"US",
    "sg:address":"182 Thompson Ln",
    "sg:city":"Nashville",
    "sg:classifiers":[
        {
            "category":"Building & Trades",
            "subcategory":"Construction",
            "type":"Services"
        }
    ],
    "sg:phone":"+1 615 385 4023",
    "sg:postcode":"37211",
    "sg:province":"TN",
    "sg:tags":[
        "contractor"
    ],
    "wof:name":"Bka General Contractors LLC",
    "wof:placetype":"venue"
},
  "geometry": {"coordinates":[-86.740332,36.110584],"type":"Point"}
}