{
  "type": "Feature",
  "properties": {
    "addr:full":"4840 Harvest Mill Way Knoxville TN 37918",
    "addr:housenumber":"4840",
    "addr:postcode":"37918",
    "addr:street":"Harvest Mill Way",
    "iso:country":"US",
    "sg:address":"4840 Harvest Mill Way",
    "sg:city":"Knoxville",
    "sg:classifiers":[
        {
            "category":"Building & Trades",
            "subcategory":"Construction",
            "type":"Services"
        }
    ],
    "sg:phone":"+1 865 687 8015",
    "sg:postcode":"37918",
    "sg:province":"TN",
    "sg:tags":[
        "general",
        "contractor"
    ],
    "wof:name":"Asfour Contractors & Engineers",
    "wof:placetype":"venue"
},
  "geometry": {"coordinates":[-83.926569,36.02736],"type":"Point"}
}