{
  "type": "Feature",
  "properties": {
    "iso:country":"US",
    "sg:address":"1819 Wartrace Rd",
    "sg:city":"Murfreesboro",
    "sg:classifiers":[
        {
            "category":"Health Services",
            "subcategory":"Podiatrist",
            "type":"Services"
        }
    ],
    "sg:phone":"+1 615 494 1234",
    "sg:postcode":"37150",
    "sg:province":"TN",
    "wof:name":"Wright M Anthony DPM",
    "wof:placetype":"venue"
},
  "geometry": {"coordinates":[-85.833369,36.419382],"type":"Point"}
}