{
  "type": "Feature",
  "properties": {
    "iso:country":"US",
    "sg:address":"9056 Corporate Gardens Dr",
    "sg:city":"Germantown",
    "sg:classifiers":[
        {
            "category":"Real Estate",
            "subcategory":"Real Estate Operator",
            "type":"Services"
        }
    ],
    "sg:phone":"+1 901 752 8270",
    "sg:postcode":"38138",
    "sg:province":"TN",
    "sg:tags":[
        "building",
        "nonresidential"
    ],
    "wof:name":"Firstpoint Properties Inc",
    "wof:placetype":"venue"
},
  "geometry": {"coordinates":[-89.760842,35.06454],"type":"Point"}
}