{
  "type": "Feature",
  "properties": {
    "addr:full":"100 N Porter St Bolivar TN 38008",
    "addr:housenumber":"100",
    "addr:postcode":"38008",
    "addr:street":"N Porter St",
    "iso:country":"US",
    "sg:address":"100 N Porter St",
    "sg:city":"Bolivar",
    "sg:classifiers":[
        {
            "category":"Building & Trades",
            "subcategory":"Equipment Rental",
            "type":"Services"
        }
    ],
    "sg:phone":"+1 731 658 1953",
    "sg:postcode":"38008",
    "sg:province":"TN",
    "wof:name":"Rent-A-Center",
    "wof:placetype":"venue"
},
  "geometry": {"coordinates":[-89.006816,35.260721],"type":"Point"}
}