{
  "type": "Feature",
  "properties": {
    "iso:country":"US",
    "sg:address":"4260 Fort Henry Dr",
    "sg:city":"Kingsport",
    "sg:classifiers":[
        {
            "category":"Real Estate",
            "subcategory":"Real Estate Operator",
            "type":"Services"
        }
    ],
    "sg:phone":"+1 423 245 4465",
    "sg:postcode":"37663",
    "sg:province":"TN",
    "sg:tags":[
        "apartment"
    ],
    "wof:name":"Barrett Properties",
    "wof:placetype":"venue"
},
  "geometry": {"coordinates":[-82.498469,36.481833],"type":"Point"}
}