{
  "type": "Feature",
  "properties": {
    "iso:country":"US",
    "sg:address":"414 Christopher Dr",
    "sg:city":"Clarksville",
    "sg:classifiers":[
        {
            "category":"Organizations",
            "subcategory":"Religious Organization",
            "type":"Services"
        }
    ],
    "sg:phone":"+1 931 572 1996",
    "sg:postcode":"37042",
    "sg:province":"TN",
    "wof:name":"New Way Community Church",
    "wof:placetype":"venue"
},
  "geometry": {"coordinates":[-87.42104999999999,36.584755],"type":"Point"}
}