{
  "type": "Feature",
  "properties": {
    "addr:full":"6227 Robertson Ave Nashville TN 37209",
    "addr:housenumber":"6227",
    "addr:postcode":"37209",
    "addr:street":"Robertson Ave",
    "iso:country":"US",
    "sg:address":"6227 Robertson Ave",
    "sg:city":"Nashville",
    "sg:classifiers":[
        {
            "category":"Personal",
            "subcategory":"Beauty Salon",
            "type":"Services"
        }
    ],
    "sg:phone":"+1 615 356 4651",
    "sg:postcode":"37209",
    "sg:province":"TN",
    "sg:tags":[
        "shop"
    ],
    "wof:name":"Sue's Hair Care",
    "wof:placetype":"venue"
},
  "geometry": {"coordinates":[-86.874601,36.157558],"type":"Point"}
}