{
  "type": "Feature",
  "properties": {
    "addr:full":"1500 N Jackson St Tullahoma TN 37388",
    "addr:housenumber":"1500",
    "addr:postcode":"37388",
    "addr:street":"N Jackson St",
    "iso:country":"US",
    "sg:address":"1500 N Jackson St",
    "sg:city":"Tullahoma",
    "sg:classifiers":[
        {
            "category":"Health Services",
            "subcategory":"Clinic",
            "type":"Services"
        }
    ],
    "sg:phone":"+1 931 461 5773",
    "sg:postcode":"37388",
    "sg:province":"TN",
    "sg:tags":[
        "banks",
        "blood",
        "center"
    ],
    "wof:name":"Blood Assurance",
    "wof:placetype":"venue"
},
  "geometry": {"coordinates":[-86.225312,35.37716],"type":"Point"}
}