{
  "type": "Feature",
  "properties": {
    "addr:full":"505 Tennessee St Memphis TN 38103",
    "addr:housenumber":"505",
    "addr:postcode":"38103",
    "addr:street":"Tennessee St",
    "iso:country":"US",
    "sg:address":"505 Tennessee St",
    "sg:city":"Memphis",
    "sg:classifiers":[
        {
            "category":"Real Estate",
            "subcategory":"Real Estate Operator",
            "type":"Services"
        }
    ],
    "sg:phone":"+1 901 544 1447",
    "sg:postcode":"38103",
    "sg:province":"TN",
    "sg:tags":[
        "apartment"
    ],
    "wof:name":"Lofts",
    "wof:placetype":"venue"
},
  "geometry": {"coordinates":[-90.06263800000001,35.133156],"type":"Point"}
}