{
  "type": "Feature",
  "properties": {
    "iso:country":"US",
    "sg:address":"817 Hawkins Rd",
    "sg:city":"Laurel Bloomery",
    "sg:classifiers":[
        {
            "category":"Organizations",
            "subcategory":"Religious Organization",
            "type":"Services"
        }
    ],
    "sg:phone":"+1 423 727 0290",
    "sg:postcode":"37683",
    "sg:province":"TN",
    "sg:tags":[
        "church"
    ],
    "wof:name":"State Line Bapt Chr Parsonage",
    "wof:placetype":"venue"
},
  "geometry": {"coordinates":[-81.721881,36.567254],"type":"Point"}
}