{
  "type": "Feature",
  "properties": {
    "iso:country":"US",
    "sg:address":"268 S Main St",
    "sg:city":"Jellico",
    "sg:classifiers":[
        {
            "category":"Health Services",
            "subcategory":"Optometrist",
            "type":"Services"
        }
    ],
    "sg:phone":"+1 423 784 2020",
    "sg:postcode":"37762",
    "sg:province":"TN",
    "wof:name":"Associates In Eye Care",
    "wof:placetype":"venue"
},
  "geometry": {"coordinates":[-84.12839099999999,36.58763],"type":"Point"}
}