{
  "type": "Feature",
  "properties": {
    "iso:country":"US",
    "sg:address":"305 Buddy Rd",
    "sg:city":"Burns",
    "sg:classifiers":[
        {
            "category":"Building & Trades",
            "subcategory":"Construction",
            "type":"Services"
        }
    ],
    "sg:phone":"+1 615 446 2241",
    "sg:postcode":"37029",
    "sg:province":"TN",
    "sg:tags":[
        "house"
    ],
    "wof:name":"SC Construction",
    "wof:placetype":"venue"
},
  "geometry": {"coordinates":[-87.314929,36.07886],"type":"Point"}
}