{
  "type": "Feature",
  "properties": {
    "addr:full":"101 Creekside Ln Brentwood TN 37034",
    "addr:housenumber":"101",
    "addr:postcode":"37034",
    "addr:street":"Creekside Ln",
    "iso:country":"US",
    "sg:address":"101 Creekside Ln",
    "sg:city":"Brentwood",
    "sg:classifiers":[
        {
            "category":"Shopping",
            "subcategory":"Gifts & Souvenirs",
            "type":"Retail Goods"
        }
    ],
    "sg:phone":"+1 615 613 0313",
    "sg:postcode":"37034",
    "sg:province":"TN",
    "sg:tags":[
        "shop"
    ],
    "wof:name":"Gabriel's Garden",
    "wof:placetype":"venue"
},
  "geometry": {"coordinates":[-86.60549899999999,35.621055],"type":"Point"}
}