{
  "type": "Feature",
  "properties": {
    "iso:country":"US",
    "sg:address":"4112 N Broadway St",
    "sg:city":"Knoxville",
    "sg:classifiers":[
        {
            "category":"Shopping",
            "subcategory":"Hobbies, Toys, & Games",
            "type":"Retail Goods"
        }
    ],
    "sg:phone":"+1 865 687 1837",
    "sg:postcode":"37917",
    "sg:province":"TN",
    "wof:name":"Woodbox",
    "wof:placetype":"venue"
},
  "geometry": {"coordinates":[-83.924922,36.010102],"type":"Point"}
}