{
  "type": "Feature",
  "properties": {
    "iso:country":"US",
    "sg:address":"325 Seaboard Ln",
    "sg:city":"Franklin",
    "sg:classifiers":[
        {
            "category":"Restaurant",
            "type":"Food & Drink"
        }
    ],
    "sg:phone":"+1 615 771 8020",
    "sg:postcode":"37067",
    "sg:province":"TN",
    "wof:name":"Off The Grill Franchising",
    "wof:placetype":"venue"
},
  "geometry": {"coordinates":[-86.830259,35.949753],"type":"Point"}
}