{
  "type": "Feature",
  "properties": {
    "addr:full":"1231 McCarter Rd Lawrenceburg TN 38464",
    "addr:housenumber":"1231",
    "addr:postcode":"38464",
    "addr:street":"Mccarter Rd",
    "iso:country":"US",
    "sg:address":"1231 McCarter Rd",
    "sg:city":"Lawrenceburg",
    "sg:classifiers":[
        {
            "category":"Farming",
            "subcategory":"Dairy Farm",
            "type":"Manufacturing & Wholesale Goods"
        }
    ],
    "sg:phone":"+1 931 762 3217",
    "sg:postcode":"38464",
    "sg:province":"TN",
    "wof:name":"Plain View Dairy",
    "wof:placetype":"venue"
},
  "geometry": {"coordinates":[-87.284576,35.248644],"type":"Point"}
}