{
  "type": "Feature",
  "properties": {
    "iso:country":"US",
    "sg:address":"206 Hedgewood Dr",
    "sg:city":"Chattanooga",
    "sg:classifiers":[
        {
            "category":"Retail",
            "subcategory":"Repair Shop",
            "type":"Services"
        }
    ],
    "sg:phone":"+1 423 875 8215",
    "sg:postcode":"37405",
    "sg:province":"TN",
    "sg:tags":[
        "contractor"
    ],
    "wof:name":"Hixon Septic Service",
    "wof:placetype":"venue"
},
  "geometry": {"coordinates":[-85.317892,35.089601],"type":"Point"}
}