{
  "type": "Feature",
  "properties": {
    "addr:full":"1408 Towson Dr Columbia TN 38401",
    "addr:housenumber":"1408",
    "addr:postcode":"38401",
    "addr:street":"Towson Dr",
    "iso:country":"US",
    "sg:address":"1408 Towson Dr",
    "sg:city":"Columbia",
    "sg:classifiers":[
        {
            "category":"Professional",
            "subcategory":"Secretarial Services",
            "type":"Services"
        }
    ],
    "sg:phone":"+1 931 388 1013",
    "sg:postcode":"38401",
    "sg:province":"TN",
    "sg:tags":[
        "reporting",
        "court"
    ],
    "wof:name":"Robinson Transcription Service",
    "wof:placetype":"venue"
},
  "geometry": {"coordinates":[-87.087369,35.585292],"type":"Point"}
}