{
  "type": "Feature",
  "properties": {
    "iso:country":"US",
    "sg:address":"5628 Nolensville Pike",
    "sg:city":"Nashville",
    "sg:classifiers":[
        {
            "category":"Restaurant",
            "type":"Food & Drink"
        }
    ],
    "sg:phone":"+1 615 831 1203",
    "sg:postcode":"37211",
    "sg:province":"TN",
    "sg:tags":[
        "eating"
    ],
    "wof:name":"Kuras Sushi",
    "wof:placetype":"venue"
},
  "geometry": {"coordinates":[-86.713232,36.045861],"type":"Point"}
}