{
  "type": "Feature",
  "properties": {
    "iso:country":"US",
    "sg:address":"2817 N Highland Ave",
    "sg:city":"Jackson",
    "sg:classifiers":[
        {
            "category":"Health Services",
            "subcategory":"Doctor",
            "type":"Services"
        }
    ],
    "sg:phone":"+1 731 661 0061",
    "sg:postcode":"38305",
    "sg:province":"TN",
    "sg:tags":[
        "physician",
        "surgeon",
        "medical"
    ],
    "wof:name":"Dermatology Associates PC",
    "wof:placetype":"venue"
},
  "geometry": {"coordinates":[-88.83020500000001,35.683871],"type":"Point"}
}