{
  "type": "Feature",
  "properties": {
    "addr:full":"5684 Cloverland Dr Brentwood TN 37027",
    "addr:housenumber":"5684",
    "addr:postcode":"37027",
    "addr:street":"Cloverland Dr",
    "iso:country":"US",
    "sg:address":"5684 Cloverland Dr",
    "sg:city":"Brentwood",
    "sg:classifiers":[
        {
            "category":"Building & Trades",
            "subcategory":"Construction",
            "type":"Services"
        }
    ],
    "sg:phone":"+1 615 370 8497",
    "sg:postcode":"37027",
    "sg:province":"TN",
    "sg:tags":[
        "house"
    ],
    "wof:name":"Homebrook Builders LLC",
    "wof:placetype":"venue"
},
  "geometry": {"coordinates":[-86.768732,36.033774],"type":"Point"}
}