{
  "type": "Feature",
  "properties": {
    "addr:full":"6307 Charlotte Pike Nashville TN 37209",
    "addr:housenumber":"6307",
    "addr:postcode":"37209",
    "addr:street":"Charlotte Pike",
    "iso:country":"US",
    "sg:address":"6307 Charlotte Pike",
    "sg:city":"Nashville",
    "sg:classifiers":[
        {
            "category":"Personal",
            "subcategory":"Tanning Parlor",
            "type":"Services"
        }
    ],
    "sg:phone":"+1 615 356 1570",
    "sg:postcode":"37209",
    "sg:province":"TN",
    "sg:tags":[
        "salon"
    ],
    "wof:name":"Ann's Tanning Club",
    "wof:placetype":"venue"
},
  "geometry": {"coordinates":[-86.87139999999999,36.145508],"type":"Point"}
}