{
  "type": "Feature",
  "properties": {
    "iso:country":"US",
    "sg:address":"3941 Trough Springs Rd",
    "sg:city":"Adams",
    "sg:classifiers":[
        {
            "category":"Real Estate",
            "subcategory":"Architect",
            "type":"Services"
        }
    ],
    "sg:phone":"+1 931 358 5120",
    "sg:postcode":"37010",
    "sg:province":"TN",
    "sg:tags":[
        "architectural"
    ],
    "wof:name":"Powell Architecture",
    "wof:placetype":"venue"
},
  "geometry": {"coordinates":[-87.18170499999999,36.51025],"type":"Point"}
}