{
  "type": "Feature",
  "properties": {
    "iso:country":"US",
    "sg:address":"1701 E Magnolia Ave",
    "sg:city":"Knoxville",
    "sg:classifiers":[
        {
            "category":"Real Estate",
            "subcategory":"Real Estate Operator",
            "type":"Services"
        }
    ],
    "sg:phone":"+1 865 524 8366",
    "sg:postcode":"37917",
    "sg:province":"TN",
    "sg:tags":[
        "apartment"
    ],
    "wof:name":"Magnolia Avenue Apartments",
    "wof:placetype":"venue"
},
  "geometry": {"coordinates":[-83.906677,35.979119],"type":"Point"}
}