{
  "type": "Feature",
  "properties": {
    "addr:full":"3860 New Covington Pike Memphis TN 38128",
    "addr:housenumber":"3860",
    "addr:postcode":"38128",
    "addr:street":"New Covington Pike",
    "iso:country":"US",
    "sg:address":"3860 New Covington Pike",
    "sg:city":"Memphis",
    "sg:classifiers":[
        {
            "category":"Health Services",
            "subcategory":"Doctor",
            "type":"Services"
        }
    ],
    "sg:phone":"+1 901 377 6805",
    "sg:postcode":"38128",
    "sg:province":"TN",
    "sg:tags":[
        "physician",
        "surgeon"
    ],
    "wof:name":"Family Doctor Doctores De Fml",
    "wof:placetype":"venue"
},
  "geometry": {"coordinates":[-89.892494,35.232342],"type":"Point"}
}