{
  "type": "Feature",
  "properties": {
    "iso:country":"US",
    "sg:address":"1116 Due West Ave",
    "sg:city":"Madison",
    "sg:classifiers":[
        {
            "category":"Professional",
            "subcategory":"Advertising",
            "type":"Services"
        }
    ],
    "sg:phone":"+1 615 474 6102",
    "sg:postcode":"37115",
    "sg:province":"TN",
    "wof:name":"KAN Enterprises",
    "wof:placetype":"venue"
},
  "geometry": {"coordinates":[-86.753902,36.255609],"type":"Point"}
}