{
  "type": "Feature",
  "properties": {
    "iso:country":"US",
    "sg:address":"3575 Indian Creek Rd",
    "sg:city":"Pulaski",
    "sg:classifiers":[
        {
            "category":"Autos & Motor Vehicles",
            "subcategory":"Auto Supplies",
            "type":"Retail Goods"
        }
    ],
    "sg:phone":"+1 931 732 4020",
    "sg:postcode":"38478",
    "sg:province":"TN",
    "sg:tags":[
        "equipment",
        "racing",
        "car",
        "automobile"
    ],
    "wof:name":"BCD Coatings",
    "wof:placetype":"venue"
},
  "geometry": {"coordinates":[-86.892426,35.153395],"type":"Point"}
}