{
  "type": "Feature",
  "properties": {
    "iso:country":"US",
    "sg:address":"2004 Red Bank Rd",
    "sg:city":"Sevierville",
    "sg:classifiers":[
        {
            "category":"Shopping",
            "subcategory":"Florist",
            "type":"Retail Goods"
        }
    ],
    "sg:phone":"+1 865 774 6640",
    "sg:postcode":"37876",
    "sg:province":"TN",
    "wof:name":"Specialty Occasions & Florists",
    "wof:placetype":"venue"
},
  "geometry": {"coordinates":[-83.48918399999999,35.840867],"type":"Point"}
}