{
  "type": "Feature",
  "properties": {
    "iso:country":"US",
    "sg:address":"1243 US Hwy 51 N Scn",
    "sg:city":"Ripley",
    "sg:classifiers":[
        {
            "category":"Retail",
            "subcategory":"Repair Shop",
            "type":"Services"
        }
    ],
    "sg:phone":"+1 731 635 5260",
    "sg:postcode":"38063",
    "sg:province":"TN",
    "sg:tags":[
        "building",
        "metal",
        "contractor",
        "iron",
        "works",
        "welding"
    ],
    "wof:name":"Bens Mini Storage",
    "wof:placetype":"venue"
},
  "geometry": {"coordinates":[-89.530036,35.773383],"type":"Point"}
}