{
  "type": "Feature",
  "properties": {
    "iso:country":"US",
    "sg:address":"507 Morgan Ave NE",
    "sg:city":"Harriman",
    "sg:classifiers":[
        {
            "category":"Organizations",
            "subcategory":"Religious Organization",
            "type":"Services"
        }
    ],
    "sg:phone":"+1 865 882 1209",
    "sg:postcode":"37748",
    "sg:province":"TN",
    "wof:name":"Gospel Light Baptist Church",
    "wof:placetype":"venue"
},
  "geometry": {"coordinates":[-84.55123399999999,35.932386],"type":"Point"}
}