{
  "type": "Feature",
  "properties": {
    "iso:country":"US",
    "sg:address":"280 Mary Ann Dr",
    "sg:city":"Memphis",
    "sg:classifiers":[
        {
            "category":"Professional",
            "type":"Services"
        }
    ],
    "sg:phone":"+1 901 763 4807",
    "sg:postcode":"38117",
    "sg:province":"TN",
    "wof:name":"Devimagination Inc",
    "wof:placetype":"venue"
},
  "geometry": {"coordinates":[-89.892132,35.137612],"type":"Point"}
}