{
  "type": "Feature",
  "properties": {
    "addr:full":"16250 US Hwy 412 E Lexington TN 38351",
    "addr:housenumber":"16250",
    "addr:postcode":"38351",
    "addr:street":"Us Hwy 412 E",
    "iso:country":"US",
    "sg:address":"16250 US Hwy 412 E",
    "sg:city":"Lexington",
    "sg:classifiers":[
        {
            "category":"Home & Garden",
            "subcategory":"Furniture",
            "type":"Retail Goods"
        }
    ],
    "sg:phone":"+1 731 968 8002",
    "sg:postcode":"38351",
    "sg:province":"TN",
    "sg:tags":[
        "cabinet"
    ],
    "wof:name":"FIC Woodworks",
    "wof:placetype":"venue"
},
  "geometry": {"coordinates":[-88.337898,35.634074],"type":"Point"}
}