{
  "type": "Feature",
  "properties": {
    "iso:country":"US",
    "sg:address":"45 Industrial Park Dr",
    "sg:city":"Hendersonville",
    "sg:classifiers":[
        {
            "category":"Home & Garden",
            "subcategory":"Building Materials",
            "type":"Retail Goods"
        }
    ],
    "sg:phone":"+1 615 826 4400",
    "sg:postcode":"37075",
    "sg:province":"TN",
    "sg:website":"www.ballarddoorsystems.com",
    "wof:name":"Ballard Garage Door Systems",
    "wof:placetype":"venue"
},
  "geometry": {"coordinates":[-86.635498,36.308359],"type":"Point"}
}