{
  "type": "Feature",
  "properties": {
    "iso:country":"US",
    "sg:address":"305 Old Hwy 27",
    "sg:city":"Lancing",
    "sg:classifiers":[
        {
            "category":"Shopping",
            "subcategory":"Used Merchandise",
            "type":"Retail Goods"
        }
    ],
    "sg:phone":"+1 423 346 6864",
    "sg:postcode":"37887",
    "sg:province":"TN",
    "sg:tags":[
        "furniture"
    ],
    "wof:name":"Sexton's Trading Post",
    "wof:placetype":"venue"
},
  "geometry": {"coordinates":[-84.60816,36.117776],"type":"Point"}
}