{
  "type": "Feature",
  "properties": {
    "iso:country":"US",
    "sg:address":"700 Greenwood St",
    "sg:city":"Union City",
    "sg:classifiers":[
        {
            "category":"Organizations",
            "subcategory":"Religious Organization",
            "type":"Services"
        }
    ],
    "sg:phone":"+1 731 885 9840",
    "sg:postcode":"38261",
    "sg:province":"TN",
    "sg:tags":[
        "church"
    ],
    "wof:name":"True Gospel Baptist Church",
    "wof:placetype":"venue"
},
  "geometry": {"coordinates":[-89.04459,36.429722],"type":"Point"}
}