{
  "type": "Feature",
  "properties": {
    "addr:full":"340 Wild Oak Rd SE Cleveland TN 37323",
    "addr:housenumber":"340",
    "addr:postcode":"37323",
    "addr:street":"Wild Oak Rd Se",
    "iso:country":"US",
    "sg:address":"340 Wild Oak Rd SE",
    "sg:city":"Cleveland",
    "sg:classifiers":[
        {
            "category":"Restaurant",
            "type":"Food & Drink"
        }
    ],
    "sg:phone":"+1 423 559 9633",
    "sg:postcode":"37323",
    "sg:province":"TN",
    "sg:tags":[
        "eating"
    ],
    "wof:name":"Cafe Expresso",
    "wof:placetype":"venue"
},
  "geometry": {"coordinates":[-84.839043,35.030688],"type":"Point"}
}