{
  "type": "Feature",
  "properties": {
    "addr:full":"4100 Highland Ave Chattanooga TN 37410",
    "addr:housenumber":"4100",
    "addr:postcode":"37410",
    "addr:street":"Highland Ave",
    "iso:country":"US",
    "sg:address":"4100 Highland Ave",
    "sg:city":"Chattanooga",
    "sg:classifiers":[
        {
            "category":"Organizations",
            "subcategory":"Religious Organization",
            "type":"Services"
        }
    ],
    "sg:phone":"+1 423 266 1829",
    "sg:postcode":"37410",
    "sg:province":"TN",
    "sg:tags":[
        "churches-baptist"
    ],
    "wof:name":"Union Grove Baptist",
    "wof:placetype":"venue"
},
  "geometry": {"coordinates":[-85.315231,35.004372],"type":"Point"}
}