{
  "type": "Feature",
  "properties": {
    "iso:country":"US",
    "sg:address":"1370 Robinson Rd",
    "sg:city":"Old Hickory",
    "sg:classifiers":[
        {
            "category":"Shopping",
            "subcategory":"Discount & Variety Stores",
            "type":"Retail Goods"
        }
    ],
    "sg:phone":"+1 615 847 8551",
    "sg:postcode":"37138",
    "sg:province":"TN",
    "wof:name":"Dollar General",
    "wof:placetype":"venue"
},
  "geometry": {"coordinates":[-86.661828,36.262871],"type":"Point"}
}