{
  "type": "Feature",
  "properties": {
    "iso:country":"US",
    "sg:address":"116 S 2nd St",
    "sg:city":"Selmer",
    "sg:classifiers":[
        {
            "category":"Personal",
            "subcategory":"Barber",
            "type":"Services"
        }
    ],
    "sg:phone":"+1 731 645 5541",
    "sg:postcode":"38375",
    "sg:province":"TN",
    "sg:tags":[
        "shop"
    ],
    "wof:name":"Texas Barbers/Crafts",
    "wof:placetype":"venue"
},
  "geometry": {"coordinates":[-88.59236799999999,35.169829],"type":"Point"}
}