{
  "type": "Feature",
  "properties": {
    "addr:full":"1092 Chamberlain Ave Chattanooga TN 37404",
    "addr:housenumber":"1092",
    "addr:postcode":"37404",
    "addr:street":"Chamberlain Ave",
    "iso:country":"US",
    "sg:address":"1092 Chamberlain Ave",
    "sg:city":"Chattanooga",
    "sg:classifiers":[
        {
            "category":"Professional",
            "subcategory":"Management & Consulting",
            "type":"Services"
        }
    ],
    "sg:phone":"+1 423 485 8077",
    "sg:postcode":"37404",
    "sg:province":"TN",
    "sg:tags":[
        "consultant",
        "business"
    ],
    "sg:website":"www.tpqvo.com",
    "wof:name":"Tennessee Physicians Quality",
    "wof:placetype":"venue"
},
  "geometry": {"coordinates":[-85.288507,35.038972],"type":"Point"}
}