{
  "type": "Feature",
  "properties": {
    "addr:full":"320 S Union St Bolivar TN 38008",
    "addr:housenumber":"320",
    "addr:postcode":"38008",
    "addr:street":"S Union St",
    "iso:country":"US",
    "sg:address":"320 S Union St",
    "sg:city":"Bolivar",
    "sg:classifiers":[
        {
            "category":"Retail",
            "subcategory":"Veterinary Services",
            "type":"Services"
        }
    ],
    "sg:phone":"+1 731 658 3855",
    "sg:postcode":"38008",
    "sg:province":"TN",
    "sg:tags":[
        "veterinarian"
    ],
    "wof:name":"Shackelford Veterinary Clinic",
    "wof:placetype":"venue"
},
  "geometry": {"coordinates":[-88.993312,35.254026],"type":"Point"}
}