{
  "type": "Feature",
  "properties": {
    "addr:full":"181 Curtis Cem Rd Mc Ewen TN 37101",
    "addr:housenumber":"181",
    "addr:postcode":"37101",
    "addr:street":"Curtis Cem Rd",
    "iso:country":"US",
    "sg:address":"181 Curtis Cem Rd",
    "sg:city":"Mc Ewen",
    "sg:classifiers":[
        {
            "category":"Professional",
            "type":"Services"
        }
    ],
    "sg:phone":"+1 931 622 0872",
    "sg:postcode":"37101",
    "sg:province":"TN",
    "sg:tags":[
        "technical",
        "writing"
    ],
    "wof:name":"D Archangel Andra",
    "wof:placetype":"venue"
},
  "geometry": {"coordinates":[-87.66355,36.137181],"type":"Point"}
}