{
  "type": "Feature",
  "properties": {
    "iso:country":"US",
    "sg:address":"174 Albert Lawson Rd NE",
    "sg:city":"Cleveland",
    "sg:classifiers":[
        {
            "category":"Retail",
            "subcategory":"Auto Repair",
            "type":"Services"
        }
    ],
    "sg:phone":"+1 423 473 6870",
    "sg:postcode":"37323",
    "sg:province":"TN",
    "sg:tags":[
        "body",
        "automobile",
        "painting"
    ],
    "wof:name":"Miss Tracy's Motors",
    "wof:placetype":"venue"
},
  "geometry": {"coordinates":[-84.798337,35.166334],"type":"Point"}
}