{
  "type": "Feature",
  "properties": {
    "addr:full":"206 Bellmore Ave Nashville TN 37209",
    "addr:housenumber":"206",
    "addr:postcode":"37209",
    "addr:street":"Bellmore Ave",
    "iso:country":"US",
    "sg:address":"206 Bellmore Ave",
    "sg:city":"Nashville",
    "sg:classifiers":[
        {
            "category":"Professional",
            "subcategory":"Advertising",
            "type":"Services"
        }
    ],
    "sg:phone":"+1 615 383 0412",
    "sg:postcode":"37209",
    "sg:province":"TN",
    "sg:tags":[
        "publicity"
    ],
    "wof:name":"Front Page Publicity",
    "wof:placetype":"venue"
},
  "geometry": {"coordinates":[-86.860992,36.145004],"type":"Point"}
}