{
  "type": "Feature",
  "properties": {
    "iso:country":"US",
    "sg:address":"1212 E Shelby Dr",
    "sg:city":"Memphis",
    "sg:classifiers":[
        {
            "category":"Shopping",
            "subcategory":"Pharmacy",
            "type":"Retail Goods"
        }
    ],
    "sg:phone":"+1 901 346 3336",
    "sg:postcode":"38116",
    "sg:province":"TN",
    "wof:name":"Schnucks Pharmacies",
    "wof:placetype":"venue"
},
  "geometry": {"coordinates":[-90.024569,35.020949],"type":"Point"}
}