{
  "type": "Feature",
  "properties": {
    "addr:full":"2346 Deadrick Ave Memphis TN 38114",
    "addr:housenumber":"2346",
    "addr:postcode":"38114",
    "addr:street":"Deadrick Ave",
    "iso:country":"US",
    "sg:address":"2346 Deadrick Ave",
    "sg:city":"Memphis",
    "sg:classifiers":[
        {
            "category":"Personal",
            "subcategory":"Beauty Salon",
            "type":"Services"
        }
    ],
    "sg:phone":"+1 901 327 0818",
    "sg:postcode":"38114",
    "sg:province":"TN",
    "wof:name":"Jordan's Beauty Salon",
    "wof:placetype":"venue"
},
  "geometry": {"coordinates":[-89.984505,35.104745],"type":"Point"}
}