{
  "type": "Feature",
  "properties": {
    "addr:full":"1523 US Hwy 70 W Camden TN 38320",
    "addr:housenumber":"1523",
    "addr:postcode":"38320",
    "addr:street":"Us Hwy 70 W",
    "iso:country":"US",
    "sg:address":"1523 US Hwy 70 W",
    "sg:city":"Camden",
    "sg:classifiers":[
        {
            "category":"Utilities",
            "subcategory":"Cable",
            "type":"Services"
        }
    ],
    "sg:phone":"+1 731 584 7100",
    "sg:postcode":"38320",
    "sg:province":"TN",
    "sg:tags":[
        "television"
    ],
    "wof:name":"Benton County Cablevision",
    "wof:placetype":"venue"
},
  "geometry": {"coordinates":[-88.121111,36.050729],"type":"Point"}
}