{
  "type": "Feature",
  "properties": {
    "iso:country":"US",
    "sg:address":"1030 Swann Ridge Rd",
    "sg:city":"Hilham",
    "sg:classifiers":[
        {
            "category":"Professional",
            "type":"Services"
        }
    ],
    "sg:phone":"+1 931 243 4418",
    "sg:postcode":"38568",
    "sg:province":"TN",
    "wof:name":"Cheryl A Smith",
    "wof:placetype":"venue"
},
  "geometry": {"coordinates":[-85.41421099999999,36.509967],"type":"Point"}
}