{
  "type": "Feature",
  "properties": {
    "iso:country":"US",
    "sg:address":"97 Byrds Creek Dr",
    "sg:city":"Crossville",
    "sg:classifiers":[
        {
            "category":"Retail",
            "subcategory":"Repair Shop",
            "type":"Services"
        }
    ],
    "sg:phone":"+1 931 707 8188",
    "sg:postcode":"38555",
    "sg:province":"TN",
    "sg:tags":[
        "scooter",
        "motorcycle",
        "motor"
    ],
    "wof:name":"Rick's ATV Repairs",
    "wof:placetype":"venue"
},
  "geometry": {"coordinates":[-84.953056,35.932285],"type":"Point"}
}