{
  "type": "Feature",
  "properties": {
    "iso:country":"US",
    "sg:address":"5800 Ferguson Rd",
    "sg:city":"Bartlett",
    "sg:classifiers":[
        {
            "category":"Retail",
            "subcategory":"Auto Repair",
            "type":"Services"
        }
    ],
    "sg:phone":"+1 901 377 3564",
    "sg:postcode":"38134",
    "sg:province":"TN",
    "sg:tags":[
        "repairing",
        "automobile",
        "general"
    ],
    "wof:name":"Mallory Automotive",
    "wof:placetype":"venue"
},
  "geometry": {"coordinates":[-89.87011699999999,35.201164],"type":"Point"}
}