{
  "type": "Feature",
  "properties": {
    "iso:country":"US",
    "sg:address":"125 Airways Blvd",
    "sg:city":"Jackson",
    "sg:classifiers":[
        {
            "category":"Shopping",
            "subcategory":"Musical Instruments",
            "type":"Retail Goods"
        }
    ],
    "sg:phone":"+1 731 423 2263",
    "sg:postcode":"38301",
    "sg:province":"TN",
    "sg:tags":[
        "store"
    ],
    "wof:name":"Wallick Music Company Inc",
    "wof:placetype":"venue"
},
  "geometry": {"coordinates":[-88.825075,35.615632],"type":"Point"}
}