{
  "type": "Feature",
  "properties": {
    "iso:country":"US",
    "sg:address":"902 Timesville Rd",
    "sg:city":"Signal Mountain",
    "sg:classifiers":[
        {
            "category":"Building & Trades",
            "subcategory":"Construction",
            "type":"Services"
        }
    ],
    "sg:phone":"+1 423 886 4949",
    "sg:postcode":"37377",
    "sg:province":"TN",
    "sg:tags":[
        "floor",
        "laying",
        "contractor"
    ],
    "wof:name":"A-1 Carpet Layers",
    "wof:placetype":"venue"
},
  "geometry": {"coordinates":[-85.322346,35.152358],"type":"Point"}
}