{
  "type": "Feature",
  "properties": {
    "addr:full":"1016 Jackson Ave Memphis TN 38107",
    "addr:housenumber":"1016",
    "addr:postcode":"38107",
    "addr:street":"Jackson Ave",
    "iso:country":"US",
    "sg:address":"1016 Jackson Ave",
    "sg:city":"Memphis",
    "sg:classifiers":[
        {
            "category":"Wholesale",
            "subcategory":"Machinery & Supplies",
            "type":"Manufacturing & Wholesale Goods"
        },
        {
            "category":"Building & Trades",
            "subcategory":"Equipment Rental",
            "type":"Services"
        },
        {
            "category":"Utilities",
            "subcategory":"Natural Gas",
            "type":"Services"
        },
        {
            "category":"Utilities",
            "subcategory":"Cable",
            "type":"Services"
        }
    ],
    "sg:phone":"+1 901 525 0422",
    "sg:postcode":"38107",
    "sg:province":"TN",
    "sg:tags":[
        "cylinders-air",
        "valve",
        "component",
        "hydraulic",
        "pneumatic",
        "industrial"
    ],
    "sg:website":"http://www.psiindustries.com",
    "wof:name":"PSI Industries",
    "wof:placetype":"venue"
},
  "geometry": {"coordinates":[-90.024689,35.1572],"type":"Point"}
}