{
  "type": "Feature",
  "properties": {
    "iso:country":"US",
    "sg:address":"1364 Marcum Rd",
    "sg:city":"Oneida",
    "sg:classifiers":[
        {
            "category":"Wholesale",
            "subcategory":"Construction Materials",
            "type":"Manufacturing & Wholesale Goods"
        }
    ],
    "sg:phone":"+1 423 286 7088",
    "sg:postcode":"37841",
    "sg:province":"TN",
    "sg:tags":[
        "timberland",
        "company",
        "timber"
    ],
    "wof:name":"Interstate Timber Products Co",
    "wof:placetype":"venue"
},
  "geometry": {"coordinates":[-84.536608,36.488425],"type":"Point"}
}