{
  "type": "Feature",
  "properties": {
    "iso:country":"US",
    "sg:address":"1580 N Broad St",
    "sg:city":"Tazewell",
    "sg:classifiers":[
        {
            "category":"Restaurant",
            "type":"Food & Drink"
        }
    ],
    "sg:menulink":"http://www.allmenus.com/tn/tazewell/191805-sonic/menu/",
    "sg:phone":"+1 423 626 7797",
    "sg:postcode":"37879",
    "sg:province":"TN",
    "sg:tags":[
        "burger",
        "american"
    ],
    "wof:name":"Sonic",
    "wof:placetype":"venue"
},
  "geometry": {"coordinates":[-83.57059599999999,36.449479],"type":"Point"}
}