{
  "type": "Feature",
  "properties": {
    "iso:country":"US",
    "sg:address":"2437 Lake Rd",
    "sg:city":"Dyersburg",
    "sg:classifiers":[
        {
            "category":"Autos & Motor Vehicles",
            "subcategory":"Auto Supplies",
            "type":"Retail Goods"
        }
    ],
    "sg:phone":"+1 731 287 0586",
    "sg:postcode":"38024",
    "sg:province":"TN",
    "sg:tags":[
        "automobile",
        "parts"
    ],
    "wof:name":"Advance Auto Parts Inc",
    "wof:placetype":"venue"
},
  "geometry": {"coordinates":[-89.39551299999999,36.061349],"type":"Point"}
}