{
  "type": "Feature",
  "properties": {
    "addr:full":"1505 E Broadway Ave Maryville TN 37804",
    "addr:housenumber":"1505",
    "addr:postcode":"37804",
    "addr:street":"E Broadway Ave",
    "iso:country":"US",
    "sg:address":"1505 E Broadway Ave",
    "sg:city":"Maryville",
    "sg:classifiers":[
        {
            "category":"Building & Trades",
            "subcategory":"Construction",
            "type":"Services"
        }
    ],
    "sg:phone":"+1 865 379 1270",
    "sg:postcode":"37804",
    "sg:province":"TN",
    "sg:tags":[
        "woodworker"
    ],
    "wof:name":"G & W Woodworkers",
    "wof:placetype":"venue"
},
  "geometry": {"coordinates":[-83.95873899999999,35.770269],"type":"Point"}
}