{
  "type": "Feature",
  "properties": {
    "iso:country":"US",
    "sg:address":"101 Center St",
    "sg:city":"Gleason",
    "sg:classifiers":[
        {
            "category":"Autos & Motor Vehicles",
            "subcategory":"Auto Supplies",
            "type":"Retail Goods"
        }
    ],
    "sg:phone":"+1 731 648 5716",
    "sg:postcode":"38229",
    "sg:province":"TN",
    "sg:tags":[
        "automobile",
        "parts"
    ],
    "wof:name":"Eveready Auto Parts",
    "wof:placetype":"venue"
},
  "geometry": {"coordinates":[-88.611915,36.213239],"type":"Point"}
}