{
  "type": "Feature",
  "properties": {
    "iso:country":"US",
    "sg:address":"11695 Highway 70",
    "sg:city":"Arlington",
    "sg:classifiers":[
        {
            "category":"Personal",
            "subcategory":"Beauty Salon",
            "type":"Services"
        }
    ],
    "sg:phone":"+1 901 867 1105",
    "sg:postcode":"38002",
    "sg:province":"TN",
    "sg:tags":[
        "hair",
        "stylist"
    ],
    "wof:name":"Infusion The Hair Gallery",
    "wof:placetype":"venue"
},
  "geometry": {"coordinates":[-89.679405,35.291904],"type":"Point"}
}