{
  "type": "Feature",
  "properties": {
    "addr:full":"900 US Hwy 51 N Covington TN 38019",
    "addr:housenumber":"900",
    "addr:postcode":"38019",
    "addr:street":"Us Hwy 51 N",
    "iso:country":"US",
    "sg:address":"900 US Hwy 51 N",
    "sg:city":"Covington",
    "sg:classifiers":[
        {
            "category":"Autos & Motor Vehicles",
            "subcategory":"Automobile Sales",
            "type":"Retail Goods"
        }
    ],
    "sg:phone":"+1 901 476 2713",
    "sg:postcode":"38019",
    "sg:province":"TN",
    "sg:tags":[
        "car",
        "dealer"
    ],
    "wof:name":"Blankenship Motor Co",
    "wof:placetype":"venue"
},
  "geometry": {"coordinates":[-89.642248,35.579792],"type":"Point"}
}