{
  "type": "Feature",
  "properties": {
    "iso:country":"US",
    "sg:address":"6923 Maynardville Pike",
    "sg:city":"Knoxville",
    "sg:classifiers":[
        {
            "category":"Professional",
            "subcategory":"Advertising",
            "type":"Services"
        }
    ],
    "sg:phone":"+1 865 922 3946",
    "sg:postcode":"37918",
    "sg:province":"TN",
    "sg:tags":[
        "mailing",
        "shipping"
    ],
    "wof:name":"UPS Store",
    "wof:placetype":"venue"
},
  "geometry": {"coordinates":[-83.927967,36.074483],"type":"Point"}
}