{
  "type": "Feature",
  "properties": {
    "iso:country":"US",
    "sg:address":"130 S Locust Ave",
    "sg:city":"Lawrenceburg",
    "sg:classifiers":[
        {
            "category":"Health Services",
            "subcategory":"Medical Lab",
            "type":"Services"
        }
    ],
    "sg:phone":"+1 931 762 3537",
    "sg:postcode":"38464",
    "sg:province":"TN",
    "sg:tags":[
        "laboratory"
    ],
    "wof:name":"Custom Service",
    "wof:placetype":"venue"
},
  "geometry": {"coordinates":[-87.33070499999999,35.239994],"type":"Point"}
}