{
  "type": "Feature",
  "properties": {
    "addr:full":"1510 Gunbarrel Rd Chattanooga TN 37421",
    "addr:postcode":"37421",
    "addr:street":"1510 Gunbarrel Rd",
    "iso:country":"US",
    "sg:address":"1510 Gunbarrel Rd",
    "sg:city":"Chattanooga",
    "sg:classifiers":[
        {
            "category":"Banks & Credit Unions",
            "subcategory":"Bank",
            "type":"Services"
        }
    ],
    "sg:phone":"+1 423 855 3770",
    "sg:postcode":"37421",
    "sg:province":"TN",
    "sg:tags":[
        "mortgage"
    ],
    "wof:name":"Beneficial",
    "wof:placetype":"venue"
},
  "geometry": {"coordinates":[-85.162775,35.016601],"type":"Point"}
}