{
  "type": "Feature",
  "properties": {
    "addr:full":"5239 US Hwy 78 Memphis TN 38118",
    "addr:housenumber":"5239",
    "addr:postcode":"38118",
    "addr:street":"Us Hwy 78",
    "iso:country":"US",
    "sg:address":"5239 US Hwy 78",
    "sg:city":"Memphis",
    "sg:classifiers":[
        {
            "category":"Building & Trades",
            "subcategory":"Equipment Rental",
            "type":"Services"
        }
    ],
    "sg:phone":"+1 901 366 4116",
    "sg:postcode":"38118",
    "sg:province":"TN",
    "sg:tags":[
        "heavy",
        "construction"
    ],
    "wof:name":"Rental Service Corp",
    "wof:placetype":"venue"
},
  "geometry": {"coordinates":[-89.88939999999999,35.0092],"type":"Point"}
}