{
  "type": "Feature",
  "properties": {
    "iso:country":"US",
    "sg:address":"7523 Nevada Ln",
    "sg:city":"Corryton",
    "sg:classifiers":[
        {
            "category":"Retail",
            "subcategory":"Laundry & Dry Cleaning",
            "type":"Services"
        }
    ],
    "sg:phone":"+1 865 688 5526",
    "sg:postcode":"37721",
    "sg:province":"TN",
    "sg:tags":[
        "cleaner",
        "rug",
        "carpet"
    ],
    "wof:name":"Chem-Dry Of Knoxville",
    "wof:placetype":"venue"
},
  "geometry": {"coordinates":[-83.867304,36.120137],"type":"Point"}
}