{
  "type": "Feature",
  "properties": {
    "iso:country":"US",
    "sg:address":"132 W Jackson Ave",
    "sg:city":"Knoxville",
    "sg:classifiers":[
        {
            "category":"Restaurant",
            "type":"Food & Drink"
        }
    ],
    "sg:phone":"+1 865 525 0012",
    "sg:postcode":"37902",
    "sg:province":"TN",
    "sg:tags":[
        "eating"
    ],
    "wof:name":"Cup A Joe In The Old City",
    "wof:placetype":"venue"
},
  "geometry": {"coordinates":[-83.91920500000001,35.969845],"type":"Point"}
}