{
  "type": "Feature",
  "properties": {
    "iso:country":"US",
    "sg:address":"198 Paradise Dr",
    "sg:city":"Lobelville",
    "sg:classifiers":[
        {
            "category":"Freight",
            "type":"Transportation"
        }
    ],
    "sg:phone":"+1 931 593 3554",
    "sg:postcode":"37075",
    "sg:province":"TN",
    "sg:tags":[
        "trucking"
    ],
    "wof:name":"Gerald Shaffer Trucking",
    "wof:placetype":"venue"
},
  "geometry": {"coordinates":[-86.620599,36.285152],"type":"Point"}
}