{
  "type": "Feature",
  "properties": {
    "iso:country":"US",
    "sg:address":"1850 Allen Ferry Rd",
    "sg:city":"Smithville",
    "sg:classifiers":[
        {
            "category":"Organizations",
            "subcategory":"Religious Organization",
            "type":"Services"
        }
    ],
    "sg:phone":"+1 615 597 6677",
    "sg:postcode":"37166",
    "sg:province":"TN",
    "sg:tags":[
        "church"
    ],
    "wof:name":"Elizabeth Chapel Baptist Chr",
    "wof:placetype":"venue"
},
  "geometry": {"coordinates":[-85.843897,35.974767],"type":"Point"}
}