{
  "type": "Feature",
  "properties": {
    "addr:full":"801 Pine St Chattanooga TN 37402",
    "addr:housenumber":"801",
    "addr:postcode":"37402",
    "addr:street":"Pine St",
    "iso:country":"US",
    "sg:address":"801 Pine St",
    "sg:city":"Chattanooga",
    "sg:classifiers":[
        {
            "category":"Travel",
            "subcategory":"Hotels & Motels",
            "type":"Entertainment"
        }
    ],
    "sg:phone":"+1 423 755 5965",
    "sg:postcode":"37402",
    "sg:province":"TN",
    "sg:tags":[
        "operation"
    ],
    "wof:name":"Marriott",
    "wof:placetype":"venue"
},
  "geometry": {"coordinates":[-85.31258699999999,35.046624],"type":"Point"}
}