{
  "type": "Feature",
  "properties": {
    "iso:country":"US",
    "sg:address":"33 Lewis Ave",
    "sg:city":"Lexington",
    "sg:classifiers":[
        {
            "category":"Organizations",
            "subcategory":"Religious Organization",
            "type":"Services"
        }
    ],
    "sg:phone":"+1 731 968 6071",
    "sg:postcode":"38351",
    "sg:province":"TN",
    "wof:name":"Pilgram Rest Missionary Baptis",
    "wof:placetype":"venue"
},
  "geometry": {"coordinates":[-88.38997000000001,35.647024],"type":"Point"}
}