{
  "type": "Feature",
  "properties": {
    "iso:country":"US",
    "sg:address":"4726 N Roan St",
    "sg:city":"Johnson City",
    "sg:classifiers":[
        {
            "category":"Professional",
            "type":"Services"
        }
    ],
    "sg:phone":"+1 423 928 3474",
    "sg:postcode":"37615",
    "sg:province":"TN",
    "wof:name":"High Tech Satellite",
    "wof:placetype":"venue"
},
  "geometry": {"coordinates":[-82.41092399999999,36.39049],"type":"Point"}
}