{
  "type": "Feature",
  "properties": {
    "iso:country":"US",
    "sg:address":"439 Parker Dr",
    "sg:city":"Bradyville",
    "sg:classifiers":[
        {
            "category":"Social Services",
            "subcategory":"Child Care",
            "type":"Services"
        }
    ],
    "sg:phone":"+1 615 765 5222",
    "sg:postcode":"37026",
    "sg:province":"TN",
    "wof:name":"Play N' Learn Daycare",
    "wof:placetype":"venue"
},
  "geometry": {"coordinates":[-86.06340400000001,35.733172],"type":"Point"}
}