{
  "type": "Feature",
  "properties": {
    "iso:country":"US",
    "sg:address":"115 S Cumberland St",
    "sg:city":"Lebanon",
    "sg:classifiers":[
        {
            "category":"Home & Garden",
            "subcategory":"Home Furnishings",
            "type":"Retail Goods"
        }
    ],
    "sg:phone":"+1 615 453 9333",
    "sg:postcode":"37087",
    "sg:province":"TN",
    "sg:tags":[
        "blanket"
    ],
    "wof:name":"Quilt Emporium Inc",
    "wof:placetype":"venue"
},
  "geometry": {"coordinates":[-86.291127,36.207265],"type":"Point"}
}