{
  "type": "Feature",
  "properties": {
    "iso:country":"US",
    "sg:address":"1628 Fort Campbell Blvd",
    "sg:city":"Clarksville",
    "sg:classifiers":[
        {
            "category":"Shopping",
            "subcategory":"Department Store",
            "type":"Retail Goods"
        }
    ],
    "sg:phone":"+1 931 645 8094",
    "sg:postcode":"37042",
    "sg:province":"TN",
    "sg:tags":[
        "shop"
    ],
    "wof:name":"Dollar Tree",
    "wof:placetype":"venue"
},
  "geometry": {"coordinates":[-87.408216,36.576022],"type":"Point"}
}