{
  "type": "Feature",
  "properties": {
    "addr:full":"194 W Main St Camden TN 38320",
    "addr:housenumber":"194",
    "addr:postcode":"38320",
    "addr:street":"W Main St",
    "iso:country":"US",
    "sg:address":"194 W Main St",
    "sg:city":"Camden",
    "sg:classifiers":[
        {
            "category":"Health Services",
            "subcategory":"Optometrist",
            "type":"Services"
        }
    ],
    "sg:phone":"+1 731 584 6161",
    "sg:postcode":"38320",
    "sg:province":"TN",
    "wof:name":"Mc Connell Vision Ctr",
    "wof:placetype":"venue"
},
  "geometry": {"coordinates":[-88.10869700000001,36.058442],"type":"Point"}
}