{
  "type": "Feature",
  "properties": {
    "addr:full":"725 Rankin Ave Dunlap TN 37327",
    "addr:housenumber":"725",
    "addr:postcode":"37327",
    "addr:street":"Rankin Ave",
    "iso:country":"US",
    "sg:address":"725 Rankin Ave",
    "sg:city":"Dunlap",
    "sg:classifiers":[
        {
            "category":"Health Services",
            "subcategory":"Doctor",
            "type":"Services"
        }
    ],
    "sg:phone":"+1 423 949 5930",
    "sg:postcode":"37327",
    "sg:province":"TN",
    "sg:tags":[
        "medical"
    ],
    "wof:name":"Gambro Hlthcare Ptent Svcs Sup",
    "wof:placetype":"venue"
},
  "geometry": {"coordinates":[-85.378781,35.386733],"type":"Point"}
}