{
  "type": "Feature",
  "properties": {
    "addr:full":"47 Brooksie Dr Jackson TN 38305",
    "addr:housenumber":"47",
    "addr:postcode":"38305",
    "addr:street":"Brooksie Dr",
    "iso:country":"US",
    "sg:address":"47 Brooksie Dr",
    "sg:city":"Jackson",
    "sg:classifiers":[
        {
            "category":"Shopping",
            "subcategory":"Computers & Home Electronics",
            "type":"Retail Goods"
        }
    ],
    "sg:phone":"+1 731 660 6094",
    "sg:postcode":"38305",
    "sg:province":"TN",
    "sg:tags":[
        "equipment",
        "dealer"
    ],
    "wof:name":"Line Computer",
    "wof:placetype":"venue"
},
  "geometry": {"coordinates":[-88.86060500000001,35.696258],"type":"Point"}
}