{
  "type": "Feature",
  "properties": {
    "iso:country":"US",
    "sg:address":"101 Hawk St",
    "sg:city":"Elizabethton",
    "sg:classifiers":[
        {
            "category":"Retail",
            "subcategory":"Auto Repair",
            "type":"Services"
        }
    ],
    "sg:phone":"+1 423 543 2121",
    "sg:postcode":"37643",
    "sg:province":"TN",
    "sg:tags":[
        "repairing",
        "automobile"
    ],
    "wof:name":"Woodby Motors-Frame & Body Ctr",
    "wof:placetype":"venue"
},
  "geometry": {"coordinates":[-82.21404,36.345027],"type":"Point"}
}