{
  "type": "Feature",
  "properties": {
    "iso:country":"US",
    "sg:address":"728 S Carter School Rd",
    "sg:city":"Mascot",
    "sg:classifiers":[
        {
            "category":"Organizations",
            "subcategory":"Religious Organization",
            "type":"Services"
        }
    ],
    "sg:phone":"+1 865 933 7159",
    "sg:postcode":"37871",
    "sg:province":"TN",
    "sg:tags":[
        "church"
    ],
    "wof:name":"Thorn Grove Christian Church",
    "wof:placetype":"venue"
},
  "geometry": {"coordinates":[-83.693458,36.005081],"type":"Point"}
}