{
  "type": "Feature",
  "properties": {
    "addr:full":"2668 Lamar Ave Memphis TN 38114",
    "addr:housenumber":"2668",
    "addr:postcode":"38114",
    "addr:street":"Lamar Ave",
    "iso:country":"US",
    "sg:address":"2668 Lamar Ave",
    "sg:city":"Memphis",
    "sg:classifiers":[
        {
            "category":"Retail",
            "subcategory":"Auto Repair",
            "type":"Services"
        }
    ],
    "sg:phone":"+1 901 743 8003",
    "sg:postcode":"38114",
    "sg:province":"TN",
    "sg:tags":[
        "general"
    ],
    "wof:name":"Precise Automotive",
    "wof:placetype":"venue"
},
  "geometry": {"coordinates":[-89.97316499999999,35.098246],"type":"Point"}
}