{
  "type": "Feature",
  "properties": {
    "addr:full":"115 N King Ave Dyersburg TN 38024",
    "addr:housenumber":"115",
    "addr:postcode":"38024",
    "addr:street":"N King Ave",
    "iso:country":"US",
    "sg:address":"115 N King Ave",
    "sg:city":"Dyersburg",
    "sg:classifiers":[
        {
            "category":"Organizations",
            "subcategory":"Non-profit Organization",
            "type":"Services"
        },
        {
            "category":"Education",
            "subcategory":"Special Training",
            "type":"Public Place"
        }
    ],
    "sg:phone":"+1 731 285 3020",
    "sg:postcode":"38024",
    "sg:province":"TN",
    "wof:name":"Dyer County Literacy Program",
    "wof:placetype":"venue"
},
  "geometry": {"coordinates":[-89.390869,36.033755],"type":"Point"}
}