{
  "type": "Feature",
  "properties": {
    "iso:country":"US",
    "sg:address":"1187 Vultee Blvd",
    "sg:city":"Nashville",
    "sg:classifiers":[
        {
            "category":"Professional",
            "subcategory":"Computer Services",
            "type":"Services"
        }
    ],
    "sg:phone":"+1 615 366 8487",
    "sg:postcode":"37217",
    "sg:province":"TN",
    "wof:name":"Ryan Credit Corp",
    "wof:placetype":"venue"
},
  "geometry": {"coordinates":[-86.705117,36.12379],"type":"Point"}
}