{
  "type": "Feature",
  "properties": {
    "iso:country":"US",
    "sg:address":"175 Walnut Ridge Ln",
    "sg:city":"Cordova",
    "sg:classifiers":[
        {
            "category":"Professional",
            "type":"Services"
        }
    ],
    "sg:phone":"+1 901 490 5041",
    "sg:postcode":"38018",
    "sg:province":"TN",
    "sg:tags":[
        "buses-charter",
        "rental"
    ],
    "wof:name":"Miles Away",
    "wof:placetype":"venue"
},
  "geometry": {"coordinates":[-89.76674300000001,35.130787],"type":"Point"}
}