{
  "type": "Feature",
  "properties": {
    "iso:country":"US",
    "sg:address":"500 Garner Rd",
    "sg:city":"Pulaski",
    "sg:classifiers":[
        {
            "category":"Manufacturing",
            "subcategory":"Tools & Machinery",
            "type":"Manufacturing & Wholesale Goods"
        }
    ],
    "sg:phone":"+1 931 215 8158",
    "sg:postcode":"38468",
    "sg:province":"TN",
    "sg:tags":[
        "industrial",
        "mfg"
    ],
    "wof:name":"S & J Designs & Machiningllc",
    "wof:placetype":"venue"
},
  "geometry": {"coordinates":[-87.311643,35.161035],"type":"Point"}
}