{
  "type": "Feature",
  "properties": {
    "addr:full":"4339 Stage Rd Memphis TN 38128",
    "addr:housenumber":"4339",
    "addr:postcode":"38128",
    "addr:street":"Stage Rd",
    "iso:country":"US",
    "sg:address":"4339 Stage Rd",
    "sg:city":"Memphis",
    "sg:classifiers":[
        {
            "category":"Freight",
            "type":"Transportation"
        }
    ],
    "sg:phone":"+1 901 691 1617",
    "sg:postcode":"38128",
    "sg:province":"TN",
    "sg:tags":[
        "operator",
        "local",
        "trucking"
    ],
    "wof:name":"Bucks Almost Anything Moving",
    "wof:placetype":"venue"
},
  "geometry": {"coordinates":[-89.920008,35.205287],"type":"Point"}
}