{
  "type": "Feature",
  "properties": {
    "iso:country":"US",
    "sg:address":"804 Middle Creek Rd",
    "sg:city":"Sevierville",
    "sg:classifiers":[
        {
            "category":"Health Services",
            "subcategory":"Doctor",
            "type":"Services"
        }
    ],
    "sg:phone":"+1 865 453 2731",
    "sg:postcode":"37862",
    "sg:province":"TN",
    "wof:name":"Dyer Lee Roy DDS PC",
    "wof:placetype":"venue"
},
  "geometry": {"coordinates":[-83.536469,35.853437],"type":"Point"}
}