{
  "type": "Feature",
  "properties": {
    "iso:country":"US",
    "sg:address":"64 Lynoak Cove",
    "sg:city":"Jackson",
    "sg:classifiers":[
        {
            "category":"Professional",
            "subcategory":"Lawyer & Legal Services",
            "type":"Services"
        }
    ],
    "sg:phone":"+1 731 664 2024",
    "sg:postcode":"38305",
    "sg:province":"TN",
    "wof:name":"Lisa June Cox",
    "wof:placetype":"venue"
},
  "geometry": {"coordinates":[-88.847089,35.647823],"type":"Point"}
}