{
  "type": "Feature",
  "properties": {
    "iso:country":"US",
    "sg:address":"3550 Austin Peay Hwy",
    "sg:city":"Memphis",
    "sg:classifiers":[
        {
            "category":"Banks & Credit Unions",
            "subcategory":"Bank",
            "type":"Services"
        },
        {
            "category":"Banks & Credit Unions",
            "subcategory":"Financial Services",
            "type":"Services"
        }
    ],
    "sg:phone":"+1 901 385 6690",
    "sg:postcode":"38128",
    "sg:province":"TN",
    "sg:tags":[
        "loan",
        "financing"
    ],
    "sg:website":"http://www.SunTrust.com",
    "wof:name":"SunTrust Bank - Raleigh Springs",
    "wof:placetype":"venue"
},
  "geometry": {"coordinates":[-89.907763,35.222603],"type":"Point"}
}