{
  "type": "Feature",
  "properties": {
    "addr:full":"1208 W Harris Dr Johnson City TN 37604",
    "addr:housenumber":"1208",
    "addr:postcode":"37604",
    "addr:street":"W Harris Dr",
    "iso:country":"US",
    "sg:address":"1208 W Harris Dr",
    "sg:city":"Johnson City",
    "sg:classifiers":[
        {
            "category":"Restaurant",
            "type":"Food & Drink"
        }
    ],
    "sg:menulink":"http://www.allmenus.com/tn/johnson-city/104023-ruby-tuesdays/menu/",
    "sg:phone":"+1 423 926 1336",
    "sg:postcode":"37604",
    "sg:province":"TN",
    "sg:tags":[
        "burger",
        "american"
    ],
    "wof:name":"Ruby Tuesdays",
    "wof:placetype":"venue"
},
  "geometry": {"coordinates":[-82.373271,36.304264],"type":"Point"}
}