{
  "type": "Feature",
  "properties": {
    "addr:full":"406 Independence Way Murfreesboro TN 37129",
    "addr:housenumber":"406",
    "addr:postcode":"37129",
    "addr:street":"Independence Way",
    "iso:country":"US",
    "sg:address":"406 Independence Way",
    "sg:city":"Murfreesboro",
    "sg:classifiers":[
        {
            "category":"Retail",
            "subcategory":"Auto Repair",
            "type":"Services"
        }
    ],
    "sg:phone":"+1 615 895 0863",
    "sg:postcode":"37129",
    "sg:province":"TN",
    "sg:tags":[
        "glass",
        "coating",
        "tinting"
    ],
    "wof:name":"Southern Shade Window Tinting",
    "wof:placetype":"venue"
},
  "geometry": {"coordinates":[-86.39246799999999,35.882374],"type":"Point"}
}