{
  "type": "Feature",
  "properties": {
    "addr:full":"2138 Kimberlin Heights Rd Knoxville TN 37920",
    "addr:housenumber":"2138",
    "addr:postcode":"37920",
    "addr:street":"Kimberlin Heights Rd",
    "iso:country":"US",
    "sg:address":"2138 Kimberlin Heights Rd",
    "sg:city":"Knoxville",
    "sg:classifiers":[
        {
            "category":"Food & Beverages",
            "subcategory":"Groceries & Convenience Stores",
            "type":"Retail Goods"
        }
    ],
    "sg:phone":"+1 865 579 9217",
    "sg:postcode":"37920",
    "sg:province":"TN",
    "wof:name":"Gap Creek Market & Deli",
    "wof:placetype":"venue"
},
  "geometry": {"coordinates":[-83.75698199999999,35.927527],"type":"Point"}
}