{
  "type": "Feature",
  "properties": {
    "iso:country":"US",
    "sg:address":"2269 Wilma Rudolph Blvd",
    "sg:city":"Clarksville",
    "sg:classifiers":[
        {
            "category":"Building & Trades",
            "subcategory":"Construction",
            "type":"Services"
        }
    ],
    "sg:phone":"+1 931 647 6848",
    "sg:postcode":"37040",
    "sg:province":"TN",
    "sg:tags":[
        "home",
        "builder"
    ],
    "sg:website":"www.tommyburneyhomes.com",
    "wof:name":"Tommy Burney Homes",
    "wof:placetype":"venue"
},
  "geometry": {"coordinates":[-87.303117,36.572427],"type":"Point"}
}