{
  "type": "Feature",
  "properties": {
    "iso:country":"US",
    "sg:address":"115 17th Ave S",
    "sg:city":"Nashville",
    "sg:classifiers":[
        {
            "category":"Professional",
            "subcategory":"Lawyer & Legal Services",
            "type":"Services"
        }
    ],
    "sg:phone":"+1 615 242 6032",
    "sg:postcode":"37203",
    "sg:province":"TN",
    "sg:tags":[
        "attorney"
    ],
    "wof:name":"J David Wykoff Law Offices",
    "wof:placetype":"venue"
},
  "geometry": {"coordinates":[-86.79420500000001,36.153405],"type":"Point"}
}