{
  "type": "Feature",
  "properties": {
    "iso:country":"US",
    "sg:address":"3251 Millbranch Rd",
    "sg:city":"Memphis",
    "sg:classifiers":[
        {
            "category":"Autos & Motor Vehicles",
            "subcategory":"Auto Supplies",
            "type":"Retail Goods"
        }
    ],
    "sg:phone":"+1 901 332 4444",
    "sg:postcode":"38116",
    "sg:province":"TN",
    "wof:name":"Rhino Linings",
    "wof:placetype":"venue"
},
  "geometry": {"coordinates":[-90.007411,35.05855],"type":"Point"}
}