{
  "type": "Feature",
  "properties": {
    "iso:country":"US",
    "sg:address":"5637 US Hwy 411",
    "sg:city":"Benton",
    "sg:classifiers":[
        {
            "category":"Shopping",
            "subcategory":"Clothing, Apparel, & Fashions",
            "type":"Retail Goods"
        }
    ],
    "sg:phone":"+1 423 338 2090",
    "sg:postcode":"37307",
    "sg:province":"TN",
    "sg:tags":[
        "shoes",
        "family"
    ],
    "wof:name":"Kens Casuals",
    "wof:placetype":"venue"
},
  "geometry": {"coordinates":[-84.675517,35.165532],"type":"Point"}
}