{
  "type": "Feature",
  "properties": {
    "iso:country":"US",
    "sg:address":"301 S 3rd St",
    "sg:city":"Smithville",
    "sg:classifiers":[
        {
            "category":"Home & Garden",
            "subcategory":"Furniture",
            "type":"Retail Goods"
        }
    ],
    "sg:phone":"+1 615 597 3196",
    "sg:postcode":"37166",
    "sg:province":"TN",
    "wof:name":"Superior Rent To Own",
    "wof:placetype":"venue"
},
  "geometry": {"coordinates":[-85.813426,35.959016],"type":"Point"}
}