{
  "type": "Feature",
  "properties": {
    "addr:full":"225 N Lindell St Martin TN 38237",
    "addr:housenumber":"225",
    "addr:postcode":"38237",
    "addr:street":"N Lindell St",
    "iso:country":"US",
    "sg:address":"225 N Lindell St",
    "sg:city":"Martin",
    "sg:classifiers":[
        {
            "category":"Building & Trades",
            "subcategory":"Construction",
            "type":"Services"
        }
    ],
    "sg:phone":"+1 731 587 0824",
    "sg:postcode":"38237",
    "sg:province":"TN",
    "sg:tags":[
        "home",
        "improvement"
    ],
    "wof:name":"Helping Hands",
    "wof:placetype":"venue"
},
  "geometry": {"coordinates":[-88.849144,36.350798],"type":"Point"}
}