{
  "type": "Feature",
  "properties": {
    "iso:country":"US",
    "sg:address":"701 S 6th St",
    "sg:city":"La Follette",
    "sg:classifiers":[
        {
            "category":"Taxi",
            "type":"Transportation"
        }
    ],
    "sg:phone":"+1 423 562 8883",
    "sg:postcode":"37766",
    "sg:province":"TN",
    "sg:tags":[
        "taxicab"
    ],
    "wof:name":"LA Feld's City Svc Cab",
    "wof:placetype":"venue"
},
  "geometry": {"coordinates":[-84.11268200000001,36.38025],"type":"Point"}
}