{
  "type": "Feature",
  "properties": {
    "iso:country":"US",
    "sg:address":"144 Cherokee Dr",
    "sg:city":"Memphis",
    "sg:classifiers":[
        {
            "category":"Professional",
            "subcategory":"Computer Services",
            "type":"Services"
        }
    ],
    "sg:phone":"+1 901 452 8174",
    "sg:postcode":"38111",
    "sg:province":"TN",
    "sg:tags":[
        "datum"
    ],
    "wof:name":"Lodestone Design Inc",
    "wof:placetype":"venue"
},
  "geometry": {"coordinates":[-89.96628800000001,35.127689],"type":"Point"}
}