{
  "type": "Feature",
  "properties": {
    "iso:country":"US",
    "sg:address":"1414 County Hospital Rd",
    "sg:city":"Nashville",
    "sg:classifiers":[
        {
            "category":"Banks & Credit Unions",
            "subcategory":"Bank",
            "type":"Services"
        }
    ],
    "sg:phone":"+1 615 862 7026",
    "sg:postcode":"37218",
    "sg:province":"TN",
    "sg:tags":[
        "state"
    ],
    "wof:name":"Ngh Credit Union",
    "wof:placetype":"venue"
},
  "geometry": {"coordinates":[-86.84568899999999,36.182582],"type":"Point"}
}