{
  "type": "Feature",
  "properties": {
    "addr:full":"301 Red Tuttle Rd Bethpage TN 37022",
    "addr:housenumber":"301",
    "addr:postcode":"37022",
    "addr:street":"Red Tuttle Rd",
    "iso:country":"US",
    "sg:address":"301 Red Tuttle Rd",
    "sg:city":"Bethpage",
    "sg:classifiers":[
        {
            "category":"Shopping",
            "subcategory":"Gifts & Souvenirs",
            "type":"Retail Goods"
        }
    ],
    "sg:phone":"+1 615 841 3683",
    "sg:postcode":"37022",
    "sg:province":"TN",
    "wof:name":"Anytime Gifts & More",
    "wof:placetype":"venue"
},
  "geometry": {"coordinates":[-86.359622,36.501458],"type":"Point"}
}