{
  "type": "Feature",
  "properties": {
    "iso:country":"US",
    "sg:address":"480 Co Rd 660",
    "sg:city":"Etowah",
    "sg:classifiers":[
        {
            "category":"Farming",
            "subcategory":"Dairy Farm",
            "type":"Manufacturing & Wholesale Goods"
        }
    ],
    "sg:phone":"+1 423 263 2451",
    "sg:postcode":"37331",
    "sg:province":"TN",
    "sg:tags":[
        "chicken"
    ],
    "wof:name":"Bivens Dairy Farm",
    "wof:placetype":"venue"
},
  "geometry": {"coordinates":[-84.59916200000001,35.326273],"type":"Point"}
}