{
  "type": "Feature",
  "properties": {
    "iso:country":"US",
    "sg:address":"114 E Commerce St",
    "sg:city":"Lewisburg",
    "sg:classifiers":[
        {
            "category":"Professional",
            "subcategory":"Employment Agencies",
            "type":"Services"
        }
    ],
    "sg:phone":"+1 931 359 3030",
    "sg:postcode":"37091",
    "sg:province":"TN",
    "sg:tags":[
        "help",
        "contractor"
    ],
    "wof:name":"Randstad",
    "wof:placetype":"venue"
},
  "geometry": {"coordinates":[-86.787477,35.449058],"type":"Point"}
}