{
  "type": "Feature",
  "properties": {
    "iso:country":"US",
    "sg:address":"5326 Ringgold Rd",
    "sg:city":"Chattanooga",
    "sg:classifiers":[
        {
            "category":"Restaurant",
            "type":"Food & Drink"
        }
    ],
    "sg:menulink":"http://www.allmenus.com/tn/east-ridge/105332-ryans/menu/",
    "sg:phone":"+1 423 894 0592",
    "sg:postcode":"37412",
    "sg:province":"TN",
    "sg:tags":[
        "american"
    ],
    "wof:name":"Ryan's",
    "wof:placetype":"venue"
},
  "geometry": {"coordinates":[-85.23324,34.994688],"type":"Point"}
}