{
  "type": "Feature",
  "properties": {
    "iso:country":"US",
    "sg:address":"109 N Main St",
    "sg:city":"Ridgely",
    "sg:classifiers":[
        {
            "category":"Shopping",
            "subcategory":"Pharmacy",
            "type":"Retail Goods"
        }
    ],
    "sg:phone":"+1 731 264 5651",
    "sg:postcode":"38080",
    "sg:province":"TN",
    "sg:tags":[
        "drug"
    ],
    "wof:name":"Taylor Brothers Pharmacy Corp",
    "wof:placetype":"venue"
},
  "geometry": {"coordinates":[-89.48756,36.265004],"type":"Point"}
}