{
  "type": "Feature",
  "properties": {
    "iso:country":"US",
    "sg:address":"2411 Elliott Ave",
    "sg:city":"Nashville",
    "sg:classifiers":[
        {
            "category":"Wholesale",
            "subcategory":"Stationery",
            "type":"Manufacturing & Wholesale Goods"
        }
    ],
    "sg:phone":"+1 615 385 9192",
    "sg:postcode":"37204",
    "sg:province":"TN",
    "sg:tags":[
        "paper"
    ],
    "wof:name":"Recyclesource Inc",
    "wof:placetype":"venue"
},
  "geometry": {"coordinates":[-86.778626,36.124767],"type":"Point"}
}