{
  "type": "Feature",
  "properties": {
    "iso:country":"US",
    "sg:address":"44 Bridge St",
    "sg:city":"Big Sandy",
    "sg:classifiers":[
        {
            "category":"Restaurant",
            "type":"Food & Drink"
        }
    ],
    "sg:phone":"+1 731 593 3383",
    "sg:postcode":"38221",
    "sg:province":"TN",
    "sg:tags":[
        "eating"
    ],
    "wof:name":"Bridge Street Cafe",
    "wof:placetype":"venue"
},
  "geometry": {"coordinates":[-88.086371,36.235811],"type":"Point"}
}