{
  "type": "Feature",
  "properties": {
    "addr:full":"1345 Alidar Pl Cordova TN 38016",
    "addr:housenumber":"1345",
    "addr:postcode":"38016",
    "addr:street":"Alidar Pl",
    "iso:country":"US",
    "sg:address":"1345 Alidar Pl",
    "sg:city":"Cordova",
    "sg:classifiers":[
        {
            "category":"Wholesale",
            "subcategory":"Vending Machines",
            "type":"Manufacturing & Wholesale Goods"
        }
    ],
    "sg:phone":"+1 901 756 1987",
    "sg:postcode":"38016",
    "sg:province":"TN",
    "sg:tags":[
        "operator"
    ],
    "wof:name":"Snak Atak Vending",
    "wof:placetype":"venue"
},
  "geometry": {"coordinates":[-89.815318,35.162349],"type":"Point"}
}