{
  "type": "Feature",
  "properties": {
    "addr:full":"3375 Bruceville Slab Rd Dyersburg TN 38024",
    "addr:housenumber":"3375",
    "addr:postcode":"38024",
    "addr:street":"Bruceville Slab Rd",
    "iso:country":"US",
    "sg:address":"3375 Bruceville Slab Rd",
    "sg:city":"Dyersburg",
    "sg:classifiers":[
        {
            "category":"Wholesale",
            "subcategory":"Non-durable Goods",
            "type":"Manufacturing & Wholesale Goods"
        }
    ],
    "sg:phone":"+1 731 285 0270",
    "sg:postcode":"38024",
    "sg:province":"TN",
    "wof:name":"Watson Distributing Inc",
    "wof:placetype":"venue"
},
  "geometry": {"coordinates":[-89.344342,35.911957],"type":"Point"}
}