{
  "type": "Feature",
  "properties": {
    "iso:country":"US",
    "sg:address":"204 N 2nd St",
    "sg:city":"Memphis",
    "sg:classifiers":[
        {
            "category":"Social Services",
            "type":"Services"
        }
    ],
    "sg:phone":"+1 901 526 8228",
    "sg:postcode":"38105",
    "sg:province":"TN",
    "sg:tags":[
        "organization",
        "religious"
    ],
    "wof:name":"Firstworks",
    "wof:placetype":"venue"
},
  "geometry": {"coordinates":[-90.049238,35.150386],"type":"Point"}
}