{
  "type": "Feature",
  "properties": {
    "iso:country":"US",
    "sg:address":"1702 W Madison Ave",
    "sg:city":"Athens",
    "sg:classifiers":[
        {
            "category":"Professional",
            "subcategory":"Accounting & Tax Preparation",
            "type":"Services"
        }
    ],
    "sg:phone":"+1 423 745 0417",
    "sg:postcode":"37303",
    "sg:province":"TN",
    "sg:tags":[
        "return",
        "filing"
    ],
    "wof:name":"Parks Tax Svc",
    "wof:placetype":"venue"
},
  "geometry": {"coordinates":[-84.619409,35.439438],"type":"Point"}
}