{
  "type": "Feature",
  "properties": {
    "addr:full":"380 Mohawk Valley Rd Monroe TN 38573",
    "addr:housenumber":"380",
    "addr:postcode":"38573",
    "addr:street":"Mohawk Valley Rd",
    "iso:country":"US",
    "sg:address":"380 Mohawk Valley Rd",
    "sg:city":"Monroe",
    "sg:classifiers":[
        {
            "category":"Farming",
            "subcategory":"Dairy Farm",
            "type":"Manufacturing & Wholesale Goods"
        }
    ],
    "sg:phone":"+1 931 823 7438",
    "sg:postcode":"38573",
    "sg:province":"TN",
    "wof:name":"S & S Farms",
    "wof:placetype":"venue"
},
  "geometry": {"coordinates":[-85.26502499999999,36.519057],"type":"Point"}
}