{
  "type": "Feature",
  "properties": {
    "iso:country":"US",
    "sg:address":"587 Woodcrest Dr",
    "sg:city":"La Vergne",
    "sg:classifiers":[
        {
            "category":"Shopping",
            "subcategory":"Computers & Home Electronics",
            "type":"Retail Goods"
        }
    ],
    "sg:phone":"+1 615 287 0197",
    "sg:postcode":"37086",
    "sg:province":"TN",
    "sg:tags":[
        "organization",
        "religious"
    ],
    "wof:name":"Christian Resource Network",
    "wof:placetype":"venue"
},
  "geometry": {"coordinates":[-86.60910699999999,35.99049],"type":"Point"}
}