{
  "type": "Feature",
  "properties": {
    "addr:full":"1986 Fort Campbell Blvd Clarksville TN 37042",
    "addr:housenumber":"1986",
    "addr:postcode":"37042",
    "addr:street":"Fort Campbell Blvd",
    "iso:country":"US",
    "sg:address":"1986 Fort Campbell Blvd",
    "sg:city":"Clarksville",
    "sg:classifiers":[
        {
            "category":"Real Estate",
            "subcategory":"Real Estate Services",
            "type":"Services"
        }
    ],
    "sg:phone":"+1 931 645 2081",
    "sg:postcode":"37042",
    "sg:province":"TN",
    "sg:tags":[
        "company",
        "title"
    ],
    "wof:name":"Titlemax",
    "wof:placetype":"venue"
},
  "geometry": {"coordinates":[-87.416685,36.592227],"type":"Point"}
}