{
  "type": "Feature",
  "properties": {
    "iso:country":"US",
    "sg:address":"3196 Hwy 231 N",
    "sg:city":"Shelbyville",
    "sg:classifiers":[
        {
            "category":"Freight",
            "type":"Transportation"
        }
    ],
    "sg:phone":"+1 931 684 6260",
    "sg:postcode":"37160",
    "sg:province":"TN",
    "sg:tags":[
        "truck"
    ],
    "wof:name":"Trott Group Inc",
    "wof:placetype":"venue"
},
  "geometry": {"coordinates":[-86.441248,35.584732],"type":"Point"}
}