{
  "type": "Feature",
  "properties": {
    "iso:country":"US",
    "sg:address":"5965 Miller Ln",
    "sg:city":"Christiana",
    "sg:classifiers":[
        {
            "category":"Autos & Motor Vehicles",
            "subcategory":"Fuel & Gas Station",
            "type":"Retail Goods"
        }
    ],
    "sg:phone":"+1 615 898 1471",
    "sg:postcode":"37037",
    "sg:province":"TN",
    "sg:tags":[
        "grocery",
        "plaza",
        "gasoline",
        "stops",
        "station",
        "truck"
    ],
    "wof:name":"Dannys Food and Fuel Plaza",
    "wof:placetype":"venue"
},
  "geometry": {"coordinates":[-86.318422,35.723468],"type":"Point"}
}