{
  "type": "Feature",
  "properties": {
    "iso:country":"US",
    "sg:address":"1211 Bell Rd",
    "sg:city":"Nashville",
    "sg:classifiers":[
        {
            "category":"Real Estate",
            "subcategory":"Real Estate Operator",
            "type":"Services"
        }
    ],
    "sg:phone":"+1 615 731 0062",
    "sg:postcode":"37214",
    "sg:province":"TN",
    "sg:tags":[
        "building",
        "apartment"
    ],
    "wof:name":"Beechwood Terrace Apartments",
    "wof:placetype":"venue"
},
  "geometry": {"coordinates":[-86.629193,36.132739],"type":"Point"}
}