{
  "type": "Feature",
  "properties": {
    "addr:full":"229 S 4th St Selmer TN 38375",
    "addr:housenumber":"229",
    "addr:postcode":"38375",
    "addr:street":"S 4Th St",
    "iso:country":"US",
    "sg:address":"229 S 4th St",
    "sg:city":"Selmer",
    "sg:classifiers":[
        {
            "category":"Personal",
            "subcategory":"Beauty Salon",
            "type":"Services"
        }
    ],
    "sg:phone":"+1 731 645 5229",
    "sg:postcode":"38375",
    "sg:province":"TN",
    "sg:tags":[
        "manicuring"
    ],
    "wof:name":"Fashion Nail",
    "wof:placetype":"venue"
},
  "geometry": {"coordinates":[-88.59526200000001,35.169692],"type":"Point"}
}