{
  "type": "Feature",
  "properties": {
    "iso:country":"US",
    "sg:address":"609 Hollandale Rd",
    "sg:city":"La Vergne",
    "sg:classifiers":[
        {
            "category":"Social Services",
            "type":"Services"
        }
    ],
    "sg:phone":"+1 615 459 4673",
    "sg:postcode":"37086",
    "sg:province":"TN",
    "sg:tags":[
        "counseling"
    ],
    "wof:name":"Alpha Point Christian Family",
    "wof:placetype":"venue"
},
  "geometry": {"coordinates":[-86.54254299999999,36.048988],"type":"Point"}
}