{
  "type": "Feature",
  "properties": {
    "iso:country":"US",
    "sg:address":"7318 Manchester Pike",
    "sg:city":"Murfreesboro",
    "sg:classifiers":[
        {
            "category":"Food & Beverages",
            "subcategory":"Groceries & Convenience Stores",
            "type":"Retail Goods"
        }
    ],
    "sg:phone":"+1 615 895 7117",
    "sg:postcode":"37127",
    "sg:province":"TN",
    "sg:tags":[
        "grocer"
    ],
    "wof:name":"Gordon's Market",
    "wof:placetype":"venue"
},
  "geometry": {"coordinates":[-86.27921600000001,35.673875],"type":"Point"}
}