{
  "type": "Feature",
  "properties": {
    "iso:country":"US",
    "sg:address":"1220 Village Dr",
    "sg:city":"Rutledge",
    "sg:classifiers":[
        {
            "category":"Travel",
            "subcategory":"Hotels & Motels",
            "type":"Entertainment"
        },
        {
            "category":"Travel",
            "subcategory":"Campground",
            "type":"Entertainment"
        }
    ],
    "sg:phone":"+1 865 828 5547",
    "sg:postcode":"37862",
    "sg:province":"TN",
    "sg:tags":[
        "operation"
    ],
    "wof:name":"WA-Ni Village Resort",
    "wof:placetype":"venue"
},
  "geometry": {"coordinates":[-83.531192,35.853451],"type":"Point"}
}