{
  "type": "Feature",
  "properties": {
    "iso:country":"US",
    "sg:address":"350 Congress Pkwy NW",
    "sg:city":"Athens",
    "sg:classifiers":[
        {
            "category":"Social Services",
            "type":"Services"
        }
    ],
    "sg:phone":"+1 423 745 3934",
    "sg:postcode":"37303",
    "sg:province":"TN",
    "sg:tags":[
        "counselor",
        "marriage",
        "family"
    ],
    "wof:name":"Family Preservation Counsel",
    "wof:placetype":"venue"
},
  "geometry": {"coordinates":[-84.609065,35.464714],"type":"Point"}
}