{
  "type": "Feature",
  "properties": {
    "iso:country":"US",
    "sg:address":"948 E Mclemore Ave",
    "sg:city":"Memphis",
    "sg:classifiers":[
        {
            "category":"Personal",
            "subcategory":"Beauty Salon",
            "type":"Services"
        }
    ],
    "sg:phone":"+1 901 775 1936",
    "sg:postcode":"38106",
    "sg:province":"TN",
    "wof:name":"Shirley's Beauty Salon",
    "wof:placetype":"venue"
},
  "geometry": {"coordinates":[-90.030632,35.115479],"type":"Point"}
}