{
  "type": "Feature",
  "properties": {
    "addr:full":"710 US Highway 51 Byp W Dyersburg TN 38024",
    "addr:housenumber":"710",
    "addr:postcode":"38024",
    "addr:street":"Us Highway 51 Byp W",
    "iso:country":"US",
    "sg:address":"710 US Highway 51 Byp W",
    "sg:city":"Dyersburg",
    "sg:classifiers":[
        {
            "category":"Banks & Credit Unions",
            "subcategory":"Bank",
            "type":"Services"
        }
    ],
    "sg:phone":"+1 731 287 4383",
    "sg:postcode":"38024",
    "sg:province":"TN",
    "wof:name":"Green Village Branch",
    "wof:placetype":"venue"
},
  "geometry": {"coordinates":[-89.412251,36.03577],"type":"Point"}
}