{
  "type": "Feature",
  "properties": {
    "addr:full":"213 Fowler Dr Maryville TN 37803",
    "addr:housenumber":"213",
    "addr:postcode":"37803",
    "addr:street":"Fowler Dr",
    "iso:country":"US",
    "sg:address":"213 Fowler Dr",
    "sg:city":"Maryville",
    "sg:classifiers":[
        {
            "category":"Recreation",
            "type":"Entertainment"
        }
    ],
    "sg:phone":"+1 865 984 1718",
    "sg:postcode":"37803",
    "sg:province":"TN",
    "sg:tags":[
        "club",
        "membership"
    ],
    "wof:name":"Robert Howdeshell",
    "wof:placetype":"venue"
},
  "geometry": {"coordinates":[-83.943214,35.722166],"type":"Point"}
}