{
  "type": "Feature",
  "properties": {
    "iso:country":"US",
    "sg:address":"651 N Gateway Ave",
    "sg:city":"Rockwood",
    "sg:classifiers":[
        {
            "category":"Shopping",
            "subcategory":"Tobacco",
            "type":"Retail Goods"
        }
    ],
    "sg:phone":"+1 865 354 8793",
    "sg:postcode":"37854",
    "sg:province":"TN",
    "sg:tags":[
        "cigarette",
        "cigar",
        "dealer"
    ],
    "wof:name":"Jiya Inc",
    "wof:placetype":"venue"
},
  "geometry": {"coordinates":[-84.676281,35.873714],"type":"Point"}
}