{
  "type": "Feature",
  "properties": {
    "iso:country":"US",
    "sg:address":"220 W Depot St",
    "sg:city":"Greeneville",
    "sg:classifiers":[
        {
            "category":"Professional",
            "type":"Services"
        }
    ],
    "sg:phone":"+1 423 639 6056",
    "sg:postcode":"37743",
    "sg:province":"TN",
    "sg:tags":[
        "establishment"
    ],
    "wof:name":"Bureau Of ATF",
    "wof:placetype":"venue"
},
  "geometry": {"coordinates":[-82.83474200000001,36.164728],"type":"Point"}
}