{
  "type": "Feature",
  "properties": {
    "addr:full":"304 Cane Creek Rd Jackson TN 38301",
    "addr:housenumber":"304",
    "addr:postcode":"38301",
    "addr:street":"Cane Creek Rd",
    "iso:country":"US",
    "sg:address":"304 Cane Creek Rd",
    "sg:city":"Jackson",
    "sg:classifiers":[
        {
            "category":"Organizations",
            "subcategory":"Religious Organization",
            "type":"Services"
        }
    ],
    "sg:phone":"+1 731 427 2730",
    "sg:postcode":"38301",
    "sg:province":"TN",
    "sg:tags":[
        "church"
    ],
    "wof:name":"Cane Creek Baptist Church",
    "wof:placetype":"venue"
},
  "geometry": {"coordinates":[-88.83762,35.564549],"type":"Point"}
}