{
  "type": "Feature",
  "properties": {
    "iso:country":"US",
    "sg:address":"220 N Elm Ave",
    "sg:city":"Erwin",
    "sg:classifiers":[
        {
            "category":"Travel",
            "subcategory":"Hotels & Motels",
            "type":"Entertainment"
        }
    ],
    "sg:phone":"+1 423 743 1932",
    "sg:postcode":"37650",
    "sg:province":"TN",
    "sg:tags":[
        "operation"
    ],
    "wof:name":"Miss Janets House",
    "wof:placetype":"venue"
},
  "geometry": {"coordinates":[-82.413448,36.14553],"type":"Point"}
}