{
  "type": "Feature",
  "properties": {
    "iso:country":"US",
    "sg:address":"113 Church St",
    "sg:city":"Goodlettsville",
    "sg:classifiers":[
        {
            "category":"Organizations",
            "subcategory":"Religious Organization",
            "type":"Services"
        }
    ],
    "sg:phone":"+1 615 859 5915",
    "sg:postcode":"37072",
    "sg:province":"TN",
    "sg:tags":[
        "church"
    ],
    "wof:name":"Connell Memorial United Mthdst",
    "wof:placetype":"venue"
},
  "geometry": {"coordinates":[-86.710875,36.324503],"type":"Point"}
}