{
  "type": "Feature",
  "properties": {
    "iso:country":"US",
    "sg:address":"608 W Trinity Ln",
    "sg:city":"Nashville",
    "sg:classifiers":[
        {
            "category":"Shopping",
            "subcategory":"Used Merchandise",
            "type":"Retail Goods"
        }
    ],
    "sg:phone":"+1 615 262 1064",
    "sg:postcode":"37207",
    "sg:province":"TN",
    "sg:tags":[
        "clothing"
    ],
    "wof:name":"On Tha Spot Clothing",
    "wof:placetype":"venue"
},
  "geometry": {"coordinates":[-86.794571,36.206815],"type":"Point"}
}