{
  "type": "Feature",
  "properties": {
    "iso:country":"US",
    "sg:address":"200 Prosser Rd",
    "sg:city":"Lawrenceburg",
    "sg:classifiers":[
        {
            "category":"Food & Beverages",
            "subcategory":"Groceries & Convenience Stores",
            "type":"Retail Goods"
        }
    ],
    "sg:phone":"+1 931 762 3373",
    "sg:postcode":"38464",
    "sg:province":"TN",
    "wof:name":"Quik Stop Markets",
    "wof:placetype":"venue"
},
  "geometry": {"coordinates":[-87.336118,35.223984],"type":"Point"}
}