{
  "type": "Feature",
  "properties": {
    "iso:country":"US",
    "sg:address":"14995 Highland Dr",
    "sg:city":"Mc Kenzie",
    "sg:classifiers":[
        {
            "category":"Autos & Motor Vehicles",
            "subcategory":"Auto Supplies",
            "type":"Retail Goods"
        }
    ],
    "sg:phone":"+1 731 352 4904",
    "sg:postcode":"38201",
    "sg:province":"TN",
    "sg:tags":[
        "brake",
        "tire"
    ],
    "wof:name":"Tires & Brakes 4 Less",
    "wof:placetype":"venue"
},
  "geometry": {"coordinates":[-88.51953899999999,36.122193],"type":"Point"}
}