{
  "type": "Feature",
  "properties": {
    "iso:country":"US",
    "sg:address":"528 Gale Dr",
    "sg:city":"Clarksville",
    "sg:classifiers":[
        {
            "category":"Building & Trades",
            "subcategory":"Plumbing",
            "type":"Services"
        }
    ],
    "sg:phone":"+1 931 216 0499",
    "sg:postcode":"37040",
    "sg:province":"TN",
    "sg:tags":[
        "contractor"
    ],
    "wof:name":"Service First",
    "wof:placetype":"venue"
},
  "geometry": {"coordinates":[-87.323201,36.585796],"type":"Point"}
}