{
  "type": "Feature",
  "properties": {
    "addr:full":"511 N Jackson St Tullahoma TN 37388",
    "addr:housenumber":"511",
    "addr:postcode":"37388",
    "addr:street":"N Jackson St",
    "iso:country":"US",
    "sg:address":"511 N Jackson St",
    "sg:city":"Tullahoma",
    "sg:classifiers":[
        {
            "category":"Banks & Credit Unions",
            "subcategory":"Bank",
            "type":"Services"
        }
    ],
    "sg:phone":"+1 931 455 5340",
    "sg:postcode":"37388",
    "sg:province":"TN",
    "sg:tags":[
        "loan",
        "mortgage",
        "real estate"
    ],
    "sg:website":"www.huskeymortgage.com",
    "wof:name":"Huskey Financial Inc",
    "wof:placetype":"venue"
},
  "geometry": {"coordinates":[-86.21597199999999,35.366649],"type":"Point"}
}