{
  "type": "Feature",
  "properties": {
    "iso:country":"US",
    "sg:address":"107 Kingston St",
    "sg:city":"Lenoir City",
    "sg:classifiers":[
        {
            "category":"Restaurant",
            "type":"Food & Drink"
        }
    ],
    "sg:phone":"+1 865 988 9263",
    "sg:postcode":"37771",
    "sg:province":"TN",
    "sg:tags":[
        "eating"
    ],
    "wof:name":"El Dorado Restaurant",
    "wof:placetype":"venue"
},
  "geometry": {"coordinates":[-84.26511499999999,35.792113],"type":"Point"}
}