{
  "type": "Feature",
  "properties": {
    "iso:country":"US",
    "sg:address":"2001 Station Loop",
    "sg:city":"Spring Hill",
    "sg:classifiers":[
        {
            "category":"Shopping",
            "subcategory":"Gifts & Souvenirs",
            "type":"Retail Goods"
        }
    ],
    "sg:phone":"+1 615 302 1045",
    "sg:postcode":"37174",
    "sg:province":"TN",
    "sg:tags":[
        "collectible"
    ],
    "wof:name":"Dugouts",
    "wof:placetype":"venue"
},
  "geometry": {"coordinates":[-86.955196,35.716234],"type":"Point"}
}