{
  "type": "Feature",
  "properties": {
    "iso:country":"US",
    "sg:address":"509 Crocus Ct",
    "sg:city":"Murfreesboro",
    "sg:classifiers":[
        {
            "category":"Bars & Pubs",
            "type":"Food & Drink"
        }
    ],
    "sg:phone":"+1 615 867 1446",
    "sg:postcode":"37128",
    "sg:province":"TN",
    "sg:tags":[
        "drinking"
    ],
    "wof:name":"Hoss Corral",
    "wof:placetype":"venue"
},
  "geometry": {"coordinates":[-86.40503,35.811627],"type":"Point"}
}