{
  "type": "Feature",
  "properties": {
    "iso:country":"US",
    "sg:address":"3898 Jackson Ave",
    "sg:city":"Memphis",
    "sg:classifiers":[
        {
            "category":"Manufacturing",
            "subcategory":"Tools & Machinery",
            "type":"Manufacturing & Wholesale Goods"
        }
    ],
    "sg:phone":"+1 901 372 0620",
    "sg:postcode":"38128",
    "sg:province":"TN",
    "sg:tags":[
        "armature",
        "rewinding",
        "mfg"
    ],
    "wof:name":"Daves Armature Service",
    "wof:placetype":"venue"
},
  "geometry": {"coordinates":[-89.931685,35.184543],"type":"Point"}
}