{
  "type": "Feature",
  "properties": {
    "addr:full":"600 N Spring St Sparta TN 38583",
    "addr:housenumber":"600",
    "addr:postcode":"38583",
    "addr:street":"N Spring St",
    "iso:country":"US",
    "sg:address":"600 N Spring St",
    "sg:city":"Sparta",
    "sg:classifiers":[
        {
            "category":"Government",
            "subcategory":"Office",
            "type":"Public Place"
        }
    ],
    "sg:phone":"+1 931 836 8000",
    "sg:postcode":"38583",
    "sg:province":"TN",
    "sg:tags":[
        "safety"
    ],
    "wof:name":"Highway Patrol",
    "wof:placetype":"venue"
},
  "geometry": {"coordinates":[-85.481838,35.961113],"type":"Point"}
}