{
  "type": "Feature",
  "properties": {
    "iso:country":"US",
    "sg:address":"9111 Cross Park Dr NW",
    "sg:city":"Knoxville",
    "sg:classifiers":[
        {
            "category":"Shopping",
            "subcategory":"Computers & Home Electronics",
            "type":"Retail Goods"
        }
    ],
    "sg:phone":"+1 865 602 2244",
    "sg:postcode":"37923",
    "sg:province":"TN",
    "sg:tags":[
        "software"
    ],
    "wof:name":"Innovative Computer Syst Inc",
    "wof:placetype":"venue"
},
  "geometry": {"coordinates":[-84.091486,35.920967],"type":"Point"}
}