{
  "type": "Feature",
  "properties": {
    "addr:full":"208 W Broad St Livingston TN 38570",
    "addr:housenumber":"208",
    "addr:postcode":"38570",
    "addr:street":"W Broad St",
    "iso:country":"US",
    "sg:address":"208 W Broad St",
    "sg:city":"Livingston",
    "sg:classifiers":[
        {
            "category":"Building & Trades",
            "subcategory":"Construction",
            "type":"Services"
        }
    ],
    "sg:phone":"+1 931 823 7803",
    "sg:postcode":"38570",
    "sg:province":"TN",
    "sg:tags":[
        "line",
        "telephone"
    ],
    "wof:name":"Phillips Industries Inc",
    "wof:placetype":"venue"
},
  "geometry": {"coordinates":[-85.323533,36.383726],"type":"Point"}
}