{
  "type": "Feature",
  "properties": {
    "iso:country":"US",
    "sg:address":"1020 Dallas Rd",
    "sg:city":"Chattanooga",
    "sg:classifiers":[
        {
            "category":"Education",
            "subcategory":"School",
            "type":"Public Place"
        },
        {
            "category":"Professional",
            "subcategory":"Accounting & Tax Preparation",
            "type":"Services"
        }
    ],
    "sg:phone":"+1 423 265 8317",
    "sg:postcode":"37405",
    "sg:province":"TN",
    "wof:name":"Brookstone College",
    "wof:placetype":"venue"
},
  "geometry": {"coordinates":[-85.30549600000001,35.073808],"type":"Point"}
}