{
  "type": "Feature",
  "properties": {
    "iso:country":"US",
    "sg:address":"1635 Fort Campbell Blvd",
    "sg:city":"Clarksville",
    "sg:classifiers":[
        {
            "category":"Retail",
            "subcategory":"Auto Repair",
            "type":"Services"
        }
    ],
    "sg:phone":"+1 931 552 0606",
    "sg:postcode":"37042",
    "sg:province":"TN",
    "sg:tags":[
        "automotive"
    ],
    "wof:name":"Pennzoil",
    "wof:placetype":"venue"
},
  "geometry": {"coordinates":[-87.407867,36.575504],"type":"Point"}
}