{
  "type": "Feature",
  "properties": {
    "iso:country":"US",
    "sg:address":"4205 E Andrew Johnson Hwy",
    "sg:city":"Morristown",
    "sg:classifiers":[
        {
            "category":"Retail",
            "subcategory":"Auto Repair",
            "type":"Services"
        }
    ],
    "sg:phone":"+1 423 581 3702",
    "sg:postcode":"37814",
    "sg:province":"TN",
    "sg:tags":[
        "body",
        "automobile",
        "painting"
    ],
    "wof:name":"Kenny's Paint & Body Shop",
    "wof:placetype":"venue"
},
  "geometry": {"coordinates":[-83.23778299999999,36.23702],"type":"Point"}
}