{
  "type": "Feature",
  "properties": {
    "iso:country":"US",
    "sg:address":"1704 Lawnville Rd",
    "sg:city":"Kingston",
    "sg:classifiers":[
        {
            "category":"Professional",
            "subcategory":"Computer Services",
            "type":"Services"
        }
    ],
    "sg:phone":"+1 865 376 0591",
    "sg:postcode":"37763",
    "sg:province":"TN",
    "sg:tags":[
        "development",
        "consulting",
        "software"
    ],
    "wof:name":"Tech Inroads Inc",
    "wof:placetype":"venue"
},
  "geometry": {"coordinates":[-84.457045,35.876833],"type":"Point"}
}