{
  "type": "Feature",
  "properties": {
    "iso:country":"US",
    "sg:address":"106 Oak St",
    "sg:city":"Lebanon",
    "sg:classifiers":[
        {
            "category":"Government",
            "subcategory":"Office",
            "type":"Public Place"
        }
    ],
    "sg:phone":"+1 615 444 9022",
    "sg:postcode":"37087",
    "sg:province":"TN",
    "wof:name":"Wilson County Road Commission",
    "wof:placetype":"venue"
},
  "geometry": {"coordinates":[-86.31281300000001,36.210764],"type":"Point"}
}