{
  "type": "Feature",
  "properties": {
    "iso:country":"US",
    "sg:address":"14625 Lebanon Rd",
    "sg:city":"Old Hickory",
    "sg:classifiers":[
        {
            "category":"Health Services",
            "subcategory":"Doctor",
            "type":"Services"
        }
    ],
    "sg:phone":"+1 615 754 0406",
    "sg:postcode":"37138",
    "sg:province":"TN",
    "sg:tags":[
        "dentist"
    ],
    "wof:name":"Kenneth G Witt DDS",
    "wof:placetype":"venue"
},
  "geometry": {"coordinates":[-86.570466,36.219503],"type":"Point"}
}