{
  "type": "Feature",
  "properties": {
    "addr:full":"721 Broad St Chattanooga TN 37402",
    "addr:housenumber":"721",
    "addr:postcode":"37402",
    "addr:street":"Broad St",
    "iso:country":"US",
    "sg:address":"721 Broad St",
    "sg:city":"Chattanooga",
    "sg:classifiers":[
        {
            "category":"Professional",
            "subcategory":"Accounting & Tax Preparation",
            "type":"Services"
        }
    ],
    "sg:phone":"+1 423 265 5997",
    "sg:postcode":"37402",
    "sg:province":"TN",
    "sg:tags":[
        "return",
        "filing"
    ],
    "wof:name":"Jackson Hewitt Tax Svc",
    "wof:placetype":"venue"
},
  "geometry": {"coordinates":[-85.31067299999999,35.047345],"type":"Point"}
}