{
  "type": "Feature",
  "properties": {
    "iso:country":"US",
    "sg:address":"254 Mayland Loop",
    "sg:city":"Crossville",
    "sg:classifiers":[
        {
            "category":"Organizations",
            "subcategory":"Religious Organization",
            "type":"Services"
        }
    ],
    "sg:phone":"+1 931 277 5482",
    "sg:postcode":"38571",
    "sg:province":"TN",
    "sg:tags":[
        "church"
    ],
    "wof:name":"Mayland Church Of The Nazarene",
    "wof:placetype":"venue"
},
  "geometry": {"coordinates":[-85.201384,36.049196],"type":"Point"}
}