{
  "type": "Feature",
  "properties": {
    "iso:country":"US",
    "sg:address":"5803 N Broadway St",
    "sg:city":"Knoxville",
    "sg:classifiers":[
        {
            "category":"Personal",
            "subcategory":"Beauty Salon",
            "type":"Services"
        }
    ],
    "sg:phone":"+1 865 687 0094",
    "sg:postcode":"37918",
    "sg:province":"TN",
    "sg:tags":[
        "shop",
        "manicuring"
    ],
    "wof:name":"Salon Teknik",
    "wof:placetype":"venue"
},
  "geometry": {"coordinates":[-83.92728,36.048472],"type":"Point"}
}