{
  "type": "Feature",
  "properties": {
    "iso:country":"US",
    "sg:address":"7304 S Colony Ct",
    "sg:city":"Nashville",
    "sg:classifiers":[
        {
            "category":"Shopping",
            "subcategory":"Gifts & Souvenirs",
            "type":"Retail Goods"
        }
    ],
    "sg:phone":"+1 615 646 8640",
    "sg:postcode":"37221",
    "sg:province":"TN",
    "wof:name":"Digi-Image",
    "wof:placetype":"venue"
},
  "geometry": {"coordinates":[-86.954599,36.052625],"type":"Point"}
}