{
  "type": "Feature",
  "properties": {
    "iso:country":"US",
    "sg:address":"2267 US Hwy 41 S",
    "sg:city":"Greenbrier",
    "sg:classifiers":[
        {
            "category":"Home & Garden",
            "subcategory":"Carpets & Floor Coverings",
            "type":"Retail Goods"
        }
    ],
    "sg:phone":"+1 615 643 3030",
    "sg:postcode":"37073",
    "sg:province":"TN",
    "sg:tags":[
        "material"
    ],
    "wof:name":"More Than Floors LLC",
    "wof:placetype":"venue"
},
  "geometry": {"coordinates":[-86.795396,36.417263],"type":"Point"}
}