{
  "type": "Feature",
  "properties": {
    "addr:full":"1235 McArthur St Manchester TN 37355",
    "addr:housenumber":"1235",
    "addr:postcode":"37355",
    "addr:street":"Mcarthur St",
    "iso:country":"US",
    "sg:address":"1235 McArthur St",
    "sg:city":"Manchester",
    "sg:classifiers":[
        {
            "category":"Wholesale",
            "subcategory":"Medical Equipment & Supplies",
            "type":"Manufacturing & Wholesale Goods"
        },
        {
            "category":"Health Services",
            "subcategory":"Clinic",
            "type":"Services"
        }
    ],
    "sg:phone":"+1 931 723 3780",
    "sg:postcode":"37355",
    "sg:province":"TN",
    "sg:tags":[
        "home",
        "physician",
        "surgeon",
        "care"
    ],
    "wof:name":"Respiratory At Home Corp",
    "wof:placetype":"venue"
},
  "geometry": {"coordinates":[-86.08779699999999,35.464314],"type":"Point"}
}