{
  "type": "Feature",
  "properties": {
    "iso:country":"US",
    "sg:address":"225 2nd Ave S",
    "sg:city":"Franklin",
    "sg:classifiers":[
        {
            "category":"Home & Garden",
            "subcategory":"Building Materials",
            "type":"Retail Goods"
        }
    ],
    "sg:phone":"+1 615 595 9872",
    "sg:postcode":"37064",
    "sg:province":"TN",
    "sg:tags":[
        "glass",
        "leaded"
    ],
    "wof:name":"Advantage Artglass",
    "wof:placetype":"venue"
},
  "geometry": {"coordinates":[-86.86595,35.923608],"type":"Point"}
}