{
  "type": "Feature",
  "properties": {
    "addr:full":"3909 Elvis Presley Blvd Memphis TN 38116",
    "addr:housenumber":"3909",
    "addr:postcode":"38116",
    "addr:street":"Elvis Presley Blvd",
    "iso:country":"US",
    "sg:address":"3909 Elvis Presley Blvd",
    "sg:city":"Memphis",
    "sg:classifiers":[
        {
            "category":"Shopping",
            "subcategory":"Gifts & Souvenirs",
            "type":"Retail Goods"
        }
    ],
    "sg:phone":"+1 901 348 1088",
    "sg:postcode":"38116",
    "sg:province":"TN",
    "sg:tags":[
        "shop"
    ],
    "wof:name":"Bobbie's Gift Shop",
    "wof:placetype":"venue"
},
  "geometry": {"coordinates":[-90.02518600000001,35.042386],"type":"Point"}
}