{
  "type": "Feature",
  "properties": {
    "addr:full":"703 Woodhaven Dr Johnson City TN 37604",
    "addr:housenumber":"703",
    "addr:postcode":"37604",
    "addr:street":"Woodhaven Dr",
    "iso:country":"US",
    "sg:address":"703 Woodhaven Dr",
    "sg:city":"Johnson City",
    "sg:classifiers":[
        {
            "category":"Real Estate",
            "subcategory":"Architect",
            "type":"Services"
        }
    ],
    "sg:phone":"+1 423 282 2306",
    "sg:postcode":"37604",
    "sg:province":"TN",
    "sg:tags":[
        "architectural"
    ],
    "wof:name":"Fred L Ward Architect",
    "wof:placetype":"venue"
},
  "geometry": {"coordinates":[-82.386629,36.338269],"type":"Point"}
}