{
  "type": "Feature",
  "properties": {
    "addr:full":"1312 Decatur Pike Athens TN 37303",
    "addr:housenumber":"1312",
    "addr:postcode":"37303",
    "addr:street":"Decatur Pike",
    "iso:country":"US",
    "sg:address":"1312 Decatur Pike",
    "sg:city":"Athens",
    "sg:classifiers":[
        {
            "category":"Food & Beverages",
            "subcategory":"Groceries & Convenience Stores",
            "type":"Retail Goods"
        }
    ],
    "sg:phone":"+1 423 744 7594",
    "sg:postcode":"37303",
    "sg:province":"TN",
    "sg:tags":[
        "grocer"
    ],
    "sg:website":"www.foodlion.com",
    "wof:name":"Food Lion",
    "wof:placetype":"venue"
},
  "geometry": {"coordinates":[-84.61447099999999,35.44865],"type":"Point"}
}