{
  "type": "Feature",
  "properties": {
    "iso:country":"US",
    "sg:address":"505 Monte Vista Dr",
    "sg:city":"Kingsport",
    "sg:classifiers":[
        {
            "category":"Professional",
            "subcategory":"Employment Agencies",
            "type":"Services"
        }
    ],
    "sg:phone":"+1 423 288 7034",
    "sg:postcode":"37660",
    "sg:province":"TN",
    "wof:name":"Hampshire Group",
    "wof:placetype":"venue"
},
  "geometry": {"coordinates":[-82.526339,36.57895],"type":"Point"}
}