{
  "type": "Feature",
  "properties": {
    "iso:country":"US",
    "sg:address":"1140 N Gateway Ave",
    "sg:city":"Rockwood",
    "sg:classifiers":[
        {
            "category":"Shopping",
            "subcategory":"Clothing, Apparel, & Fashions",
            "type":"Retail Goods"
        }
    ],
    "sg:phone":"+1 865 354 4554",
    "sg:postcode":"37854",
    "sg:province":"TN",
    "sg:website":"www.catofashions.com",
    "wof:name":"Cato",
    "wof:placetype":"venue"
},
  "geometry": {"coordinates":[-84.66836000000001,35.878834],"type":"Point"}
}