{
  "type": "Feature",
  "properties": {
    "addr:full":"2046 Upper Middle Creek Rd Sevierville TN 37876",
    "addr:housenumber":"2046",
    "addr:postcode":"37876",
    "addr:street":"Upper Middle Creek Rd",
    "iso:country":"US",
    "sg:address":"2046 Upper Middle Creek Rd",
    "sg:city":"Sevierville",
    "sg:classifiers":[
        {
            "category":"Real Estate",
            "subcategory":"Real Estate Agent",
            "type":"Services"
        }
    ],
    "sg:phone":"+1 865 774 7893",
    "sg:postcode":"37876",
    "sg:province":"TN",
    "wof:name":"Smoky Mountain Escapes",
    "wof:placetype":"venue"
},
  "geometry": {"coordinates":[-83.486188,35.790492],"type":"Point"}
}