{
  "type": "Feature",
  "properties": {
    "addr:full":"3509 Gainsville Rd Mason TN 38049",
    "addr:housenumber":"3509",
    "addr:postcode":"38049",
    "addr:street":"Gainsville Rd",
    "iso:country":"US",
    "sg:address":"3509 Gainsville Rd",
    "sg:city":"Mason",
    "sg:classifiers":[
        {
            "category":"Arts & Performance",
            "subcategory":"Theater",
            "type":"Entertainment"
        }
    ],
    "sg:phone":"+1 901 294 3264",
    "sg:postcode":"38049",
    "sg:province":"TN",
    "sg:tags":[
        "group"
    ],
    "wof:name":"Shady Tree Fun Farm",
    "wof:placetype":"venue"
},
  "geometry": {"coordinates":[-89.59728800000001,35.413415],"type":"Point"}
}