{
  "type": "Feature",
  "properties": {
    "iso:country":"US",
    "sg:address":"483 Davidson St",
    "sg:city":"Nashville",
    "sg:phone":"+1 615 254 5731",
    "sg:postcode":"37206",
    "sg:province":"TN",
    "sg:tags":[
        "oil"
    ],
    "wof:name":"Kimbro Oil Co",
    "wof:placetype":"venue"
},
  "geometry": {"coordinates":[-86.759944,36.161079],"type":"Point"}
}