{
  "type": "Feature",
  "properties": {
    "addr:full":"3001 Gallatin Pike Nashville TN 37216",
    "addr:housenumber":"3001",
    "addr:postcode":"37216",
    "addr:street":"Gallatin Pike",
    "iso:country":"US",
    "sg:address":"3001 Gallatin Pike",
    "sg:city":"Nashville",
    "sg:classifiers":[
        {
            "category":"Restaurant",
            "type":"Food & Drink"
        }
    ],
    "sg:phone":"+1 615 228 6584",
    "sg:postcode":"37216",
    "sg:province":"TN",
    "sg:tags":[
        "eating"
    ],
    "sg:website":"www.checkers.com",
    "wof:name":"Checkers Drive-In Restaurant",
    "wof:placetype":"venue"
},
  "geometry": {"coordinates":[-86.73853099999999,36.203551],"type":"Point"}
}