{
  "type": "Feature",
  "properties": {
    "addr:full":"304 E Meeting St Dandridge TN 37725",
    "addr:housenumber":"304",
    "addr:postcode":"37725",
    "addr:street":"E Meeting St",
    "iso:country":"US",
    "sg:address":"304 E Meeting St",
    "sg:city":"Dandridge",
    "sg:classifiers":[
        {
            "category":"Social Services",
            "subcategory":"Child Care",
            "type":"Services"
        }
    ],
    "sg:phone":"+1 865 397 3500",
    "sg:postcode":"37725",
    "sg:province":"TN",
    "sg:tags":[
        "day"
    ],
    "wof:name":"Miss Karens",
    "wof:placetype":"venue"
},
  "geometry": {"coordinates":[-83.40782,36.021444],"type":"Point"}
}