{
  "type": "Feature",
  "properties": {
    "iso:country":"US",
    "sg:address":"1105 W College St",
    "sg:city":"Murfreesboro",
    "sg:classifiers":[
        {
            "category":"Building & Trades",
            "subcategory":"Electrical",
            "type":"Services"
        }
    ],
    "sg:phone":"+1 615 896 4265",
    "sg:postcode":"37129",
    "sg:province":"TN",
    "sg:tags":[
        "electric",
        "contractor"
    ],
    "wof:name":"Creasey Electric",
    "wof:placetype":"venue"
},
  "geometry": {"coordinates":[-86.404805,35.855413],"type":"Point"}
}