{
  "type": "Feature",
  "properties": {
    "iso:country":"US",
    "sg:address":"6761 Winchester Rd",
    "sg:city":"Memphis",
    "sg:classifiers":[
        {
            "category":"Restaurant",
            "type":"Food & Drink"
        }
    ],
    "sg:phone":"+1 901 257 1756",
    "sg:postcode":"38115",
    "sg:province":"TN",
    "wof:name":"Stewart's Bar & Grill",
    "wof:placetype":"venue"
},
  "geometry": {"coordinates":[-89.837962,35.0493],"type":"Point"}
}