{
  "type": "Feature",
  "properties": {
    "addr:full":"8530 Hixson Pike Hixson TN 37343",
    "addr:housenumber":"8530",
    "addr:postcode":"37343",
    "addr:street":"Hixson Pike",
    "iso:country":"US",
    "sg:address":"8530 Hixson Pike",
    "sg:city":"Hixson",
    "sg:classifiers":[
        {
            "category":"Shopping",
            "subcategory":"Pharmacy",
            "type":"Retail Goods"
        }
    ],
    "sg:phone":"+1 423 842 2197",
    "sg:postcode":"37343",
    "sg:province":"TN",
    "wof:name":"CVS",
    "wof:placetype":"venue"
},
  "geometry": {"coordinates":[-85.160146,35.199925],"type":"Point"}
}