{
  "type": "Feature",
  "properties": {
    "iso:country":"US",
    "sg:address":"155 Doster Rd",
    "sg:city":"Mc Kenzie",
    "sg:classifiers":[
        {
            "category":"Building & Trades",
            "subcategory":"Construction",
            "type":"Services"
        }
    ],
    "sg:phone":"+1 731 352 7158",
    "sg:postcode":"38201",
    "sg:province":"TN",
    "sg:tags":[
        "house"
    ],
    "wof:name":"Moore Builder James",
    "wof:placetype":"venue"
},
  "geometry": {"coordinates":[-88.55185899999999,36.166418],"type":"Point"}
}