{
  "type": "Feature",
  "properties": {
    "addr:full":"1408 E 3rd St Corinth TN 38834",
    "addr:housenumber":"1408",
    "addr:postcode":"38834",
    "addr:street":"E 3Rd St",
    "iso:country":"US",
    "sg:address":"1408 E 3rd St",
    "sg:city":"Corinth",
    "sg:classifiers":[
        {
            "category":"Organizations",
            "subcategory":"Religious Organization",
            "type":"Services"
        }
    ],
    "sg:phone":"+1 662 286 6577",
    "sg:postcode":"38834",
    "sg:province":"TN",
    "sg:tags":[
        "clergy"
    ],
    "wof:name":"Hall's Of Faith Inc",
    "wof:placetype":"venue"
},
  "geometry": {"coordinates":[-88.505466,34.941519],"type":"Point"}
}