{
  "type": "Feature",
  "properties": {
    "iso:country":"US",
    "sg:address":"1111 Workman Rd",
    "sg:city":"Chattanooga",
    "sg:classifiers":[
        {
            "category":"Freight",
            "type":"Transportation"
        }
    ],
    "sg:phone":"+1 423 821 0502",
    "sg:postcode":"37410",
    "sg:province":"TN",
    "sg:tags":[
        "broker",
        "trucking"
    ],
    "wof:name":"Tankstar",
    "wof:placetype":"venue"
},
  "geometry": {"coordinates":[-85.302396,34.994427],"type":"Point"}
}