{
  "type": "Feature",
  "properties": {
    "iso:country":"US",
    "sg:address":"1509 Old Cowan Rd",
    "sg:city":"Winchester",
    "sg:classifiers":[
        {
            "category":"Health Services",
            "subcategory":"Doctor",
            "type":"Services"
        }
    ],
    "sg:phone":"+1 931 962 1004",
    "sg:postcode":"37398",
    "sg:province":"TN",
    "sg:tags":[
        "medical"
    ],
    "wof:name":"Doctors Office",
    "wof:placetype":"venue"
},
  "geometry": {"coordinates":[-86.094313,35.181017],"type":"Point"}
}