{
  "type": "Feature",
  "properties": {
    "iso:country":"US",
    "sg:address":"209 Bellevue Rd",
    "sg:city":"Nashville",
    "sg:classifiers":[
        {
            "category":"Place Of Worship",
            "subcategory":"Church",
            "type":"Public Place"
        },
        {
            "category":"Place Of Worship",
            "type":"Public Place"
        }
    ],
    "sg:phone":"+1 615 646 4030",
    "sg:postcode":"37221",
    "sg:province":"TN",
    "sg:tags":[
        "churches-presbyterian-arp",
        "churches-presbyterian"
    ],
    "wof:name":"West Side Cumberland Presbyterian Church",
    "wof:placetype":"venue"
},
  "geometry": {"coordinates":[-86.92921200000001,36.062849],"type":"Point"}
}