{
  "type": "Feature",
  "properties": {
    "iso:country":"US",
    "sg:address":"1011 Oscar Armstrong Rd",
    "sg:city":"Knoxville",
    "sg:classifiers":[
        {
            "category":"Building & Trades",
            "subcategory":"Construction",
            "type":"Services"
        }
    ],
    "sg:phone":"+1 865 933 7298",
    "sg:postcode":"37914",
    "sg:province":"TN",
    "sg:tags":[
        "contractor"
    ],
    "wof:name":"Gable Contractors",
    "wof:placetype":"venue"
},
  "geometry": {"coordinates":[-83.74369900000001,36.003705],"type":"Point"}
}