{
  "type": "Feature",
  "properties": {
    "iso:country":"US",
    "sg:address":"105 Forrest Ave N",
    "sg:city":"Lookout Mountain",
    "sg:classifiers":[
        {
            "category":"Banks & Credit Unions",
            "subcategory":"Investment Brokerage",
            "type":"Services"
        }
    ],
    "sg:phone":"+1 423 821 0111",
    "sg:postcode":"37350",
    "sg:province":"TN",
    "sg:tags":[
        "security"
    ],
    "wof:name":"North Forest LLC",
    "wof:placetype":"venue"
},
  "geometry": {"coordinates":[-85.347773,34.994355],"type":"Point"}
}