{
  "type": "Feature",
  "properties": {
    "iso:country":"US",
    "sg:address":"4854 Millbranch Rd",
    "sg:city":"Memphis",
    "sg:classifiers":[
        {
            "category":"Organizations",
            "subcategory":"Religious Organization",
            "type":"Services"
        }
    ],
    "sg:phone":"+1 901 398 4504",
    "sg:postcode":"38116",
    "sg:province":"TN",
    "sg:tags":[
        "church"
    ],
    "wof:name":"New Beginning MB Church",
    "wof:placetype":"venue"
},
  "geometry": {"coordinates":[-90.00749999999999,35.015988],"type":"Point"}
}