{
  "type": "Feature",
  "properties": {
    "iso:country":"US",
    "sg:address":"1807 Waters Edge Dr",
    "sg:city":"Johnson City",
    "sg:classifiers":[
        {
            "category":"Building & Trades",
            "subcategory":"Cleaning & Sanitation",
            "type":"Services"
        }
    ],
    "sg:phone":"+1 423 282 5538",
    "sg:postcode":"37604",
    "sg:province":"TN",
    "sg:tags":[
        "janitor",
        "maintenance"
    ],
    "wof:name":"Reliable Janitorial Service",
    "wof:placetype":"venue"
},
  "geometry": {"coordinates":[-82.387124,36.32814],"type":"Point"}
}