{
  "type": "Feature",
  "properties": {
    "addr:full":"670 New York St Memphis TN 38104",
    "addr:housenumber":"670",
    "addr:postcode":"38104",
    "addr:street":"New York St",
    "iso:country":"US",
    "sg:address":"670 New York St",
    "sg:city":"Memphis",
    "sg:classifiers":[
        {
            "category":"Banks & Credit Unions",
            "subcategory":"Financial Services",
            "type":"Services"
        }
    ],
    "sg:phone":"+1 901 274 3347",
    "sg:postcode":"38104",
    "sg:province":"TN",
    "sg:tags":[
        "international",
        "exporter",
        "trade"
    ],
    "sg:website":"http://www.chemicar.com",
    "wof:name":"Chemicar USA",
    "wof:placetype":"venue"
},
  "geometry": {"coordinates":[-89.987083,35.126333],"type":"Point"}
}