{
  "type": "Feature",
  "properties": {
    "iso:country":"US",
    "sg:address":"410 W Main St",
    "sg:city":"Mountain City",
    "sg:classifiers":[
        {
            "category":"Professional",
            "subcategory":"Lawyer & Legal Services",
            "type":"Services"
        }
    ],
    "sg:phone":"+1 423 727 9671",
    "sg:postcode":"37683",
    "sg:province":"TN",
    "sg:tags":[
        "attorney"
    ],
    "wof:name":"Grayson & Wright",
    "wof:placetype":"venue"
},
  "geometry": {"coordinates":[-81.80895099999999,36.475963],"type":"Point"}
}