{
  "type": "Feature",
  "properties": {
    "iso:country":"US",
    "sg:address":"1147 Tusculum Blvd",
    "sg:city":"Greeneville",
    "sg:classifiers":[
        {
            "category":"Autos & Motor Vehicles",
            "subcategory":"Automobile Sales",
            "type":"Retail Goods"
        }
    ],
    "sg:phone":"+1 423 638 2838",
    "sg:postcode":"37745",
    "sg:province":"TN",
    "sg:tags":[
        "car",
        "dealer"
    ],
    "wof:name":"E-Z Deal Auto Sales",
    "wof:placetype":"venue"
},
  "geometry": {"coordinates":[-82.804675,36.170179],"type":"Point"}
}