{
  "type": "Feature",
  "properties": {
    "addr:full":"4771 Knight Arnold Rd Memphis TN 38118",
    "addr:housenumber":"4771",
    "addr:postcode":"38118",
    "addr:street":"Knight Arnold Rd",
    "iso:country":"US",
    "sg:address":"4771 Knight Arnold Rd",
    "sg:city":"Memphis",
    "sg:classifiers":[
        {
            "category":"Personal",
            "subcategory":"Beauty Salon",
            "type":"Services"
        }
    ],
    "sg:phone":"+1 901 360 9074",
    "sg:postcode":"38118",
    "sg:province":"TN",
    "sg:tags":[
        "shop"
    ],
    "wof:name":"Simply U Hair & Nail Salon",
    "wof:placetype":"venue"
},
  "geometry": {"coordinates":[-89.903875,35.062265],"type":"Point"}
}