{
  "type": "Feature",
  "properties": {
    "iso:country":"US",
    "sg:address":"100 Vann Dr",
    "sg:city":"Jackson",
    "sg:classifiers":[
        {
            "category":"Home & Garden",
            "subcategory":"Home Furnishings",
            "type":"Retail Goods"
        }
    ],
    "sg:phone":"+1 731 668 5441",
    "sg:postcode":"38305",
    "sg:province":"TN",
    "sg:tags":[
        "accessory"
    ],
    "wof:name":"Ambrosia",
    "wof:placetype":"venue"
},
  "geometry": {"coordinates":[-88.83120599999999,35.672481],"type":"Point"}
}