{
  "type": "Feature",
  "properties": {
    "addr:full":"253 W 7th St Cookeville TN 38501",
    "addr:housenumber":"253",
    "addr:postcode":"38501",
    "addr:street":"W 7Th St",
    "iso:country":"US",
    "sg:address":"253 W 7th St",
    "sg:city":"Cookeville",
    "sg:classifiers":[
        {
            "category":"Professional",
            "subcategory":"Business Services",
            "type":"Services"
        }
    ],
    "sg:phone":"+1 931 520 7475",
    "sg:postcode":"38501",
    "sg:province":"TN",
    "wof:name":"Cobblestone Corner Auctn Antq",
    "wof:placetype":"venue"
},
  "geometry": {"coordinates":[-85.511616,36.172343],"type":"Point"}
}