{
  "type": "Feature",
  "properties": {
    "iso:country":"US",
    "sg:address":"5726 Marlin Rd",
    "sg:city":"Chattanooga",
    "sg:classifiers":[
        {
            "category":"Health Services",
            "subcategory":"Doctor",
            "type":"Services"
        },
        {
            "category":"Health Services",
            "subcategory":"Clinic",
            "type":"Services"
        }
    ],
    "sg:phone":"+1 423 718 1040",
    "sg:postcode":"37411",
    "sg:province":"TN",
    "sg:tags":[
        "physician",
        "surgeon",
        "mental",
        "information"
    ],
    "wof:name":"Coping Concepts Clinical Services Inc",
    "wof:placetype":"venue"
},
  "geometry": {"coordinates":[-85.20988,35.008793],"type":"Point"}
}