{
  "type": "Feature",
  "properties": {
    "iso:country":"US",
    "sg:address":"102 Hickory Heights Dr",
    "sg:city":"Hendersonville",
    "sg:classifiers":[
        {
            "category":"Building & Trades",
            "subcategory":"Electrical",
            "type":"Services"
        },
        {
            "category":"Building & Trades",
            "subcategory":"Plumbing",
            "type":"Services"
        }
    ],
    "sg:phone":"+1 615 824 5386",
    "sg:postcode":"37075",
    "sg:province":"TN",
    "sg:tags":[
        "electrical",
        "electric",
        "contractor"
    ],
    "wof:name":"Bradford Electric Company",
    "wof:placetype":"venue"
},
  "geometry": {"coordinates":[-86.621138,36.285758],"type":"Point"}
}