{
  "type": "Feature",
  "properties": {
    "iso:country":"US",
    "sg:address":"170 Harvester Ave",
    "sg:city":"Lawrenceburg",
    "sg:classifiers":[
        {
            "category":"Organizations",
            "subcategory":"Religious Organization",
            "type":"Services"
        }
    ],
    "sg:phone":"+1 931 762 9106",
    "sg:postcode":"38464",
    "sg:province":"TN",
    "sg:tags":[
        "church"
    ],
    "wof:name":"Lawrenceburg Congregation",
    "wof:placetype":"venue"
},
  "geometry": {"coordinates":[-87.29272400000001,35.240697],"type":"Point"}
}