{
  "type": "Feature",
  "properties": {
    "iso:country":"US",
    "sg:address":"205 S 10th St",
    "sg:city":"Nashville",
    "sg:classifiers":[
        {
            "category":"Health Services",
            "subcategory":"Hospital",
            "type":"Services"
        }
    ],
    "sg:phone":"+1 615 226 1077",
    "sg:postcode":"37206",
    "sg:province":"TN",
    "sg:tags":[
        "center",
        "birth"
    ],
    "wof:name":"East End Women's Health & Brth",
    "wof:placetype":"venue"
},
  "geometry": {"coordinates":[-86.751632,36.175707],"type":"Point"}
}