{
  "type": "Feature",
  "properties": {
    "iso:country":"US",
    "sg:address":"3901 Asheville Hwy",
    "sg:city":"Knoxville",
    "sg:classifiers":[
        {
            "category":"Banks & Credit Unions",
            "subcategory":"Bank",
            "type":"Services"
        }
    ],
    "sg:phone":"+1 865 521 0739",
    "sg:postcode":"37914",
    "sg:province":"TN",
    "sg:tags":[
        "cashing",
        "check"
    ],
    "wof:name":"A 1 Check Cash Advance",
    "wof:placetype":"venue"
},
  "geometry": {"coordinates":[-83.876216,36.000547],"type":"Point"}
}