{
  "type": "Feature",
  "properties": {
    "addr:full":"6565 Buncombe Rd Huntland TN 37345",
    "addr:housenumber":"6565",
    "addr:postcode":"37345",
    "addr:street":"Buncombe Rd",
    "iso:country":"US",
    "sg:address":"6565 Buncombe Rd",
    "sg:city":"Huntland",
    "sg:classifiers":[
        {
            "category":"Home & Garden",
            "subcategory":"Garden Supply",
            "type":"Retail Goods"
        }
    ],
    "sg:phone":"+1 931 469 8002",
    "sg:postcode":"37345",
    "sg:province":"TN",
    "sg:tags":[
        "nurseryman"
    ],
    "wof:name":"Lantenn Farms Inc",
    "wof:placetype":"venue"
},
  "geometry": {"coordinates":[-86.213114,35.069393],"type":"Point"}
}