{
  "type": "Feature",
  "properties": {
    "addr:full":"1659 Sydney St Memphis TN 38108",
    "addr:housenumber":"1659",
    "addr:postcode":"38108",
    "addr:street":"Sydney St",
    "iso:country":"US",
    "sg:address":"1659 Sydney St",
    "sg:city":"Memphis",
    "sg:classifiers":[
        {
            "category":"Building & Trades",
            "subcategory":"Landscaping Services",
            "type":"Services"
        }
    ],
    "sg:phone":"+1 901 452 0582",
    "sg:postcode":"38108",
    "sg:province":"TN",
    "sg:tags":[
        "lawn",
        "maintenance"
    ],
    "wof:name":"Good Friday Lawn Services",
    "wof:placetype":"venue"
},
  "geometry": {"coordinates":[-89.96010699999999,35.177801],"type":"Point"}
}