{
  "type": "Feature",
  "properties": {
    "iso:country":"US",
    "sg:address":"1918 Shady Brook St",
    "sg:city":"Columbia",
    "sg:classifiers":[
        {
            "category":"Restaurant",
            "type":"Food & Drink"
        }
    ],
    "sg:phone":"+1 931 540 8989",
    "sg:postcode":"38401",
    "sg:province":"TN",
    "sg:tags":[
        "eating"
    ],
    "wof:name":"China King Buffet",
    "wof:placetype":"venue"
},
  "geometry": {"coordinates":[-87.057732,35.599962],"type":"Point"}
}