{
  "type": "Feature",
  "properties": {
    "iso:country":"US",
    "sg:address":"1702 Charlotte Ave",
    "sg:city":"Nashville",
    "sg:classifiers":[
        {
            "category":"Health Services",
            "subcategory":"Clinic",
            "type":"Services"
        },
        {
            "category":"Personal",
            "type":"Services"
        },
        {
            "category":"Health Services",
            "subcategory":"Health Practitioner",
            "type":"Services"
        }
    ],
    "sg:phone":"+1 615 269 0029",
    "sg:postcode":"37203",
    "sg:province":"TN",
    "sg:tags":[
        "information",
        "counselors-licensed",
        "abuse",
        "drug",
        "professional",
        "addiction",
        "alcoholism",
        "treatment"
    ],
    "wof:name":"Alcohol & Drug Council Of Middle Tennessee",
    "wof:placetype":"venue"
},
  "geometry": {"coordinates":[-86.798391,36.158717],"type":"Point"}
}