{
  "type": "Feature",
  "properties": {
    "iso:country":"US",
    "sg:address":"530 3rd Ave S",
    "sg:city":"Nashville",
    "sg:classifiers":[
        {
            "category":"Retail",
            "subcategory":"Repair Shop",
            "type":"Services"
        }
    ],
    "sg:phone":"+1 615 244 5454",
    "sg:postcode":"37210",
    "sg:province":"TN",
    "sg:tags":[
        "appliance"
    ],
    "wof:name":"Homesmart Appliance Repair",
    "wof:placetype":"venue"
},
  "geometry": {"coordinates":[-86.771896,36.155125],"type":"Point"}
}