{
  "type": "Feature",
  "properties": {
    "addr:full":"6202 Winchester Rd Memphis TN 38115",
    "addr:housenumber":"6202",
    "addr:postcode":"38115",
    "addr:street":"Winchester Rd",
    "iso:country":"US",
    "sg:address":"6202 Winchester Rd",
    "sg:city":"Memphis",
    "sg:classifiers":[
        {
            "category":"Professional",
            "subcategory":"Accounting & Tax Preparation",
            "type":"Services"
        }
    ],
    "sg:phone":"+1 901 366 2001",
    "sg:postcode":"38115",
    "sg:province":"TN",
    "sg:tags":[
        "return",
        "filing"
    ],
    "sg:website":"www.hrblock.com",
    "wof:name":"H & R Block Tax Svc",
    "wof:placetype":"venue"
},
  "geometry": {"coordinates":[-89.85366999999999,35.049746],"type":"Point"}
}