{
  "type": "Feature",
  "properties": {
    "iso:country":"US",
    "sg:address":"103 Falcon Dr",
    "sg:city":"Byrdstown",
    "sg:classifiers":[
        {
            "category":"Retail",
            "subcategory":"Portrait Studio",
            "type":"Services"
        }
    ],
    "sg:phone":"+1 931 864 6018",
    "sg:postcode":"38549",
    "sg:province":"TN",
    "sg:tags":[
        "photo"
    ],
    "wof:name":"Eagles Cove Photography",
    "wof:placetype":"venue"
},
  "geometry": {"coordinates":[-85.23949,36.619274],"type":"Point"}
}