{
  "type": "Feature",
  "properties": {
    "iso:country":"US",
    "sg:address":"109 Castle Heights Ave N",
    "sg:city":"Lebanon",
    "sg:classifiers":[
        {
            "category":"Professional",
            "subcategory":"Lawyer & Legal Services",
            "type":"Services"
        }
    ],
    "sg:phone":"+1 615 443 8757",
    "sg:postcode":"37087",
    "sg:province":"TN",
    "wof:name":"David B Foutch",
    "wof:placetype":"venue"
},
  "geometry": {"coordinates":[-86.307351,36.211134],"type":"Point"}
}