{
  "type": "Feature",
  "properties": {
    "iso:country":"US",
    "sg:address":"1216 Industrial Park Rd",
    "sg:city":"Columbia",
    "sg:classifiers":[
        {
            "category":"Government",
            "subcategory":"Office",
            "type":"Public Place"
        }
    ],
    "sg:phone":"+1 931 388 2432",
    "sg:postcode":"38401",
    "sg:province":"TN",
    "wof:name":"Maury County Pupil Trans",
    "wof:placetype":"venue"
},
  "geometry": {"coordinates":[-87.068113,35.644707],"type":"Point"}
}