{
  "type": "Feature",
  "properties": {
    "iso:country":"US",
    "sg:address":"6016 Forked Deer Rd",
    "sg:city":"Gates",
    "sg:classifiers":[
        {
            "category":"Farming",
            "subcategory":"Farm",
            "type":"Manufacturing & Wholesale Goods"
        }
    ],
    "sg:phone":"+1 731 836 5195",
    "sg:postcode":"38037",
    "sg:province":"TN",
    "sg:tags":[
        "crop",
        "general"
    ],
    "wof:name":"Keith Warren",
    "wof:placetype":"venue"
},
  "geometry": {"coordinates":[-89.385751,35.770298],"type":"Point"}
}