{
  "type": "Feature",
  "properties": {
    "iso:country":"US",
    "sg:address":"1907 Old Murfreesboro Pike",
    "sg:city":"Nashville",
    "sg:classifiers":[
        {
            "category":"Wholesale",
            "subcategory":"Electrical",
            "type":"Manufacturing & Wholesale Goods"
        }
    ],
    "sg:phone":"+1 615 399 9963",
    "sg:postcode":"37217",
    "sg:province":"TN",
    "sg:tags":[
        "control",
        "security",
        "system"
    ],
    "wof:name":"Alert America Of Tennessee Inc",
    "wof:placetype":"venue"
},
  "geometry": {"coordinates":[-86.661721,36.101713],"type":"Point"}
}