{
  "type": "Feature",
  "properties": {
    "iso:country":"US",
    "sg:address":"9692 Bradley Creek Rd",
    "sg:city":"Milton",
    "sg:classifiers":[
        {
            "category":"Freight",
            "type":"Transportation"
        }
    ],
    "sg:phone":"+1 615 273 2181",
    "sg:postcode":"37118",
    "sg:province":"TN",
    "sg:tags":[
        "operator",
        "trucking"
    ],
    "wof:name":"Mike Lewis Trucking",
    "wof:placetype":"venue"
},
  "geometry": {"coordinates":[-86.229578,35.939481],"type":"Point"}
}