{
  "type": "Feature",
  "properties": {
    "addr:full":"5721 Lee Hwy Chattanooga TN 37421",
    "addr:housenumber":"5721",
    "addr:postcode":"37421",
    "addr:street":"Lee Hwy",
    "iso:country":"US",
    "sg:address":"5721 Lee Hwy",
    "sg:city":"Chattanooga",
    "sg:classifiers":[
        {
            "category":"Autos & Motor Vehicles",
            "subcategory":"Automobile Sales",
            "type":"Retail Goods"
        }
    ],
    "sg:phone":"+1 423 892 8310",
    "sg:postcode":"37421",
    "sg:province":"TN",
    "sg:tags":[
        "a",
        "car",
        "used",
        "dealer",
        "general"
    ],
    "sg:website":"www.herbadcox.com",
    "wof:name":"Herb Adcox Chevrolet Company",
    "wof:placetype":"venue"
},
  "geometry": {"coordinates":[-85.203816,35.019056],"type":"Point"}
}