{
  "type": "Feature",
  "properties": {
    "addr:full":"1809 Francis Rd NW Knoxville TN 37909",
    "addr:housenumber":"1809",
    "addr:postcode":"37909",
    "addr:street":"Francis Rd Nw",
    "iso:country":"US",
    "sg:address":"1809 Francis Rd NW",
    "sg:city":"Knoxville",
    "sg:classifiers":[
        {
            "category":"Professional",
            "type":"Services"
        }
    ],
    "sg:phone":"+1 865 558 1205",
    "sg:postcode":"37909",
    "sg:province":"TN",
    "wof:name":"Stripes & Moore",
    "wof:placetype":"venue"
},
  "geometry": {"coordinates":[-84.03199600000001,35.958804],"type":"Point"}
}