{
  "type": "Feature",
  "properties": {
    "iso:country":"US",
    "sg:address":"7310 US Hwy 64",
    "sg:city":"Oakland",
    "sg:classifiers":[
        {
            "category":"Organizations",
            "subcategory":"Religious Organization",
            "type":"Services"
        }
    ],
    "sg:phone":"+1 901 465 5833",
    "sg:postcode":"38060",
    "sg:province":"TN",
    "wof:name":"Daybreak Ministries Inc",
    "wof:placetype":"venue"
},
  "geometry": {"coordinates":[-89.513975,35.228836],"type":"Point"}
}