{
  "type": "Feature",
  "properties": {
    "addr:full":"119 Cole Rd Camden TN 38320",
    "addr:housenumber":"119",
    "addr:postcode":"38320",
    "addr:street":"Cole Rd",
    "iso:country":"US",
    "sg:address":"119 Cole Rd",
    "sg:city":"Camden",
    "sg:classifiers":[
        {
            "category":"Social Services",
            "type":"Services"
        }
    ],
    "sg:phone":"+1 731 584 9578",
    "sg:postcode":"38320",
    "sg:province":"TN",
    "sg:tags":[
        "senior",
        "citizen"
    ],
    "wof:name":"Benton County Senior Citizen",
    "wof:placetype":"venue"
},
  "geometry": {"coordinates":[-88.191329,36.035157],"type":"Point"}
}