{
  "type": "Feature",
  "properties": {
    "addr:full":"1548 Gallatin Ave Nashville TN 37206",
    "addr:housenumber":"1548",
    "addr:postcode":"37206",
    "addr:street":"Gallatin Ave",
    "iso:country":"US",
    "sg:address":"1548 Gallatin Ave",
    "sg:city":"Nashville",
    "sg:classifiers":[
        {
            "category":"Shopping",
            "type":"Retail Goods"
        }
    ],
    "sg:phone":"+1 615 868 7287",
    "sg:postcode":"37206",
    "sg:province":"TN",
    "sg:tags":[
        "picture",
        "frame"
    ],
    "wof:name":"Picture Frame Warehouse",
    "wof:placetype":"venue"
},
  "geometry": {"coordinates":[-86.74328,36.194905],"type":"Point"}
}