{
  "type": "Feature",
  "properties": {
    "addr:full":"101 Thomas St Lawrenceburg TN 38464",
    "addr:housenumber":"101",
    "addr:postcode":"38464",
    "addr:street":"Thomas St",
    "iso:country":"US",
    "sg:address":"101 Thomas St",
    "sg:city":"Lawrenceburg",
    "sg:classifiers":[
        {
            "category":"Wholesale",
            "subcategory":"Auto Parts",
            "type":"Manufacturing & Wholesale Goods"
        },
        {
            "category":"Manufacturing",
            "subcategory":"Motor Vehicles & Parts",
            "type":"Manufacturing & Wholesale Goods"
        }
    ],
    "sg:phone":"+1 931 762 5378",
    "sg:postcode":"38464",
    "sg:province":"TN",
    "sg:tags":[
        "shell",
        "mfg",
        "cap",
        "cover",
        "accessory",
        "truck"
    ],
    "wof:name":"Truck Cap Express Inc",
    "wof:placetype":"venue"
},
  "geometry": {"coordinates":[-87.332641,35.264219],"type":"Point"}
}