{
  "type": "Feature",
  "properties": {
    "addr:full":"200 31st Ave N Nashville TN 37203",
    "addr:housenumber":"200",
    "addr:postcode":"37203",
    "addr:street":"31St Ave N",
    "iso:country":"US",
    "sg:address":"200 31st Ave N",
    "sg:city":"Nashville",
    "sg:classifiers":[
        {
            "category":"Professional",
            "type":"Services"
        }
    ],
    "sg:phone":"+1 615 627 4444",
    "sg:postcode":"37203",
    "sg:province":"TN",
    "sg:tags":[
        "establishment"
    ],
    "wof:name":"Howard & Mobley Pllc",
    "wof:placetype":"venue"
},
  "geometry": {"coordinates":[-86.816467,36.145221],"type":"Point"}
}