{
  "type": "Feature",
  "properties": {
    "addr:full":"315 Carlton Ridge Ln Greeneville TN 37745",
    "addr:housenumber":"315",
    "addr:postcode":"37745",
    "addr:street":"Carlton Ridge Ln",
    "iso:country":"US",
    "sg:address":"315 Carlton Ridge Ln",
    "sg:city":"Greeneville",
    "sg:classifiers":[
        {
            "category":"Manufacturing",
            "subcategory":"Building Materials",
            "type":"Manufacturing & Wholesale Goods"
        },
        {
            "category":"Home & Garden",
            "subcategory":"Furniture",
            "type":"Retail Goods"
        }
    ],
    "sg:phone":"+1 423 636 1251",
    "sg:postcode":"37745",
    "sg:province":"TN",
    "sg:tags":[
        "equipment",
        "cabinet",
        "wood",
        "kitchen",
        "mfg"
    ],
    "wof:name":"Carlton Woodworks",
    "wof:placetype":"venue"
},
  "geometry": {"coordinates":[-82.797628,36.206187],"type":"Point"}
}