{
  "type": "Feature",
  "properties": {
    "iso:country":"US",
    "sg:address":"730 E Church St",
    "sg:city":"Union City",
    "sg:classifiers":[
        {
            "category":"Building & Trades",
            "subcategory":"Plumbing",
            "type":"Services"
        }
    ],
    "sg:phone":"+1 731 885 0016",
    "sg:postcode":"38261",
    "sg:province":"TN",
    "sg:tags":[
        "contractor"
    ],
    "wof:name":"Insite Uptime Engineers LLC",
    "wof:placetype":"venue"
},
  "geometry": {"coordinates":[-89.049893,36.423956],"type":"Point"}
}