{
  "type": "Feature",
  "properties": {
    "iso:country":"US",
    "sg:address":"3168 Baileyton Rd",
    "sg:city":"Greeneville",
    "sg:classifiers":[
        {
            "category":"Building & Trades",
            "subcategory":"Plumbing",
            "type":"Services"
        }
    ],
    "sg:phone":"+1 423 787 0399",
    "sg:postcode":"37745",
    "sg:province":"TN",
    "sg:tags":[
        "tank",
        "septic"
    ],
    "wof:name":"M C Septic Svc",
    "wof:placetype":"venue"
},
  "geometry": {"coordinates":[-82.84539599999999,36.194466],"type":"Point"}
}