{
  "type": "Feature",
  "properties": {
    "addr:full":"5865 Ridgeway Center Pkwy Memphis TN 38120",
    "addr:housenumber":"5865",
    "addr:postcode":"38120",
    "addr:street":"Ridgeway Center Pkwy",
    "iso:country":"US",
    "sg:address":"5865 Ridgeway Center Pkwy",
    "sg:city":"Memphis",
    "sg:classifiers":[
        {
            "category":"Banks & Credit Unions",
            "subcategory":"Bank",
            "type":"Services"
        }
    ],
    "sg:phone":"+1 901 525 2902",
    "sg:postcode":"38120",
    "sg:province":"TN",
    "wof:name":"PNC Business Credit",
    "wof:placetype":"venue"
},
  "geometry": {"coordinates":[-89.865944,35.104807],"type":"Point"}
}