{
  "type": "Feature",
  "properties": {
    "addr:full":"109 Peyton Rd Smyrna TN 37167",
    "addr:housenumber":"109",
    "addr:postcode":"37167",
    "addr:street":"Peyton Rd",
    "iso:country":"US",
    "sg:address":"109 Peyton Rd",
    "sg:city":"Smyrna",
    "sg:classifiers":[
        {
            "category":"Real Estate",
            "subcategory":"Real Estate Operator",
            "type":"Services"
        }
    ],
    "sg:phone":"+1 615 459 7562",
    "sg:postcode":"37167",
    "sg:province":"TN",
    "sg:tags":[
        "apartment"
    ],
    "wof:name":"Peyton Farms Apartments",
    "wof:placetype":"venue"
},
  "geometry": {"coordinates":[-86.486554,35.975613],"type":"Point"}
}