{
  "type": "Feature",
  "properties": {
    "iso:country":"US",
    "sg:address":"7736 Ashley Rd",
    "sg:city":"Powell",
    "sg:classifiers":[
        {
            "category":"Retail",
            "subcategory":"Auto Repair",
            "type":"Services"
        }
    ],
    "sg:phone":"+1 865 938 0401",
    "sg:postcode":"37849",
    "sg:province":"TN",
    "sg:tags":[
        "repairing",
        "engine"
    ],
    "wof:name":"Rick's Small Engine Svc/Repair",
    "wof:placetype":"venue"
},
  "geometry": {"coordinates":[-84.039886,36.033046],"type":"Point"}
}