{
  "type": "Feature",
  "properties": {
    "addr:full":"562 Carole Anne Dr Woodbury TN 37190",
    "addr:housenumber":"562",
    "addr:postcode":"37190",
    "addr:street":"Carole Anne Dr",
    "iso:country":"US",
    "sg:address":"562 Carole Anne Dr",
    "sg:city":"Woodbury",
    "sg:classifiers":[
        {
            "category":"Shopping",
            "subcategory":"Used Merchandise",
            "type":"Retail Goods"
        }
    ],
    "sg:phone":"+1 615 563 4161",
    "sg:postcode":"37190",
    "sg:province":"TN",
    "sg:tags":[
        "antique"
    ],
    "wof:name":"Emmas Antiques & Gift Shop",
    "wof:placetype":"venue"
},
  "geometry": {"coordinates":[-86.044494,35.747028],"type":"Point"}
}