{
  "type": "Feature",
  "properties": {
    "addr:full":"1808 Nolensville Pike Nashville TN 37210",
    "addr:housenumber":"1808",
    "addr:postcode":"37210",
    "addr:street":"Nolensville Pike",
    "iso:country":"US",
    "sg:address":"1808 Nolensville Pike",
    "sg:city":"Nashville",
    "sg:classifiers":[
        {
            "category":"Freight",
            "type":"Transportation"
        }
    ],
    "sg:phone":"+1 615 256 0700",
    "sg:postcode":"37210",
    "sg:province":"TN",
    "sg:tags":[
        "trailer"
    ],
    "wof:name":"Storage Trailer Rental Inc",
    "wof:placetype":"venue"
},
  "geometry": {"coordinates":[-86.759973,36.135453],"type":"Point"}
}