{
  "type": "Feature",
  "properties": {
    "iso:country":"US",
    "sg:address":"105 Northgate Mall",
    "sg:city":"Chattanooga",
    "sg:classifiers":[
        {
            "category":"Shopping",
            "subcategory":"Department Store",
            "type":"Retail Goods"
        }
    ],
    "sg:phone":"+1 423 870 1884",
    "sg:postcode":"37415",
    "sg:province":"TN",
    "sg:tags":[
        "shop"
    ],
    "wof:name":"Dollar Mania",
    "wof:placetype":"venue"
},
  "geometry": {"coordinates":[-85.244387,35.136926],"type":"Point"}
}