{
  "type": "Feature",
  "properties": {
    "addr:full":"527 Old Nashville Hwy La Vergne TN 37086",
    "addr:housenumber":"527",
    "addr:postcode":"37086",
    "addr:street":"Old Nashville Hwy",
    "iso:country":"US",
    "sg:address":"527 Old Nashville Hwy",
    "sg:city":"La Vergne",
    "sg:classifiers":[
        {
            "category":"Autos & Motor Vehicles",
            "subcategory":"Automobile Sales",
            "type":"Retail Goods"
        }
    ],
    "sg:phone":"+1 615 793 4469",
    "sg:postcode":"37086",
    "sg:province":"TN",
    "sg:tags":[
        "car",
        "dealer"
    ],
    "wof:name":"Driggers Inc",
    "wof:placetype":"venue"
},
  "geometry": {"coordinates":[-86.559759,35.999301],"type":"Point"}
}