{
  "type": "Feature",
  "properties": {
    "iso:country":"US",
    "sg:address":"1093 Derryberry Cemetery Rd",
    "sg:city":"Columbia",
    "sg:classifiers":[
        {
            "category":"Freight",
            "type":"Transportation"
        }
    ],
    "sg:phone":"+1 931 364 2606",
    "sg:postcode":"38401",
    "sg:province":"TN",
    "sg:tags":[
        "hauling",
        "trucking"
    ],
    "wof:name":"E & E Fabrication Inc",
    "wof:placetype":"venue"
},
  "geometry": {"coordinates":[-86.787215,35.690207],"type":"Point"}
}