{
  "type": "Feature",
  "properties": {
    "iso:country":"US",
    "sg:address":"720 E 4th St",
    "sg:city":"Chattanooga",
    "sg:classifiers":[
        {
            "category":"Education",
            "subcategory":"College",
            "type":"Public Place"
        }
    ],
    "sg:phone":"+1 423 755 4706",
    "sg:postcode":"37403",
    "sg:province":"TN",
    "sg:tags":[
        "sport"
    ],
    "wof:name":"Arena The",
    "wof:placetype":"venue"
},
  "geometry": {"coordinates":[-85.30136299999999,35.051188],"type":"Point"}
}