{
  "type": "Feature",
  "properties": {
    "iso:country":"US",
    "sg:address":"7019 Wilson Pike Cir",
    "sg:city":"Brentwood",
    "sg:classifiers":[
        {
            "category":"Banks & Credit Unions",
            "subcategory":"Investment Brokerage",
            "type":"Services"
        }
    ],
    "sg:phone":"+1 615 373 5330",
    "sg:postcode":"37027",
    "sg:province":"TN",
    "sg:tags":[
        "consultant",
        "planning",
        "financial"
    ],
    "wof:name":"Value Investment Svc Inc",
    "wof:placetype":"venue"
},
  "geometry": {"coordinates":[-86.79128300000001,36.021484],"type":"Point"}
}