{
  "type": "Feature",
  "properties": {
    "iso:country":"US",
    "sg:address":"823 Cammack Ct",
    "sg:city":"Nashville",
    "sg:classifiers":[
        {
            "category":"Building & Trades",
            "subcategory":"Plumbing",
            "type":"Services"
        }
    ],
    "sg:phone":"+1 615 356 0087",
    "sg:postcode":"37205",
    "sg:province":"TN",
    "sg:tags":[
        "contractor"
    ],
    "wof:name":"Iroquois Irrigation Inc",
    "wof:placetype":"venue"
},
  "geometry": {"coordinates":[-86.908216,36.108561],"type":"Point"}
}