{
  "type": "Feature",
  "properties": {
    "iso:country":"US",
    "sg:address":"19769 E Main St",
    "sg:city":"Huntingdon",
    "sg:classifiers":[
        {
            "category":"Insurance",
            "subcategory":"Insurance Agent",
            "type":"Services"
        }
    ],
    "sg:phone":"+1 731 986 2407",
    "sg:postcode":"38344",
    "sg:province":"TN",
    "sg:website":"www.modern-woodmen.org",
    "wof:name":"Modern Woodmen Of America",
    "wof:placetype":"venue"
},
  "geometry": {"coordinates":[-88.42664499999999,36.001135],"type":"Point"}
}