{
  "type": "Feature",
  "properties": {
    "addr:full":"2509 Parkview Dr Memphis TN 38128",
    "addr:housenumber":"2509",
    "addr:postcode":"38128",
    "addr:street":"Parkview Dr",
    "iso:country":"US",
    "sg:address":"2509 Parkview Dr",
    "sg:city":"Memphis",
    "sg:classifiers":[
        {
            "category":"Landmark",
            "subcategory":"Tourist Information",
            "type":"Public Place"
        }
    ],
    "sg:phone":"+1 901 382 2781",
    "sg:postcode":"38128",
    "sg:province":"TN",
    "sg:tags":[
        "promoter",
        "tours-operators"
    ],
    "wof:name":"Budget Tour",
    "wof:placetype":"venue"
},
  "geometry": {"coordinates":[-89.90827,35.194083],"type":"Point"}
}