{
  "type": "Feature",
  "properties": {
    "iso:country":"US",
    "sg:address":"1503 Nashville Hwy",
    "sg:city":"Columbia",
    "sg:classifiers":[
        {
            "category":"Professional",
            "subcategory":"Accounting & Tax Preparation",
            "type":"Services"
        }
    ],
    "sg:phone":"+1 931 381 9146",
    "sg:postcode":"38401",
    "sg:province":"TN",
    "wof:name":"Galloway Business Service",
    "wof:placetype":"venue"
},
  "geometry": {"coordinates":[-87.012387,35.647536],"type":"Point"}
}