{
  "type": "Feature",
  "properties": {
    "iso:country":"US",
    "sg:address":"1361 Railroad St",
    "sg:city":"Dayton",
    "sg:classifiers":[
        {
            "category":"Banks & Credit Unions",
            "subcategory":"Bank",
            "type":"Services"
        }
    ],
    "sg:phone":"+1 423 570 8874",
    "sg:postcode":"37321",
    "sg:province":"TN",
    "sg:tags":[
        "commercial"
    ],
    "wof:name":"Advance Banking Systems",
    "wof:placetype":"venue"
},
  "geometry": {"coordinates":[-85.014121,35.495618],"type":"Point"}
}