{
  "type": "Feature",
  "properties": {
    "iso:country":"US",
    "sg:address":"100 New Hope Rd",
    "sg:city":"Hilham",
    "sg:classifiers":[
        {
            "category":"Retail",
            "subcategory":"Laundry & Dry Cleaning",
            "type":"Services"
        }
    ],
    "sg:phone":"+1 931 268 6426",
    "sg:postcode":"38568",
    "sg:province":"TN",
    "wof:name":"Morgan Carpet Cleaning",
    "wof:placetype":"venue"
},
  "geometry": {"coordinates":[-85.543281,36.578745],"type":"Point"}
}