{
  "type": "Feature",
  "properties": {
    "iso:country":"US",
    "sg:address":"3815 Hillsboro Pike",
    "sg:city":"Nashville",
    "sg:classifiers":[
        {
            "category":"Autos & Motor Vehicles",
            "subcategory":"Fuel & Gas Station",
            "type":"Retail Goods"
        }
    ],
    "sg:phone":"+1 615 386 3529",
    "sg:postcode":"37215",
    "sg:province":"TN",
    "sg:tags":[
        "station",
        "gasoline"
    ],
    "wof:name":"Exxon 50673",
    "wof:placetype":"venue"
},
  "geometry": {"coordinates":[-86.813688,36.106206],"type":"Point"}
}