{
  "type": "Feature",
  "properties": {
    "addr:full":"242 Hickorydale Dr Nashville TN 37210",
    "addr:housenumber":"242",
    "addr:postcode":"37210",
    "addr:street":"Hickorydale Dr",
    "iso:country":"US",
    "sg:address":"242 Hickorydale Dr",
    "sg:city":"Nashville",
    "sg:classifiers":[
        {
            "category":"Shopping",
            "type":"Retail Goods"
        }
    ],
    "sg:phone":"+1 615 883 6420",
    "sg:postcode":"37210",
    "sg:province":"TN",
    "sg:tags":[
        "equipment",
        "telephone",
        "supply"
    ],
    "sg:website":"www.digitel.com",
    "wof:name":"Digitel Communications Group",
    "wof:placetype":"venue"
},
  "geometry": {"coordinates":[-86.71574699999999,36.158166],"type":"Point"}
}