{
  "type": "Feature",
  "properties": {
    "iso:country":"US",
    "sg:address":"334 Highwood Ct",
    "sg:city":"Knoxville",
    "sg:classifiers":[
        {
            "category":"Professional",
            "subcategory":"Business Services",
            "type":"Services"
        }
    ],
    "sg:phone":"+1 865 609 6181",
    "sg:postcode":"37920",
    "sg:province":"TN",
    "wof:name":"Alias Subpoena LLC",
    "wof:placetype":"venue"
},
  "geometry": {"coordinates":[-83.910473,35.947703],"type":"Point"}
}