{
  "type": "Feature",
  "properties": {
    "addr:full":"1926 Washington Pike Knoxville TN 37917",
    "addr:housenumber":"1926",
    "addr:postcode":"37917",
    "addr:street":"Washington Pike",
    "iso:country":"US",
    "sg:address":"1926 Washington Pike",
    "sg:city":"Knoxville",
    "sg:classifiers":[
        {
            "category":"Organizations",
            "subcategory":"Religious Organization",
            "type":"Services"
        }
    ],
    "sg:phone":"+1 865 637 4146",
    "sg:postcode":"37917",
    "sg:province":"TN",
    "wof:name":"Severe Avenue Baptist Church",
    "wof:placetype":"venue"
},
  "geometry": {"coordinates":[-83.916951,35.998462],"type":"Point"}
}