{
  "type": "Feature",
  "properties": {
    "iso:country":"US",
    "sg:address":"424 E Bernard Ave",
    "sg:city":"Greeneville",
    "sg:classifiers":[
        {
            "category":"Real Estate",
            "subcategory":"Developer",
            "type":"Services"
        }
    ],
    "sg:phone":"+1 423 636 3091",
    "sg:postcode":"37745",
    "sg:province":"TN",
    "wof:name":"Ferguson Development Network",
    "wof:placetype":"venue"
},
  "geometry": {"coordinates":[-82.816733,36.163969],"type":"Point"}
}