{
  "type": "Feature",
  "properties": {
    "iso:country":"US",
    "sg:address":"510 Justice Dr",
    "sg:city":"Greeneville",
    "sg:classifiers":[
        {
            "category":"Health Services",
            "subcategory":"Chiropractor",
            "type":"Services"
        }
    ],
    "sg:phone":"+1 423 639 4440",
    "sg:postcode":"37745",
    "sg:province":"TN",
    "wof:name":"Appalachian Chiropractic",
    "wof:placetype":"venue"
},
  "geometry": {"coordinates":[-82.79449,36.17668],"type":"Point"}
}