{
  "type": "Feature",
  "properties": {
    "iso:country":"US",
    "sg:address":"1651 NW Broad St",
    "sg:city":"Murfreesboro",
    "sg:classifiers":[
        {
            "category":"Autos & Motor Vehicles",
            "subcategory":"Boat Sales",
            "type":"Retail Goods"
        }
    ],
    "sg:phone":"+1 615 848 6981",
    "sg:postcode":"37129",
    "sg:province":"TN",
    "sg:tags":[
        "dealer",
        "sales"
    ],
    "wof:name":"Murfreesboro Marine",
    "wof:placetype":"venue"
},
  "geometry": {"coordinates":[-86.401444,35.852628],"type":"Point"}
}