{
  "type": "Feature",
  "properties": {
    "addr:full":"120 Lincoln Ct Nashville TN 37205",
    "addr:housenumber":"120",
    "addr:postcode":"37205",
    "addr:street":"Lincoln Ct",
    "iso:country":"US",
    "sg:address":"120 Lincoln Ct",
    "sg:city":"Nashville",
    "sg:classifiers":[
        {
            "category":"Wholesale",
            "subcategory":"Electrical",
            "type":"Manufacturing & Wholesale Goods"
        }
    ],
    "sg:phone":"+1 615 308 2975",
    "sg:postcode":"37205",
    "sg:province":"TN",
    "sg:tags":[
        "wholesaler",
        "electronics"
    ],
    "wof:name":"Atticus Inc",
    "wof:placetype":"venue"
},
  "geometry": {"coordinates":[-86.864479,36.102607],"type":"Point"}
}