{
  "type": "Feature",
  "properties": {
    "iso:country":"US",
    "sg:address":"221 Mill St",
    "sg:city":"Cookeville",
    "sg:classifiers":[
        {
            "category":"Building & Trades",
            "subcategory":"Construction",
            "type":"Services"
        }
    ],
    "sg:phone":"+1 931 528 2816",
    "sg:postcode":"38506",
    "sg:province":"TN",
    "sg:tags":[
        "downspouts",
        "gutter"
    ],
    "wof:name":"Borden Seamless Guttering",
    "wof:placetype":"venue"
},
  "geometry": {"coordinates":[-85.459265,36.190914],"type":"Point"}
}