{
  "type": "Feature",
  "properties": {
    "addr:full":"1706 Rossville Ave Chattanooga TN 37408",
    "addr:housenumber":"1706",
    "addr:postcode":"37408",
    "addr:street":"Rossville Ave",
    "iso:country":"US",
    "sg:address":"1706 Rossville Ave",
    "sg:city":"Chattanooga",
    "sg:classifiers":[
        {
            "category":"Wholesale",
            "subcategory":"Machinery & Supplies",
            "type":"Manufacturing & Wholesale Goods"
        }
    ],
    "sg:phone":"+1 423 756 5763",
    "sg:postcode":"37408",
    "sg:province":"TN",
    "sg:tags":[
        "equipment",
        "product",
        "industrial",
        "steam",
        "cleaning"
    ],
    "wof:name":"Etowah Chemicals Sales & Svc",
    "wof:placetype":"venue"
},
  "geometry": {"coordinates":[-85.303669,35.032468],"type":"Point"}
}