{
  "type": "Feature",
  "properties": {
    "iso:country":"US",
    "sg:address":"460 W Broad St",
    "sg:city":"Smithville",
    "sg:classifiers":[
        {
            "category":"Personal",
            "subcategory":"Beauty Salon",
            "type":"Services"
        }
    ],
    "sg:phone":"+1 615 597 7529",
    "sg:postcode":"37166",
    "sg:province":"TN",
    "sg:tags":[
        "shop"
    ],
    "wof:name":"Gateway To Beauty Beauty Salon",
    "wof:placetype":"venue"
},
  "geometry": {"coordinates":[-85.827506,35.958316],"type":"Point"}
}