{
  "type": "Feature",
  "properties": {
    "addr:full":"7501 Old Harding Rd Nashville TN 37221",
    "addr:housenumber":"7501",
    "addr:postcode":"37221",
    "addr:street":"Old Harding Rd",
    "iso:country":"US",
    "sg:address":"7501 Old Harding Rd",
    "sg:city":"Nashville",
    "sg:classifiers":[
        {
            "category":"Organizations",
            "subcategory":"Religious Organization",
            "type":"Services"
        }
    ],
    "sg:phone":"+1 615 646 4146",
    "sg:postcode":"37221",
    "sg:province":"TN",
    "wof:name":"Bellevue United Methdst Church",
    "wof:placetype":"venue"
},
  "geometry": {"coordinates":[-86.942581,36.062409],"type":"Point"}
}