{
  "type": "Feature",
  "properties": {
    "iso:country":"US",
    "sg:address":"2152 N Thompson Ln",
    "sg:city":"Murfreesboro",
    "sg:classifiers":[
        {
            "category":"Autos & Motor Vehicles",
            "subcategory":"Fuel & Gas Station",
            "type":"Retail Goods"
        }
    ],
    "sg:phone":"+1 615 895 9076",
    "sg:postcode":"37129",
    "sg:province":"TN",
    "sg:tags":[
        "oil"
    ],
    "wof:name":"Marathon Service Station",
    "wof:placetype":"venue"
},
  "geometry": {"coordinates":[-86.423119,35.885385],"type":"Point"}
}