{
  "type": "Feature",
  "properties": {
    "iso:country":"US",
    "sg:address":"580 Hwy 70",
    "sg:city":"Pegram",
    "sg:classifiers":[
        {
            "category":"Restaurant",
            "type":"Food & Drink"
        }
    ],
    "sg:phone":"+1 615 662 3889",
    "sg:postcode":"37143",
    "sg:province":"TN",
    "wof:name":"Joyce's Coffee & Pastry Shop",
    "wof:placetype":"venue"
},
  "geometry": {"coordinates":[-87.058212,36.104721],"type":"Point"}
}