{
  "type": "Feature",
  "properties": {
    "addr:full":"3308 Long Blvd Nashville TN 37203",
    "addr:housenumber":"3308",
    "addr:postcode":"37203",
    "addr:street":"Long Blvd",
    "iso:country":"US",
    "sg:address":"3308 Long Blvd",
    "sg:city":"Nashville",
    "sg:classifiers":[
        {
            "category":"Autos & Motor Vehicles",
            "subcategory":"Automobile Sales",
            "type":"Retail Goods"
        }
    ],
    "sg:phone":"+1 615 292 5095",
    "sg:postcode":"37203",
    "sg:province":"TN",
    "sg:tags":[
        "new",
        "used",
        "dealer",
        "car"
    ],
    "wof:name":"Whitts Auto Sales Inc",
    "wof:placetype":"venue"
},
  "geometry": {"coordinates":[-86.821287,36.142104],"type":"Point"}
}