{
  "type": "Feature",
  "properties": {
    "iso:country":"US",
    "sg:address":"4464 Stage Rd",
    "sg:city":"Memphis",
    "sg:classifiers":[
        {
            "category":"Professional",
            "subcategory":"Accounting & Tax Preparation",
            "type":"Services"
        }
    ],
    "sg:phone":"+1 901 388 4999",
    "sg:postcode":"38128",
    "sg:province":"TN",
    "sg:tags":[
        "bookkeeping",
        "general"
    ],
    "sg:website":"www.ledgerplus.com",
    "wof:name":"Ledger Plus",
    "wof:placetype":"venue"
},
  "geometry": {"coordinates":[-89.914321,35.205939],"type":"Point"}
}