{
  "type": "Feature",
  "properties": {
    "addr:full":"2764 US Hwy 11E Strawberry Plns TN 37871",
    "addr:housenumber":"2764",
    "addr:postcode":"37871",
    "addr:street":"Us Hwy 11E Strawberry",
    "iso:country":"US",
    "sg:address":"2764 US Hwy 11E",
    "sg:city":"Strawberry Plns",
    "sg:classifiers":[
        {
            "category":"Retail",
            "subcategory":"Auto Repair",
            "type":"Services"
        }
    ],
    "sg:phone":"+1 865 932 2002",
    "sg:postcode":"37871",
    "sg:province":"TN",
    "sg:tags":[
        "glass",
        "coating",
        "tinting"
    ],
    "wof:name":"East End Customs",
    "wof:placetype":"venue"
},
  "geometry": {"coordinates":[-83.674662,36.065833],"type":"Point"}
}