{
  "type": "Feature",
  "properties": {
    "addr:full":"4854 Dayton Blvd Chattanooga TN 37415",
    "addr:housenumber":"4854",
    "addr:postcode":"37415",
    "addr:street":"Dayton Blvd",
    "iso:country":"US",
    "sg:address":"4854 Dayton Blvd",
    "sg:city":"Chattanooga",
    "sg:classifiers":[
        {
            "category":"Retail",
            "subcategory":"Auto Repair",
            "type":"Services"
        }
    ],
    "sg:phone":"+1 423 875 5482",
    "sg:postcode":"37415",
    "sg:province":"TN",
    "sg:tags":[
        "body",
        "automobile",
        "painting",
        "repairing"
    ],
    "sg:website":"http://www.redbankbodyshop.com",
    "wof:name":"Red Bank Bodyshop",
    "wof:placetype":"venue"
},
  "geometry": {"coordinates":[-85.278425,35.139127],"type":"Point"}
}