{
  "type": "Feature",
  "properties": {
    "iso:country":"US",
    "sg:address":"619 Crescent Dr",
    "sg:city":"Gatlinburg",
    "sg:classifiers":[
        {
            "category":"Manufacturing",
            "subcategory":"Apparel",
            "type":"Manufacturing & Wholesale Goods"
        }
    ],
    "sg:phone":"+1 865 436 2861",
    "sg:postcode":"37738",
    "sg:province":"TN",
    "sg:tags":[
        "product",
        "mfg"
    ],
    "wof:name":"Living Canvas Productions",
    "wof:placetype":"venue"
},
  "geometry": {"coordinates":[-83.456045,35.739573],"type":"Point"}
}