{
  "type": "Feature",
  "properties": {
    "iso:country":"US",
    "sg:address":"915 Old Fort Pkwy",
    "sg:city":"Murfreesboro",
    "sg:classifiers":[
        {
            "category":"Bars & Pubs",
            "type":"Food & Drink"
        }
    ],
    "sg:phone":"+1 615 890 6666",
    "sg:postcode":"37129",
    "sg:province":"TN",
    "sg:tags":[
        "drinking"
    ],
    "wof:name":"Pardners",
    "wof:placetype":"venue"
},
  "geometry": {"coordinates":[-86.422354,35.845763],"type":"Point"}
}