{
  "type": "Feature",
  "properties": {
    "iso:country":"US",
    "sg:address":"530 Winfield Dunn Pkwy",
    "sg:city":"Sevierville",
    "sg:classifiers":[
        {
            "category":"Restaurant",
            "type":"Food & Drink"
        }
    ],
    "sg:menulink":"http://www.allmenus.com/tn/sevierville/228911-jersey-mikes/menu/",
    "sg:phone":"+1 865 908 6808",
    "sg:postcode":"37876",
    "sg:province":"TN",
    "sg:tags":[
        "american",
        "sandwich"
    ],
    "wof:name":"Jersey Mike's",
    "wof:placetype":"venue"
},
  "geometry": {"coordinates":[-83.57181199999999,35.876891],"type":"Point"}
}