{
  "type": "Feature",
  "properties": {
    "iso:country":"US",
    "sg:address":"1704 8th Ave N",
    "sg:city":"Nashville",
    "sg:classifiers":[
        {
            "category":"Food & Beverages",
            "subcategory":"Groceries & Convenience Stores",
            "type":"Retail Goods"
        }
    ],
    "sg:phone":"+1 615 256 7450",
    "sg:postcode":"37208",
    "sg:province":"TN",
    "wof:name":"Northside Market",
    "wof:placetype":"venue"
},
  "geometry": {"coordinates":[-86.797437,36.182339],"type":"Point"}
}