{
  "type": "Feature",
  "properties": {
    "iso:country":"US",
    "sg:address":"603 Davidson Rd",
    "sg:city":"Nashville",
    "sg:classifiers":[
        {
            "category":"Building & Trades",
            "subcategory":"Construction",
            "type":"Services"
        }
    ],
    "sg:phone":"+1 615 354 5402",
    "sg:postcode":"37205",
    "sg:province":"TN",
    "sg:tags":[
        "concrete",
        "contractor"
    ],
    "wof:name":"RCC Concrete Svc",
    "wof:placetype":"venue"
},
  "geometry": {"coordinates":[-86.884911,36.11727],"type":"Point"}
}