{
  "type": "Feature",
  "properties": {
    "iso:country":"US",
    "sg:address":"1000 Pin Oak Ct",
    "sg:city":"Dickson",
    "sg:classifiers":[
        {
            "category":"Building & Trades",
            "subcategory":"Construction",
            "type":"Services"
        }
    ],
    "sg:phone":"+1 615 441 3708",
    "sg:postcode":"37055",
    "sg:province":"TN",
    "sg:tags":[
        "concrete",
        "contractor"
    ],
    "wof:name":"Custom Concrete",
    "wof:placetype":"venue"
},
  "geometry": {"coordinates":[-87.411745,36.082404],"type":"Point"}
}