{
  "type": "Feature",
  "properties": {
    "addr:full":"2015 NW Broad St Murfreesboro TN 37129",
    "addr:housenumber":"2015",
    "addr:postcode":"37129",
    "addr:street":"Nw Broad St",
    "iso:country":"US",
    "sg:address":"2015 NW Broad St",
    "sg:city":"Murfreesboro",
    "sg:classifiers":[
        {
            "category":"Home & Garden",
            "subcategory":"Mobile Homes",
            "type":"Retail Goods"
        }
    ],
    "sg:phone":"+1 615 890 4947",
    "sg:postcode":"37129",
    "sg:province":"TN",
    "sg:website":"www.clayton.net",
    "wof:name":"Country Squire",
    "wof:placetype":"venue"
},
  "geometry": {"coordinates":[-86.406576,35.860125],"type":"Point"}
}