{
  "type": "Feature",
  "properties": {
    "addr:full":"5440 Rich Rd Memphis TN 38120",
    "addr:housenumber":"5440",
    "addr:postcode":"38120",
    "addr:street":"Rich Rd",
    "iso:country":"US",
    "sg:address":"5440 Rich Rd",
    "sg:city":"Memphis",
    "sg:classifiers":[
        {
            "category":"Education",
            "subcategory":"School",
            "type":"Public Place"
        }
    ],
    "sg:phone":"+1 901 416 2148",
    "sg:postcode":"38120",
    "sg:province":"TN",
    "sg:website":"www.mcsk12.net",
    "wof:name":"Richland Elementary School",
    "wof:placetype":"venue"
},
  "geometry": {"coordinates":[-89.88149300000001,35.135557],"type":"Point"}
}