{
  "type": "Feature",
  "properties": {
    "addr:full":"281 Pleasant Grove Rd Mc Donald TN 37353",
    "addr:housenumber":"281",
    "addr:postcode":"37353",
    "addr:street":"Pleasant Grove Rd",
    "iso:country":"US",
    "sg:address":"281 Pleasant Grove Rd",
    "sg:city":"Mc Donald",
    "sg:classifiers":[
        {
            "category":"Ice Cream",
            "type":"Food & Drink"
        }
    ],
    "sg:menulink":"http://www.allmenus.com/tn/west-bradley/192666-dairy-queen/menu/",
    "sg:phone":"+1 423 476 3890",
    "sg:postcode":"37353",
    "sg:province":"TN",
    "sg:tags":[
        "burger",
        "american"
    ],
    "wof:name":"Dairy Queen",
    "wof:placetype":"venue"
},
  "geometry": {"coordinates":[-84.953385,35.153526],"type":"Point"}
}