{
  "type": "Feature",
  "properties": {
    "iso:country":"US",
    "sg:address":"402 Central Ave W",
    "sg:city":"Springfield",
    "sg:classifiers":[
        {
            "category":"Professional",
            "subcategory":"Accounting & Tax Preparation",
            "type":"Services"
        }
    ],
    "sg:phone":"+1 615 384 6999",
    "sg:postcode":"37172",
    "sg:province":"TN",
    "sg:tags":[
        "accountant"
    ],
    "wof:name":"Singleton CPA",
    "wof:placetype":"venue"
},
  "geometry": {"coordinates":[-86.889636,36.501794],"type":"Point"}
}