{
  "type": "Feature",
  "properties": {
    "iso:country":"US",
    "sg:address":"779 Walnut Knoll Ln",
    "sg:city":"Cordova",
    "sg:classifiers":[
        {
            "category":"Insurance",
            "subcategory":"Insurance Agent",
            "type":"Services"
        }
    ],
    "sg:phone":"+1 901 757 5600",
    "sg:postcode":"38018",
    "sg:province":"TN",
    "wof:name":"Benefit Partners LLC",
    "wof:placetype":"venue"
},
  "geometry": {"coordinates":[-89.792798,35.145612],"type":"Point"}
}