{
  "type": "Feature",
  "properties": {
    "addr:full":"825 Timber Creek Dr Cordova TN 38018",
    "addr:housenumber":"825",
    "addr:postcode":"38018",
    "addr:street":"Timber Creek Dr",
    "iso:country":"US",
    "sg:address":"825 Timber Creek Dr",
    "sg:city":"Cordova",
    "sg:classifiers":[
        {
            "category":"Building & Trades",
            "subcategory":"Construction",
            "type":"Services"
        }
    ],
    "sg:phone":"+1 901 759 7000",
    "sg:postcode":"38018",
    "sg:province":"TN",
    "sg:tags":[
        "home",
        "builder"
    ],
    "sg:website":"www.faxongillis.com",
    "wof:name":"Faxon Gilllis Homes Inc",
    "wof:placetype":"venue"
},
  "geometry": {"coordinates":[-89.79104,35.147804],"type":"Point"}
}