{
  "type": "Feature",
  "properties": {
    "addr:full":"905 Crockett St Nashville TN 37207",
    "addr:housenumber":"905",
    "addr:postcode":"37207",
    "addr:street":"Crockett St",
    "iso:country":"US",
    "sg:address":"905 Crockett St",
    "sg:city":"Nashville",
    "sg:classifiers":[
        {
            "category":"Shopping",
            "type":"Retail Goods"
        }
    ],
    "sg:phone":"+1 615 582 4223",
    "sg:postcode":"37207",
    "sg:province":"TN",
    "sg:tags":[
        "merchandise"
    ],
    "wof:name":"Zeeks Paint & Body Shop",
    "wof:placetype":"venue"
},
  "geometry": {"coordinates":[-86.75560299999999,36.195789],"type":"Point"}
}