{
  "type": "Feature",
  "properties": {
    "iso:country":"US",
    "sg:address":"3055 Dury Ct",
    "sg:city":"Clarksville",
    "sg:classifiers":[
        {
            "category":"Home & Garden",
            "subcategory":"Building Materials",
            "type":"Retail Goods"
        }
    ],
    "sg:phone":"+1 931 368 1252",
    "sg:postcode":"37043",
    "sg:province":"TN",
    "sg:tags":[
        "door"
    ],
    "wof:name":"Commercial Installation",
    "wof:placetype":"venue"
},
  "geometry": {"coordinates":[-87.22548,36.521215],"type":"Point"}
}