{
  "type": "Feature",
  "properties": {
    "addr:full":"3429 Melodywood Dr Memphis TN 38118",
    "addr:housenumber":"3429",
    "addr:postcode":"38118",
    "addr:street":"Melodywood Dr",
    "iso:country":"US",
    "sg:address":"3429 Melodywood Dr",
    "sg:city":"Memphis",
    "sg:classifiers":[
        {
            "category":"Home & Garden",
            "subcategory":"Building Materials",
            "type":"Retail Goods"
        }
    ],
    "sg:phone":"+1 901 363 9540",
    "sg:postcode":"38118",
    "sg:province":"TN",
    "sg:tags":[
        "tile",
        "ceramic"
    ],
    "wof:name":"Collins Tile Incorporated",
    "wof:placetype":"venue"
},
  "geometry": {"coordinates":[-89.949968,35.013831],"type":"Point"}
}