{
  "type": "Feature",
  "properties": {
    "addr:full":"113 S Court St Tiptonville TN 38079",
    "addr:housenumber":"113",
    "addr:postcode":"38079",
    "addr:street":"S Court",
    "iso:country":"US",
    "sg:address":"113 S Court St",
    "sg:city":"Tiptonville",
    "sg:classifiers":[
        {
            "category":"Home & Garden",
            "subcategory":"Garden Supply",
            "type":"Retail Goods"
        }
    ],
    "sg:phone":"+1 731 253 7855",
    "sg:postcode":"38079",
    "sg:province":"TN",
    "sg:tags":[
        "soil",
        "conservation"
    ],
    "wof:name":"Natural Resources Conservation Service",
    "wof:placetype":"venue"
},
  "geometry": {"coordinates":[-89.483851,36.378267],"type":"Point"}
}