{
  "type": "Feature",
  "properties": {
    "iso:country":"US",
    "sg:address":"497 Pryor Rd",
    "sg:city":"Drummonds",
    "sg:classifiers":[
        {
            "category":"Wholesale",
            "subcategory":"Durable Goods & Equipment",
            "type":"Manufacturing & Wholesale Goods"
        }
    ],
    "sg:phone":"+1 901 835 3088",
    "sg:postcode":"38023",
    "sg:province":"TN",
    "wof:name":"Mona Belle & Co",
    "wof:placetype":"venue"
},
  "geometry": {"coordinates":[-89.95064000000001,35.477374],"type":"Point"}
}