{
  "type": "Feature",
  "properties": {
    "addr:full":"129 Denning Ford Rd Portland TN 37148",
    "addr:housenumber":"129",
    "addr:postcode":"37148",
    "addr:street":"Denning Ford Rd",
    "iso:country":"US",
    "sg:address":"129 Denning Ford Rd",
    "sg:city":"Portland",
    "sg:classifiers":[
        {
            "category":"Freight",
            "type":"Transportation"
        }
    ],
    "sg:phone":"+1 615 323 0650",
    "sg:postcode":"37148",
    "sg:province":"TN",
    "sg:tags":[
        "broker",
        "trucking"
    ],
    "wof:name":"RGT Express",
    "wof:placetype":"venue"
},
  "geometry": {"coordinates":[-86.499909,36.598289],"type":"Point"}
}