{
  "type": "Feature",
  "properties": {
    "iso:country":"US",
    "sg:address":"182 Prentice St",
    "sg:city":"Crossville",
    "sg:classifiers":[
        {
            "category":"Building & Trades",
            "subcategory":"Electrical",
            "type":"Services"
        }
    ],
    "sg:phone":"+1 931 707 5670",
    "sg:postcode":"38555",
    "sg:province":"TN",
    "sg:tags":[
        "electrical",
        "contractor"
    ],
    "wof:name":"Dezine Electric Co",
    "wof:placetype":"venue"
},
  "geometry": {"coordinates":[-85.049875,35.938173],"type":"Point"}
}