{
  "type": "Feature",
  "properties": {
    "addr:full":"6231 Perimeter Dr Chattanooga TN 37421",
    "addr:housenumber":"6231",
    "addr:postcode":"37421",
    "addr:street":"Perimeter Dr",
    "iso:country":"US",
    "sg:address":"6231 Perimeter Dr",
    "sg:city":"Chattanooga",
    "sg:classifiers":[
        {
            "category":"Home & Garden",
            "subcategory":"Furniture",
            "type":"Retail Goods"
        }
    ],
    "sg:phone":"+1 423 499 5151",
    "sg:postcode":"37421",
    "sg:province":"TN",
    "wof:name":"Catnapper Factory Outlet",
    "wof:placetype":"venue"
},
  "geometry": {"coordinates":[-85.181682,35.028457],"type":"Point"}
}