{
  "type": "Feature",
  "properties": {
    "iso:country":"US",
    "sg:address":"1305 Old Alabama Rd SW",
    "sg:city":"Mc Donald",
    "sg:classifiers":[
        {
            "category":"Professional",
            "subcategory":"Research",
            "type":"Services"
        },
        {
            "category":"Shopping",
            "subcategory":"Computers & Home Electronics",
            "type":"Retail Goods"
        }
    ],
    "sg:phone":"+1 423 478 1741",
    "sg:postcode":"37353",
    "sg:province":"TN",
    "sg:tags":[
        "commercial",
        "custom",
        "equipment",
        "dealer",
        "programing",
        "physical"
    ],
    "wof:name":"Jet Systems",
    "wof:placetype":"venue"
},
  "geometry": {"coordinates":[-84.968994,35.08799],"type":"Point"}
}