{
  "type": "Feature",
  "properties": {
    "iso:country":"US",
    "sg:address":"380 Bowen Ln",
    "sg:city":"Dyersburg",
    "sg:classifiers":[
        {
            "category":"Home & Garden",
            "subcategory":"Building Materials",
            "type":"Retail Goods"
        }
    ],
    "sg:phone":"+1 731 285 7232",
    "sg:postcode":"38024",
    "sg:province":"TN",
    "sg:tags":[
        "mixed",
        "concrete"
    ],
    "wof:name":"Fowlkes Concrete & Constr Co",
    "wof:placetype":"venue"
},
  "geometry": {"coordinates":[-89.408737,36.030478],"type":"Point"}
}