{
  "type": "Feature",
  "properties": {
    "iso:country":"US",
    "sg:address":"5300 Middlebrook Pk S",
    "sg:city":"Knoxville",
    "sg:classifiers":[
        {
            "category":"Building & Trades",
            "subcategory":"Equipment Rental",
            "type":"Services"
        }
    ],
    "sg:phone":"+1 865 588 8115",
    "sg:postcode":"37921",
    "sg:province":"TN",
    "sg:tags":[
        "yard"
    ],
    "sg:website":"www.bobcatofknoxville.com",
    "wof:name":"Bobcat Of Knoxville",
    "wof:placetype":"venue"
},
  "geometry": {"coordinates":[-84.00196099999999,35.956627],"type":"Point"}
}