{
  "type": "Feature",
  "properties": {
    "iso:country":"US",
    "sg:address":"126 Hazel Trce",
    "sg:city":"Hazel Green",
    "sg:classifiers":[
        {
            "category":"Building & Trades",
            "subcategory":"Landscaping Services",
            "type":"Services"
        }
    ],
    "sg:phone":"+1 256 828 3976",
    "sg:postcode":"35750",
    "sg:province":"TN",
    "sg:tags":[
        "lawn",
        "maintenance",
        "grounds"
    ],
    "wof:name":"Ikard's Lawn & Garden Care",
    "wof:placetype":"venue"
},
  "geometry": {"coordinates":[-86.592803,34.949561],"type":"Point"}
}