{
  "type": "Feature",
  "properties": {
    "iso:country":"US",
    "sg:address":"103 S Mill Ave",
    "sg:city":"Dyersburg",
    "sg:classifiers":[
        {
            "category":"Home & Garden",
            "subcategory":"Furniture",
            "type":"Retail Goods"
        }
    ],
    "sg:phone":"+1 731 285 5011",
    "sg:postcode":"38024",
    "sg:province":"TN",
    "wof:name":"Galleria",
    "wof:placetype":"venue"
},
  "geometry": {"coordinates":[-89.38685099999999,36.032856],"type":"Point"}
}