{
  "type": "Feature",
  "properties": {
    "addr:full":"100 Bluegrass Cove Hendersonville TN 37075",
    "addr:housenumber":"100",
    "addr:postcode":"37075",
    "addr:street":"Bluegrass Cove",
    "iso:country":"US",
    "sg:address":"100 Bluegrass Cove",
    "sg:city":"Hendersonville",
    "sg:classifiers":[
        {
            "category":"Organizations",
            "subcategory":"Non-profit Organization",
            "type":"Services"
        },
        {
            "category":"Professional",
            "type":"Services"
        }
    ],
    "sg:phone":"+1 615 822 9499",
    "sg:postcode":"37075",
    "sg:province":"TN",
    "sg:tags":[
        "establishment"
    ],
    "wof:name":"Memorial Foundation",
    "wof:placetype":"venue"
},
  "geometry": {"coordinates":[-86.565226,36.309098],"type":"Point"}
}