{
  "type": "Feature",
  "properties": {
    "addr:full":"4013 Wallace Ln Nashville TN 37215",
    "addr:housenumber":"4013",
    "addr:postcode":"37215",
    "addr:street":"Wallace Ln",
    "iso:country":"US",
    "sg:address":"4013 Wallace Ln",
    "sg:city":"Nashville",
    "sg:classifiers":[
        {
            "category":"Autos & Motor Vehicles",
            "subcategory":"Automobile Sales",
            "type":"Retail Goods"
        }
    ],
    "sg:phone":"+1 615 742 5599",
    "sg:postcode":"37215",
    "sg:province":"TN",
    "sg:tags":[
        "car",
        "dealer"
    ],
    "sg:website":"www.euronashville.com",
    "wof:name":"Euro Motors Cars",
    "wof:placetype":"venue"
},
  "geometry": {"coordinates":[-86.834757,36.107625],"type":"Point"}
}