{
  "type": "Feature",
  "properties": {
    "iso:country":"US",
    "sg:address":"1009 Belmont Ave",
    "sg:city":"Shelbyville",
    "sg:classifiers":[
        {
            "category":"Social Services",
            "type":"Services"
        }
    ],
    "sg:phone":"+1 931 680 1977",
    "sg:postcode":"37160",
    "sg:province":"TN",
    "sg:tags":[
        "youth",
        "organization",
        "center"
    ],
    "wof:name":"Rock Outreach Ministries",
    "wof:placetype":"venue"
},
  "geometry": {"coordinates":[-86.449438,35.476132],"type":"Point"}
}