{
  "type": "Feature",
  "properties": {
    "iso:country":"US",
    "sg:address":"2205 West St",
    "sg:city":"Germantown",
    "sg:classifiers":[
        {
            "category":"Banks & Credit Unions",
            "subcategory":"Bank",
            "type":"Services"
        }
    ],
    "sg:phone":"+1 901 757 2727",
    "sg:postcode":"38138",
    "sg:province":"TN",
    "sg:tags":[
        "mortgage"
    ],
    "wof:name":"Commercial Bank & Trust Co",
    "wof:placetype":"venue"
},
  "geometry": {"coordinates":[-89.811699,35.08901],"type":"Point"}
}