{
  "type": "Feature",
  "properties": {
    "addr:full":"1954 Green Hills Blvd Franklin TN 37067",
    "addr:housenumber":"1954",
    "addr:postcode":"37067",
    "addr:street":"Green Hills Blvd",
    "iso:country":"US",
    "sg:address":"1954 Green Hills Blvd",
    "sg:city":"Franklin",
    "sg:classifiers":[
        {
            "category":"Wholesale",
            "subcategory":"Hardware",
            "type":"Manufacturing & Wholesale Goods"
        }
    ],
    "sg:phone":"+1 615 771 0778",
    "sg:postcode":"37067",
    "sg:province":"TN",
    "sg:tags":[
        "equipment",
        "heating",
        "system"
    ],
    "wof:name":"Reznor Heators Armour Enter",
    "wof:placetype":"venue"
},
  "geometry": {"coordinates":[-86.75368400000001,35.921698],"type":"Point"}
}