{
  "type": "Feature",
  "properties": {
    "addr:full":"8277 Niblik Cove Cordova TN 38016",
    "addr:housenumber":"8277",
    "addr:postcode":"38016",
    "addr:street":"Niblik Cove",
    "iso:country":"US",
    "sg:address":"8277 Niblik Cove",
    "sg:city":"Cordova",
    "sg:classifiers":[
        {
            "category":"Professional",
            "subcategory":"Management & Consulting",
            "type":"Services"
        }
    ],
    "sg:phone":"+1 901 270 3270",
    "sg:postcode":"38016",
    "sg:province":"TN",
    "sg:tags":[
        "consultant",
        "resource",
        "human"
    ],
    "wof:name":"Human Capital Solutions Inc",
    "wof:placetype":"venue"
},
  "geometry": {"coordinates":[-89.786817,35.195075],"type":"Point"}
}