{
  "type": "Feature",
  "properties": {
    "addr:full":"902 W College St Pulaski TN 38478",
    "addr:housenumber":"902",
    "addr:postcode":"38478",
    "addr:street":"W College St",
    "iso:country":"US",
    "sg:address":"902 W College St",
    "sg:city":"Pulaski",
    "sg:classifiers":[
        {
            "category":"Coffee & Tea",
            "type":"Food & Drink"
        },
        {
            "category":"Bakery",
            "type":"Food & Drink"
        },
        {
            "category":"Donuts",
            "type":"Food & Drink"
        }
    ],
    "sg:menulink":"http://www.allmenus.com/tn/pulaski/231195-daylight-donuts/menu/",
    "sg:phone":"+1 931 363 9594",
    "sg:postcode":"38478",
    "sg:province":"TN",
    "sg:tags":[
        "american",
        "pastry"
    ],
    "wof:name":"Daylight Donuts",
    "wof:placetype":"venue"
},
  "geometry": {"coordinates":[-87.04376000000001,35.200518],"type":"Point"}
}