{
  "type": "Feature",
  "properties": {
    "iso:country":"US",
    "sg:address":"584 N Germantown Pkwy",
    "sg:city":"Cordova",
    "sg:classifiers":[
        {
            "category":"Health Services",
            "subcategory":"Doctor",
            "type":"Services"
        }
    ],
    "sg:phone":"+1 901 757 5594",
    "sg:postcode":"38018",
    "sg:province":"TN",
    "sg:tags":[
        "physician",
        "surgeon"
    ],
    "wof:name":"Health First Medical Group",
    "wof:placetype":"venue"
},
  "geometry": {"coordinates":[-89.795507,35.140522],"type":"Point"}
}