{
  "type": "Feature",
  "properties": {
    "addr:full":"2539 Cecil Ave Knoxville TN 37917",
    "addr:housenumber":"2539",
    "addr:postcode":"37917",
    "addr:street":"Cecil Ave",
    "iso:country":"US",
    "sg:address":"2539 Cecil Ave",
    "sg:city":"Knoxville",
    "sg:classifiers":[
        {
            "category":"Autos & Motor Vehicles",
            "subcategory":"Auto Supplies",
            "type":"Retail Goods"
        }
    ],
    "sg:phone":"+1 865 522 1569",
    "sg:postcode":"37917",
    "sg:province":"TN",
    "wof:name":"Davids Emergency Road Service",
    "wof:placetype":"venue"
},
  "geometry": {"coordinates":[-83.90571199999999,35.99726],"type":"Point"}
}