{
  "type": "Feature",
  "properties": {
    "iso:country":"US",
    "sg:address":"924 Lebanon Pike",
    "sg:city":"Nashville",
    "sg:classifiers":[
        {
            "category":"Real Estate",
            "subcategory":"Real Estate Agent",
            "type":"Services"
        }
    ],
    "sg:phone":"+1 615 255 8888",
    "sg:postcode":"37210",
    "sg:province":"TN",
    "sg:tags":[
        "broker"
    ],
    "wof:name":"Bruce Fitzpatrick Realty",
    "wof:placetype":"venue"
},
  "geometry": {"coordinates":[-86.74200399999999,36.154395],"type":"Point"}
}