{
  "type": "Feature",
  "properties": {
    "iso:country":"US",
    "sg:address":"1810 Violet Ct",
    "sg:city":"Murfreesboro",
    "sg:classifiers":[
        {
            "category":"Building & Trades",
            "subcategory":"Cleaning & Sanitation",
            "type":"Services"
        }
    ],
    "sg:phone":"+1 615 867 9544",
    "sg:postcode":"37128",
    "sg:province":"TN",
    "sg:tags":[
        "butler",
        "maid"
    ],
    "wof:name":"LA Belle Concierge",
    "wof:placetype":"venue"
},
  "geometry": {"coordinates":[-86.40219999999999,35.80971],"type":"Point"}
}