{
  "type": "Feature",
  "properties": {
    "iso:country":"US",
    "sg:address":"121 Cedarcrest Dr",
    "sg:city":"Hendersonville",
    "sg:classifiers":[
        {
            "category":"Professional",
            "subcategory":"Secretarial Services",
            "type":"Services"
        }
    ],
    "sg:phone":"+1 615 264 6654",
    "sg:postcode":"37075",
    "sg:province":"TN",
    "sg:tags":[
        "reporting"
    ],
    "wof:name":"All Write Reporting",
    "wof:placetype":"venue"
},
  "geometry": {"coordinates":[-86.631608,36.316041],"type":"Point"}
}