{
  "type": "Feature",
  "properties": {
    "addr:full":"7595 Poplar Ave Germantown TN 38138",
    "addr:housenumber":"7595",
    "addr:postcode":"38138",
    "addr:street":"Poplar Ave",
    "iso:country":"US",
    "sg:address":"7595 Poplar Ave",
    "sg:city":"Germantown",
    "sg:classifiers":[
        {
            "category":"Autos & Motor Vehicles",
            "subcategory":"Fuel & Gas Station",
            "type":"Retail Goods"
        }
    ],
    "sg:phone":"+1 901 754 2240",
    "sg:postcode":"38138",
    "sg:province":"TN",
    "sg:tags":[
        "station",
        "gasoline"
    ],
    "wof:name":"Amoco",
    "wof:placetype":"venue"
},
  "geometry": {"coordinates":[-89.810185,35.093445],"type":"Point"}
}