{
  "type": "Feature",
  "properties": {
    "addr:full":"306 N Boone St Johnson City TN 37604",
    "addr:housenumber":"306",
    "addr:postcode":"37604",
    "addr:street":"N Boone St",
    "iso:country":"US",
    "sg:address":"306 N Boone St",
    "sg:city":"Johnson City",
    "sg:classifiers":[
        {
            "category":"Shopping",
            "subcategory":"Clothing, Apparel, & Fashions",
            "type":"Retail Goods"
        }
    ],
    "sg:phone":"+1 423 926 0909",
    "sg:postcode":"37604",
    "sg:province":"TN",
    "wof:name":"Shonuff Fashion & Accessories",
    "wof:placetype":"venue"
},
  "geometry": {"coordinates":[-82.356054,36.318654],"type":"Point"}
}