{
  "type": "Feature",
  "properties": {
    "iso:country":"US",
    "sg:address":"6150 Poplar Ave",
    "sg:city":"Memphis",
    "sg:classifiers":[
        {
            "category":"Shopping",
            "subcategory":"Books",
            "type":"Retail Goods"
        }
    ],
    "sg:phone":"+1 901 683 8271",
    "sg:postcode":"38119",
    "sg:province":"TN",
    "sg:tags":[
        "dealer"
    ],
    "wof:name":"Cokesbury Book & Church Supls",
    "wof:placetype":"venue"
},
  "geometry": {"coordinates":[-89.857159,35.10157],"type":"Point"}
}