{
  "type": "Feature",
  "properties": {
    "iso:country":"US",
    "sg:address":"2946 Middlebrook Pike",
    "sg:city":"Knoxville",
    "sg:classifiers":[
        {
            "category":"Freight",
            "type":"Transportation"
        }
    ],
    "sg:phone":"+1 865 389 0700",
    "sg:postcode":"37921",
    "sg:province":"TN",
    "sg:tags":[
        "delivery"
    ],
    "sg:website":"www.pinnacledeliveryservice.com",
    "wof:name":"Pinnacle Delivery Svc",
    "wof:placetype":"venue"
},
  "geometry": {"coordinates":[-83.960752,35.963303],"type":"Point"}
}