{
  "type": "Feature",
  "properties": {
    "iso:country":"US",
    "sg:address":"383 Bill Bennett Rd",
    "sg:city":"Johnson City",
    "sg:classifiers":[
        {
            "category":"Building & Trades",
            "subcategory":"Plumbing",
            "type":"Services"
        }
    ],
    "sg:phone":"+1 423 434 2899",
    "sg:postcode":"37604",
    "sg:province":"TN",
    "sg:tags":[
        "contractor"
    ],
    "wof:name":"Mild To Extreme Plbg Contrs",
    "wof:placetype":"venue"
},
  "geometry": {"coordinates":[-82.390863,36.264887],"type":"Point"}
}