{
  "type": "Feature",
  "properties": {
    "iso:country":"US",
    "sg:address":"3815 US Hwy 79 N",
    "sg:city":"Paris",
    "sg:classifiers":[
        {
            "category":"Wholesale",
            "subcategory":"Hardware",
            "type":"Manufacturing & Wholesale Goods"
        }
    ],
    "sg:phone":"+1 731 642 3361",
    "sg:postcode":"38242",
    "sg:province":"TN",
    "sg:tags":[
        "plumbing",
        "fixture",
        "supply"
    ],
    "wof:name":"Paris Plumbing & Electric Supl",
    "wof:placetype":"venue"
},
  "geometry": {"coordinates":[-88.254536,36.334817],"type":"Point"}
}