{
  "type": "Feature",
  "properties": {
    "iso:country":"US",
    "sg:address":"115 Smith Ave",
    "sg:city":"Hohenwald",
    "sg:classifiers":[
        {
            "category":"Recreation",
            "type":"Entertainment"
        }
    ],
    "sg:phone":"+1 931 796 3846",
    "sg:postcode":"38462",
    "sg:province":"TN",
    "sg:tags":[
        "parks"
    ],
    "wof:name":"Lewis County Baseball",
    "wof:placetype":"venue"
},
  "geometry": {"coordinates":[-87.55392399999999,35.552038],"type":"Point"}
}