{
  "type": "Feature",
  "properties": {
    "addr:full":"213 Downs Blvd Franklin TN 37064",
    "addr:housenumber":"213",
    "addr:postcode":"37064",
    "addr:street":"Downs Blvd",
    "iso:country":"US",
    "sg:address":"213 Downs Blvd",
    "sg:city":"Franklin",
    "sg:classifiers":[
        {
            "category":"Manufacturing",
            "subcategory":"Glass & Minerals",
            "type":"Manufacturing & Wholesale Goods"
        }
    ],
    "sg:phone":"+1 615 794 6688",
    "sg:postcode":"37064",
    "sg:province":"TN",
    "sg:tags":[
        "concrete",
        "brick",
        "prod",
        "block"
    ],
    "wof:name":"Sherman-Dixie Concrete Ind Inc",
    "wof:placetype":"venue"
},
  "geometry": {"coordinates":[-86.88024,35.908207],"type":"Point"}
}