{
  "type": "Feature",
  "properties": {
    "addr:full":"516 W Oakland Ave Johnson City TN 37604",
    "addr:housenumber":"516",
    "addr:postcode":"37604",
    "addr:street":"W Oakland Ave",
    "iso:country":"US",
    "sg:address":"516 W Oakland Ave",
    "sg:city":"Johnson City",
    "sg:classifiers":[
        {
            "category":"Banks & Credit Unions",
            "subcategory":"Bank",
            "type":"Services"
        }
    ],
    "sg:phone":"+1 423 434 2211",
    "sg:postcode":"37604",
    "sg:province":"TN",
    "wof:name":"Nations Heritage Fed CU",
    "wof:placetype":"venue"
},
  "geometry": {"coordinates":[-82.39211299999999,36.357825],"type":"Point"}
}