{
  "type": "Feature",
  "properties": {
    "iso:country":"US",
    "sg:address":"359 Satterfield Rd",
    "sg:city":"Luttrell",
    "sg:classifiers":[
        {
            "category":"Building & Trades",
            "subcategory":"Construction",
            "type":"Services"
        }
    ],
    "sg:phone":"+1 865 992 4517",
    "sg:postcode":"37779",
    "sg:province":"TN",
    "sg:tags":[
        "excavation",
        "contractor"
    ],
    "wof:name":"Hankins Excavating",
    "wof:placetype":"venue"
},
  "geometry": {"coordinates":[-83.84448500000001,36.18866],"type":"Point"}
}