{
  "type": "Feature",
  "properties": {
    "iso:country":"US",
    "sg:address":"9417 College St",
    "sg:city":"Strawberry Plains",
    "sg:classifiers":[
        {
            "category":"Manufacturing",
            "subcategory":"Textiles",
            "type":"Manufacturing & Wholesale Goods"
        }
    ],
    "sg:phone":"+1 865 932 1883",
    "sg:postcode":"37871",
    "sg:province":"TN",
    "sg:tags":[
        "screen",
        "printing"
    ],
    "wof:name":"Design of Knoxville",
    "wof:placetype":"venue"
},
  "geometry": {"coordinates":[-83.714073,36.026997],"type":"Point"}
}