{
  "type": "Feature",
  "properties": {
    "addr:full":"1837 Walter Garrett Rd Parsons TN 38363",
    "addr:housenumber":"1837",
    "addr:postcode":"38363",
    "addr:street":"Walter Garrett Rd",
    "iso:country":"US",
    "sg:address":"1837 Walter Garrett Rd",
    "sg:city":"Parsons",
    "sg:classifiers":[
        {
            "category":"Building & Trades",
            "subcategory":"Construction",
            "type":"Services"
        }
    ],
    "sg:phone":"+1 731 847 2246",
    "sg:postcode":"38363",
    "sg:province":"TN",
    "sg:tags":[
        "concrete",
        "contractor"
    ],
    "wof:name":"Hicks Concrete Finishing",
    "wof:placetype":"venue"
},
  "geometry": {"coordinates":[-88.096479,35.671793],"type":"Point"}
}