{
  "type": "Feature",
  "properties": {
    "addr:full":"2315 Luray Rd Huron TN 38345",
    "addr:housenumber":"2315",
    "addr:postcode":"38345",
    "addr:street":"Luray Rd",
    "iso:country":"US",
    "sg:address":"2315 Luray Rd",
    "sg:city":"Huron",
    "sg:classifiers":[
        {
            "category":"Organizations",
            "subcategory":"Religious Organization",
            "type":"Services"
        }
    ],
    "sg:phone":"+1 731 968 5846",
    "sg:postcode":"38345",
    "sg:province":"TN",
    "wof:name":"Emmanuel Baptist Church",
    "wof:placetype":"venue"
},
  "geometry": {"coordinates":[-88.56576,35.622651],"type":"Point"}
}