{
  "type": "Feature",
  "properties": {
    "iso:country":"US",
    "sg:address":"745 S Church St",
    "sg:city":"Murfreesboro",
    "sg:classifiers":[
        {
            "category":"Professional",
            "subcategory":"Management & Consulting",
            "type":"Services"
        }
    ],
    "sg:phone":"+1 615 890 9411",
    "sg:postcode":"37130",
    "sg:province":"TN",
    "wof:name":"American Express",
    "wof:placetype":"venue"
},
  "geometry": {"coordinates":[-86.39259199999999,35.837705],"type":"Point"}
}