{
  "type": "Feature",
  "properties": {
    "addr:full":"313 S Church St Murfreesboro TN 37130",
    "addr:housenumber":"313",
    "addr:postcode":"37130",
    "addr:street":"S Church St",
    "iso:country":"US",
    "sg:address":"313 S Church St",
    "sg:city":"Murfreesboro",
    "sg:classifiers":[
        {
            "category":"Sports & Exercise",
            "subcategory":"Gym",
            "type":"Entertainment"
        }
    ],
    "sg:phone":"+1 615 849 8844",
    "sg:postcode":"37130",
    "sg:province":"TN",
    "sg:tags":[
        "facility",
        "club",
        "gymnasium",
        "health",
        "fitness",
        "studio",
        "physical"
    ],
    "wof:name":"Gold's Gym",
    "wof:placetype":"venue"
},
  "geometry": {"coordinates":[-86.391685,35.843728],"type":"Point"}
}