{
  "type": "Feature",
  "properties": {
    "addr:full":"626 Perkins St Union City TN 38261",
    "addr:housenumber":"626",
    "addr:postcode":"38261",
    "addr:street":"Perkins St",
    "iso:country":"US",
    "sg:address":"626 Perkins St",
    "sg:city":"Union City",
    "sg:classifiers":[
        {
            "category":"Autos & Motor Vehicles",
            "subcategory":"Auto Supplies",
            "type":"Retail Goods"
        }
    ],
    "sg:phone":"+1 731 885 1731",
    "sg:postcode":"38261",
    "sg:province":"TN",
    "sg:tags":[
        "tire"
    ],
    "wof:name":"Goodyear Auto Svc Ctr",
    "wof:placetype":"venue"
},
  "geometry": {"coordinates":[-89.05589500000001,36.422004],"type":"Point"}
}