{
  "type": "Feature",
  "properties": {
    "iso:country":"US",
    "sg:address":"324 Gill St",
    "sg:city":"Alcoa",
    "sg:classifiers":[
        {
            "category":"Shopping",
            "subcategory":"Computers & Home Electronics",
            "type":"Retail Goods"
        }
    ],
    "sg:phone":"+1 865 681 6682",
    "sg:postcode":"37701",
    "sg:province":"TN",
    "wof:name":"Tritek Computer Services",
    "wof:placetype":"venue"
},
  "geometry": {"coordinates":[-83.973871,35.760845],"type":"Point"}
}