{
  "type": "Feature",
  "properties": {
    "iso:country":"US",
    "sg:address":"1100 E Main St",
    "sg:city":"Rogersville",
    "sg:classifiers":[
        {
            "category":"Autos & Motor Vehicles",
            "subcategory":"Fuel & Gas Station",
            "type":"Retail Goods"
        }
    ],
    "sg:phone":"+1 423 272 7159",
    "sg:postcode":"37857",
    "sg:province":"TN",
    "sg:tags":[
        "oil"
    ],
    "wof:name":"Liberty",
    "wof:placetype":"venue"
},
  "geometry": {"coordinates":[-82.992165,36.413678],"type":"Point"}
}