{
  "type": "Feature",
  "properties": {
    "iso:country":"US",
    "sg:address":"116 S Cannon Ave",
    "sg:city":"Murfreesboro",
    "sg:classifiers":[
        {
            "category":"Professional",
            "type":"Services"
        }
    ],
    "sg:phone":"+1 615 867 8715",
    "sg:postcode":"37129",
    "sg:province":"TN",
    "sg:tags":[
        "establishment"
    ],
    "wof:name":"Servpro Of Rutherford County",
    "wof:placetype":"venue"
},
  "geometry": {"coordinates":[-86.402057,35.846182],"type":"Point"}
}