{
  "type": "Feature",
  "properties": {
    "iso:country":"US",
    "sg:address":"5431 Sycamore Grove Ln",
    "sg:city":"Memphis",
    "sg:classifiers":[
        {
            "category":"Organizations",
            "subcategory":"Professional Association",
            "type":"Services"
        }
    ],
    "sg:phone":"+1 901 683 4171",
    "sg:postcode":"38120",
    "sg:province":"TN",
    "wof:name":"Teresa M Waters",
    "wof:placetype":"venue"
},
  "geometry": {"coordinates":[-89.88053499999999,35.125362],"type":"Point"}
}