{
  "type": "Feature",
  "properties": {
    "addr:full":"1509 Rapids Rd Portland TN 37148",
    "addr:housenumber":"1509",
    "addr:postcode":"37148",
    "addr:street":"Rapids Rd",
    "iso:country":"US",
    "sg:address":"1509 Rapids Rd",
    "sg:city":"Portland",
    "sg:classifiers":[
        {
            "category":"Building & Trades",
            "subcategory":"Construction",
            "type":"Services"
        }
    ],
    "sg:phone":"+1 615 325 4560",
    "sg:postcode":"37148",
    "sg:province":"TN",
    "sg:tags":[
        "general",
        "contractor"
    ],
    "wof:name":"Jeff Woods Construction",
    "wof:placetype":"venue"
},
  "geometry": {"coordinates":[-86.48956,36.63912],"type":"Point"}
}