{
  "type": "Feature",
  "properties": {
    "iso:country":"US",
    "sg:address":"1044 Jackson Felts Rd",
    "sg:city":"Joelton",
    "sg:classifiers":[
        {
            "category":"Organizations",
            "subcategory":"Religious Organization",
            "type":"Services"
        }
    ],
    "sg:phone":"+1 615 746 0280",
    "sg:postcode":"37080",
    "sg:province":"TN",
    "wof:name":"Charity Baptist Church",
    "wof:placetype":"venue"
},
  "geometry": {"coordinates":[-86.945559,36.334927],"type":"Point"}
}