{
  "type": "Feature",
  "properties": {
    "iso:country":"US",
    "sg:address":"125 Gwinn Rd",
    "sg:city":"Ethridge",
    "sg:classifiers":[
        {
            "category":"Farming",
            "subcategory":"Farm",
            "type":"Manufacturing & Wholesale Goods"
        }
    ],
    "sg:phone":"+1 931 829 4630",
    "sg:postcode":"38456",
    "sg:province":"TN",
    "sg:tags":[
        "crop",
        "general"
    ],
    "wof:name":"Brian Beck",
    "wof:placetype":"venue"
},
  "geometry": {"coordinates":[-87.300742,35.315879],"type":"Point"}
}