{
  "type": "Feature",
  "properties": {
    "addr:full":"200 Norandal Dr Huntingdon TN 38344",
    "addr:housenumber":"200",
    "addr:postcode":"38344",
    "addr:street":"Norandal Dr",
    "iso:country":"US",
    "sg:address":"200 Norandal Dr",
    "sg:city":"Huntingdon",
    "sg:classifiers":[
        {
            "category":"Organizations",
            "subcategory":"Non-profit Organization",
            "type":"Services"
        }
    ],
    "sg:phone":"+1 731 986 8228",
    "sg:postcode":"38344",
    "sg:province":"TN",
    "wof:name":"Crime Stoppers",
    "wof:placetype":"venue"
},
  "geometry": {"coordinates":[-88.378798,36.021976],"type":"Point"}
}