{
  "type": "Feature",
  "properties": {
    "iso:country":"US",
    "sg:address":"24 Kingsboro Ln",
    "sg:city":"Crossville",
    "sg:classifiers":[
        {
            "category":"Professional",
            "subcategory":"Management & Consulting",
            "type":"Services"
        }
    ],
    "sg:phone":"+1 931 456 1213",
    "sg:postcode":"38558",
    "sg:province":"TN",
    "wof:name":"Bentley Consultants Inc",
    "wof:placetype":"venue"
},
  "geometry": {"coordinates":[-84.88470700000001,36.017718],"type":"Point"}
}