{
  "type": "Feature",
  "properties": {
    "addr:full":"704 S Parkway E Memphis TN 38106",
    "addr:housenumber":"704",
    "addr:postcode":"38106",
    "addr:street":"S Parkway E",
    "iso:country":"US",
    "sg:address":"704 S Parkway E",
    "sg:city":"Memphis",
    "sg:classifiers":[
        {
            "category":"Place Of Worship",
            "type":"Public Place"
        }
    ],
    "sg:phone":"+1 901 946 2529",
    "sg:postcode":"38106",
    "sg:province":"TN",
    "sg:tags":[
        "church"
    ],
    "wof:name":"Monumental Day Care Center",
    "wof:placetype":"venue"
},
  "geometry": {"coordinates":[-90.03908,35.107258],"type":"Point"}
}