{
  "type": "Feature",
  "properties": {
    "iso:country":"US",
    "sg:address":"401 Church St",
    "sg:city":"Nashville",
    "sg:classifiers":[
        {
            "category":"Sports & Exercise",
            "subcategory":"Gym",
            "type":"Entertainment"
        }
    ],
    "sg:phone":"+1 615 726 2878",
    "sg:postcode":"37219",
    "sg:province":"TN",
    "sg:tags":[
        "club",
        "health",
        "studio",
        "gymnasium"
    ],
    "wof:name":"Curves",
    "wof:placetype":"venue"
},
  "geometry": {"coordinates":[-86.779568,36.163438],"type":"Point"}
}