{
  "type": "Feature",
  "properties": {
    "addr:full":"720 College St Madisonville TN 37354",
    "addr:housenumber":"720",
    "addr:postcode":"37354",
    "addr:street":"College St",
    "iso:country":"US",
    "sg:address":"720 College St",
    "sg:city":"Madisonville",
    "sg:classifiers":[
        {
            "category":"Food & Beverages",
            "subcategory":"Groceries & Convenience Stores",
            "type":"Retail Goods"
        }
    ],
    "sg:phone":"+1 423 442 3873",
    "sg:postcode":"37354",
    "sg:province":"TN",
    "sg:tags":[
        "grocer"
    ],
    "wof:name":"Corner Market",
    "wof:placetype":"venue"
},
  "geometry": {"coordinates":[-84.36371200000001,35.527505],"type":"Point"}
}