{
  "type": "Feature",
  "properties": {
    "iso:country":"US",
    "sg:address":"9539 Kingston Pike",
    "sg:city":"Knoxville",
    "sg:classifiers":[
        {
            "category":"Organizations",
            "subcategory":"Membership Organization",
            "type":"Services"
        }
    ],
    "sg:phone":"+1 865 637 1910",
    "sg:postcode":"37922",
    "sg:province":"TN",
    "sg:tags":[
        "co",
        "club",
        "travel",
        "agency",
        "motor",
        "insurance"
    ],
    "wof:name":"Auto Club South",
    "wof:placetype":"venue"
},
  "geometry": {"coordinates":[-84.09968600000001,35.909448],"type":"Point"}
}