{
  "type": "Feature",
  "properties": {
    "iso:country":"US",
    "sg:address":"1617 Dilton Mankin Rd",
    "sg:city":"Murfreesboro",
    "sg:classifiers":[
        {
            "category":"Organizations",
            "subcategory":"Religious Organization",
            "type":"Services"
        }
    ],
    "sg:phone":"+1 615 890 3243",
    "sg:postcode":"37127",
    "sg:province":"TN",
    "wof:name":"Dilton Church Of Christ",
    "wof:placetype":"venue"
},
  "geometry": {"coordinates":[-86.323419,35.798633],"type":"Point"}
}