{
  "type": "Feature",
  "properties": {
    "addr:full":"302 Wesley St Johnson City TN 37601",
    "addr:housenumber":"302",
    "addr:postcode":"37601",
    "addr:street":"Wesley St",
    "iso:country":"US",
    "sg:address":"302 Wesley St",
    "sg:city":"Johnson City",
    "sg:classifiers":[
        {
            "category":"Professional",
            "subcategory":"Employment Agencies",
            "type":"Services"
        }
    ],
    "sg:phone":"+1 423 283 7774",
    "sg:postcode":"37601",
    "sg:province":"TN",
    "sg:tags":[
        "opportunity"
    ],
    "wof:name":"Comforce Staffing Svc",
    "wof:placetype":"venue"
},
  "geometry": {"coordinates":[-82.376496,36.351499],"type":"Point"}
}