{
  "type": "Feature",
  "properties": {
    "addr:full":"5025 Hillsboro Pike Nashville TN 37215",
    "addr:housenumber":"5025",
    "addr:postcode":"37215",
    "addr:street":"Hillsboro Pike",
    "iso:country":"US",
    "sg:address":"5025 Hillsboro Pike",
    "sg:city":"Nashville",
    "sg:classifiers":[
        {
            "category":"Professional",
            "subcategory":"Management & Consulting",
            "type":"Services"
        }
    ],
    "sg:phone":"+1 615 297 6007",
    "sg:postcode":"37215",
    "sg:province":"TN",
    "sg:tags":[
        "computer",
        "business",
        "related"
    ],
    "wof:name":"James R Stelling",
    "wof:placetype":"venue"
},
  "geometry": {"coordinates":[-86.82308500000001,36.097857],"type":"Point"}
}