{
  "type": "Feature",
  "properties": {
    "iso:country":"US",
    "sg:address":"441 Murfreesboro Pike",
    "sg:city":"Nashville",
    "sg:classifiers":[
        {
            "category":"Communications",
            "subcategory":"Television Station",
            "type":"Services"
        }
    ],
    "sg:phone":"+1 615 259 2200",
    "sg:postcode":"37210",
    "sg:province":"TN",
    "sg:tags":[
        "broadcasting",
        "co"
    ],
    "sg:website":"www.wkrn.com",
    "wof:name":"Young Broadcasting Inc",
    "wof:placetype":"venue"
},
  "geometry": {"coordinates":[-86.744366,36.142799],"type":"Point"}
}