{
  "type": "Feature",
  "properties": {
    "iso:country":"US",
    "sg:address":"1714 N Main St",
    "sg:city":"Shelbyville",
    "sg:classifiers":[
        {
            "category":"Wholesale",
            "subcategory":"Farm Supplies",
            "type":"Manufacturing & Wholesale Goods"
        },
        {
            "category":"Shopping",
            "type":"Retail Goods"
        }
    ],
    "sg:phone":"+1 931 680 9644",
    "sg:postcode":"37160",
    "sg:province":"TN",
    "sg:tags":[
        "tractor",
        "store"
    ],
    "sg:website":"www.mytscstore.com",
    "wof:name":"Tractor Supply 706",
    "wof:placetype":"venue"
},
  "geometry": {"coordinates":[-86.45641999999999,35.508403],"type":"Point"}
}