{
  "type": "Feature",
  "properties": {
    "addr:full":"7798 Hidden Grotto Rd Memphis TN 38125",
    "addr:housenumber":"7798",
    "addr:postcode":"38125",
    "addr:street":"Hidden Grotto Rd",
    "iso:country":"US",
    "sg:address":"7798 Hidden Grotto Rd",
    "sg:city":"Memphis",
    "sg:classifiers":[
        {
            "category":"Arts & Performance",
            "subcategory":"Theater",
            "type":"Entertainment"
        }
    ],
    "sg:phone":"+1 901 751 3566",
    "sg:postcode":"38125",
    "sg:province":"TN",
    "sg:tags":[
        "airshow"
    ],
    "wof:name":"Mary Dilda Airshows",
    "wof:placetype":"venue"
},
  "geometry": {"coordinates":[-89.80092,35.012277],"type":"Point"}
}