{
  "type": "Feature",
  "properties": {
    "iso:country":"US",
    "sg:address":"1 N Washington Ave",
    "sg:city":"Brownsville",
    "sg:classifiers":[
        {
            "category":"Government",
            "subcategory":"Office",
            "type":"Public Place"
        }
    ],
    "sg:phone":"+1 731 772 0332",
    "sg:postcode":"38012",
    "sg:province":"TN",
    "wof:name":"Haywood County Register Ofc",
    "wof:placetype":"venue"
},
  "geometry": {"coordinates":[-89.26215999999999,35.59391],"type":"Point"}
}