{
  "type": "Feature",
  "properties": {
    "iso:country":"US",
    "sg:address":"147 Jefferson Ave",
    "sg:city":"Memphis",
    "sg:classifiers":[
        {
            "category":"Organizations",
            "subcategory":"Non-profit Organization",
            "type":"Services"
        },
        {
            "category":"Professional",
            "subcategory":"Computer Services",
            "type":"Services"
        }
    ],
    "sg:phone":"+1 901 526 9411",
    "sg:postcode":"38103",
    "sg:province":"TN",
    "sg:tags":[
        "technical",
        "support",
        "resource"
    ],
    "wof:name":"Partners For The Homeless",
    "wof:placetype":"venue"
},
  "geometry": {"coordinates":[-90.050552,35.146733],"type":"Point"}
}