{
  "type": "Feature",
  "properties": {
    "iso:country":"US",
    "sg:address":"404 Eastley Ct",
    "sg:city":"Kingsport",
    "sg:classifiers":[
        {
            "category":"Professional",
            "subcategory":"Business Services",
            "type":"Services"
        }
    ],
    "sg:phone":"+1 423 246 8619",
    "sg:postcode":"37660",
    "sg:province":"TN",
    "wof:name":"Global Automotive Selling",
    "wof:placetype":"venue"
},
  "geometry": {"coordinates":[-82.592495,36.54627],"type":"Point"}
}