{
  "type": "Feature",
  "properties": {
    "iso:country":"US",
    "sg:address":"2544 Delmead Cove",
    "sg:city":"Germantown",
    "sg:classifiers":[
        {
            "category":"Professional",
            "type":"Services"
        }
    ],
    "sg:phone":"+1 901 756 7476",
    "sg:postcode":"38139",
    "sg:province":"TN",
    "sg:tags":[
        "establishment"
    ],
    "wof:name":"Mc Culloch Enterprises",
    "wof:placetype":"venue"
},
  "geometry": {"coordinates":[-89.74736300000001,35.079237],"type":"Point"}
}