{
  "type": "Feature",
  "properties": {
    "iso:country":"US",
    "sg:address":"2525 Perimeter Place Dr",
    "sg:city":"Nashville",
    "sg:classifiers":[
        {
            "category":"Wholesale",
            "subcategory":"Office Equipment",
            "type":"Manufacturing & Wholesale Goods"
        }
    ],
    "sg:phone":"+1 615 391 1960",
    "sg:postcode":"37214",
    "sg:province":"TN",
    "sg:tags":[
        "bank",
        "supply"
    ],
    "sg:website":"www.diebold.com",
    "wof:name":"Diebold Inc",
    "wof:placetype":"venue"
},
  "geometry": {"coordinates":[-86.679849,36.1487],"type":"Point"}
}