{
  "type": "Feature",
  "properties": {
    "addr:full":"613 Pan Gap Rd Chattanooga TN 37419",
    "addr:housenumber":"613",
    "addr:postcode":"37419",
    "addr:street":"Pan Gap Rd",
    "iso:country":"US",
    "sg:address":"613 Pan Gap Rd",
    "sg:city":"Chattanooga",
    "sg:classifiers":[
        {
            "category":"Professional",
            "type":"Services"
        }
    ],
    "sg:phone":"+1 423 825 6824",
    "sg:postcode":"37419",
    "sg:province":"TN",
    "sg:tags":[
        "cleaner",
        "rug",
        "carpet"
    ],
    "wof:name":"Chem. Tech Dispensing Systems",
    "wof:placetype":"venue"
},
  "geometry": {"coordinates":[-85.366642,35.045526],"type":"Point"}
}