{
  "type": "Feature",
  "properties": {
    "iso:country":"US",
    "sg:address":"2805 Foster Ave",
    "sg:city":"Nashville",
    "sg:classifiers":[
        {
            "category":"Banks & Credit Unions",
            "subcategory":"Bank",
            "type":"Services"
        }
    ],
    "sg:phone":"+1 615 429 6848",
    "sg:postcode":"37210",
    "sg:province":"TN",
    "sg:tags":[
        "mortgage",
        "loan",
        "broker",
        "real estate"
    ],
    "wof:name":"Integrity Financial Svcs Inc",
    "wof:placetype":"venue"
},
  "geometry": {"coordinates":[-86.743416,36.114139],"type":"Point"}
}