{
  "type": "Feature",
  "properties": {
    "addr:full":"2046 Belmont Cir Franklin TN 37069",
    "addr:housenumber":"2046",
    "addr:postcode":"37069",
    "addr:street":"Belmont Cir",
    "iso:country":"US",
    "sg:address":"2046 Belmont Cir",
    "sg:city":"Franklin",
    "sg:classifiers":[
        {
            "category":"Organizations",
            "subcategory":"Community Association",
            "type":"Services"
        }
    ],
    "sg:phone":"+1 615 599 0845",
    "sg:postcode":"37069",
    "sg:province":"TN",
    "sg:tags":[
        "consulting",
        "business"
    ],
    "wof:name":"Akel Envmtl Resources LLC",
    "wof:placetype":"venue"
},
  "geometry": {"coordinates":[-86.89510199999999,35.967749],"type":"Point"}
}