{
  "type": "Feature",
  "properties": {
    "addr:full":"1393 Elvis Presley Blvd Memphis TN 38106",
    "addr:housenumber":"1393",
    "addr:postcode":"38106",
    "addr:street":"Elvis Presley Blvd",
    "iso:country":"US",
    "sg:address":"1393 Elvis Presley Blvd",
    "sg:city":"Memphis",
    "sg:classifiers":[
        {
            "category":"Restaurant",
            "type":"Food & Drink"
        }
    ],
    "sg:phone":"+1 901 942 7433",
    "sg:postcode":"38106",
    "sg:province":"TN",
    "sg:tags":[
        "eating"
    ],
    "wof:name":"Payne's Bar-B-Q",
    "wof:placetype":"venue"
},
  "geometry": {"coordinates":[-90.021362,35.107744],"type":"Point"}
}