{
  "type": "Feature",
  "properties": {
    "addr:full":"5555 Edmondson Pike Nashville TN 37211",
    "addr:housenumber":"5555",
    "addr:postcode":"37211",
    "addr:street":"Edmondson Pike",
    "iso:country":"US",
    "sg:address":"5555 Edmondson Pike",
    "sg:city":"Nashville",
    "sg:phone":"+1 615 333 2722",
    "sg:postcode":"37211",
    "sg:province":"TN",
    "sg:website":"http://www.walgreens.com/default.jsp?ec=iyp_yellowpages_trademark",
    "wof:name":"Walgreens Pharmacies",
    "wof:placetype":"venue"
},
  "geometry": {"coordinates":[-86.743731,36.041184],"type":"Point"}
}