{
  "type": "Feature",
  "properties": {
    "addr:full":"1958 Oak Ridge Tpke Oak Ridge TN 37830",
    "addr:housenumber":"1958",
    "addr:postcode":"37830",
    "addr:street":"Oak Ridge Tpke",
    "iso:country":"US",
    "sg:address":"1958 Oak Ridge Tpke",
    "sg:city":"Oak Ridge",
    "sg:classifiers":[
        {
            "category":"Personal",
            "subcategory":"Beauty Salon",
            "type":"Services"
        }
    ],
    "sg:phone":"+1 865 482 2331",
    "sg:postcode":"37830",
    "sg:province":"TN",
    "sg:tags":[
        "shop"
    ],
    "wof:name":"Prisms & Profiles",
    "wof:placetype":"venue"
},
  "geometry": {"coordinates":[-84.288014,36.003396],"type":"Point"}
}