{
  "type": "Feature",
  "properties": {
    "addr:full":"311 S Parkway St Corinth TN 38834",
    "addr:housenumber":"311",
    "addr:postcode":"38834",
    "addr:street":"S Parkway St",
    "iso:country":"US",
    "sg:address":"311 S Parkway St",
    "sg:city":"Corinth",
    "sg:classifiers":[
        {
            "category":"Manufacturing",
            "subcategory":"Electronics",
            "type":"Manufacturing & Wholesale Goods"
        }
    ],
    "sg:phone":"+1 662 287 0220",
    "sg:postcode":"38834",
    "sg:province":"TN",
    "sg:tags":[
        "mfg",
        "boards",
        "circuit",
        "printed"
    ],
    "wof:name":"Design Plus",
    "wof:placetype":"venue"
},
  "geometry": {"coordinates":[-88.50569,34.925962],"type":"Point"}
}