{
  "type": "Feature",
  "properties": {
    "addr:full":"5301 California Ave Nashville TN 37209",
    "addr:housenumber":"5301",
    "addr:postcode":"37209",
    "addr:street":"California Ave",
    "iso:country":"US",
    "sg:address":"5301 California Ave",
    "sg:city":"Nashville",
    "sg:classifiers":[
        {
            "category":"Retail",
            "subcategory":"Auto Repair",
            "type":"Services"
        }
    ],
    "sg:phone":"+1 615 730 7038",
    "sg:postcode":"37209",
    "sg:province":"TN",
    "sg:tags":[
        "repairing",
        "automobile",
        "service-equipment",
        "supply"
    ],
    "wof:name":"C &M Autocare",
    "wof:placetype":"venue"
},
  "geometry": {"coordinates":[-86.852287,36.164169],"type":"Point"}
}