{
  "type": "Feature",
  "properties": {
    "iso:country":"US",
    "sg:address":"2032 Galahad Rd",
    "sg:city":"Chattanooga",
    "sg:classifiers":[
        {
            "category":"Building & Trades",
            "subcategory":"Construction",
            "type":"Services"
        }
    ],
    "sg:phone":"+1 423 843 1451",
    "sg:postcode":"37421",
    "sg:province":"TN",
    "sg:tags":[
        "general",
        "contractor"
    ],
    "wof:name":"GMC Construction",
    "wof:placetype":"venue"
},
  "geometry": {"coordinates":[-85.141734,35.030158],"type":"Point"}
}