{
  "type": "Feature",
  "properties": {
    "addr:full":"11 Lee Ln Manchester TN 37355",
    "addr:housenumber":"11",
    "addr:postcode":"37355",
    "addr:street":"Lee Ln",
    "iso:country":"US",
    "sg:address":"11 Lee Ln",
    "sg:city":"Manchester",
    "sg:classifiers":[
        {
            "category":"Autos & Motor Vehicles",
            "subcategory":"Automobile Sales",
            "type":"Retail Goods"
        }
    ],
    "sg:phone":"+1 931 723 7872",
    "sg:postcode":"37355",
    "sg:province":"TN",
    "sg:tags":[
        "car",
        "dealer"
    ],
    "wof:name":"Custom Auto Sales",
    "wof:placetype":"venue"
},
  "geometry": {"coordinates":[-86.018666,35.524464],"type":"Point"}
}