{
  "type": "Feature",
  "properties": {
    "addr:full":"79 Bowling Dr Jackson TN 38305",
    "addr:housenumber":"79",
    "addr:postcode":"38305",
    "addr:street":"Bowling Dr",
    "iso:country":"US",
    "sg:address":"79 Bowling Dr",
    "sg:city":"Jackson",
    "sg:classifiers":[
        {
            "category":"Autos & Motor Vehicles",
            "subcategory":"Automobile Sales",
            "type":"Retail Goods"
        }
    ],
    "sg:phone":"+1 731 661 9474",
    "sg:postcode":"38305",
    "sg:province":"TN",
    "sg:tags":[
        "group"
    ],
    "wof:name":"45 Gran Prix Go Cart Amsements",
    "wof:placetype":"venue"
},
  "geometry": {"coordinates":[-88.85348,35.70818],"type":"Point"}
}