{
  "type": "Feature",
  "properties": {
    "iso:country":"US",
    "sg:address":"4198 Sequoia Rd",
    "sg:city":"Memphis",
    "sg:classifiers":[
        {
            "category":"Health Services",
            "subcategory":"Doctor",
            "type":"Services"
        }
    ],
    "sg:phone":"+1 901 767 6266",
    "sg:postcode":"38117",
    "sg:province":"TN",
    "sg:tags":[
        "medical"
    ],
    "wof:name":"Elaine Shelton",
    "wof:placetype":"venue"
},
  "geometry": {"coordinates":[-89.924801,35.142299],"type":"Point"}
}