{
  "type": "Feature",
  "properties": {
    "addr:full":"721 Royal Pkwy Nashville TN 37214",
    "addr:housenumber":"721",
    "addr:postcode":"37214",
    "addr:street":"Royal Pkwy",
    "iso:country":"US",
    "sg:address":"721 Royal Pkwy",
    "sg:city":"Nashville",
    "sg:classifiers":[
        {
            "category":"Travel",
            "subcategory":"Hotels & Motels",
            "type":"Entertainment"
        }
    ],
    "sg:phone":"+1 615 493 5200",
    "sg:postcode":"37214",
    "sg:province":"TN",
    "sg:tags":[
        "lodging"
    ],
    "wof:name":"Hyatt Place Nashville Airport",
    "wof:placetype":"venue"
},
  "geometry": {"coordinates":[-86.666392,36.145999],"type":"Point"}
}