{
  "type": "Feature",
  "properties": {
    "addr:full":"7540 E Brainerd Rd Chattanooga TN 37421",
    "addr:housenumber":"7540",
    "addr:postcode":"37421",
    "addr:street":"E Brainerd Rd",
    "iso:country":"US",
    "sg:address":"7540 E Brainerd Rd",
    "sg:city":"Chattanooga",
    "sg:classifiers":[
        {
            "category":"Shopping",
            "subcategory":"Gifts & Souvenirs",
            "type":"Retail Goods"
        }
    ],
    "sg:phone":"+1 423 648 6547",
    "sg:postcode":"37421",
    "sg:province":"TN",
    "sg:tags":[
        "shop"
    ],
    "wof:name":"Polka Dot",
    "wof:placetype":"venue"
},
  "geometry": {"coordinates":[-85.160056,35.013145],"type":"Point"}
}