{
  "type": "Feature",
  "properties": {
    "iso:country":"US",
    "sg:address":"200 New York Ave",
    "sg:city":"Oak Ridge",
    "sg:classifiers":[
        {
            "category":"Health Services",
            "subcategory":"Doctor",
            "type":"Services"
        }
    ],
    "sg:phone":"+1 865 482 8944",
    "sg:postcode":"37830",
    "sg:province":"TN",
    "sg:tags":[
        "physician",
        "surgeon"
    ],
    "wof:name":"Oak Ridge Neurosurgery",
    "wof:placetype":"venue"
},
  "geometry": {"coordinates":[-84.248907,36.022684],"type":"Point"}
}