{
  "type": "Feature",
  "properties": {
    "iso:country":"US",
    "sg:address":"3009 Columbia Ave",
    "sg:city":"Franklin",
    "sg:classifiers":[
        {
            "category":"Retail",
            "subcategory":"Funeral Services",
            "type":"Services"
        },
        {
            "category":"Landmark",
            "subcategory":"Monument",
            "type":"Public Place"
        },
        {
            "category":"Cemetery",
            "type":"Public Place"
        }
    ],
    "sg:phone":"+1 615 794 2289",
    "sg:postcode":"37064",
    "sg:province":"TN",
    "sg:tags":[
        "casket",
        "supply",
        "crematory",
        "director",
        "plans-pre-arranged",
        "embalmer"
    ],
    "sg:website":"http://www.williamsonmemorial.com",
    "wof:name":"Williamson Memorial Funeral Home & Gardens",
    "wof:placetype":"venue"
},
  "geometry": {"coordinates":[-86.876926,35.893103],"type":"Point"}
}