{
  "type": "Feature",
  "properties": {
    "iso:country":"US",
    "sg:address":"5330 Lake Village Dr",
    "sg:city":"Memphis",
    "sg:classifiers":[
        {
            "category":"Professional",
            "subcategory":"Management & Consulting",
            "type":"Services"
        }
    ],
    "sg:phone":"+1 901 753 2038",
    "sg:postcode":"38125",
    "sg:province":"TN",
    "sg:tags":[
        "business"
    ],
    "wof:name":"Pw Consulting",
    "wof:placetype":"venue"
},
  "geometry": {"coordinates":[-89.81952699999999,35.004353],"type":"Point"}
}