{
  "type": "Feature",
  "properties": {
    "iso:country":"US",
    "sg:address":"3627 Bristol Hwy",
    "sg:city":"Johnson City",
    "sg:classifiers":[
        {
            "category":"Autos & Motor Vehicles",
            "subcategory":"Automobile Sales",
            "type":"Retail Goods"
        }
    ],
    "sg:phone":"+1 423 282 5246",
    "sg:postcode":"37601",
    "sg:province":"TN",
    "sg:tags":[
        "used"
    ],
    "wof:name":"S & S Motors",
    "wof:placetype":"venue"
},
  "geometry": {"coordinates":[-82.367238,36.380473],"type":"Point"}
}