{
  "type": "Feature",
  "properties": {
    "addr:full":"3538 Tom Austin Hwy Springfield TN 37172",
    "addr:housenumber":"3538",
    "addr:postcode":"37172",
    "addr:street":"Tom Austin Hwy",
    "iso:country":"US",
    "sg:address":"3538 Tom Austin Hwy",
    "sg:city":"Springfield",
    "sg:classifiers":[
        {
            "category":"Banks & Credit Unions",
            "subcategory":"Investment Brokerage",
            "type":"Services"
        }
    ],
    "sg:phone":"+1 615 212 0269",
    "sg:postcode":"37172",
    "sg:province":"TN",
    "sg:tags":[
        "advisory",
        "financial"
    ],
    "wof:name":"American General Financial Svc",
    "wof:placetype":"venue"
},
  "geometry": {"coordinates":[-86.880169,36.489543],"type":"Point"}
}