{
  "type": "Feature",
  "properties": {
    "addr:full":"1466 Francis Station Dr Knoxville TN 37909",
    "addr:housenumber":"1466",
    "addr:postcode":"37909",
    "addr:street":"Francis Station Dr",
    "iso:country":"US",
    "sg:address":"1466 Francis Station Dr",
    "sg:city":"Knoxville",
    "sg:classifiers":[
        {
            "category":"Professional",
            "type":"Services"
        }
    ],
    "sg:phone":"+1 865 539 4581",
    "sg:postcode":"37909",
    "sg:province":"TN",
    "wof:name":"Firmm Inc",
    "wof:placetype":"venue"
},
  "geometry": {"coordinates":[-84.034734,35.953399],"type":"Point"}
}