{
  "type": "Feature",
  "properties": {
    "addr:full":"1320 Farmville Rd Memphis TN 38122",
    "addr:housenumber":"1320",
    "addr:postcode":"38122",
    "addr:street":"Farmville Rd",
    "iso:country":"US",
    "sg:address":"1320 Farmville Rd",
    "sg:city":"Memphis",
    "sg:classifiers":[
        {
            "category":"Home & Garden",
            "subcategory":"Furniture",
            "type":"Retail Goods"
        }
    ],
    "sg:phone":"+1 901 323 3436",
    "sg:postcode":"38122",
    "sg:province":"TN",
    "wof:name":"Mattress Factory Showroom Inc",
    "wof:placetype":"venue"
},
  "geometry": {"coordinates":[-89.951121,35.167314],"type":"Point"}
}