{
  "type": "Feature",
  "properties": {
    "iso:country":"US",
    "sg:address":"1008 Linwood Rd",
    "sg:city":"Memphis",
    "sg:classifiers":[
        {
            "category":"Professional",
            "subcategory":"Management & Consulting",
            "type":"Services"
        }
    ],
    "sg:phone":"+1 901 332 1332",
    "sg:postcode":"38116",
    "sg:province":"TN",
    "sg:tags":[
        "party",
        "planning"
    ],
    "wof:name":"CLT Production",
    "wof:placetype":"venue"
},
  "geometry": {"coordinates":[-90.034622,35.023446],"type":"Point"}
}