{
  "type": "Feature",
  "properties": {
    "addr:full":"4238 Wildwood Rd Maryville TN 37804",
    "addr:housenumber":"4238",
    "addr:postcode":"37804",
    "addr:street":"Wildwood Rd",
    "iso:country":"US",
    "sg:address":"4238 Wildwood Rd",
    "sg:city":"Maryville",
    "sg:classifiers":[
        {
            "category":"Building & Trades",
            "subcategory":"Construction",
            "type":"Services"
        }
    ],
    "sg:phone":"+1 865 681 8942",
    "sg:postcode":"37804",
    "sg:province":"TN",
    "wof:name":"Pro Natural Gas Contractors",
    "wof:placetype":"venue"
},
  "geometry": {"coordinates":[-83.88102000000001,35.80636],"type":"Point"}
}