{
  "type": "Feature",
  "properties": {
    "iso:country":"US",
    "sg:address":"906 E Tri County Blvd",
    "sg:city":"Oliver Springs",
    "sg:classifiers":[
        {
            "category":"Government",
            "subcategory":"Court House",
            "type":"Public Place"
        }
    ],
    "sg:phone":"+1 865 435 5946",
    "sg:postcode":"37840",
    "sg:province":"TN",
    "sg:tags":[
        "city"
    ],
    "wof:name":"Oliver Springs City Court",
    "wof:placetype":"venue"
},
  "geometry": {"coordinates":[-84.311704,36.021647],"type":"Point"}
}