{
  "type": "Feature",
  "properties": {
    "iso:country":"US",
    "sg:address":"270 Holt Hills Rd",
    "sg:city":"Nashville",
    "sg:classifiers":[
        {
            "category":"Organizations",
            "subcategory":"Religious Organization",
            "type":"Services"
        }
    ],
    "sg:phone":"+1 615 833 5805",
    "sg:postcode":"37211",
    "sg:province":"TN",
    "wof:name":"Adventres With Jsus Ministries",
    "wof:placetype":"venue"
},
  "geometry": {"coordinates":[-86.72563599999999,36.023762],"type":"Point"}
}