{
  "type": "Feature",
  "properties": {
    "iso:country":"US",
    "sg:address":"1916 Patterson St",
    "sg:city":"Nashville",
    "sg:classifiers":[
        {
            "category":"Health Services",
            "subcategory":"Doctor",
            "type":"Services"
        }
    ],
    "sg:phone":"+1 615 327 2630",
    "sg:postcode":"37203",
    "sg:province":"TN",
    "sg:tags":[
        "dentist"
    ],
    "wof:name":"David Pittman DDS",
    "wof:placetype":"venue"
},
  "geometry": {"coordinates":[-86.802049,36.155518],"type":"Point"}
}