{
  "type": "Feature",
  "properties": {
    "iso:country":"US",
    "sg:address":"202 W Mill St",
    "sg:city":"Rutherford",
    "sg:classifiers":[
        {
            "category":"Autos & Motor Vehicles",
            "subcategory":"Auto Supplies",
            "type":"Retail Goods"
        }
    ],
    "sg:phone":"+1 731 665 6196",
    "sg:postcode":"38369",
    "sg:province":"TN",
    "sg:tags":[
        "automobile",
        "parts"
    ],
    "wof:name":"Sample's Auto & Tractor Supply",
    "wof:placetype":"venue"
},
  "geometry": {"coordinates":[-88.987052,36.126389],"type":"Point"}
}