{
  "type": "Feature",
  "properties": {
    "iso:country":"US",
    "sg:address":"2235 Covington Pike",
    "sg:city":"Memphis",
    "sg:classifiers":[
        {
            "category":"Social Services",
            "type":"Services"
        }
    ],
    "sg:phone":"+1 901 388 1172",
    "sg:postcode":"38128",
    "sg:province":"TN",
    "wof:name":"Life Choices Pregnancy Resourc",
    "wof:placetype":"venue"
},
  "geometry": {"coordinates":[-89.89623,35.18665],"type":"Point"}
}