{
  "type": "Feature",
  "properties": {
    "addr:full":"107 Sequoia Ln Oak Ridge TN 37830",
    "addr:housenumber":"107",
    "addr:postcode":"37830",
    "addr:street":"Sequoia Ln",
    "iso:country":"US",
    "sg:address":"107 Sequoia Ln",
    "sg:city":"Oak Ridge",
    "sg:classifiers":[
        {
            "category":"Shopping",
            "subcategory":"Used Merchandise",
            "type":"Retail Goods"
        }
    ],
    "sg:phone":"+1 865 483 8717",
    "sg:postcode":"37830",
    "sg:province":"TN",
    "wof:name":"Second Touch",
    "wof:placetype":"venue"
},
  "geometry": {"coordinates":[-84.29716000000001,36.0029],"type":"Point"}
}