{
  "type": "Feature",
  "properties": {
    "iso:country":"US",
    "sg:address":"320 N Cumberland St",
    "sg:city":"Lebanon",
    "sg:classifiers":[
        {
            "category":"Home & Garden",
            "subcategory":"Furniture",
            "type":"Retail Goods"
        }
    ],
    "sg:phone":"+1 615 444 1934",
    "sg:postcode":"37087",
    "sg:province":"TN",
    "wof:name":"Smith's Factory Direct Furn",
    "wof:placetype":"venue"
},
  "geometry": {"coordinates":[-86.29071399999999,36.210929],"type":"Point"}
}