{
  "type": "Feature",
  "properties": {
    "iso:country":"US",
    "sg:address":"102 Mallard Ln",
    "sg:city":"Oak Ridge",
    "sg:classifiers":[
        {
            "category":"Professional",
            "type":"Services"
        },
        {
            "category":"Shopping",
            "subcategory":"Pharmacy",
            "type":"Retail Goods"
        }
    ],
    "sg:phone":"+1 865 425 0697",
    "sg:postcode":"37830",
    "sg:province":"TN",
    "sg:tags":[
        "establishment"
    ],
    "wof:name":"Clinical Pharmacy Associates",
    "wof:placetype":"venue"
},
  "geometry": {"coordinates":[-84.31921800000001,35.994364],"type":"Point"}
}