{
  "type": "Feature",
  "properties": {
    "addr:full":"1311 Florence Rd Savannah TN 38372",
    "addr:housenumber":"1311",
    "addr:postcode":"38372",
    "addr:street":"Florence Rd",
    "iso:country":"US",
    "sg:address":"1311 Florence Rd",
    "sg:city":"Savannah",
    "sg:classifiers":[
        {
            "category":"Retail",
            "subcategory":"Portrait Studio",
            "type":"Services"
        }
    ],
    "sg:phone":"+1 731 925 7110",
    "sg:postcode":"38372",
    "sg:province":"TN",
    "sg:tags":[
        "photo"
    ],
    "sg:website":"www.finelight.org",
    "wof:name":"Finelight Photography",
    "wof:placetype":"venue"
},
  "geometry": {"coordinates":[-88.23933599999999,35.204177],"type":"Point"}
}