{
  "type": "Feature",
  "properties": {
    "addr:full":"714 Medaris St Clinton TN 37716",
    "addr:housenumber":"714",
    "addr:postcode":"37716",
    "addr:street":"Medaris St",
    "iso:country":"US",
    "sg:address":"714 Medaris St",
    "sg:city":"Clinton",
    "sg:classifiers":[
        {
            "category":"Professional",
            "subcategory":"Management & Consulting",
            "type":"Services"
        }
    ],
    "sg:phone":"+1 865 463 9862",
    "sg:postcode":"37716",
    "sg:province":"TN",
    "sg:tags":[
        "business"
    ],
    "wof:name":"Lonnie Thurston",
    "wof:placetype":"venue"
},
  "geometry": {"coordinates":[-84.12818,36.110345],"type":"Point"}
}