{
  "type": "Feature",
  "properties": {
    "addr:full":"4405 Elvis Presley Blvd Memphis TN 38116",
    "addr:housenumber":"4405",
    "addr:postcode":"38116",
    "addr:street":"Elvis Presley Blvd",
    "iso:country":"US",
    "sg:address":"4405 Elvis Presley Blvd",
    "sg:city":"Memphis",
    "sg:classifiers":[
        {
            "category":"Restaurant",
            "type":"Food & Drink"
        }
    ],
    "sg:menulink":"http://www.allmenus.com/tn/memphis/140173-subway/menu/",
    "sg:phone":"+1 901 345 2171",
    "sg:postcode":"38116",
    "sg:province":"TN",
    "sg:tags":[
        "american",
        "sandwich"
    ],
    "wof:name":"Subway",
    "wof:placetype":"venue"
},
  "geometry": {"coordinates":[-90.025992,35.02834],"type":"Point"}
}