{
  "type": "Feature",
  "properties": {
    "iso:country":"US",
    "sg:address":"179 Gail Ln",
    "sg:city":"Jacksboro",
    "sg:classifiers":[
        {
            "category":"Restaurant",
            "type":"Food & Drink"
        }
    ],
    "sg:phone":"+1 423 562 9841",
    "sg:postcode":"37757",
    "sg:province":"TN",
    "sg:tags":[
        "eating"
    ],
    "wof:name":"Eddies Pizza",
    "wof:placetype":"venue"
},
  "geometry": {"coordinates":[-84.159559,36.3057],"type":"Point"}
}