{
  "type": "Feature",
  "properties": {
    "addr:full":"3935 Summer Ave Memphis TN 38122",
    "addr:housenumber":"3935",
    "addr:postcode":"38122",
    "addr:street":"Summer Ave",
    "iso:country":"US",
    "sg:address":"3935 Summer Ave",
    "sg:city":"Memphis",
    "sg:classifiers":[
        {
            "category":"Professional",
            "subcategory":"Lawyer & Legal Services",
            "type":"Services"
        }
    ],
    "sg:phone":"+1 901 323 4455",
    "sg:postcode":"38122",
    "sg:province":"TN",
    "sg:tags":[
        "attorney"
    ],
    "wof:name":"Smith & Jones",
    "wof:placetype":"venue"
},
  "geometry": {"coordinates":[-89.92848600000001,35.149052],"type":"Point"}
}