{
  "type": "Feature",
  "properties": {
    "addr:full":"2920 Newport Hwy Sevierville TN 37876",
    "addr:housenumber":"2920",
    "addr:postcode":"37876",
    "addr:street":"Newport Hwy",
    "iso:country":"US",
    "sg:address":"2920 Newport Hwy",
    "sg:city":"Sevierville",
    "sg:classifiers":[
        {
            "category":"Shopping",
            "subcategory":"Used Merchandise",
            "type":"Retail Goods"
        }
    ],
    "sg:phone":"+1 865 429 2772",
    "sg:postcode":"37876",
    "sg:province":"TN",
    "sg:tags":[
        "antique"
    ],
    "wof:name":"Cobblestone Antique Mall",
    "wof:placetype":"venue"
},
  "geometry": {"coordinates":[-83.434828,35.894871],"type":"Point"}
}