{
  "type": "Feature",
  "properties": {
    "iso:country":"US",
    "sg:address":"5110 Gallatin Pike",
    "sg:city":"Nashville",
    "sg:classifiers":[
        {
            "category":"Retail",
            "subcategory":"Funeral Services",
            "type":"Services"
        }
    ],
    "sg:phone":"+1 615 865 1101",
    "sg:postcode":"37216",
    "sg:province":"TN",
    "sg:tags":[
        "director",
        "home"
    ],
    "wof:name":"Spring Hill Funeral Home",
    "wof:placetype":"venue"
},
  "geometry": {"coordinates":[-86.724812,36.234131],"type":"Point"}
}