{
  "type": "Feature",
  "properties": {
    "addr:full":"1200 Pineville Rd Chattanooga TN 37405",
    "addr:housenumber":"1200",
    "addr:postcode":"37405",
    "addr:street":"Pineville Rd",
    "iso:country":"US",
    "sg:address":"1200 Pineville Rd",
    "sg:city":"Chattanooga",
    "sg:classifiers":[
        {
            "category":"Health Services",
            "subcategory":"Doctor",
            "type":"Services"
        }
    ],
    "sg:phone":"+1 423 265 0063",
    "sg:postcode":"37405",
    "sg:province":"TN",
    "sg:tags":[
        "physician",
        "family",
        "medical",
        "practice",
        "surgeons",
        "medicine"
    ],
    "wof:name":"Chattnoga Prmry Care Athc Hlth",
    "wof:placetype":"venue"
},
  "geometry": {"coordinates":[-85.326691,35.084171],"type":"Point"}
}