{
  "type": "Feature",
  "properties": {
    "iso:country":"US",
    "sg:address":"818 Ogrady Dr",
    "sg:city":"Chattanooga",
    "sg:classifiers":[
        {
            "category":"Bus Charters",
            "type":"Transportation"
        }
    ],
    "sg:phone":"+1 423 821 8972",
    "sg:postcode":"37419",
    "sg:province":"TN",
    "sg:tags":[
        "local"
    ],
    "wof:name":"Mashburn Bus Service",
    "wof:placetype":"venue"
},
  "geometry": {"coordinates":[-85.357719,35.047351],"type":"Point"}
}