{
  "type": "Feature",
  "properties": {
    "iso:country":"US",
    "sg:address":"7386 Bridle Dr",
    "sg:city":"Nashville",
    "sg:classifiers":[
        {
            "category":"Organizations",
            "subcategory":"Religious Organization",
            "type":"Services"
        }
    ],
    "sg:phone":"+1 615 646 9616",
    "sg:postcode":"37221",
    "sg:province":"TN",
    "sg:tags":[
        "church"
    ],
    "wof:name":"Westfield Church Of Christ",
    "wof:placetype":"venue"
},
  "geometry": {"coordinates":[-86.933999,36.078137],"type":"Point"}
}