{
  "type": "Feature",
  "properties": {
    "addr:full":"6005 Kestner Private Dr Kingsport TN 37660",
    "addr:postcode":"6005;37660",
    "addr:street":"Kestner Private Dr",
    "iso:country":"US",
    "sg:address":"6005 Kestner Private Dr",
    "sg:city":"Kingsport",
    "sg:classifiers":[
        {
            "category":"Building & Trades",
            "subcategory":"Construction",
            "type":"Services"
        }
    ],
    "sg:phone":"+1 423 239 8010",
    "sg:postcode":"37660",
    "sg:province":"TN",
    "sg:tags":[
        "painter"
    ],
    "wof:name":"Jones Painting & Pressure Wash",
    "wof:placetype":"venue"
},
  "geometry": {"coordinates":[-82.489481,36.595679],"type":"Point"}
}