{
  "type": "Feature",
  "properties": {
    "iso:country":"US",
    "sg:address":"945 Dolly Parton Pkwy",
    "sg:city":"Sevierville",
    "sg:classifiers":[
        {
            "category":"Professional",
            "subcategory":"Business Services",
            "type":"Services"
        }
    ],
    "sg:phone":"+1 865 908 2505",
    "sg:postcode":"37862",
    "sg:province":"TN",
    "wof:name":"Touch of Class Interiors A",
    "wof:placetype":"venue"
},
  "geometry": {"coordinates":[-83.54423,35.864049],"type":"Point"}
}