{
  "type": "Feature",
  "properties": {
    "iso:country":"US",
    "sg:address":"2221 Cherokee Blvd",
    "sg:city":"Knoxville",
    "sg:classifiers":[
        {
            "category":"Shopping",
            "subcategory":"Gifts & Souvenirs",
            "type":"Retail Goods"
        }
    ],
    "sg:phone":"+1 865 522 9074",
    "sg:postcode":"37919",
    "sg:province":"TN",
    "sg:tags":[
        "novelty"
    ],
    "wof:name":"Cottage Gate",
    "wof:placetype":"venue"
},
  "geometry": {"coordinates":[-83.973384,35.929905],"type":"Point"}
}