{
  "type": "Feature",
  "properties": {
    "iso:country":"US",
    "sg:address":"6801 US Hwy 70",
    "sg:city":"Memphis",
    "sg:classifiers":[
        {
            "category":"Retail",
            "subcategory":"Repair Shop",
            "type":"Services"
        }
    ],
    "sg:phone":"+1 901 373 5265",
    "sg:postcode":"38134",
    "sg:province":"TN",
    "sg:tags":[
        "sharpening"
    ],
    "wof:name":"Clipper Shop",
    "wof:placetype":"venue"
},
  "geometry": {"coordinates":[-89.83471,35.205027],"type":"Point"}
}