{
  "type": "Feature",
  "properties": {
    "iso:country":"US",
    "sg:address":"448 N Cedar Bluff Rd",
    "sg:city":"Knoxville",
    "sg:classifiers":[
        {
            "category":"Retail",
            "subcategory":"Laundry & Dry Cleaning",
            "type":"Services"
        }
    ],
    "sg:phone":"+1 865 675 4750",
    "sg:postcode":"37923",
    "sg:province":"TN",
    "sg:tags":[
        "cleaners",
        "rug",
        "carpet"
    ],
    "wof:name":"All Seasons Chem-Dry",
    "wof:placetype":"venue"
},
  "geometry": {"coordinates":[-84.093838,35.924281],"type":"Point"}
}