{
  "type": "Feature",
  "properties": {
    "iso:country":"US",
    "sg:address":"2254 Jersey Way",
    "sg:city":"Maryville",
    "sg:classifiers":[
        {
            "category":"Building & Trades",
            "subcategory":"Construction",
            "type":"Services"
        }
    ],
    "sg:phone":"+1 865 219 3023",
    "sg:postcode":"37803",
    "sg:province":"TN",
    "sg:tags":[
        "roofing",
        "contractor"
    ],
    "wof:name":"First Impression Restoration",
    "wof:placetype":"venue"
},
  "geometry": {"coordinates":[-84.01864399999999,35.627747],"type":"Point"}
}