{
  "type": "Feature",
  "properties": {
    "iso:country":"US",
    "sg:address":"2613 Shady Grove Ln",
    "sg:city":"Knoxville",
    "sg:classifiers":[
        {
            "category":"Shopping",
            "subcategory":"Clothing, Apparel, & Fashions",
            "type":"Retail Goods"
        }
    ],
    "sg:phone":"+1 865 470 2436",
    "sg:postcode":"37921",
    "sg:province":"TN",
    "wof:name":"Male Properties Inc",
    "wof:placetype":"venue"
},
  "geometry": {"coordinates":[-84.04312299999999,35.968465],"type":"Point"}
}