{
  "type": "Feature",
  "properties": {
    "addr:full":"121 Jones Dr Murfreesboro TN 37143",
    "addr:housenumber":"121",
    "addr:postcode":"37143",
    "addr:street":"Jones Dr",
    "iso:country":"US",
    "sg:address":"121 Jones Dr",
    "sg:city":"Murfreesboro",
    "sg:classifiers":[
        {
            "category":"Food & Beverages",
            "subcategory":"Bakery",
            "type":"Retail Goods"
        }
    ],
    "sg:phone":"+1 615 631 1905",
    "sg:postcode":"37143",
    "sg:province":"TN",
    "sg:tags":[
        "baker"
    ],
    "wof:name":"B Jackson's",
    "wof:placetype":"venue"
},
  "geometry": {"coordinates":[-87.006371,36.186491],"type":"Point"}
}