{
  "type": "Feature",
  "properties": {
    "addr:full":"33 Music Sq W Nashville TN 37203",
    "addr:housenumber":"33",
    "addr:postcode":"37203",
    "addr:street":"Music Sq W",
    "iso:country":"US",
    "sg:address":"33 Music Sq W",
    "sg:city":"Nashville",
    "sg:classifiers":[
        {
            "category":"Shopping",
            "subcategory":"Music",
            "type":"Retail Goods"
        }
    ],
    "sg:phone":"+1 615 742 1250",
    "sg:postcode":"37203",
    "sg:province":"TN",
    "sg:tags":[
        "prerecorded",
        "record",
        "tape",
        "store"
    ],
    "wof:name":"Oh-Boy Records",
    "wof:placetype":"venue"
},
  "geometry": {"coordinates":[-86.793464,36.149112],"type":"Point"}
}