{
  "type": "Feature",
  "properties": {
    "iso:country":"US",
    "sg:address":"3800 Plantation Dr",
    "sg:city":"Hermitage",
    "sg:classifiers":[
        {
            "category":"Education",
            "subcategory":"School",
            "type":"Public Place"
        }
    ],
    "sg:phone":"+1 615 885 8838",
    "sg:postcode":"37076",
    "sg:province":"TN",
    "sg:tags":[
        "elementary"
    ],
    "sg:website":"www.mnps.org",
    "wof:name":"Hermitage Elementary School",
    "wof:placetype":"venue"
},
  "geometry": {"coordinates":[-86.63476799999999,36.198251],"type":"Point"}
}