{
  "type": "Feature",
  "properties": {
    "iso:country":"US",
    "sg:address":"615 E Chester St",
    "sg:city":"Jackson",
    "sg:classifiers":[
        {
            "category":"Organizations",
            "subcategory":"Religious Organization",
            "type":"Services"
        }
    ],
    "sg:phone":"+1 731 423 9695",
    "sg:postcode":"38301",
    "sg:province":"TN",
    "wof:name":"Oasis Of Hope Cathedral",
    "wof:placetype":"venue"
},
  "geometry": {"coordinates":[-88.809642,35.612362],"type":"Point"}
}