{
  "type": "Feature",
  "properties": {
    "addr:full":"121 Main St New Tazewell TN 37825",
    "addr:housenumber":"121",
    "addr:postcode":"37825",
    "addr:street":"Main St",
    "iso:country":"US",
    "sg:address":"121 Main St",
    "sg:city":"New Tazewell",
    "sg:classifiers":[
        {
            "category":"Personal",
            "subcategory":"Beauty Salon",
            "type":"Services"
        }
    ],
    "sg:phone":"+1 423 626 5266",
    "sg:postcode":"37825",
    "sg:province":"TN",
    "wof:name":"Beauty Unlimited",
    "wof:placetype":"venue"
},
  "geometry": {"coordinates":[-83.598489,36.442088],"type":"Point"}
}