{
  "type": "Feature",
  "properties": {
    "addr:full":"731 Pineville Rd Chattanooga TN 37405",
    "addr:housenumber":"731",
    "addr:postcode":"37405",
    "addr:street":"Pineville Rd",
    "iso:country":"US",
    "sg:address":"731 Pineville Rd",
    "sg:city":"Chattanooga",
    "sg:classifiers":[
        {
            "category":"Wholesale",
            "subcategory":"Construction Materials",
            "type":"Manufacturing & Wholesale Goods"
        }
    ],
    "sg:phone":"+1 423 634 0184",
    "sg:postcode":"37405",
    "sg:province":"TN",
    "sg:tags":[
        "sand",
        "gravel"
    ],
    "wof:name":"Monteagle Sand LLC",
    "wof:placetype":"venue"
},
  "geometry": {"coordinates":[-85.33069999999999,35.060715],"type":"Point"}
}