{
  "type": "Feature",
  "properties": {
    "addr:full":"23 Bills Dr Camden TN 38320",
    "addr:housenumber":"23",
    "addr:postcode":"38320",
    "addr:street":"Bills Dr",
    "iso:country":"US",
    "sg:address":"23 Bills Dr",
    "sg:city":"Camden",
    "sg:classifiers":[
        {
            "category":"Autos & Motor Vehicles",
            "subcategory":"Fuel & Gas Station",
            "type":"Retail Goods"
        }
    ],
    "sg:phone":"+1 731 584 8752",
    "sg:postcode":"38320",
    "sg:province":"TN",
    "sg:tags":[
        "station",
        "gasoline"
    ],
    "wof:name":"Amoco",
    "wof:placetype":"venue"
},
  "geometry": {"coordinates":[-88.131618,36.069557],"type":"Point"}
}