{
  "type": "Feature",
  "properties": {
    "iso:country":"US",
    "sg:address":"367 Harding Pl",
    "sg:city":"Nashville",
    "sg:classifiers":[
        {
            "category":"Banks & Credit Unions",
            "subcategory":"Bank",
            "type":"Services"
        }
    ],
    "sg:phone":"+1 615 331 5439",
    "sg:postcode":"37211",
    "sg:province":"TN",
    "sg:tags":[
        "cashing",
        "sell",
        "money",
        "order",
        "check"
    ],
    "sg:website":"www.acecashexpress.com",
    "wof:name":"Ace Cash Express",
    "wof:placetype":"venue"
},
  "geometry": {"coordinates":[-86.704919,36.084314],"type":"Point"}
}