{
  "type": "Feature",
  "properties": {
    "iso:country":"US",
    "sg:address":"400 S Highland St",
    "sg:city":"Memphis",
    "sg:classifiers":[
        {
            "category":"Social Services",
            "type":"Services"
        }
    ],
    "sg:phone":"+1 901 452 0710",
    "sg:postcode":"38111",
    "sg:province":"TN",
    "sg:tags":[
        "counselor",
        "marriage",
        "family"
    ],
    "wof:name":"Counseling & Education Center",
    "wof:placetype":"venue"
},
  "geometry": {"coordinates":[-89.94545100000001,35.120906],"type":"Point"}
}