{
  "type": "Feature",
  "properties": {
    "addr:full":"6012 Lakeland Dr Lenoir City TN 37772",
    "addr:housenumber":"6012",
    "addr:postcode":"37772",
    "addr:street":"Lakeland Dr",
    "iso:country":"US",
    "sg:address":"6012 Lakeland Dr",
    "sg:city":"Lenoir City",
    "sg:classifiers":[
        {
            "category":"Professional",
            "type":"Services"
        }
    ],
    "sg:phone":"+1 865 988 7819",
    "sg:postcode":"37772",
    "sg:province":"TN",
    "sg:tags":[
        "establishment"
    ],
    "wof:name":"Wise Giner Smith & Oscar",
    "wof:placetype":"venue"
},
  "geometry": {"coordinates":[-84.184195,35.809434],"type":"Point"}
}