{
  "type": "Feature",
  "properties": {
    "addr:full":"2220 Channel Ave Memphis TN 38113",
    "addr:housenumber":"2220",
    "addr:postcode":"38113",
    "addr:street":"Channel Ave",
    "iso:country":"US",
    "sg:address":"2220 Channel Ave",
    "sg:city":"Memphis",
    "sg:classifiers":[
        {
            "category":"Wholesale",
            "subcategory":"Scrap",
            "type":"Manufacturing & Wholesale Goods"
        }
    ],
    "sg:phone":"+1 901 948 5275",
    "sg:postcode":"38113",
    "sg:province":"TN",
    "sg:tags":[
        "metal",
        "iron"
    ],
    "wof:name":"Remarket Inc",
    "wof:placetype":"venue"
},
  "geometry": {"coordinates":[-90.10767800000001,35.097155],"type":"Point"}
}