{
  "type": "Feature",
  "properties": {
    "addr:full":"157 N Bells St Alamo TN 38001",
    "addr:housenumber":"157",
    "addr:postcode":"38001",
    "addr:street":"N Bells St",
    "iso:country":"US",
    "sg:address":"157 N Bells St",
    "sg:city":"Alamo",
    "sg:classifiers":[
        {
            "category":"Health Services",
            "subcategory":"Medical Lab",
            "type":"Services"
        }
    ],
    "sg:phone":"+1 731 696 2508",
    "sg:postcode":"38001",
    "sg:province":"TN",
    "sg:tags":[
        "laboratory"
    ],
    "wof:name":"Laboratory Corp Of America",
    "wof:placetype":"venue"
},
  "geometry": {"coordinates":[-89.11677400000001,35.791203],"type":"Point"}
}