{
  "type": "Feature",
  "properties": {
    "iso:country":"US",
    "sg:address":"8905 Sony Ln SW",
    "sg:city":"Knoxville",
    "sg:classifiers":[
        {
            "category":"Shopping",
            "subcategory":"Computers & Home Electronics",
            "type":"Retail Goods"
        }
    ],
    "sg:phone":"+1 865 690 3614",
    "sg:postcode":"37923",
    "sg:province":"TN",
    "sg:tags":[
        "software"
    ],
    "sg:website":"www.howe-two.com",
    "wof:name":"Howe Two Software",
    "wof:placetype":"venue"
},
  "geometry": {"coordinates":[-84.077591,35.906451],"type":"Point"}
}