{
  "type": "Feature",
  "properties": {
    "addr:full":"5362 Republic Dr Memphis TN 38118",
    "addr:housenumber":"5362",
    "addr:postcode":"38118",
    "addr:street":"Republic Dr",
    "iso:country":"US",
    "sg:address":"5362 Republic Dr",
    "sg:city":"Memphis",
    "sg:classifiers":[
        {
            "category":"Building & Trades",
            "subcategory":"Construction",
            "type":"Services"
        }
    ],
    "sg:phone":"+1 901 368 4700",
    "sg:postcode":"38118",
    "sg:province":"TN",
    "sg:tags":[
        "general",
        "commercial",
        "for",
        "contractor"
    ],
    "wof:name":"Eb Construction Company Inc",
    "wof:placetype":"venue"
},
  "geometry": {"coordinates":[-89.87937100000001,35.001685],"type":"Point"}
}