{
  "type": "Feature",
  "properties": {
    "addr:full":"730 E 22nd St Cookeville TN 38501",
    "addr:housenumber":"730",
    "addr:postcode":"38501",
    "addr:street":"E 22Nd St",
    "iso:country":"US",
    "sg:address":"730 E 22nd St",
    "sg:city":"Cookeville",
    "sg:classifiers":[
        {
            "category":"Bars & Pubs",
            "type":"Food & Drink"
        }
    ],
    "sg:phone":"+1 931 526 9848",
    "sg:postcode":"38501",
    "sg:province":"TN",
    "sg:tags":[
        "drinking"
    ],
    "wof:name":"Hilltop Tavern",
    "wof:placetype":"venue"
},
  "geometry": {"coordinates":[-85.489575,36.190257],"type":"Point"}
}