{
  "type": "Feature",
  "properties": {
    "iso:country":"US",
    "sg:address":"611 Oak St",
    "sg:city":"Gatlinburg",
    "sg:classifiers":[
        {
            "category":"Real Estate",
            "subcategory":"Real Estate Agent",
            "type":"Services"
        }
    ],
    "sg:phone":"+1 865 430 1562",
    "sg:postcode":"37738",
    "sg:province":"TN",
    "wof:name":"Gatlinburg Mountain Top Realty",
    "wof:placetype":"venue"
},
  "geometry": {"coordinates":[-83.521773,35.710358],"type":"Point"}
}