{
  "type": "Feature",
  "properties": {
    "iso:country":"US",
    "sg:address":"668 Waring Rd",
    "sg:city":"Memphis",
    "sg:classifiers":[
        {
            "category":"Home & Garden",
            "subcategory":"Carpets & Floor Coverings",
            "type":"Retail Goods"
        }
    ],
    "sg:phone":"+1 901 683 3507",
    "sg:postcode":"38122",
    "sg:province":"TN",
    "sg:tags":[
        "installs"
    ],
    "wof:name":"Brazzels Carpet & Floor Cvg Co",
    "wof:placetype":"venue"
},
  "geometry": {"coordinates":[-89.915802,35.150576],"type":"Point"}
}