{
  "type": "Feature",
  "properties": {
    "iso:country":"US",
    "sg:address":"7000 Goodlett Farms Pkwy # 500",
    "sg:city":"Cordova",
    "sg:classifiers":[
        {
            "category":"Utilities",
            "subcategory":"Mobile Phone",
            "type":"Services"
        }
    ],
    "sg:phone":"+1 901 381 8500",
    "sg:postcode":"38016",
    "sg:province":"TN",
    "sg:tags":[
        "telephone",
        "cellular"
    ],
    "sg:website":"http://www.cingular.com",
    "wof:name":"Cingular Wireless",
    "wof:placetype":"venue"
},
  "geometry": {"coordinates":[-89.829206,35.173982],"type":"Point"}
}