{
  "type": "Feature",
  "properties": {
    "iso:country":"US",
    "sg:address":"1401 Dodds Ave",
    "sg:city":"Chattanooga",
    "sg:classifiers":[
        {
            "category":"Building & Trades",
            "subcategory":"Plumbing",
            "type":"Services"
        }
    ],
    "sg:phone":"+1 423 870 8322",
    "sg:postcode":"37404",
    "sg:province":"TN",
    "sg:tags":[
        "conditioning",
        "air",
        "system",
        "contractor"
    ],
    "wof:name":"A-Tech Heating & Air",
    "wof:placetype":"venue"
},
  "geometry": {"coordinates":[-85.26949500000001,35.022192],"type":"Point"}
}