{
  "type": "Feature",
  "properties": {
    "iso:country":"US",
    "sg:address":"528 Myatt Dr",
    "sg:city":"Madison",
    "sg:classifiers":[
        {
            "category":"Manufacturing",
            "subcategory":"Textiles",
            "type":"Manufacturing & Wholesale Goods"
        }
    ],
    "sg:phone":"+1 615 865 6242",
    "sg:postcode":"37115",
    "sg:province":"TN",
    "sg:tags":[
        "fabric",
        "manufacturer"
    ],
    "wof:name":"BBA",
    "wof:placetype":"venue"
},
  "geometry": {"coordinates":[-86.692903,36.286154],"type":"Point"}
}