{
  "type": "Feature",
  "properties": {
    "iso:country":"US",
    "sg:address":"2026 E Van Hook St",
    "sg:city":"Milan",
    "sg:classifiers":[
        {
            "category":"Wholesale",
            "subcategory":"Electrical",
            "type":"Manufacturing & Wholesale Goods"
        }
    ],
    "sg:phone":"+1 731 686 9387",
    "sg:postcode":"38358",
    "sg:province":"TN",
    "sg:tags":[
        "plumbing",
        "hard",
        "lumber",
        "supply"
    ],
    "wof:name":"Arrow Wholesale Supply Inc",
    "wof:placetype":"venue"
},
  "geometry": {"coordinates":[-88.74670399999999,35.921316],"type":"Point"}
}