{
  "type": "Feature",
  "properties": {
    "iso:country":"US",
    "sg:address":"3090 Highland St",
    "sg:city":"Milan",
    "sg:classifiers":[
        {
            "category":"Building & Trades",
            "subcategory":"Construction",
            "type":"Services"
        }
    ],
    "sg:phone":"+1 731 686 0569",
    "sg:postcode":"38358",
    "sg:province":"TN",
    "sg:tags":[
        "dry wall",
        "contractor"
    ],
    "wof:name":"Interior Concepts & Designs",
    "wof:placetype":"venue"
},
  "geometry": {"coordinates":[-88.753514,35.913448],"type":"Point"}
}