{
  "type": "Feature",
  "properties": {
    "iso:country":"US",
    "sg:address":"61 Edenwold Rd",
    "sg:city":"Madison",
    "sg:classifiers":[
        {
            "category":"Government",
            "subcategory":"Office",
            "type":"Public Place"
        }
    ],
    "sg:phone":"+1 615 862 8577",
    "sg:postcode":"37115",
    "sg:province":"TN",
    "wof:name":"Davidson County Wastewater",
    "wof:placetype":"venue"
},
  "geometry": {"coordinates":[-86.690325,36.289572],"type":"Point"}
}