{
  "type": "Feature",
  "properties": {
    "iso:country":"US",
    "sg:address":"1400 Bloomingdale Rd",
    "sg:city":"Kingsport",
    "sg:classifiers":[
        {
            "category":"Manufacturing",
            "subcategory":"Rubber & Plastics",
            "type":"Manufacturing & Wholesale Goods"
        },
        {
            "category":"Autos & Motor Vehicles",
            "subcategory":"Auto Supplies",
            "type":"Retail Goods"
        },
        {
            "category":"Retail",
            "subcategory":"Auto Repair",
            "type":"Services"
        }
    ],
    "sg:phone":"+1 423 578 8178",
    "sg:postcode":"37660",
    "sg:province":"TN",
    "sg:tags":[
        "recap",
        "retread",
        "tires-wholesale",
        "tire",
        "manufacturer"
    ],
    "sg:website":"http://www.coopertire.com/html/",
    "wof:name":"Hunley's Tire",
    "wof:placetype":"venue"
},
  "geometry": {"coordinates":[-82.53563699999999,36.568611],"type":"Point"}
}