{
  "type": "Feature",
  "properties": {
    "iso:country":"US",
    "sg:address":"4285 Horton Hwy",
    "sg:city":"Greeneville",
    "sg:classifiers":[
        {
            "category":"Farming",
            "subcategory":"Farm",
            "type":"Manufacturing & Wholesale Goods"
        }
    ],
    "sg:phone":"+1 423 234 8192",
    "sg:postcode":"37745",
    "sg:province":"TN",
    "sg:tags":[
        "crop",
        "general"
    ],
    "wof:name":"Robert Tucker",
    "wof:placetype":"venue"
},
  "geometry": {"coordinates":[-82.870498,36.310725],"type":"Point"}
}