{
  "type": "Feature",
  "properties": {
    "addr:full":"205 E College St Dickson TN 37055",
    "addr:housenumber":"205",
    "addr:postcode":"37055",
    "addr:street":"E College St",
    "iso:country":"US",
    "sg:address":"205 E College St",
    "sg:city":"Dickson",
    "sg:classifiers":[
        {
            "category":"Autos & Motor Vehicles",
            "subcategory":"Motorcycle Sales",
            "type":"Retail Goods"
        }
    ],
    "sg:phone":"+1 615 446 1116",
    "sg:postcode":"37055",
    "sg:province":"TN",
    "sg:tags":[
        "scooter"
    ],
    "wof:name":"Cooley's Amen Motorcycles",
    "wof:placetype":"venue"
},
  "geometry": {"coordinates":[-87.386199,36.075484],"type":"Point"}
}