{
  "type": "Feature",
  "properties": {
    "iso:country":"US",
    "sg:address":"2765 Old Sams Creek Rd",
    "sg:city":"Pegram",
    "sg:classifiers":[
        {
            "category":"Professional",
            "subcategory":"Management & Consulting",
            "type":"Services"
        }
    ],
    "sg:phone":"+1 615 356 4984",
    "sg:postcode":"37143",
    "sg:province":"TN",
    "sg:tags":[
        "business"
    ],
    "wof:name":"Cata List Services",
    "wof:placetype":"venue"
},
  "geometry": {"coordinates":[-87.03612699999999,36.153334],"type":"Point"}
}