{
  "type": "Feature",
  "properties": {
    "iso:country":"US",
    "sg:address":"434 Harding Industrial Dr",
    "sg:city":"Nashville",
    "sg:classifiers":[
        {
            "category":"Professional",
            "subcategory":"Management & Consulting",
            "type":"Services"
        },
        {
            "category":"Wholesale",
            "subcategory":"Non-durable Goods",
            "type":"Manufacturing & Wholesale Goods"
        }
    ],
    "sg:phone":"+1 615 832 0300",
    "sg:postcode":"37211",
    "sg:province":"TN",
    "sg:tags":[
        "marketing",
        "advertising",
        "specialty",
        "consultant"
    ],
    "wof:name":"Innovative Productions LLC",
    "wof:placetype":"venue"
},
  "geometry": {"coordinates":[-86.697407,36.09581],"type":"Point"}
}