{
  "type": "Feature",
  "properties": {
    "iso:country":"US",
    "sg:address":"7790 US Hwy 70",
    "sg:city":"Memphis",
    "sg:classifiers":[
        {
            "category":"Personal",
            "subcategory":"Beauty Salon",
            "type":"Services"
        }
    ],
    "sg:phone":"+1 901 371 9912",
    "sg:postcode":"38133",
    "sg:province":"TN",
    "sg:tags":[
        "shop"
    ],
    "wof:name":"Kalipso Hair Studio",
    "wof:placetype":"venue"
},
  "geometry": {"coordinates":[-89.80989599999999,35.229615],"type":"Point"}
}