{
  "type": "Feature",
  "properties": {
    "iso:country":"US",
    "sg:address":"504 E E St",
    "sg:city":"Elizabethton",
    "sg:classifiers":[
        {
            "category":"Banks & Credit Unions",
            "subcategory":"Investment Brokerage",
            "type":"Services"
        }
    ],
    "sg:phone":"+1 423 543 7848",
    "sg:postcode":"37643",
    "sg:province":"TN",
    "sg:tags":[
        "security"
    ],
    "wof:name":"Edward Jones 03173",
    "wof:placetype":"venue"
},
  "geometry": {"coordinates":[-82.214837,36.348792],"type":"Point"}
}