{
  "type": "Feature",
  "properties": {
    "iso:country":"US",
    "sg:address":"186 Gregory Rd",
    "sg:city":"Portland",
    "sg:classifiers":[
        {
            "category":"Freight",
            "type":"Transportation"
        }
    ],
    "sg:phone":"+1 615 325 4790",
    "sg:postcode":"37148",
    "sg:province":"TN",
    "wof:name":"Rock Solid Freight Transport",
    "wof:placetype":"venue"
},
  "geometry": {"coordinates":[-86.401287,36.629256],"type":"Point"}
}