{
  "type": "Feature",
  "properties": {
    "iso:country":"US",
    "sg:address":"2000 Glen Echo Rd",
    "sg:city":"Nashville",
    "sg:classifiers":[
        {
            "category":"Banks & Credit Unions",
            "subcategory":"Investment Brokerage",
            "type":"Services"
        }
    ],
    "sg:phone":"+1 615 383 8600",
    "sg:postcode":"37215",
    "sg:province":"TN",
    "sg:tags":[
        "security"
    ],
    "sg:website":"www.rodgerscapital.com",
    "wof:name":"Rodgers Capital Group LP",
    "wof:placetype":"venue"
},
  "geometry": {"coordinates":[-86.810841,36.108385],"type":"Point"}
}