{
  "type": "Feature",
  "properties": {
    "addr:full":"1860 N Main St Crossville TN 38555",
    "addr:housenumber":"1860",
    "addr:postcode":"38555",
    "addr:street":"N Main St",
    "iso:country":"US",
    "sg:address":"1860 N Main St",
    "sg:city":"Crossville",
    "sg:classifiers":[
        {
            "category":"Shopping",
            "subcategory":"Department Store",
            "type":"Retail Goods"
        }
    ],
    "sg:phone":"+1 931 456 7678",
    "sg:postcode":"38555",
    "sg:province":"TN",
    "wof:name":"Sears Roebuck & Co",
    "wof:placetype":"venue"
},
  "geometry": {"coordinates":[-85.03807399999999,35.973669],"type":"Point"}
}