{
  "type": "Feature",
  "properties": {
    "iso:country":"US",
    "sg:address":"317 Oak St",
    "sg:city":"Chattanooga",
    "sg:classifiers":[
        {
            "category":"Government",
            "subcategory":"Office",
            "type":"Public Place"
        }
    ],
    "sg:phone":"+1 423 209 6495",
    "sg:postcode":"37403",
    "sg:province":"TN",
    "wof:name":"Hamilton County Guard Svc",
    "wof:placetype":"venue"
},
  "geometry": {"coordinates":[-85.305054,35.048351],"type":"Point"}
}