{
  "type": "Feature",
  "properties": {
    "iso:country":"US",
    "sg:address":"559 Pine Ridge Rd",
    "sg:city":"Clinton",
    "sg:classifiers":[
        {
            "category":"Building & Trades",
            "subcategory":"Construction",
            "type":"Services"
        }
    ],
    "sg:phone":"+1 865 388 8049",
    "sg:postcode":"37716",
    "sg:province":"TN",
    "sg:tags":[
        "downspouts",
        "gutter"
    ],
    "wof:name":"Oakridge Siding",
    "wof:placetype":"venue"
},
  "geometry": {"coordinates":[-84.258171,36.056875],"type":"Point"}
}