{
  "type": "Feature",
  "properties": {
    "iso:country":"US",
    "sg:address":"2154 S 3rd St",
    "sg:city":"Memphis",
    "sg:classifiers":[
        {
            "category":"Education",
            "subcategory":"School",
            "type":"Public Place"
        }
    ],
    "sg:phone":"+1 901 947 1207",
    "sg:postcode":"38109",
    "sg:province":"TN",
    "wof:name":"Yo Academy",
    "wof:placetype":"venue"
},
  "geometry": {"coordinates":[-90.056517,35.087584],"type":"Point"}
}