{
  "type": "Feature",
  "properties": {
    "iso:country":"US",
    "sg:address":"307 Johnsons Corner Rd",
    "sg:city":"Knoxville",
    "sg:classifiers":[
        {
            "category":"Professional",
            "subcategory":"Business Services",
            "type":"Services"
        }
    ],
    "sg:phone":"+1 865 777 0636",
    "sg:postcode":"37934",
    "sg:province":"TN",
    "wof:name":"Kari Openshaw Interiors",
    "wof:placetype":"venue"
},
  "geometry": {"coordinates":[-84.21305,35.860071],"type":"Point"}
}