{
  "type": "Feature",
  "properties": {
    "iso:country":"US",
    "sg:address":"314 Madison St",
    "sg:city":"Shelbyville",
    "sg:classifiers":[
        {
            "category":"Shopping",
            "subcategory":"Jewelry",
            "type":"Retail Goods"
        }
    ],
    "sg:phone":"+1 931 684 5388",
    "sg:postcode":"37160",
    "sg:province":"TN",
    "wof:name":"Joyeria Ivanidades 3 Diamantes",
    "wof:placetype":"venue"
},
  "geometry": {"coordinates":[-86.456126,35.488589],"type":"Point"}
}