{
  "type": "Feature",
  "properties": {
    "iso:country":"US",
    "sg:address":"2520 Keith St NW Suite 8",
    "sg:city":"Cleveland",
    "sg:classifiers":[
        {
            "category":"Insurance",
            "subcategory":"Hazard Insurance",
            "type":"Services"
        },
        {
            "category":"Insurance",
            "subcategory":"Insurance Agent",
            "type":"Services"
        },
        {
            "category":"Insurance",
            "subcategory":"Life Insurance",
            "type":"Services"
        },
        {
            "category":"Insurance",
            "subcategory":"Title Insurance",
            "type":"Services"
        }
    ],
    "sg:phone":"+1 423 472 0419",
    "sg:postcode":"37312",
    "sg:province":"TN",
    "sg:tags":[
        "auto",
        "homeowner"
    ],
    "sg:website":"http://www.nationwide.com/agent/Cleveland-TENNESSEE-insurance-agent/kathrine-wilson/office.html",
    "wof:name":"Kathrine Wilson - Nationwide Insurance",
    "wof:placetype":"venue"
},
  "geometry": {"coordinates":[-84.872654,35.183215],"type":"Point"}
}