{
  "type": "Feature",
  "properties": {
    "iso:country":"US",
    "sg:address":"114 Harbor Light Dr",
    "sg:city":"Johnson City",
    "sg:classifiers":[
        {
            "category":"Organizations",
            "subcategory":"Religious Organization",
            "type":"Services"
        }
    ],
    "sg:phone":"+1 423 926 1026",
    "sg:postcode":"37601",
    "sg:province":"TN",
    "sg:tags":[
        "church"
    ],
    "wof:name":"Harbor Light Baptist Church",
    "wof:placetype":"venue"
},
  "geometry": {"coordinates":[-82.28510199999999,36.335464],"type":"Point"}
}