{
  "type": "Feature",
  "properties": {
    "addr:full":"526 George Rd Memphis TN 38109",
    "addr:housenumber":"526",
    "addr:postcode":"38109",
    "addr:street":"George Rd",
    "iso:country":"US",
    "sg:address":"526 George Rd",
    "sg:city":"Memphis",
    "sg:classifiers":[
        {
            "category":"Organizations",
            "subcategory":"Religious Organization",
            "type":"Services"
        }
    ],
    "sg:phone":"+1 901 785 2129",
    "sg:postcode":"38109",
    "sg:province":"TN",
    "sg:tags":[
        "church"
    ],
    "wof:name":"Walls Chapel Church",
    "wof:placetype":"venue"
},
  "geometry": {"coordinates":[-90.08469700000001,35.015467],"type":"Point"}
}