{
  "type": "Feature",
  "properties": {
    "addr:full":"1433 Jackson Ave Memphis TN 38107",
    "addr:housenumber":"1433",
    "addr:postcode":"38107",
    "addr:street":"Jackson Ave",
    "iso:country":"US",
    "sg:address":"1433 Jackson Ave",
    "sg:city":"Memphis",
    "sg:classifiers":[
        {
            "category":"Food & Beverages",
            "subcategory":"Liquor & Beverages",
            "type":"Retail Goods"
        }
    ],
    "sg:phone":"+1 901 725 5003",
    "sg:postcode":"38107",
    "sg:province":"TN",
    "sg:tags":[
        "alcoholic"
    ],
    "wof:name":"Azors Liquors",
    "wof:placetype":"venue"
},
  "geometry": {"coordinates":[-90.01068100000001,35.15814],"type":"Point"}
}