{
  "type": "Feature",
  "properties": {
    "addr:full":"705 Winfield Dunn Pkwy Sevierville TN 37876",
    "addr:housenumber":"705",
    "addr:postcode":"37876",
    "addr:street":"Winfield Dunn Pkwy",
    "iso:country":"US",
    "sg:address":"705 Winfield Dunn Pkwy",
    "sg:city":"Sevierville",
    "sg:classifiers":[
        {
            "category":"Restaurant",
            "type":"Food & Drink"
        }
    ],
    "sg:phone":"+1 865 428 5001",
    "sg:postcode":"37876",
    "sg:province":"TN",
    "sg:website":"www.buddysbarbq.com",
    "wof:name":"Buddy's Bar-B-Q",
    "wof:placetype":"venue"
},
  "geometry": {"coordinates":[-83.572818,35.883237],"type":"Point"}
}