{
  "type": "Feature",
  "properties": {
    "iso:country":"US",
    "sg:address":"330 Gallatin Pike S",
    "sg:city":"Madison",
    "sg:classifiers":[
        {
            "category":"Shopping",
            "type":"Retail Goods"
        }
    ],
    "sg:phone":"+1 615 865 8791",
    "sg:postcode":"37115",
    "sg:province":"TN",
    "sg:tags":[
        "stamp",
        "coin",
        "dealer",
        "supply"
    ],
    "wof:name":"American Coin & Stamp Exchange",
    "wof:placetype":"venue"
},
  "geometry": {"coordinates":[-86.713426,36.258603],"type":"Point"}
}