{
  "type": "Feature",
  "properties": {
    "addr:full":"4384 Stage Rd Memphis TN 38128",
    "addr:housenumber":"4384",
    "addr:postcode":"38128",
    "addr:street":"Stage Rd",
    "iso:country":"US",
    "sg:address":"4384 Stage Rd",
    "sg:city":"Memphis",
    "sg:classifiers":[
        {
            "category":"Banks & Credit Unions",
            "subcategory":"Bank",
            "type":"Services"
        }
    ],
    "sg:phone":"+1 901 373 7773",
    "sg:postcode":"38128",
    "sg:province":"TN",
    "sg:tags":[
        "loan",
        "real estate"
    ],
    "wof:name":"Family First Mortgage",
    "wof:placetype":"venue"
},
  "geometry": {"coordinates":[-89.91955799999999,35.205362],"type":"Point"}
}