{
  "type": "Feature",
  "properties": {
    "iso:country":"US",
    "sg:address":"6024 Zachary Rd",
    "sg:city":"Corryton",
    "sg:classifiers":[
        {
            "category":"Shopping",
            "subcategory":"Crafts & Fabrics",
            "type":"Retail Goods"
        }
    ],
    "sg:phone":"+1 865 933 3330",
    "sg:postcode":"37721",
    "sg:province":"TN",
    "sg:tags":[
        "accessory",
        "costume",
        "trimmings"
    ],
    "wof:name":"Mary Kay Cosmetics",
    "wof:placetype":"venue"
},
  "geometry": {"coordinates":[-83.731948,36.132018],"type":"Point"}
}