{
  "type": "Feature",
  "properties": {
    "iso:country":"US",
    "sg:address":"1162 Breedlove St",
    "sg:city":"Memphis",
    "sg:classifiers":[
        {
            "category":"Shopping",
            "subcategory":"Florist",
            "type":"Retail Goods"
        }
    ],
    "sg:phone":"+1 901 526 1697",
    "sg:postcode":"38107",
    "sg:province":"TN",
    "wof:name":"Kenya's Flowers",
    "wof:placetype":"venue"
},
  "geometry": {"coordinates":[-90.02158,35.169748],"type":"Point"}
}