{
  "type": "Feature",
  "properties": {
    "iso:country":"US",
    "sg:address":"141 N Peters Rd",
    "sg:city":"Knoxville",
    "sg:classifiers":[
        {
            "category":"Home & Garden",
            "subcategory":"Household Appliances",
            "type":"Retail Goods"
        }
    ],
    "sg:phone":"+1 865 693 4344",
    "sg:postcode":"37923",
    "sg:province":"TN",
    "sg:tags":[
        "major"
    ],
    "wof:name":"Bone Enterprises Inc",
    "wof:placetype":"venue"
},
  "geometry": {"coordinates":[-84.081996,35.914657],"type":"Point"}
}