{
  "type": "Feature",
  "properties": {
    "iso:country":"US",
    "sg:address":"627 Congress Pkwy NW",
    "sg:city":"Athens",
    "sg:classifiers":[
        {
            "category":"Organizations",
            "subcategory":"Non-profit Organization",
            "type":"Services"
        },
        {
            "category":"Wholesale",
            "subcategory":"Non-durable Goods",
            "type":"Manufacturing & Wholesale Goods"
        }
    ],
    "sg:phone":"+1 423 744 9543",
    "sg:postcode":"37303",
    "sg:province":"TN",
    "sg:tags":[
        "fund",
        "counselor",
        "novelty",
        "raising",
        "gift"
    ],
    "wof:name":"United Service Associates",
    "wof:placetype":"venue"
},
  "geometry": {"coordinates":[-84.61363299999999,35.460216],"type":"Point"}
}