{
  "type": "Feature",
  "properties": {
    "iso:country":"US",
    "sg:address":"124 Lakeside Dr",
    "sg:city":"Butler",
    "sg:classifiers":[
        {
            "category":"Building & Trades",
            "subcategory":"Construction",
            "type":"Services"
        }
    ],
    "sg:phone":"+1 423 768 4491",
    "sg:postcode":"37640",
    "sg:province":"TN",
    "sg:tags":[
        "concrete",
        "contractor"
    ],
    "wof:name":"Appalachian Decorative Concret",
    "wof:placetype":"venue"
},
  "geometry": {"coordinates":[-82.056809,36.343183],"type":"Point"}
}