{
  "type": "Feature",
  "properties": {
    "iso:country":"US",
    "sg:address":"7139 Wassom Memorial Hwy",
    "sg:city":"Grandview",
    "sg:classifiers":[
        {
            "category":"Home & Garden",
            "subcategory":"Building Materials",
            "type":"Retail Goods"
        }
    ],
    "sg:phone":"+1 423 365 9542",
    "sg:postcode":"37337",
    "sg:province":"TN",
    "sg:website":"www.virgilreedstone.com",
    "wof:name":"Virgil Reed Stone Quarries",
    "wof:placetype":"venue"
},
  "geometry": {"coordinates":[-84.863188,35.763279],"type":"Point"}
}