{
  "type": "Feature",
  "properties": {
    "addr:full":"612 8th Ave S Nashville TN 37203",
    "addr:housenumber":"612",
    "addr:postcode":"37203",
    "addr:street":"8Th Ave S",
    "iso:country":"US",
    "sg:address":"612 8th Ave S",
    "sg:city":"Nashville",
    "sg:classifiers":[
        {
            "category":"Real Estate",
            "subcategory":"Real Estate Operator",
            "type":"Services"
        }
    ],
    "sg:phone":"+1 615 256 6617",
    "sg:postcode":"37203",
    "sg:province":"TN",
    "sg:tags":[
        "building",
        "nonresidential"
    ],
    "sg:website":"www.nashvilleantiques.com",
    "wof:name":"Downtown Antique Mall",
    "wof:placetype":"venue"
},
  "geometry": {"coordinates":[-86.779173,36.151393],"type":"Point"}
}