{
  "type": "Feature",
  "properties": {
    "iso:country":"US",
    "sg:address":"2018 Pointe Barton Dr",
    "sg:city":"Lebanon",
    "sg:classifiers":[
        {
            "category":"Banks & Credit Unions",
            "subcategory":"Bank",
            "type":"Services"
        }
    ],
    "sg:phone":"+1 615 453 2721",
    "sg:postcode":"37087",
    "sg:province":"TN",
    "sg:tags":[
        "institution",
        "business"
    ],
    "wof:name":"US Bank",
    "wof:placetype":"venue"
},
  "geometry": {"coordinates":[-86.372066,36.28168],"type":"Point"}
}