{
  "type": "Feature",
  "properties": {
    "addr:full":"1210 E Broadway St Lenoir City TN 37772",
    "addr:housenumber":"1210",
    "addr:postcode":"37772",
    "addr:street":"E Broadway St",
    "iso:country":"US",
    "sg:address":"1210 E Broadway St",
    "sg:city":"Lenoir City",
    "sg:classifiers":[
        {
            "category":"Food & Beverages",
            "subcategory":"Groceries & Convenience Stores",
            "type":"Retail Goods"
        }
    ],
    "sg:phone":"+1 865 986 2471",
    "sg:postcode":"37772",
    "sg:province":"TN",
    "sg:tags":[
        "grocer"
    ],
    "wof:name":"United Grocery Outlet Inc",
    "wof:placetype":"venue"
},
  "geometry": {"coordinates":[-84.25538400000001,35.798677],"type":"Point"}
}