{
  "type": "Feature",
  "properties": {
    "iso:country":"US",
    "sg:address":"918 Arctic Dr",
    "sg:city":"Lebanon",
    "sg:classifiers":[
        {
            "category":"Freight",
            "type":"Transportation"
        }
    ],
    "sg:phone":"+1 615 449 2653",
    "sg:postcode":"37090",
    "sg:province":"TN",
    "sg:tags":[
        "warehouse",
        "storage"
    ],
    "sg:website":"www.nrs-tn.com",
    "wof:name":"Nashville Refrigerated Svc Inc",
    "wof:placetype":"venue"
},
  "geometry": {"coordinates":[-86.270116,36.183576],"type":"Point"}
}