{
  "type": "Feature",
  "properties": {
    "addr:full":"9306 E Brainerd Rd Chattanooga TN 37421",
    "addr:housenumber":"9306",
    "addr:postcode":"37421",
    "addr:street":"E Brainerd Rd",
    "iso:country":"US",
    "sg:address":"9306 E Brainerd Rd",
    "sg:city":"Chattanooga",
    "sg:classifiers":[
        {
            "category":"Personal",
            "subcategory":"Beauty Salon",
            "type":"Services"
        }
    ],
    "sg:phone":"+1 423 894 7887",
    "sg:postcode":"37421",
    "sg:province":"TN",
    "sg:tags":[
        "shop"
    ],
    "wof:name":"Safari Cuts",
    "wof:placetype":"venue"
},
  "geometry": {"coordinates":[-85.115906,35.003197],"type":"Point"}
}