{
  "type": "Feature",
  "properties": {
    "iso:country":"US",
    "sg:address":"1827 NW Broad St",
    "sg:city":"Murfreesboro",
    "sg:classifiers":[
        {
            "category":"Autos & Motor Vehicles",
            "subcategory":"Automobile Sales",
            "type":"Retail Goods"
        }
    ],
    "sg:phone":"+1 615 754 2111",
    "sg:postcode":"37129",
    "sg:province":"TN",
    "sg:tags":[
        "car",
        "dealer"
    ],
    "wof:name":"College Motors II Inc",
    "wof:placetype":"venue"
},
  "geometry": {"coordinates":[-86.40494,35.85774],"type":"Point"}
}