{
  "type": "Feature",
  "properties": {
    "iso:country":"US",
    "sg:address":"44 N 2nd St",
    "sg:city":"Memphis",
    "sg:classifiers":[
        {
            "category":"Professional",
            "subcategory":"Lawyer & Legal Services",
            "type":"Services"
        }
    ],
    "sg:phone":"+1 901 526 6428",
    "sg:postcode":"38103",
    "sg:province":"TN",
    "wof:name":"Allen Gardner Atty",
    "wof:placetype":"venue"
},
  "geometry": {"coordinates":[-90.051,35.145996],"type":"Point"}
}