{
  "type": "Feature",
  "properties": {
    "addr:full":"426 US Hwy 51 S Covington TN 38019",
    "addr:housenumber":"426",
    "addr:postcode":"38019",
    "addr:street":"Us Hwy 51 S",
    "iso:country":"US",
    "sg:address":"426 US Hwy 51 S",
    "sg:city":"Covington",
    "sg:classifiers":[
        {
            "category":"Health Services",
            "subcategory":"Doctor",
            "type":"Services"
        }
    ],
    "sg:phone":"+1 901 476 3626",
    "sg:postcode":"38019",
    "sg:province":"TN",
    "sg:tags":[
        "dentist"
    ],
    "wof:name":"James Baddour III DDS",
    "wof:placetype":"venue"
},
  "geometry": {"coordinates":[-89.65108600000001,35.561913],"type":"Point"}
}