{
  "type": "Feature",
  "properties": {
    "iso:country":"US",
    "sg:address":"4306 Summerfield Dr",
    "sg:city":"Piney Flats",
    "sg:classifiers":[
        {
            "category":"Building & Trades",
            "subcategory":"Cleaning & Sanitation",
            "type":"Services"
        }
    ],
    "sg:phone":"+1 423 262 0185",
    "sg:postcode":"37686",
    "sg:province":"TN",
    "sg:tags":[
        "maintenance"
    ],
    "wof:name":"Pj Cleaning Service",
    "wof:placetype":"venue"
},
  "geometry": {"coordinates":[-82.360029,36.404444],"type":"Point"}
}