{
  "type": "Feature",
  "properties": {
    "iso:country":"US",
    "sg:address":"211 Holiday Dr",
    "sg:city":"Clarksville",
    "sg:classifiers":[
        {
            "category":"Manufacturing",
            "subcategory":"Apparel",
            "type":"Manufacturing & Wholesale Goods"
        }
    ],
    "sg:phone":"+1 931 553 8324",
    "sg:postcode":"37040",
    "sg:province":"TN",
    "sg:tags":[
        "sewing",
        "fabric",
        "glove",
        "mfg"
    ],
    "wof:name":"Fabric Outlet",
    "wof:placetype":"venue"
},
  "geometry": {"coordinates":[-87.28022900000001,36.594674],"type":"Point"}
}