{
  "type": "Feature",
  "properties": {
    "addr:full":"3472 Coleman Ave Memphis TN 38122",
    "addr:housenumber":"3472",
    "addr:postcode":"38122",
    "addr:street":"Coleman Ave",
    "iso:country":"US",
    "sg:address":"3472 Coleman Ave",
    "sg:city":"Memphis",
    "sg:classifiers":[
        {
            "category":"Professional",
            "subcategory":"Research",
            "type":"Services"
        },
        {
            "category":"Professional",
            "subcategory":"Management & Consulting",
            "type":"Services"
        }
    ],
    "sg:phone":"+1 901 324 0157",
    "sg:postcode":"38122",
    "sg:province":"TN",
    "sg:tags":[
        "environmental",
        "ecological",
        "business"
    ],
    "wof:name":"Environmental Training Svc",
    "wof:placetype":"venue"
},
  "geometry": {"coordinates":[-89.946405,35.155859],"type":"Point"}
}