{
  "type": "Feature",
  "properties": {
    "iso:country":"US",
    "sg:address":"971 N McLean Blvd",
    "sg:city":"Memphis",
    "sg:classifiers":[
        {
            "category":"Building & Trades",
            "subcategory":"Construction",
            "type":"Services"
        }
    ],
    "sg:phone":"+1 901 722 7867",
    "sg:postcode":"38107",
    "sg:province":"TN",
    "sg:tags":[
        "residential"
    ],
    "wof:name":"C & E Construction Co",
    "wof:placetype":"venue"
},
  "geometry": {"coordinates":[-89.995808,35.164692],"type":"Point"}
}