{
  "type": "Feature",
  "properties": {
    "iso:country":"US",
    "sg:address":"1296 Teddys Pl",
    "sg:city":"Mt Juliet",
    "sg:classifiers":[
        {
            "category":"Freight",
            "type":"Transportation"
        }
    ],
    "sg:phone":"+1 615 453 5587",
    "sg:postcode":"37122",
    "sg:province":"TN",
    "sg:tags":[
        "broker",
        "trucking"
    ],
    "wof:name":"D & D Transportation LLC",
    "wof:placetype":"venue"
},
  "geometry": {"coordinates":[-86.47308,36.23663],"type":"Point"}
}