{
  "type": "Feature",
  "properties": {
    "iso:country":"US",
    "sg:address":"2870 Holly Creek Rd",
    "sg:city":"Greeneville",
    "sg:classifiers":[
        {
            "category":"Organizations",
            "subcategory":"Membership Organization",
            "type":"Services"
        }
    ],
    "sg:phone":"+1 423 636 8171",
    "sg:postcode":"37745",
    "sg:province":"TN",
    "sg:website":"www.ruralresources.net",
    "wof:name":"Rural Resources",
    "wof:placetype":"venue"
},
  "geometry": {"coordinates":[-82.76319700000001,36.146686],"type":"Point"}
}