{
  "type": "Feature",
  "properties": {
    "addr:full":"6254 Hunters Point Pike Lebanon TN 37087",
    "addr:housenumber":"6254",
    "addr:postcode":"37087",
    "addr:street":"Hunters Point Pike",
    "iso:country":"US",
    "sg:address":"6254 Hunters Point Pike",
    "sg:city":"Lebanon",
    "sg:classifiers":[
        {
            "category":"Freight",
            "type":"Transportation"
        }
    ],
    "sg:phone":"+1 615 443 5033",
    "sg:postcode":"37087",
    "sg:province":"TN",
    "sg:tags":[
        "operator",
        "local",
        "trucking"
    ],
    "wof:name":"Maynard Brothers Trucking LLC",
    "wof:placetype":"venue"
},
  "geometry": {"coordinates":[-86.266246,36.291902],"type":"Point"}
}