{
  "type": "Feature",
  "properties": {
    "iso:country":"US",
    "sg:address":"201 N Broad St",
    "sg:city":"New Tazewell",
    "sg:classifiers":[
        {
            "category":"Shopping",
            "subcategory":"Pharmacy",
            "type":"Retail Goods"
        }
    ],
    "sg:phone":"+1 423 626 3151",
    "sg:postcode":"37825",
    "sg:province":"TN",
    "sg:website":"www.cunninghamdrugs.com",
    "wof:name":"Cunningham Drug",
    "wof:placetype":"venue"
},
  "geometry": {"coordinates":[-83.59903300000001,36.442922],"type":"Point"}
}