{
  "type": "Feature",
  "properties": {
    "iso:country":"US",
    "sg:address":"80 Powers Rd",
    "sg:city":"Decherd",
    "sg:classifiers":[
        {
            "category":"Manufacturing",
            "subcategory":"Tools & Machinery",
            "type":"Manufacturing & Wholesale Goods"
        }
    ],
    "sg:phone":"+1 931 967 5691",
    "sg:postcode":"37324",
    "sg:province":"TN",
    "sg:tags":[
        "machine",
        "shop",
        "general"
    ],
    "wof:name":"Powers Machine Shop",
    "wof:placetype":"venue"
},
  "geometry": {"coordinates":[-86.064502,35.227742],"type":"Point"}
}