{
  "type": "Feature",
  "properties": {
    "addr:full":"885 State Hwy 2 Greeneville TN 37771",
    "addr:housenumber":"885",
    "addr:postcode":"37771",
    "addr:street":"State Hwy 2",
    "iso:country":"US",
    "sg:address":"885 State Hwy 2",
    "sg:city":"Greeneville",
    "sg:classifiers":[
        {
            "category":"Freight",
            "type":"Transportation"
        }
    ],
    "sg:phone":"+1 423 470 0936",
    "sg:postcode":"37771",
    "sg:province":"TN",
    "sg:tags":[
        "delivery"
    ],
    "wof:name":"Delivery On Call",
    "wof:placetype":"venue"
},
  "geometry": {"coordinates":[-84.275367,35.785045],"type":"Point"}
}