{
  "type": "Feature",
  "properties": {
    "addr:full":"803 E Lane St Shelbyville TN 37160",
    "addr:housenumber":"803",
    "addr:postcode":"37160",
    "addr:street":"E Lane",
    "iso:country":"US",
    "sg:address":"803 E Lane St",
    "sg:city":"Shelbyville",
    "sg:classifiers":[
        {
            "category":"Freight",
            "type":"Transportation"
        }
    ],
    "sg:phone":"+1 931 224 2364",
    "sg:postcode":"37160",
    "sg:province":"TN",
    "sg:tags":[
        "warehouse",
        "merchandise"
    ],
    "wof:name":"Adds Storage",
    "wof:placetype":"venue"
},
  "geometry": {"coordinates":[-86.43916400000001,35.487188],"type":"Point"}
}