{
  "type": "Feature",
  "properties": {
    "iso:country":"US",
    "sg:address":"1 Blue Grass Dr",
    "sg:city":"Ashland City",
    "sg:classifiers":[
        {
            "category":"Manufacturing",
            "subcategory":"Glass & Minerals",
            "type":"Manufacturing & Wholesale Goods"
        }
    ],
    "sg:phone":"+1 615 792 4871",
    "sg:postcode":"37015",
    "sg:province":"TN",
    "sg:tags":[
        "concrete",
        "product",
        "mfg"
    ],
    "sg:website":"www.gateprecast.com",
    "wof:name":"Gate Bluegrass Precast Inc",
    "wof:placetype":"venue"
},
  "geometry": {"coordinates":[-87.01496299999999,36.228212],"type":"Point"}
}