{
  "type": "Feature",
  "properties": {
    "addr:full":"3500 Dodds Ave Chattanooga TN 37407",
    "addr:housenumber":"3500",
    "addr:postcode":"37407",
    "addr:street":"Dodds Ave",
    "iso:country":"US",
    "sg:address":"3500 Dodds Ave",
    "sg:city":"Chattanooga",
    "sg:classifiers":[
        {
            "category":"Shopping",
            "subcategory":"Used Merchandise",
            "type":"Retail Goods"
        }
    ],
    "sg:phone":"+1 423 242 0594",
    "sg:postcode":"37407",
    "sg:province":"TN",
    "wof:name":"Goodwill Family Stores 1",
    "wof:placetype":"venue"
},
  "geometry": {"coordinates":[-85.281868,35.000434],"type":"Point"}
}