{
  "type": "Feature",
  "properties": {
    "iso:country":"US",
    "sg:address":"206 Tyson Ave",
    "sg:city":"Paris",
    "sg:classifiers":[
        {
            "category":"Personal",
            "subcategory":"Beauty Salon",
            "type":"Services"
        }
    ],
    "sg:phone":"+1 731 642 1860",
    "sg:postcode":"38242",
    "sg:province":"TN",
    "sg:tags":[
        "shop"
    ],
    "wof:name":"Charisma Salon",
    "wof:placetype":"venue"
},
  "geometry": {"coordinates":[-88.31013799999999,36.300071],"type":"Point"}
}