{
  "type": "Feature",
  "properties": {
    "iso:country":"US",
    "sg:address":"239 S Lowe Ave",
    "sg:city":"Cookeville",
    "sg:classifiers":[
        {
            "category":"Personal",
            "subcategory":"Beauty Salon",
            "type":"Services"
        }
    ],
    "sg:phone":"+1 931 525 3673",
    "sg:postcode":"38501",
    "sg:province":"TN",
    "wof:name":"Art Of Hair",
    "wof:placetype":"venue"
},
  "geometry": {"coordinates":[-85.498903,36.157639],"type":"Point"}
}