{
  "type": "Feature",
  "properties": {
    "addr:full":"972 Chambliss Rd Memphis TN 38116",
    "addr:housenumber":"972",
    "addr:postcode":"38116",
    "addr:street":"Chambliss Rd",
    "iso:country":"US",
    "sg:address":"972 Chambliss Rd",
    "sg:city":"Memphis",
    "sg:classifiers":[
        {
            "category":"Building & Trades",
            "subcategory":"Plumbing",
            "type":"Services"
        }
    ],
    "sg:phone":"+1 901 344 7906",
    "sg:postcode":"38116",
    "sg:province":"TN",
    "sg:tags":[
        "conditioning",
        "air",
        "system",
        "contractor"
    ],
    "wof:name":"Nathaniel's Heating & Air",
    "wof:placetype":"venue"
},
  "geometry": {"coordinates":[-90.03035300000001,35.031128],"type":"Point"}
}