{
  "type": "Feature",
  "properties": {
    "iso:country":"US",
    "sg:address":"141 Donelson Pike",
    "sg:city":"Nashville",
    "sg:classifiers":[
        {
            "category":"Autos & Motor Vehicles",
            "subcategory":"Automobile Sales",
            "type":"Retail Goods"
        }
    ],
    "sg:phone":"+1 615 871 0971",
    "sg:postcode":"37214",
    "sg:province":"TN",
    "sg:tags":[
        "used"
    ],
    "wof:name":"Executive Auto Sales",
    "wof:placetype":"venue"
},
  "geometry": {"coordinates":[-86.66366499999999,36.165281],"type":"Point"}
}