{
  "type": "Feature",
  "properties": {
    "iso:country":"US",
    "sg:address":"701 Langford Ct",
    "sg:city":"Franklin",
    "sg:classifiers":[
        {
            "category":"Manufacturing",
            "subcategory":"Tools & Machinery",
            "type":"Manufacturing & Wholesale Goods"
        }
    ],
    "sg:phone":"+1 615 595 8299",
    "sg:postcode":"37067",
    "sg:province":"TN",
    "sg:tags":[
        "electric",
        "mfg"
    ],
    "wof:name":"Summit Manufacturing",
    "wof:placetype":"venue"
},
  "geometry": {"coordinates":[-86.81179,35.919478],"type":"Point"}
}