{
  "type": "Feature",
  "properties": {
    "iso:country":"US",
    "sg:address":"2516 Knoxville Hwy",
    "sg:city":"Wartburg",
    "sg:classifiers":[
        {
            "category":"Wholesale",
            "subcategory":"Electrical",
            "type":"Manufacturing & Wholesale Goods"
        }
    ],
    "sg:phone":"+1 423 346 2525",
    "sg:postcode":"37887",
    "sg:province":"TN",
    "sg:tags":[
        "equipment"
    ],
    "wof:name":"DLites",
    "wof:placetype":"venue"
},
  "geometry": {"coordinates":[-84.53564900000001,36.08927],"type":"Point"}
}