{
  "type": "Feature",
  "properties": {
    "iso:country":"US",
    "sg:address":"217 Old Hickory Blvd",
    "sg:city":"Nashville",
    "sg:classifiers":[
        {
            "category":"Cinema",
            "subcategory":"Movie Rental",
            "type":"Entertainment"
        }
    ],
    "sg:phone":"+1 615 662 0770",
    "sg:postcode":"37209",
    "sg:province":"TN",
    "sg:tags":[
        "video",
        "tape"
    ],
    "wof:name":"Xanadu",
    "wof:placetype":"venue"
},
  "geometry": {"coordinates":[-86.919529,36.078372],"type":"Point"}
}