{
  "type": "Feature",
  "properties": {
    "iso:country":"US",
    "sg:address":"117 E Winchester St",
    "sg:city":"Gallatin",
    "sg:classifiers":[
        {
            "category":"Social Services",
            "type":"Services"
        }
    ],
    "sg:phone":"+1 615 452 5868",
    "sg:postcode":"37148",
    "sg:province":"TN",
    "sg:tags":[
        "organization",
        "welfare"
    ],
    "wof:name":"Mid-Cumberland Human Resource",
    "wof:placetype":"venue"
},
  "geometry": {"coordinates":[-86.442894,36.385849],"type":"Point"}
}