{
  "type": "Feature",
  "properties": {
    "iso:country":"US",
    "sg:address":"1802 Turtle Hill Dr",
    "sg:city":"Cordova",
    "sg:classifiers":[
        {
            "category":"Farming",
            "subcategory":"Poultry Farm",
            "type":"Manufacturing & Wholesale Goods"
        }
    ],
    "sg:phone":"+1 901 756 7554",
    "sg:postcode":"38016",
    "sg:province":"TN",
    "sg:tags":[
        "poultry-wholesale"
    ],
    "wof:name":"Henderson Dan",
    "wof:placetype":"venue"
},
  "geometry": {"coordinates":[-89.760437,35.173967],"type":"Point"}
}