{
  "type": "Feature",
  "properties": {
    "iso:country":"US",
    "sg:address":"203 E Main St",
    "sg:city":"Mc Minnville",
    "sg:classifiers":[
        {
            "category":"Shopping",
            "subcategory":"Shoes",
            "type":"Retail Goods"
        }
    ],
    "sg:phone":"+1 931 473 0804",
    "sg:postcode":"37110",
    "sg:province":"TN",
    "wof:name":"Wayne's Shoes & Boots",
    "wof:placetype":"venue"
},
  "geometry": {"coordinates":[-85.771601,35.68119],"type":"Point"}
}