{
  "type": "Feature",
  "properties": {
    "iso:country":"US",
    "sg:address":"2617 Grandview Ave",
    "sg:city":"Nashville",
    "sg:classifiers":[
        {
            "category":"Professional",
            "subcategory":"Management & Consulting",
            "type":"Services"
        }
    ],
    "sg:phone":"+1 615 242 1074",
    "sg:postcode":"37211",
    "sg:province":"TN",
    "sg:tags":[
        "construction"
    ],
    "sg:website":"www.knestrick.com",
    "wof:name":"KMI",
    "wof:placetype":"venue"
},
  "geometry": {"coordinates":[-86.748503,36.114328],"type":"Point"}
}