{
  "type": "Feature",
  "properties": {
    "iso:country":"US",
    "sg:address":"241 Co Rd 342",
    "sg:city":"Sweetwater",
    "sg:classifiers":[
        {
            "category":"Farming",
            "subcategory":"Livestock Farm",
            "type":"Manufacturing & Wholesale Goods"
        }
    ],
    "sg:phone":"+1 423 337 4640",
    "sg:postcode":"37874",
    "sg:province":"TN",
    "sg:tags":[
        "beef",
        "feedlot",
        "cattle"
    ],
    "wof:name":"Hummingbyrd Farms",
    "wof:placetype":"venue"
},
  "geometry": {"coordinates":[-84.542435,35.578862],"type":"Point"}
}