{
  "type": "Feature",
  "properties": {
    "iso:country":"US",
    "sg:address":"6742 Owens Chapel Rd",
    "sg:city":"Springfield",
    "sg:classifiers":[
        {
            "category":"Organizations",
            "subcategory":"Religious Organization",
            "type":"Services"
        }
    ],
    "sg:phone":"+1 615 384 5601",
    "sg:postcode":"37172",
    "sg:province":"TN",
    "sg:tags":[
        "church"
    ],
    "wof:name":"Owens Chapel Methodist Church",
    "wof:placetype":"venue"
},
  "geometry": {"coordinates":[-86.764754,36.519706],"type":"Point"}
}