{
  "type": "Feature",
  "properties": {
    "iso:country":"US",
    "sg:address":"1206 State Hwy 46",
    "sg:city":"Indian Mound",
    "sg:classifiers":[
        {
            "category":"Retail",
            "subcategory":"Auto Repair",
            "type":"Services"
        }
    ],
    "sg:phone":"+1 931 232 2305",
    "sg:postcode":"37079",
    "sg:province":"TN",
    "sg:tags":[
        "general"
    ],
    "wof:name":"G & G Auto Care & Small Engine",
    "wof:placetype":"venue"
},
  "geometry": {"coordinates":[-87.69291200000001,36.502569],"type":"Point"}
}