{
  "type": "Feature",
  "properties": {
    "iso:country":"US",
    "sg:address":"1800 Savannah Hwy",
    "sg:city":"Waynesboro",
    "sg:classifiers":[
        {
            "category":"Real Estate",
            "subcategory":"Real Estate Agent",
            "type":"Services"
        }
    ],
    "sg:phone":"+1 931 722 5034",
    "sg:postcode":"38485",
    "sg:province":"TN",
    "sg:tags":[
        "investment"
    ],
    "wof:name":"Midsouth Land Investors Inc",
    "wof:placetype":"venue"
},
  "geometry": {"coordinates":[-87.90263899999999,35.306196],"type":"Point"}
}