{
  "type": "Feature",
  "properties": {
    "iso:country":"US",
    "sg:address":"1419 Cedar Run Dr",
    "sg:city":"Cordova",
    "sg:classifiers":[
        {
            "category":"Professional",
            "subcategory":"Management & Consulting",
            "type":"Services"
        }
    ],
    "sg:phone":"+1 901 751 0932",
    "sg:postcode":"38016",
    "sg:province":"TN",
    "wof:name":"Robert Campbell",
    "wof:placetype":"venue"
},
  "geometry": {"coordinates":[-89.767566,35.163808],"type":"Point"}
}