{
  "type": "Feature",
  "properties": {
    "addr:full":"1017 Jefferson Ave Gallatin TN 37066",
    "addr:housenumber":"1017",
    "addr:postcode":"37066",
    "addr:street":"Jefferson Ave",
    "iso:country":"US",
    "sg:address":"1017 Jefferson Ave",
    "sg:city":"Gallatin",
    "sg:classifiers":[
        {
            "category":"Professional",
            "type":"Services"
        }
    ],
    "sg:phone":"+1 615 230 0330",
    "sg:postcode":"37066",
    "sg:province":"TN",
    "sg:tags":[
        "establishment"
    ],
    "wof:name":"Jeff Ellis & Assoc",
    "wof:placetype":"venue"
},
  "geometry": {"coordinates":[-86.470315,36.3751],"type":"Point"}
}