{
  "type": "Feature",
  "properties": {
    "iso:country":"US",
    "sg:address":"6145 Shallowford Rd",
    "sg:city":"Chattanooga",
    "sg:classifiers":[
        {
            "category":"Health Services",
            "subcategory":"Doctor",
            "type":"Services"
        }
    ],
    "sg:phone":"+1 423 893 6890",
    "sg:postcode":"37421",
    "sg:province":"TN",
    "sg:tags":[
        "physician",
        "surgeon"
    ],
    "wof:name":"Brackett Reumatology",
    "wof:placetype":"venue"
},
  "geometry": {"coordinates":[-85.18243200000001,35.053265],"type":"Point"}
}