{
  "type": "Feature",
  "properties": {
    "addr:full":"6077 Primacy Pkwy Memphis TN 38119",
    "addr:housenumber":"6077",
    "addr:postcode":"38119",
    "addr:street":"Primacy Pkwy",
    "iso:country":"US",
    "sg:address":"6077 Primacy Pkwy",
    "sg:city":"Memphis",
    "sg:classifiers":[
        {
            "category":"Airline",
            "type":"Transportation"
        }
    ],
    "sg:phone":"+1 901 434 6188",
    "sg:postcode":"38119",
    "sg:province":"TN",
    "sg:tags":[
        "courier",
        "air"
    ],
    "wof:name":"Fedex",
    "wof:placetype":"venue"
},
  "geometry": {"coordinates":[-89.861119,35.095083],"type":"Point"}
}