{
  "type": "Feature",
  "properties": {
    "iso:country":"US",
    "sg:address":"1012 Douglas Ave",
    "sg:city":"Nashville",
    "sg:classifiers":[
        {
            "category":"Retail",
            "subcategory":"Repair Shop",
            "type":"Services"
        }
    ],
    "sg:phone":"+1 615 438 8317",
    "sg:postcode":"37206",
    "sg:province":"TN",
    "sg:tags":[
        "leather",
        "good"
    ],
    "wof:name":"Leatherwerks By Chris",
    "wof:placetype":"venue"
},
  "geometry": {"coordinates":[-86.74852300000001,36.192981],"type":"Point"}
}