{
  "type": "Feature",
  "properties": {
    "addr:full":"2000 Shoppers Ln Knoxville TN 37921",
    "addr:housenumber":"2000",
    "addr:postcode":"37921",
    "addr:street":"Shoppers Ln",
    "iso:country":"US",
    "sg:address":"2000 Shoppers Ln",
    "sg:city":"Knoxville",
    "sg:classifiers":[
        {
            "category":"Wholesale",
            "subcategory":"Machinery & Supplies",
            "type":"Manufacturing & Wholesale Goods"
        }
    ],
    "sg:phone":"+1 865 524 1206",
    "sg:postcode":"37921",
    "sg:province":"TN",
    "sg:tags":[
        "equipment",
        "industrial"
    ],
    "sg:website":"www.hagemeyerna.com",
    "wof:name":"Hagemeyer",
    "wof:placetype":"venue"
},
  "geometry": {"coordinates":[-83.98593700000001,35.971116],"type":"Point"}
}