{
  "type": "Feature",
  "properties": {
    "addr:full":"3012 Hwy 31 W White House TN 37188",
    "addr:housenumber":"3012",
    "addr:postcode":"37188",
    "addr:street":"Hwy 31 W",
    "iso:country":"US",
    "sg:address":"3012 Hwy 31 W",
    "sg:city":"White House",
    "sg:classifiers":[
        {
            "category":"Shopping",
            "subcategory":"Discount & Variety Stores",
            "type":"Retail Goods"
        }
    ],
    "sg:phone":"+1 615 672 4941",
    "sg:postcode":"37188",
    "sg:province":"TN",
    "wof:name":"Fred's Store",
    "wof:placetype":"venue"
},
  "geometry": {"coordinates":[-86.654084,36.468157],"type":"Point"}
}