{
  "type": "Feature",
  "properties": {
    "iso:country":"US",
    "sg:address":"919 W Central Ave",
    "sg:city":"La Follette",
    "sg:classifiers":[
        {
            "category":"Health Services",
            "subcategory":"Hospital",
            "type":"Services"
        }
    ],
    "sg:phone":"+1 423 907 1198",
    "sg:postcode":"37766",
    "sg:province":"TN",
    "sg:tags":[
        "specialty"
    ],
    "wof:name":"Knoxville Cancer Center",
    "wof:placetype":"venue"
},
  "geometry": {"coordinates":[-84.13275,36.37254],"type":"Point"}
}