{
  "type": "Feature",
  "properties": {
    "iso:country":"US",
    "sg:address":"2282 Park Ave",
    "sg:city":"Memphis",
    "sg:classifiers":[
        {
            "category":"Shopping",
            "type":"Retail Goods"
        }
    ],
    "sg:phone":"+1 901 323 7450",
    "sg:postcode":"38114",
    "sg:province":"TN",
    "sg:tags":[
        "cosmetic",
        "perfume"
    ],
    "wof:name":"Super Beauty Supply",
    "wof:placetype":"venue"
},
  "geometry": {"coordinates":[-89.98729400000001,35.108646],"type":"Point"}
}