{
  "type": "Feature",
  "properties": {
    "iso:country":"US",
    "sg:address":"8676 Eagle View Dr",
    "sg:city":"Cordova",
    "sg:classifiers":[
        {
            "category":"Food & Beverages",
            "subcategory":"Liquor & Beverages",
            "type":"Retail Goods"
        }
    ],
    "sg:phone":"+1 901 309 6577",
    "sg:postcode":"38018",
    "sg:province":"TN",
    "sg:tags":[
        "alcoholic"
    ],
    "wof:name":"Cordova Beverage & Tobacco",
    "wof:placetype":"venue"
},
  "geometry": {"coordinates":[-89.773055,35.143729],"type":"Point"}
}