{
  "type": "Feature",
  "properties": {
    "iso:country":"US",
    "sg:address":"609 Swansons Ridge Rd",
    "sg:city":"Chattanooga",
    "sg:classifiers":[
        {
            "category":"Home & Garden",
            "subcategory":"Building Materials",
            "type":"Retail Goods"
        }
    ],
    "sg:phone":"+1 423 954 1406",
    "sg:postcode":"37421",
    "sg:province":"TN",
    "wof:name":"De Verre",
    "wof:placetype":"venue"
},
  "geometry": {"coordinates":[-85.134044,34.992058],"type":"Point"}
}