{
  "type": "Feature",
  "properties": {
    "iso:country":"US",
    "sg:address":"291 Meadowgrove Ln",
    "sg:city":"Memphis",
    "sg:classifiers":[
        {
            "category":"Building & Trades",
            "subcategory":"Construction",
            "type":"Services"
        }
    ],
    "sg:phone":"+1 901 683 9207",
    "sg:postcode":"38120",
    "sg:province":"TN",
    "sg:tags":[
        "house",
        "real estate"
    ],
    "wof:name":"Erb Guy Co Realtors",
    "wof:placetype":"venue"
},
  "geometry": {"coordinates":[-89.856587,35.123229],"type":"Point"}
}