{
  "type": "Feature",
  "properties": {
    "iso:country":"US",
    "sg:address":"188 Houston Ave",
    "sg:city":"Selmer",
    "sg:classifiers":[
        {
            "category":"Professional",
            "subcategory":"Lawyer & Legal Services",
            "type":"Services"
        }
    ],
    "sg:phone":"+1 731 645 7222",
    "sg:postcode":"38375",
    "sg:province":"TN",
    "sg:tags":[
        "attorney"
    ],
    "wof:name":"Van D Mc Mahan",
    "wof:placetype":"venue"
},
  "geometry": {"coordinates":[-88.594004,35.170137],"type":"Point"}
}