{
  "type": "Feature",
  "properties": {
    "addr:full":"1670 Old Bonair Rd Sparta TN 38583",
    "addr:housenumber":"1670",
    "addr:postcode":"38583",
    "addr:street":"Old Bonair Rd",
    "iso:country":"US",
    "sg:address":"1670 Old Bonair Rd",
    "sg:city":"Sparta",
    "sg:classifiers":[
        {
            "category":"Real Estate",
            "subcategory":"Developer",
            "type":"Services"
        }
    ],
    "sg:phone":"+1 931 738 5860",
    "sg:postcode":"38583",
    "sg:province":"TN",
    "sg:tags":[
        "cemetery"
    ],
    "wof:name":"Old Bon Air Cemetery",
    "wof:placetype":"venue"
},
  "geometry": {"coordinates":[-85.379611,35.914422],"type":"Point"}
}