{
  "type": "Feature",
  "properties": {
    "iso:country":"US",
    "sg:address":"1406 Kirby Rd",
    "sg:city":"Knoxville",
    "sg:classifiers":[
        {
            "category":"Professional",
            "subcategory":"Business Services",
            "type":"Services"
        }
    ],
    "sg:phone":"+1 865 588 6781",
    "sg:postcode":"37909",
    "sg:province":"TN",
    "sg:tags":[
        "motion",
        "production"
    ],
    "wof:name":"Nightsong Recording Studios",
    "wof:placetype":"venue"
},
  "geometry": {"coordinates":[-83.998026,35.946086],"type":"Point"}
}