{
  "type": "Feature",
  "properties": {
    "iso:country":"US",
    "sg:address":"2861 Ridgeville Rd",
    "sg:city":"Tullahoma",
    "sg:classifiers":[
        {
            "category":"Organizations",
            "subcategory":"Religious Organization",
            "type":"Services"
        }
    ],
    "sg:phone":"+1 931 455 1012",
    "sg:postcode":"37388",
    "sg:province":"TN",
    "sg:tags":[
        "church"
    ],
    "wof:name":"Hoover's Grove Church-Christ",
    "wof:placetype":"venue"
},
  "geometry": {"coordinates":[-86.291676,35.305693],"type":"Point"}
}