{
  "type": "Feature",
  "properties": {
    "iso:country":"US",
    "sg:address":"405 E University St",
    "sg:city":"Livingston",
    "sg:classifiers":[
        {
            "category":"Professional",
            "type":"Services"
        }
    ],
    "sg:phone":"+1 931 823 9841",
    "sg:postcode":"38570",
    "sg:province":"TN",
    "sg:tags":[
        "establishment"
    ],
    "wof:name":"Progressive Sentencing Inc",
    "wof:placetype":"venue"
},
  "geometry": {"coordinates":[-85.318668,36.386351],"type":"Point"}
}