{
  "type": "Feature",
  "properties": {
    "addr:full":"2310 Miles Rd Martin TN 38237",
    "addr:housenumber":"2310",
    "addr:postcode":"38237",
    "addr:street":"Miles Rd",
    "iso:country":"US",
    "sg:address":"2310 Miles Rd",
    "sg:city":"Martin",
    "sg:classifiers":[
        {
            "category":"Organizations",
            "subcategory":"Religious Organization",
            "type":"Services"
        }
    ],
    "sg:phone":"+1 731 587 5686",
    "sg:postcode":"38237",
    "sg:province":"TN",
    "wof:name":"Gods Chapel Church Inc",
    "wof:placetype":"venue"
},
  "geometry": {"coordinates":[-88.797624,36.294548],"type":"Point"}
}