{
  "type": "Feature",
  "properties": {
    "iso:country":"US",
    "sg:address":"378 Curve Woodville Rd",
    "sg:city":"Ripley",
    "sg:classifiers":[
        {
            "category":"Building & Trades",
            "subcategory":"Plumbing",
            "type":"Services"
        }
    ],
    "sg:phone":"+1 731 635 0040",
    "sg:postcode":"38037",
    "sg:province":"TN",
    "sg:tags":[
        "plumbing",
        "contractor"
    ],
    "wof:name":"After Hours Plumbing",
    "wof:placetype":"venue"
},
  "geometry": {"coordinates":[-89.454215,35.80147],"type":"Point"}
}