{
  "type": "Feature",
  "properties": {
    "iso:country":"US",
    "sg:address":"817 Vann Dr",
    "sg:city":"Jackson",
    "sg:classifiers":[
        {
            "category":"Retail",
            "subcategory":"Auto Repair",
            "type":"Services"
        }
    ],
    "sg:phone":"+1 731 664 9391",
    "sg:postcode":"38305",
    "sg:province":"TN",
    "sg:tags":[
        "repairing",
        "automobile"
    ],
    "wof:name":"Gateway Tire Svc Ctr",
    "wof:placetype":"venue"
},
  "geometry": {"coordinates":[-88.85071499999999,35.669836],"type":"Point"}
}