{
  "type": "Feature",
  "properties": {
    "iso:country":"US",
    "sg:address":"402 7th Ave",
    "sg:city":"Fayetteville",
    "sg:classifiers":[
        {
            "category":"Restaurant",
            "type":"Food & Drink"
        }
    ],
    "sg:phone":"+1 931 438 2737",
    "sg:postcode":"37334",
    "sg:province":"TN",
    "sg:tags":[
        "eating"
    ],
    "wof:name":"Lunch Box",
    "wof:placetype":"venue"
},
  "geometry": {"coordinates":[-86.587771,35.157497],"type":"Point"}
}