{
  "type": "Feature",
  "properties": {
    "iso:country":"US",
    "sg:address":"395 Brazzle Rd",
    "sg:city":"Waverly",
    "sg:classifiers":[
        {
            "category":"Building & Trades",
            "subcategory":"Construction",
            "type":"Services"
        }
    ],
    "sg:phone":"+1 931 296 8071",
    "sg:postcode":"37185",
    "sg:province":"TN",
    "sg:tags":[
        "excavating",
        "contractor"
    ],
    "wof:name":"Mallard Excavating",
    "wof:placetype":"venue"
},
  "geometry": {"coordinates":[-87.797426,36.101235],"type":"Point"}
}