{
  "type": "Feature",
  "properties": {
    "iso:country":"US",
    "sg:address":"440 Bell Rd",
    "sg:city":"Watertown",
    "sg:classifiers":[
        {
            "category":"Wholesale",
            "subcategory":"Vending Machines",
            "type":"Manufacturing & Wholesale Goods"
        }
    ],
    "sg:phone":"+1 615 237 9934",
    "sg:postcode":"37184",
    "sg:province":"TN",
    "sg:tags":[
        "operator"
    ],
    "wof:name":"J & B Vending",
    "wof:placetype":"venue"
},
  "geometry": {"coordinates":[-86.126716,36.168057],"type":"Point"}
}