{
  "type": "Feature",
  "properties": {
    "iso:country":"US",
    "sg:address":"1546 Old Chisholm Trl",
    "sg:city":"Dandridge",
    "sg:classifiers":[
        {
            "category":"Professional",
            "subcategory":"Management & Consulting",
            "type":"Services"
        }
    ],
    "sg:phone":"+1 865 397 3186",
    "sg:postcode":"37725",
    "sg:province":"TN",
    "wof:name":"Lueven Marketing",
    "wof:placetype":"venue"
},
  "geometry": {"coordinates":[-83.348758,35.993915],"type":"Point"}
}