{
  "type": "Feature",
  "properties": {
    "iso:country":"US",
    "sg:address":"7210 Nashville Hwy",
    "sg:city":"Baxter",
    "sg:classifiers":[
        {
            "category":"Wholesale",
            "subcategory":"Construction Materials",
            "type":"Manufacturing & Wholesale Goods"
        }
    ],
    "sg:phone":"+1 931 858 5604",
    "sg:postcode":"38544",
    "sg:province":"TN",
    "sg:tags":[
        "concrete",
        "product"
    ],
    "wof:name":"Williams Concrete Craft",
    "wof:placetype":"venue"
},
  "geometry": {"coordinates":[-85.642878,36.169384],"type":"Point"}
}