{
  "type": "Feature",
  "properties": {
    "iso:country":"US",
    "sg:address":"205 Oak Grove Dr",
    "sg:city":"Nashville",
    "sg:classifiers":[
        {
            "category":"Professional",
            "type":"Services"
        }
    ],
    "sg:phone":"+1 615 361 7244",
    "sg:postcode":"37217",
    "sg:province":"TN",
    "wof:name":"Stephen Bergen",
    "wof:placetype":"venue"
},
  "geometry": {"coordinates":[-86.707127,36.138276],"type":"Point"}
}