{
  "type": "Feature",
  "properties": {
    "iso:country":"US",
    "sg:address":"310 N Fuller St",
    "sg:city":"Dresden",
    "sg:classifiers":[
        {
            "category":"Organizations",
            "subcategory":"Religious Organization",
            "type":"Services"
        }
    ],
    "sg:phone":"+1 731 364 2064",
    "sg:postcode":"38225",
    "sg:province":"TN",
    "sg:tags":[
        "church"
    ],
    "wof:name":"Fuller Street Baptist Church",
    "wof:placetype":"venue"
},
  "geometry": {"coordinates":[-88.70980299999999,36.293478],"type":"Point"}
}