{
  "type": "Feature",
  "properties": {
    "addr:full":"6051 Dayton Blvd Chattanooga TN 37415",
    "addr:housenumber":"6051",
    "addr:postcode":"37415",
    "addr:street":"Dayton Blvd",
    "iso:country":"US",
    "sg:address":"6051 Dayton Blvd",
    "sg:city":"Chattanooga",
    "sg:classifiers":[
        {
            "category":"Freight",
            "type":"Transportation"
        }
    ],
    "sg:phone":"+1 423 870 4861",
    "sg:postcode":"37415",
    "sg:province":"TN",
    "sg:tags":[
        "commercial",
        "storage"
    ],
    "wof:name":"Dayton Blvd Self Storage",
    "wof:placetype":"venue"
},
  "geometry": {"coordinates":[-85.260559,35.16605],"type":"Point"}
}