{
  "type": "Feature",
  "properties": {
    "addr:full":"4230 Argonne St Memphis TN 38127",
    "addr:housenumber":"4230",
    "addr:postcode":"38127",
    "addr:street":"Argonne St",
    "iso:country":"US",
    "sg:address":"4230 Argonne St",
    "sg:city":"Memphis",
    "sg:classifiers":[
        {
            "category":"Real Estate",
            "subcategory":"Real Estate Agent",
            "type":"Services"
        }
    ],
    "sg:phone":"+1 901 358 6564",
    "sg:postcode":"38127",
    "sg:province":"TN",
    "wof:name":"Lavadas Est Sales",
    "wof:placetype":"venue"
},
  "geometry": {"coordinates":[-89.996573,35.241558],"type":"Point"}
}