{
  "type": "Feature",
  "properties": {
    "iso:country":"US",
    "sg:address":"105 Glen Oak Blvd",
    "sg:city":"Hendersonville",
    "sg:classifiers":[
        {
            "category":"Health Services",
            "subcategory":"Doctor",
            "type":"Services"
        }
    ],
    "sg:phone":"+1 615 822 6701",
    "sg:postcode":"37075",
    "sg:province":"TN",
    "sg:tags":[
        "physician",
        "medical",
        "surgeon"
    ],
    "wof:name":"Carmack James H Jr MD",
    "wof:placetype":"venue"
},
  "geometry": {"coordinates":[-86.6152,36.325579],"type":"Point"}
}