{
  "type": "Feature",
  "properties": {
    "iso:country":"US",
    "sg:address":"1201 Westbury Rd",
    "sg:city":"Knoxville",
    "sg:classifiers":[
        {
            "category":"Professional",
            "type":"Services"
        }
    ],
    "sg:phone":"+1 865 531 2808",
    "sg:postcode":"37922",
    "sg:province":"TN",
    "wof:name":"Skip & Teri Bibb",
    "wof:placetype":"venue"
},
  "geometry": {"coordinates":[-84.043283,35.891134],"type":"Point"}
}