{
  "type": "Feature",
  "properties": {
    "iso:country":"US",
    "sg:address":"2201 McGavock Pike",
    "sg:city":"Nashville",
    "sg:classifiers":[
        {
            "category":"Health Services",
            "subcategory":"Clinic",
            "type":"Services"
        }
    ],
    "sg:phone":"+1 615 228 3448",
    "sg:postcode":"37216",
    "sg:province":"TN",
    "sg:tags":[
        "specialty",
        "outpatient"
    ],
    "wof:name":"Cumberland Rehabilitation Cons",
    "wof:placetype":"venue"
},
  "geometry": {"coordinates":[-86.711471,36.213157],"type":"Point"}
}