{
  "type": "Feature",
  "properties": {
    "addr:full":"574 Beaver Creek Rd Bluff City TN 37618",
    "addr:housenumber":"574",
    "addr:postcode":"37618",
    "addr:street":"Beaver Creek Rd",
    "iso:country":"US",
    "sg:address":"574 Beaver Creek Rd",
    "sg:city":"Bluff City",
    "sg:classifiers":[
        {
            "category":"Government",
            "subcategory":"Office",
            "type":"Public Place"
        }
    ],
    "sg:phone":"+1 423 989 5574",
    "sg:postcode":"37618",
    "sg:province":"TN",
    "sg:tags":[
        "village"
    ],
    "sg:website":"www.veoliawaterna.com",
    "wof:name":"Bristol Compost Production",
    "wof:placetype":"venue"
},
  "geometry": {"coordinates":[-82.289967,36.500392],"type":"Point"}
}