{
  "type": "Feature",
  "properties": {
    "iso:country":"US",
    "sg:address":"728 Stone Crest Cir",
    "sg:city":"Chattanooga",
    "sg:classifiers":[
        {
            "category":"Building & Trades",
            "subcategory":"Landscaping Services",
            "type":"Services"
        }
    ],
    "sg:phone":"+1 423 892 5899",
    "sg:postcode":"37421",
    "sg:province":"TN",
    "sg:tags":[
        "lawn",
        "garden"
    ],
    "wof:name":"Harvey Grounds",
    "wof:placetype":"venue"
},
  "geometry": {"coordinates":[-85.127748,34.992119],"type":"Point"}
}