{
  "type": "Feature",
  "properties": {
    "iso:country":"US",
    "sg:address":"215 Bragg Cir",
    "sg:city":"Tullahoma",
    "sg:classifiers":[
        {
            "category":"Building & Trades",
            "subcategory":"Construction",
            "type":"Services"
        }
    ],
    "sg:phone":"+1 931 393 3587",
    "sg:postcode":"37388",
    "sg:province":"TN",
    "sg:tags":[
        "hanging",
        "contractor"
    ],
    "wof:name":"Newtons Painting",
    "wof:placetype":"venue"
},
  "geometry": {"coordinates":[-86.234238,35.363229],"type":"Point"}
}