{
  "type": "Feature",
  "properties": {
    "addr:full":"2138 Gallatin Pike N Madison TN 37115",
    "addr:housenumber":"2138",
    "addr:postcode":"37115",
    "addr:street":"Gallatin Pike N",
    "iso:country":"US",
    "sg:address":"2138 Gallatin Pike N",
    "sg:city":"Madison",
    "sg:classifiers":[
        {
            "category":"Personal",
            "subcategory":"Beauty Salon",
            "type":"Services"
        }
    ],
    "sg:phone":"+1 615 859 6164",
    "sg:postcode":"37115",
    "sg:province":"TN",
    "sg:tags":[
        "shop"
    ],
    "wof:name":"5th Ave Salon",
    "wof:placetype":"venue"
},
  "geometry": {"coordinates":[-86.689139,36.304481],"type":"Point"}
}