{
  "type": "Feature",
  "properties": {
    "iso:country":"US",
    "sg:address":"1118 S 1st St",
    "sg:city":"Union City",
    "sg:classifiers":[
        {
            "category":"Wholesale",
            "subcategory":"Fruits & Vegetables",
            "type":"Manufacturing & Wholesale Goods"
        }
    ],
    "sg:phone":"+1 731 884 0002",
    "sg:postcode":"38261",
    "sg:province":"TN",
    "wof:name":"Kendalls Fruit Market",
    "wof:placetype":"venue"
},
  "geometry": {"coordinates":[-89.05846099999999,36.41],"type":"Point"}
}