{
  "type": "Feature",
  "properties": {
    "addr:full":"4414 W Stone Dr Kingsport TN 37660",
    "addr:housenumber":"4414",
    "addr:postcode":"37660",
    "addr:street":"W Stone Dr",
    "iso:country":"US",
    "sg:address":"4414 W Stone Dr",
    "sg:city":"Kingsport",
    "sg:classifiers":[
        {
            "category":"Restaurant",
            "type":"Food & Drink"
        }
    ],
    "sg:menulink":"http://www.allmenus.com/tn/mount-carmel/73161-pizza-hut/menu/",
    "sg:phone":"+1 423 245 6659",
    "sg:postcode":"37660",
    "sg:province":"TN",
    "sg:tags":[
        "american",
        "pizza"
    ],
    "wof:name":"Pizza Hut",
    "wof:placetype":"venue"
},
  "geometry": {"coordinates":[-82.62733,36.552686],"type":"Point"}
}