{
  "type": "Feature",
  "properties": {
    "iso:country":"US",
    "sg:address":"130 Frazier St",
    "sg:city":"Pikeville",
    "sg:classifiers":[
        {
            "category":"Government",
            "subcategory":"Police Station",
            "type":"Public Place"
        }
    ],
    "sg:phone":"+1 423 447 2197",
    "sg:postcode":"37367",
    "sg:province":"TN",
    "sg:tags":[
        "sheriff"
    ],
    "wof:name":"Bledsoe Sheriff Department",
    "wof:placetype":"venue"
},
  "geometry": {"coordinates":[-85.18824600000001,35.604752],"type":"Point"}
}