{
  "type": "Feature",
  "properties": {
    "addr:full":"745 E Main St Chattanooga TN 37408",
    "addr:housenumber":"745",
    "addr:postcode":"37408",
    "addr:street":"E Main St",
    "iso:country":"US",
    "sg:address":"745 E Main St",
    "sg:city":"Chattanooga",
    "sg:classifiers":[
        {
            "category":"Professional",
            "subcategory":"Computer Services",
            "type":"Services"
        }
    ],
    "sg:phone":"+1 423 267 8867",
    "sg:postcode":"37408",
    "sg:province":"TN",
    "sg:tags":[
        "development",
        "software",
        "internet"
    ],
    "wof:name":"Chattanooga On Line",
    "wof:placetype":"venue"
},
  "geometry": {"coordinates":[-85.297504,35.032481],"type":"Point"}
}