{
  "type": "Feature",
  "properties": {
    "addr:full":"317 Pullen Ave Nashville TN 37207",
    "addr:housenumber":"317",
    "addr:postcode":"37207",
    "addr:street":"Pullen Ave",
    "iso:country":"US",
    "sg:address":"317 Pullen Ave",
    "sg:city":"Nashville",
    "sg:classifiers":[
        {
            "category":"Professional",
            "type":"Services"
        },
        {
            "category":"Shopping",
            "subcategory":"Musical Instruments",
            "type":"Retail Goods"
        }
    ],
    "sg:phone":"+1 615 650 8615",
    "sg:postcode":"37207",
    "sg:province":"TN",
    "sg:tags":[
        "music",
        "dealer"
    ],
    "wof:name":"Gathering Stones Music",
    "wof:placetype":"venue"
},
  "geometry": {"coordinates":[-86.763413,36.20037],"type":"Point"}
}