{
  "type": "Feature",
  "properties": {
    "iso:country":"US",
    "sg:address":"101 Spring Creek Trl",
    "sg:city":"Hendersonville",
    "sg:classifiers":[
        {
            "category":"Banks & Credit Unions",
            "subcategory":"Bank",
            "type":"Services"
        }
    ],
    "sg:phone":"+1 615 338 0565",
    "sg:postcode":"37075",
    "sg:province":"TN",
    "wof:name":"American Security Bank & Trust",
    "wof:placetype":"venue"
},
  "geometry": {"coordinates":[-86.553815,36.327],"type":"Point"}
}