{
  "type": "Feature",
  "properties": {
    "iso:country":"US",
    "sg:address":"3532 McCains Ln",
    "sg:city":"Columbia",
    "sg:classifiers":[
        {
            "category":"Organizations",
            "subcategory":"Religious Organization",
            "type":"Services"
        }
    ],
    "sg:phone":"+1 931 540 0160",
    "sg:postcode":"38401",
    "sg:province":"TN",
    "sg:tags":[
        "church"
    ],
    "wof:name":"Mc Cains Cumberland",
    "wof:placetype":"venue"
},
  "geometry": {"coordinates":[-87.050321,35.519144],"type":"Point"}
}