{
  "type": "Feature",
  "properties": {
    "addr:full":"240 Carriage House Dr Jackson TN 38305",
    "addr:housenumber":"240",
    "addr:postcode":"38305",
    "addr:street":"Carriage House Dr",
    "iso:country":"US",
    "sg:address":"240 Carriage House Dr",
    "sg:city":"Jackson",
    "sg:classifiers":[
        {
            "category":"Insurance",
            "subcategory":"Insurance Agent",
            "type":"Services"
        }
    ],
    "sg:phone":"+1 731 668 4636",
    "sg:postcode":"38305",
    "sg:province":"TN",
    "sg:tags":[
        "agency",
        "general"
    ],
    "wof:name":"Mike Freeman Insurance Agency",
    "wof:placetype":"venue"
},
  "geometry": {"coordinates":[-88.838359,35.668221],"type":"Point"}
}