{
  "type": "Feature",
  "properties": {
    "iso:country":"US",
    "sg:address":"1007 E Reelfoot Ave",
    "sg:city":"Union City",
    "sg:classifiers":[
        {
            "category":"Health Services",
            "subcategory":"Doctor",
            "type":"Services"
        }
    ],
    "sg:phone":"+1 731 885 2277",
    "sg:postcode":"38261",
    "sg:province":"TN",
    "sg:tags":[
        "dentist"
    ],
    "wof:name":"Jerry L Sullivan DDS",
    "wof:placetype":"venue"
},
  "geometry": {"coordinates":[-89.04920300000001,36.41375],"type":"Point"}
}