{
  "type": "Feature",
  "properties": {
    "addr:full":"312 Preston Ave Lewisburg TN 37091",
    "addr:housenumber":"312",
    "addr:postcode":"37091",
    "addr:street":"Preston Ave",
    "iso:country":"US",
    "sg:address":"312 Preston Ave",
    "sg:city":"Lewisburg",
    "sg:classifiers":[
        {
            "category":"Professional",
            "subcategory":"Detective & Security Services",
            "type":"Services"
        }
    ],
    "sg:phone":"+1 931 270 1216",
    "sg:postcode":"37091",
    "sg:province":"TN",
    "sg:tags":[
        "car"
    ],
    "wof:name":"Service On Guard Security",
    "wof:placetype":"venue"
},
  "geometry": {"coordinates":[-86.808488,35.454421],"type":"Point"}
}