{
  "type": "Feature",
  "properties": {
    "addr:full":"1192 Lamar Ave Memphis TN 38104",
    "addr:housenumber":"1192",
    "addr:postcode":"38104",
    "addr:street":"Lamar Ave",
    "iso:country":"US",
    "sg:address":"1192 Lamar Ave",
    "sg:city":"Memphis",
    "sg:classifiers":[
        {
            "category":"Professional",
            "subcategory":"Employment Agencies",
            "type":"Services"
        }
    ],
    "sg:phone":"+1 901 272 6961",
    "sg:postcode":"38104",
    "sg:province":"TN",
    "sg:tags":[
        "opportunity",
        "contractor"
    ],
    "wof:name":"Command Center Inc",
    "wof:placetype":"venue"
},
  "geometry": {"coordinates":[-90.02231999999999,35.129384],"type":"Point"}
}