{
  "type": "Feature",
  "properties": {
    "addr:full":"2002 Richard Jones Rd Nashville TN 37215",
    "addr:housenumber":"2002",
    "addr:postcode":"37215",
    "addr:street":"Richard Jones Rd",
    "iso:country":"US",
    "sg:address":"2002 Richard Jones Rd",
    "sg:city":"Nashville",
    "sg:classifiers":[
        {
            "category":"Real Estate",
            "subcategory":"Real Estate Agent",
            "type":"Services"
        }
    ],
    "sg:phone":"+1 615 386 9242",
    "sg:postcode":"37215",
    "sg:province":"TN",
    "sg:tags":[
        "owner",
        "commercial"
    ],
    "wof:name":"Woodlawn Office Properties",
    "wof:placetype":"venue"
},
  "geometry": {"coordinates":[-86.814498,36.104866],"type":"Point"}
}