{
  "type": "Feature",
  "properties": {
    "addr:full":"2850 Lamb Pl Memphis TN 38118",
    "addr:housenumber":"2850",
    "addr:postcode":"38118",
    "addr:street":"Lamb Pl",
    "iso:country":"US",
    "sg:address":"2850 Lamb Pl",
    "sg:city":"Memphis",
    "sg:classifiers":[
        {
            "category":"Building & Trades",
            "subcategory":"Cleaning & Sanitation",
            "type":"Services"
        }
    ],
    "sg:phone":"+1 901 433 1154",
    "sg:postcode":"38118",
    "sg:province":"TN",
    "sg:tags":[
        "janitor"
    ],
    "wof:name":"Immaculate Connection Cleaning",
    "wof:placetype":"venue"
},
  "geometry": {"coordinates":[-89.961935,35.071858],"type":"Point"}
}