{
  "type": "Feature",
  "properties": {
    "iso:country":"US",
    "sg:address":"2978 Austin Peay Hwy",
    "sg:city":"Memphis",
    "sg:classifiers":[
        {
            "category":"Autos & Motor Vehicles",
            "subcategory":"Auto Supplies",
            "type":"Retail Goods"
        }
    ],
    "sg:phone":"+1 901 266 9996",
    "sg:postcode":"38128",
    "sg:province":"TN",
    "sg:tags":[
        "automobile",
        "rebuilt",
        "part",
        "supplies-used"
    ],
    "wof:name":"Low Mileage Engines",
    "wof:placetype":"venue"
},
  "geometry": {"coordinates":[-89.921544,35.206071],"type":"Point"}
}