{
  "type": "Feature",
  "properties": {
    "iso:country":"US",
    "sg:address":"229 Tobacco Rd",
    "sg:city":"Clarksville",
    "sg:classifiers":[
        {
            "category":"Professional",
            "type":"Services"
        }
    ],
    "sg:phone":"+1 931 647 9751",
    "sg:postcode":"37042",
    "sg:province":"TN",
    "wof:name":"Jackie Chin Inc",
    "wof:placetype":"venue"
},
  "geometry": {"coordinates":[-87.42083599999999,36.603957],"type":"Point"}
}