{
  "type": "Feature",
  "properties": {
    "addr:full":"106 Rivergate Meadows Dr Goodlettsville TN 37072",
    "addr:housenumber":"106",
    "addr:postcode":"37072",
    "addr:street":"Rivergate Meadows Dr",
    "iso:country":"US",
    "sg:address":"106 Rivergate Meadows Dr",
    "sg:city":"Goodlettsville",
    "sg:classifiers":[
        {
            "category":"Food & Beverages",
            "subcategory":"Groceries & Convenience Stores",
            "type":"Retail Goods"
        }
    ],
    "sg:phone":"+1 615 855 1217",
    "sg:postcode":"37072",
    "sg:province":"TN",
    "wof:name":"Super Stop Market",
    "wof:placetype":"venue"
},
  "geometry": {"coordinates":[-86.710021,36.298134],"type":"Point"}
}