{
  "type": "Feature",
  "properties": {
    "iso:country":"US",
    "sg:address":"114 Mathis Dr",
    "sg:city":"Dickson",
    "sg:classifiers":[
        {
            "category":"Restaurant",
            "type":"Food & Drink"
        }
    ],
    "sg:menulink":"http://www.allmenus.com/tn/dickson/215204-taco-bell/menu/",
    "sg:phone":"+1 615 446 3713",
    "sg:postcode":"37055",
    "sg:province":"TN",
    "sg:tags":[
        "mexican"
    ],
    "wof:name":"Taco Bell",
    "wof:placetype":"venue"
},
  "geometry": {"coordinates":[-87.37478299999999,36.076272],"type":"Point"}
}