{
  "type": "Feature",
  "properties": {
    "addr:full":"7970 Patriot Dr Cordova TN 38018",
    "addr:housenumber":"7970",
    "addr:postcode":"38018",
    "addr:street":"Patriot Dr",
    "iso:country":"US",
    "sg:address":"7970 Patriot Dr",
    "sg:city":"Cordova",
    "sg:classifiers":[
        {
            "category":"Retail",
            "subcategory":"Auto Repair",
            "type":"Services"
        }
    ],
    "sg:phone":"+1 901 754 8381",
    "sg:postcode":"38018",
    "sg:province":"TN",
    "sg:tags":[
        "repairing",
        "automotive",
        "automobile",
        "general"
    ],
    "sg:website":"www.cordovaauto.com",
    "wof:name":"Cordova Automotive Inc",
    "wof:placetype":"venue"
},
  "geometry": {"coordinates":[-89.79740099999999,35.149327],"type":"Point"}
}