{
  "type": "Feature",
  "properties": {
    "iso:country":"US",
    "sg:address":"203 Cumberland Blvd",
    "sg:city":"Huntland",
    "sg:classifiers":[
        {
            "category":"Organizations",
            "subcategory":"Religious Organization",
            "type":"Services"
        }
    ],
    "sg:phone":"+1 931 469 0271",
    "sg:postcode":"37345",
    "sg:province":"TN",
    "sg:tags":[
        "church"
    ],
    "wof:name":"Emmanuel Church Of Christ",
    "wof:placetype":"venue"
},
  "geometry": {"coordinates":[-86.266865,35.054798],"type":"Point"}
}