{
  "type": "Feature",
  "properties": {
    "iso:country":"US",
    "sg:address":"3677 Miac Dr",
    "sg:city":"Memphis",
    "sg:classifiers":[
        {
            "category":"Banks & Credit Unions",
            "subcategory":"Financial Services",
            "type":"Services"
        }
    ],
    "sg:phone":"+1 901 794 1763",
    "sg:postcode":"38118",
    "sg:province":"TN",
    "sg:tags":[
        "investor"
    ],
    "wof:name":"Belz In Best Co",
    "wof:placetype":"venue"
},
  "geometry": {"coordinates":[-89.942796,35.055633],"type":"Point"}
}