{
  "type": "Feature",
  "properties": {
    "iso:country":"US",
    "sg:address":"592 Carson Creek Rd",
    "sg:city":"Limestone",
    "sg:classifiers":[
        {
            "category":"Building & Trades",
            "subcategory":"Construction",
            "type":"Services"
        }
    ],
    "sg:phone":"+1 423 791 3624",
    "sg:postcode":"37690",
    "sg:province":"TN",
    "sg:tags":[
        "home",
        "improvement"
    ],
    "wof:name":"Morris Construction",
    "wof:placetype":"venue"
},
  "geometry": {"coordinates":[-82.630228,36.275137],"type":"Point"}
}