{
  "type": "Feature",
  "properties": {
    "iso:country":"US",
    "sg:address":"2174 Westchester Dr",
    "sg:city":"Memphis",
    "sg:classifiers":[
        {
            "category":"Real Estate",
            "subcategory":"Real Estate Operator",
            "type":"Services"
        }
    ],
    "sg:phone":"+1 901 388 0583",
    "sg:postcode":"38134",
    "sg:province":"TN",
    "sg:tags":[
        "building",
        "apartment"
    ],
    "sg:website":"www.hmheckle.com",
    "wof:name":"Sycamore Lake Apartments",
    "wof:placetype":"venue"
},
  "geometry": {"coordinates":[-89.86935699999999,35.184355],"type":"Point"}
}