{
  "type": "Feature",
  "properties": {
    "iso:country":"US",
    "sg:address":"2809 Tarleton Ave",
    "sg:city":"Knoxville",
    "sg:classifiers":[
        {
            "category":"Professional",
            "subcategory":"Business Services",
            "type":"Services"
        }
    ],
    "sg:phone":"+1 865 525 3659",
    "sg:postcode":"37914",
    "sg:province":"TN",
    "wof:name":"Hqh Enterprises",
    "wof:placetype":"venue"
},
  "geometry": {"coordinates":[-83.887443,35.988626],"type":"Point"}
}