{
  "type": "Feature",
  "properties": {
    "iso:country":"US",
    "sg:address":"5729 E Burnette Pl",
    "sg:city":"Memphis",
    "sg:classifiers":[
        {
            "category":"Shopping",
            "subcategory":"Stationery & Office Supplies",
            "type":"Retail Goods"
        }
    ],
    "sg:phone":"+1 901 368 0528",
    "sg:postcode":"38141",
    "sg:province":"TN",
    "wof:name":"Designs By Lesa",
    "wof:placetype":"venue"
},
  "geometry": {"coordinates":[-89.87302800000001,35.026793],"type":"Point"}
}