{
  "type": "Feature",
  "properties": {
    "iso:country":"US",
    "sg:address":"195 Brooksboro Ter",
    "sg:city":"Nashville",
    "sg:classifiers":[
        {
            "category":"Freight",
            "type":"Transportation"
        }
    ],
    "sg:phone":"+1 615 399 2269",
    "sg:postcode":"37217",
    "sg:province":"TN",
    "sg:tags":[
        "operator",
        "local",
        "trucking"
    ],
    "wof:name":"Woodruff Delivery Serv",
    "wof:placetype":"venue"
},
  "geometry": {"coordinates":[-86.645439,36.085109],"type":"Point"}
}