{
  "type": "Feature",
  "properties": {
    "iso:country":"US",
    "sg:address":"1421 McMinnville Hwy",
    "sg:city":"Manchester",
    "sg:classifiers":[
        {
            "category":"Autos & Motor Vehicles",
            "subcategory":"Fuel & Gas Station",
            "type":"Retail Goods"
        }
    ],
    "sg:phone":"+1 931 728 5857",
    "sg:postcode":"37355",
    "sg:province":"TN",
    "sg:tags":[
        "oil"
    ],
    "wof:name":"Chevron Food Mart",
    "wof:placetype":"venue"
},
  "geometry": {"coordinates":[-86.069885,35.494922],"type":"Point"}
}