{
  "type": "Feature",
  "properties": {
    "iso:country":"US",
    "sg:address":"1298 State Hwy 1",
    "sg:city":"Memphis",
    "sg:classifiers":[
        {
            "category":"Professional",
            "subcategory":"Accounting & Tax Preparation",
            "type":"Services"
        }
    ],
    "sg:phone":"+1 901 725 4305",
    "sg:postcode":"38104",
    "sg:province":"TN",
    "wof:name":"Sullivan  Lady F CPA",
    "wof:placetype":"venue"
},
  "geometry": {"coordinates":[-90.01770999999999,35.154202],"type":"Point"}
}