{
  "type": "Feature",
  "properties": {
    "iso:country":"US",
    "sg:address":"135 Snyder Ln",
    "sg:city":"Greeneville",
    "sg:classifiers":[
        {
            "category":"Building & Trades",
            "subcategory":"Plumbing",
            "type":"Services"
        }
    ],
    "sg:phone":"+1 423 636 2617",
    "sg:postcode":"37743",
    "sg:province":"TN",
    "sg:tags":[
        "conditioning",
        "air",
        "system",
        "contractor"
    ],
    "wof:name":"Jerry's Heat & Air",
    "wof:placetype":"venue"
},
  "geometry": {"coordinates":[-82.842446,36.025721],"type":"Point"}
}