{
  "type": "Feature",
  "properties": {
    "iso:country":"US",
    "sg:address":"109 S Trenton St",
    "sg:city":"Rutherford",
    "sg:classifiers":[
        {
            "category":"Retail",
            "subcategory":"Funeral Services",
            "type":"Services"
        }
    ],
    "sg:phone":"+1 731 665 7654",
    "sg:postcode":"38369",
    "sg:province":"TN",
    "sg:tags":[
        "director"
    ],
    "wof:name":"Roberts & Karnes Funeral Home",
    "wof:placetype":"venue"
},
  "geometry": {"coordinates":[-88.986341,36.127389],"type":"Point"}
}