{
  "type": "Feature",
  "properties": {
    "iso:country":"US",
    "sg:address":"3313 Ironwood Dr",
    "sg:city":"Nashville",
    "sg:classifiers":[
        {
            "category":"Professional",
            "subcategory":"Business Services",
            "type":"Services"
        }
    ],
    "sg:phone":"+1 615 871 9507",
    "sg:postcode":"37214",
    "sg:province":"TN",
    "wof:name":"Richard Delima",
    "wof:placetype":"venue"
},
  "geometry": {"coordinates":[-86.650092,36.148987],"type":"Point"}
}