{
  "type": "Feature",
  "properties": {
    "addr:full":"1828 Ryder Dr Kingsport TN 37664",
    "addr:housenumber":"1828",
    "addr:postcode":"37664",
    "addr:street":"Ryder Dr",
    "iso:country":"US",
    "sg:address":"1828 Ryder Dr",
    "sg:city":"Kingsport",
    "sg:classifiers":[
        {
            "category":"Manufacturing",
            "subcategory":"Tools & Machinery",
            "type":"Manufacturing & Wholesale Goods"
        }
    ],
    "sg:phone":"+1 423 246 2157",
    "sg:postcode":"37664",
    "sg:province":"TN",
    "sg:tags":[
        "mfg"
    ],
    "wof:name":"Fleenor Tool & Die Inc",
    "wof:placetype":"venue"
},
  "geometry": {"coordinates":[-82.517596,36.542134],"type":"Point"}
}