{
  "type": "Feature",
  "properties": {
    "iso:country":"US",
    "sg:address":"2839 Lamar Ave",
    "sg:city":"Memphis",
    "sg:classifiers":[
        {
            "category":"Restaurant",
            "type":"Food & Drink"
        }
    ],
    "sg:phone":"+1 901 743 2719",
    "sg:postcode":"38114",
    "sg:province":"TN",
    "sg:tags":[
        "eating"
    ],
    "wof:name":"Clark's Diner",
    "wof:placetype":"venue"
},
  "geometry": {"coordinates":[-89.969297,35.094268],"type":"Point"}
}