{
  "type": "Feature",
  "properties": {
    "iso:country":"US",
    "sg:address":"1625 Cold Springs Rd",
    "sg:city":"Mountain City",
    "sg:classifiers":[
        {
            "category":"Utilities",
            "subcategory":"Water",
            "type":"Services"
        }
    ],
    "sg:phone":"+1 423 727 8851",
    "sg:postcode":"37683",
    "sg:province":"TN",
    "sg:tags":[
        "company",
        "sewage"
    ],
    "wof:name":"Cold Springs Utilities",
    "wof:placetype":"venue"
},
  "geometry": {"coordinates":[-81.822638,36.506235],"type":"Point"}
}