{
  "type": "Feature",
  "properties": {
    "iso:country":"US",
    "sg:address":"144 Westwood Cir",
    "sg:city":"Ripley",
    "sg:phone":"+1 731 635 1743",
    "sg:postcode":"38063",
    "sg:province":"TN",
    "sg:tags":[
        "farm",
        "soybean"
    ],
    "wof:name":"Charles Walker",
    "wof:placetype":"venue"
},
  "geometry": {"coordinates":[-89.542796,35.747547],"type":"Point"}
}