{
  "type": "Feature",
  "properties": {
    "addr:full":"2388 Lebanon Pike Nashville TN 37214",
    "addr:housenumber":"2388",
    "addr:postcode":"37214",
    "addr:street":"Lebanon Pike",
    "iso:country":"US",
    "sg:address":"2388 Lebanon Pike",
    "sg:city":"Nashville",
    "sg:classifiers":[
        {
            "category":"Restaurant",
            "type":"Food & Drink"
        }
    ],
    "sg:menulink":"http://www.allmenus.com/tn/nashville/214928-burger-king/menu/",
    "sg:phone":"+1 615 883 4992",
    "sg:postcode":"37214",
    "sg:province":"TN",
    "sg:tags":[
        "burger",
        "american"
    ],
    "wof:name":"Burger King",
    "wof:placetype":"venue"
},
  "geometry": {"coordinates":[-86.682793,36.169019],"type":"Point"}
}