{
  "type": "Feature",
  "properties": {
    "iso:country":"US",
    "sg:address":"3636 Orebank Rd",
    "sg:city":"Kingsport",
    "sg:classifiers":[
        {
            "category":"Building & Trades",
            "subcategory":"Landscaping Services",
            "type":"Services"
        }
    ],
    "sg:phone":"+1 423 340 2036",
    "sg:postcode":"37664",
    "sg:province":"TN",
    "sg:tags":[
        "landscape"
    ],
    "wof:name":"Rocky Top Landscaping",
    "wof:placetype":"venue"
},
  "geometry": {"coordinates":[-82.505599,36.535639],"type":"Point"}
}