{
  "type": "Feature",
  "properties": {
    "iso:country":"US",
    "sg:address":"185 Eaton Ln",
    "sg:city":"Manchester",
    "sg:classifiers":[
        {
            "category":"Shopping",
            "subcategory":"Catalog Store",
            "type":"Retail Goods"
        }
    ],
    "sg:phone":"+1 931 723 0173",
    "sg:postcode":"37355",
    "sg:province":"TN",
    "sg:tags":[
        "house",
        "mail"
    ],
    "wof:name":"Somatech",
    "wof:placetype":"venue"
},
  "geometry": {"coordinates":[-86.161295,35.494178],"type":"Point"}
}