{
  "type": "Feature",
  "properties": {
    "iso:country":"US",
    "sg:address":"4135 Parsons Rd",
    "sg:city":"Wildersville",
    "sg:phone":"+1 731 845 5701",
    "sg:postcode":"38388",
    "sg:province":"TN",
    "sg:tags":[
        "farm",
        "corn"
    ],
    "wof:name":"Wayne Stephens",
    "wof:placetype":"venue"
},
  "geometry": {"coordinates":[-88.209383,35.771078],"type":"Point"}
}