{
  "type": "Feature",
  "properties": {
    "addr:full":"1350 Peabody Ave Memphis TN 38104",
    "addr:housenumber":"1350",
    "addr:postcode":"38104",
    "addr:street":"Peabody Ave",
    "iso:country":"US",
    "sg:address":"1350 Peabody Ave",
    "sg:city":"Memphis",
    "sg:classifiers":[
        {
            "category":"Health Services",
            "subcategory":"Doctor",
            "type":"Services"
        }
    ],
    "sg:phone":"+1 901 725 4204",
    "sg:postcode":"38104",
    "sg:province":"TN",
    "sg:tags":[
        "medical"
    ],
    "wof:name":"Edna M Davis MD",
    "wof:placetype":"venue"
},
  "geometry": {"coordinates":[-90.014352,35.132588],"type":"Point"}
}