{
  "type": "Feature",
  "properties": {
    "iso:country":"US",
    "sg:address":"1461 W 3rd Ave",
    "sg:city":"Oneida",
    "sg:phone":"+1 423 569 5506",
    "sg:postcode":"37841",
    "sg:province":"TN",
    "sg:tags":[
        "gas"
    ],
    "wof:name":"Cannon Brothers Co Inc",
    "wof:placetype":"venue"
},
  "geometry": {"coordinates":[-84.53842299999999,36.5023],"type":"Point"}
}