{
  "type": "Feature",
  "properties": {
    "iso:country":"US",
    "sg:address":"2013 Columbia Ave",
    "sg:city":"Franklin",
    "sg:classifiers":[
        {
            "category":"Shopping",
            "type":"Retail Goods"
        }
    ],
    "sg:phone":"+1 615 595 1177",
    "sg:postcode":"37064",
    "sg:province":"TN",
    "sg:tags":[
        "merchandise"
    ],
    "wof:name":"Keeling",
    "wof:placetype":"venue"
},
  "geometry": {"coordinates":[-86.876519,35.895607],"type":"Point"}
}