{
  "type": "Feature",
  "properties": {
    "iso:country":"US",
    "sg:address":"3030 McDonald Rd",
    "sg:city":"Midway",
    "sg:classifiers":[
        {
            "category":"Building & Trades",
            "subcategory":"Plumbing",
            "type":"Services"
        }
    ],
    "sg:phone":"+1 423 422 7399",
    "sg:postcode":"37809",
    "sg:province":"TN",
    "sg:tags":[
        "conditioning",
        "air",
        "system",
        "contractor"
    ],
    "wof:name":"Four Seasons Heating & Air",
    "wof:placetype":"venue"
},
  "geometry": {"coordinates":[-83.046491,36.180187],"type":"Point"}
}