{
  "type": "Feature",
  "properties": {
    "iso:country":"US",
    "sg:address":"69 E 1st St",
    "sg:city":"Crossville",
    "sg:classifiers":[
        {
            "category":"Professional",
            "subcategory":"Lawyer & Legal Services",
            "type":"Services"
        }
    ],
    "sg:phone":"+1 931 456 1313",
    "sg:postcode":"38555",
    "sg:province":"TN",
    "wof:name":"Burnett Jane E",
    "wof:placetype":"venue"
},
  "geometry": {"coordinates":[-85.024665,35.947334],"type":"Point"}
}