{
  "type": "Feature",
  "properties": {
    "iso:country":"US",
    "sg:address":"640 Nuckolls Rd",
    "sg:city":"Bolivar",
    "sg:classifiers":[
        {
            "category":"Shopping",
            "subcategory":"Pharmacy",
            "type":"Retail Goods"
        }
    ],
    "sg:phone":"+1 731 659 3740",
    "sg:postcode":"38008",
    "sg:province":"TN",
    "wof:name":"Hatchie Pharmacy",
    "wof:placetype":"venue"
},
  "geometry": {"coordinates":[-89.00053,35.267202],"type":"Point"}
}