{
  "type": "Feature",
  "properties": {
    "iso:country":"US",
    "sg:address":"100 Antioch Pike",
    "sg:city":"Nashville",
    "sg:classifiers":[
        {
            "category":"Shopping",
            "subcategory":"Clothing, Apparel, & Fashions",
            "type":"Retail Goods"
        }
    ],
    "sg:phone":"+1 615 589 2683",
    "sg:postcode":"37211",
    "sg:province":"TN",
    "wof:name":"W B Enterprises",
    "wof:placetype":"venue"
},
  "geometry": {"coordinates":[-86.720761,36.101333],"type":"Point"}
}