{
  "type": "Feature",
  "properties": {
    "iso:country":"US",
    "sg:address":"127 Rushwood Dr",
    "sg:city":"Murfreesboro",
    "sg:classifiers":[
        {
            "category":"Organizations",
            "subcategory":"Religious Organization",
            "type":"Services"
        }
    ],
    "sg:phone":"+1 615 217 9001",
    "sg:postcode":"37130",
    "sg:province":"TN",
    "sg:tags":[
        "church"
    ],
    "wof:name":"Fair Havens Independent Bapt",
    "wof:placetype":"venue"
},
  "geometry": {"coordinates":[-86.392398,35.83663],"type":"Point"}
}