{
  "type": "Feature",
  "properties": {
    "iso:country":"US",
    "sg:address":"644 Fall River Rd",
    "sg:city":"Goodspring",
    "sg:classifiers":[
        {
            "category":"Organizations",
            "subcategory":"Religious Organization",
            "type":"Services"
        }
    ],
    "sg:phone":"+1 931 363 8675",
    "sg:postcode":"38478",
    "sg:province":"TN",
    "sg:tags":[
        "church"
    ],
    "wof:name":"Ebenezer Baptist Church",
    "wof:placetype":"venue"
},
  "geometry": {"coordinates":[-87.107671,35.140974],"type":"Point"}
}