{
  "type": "Feature",
  "properties": {
    "iso:country":"US",
    "sg:address":"1738 Crestview Dr",
    "sg:city":"Clarksville",
    "sg:classifiers":[
        {
            "category":"Shopping",
            "subcategory":"Clothing, Apparel, & Fashions",
            "type":"Retail Goods"
        }
    ],
    "sg:phone":"+1 931 645 4200",
    "sg:postcode":"37042",
    "sg:province":"TN",
    "wof:name":"Shirts For Soldiers",
    "wof:placetype":"venue"
},
  "geometry": {"coordinates":[-87.352287,36.623023],"type":"Point"}
}