{
  "type": "Feature",
  "properties": {
    "iso:country":"US",
    "sg:address":"8549 Troutman Ln",
    "sg:city":"Knoxville",
    "sg:classifiers":[
        {
            "category":"Personal",
            "subcategory":"Beauty Salon",
            "type":"Services"
        }
    ],
    "sg:phone":"+1 865 693 8779",
    "sg:postcode":"37931",
    "sg:province":"TN",
    "sg:tags":[
        "shop"
    ],
    "wof:name":"Styles By Chris",
    "wof:placetype":"venue"
},
  "geometry": {"coordinates":[-84.096011,35.956423],"type":"Point"}
}