{
  "type": "Feature",
  "properties": {
    "iso:country":"US",
    "sg:address":"1933 Fain Cemetery Rd",
    "sg:city":"Dandridge",
    "sg:classifiers":[
        {
            "category":"Building & Trades",
            "subcategory":"Construction",
            "type":"Services"
        }
    ],
    "sg:phone":"+1 865 397 5412",
    "sg:postcode":"37725",
    "sg:province":"TN",
    "sg:tags":[
        "house"
    ],
    "wof:name":"Landmark Visions Inc",
    "wof:placetype":"venue"
},
  "geometry": {"coordinates":[-83.523597,35.980677],"type":"Point"}
}