{
  "type": "Feature",
  "properties": {
    "iso:country":"US",
    "sg:address":"3333 Stafford Dr",
    "sg:city":"Cookeville",
    "sg:classifiers":[
        {
            "category":"Communications",
            "subcategory":"Film & Video Production",
            "type":"Services"
        }
    ],
    "sg:phone":"+1 931 528 8240",
    "sg:postcode":"38506",
    "sg:province":"TN",
    "sg:tags":[
        "consultant",
        "audio"
    ],
    "wof:name":"Biz Media",
    "wof:placetype":"venue"
},
  "geometry": {"coordinates":[-85.441892,36.133861],"type":"Point"}
}