{
  "type": "Feature",
  "properties": {
    "iso:country":"US",
    "sg:address":"114 Austin St",
    "sg:city":"Greeneville",
    "sg:classifiers":[
        {
            "category":"Home & Garden",
            "subcategory":"Carpets & Floor Coverings",
            "type":"Retail Goods"
        }
    ],
    "sg:phone":"+1 423 639 9013",
    "sg:postcode":"37745",
    "sg:province":"TN",
    "sg:tags":[
        "material"
    ],
    "wof:name":"Gateway Floor Center",
    "wof:placetype":"venue"
},
  "geometry": {"coordinates":[-82.819122,36.170967],"type":"Point"}
}