{
  "type": "Feature",
  "properties": {
    "iso:country":"US",
    "sg:address":"2239 Jasmine Dr",
    "sg:city":"Clarksville",
    "sg:classifiers":[
        {
            "category":"Building & Trades",
            "subcategory":"Plumbing",
            "type":"Services"
        }
    ],
    "sg:phone":"+1 931 906 7424",
    "sg:postcode":"37043",
    "sg:province":"TN",
    "sg:tags":[
        "contractor"
    ],
    "wof:name":"Mattoc Distributing",
    "wof:placetype":"venue"
},
  "geometry": {"coordinates":[-87.27863600000001,36.566187],"type":"Point"}
}