{
  "type": "Feature",
  "properties": {
    "addr:full":"1192 Murfreesboro Pike Nashville TN 37217",
    "addr:housenumber":"1192",
    "addr:postcode":"37217",
    "addr:street":"Murfreesboro Pike",
    "iso:country":"US",
    "sg:address":"1192 Murfreesboro Pike",
    "sg:city":"Nashville",
    "sg:classifiers":[
        {
            "category":"Autos & Motor Vehicles",
            "subcategory":"Auto Supplies",
            "type":"Retail Goods"
        }
    ],
    "sg:phone":"+1 615 361 3094",
    "sg:postcode":"37217",
    "sg:province":"TN",
    "sg:tags":[
        "tire"
    ],
    "wof:name":"Firestone",
    "wof:placetype":"venue"
},
  "geometry": {"coordinates":[-86.70384,36.121131],"type":"Point"}
}