{
  "type": "Feature",
  "properties": {
    "addr:full":"788 W Main St Hendersonville TN 37075",
    "addr:housenumber":"788",
    "addr:postcode":"37075",
    "addr:street":"W Main St",
    "iso:country":"US",
    "sg:address":"788 W Main St",
    "sg:city":"Hendersonville",
    "sg:classifiers":[
        {
            "category":"Autos & Motor Vehicles",
            "subcategory":"Boat Sales",
            "type":"Retail Goods"
        }
    ],
    "sg:phone":"+1 615 826 2655",
    "sg:postcode":"37075",
    "sg:province":"TN",
    "sg:tags":[
        "equipment",
        "supply"
    ],
    "wof:name":"TNT Water Sports",
    "wof:placetype":"venue"
},
  "geometry": {"coordinates":[-86.644718,36.303539],"type":"Point"}
}