{
  "type": "Feature",
  "properties": {
    "addr:full":"354 Campbell Rd South Pittsburg TN 37380",
    "addr:housenumber":"354",
    "addr:postcode":"37380",
    "addr:street":"Campbell Rd",
    "iso:country":"US",
    "sg:address":"354 Campbell Rd",
    "sg:city":"South Pittsburg",
    "sg:classifiers":[
        {
            "category":"Restaurant",
            "type":"Food & Drink"
        }
    ],
    "sg:phone":"+1 423 837 6773",
    "sg:postcode":"37380",
    "sg:province":"TN",
    "sg:tags":[
        "eating"
    ],
    "wof:name":"Pizza Hut",
    "wof:placetype":"venue"
},
  "geometry": {"coordinates":[-85.65801999999999,35.004971],"type":"Point"}
}