{
  "type": "Feature",
  "properties": {
    "addr:full":"200 Gunn Dr Greeneville TN 37743",
    "addr:housenumber":"200",
    "addr:postcode":"37743",
    "addr:street":"Gunn Dr",
    "iso:country":"US",
    "sg:address":"200 Gunn Dr",
    "sg:city":"Greeneville",
    "sg:classifiers":[
        {
            "category":"Building & Trades",
            "subcategory":"Construction",
            "type":"Services"
        }
    ],
    "sg:phone":"+1 423 638 9937",
    "sg:postcode":"37743",
    "sg:province":"TN",
    "sg:tags":[
        "house"
    ],
    "wof:name":"Praise Construction",
    "wof:placetype":"venue"
},
  "geometry": {"coordinates":[-82.89146599999999,36.185343],"type":"Point"}
}