{
  "type": "Feature",
  "properties": {
    "iso:country":"US",
    "sg:address":"1297 Marlin Rd",
    "sg:city":"Memphis",
    "sg:classifiers":[
        {
            "category":"Health Services",
            "subcategory":"Doctor",
            "type":"Services"
        }
    ],
    "sg:phone":"+1 901 396 6753",
    "sg:postcode":"38116",
    "sg:province":"TN",
    "wof:name":"Lott Fmly Dntstry Emrgncy Care",
    "wof:placetype":"venue"
},
  "geometry": {"coordinates":[-90.02210700000001,35.03412],"type":"Point"}
}