{
  "type": "Feature",
  "properties": {
    "iso:country":"US",
    "sg:address":"3513 Obion Dr",
    "sg:city":"Memphis",
    "sg:classifiers":[
        {
            "category":"Personal",
            "subcategory":"Nail Salon",
            "type":"Services"
        }
    ],
    "sg:phone":"+1 901 357 9056",
    "sg:postcode":"38127",
    "sg:province":"TN",
    "wof:name":"Keshas Nails",
    "wof:placetype":"venue"
},
  "geometry": {"coordinates":[-90.01609500000001,35.220768],"type":"Point"}
}