{
  "type": "Feature",
  "properties": {
    "iso:country":"US",
    "sg:address":"5281 Knight Arnold Rd",
    "sg:city":"Memphis",
    "sg:classifiers":[
        {
            "category":"Personal",
            "subcategory":"Beauty Salon",
            "type":"Services"
        }
    ],
    "sg:phone":"+1 901 369 1177",
    "sg:postcode":"38118",
    "sg:province":"TN",
    "sg:tags":[
        "shop"
    ],
    "wof:name":"Professional Salon Cleaning",
    "wof:placetype":"venue"
},
  "geometry": {"coordinates":[-89.886017,35.06184],"type":"Point"}
}