{
  "type": "Feature",
  "properties": {
    "addr:full":"7515 Hydrus Dr Harrison TN 37341",
    "addr:housenumber":"7515",
    "addr:postcode":"37341",
    "addr:street":"Hydrus Dr",
    "iso:country":"US",
    "sg:address":"7515 Hydrus Dr",
    "sg:city":"Harrison",
    "sg:classifiers":[
        {
            "category":"Building & Trades",
            "subcategory":"Construction",
            "type":"Services"
        }
    ],
    "sg:phone":"+1 423 421 3210",
    "sg:postcode":"37341",
    "sg:province":"TN",
    "sg:tags":[
        "home",
        "improvement"
    ],
    "wof:name":"Custom Remodeling",
    "wof:placetype":"venue"
},
  "geometry": {"coordinates":[-85.066818,35.194391],"type":"Point"}
}