{
  "type": "Feature",
  "properties": {
    "iso:country":"US",
    "sg:address":"4171 Lamar Ave",
    "sg:city":"Memphis",
    "sg:classifiers":[
        {
            "category":"Insurance",
            "subcategory":"Hazard Insurance",
            "type":"Services"
        }
    ],
    "sg:phone":"+1 901 365 8008",
    "sg:postcode":"38118",
    "sg:province":"TN",
    "sg:tags":[
        "commercial",
        "business"
    ],
    "wof:name":"Direct General Insurance Agency Inc",
    "wof:placetype":"venue"
},
  "geometry": {"coordinates":[-89.924193,35.050065],"type":"Point"}
}