{
  "type": "Feature",
  "properties": {
    "iso:country":"US",
    "sg:address":"6773 Macon Rd",
    "sg:city":"Memphis",
    "sg:classifiers":[
        {
            "category":"Social Services",
            "type":"Services"
        }
    ],
    "sg:phone":"+1 901 266 3976",
    "sg:postcode":"38134",
    "sg:province":"TN",
    "sg:tags":[
        "info",
        "program",
        "referral"
    ],
    "wof:name":"Teen Moms Mission",
    "wof:placetype":"venue"
},
  "geometry": {"coordinates":[-89.83701000000001,35.166291],"type":"Point"}
}