{
  "type": "Feature",
  "properties": {
    "iso:country":"US",
    "sg:address":"331 Plus Park Blvd",
    "sg:city":"Nashville",
    "sg:classifiers":[
        {
            "category":"Building & Trades",
            "subcategory":"Construction",
            "type":"Services"
        }
    ],
    "sg:phone":"+1 615 366 6162",
    "sg:postcode":"37217",
    "sg:province":"TN",
    "sg:tags":[
        "concrete",
        "contractor"
    ],
    "wof:name":"R & Kelley Concrete Finishing",
    "wof:placetype":"venue"
},
  "geometry": {"coordinates":[-86.722752,36.133888],"type":"Point"}
}