{
  "type": "Feature",
  "properties": {
    "iso:country":"US",
    "sg:address":"9815 Cogdill Rd",
    "sg:city":"Knoxville",
    "sg:classifiers":[
        {
            "category":"Communications",
            "type":"Services"
        }
    ],
    "sg:phone":"+1 865 777 1789",
    "sg:postcode":"37932",
    "sg:province":"TN",
    "wof:name":"Ferradonna Communication",
    "wof:placetype":"venue"
},
  "geometry": {"coordinates":[-84.126898,35.917785],"type":"Point"}
}