{
  "type": "Feature",
  "properties": {
    "iso:country":"US",
    "sg:address":"173 Archwood Pl",
    "sg:city":"Madison",
    "sg:classifiers":[
        {
            "category":"Professional",
            "type":"Services"
        }
    ],
    "sg:phone":"+1 615 474 1676",
    "sg:postcode":"37115",
    "sg:province":"TN",
    "wof:name":"Kevins Maintenance Service",
    "wof:placetype":"venue"
},
  "geometry": {"coordinates":[-86.68408599999999,36.265313],"type":"Point"}
}