{
  "type": "Feature",
  "properties": {
    "addr:full":"13512 Chapman Hwy Seymour TN 37865",
    "addr:housenumber":"13512",
    "addr:postcode":"37865",
    "addr:street":"Chapman Hwy",
    "iso:country":"US",
    "sg:address":"13512 Chapman Hwy",
    "sg:city":"Seymour",
    "sg:classifiers":[
        {
            "category":"Building & Trades",
            "subcategory":"Construction",
            "type":"Services"
        }
    ],
    "sg:phone":"+1 865 428 6060",
    "sg:postcode":"37865",
    "sg:province":"TN",
    "sg:tags":[
        "excavation",
        "contractor"
    ],
    "wof:name":"L & E Excavating & Landscaping",
    "wof:placetype":"venue"
},
  "geometry": {"coordinates":[-83.66704300000001,35.862375],"type":"Point"}
}