{
  "type": "Feature",
  "properties": {
    "iso:country":"US",
    "sg:address":"411 S 4th St",
    "sg:city":"Union City",
    "sg:classifiers":[
        {
            "category":"Professional",
            "type":"Services"
        }
    ],
    "sg:phone":"+1 731 885 9601",
    "sg:postcode":"38261",
    "sg:province":"TN",
    "wof:name":"Union City Bmx Inc",
    "wof:placetype":"venue"
},
  "geometry": {"coordinates":[-89.06039199999999,36.423201],"type":"Point"}
}