{
  "type": "Feature",
  "properties": {
    "addr:full":"9118 George Williams Rd Knoxville TN 37922",
    "addr:housenumber":"9118",
    "addr:postcode":"37922",
    "addr:street":"George Williams Rd",
    "iso:country":"US",
    "sg:address":"9118 George Williams Rd",
    "sg:city":"Knoxville",
    "sg:classifiers":[
        {
            "category":"Education",
            "subcategory":"School",
            "type":"Public Place"
        }
    ],
    "sg:phone":"+1 865 539 5145",
    "sg:postcode":"37922",
    "sg:province":"TN",
    "sg:tags":[
        "middle"
    ],
    "wof:name":"West Valley Middle School",
    "wof:placetype":"venue"
},
  "geometry": {"coordinates":[-84.07847099999999,35.902321],"type":"Point"}
}