{
  "type": "Feature",
  "properties": {
    "addr:full":"528 Wilson St Jackson TN 38301",
    "addr:housenumber":"528",
    "addr:postcode":"38301",
    "addr:street":"Wilson St",
    "iso:country":"US",
    "sg:address":"528 Wilson St",
    "sg:city":"Jackson",
    "sg:classifiers":[
        {
            "category":"Social Services",
            "subcategory":"Child Care",
            "type":"Services"
        }
    ],
    "sg:phone":"+1 731 427 1911",
    "sg:postcode":"38301",
    "sg:province":"TN",
    "sg:tags":[
        "day"
    ],
    "wof:name":"Kids Kount Child",
    "wof:placetype":"venue"
},
  "geometry": {"coordinates":[-88.806291,35.605959],"type":"Point"}
}