{
  "type": "Feature",
  "properties": {
    "addr:full":"200 Green Shanty Rd Tennessee Ridge TN 37178",
    "addr:housenumber":"200",
    "addr:postcode":"37178",
    "addr:street":"Green Shanty Rd",
    "iso:country":"US",
    "sg:address":"200 Green Shanty Rd",
    "sg:city":"Tennessee Ridge",
    "sg:classifiers":[
        {
            "category":"Autos & Motor Vehicles",
            "subcategory":"Automobile Sales",
            "type":"Retail Goods"
        }
    ],
    "sg:phone":"+1 931 721 2724",
    "sg:postcode":"37178",
    "sg:province":"TN",
    "sg:tags":[
        "car",
        "used",
        "dealer"
    ],
    "wof:name":"P & P Auto Sales",
    "wof:placetype":"venue"
},
  "geometry": {"coordinates":[-87.75165800000001,36.343344],"type":"Point"}
}