{
  "type": "Feature",
  "properties": {
    "iso:country":"US",
    "sg:address":"2926 Willow St",
    "sg:city":"Pigeon Forge",
    "sg:classifiers":[
        {
            "category":"Home & Garden",
            "subcategory":"Garden Supply",
            "type":"Retail Goods"
        }
    ],
    "sg:phone":"+1 865 429 2832",
    "sg:postcode":"37863",
    "sg:province":"TN",
    "wof:name":"Country Craft Shop",
    "wof:placetype":"venue"
},
  "geometry": {"coordinates":[-83.566548,35.796687],"type":"Point"}
}