{
  "type": "Feature",
  "properties": {
    "addr:full":"1386 Rabbit Valley Rd NW Cleveland TN 37312",
    "addr:housenumber":"1386",
    "addr:postcode":"37312",
    "addr:street":"Rabbit Valley Rd Nw",
    "iso:country":"US",
    "sg:address":"1386 Rabbit Valley Rd NW",
    "sg:city":"Cleveland",
    "sg:classifiers":[
        {
            "category":"Building & Trades",
            "subcategory":"Construction",
            "type":"Services"
        }
    ],
    "sg:phone":"+1 423 479 8588",
    "sg:postcode":"37312",
    "sg:province":"TN",
    "sg:tags":[
        "house"
    ],
    "wof:name":"Hop To It Construction",
    "wof:placetype":"venue"
},
  "geometry": {"coordinates":[-84.914293,35.239443],"type":"Point"}
}