{
  "type": "Feature",
  "properties": {
    "addr:full":"1355 Lynnfield Rd Memphis TN 38119",
    "addr:housenumber":"1355",
    "addr:postcode":"38119",
    "addr:street":"Lynnfield Rd",
    "iso:country":"US",
    "sg:address":"1355 Lynnfield Rd",
    "sg:city":"Memphis",
    "sg:classifiers":[
        {
            "category":"Wholesale",
            "subcategory":"Stationery",
            "type":"Manufacturing & Wholesale Goods"
        }
    ],
    "sg:phone":"+1 901 685 9201",
    "sg:postcode":"38119",
    "sg:province":"TN",
    "sg:tags":[
        "supply"
    ],
    "wof:name":"Standard Register Company",
    "wof:placetype":"venue"
},
  "geometry": {"coordinates":[-89.868843,35.094602],"type":"Point"}
}