{
  "type": "Feature",
  "properties": {
    "iso:country":"US",
    "sg:address":"12128 Laur Brow Rd",
    "sg:city":"Soddy Daisy",
    "sg:classifiers":[
        {
            "category":"Building & Trades",
            "subcategory":"Construction",
            "type":"Services"
        }
    ],
    "sg:phone":"+1 423 332 7884",
    "sg:postcode":"37379",
    "sg:province":"TN",
    "sg:tags":[
        "painter"
    ],
    "wof:name":"Painting Plus By Jerry & Deb",
    "wof:placetype":"venue"
},
  "geometry": {"coordinates":[-85.16525300000001,35.315763],"type":"Point"}
}