{
  "type": "Feature",
  "properties": {
    "iso:country":"US",
    "sg:address":"1154 Old Andersonville Pike",
    "sg:city":"Heiskell",
    "sg:classifiers":[
        {
            "category":"Building & Trades",
            "subcategory":"Construction",
            "type":"Services"
        }
    ],
    "sg:phone":"+1 865 494 5042",
    "sg:postcode":"37754",
    "sg:province":"TN",
    "sg:tags":[
        "repairing",
        "remodeling",
        "contractor"
    ],
    "wof:name":"S & S Remodeling",
    "wof:placetype":"venue"
},
  "geometry": {"coordinates":[-83.99963200000001,36.141019],"type":"Point"}
}