{
  "type": "Feature",
  "properties": {
    "iso:country":"US",
    "sg:address":"582 Ford Rd",
    "sg:city":"Lebanon",
    "sg:classifiers":[
        {
            "category":"Freight",
            "type":"Transportation"
        }
    ],
    "sg:phone":"+1 615 444 8277",
    "sg:postcode":"37087",
    "sg:province":"TN",
    "sg:tags":[
        "operator",
        "local",
        "trucking"
    ],
    "wof:name":"K M V Trucking Inc",
    "wof:placetype":"venue"
},
  "geometry": {"coordinates":[-86.204795,36.32119],"type":"Point"}
}