{
  "type": "Feature",
  "properties": {
    "iso:country":"US",
    "sg:address":"5768 Pond Creek Rd",
    "sg:city":"Philadelphia",
    "sg:classifiers":[
        {
            "category":"Building & Trades",
            "subcategory":"Landscaping Services",
            "type":"Services"
        }
    ],
    "sg:phone":"+1 865 458 4094",
    "sg:postcode":"37846",
    "sg:province":"TN",
    "sg:tags":[
        "lawn",
        "maintenance",
        "grounds"
    ],
    "wof:name":"Lawncare Of East Tennessee",
    "wof:placetype":"venue"
},
  "geometry": {"coordinates":[-84.41548299999999,35.690221],"type":"Point"}
}