{
  "type": "Feature",
  "properties": {
    "iso:country":"US",
    "sg:address":"5675 Pidgeon Roost Rd",
    "sg:city":"Memphis",
    "sg:classifiers":[
        {
            "category":"Professional",
            "subcategory":"Business Services",
            "type":"Services"
        }
    ],
    "sg:phone":"+1 901 888 0099",
    "sg:postcode":"38118",
    "sg:province":"TN",
    "wof:name":"Pages Book Fair",
    "wof:placetype":"venue"
},
  "geometry": {"coordinates":[-89.873824,34.995076],"type":"Point"}
}