{
  "type": "Feature",
  "properties": {
    "addr:full":"531 S Gay St Knoxville TN 37902",
    "addr:housenumber":"531",
    "addr:postcode":"37902",
    "addr:street":"S Gay St",
    "iso:country":"US",
    "sg:address":"531 S Gay St",
    "sg:city":"Knoxville",
    "sg:classifiers":[
        {
            "category":"Professional",
            "subcategory":"Detective & Security Services",
            "type":"Services"
        }
    ],
    "sg:phone":"+1 865 688 4000",
    "sg:postcode":"37902",
    "sg:province":"TN",
    "sg:tags":[
        "investigator"
    ],
    "wof:name":"Private Consultants & Invstgtn",
    "wof:placetype":"venue"
},
  "geometry": {"coordinates":[-83.91793,35.964498],"type":"Point"}
}