{
  "type": "Feature",
  "properties": {
    "iso:country":"US",
    "sg:address":"437 Battle Ave",
    "sg:city":"Franklin",
    "sg:classifiers":[
        {
            "category":"Wholesale",
            "subcategory":"Computers",
            "type":"Manufacturing & Wholesale Goods"
        }
    ],
    "sg:phone":"+1 615 591 0017",
    "sg:postcode":"37064",
    "sg:province":"TN",
    "wof:name":"Sand In Shoes Software",
    "wof:placetype":"venue"
},
  "geometry": {"coordinates":[-86.88395300000001,35.912811],"type":"Point"}
}