{
  "type": "Feature",
  "properties": {
    "iso:country":"US",
    "sg:address":"4411 Barfield Rd",
    "sg:city":"Memphis",
    "sg:classifiers":[
        {
            "category":"Professional",
            "subcategory":"Computer Services",
            "type":"Services"
        }
    ],
    "sg:phone":"+1 901 766 9918",
    "sg:postcode":"38117",
    "sg:province":"TN",
    "sg:website":"www.globalconnexions.com",
    "wof:name":"Global Connexions",
    "wof:placetype":"venue"
},
  "geometry": {"coordinates":[-89.909567,35.135839],"type":"Point"}
}