{
  "type": "Feature",
  "properties": {
    "addr:full":"1436 Winfield Dunn Pkwy Sevierville TN 37876",
    "addr:housenumber":"1436",
    "addr:postcode":"37876",
    "addr:street":"Winfield Dunn Pkwy",
    "iso:country":"US",
    "sg:address":"1436 Winfield Dunn Pkwy",
    "sg:city":"Sevierville",
    "sg:classifiers":[
        {
            "category":"Shopping",
            "type":"Retail Goods"
        }
    ],
    "sg:phone":"+1 865 774 1007",
    "sg:postcode":"37876",
    "sg:province":"TN",
    "sg:tags":[
        "pet",
        "shop"
    ],
    "wof:name":"Smokey Mountain Bird Shop",
    "wof:placetype":"venue"
},
  "geometry": {"coordinates":[-83.581276,35.905895],"type":"Point"}
}