{
  "type": "Feature",
  "properties": {
    "iso:country":"US",
    "sg:address":"168 Grandview Dr",
    "sg:city":"Maynardville",
    "sg:classifiers":[
        {
            "category":"Building & Trades",
            "subcategory":"Electrical",
            "type":"Services"
        }
    ],
    "sg:phone":"+1 865 992 1051",
    "sg:postcode":"37807",
    "sg:province":"TN",
    "sg:tags":[
        "electrical",
        "contractor"
    ],
    "wof:name":"Union Electrical Contracting",
    "wof:placetype":"venue"
},
  "geometry": {"coordinates":[-83.765437,36.273874],"type":"Point"}
}