{
  "type": "Feature",
  "properties": {
    "iso:country":"US",
    "sg:address":"607 Woodbury Hwy",
    "sg:city":"Manchester",
    "sg:classifiers":[
        {
            "category":"Freight",
            "type":"Transportation"
        },
        {
            "category":"Real Estate",
            "subcategory":"Real Estate Operator",
            "type":"Services"
        }
    ],
    "sg:phone":"+1 931 728 2230",
    "sg:postcode":"37355",
    "sg:province":"TN",
    "sg:tags":[
        "apartment",
        "general"
    ],
    "wof:name":"Powers Mini Storage",
    "wof:placetype":"venue"
},
  "geometry": {"coordinates":[-86.087053,35.497589],"type":"Point"}
}