{
  "type": "Feature",
  "properties": {
    "iso:country":"US",
    "sg:address":"506 Wanda Dr",
    "sg:city":"Nashville",
    "sg:classifiers":[
        {
            "category":"Building & Trades",
            "subcategory":"Construction",
            "type":"Services"
        }
    ],
    "sg:phone":"+1 615 889 1992",
    "sg:postcode":"37210",
    "sg:province":"TN",
    "sg:tags":[
        "contractor"
    ],
    "wof:name":"Bobby Goodwin Roofing",
    "wof:placetype":"venue"
},
  "geometry": {"coordinates":[-86.696519,36.155619],"type":"Point"}
}