{
  "type": "Feature",
  "properties": {
    "iso:country":"US",
    "sg:address":"6661 River View Dr",
    "sg:city":"Nashville",
    "sg:classifiers":[
        {
            "category":"Retail",
            "subcategory":"Portrait Studio",
            "type":"Services"
        }
    ],
    "sg:phone":"+1 615 254 6802",
    "sg:postcode":"37209",
    "sg:province":"TN",
    "sg:tags":[
        "photo"
    ],
    "wof:name":"Mark Tucker Photography LLC",
    "wof:placetype":"venue"
},
  "geometry": {"coordinates":[-86.924899,36.137574],"type":"Point"}
}