{
  "type": "Feature",
  "properties": {
    "iso:country":"US",
    "sg:address":"106 Oak Cir",
    "sg:city":"Ashland City",
    "sg:classifiers":[
        {
            "category":"Professional",
            "type":"Services"
        },
        {
            "category":"Organizations",
            "subcategory":"Professional Association",
            "type":"Services"
        }
    ],
    "sg:phone":"+1 615 792 7714",
    "sg:postcode":"37015",
    "sg:province":"TN",
    "wof:name":"Community Progress Associ",
    "wof:placetype":"venue"
},
  "geometry": {"coordinates":[-87.06270499999999,36.279932],"type":"Point"}
}