{
  "type": "Feature",
  "properties": {
    "iso:country":"US",
    "sg:address":"103 Carriage Pl",
    "sg:city":"Hendersonville",
    "sg:classifiers":[
        {
            "category":"Professional",
            "type":"Services"
        }
    ],
    "sg:phone":"+1 615 824 4099",
    "sg:postcode":"37075",
    "sg:province":"TN",
    "wof:name":"Randy Steve Morton",
    "wof:placetype":"venue"
},
  "geometry": {"coordinates":[-86.610497,36.37498],"type":"Point"}
}