{
  "type": "Feature",
  "properties": {
    "iso:country":"US",
    "sg:address":"507 Main St",
    "sg:city":"Savannah",
    "sg:classifiers":[
        {
            "category":"Social Services",
            "type":"Services"
        }
    ],
    "sg:phone":"+1 731 925 8979",
    "sg:postcode":"38372",
    "sg:province":"TN",
    "sg:tags":[
        "organization",
        "welfare"
    ],
    "wof:name":"American Red Cross",
    "wof:placetype":"venue"
},
  "geometry": {"coordinates":[-88.25116199999999,35.225176],"type":"Point"}
}