{
  "type": "Feature",
  "properties": {
    "iso:country":"US",
    "sg:address":"11 Medical Park Ct",
    "sg:city":"Jackson",
    "sg:classifiers":[
        {
            "category":"Health Services",
            "subcategory":"Doctor",
            "type":"Services"
        }
    ],
    "sg:phone":"+1 731 668 0067",
    "sg:postcode":"38305",
    "sg:province":"TN",
    "wof:name":"Jack C Fisher DMD",
    "wof:placetype":"venue"
},
  "geometry": {"coordinates":[-88.85229699999999,35.685582],"type":"Point"}
}