{
  "type": "Feature",
  "properties": {
    "addr:full":"616 Hwy 76 White House TN 37188",
    "addr:housenumber":"616",
    "addr:postcode":"37188",
    "addr:street":"Hwy 76",
    "iso:country":"US",
    "sg:address":"616 Hwy 76",
    "sg:city":"White House",
    "sg:classifiers":[
        {
            "category":"Government",
            "subcategory":"Post Office",
            "type":"Public Place"
        }
    ],
    "sg:phone":"+1 615 672 3281",
    "sg:postcode":"37188",
    "sg:province":"TN",
    "sg:tags":[
        "postal",
        "us"
    ],
    "wof:name":"US Post Office",
    "wof:placetype":"venue"
},
  "geometry": {"coordinates":[-86.67076299999999,36.469471],"type":"Point"}
}