{
  "type": "Feature",
  "properties": {
    "iso:country":"US",
    "sg:address":"887 Kidwell Ridge Rd",
    "sg:city":"Morristown",
    "sg:classifiers":[
        {
            "category":"Food & Beverages",
            "subcategory":"Groceries & Convenience Stores",
            "type":"Retail Goods"
        }
    ],
    "sg:phone":"+1 423 581 4831",
    "sg:postcode":"37814",
    "sg:province":"TN",
    "sg:tags":[
        "grocer"
    ],
    "wof:name":"Kidwells Ridge Market",
    "wof:placetype":"venue"
},
  "geometry": {"coordinates":[-83.359759,36.203953],"type":"Point"}
}