{
  "type": "Feature",
  "properties": {
    "addr:full":"677 Mercer Dr Hermitage TN 37076",
    "addr:housenumber":"677",
    "addr:postcode":"37076",
    "addr:street":"Mercer Dr",
    "iso:country":"US",
    "sg:address":"677 Mercer Dr",
    "sg:city":"Hermitage",
    "sg:classifiers":[
        {
            "category":"Professional",
            "type":"Services"
        }
    ],
    "sg:phone":"+1 615 889 2401",
    "sg:postcode":"37076",
    "sg:province":"TN",
    "sg:tags":[
        "information",
        "bureau"
    ],
    "wof:name":"Hankster Publications",
    "wof:placetype":"venue"
},
  "geometry": {"coordinates":[-86.599906,36.198416],"type":"Point"}
}