{
  "type": "Feature",
  "properties": {
    "iso:country":"US",
    "sg:address":"906 Madison St",
    "sg:city":"Shelbyville",
    "sg:classifiers":[
        {
            "category":"Retail",
            "subcategory":"Car Wash",
            "type":"Services"
        }
    ],
    "sg:phone":"+1 931 684 7114",
    "sg:postcode":"37160",
    "sg:province":"TN",
    "sg:tags":[
        "carwash",
        "automotive",
        "repair"
    ],
    "wof:name":"Shock Wave Customs",
    "wof:placetype":"venue"
},
  "geometry": {"coordinates":[-86.441718,35.486783],"type":"Point"}
}