{
  "type": "Feature",
  "properties": {
    "iso:country":"US",
    "sg:address":"8577 Cordes Cir",
    "sg:city":"Germantown",
    "sg:classifiers":[
        {
            "category":"Wholesale",
            "subcategory":"Farm Supplies",
            "type":"Manufacturing & Wholesale Goods"
        }
    ],
    "sg:phone":"+1 901 753 0303",
    "sg:postcode":"38139",
    "sg:province":"TN",
    "wof:name":"Valent U S A Corporation",
    "wof:placetype":"venue"
},
  "geometry": {"coordinates":[-89.777824,35.096694],"type":"Point"}
}