{
  "type": "Feature",
  "properties": {
    "iso:country":"US",
    "sg:address":"1370 Middle Creek Rd",
    "sg:city":"Sevierville",
    "sg:classifiers":[
        {
            "category":"Retail",
            "subcategory":"Laundry & Dry Cleaning",
            "type":"Services"
        },
        {
            "category":"Retail",
            "subcategory":"Repair Shop",
            "type":"Services"
        },
        {
            "category":"Building & Trades",
            "subcategory":"Cleaning & Sanitation",
            "type":"Services"
        }
    ],
    "sg:phone":"+1 865 453 5624",
    "sg:postcode":"37862",
    "sg:province":"TN",
    "sg:tags":[
        "cleaner",
        "fabric",
        "damage",
        "rug",
        "water",
        "protection",
        "furniture",
        "steam",
        "restoration",
        "carpet"
    ],
    "sg:website":"http://www.hansensteamway.com",
    "wof:name":"Hansen Steamway Carpet & Upholstery Cleaning",
    "wof:placetype":"venue"
},
  "geometry": {"coordinates":[-83.545287,35.836543],"type":"Point"}
}