{
  "type": "Feature",
  "properties": {
    "addr:full":"250 Bakers Chapel Church Ln Big Sandy TN 38221",
    "addr:housenumber":"250;chapel",
    "addr:postcode":"38221",
    "addr:street":"Bakers;Church Ln",
    "iso:country":"US",
    "sg:address":"250 Bakers Chapel Church Ln",
    "sg:city":"Big Sandy",
    "sg:classifiers":[
        {
            "category":"Professional",
            "subcategory":"Business Services",
            "type":"Services"
        }
    ],
    "sg:phone":"+1 731 593 3856",
    "sg:postcode":"38221",
    "sg:province":"TN",
    "wof:name":"Gingerbread Country",
    "wof:placetype":"venue"
},
  "geometry": {"coordinates":[-88.118087,36.173191],"type":"Point"}
}