{
  "type": "Feature",
  "properties": {
    "iso:country":"US",
    "sg:address":"216 W Broadway",
    "sg:city":"Gallatin",
    "sg:classifiers":[
        {
            "category":"Home & Garden",
            "subcategory":"Furniture",
            "type":"Retail Goods"
        }
    ],
    "sg:phone":"+1 615 230 8305",
    "sg:postcode":"37066",
    "sg:province":"TN",
    "wof:name":"Gallatin Furniture LLC",
    "wof:placetype":"venue"
},
  "geometry": {"coordinates":[-86.451284,36.388487],"type":"Point"}
}