{
  "type": "Feature",
  "properties": {
    "addr:full":"600 Poplar Ave Memphis TN 38105",
    "addr:housenumber":"600",
    "addr:postcode":"38105",
    "addr:street":"Poplar Ave",
    "iso:country":"US",
    "sg:address":"600 Poplar Ave",
    "sg:city":"Memphis",
    "sg:classifiers":[
        {
            "category":"Health Services",
            "subcategory":"Hospital",
            "type":"Services"
        }
    ],
    "sg:phone":"+1 901 544 9389",
    "sg:postcode":"38105",
    "sg:province":"TN",
    "sg:tags":[
        "mental"
    ],
    "wof:name":"Whitehaven Mental Health Path",
    "wof:placetype":"venue"
},
  "geometry": {"coordinates":[-90.040504,35.147575],"type":"Point"}
}