{
  "type": "Feature",
  "properties": {
    "iso:country":"US",
    "sg:address":"10 Wiley Hollow Rd",
    "sg:city":"Fayetteville",
    "sg:classifiers":[
        {
            "category":"Organizations",
            "subcategory":"Religious Organization",
            "type":"Services"
        }
    ],
    "sg:phone":"+1 931 433 4379",
    "sg:postcode":"37334",
    "sg:province":"TN",
    "sg:tags":[
        "church"
    ],
    "wof:name":"Oak Hill Baptist Church",
    "wof:placetype":"venue"
},
  "geometry": {"coordinates":[-86.55879299999999,35.274349],"type":"Point"}
}