{
  "type": "Feature",
  "properties": {
    "addr:full":"2030 Mallory Ln Franklin TN 37067",
    "addr:housenumber":"2030",
    "addr:postcode":"37067",
    "addr:street":"Mallory Ln",
    "iso:country":"US",
    "sg:address":"2030 Mallory Ln",
    "sg:city":"Franklin",
    "sg:classifiers":[
        {
            "category":"Banks & Credit Unions",
            "subcategory":"Bank",
            "type":"Services"
        }
    ],
    "sg:phone":"+1 615 771 6062",
    "sg:postcode":"37067",
    "sg:province":"TN",
    "sg:tags":[
        "state",
        "commercial"
    ],
    "wof:name":"South Trust Bank",
    "wof:placetype":"venue"
},
  "geometry": {"coordinates":[-86.818468,35.950751],"type":"Point"}
}