{
  "type": "Feature",
  "properties": {
    "addr:full":"17 Allen Rd Pinson TN 38366",
    "addr:housenumber":"17",
    "addr:postcode":"38366",
    "addr:street":"Allen Rd",
    "iso:country":"US",
    "sg:address":"17 Allen Rd",
    "sg:city":"Pinson",
    "sg:classifiers":[
        {
            "category":"Real Estate",
            "subcategory":"Real Estate Operator",
            "type":"Services"
        }
    ],
    "sg:phone":"+1 731 234 3436",
    "sg:postcode":"38366",
    "sg:province":"TN",
    "sg:tags":[
        "building",
        "nonresidential"
    ],
    "wof:name":"Russell Properties",
    "wof:placetype":"venue"
},
  "geometry": {"coordinates":[-88.68914700000001,35.530379],"type":"Point"}
}