{
  "type": "Feature",
  "properties": {
    "addr:full":"2270 Carrollwood Ln Cordova TN 38016",
    "addr:postcode":"2270;38016",
    "addr:street":"Carrollwood Ln",
    "iso:country":"US",
    "sg:address":"2270 Carrollwood Ln",
    "sg:city":"Cordova",
    "sg:classifiers":[
        {
            "category":"Banks & Credit Unions",
            "subcategory":"Bank",
            "type":"Services"
        }
    ],
    "sg:phone":"+1 901 373 1940",
    "sg:postcode":"38016",
    "sg:province":"TN",
    "sg:tags":[
        "financing"
    ],
    "wof:name":"Transamerica Distribution",
    "wof:placetype":"venue"
},
  "geometry": {"coordinates":[-89.772976,35.187268],"type":"Point"}
}