{
  "type": "Feature",
  "properties": {
    "iso:country":"US",
    "sg:address":"940 US Hwy 11",
    "sg:city":"Sweetwater",
    "sg:classifiers":[
        {
            "category":"Organizations",
            "subcategory":"Religious Organization",
            "type":"Services"
        }
    ],
    "sg:phone":"+1 423 337 6037",
    "sg:postcode":"37874",
    "sg:province":"TN",
    "sg:tags":[
        "church"
    ],
    "sg:website":"www.sweetwaterfirstassembly.org",
    "wof:name":"First Assembly Of God",
    "wof:placetype":"venue"
},
  "geometry": {"coordinates":[-84.460883,35.606098],"type":"Point"}
}