{
  "type": "Feature",
  "properties": {
    "iso:country":"US",
    "sg:address":"1221 S Willow Ave",
    "sg:city":"Cookeville",
    "sg:classifiers":[
        {
            "category":"Government",
            "subcategory":"Office",
            "type":"Public Place"
        }
    ],
    "sg:phone":"+1 931 432 4048",
    "sg:postcode":"38506",
    "sg:province":"TN",
    "sg:tags":[
        "education",
        "center"
    ],
    "wof:name":"Cookeville Education Center",
    "wof:placetype":"venue"
},
  "geometry": {"coordinates":[-85.533773,36.129385],"type":"Point"}
}