{
  "type": "Feature",
  "properties": {
    "addr:full":"816 Main St Savannah TN 38372",
    "addr:housenumber":"816",
    "addr:postcode":"38372",
    "addr:street":"Main St",
    "iso:country":"US",
    "sg:address":"816 Main St",
    "sg:city":"Savannah",
    "sg:classifiers":[
        {
            "category":"Health Services",
            "subcategory":"Doctor",
            "type":"Services"
        }
    ],
    "sg:phone":"+1 731 925 9909",
    "sg:postcode":"38372",
    "sg:province":"TN",
    "sg:tags":[
        "physician",
        "surgeon"
    ],
    "wof:name":"Savannah Bone & Joint Spec",
    "wof:placetype":"venue"
},
  "geometry": {"coordinates":[-88.24884900000001,35.224935],"type":"Point"}
}