{
  "type": "Feature",
  "properties": {
    "iso:country":"US",
    "sg:address":"508 Shawnee Ave",
    "sg:city":"Memphis",
    "sg:classifiers":[
        {
            "category":"Shopping",
            "subcategory":"Books",
            "type":"Retail Goods"
        }
    ],
    "sg:phone":"+1 901 948 6153",
    "sg:postcode":"38106",
    "sg:province":"TN",
    "sg:tags":[
        "store"
    ],
    "wof:name":"21st Century Book Store",
    "wof:placetype":"venue"
},
  "geometry": {"coordinates":[-90.04621299999999,35.09776],"type":"Point"}
}