{
  "type": "Feature",
  "properties": {
    "iso:country":"US",
    "sg:address":"313 Brakebill Rd",
    "sg:city":"Knoxville",
    "sg:classifiers":[
        {
            "category":"Building & Trades",
            "subcategory":"Construction",
            "type":"Services"
        }
    ],
    "sg:phone":"+1 865 933 7611",
    "sg:postcode":"37924",
    "sg:province":"TN",
    "sg:tags":[
        "house"
    ],
    "wof:name":"Olympia Construction Inc",
    "wof:placetype":"venue"
},
  "geometry": {"coordinates":[-83.776028,36.018487],"type":"Point"}
}