{
  "type": "Feature",
  "properties": {
    "iso:country":"US",
    "sg:address":"3680 Lamar Ave",
    "sg:city":"Memphis",
    "sg:classifiers":[
        {
            "category":"Restaurant",
            "type":"Food & Drink"
        }
    ],
    "sg:menulink":"http://www.allmenus.com/tn/memphis/162958-rallys/menu/",
    "sg:phone":"+1 901 542 9120",
    "sg:postcode":"38118",
    "sg:province":"TN",
    "sg:tags":[
        "sandwich",
        "dog",
        "burger",
        "hot",
        "wrap",
        "american"
    ],
    "wof:name":"Rally's",
    "wof:placetype":"venue"
},
  "geometry": {"coordinates":[-89.94052000000001,35.064676],"type":"Point"}
}