{
  "type": "Feature",
  "properties": {
    "iso:country":"US",
    "sg:address":"604 E Thompkins Ln",
    "sg:city":"Clarksville",
    "sg:classifiers":[
        {
            "category":"Organizations",
            "subcategory":"Religious Organization",
            "type":"Services"
        }
    ],
    "sg:phone":"+1 931 647 2776",
    "sg:postcode":"37043",
    "sg:province":"TN",
    "sg:tags":[
        "church"
    ],
    "wof:name":"Edgefield Baptist Church",
    "wof:placetype":"venue"
},
  "geometry": {"coordinates":[-87.32886000000001,36.508594],"type":"Point"}
}