{
  "type": "Feature",
  "properties": {
    "iso:country":"US",
    "sg:address":"1566 Stribling St",
    "sg:city":"Memphis",
    "sg:classifiers":[
        {
            "category":"Real Estate",
            "subcategory":"Real Estate Operator",
            "type":"Services"
        }
    ],
    "sg:phone":"+1 901 744 7361",
    "sg:postcode":"38111",
    "sg:province":"TN",
    "sg:tags":[
        "apartment"
    ],
    "wof:name":"Forest Pine Apts",
    "wof:placetype":"venue"
},
  "geometry": {"coordinates":[-89.932351,35.088756],"type":"Point"}
}