{
  "type": "Feature",
  "properties": {
    "addr:full":"132 Hospital Dr Mc Kenzie TN 38201",
    "addr:housenumber":"132",
    "addr:postcode":"38201",
    "addr:street":"Hospital Dr",
    "iso:country":"US",
    "sg:address":"132 Hospital Dr",
    "sg:city":"Mc Kenzie",
    "sg:classifiers":[
        {
            "category":"Health Services",
            "subcategory":"Doctor",
            "type":"Services"
        }
    ],
    "sg:phone":"+1 731 352 7435",
    "sg:postcode":"38201",
    "sg:province":"TN",
    "sg:tags":[
        "physician",
        "surgeon"
    ],
    "wof:name":"Jackson Clinic Of Mc Kenzie",
    "wof:placetype":"venue"
},
  "geometry": {"coordinates":[-88.490382,36.136867],"type":"Point"}
}