{
  "type": "Feature",
  "properties": {
    "iso:country":"US",
    "sg:address":"1106 S Water Ave",
    "sg:city":"Gallatin",
    "sg:classifiers":[
        {
            "category":"Professional",
            "subcategory":"Business Services",
            "type":"Services"
        }
    ],
    "sg:phone":"+1 615 826 7539",
    "sg:postcode":"37066",
    "sg:province":"TN",
    "sg:tags":[
        "appraiser"
    ],
    "wof:name":"James Abernathy & Co",
    "wof:placetype":"venue"
},
  "geometry": {"coordinates":[-86.440828,36.369235],"type":"Point"}
}