{
  "type": "Feature",
  "properties": {
    "iso:country":"US",
    "sg:address":"40 W Spring St",
    "sg:city":"Cookeville",
    "sg:classifiers":[
        {
            "category":"Manufacturing",
            "subcategory":"Building Materials",
            "type":"Manufacturing & Wholesale Goods"
        },
        {
            "category":"Home & Garden",
            "subcategory":"Furniture",
            "type":"Retail Goods"
        }
    ],
    "sg:phone":"+1 931 528 8066",
    "sg:postcode":"38501",
    "sg:province":"TN",
    "sg:tags":[
        "cabinet",
        "wood",
        "kitchen",
        "mfg"
    ],
    "wof:name":"R & R Cabinet Shop",
    "wof:placetype":"venue"
},
  "geometry": {"coordinates":[-85.507435,36.161713],"type":"Point"}
}