{
  "type": "Feature",
  "properties": {
    "addr:full":"2988 Park Ave Memphis TN 38114",
    "addr:housenumber":"2988",
    "addr:postcode":"38114",
    "addr:street":"Park Ave",
    "iso:country":"US",
    "sg:address":"2988 Park Ave",
    "sg:city":"Memphis",
    "sg:classifiers":[
        {
            "category":"Social Services",
            "subcategory":"Child Care",
            "type":"Services"
        }
    ],
    "sg:phone":"+1 901 324 8282",
    "sg:postcode":"38114",
    "sg:province":"TN",
    "sg:tags":[
        "day"
    ],
    "wof:name":"Supreme Learning Center",
    "wof:placetype":"venue"
},
  "geometry": {"coordinates":[-89.963447,35.107963],"type":"Point"}
}