{
  "type": "Feature",
  "properties": {
    "iso:country":"US",
    "sg:address":"313 S Concord St",
    "sg:city":"Knoxville",
    "sg:classifiers":[
        {
            "category":"Health Services",
            "subcategory":"Doctor",
            "type":"Services"
        }
    ],
    "sg:phone":"+1 865 522 5173",
    "sg:postcode":"37919",
    "sg:province":"TN",
    "sg:tags":[
        "clinic"
    ],
    "sg:website":"www.volunteermedical.com",
    "wof:name":"Volunteer Women's Med Clinic",
    "wof:placetype":"venue"
},
  "geometry": {"coordinates":[-83.949828,35.955787],"type":"Point"}
}