{
  "type": "Feature",
  "properties": {
    "iso:country":"US",
    "sg:address":"3405 Chapman Hwy",
    "sg:city":"Knoxville",
    "sg:classifiers":[
        {
            "category":"Insurance",
            "subcategory":"Insurance Agent",
            "type":"Services"
        }
    ],
    "sg:phone":"+1 865 577 0202",
    "sg:postcode":"37920",
    "sg:province":"TN",
    "wof:name":"Acceptance Insurance Agency",
    "wof:placetype":"venue"
},
  "geometry": {"coordinates":[-83.91083,35.942239],"type":"Point"}
}