{
  "type": "Feature",
  "properties": {
    "addr:full":"10513 Kingston Pike Knoxville TN 37922",
    "addr:housenumber":"10513",
    "addr:postcode":"37922",
    "addr:street":"Kingston Pike",
    "iso:country":"US",
    "sg:address":"10513 Kingston Pike",
    "sg:city":"Knoxville",
    "sg:classifiers":[
        {
            "category":"Home & Garden",
            "subcategory":"Furniture",
            "type":"Retail Goods"
        }
    ],
    "sg:phone":"+1 865 670 1101",
    "sg:postcode":"37922",
    "sg:province":"TN",
    "wof:name":"BILL COX FURNITURE",
    "wof:placetype":"venue"
},
  "geometry": {"coordinates":[-84.129845,35.898087],"type":"Point"}
}