{
  "type": "Feature",
  "properties": {
    "iso:country":"US",
    "sg:address":"126 Morningside Dr",
    "sg:city":"Soddy Daisy",
    "sg:classifiers":[
        {
            "category":"Personal",
            "type":"Services"
        }
    ],
    "sg:phone":"+1 423 332 3576",
    "sg:postcode":"37379",
    "sg:province":"TN",
    "wof:name":"Carl S Handiman Service",
    "wof:placetype":"venue"
},
  "geometry": {"coordinates":[-85.21346,35.226442],"type":"Point"}
}