{
  "type": "Feature",
  "properties": {
    "addr:full":"112 E Washington St Paris TN 38242",
    "addr:housenumber":"112",
    "addr:postcode":"38242",
    "addr:street":"E Washington St",
    "iso:country":"US",
    "sg:address":"112 E Washington St",
    "sg:city":"Paris",
    "sg:classifiers":[
        {
            "category":"Shopping",
            "subcategory":"Gifts & Souvenirs",
            "type":"Retail Goods"
        }
    ],
    "sg:phone":"+1 731 642 1956",
    "sg:postcode":"38242",
    "sg:province":"TN",
    "sg:tags":[
        "basket",
        "shop"
    ],
    "wof:name":"Najie's Gifts 'n Baskets",
    "wof:placetype":"venue"
},
  "geometry": {"coordinates":[-88.32520700000001,36.302807],"type":"Point"}
}