{
  "type": "Feature",
  "properties": {
    "iso:country":"US",
    "sg:address":"5000 Western Ave",
    "sg:city":"Knoxville",
    "sg:classifiers":[
        {
            "category":"Professional",
            "type":"Services"
        }
    ],
    "sg:phone":"+1 865 909 0236",
    "sg:postcode":"37921",
    "sg:province":"TN",
    "wof:name":"Dan Cragan Music Services",
    "wof:placetype":"venue"
},
  "geometry": {"coordinates":[-84.004475,35.97531],"type":"Point"}
}