{
  "type": "Feature",
  "properties": {
    "iso:country":"US",
    "sg:address":"7193 US Hwy 64",
    "sg:city":"Bartlett",
    "sg:classifiers":[
        {
            "category":"Sports & Exercise",
            "subcategory":"Gym",
            "type":"Entertainment"
        }
    ],
    "sg:phone":"+1 901 213 0933",
    "sg:postcode":"38133",
    "sg:province":"TN",
    "sg:tags":[
        "club",
        "health",
        "studio",
        "gymnasium"
    ],
    "wof:name":"Midsouth KRAV-Maga",
    "wof:placetype":"venue"
},
  "geometry": {"coordinates":[-89.82282600000001,35.203912],"type":"Point"}
}