{
  "type": "Feature",
  "properties": {
    "addr:full":"446 Old Hwy 46 S Dickson TN 37055",
    "addr:housenumber":"446",
    "addr:postcode":"37055",
    "addr:street":"Old Hwy 46 S",
    "iso:country":"US",
    "sg:address":"446 Old Hwy 46 S",
    "sg:city":"Dickson",
    "sg:classifiers":[
        {
            "category":"Social Services",
            "type":"Services"
        }
    ],
    "sg:phone":"+1 615 446 0229",
    "sg:postcode":"37055",
    "sg:province":"TN",
    "wof:name":"Workforce Essentials Inc",
    "wof:placetype":"venue"
},
  "geometry": {"coordinates":[-87.332869,36.009037],"type":"Point"}
}