{
  "type": "Feature",
  "properties": {
    "addr:full":"513 Patterson St Nashville TN 37211",
    "addr:housenumber":"513",
    "addr:postcode":"37211",
    "addr:street":"Patterson St",
    "iso:country":"US",
    "sg:address":"513 Patterson St",
    "sg:city":"Nashville",
    "sg:classifiers":[
        {
            "category":"Building & Trades",
            "subcategory":"Construction",
            "type":"Services"
        }
    ],
    "sg:phone":"+1 615 834 5414",
    "sg:postcode":"37211",
    "sg:province":"TN",
    "sg:tags":[
        "resurfacing",
        "laying",
        "refinishing",
        "floor"
    ],
    "wof:name":"Petty Flooring",
    "wof:placetype":"venue"
},
  "geometry": {"coordinates":[-86.746869,36.103101],"type":"Point"}
}