{
  "type": "Feature",
  "properties": {
    "iso:country":"US",
    "sg:address":"224 Highland Villa Cir",
    "sg:city":"Nashville",
    "sg:classifiers":[
        {
            "category":"Building & Trades",
            "subcategory":"Construction",
            "type":"Services"
        }
    ],
    "sg:phone":"+1 615 503 9727",
    "sg:postcode":"37211",
    "sg:province":"TN",
    "sg:tags":[
        "home",
        "builder"
    ],
    "wof:name":"Mike Ford Custom Builders",
    "wof:placetype":"venue"
},
  "geometry": {"coordinates":[-86.73955100000001,36.041548],"type":"Point"}
}