{
  "type": "Feature",
  "properties": {
    "iso:country":"US",
    "sg:address":"1907 Eastland Ave",
    "sg:city":"Nashville",
    "sg:classifiers":[
        {
            "category":"Restaurant",
            "type":"Food & Drink"
        }
    ],
    "sg:phone":"+1 615 262 2994",
    "sg:postcode":"37206",
    "sg:province":"TN",
    "sg:tags":[
        "eating"
    ],
    "wof:name":"Joes Diner",
    "wof:placetype":"venue"
},
  "geometry": {"coordinates":[-86.73390499999999,36.182567],"type":"Point"}
}