{
  "type": "Feature",
  "properties": {
    "addr:full":"313 S Lindell St Martin TN 38237",
    "addr:housenumber":"313",
    "addr:postcode":"38237",
    "addr:street":"S Lindell St",
    "iso:country":"US",
    "sg:address":"313 S Lindell St",
    "sg:city":"Martin",
    "sg:classifiers":[
        {
            "category":"Shopping",
            "subcategory":"Florist",
            "type":"Retail Goods"
        }
    ],
    "sg:phone":"+1 731 587 6775",
    "sg:postcode":"38237",
    "sg:province":"TN",
    "wof:name":"Four Seasons Florist",
    "wof:placetype":"venue"
},
  "geometry": {"coordinates":[-88.850542,36.343216],"type":"Point"}
}