{
  "type": "Feature",
  "properties": {
    "addr:full":"1063 Bunker Hill Rd Cookeville TN 38501",
    "addr:housenumber":"1063",
    "addr:postcode":"38501",
    "addr:street":"Bunker Hill Rd",
    "iso:country":"US",
    "sg:address":"1063 Bunker Hill Rd",
    "sg:city":"Cookeville",
    "sg:classifiers":[
        {
            "category":"Restaurant",
            "type":"Food & Drink"
        }
    ],
    "sg:menulink":"http://www.allmenus.com/tn/cookeville/121556-fazolis/menu/",
    "sg:phone":"+1 931 528 5500",
    "sg:postcode":"38501",
    "sg:province":"TN",
    "sg:tags":[
        "italian"
    ],
    "wof:name":"Fazoli's",
    "wof:placetype":"venue"
},
  "geometry": {"coordinates":[-85.502608,36.153877],"type":"Point"}
}