{
  "type": "Feature",
  "properties": {
    "iso:country":"US",
    "sg:address":"113 Sanders Ferry Rd",
    "sg:city":"Hendersonville",
    "sg:classifiers":[
        {
            "category":"Shopping",
            "subcategory":"Gifts & Souvenirs",
            "type":"Retail Goods"
        }
    ],
    "sg:phone":"+1 615 338 4900",
    "sg:postcode":"37075",
    "sg:province":"TN",
    "sg:tags":[
        "shop"
    ],
    "wof:name":"Ole Waterfront Shoppe",
    "wof:placetype":"venue"
},
  "geometry": {"coordinates":[-86.615094,36.301286],"type":"Point"}
}