{
  "type": "Feature",
  "properties": {
    "addr:full":"135 W Jackson St Cookeville TN 38501",
    "addr:housenumber":"135",
    "addr:postcode":"38501",
    "addr:street":"W Jackson St",
    "iso:country":"US",
    "sg:address":"135 W Jackson St",
    "sg:city":"Cookeville",
    "sg:classifiers":[
        {
            "category":"Health Services",
            "subcategory":"Doctor",
            "type":"Services"
        }
    ],
    "sg:phone":"+1 931 528 6758",
    "sg:postcode":"38501",
    "sg:province":"TN",
    "sg:tags":[
        "osteopathic"
    ],
    "wof:name":"Dr Rosanne Ellis Chiropractor",
    "wof:placetype":"venue"
},
  "geometry": {"coordinates":[-85.51039,36.154342],"type":"Point"}
}