{
  "type": "Feature",
  "properties": {
    "addr:full":"2624 Teaster Ln Pigeon Forge TN 37863",
    "addr:housenumber":"2624",
    "addr:postcode":"37863",
    "addr:street":"Teaster Ln",
    "iso:country":"US",
    "sg:address":"2624 Teaster Ln",
    "sg:city":"Pigeon Forge",
    "sg:classifiers":[
        {
            "category":"Shopping",
            "subcategory":"Shoes",
            "type":"Retail Goods"
        }
    ],
    "sg:phone":"+1 865 453 0025",
    "sg:postcode":"37863",
    "sg:province":"TN",
    "sg:website":"www.rackroomshoes.com",
    "wof:name":"Rack Room Shoes Inc",
    "wof:placetype":"venue"
},
  "geometry": {"coordinates":[-83.55511,35.794541],"type":"Point"}
}