{
  "type": "Feature",
  "properties": {
    "iso:country":"US",
    "sg:address":"810 Crown Point Rd W",
    "sg:city":"Signal Mountain",
    "sg:classifiers":[
        {
            "category":"Arts & Performance",
            "subcategory":"Theater",
            "type":"Entertainment"
        }
    ],
    "sg:phone":"+1 423 886 2747",
    "sg:postcode":"37377",
    "sg:province":"TN",
    "sg:tags":[
        "group"
    ],
    "wof:name":"Glenn Draper Company",
    "wof:placetype":"venue"
},
  "geometry": {"coordinates":[-85.34450099999999,35.136367],"type":"Point"}
}