{
  "type": "Feature",
  "properties": {
    "iso:country":"US",
    "sg:address":"241 Forrest Ave",
    "sg:city":"Hohenwald",
    "sg:classifiers":[
        {
            "category":"Building & Trades",
            "subcategory":"Construction",
            "type":"Services"
        }
    ],
    "sg:phone":"+1 931 796 2006",
    "sg:postcode":"38462",
    "sg:province":"TN",
    "sg:tags":[
        "coating",
        "painter",
        "sandblasting",
        "painting",
        "special"
    ],
    "wof:name":"Mid South Painting Inc",
    "wof:placetype":"venue"
},
  "geometry": {"coordinates":[-87.55541599999999,35.556644],"type":"Point"}
}