{
  "type": "Feature",
  "properties": {
    "iso:country":"US",
    "sg:address":"1001 N Locust Ave",
    "sg:city":"Lawrenceburg",
    "sg:classifiers":[
        {
            "category":"Food & Beverages",
            "subcategory":"Groceries & Convenience Stores",
            "type":"Retail Goods"
        }
    ],
    "sg:phone":"+1 931 762 8206",
    "sg:postcode":"38464",
    "sg:province":"TN",
    "sg:tags":[
        "gasoline"
    ],
    "wof:name":"Mapco Express 1015",
    "wof:placetype":"venue"
},
  "geometry": {"coordinates":[-87.32650599999999,35.251335],"type":"Point"}
}