{
  "type": "Feature",
  "properties": {
    "addr:full":"6552 Winchester Rd Memphis TN 38115",
    "addr:housenumber":"6552",
    "addr:postcode":"38115",
    "addr:street":"Winchester Rd",
    "iso:country":"US",
    "sg:address":"6552 Winchester Rd",
    "sg:city":"Memphis",
    "sg:classifiers":[
        {
            "category":"Retail",
            "subcategory":"Laundry & Dry Cleaning",
            "type":"Services"
        }
    ],
    "sg:phone":"+1 901 362 9156",
    "sg:postcode":"38115",
    "sg:province":"TN",
    "sg:tags":[
        "drycleaning",
        "plant"
    ],
    "wof:name":"Sparkle Cleaners",
    "wof:placetype":"venue"
},
  "geometry": {"coordinates":[-89.845178,35.049611],"type":"Point"}
}