{
  "type": "Feature",
  "properties": {
    "addr:full":"1536 National St Memphis TN 38122",
    "addr:housenumber":"1536",
    "addr:postcode":"38122",
    "addr:street":"National St",
    "iso:country":"US",
    "sg:address":"1536 National St",
    "sg:city":"Memphis",
    "sg:classifiers":[
        {
            "category":"Building & Trades",
            "subcategory":"Construction",
            "type":"Services"
        }
    ],
    "sg:phone":"+1 901 323 6552",
    "sg:postcode":"38122",
    "sg:province":"TN",
    "sg:tags":[
        "tile",
        "dealer"
    ],
    "wof:name":"J T Hill Tile Co",
    "wof:placetype":"venue"
},
  "geometry": {"coordinates":[-89.941529,35.173297],"type":"Point"}
}