{
  "type": "Feature",
  "properties": {
    "iso:country":"US",
    "sg:address":"2970 Hwy 11 E",
    "sg:city":"Bluff City",
    "sg:classifiers":[
        {
            "category":"Autos & Motor Vehicles",
            "subcategory":"Automobile Sales",
            "type":"Retail Goods"
        }
    ],
    "sg:phone":"+1 423 391 0422",
    "sg:postcode":"37618",
    "sg:province":"TN",
    "sg:tags":[
        "car",
        "dealer"
    ],
    "wof:name":"Bales Auto Sales",
    "wof:placetype":"venue"
},
  "geometry": {"coordinates":[-82.262353,36.513314],"type":"Point"}
}