{
  "type": "Feature",
  "properties": {
    "addr:full":"116 Cripple Creek Loop Watauga TN 37694",
    "addr:housenumber":"116",
    "addr:postcode":"37694",
    "addr:street":"Cripple Creek Loop",
    "iso:country":"US",
    "sg:address":"116 Cripple Creek Loop",
    "sg:city":"Watauga",
    "sg:classifiers":[
        {
            "category":"Building & Trades",
            "subcategory":"Construction",
            "type":"Services"
        }
    ],
    "sg:phone":"+1 423 542 8888",
    "sg:postcode":"37694",
    "sg:province":"TN",
    "sg:tags":[
        "concrete",
        "cutting",
        "breaking",
        "sawing"
    ],
    "sg:website":"www.concretecuttingsystems.com",
    "wof:name":"Concrete Cutting Systems Inc",
    "wof:placetype":"venue"
},
  "geometry": {"coordinates":[-82.257986,36.379201],"type":"Point"}
}