{
  "type": "Feature",
  "properties": {
    "iso:country":"US",
    "sg:address":"644 Piney Flats Rd",
    "sg:city":"Piney Flats",
    "sg:classifiers":[
        {
            "category":"Building & Trades",
            "subcategory":"Construction",
            "type":"Services"
        }
    ],
    "sg:phone":"+1 423 538 3254",
    "sg:postcode":"37694",
    "sg:province":"TN",
    "sg:tags":[
        "downspouts",
        "gutter"
    ],
    "wof:name":"Exterior Works Unlimited",
    "wof:placetype":"venue"
},
  "geometry": {"coordinates":[-82.302754,36.417092],"type":"Point"}
}