{
  "type": "Feature",
  "properties": {
    "iso:country":"US",
    "sg:address":"2793 Lola Ave",
    "sg:city":"Memphis",
    "sg:classifiers":[
        {
            "category":"Professional",
            "type":"Services"
        }
    ],
    "sg:phone":"+1 901 743 7323",
    "sg:postcode":"38114",
    "sg:province":"TN",
    "wof:name":"Rnr",
    "wof:placetype":"venue"
},
  "geometry": {"coordinates":[-89.970811,35.08304],"type":"Point"}
}