{
  "type": "Feature",
  "properties": {
    "iso:country":"US",
    "sg:address":"686 N 2nd St",
    "sg:city":"Memphis",
    "sg:classifiers":[
        {
            "category":"Food & Beverages",
            "subcategory":"Liquor & Beverages",
            "type":"Retail Goods"
        }
    ],
    "sg:phone":"+1 901 525 1909",
    "sg:postcode":"38107",
    "sg:province":"TN",
    "sg:tags":[
        "alcoholic"
    ],
    "wof:name":"Pyramid Liquors",
    "wof:placetype":"venue"
},
  "geometry": {"coordinates":[-90.043988,35.163728],"type":"Point"}
}