{
  "type": "Feature",
  "properties": {
    "addr:full":"48 S Mclean Blvd Memphis TN 38104",
    "addr:housenumber":"48",
    "addr:postcode":"38104",
    "addr:street":"S Mclean Blvd",
    "iso:country":"US",
    "sg:address":"48 S Mclean Blvd",
    "sg:city":"Memphis",
    "sg:classifiers":[
        {
            "category":"Home & Garden",
            "subcategory":"Home Furnishings",
            "type":"Retail Goods"
        },
        {
            "category":"Home & Garden",
            "subcategory":"Furniture",
            "type":"Retail Goods"
        }
    ],
    "sg:phone":"+1 901 278 2259",
    "sg:postcode":"38104",
    "sg:province":"TN",
    "sg:tags":[
        "decor",
        "store"
    ],
    "wof:name":"Cosmic Closet",
    "wof:placetype":"venue"
},
  "geometry": {"coordinates":[-89.999933,35.136084],"type":"Point"}
}