{
  "type": "Feature",
  "properties": {
    "addr:full":"414 Neill Ave Nashville TN 37206",
    "addr:housenumber":"414",
    "addr:postcode":"37206",
    "addr:street":"Neill Ave",
    "iso:country":"US",
    "sg:address":"414 Neill Ave",
    "sg:city":"Nashville",
    "sg:classifiers":[
        {
            "category":"Real Estate",
            "subcategory":"Real Estate Operator",
            "type":"Services"
        }
    ],
    "sg:phone":"+1 615 226 0374",
    "sg:postcode":"37206",
    "sg:province":"TN",
    "sg:tags":[
        "building",
        "apartment"
    ],
    "wof:name":"Marina Manor East",
    "wof:placetype":"venue"
},
  "geometry": {"coordinates":[-86.75981899999999,36.179453],"type":"Point"}
}