{
  "type": "Feature",
  "properties": {
    "iso:country":"US",
    "sg:address":"3361 Sheila Cir",
    "sg:city":"White Pine",
    "sg:classifiers":[
        {
            "category":"Building & Trades",
            "subcategory":"Construction",
            "type":"Services"
        }
    ],
    "sg:phone":"+1 865 674 7581",
    "sg:postcode":"37890",
    "sg:province":"TN",
    "sg:tags":[
        "designer",
        "dealer",
        "pool",
        "swimming"
    ],
    "wof:name":"Paradise Pools",
    "wof:placetype":"venue"
},
  "geometry": {"coordinates":[-83.285011,36.1022],"type":"Point"}
}