{
  "type": "Feature",
  "properties": {
    "iso:country":"US",
    "sg:address":"3450 Eastend Dr",
    "sg:city":"Humboldt",
    "sg:classifiers":[
        {
            "category":"Autos & Motor Vehicles",
            "subcategory":"Automobile Sales",
            "type":"Retail Goods"
        }
    ],
    "sg:phone":"+1 731 784 2560",
    "sg:postcode":"38343",
    "sg:province":"TN",
    "sg:tags":[
        "car",
        "dealer"
    ],
    "wof:name":"Hawk's Used Cars",
    "wof:placetype":"venue"
},
  "geometry": {"coordinates":[-88.89214,35.8378],"type":"Point"}
}