{
  "type": "Feature",
  "properties": {
    "iso:country":"US",
    "sg:address":"264 Berry St NE",
    "sg:city":"Cleveland",
    "sg:classifiers":[
        {
            "category":"Social Services",
            "subcategory":"Child Care",
            "type":"Services"
        }
    ],
    "sg:phone":"+1 423 479 6370",
    "sg:postcode":"37311",
    "sg:province":"TN",
    "sg:tags":[
        "day"
    ],
    "wof:name":"City Cleveland Recreation Ctr",
    "wof:placetype":"venue"
},
  "geometry": {"coordinates":[-84.86559699999999,35.156892],"type":"Point"}
}