{
  "type": "Feature",
  "properties": {
    "iso:country":"US",
    "sg:address":"51 Old Jones Rd",
    "sg:city":"Munford",
    "sg:classifiers":[
        {
            "category":"Museum",
            "type":"Entertainment"
        }
    ],
    "sg:phone":"+1 901 840 2483",
    "sg:postcode":"38024",
    "sg:province":"TN",
    "sg:tags":[
        "organization",
        "arts",
        "information"
    ],
    "wof:name":"Masters & Numbered Accents",
    "wof:placetype":"venue"
},
  "geometry": {"coordinates":[-89.308564,36.089175],"type":"Point"}
}