{
  "type": "Feature",
  "properties": {
    "addr:full":"103 Hazelwood Dr Smyrna TN 37167",
    "addr:housenumber":"103",
    "addr:postcode":"37167",
    "addr:street":"Hazelwood Dr",
    "iso:country":"US",
    "sg:address":"103 Hazelwood Dr",
    "sg:city":"Smyrna",
    "sg:classifiers":[
        {
            "category":"Wholesale",
            "subcategory":"Farm Supplies",
            "type":"Manufacturing & Wholesale Goods"
        }
    ],
    "sg:phone":"+1 615 459 2691",
    "sg:postcode":"37167",
    "sg:province":"TN",
    "sg:tags":[
        "feed"
    ],
    "wof:name":"Smyrna Feed & Supplies",
    "wof:placetype":"venue"
},
  "geometry": {"coordinates":[-86.51776700000001,35.979694],"type":"Point"}
}