{
  "type": "Feature",
  "properties": {
    "iso:country":"US",
    "sg:address":"4900 Poplar Ave",
    "sg:city":"Memphis",
    "sg:classifiers":[
        {
            "category":"Retail",
            "subcategory":"Repair Shop",
            "type":"Services"
        }
    ],
    "sg:phone":"+1 901 761 4343",
    "sg:postcode":"38117",
    "sg:province":"TN",
    "wof:name":"Clock Shop The",
    "wof:placetype":"venue"
},
  "geometry": {"coordinates":[-89.89783799999999,35.113674],"type":"Point"}
}