{
  "type": "Feature",
  "properties": {
    "iso:country":"US",
    "sg:address":"4000 N Watkins St",
    "sg:city":"Memphis",
    "sg:classifiers":[
        {
            "category":"Building & Trades",
            "subcategory":"Construction",
            "type":"Services"
        }
    ],
    "sg:phone":"+1 901 345 6333",
    "sg:postcode":"38127",
    "sg:province":"TN",
    "sg:tags":[
        "consulting",
        "refuse",
        "business",
        "contractor"
    ],
    "sg:website":"www.hepaco.com",
    "wof:name":"Hepaco Inc",
    "wof:placetype":"venue"
},
  "geometry": {"coordinates":[-90.010198,35.234037],"type":"Point"}
}