{
  "type": "Feature",
  "properties": {
    "addr:full":"501 High St Sevierville TN 37862",
    "addr:housenumber":"501",
    "addr:postcode":"37862",
    "addr:street":"High St",
    "iso:country":"US",
    "sg:address":"501 High St",
    "sg:city":"Sevierville",
    "sg:classifiers":[
        {
            "category":"Organizations",
            "subcategory":"Religious Organization",
            "type":"Services"
        }
    ],
    "sg:phone":"+1 865 453 6675",
    "sg:postcode":"37862",
    "sg:province":"TN",
    "wof:name":"Fellowship Baptist Church",
    "wof:placetype":"venue"
},
  "geometry": {"coordinates":[-83.558932,35.863172],"type":"Point"}
}