{
  "type": "Feature",
  "properties": {
    "iso:country":"US",
    "sg:address":"218 S 3rd St",
    "sg:city":"Clarksville",
    "sg:classifiers":[
        {
            "category":"Professional",
            "subcategory":"Lawyer & Legal Services",
            "type":"Services"
        }
    ],
    "sg:phone":"+1 931 645 9478",
    "sg:postcode":"37040",
    "sg:province":"TN",
    "sg:tags":[
        "attorney"
    ],
    "wof:name":"Patricia Rust",
    "wof:placetype":"venue"
},
  "geometry": {"coordinates":[-87.35718300000001,36.525591],"type":"Point"}
}