{
  "type": "Feature",
  "properties": {
    "iso:country":"US",
    "sg:address":"2700 S Roan St",
    "sg:city":"Johnson City",
    "sg:classifiers":[
        {
            "category":"Health Services",
            "subcategory":"Health Practitioner",
            "type":"Services"
        }
    ],
    "sg:phone":"+1 423 926 4357",
    "sg:postcode":"37601",
    "sg:province":"TN",
    "sg:tags":[
        "psychologist"
    ],
    "wof:name":"Womancare",
    "wof:placetype":"venue"
},
  "geometry": {"coordinates":[-82.32928,36.292141],"type":"Point"}
}