{
  "type": "Feature",
  "properties": {
    "addr:full":"1691 Burgess Falls Rd Cookeville TN 38506",
    "addr:housenumber":"1691",
    "addr:postcode":"38506",
    "addr:street":"Burgess Falls Rd",
    "iso:country":"US",
    "sg:address":"1691 Burgess Falls Rd",
    "sg:city":"Cookeville",
    "sg:classifiers":[
        {
            "category":"Organizations",
            "subcategory":"Religious Organization",
            "type":"Services"
        }
    ],
    "sg:phone":"+1 931 432 7729",
    "sg:postcode":"38506",
    "sg:province":"TN",
    "sg:tags":[
        "church"
    ],
    "wof:name":"Colonial Hills Church Of God",
    "wof:placetype":"venue"
},
  "geometry": {"coordinates":[-85.542344,36.12527],"type":"Point"}
}