{
  "type": "Feature",
  "properties": {
    "iso:country":"US",
    "sg:address":"214 Oil Well Rd",
    "sg:city":"Jackson",
    "sg:classifiers":[
        {
            "category":"Banks & Credit Unions",
            "subcategory":"Bank",
            "type":"Services"
        }
    ],
    "sg:phone":"+1 731 664 1784",
    "sg:postcode":"38305",
    "sg:province":"TN",
    "sg:website":"www.leaderscu.org",
    "wof:name":"Leaders Credit Union",
    "wof:placetype":"venue"
},
  "geometry": {"coordinates":[-88.849732,35.689433],"type":"Point"}
}