{
  "type": "Feature",
  "properties": {
    "addr:full":"300 Bass Rd Bethpage TN 37022",
    "addr:housenumber":"300",
    "addr:postcode":"37022",
    "addr:street":"Bass Rd",
    "iso:country":"US",
    "sg:address":"300 Bass Rd",
    "sg:city":"Bethpage",
    "sg:classifiers":[
        {
            "category":"Building & Trades",
            "subcategory":"Construction",
            "type":"Services"
        }
    ],
    "sg:phone":"+1 615 374 9814",
    "sg:postcode":"37022",
    "sg:province":"TN",
    "wof:name":"Columbia Gulf Transmission Co",
    "wof:placetype":"venue"
},
  "geometry": {"coordinates":[-86.262047,36.389283],"type":"Point"}
}