{
  "type": "Feature",
  "properties": {
    "addr:full":"1253 Dinah Shore Blvd Winchester TN 37398",
    "addr:housenumber":"1253",
    "addr:postcode":"37398",
    "addr:street":"Dinah Shore Blvd",
    "iso:country":"US",
    "sg:address":"1253 Dinah Shore Blvd",
    "sg:city":"Winchester",
    "sg:classifiers":[
        {
            "category":"Autos & Motor Vehicles",
            "subcategory":"Auto Supplies",
            "type":"Retail Goods"
        }
    ],
    "sg:phone":"+1 931 967 3828",
    "sg:postcode":"37398",
    "sg:province":"TN",
    "sg:tags":[
        "wheel",
        "brake",
        "rim",
        "drum",
        "tire"
    ],
    "wof:name":"Goodyear",
    "wof:placetype":"venue"
},
  "geometry": {"coordinates":[-86.098305,35.196776],"type":"Point"}
}