{
  "type": "Feature",
  "properties": {
    "iso:country":"US",
    "sg:address":"609 Smithview Dr",
    "sg:city":"Maryville",
    "sg:classifiers":[
        {
            "category":"Professional",
            "subcategory":"Lawyer & Legal Services",
            "type":"Services"
        }
    ],
    "sg:phone":"+1 865 980 5588",
    "sg:postcode":"37803",
    "sg:province":"TN",
    "sg:tags":[
        "attorney"
    ],
    "wof:name":"Nicholson & Associates",
    "wof:placetype":"venue"
},
  "geometry": {"coordinates":[-83.951218,35.754033],"type":"Point"}
}