{
  "type": "Feature",
  "properties": {
    "iso:country":"US",
    "sg:address":"114 Kraft St",
    "sg:city":"Clarksville",
    "sg:classifiers":[
        {
            "category":"Manufacturing",
            "subcategory":"Tools & Machinery",
            "type":"Manufacturing & Wholesale Goods"
        }
    ],
    "sg:phone":"+1 931 920 5200",
    "sg:postcode":"37040",
    "sg:province":"TN",
    "sg:tags":[
        "machine",
        "shop"
    ],
    "wof:name":"M & M Machine Co Inc",
    "wof:placetype":"venue"
},
  "geometry": {"coordinates":[-87.34226,36.540224],"type":"Point"}
}