{
  "type": "Feature",
  "properties": {
    "iso:country":"US",
    "sg:address":"5892 Elmore Rd",
    "sg:city":"Memphis",
    "sg:classifiers":[
        {
            "category":"Organizations",
            "subcategory":"Religious Organization",
            "type":"Services"
        }
    ],
    "sg:phone":"+1 901 323 6938",
    "sg:postcode":"38134",
    "sg:province":"TN",
    "sg:tags":[
        "church"
    ],
    "wof:name":"House Of Truth Church",
    "wof:placetype":"venue"
},
  "geometry": {"coordinates":[-89.867019,35.190717],"type":"Point"}
}