{
  "type": "Feature",
  "properties": {
    "iso:country":"US",
    "sg:address":"525 Old Hwy 46 S",
    "sg:city":"Dickson",
    "sg:classifiers":[
        {
            "category":"Retail",
            "subcategory":"Auto Repair",
            "type":"Services"
        }
    ],
    "sg:phone":"+1 615 446 4134",
    "sg:postcode":"37055",
    "sg:province":"TN",
    "sg:tags":[
        "body",
        "automobile",
        "painting"
    ],
    "wof:name":"Carl's Collision & Auto Repair",
    "wof:placetype":"venue"
},
  "geometry": {"coordinates":[-87.32981599999999,36.001345],"type":"Point"}
}