{
  "type": "Feature",
  "properties": {
    "iso:country":"US",
    "sg:address":"301 E 11th St",
    "sg:city":"Chattanooga",
    "sg:classifiers":[
        {
            "category":"Shopping",
            "subcategory":"Used Merchandise",
            "type":"Retail Goods"
        }
    ],
    "sg:phone":"+1 423 634 5145",
    "sg:postcode":"37403",
    "sg:province":"TN",
    "sg:tags":[
        "antique"
    ],
    "wof:name":"Cottage Walk Antique Warehouse",
    "wof:placetype":"venue"
},
  "geometry": {"coordinates":[-85.30504500000001,35.042294],"type":"Point"}
}