{
  "type": "Feature",
  "properties": {
    "iso:country":"US",
    "sg:address":"2122 Utopia Ave",
    "sg:city":"Nashville",
    "sg:classifiers":[
        {
            "category":"Social Services",
            "type":"Services"
        }
    ],
    "sg:phone":"+1 615 259 2741",
    "sg:postcode":"37211",
    "sg:province":"TN",
    "wof:name":"The Last Stop Inc",
    "wof:placetype":"venue"
},
  "geometry": {"coordinates":[-86.756428,36.127062],"type":"Point"}
}