{
  "type": "Feature",
  "properties": {
    "iso:country":"US",
    "sg:address":"626 N Washington Ave",
    "sg:city":"Cookeville",
    "sg:classifiers":[
        {
            "category":"Building & Trades",
            "subcategory":"Construction",
            "type":"Services"
        }
    ],
    "sg:phone":"+1 931 526 9541",
    "sg:postcode":"38501",
    "sg:province":"TN",
    "sg:tags":[
        "utility",
        "contractor"
    ],
    "wof:name":"Putnam Contracting Services",
    "wof:placetype":"venue"
},
  "geometry": {"coordinates":[-85.498006,36.170301],"type":"Point"}
}