{
  "type": "Feature",
  "properties": {
    "addr:full":"600 Dusan Blvd Murfreesboro TN 37129",
    "addr:housenumber":"600",
    "addr:postcode":"37129",
    "addr:street":"Dusan Blvd",
    "iso:country":"US",
    "sg:address":"600 Dusan Blvd",
    "sg:city":"Murfreesboro",
    "sg:classifiers":[
        {
            "category":"Real Estate",
            "subcategory":"Real Estate Operator",
            "type":"Services"
        }
    ],
    "sg:phone":"+1 615 898 0210",
    "sg:postcode":"37129",
    "sg:province":"TN",
    "sg:tags":[
        "building",
        "apartment"
    ],
    "wof:name":"Dusan Apts",
    "wof:placetype":"venue"
},
  "geometry": {"coordinates":[-86.393164,35.869116],"type":"Point"}
}