{
  "type": "Feature",
  "properties": {
    "iso:country":"US",
    "sg:address":"1121 Riverwood Pl",
    "sg:city":"Clarksville",
    "sg:classifiers":[
        {
            "category":"Real Estate",
            "subcategory":"Real Estate Operator",
            "type":"Services"
        }
    ],
    "sg:phone":"+1 931 572 3255",
    "sg:postcode":"37040",
    "sg:province":"TN",
    "sg:tags":[
        "apartment"
    ],
    "wof:name":"Cumberland Manor",
    "wof:placetype":"venue"
},
  "geometry": {"coordinates":[-87.364296,36.506434],"type":"Point"}
}