{
  "type": "Feature",
  "properties": {
    "iso:country":"US",
    "sg:address":"482 Co Rd 709",
    "sg:city":"Riceville",
    "sg:classifiers":[
        {
            "category":"Real Estate",
            "subcategory":"Real Estate Agent",
            "type":"Services"
        }
    ],
    "sg:phone":"+1 423 745 4929",
    "sg:postcode":"37370",
    "sg:province":"TN",
    "sg:tags":[
        "appraiser"
    ],
    "wof:name":"Appraisal Svc",
    "wof:placetype":"venue"
},
  "geometry": {"coordinates":[-84.657927,35.385948],"type":"Point"}
}