{
  "type": "Feature",
  "properties": {
    "iso:country":"US",
    "sg:address":"201 4th Ave N",
    "sg:city":"Nashville",
    "sg:classifiers":[
        {
            "category":"Parking",
            "type":"Transportation"
        }
    ],
    "sg:phone":"+1 615 238 2250",
    "sg:postcode":"37219",
    "sg:province":"TN",
    "sg:tags":[
        "garage"
    ],
    "wof:name":"Premier Parking LLC",
    "wof:placetype":"venue"
},
  "geometry": {"coordinates":[-86.778555,36.163067],"type":"Point"}
}