{
  "type": "Feature",
  "properties": {
    "addr:full":"450 Ponder Rd Smithville TN 37166",
    "addr:housenumber":"450",
    "addr:postcode":"37166",
    "addr:street":"Ponder Rd",
    "iso:country":"US",
    "sg:address":"450 Ponder Rd",
    "sg:city":"Smithville",
    "sg:classifiers":[
        {
            "category":"Freight",
            "type":"Transportation"
        }
    ],
    "sg:phone":"+1 615 597 6510",
    "sg:postcode":"37166",
    "sg:province":"TN",
    "sg:tags":[
        "operator",
        "local",
        "trucking"
    ],
    "wof:name":"Parsley Trucking",
    "wof:placetype":"venue"
},
  "geometry": {"coordinates":[-85.741648,35.991871],"type":"Point"}
}