{
  "type": "Feature",
  "properties": {
    "iso:country":"US",
    "sg:address":"155 Walker St",
    "sg:city":"Crossville",
    "sg:classifiers":[
        {
            "category":"Manufacturing",
            "subcategory":"Glass & Minerals",
            "type":"Manufacturing & Wholesale Goods"
        }
    ],
    "sg:phone":"+1 931 484 9314",
    "sg:postcode":"38555",
    "sg:province":"TN",
    "sg:tags":[
        "product",
        "mfg"
    ],
    "wof:name":"Delbar Products Incorporated",
    "wof:placetype":"venue"
},
  "geometry": {"coordinates":[-85.03429300000001,35.96479],"type":"Point"}
}