{
  "type": "Feature",
  "properties": {
    "addr:full":"928 Airways Blvd Jackson TN 38301",
    "addr:housenumber":"928",
    "addr:postcode":"38301",
    "addr:street":"Airways Blvd",
    "iso:country":"US",
    "sg:address":"928 Airways Blvd",
    "sg:city":"Jackson",
    "sg:classifiers":[
        {
            "category":"Freight",
            "type":"Transportation"
        }
    ],
    "sg:phone":"+1 731 422 5841",
    "sg:postcode":"38301",
    "sg:province":"TN",
    "sg:tags":[
        "mover"
    ],
    "wof:name":"Ray Hill & Sons Moving & Stge",
    "wof:placetype":"venue"
},
  "geometry": {"coordinates":[-88.87912799999999,35.617913],"type":"Point"}
}