{
  "type": "Feature",
  "properties": {
    "iso:country":"US",
    "sg:address":"5212 Hwy 87",
    "sg:city":"Henning",
    "sg:classifiers":[
        {
            "category":"Freight",
            "type":"Transportation"
        }
    ],
    "sg:phone":"+1 731 738 5552",
    "sg:postcode":"38041",
    "sg:province":"TN",
    "sg:tags":[
        "operator",
        "local",
        "trucking"
    ],
    "wof:name":"Freds Trucking",
    "wof:placetype":"venue"
},
  "geometry": {"coordinates":[-89.658784,35.70059],"type":"Point"}
}