{
  "type": "Feature",
  "properties": {
    "iso:country":"US",
    "sg:address":"322 Frey St",
    "sg:city":"Ashland City",
    "sg:classifiers":[
        {
            "category":"Government",
            "subcategory":"Office",
            "type":"Public Place"
        }
    ],
    "sg:phone":"+1 615 792 5628",
    "sg:postcode":"37015",
    "sg:province":"TN",
    "sg:tags":[
        "state",
        "resource"
    ],
    "wof:name":"Human Service Dept",
    "wof:placetype":"venue"
},
  "geometry": {"coordinates":[-87.051991,36.292986],"type":"Point"}
}