{
  "type": "Feature",
  "properties": {
    "iso:country":"US",
    "sg:address":"2700 Middlebrook Pike",
    "sg:city":"Knoxville",
    "sg:classifiers":[
        {
            "category":"Professional",
            "subcategory":"Business Services",
            "type":"Services"
        }
    ],
    "sg:phone":"+1 865 594 6200",
    "sg:postcode":"37921",
    "sg:province":"TN",
    "wof:name":"Tenn Dept Cnsrvtion Invornment",
    "wof:placetype":"venue"
},
  "geometry": {"coordinates":[-83.957904,35.96405],"type":"Point"}
}