{
  "type": "Feature",
  "properties": {
    "iso:country":"US",
    "sg:address":"14 Dundee Cir",
    "sg:city":"Mc Minnville",
    "sg:classifiers":[
        {
            "category":"Personal",
            "subcategory":"Beauty Salon",
            "type":"Services"
        }
    ],
    "sg:phone":"+1 931 473 3074",
    "sg:postcode":"37110",
    "sg:province":"TN",
    "wof:name":"Designers Limited",
    "wof:placetype":"venue"
},
  "geometry": {"coordinates":[-85.825531,35.64079],"type":"Point"}
}