{
  "type": "Feature",
  "properties": {
    "iso:country":"US",
    "sg:address":"2450 Saint John Ave",
    "sg:city":"Dyersburg",
    "sg:classifiers":[
        {
            "category":"Retail",
            "subcategory":"Auto Repair",
            "type":"Services"
        }
    ],
    "sg:phone":"+1 731 286 5006",
    "sg:postcode":"38024",
    "sg:province":"TN",
    "sg:tags":[
        "automotive",
        "used",
        "automobile",
        "general"
    ],
    "wof:name":"B & L Salvage Yard",
    "wof:placetype":"venue"
},
  "geometry": {"coordinates":[-89.33961499999999,36.068867],"type":"Point"}
}