{
  "type": "Feature",
  "properties": {
    "iso:country":"US",
    "sg:address":"612 Transit Ave",
    "sg:city":"Columbia",
    "sg:classifiers":[
        {
            "category":"Building & Trades",
            "subcategory":"Plumbing",
            "type":"Services"
        }
    ],
    "sg:phone":"+1 931 380 0510",
    "sg:postcode":"38401",
    "sg:province":"TN",
    "sg:tags":[
        "mechanical",
        "contractor"
    ],
    "wof:name":"Heiss Heating & Cooling",
    "wof:placetype":"venue"
},
  "geometry": {"coordinates":[-87.057433,35.619258],"type":"Point"}
}