{
  "type": "Feature",
  "properties": {
    "addr:full":"5055 Stage Rd Memphis TN 38128",
    "addr:housenumber":"5055",
    "addr:postcode":"38128",
    "addr:street":"Stage Rd",
    "iso:country":"US",
    "sg:address":"5055 Stage Rd",
    "sg:city":"Memphis",
    "sg:classifiers":[
        {
            "category":"Cinema",
            "subcategory":"Movie Rental",
            "type":"Entertainment"
        }
    ],
    "sg:phone":"+1 901 377 5491",
    "sg:postcode":"38128",
    "sg:province":"TN",
    "sg:tags":[
        "video",
        "tape"
    ],
    "sg:website":"www.hollywoodvideo.com",
    "wof:name":"Hollywood Video",
    "wof:placetype":"venue"
},
  "geometry": {"coordinates":[-89.89640900000001,35.206983],"type":"Point"}
}