{
  "type": "Feature",
  "properties": {
    "iso:country":"US",
    "sg:address":"56 Beechwood Cir",
    "sg:city":"Manchester",
    "sg:classifiers":[
        {
            "category":"Professional",
            "type":"Services"
        }
    ],
    "sg:phone":"+1 931 723 3259",
    "sg:postcode":"37355",
    "sg:province":"TN",
    "wof:name":"Robert D Morse LLC",
    "wof:placetype":"venue"
},
  "geometry": {"coordinates":[-86.123581,35.481627],"type":"Point"}
}