{
  "type": "Feature",
  "properties": {
    "iso:country":"US",
    "sg:address":"911 Old Humboldt Rd",
    "sg:city":"Jackson",
    "sg:classifiers":[
        {
            "category":"Social Services",
            "subcategory":"Adult Care",
            "type":"Services"
        }
    ],
    "sg:phone":"+1 731 664 7787",
    "sg:postcode":"38305",
    "sg:province":"TN",
    "sg:tags":[
        "home",
        "residential"
    ],
    "wof:name":"Dogwood Point-Milan Assisted",
    "wof:placetype":"venue"
},
  "geometry": {"coordinates":[-88.853067,35.706146],"type":"Point"}
}