{
  "type": "Feature",
  "properties": {
    "iso:country":"US",
    "sg:address":"635 Tibbs Rd",
    "sg:city":"Ripley",
    "sg:classifiers":[
        {
            "category":"Personal",
            "subcategory":"Beauty Salon",
            "type":"Services"
        }
    ],
    "sg:phone":"+1 731 221 8085",
    "sg:postcode":"38063",
    "sg:province":"TN",
    "wof:name":"Haley's",
    "wof:placetype":"venue"
},
  "geometry": {"coordinates":[-89.49303999999999,35.786071],"type":"Point"}
}