{
  "type": "Feature",
  "properties": {
    "iso:country":"US",
    "sg:address":"1115 5th St",
    "sg:city":"Bristol",
    "sg:classifiers":[
        {
            "category":"Wholesale",
            "subcategory":"Scrap",
            "type":"Manufacturing & Wholesale Goods"
        }
    ],
    "sg:phone":"+1 423 764 1442",
    "sg:postcode":"37620",
    "sg:province":"TN",
    "sg:tags":[
        "material"
    ],
    "wof:name":"Bristol Scrap Metal",
    "wof:placetype":"venue"
},
  "geometry": {"coordinates":[-82.173372,36.582153],"type":"Point"}
}