{
  "type": "Feature",
  "properties": {
    "addr:full":"104 Short Springs Rd Tullahoma TN 37388",
    "addr:housenumber":"104",
    "addr:postcode":"37388",
    "addr:street":"Short Springs Rd",
    "iso:country":"US",
    "sg:address":"104 Short Springs Rd",
    "sg:city":"Tullahoma",
    "sg:classifiers":[
        {
            "category":"Professional",
            "type":"Services"
        }
    ],
    "sg:phone":"+1 931 455 0882",
    "sg:postcode":"37388",
    "sg:province":"TN",
    "wof:name":"JMS Incoroprated",
    "wof:placetype":"venue"
},
  "geometry": {"coordinates":[-86.201684,35.390723],"type":"Point"}
}