{
  "type": "Feature",
  "properties": {
    "iso:country":"US",
    "sg:address":"1702 Carmack Blvd",
    "sg:city":"Columbia",
    "sg:classifiers":[
        {
            "category":"Wholesale",
            "subcategory":"Motor Vehicles",
            "type":"Manufacturing & Wholesale Goods"
        }
    ],
    "sg:phone":"+1 931 388 5117",
    "sg:postcode":"38401",
    "sg:province":"TN",
    "sg:tags":[
        "automobile"
    ],
    "wof:name":"Car Exchange",
    "wof:placetype":"venue"
},
  "geometry": {"coordinates":[-87.03632,35.600863],"type":"Point"}
}