{
  "type": "Feature",
  "properties": {
    "iso:country":"US",
    "sg:address":"211 Shady Grove Dr",
    "sg:city":"Nashville",
    "sg:classifiers":[
        {
            "category":"Building & Trades",
            "subcategory":"Pest Control",
            "type":"Services"
        }
    ],
    "sg:phone":"+1 615 885 1364",
    "sg:postcode":"37214",
    "sg:province":"TN",
    "sg:website":"http://greensPCTN.com",
    "wof:name":"Green's Exterminating Co",
    "wof:placetype":"venue"
},
  "geometry": {"coordinates":[-86.673563,36.172753],"type":"Point"}
}