{
  "type": "Feature",
  "properties": {
    "addr:full":"509 S Stonegate Ct Antioch TN 37013",
    "addr:housenumber":"509",
    "addr:postcode":"37013",
    "addr:street":"S Stonegate Ct",
    "iso:country":"US",
    "sg:address":"509 S Stonegate Ct",
    "sg:city":"Antioch",
    "sg:classifiers":[
        {
            "category":"Professional",
            "type":"Services"
        }
    ],
    "sg:phone":"+1 615 641 6017",
    "sg:postcode":"37013",
    "sg:province":"TN",
    "wof:name":"Sheryl Short Ltd",
    "wof:placetype":"venue"
},
  "geometry": {"coordinates":[-86.581687,36.038818],"type":"Point"}
}