{
  "type": "Feature",
  "properties": {
    "iso:country":"US",
    "sg:address":"145 Industrial Dr SW",
    "sg:city":"Cleveland",
    "sg:classifiers":[
        {
            "category":"Wholesale",
            "subcategory":"Drugs",
            "type":"Manufacturing & Wholesale Goods"
        }
    ],
    "sg:phone":"+1 423 728 5879",
    "sg:postcode":"37311",
    "sg:province":"TN",
    "sg:tags":[
        "pharmaceutical",
        "product"
    ],
    "wof:name":"Pharma Care",
    "wof:placetype":"venue"
},
  "geometry": {"coordinates":[-84.90857699999999,35.122191],"type":"Point"}
}