{
  "type": "Feature",
  "properties": {
    "addr:full":"522 3rd Ave S Nashville TN 37210",
    "addr:housenumber":"522",
    "addr:postcode":"37210",
    "addr:street":"3Rd Ave S",
    "iso:country":"US",
    "sg:address":"522 3rd Ave S",
    "sg:city":"Nashville",
    "sg:classifiers":[
        {
            "category":"Shopping",
            "type":"Retail Goods"
        },
        {
            "category":"Museum",
            "type":"Entertainment"
        }
    ],
    "sg:phone":"+1 615 252 6655",
    "sg:postcode":"37210",
    "sg:province":"TN",
    "sg:tags":[
        "art",
        "gallery",
        "dealer"
    ],
    "wof:name":"Striped Door Gallery",
    "wof:placetype":"venue"
},
  "geometry": {"coordinates":[-86.77248899999999,36.156331],"type":"Point"}
}