{
  "type": "Feature",
  "properties": {
    "iso:country":"US",
    "sg:address":"208 Old Williamsburg Ct",
    "sg:city":"Nashville",
    "sg:classifiers":[
        {
            "category":"Place Of Worship",
            "subcategory":"Church",
            "type":"Public Place"
        },
        {
            "category":"Place Of Worship",
            "type":"Public Place"
        }
    ],
    "sg:phone":"+1 615 292 7373",
    "sg:postcode":"37215",
    "sg:province":"TN",
    "sg:tags":[
        "churches-baptist-general",
        "churches-baptist"
    ],
    "wof:name":"Friends Of American Baptist College Library",
    "wof:placetype":"venue"
},
  "geometry": {"coordinates":[-86.80353100000001,36.093069],"type":"Point"}
}