{
  "type": "Feature",
  "properties": {
    "iso:country":"US",
    "sg:address":"916 Main St",
    "sg:city":"Nashville",
    "sg:classifiers":[
        {
            "category":"Retail",
            "subcategory":"Auto Repair",
            "type":"Services"
        }
    ],
    "sg:phone":"+1 615 228 5070",
    "sg:postcode":"37206",
    "sg:province":"TN",
    "sg:tags":[
        "repairing",
        "automobile",
        "transmission"
    ],
    "wof:name":"Sharpe Transmission Co",
    "wof:placetype":"venue"
},
  "geometry": {"coordinates":[-86.756462,36.176174],"type":"Point"}
}