{
  "type": "Feature",
  "properties": {
    "iso:country":"US",
    "sg:address":"791 Old Laguardo Rd E",
    "sg:city":"Lebanon",
    "sg:classifiers":[
        {
            "category":"Wholesale",
            "subcategory":"Electrical",
            "type":"Manufacturing & Wholesale Goods"
        }
    ],
    "sg:phone":"+1 615 758 8300",
    "sg:postcode":"37087",
    "sg:province":"TN",
    "sg:tags":[
        "repair"
    ],
    "wof:name":"Barnards Appliance Service",
    "wof:placetype":"venue"
},
  "geometry": {"coordinates":[-86.43224600000001,36.242472],"type":"Point"}
}