{
  "type": "Feature",
  "properties": {
    "iso:country":"US",
    "sg:address":"1495 Catlettsburg Rd",
    "sg:city":"Sevierville",
    "sg:classifiers":[
        {
            "category":"Building & Trades",
            "subcategory":"Construction",
            "type":"Services"
        }
    ],
    "sg:phone":"+1 865 429 6977",
    "sg:postcode":"37876",
    "sg:province":"TN",
    "sg:tags":[
        "painter"
    ],
    "wof:name":"Paint Tex",
    "wof:placetype":"venue"
},
  "geometry": {"coordinates":[-83.580082,35.905869],"type":"Point"}
}