{
  "type": "Feature",
  "properties": {
    "iso:country":"US",
    "sg:address":"915 Main St",
    "sg:city":"Wartburg",
    "sg:classifiers":[
        {
            "category":"Travel",
            "subcategory":"Hotels & Motels",
            "type":"Entertainment"
        }
    ],
    "sg:phone":"+1 423 346 5733",
    "sg:postcode":"37887",
    "sg:province":"TN",
    "wof:name":"Scenic River Inn",
    "wof:placetype":"venue"
},
  "geometry": {"coordinates":[-84.593857,36.104247],"type":"Point"}
}