{
  "type": "Feature",
  "properties": {
    "addr:full":"3221 Knobview Dr Nashville TN 37214",
    "addr:housenumber":"3221",
    "addr:postcode":"37214",
    "addr:street":"Knobview Dr",
    "iso:country":"US",
    "sg:address":"3221 Knobview Dr",
    "sg:city":"Nashville",
    "sg:classifiers":[
        {
            "category":"Shopping",
            "subcategory":"Beauty & Cosmetics",
            "type":"Retail Goods"
        }
    ],
    "sg:phone":"+1 615 883 9319",
    "sg:postcode":"37214",
    "sg:province":"TN",
    "sg:tags":[
        "merchandise"
    ],
    "wof:name":"Mary Kay Cosmetics",
    "wof:placetype":"venue"
},
  "geometry": {"coordinates":[-86.672209,36.175776],"type":"Point"}
}