{
  "type": "Feature",
  "properties": {
    "addr:full":"1500 Poplar Ave Memphis TN 38104",
    "addr:housenumber":"1500",
    "addr:postcode":"38104",
    "addr:street":"Poplar Ave",
    "iso:country":"US",
    "sg:address":"1500 Poplar Ave",
    "sg:city":"Memphis",
    "sg:classifiers":[
        {
            "category":"Professional",
            "subcategory":"Management & Consulting",
            "type":"Services"
        }
    ],
    "sg:phone":"+1 901 322 6002",
    "sg:postcode":"38104",
    "sg:province":"TN",
    "wof:name":"Capital Opportunities",
    "wof:placetype":"venue"
},
  "geometry": {"coordinates":[-90.009896,35.143426],"type":"Point"}
}