{
  "type": "Feature",
  "properties": {
    "addr:full":"4580 Chapman Hwy Knoxville TN 37920",
    "addr:housenumber":"4580",
    "addr:postcode":"37920",
    "addr:street":"Chapman Hwy",
    "iso:country":"US",
    "sg:address":"4580 Chapman Hwy",
    "sg:city":"Knoxville",
    "sg:classifiers":[
        {
            "category":"Food & Beverages",
            "subcategory":"Groceries & Convenience Stores",
            "type":"Retail Goods"
        }
    ],
    "sg:phone":"+1 865 573 3841",
    "sg:postcode":"37920",
    "sg:province":"TN",
    "sg:tags":[
        "grocer"
    ],
    "sg:website":"www.foodcity.com",
    "wof:name":"Food City",
    "wof:placetype":"venue"
},
  "geometry": {"coordinates":[-83.90357299999999,35.932619],"type":"Point"}
}