{
  "type": "Feature",
  "properties": {
    "iso:country":"US",
    "sg:address":"3605 Upper Finley Rd",
    "sg:city":"Dyersburg",
    "sg:classifiers":[
        {
            "category":"Organizations",
            "subcategory":"Community Association",
            "type":"Services"
        }
    ],
    "sg:phone":"+1 731 285 8750",
    "sg:postcode":"38024",
    "sg:province":"TN",
    "wof:name":"R C King Jr",
    "wof:placetype":"venue"
},
  "geometry": {"coordinates":[-89.437847,36.047808],"type":"Point"}
}