{
  "type": "Feature",
  "properties": {
    "iso:country":"US",
    "sg:address":"2750 Salem Hwy",
    "sg:city":"Murfreesboro",
    "sg:classifiers":[
        {
            "category":"Retail",
            "subcategory":"Veterinary Services",
            "type":"Services"
        }
    ],
    "sg:phone":"+1 615 896 3434",
    "sg:postcode":"37128",
    "sg:province":"TN",
    "sg:tags":[
        "hospital",
        "animal"
    ],
    "sg:website":"www.animalcarevet.net",
    "wof:name":"Animal Care Veterinary Hosp",
    "wof:placetype":"venue"
},
  "geometry": {"coordinates":[-86.44953,35.812677],"type":"Point"}
}