{
  "type": "Feature",
  "properties": {
    "iso:country":"US",
    "sg:address":"500 Maryville Hwy",
    "sg:city":"Seymour",
    "sg:classifiers":[
        {
            "category":"Shopping",
            "subcategory":"Clothing, Apparel, & Fashions",
            "type":"Retail Goods"
        }
    ],
    "sg:phone":"+1 865 573 1017",
    "sg:postcode":"37865",
    "sg:province":"TN",
    "wof:name":"Clothing Discounters Ware",
    "wof:placetype":"venue"
},
  "geometry": {"coordinates":[-83.769701,35.862511],"type":"Point"}
}