{
  "type": "Feature",
  "properties": {
    "iso:country":"US",
    "sg:address":"3025 Highland St",
    "sg:city":"Milan",
    "sg:classifiers":[
        {
            "category":"Restaurant",
            "type":"Food & Drink"
        }
    ],
    "sg:phone":"+1 731 723 0036",
    "sg:postcode":"38358",
    "sg:province":"TN",
    "sg:tags":[
        "eating"
    ],
    "wof:name":"Hometown Restaurant",
    "wof:placetype":"venue"
},
  "geometry": {"coordinates":[-88.753559,35.913289],"type":"Point"}
}