{
  "type": "Feature",
  "properties": {
    "iso:country":"US",
    "sg:address":"1812 S Main St",
    "sg:city":"Columbia",
    "sg:classifiers":[
        {
            "category":"Bars & Pubs",
            "type":"Food & Drink"
        }
    ],
    "sg:phone":"+1 931 380 2118",
    "sg:postcode":"38401",
    "sg:province":"TN",
    "sg:tags":[
        "drinking"
    ],
    "wof:name":"Backstreet Tavern",
    "wof:placetype":"venue"
},
  "geometry": {"coordinates":[-87.03874999999999,35.600315],"type":"Point"}
}