{
  "type": "Feature",
  "properties": {
    "iso:country":"US",
    "sg:address":"3024 S 3rd St",
    "sg:city":"Memphis",
    "sg:classifiers":[
        {
            "category":"Restaurant",
            "type":"Food & Drink"
        }
    ],
    "sg:phone":"+1 901 332 8783",
    "sg:postcode":"38109",
    "sg:province":"TN",
    "sg:tags":[
        "barbecue"
    ],
    "wof:name":"Back Yard Bbq",
    "wof:placetype":"venue"
},
  "geometry": {"coordinates":[-90.058948,35.064867],"type":"Point"}
}