{
  "type": "Feature",
  "properties": {
    "addr:full":"277 Foster Rd Gleason TN 38229",
    "addr:housenumber":"277",
    "addr:postcode":"38229",
    "addr:street":"Foster Rd",
    "iso:country":"US",
    "sg:address":"277 Foster Rd",
    "sg:city":"Gleason",
    "sg:phone":"+1 731 364 5568",
    "sg:postcode":"38229",
    "sg:province":"TN",
    "sg:tags":[
        "farm",
        "corn"
    ],
    "wof:name":"David F Oliver",
    "wof:placetype":"venue"
},
  "geometry": {"coordinates":[-88.549043,36.290061],"type":"Point"}
}