{
  "type": "Feature",
  "properties": {
    "iso:country":"US",
    "sg:address":"10644 Lexington Dr",
    "sg:city":"Knoxville",
    "sg:classifiers":[
        {
            "category":"Building & Trades",
            "subcategory":"Equipment Rental",
            "type":"Services"
        }
    ],
    "sg:phone":"+1 865 218 8800",
    "sg:postcode":"37932",
    "sg:province":"TN",
    "sg:tags":[
        "yard"
    ],
    "wof:name":"Stowers Rental & Supply",
    "wof:placetype":"venue"
},
  "geometry": {"coordinates":[-84.144497,35.909153],"type":"Point"}
}