{
  "type": "Feature",
  "properties": {
    "iso:country":"US",
    "sg:address":"17 W Pontotoc Ave",
    "sg:city":"Memphis",
    "sg:classifiers":[
        {
            "category":"Professional",
            "subcategory":"Lawyer & Legal Services",
            "type":"Services"
        }
    ],
    "sg:phone":"+1 901 432 4726",
    "sg:postcode":"38103",
    "sg:province":"TN",
    "sg:tags":[
        "attorney"
    ],
    "wof:name":"Brian T Grisham",
    "wof:placetype":"venue"
},
  "geometry": {"coordinates":[-90.058825,35.139183],"type":"Point"}
}