{
  "type": "Feature",
  "properties": {
    "iso:country":"US",
    "sg:address":"1102 Paula Dr",
    "sg:city":"Newbern",
    "sg:classifiers":[
        {
            "category":"Building & Trades",
            "subcategory":"Electrical",
            "type":"Services"
        }
    ],
    "sg:phone":"+1 731 627 3050",
    "sg:postcode":"38059",
    "sg:province":"TN",
    "sg:tags":[
        "electric",
        "contractor"
    ],
    "wof:name":"Edison Electric",
    "wof:placetype":"venue"
},
  "geometry": {"coordinates":[-89.302632,36.095763],"type":"Point"}
}