{
  "type": "Feature",
  "properties": {
    "iso:country":"US",
    "sg:address":"10319 Cogdill Rd",
    "sg:city":"Knoxville",
    "sg:classifiers":[
        {
            "category":"Building & Trades",
            "subcategory":"Construction",
            "type":"Services"
        }
    ],
    "sg:phone":"+1 865 966 3536",
    "sg:postcode":"37932",
    "sg:province":"TN",
    "sg:tags":[
        "heavy"
    ],
    "wof:name":"Advantage Docks",
    "wof:placetype":"venue"
},
  "geometry": {"coordinates":[-84.130346,35.911933],"type":"Point"}
}