{
  "type": "Feature",
  "properties": {
    "addr:full":"110 4th Rd Summertown TN 38483",
    "addr:housenumber":"110",
    "addr:postcode":"38483",
    "addr:street":"4Th Rd",
    "iso:country":"US",
    "sg:address":"110 4th Rd",
    "sg:city":"Summertown",
    "sg:classifiers":[
        {
            "category":"Building & Trades",
            "subcategory":"Construction",
            "type":"Services"
        }
    ],
    "sg:phone":"+1 931 964 3579",
    "sg:postcode":"38483",
    "sg:province":"TN",
    "sg:tags":[
        "contractor"
    ],
    "wof:name":"Farm Building Co",
    "wof:placetype":"venue"
},
  "geometry": {"coordinates":[-87.339884,35.486074],"type":"Point"}
}