{
  "type": "Feature",
  "properties": {
    "iso:country":"US",
    "sg:address":"4042 Buck Matthews Rd",
    "sg:city":"Columbia",
    "sg:classifiers":[
        {
            "category":"Farming",
            "subcategory":"Dairy Farm",
            "type":"Manufacturing & Wholesale Goods"
        }
    ],
    "sg:phone":"+1 931 381 9603",
    "sg:postcode":"38401",
    "sg:province":"TN",
    "wof:name":"Roger Toombs",
    "wof:placetype":"venue"
},
  "geometry": {"coordinates":[-87.072765,35.503569],"type":"Point"}
}