{
  "type": "Feature",
  "properties": {
    "addr:full":"1108 W Main St Lebanon TN 37087",
    "addr:housenumber":"1108",
    "addr:postcode":"37087",
    "addr:street":"W Main St",
    "iso:country":"US",
    "sg:address":"1108 W Main St",
    "sg:city":"Lebanon",
    "sg:classifiers":[
        {
            "category":"Autos & Motor Vehicles",
            "subcategory":"Automobile Sales",
            "type":"Retail Goods"
        }
    ],
    "sg:phone":"+1 615 547 0606",
    "sg:postcode":"37087",
    "sg:province":"TN",
    "sg:tags":[
        "car",
        "dealer"
    ],
    "wof:name":"Auto Village",
    "wof:placetype":"venue"
},
  "geometry": {"coordinates":[-86.319047,36.21243],"type":"Point"}
}