{
  "type": "Feature",
  "properties": {
    "iso:country":"US",
    "sg:address":"101 Southside Park Dr",
    "sg:city":"Lebanon",
    "sg:classifiers":[
        {
            "category":"Autos & Motor Vehicles",
            "subcategory":"Automobile Sales",
            "type":"Retail Goods"
        }
    ],
    "sg:phone":"+1 615 444 0514",
    "sg:postcode":"37090",
    "sg:province":"TN",
    "sg:tags":[
        "car",
        "dealer"
    ],
    "wof:name":"Auto Ranch",
    "wof:placetype":"venue"
},
  "geometry": {"coordinates":[-86.30349699999999,36.171511],"type":"Point"}
}