{
  "type": "Feature",
  "properties": {
    "iso:country":"US",
    "sg:address":"6789 Amersham Dr",
    "sg:city":"Memphis",
    "sg:classifiers":[
        {
            "category":"Wholesale",
            "subcategory":"Hardware",
            "type":"Manufacturing & Wholesale Goods"
        }
    ],
    "sg:phone":"+1 901 737 9761",
    "sg:postcode":"38119",
    "sg:province":"TN",
    "sg:tags":[
        "rivet",
        "mfg"
    ],
    "wof:name":"Tom Kavanagh & Associates",
    "wof:placetype":"venue"
},
  "geometry": {"coordinates":[-89.833445,35.072045],"type":"Point"}
}