{
  "type": "Feature",
  "properties": {
    "iso:country":"US",
    "sg:address":"112 Alpha Dr",
    "sg:city":"Franklin",
    "sg:classifiers":[
        {
            "category":"Autos & Motor Vehicles",
            "subcategory":"Auto Supplies",
            "type":"Retail Goods"
        }
    ],
    "sg:phone":"+1 615 944 6243",
    "sg:postcode":"37064",
    "sg:province":"TN",
    "wof:name":"Off Road Carts Inc",
    "wof:placetype":"venue"
},
  "geometry": {"coordinates":[-86.875264,35.896527],"type":"Point"}
}