{
  "type": "Feature",
  "properties": {
    "iso:country":"US",
    "sg:address":"103 Dover St",
    "sg:city":"Shelbyville",
    "sg:classifiers":[
        {
            "category":"Retail",
            "subcategory":"Car Wash",
            "type":"Services"
        }
    ],
    "sg:phone":"+1 931 684 5785",
    "sg:postcode":"37160",
    "sg:province":"TN",
    "sg:tags":[
        "automobile",
        "detail",
        "clean"
    ],
    "wof:name":"Auto Heaven",
    "wof:placetype":"venue"
},
  "geometry": {"coordinates":[-86.474334,35.491809],"type":"Point"}
}