{
  "type": "Feature",
  "properties": {
    "iso:country":"US",
    "sg:address":"15671 Hwy 70 N",
    "sg:city":"Monterey",
    "sg:classifiers":[
        {
            "category":"Banks & Credit Unions",
            "subcategory":"Financial Services",
            "type":"Services"
        }
    ],
    "sg:phone":"+1 931 839 8122",
    "sg:postcode":"38574",
    "sg:province":"TN",
    "sg:tags":[
        "trust",
        "management"
    ],
    "wof:name":"Roger D Toft",
    "wof:placetype":"venue"
},
  "geometry": {"coordinates":[-85.222256,36.065472],"type":"Point"}
}