{
  "type": "Feature",
  "properties": {
    "iso:country":"US",
    "sg:address":"7216 Chapman Hwy",
    "sg:city":"Knoxville",
    "sg:classifiers":[
        {
            "category":"Restaurant",
            "type":"Food & Drink"
        }
    ],
    "sg:menulink":"http://www.allmenus.com/tn/knoxville/214903-burger-king/menu/",
    "sg:phone":"+1 423 573 4101",
    "sg:postcode":"37920",
    "sg:province":"TN",
    "sg:tags":[
        "burger",
        "american"
    ],
    "wof:name":"Burger King",
    "wof:placetype":"venue"
},
  "geometry": {"coordinates":[-83.85063700000001,35.909622],"type":"Point"}
}