{
  "type": "Feature",
  "properties": {
    "addr:full":"5070 Raleigh Lagrange Rd Memphis TN 38134",
    "addr:housenumber":"5070",
    "addr:postcode":"38134",
    "addr:street":"Raleigh Lagrange Rd",
    "iso:country":"US",
    "sg:address":"5070 Raleigh Lagrange Rd",
    "sg:city":"Memphis",
    "sg:classifiers":[
        {
            "category":"Personal",
            "subcategory":"Beauty Salon",
            "type":"Services"
        }
    ],
    "sg:phone":"+1 901 937 1777",
    "sg:postcode":"38134",
    "sg:province":"TN",
    "sg:tags":[
        "shop",
        "manicuring"
    ],
    "wof:name":"Cathy's Nail Salon",
    "wof:placetype":"venue"
},
  "geometry": {"coordinates":[-89.89248000000001,35.191806],"type":"Point"}
}