{
  "type": "Feature",
  "properties": {
    "iso:country":"US",
    "sg:address":"3424 Binkley Rd",
    "sg:city":"Joelton",
    "sg:classifiers":[
        {
            "category":"Building & Trades",
            "subcategory":"Construction",
            "type":"Services"
        }
    ],
    "sg:phone":"+1 615 876 0744",
    "sg:postcode":"37080",
    "sg:province":"TN",
    "sg:tags":[
        "contractor"
    ],
    "wof:name":"Raideaux Mc Alister Contractor",
    "wof:placetype":"venue"
},
  "geometry": {"coordinates":[-86.87837500000001,36.323738],"type":"Point"}
}