{
  "type": "Feature",
  "properties": {
    "iso:country":"US",
    "sg:address":"200 Iris Dr",
    "sg:city":"Sparta",
    "sg:classifiers":[
        {
            "category":"Manufacturing",
            "subcategory":"Rubber & Plastics",
            "type":"Manufacturing & Wholesale Goods"
        }
    ],
    "sg:phone":"+1 931 738 2210",
    "sg:postcode":"38583",
    "sg:province":"TN",
    "sg:tags":[
        "product",
        "custom",
        "compounding",
        "resin",
        "mfg"
    ],
    "wof:name":"Allied Signal Engineering Plas",
    "wof:placetype":"venue"
},
  "geometry": {"coordinates":[-85.485903,35.915285],"type":"Point"}
}