{
  "type": "Feature",
  "properties": {
    "addr:full":"1578 Cherry Tree Dr Clarksville TN 37042",
    "addr:housenumber":"1578",
    "addr:postcode":"37042",
    "addr:street":"Cherry Tree Dr",
    "iso:country":"US",
    "sg:address":"1578 Cherry Tree Dr",
    "sg:city":"Clarksville",
    "sg:classifiers":[
        {
            "category":"Real Estate",
            "subcategory":"Real Estate Agent",
            "type":"Services"
        }
    ],
    "sg:phone":"+1 931 503 2704",
    "sg:postcode":"37042",
    "sg:province":"TN",
    "wof:name":"Rosa I Rivera Enterprises",
    "wof:placetype":"venue"
},
  "geometry": {"coordinates":[-87.42021099999999,36.572182],"type":"Point"}
}