{
  "type": "Feature",
  "properties": {
    "iso:country":"US",
    "sg:address":"605 Glenwood Dr",
    "sg:city":"Chattanooga",
    "sg:classifiers":[
        {
            "category":"Building & Trades",
            "subcategory":"Cleaning & Sanitation",
            "type":"Services"
        }
    ],
    "sg:phone":"+1 423 624 0764",
    "sg:postcode":"37404",
    "sg:province":"TN",
    "sg:tags":[
        "maintenance"
    ],
    "wof:name":"Chattanooga Plaza Owners",
    "wof:placetype":"venue"
},
  "geometry": {"coordinates":[-85.259503,35.041165],"type":"Point"}
}