{
  "type": "Feature",
  "properties": {
    "iso:country":"US",
    "sg:address":"810 Old Midway Rd",
    "sg:city":"Lenoir City",
    "sg:classifiers":[
        {
            "category":"Retail",
            "subcategory":"Auto Repair",
            "type":"Services"
        }
    ],
    "sg:phone":"+1 865 988 3824",
    "sg:postcode":"37772",
    "sg:province":"TN",
    "sg:tags":[
        "automotive",
        "general"
    ],
    "wof:name":"R & S Automotive",
    "wof:placetype":"venue"
},
  "geometry": {"coordinates":[-84.248919,35.81646],"type":"Point"}
}