{
  "type": "Feature",
  "properties": {
    "addr:full":"211 Center Park Dr Knoxville TN 37922",
    "addr:housenumber":"211",
    "addr:postcode":"37922",
    "addr:street":"Center Park Dr",
    "iso:country":"US",
    "sg:address":"211 Center Park Dr",
    "sg:city":"Knoxville",
    "sg:classifiers":[
        {
            "category":"Professional",
            "subcategory":"Lawyer & Legal Services",
            "type":"Services"
        }
    ],
    "sg:phone":"+1 865 675 5858",
    "sg:postcode":"37922",
    "sg:province":"TN",
    "sg:tags":[
        "attorney"
    ],
    "wof:name":"David Booth",
    "wof:placetype":"venue"
},
  "geometry": {"coordinates":[-84.121354,35.907426],"type":"Point"}
}