{
  "type": "Feature",
  "properties": {
    "addr:full":"646 Thompson Ln Nashville TN 37204",
    "addr:housenumber":"646",
    "addr:postcode":"37204",
    "addr:street":"Thompson Ln",
    "iso:country":"US",
    "sg:address":"646 Thompson Ln",
    "sg:city":"Nashville",
    "sg:classifiers":[
        {
            "category":"Autos & Motor Vehicles",
            "subcategory":"Automobile Sales",
            "type":"Retail Goods"
        }
    ],
    "sg:phone":"+1 615 244 3615",
    "sg:postcode":"37204",
    "sg:province":"TN",
    "sg:tags":[
        "car",
        "dealer"
    ],
    "sg:website":"www.crownford.com",
    "wof:name":"Crown Ford",
    "wof:placetype":"venue"
},
  "geometry": {"coordinates":[-86.758005,36.111442],"type":"Point"}
}