{
  "type": "Feature",
  "properties": {
    "iso:country":"US",
    "sg:address":"420 E Lauderdale St",
    "sg:city":"Tullahoma",
    "sg:classifiers":[
        {
            "category":"Wholesale",
            "subcategory":"Vending Machines",
            "type":"Manufacturing & Wholesale Goods"
        }
    ],
    "sg:phone":"+1 931 455 8338",
    "sg:postcode":"37388",
    "sg:province":"TN",
    "sg:tags":[
        "operator",
        "business"
    ],
    "wof:name":"Interstate Automatic Food Svcs",
    "wof:placetype":"venue"
},
  "geometry": {"coordinates":[-86.201943,35.365847],"type":"Point"}
}