{
  "type": "Feature",
  "properties": {
    "iso:country":"US",
    "sg:address":"7169 Donnington Dr",
    "sg:city":"Germantown",
    "sg:classifiers":[
        {
            "category":"Home & Garden",
            "subcategory":"Building Materials",
            "type":"Retail Goods"
        },
        {
            "category":"Building & Trades",
            "subcategory":"Construction",
            "type":"Services"
        }
    ],
    "sg:phone":"+1 901 757 4689",
    "sg:postcode":"38138",
    "sg:province":"TN",
    "sg:tags":[
        "altering",
        "improvement",
        "remodeling",
        "contractor"
    ],
    "wof:name":"Home Concepts Group",
    "wof:placetype":"venue"
},
  "geometry": {"coordinates":[-89.82396799999999,35.089841],"type":"Point"}
}