{
  "type": "Feature",
  "properties": {
    "iso:country":"US",
    "sg:address":"5006 Jim Jones Ln",
    "sg:city":"Knoxville",
    "sg:classifiers":[
        {
            "category":"Banks & Credit Unions",
            "subcategory":"Bank",
            "type":"Services"
        }
    ],
    "sg:phone":"+1 865 927 7000",
    "sg:postcode":"37931",
    "sg:province":"TN",
    "sg:tags":[
        "mortgage"
    ],
    "wof:name":"Ridge Mortgage Co",
    "wof:placetype":"venue"
},
  "geometry": {"coordinates":[-84.180402,35.985869],"type":"Point"}
}