{
  "type": "Feature",
  "properties": {
    "iso:country":"US",
    "sg:address":"181 E Church St",
    "sg:city":"Lexington",
    "sg:classifiers":[
        {
            "category":"Building & Trades",
            "subcategory":"Construction",
            "type":"Services"
        }
    ],
    "sg:phone":"+1 731 968 0304",
    "sg:postcode":"38351",
    "sg:province":"TN",
    "sg:tags":[
        "roofing",
        "contractor"
    ],
    "wof:name":"Darrell Davis Roofing Inc",
    "wof:placetype":"venue"
},
  "geometry": {"coordinates":[-88.389112,35.646939],"type":"Point"}
}