{
  "type": "Feature",
  "properties": {
    "iso:country":"US",
    "sg:address":"1176 Williamson St",
    "sg:city":"Milan",
    "sg:classifiers":[
        {
            "category":"Shopping",
            "type":"Retail Goods"
        }
    ],
    "sg:phone":"+1 731 686 0657",
    "sg:postcode":"38358",
    "sg:province":"TN",
    "sg:tags":[
        "equipment",
        "telephone",
        "supply"
    ],
    "wof:name":"Telephone Switching Supply Inc",
    "wof:placetype":"venue"
},
  "geometry": {"coordinates":[-88.759584,35.919252],"type":"Point"}
}