{
  "type": "Feature",
  "properties": {
    "iso:country":"US",
    "sg:address":"812 S High St",
    "sg:city":"Columbia",
    "sg:classifiers":[
        {
            "category":"Organizations",
            "subcategory":"Religious Organization",
            "type":"Services"
        }
    ],
    "sg:phone":"+1 931 380 0820",
    "sg:postcode":"38401",
    "sg:province":"TN",
    "sg:website":"www.mauryhills.com",
    "wof:name":"Maury Hill Church Of Christ",
    "wof:placetype":"venue"
},
  "geometry": {"coordinates":[-87.037305,35.615029],"type":"Point"}
}