{
  "type": "Feature",
  "properties": {
    "addr:full":"45 Reeder Ave Munford TN 38058",
    "addr:housenumber":"45",
    "addr:postcode":"38058",
    "addr:street":"Reeder Ave",
    "iso:country":"US",
    "sg:address":"45 Reeder Ave",
    "sg:city":"Munford",
    "sg:classifiers":[
        {
            "category":"Restaurant",
            "type":"Food & Drink"
        }
    ],
    "sg:phone":"+1 901 840 3751",
    "sg:postcode":"38058",
    "sg:province":"TN",
    "sg:tags":[
        "barbecue"
    ],
    "wof:name":"Gridley's Bar BQ",
    "wof:placetype":"venue"
},
  "geometry": {"coordinates":[-89.811059,35.454879],"type":"Point"}
}