{
  "type": "Feature",
  "properties": {
    "addr:full":"4307 Rossville Blvd Chattanooga TN 37407",
    "addr:housenumber":"4307",
    "addr:postcode":"37407",
    "addr:street":"Rossville Blvd",
    "iso:country":"US",
    "sg:address":"4307 Rossville Blvd",
    "sg:city":"Chattanooga",
    "sg:classifiers":[
        {
            "category":"Autos & Motor Vehicles",
            "subcategory":"Auto Supplies",
            "type":"Retail Goods"
        }
    ],
    "sg:phone":"+1 423 867 2250",
    "sg:postcode":"37407",
    "sg:province":"TN",
    "sg:tags":[
        "automobile",
        "parts"
    ],
    "wof:name":"Autozone",
    "wof:placetype":"venue"
},
  "geometry": {"coordinates":[-85.290778,34.993977],"type":"Point"}
}