{
  "type": "Feature",
  "properties": {
    "iso:country":"US",
    "sg:address":"931 S Willow Ave",
    "sg:city":"Cookeville",
    "sg:classifiers":[
        {
            "category":"Autos & Motor Vehicles",
            "subcategory":"Automobile Sales",
            "type":"Retail Goods"
        }
    ],
    "sg:phone":"+1 931 526 5121",
    "sg:postcode":"38501",
    "sg:province":"TN",
    "sg:tags":[
        "car",
        "dealer"
    ],
    "wof:name":"Cookeville Motors Inc",
    "wof:placetype":"venue"
},
  "geometry": {"coordinates":[-85.52419500000001,36.143774],"type":"Point"}
}