{
  "type": "Feature",
  "properties": {
    "iso:country":"US",
    "sg:address":"327 Green Acres Rd",
    "sg:city":"Kingston",
    "sg:classifiers":[
        {
            "category":"Building & Trades",
            "subcategory":"Plumbing",
            "type":"Services"
        }
    ],
    "sg:phone":"+1 865 376 9872",
    "sg:postcode":"37763",
    "sg:province":"TN",
    "sg:tags":[
        "engineering",
        "contractor"
    ],
    "wof:name":"Oak Ridge Heating",
    "wof:placetype":"venue"
},
  "geometry": {"coordinates":[-84.511959,35.840572],"type":"Point"}
}