{
  "type": "Feature",
  "properties": {
    "addr:full":"202 Sutter Ct Smyrna TN 37167",
    "addr:housenumber":"202",
    "addr:postcode":"37167",
    "addr:street":"Sutter Ct",
    "iso:country":"US",
    "sg:address":"202 Sutter Ct",
    "sg:city":"Smyrna",
    "sg:classifiers":[
        {
            "category":"Education",
            "subcategory":"Special Training",
            "type":"Public Place"
        }
    ],
    "sg:phone":"+1 615 223 1255",
    "sg:postcode":"37167",
    "sg:province":"TN",
    "sg:tags":[
        "school",
        "language"
    ],
    "wof:name":"Hablemos",
    "wof:placetype":"venue"
},
  "geometry": {"coordinates":[-86.52986199999999,35.962118],"type":"Point"}
}