{
  "type": "Feature",
  "properties": {
    "iso:country":"US",
    "sg:address":"308 W Crawford Ave",
    "sg:city":"Monterey",
    "sg:classifiers":[
        {
            "category":"Organizations",
            "subcategory":"Religious Organization",
            "type":"Services"
        }
    ],
    "sg:phone":"+1 931 839 2660",
    "sg:postcode":"38574",
    "sg:province":"TN",
    "wof:name":"Church Of Christ",
    "wof:placetype":"venue"
},
  "geometry": {"coordinates":[-85.27011400000001,36.151331],"type":"Point"}
}