{
  "type": "Feature",
  "properties": {
    "iso:country":"US",
    "sg:address":"3402 Wetherburns Cir",
    "sg:city":"Memphis",
    "sg:classifiers":[
        {
            "category":"Building & Trades",
            "subcategory":"Construction",
            "type":"Services"
        }
    ],
    "sg:phone":"+1 901 383 7339",
    "sg:postcode":"38134",
    "sg:province":"TN",
    "sg:tags":[
        "house"
    ],
    "wof:name":"Steel Home Services",
    "wof:placetype":"venue"
},
  "geometry": {"coordinates":[-89.882814,35.218411],"type":"Point"}
}