{
  "type": "Feature",
  "properties": {
    "iso:country":"US",
    "sg:address":"333 Gallatin Pike S",
    "sg:city":"Madison",
    "sg:classifiers":[
        {
            "category":"Insurance",
            "subcategory":"Life Insurance",
            "type":"Services"
        }
    ],
    "sg:phone":"+1 615 868 7093",
    "sg:postcode":"37115",
    "sg:province":"TN",
    "sg:tags":[
        "carrier"
    ],
    "wof:name":"Woodman of World Lf Insur Soc",
    "wof:placetype":"venue"
},
  "geometry": {"coordinates":[-86.713567,36.258657],"type":"Point"}
}