{
  "type": "Feature",
  "properties": {
    "iso:country":"US",
    "sg:address":"526 Old Hwy 46 S",
    "sg:city":"Dickson",
    "sg:classifiers":[
        {
            "category":"Retail",
            "subcategory":"Auto Repair",
            "type":"Services"
        }
    ],
    "sg:phone":"+1 615 441 3355",
    "sg:postcode":"37055",
    "sg:province":"TN",
    "sg:tags":[
        "repairing",
        "automobile",
        "general",
        "accessory"
    ],
    "wof:name":"Lucky's Speed Sport",
    "wof:placetype":"venue"
},
  "geometry": {"coordinates":[-87.32981599999999,36.001345],"type":"Point"}
}