{
  "type": "Feature",
  "properties": {
    "iso:country":"US",
    "sg:address":"3845 Holston Hills Rd",
    "sg:city":"Knoxville",
    "sg:classifiers":[
        {
            "category":"Organizations",
            "subcategory":"Non-profit Organization",
            "type":"Services"
        }
    ],
    "sg:phone":"+1 865 524 5757",
    "sg:postcode":"37914",
    "sg:province":"TN",
    "sg:tags":[
        "information",
        "alcoholism",
        "treatment"
    ],
    "wof:name":"Helen Ross Mc Nabb Ctr Inc",
    "wof:placetype":"venue"
},
  "geometry": {"coordinates":[-83.86054900000001,35.983234],"type":"Point"}
}