{
  "type": "Feature",
  "properties": {
    "addr:full":"6301 White Oak Valley Cir Mc Donald TN 37353",
    "addr:housenumber":"6301",
    "addr:postcode":"37353",
    "addr:street":"White Oak Valley Cir Mc",
    "iso:country":"US",
    "sg:address":"6301 White Oak Valley Cir",
    "sg:city":"Mc Donald",
    "sg:classifiers":[
        {
            "category":"Retail",
            "subcategory":"Repair Shop",
            "type":"Services"
        }
    ],
    "sg:phone":"+1 423 238 8558",
    "sg:postcode":"37353",
    "sg:province":"TN",
    "sg:tags":[
        "electrical"
    ],
    "wof:name":"Spectra Com Inc",
    "wof:placetype":"venue"
},
  "geometry": {"coordinates":[-85.023915,35.093503],"type":"Point"}
}