{
  "type": "Feature",
  "properties": {
    "iso:country":"US",
    "sg:address":"1013 N Main St",
    "sg:city":"Bolivar",
    "sg:classifiers":[
        {
            "category":"Shopping",
            "type":"Retail Goods"
        }
    ],
    "sg:phone":"+1 731 658 2584",
    "sg:postcode":"38008",
    "sg:province":"TN",
    "sg:tags":[
        "pet",
        "food",
        "supply"
    ],
    "wof:name":"Adkins Leather & Dog Supply",
    "wof:placetype":"venue"
},
  "geometry": {"coordinates":[-88.97855800000001,35.272708],"type":"Point"}
}