{
  "type": "Feature",
  "properties": {
    "iso:country":"US",
    "sg:address":"8109 Beaver Ridge Rd",
    "sg:city":"Knoxville",
    "sg:classifiers":[
        {
            "category":"Education",
            "subcategory":"School",
            "type":"Public Place"
        },
        {
            "category":"Education",
            "subcategory":"Special Training",
            "type":"Public Place"
        }
    ],
    "sg:phone":"+1 865 470 2134",
    "sg:postcode":"37931",
    "sg:province":"TN",
    "sg:tags":[
        "educational"
    ],
    "wof:name":"Karns Annex Alternative Prgrm",
    "wof:placetype":"venue"
},
  "geometry": {"coordinates":[-84.113207,35.982036],"type":"Point"}
}