{
  "type": "Feature",
  "properties": {
    "addr:full":"9111 Hunters Bend Cir Ooltewah TN 37363",
    "addr:housenumber":"9111",
    "addr:postcode":"37363",
    "addr:street":"Hunters Bend Cir",
    "iso:country":"US",
    "sg:address":"9111 Hunters Bend Cir",
    "sg:city":"Ooltewah",
    "sg:classifiers":[
        {
            "category":"Travel",
            "subcategory":"Travel Agent",
            "type":"Entertainment"
        }
    ],
    "sg:phone":"+1 423 954 1234",
    "sg:postcode":"37363",
    "sg:province":"TN",
    "sg:tags":[
        "agency",
        "cruise"
    ],
    "wof:name":"Elrod Cruise Agency Inc",
    "wof:placetype":"venue"
},
  "geometry": {"coordinates":[-85.08886200000001,35.019581],"type":"Point"}
}