{
  "type": "Feature",
  "properties": {
    "iso:country":"US",
    "sg:address":"621 Nawakwa Trl",
    "sg:city":"Madison",
    "sg:classifiers":[
        {
            "category":"Building & Trades",
            "subcategory":"Construction",
            "type":"Services"
        }
    ],
    "sg:phone":"+1 615 865 7454",
    "sg:postcode":"37115",
    "sg:province":"TN",
    "sg:tags":[
        "cleaning",
        "contractor"
    ],
    "wof:name":"Super Steam Cleaning",
    "wof:placetype":"venue"
},
  "geometry": {"coordinates":[-86.669359,36.235282],"type":"Point"}
}