{
  "type": "Feature",
  "properties": {
    "iso:country":"US",
    "sg:address":"1953 Madison St",
    "sg:city":"Clarksville",
    "sg:classifiers":[
        {
            "category":"Shopping",
            "subcategory":"Crafts & Fabrics",
            "type":"Retail Goods"
        }
    ],
    "sg:phone":"+1 931 551 3650",
    "sg:postcode":"37043",
    "sg:province":"TN",
    "sg:tags":[
        "sewing",
        "quilting",
        "tea",
        "material",
        "also",
        "smocking"
    ],
    "sg:website":"www.countryquilting.com",
    "wof:name":"Country Quilting",
    "wof:placetype":"venue"
},
  "geometry": {"coordinates":[-87.29765999999999,36.514405],"type":"Point"}
}