{
  "type": "Feature",
  "properties": {
    "iso:country":"US",
    "sg:address":"2017 Wilma Rudolph Blvd",
    "sg:city":"Clarksville",
    "sg:classifiers":[
        {
            "category":"Insurance",
            "subcategory":"Insurance Agent",
            "type":"Services"
        }
    ],
    "sg:phone":"+1 931 552 0359",
    "sg:postcode":"37040",
    "sg:province":"TN",
    "wof:name":"State Farm Insurance",
    "wof:placetype":"venue"
},
  "geometry": {"coordinates":[-87.31583500000001,36.560182],"type":"Point"}
}