{
  "type": "Feature",
  "properties": {
    "addr:full":"420 N Broadway Portland TN 37148",
    "addr:housenumber":"420",
    "addr:postcode":"37148",
    "addr:street":"N Broadway",
    "iso:country":"US",
    "sg:address":"420 N Broadway",
    "sg:city":"Portland",
    "sg:classifiers":[
        {
            "category":"Building & Trades",
            "subcategory":"Construction",
            "type":"Services"
        }
    ],
    "sg:phone":"+1 615 325 6530",
    "sg:postcode":"37148",
    "sg:province":"TN",
    "sg:tags":[
        "carpentry",
        "contractor"
    ],
    "wof:name":"Raines Cabinet",
    "wof:placetype":"venue"
},
  "geometry": {"coordinates":[-86.518671,36.584962],"type":"Point"}
}