{
  "type": "Feature",
  "properties": {
    "addr:full":"110 S Locust Ave Gallatin TN 37066",
    "addr:housenumber":"110",
    "addr:postcode":"37066",
    "addr:street":"S Locust Ave",
    "iso:country":"US",
    "sg:address":"110 S Locust Ave",
    "sg:city":"Gallatin",
    "sg:classifiers":[
        {
            "category":"Home & Garden",
            "subcategory":"Building Materials",
            "type":"Retail Goods"
        }
    ],
    "sg:phone":"+1 615 452 7410",
    "sg:postcode":"37066",
    "sg:province":"TN",
    "sg:tags":[
        "door"
    ],
    "wof:name":"Leath Sales",
    "wof:placetype":"venue"
},
  "geometry": {"coordinates":[-86.44908599999999,36.386523],"type":"Point"}
}