{
  "type": "Feature",
  "properties": {
    "iso:country":"US",
    "sg:address":"2709 Rifle Range Rd",
    "sg:city":"Knoxville",
    "sg:classifiers":[
        {
            "category":"Building & Trades",
            "subcategory":"Construction",
            "type":"Services"
        }
    ],
    "sg:phone":"+1 865 688 7266",
    "sg:postcode":"37918",
    "sg:province":"TN",
    "sg:tags":[
        "home",
        "improvement"
    ],
    "wof:name":"Residential Services",
    "wof:placetype":"venue"
},
  "geometry": {"coordinates":[-83.940652,36.049436],"type":"Point"}
}