{
  "type": "Feature",
  "properties": {
    "iso:country":"US",
    "sg:address":"1241 Birmingham Hwy",
    "sg:city":"Chattanooga",
    "sg:classifiers":[
        {
            "category":"Building & Trades",
            "subcategory":"Construction",
            "type":"Services"
        },
        {
            "category":"Home & Garden",
            "subcategory":"Building Materials",
            "type":"Retail Goods"
        },
        {
            "category":"Military Area",
            "subcategory":"Armory",
            "type":"Public Place"
        },
        {
            "category":"Manufacturing",
            "subcategory":"Building Materials",
            "type":"Manufacturing & Wholesale Goods"
        },
        {
            "category":"Sports & Exercise",
            "subcategory":"Swimming Pool",
            "type":"Entertainment"
        }
    ],
    "sg:phone":"+1 423 825 0513",
    "sg:postcode":"37419",
    "sg:province":"TN",
    "sg:tags":[
        "repair",
        "fence",
        "cover",
        "contractor",
        "vinyl",
        "gate",
        "accessory",
        "enclosure",
        "fence-sales"
    ],
    "sg:website":"http://www.fence.net",
    "wof:name":"Quality Fence Company",
    "wof:placetype":"venue"
},
  "geometry": {"coordinates":[-85.39244100000001,34.986038],"type":"Point"}
}