{
  "type": "Feature",
  "properties": {
    "addr:full":"1050 W Stone Dr Kingsport TN 37660",
    "addr:housenumber":"1050",
    "addr:postcode":"37660",
    "addr:street":"W Stone Dr",
    "iso:country":"US",
    "sg:address":"1050 W Stone Dr",
    "sg:city":"Kingsport",
    "sg:classifiers":[
        {
            "category":"Government",
            "subcategory":"Office",
            "type":"Public Place"
        }
    ],
    "sg:phone":"+1 423 247 6572",
    "sg:postcode":"37660",
    "sg:province":"TN",
    "sg:tags":[
        "federal",
        "security"
    ],
    "wof:name":"US Army National Guard Recruit",
    "wof:placetype":"venue"
},
  "geometry": {"coordinates":[-82.570126,36.559089],"type":"Point"}
}