{
  "type": "Feature",
  "properties": {
    "addr:full":"3040 Sinai Dr Mason TN 38049",
    "addr:postcode":"3040;38049",
    "addr:street":"Sinai Dr",
    "iso:country":"US",
    "sg:address":"3040 Sinai Dr",
    "sg:city":"Mason",
    "sg:classifiers":[
        {
            "category":"Organizations",
            "subcategory":"Religious Organization",
            "type":"Services"
        }
    ],
    "sg:phone":"+1 901 594 5059",
    "sg:postcode":"38049",
    "sg:province":"TN",
    "sg:tags":[
        "synagogue"
    ],
    "wof:name":"Tucker's Temple",
    "wof:placetype":"venue"
},
  "geometry": {"coordinates":[-89.505972,35.36923],"type":"Point"}
}