{
  "type": "Feature",
  "properties": {
    "iso:country":"US",
    "sg:address":"245 Greenbrier Rd",
    "sg:city":"Eads",
    "sg:classifiers":[
        {
            "category":"Home & Garden",
            "subcategory":"Home Furnishings",
            "type":"Retail Goods"
        }
    ],
    "sg:phone":"+1 901 465 0487",
    "sg:postcode":"38028",
    "sg:province":"TN",
    "sg:tags":[
        "new",
        "lighting"
    ],
    "wof:name":"Oldfashionedlampscom",
    "wof:placetype":"venue"
},
  "geometry": {"coordinates":[-89.61071699999999,35.240165],"type":"Point"}
}