{
  "type": "Feature",
  "properties": {
    "addr:full":"3030 Drummonds Rd Munford TN 38058",
    "addr:housenumber":"3030",
    "addr:postcode":"38058",
    "addr:street":"Drummonds Rd",
    "iso:country":"US",
    "sg:address":"3030 Drummonds Rd",
    "sg:city":"Munford",
    "sg:classifiers":[
        {
            "category":"Organizations",
            "subcategory":"Religious Organization",
            "type":"Services"
        }
    ],
    "sg:phone":"+1 901 837 6777",
    "sg:postcode":"38058",
    "sg:province":"TN",
    "sg:tags":[
        "church"
    ],
    "wof:name":"Life Way Baptist Fellowshp",
    "wof:placetype":"venue"
},
  "geometry": {"coordinates":[-89.872494,35.451032],"type":"Point"}
}