{
  "type": "Feature",
  "properties": {
    "iso:country":"US",
    "sg:address":"1779 Winfield Rd",
    "sg:city":"Memphis",
    "sg:classifiers":[
        {
            "category":"Freight",
            "type":"Transportation"
        }
    ],
    "sg:phone":"+1 901 346 1491",
    "sg:postcode":"38116",
    "sg:province":"TN",
    "sg:tags":[
        "operator",
        "local",
        "trucking"
    ],
    "wof:name":"Ray Tony Conley",
    "wof:placetype":"venue"
},
  "geometry": {"coordinates":[-90.00547,35.000089],"type":"Point"}
}