{
  "type": "Feature",
  "properties": {
    "iso:country":"US",
    "sg:address":"1010 Volunteer Dr",
    "sg:city":"Cookeville",
    "sg:classifiers":[
        {
            "category":"Manufacturing",
            "subcategory":"Metals",
            "type":"Manufacturing & Wholesale Goods"
        }
    ],
    "sg:phone":"+1 931 526 2137",
    "sg:postcode":"38506",
    "sg:province":"TN",
    "sg:tags":[
        "stamping"
    ],
    "wof:name":"APCOM Inc",
    "wof:placetype":"venue"
},
  "geometry": {"coordinates":[-85.48340399999999,36.187005],"type":"Point"}
}