{
  "type": "Feature",
  "properties": {
    "addr:full":"561 S Water Ave Gallatin TN 37066",
    "addr:housenumber":"561",
    "addr:postcode":"37066",
    "addr:street":"S Water Ave",
    "iso:country":"US",
    "sg:address":"561 S Water Ave",
    "sg:city":"Gallatin",
    "sg:classifiers":[
        {
            "category":"Health Services",
            "subcategory":"Clinic",
            "type":"Services"
        },
        {
            "category":"Health Services",
            "subcategory":"Doctor",
            "type":"Services"
        }
    ],
    "sg:phone":"+1 615 451 0093",
    "sg:postcode":"37066",
    "sg:province":"TN",
    "sg:tags":[
        "kidney",
        "dialysis",
        "center"
    ],
    "wof:name":"Dialysis Assoc of Gallatin",
    "wof:placetype":"venue"
},
  "geometry": {"coordinates":[-86.443111,36.379995],"type":"Point"}
}