{
  "type": "Feature",
  "properties": {
    "addr:full":"1310 Wolf Lair Dr Collierville TN 38017",
    "addr:housenumber":"1310",
    "addr:postcode":"38017",
    "addr:street":"Wolf Lair Dr",
    "iso:country":"US",
    "sg:address":"1310 Wolf Lair Dr",
    "sg:city":"Collierville",
    "sg:classifiers":[
        {
            "category":"Building & Trades",
            "subcategory":"Construction",
            "type":"Services"
        }
    ],
    "sg:phone":"+1 901 488 3445",
    "sg:postcode":"38017",
    "sg:province":"TN",
    "sg:tags":[
        "contractor",
        "carpenter",
        "carpentry"
    ],
    "wof:name":"Perkins' Trim & Carpentry",
    "wof:placetype":"venue"
},
  "geometry": {"coordinates":[-89.67401,35.075387],"type":"Point"}
}