{
  "type": "Feature",
  "properties": {
    "iso:country":"US",
    "sg:address":"211 Nim Rd",
    "sg:city":"Red Boiling Spgs",
    "sg:classifiers":[
        {
            "category":"Personal",
            "subcategory":"Beauty Salon",
            "type":"Services"
        }
    ],
    "sg:phone":"+1 615 699 2388",
    "sg:postcode":"37150",
    "sg:province":"TN",
    "wof:name":"D I's Designs",
    "wof:placetype":"venue"
},
  "geometry": {"coordinates":[-85.813332,36.544249],"type":"Point"}
}