{
  "type": "Feature",
  "properties": {
    "iso:country":"US",
    "sg:address":"3296 Cumberland Hills Cir NW",
    "sg:city":"Cleveland",
    "sg:classifiers":[
        {
            "category":"Restaurant",
            "type":"Food & Drink"
        }
    ],
    "sg:phone":"+1 423 476 2301",
    "sg:postcode":"37312",
    "sg:province":"TN",
    "wof:name":"Chuck Pat & Chas Burger",
    "wof:placetype":"venue"
},
  "geometry": {"coordinates":[-84.909189,35.193633],"type":"Point"}
}