{
  "type": "Feature",
  "properties": {
    "addr:full":"1500 W Poplar Ave Collierville TN 38017",
    "addr:housenumber":"1500",
    "addr:postcode":"38017",
    "addr:street":"W Poplar Ave",
    "iso:country":"US",
    "sg:address":"1500 W Poplar Ave",
    "sg:city":"Collierville",
    "sg:classifiers":[
        {
            "category":"Health Services",
            "subcategory":"Doctor",
            "type":"Services"
        }
    ],
    "sg:phone":"+1 901 850 1456",
    "sg:postcode":"38017",
    "sg:province":"TN",
    "sg:tags":[
        "physician",
        "surgeon"
    ],
    "sg:website":"www.westclinic.com",
    "wof:name":"West Clinic PC",
    "wof:placetype":"venue"
},
  "geometry": {"coordinates":[-89.712136,35.047246],"type":"Point"}
}