{
  "type": "Feature",
  "properties": {
    "addr:full":"908 Green Valley Rd Mount Juliet TN 37122",
    "addr:housenumber":"908",
    "addr:postcode":"37122",
    "addr:street":"Green Valley Rd",
    "iso:country":"US",
    "sg:address":"908 Green Valley Rd",
    "sg:city":"Mount Juliet",
    "sg:classifiers":[
        {
            "category":"Farming",
            "subcategory":"Orchard",
            "type":"Manufacturing & Wholesale Goods"
        }
    ],
    "sg:phone":"+1 615 758 7300",
    "sg:postcode":"37122",
    "sg:province":"TN",
    "sg:tags":[
        "fruit",
        "tree"
    ],
    "wof:name":"Finchs Nest Farm",
    "wof:placetype":"venue"
},
  "geometry": {"coordinates":[-86.54627600000001,36.262441],"type":"Point"}
}