{
  "type": "Feature",
  "properties": {
    "iso:country":"US",
    "sg:address":"1087 Little Swan Creek Rd",
    "sg:city":"Hohenwald",
    "sg:classifiers":[
        {
            "category":"Professional",
            "subcategory":"Management & Consulting",
            "type":"Services"
        }
    ],
    "sg:phone":"+1 931 796 1714",
    "sg:postcode":"38462",
    "sg:province":"TN",
    "wof:name":"Buffalo Ridge Enterprises",
    "wof:placetype":"venue"
},
  "geometry": {"coordinates":[-87.47184900000001,35.545726],"type":"Point"}
}