{
  "type": "Feature",
  "properties": {
    "addr:full":"2711 Simmons Rd Rives TN 38253",
    "addr:housenumber":"2711",
    "addr:postcode":"38253",
    "addr:street":"Simmons Rd",
    "iso:country":"US",
    "sg:address":"2711 Simmons Rd",
    "sg:city":"Rives",
    "sg:classifiers":[
        {
            "category":"Building & Trades",
            "subcategory":"Construction",
            "type":"Services"
        }
    ],
    "sg:phone":"+1 731 973 2273",
    "sg:postcode":"38253",
    "sg:province":"TN",
    "sg:tags":[
        "siding",
        "contractor"
    ],
    "wof:name":"Simmons Siding & Roofing",
    "wof:placetype":"venue"
},
  "geometry": {"coordinates":[-88.974386,36.275402],"type":"Point"}
}