{
  "type": "Feature",
  "properties": {
    "addr:full":"943 Foothills Mall Dr Maryville TN 37801",
    "addr:housenumber":"943",
    "addr:postcode":"37801",
    "addr:street":"Foothills Mall Dr",
    "iso:country":"US",
    "sg:address":"943 Foothills Mall Dr",
    "sg:city":"Maryville",
    "sg:classifiers":[
        {
            "category":"Home & Garden",
            "subcategory":"Building Materials",
            "type":"Retail Goods"
        }
    ],
    "sg:phone":"+1 865 983 6200",
    "sg:postcode":"37801",
    "sg:province":"TN",
    "sg:website":"www.homedepot.com",
    "wof:name":"Home Depot",
    "wof:placetype":"venue"
},
  "geometry": {"coordinates":[-83.99551700000001,35.752636],"type":"Point"}
}