{
  "type": "Feature",
  "properties": {
    "iso:country":"US",
    "sg:address":"651 Jefferson Ave",
    "sg:city":"Memphis",
    "sg:classifiers":[
        {
            "category":"Wholesale",
            "subcategory":"Groceries",
            "type":"Manufacturing & Wholesale Goods"
        }
    ],
    "sg:phone":"+1 901 523 9515",
    "sg:postcode":"38105",
    "sg:province":"TN",
    "wof:name":"Discount Grocery & Salvage",
    "wof:placetype":"venue"
},
  "geometry": {"coordinates":[-90.03973499999999,35.14376],"type":"Point"}
}