{
  "type": "Feature",
  "properties": {
    "iso:country":"US",
    "sg:address":"2862 Prince Dr",
    "sg:city":"Clarksville",
    "sg:classifiers":[
        {
            "category":"Shopping",
            "subcategory":"Clothing, Apparel, & Fashions",
            "type":"Retail Goods"
        }
    ],
    "sg:phone":"+1 931 358 5940",
    "sg:postcode":"37043",
    "sg:province":"TN",
    "wof:name":"Hit Enterprises Inc",
    "wof:placetype":"venue"
},
  "geometry": {"coordinates":[-87.246251,36.509213],"type":"Point"}
}