{
  "type": "Feature",
  "properties": {
    "iso:country":"US",
    "sg:address":"1 Trenton Hwy",
    "sg:city":"Dyer",
    "sg:classifiers":[
        {
            "category":"Organizations",
            "subcategory":"Community Association",
            "type":"Services"
        }
    ],
    "sg:phone":"+1 731 692 3690",
    "sg:postcode":"38330",
    "sg:province":"TN",
    "sg:tags":[
        "club"
    ],
    "wof:name":"Pine Crest Country Club",
    "wof:placetype":"venue"
},
  "geometry": {"coordinates":[-88.974676,36.040828],"type":"Point"}
}