{
  "type": "Feature",
  "properties": {
    "iso:country":"US",
    "sg:address":"40 Kay Cove",
    "sg:city":"Oakland",
    "sg:classifiers":[
        {
            "category":"Building & Trades",
            "subcategory":"Cleaning & Sanitation",
            "type":"Services"
        }
    ],
    "sg:phone":"+1 901 465 8160",
    "sg:postcode":"38060",
    "sg:province":"TN",
    "sg:tags":[
        "maintenance"
    ],
    "wof:name":"H Js Cleaning Service",
    "wof:placetype":"venue"
},
  "geometry": {"coordinates":[-89.50523699999999,35.211809],"type":"Point"}
}