{
  "type": "Feature",
  "properties": {
    "addr:full":"2600 Grandview Ave Nashville TN 37211",
    "addr:housenumber":"2600",
    "addr:postcode":"37211",
    "addr:street":"Grandview Ave",
    "iso:country":"US",
    "sg:address":"2600 Grandview Ave",
    "sg:city":"Nashville",
    "sg:classifiers":[
        {
            "category":"Restaurant",
            "type":"Food & Drink"
        }
    ],
    "sg:phone":"+1 615 242 9953",
    "sg:postcode":"37211",
    "sg:province":"TN",
    "wof:name":"Pop's Diner",
    "wof:placetype":"venue"
},
  "geometry": {"coordinates":[-86.74928800000001,36.116126],"type":"Point"}
}