{
  "type": "Feature",
  "properties": {
    "iso:country":"US",
    "sg:address":"1869 Lake Rd",
    "sg:city":"Greenbrier",
    "sg:classifiers":[
        {
            "category":"Building & Trades",
            "subcategory":"Plumbing",
            "type":"Services"
        }
    ],
    "sg:phone":"+1 615 335 9068",
    "sg:postcode":"37073",
    "sg:province":"TN",
    "sg:tags":[
        "contractor"
    ],
    "wof:name":"Walter Cress",
    "wof:placetype":"venue"
},
  "geometry": {"coordinates":[-86.762806,36.400071],"type":"Point"}
}