{
  "type": "Feature",
  "properties": {
    "iso:country":"US",
    "sg:address":"3913 Chapman Hwy",
    "sg:city":"Knoxville",
    "sg:classifiers":[
        {
            "category":"Shopping",
            "subcategory":"Hobbies, Toys, & Games",
            "type":"Retail Goods"
        }
    ],
    "sg:phone":"+1 865 573 6600",
    "sg:postcode":"37920",
    "sg:province":"TN",
    "sg:tags":[
        "supply"
    ],
    "wof:name":"Movies Games & More",
    "wof:placetype":"venue"
},
  "geometry": {"coordinates":[-83.908202,35.93792],"type":"Point"}
}