{
  "type": "Feature",
  "properties": {
    "iso:country":"US",
    "sg:address":"3341 US Hwy 11W",
    "sg:city":"Surgoinsville",
    "sg:classifiers":[
        {
            "category":"Autos & Motor Vehicles",
            "subcategory":"Auto Supplies",
            "type":"Retail Goods"
        }
    ],
    "sg:phone":"+1 423 345 3549",
    "sg:postcode":"37873",
    "sg:province":"TN",
    "sg:tags":[
        "automobile",
        "parts"
    ],
    "wof:name":"Mark's Auto Parts",
    "wof:placetype":"venue"
},
  "geometry": {"coordinates":[-82.840495,36.486704],"type":"Point"}
}