{
  "type": "Feature",
  "properties": {
    "iso:country":"US",
    "sg:address":"5517 Charlotte Pike",
    "sg:city":"Nashville",
    "sg:classifiers":[
        {
            "category":"Professional",
            "subcategory":"Accounting & Tax Preparation",
            "type":"Services"
        }
    ],
    "sg:phone":"+1 615 352 1372",
    "sg:postcode":"37209",
    "sg:province":"TN",
    "sg:tags":[
        "return",
        "filing"
    ],
    "wof:name":"Jackson Hewitt Tax Svc",
    "wof:placetype":"venue"
},
  "geometry": {"coordinates":[-86.85697,36.150335],"type":"Point"}
}