{
  "type": "Feature",
  "properties": {
    "addr:full":"130 Maple Ridge Ln Seymour TN 37865",
    "addr:housenumber":"130",
    "addr:postcode":"37865",
    "addr:street":"Maple Ridge Ln",
    "iso:country":"US",
    "sg:address":"130 Maple Ridge Ln",
    "sg:city":"Seymour",
    "sg:classifiers":[
        {
            "category":"Building & Trades",
            "subcategory":"Landscaping Services",
            "type":"Services"
        }
    ],
    "sg:phone":"+1 865 429 2011",
    "sg:postcode":"37865",
    "sg:province":"TN",
    "wof:name":"Genesis Lawn Care Inc",
    "wof:placetype":"venue"
},
  "geometry": {"coordinates":[-83.715457,35.898486],"type":"Point"}
}