{
  "type": "Feature",
  "properties": {
    "iso:country":"US",
    "sg:address":"508 E Broadway Blvd",
    "sg:city":"Jefferson City",
    "sg:classifiers":[
        {
            "category":"Restaurant",
            "type":"Food & Drink"
        }
    ],
    "sg:menulink":"http://www.allmenus.com/tn/jefferson-city/153826-zaxbys/menu/",
    "sg:phone":"+1 865 471 5511",
    "sg:postcode":"37760",
    "sg:province":"TN",
    "sg:tags":[
        "american",
        "wing"
    ],
    "wof:name":"Zaxby's",
    "wof:placetype":"venue"
},
  "geometry": {"coordinates":[-83.471611,36.125132],"type":"Point"}
}