{
  "type": "Feature",
  "properties": {
    "iso:country":"US",
    "sg:address":"814 Oliver Rd",
    "sg:city":"Knoxville",
    "sg:classifiers":[
        {
            "category":"Wholesale",
            "subcategory":"Non-durable Goods",
            "type":"Manufacturing & Wholesale Goods"
        },
        {
            "category":"Manufacturing",
            "subcategory":"Printing",
            "type":"Manufacturing & Wholesale Goods"
        }
    ],
    "sg:phone":"+1 865 573 6947",
    "sg:postcode":"37920",
    "sg:province":"TN",
    "sg:tags":[
        "decal"
    ],
    "wof:name":"Attention Getters By George",
    "wof:placetype":"venue"
},
  "geometry": {"coordinates":[-83.89762500000001,35.915203],"type":"Point"}
}