{
  "type": "Feature",
  "properties": {
    "iso:country":"US",
    "sg:address":"314 Depot St",
    "sg:city":"Soddy Daisy",
    "sg:classifiers":[
        {
            "category":"Organizations",
            "subcategory":"Religious Organization",
            "type":"Services"
        }
    ],
    "sg:phone":"+1 423 332 7416",
    "sg:postcode":"37379",
    "sg:province":"TN",
    "wof:name":"Good Shperd Otreach Ministries",
    "wof:placetype":"venue"
},
  "geometry": {"coordinates":[-85.164906,35.288712],"type":"Point"}
}