{
  "type": "Feature",
  "properties": {
    "iso:country":"US",
    "sg:address":"1317 Virginia Ave",
    "sg:city":"Bristol",
    "sg:classifiers":[
        {
            "category":"Food & Beverages",
            "subcategory":"Groceries & Convenience Stores",
            "type":"Retail Goods"
        }
    ],
    "sg:phone":"+1 423 968 5524",
    "sg:postcode":"37620",
    "sg:province":"TN",
    "sg:website":"www.foodcity.com",
    "wof:name":"Food City",
    "wof:placetype":"venue"
},
  "geometry": {"coordinates":[-82.167219,36.579841],"type":"Point"}
}