{
  "type": "Feature",
  "properties": {
    "iso:country":"US",
    "sg:address":"2542 N Main St",
    "sg:city":"Crossville",
    "sg:classifiers":[
        {
            "category":"Retail",
            "subcategory":"Portrait Studio",
            "type":"Services"
        }
    ],
    "sg:phone":"+1 931 456 7909",
    "sg:postcode":"38555",
    "sg:province":"TN",
    "sg:tags":[
        "photo"
    ],
    "wof:name":"Wal-Mart Prtrait Studio 00687",
    "wof:placetype":"venue"
},
  "geometry": {"coordinates":[-85.038439,35.980737],"type":"Point"}
}