{
  "type": "Feature",
  "properties": {
    "iso:country":"US",
    "sg:address":"2718 Pershing Ave",
    "sg:city":"Memphis",
    "sg:classifiers":[
        {
            "category":"Professional",
            "type":"Services"
        }
    ],
    "sg:phone":"+1 901 452 9224",
    "sg:postcode":"38112",
    "sg:province":"TN",
    "sg:tags":[
        "pond",
        "supply"
    ],
    "wof:name":"Iver's Pond",
    "wof:placetype":"venue"
},
  "geometry": {"coordinates":[-89.96861,35.153901],"type":"Point"}
}