{
  "type": "Feature",
  "properties": {
    "iso:country":"US",
    "sg:address":"1501 Socony Ln NW",
    "sg:city":"Knoxville",
    "sg:classifiers":[
        {
            "category":"Professional",
            "type":"Services"
        }
    ],
    "sg:phone":"+1 865 558 5764",
    "sg:postcode":"37909",
    "sg:province":"TN",
    "wof:name":"Charles Paarlberg",
    "wof:placetype":"venue"
},
  "geometry": {"coordinates":[-84.03528900000001,35.956483],"type":"Point"}
}