{
  "type": "Feature",
  "properties": {
    "iso:country":"US",
    "sg:address":"321 Harrison Ferry Rd",
    "sg:city":"Mc Minnville",
    "sg:classifiers":[
        {
            "category":"Building & Trades",
            "subcategory":"Construction",
            "type":"Services"
        }
    ],
    "sg:phone":"+1 931 473 7884",
    "sg:postcode":"37110",
    "sg:province":"TN",
    "sg:tags":[
        "product",
        "mfg"
    ],
    "wof:name":"Jimmy Yates",
    "wof:placetype":"venue"
},
  "geometry": {"coordinates":[-85.745411,35.667552],"type":"Point"}
}