{
  "type": "Feature",
  "properties": {
    "addr:full":"3703 Hixson Pike Chattanooga TN 37415",
    "addr:housenumber":"3703",
    "addr:postcode":"37415",
    "addr:street":"Hixson Pike",
    "iso:country":"US",
    "sg:address":"3703 Hixson Pike",
    "sg:city":"Chattanooga",
    "sg:classifiers":[
        {
            "category":"Social Services",
            "type":"Services"
        }
    ],
    "sg:phone":"+1 423 309 3906",
    "sg:postcode":"37415",
    "sg:province":"TN",
    "sg:tags":[
        "worker"
    ],
    "wof:name":"Cheryl Sevigney",
    "wof:placetype":"venue"
},
  "geometry": {"coordinates":[-85.271416,35.109144],"type":"Point"}
}