{
  "type": "Feature",
  "properties": {
    "addr:full":"9305 S Northshore Dr Knoxville TN 37922",
    "addr:housenumber":"9305",
    "addr:postcode":"37922",
    "addr:street":"S Northshore Dr",
    "iso:country":"US",
    "sg:address":"9305 S Northshore Dr",
    "sg:city":"Knoxville",
    "sg:classifiers":[
        {
            "category":"Utilities",
            "subcategory":"Mobile Phone",
            "type":"Services"
        }
    ],
    "sg:phone":"+1 865 212 4991",
    "sg:postcode":"37922",
    "sg:province":"TN",
    "sg:tags":[
        "radiotelephone"
    ],
    "wof:name":"Wireless Image LLC",
    "wof:placetype":"venue"
},
  "geometry": {"coordinates":[-84.060976,35.865262],"type":"Point"}
}