{
  "type": "Feature",
  "properties": {
    "addr:full":"1787 Bob Miles Rd Sharon TN 38255",
    "addr:housenumber":"1787",
    "addr:postcode":"38255",
    "addr:street":"Bob Miles Rd",
    "iso:country":"US",
    "sg:address":"1787 Bob Miles Rd",
    "sg:city":"Sharon",
    "sg:classifiers":[
        {
            "category":"Farming",
            "subcategory":"Farm",
            "type":"Manufacturing & Wholesale Goods"
        }
    ],
    "sg:phone":"+1 731 973 3923",
    "sg:postcode":"38255",
    "sg:province":"TN",
    "sg:tags":[
        "crop",
        "general"
    ],
    "wof:name":"Gail Edward Hall",
    "wof:placetype":"venue"
},
  "geometry": {"coordinates":[-88.93002300000001,36.260641],"type":"Point"}
}