{
  "type": "Feature",
  "properties": {
    "iso:country":"US",
    "sg:address":"190 Mosby Rd",
    "sg:city":"Oakland",
    "sg:classifiers":[
        {
            "category":"Building & Trades",
            "subcategory":"Landscaping Services",
            "type":"Services"
        }
    ],
    "sg:phone":"+1 901 465 5364",
    "sg:postcode":"38060",
    "sg:province":"TN",
    "sg:tags":[
        "lawn",
        "maintenance"
    ],
    "wof:name":"Clark's Lawn Care",
    "wof:placetype":"venue"
},
  "geometry": {"coordinates":[-89.48100700000001,35.160809],"type":"Point"}
}