{
  "type": "Feature",
  "properties": {
    "iso:country":"US",
    "sg:address":"602 S Congress Blvd",
    "sg:city":"Smithville",
    "sg:classifiers":[
        {
            "category":"Restaurant",
            "type":"Food & Drink"
        }
    ],
    "sg:menulink":"http://www.allmenus.com/tn/smithville/191745-sonic/menu/",
    "sg:phone":"+1 615 597 9494",
    "sg:postcode":"37166",
    "sg:province":"TN",
    "sg:tags":[
        "burger",
        "american"
    ],
    "wof:name":"Sonic",
    "wof:placetype":"venue"
},
  "geometry": {"coordinates":[-85.81132700000001,35.955285],"type":"Point"}
}