{
  "type": "Feature",
  "properties": {
    "iso:country":"US",
    "sg:address":"636 Lantana Rd",
    "sg:city":"Crossville",
    "sg:classifiers":[
        {
            "category":"Personal",
            "subcategory":"Beauty Salon",
            "type":"Services"
        }
    ],
    "sg:phone":"+1 931 456 6256",
    "sg:postcode":"38555",
    "sg:province":"TN",
    "wof:name":"Salon Twelve 13",
    "wof:placetype":"venue"
},
  "geometry": {"coordinates":[-85.0312,35.938529],"type":"Point"}
}