{
  "type": "Feature",
  "properties": {
    "iso:country":"US",
    "sg:address":"8141 Farmington Blvd",
    "sg:city":"Germantown",
    "sg:classifiers":[
        {
            "category":"Professional",
            "subcategory":"Management & Consulting",
            "type":"Services"
        }
    ],
    "sg:phone":"+1 901 624 3448",
    "sg:postcode":"38138",
    "sg:province":"TN",
    "wof:name":"Clare Grace & Associates Inc",
    "wof:placetype":"venue"
},
  "geometry": {"coordinates":[-89.79097,35.095379],"type":"Point"}
}