{
  "type": "Feature",
  "properties": {
    "addr:full":"7605 US Hwy 70 Memphis TN 38133",
    "addr:housenumber":"7605",
    "addr:postcode":"38133",
    "addr:street":"Us Hwy 70",
    "iso:country":"US",
    "sg:address":"7605 US Hwy 70",
    "sg:city":"Memphis",
    "sg:classifiers":[
        {
            "category":"Cinema",
            "subcategory":"Movie Rental",
            "type":"Entertainment"
        }
    ],
    "sg:phone":"+1 901 888 0315",
    "sg:postcode":"38133",
    "sg:province":"TN",
    "sg:tags":[
        "video",
        "tape"
    ],
    "wof:name":"Cinemagic Video",
    "wof:placetype":"venue"
},
  "geometry": {"coordinates":[-89.80310799999999,35.233567],"type":"Point"}
}