{
  "type": "Feature",
  "properties": {
    "iso:country":"US",
    "sg:address":"1413 Hatcher Ln",
    "sg:city":"Columbia",
    "sg:classifiers":[
        {
            "category":"Health Services",
            "subcategory":"Podiatrist",
            "type":"Services"
        }
    ],
    "sg:phone":"+1 931 388 9922",
    "sg:postcode":"38401",
    "sg:province":"TN",
    "wof:name":"Ann R Goranson DPM",
    "wof:placetype":"venue"
},
  "geometry": {"coordinates":[-87.060036,35.603795],"type":"Point"}
}