{
  "type": "Feature",
  "properties": {
    "iso:country":"US",
    "sg:address":"109 Noblitt St",
    "sg:city":"Shelbyville",
    "sg:classifiers":[
        {
            "category":"Retail",
            "subcategory":"Laundry & Dry Cleaning",
            "type":"Services"
        }
    ],
    "sg:phone":"+1 931 684 8992",
    "sg:postcode":"37160",
    "sg:province":"TN",
    "sg:tags":[
        "upholstery",
        "carpet"
    ],
    "wof:name":"J Friskey/M Shepherd",
    "wof:placetype":"venue"
},
  "geometry": {"coordinates":[-86.460317,35.493043],"type":"Point"}
}