{
  "type": "Feature",
  "properties": {
    "addr:full":"627 Grassland Dr Maryville TN 37804",
    "addr:housenumber":"627",
    "addr:postcode":"37804",
    "addr:street":"Grassland Dr",
    "iso:country":"US",
    "sg:address":"627 Grassland Dr",
    "sg:city":"Maryville",
    "sg:classifiers":[
        {
            "category":"Retail",
            "subcategory":"Laundry & Dry Cleaning",
            "type":"Services"
        }
    ],
    "sg:phone":"+1 865 982 7210",
    "sg:postcode":"37804",
    "sg:province":"TN",
    "sg:tags":[
        "linen",
        "supply"
    ],
    "wof:name":"Endless Possibilities Inc",
    "wof:placetype":"venue"
},
  "geometry": {"coordinates":[-83.925804,35.776292],"type":"Point"}
}