{
  "type": "Feature",
  "properties": {
    "iso:country":"US",
    "sg:address":"5415 Brainerd Rd",
    "sg:city":"Chattanooga",
    "sg:classifiers":[
        {
            "category":"Autos & Motor Vehicles",
            "subcategory":"Auto Supplies",
            "type":"Retail Goods"
        }
    ],
    "sg:phone":"+1 423 490 0380",
    "sg:postcode":"37411",
    "sg:province":"TN",
    "wof:name":"S & S Motors LLC",
    "wof:placetype":"venue"
},
  "geometry": {"coordinates":[-85.22131,35.010341],"type":"Point"}
}