{
  "type": "Feature",
  "properties": {
    "iso:country":"US",
    "sg:address":"4922 N Broadway St",
    "sg:city":"Knoxville",
    "sg:classifiers":[
        {
            "category":"Banks & Credit Unions",
            "subcategory":"Bank",
            "type":"Services"
        }
    ],
    "sg:phone":"+1 865 687 5570",
    "sg:postcode":"37918",
    "sg:province":"TN",
    "sg:tags":[
        "personal",
        "financing",
        "institution"
    ],
    "wof:name":"Citi Financial",
    "wof:placetype":"venue"
},
  "geometry": {"coordinates":[-83.92870499999999,36.029586],"type":"Point"}
}