{
  "type": "Feature",
  "properties": {
    "iso:country":"US",
    "sg:address":"929 Acklen Ave",
    "sg:city":"Nashville",
    "sg:classifiers":[
        {
            "category":"Building & Trades",
            "subcategory":"Construction",
            "type":"Services"
        }
    ],
    "sg:phone":"+1 615 210 2210",
    "sg:postcode":"37203",
    "sg:province":"TN",
    "sg:tags":[
        "home",
        "improvement"
    ],
    "wof:name":"Turner Turner & Turner",
    "wof:placetype":"venue"
},
  "geometry": {"coordinates":[-86.78325599999999,36.133647],"type":"Point"}
}