{
  "type": "Feature",
  "properties": {
    "iso:country":"US",
    "sg:address":"503 Bohannon Ave",
    "sg:city":"Greeneville",
    "sg:classifiers":[
        {
            "category":"Manufacturing",
            "subcategory":"Metals",
            "type":"Manufacturing & Wholesale Goods"
        }
    ],
    "sg:phone":"+1 423 787 8800",
    "sg:postcode":"37745",
    "sg:province":"TN",
    "sg:tags":[
        "lock",
        "safe",
        "coin",
        "vault"
    ],
    "sg:website":"www.centuryproductsonline.com",
    "wof:name":"Hurd Corporation",
    "wof:placetype":"venue"
},
  "geometry": {"coordinates":[-82.811739,36.176953],"type":"Point"}
}