{
  "type": "Feature",
  "properties": {
    "addr:full":"72 Jefferson Ave Memphis TN 38103",
    "addr:housenumber":"72",
    "addr:postcode":"38103",
    "addr:street":"Jefferson Ave",
    "iso:country":"US",
    "sg:address":"72 Jefferson Ave",
    "sg:city":"Memphis",
    "sg:classifiers":[
        {
            "category":"Shopping",
            "subcategory":"Clothing, Apparel, & Fashions",
            "type":"Retail Goods"
        }
    ],
    "sg:phone":"+1 901 578 7577",
    "sg:postcode":"38103",
    "sg:province":"TN",
    "sg:tags":[
        "tailoring",
        "alteration"
    ],
    "wof:name":"Genevas Tlrg & Alterations",
    "wof:placetype":"venue"
},
  "geometry": {"coordinates":[-90.052364,35.147393],"type":"Point"}
}