{
  "type": "Feature",
  "properties": {
    "iso:country":"US",
    "sg:address":"7043 Naples Dr",
    "sg:city":"Cordova",
    "sg:classifiers":[
        {
            "category":"Personal",
            "subcategory":"Beauty Salon",
            "type":"Services"
        }
    ],
    "sg:phone":"+1 901 465 0006",
    "sg:postcode":"38018",
    "sg:province":"TN",
    "wof:name":"Positive Image Salon",
    "wof:placetype":"venue"
},
  "geometry": {"coordinates":[-89.826707,35.15499],"type":"Point"}
}