{
  "type": "Feature",
  "properties": {
    "iso:country":"US",
    "sg:address":"112 S Water Ave",
    "sg:city":"Gallatin",
    "sg:classifiers":[
        {
            "category":"Home & Garden",
            "subcategory":"Carpets & Floor Coverings",
            "type":"Retail Goods"
        }
    ],
    "sg:phone":"+1 615 452 2018",
    "sg:postcode":"37066",
    "sg:province":"TN",
    "wof:name":"Carpet Store",
    "wof:placetype":"venue"
},
  "geometry": {"coordinates":[-86.44617599999999,36.387517],"type":"Point"}
}