{
  "type": "Feature",
  "properties": {
    "iso:country":"US",
    "sg:address":"7421 Commons Blvd",
    "sg:city":"Chattanooga",
    "sg:classifiers":[
        {
            "category":"Home & Garden",
            "subcategory":"Building Materials",
            "type":"Retail Goods"
        }
    ],
    "sg:phone":"+1 423 499 4980",
    "sg:postcode":"37421",
    "sg:province":"TN",
    "sg:website":"www.homedepot.com",
    "wof:name":"Home Depot",
    "wof:placetype":"venue"
},
  "geometry": {"coordinates":[-85.149974,35.036175],"type":"Point"}
}