{
  "type": "Feature",
  "properties": {
    "addr:full":"1110 Jackson Love Hwy Erwin TN 37650",
    "addr:housenumber":"1110",
    "addr:postcode":"37650",
    "addr:street":"Jackson Love Hwy",
    "iso:country":"US",
    "sg:address":"1110 Jackson Love Hwy",
    "sg:city":"Erwin",
    "sg:classifiers":[
        {
            "category":"Autos & Motor Vehicles",
            "subcategory":"Automobile Sales",
            "type":"Retail Goods"
        }
    ],
    "sg:phone":"+1 423 743 9585",
    "sg:postcode":"37650",
    "sg:province":"TN",
    "sg:tags":[
        "station",
        "gasoline",
        "used"
    ],
    "wof:name":"Exxon",
    "wof:placetype":"venue"
},
  "geometry": {"coordinates":[-82.421063,36.129352],"type":"Point"}
}