{
  "type": "Feature",
  "properties": {
    "iso:country":"US",
    "sg:address":"11511 Lebanon Rd",
    "sg:city":"Mount Juliet",
    "sg:classifiers":[
        {
            "category":"Banks & Credit Unions",
            "subcategory":"Bank",
            "type":"Services"
        }
    ],
    "sg:phone":"+1 615 758 7650",
    "sg:postcode":"37122",
    "sg:province":"TN",
    "sg:tags":[
        "depository",
        "banking",
        "se",
        "institution",
        "business"
    ],
    "wof:name":"Capitol Cash",
    "wof:placetype":"venue"
},
  "geometry": {"coordinates":[-86.518665,36.231068],"type":"Point"}
}