{
  "type": "Feature",
  "properties": {
    "addr:full":"224 Mount Area Dr Bristol TN 37620",
    "addr:housenumber":"224",
    "addr:postcode":"37620",
    "addr:street":"Mount Area Dr",
    "iso:country":"US",
    "sg:address":"224 Mount Area Dr",
    "sg:city":"Bristol",
    "sg:classifiers":[
        {
            "category":"Education",
            "subcategory":"School",
            "type":"Public Place"
        }
    ],
    "sg:phone":"+1 423 354 1675",
    "sg:postcode":"37620",
    "sg:province":"TN",
    "wof:name":"Akard Elementary School",
    "wof:placetype":"venue"
},
  "geometry": {"coordinates":[-82.256243,36.565053],"type":"Point"}
}