{
  "type": "Feature",
  "properties": {
    "iso:country":"US",
    "sg:address":"841 Union St",
    "sg:city":"Shelbyville",
    "sg:classifiers":[
        {
            "category":"Health Services",
            "subcategory":"Doctor",
            "type":"Services"
        }
    ],
    "sg:phone":"+1 931 684 8029",
    "sg:postcode":"37160",
    "sg:province":"TN",
    "sg:tags":[
        "physician",
        "surgeon"
    ],
    "wof:name":"Alex Fider MD",
    "wof:placetype":"venue"
},
  "geometry": {"coordinates":[-86.47391,35.495894],"type":"Point"}
}