{
  "type": "Feature",
  "properties": {
    "addr:full":"504 Princeton Rd Johnson City TN 37601",
    "addr:housenumber":"504",
    "addr:postcode":"37601",
    "addr:street":"Princeton Rd",
    "iso:country":"US",
    "sg:address":"504 Princeton Rd",
    "sg:city":"Johnson City",
    "sg:classifiers":[
        {
            "category":"Social Services",
            "subcategory":"Child Care",
            "type":"Services"
        }
    ],
    "sg:phone":"+1 423 283 4549",
    "sg:postcode":"37601",
    "sg:province":"TN",
    "wof:name":"Princeton Prep",
    "wof:placetype":"venue"
},
  "geometry": {"coordinates":[-82.36446599999999,36.360108],"type":"Point"}
}