{
  "type": "Feature",
  "properties": {
    "iso:country":"US",
    "sg:address":"668 S Main St",
    "sg:city":"Memphis",
    "sg:classifiers":[
        {
            "category":"Animal Shelter",
            "type":"Public Place"
        },
        {
            "category":"Retail",
            "subcategory":"Veterinary Services",
            "type":"Services"
        },
        {
            "category":"Retail",
            "subcategory":"Animal Services",
            "type":"Services"
        }
    ],
    "sg:phone":"+1 901 590 1228",
    "sg:postcode":"38103",
    "sg:province":"TN",
    "sg:tags":[
        "pet",
        "hospital",
        "clinic",
        "veterinarian",
        "grooming",
        "kennel"
    ],
    "sg:website":"http://www.berclairvet.com",
    "wof:name":"Berclair Downtown Animal Hospital",
    "wof:placetype":"venue"
},
  "geometry": {"coordinates":[-90.059059,35.129292],"type":"Point"}
}