{
  "type": "Feature",
  "properties": {
    "iso:country":"US",
    "sg:address":"31 S Court St",
    "sg:city":"Alamo",
    "sg:classifiers":[
        {
            "category":"Restaurant",
            "type":"Food & Drink"
        }
    ],
    "sg:phone":"+1 731 696 5938",
    "sg:postcode":"38001",
    "sg:province":"TN",
    "sg:tags":[
        "eating"
    ],
    "wof:name":"Kountry Kitchen",
    "wof:placetype":"venue"
},
  "geometry": {"coordinates":[-89.11702,35.784734],"type":"Point"}
}