{
  "type": "Feature",
  "properties": {
    "iso:country":"US",
    "sg:address":"104 E Commercial Ave",
    "sg:city":"Monterey",
    "sg:classifiers":[
        {
            "category":"Shopping",
            "subcategory":"Florist",
            "type":"Retail Goods"
        }
    ],
    "sg:phone":"+1 931 839 2113",
    "sg:postcode":"38574",
    "sg:province":"TN",
    "sg:tags":[
        "sewing",
        "merchandise"
    ],
    "wof:name":"Reba's Flower Shop",
    "wof:placetype":"venue"
},
  "geometry": {"coordinates":[-85.267979,36.147843],"type":"Point"}
}