{
  "type": "Feature",
  "properties": {
    "iso:country":"US",
    "sg:address":"1920 Madison St",
    "sg:city":"Clarksville",
    "sg:classifiers":[
        {
            "category":"Education",
            "subcategory":"School",
            "type":"Public Place"
        }
    ],
    "sg:phone":"+1 931 648 5685",
    "sg:postcode":"37043",
    "sg:province":"TN",
    "sg:website":"www.cmcss.net",
    "wof:name":"Barksdale Elementary School",
    "wof:placetype":"venue"
},
  "geometry": {"coordinates":[-87.30185299999999,36.514407],"type":"Point"}
}