{
  "type": "Feature",
  "properties": {
    "iso:country":"US",
    "sg:address":"343 Sagewood Dr",
    "sg:city":"Morristown",
    "sg:classifiers":[
        {
            "category":"Professional",
            "subcategory":"Accounting & Tax Preparation",
            "type":"Services"
        }
    ],
    "sg:phone":"+1 423 317 9990",
    "sg:postcode":"37813",
    "sg:province":"TN",
    "sg:tags":[
        "return"
    ],
    "wof:name":"Griffith Business & Tax Servic",
    "wof:placetype":"venue"
},
  "geometry": {"coordinates":[-83.277736,36.16308],"type":"Point"}
}