{
  "type": "Feature",
  "properties": {
    "addr:full":"6210 Hixson Pike Hixson TN 37343",
    "addr:housenumber":"6210",
    "addr:postcode":"37343",
    "addr:street":"Hixson Pike",
    "iso:country":"US",
    "sg:address":"6210 Hixson Pike",
    "sg:city":"Hixson",
    "sg:classifiers":[
        {
            "category":"Restaurant",
            "type":"Food & Drink"
        }
    ],
    "sg:menulink":"http://www.allmenus.com/tn/chattanooga/140247-subway/menu/",
    "sg:phone":"+1 423 847 9353",
    "sg:postcode":"37343",
    "sg:province":"TN",
    "sg:tags":[
        "american",
        "sandwich"
    ],
    "wof:name":"Subway",
    "wof:placetype":"venue"
},
  "geometry": {"coordinates":[-85.200661,35.152162],"type":"Point"}
}