{
  "type": "Feature",
  "properties": {
    "iso:country":"US",
    "sg:address":"5217 Maryland Way",
    "sg:city":"Brentwood",
    "sg:classifiers":[
        {
            "category":"Professional",
            "subcategory":"Lawyer & Legal Services",
            "type":"Services"
        }
    ],
    "sg:phone":"+1 615 248 0051",
    "sg:postcode":"37027",
    "sg:province":"TN",
    "sg:tags":[
        "attorney"
    ],
    "wof:name":"Jackson Law Office",
    "wof:placetype":"venue"
},
  "geometry": {"coordinates":[-86.80589000000001,36.035228],"type":"Point"}
}