{
  "type": "Feature",
  "properties": {
    "addr:full":"815 W Summer St Greeneville TN 37743",
    "addr:housenumber":"815",
    "addr:postcode":"37743",
    "addr:street":"W Summer St",
    "iso:country":"US",
    "sg:address":"815 W Summer St",
    "sg:city":"Greeneville",
    "sg:classifiers":[
        {
            "category":"Government",
            "subcategory":"Office",
            "type":"Public Place"
        }
    ],
    "sg:phone":"+1 423 798 1720",
    "sg:postcode":"37743",
    "sg:province":"TN",
    "wof:name":"Greene County Emergency Mdcl",
    "wof:placetype":"venue"
},
  "geometry": {"coordinates":[-82.846671,36.166892],"type":"Point"}
}