{
  "type": "Feature",
  "properties": {
    "iso:country":"US",
    "sg:address":"807 3rd Ave S",
    "sg:city":"Nashville",
    "sg:classifiers":[
        {
            "category":"Professional",
            "subcategory":"Advertising",
            "type":"Services"
        }
    ],
    "sg:phone":"+1 615 256 3393",
    "sg:postcode":"37210",
    "sg:province":"TN",
    "sg:tags":[
        "studio"
    ],
    "sg:website":"www.harmongrp.com",
    "wof:name":"Harmon Group",
    "wof:placetype":"venue"
},
  "geometry": {"coordinates":[-86.770089,36.151945],"type":"Point"}
}