{
  "type": "Feature",
  "properties": {
    "iso:country":"US",
    "sg:address":"3613 7th Ave",
    "sg:city":"Chattanooga",
    "sg:classifiers":[
        {
            "category":"Organizations",
            "subcategory":"Religious Organization",
            "type":"Services"
        }
    ],
    "sg:phone":"+1 423 867 4406",
    "sg:postcode":"37407",
    "sg:province":"TN",
    "sg:tags":[
        "church"
    ],
    "wof:name":"Calvery Church Of God",
    "wof:placetype":"venue"
},
  "geometry": {"coordinates":[-85.28462399999999,35.00092],"type":"Point"}
}