{
  "type": "Feature",
  "properties": {
    "addr:full":"351 Harding Pl Nashville TN 37211",
    "addr:housenumber":"351",
    "addr:postcode":"37211",
    "addr:street":"Harding Pl",
    "iso:country":"US",
    "sg:address":"351 Harding Pl",
    "sg:city":"Nashville",
    "sg:classifiers":[
        {
            "category":"Food & Beverages",
            "subcategory":"Groceries & Convenience Stores",
            "type":"Retail Goods"
        }
    ],
    "sg:phone":"+1 615 331 2768",
    "sg:postcode":"37211",
    "sg:province":"TN",
    "wof:name":"Taylor Mart",
    "wof:placetype":"venue"
},
  "geometry": {"coordinates":[-86.70171499999999,36.085473],"type":"Point"}
}