{
  "type": "Feature",
  "properties": {
    "iso:country":"US",
    "sg:address":"1040 Wildlife Trl",
    "sg:city":"Kingston Springs",
    "sg:classifiers":[
        {
            "category":"Real Estate",
            "subcategory":"Real Estate Operator",
            "type":"Services"
        }
    ],
    "sg:phone":"+1 615 952 4809",
    "sg:postcode":"37082",
    "sg:province":"TN",
    "sg:tags":[
        "building",
        "nonresidential"
    ],
    "wof:name":"Dream Property",
    "wof:placetype":"venue"
},
  "geometry": {"coordinates":[-87.15635,36.061859],"type":"Point"}
}