{
  "type": "Feature",
  "properties": {
    "iso:country":"US",
    "sg:address":"8418 Kingston Pike",
    "sg:city":"Knoxville",
    "sg:classifiers":[
        {
            "category":"Retail",
            "subcategory":"Auto Repair",
            "type":"Services"
        }
    ],
    "sg:phone":"+1 865 691 1558",
    "sg:postcode":"37919",
    "sg:province":"TN",
    "sg:tags":[
        "body",
        "automobile",
        "painting"
    ],
    "wof:name":"Greater Knoxville Auto Paintng",
    "wof:placetype":"venue"
},
  "geometry": {"coordinates":[-84.06420799999999,35.921547],"type":"Point"}
}