{
  "type": "Feature",
  "properties": {
    "iso:country":"US",
    "sg:address":"1257 Heathcliff Dr",
    "sg:city":"Memphis",
    "sg:classifiers":[
        {
            "category":"Organizations",
            "subcategory":"Community Association",
            "type":"Services"
        }
    ],
    "sg:phone":"+1 901 372 3768",
    "sg:postcode":"38134",
    "sg:province":"TN",
    "sg:tags":[
        "youth",
        "development"
    ],
    "wof:name":"Youth Empowerment Services",
    "wof:placetype":"venue"
},
  "geometry": {"coordinates":[-89.85380600000001,35.159117],"type":"Point"}
}