{
  "type": "Feature",
  "properties": {
    "iso:country":"US",
    "sg:address":"4000 Andrew Jackson Pkwy",
    "sg:city":"Hermitage",
    "sg:classifiers":[
        {
            "category":"Sports & Exercise",
            "subcategory":"Golf",
            "type":"Entertainment"
        },
        {
            "category":"Recreation",
            "type":"Entertainment"
        }
    ],
    "sg:phone":"+1 615 883 5200",
    "sg:postcode":"37138",
    "sg:province":"TN",
    "sg:tags":[
        "course",
        "sporting",
        "practice",
        "range",
        "public"
    ],
    "wof:name":"Hermitage Golf Learning Center",
    "wof:placetype":"venue"
},
  "geometry": {"coordinates":[-86.609832,36.184958],"type":"Point"}
}