{
  "type": "Feature",
  "properties": {
    "iso:country":"US",
    "sg:address":"2918 Amesbury Dr",
    "sg:city":"Morristown",
    "sg:classifiers":[
        {
            "category":"Building & Trades",
            "subcategory":"Construction",
            "type":"Services"
        }
    ],
    "sg:phone":"+1 423 587 6711",
    "sg:postcode":"37814",
    "sg:province":"TN",
    "sg:tags":[
        "residential"
    ],
    "wof:name":"Harold Knight Properties",
    "wof:placetype":"venue"
},
  "geometry": {"coordinates":[-83.33613200000001,36.210754],"type":"Point"}
}