{
  "type": "Feature",
  "properties": {
    "iso:country":"US",
    "sg:address":"233 W Main St",
    "sg:city":"Johnson City",
    "sg:classifiers":[
        {
            "category":"Shopping",
            "subcategory":"Used Merchandise",
            "type":"Retail Goods"
        }
    ],
    "sg:phone":"+1 423 928 3882",
    "sg:postcode":"37604",
    "sg:province":"TN",
    "wof:name":"Bowers Title & Pawn",
    "wof:placetype":"venue"
},
  "geometry": {"coordinates":[-82.355705,36.316493],"type":"Point"}
}