{
  "type": "Feature",
  "properties": {
    "iso:country":"US",
    "sg:address":"4060 S Plaza Dr",
    "sg:city":"Memphis",
    "sg:classifiers":[
        {
            "category":"Shopping",
            "subcategory":"Department Store",
            "type":"Retail Goods"
        }
    ],
    "sg:phone":"+1 901 398 8235",
    "sg:postcode":"38116",
    "sg:province":"TN",
    "wof:name":"Dollar Days Inc",
    "wof:placetype":"venue"
},
  "geometry": {"coordinates":[-90.02663200000001,35.036465],"type":"Point"}
}