{
  "type": "Feature",
  "properties": {
    "addr:full":"119 Dameron Ave Knoxville TN 37917",
    "addr:housenumber":"119",
    "addr:postcode":"37917",
    "addr:street":"Dameron Ave",
    "iso:country":"US",
    "sg:address":"119 Dameron Ave",
    "sg:city":"Knoxville",
    "sg:classifiers":[
        {
            "category":"Social Services",
            "type":"Services"
        }
    ],
    "sg:phone":"+1 865 522 6341",
    "sg:postcode":"37917",
    "sg:province":"TN",
    "sg:tags":[
        "organization",
        "welfare"
    ],
    "wof:name":"Ladies Of Charity",
    "wof:placetype":"venue"
},
  "geometry": {"coordinates":[-83.92743900000001,35.978758],"type":"Point"}
}