{
  "type": "Feature",
  "properties": {
    "iso:country":"US",
    "sg:address":"3384 Austin Peay Hwy",
    "sg:city":"Memphis",
    "sg:classifiers":[
        {
            "category":"Utilities",
            "subcategory":"Telephone",
            "type":"Services"
        },
        {
            "category":"Manufacturing",
            "subcategory":"Electronics",
            "type":"Manufacturing & Wholesale Goods"
        },
        {
            "category":"Communications",
            "type":"Services"
        }
    ],
    "sg:phone":"+1 901 372 4922",
    "sg:postcode":"38128",
    "sg:province":"TN",
    "sg:tags":[
        "telecommunications-equipment",
        "systems-repair",
        "supply",
        "system",
        "equipment",
        "paging",
        "signaling"
    ],
    "wof:name":"Powertel Inc",
    "wof:placetype":"venue"
},
  "geometry": {"coordinates":[-89.912401,35.21792],"type":"Point"}
}