{
  "type": "Feature",
  "properties": {
    "iso:country":"US",
    "sg:address":"122 Front St",
    "sg:city":"Smyrna",
    "sg:classifiers":[
        {
            "category":"Social Services",
            "subcategory":"Child Care",
            "type":"Services"
        }
    ],
    "sg:phone":"+1 615 355 8373",
    "sg:postcode":"37167",
    "sg:province":"TN",
    "wof:name":"Lil' Angels",
    "wof:placetype":"venue"
},
  "geometry": {"coordinates":[-86.51890400000001,35.980892],"type":"Point"}
}