{
  "type": "Feature",
  "properties": {
    "iso:country":"US",
    "sg:address":"430 Baugh Hollow Ln",
    "sg:city":"Gainesboro",
    "sg:classifiers":[
        {
            "category":"Autos & Motor Vehicles",
            "subcategory":"Fuel & Gas Station",
            "type":"Retail Goods"
        }
    ],
    "sg:phone":"+1 931 268 2121",
    "sg:postcode":"38562",
    "sg:province":"TN",
    "sg:tags":[
        "oil"
    ],
    "wof:name":"Smith Bp",
    "wof:placetype":"venue"
},
  "geometry": {"coordinates":[-85.64653,36.356801],"type":"Point"}
}