{
  "type": "Feature",
  "properties": {
    "addr:full":"6861 Tazewell Hwy Sneedville TN 37869",
    "addr:housenumber":"6861",
    "addr:postcode":"37869",
    "addr:street":"Tazewell Hwy",
    "iso:country":"US",
    "sg:address":"6861 Tazewell Hwy",
    "sg:city":"Sneedville",
    "sg:classifiers":[
        {
            "category":"Shopping",
            "type":"Retail Goods"
        }
    ],
    "sg:phone":"+1 423 733 0029",
    "sg:postcode":"37869",
    "sg:province":"TN",
    "sg:tags":[
        "merchandise"
    ],
    "wof:name":"Tennessee Boxers",
    "wof:placetype":"venue"
},
  "geometry": {"coordinates":[-83.23521599999999,36.509734],"type":"Point"}
}