{
  "type": "Feature",
  "properties": {
    "iso:country":"US",
    "sg:address":"888 US Hwy 51 N",
    "sg:city":"Covington",
    "sg:classifiers":[
        {
            "category":"Sports & Exercise",
            "subcategory":"Bowling",
            "type":"Entertainment"
        }
    ],
    "sg:phone":"+1 901 476 3300",
    "sg:postcode":"38019",
    "sg:province":"TN",
    "sg:tags":[
        "center"
    ],
    "wof:name":"Rollie's Lanes",
    "wof:placetype":"venue"
},
  "geometry": {"coordinates":[-89.643248,35.577283],"type":"Point"}
}