{
  "type": "Feature",
  "properties": {
    "iso:country":"US",
    "sg:address":"100 N Main St",
    "sg:city":"Memphis",
    "sg:classifiers":[
        {
            "category":"Parking",
            "type":"Transportation"
        }
    ],
    "sg:phone":"+1 901 526 0655",
    "sg:postcode":"38103",
    "sg:province":"TN",
    "sg:tags":[
        "garage"
    ],
    "wof:name":"Allright System Parking Inc",
    "wof:placetype":"venue"
},
  "geometry": {"coordinates":[-90.051801,35.147461],"type":"Point"}
}