{
  "type": "Feature",
  "properties": {
    "addr:full":"329 Mc Kennell Dr Nashville TN 37206",
    "addr:housenumber":"329",
    "addr:postcode":"37206",
    "addr:street":"Mc Kennell Dr",
    "iso:country":"US",
    "sg:address":"329 Mc Kennell Dr",
    "sg:city":"Nashville",
    "sg:classifiers":[
        {
            "category":"Manufacturing",
            "subcategory":"Printing",
            "type":"Manufacturing & Wholesale Goods"
        }
    ],
    "sg:phone":"+1 615 227 8284",
    "sg:postcode":"37206",
    "sg:province":"TN",
    "sg:tags":[
        "printer"
    ],
    "wof:name":"D & B Printer Svc",
    "wof:placetype":"venue"
},
  "geometry": {"coordinates":[-86.719594,36.191336],"type":"Point"}
}