{
  "type": "Feature",
  "properties": {
    "iso:country":"US",
    "sg:address":"1890 N Germantown Pkwy",
    "sg:city":"Cordova",
    "sg:classifiers":[
        {
            "category":"Home & Garden",
            "subcategory":"Furniture",
            "type":"Retail Goods"
        }
    ],
    "sg:phone":"+1 901 757 9292",
    "sg:postcode":"38016",
    "sg:province":"TN",
    "sg:tags":[
        "mattress"
    ],
    "wof:name":"Mattress Value Place",
    "wof:placetype":"venue"
},
  "geometry": {"coordinates":[-89.792793,35.176849],"type":"Point"}
}