{
  "type": "Feature",
  "properties": {
    "iso:country":"US",
    "sg:address":"929 Dunsinane Rd",
    "sg:city":"Signal Mountain",
    "sg:classifiers":[
        {
            "category":"Social Services",
            "subcategory":"Job Training",
            "type":"Services"
        }
    ],
    "sg:phone":"+1 423 886 9863",
    "sg:postcode":"37377",
    "sg:province":"TN",
    "sg:tags":[
        "management"
    ],
    "wof:name":"Workforce Development Assn",
    "wof:placetype":"venue"
},
  "geometry": {"coordinates":[-85.33979600000001,35.14347],"type":"Point"}
}