{
  "type": "Feature",
  "properties": {
    "iso:country":"US",
    "sg:address":"2045 US Hwy 70 Byp",
    "sg:city":"Camden",
    "sg:classifiers":[
        {
            "category":"Manufacturing",
            "subcategory":"Building Materials",
            "type":"Manufacturing & Wholesale Goods"
        },
        {
            "category":"Manufacturing",
            "subcategory":"Lumber",
            "type":"Manufacturing & Wholesale Goods"
        }
    ],
    "sg:phone":"+1 731 584 2771",
    "sg:postcode":"38320",
    "sg:province":"TN",
    "sg:tags":[
        "hardwood",
        "mills",
        "dimension",
        "flooring",
        "mfg"
    ],
    "wof:name":"R Ana J Hardwood Products",
    "wof:placetype":"venue"
},
  "geometry": {"coordinates":[-88.10275300000001,36.031113],"type":"Point"}
}