{
  "type": "Feature",
  "properties": {
    "iso:country":"US",
    "sg:address":"143 Lexington St S",
    "sg:city":"Bruceton",
    "sg:classifiers":[
        {
            "category":"Recreation",
            "type":"Entertainment"
        }
    ],
    "sg:phone":"+1 731 586 2133",
    "sg:postcode":"38317",
    "sg:province":"TN",
    "sg:tags":[
        "parlor",
        "billiard"
    ],
    "wof:name":"Jim's Recreation Hall",
    "wof:placetype":"venue"
},
  "geometry": {"coordinates":[-88.24533,36.034384],"type":"Point"}
}