{
  "type": "Feature",
  "properties": {
    "addr:full":"21 N Main St Memphis TN 38103",
    "addr:housenumber":"21",
    "addr:postcode":"38103",
    "addr:street":"N Main St",
    "iso:country":"US",
    "sg:address":"21 N Main St",
    "sg:city":"Memphis",
    "sg:classifiers":[
        {
            "category":"Restaurant",
            "type":"Food & Drink"
        }
    ],
    "sg:menulink":"http://www.allmenus.com/tn/memphis/116194-quiznos-sub/menu/",
    "sg:phone":"+1 901 528 5000",
    "sg:postcode":"38103",
    "sg:province":"TN",
    "sg:tags":[
        "wrap",
        "american",
        "sandwich"
    ],
    "wof:name":"Quiznos Sub",
    "wof:placetype":"venue"
},
  "geometry": {"coordinates":[-90.052897,35.146012],"type":"Point"}
}