{
  "type": "Feature",
  "properties": {
    "iso:country":"US",
    "sg:address":"130 Gladwood Rd",
    "sg:city":"Clinton",
    "sg:classifiers":[
        {
            "category":"Personal",
            "subcategory":"Beauty Salon",
            "type":"Services"
        }
    ],
    "sg:phone":"+1 865 457 2822",
    "sg:postcode":"37716",
    "sg:province":"TN",
    "wof:name":"Jeanne Richardson Hair Design",
    "wof:placetype":"venue"
},
  "geometry": {"coordinates":[-84.180879,36.100571],"type":"Point"}
}