{
  "type": "Feature",
  "properties": {
    "addr:full":"1454 E Holmes Rd Memphis TN 38116",
    "addr:housenumber":"1454",
    "addr:postcode":"38116",
    "addr:street":"E Holmes Rd",
    "iso:country":"US",
    "sg:address":"1454 E Holmes Rd",
    "sg:city":"Memphis",
    "sg:classifiers":[
        {
            "category":"Building & Trades",
            "subcategory":"Cleaning & Sanitation",
            "type":"Services"
        },
        {
            "category":"Retail",
            "subcategory":"Repair Shop",
            "type":"Services"
        }
    ],
    "sg:phone":"+1 901 345 3997",
    "sg:postcode":"38116",
    "sg:province":"TN",
    "sg:tags":[
        "polishing",
        "waxing",
        "floor"
    ],
    "wof:name":"B & C Cleaning Svc",
    "wof:placetype":"venue"
},
  "geometry": {"coordinates":[-90.013769,35.006494],"type":"Point"}
}