{
  "type": "Feature",
  "properties": {
    "iso:country":"US",
    "sg:address":"200 E Pkwy",
    "sg:city":"Gatlinburg",
    "sg:classifiers":[
        {
            "category":"Travel",
            "subcategory":"Hotels & Motels",
            "type":"Entertainment"
        }
    ],
    "sg:phone":"+1 865 436 5043",
    "sg:postcode":"37738",
    "sg:province":"TN",
    "sg:website":"www.reaganresorts.com",
    "wof:name":"Howard Johnson",
    "wof:placetype":"venue"
},
  "geometry": {"coordinates":[-83.50837199999999,35.716035],"type":"Point"}
}