{
  "type": "Feature",
  "properties": {
    "iso:country":"US",
    "sg:address":"3101 Sutherland Ave",
    "sg:city":"Knoxville",
    "sg:classifiers":[
        {
            "category":"Bars & Pubs",
            "type":"Food & Drink"
        }
    ],
    "sg:phone":"+1 865 523 5738",
    "sg:postcode":"37919",
    "sg:province":"TN",
    "sg:tags":[
        "drinking"
    ],
    "wof:name":"T J Sport Bar",
    "wof:placetype":"venue"
},
  "geometry": {"coordinates":[-83.968526,35.951496],"type":"Point"}
}