{
  "type": "Feature",
  "properties": {
    "iso:country":"US",
    "sg:address":"901 Park Ln",
    "sg:city":"Nashville",
    "sg:classifiers":[
        {
            "category":"Professional",
            "subcategory":"Business Services",
            "type":"Services"
        },
        {
            "category":"Shopping",
            "subcategory":"Gifts & Souvenirs",
            "type":"Retail Goods"
        }
    ],
    "sg:phone":"+1 615 376 9122",
    "sg:postcode":"37221",
    "sg:province":"TN",
    "sg:tags":[
        "shop"
    ],
    "wof:name":"Greek By Designs LLC",
    "wof:placetype":"venue"
},
  "geometry": {"coordinates":[-86.920925,36.049195],"type":"Point"}
}