{
  "type": "Feature",
  "properties": {
    "addr:full":"2065 Fletcher Creek Dr Memphis TN 38133",
    "addr:housenumber":"2065",
    "addr:postcode":"38133",
    "addr:street":"Fletcher Creek Dr",
    "iso:country":"US",
    "sg:address":"2065 Fletcher Creek Dr",
    "sg:city":"Memphis",
    "sg:classifiers":[
        {
            "category":"Professional",
            "subcategory":"Advertising",
            "type":"Services"
        }
    ],
    "sg:phone":"+1 901 843 0477",
    "sg:postcode":"38133",
    "sg:province":"TN",
    "sg:tags":[
        "distribution"
    ],
    "wof:name":"Memphis Distributing",
    "wof:placetype":"venue"
},
  "geometry": {"coordinates":[-89.838632,35.182145],"type":"Point"}
}