{
  "type": "Feature",
  "properties": {
    "iso:country":"US",
    "sg:address":"471 Lexington Ave",
    "sg:city":"Jackson",
    "sg:classifiers":[
        {
            "category":"Food & Beverages",
            "subcategory":"Groceries & Convenience Stores",
            "type":"Retail Goods"
        }
    ],
    "sg:phone":"+1 731 422 1822",
    "sg:postcode":"38301",
    "sg:province":"TN",
    "wof:name":"Forrest Grocery",
    "wof:placetype":"venue"
},
  "geometry": {"coordinates":[-88.800166,35.619545],"type":"Point"}
}