{
  "type": "Feature",
  "properties": {
    "iso:country":"US",
    "sg:address":"2700 Greystone Rd",
    "sg:city":"Nashville",
    "sg:phone":"+1 615 866 0084",
    "sg:postcode":"37204",
    "sg:province":"TN",
    "sg:website":"http://nashville.citysearch.com/profile/external/46309351/nashville_tn/imagine_design_team.html?publisher=yellowpages&reference_id=1&placement=ypwebsitemip",
    "wof:name":"IMAGINE DESIGN TEAM",
    "wof:placetype":"venue"
},
  "geometry": {"coordinates":[-86.768784,36.120129],"type":"Point"}
}