{
  "type": "Feature",
  "properties": {
    "addr:full":"2717 E Magnolia Ave Knoxville TN 37914",
    "addr:housenumber":"2717",
    "addr:postcode":"37914",
    "addr:street":"E Magnolia Ave",
    "iso:country":"US",
    "sg:address":"2717 E Magnolia Ave",
    "sg:city":"Knoxville",
    "sg:classifiers":[
        {
            "category":"Health Services",
            "subcategory":"Clinic",
            "type":"Services"
        },
        {
            "category":"Health Services",
            "subcategory":"Doctor",
            "type":"Services"
        }
    ],
    "sg:phone":"+1 865 544 0082",
    "sg:postcode":"37914",
    "sg:province":"TN",
    "sg:tags":[
        "medical",
        "kidney",
        "dialysis",
        "center"
    ],
    "wof:name":"East Knoxville Dialysis Center",
    "wof:placetype":"venue"
},
  "geometry": {"coordinates":[-83.89099,35.989984],"type":"Point"}
}