{
  "type": "Feature",
  "properties": {
    "iso:country":"US",
    "sg:address":"7850 Stage Hills Blvd",
    "sg:city":"Memphis",
    "sg:classifiers":[
        {
            "category":"Insurance",
            "subcategory":"Insurance Agent",
            "type":"Services"
        },
        {
            "category":"Insurance",
            "subcategory":"Hazard Insurance",
            "type":"Services"
        }
    ],
    "sg:phone":"+1 901 398 0245",
    "sg:postcode":"38133",
    "sg:province":"TN",
    "sg:tags":[
        "property",
        "commercial",
        "casualty",
        "business"
    ],
    "wof:name":"Couch & Associates Insurance Agency Inc",
    "wof:placetype":"venue"
},
  "geometry": {"coordinates":[-89.801293,35.209183],"type":"Point"}
}