{
  "type": "Feature",
  "properties": {
    "addr:full":"1028 S Yates Rd Memphis TN 38120",
    "addr:housenumber":"1028",
    "addr:postcode":"38120",
    "addr:street":"S Yates Rd",
    "iso:country":"US",
    "sg:address":"1028 S Yates Rd",
    "sg:city":"Memphis",
    "sg:classifiers":[
        {
            "category":"Personal",
            "subcategory":"Beauty Salon",
            "type":"Services"
        }
    ],
    "sg:phone":"+1 901 682 8069",
    "sg:postcode":"38120",
    "sg:province":"TN",
    "sg:tags":[
        "shop",
        "manicuring"
    ],
    "wof:name":"Perfectly Polished Inc",
    "wof:placetype":"venue"
},
  "geometry": {"coordinates":[-89.877244,35.105489],"type":"Point"}
}