{
  "type": "Feature",
  "properties": {
    "iso:country":"US",
    "sg:address":"5611 Pinewood Rd",
    "sg:city":"Franklin",
    "sg:classifiers":[
        {
            "category":"Building & Trades",
            "subcategory":"Construction",
            "type":"Services"
        }
    ],
    "sg:phone":"+1 615 790 3481",
    "sg:postcode":"37064",
    "sg:province":"TN",
    "sg:tags":[
        "contractor"
    ],
    "wof:name":"Ringer John",
    "wof:placetype":"venue"
},
  "geometry": {"coordinates":[-87.07681599999999,35.883446],"type":"Point"}
}