{
  "type": "Feature",
  "properties": {
    "addr:full":"6138 Preservation Dr Chattanooga TN 37416",
    "addr:housenumber":"6138",
    "addr:postcode":"37416",
    "addr:street":"Preservation Dr",
    "iso:country":"US",
    "sg:address":"6138 Preservation Dr",
    "sg:city":"Chattanooga",
    "sg:classifiers":[
        {
            "category":"Food & Beverages",
            "subcategory":"Groceries & Convenience Stores",
            "type":"Retail Goods"
        },
        {
            "category":"Professional",
            "subcategory":"Management & Consulting",
            "type":"Services"
        }
    ],
    "sg:phone":"+1 423 855 9001",
    "sg:postcode":"37416",
    "sg:province":"TN",
    "sg:tags":[
        "consultant",
        "business"
    ],
    "wof:name":"Convenience Management Group L",
    "wof:placetype":"venue"
},
  "geometry": {"coordinates":[-85.185751,35.074861],"type":"Point"}
}