{
  "type": "Feature",
  "properties": {
    "iso:country":"US",
    "sg:address":"3502 Peppermint Hills Dr",
    "sg:city":"Maryville",
    "sg:classifiers":[
        {
            "category":"Arts & Performance",
            "subcategory":"Theater",
            "type":"Entertainment"
        }
    ],
    "sg:phone":"+1 865 984 4891",
    "sg:postcode":"37804",
    "sg:province":"TN",
    "sg:tags":[
        "arranging",
        "contest",
        "judging"
    ],
    "wof:name":"Imperial Miss Prod",
    "wof:placetype":"venue"
},
  "geometry": {"coordinates":[-83.893833,35.789346],"type":"Point"}
}