{
  "type": "Feature",
  "properties": {
    "iso:country":"US",
    "sg:address":"1900 Sparta Pike",
    "sg:city":"Lebanon",
    "sg:classifiers":[
        {
            "category":"Professional",
            "type":"Services"
        }
    ],
    "sg:phone":"+1 615 405 4504",
    "sg:postcode":"37090",
    "sg:province":"TN",
    "wof:name":"Cds Services",
    "wof:placetype":"venue"
},
  "geometry": {"coordinates":[-86.25066099999999,36.165411],"type":"Point"}
}