{
  "type": "Feature",
  "properties": {
    "iso:country":"US",
    "sg:address":"816 Foothills Mall Dr",
    "sg:city":"Maryville",
    "sg:classifiers":[
        {
            "category":"Restaurant",
            "type":"Food & Drink"
        }
    ],
    "sg:menulink":"http://www.allmenus.com/tn/maryville-alcoa/166325-arbys/menu/",
    "sg:phone":"+1 865 982 7973",
    "sg:postcode":"37801",
    "sg:province":"TN",
    "sg:tags":[
        "burger",
        "american"
    ],
    "wof:name":"Arby's",
    "wof:placetype":"venue"
},
  "geometry": {"coordinates":[-83.998113,35.751359],"type":"Point"}
}