{
  "type": "Feature",
  "properties": {
    "addr:full":"2069 Oak Ridge Tpke Oak Ridge TN 37830",
    "addr:housenumber":"2069",
    "addr:postcode":"37830",
    "addr:street":"Oak Ridge Tpke",
    "iso:country":"US",
    "sg:address":"2069 Oak Ridge Tpke",
    "sg:city":"Oak Ridge",
    "sg:classifiers":[
        {
            "category":"Retail",
            "subcategory":"Auto Repair",
            "type":"Services"
        }
    ],
    "sg:phone":"+1 865 483 1800",
    "sg:postcode":"37830",
    "sg:province":"TN",
    "sg:tags":[
        "automobile",
        "lubrication"
    ],
    "wof:name":"Shell Rapid Lube",
    "wof:placetype":"venue"
},
  "geometry": {"coordinates":[-84.293508,36.000473],"type":"Point"}
}