{
  "type": "Feature",
  "properties": {
    "iso:country":"US",
    "sg:address":"410 5th Ave",
    "sg:city":"Columbia",
    "sg:classifiers":[
        {
            "category":"Building & Trades",
            "subcategory":"Cleaning & Sanitation",
            "type":"Services"
        }
    ],
    "sg:phone":"+1 931 381 6799",
    "sg:postcode":"38401",
    "sg:province":"TN",
    "sg:tags":[
        "maintenance"
    ],
    "wof:name":"Clear Choice Services",
    "wof:placetype":"venue"
},
  "geometry": {"coordinates":[-87.024944,35.623648],"type":"Point"}
}