{
  "type": "Feature",
  "properties": {
    "addr:full":"4785 Walnut Grove Rd Memphis TN 38117",
    "addr:housenumber":"4785",
    "addr:postcode":"38117",
    "addr:street":"Walnut Grove Rd",
    "iso:country":"US",
    "sg:address":"4785 Walnut Grove Rd",
    "sg:city":"Memphis",
    "sg:classifiers":[
        {
            "category":"Professional",
            "subcategory":"Lawyer & Legal Services",
            "type":"Services"
        }
    ],
    "sg:phone":"+1 901 844 6241",
    "sg:postcode":"38117",
    "sg:province":"TN",
    "sg:tags":[
        "plan"
    ],
    "wof:name":"Law Offices Of Steven Cra",
    "wof:placetype":"venue"
},
  "geometry": {"coordinates":[-89.902657,35.130989],"type":"Point"}
}