{
  "type": "Feature",
  "properties": {
    "addr:full":"503 Figuers Dr Franklin TN 37064",
    "addr:housenumber":"503",
    "addr:postcode":"37064",
    "addr:street":"Figuers Dr",
    "iso:country":"US",
    "sg:address":"503 Figuers Dr",
    "sg:city":"Franklin",
    "sg:classifiers":[
        {
            "category":"Building & Trades",
            "subcategory":"Plumbing",
            "type":"Services"
        }
    ],
    "sg:phone":"+1 615 790 6329",
    "sg:postcode":"37064",
    "sg:province":"TN",
    "sg:tags":[
        "contractor"
    ],
    "wof:name":"Raines Refrigeration & Elc",
    "wof:placetype":"venue"
},
  "geometry": {"coordinates":[-86.884742,35.909547],"type":"Point"}
}