{
  "type": "Feature",
  "properties": {
    "iso:country":"US",
    "sg:address":"1722 Breda Dr NE",
    "sg:city":"Knoxville",
    "sg:classifiers":[
        {
            "category":"Building & Trades",
            "subcategory":"Construction",
            "type":"Services"
        }
    ],
    "sg:phone":"+1 865 689 5157",
    "sg:postcode":"37918",
    "sg:province":"TN",
    "sg:tags":[
        "nonresidential"
    ],
    "wof:name":"Dirt Daubber",
    "wof:placetype":"venue"
},
  "geometry": {"coordinates":[-83.93663100000001,36.009646],"type":"Point"}
}