{
  "type": "Feature",
  "properties": {
    "iso:country":"US",
    "sg:address":"1401 Rosetree Ln",
    "sg:city":"Kingsport",
    "sg:classifiers":[
        {
            "category":"Professional",
            "subcategory":"Business Services",
            "type":"Services"
        }
    ],
    "sg:phone":"+1 423 245 3872",
    "sg:postcode":"37660",
    "sg:province":"TN",
    "sg:tags":[
        "prof",
        "disc"
    ],
    "wof:name":"Pro Entertainment",
    "wof:placetype":"venue"
},
  "geometry": {"coordinates":[-82.532706,36.563189],"type":"Point"}
}