{
  "type": "Feature",
  "properties": {
    "iso:country":"US",
    "sg:address":"9145 Cross Park Dr",
    "sg:city":"Knoxville",
    "sg:classifiers":[
        {
            "category":"Shopping",
            "subcategory":"Bicycles & Sporting Goods",
            "type":"Retail Goods"
        }
    ],
    "sg:phone":"+1 865 694 7606",
    "sg:postcode":"37923",
    "sg:province":"TN",
    "sg:tags":[
        "repair"
    ],
    "wof:name":"Sale Winning Edge Golf Tennis",
    "wof:placetype":"venue"
},
  "geometry": {"coordinates":[-84.08965000000001,35.921641],"type":"Point"}
}