{
  "type": "Feature",
  "properties": {
    "addr:full":"2601 Hacks Cross Rd Germantown TN 38138",
    "addr:housenumber":"2601",
    "addr:postcode":"38138",
    "addr:street":"Hacks Cross Rd",
    "iso:country":"US",
    "sg:address":"2601 Hacks Cross Rd",
    "sg:city":"Germantown",
    "sg:classifiers":[
        {
            "category":"Arts & Performance",
            "subcategory":"Theater",
            "type":"Entertainment"
        }
    ],
    "sg:phone":"+1 901 753 4322",
    "sg:postcode":"38138",
    "sg:province":"TN",
    "sg:tags":[
        "program",
        "radio",
        "producer"
    ],
    "sg:website":"www.d1sports.net",
    "wof:name":"D 1 Sports",
    "wof:placetype":"venue"
},
  "geometry": {"coordinates":[-89.79407999999999,35.075784],"type":"Point"}
}