{
  "type": "Feature",
  "properties": {
    "addr:full":"327 Gill St Alcoa TN 37701",
    "addr:housenumber":"327",
    "addr:postcode":"37701",
    "addr:street":"Gill St",
    "iso:country":"US",
    "sg:address":"327 Gill St",
    "sg:city":"Alcoa",
    "sg:classifiers":[
        {
            "category":"Building & Trades",
            "subcategory":"Construction",
            "type":"Services"
        }
    ],
    "sg:phone":"+1 865 977 6584",
    "sg:postcode":"37701",
    "sg:province":"TN",
    "sg:tags":[
        "tile",
        "dealer"
    ],
    "wof:name":"Kirkland's Carpets",
    "wof:placetype":"venue"
},
  "geometry": {"coordinates":[-83.97381300000001,35.760697],"type":"Point"}
}