{
  "type": "Feature",
  "properties": {
    "iso:country":"US",
    "sg:address":"2834 US Hwy 11 Bus",
    "sg:city":"Athens",
    "sg:classifiers":[
        {
            "category":"Home & Garden",
            "subcategory":"Building Materials",
            "type":"Retail Goods"
        }
    ],
    "sg:phone":"+1 423 745 2707",
    "sg:postcode":"37303",
    "sg:province":"TN",
    "wof:name":"Furniture",
    "wof:placetype":"venue"
},
  "geometry": {"coordinates":[-84.644994,35.427559],"type":"Point"}
}