{
  "type": "Feature",
  "properties": {
    "iso:country":"US",
    "sg:address":"4012 Hillsboro Cir",
    "sg:city":"Nashville",
    "sg:classifiers":[
        {
            "category":"Professional",
            "type":"Services"
        }
    ],
    "sg:phone":"+1 615 383 3777",
    "sg:postcode":"37215",
    "sg:province":"TN",
    "wof:name":"Commercial Media Services",
    "wof:placetype":"venue"
},
  "geometry": {"coordinates":[-86.819512,36.103914],"type":"Point"}
}