{
  "type": "Feature",
  "properties": {
    "iso:country":"US",
    "sg:address":"1000 Sycamore St",
    "sg:city":"Bristol",
    "sg:classifiers":[
        {
            "category":"Professional",
            "subcategory":"Management & Consulting",
            "type":"Services"
        }
    ],
    "sg:phone":"+1 276 669 1277",
    "sg:postcode":"24201",
    "sg:province":"TN",
    "sg:tags":[
        "consultant",
        "business"
    ],
    "wof:name":"Southeastern Employers Assn",
    "wof:placetype":"venue"
},
  "geometry": {"coordinates":[-82.18749699999999,36.599468],"type":"Point"}
}