{
  "type": "Feature",
  "properties": {
    "addr:full":"718 Albany Dr Hermitage TN 37076",
    "addr:housenumber":"718",
    "addr:postcode":"37076",
    "addr:street":"Albany Dr",
    "iso:country":"US",
    "sg:address":"718 Albany Dr",
    "sg:city":"Hermitage",
    "sg:classifiers":[
        {
            "category":"Retail",
            "subcategory":"Auto Repair",
            "type":"Services"
        }
    ],
    "sg:phone":"+1 615 874 4146",
    "sg:postcode":"37076",
    "sg:province":"TN",
    "sg:tags":[
        "electrician",
        "electrical"
    ],
    "wof:name":"Abc Electric",
    "wof:placetype":"venue"
},
  "geometry": {"coordinates":[-86.595461,36.205254],"type":"Point"}
}