{
  "type": "Feature",
  "properties": {
    "addr:full":"622 N Water St Bolivar TN 38008",
    "addr:housenumber":"622",
    "addr:postcode":"38008",
    "addr:street":"N Water St Bolivar",
    "iso:country":"US",
    "sg:address":"622 N Water St",
    "sg:city":"Bolivar",
    "sg:classifiers":[
        {
            "category":"Building & Trades",
            "subcategory":"Construction",
            "type":"Services"
        }
    ],
    "sg:phone":"+1 731 658 9797",
    "sg:postcode":"38008",
    "sg:province":"TN",
    "sg:tags":[
        "home",
        "builder"
    ],
    "wof:name":"Support Solutions",
    "wof:placetype":"venue"
},
  "geometry": {"coordinates":[-88.986369,35.259745],"type":"Point"}
}