{
  "type": "Feature",
  "properties": {
    "addr:full":"1111 N Market St Paris TN 38242",
    "addr:housenumber":"1111",
    "addr:postcode":"38242",
    "addr:street":"N Market St",
    "iso:country":"US",
    "sg:address":"1111 N Market St",
    "sg:city":"Paris",
    "sg:classifiers":[
        {
            "category":"Food & Beverages",
            "subcategory":"Groceries & Convenience Stores",
            "type":"Retail Goods"
        }
    ],
    "sg:phone":"+1 731 642 6481",
    "sg:postcode":"38242",
    "sg:province":"TN",
    "sg:tags":[
        "grocer"
    ],
    "wof:name":"Maverick Quick Shop",
    "wof:placetype":"venue"
},
  "geometry": {"coordinates":[-88.32701,36.313141],"type":"Point"}
}