{
  "type": "Feature",
  "properties": {
    "iso:country":"US",
    "sg:address":"4420 N Broadway St",
    "sg:city":"Knoxville",
    "sg:classifiers":[
        {
            "category":"Retail",
            "subcategory":"Laundry & Dry Cleaning",
            "type":"Services"
        }
    ],
    "sg:phone":"+1 865 688 3164",
    "sg:postcode":"37917",
    "sg:province":"TN",
    "sg:tags":[
        "drycleaning",
        "plant",
        "cleaners"
    ],
    "wof:name":"Knoxville Dry Cleaners No 2",
    "wof:placetype":"venue"
},
  "geometry": {"coordinates":[-83.92374599999999,36.013306],"type":"Point"}
}