{
  "type": "Feature",
  "properties": {
    "iso:country":"US",
    "sg:address":"2159 Walnut Grove Rd",
    "sg:city":"Sevierville",
    "sg:classifiers":[
        {
            "category":"Building & Trades",
            "subcategory":"Construction",
            "type":"Services"
        }
    ],
    "sg:phone":"+1 865 453 8977",
    "sg:postcode":"37876",
    "sg:province":"TN",
    "sg:tags":[
        "excavating",
        "contractor"
    ],
    "wof:name":"Triple C Excavating",
    "wof:placetype":"venue"
},
  "geometry": {"coordinates":[-83.472244,35.883196],"type":"Point"}
}