{
  "type": "Feature",
  "properties": {
    "iso:country":"US",
    "sg:address":"1940 State Hwy 196",
    "sg:city":"Collierville",
    "sg:classifiers":[
        {
            "category":"Personal",
            "subcategory":"Beauty Salon",
            "type":"Services"
        }
    ],
    "sg:phone":"+1 901 853 9535",
    "sg:postcode":"38017",
    "sg:province":"TN",
    "sg:tags":[
        "shop"
    ],
    "wof:name":"Ida's Beauty Shop",
    "wof:placetype":"venue"
},
  "geometry": {"coordinates":[-89.617344,35.026178],"type":"Point"}
}