{
  "type": "Feature",
  "properties": {
    "addr:full":"110 Raleigh Rd Oak Ridge TN 37830",
    "addr:housenumber":"110",
    "addr:postcode":"37830",
    "addr:street":"Raleigh Rd",
    "iso:country":"US",
    "sg:address":"110 Raleigh Rd",
    "sg:city":"Oak Ridge",
    "sg:classifiers":[
        {
            "category":"Government",
            "subcategory":"Post Office",
            "type":"Public Place"
        }
    ],
    "sg:phone":"+1 865 483 0373",
    "sg:postcode":"37830",
    "sg:province":"TN",
    "wof:name":"US Postal Contract Station",
    "wof:placetype":"venue"
},
  "geometry": {"coordinates":[-84.266864,36.013689],"type":"Point"}
}