{
  "type": "Feature",
  "properties": {
    "iso:country":"US",
    "sg:address":"750 Rankin Hill Rd",
    "sg:city":"Newport",
    "sg:phone":"+1 423 623 1714",
    "sg:postcode":"37821",
    "sg:province":"TN",
    "sg:tags":[
        "farm",
        "grain",
        "cash"
    ],
    "wof:name":"Hurley Ivan Cash Grains Farms",
    "wof:placetype":"venue"
},
  "geometry": {"coordinates":[-83.227958,36.050024],"type":"Point"}
}