{
  "type": "Feature",
  "properties": {
    "iso:country":"US",
    "sg:address":"1507 State Hwy 81 N",
    "sg:city":"Jonesborough",
    "sg:classifiers":[
        {
            "category":"Building & Trades",
            "subcategory":"Construction",
            "type":"Services"
        }
    ],
    "sg:phone":"+1 423 477 8258",
    "sg:postcode":"37659",
    "sg:province":"TN",
    "sg:tags":[
        "dry wall",
        "contractor"
    ],
    "wof:name":"Convenant Drywall",
    "wof:placetype":"venue"
},
  "geometry": {"coordinates":[-82.557897,36.323109],"type":"Point"}
}