{
  "type": "Feature",
  "properties": {
    "addr:full":"6996 Bent Creek Dr Germantown TN 38138",
    "addr:housenumber":"6996",
    "addr:postcode":"38138",
    "addr:street":"Bent Creek Dr",
    "iso:country":"US",
    "sg:address":"6996 Bent Creek Dr",
    "sg:city":"Germantown",
    "sg:classifiers":[
        {
            "category":"Shopping",
            "subcategory":"Computers & Home Electronics",
            "type":"Retail Goods"
        }
    ],
    "sg:phone":"+1 901 753 4700",
    "sg:postcode":"38138",
    "sg:province":"TN",
    "sg:tags":[
        "equipment",
        "dealer"
    ],
    "wof:name":"Rocket Computers",
    "wof:placetype":"venue"
},
  "geometry": {"coordinates":[-89.83082400000001,35.113729],"type":"Point"}
}