{
  "type": "Feature",
  "properties": {
    "addr:full":"310 S Main St Greeneville TN 37743",
    "addr:housenumber":"310",
    "addr:postcode":"37743",
    "addr:street":"S Main St",
    "iso:country":"US",
    "sg:address":"310 S Main St",
    "sg:city":"Greeneville",
    "sg:classifiers":[
        {
            "category":"Organizations",
            "subcategory":"Professional Association",
            "type":"Services"
        }
    ],
    "sg:phone":"+1 423 639 7102",
    "sg:postcode":"37743",
    "sg:province":"TN",
    "sg:tags":[
        "business"
    ],
    "wof:name":"Main Street Greeneville Inc",
    "wof:placetype":"venue"
},
  "geometry": {"coordinates":[-82.832831,36.160032],"type":"Point"}
}