{
  "type": "Feature",
  "properties": {
    "addr:full":"2189 State Hwy 76 Portland TN 37148",
    "addr:housenumber":"2189",
    "addr:postcode":"37148",
    "addr:street":"State Hwy 76",
    "iso:country":"US",
    "sg:address":"2189 State Hwy 76",
    "sg:city":"Portland",
    "sg:classifiers":[
        {
            "category":"Manufacturing",
            "subcategory":"Tools & Machinery",
            "type":"Manufacturing & Wholesale Goods"
        }
    ],
    "sg:phone":"+1 615 325 9927",
    "sg:postcode":"37148",
    "sg:province":"TN",
    "sg:tags":[
        "machine",
        "shop"
    ],
    "wof:name":"Kellys Machine Shop",
    "wof:placetype":"venue"
},
  "geometry": {"coordinates":[-86.518438,36.544354],"type":"Point"}
}