{
  "type": "Feature",
  "properties": {
    "iso:country":"US",
    "sg:address":"52 Altamont Dr",
    "sg:city":"Jackson",
    "sg:classifiers":[
        {
            "category":"Professional",
            "subcategory":"Management & Consulting",
            "type":"Services"
        }
    ],
    "sg:phone":"+1 731 935 2153",
    "sg:postcode":"38301",
    "sg:province":"TN",
    "sg:tags":[
        "marketing",
        "program"
    ],
    "wof:name":"P H & K Marketing",
    "wof:placetype":"venue"
},
  "geometry": {"coordinates":[-88.787986,35.610205],"type":"Point"}
}