{
  "type": "Feature",
  "properties": {
    "iso:country":"US",
    "sg:address":"6305 Ringgold Rd",
    "sg:city":"Chattanooga",
    "sg:classifiers":[
        {
            "category":"Restaurant",
            "type":"Food & Drink"
        }
    ],
    "sg:menulink":"http://www.allmenus.com/tn/east-ridge/154889-hardees/menu/",
    "sg:phone":"+1 423 894 2307",
    "sg:postcode":"37412",
    "sg:province":"TN",
    "sg:tags":[
        "burger",
        "american"
    ],
    "wof:name":"Hardee's",
    "wof:placetype":"venue"
},
  "geometry": {"coordinates":[-85.211043,34.990202],"type":"Point"}
}