{
  "type": "Feature",
  "properties": {
    "addr:full":"5353 Cane Ridge Rd Antioch TN 37013",
    "addr:housenumber":"5353",
    "addr:postcode":"37013",
    "addr:street":"Cane Ridge Rd",
    "iso:country":"US",
    "sg:address":"5353 Cane Ridge Rd",
    "sg:city":"Antioch",
    "sg:classifiers":[
        {
            "category":"Building & Trades",
            "subcategory":"Construction",
            "type":"Services"
        }
    ],
    "sg:phone":"+1 615 554 4548",
    "sg:postcode":"37013",
    "sg:province":"TN",
    "sg:tags":[
        "tile",
        "dealer",
        "contractor"
    ],
    "wof:name":"General Tile & Marble",
    "wof:placetype":"venue"
},
  "geometry": {"coordinates":[-86.66163899999999,36.043475],"type":"Point"}
}