{
  "type": "Feature",
  "properties": {
    "iso:country":"US",
    "sg:address":"1521 Gravel Hill Rd",
    "sg:city":"Columbia",
    "sg:classifiers":[
        {
            "category":"Building & Trades",
            "subcategory":"Landscaping Services",
            "type":"Services"
        }
    ],
    "sg:phone":"+1 931 487 9007",
    "sg:postcode":"38401",
    "sg:province":"TN",
    "sg:tags":[
        "lawn",
        "maintenance",
        "grounds"
    ],
    "wof:name":"Gardener",
    "wof:placetype":"venue"
},
  "geometry": {"coordinates":[-87.030649,35.753839],"type":"Point"}
}