{
  "type": "Feature",
  "properties": {
    "addr:full":"109 Murphy Ct Nashville TN 37203",
    "addr:housenumber":"109",
    "addr:postcode":"37203",
    "addr:street":"Murphy Ct",
    "iso:country":"US",
    "sg:address":"109 Murphy Ct",
    "sg:city":"Nashville",
    "sg:classifiers":[
        {
            "category":"Real Estate",
            "subcategory":"Real Estate Agent",
            "type":"Services"
        }
    ],
    "sg:phone":"+1 615 383 3111",
    "sg:postcode":"37203",
    "sg:province":"TN",
    "sg:tags":[
        "management"
    ],
    "wof:name":"Freeman Management Corp",
    "wof:placetype":"venue"
},
  "geometry": {"coordinates":[-86.81151300000001,36.152842],"type":"Point"}
}