{
  "type": "Feature",
  "properties": {
    "iso:country":"US",
    "sg:address":"9041 Executive Park Dr",
    "sg:city":"Knoxville",
    "sg:classifiers":[
        {
            "category":"Education",
            "subcategory":"Junior College",
            "type":"Public Place"
        },
        {
            "category":"Real Estate",
            "subcategory":"Real Estate Agent",
            "type":"Services"
        }
    ],
    "sg:phone":"+1 877 873 2704",
    "sg:postcode":"37923",
    "sg:province":"TN",
    "sg:tags":[
        "school"
    ],
    "sg:website":"http://www.trecs.org",
    "wof:name":"TRECS Real Estate School",
    "wof:placetype":"venue"
},
  "geometry": {"coordinates":[-84.08248399999999,35.921761],"type":"Point"}
}