{
  "type": "Feature",
  "properties": {
    "addr:full":"5252 Hickory Hollow Pkwy Antioch TN 37013",
    "addr:housenumber":"5252",
    "addr:postcode":"37013",
    "addr:street":"Hickory Hollow Pkwy",
    "iso:country":"US",
    "sg:address":"5252 Hickory Hollow Pkwy",
    "sg:city":"Antioch",
    "sg:classifiers":[
        {
            "category":"Professional",
            "type":"Services"
        }
    ],
    "sg:phone":"+1 615 731 1519",
    "sg:postcode":"37013",
    "sg:province":"TN",
    "wof:name":"Carbolycious Low Carb Nook",
    "wof:placetype":"venue"
},
  "geometry": {"coordinates":[-86.6574,36.048417],"type":"Point"}
}