{
  "type": "Feature",
  "properties": {
    "iso:country":"US",
    "sg:address":"12003 Kingston Pike",
    "sg:city":"Knoxville",
    "sg:classifiers":[
        {
            "category":"Recreation",
            "type":"Entertainment"
        }
    ],
    "sg:phone":"+1 865 675 0100",
    "sg:postcode":"37934",
    "sg:province":"TN",
    "sg:tags":[
        "course",
        "golf"
    ],
    "sg:website":"www.willowcreekgolf.com",
    "wof:name":"Willow Creek Golf Club",
    "wof:placetype":"venue"
},
  "geometry": {"coordinates":[-84.181933,35.871352],"type":"Point"}
}