{
  "type": "Feature",
  "properties": {
    "addr:full":"3264 Wears Valley Rd Sevierville TN 37862",
    "addr:housenumber":"3264",
    "addr:postcode":"37862",
    "addr:street":"Wears Valley Rd",
    "iso:country":"US",
    "sg:address":"3264 Wears Valley Rd",
    "sg:city":"Sevierville",
    "sg:classifiers":[
        {
            "category":"Shopping",
            "subcategory":"Gifts & Souvenirs",
            "type":"Retail Goods"
        }
    ],
    "sg:phone":"+1 865 908 6882",
    "sg:postcode":"37862",
    "sg:province":"TN",
    "wof:name":"Best of Christmas Inc",
    "wof:placetype":"venue"
},
  "geometry": {"coordinates":[-83.639021,35.724656],"type":"Point"}
}