{
  "type": "Feature",
  "properties": {
    "addr:full":"1000 Northchase Dr Goodlettsville TN 37072",
    "addr:housenumber":"1000",
    "addr:postcode":"37072",
    "addr:street":"Northchase Dr",
    "iso:country":"US",
    "sg:address":"1000 Northchase Dr",
    "sg:city":"Goodlettsville",
    "sg:classifiers":[
        {
            "category":"Building & Trades",
            "subcategory":"Construction",
            "type":"Services"
        }
    ],
    "sg:phone":"+1 615 256 2200",
    "sg:postcode":"37072",
    "sg:province":"TN",
    "sg:tags":[
        "general",
        "nonresidential",
        "architectural",
        "contractor"
    ],
    "sg:website":"www.powellbuilding.com",
    "wof:name":"Powell Building Group Inc",
    "wof:placetype":"venue"
},
  "geometry": {"coordinates":[-86.697197,36.311249],"type":"Point"}
}