{
  "type": "Feature",
  "properties": {
    "iso:country":"US",
    "sg:address":"3736 Old Hickory Blvd",
    "sg:city":"Nashville",
    "sg:classifiers":[
        {
            "category":"Restaurant",
            "type":"Food & Drink"
        }
    ],
    "sg:phone":"+1 615 354 9266",
    "sg:postcode":"37209",
    "sg:province":"TN",
    "sg:tags":[
        "eating"
    ],
    "wof:name":"Claiborne & Company",
    "wof:placetype":"venue"
},
  "geometry": {"coordinates":[-86.881111,36.139639],"type":"Point"}
}