{
  "type": "Feature",
  "properties": {
    "addr:full":"2505 Dale Cemetery Rd Buchanan TN 38222",
    "addr:housenumber":"2505",
    "addr:postcode":"38222",
    "addr:street":"Dale Cemetery Rd",
    "iso:country":"US",
    "sg:address":"2505 Dale Cemetery Rd",
    "sg:city":"Buchanan",
    "sg:classifiers":[
        {
            "category":"Retail",
            "subcategory":"Repair Shop",
            "type":"Services"
        },
        {
            "category":"Recreation",
            "subcategory":"Marina",
            "type":"Entertainment"
        }
    ],
    "sg:phone":"+1 731 247 5833",
    "sg:postcode":"38222",
    "sg:province":"TN",
    "sg:tags":[
        "repairing",
        "boat"
    ],
    "wof:name":"Rick's Boat Repair",
    "wof:placetype":"venue"
},
  "geometry": {"coordinates":[-88.201813,36.468881],"type":"Point"}
}