{
  "type": "Feature",
  "properties": {
    "iso:country":"US",
    "sg:address":"1203 Murfreesboro Rd",
    "sg:city":"Franklin",
    "sg:classifiers":[
        {
            "category":"Travel",
            "subcategory":"Travel Agent",
            "type":"Entertainment"
        }
    ],
    "sg:phone":"+1 615 791 4690",
    "sg:postcode":"37067",
    "sg:province":"TN",
    "sg:tags":[
        "agency"
    ],
    "wof:name":"Franklin Travel Services Inc",
    "wof:placetype":"venue"
},
  "geometry": {"coordinates":[-86.831248,35.915676],"type":"Point"}
}