{
  "type": "Feature",
  "properties": {
    "iso:country":"US",
    "sg:address":"3516 Tom Austin Hwy",
    "sg:city":"Springfield",
    "sg:classifiers":[
        {
            "category":"Restaurant",
            "type":"Food & Drink"
        }
    ],
    "sg:phone":"+1 615 382 6887",
    "sg:postcode":"37172",
    "sg:province":"TN",
    "sg:tags":[
        "eating"
    ],
    "sg:website":"www.whittsbarbecue.com",
    "wof:name":"Whitts Barbecue",
    "wof:placetype":"venue"
},
  "geometry": {"coordinates":[-86.88081,36.489266],"type":"Point"}
}