{
  "type": "Feature",
  "properties": {
    "iso:country":"US",
    "sg:address":"300 Manis Ln",
    "sg:city":"Oneida",
    "sg:classifiers":[
        {
            "category":"Travel",
            "subcategory":"Hotels & Motels",
            "type":"Entertainment"
        }
    ],
    "sg:phone":"+1 423 569 5135",
    "sg:postcode":"37841",
    "sg:province":"TN",
    "sg:tags":[
        "resort"
    ],
    "wof:name":"Laurel Fork Rustic Retreat",
    "wof:placetype":"venue"
},
  "geometry": {"coordinates":[-84.573199,36.500847],"type":"Point"}
}