{
  "type": "Feature",
  "properties": {
    "iso:country":"US",
    "sg:address":"2731 Mossdale Dr",
    "sg:city":"Nashville",
    "sg:classifiers":[
        {
            "category":"Organizations",
            "subcategory":"Community Association",
            "type":"Services"
        }
    ],
    "sg:phone":"+1 615 365 7000",
    "sg:postcode":"37217",
    "sg:province":"TN",
    "wof:name":"Alpha Alpha Kappa",
    "wof:placetype":"venue"
},
  "geometry": {"coordinates":[-86.62455300000001,36.080429],"type":"Point"}
}