{
  "type": "Feature",
  "properties": {
    "iso:country":"US",
    "sg:address":"1121 Mitchell Rd",
    "sg:city":"New Market",
    "sg:classifiers":[
        {
            "category":"Building & Trades",
            "subcategory":"Construction",
            "type":"Services"
        }
    ],
    "sg:phone":"+1 865 475 5682",
    "sg:postcode":"37820",
    "sg:province":"TN",
    "sg:tags":[
        "sewer",
        "contractor"
    ],
    "wof:name":"Russell Kent Construction",
    "wof:placetype":"venue"
},
  "geometry": {"coordinates":[-83.55017100000001,36.107735],"type":"Point"}
}