{
  "type": "Feature",
  "properties": {
    "iso:country":"US",
    "sg:address":"425 E McKinney Ave",
    "sg:city":"Rogersville",
    "sg:classifiers":[
        {
            "category":"Professional",
            "type":"Services"
        }
    ],
    "sg:phone":"+1 423 272 6918",
    "sg:postcode":"37857",
    "sg:province":"TN",
    "wof:name":"A1 Merchandiser",
    "wof:placetype":"venue"
},
  "geometry": {"coordinates":[-83.00066099999999,36.406744],"type":"Point"}
}