{
  "type": "Feature",
  "properties": {
    "iso:country":"US",
    "sg:address":"7454 Smithville Hwy",
    "sg:city":"Mc Minnville",
    "sg:classifiers":[
        {
            "category":"Retail",
            "subcategory":"Repair Shop",
            "type":"Services"
        }
    ],
    "sg:phone":"+1 931 934 2916",
    "sg:postcode":"37110",
    "sg:province":"TN",
    "sg:tags":[
        "related"
    ],
    "wof:name":"D & D Repair Svc",
    "wof:placetype":"venue"
},
  "geometry": {"coordinates":[-85.792501,35.795426],"type":"Point"}
}