{
  "type": "Feature",
  "properties": {
    "iso:country":"US",
    "sg:address":"6820 Robin Dr",
    "sg:city":"Chattanooga",
    "sg:classifiers":[
        {
            "category":"Professional",
            "type":"Services"
        }
    ],
    "sg:phone":"+1 423 894 1376",
    "sg:postcode":"37421",
    "sg:province":"TN",
    "wof:name":"Joseph W Hearn",
    "wof:placetype":"venue"
},
  "geometry": {"coordinates":[-85.157431,35.052303],"type":"Point"}
}