{
  "type": "Feature",
  "properties": {
    "iso:country":"US",
    "sg:address":"2565 Dibrell Trail Dr",
    "sg:city":"Collierville",
    "sg:classifiers":[
        {
            "category":"Banks & Credit Unions",
            "subcategory":"Bank",
            "type":"Services"
        }
    ],
    "sg:phone":"+1 901 861 5095",
    "sg:postcode":"38017",
    "sg:province":"TN",
    "sg:tags":[
        "institution",
        "business"
    ],
    "wof:name":"C It",
    "wof:placetype":"venue"
},
  "geometry": {"coordinates":[-89.717907,35.078033],"type":"Point"}
}