{
  "type": "Feature",
  "properties": {
    "iso:country":"US",
    "sg:address":"5437 Strawberry Plains Pike",
    "sg:city":"Knoxville",
    "sg:classifiers":[
        {
            "category":"Education",
            "subcategory":"Special Training",
            "type":"Public Place"
        }
    ],
    "sg:phone":"+1 865 522 2242",
    "sg:postcode":"37914",
    "sg:province":"TN",
    "sg:tags":[
        "center"
    ],
    "wof:name":"Prosoft Learning Corp",
    "wof:placetype":"venue"
},
  "geometry": {"coordinates":[-83.829295,35.979903],"type":"Point"}
}