{
  "type": "Feature",
  "properties": {
    "iso:country":"US",
    "sg:address":"2011 N Roan St",
    "sg:city":"Johnson City",
    "sg:classifiers":[
        {
            "category":"Restaurant",
            "type":"Food & Drink"
        }
    ],
    "sg:menulink":"http://www.allmenus.com/tn/johnson-city/95942-charleys-grilled-subs/menu/",
    "sg:phone":"+1 423 283 0784",
    "sg:postcode":"37601",
    "sg:province":"TN",
    "sg:tags":[
        "wrap",
        "american",
        "sandwich"
    ],
    "wof:name":"Charley's Grilled Subs",
    "wof:placetype":"venue"
},
  "geometry": {"coordinates":[-82.374728,36.339794],"type":"Point"}
}