{
  "type": "Feature",
  "properties": {
    "addr:full":"1117 E Raines Rd Memphis TN 38116",
    "addr:housenumber":"1117",
    "addr:postcode":"38116",
    "addr:street":"E Raines Rd",
    "iso:country":"US",
    "sg:address":"1117 E Raines Rd",
    "sg:city":"Memphis",
    "sg:classifiers":[
        {
            "category":"Professional",
            "subcategory":"Accounting & Tax Preparation",
            "type":"Services"
        }
    ],
    "sg:phone":"+1 901 398 4829",
    "sg:postcode":"38116",
    "sg:province":"TN",
    "sg:tags":[
        "return",
        "filing"
    ],
    "wof:name":"Milan & Milan Bookkeeping",
    "wof:placetype":"venue"
},
  "geometry": {"coordinates":[-90.02760000000001,35.035241],"type":"Point"}
}