{
  "type": "Feature",
  "properties": {
    "addr:full":"9815 Manchester Hwy Morrison TN 37357",
    "addr:housenumber":"9815",
    "addr:postcode":"37357",
    "addr:street":"Manchester Hwy",
    "iso:country":"US",
    "sg:address":"9815 Manchester Hwy",
    "sg:city":"Morrison",
    "sg:classifiers":[
        {
            "category":"Shopping",
            "subcategory":"Department Store",
            "type":"Retail Goods"
        }
    ],
    "sg:phone":"+1 931 635 3390",
    "sg:postcode":"37357",
    "sg:province":"TN",
    "wof:name":"Dollar General",
    "wof:placetype":"venue"
},
  "geometry": {"coordinates":[-85.91198,35.604089],"type":"Point"}
}