{
  "type": "Feature",
  "properties": {
    "iso:country":"US",
    "sg:address":"378 E Olive Ave",
    "sg:city":"Memphis",
    "sg:classifiers":[
        {
            "category":"Shopping",
            "type":"Retail Goods"
        }
    ],
    "sg:phone":"+1 901 948 7545",
    "sg:postcode":"38106",
    "sg:province":"TN",
    "sg:tags":[
        "merchandise"
    ],
    "wof:name":"Dukes Candy Store",
    "wof:placetype":"venue"
},
  "geometry": {"coordinates":[-90.04977700000001,35.110279],"type":"Point"}
}