{
  "type": "Feature",
  "properties": {
    "iso:country":"US",
    "sg:address":"1445 Janie Ave",
    "sg:city":"Nashville",
    "sg:classifiers":[
        {
            "category":"Manufacturing",
            "subcategory":"Soap",
            "type":"Manufacturing & Wholesale Goods"
        }
    ],
    "sg:phone":"+1 615 228 1790",
    "sg:postcode":"37216",
    "sg:province":"TN",
    "sg:tags":[
        "detergent",
        "mfg"
    ],
    "wof:name":"E&E Enterprises",
    "wof:placetype":"venue"
},
  "geometry": {"coordinates":[-86.714035,36.212506],"type":"Point"}
}