{
  "type": "Feature",
  "properties": {
    "addr:full":"3046 Nolensville Pike Nashville TN 37211",
    "addr:housenumber":"3046",
    "addr:postcode":"37211",
    "addr:street":"Nolensville Pike",
    "iso:country":"US",
    "sg:address":"3046 Nolensville Pike",
    "sg:city":"Nashville",
    "sg:classifiers":[
        {
            "category":"Insurance",
            "subcategory":"Insurance Agent",
            "type":"Services"
        }
    ],
    "sg:phone":"+1 615 331 2600",
    "sg:postcode":"37211",
    "sg:province":"TN",
    "wof:name":"Larry E Crum & Assoc",
    "wof:placetype":"venue"
},
  "geometry": {"coordinates":[-86.741711,36.104274],"type":"Point"}
}