{
  "type": "Feature",
  "properties": {
    "addr:full":"3900 Rossville Blvd Chattanooga TN 37407",
    "addr:housenumber":"3900",
    "addr:postcode":"37407",
    "addr:street":"Rossville Blvd",
    "iso:country":"US",
    "sg:address":"3900 Rossville Blvd",
    "sg:city":"Chattanooga",
    "sg:classifiers":[
        {
            "category":"Autos & Motor Vehicles",
            "subcategory":"Automobile Sales",
            "type":"Retail Goods"
        }
    ],
    "sg:phone":"+1 423 867 1090",
    "sg:postcode":"37407",
    "sg:province":"TN",
    "sg:tags":[
        "car",
        "dealer"
    ],
    "wof:name":"Donnie's Auto Sales",
    "wof:placetype":"venue"
},
  "geometry": {"coordinates":[-85.291433,34.997656],"type":"Point"}
}