{
  "type": "Feature",
  "properties": {
    "iso:country":"US",
    "sg:address":"2168 E Shelby Dr",
    "sg:city":"Memphis",
    "sg:classifiers":[
        {
            "category":"Social Services",
            "subcategory":"Child Care",
            "type":"Services"
        }
    ],
    "sg:phone":"+1 901 345 9528",
    "sg:postcode":"38116",
    "sg:province":"TN",
    "sg:tags":[
        "day"
    ],
    "wof:name":"Fresh Start Enrichment Center",
    "wof:placetype":"venue"
},
  "geometry": {"coordinates":[-89.990452,35.02112],"type":"Point"}
}