{
  "type": "Feature",
  "properties": {
    "iso:country":"US",
    "sg:address":"8052 Claytie Cir",
    "sg:city":"Nashville",
    "sg:classifiers":[
        {
            "category":"Home & Garden",
            "subcategory":"Furniture",
            "type":"Retail Goods"
        }
    ],
    "sg:phone":"+1 615 376 9570",
    "sg:postcode":"37221",
    "sg:province":"TN",
    "wof:name":"Countiss Collection",
    "wof:placetype":"venue"
},
  "geometry": {"coordinates":[-86.97479800000001,36.064134],"type":"Point"}
}