{
  "type": "Feature",
  "properties": {
    "iso:country":"US",
    "sg:address":"109 Holiday Ct",
    "sg:city":"Franklin",
    "sg:classifiers":[
        {
            "category":"Professional",
            "subcategory":"Lawyer & Legal Services",
            "type":"Services"
        }
    ],
    "sg:phone":"+1 615 424 8617",
    "sg:postcode":"37067",
    "sg:province":"TN",
    "sg:tags":[
        "attorney"
    ],
    "wof:name":"Joseph D Johnson",
    "wof:placetype":"venue"
},
  "geometry": {"coordinates":[-86.828003,35.917202],"type":"Point"}
}