{
  "type": "Feature",
  "properties": {
    "iso:country":"US",
    "sg:address":"501 Ligon Dr",
    "sg:city":"Nashville",
    "sg:classifiers":[
        {
            "category":"Real Estate",
            "subcategory":"Real Estate Agent",
            "type":"Services"
        }
    ],
    "sg:phone":"+1 615 255 6256",
    "sg:postcode":"37204",
    "sg:province":"TN",
    "wof:name":"Rocket Realty",
    "wof:placetype":"venue"
},
  "geometry": {"coordinates":[-86.76399000000001,36.122412],"type":"Point"}
}