{
  "type": "Feature",
  "properties": {
    "addr:full":"1526 William Blount Dr Maryville TN 37801",
    "addr:housenumber":"1526",
    "addr:postcode":"37801",
    "addr:street":"William Blount Dr",
    "iso:country":"US",
    "sg:address":"1526 William Blount Dr",
    "sg:city":"Maryville",
    "sg:classifiers":[
        {
            "category":"Building & Trades",
            "subcategory":"Construction",
            "type":"Services"
        }
    ],
    "sg:phone":"+1 865 977 8897",
    "sg:postcode":"37801",
    "sg:province":"TN",
    "sg:tags":[
        "designer",
        "dealer",
        "pool",
        "swimming"
    ],
    "sg:website":"www.bluehaven.com",
    "wof:name":"Luxury Pool & Spas",
    "wof:placetype":"venue"
},
  "geometry": {"coordinates":[-84.044206,35.747825],"type":"Point"}
}