{
  "type": "Feature",
  "properties": {
    "addr:full":"111 Bruce Rd Gatlinburg TN 37738",
    "addr:housenumber":"111",
    "addr:postcode":"37738",
    "addr:street":"Bruce Rd",
    "iso:country":"US",
    "sg:address":"111 Bruce Rd",
    "sg:city":"Gatlinburg",
    "sg:classifiers":[
        {
            "category":"Health Services",
            "subcategory":"Doctor",
            "type":"Services"
        }
    ],
    "sg:phone":"+1 865 436 5024",
    "sg:postcode":"37738",
    "sg:province":"TN",
    "wof:name":"J A Collart DDS",
    "wof:placetype":"venue"
},
  "geometry": {"coordinates":[-83.47205700000001,35.726802],"type":"Point"}
}