{
  "type": "Feature",
  "properties": {
    "iso:country":"US",
    "sg:address":"22579 US Hwy 41",
    "sg:city":"Chattanooga",
    "sg:classifiers":[
        {
            "category":"Museum",
            "subcategory":"Botanical Garden",
            "type":"Entertainment"
        },
        {
            "category":"Government",
            "subcategory":"Office",
            "type":"Public Place"
        }
    ],
    "sg:phone":"+1 423 821 7341",
    "sg:postcode":"37419",
    "sg:province":"TN",
    "sg:tags":[
        "conservation"
    ],
    "wof:name":"Tennessee River Gardens",
    "wof:placetype":"venue"
},
  "geometry": {"coordinates":[-85.51179399999999,35.065883],"type":"Point"}
}