{
  "type": "Feature",
  "properties": {
    "iso:country":"US",
    "sg:address":"2010 Elmer Pogue Dr",
    "sg:city":"Columbia",
    "sg:classifiers":[
        {
            "category":"Professional",
            "subcategory":"Business Services",
            "type":"Services"
        }
    ],
    "sg:phone":"+1 931 381 6008",
    "sg:postcode":"38401",
    "sg:province":"TN",
    "sg:tags":[
        "inventory"
    ],
    "wof:name":"R G I S Inventory Specialists",
    "wof:placetype":"venue"
},
  "geometry": {"coordinates":[-87.000227,35.672498],"type":"Point"}
}