{
  "type": "Feature",
  "properties": {
    "addr:full":"1343 Brinkley Rd Murfreesboro TN 37128",
    "addr:housenumber":"1343",
    "addr:postcode":"37128",
    "addr:street":"Brinkley Rd",
    "iso:country":"US",
    "sg:address":"1343 Brinkley Rd",
    "sg:city":"Murfreesboro",
    "sg:classifiers":[
        {
            "category":"Retail",
            "subcategory":"Laundry & Dry Cleaning",
            "type":"Services"
        }
    ],
    "sg:phone":"+1 615 896 8063",
    "sg:postcode":"37128",
    "sg:province":"TN",
    "wof:name":"K & K Window Treatments",
    "wof:placetype":"venue"
},
  "geometry": {"coordinates":[-86.483739,35.869062],"type":"Point"}
}