{
  "type": "Feature",
  "properties": {
    "iso:country":"US",
    "sg:address":"5530 Clarksville Pike",
    "sg:city":"Joelton",
    "sg:classifiers":[
        {
            "category":"Home & Garden",
            "subcategory":"Hardware",
            "type":"Retail Goods"
        }
    ],
    "sg:phone":"+1 615 876 0035",
    "sg:postcode":"37080",
    "sg:province":"TN",
    "sg:tags":[
        "building",
        "material"
    ],
    "wof:name":"Swain's Hardware",
    "wof:placetype":"venue"
},
  "geometry": {"coordinates":[-86.876964,36.28208],"type":"Point"}
}