{
  "type": "Feature",
  "properties": {
    "addr:full":"1905 N Jackson St Tullahoma TN 37388",
    "addr:housenumber":"1905",
    "addr:postcode":"37388",
    "addr:street":"N Jackson St",
    "iso:country":"US",
    "sg:address":"1905 N Jackson St",
    "sg:city":"Tullahoma",
    "sg:classifiers":[
        {
            "category":"Shopping",
            "subcategory":"Books",
            "type":"Retail Goods"
        }
    ],
    "sg:phone":"+1 931 455 4452",
    "sg:postcode":"37388",
    "sg:province":"TN",
    "sg:tags":[
        "dealer"
    ],
    "wof:name":"Hastings Books Music & Video",
    "wof:placetype":"venue"
},
  "geometry": {"coordinates":[-86.232747,35.385248],"type":"Point"}
}