{
  "type": "Feature",
  "properties": {
    "iso:country":"US",
    "sg:address":"3723 Woodland Dr",
    "sg:city":"Memphis",
    "sg:classifiers":[
        {
            "category":"Professional",
            "subcategory":"Business Services",
            "type":"Services"
        }
    ],
    "sg:phone":"+1 901 324 0567",
    "sg:postcode":"38111",
    "sg:province":"TN",
    "wof:name":"Curt Guenther",
    "wof:placetype":"venue"
},
  "geometry": {"coordinates":[-89.933881,35.132773],"type":"Point"}
}