{
  "type": "Feature",
  "properties": {
    "iso:country":"US",
    "sg:address":"2175 Hunt Rd SE",
    "sg:city":"Cleveland",
    "sg:classifiers":[
        {
            "category":"Building & Trades",
            "subcategory":"Construction",
            "type":"Services"
        }
    ],
    "sg:phone":"+1 423 479 7719",
    "sg:postcode":"37323",
    "sg:province":"TN",
    "sg:tags":[
        "hanging",
        "contractor"
    ],
    "wof:name":"Maples Painting",
    "wof:placetype":"venue"
},
  "geometry": {"coordinates":[-84.865241,35.049464],"type":"Point"}
}