{
  "type": "Feature",
  "properties": {
    "iso:country":"US",
    "sg:address":"5725 Hwy 11 E",
    "sg:city":"Piney Flats",
    "sg:classifiers":[
        {
            "category":"Insurance",
            "subcategory":"Insurance Agent",
            "type":"Services"
        }
    ],
    "sg:phone":"+1 423 538 0534",
    "sg:postcode":"37686",
    "sg:province":"TN",
    "wof:name":"L & H Insurance",
    "wof:placetype":"venue"
},
  "geometry": {"coordinates":[-82.309197,36.432533],"type":"Point"}
}