{
  "type": "Feature",
  "properties": {
    "addr:full":"1337 Greenville Pike Hazel Green TN 35750",
    "addr:housenumber":"1337",
    "addr:postcode":"35750",
    "addr:street":"Greenville Pike",
    "iso:country":"US",
    "sg:address":"1337 Greenville Pike",
    "sg:city":"Hazel Green",
    "sg:classifiers":[
        {
            "category":"Building & Trades",
            "subcategory":"Plumbing",
            "type":"Services"
        }
    ],
    "sg:phone":"+1 256 829 1021",
    "sg:postcode":"35750",
    "sg:province":"TN",
    "sg:tags":[
        "air",
        "heating",
        "conditioning",
        "contractor"
    ],
    "wof:name":"David Britton",
    "wof:placetype":"venue"
},
  "geometry": {"coordinates":[-86.518034,34.983102],"type":"Point"}
}