{
  "type": "Feature",
  "properties": {
    "iso:country":"US",
    "sg:address":"5252 Hickory Hollow Pkwy",
    "sg:city":"Antioch",
    "sg:classifiers":[
        {
            "category":"Shopping",
            "subcategory":"Clothing, Apparel, & Fashions",
            "type":"Retail Goods"
        }
    ],
    "sg:phone":"+1 615 731 6204",
    "sg:postcode":"37013",
    "sg:province":"TN",
    "sg:website":"www.aeropostale.com",
    "wof:name":"Aeropostale",
    "wof:placetype":"venue"
},
  "geometry": {"coordinates":[-86.6574,36.048417],"type":"Point"}
}