{
  "type": "Feature",
  "properties": {
    "iso:country":"US",
    "sg:address":"2046 Chapman Hwy",
    "sg:city":"Sevierville",
    "sg:classifiers":[
        {
            "category":"Food & Beverages",
            "subcategory":"Groceries & Convenience Stores",
            "type":"Retail Goods"
        }
    ],
    "sg:phone":"+1 865 908 9501",
    "sg:postcode":"37876",
    "sg:province":"TN",
    "wof:name":"Miles Market Grill & Mini Strg",
    "wof:placetype":"venue"
},
  "geometry": {"coordinates":[-83.633529,35.854049],"type":"Point"}
}