{
  "type": "Feature",
  "properties": {
    "addr:full":"2049 Stonebrook Pl Kingsport TN 37660",
    "addr:housenumber":"2049",
    "addr:postcode":"37660",
    "addr:street":"Stonebrook Pl",
    "iso:country":"US",
    "sg:address":"2049 Stonebrook Pl",
    "sg:city":"Kingsport",
    "sg:classifiers":[
        {
            "category":"Organizations",
            "subcategory":"Religious Organization",
            "type":"Services"
        }
    ],
    "sg:phone":"+1 423 245 8111",
    "sg:postcode":"37660",
    "sg:province":"TN",
    "wof:name":"Jehovahs Wtnsss-West Kingsport",
    "wof:placetype":"venue"
},
  "geometry": {"coordinates":[-82.54306200000001,36.555775],"type":"Point"}
}