{
  "type": "Feature",
  "properties": {
    "addr:full":"1789 Gallatin Pike N Madison TN 37115",
    "addr:housenumber":"1789",
    "addr:postcode":"37115",
    "addr:street":"Gallatin Pike N",
    "iso:country":"US",
    "sg:address":"1789 Gallatin Pike N",
    "sg:city":"Madison",
    "sg:classifiers":[
        {
            "category":"Shopping",
            "subcategory":"Books",
            "type":"Retail Goods"
        }
    ],
    "sg:phone":"+1 615 860 3133",
    "sg:postcode":"37115",
    "sg:province":"TN",
    "sg:tags":[
        "dealer"
    ],
    "sg:website":"www.booksamillioninc.com",
    "wof:name":"Books-A-Million",
    "wof:placetype":"venue"
},
  "geometry": {"coordinates":[-86.70217599999999,36.293473],"type":"Point"}
}