{
  "type": "Feature",
  "properties": {
    "iso:country":"US",
    "sg:address":"11408 Kingston Pike",
    "sg:city":"Knoxville",
    "sg:classifiers":[
        {
            "category":"Health Services",
            "subcategory":"Doctor",
            "type":"Services"
        }
    ],
    "sg:phone":"+1 865 671 6026",
    "sg:postcode":"37934",
    "sg:province":"TN",
    "sg:tags":[
        "clinic"
    ],
    "wof:name":"Farragut Walk In Clinic",
    "wof:placetype":"venue"
},
  "geometry": {"coordinates":[-84.16075600000001,35.88099],"type":"Point"}
}