{
  "type": "Feature",
  "properties": {
    "iso:country":"US",
    "sg:address":"1020 S 1st St",
    "sg:city":"Union City",
    "sg:classifiers":[
        {
            "category":"Restaurant",
            "type":"Food & Drink"
        }
    ],
    "sg:phone":"+1 731 884 2184",
    "sg:postcode":"38261",
    "sg:province":"TN",
    "sg:tags":[
        "eating"
    ],
    "wof:name":"Penny Hill Shoppe",
    "wof:placetype":"venue"
},
  "geometry": {"coordinates":[-89.058233,36.411441],"type":"Point"}
}