{
  "type": "Feature",
  "properties": {
    "addr:full":"2415 Dayton Blvd Chattanooga TN 37415",
    "addr:housenumber":"2415",
    "addr:postcode":"37415",
    "addr:street":"Dayton Blvd",
    "iso:country":"US",
    "sg:address":"2415 Dayton Blvd",
    "sg:city":"Chattanooga",
    "sg:classifiers":[
        {
            "category":"Retail",
            "subcategory":"Repair Shop",
            "type":"Services"
        }
    ],
    "sg:phone":"+1 423 877 5848",
    "sg:postcode":"37415",
    "sg:province":"TN",
    "sg:tags":[
        "lock",
        "locksmith"
    ],
    "wof:name":"Red Bank Lock & Key",
    "wof:placetype":"venue"
},
  "geometry": {"coordinates":[-85.30439200000001,35.097617],"type":"Point"}
}