{
  "type": "Feature",
  "properties": {
    "addr:full":"306 Valleywood Dr Dickson TN 37055",
    "addr:housenumber":"306",
    "addr:postcode":"37055",
    "addr:street":"Valleywood Dr",
    "iso:country":"US",
    "sg:address":"306 Valleywood Dr",
    "sg:city":"Dickson",
    "sg:classifiers":[
        {
            "category":"Personal",
            "subcategory":"Beauty Salon",
            "type":"Services"
        }
    ],
    "sg:phone":"+1 615 446 9754",
    "sg:postcode":"37055",
    "sg:province":"TN",
    "wof:name":"Marla's Hair Carousel",
    "wof:placetype":"venue"
},
  "geometry": {"coordinates":[-87.420052,36.090944],"type":"Point"}
}