{
  "type": "Feature",
  "properties": {
    "addr:full":"637 Wallace Rd Jackson TN 38305",
    "addr:housenumber":"637",
    "addr:postcode":"38305",
    "addr:street":"Wallace Rd",
    "iso:country":"US",
    "sg:address":"637 Wallace Rd",
    "sg:city":"Jackson",
    "sg:classifiers":[
        {
            "category":"Social Services",
            "subcategory":"Child Care",
            "type":"Services"
        },
        {
            "category":"Organizations",
            "subcategory":"Religious Organization",
            "type":"Services"
        }
    ],
    "sg:phone":"+1 731 668 0757",
    "sg:postcode":"38305",
    "sg:province":"TN",
    "sg:tags":[
        "school",
        "day",
        "church"
    ],
    "wof:name":"Concordia Lutheran Church-Lcms",
    "wof:placetype":"venue"
},
  "geometry": {"coordinates":[-88.84474899999999,35.659029],"type":"Point"}
}