{
  "type": "Feature",
  "properties": {
    "addr:full":"1918 McArthur St Manchester TN 37355",
    "addr:housenumber":"1918",
    "addr:postcode":"37355",
    "addr:street":"Mcarthur St",
    "iso:country":"US",
    "sg:address":"1918 McArthur St",
    "sg:city":"Manchester",
    "sg:classifiers":[
        {
            "category":"Personal",
            "subcategory":"Beauty Salon",
            "type":"Services"
        }
    ],
    "sg:phone":"+1 931 728 0795",
    "sg:postcode":"37355",
    "sg:province":"TN",
    "sg:tags":[
        "shop"
    ],
    "wof:name":"Lasting Impressions",
    "wof:placetype":"venue"
},
  "geometry": {"coordinates":[-86.095203,35.450905],"type":"Point"}
}