{
  "type": "Feature",
  "properties": {
    "iso:country":"US",
    "sg:address":"1214 Gallatin Ave",
    "sg:city":"Nashville",
    "sg:classifiers":[
        {
            "category":"Wholesale",
            "subcategory":"Groceries",
            "type":"Manufacturing & Wholesale Goods"
        }
    ],
    "sg:phone":"+1 615 228 8054",
    "sg:postcode":"37206",
    "sg:province":"TN",
    "sg:tags":[
        "line",
        "general"
    ],
    "wof:name":"R & C Produce",
    "wof:placetype":"venue"
},
  "geometry": {"coordinates":[-86.745052,36.191508],"type":"Point"}
}