{
  "type": "Feature",
  "properties": {
    "iso:country":"US",
    "sg:address":"521 E Columbia Ave",
    "sg:city":"Knoxville",
    "sg:classifiers":[
        {
            "category":"Retail",
            "subcategory":"Laundry & Dry Cleaning",
            "type":"Services"
        }
    ],
    "sg:phone":"+1 865 973 0531",
    "sg:postcode":"37917",
    "sg:province":"TN",
    "sg:tags":[
        "cleaners",
        "rug",
        "carpet"
    ],
    "wof:name":"Jarvis Carpet Cleaning",
    "wof:placetype":"venue"
},
  "geometry": {"coordinates":[-83.931787,35.992028],"type":"Point"}
}