{
  "type": "Feature",
  "properties": {
    "addr:full":"1237 Clay St Nashville TN 37208",
    "addr:housenumber":"1237",
    "addr:postcode":"37208",
    "addr:street":"Clay St",
    "iso:country":"US",
    "sg:address":"1237 Clay St",
    "sg:city":"Nashville",
    "sg:classifiers":[
        {
            "category":"Food & Beverages",
            "subcategory":"Groceries & Convenience Stores",
            "type":"Retail Goods"
        }
    ],
    "sg:phone":"+1 615 291 5003",
    "sg:postcode":"37208",
    "sg:province":"TN",
    "wof:name":"Clay Street Market",
    "wof:placetype":"venue"
},
  "geometry": {"coordinates":[-86.807923,36.183645],"type":"Point"}
}