{
  "type": "Feature",
  "properties": {
    "addr:full":"111 S Court Sq Mc Minnville TN 37110",
    "addr:housenumber":"111",
    "addr:postcode":"37110",
    "addr:street":"S Court Sq",
    "iso:country":"US",
    "sg:address":"111 S Court Sq",
    "sg:city":"Mc Minnville",
    "sg:classifiers":[
        {
            "category":"Government",
            "subcategory":"Office",
            "type":"Public Place"
        }
    ],
    "sg:phone":"+1 931 473 2393",
    "sg:postcode":"37110",
    "sg:province":"TN",
    "wof:name":"Warren County General Sessions",
    "wof:placetype":"venue"
},
  "geometry": {"coordinates":[-85.773134,35.681334],"type":"Point"}
}