{
  "type": "Feature",
  "properties": {
    "iso:country":"US",
    "sg:address":"2900 Corral Rd",
    "sg:city":"Signal Mountain",
    "sg:classifiers":[
        {
            "category":"Wholesale",
            "subcategory":"Jewelry",
            "type":"Manufacturing & Wholesale Goods"
        }
    ],
    "sg:phone":"+1 423 886 6949",
    "sg:postcode":"37377",
    "sg:province":"TN",
    "sg:tags":[
        "stone"
    ],
    "wof:name":"Brazil To You",
    "wof:placetype":"venue"
},
  "geometry": {"coordinates":[-85.341943,35.195481],"type":"Point"}
}