{
  "type": "Feature",
  "properties": {
    "iso:country":"US",
    "sg:address":"105 Double Springs Rd",
    "sg:city":"Cookeville",
    "sg:classifiers":[
        {
            "category":"Retail",
            "subcategory":"Repair Shop",
            "type":"Services"
        }
    ],
    "sg:phone":"+1 931 528 5423",
    "sg:postcode":"38501",
    "sg:province":"TN",
    "sg:tags":[
        "taxidermist"
    ],
    "wof:name":"Sircy's Whitetail Taxidermy",
    "wof:placetype":"venue"
},
  "geometry": {"coordinates":[-85.59741200000001,36.171076],"type":"Point"}
}