{
  "type": "Feature",
  "properties": {
    "iso:country":"US",
    "sg:address":"2215 Central Ave",
    "sg:city":"Memphis",
    "sg:classifiers":[
        {
            "category":"Shopping",
            "type":"Retail Goods"
        }
    ],
    "sg:phone":"+1 901 452 5565",
    "sg:postcode":"38104",
    "sg:province":"TN",
    "sg:tags":[
        "picture",
        "frame"
    ],
    "wof:name":"Town & Country Custom Framing",
    "wof:placetype":"venue"
},
  "geometry": {"coordinates":[-89.987807,35.125904],"type":"Point"}
}