{
  "type": "Feature",
  "properties": {
    "iso:country":"US",
    "sg:address":"1940 Neelys Bend Rd",
    "sg:city":"Madison",
    "sg:classifiers":[
        {
            "category":"Communications",
            "subcategory":"Radio Station",
            "type":"Services"
        }
    ],
    "sg:phone":"+1 615 868 4458",
    "sg:postcode":"37115",
    "sg:province":"TN",
    "sg:tags":[
        "company",
        "broadcasting"
    ],
    "wof:name":"WYFN",
    "wof:placetype":"venue"
},
  "geometry": {"coordinates":[-86.665566,36.210482],"type":"Point"}
}