{
  "type": "Feature",
  "properties": {
    "addr:full":"306 Front St Fayetteville TN 37334",
    "addr:housenumber":"306",
    "addr:postcode":"37334",
    "addr:street":"Front St",
    "iso:country":"US",
    "sg:address":"306 Front St",
    "sg:city":"Fayetteville",
    "sg:classifiers":[
        {
            "category":"Restaurant",
            "type":"Food & Drink"
        }
    ],
    "sg:phone":"+1 931 438 0147",
    "sg:postcode":"37334",
    "sg:province":"TN",
    "sg:tags":[
        "eating"
    ],
    "wof:name":"Rays Bar B Que Pit",
    "wof:placetype":"venue"
},
  "geometry": {"coordinates":[-86.565658,35.14992],"type":"Point"}
}