{
  "type": "Feature",
  "properties": {
    "iso:country":"US",
    "sg:address":"1538 Georgetown Ln",
    "sg:city":"Murfreesboro",
    "sg:classifiers":[
        {
            "category":"Professional",
            "subcategory":"Business Services",
            "type":"Services"
        }
    ],
    "sg:phone":"+1 615 494 9898",
    "sg:postcode":"37129",
    "sg:province":"TN",
    "wof:name":"Satellite Auction Development",
    "wof:placetype":"venue"
},
  "geometry": {"coordinates":[-86.41386900000001,35.872886],"type":"Point"}
}