{
  "type": "Feature",
  "properties": {
    "iso:country":"US",
    "sg:address":"1254 Burnett Ln",
    "sg:city":"Covington",
    "sg:classifiers":[
        {
            "category":"Building & Trades",
            "subcategory":"Plumbing",
            "type":"Services"
        }
    ],
    "sg:phone":"+1 901 476 0329",
    "sg:postcode":"38019",
    "sg:province":"TN",
    "sg:tags":[
        "contractor"
    ],
    "wof:name":"Lanes Heat & Air",
    "wof:placetype":"venue"
},
  "geometry": {"coordinates":[-89.615005,35.538986],"type":"Point"}
}