{
  "type": "Feature",
  "properties": {
    "iso:country":"US",
    "sg:address":"7294 Dexter Rd",
    "sg:city":"Cordova",
    "sg:classifiers":[
        {
            "category":"Building & Trades",
            "subcategory":"Construction",
            "type":"Services"
        }
    ],
    "sg:phone":"+1 901 377 1415",
    "sg:postcode":"38016",
    "sg:province":"TN",
    "sg:tags":[
        "contractor"
    ],
    "wof:name":"Mosley Masonry",
    "wof:placetype":"venue"
},
  "geometry": {"coordinates":[-89.821257,35.171414],"type":"Point"}
}