{
  "type": "Feature",
  "properties": {
    "iso:country":"US",
    "sg:address":"144 N 3rd St",
    "sg:city":"Memphis",
    "sg:classifiers":[
        {
            "category":"Insurance",
            "subcategory":"Hazard Insurance",
            "type":"Services"
        },
        {
            "category":"Professional",
            "subcategory":"Business Services",
            "type":"Services"
        }
    ],
    "sg:phone":"+1 901 523 1308",
    "sg:postcode":"38103",
    "sg:province":"TN",
    "sg:tags":[
        "bond"
    ],
    "wof:name":"M & M Bail Bond Co",
    "wof:placetype":"venue"
},
  "geometry": {"coordinates":[-90.048976,35.147653],"type":"Point"}
}