{
  "type": "Feature",
  "properties": {
    "addr:full":"5386 N Angela Rd Memphis TN 38120",
    "addr:housenumber":"5386",
    "addr:postcode":"38120",
    "addr:street":"N Angela Rd",
    "iso:country":"US",
    "sg:address":"5386 N Angela Rd",
    "sg:city":"Memphis",
    "sg:classifiers":[
        {
            "category":"Food & Beverages",
            "subcategory":"Meat & Fish",
            "type":"Retail Goods"
        }
    ],
    "sg:phone":"+1 901 682 6243",
    "sg:postcode":"38120",
    "sg:province":"TN",
    "wof:name":"Justus 8 Co Just Good Food",
    "wof:placetype":"venue"
},
  "geometry": {"coordinates":[-89.880026,35.128838],"type":"Point"}
}