{
  "type": "Feature",
  "properties": {
    "iso:country":"US",
    "sg:address":"6 US Hwy 412 E",
    "sg:city":"Jackson",
    "sg:classifiers":[
        {
            "category":"Professional",
            "type":"Services"
        }
    ],
    "sg:phone":"+1 731 424 2929",
    "sg:postcode":"38305",
    "sg:province":"TN",
    "wof:name":"Autocorp",
    "wof:placetype":"venue"
},
  "geometry": {"coordinates":[-88.738848,35.676969],"type":"Point"}
}