{
  "type": "Feature",
  "properties": {
    "iso:country":"US",
    "sg:address":"1020 Elmshade Ln",
    "sg:city":"Nashville",
    "sg:classifiers":[
        {
            "category":"Shopping",
            "subcategory":"Clothing, Apparel, & Fashions",
            "type":"Retail Goods"
        }
    ],
    "sg:phone":"+1 615 376 2185",
    "sg:postcode":"37211",
    "sg:province":"TN",
    "sg:tags":[
        "accessory"
    ],
    "wof:name":"Rich Bich Designs",
    "wof:placetype":"venue"
},
  "geometry": {"coordinates":[-86.725241,36.034994],"type":"Point"}
}