{
  "type": "Feature",
  "properties": {
    "iso:country":"US",
    "sg:address":"2415 Dutch Valley Dr",
    "sg:city":"Knoxville",
    "sg:classifiers":[
        {
            "category":"Wholesale",
            "subcategory":"Non-durable Goods",
            "type":"Manufacturing & Wholesale Goods"
        }
    ],
    "sg:phone":"+1 865 687 0304",
    "sg:postcode":"37918",
    "sg:province":"TN",
    "wof:name":"Derby Distribution",
    "wof:placetype":"venue"
},
  "geometry": {"coordinates":[-83.929104,36.015867],"type":"Point"}
}