{
  "type": "Feature",
  "properties": {
    "iso:country":"US",
    "sg:address":"1955 Madison St",
    "sg:city":"Clarksville",
    "sg:classifiers":[
        {
            "category":"Recreation",
            "type":"Entertainment"
        }
    ],
    "sg:phone":"+1 931 552 5433",
    "sg:postcode":"37043",
    "sg:province":"TN",
    "wof:name":"Kingdom Sports Inc",
    "wof:placetype":"venue"
},
  "geometry": {"coordinates":[-87.297769,36.51443],"type":"Point"}
}