{
  "type": "Feature",
  "properties": {
    "iso:country":"US",
    "sg:address":"141 E Broad St",
    "sg:city":"Clinton",
    "sg:classifiers":[
        {
            "category":"Health Services",
            "subcategory":"Hospital",
            "type":"Services"
        }
    ],
    "sg:phone":"+1 865 463 8870",
    "sg:postcode":"37716",
    "sg:province":"TN",
    "sg:tags":[
        "mental"
    ],
    "wof:name":"Anderson County Health Council",
    "wof:placetype":"venue"
},
  "geometry": {"coordinates":[-84.13274199999999,36.099399],"type":"Point"}
}