{
  "type": "Feature",
  "properties": {
    "addr:full":"736 Richfield Dr Nashville TN 37205",
    "addr:housenumber":"736",
    "addr:postcode":"37205",
    "addr:street":"Richfield Dr",
    "iso:country":"US",
    "sg:address":"736 Richfield Dr",
    "sg:city":"Nashville",
    "sg:classifiers":[
        {
            "category":"Communications",
            "subcategory":"Film & Video Production",
            "type":"Services"
        }
    ],
    "sg:phone":"+1 615 352 7629",
    "sg:postcode":"37205",
    "sg:province":"TN",
    "sg:tags":[
        "motion"
    ],
    "wof:name":"Bigscreen Inc",
    "wof:placetype":"venue"
},
  "geometry": {"coordinates":[-86.88556800000001,36.125811],"type":"Point"}
}