{
  "type": "Feature",
  "properties": {
    "iso:country":"US",
    "sg:address":"6860 Innsbrook Cove",
    "sg:city":"Memphis",
    "sg:classifiers":[
        {
            "category":"Social Services",
            "subcategory":"Child Care",
            "type":"Services"
        }
    ],
    "sg:phone":"+1 901 370 6744",
    "sg:postcode":"38115",
    "sg:province":"TN",
    "sg:tags":[
        "day"
    ],
    "wof:name":"Wrightway Childcare",
    "wof:placetype":"venue"
},
  "geometry": {"coordinates":[-89.83438200000001,35.043476],"type":"Point"}
}