{
  "type": "Feature",
  "properties": {
    "iso:country":"US",
    "sg:address":"699 Monroe Ave",
    "sg:city":"Memphis",
    "sg:classifiers":[
        {
            "category":"Retail",
            "subcategory":"Auto Repair",
            "type":"Services"
        }
    ],
    "sg:phone":"+1 901 527 3345",
    "sg:postcode":"38103",
    "sg:province":"TN",
    "sg:tags":[
        "body",
        "automobile",
        "painting"
    ],
    "wof:name":"Gordon's Body Shop",
    "wof:placetype":"venue"
},
  "geometry": {"coordinates":[-90.041376,35.141031],"type":"Point"}
}