{
  "type": "Feature",
  "properties": {
    "addr:full":"515 J B Stricklin Rd Troy TN 38260",
    "addr:housenumber":"515",
    "addr:postcode":"38260",
    "addr:street":"J B Stricklin Rd",
    "iso:country":"US",
    "sg:address":"515 J B Stricklin Rd",
    "sg:city":"Troy",
    "sg:classifiers":[
        {
            "category":"Farming",
            "subcategory":"Farm",
            "type":"Manufacturing & Wholesale Goods"
        }
    ],
    "sg:phone":"+1 731 538 9691",
    "sg:postcode":"38260",
    "sg:province":"TN",
    "sg:tags":[
        "crop",
        "general"
    ],
    "wof:name":"Davis Farms",
    "wof:placetype":"venue"
},
  "geometry": {"coordinates":[-89.23844699999999,36.345341],"type":"Point"}
}