{
  "type": "Feature",
  "properties": {
    "iso:country":"US",
    "sg:address":"3206 Broad Ave",
    "sg:city":"Memphis",
    "sg:classifiers":[
        {
            "category":"Retail",
            "subcategory":"Repair Shop",
            "type":"Services"
        },
        {
            "category":"Home & Garden",
            "subcategory":"Building Materials",
            "type":"Retail Goods"
        },
        {
            "category":"Building & Trades",
            "subcategory":"Construction",
            "type":"Services"
        },
        {
            "category":"Building & Trades",
            "subcategory":"Electrical",
            "type":"Services"
        }
    ],
    "sg:phone":"+1 901 842 2525",
    "sg:postcode":"38112",
    "sg:province":"TN",
    "sg:tags":[
        "industrial",
        "electrician",
        "electric",
        "improvement",
        "generators-electric-service",
        "contractors-commercial",
        "maintenance"
    ],
    "sg:website":"http://www.mrelectric.com",
    "wof:name":"Mr. Electric Of Memphis",
    "wof:placetype":"venue"
},
  "geometry": {"coordinates":[-89.954089,35.148117],"type":"Point"}
}