{
  "type": "Feature",
  "properties": {
    "addr:full":"1126 William Blount Dr Maryville TN 37801",
    "addr:housenumber":"1126",
    "addr:postcode":"37801",
    "addr:street":"William Blount Dr",
    "iso:country":"US",
    "sg:address":"1126 William Blount Dr",
    "sg:city":"Maryville",
    "sg:classifiers":[
        {
            "category":"Organizations",
            "subcategory":"Religious Organization",
            "type":"Services"
        }
    ],
    "sg:phone":"+1 865 379 1384",
    "sg:postcode":"37801",
    "sg:province":"TN",
    "sg:tags":[
        "church"
    ],
    "sg:website":"www.vineyardchristiancommunity.com",
    "wof:name":"Vineyard Christian Community",
    "wof:placetype":"venue"
},
  "geometry": {"coordinates":[-84.036315,35.737935],"type":"Point"}
}