{
  "type": "Feature",
  "properties": {
    "iso:country":"US",
    "sg:address":"1753 Pleasant Valley Rd",
    "sg:city":"Union City",
    "sg:classifiers":[
        {
            "category":"Professional",
            "subcategory":"Art Services",
            "type":"Services"
        }
    ],
    "sg:phone":"+1 731 885 4695",
    "sg:postcode":"38261",
    "sg:province":"TN",
    "sg:tags":[
        "commercial",
        "design"
    ],
    "wof:name":"Fanfare Creative Services",
    "wof:placetype":"venue"
},
  "geometry": {"coordinates":[-89.041147,36.372052],"type":"Point"}
}