{
  "type": "Feature",
  "properties": {
    "iso:country":"US",
    "sg:address":"6400 Papermill Dr",
    "sg:city":"Knoxville",
    "sg:classifiers":[
        {
            "category":"Banks & Credit Unions",
            "subcategory":"Investment Brokerage",
            "type":"Services"
        },
        {
            "category":"Insurance",
            "subcategory":"Insurance Agent",
            "type":"Services"
        }
    ],
    "sg:phone":"+1 865 558 9475",
    "sg:postcode":"37909",
    "sg:province":"TN",
    "sg:tags":[
        "consultant",
        "planning",
        "financial"
    ],
    "wof:name":"Swofford Financial Services",
    "wof:placetype":"venue"
},
  "geometry": {"coordinates":[-84.010594,35.936778],"type":"Point"}
}