{
  "type": "Feature",
  "properties": {
    "iso:country":"US",
    "sg:address":"2725 Ash Way",
    "sg:city":"Newport",
    "sg:classifiers":[
        {
            "category":"Food & Beverages",
            "subcategory":"Candy",
            "type":"Retail Goods"
        }
    ],
    "sg:phone":"+1 423 625 3066",
    "sg:postcode":"37821",
    "sg:province":"TN",
    "sg:tags":[
        "nut",
        "retailer"
    ],
    "wof:name":"Roasted Nut Treats",
    "wof:placetype":"venue"
},
  "geometry": {"coordinates":[-83.228799,35.874291],"type":"Point"}
}