{
  "type": "Feature",
  "properties": {
    "iso:country":"US",
    "sg:address":"1005 E Shelby Dr",
    "sg:city":"Memphis",
    "sg:classifiers":[
        {
            "category":"Organizations",
            "subcategory":"Religious Organization",
            "type":"Services"
        }
    ],
    "sg:phone":"+1 901 348 0985",
    "sg:postcode":"38116",
    "sg:province":"TN",
    "sg:tags":[
        "church"
    ],
    "wof:name":"Parkway Gardens Presbyterian",
    "wof:placetype":"venue"
},
  "geometry": {"coordinates":[-90.031868,35.020838],"type":"Point"}
}