{
  "type": "Feature",
  "properties": {
    "addr:full":"5648 Summer Ave Bartlett TN 38134",
    "addr:housenumber":"5648",
    "addr:postcode":"38134",
    "addr:street":"Summer Ave",
    "iso:country":"US",
    "sg:address":"5648 Summer Ave",
    "sg:city":"Bartlett",
    "sg:classifiers":[
        {
            "category":"Building & Trades",
            "subcategory":"Equipment Rental",
            "type":"Services"
        }
    ],
    "sg:phone":"+1 901 377 7052",
    "sg:postcode":"38134",
    "sg:province":"TN",
    "sg:tags":[
        "leasing"
    ],
    "wof:name":"GE Capital Corp",
    "wof:placetype":"venue"
},
  "geometry": {"coordinates":[-89.874393,35.166211],"type":"Point"}
}