{
  "type": "Feature",
  "properties": {
    "addr:full":"1751 S Prescott St Memphis TN 38111",
    "addr:housenumber":"1751",
    "addr:postcode":"38111",
    "addr:street":"S Prescott St",
    "iso:country":"US",
    "sg:address":"1751 S Prescott St",
    "sg:city":"Memphis",
    "sg:classifiers":[
        {
            "category":"Autos & Motor Vehicles",
            "subcategory":"Fuel & Gas Station",
            "type":"Retail Goods"
        }
    ],
    "sg:phone":"+1 901 743 1959",
    "sg:postcode":"38111",
    "sg:province":"TN",
    "sg:tags":[
        "oil"
    ],
    "wof:name":"Phillips 66",
    "wof:placetype":"venue"
},
  "geometry": {"coordinates":[-89.956103,35.082467],"type":"Point"}
}