{
  "type": "Feature",
  "properties": {
    "iso:country":"US",
    "sg:address":"569 Loyston Rd",
    "sg:city":"Maynardville",
    "sg:classifiers":[
        {
            "category":"Wholesale",
            "subcategory":"Construction Materials",
            "type":"Manufacturing & Wholesale Goods"
        }
    ],
    "sg:phone":"+1 865 992 2442",
    "sg:postcode":"37807",
    "sg:province":"TN",
    "sg:tags":[
        "quarry"
    ],
    "wof:name":"Loyston Road Quarry",
    "wof:placetype":"venue"
},
  "geometry": {"coordinates":[-83.927031,36.181116],"type":"Point"}
}