{
  "type": "Feature",
  "properties": {
    "iso:country":"US",
    "sg:address":"212 Cherokee Rd",
    "sg:city":"Hendersonville",
    "sg:classifiers":[
        {
            "category":"Wholesale",
            "subcategory":"Hardware",
            "type":"Manufacturing & Wholesale Goods"
        }
    ],
    "sg:phone":"+1 615 822 3331",
    "sg:postcode":"37075",
    "sg:province":"TN",
    "sg:tags":[
        "purifying",
        "cleaning",
        "air"
    ],
    "wof:name":"Fresh Air Resolution",
    "wof:placetype":"venue"
},
  "geometry": {"coordinates":[-86.60637,36.29523],"type":"Point"}
}