{
  "type": "Feature",
  "properties": {
    "iso:country":"US",
    "sg:address":"2403 Elliott Ave",
    "sg:city":"Nashville",
    "sg:classifiers":[
        {
            "category":"Professional",
            "subcategory":"Business Services",
            "type":"Services"
        }
    ],
    "sg:phone":"+1 615 269 4449",
    "sg:postcode":"37204",
    "sg:province":"TN",
    "wof:name":"M S I Nashville",
    "wof:placetype":"venue"
},
  "geometry": {"coordinates":[-86.77858000000001,36.124607],"type":"Point"}
}