{
  "type": "Feature",
  "properties": {
    "iso:country":"US",
    "sg:address":"711 Groves Park Rd",
    "sg:city":"Nashville",
    "sg:classifiers":[
        {
            "category":"Shopping",
            "subcategory":"Gifts & Souvenirs",
            "type":"Retail Goods"
        }
    ],
    "sg:phone":"+1 615 227 2494",
    "sg:postcode":"37206",
    "sg:province":"TN",
    "wof:name":"R C Noveltys",
    "wof:placetype":"venue"
},
  "geometry": {"coordinates":[-86.727078,36.18191],"type":"Point"}
}