{
  "type": "Feature",
  "properties": {
    "addr:full":"9002 Lovell Rd Hixson TN 37343",
    "addr:housenumber":"9002",
    "addr:postcode":"37343",
    "addr:street":"Lovell Rd",
    "iso:country":"US",
    "sg:address":"9002 Lovell Rd",
    "sg:city":"Hixson",
    "sg:classifiers":[
        {
            "category":"Professional",
            "subcategory":"Business Services",
            "type":"Services"
        }
    ],
    "sg:phone":"+1 423 842 1848",
    "sg:postcode":"37343",
    "sg:province":"TN",
    "wof:name":"Horne Enterprises Inc",
    "wof:placetype":"venue"
},
  "geometry": {"coordinates":[-85.176991,35.220202],"type":"Point"}
}