{
  "type": "Feature",
  "properties": {
    "addr:full":"6743 Clinton Hwy Knoxville TN 37912",
    "addr:housenumber":"6743",
    "addr:postcode":"37912",
    "addr:street":"Clinton Hwy",
    "iso:country":"US",
    "sg:address":"6743 Clinton Hwy",
    "sg:city":"Knoxville",
    "sg:classifiers":[
        {
            "category":"Shopping",
            "subcategory":"Jewelry",
            "type":"Retail Goods"
        }
    ],
    "sg:phone":"+1 865 938 2833",
    "sg:postcode":"37912",
    "sg:province":"TN",
    "wof:name":"Friedmans Jewelers",
    "wof:placetype":"venue"
},
  "geometry": {"coordinates":[-84.021259,36.006843],"type":"Point"}
}