{
  "type": "Feature",
  "properties": {
    "iso:country":"US",
    "sg:address":"8125 US Hwy 51 N",
    "sg:city":"Millington",
    "sg:classifiers":[
        {
            "category":"Banks & Credit Unions",
            "subcategory":"Bank",
            "type":"Services"
        }
    ],
    "sg:phone":"+1 901 873 3707",
    "sg:postcode":"38053",
    "sg:province":"TN",
    "sg:tags":[
        "depository",
        "banking"
    ],
    "wof:name":"Tennessee Check Advance LLC",
    "wof:placetype":"venue"
},
  "geometry": {"coordinates":[-89.903925,35.347099],"type":"Point"}
}