{
  "type": "Feature",
  "properties": {
    "iso:country":"US",
    "sg:address":"8465 Old Charlotte Pike",
    "sg:city":"Pegram",
    "sg:classifiers":[
        {
            "category":"Building & Trades",
            "subcategory":"Construction",
            "type":"Services"
        }
    ],
    "sg:phone":"+1 615 310 9225",
    "sg:postcode":"37143",
    "sg:province":"TN",
    "sg:tags":[
        "repairing",
        "remodeling",
        "contractor"
    ],
    "wof:name":"Redarts",
    "wof:placetype":"venue"
},
  "geometry": {"coordinates":[-86.993883,36.119532],"type":"Point"}
}