{
  "type": "Feature",
  "properties": {
    "addr:full":"400 William Battle Blvd Fayetteville TN 37334",
    "addr:housenumber":"400",
    "addr:postcode":"37334",
    "addr:street":"William Battle Blvd",
    "iso:country":"US",
    "sg:address":"400 William Battle Blvd",
    "sg:city":"Fayetteville",
    "sg:classifiers":[
        {
            "category":"Farming",
            "subcategory":"Vineyard",
            "type":"Manufacturing & Wholesale Goods"
        }
    ],
    "sg:phone":"+1 931 433 3271",
    "sg:postcode":"37334",
    "sg:province":"TN",
    "sg:tags":[
        "grape"
    ],
    "wof:name":"Robert Eady",
    "wof:placetype":"venue"
},
  "geometry": {"coordinates":[-86.587412,35.150137],"type":"Point"}
}