{
  "type": "Feature",
  "properties": {
    "iso:country":"US",
    "sg:address":"200 N Poplar St",
    "sg:city":"Paris",
    "sg:classifiers":[
        {
            "category":"Professional",
            "subcategory":"Lawyer & Legal Services",
            "type":"Services"
        }
    ],
    "sg:phone":"+1 731 642 0178",
    "sg:postcode":"38242",
    "sg:province":"TN",
    "sg:tags":[
        "attorney"
    ],
    "sg:website":"www.ahchlaw.com",
    "wof:name":"Ainley Hoover & Clark",
    "wof:placetype":"venue"
},
  "geometry": {"coordinates":[-88.325287,36.303561],"type":"Point"}
}