{
  "type": "Feature",
  "properties": {
    "addr:full":"5379 Mount View Rd Antioch TN 37013",
    "addr:housenumber":"5379",
    "addr:postcode":"37013",
    "addr:street":"Mount View Rd",
    "iso:country":"US",
    "sg:address":"5379 Mount View Rd",
    "sg:city":"Antioch",
    "sg:classifiers":[
        {
            "category":"Shopping",
            "type":"Retail Goods"
        }
    ],
    "sg:phone":"+1 615 627 4848",
    "sg:postcode":"37013",
    "sg:province":"TN",
    "sg:tags":[
        "merchandise"
    ],
    "wof:name":"Nextel",
    "wof:placetype":"venue"
},
  "geometry": {"coordinates":[-86.64809700000001,36.048663],"type":"Point"}
}