{
  "type": "Feature",
  "properties": {
    "iso:country":"US",
    "sg:address":"490 US Highway 51 Byp W",
    "sg:city":"Dyersburg",
    "sg:classifiers":[
        {
            "category":"Professional",
            "type":"Services"
        },
        {
            "category":"Restaurant",
            "type":"Food & Drink"
        },
        {
            "category":"Fast Food",
            "type":"Food & Drink"
        }
    ],
    "sg:phone":"+1 731 285 0777",
    "sg:postcode":"38024",
    "sg:province":"TN",
    "sg:tags":[
        "delivery",
        "take",
        "pizza"
    ],
    "sg:website":"http://www.littlecaesars.com",
    "wof:name":"Little Caesars Pizza",
    "wof:placetype":"venue"
},
  "geometry": {"coordinates":[-89.412251,36.03577],"type":"Point"}
}