{
  "type": "Feature",
  "properties": {
    "addr:full":"498 Giltedge Rd Munford TN 38058",
    "addr:housenumber":"498",
    "addr:postcode":"38058",
    "addr:street":"Giltedge Rd",
    "iso:country":"US",
    "sg:address":"498 Giltedge Rd",
    "sg:city":"Munford",
    "sg:classifiers":[
        {
            "category":"Building & Trades",
            "subcategory":"Construction",
            "type":"Services"
        }
    ],
    "sg:phone":"+1 901 837 0549",
    "sg:postcode":"38058",
    "sg:province":"TN",
    "sg:tags":[
        "wallcoverings-installation",
        "wallpaper",
        "painting",
        "contractor"
    ],
    "wof:name":"Steve's Custom Painting",
    "wof:placetype":"venue"
},
  "geometry": {"coordinates":[-89.81874500000001,35.455993],"type":"Point"}
}