{
  "type": "Feature",
  "properties": {
    "iso:country":"US",
    "sg:address":"2051 Cedar St",
    "sg:city":"Mc Kenzie",
    "sg:classifiers":[
        {
            "category":"Real Estate",
            "subcategory":"Real Estate Agent",
            "type":"Services"
        }
    ],
    "sg:phone":"+1 731 352 2255",
    "sg:postcode":"38201",
    "sg:province":"TN",
    "sg:tags":[
        "motion",
        "picture"
    ],
    "wof:name":"3M",
    "wof:placetype":"venue"
},
  "geometry": {"coordinates":[-88.513623,36.129964],"type":"Point"}
}