{
  "type": "Feature",
  "properties": {
    "addr:full":"1337 Lucy Kelly Rd Brighton TN 38011",
    "addr:housenumber":"1337",
    "addr:postcode":"38011",
    "addr:street":"Lucy Kelly Rd",
    "iso:country":"US",
    "sg:address":"1337 Lucy Kelly Rd",
    "sg:city":"Brighton",
    "sg:classifiers":[
        {
            "category":"Retail",
            "subcategory":"Auto Repair",
            "type":"Services"
        }
    ],
    "sg:phone":"+1 901 475 4910",
    "sg:postcode":"38011",
    "sg:province":"TN",
    "sg:tags":[
        "machine",
        "automotive",
        "shop",
        "automobile"
    ],
    "wof:name":"Hy Performance Engines",
    "wof:placetype":"venue"
},
  "geometry": {"coordinates":[-89.719599,35.462774],"type":"Point"}
}