{
  "type": "Feature",
  "properties": {
    "iso:country":"US",
    "sg:address":"10638 Deerbrook Dr",
    "sg:city":"Knoxville",
    "sg:classifiers":[
        {
            "category":"Freight",
            "type":"Transportation"
        }
    ],
    "sg:phone":"+1 865 671 1909",
    "sg:postcode":"37922",
    "sg:province":"TN",
    "sg:tags":[
        "general"
    ],
    "wof:name":"Lovell Road Mini Storage Inc",
    "wof:placetype":"venue"
},
  "geometry": {"coordinates":[-84.138339,35.899912],"type":"Point"}
}