{
  "type": "Feature",
  "properties": {
    "addr:full":"6375 Summer Ave Memphis TN 38134",
    "addr:housenumber":"6375",
    "addr:postcode":"38134",
    "addr:street":"Summer Ave",
    "iso:country":"US",
    "sg:address":"6375 Summer Ave",
    "sg:city":"Memphis",
    "sg:classifiers":[
        {
            "category":"Wholesale",
            "subcategory":"Construction Materials",
            "type":"Manufacturing & Wholesale Goods"
        },
        {
            "category":"Home & Garden",
            "subcategory":"Building Materials",
            "type":"Retail Goods"
        }
    ],
    "sg:phone":"+1 901 363 3400",
    "sg:postcode":"38134",
    "sg:province":"TN",
    "sg:tags":[
        "trade",
        "fence",
        "contractor"
    ],
    "wof:name":"Country Estate Fence Memphis",
    "wof:placetype":"venue"
},
  "geometry": {"coordinates":[-89.851851,35.188113],"type":"Point"}
}