{
  "type": "Feature",
  "properties": {
    "iso:country":"US",
    "sg:address":"135 E Swan St",
    "sg:city":"Centerville",
    "sg:classifiers":[
        {
            "category":"Health Services",
            "subcategory":"Clinic",
            "type":"Services"
        }
    ],
    "sg:phone":"+1 931 729 4500",
    "sg:postcode":"37033",
    "sg:province":"TN",
    "sg:tags":[
        "home",
        "medical",
        "care"
    ],
    "wof:name":"Baptist Cmnty HM Care Hospice",
    "wof:placetype":"venue"
},
  "geometry": {"coordinates":[-87.46238,35.781506],"type":"Point"}
}