{
  "type": "Feature",
  "properties": {
    "iso:country":"US",
    "sg:address":"262 German Oak Dr",
    "sg:city":"Cordova",
    "sg:classifiers":[
        {
            "category":"Professional",
            "subcategory":"Business Services",
            "type":"Services"
        }
    ],
    "sg:phone":"+1 901 754 8870",
    "sg:postcode":"38018",
    "sg:province":"TN",
    "wof:name":"Employers Assoc",
    "wof:placetype":"venue"
},
  "geometry": {"coordinates":[-89.797513,35.123378],"type":"Point"}
}