{
  "type": "Feature",
  "properties": {
    "addr:full":"8544 E Andrew Johnson Hwy Chuckey TN 37641",
    "addr:housenumber":"8544",
    "addr:postcode":"37641",
    "addr:street":"E Andrew Johnson Hwy",
    "iso:country":"US",
    "sg:address":"8544 E Andrew Johnson Hwy",
    "sg:city":"Chuckey",
    "sg:classifiers":[
        {
            "category":"Social Services",
            "subcategory":"Child Care",
            "type":"Services"
        }
    ],
    "sg:phone":"+1 423 257 4442",
    "sg:postcode":"37641",
    "sg:province":"TN",
    "wof:name":"Little Rascals Child Care",
    "wof:placetype":"venue"
},
  "geometry": {"coordinates":[-82.69436399999999,36.225581],"type":"Point"}
}