{
  "type": "Feature",
  "properties": {
    "iso:country":"US",
    "sg:address":"385 Airport Rd",
    "sg:city":"Gallatin",
    "sg:classifiers":[
        {
            "category":"Building & Trades",
            "subcategory":"Construction",
            "type":"Services"
        }
    ],
    "sg:phone":"+1 615 452 5659",
    "sg:postcode":"37066",
    "sg:province":"TN",
    "sg:tags":[
        "roofing",
        "contractor"
    ],
    "sg:website":"www.watercontrol.net",
    "wof:name":"Water Control Roofing Co",
    "wof:placetype":"venue"
},
  "geometry": {"coordinates":[-86.40591000000001,36.403652],"type":"Point"}
}