{
  "type": "Feature",
  "properties": {
    "addr:full":"9137 Lynwood Ln Rockford TN 37853",
    "addr:housenumber":"9137",
    "addr:postcode":"37853",
    "addr:street":"Lynwood Ln",
    "iso:country":"US",
    "sg:address":"9137 Lynwood Ln",
    "sg:city":"Rockford",
    "sg:classifiers":[
        {
            "category":"Organizations",
            "subcategory":"Community Association",
            "type":"Services"
        }
    ],
    "sg:phone":"+1 865 980 0525",
    "sg:postcode":"37853",
    "sg:province":"TN",
    "sg:tags":[
        "club"
    ],
    "sg:website":"www.bgca.org",
    "wof:name":"Boys & Girls Club Of America",
    "wof:placetype":"venue"
},
  "geometry": {"coordinates":[-83.876812,35.846275],"type":"Point"}
}