{
  "type": "Feature",
  "properties": {
    "iso:country":"US",
    "sg:address":"1416 Woodbury Hwy",
    "sg:city":"Manchester",
    "sg:classifiers":[
        {
            "category":"Farming",
            "subcategory":"Livestock Farm",
            "type":"Manufacturing & Wholesale Goods"
        }
    ],
    "sg:phone":"+1 931 728 2331",
    "sg:postcode":"37355",
    "sg:province":"TN",
    "sg:tags":[
        "beef",
        "feedlot",
        "cattle"
    ],
    "wof:name":"Linda Verne Farm",
    "wof:placetype":"venue"
},
  "geometry": {"coordinates":[-86.08531000000001,35.506716],"type":"Point"}
}