{
  "type": "Feature",
  "properties": {
    "iso:country":"US",
    "sg:address":"2115 W Andrew Johnson Hwy",
    "sg:city":"Morristown",
    "sg:classifiers":[
        {
            "category":"Insurance",
            "subcategory":"Insurance Agent",
            "type":"Services"
        }
    ],
    "sg:phone":"+1 423 587 6655",
    "sg:postcode":"37814",
    "sg:province":"TN",
    "wof:name":"Direct General Insurance Agcy",
    "wof:placetype":"venue"
},
  "geometry": {"coordinates":[-83.320869,36.206582],"type":"Point"}
}