{
  "type": "Feature",
  "properties": {
    "addr:full":"1150 Traywick Rd Mc Kenzie TN 38201",
    "addr:housenumber":"1150",
    "addr:postcode":"38201",
    "addr:street":"Traywick Rd",
    "iso:country":"US",
    "sg:address":"1150 Traywick Rd",
    "sg:city":"Mc Kenzie",
    "sg:classifiers":[
        {
            "category":"Building & Trades",
            "subcategory":"Construction",
            "type":"Services"
        }
    ],
    "sg:phone":"+1 731 243 7209",
    "sg:postcode":"38201",
    "sg:province":"TN",
    "sg:tags":[
        "contractor"
    ],
    "wof:name":"Klopfenstein Construction",
    "wof:placetype":"venue"
},
  "geometry": {"coordinates":[-88.52476,36.197105],"type":"Point"}
}