{
  "type": "Feature",
  "properties": {
    "iso:country":"US",
    "sg:address":"1025 E Lake Ave",
    "sg:city":"Celina",
    "sg:classifiers":[
        {
            "category":"Food & Beverages",
            "subcategory":"Liquor & Beverages",
            "type":"Retail Goods"
        }
    ],
    "sg:phone":"+1 931 243 6263",
    "sg:postcode":"38551",
    "sg:province":"TN",
    "sg:tags":[
        "alcoholic"
    ],
    "wof:name":"Boles Whiskey River Liquors",
    "wof:placetype":"venue"
},
  "geometry": {"coordinates":[-85.49033799999999,36.542117],"type":"Point"}
}