{
  "type": "Feature",
  "properties": {
    "iso:country":"US",
    "sg:address":"170 Lt George W Lee Ave",
    "sg:city":"Memphis",
    "sg:classifiers":[
        {
            "category":"Restaurant",
            "type":"Food & Drink"
        }
    ],
    "sg:menulink":"http://www.allmenus.com/tn/memphis/161308-daily-grill/menu/",
    "sg:phone":"+1 901 334 5950",
    "sg:postcode":"38103",
    "sg:province":"TN",
    "sg:tags":[
        "american"
    ],
    "wof:name":"Daily Grill",
    "wof:placetype":"venue"
},
  "geometry": {"coordinates":[-90.052728,35.138791],"type":"Point"}
}