{
  "type": "Feature",
  "properties": {
    "iso:country":"US",
    "sg:address":"1083 Martinsburg Cove",
    "sg:city":"Collierville",
    "sg:classifiers":[
        {
            "category":"Retail",
            "subcategory":"Auto Repair",
            "type":"Services"
        }
    ],
    "sg:phone":"+1 901 854 4005",
    "sg:postcode":"38017",
    "sg:province":"TN",
    "sg:tags":[
        "body",
        "automobile",
        "painting"
    ],
    "wof:name":"Dent Express Inc",
    "wof:placetype":"venue"
},
  "geometry": {"coordinates":[-89.65646700000001,35.068468],"type":"Point"}
}