{
  "type": "Feature",
  "properties": {
    "addr:full":"725 Union B Rd Monterey TN 38574",
    "addr:housenumber":"725",
    "addr:postcode":"38574",
    "addr:street":"Union B Rd",
    "iso:country":"US",
    "sg:address":"725 Union B Rd",
    "sg:city":"Monterey",
    "sg:classifiers":[
        {
            "category":"Building & Trades",
            "subcategory":"Cleaning & Sanitation",
            "type":"Services"
        }
    ],
    "sg:phone":"+1 931 445 2155",
    "sg:postcode":"38574",
    "sg:province":"TN",
    "sg:tags":[
        "maintenance"
    ],
    "wof:name":"Greenscape Property Maint",
    "wof:placetype":"venue"
},
  "geometry": {"coordinates":[-85.14454000000001,36.168221],"type":"Point"}
}