{
  "type": "Feature",
  "properties": {
    "iso:country":"US",
    "sg:address":"3322 Carrie Dr",
    "sg:city":"Clarksville",
    "sg:classifiers":[
        {
            "category":"Social Services",
            "subcategory":"Child Care",
            "type":"Services"
        }
    ],
    "sg:phone":"+1 931 431 4660",
    "sg:postcode":"37042",
    "sg:province":"TN",
    "sg:tags":[
        "day"
    ],
    "wof:name":"Brittas Happy Home",
    "wof:placetype":"venue"
},
  "geometry": {"coordinates":[-87.406391,36.633376],"type":"Point"}
}