{
  "type": "Feature",
  "properties": {
    "iso:country":"US",
    "sg:address":"4557 Millbranch Rd",
    "sg:city":"Memphis",
    "sg:classifiers":[
        {
            "category":"Health Services",
            "subcategory":"Optometrist",
            "type":"Services"
        }
    ],
    "sg:phone":"+1 901 346 8222",
    "sg:postcode":"38116",
    "sg:province":"TN",
    "sg:tags":[
        "optical",
        "good"
    ],
    "wof:name":"Family Vision Care",
    "wof:placetype":"venue"
},
  "geometry": {"coordinates":[-90.007605,35.023718],"type":"Point"}
}