{
  "type": "Feature",
  "properties": {
    "iso:country":"US",
    "sg:address":"455 Cusick Cir",
    "sg:city":"Lenoir City",
    "sg:classifiers":[
        {
            "category":"Personal",
            "subcategory":"Barber",
            "type":"Services"
        }
    ],
    "sg:phone":"+1 865 986 7592",
    "sg:postcode":"37772",
    "sg:province":"TN",
    "sg:tags":[
        "shop"
    ],
    "wof:name":"Hair In Motion",
    "wof:placetype":"venue"
},
  "geometry": {"coordinates":[-84.22301400000001,35.852427],"type":"Point"}
}