{
  "type": "Feature",
  "properties": {
    "iso:country":"US",
    "sg:address":"106 Cherry St N",
    "sg:city":"Cowan",
    "sg:classifiers":[
        {
            "category":"Government",
            "subcategory":"Police Station",
            "type":"Public Place"
        }
    ],
    "sg:phone":"+1 931 962 0110",
    "sg:postcode":"37318",
    "sg:province":"TN",
    "sg:tags":[
        "department"
    ],
    "wof:name":"Cowan Police Dept",
    "wof:placetype":"venue"
},
  "geometry": {"coordinates":[-86.01052799999999,35.165368],"type":"Point"}
}