{
  "type": "Feature",
  "properties": {
    "iso:country":"US",
    "sg:address":"9942 Maupin Rd",
    "sg:city":"Brentwood",
    "sg:classifiers":[
        {
            "category":"Home & Garden",
            "subcategory":"Carpets & Floor Coverings",
            "type":"Retail Goods"
        }
    ],
    "sg:phone":"+1 615 776 5354",
    "sg:postcode":"37027",
    "sg:province":"TN",
    "sg:tags":[
        "material"
    ],
    "sg:website":"www.floorcoveringsinternational.com",
    "wof:name":"Floor Coverings International",
    "wof:placetype":"venue"
},
  "geometry": {"coordinates":[-86.69856900000001,35.982842],"type":"Point"}
}