{
  "type": "Feature",
  "properties": {
    "iso:country":"US",
    "sg:address":"1668 Kansas St",
    "sg:city":"Memphis",
    "sg:classifiers":[
        {
            "category":"Bars & Pubs",
            "type":"Food & Drink"
        }
    ],
    "sg:phone":"+1 901 775 2904",
    "sg:postcode":"38109",
    "sg:province":"TN",
    "sg:tags":[
        "drinking"
    ],
    "wof:name":"Kansas Street Lounge",
    "wof:placetype":"venue"
},
  "geometry": {"coordinates":[-90.064902,35.101859],"type":"Point"}
}