{
  "type": "Feature",
  "properties": {
    "iso:country":"US",
    "sg:address":"7024 Church St E",
    "sg:city":"Brentwood",
    "sg:classifiers":[
        {
            "category":"Personal",
            "subcategory":"Beauty Salon",
            "type":"Services"
        }
    ],
    "sg:phone":"+1 615 376 2177",
    "sg:postcode":"37027",
    "sg:province":"TN",
    "wof:name":"Eclipse Hair Salon",
    "wof:placetype":"venue"
},
  "geometry": {"coordinates":[-86.786644,36.033182],"type":"Point"}
}