{
  "type": "Feature",
  "properties": {
    "addr:full":"367 Harding Pl Nashville TN 37211",
    "addr:housenumber":"367",
    "addr:postcode":"37211",
    "addr:street":"Harding Pl",
    "iso:country":"US",
    "sg:address":"367 Harding Pl",
    "sg:city":"Nashville",
    "sg:classifiers":[
        {
            "category":"Insurance",
            "subcategory":"Insurance Agent",
            "type":"Services"
        }
    ],
    "sg:phone":"+1 615 834 0021",
    "sg:postcode":"37211",
    "sg:province":"TN",
    "wof:name":"State Farm Insurance",
    "wof:placetype":"venue"
},
  "geometry": {"coordinates":[-86.704919,36.084314],"type":"Point"}
}