{
  "type": "Feature",
  "properties": {
    "iso:country":"US",
    "sg:address":"3401 W End Ave",
    "sg:city":"Nashville",
    "sg:classifiers":[
        {
            "category":"Health Services",
            "subcategory":"Clinic",
            "type":"Services"
        }
    ],
    "sg:phone":"+1 615 298 3666",
    "sg:postcode":"37203",
    "sg:province":"TN",
    "sg:tags":[
        "home",
        "care"
    ],
    "wof:name":"Xantus Health Plan of Tenn",
    "wof:placetype":"venue"
},
  "geometry": {"coordinates":[-86.820881,36.137624],"type":"Point"}
}