{
  "type": "Feature",
  "properties": {
    "addr:full":"9416 Apison Pike Ooltewah TN 37315",
    "addr:housenumber":"9416",
    "addr:postcode":"37315",
    "addr:street":"Apison Pike",
    "iso:country":"US",
    "sg:address":"9416 Apison Pike",
    "sg:city":"Ooltewah",
    "sg:classifiers":[
        {
            "category":"Autos & Motor Vehicles",
            "subcategory":"Fuel & Gas Station",
            "type":"Retail Goods"
        }
    ],
    "sg:phone":"+1 423 396 3863",
    "sg:postcode":"37315",
    "sg:province":"TN",
    "sg:tags":[
        "oil"
    ],
    "wof:name":"Collegedale Central Exxon",
    "wof:placetype":"venue"
},
  "geometry": {"coordinates":[-85.06969700000001,35.060651],"type":"Point"}
}