{
  "type": "Feature",
  "properties": {
    "addr:full":"5313 Lazard St Chattanooga TN 37412",
    "addr:housenumber":"5313",
    "addr:postcode":"37412",
    "addr:street":"Lazard St",
    "iso:country":"US",
    "sg:address":"5313 Lazard St",
    "sg:city":"Chattanooga",
    "sg:classifiers":[
        {
            "category":"Building & Trades",
            "subcategory":"Electrical",
            "type":"Services"
        }
    ],
    "sg:phone":"+1 423 867 2610",
    "sg:postcode":"37412",
    "sg:province":"TN",
    "sg:tags":[
        "electrical",
        "contractor"
    ],
    "wof:name":"Baxter Electric Co",
    "wof:placetype":"venue"
},
  "geometry": {"coordinates":[-85.23464300000001,34.988586],"type":"Point"}
}