{
  "type": "Feature",
  "properties": {
    "addr:full":"3655 Trousdale Dr Nashville TN 37220",
    "addr:housenumber":"3655",
    "addr:postcode":"37220",
    "addr:street":"Trousdale Dr",
    "iso:country":"US",
    "sg:address":"3655 Trousdale Dr",
    "sg:city":"Nashville",
    "sg:classifiers":[
        {
            "category":"Freight",
            "type":"Transportation"
        }
    ],
    "sg:phone":"+1 615 834 0574",
    "sg:postcode":"37220",
    "sg:province":"TN",
    "sg:tags":[
        "storage"
    ],
    "wof:name":"Car Storage",
    "wof:placetype":"venue"
},
  "geometry": {"coordinates":[-86.749835,36.093795],"type":"Point"}
}