{
  "type": "Feature",
  "properties": {
    "addr:full":"214 Cedar St Sevierville TN 37862",
    "addr:housenumber":"214",
    "addr:postcode":"37862",
    "addr:street":"Cedar St",
    "iso:country":"US",
    "sg:address":"214 Cedar St",
    "sg:city":"Sevierville",
    "sg:classifiers":[
        {
            "category":"Social Services",
            "subcategory":"Child Care",
            "type":"Services"
        }
    ],
    "sg:phone":"+1 865 453 5708",
    "sg:postcode":"37862",
    "sg:province":"TN",
    "sg:tags":[
        "day"
    ],
    "wof:name":"First United Methodist Church",
    "wof:placetype":"venue"
},
  "geometry": {"coordinates":[-83.56297000000001,35.865615],"type":"Point"}
}