{
  "type": "Feature",
  "properties": {
    "iso:country":"US",
    "sg:address":"500 S Anderson St",
    "sg:city":"Tullahoma",
    "sg:classifiers":[
        {
            "category":"Freight",
            "type":"Transportation"
        }
    ],
    "sg:phone":"+1 931 461 5101",
    "sg:postcode":"37388",
    "sg:province":"TN",
    "sg:tags":[
        "storage",
        "commercial",
        "special"
    ],
    "wof:name":"Anderson Street Climate Contro",
    "wof:placetype":"venue"
},
  "geometry": {"coordinates":[-86.200908,35.360766],"type":"Point"}
}