{
  "type": "Feature",
  "properties": {
    "addr:full":"4027 University St Memphis TN 38127",
    "addr:housenumber":"4027",
    "addr:postcode":"38127",
    "addr:street":"University St",
    "iso:country":"US",
    "sg:address":"4027 University St",
    "sg:city":"Memphis",
    "sg:classifiers":[
        {
            "category":"Farming",
            "subcategory":"Fish & Marine Products",
            "type":"Manufacturing & Wholesale Goods"
        },
        {
            "category":"Retail",
            "subcategory":"Repair Shop",
            "type":"Services"
        },
        {
            "category":"Professional",
            "subcategory":"Art Services",
            "type":"Services"
        }
    ],
    "sg:phone":"+1 901 354 6619",
    "sg:postcode":"38127",
    "sg:province":"TN",
    "sg:tags":[
        "picture",
        "frame",
        "restoration",
        "framing"
    ],
    "wof:name":"Glamour Picture Frames",
    "wof:placetype":"venue"
},
  "geometry": {"coordinates":[-89.98875099999999,35.235457],"type":"Point"}
}