{
  "type": "Feature",
  "properties": {
    "iso:country":"US",
    "sg:address":"1740 September Ave",
    "sg:city":"Memphis",
    "sg:classifiers":[
        {
            "category":"Home & Garden",
            "subcategory":"Building Materials",
            "type":"Retail Goods"
        }
    ],
    "sg:phone":"+1 901 345 9114",
    "sg:postcode":"38116",
    "sg:province":"TN",
    "sg:tags":[
        "sand",
        "gravel"
    ],
    "wof:name":"B N B Sand & Gravel Transport",
    "wof:placetype":"venue"
},
  "geometry": {"coordinates":[-90.00616100000001,35.054744],"type":"Point"}
}