{
  "type": "Feature",
  "properties": {
    "addr:full":"15660 Highland Dr Mc Kenzie TN 38201",
    "addr:housenumber":"15660",
    "addr:postcode":"38201",
    "addr:street":"Highland Dr",
    "iso:country":"US",
    "sg:address":"15660 Highland Dr",
    "sg:city":"Mc Kenzie",
    "sg:classifiers":[
        {
            "category":"Restaurant",
            "type":"Food & Drink"
        }
    ],
    "sg:phone":"+1 731 352 3000",
    "sg:postcode":"38201",
    "sg:province":"TN",
    "sg:tags":[
        "eating",
        "pizza"
    ],
    "sg:website":"www.dominos.com",
    "wof:name":"Domino's Pizza",
    "wof:placetype":"venue"
},
  "geometry": {"coordinates":[-88.51149100000001,36.127619],"type":"Point"}
}