{
  "type": "Feature",
  "properties": {
    "iso:country":"US",
    "sg:address":"88 Weblon Ln",
    "sg:city":"Sewanee",
    "sg:classifiers":[
        {
            "category":"Shopping",
            "subcategory":"Jewelry",
            "type":"Retail Goods"
        }
    ],
    "sg:phone":"+1 931 598 0400",
    "sg:postcode":"37375",
    "sg:province":"TN",
    "wof:name":"Judith/Shipp Jewelry",
    "wof:placetype":"venue"
},
  "geometry": {"coordinates":[-85.92013,35.166703],"type":"Point"}
}