{
  "type": "Feature",
  "properties": {
    "addr:full":"911 Mineral Wells Ave Paris TN 38242",
    "addr:housenumber":"911",
    "addr:postcode":"38242",
    "addr:street":"Mineral Wells Ave",
    "iso:country":"US",
    "sg:address":"911 Mineral Wells Ave",
    "sg:city":"Paris",
    "sg:classifiers":[
        {
            "category":"Restaurant",
            "type":"Food & Drink"
        }
    ],
    "sg:menulink":"http://www.allmenus.com/tn/paris/176902-kfc---kentucky-fried-chicken/menu/",
    "sg:phone":"+1 901 642 4075",
    "sg:postcode":"38242",
    "sg:province":"TN",
    "sg:tags":[
        "american",
        "chicken"
    ],
    "wof:name":"KFC - Kentucky Fried Chicken",
    "wof:placetype":"venue"
},
  "geometry": {"coordinates":[-88.315945,36.291591],"type":"Point"}
}