{
  "type": "Feature",
  "properties": {
    "iso:country":"US",
    "sg:address":"1078 Baugh Springs Rd",
    "sg:city":"Mc Donald",
    "sg:classifiers":[
        {
            "category":"Building & Trades",
            "subcategory":"Plumbing",
            "type":"Services"
        }
    ],
    "sg:phone":"+1 423 479 7978",
    "sg:postcode":"37353",
    "sg:province":"TN",
    "sg:tags":[
        "contractor"
    ],
    "wof:name":"H&M Enterprises of Tennes",
    "wof:placetype":"venue"
},
  "geometry": {"coordinates":[-84.98791300000001,35.123544],"type":"Point"}
}