{
  "type": "Feature",
  "properties": {
    "iso:country":"US",
    "sg:address":"503 N Main St",
    "sg:city":"Ashland City",
    "sg:classifiers":[
        {
            "category":"Shopping",
            "subcategory":"Tobacco",
            "type":"Retail Goods"
        }
    ],
    "sg:phone":"+1 615 792 3960",
    "sg:postcode":"37015",
    "sg:province":"TN",
    "sg:tags":[
        "product"
    ],
    "wof:name":"Tobacco Patch",
    "wof:placetype":"venue"
},
  "geometry": {"coordinates":[-87.066397,36.277625],"type":"Point"}
}