{
  "type": "Feature",
  "properties": {
    "iso:country":"US",
    "sg:address":"1191 Winfield Rd",
    "sg:city":"Memphis",
    "sg:classifiers":[
        {
            "category":"Personal",
            "subcategory":"Beauty Salon",
            "type":"Services"
        }
    ],
    "sg:phone":"+1 901 396 1042",
    "sg:postcode":"38116",
    "sg:province":"TN",
    "sg:tags":[
        "shop"
    ],
    "wof:name":"Shirleys Hair Fixx",
    "wof:placetype":"venue"
},
  "geometry": {"coordinates":[-90.024185,35.000459],"type":"Point"}
}