{
  "type": "Feature",
  "properties": {
    "iso:country":"US",
    "sg:address":"1474 Murfreesboro Hwy",
    "sg:city":"Manchester",
    "sg:classifiers":[
        {
            "category":"Autos & Motor Vehicles",
            "subcategory":"Fuel & Gas Station",
            "type":"Retail Goods"
        }
    ],
    "sg:phone":"+1 931 728 8098",
    "sg:postcode":"37355",
    "sg:province":"TN",
    "sg:tags":[
        "oil"
    ],
    "wof:name":"Crown 1 Rigney Spur",
    "wof:placetype":"venue"
},
  "geometry": {"coordinates":[-86.098878,35.49215],"type":"Point"}
}