{
  "type": "Feature",
  "properties": {
    "addr:full":"2833 John Deere Dr Knoxville TN 37917",
    "addr:housenumber":"2833",
    "addr:postcode":"37917",
    "addr:street":"John Deere Dr",
    "iso:country":"US",
    "sg:address":"2833 John Deere Dr",
    "sg:city":"Knoxville",
    "sg:classifiers":[
        {
            "category":"Autos & Motor Vehicles",
            "subcategory":"Auto Supplies",
            "type":"Retail Goods"
        }
    ],
    "sg:phone":"+1 865 546 7751",
    "sg:postcode":"37917",
    "sg:province":"TN",
    "sg:tags":[
        "repair",
        "general"
    ],
    "wof:name":"Diesel Sales & Service",
    "wof:placetype":"venue"
},
  "geometry": {"coordinates":[-83.900063,35.995072],"type":"Point"}
}