{
  "type": "Feature",
  "properties": {
    "iso:country":"US",
    "sg:address":"58 College St N",
    "sg:city":"Mc Ewen",
    "sg:classifiers":[
        {
            "category":"Manufacturing",
            "subcategory":"Metals",
            "type":"Manufacturing & Wholesale Goods"
        }
    ],
    "sg:phone":"+1 931 582 3500",
    "sg:postcode":"37101",
    "sg:province":"TN",
    "sg:tags":[
        "product",
        "wire"
    ],
    "wof:name":"Nashville Wire-Mc Ewen",
    "wof:placetype":"venue"
},
  "geometry": {"coordinates":[-87.636169,36.115031],"type":"Point"}
}