{
  "type": "Feature",
  "properties": {
    "iso:country":"US",
    "sg:address":"6090 Anthony Rd",
    "sg:city":"Adams",
    "sg:classifiers":[
        {
            "category":"Professional",
            "type":"Services"
        }
    ],
    "sg:phone":"+1 615 696 0004",
    "sg:postcode":"37010",
    "sg:province":"TN",
    "wof:name":"Farrell Jeffrey",
    "wof:placetype":"venue"
},
  "geometry": {"coordinates":[-87.06844,36.630142],"type":"Point"}
}