{
  "type": "Feature",
  "properties": {
    "iso:country":"US",
    "sg:address":"210 S Aztec Dr",
    "sg:city":"White House",
    "sg:classifiers":[
        {
            "category":"Professional",
            "type":"Services"
        }
    ],
    "sg:phone":"+1 615 672 1342",
    "sg:postcode":"37188",
    "sg:province":"TN",
    "wof:name":"Theresa M Bond",
    "wof:placetype":"venue"
},
  "geometry": {"coordinates":[-86.65898799999999,36.4777],"type":"Point"}
}