{
  "type": "Feature",
  "properties": {
    "iso:country":"US",
    "sg:address":"3648 Millbranch Rd",
    "sg:city":"Memphis",
    "sg:classifiers":[
        {
            "category":"Personal",
            "subcategory":"Beauty Salon",
            "type":"Services"
        }
    ],
    "sg:phone":"+1 901 346 5550",
    "sg:postcode":"38116",
    "sg:province":"TN",
    "wof:name":"Hymon Perfect Touch",
    "wof:placetype":"venue"
},
  "geometry": {"coordinates":[-90.00740399999999,35.048906],"type":"Point"}
}