{
  "type": "Feature",
  "properties": {
    "addr:full":"7045 Nolensville Rd Brentwood TN 37027",
    "addr:housenumber":"7045",
    "addr:postcode":"37027",
    "addr:street":"Nolensville Rd",
    "iso:country":"US",
    "sg:address":"7045 Nolensville Rd",
    "sg:city":"Brentwood",
    "sg:classifiers":[
        {
            "category":"Food & Beverages",
            "subcategory":"Groceries & Convenience Stores",
            "type":"Retail Goods"
        }
    ],
    "sg:phone":"+1 615 776 2941",
    "sg:postcode":"37027",
    "sg:province":"TN",
    "wof:name":"Coast In Market",
    "wof:placetype":"venue"
},
  "geometry": {"coordinates":[-86.678798,35.983419],"type":"Point"}
}