{
  "type": "Feature",
  "properties": {
    "iso:country":"US",
    "sg:address":"107 Brookfield Ave",
    "sg:city":"Chattanooga",
    "sg:classifiers":[
        {
            "category":"Professional",
            "type":"Services"
        }
    ],
    "sg:phone":"+1 423 624 8074",
    "sg:postcode":"37411",
    "sg:province":"TN",
    "wof:name":"Netgazer Networks LLC",
    "wof:placetype":"venue"
},
  "geometry": {"coordinates":[-85.239057,35.014984],"type":"Point"}
}