{
  "type": "Feature",
  "properties": {
    "addr:full":"1321 S Locust Ave Lawrenceburg TN 38464",
    "addr:housenumber":"1321",
    "addr:postcode":"38464",
    "addr:street":"S Locust Ave",
    "iso:country":"US",
    "sg:address":"1321 S Locust Ave",
    "sg:city":"Lawrenceburg",
    "sg:classifiers":[
        {
            "category":"Health Services",
            "subcategory":"Doctor",
            "type":"Services"
        }
    ],
    "sg:phone":"+1 931 766 7775",
    "sg:postcode":"38464",
    "sg:province":"TN",
    "sg:tags":[
        "physician",
        "surgeon"
    ],
    "wof:name":"Atiyah Raja MD PC",
    "wof:placetype":"venue"
},
  "geometry": {"coordinates":[-87.336308,35.223496],"type":"Point"}
}