{
  "type": "Feature",
  "properties": {
    "iso:country":"US",
    "sg:address":"1022 W Main St",
    "sg:city":"Greeneville",
    "sg:classifiers":[
        {
            "category":"Utilities",
            "subcategory":"Refuse",
            "type":"Services"
        }
    ],
    "sg:phone":"+1 423 639 2018",
    "sg:postcode":"37743",
    "sg:province":"TN",
    "sg:tags":[
        "garbage",
        "collection"
    ],
    "wof:name":"Countryside Garbage Svc",
    "wof:placetype":"venue"
},
  "geometry": {"coordinates":[-82.846839,36.155435],"type":"Point"}
}