{
  "type": "Feature",
  "properties": {
    "addr:full":"6465 Mullins Station Rd Bartlett TN 38134",
    "addr:housenumber":"6465",
    "addr:postcode":"38134",
    "addr:street":"Mullins Station Rd",
    "iso:country":"US",
    "sg:address":"6465 Mullins Station Rd",
    "sg:city":"Bartlett",
    "sg:classifiers":[
        {
            "category":"Government",
            "subcategory":"Office",
            "type":"Public Place"
        }
    ],
    "sg:phone":"+1 901 379 4201",
    "sg:postcode":"38134",
    "sg:province":"TN",
    "sg:tags":[
        "village"
    ],
    "wof:name":"Memphis City Government",
    "wof:placetype":"venue"
},
  "geometry": {"coordinates":[-89.84727700000001,35.153223],"type":"Point"}
}