{
  "type": "Feature",
  "properties": {
    "iso:country":"US",
    "sg:address":"821 E 10th St",
    "sg:city":"Cookeville",
    "sg:classifiers":[
        {
            "category":"Retail",
            "subcategory":"Veterinary Services",
            "type":"Services"
        }
    ],
    "sg:phone":"+1 931 528 1111",
    "sg:postcode":"38501",
    "sg:province":"TN",
    "sg:tags":[
        "veterinarian"
    ],
    "wof:name":"Copeland Veterinary Hospital",
    "wof:placetype":"venue"
},
  "geometry": {"coordinates":[-85.486789,36.175559],"type":"Point"}
}