{
  "type": "Feature",
  "properties": {
    "iso:country":"US",
    "sg:address":"434 W 1st North St",
    "sg:city":"Morristown",
    "sg:classifiers":[
        {
            "category":"Professional",
            "subcategory":"Business Services",
            "type":"Services"
        }
    ],
    "sg:phone":"+1 423 587 3085",
    "sg:postcode":"37814",
    "sg:province":"TN",
    "sg:tags":[
        "appraiser"
    ],
    "wof:name":"Blackburn Appraisals",
    "wof:placetype":"venue"
},
  "geometry": {"coordinates":[-83.296803,36.212692],"type":"Point"}
}