{
  "type": "Feature",
  "properties": {
    "addr:full":"7111 Lakeview Dr Fairview TN 37062",
    "addr:housenumber":"7111",
    "addr:postcode":"37062",
    "addr:street":"Lakeview Dr",
    "iso:country":"US",
    "sg:address":"7111 Lakeview Dr",
    "sg:city":"Fairview",
    "sg:classifiers":[
        {
            "category":"Organizations",
            "subcategory":"Religious Organization",
            "type":"Services"
        }
    ],
    "sg:phone":"+1 615 799 9970",
    "sg:postcode":"37062",
    "sg:province":"TN",
    "sg:tags":[
        "church"
    ],
    "wof:name":"Emmanuel Prince Of Peace",
    "wof:placetype":"venue"
},
  "geometry": {"coordinates":[-87.07129,35.998845],"type":"Point"}
}