{
  "type": "Feature",
  "properties": {
    "addr:full":"7129 Bakers Bridge Ave Brentwood TN 37027",
    "addr:housenumber":"7129",
    "addr:postcode":"37027",
    "addr:street":"Bakers Bridge Ave",
    "iso:country":"US",
    "sg:address":"7129 Bakers Bridge Ave",
    "sg:city":"Brentwood",
    "sg:classifiers":[
        {
            "category":"Autos & Motor Vehicles",
            "subcategory":"Auto Supplies",
            "type":"Retail Goods"
        }
    ],
    "sg:phone":"+1 615 377 9060",
    "sg:postcode":"37027",
    "sg:province":"TN",
    "sg:tags":[
        "tire"
    ],
    "wof:name":"Team Tires Plus",
    "wof:placetype":"venue"
},
  "geometry": {"coordinates":[-86.818376,35.962764],"type":"Point"}
}