{
  "type": "Feature",
  "properties": {
    "addr:full":"212 S Jefferson Ave Cookeville TN 38501",
    "addr:housenumber":"212",
    "addr:postcode":"38501",
    "addr:street":"S Jefferson Ave",
    "iso:country":"US",
    "sg:address":"212 S Jefferson Ave",
    "sg:city":"Cookeville",
    "sg:classifiers":[
        {
            "category":"Professional",
            "subcategory":"Lawyer & Legal Services",
            "type":"Services"
        }
    ],
    "sg:phone":"+1 931 372 7224",
    "sg:postcode":"38501",
    "sg:province":"TN",
    "sg:tags":[
        "attorney"
    ],
    "wof:name":"Steven R Randolph",
    "wof:placetype":"venue"
},
  "geometry": {"coordinates":[-85.500293,36.158981],"type":"Point"}
}