{
  "type": "Feature",
  "properties": {
    "iso:country":"US",
    "sg:address":"3300 Mccorkle Rd",
    "sg:city":"Memphis",
    "sg:classifiers":[
        {
            "category":"Personal",
            "type":"Services"
        },
        {
            "category":"Retail",
            "subcategory":"Laundry & Dry Cleaning",
            "type":"Services"
        },
        {
            "category":"Building & Trades",
            "subcategory":"Cleaning & Sanitation",
            "type":"Services"
        }
    ],
    "sg:phone":"+1 615 431 3091",
    "sg:postcode":"38116",
    "sg:province":"TN",
    "sg:tags":[
        "cleaner",
        "site-clean-up",
        "maids'",
        "house",
        "rug",
        "construction",
        "butlers'",
        "janitorial",
        "carpet"
    ],
    "wof:name":"Commercial Janitoral Service of Memphis",
    "wof:placetype":"venue"
},
  "geometry": {"coordinates":[-90.038546,35.058823],"type":"Point"}
}