{
  "type": "Feature",
  "properties": {
    "addr:full":"1830 Safari Camp Rd Lebanon TN 37090",
    "addr:housenumber":"1830",
    "addr:postcode":"37090",
    "addr:street":"Safari Camp Rd",
    "iso:country":"US",
    "sg:address":"1830 Safari Camp Rd",
    "sg:city":"Lebanon",
    "sg:classifiers":[
        {
            "category":"Freight",
            "type":"Transportation"
        }
    ],
    "sg:phone":"+1 615 547 0650",
    "sg:postcode":"37090",
    "sg:province":"TN",
    "sg:tags":[
        "operator",
        "trucking"
    ],
    "wof:name":"Royal Freight LP",
    "wof:placetype":"venue"
},
  "geometry": {"coordinates":[-86.374492,36.183792],"type":"Point"}
}