{
  "type": "Feature",
  "properties": {
    "iso:country":"US",
    "sg:address":"10 7th St",
    "sg:city":"Bristol",
    "sg:classifiers":[
        {
            "category":"Shopping",
            "subcategory":"Bicycles & Sporting Goods",
            "type":"Retail Goods"
        }
    ],
    "sg:phone":"+1 423 764 4932",
    "sg:postcode":"37620",
    "sg:province":"TN",
    "sg:tags":[
        "repair"
    ],
    "wof:name":"Boyd's Bicycle Shop",
    "wof:placetype":"venue"
},
  "geometry": {"coordinates":[-82.18523999999999,36.594967],"type":"Point"}
}