{
  "type": "Feature",
  "properties": {
    "iso:country":"US",
    "sg:address":"129 Bruce St",
    "sg:city":"Sevierville",
    "sg:classifiers":[
        {
            "category":"Shopping",
            "type":"Retail Goods"
        }
    ],
    "sg:phone":"+1 865 429 0064",
    "sg:postcode":"37862",
    "sg:province":"TN",
    "sg:tags":[
        "equipment",
        "care",
        "health",
        "home"
    ],
    "wof:name":"Bess & Co",
    "wof:placetype":"venue"
},
  "geometry": {"coordinates":[-83.562877,35.866586],"type":"Point"}
}