{
  "type": "Feature",
  "properties": {
    "addr:full":"213 Upwind Ct Nashville TN 37217",
    "addr:housenumber":"213",
    "addr:postcode":"37217",
    "addr:street":"Upwind Ct",
    "iso:country":"US",
    "sg:address":"213 Upwind Ct",
    "sg:city":"Nashville",
    "sg:classifiers":[
        {
            "category":"Manufacturing",
            "subcategory":"Printing",
            "type":"Manufacturing & Wholesale Goods"
        }
    ],
    "sg:phone":"+1 615 255 7642",
    "sg:postcode":"37217",
    "sg:province":"TN",
    "sg:tags":[
        "screen"
    ],
    "sg:website":"www.customletter.com",
    "wof:name":"Custom Lettering Inc",
    "wof:placetype":"venue"
},
  "geometry": {"coordinates":[-86.610212,36.083941],"type":"Point"}
}