{
  "type": "Feature",
  "properties": {
    "addr:full":"292 Walker Rd Jackson TN 38305",
    "addr:housenumber":"292",
    "addr:postcode":"38305",
    "addr:street":"Walker Rd",
    "iso:country":"US",
    "sg:address":"292 Walker Rd",
    "sg:city":"Jackson",
    "sg:classifiers":[
        {
            "category":"Organizations",
            "subcategory":"Community Association",
            "type":"Services"
        }
    ],
    "sg:phone":"+1 731 660 2812",
    "sg:postcode":"38305",
    "sg:province":"TN",
    "sg:tags":[
        "sorority",
        "fraternity"
    ],
    "wof:name":"Lambda Chi Alpha Fraternity",
    "wof:placetype":"venue"
},
  "geometry": {"coordinates":[-88.859561,35.682377],"type":"Point"}
}