{
  "type": "Feature",
  "properties": {
    "iso:country":"US",
    "sg:address":"3327 Old Mill St",
    "sg:city":"Pigeon Forge",
    "sg:classifiers":[
        {
            "category":"Shopping",
            "type":"Retail Goods"
        }
    ],
    "sg:phone":"+1 865 428 6133",
    "sg:postcode":"37863",
    "sg:province":"TN",
    "sg:tags":[
        "pet",
        "food",
        "supply"
    ],
    "sg:website":"www.smokymountaincathouse.com",
    "wof:name":"Smoky Mountain Cat House",
    "wof:placetype":"venue"
},
  "geometry": {"coordinates":[-83.554755,35.790115],"type":"Point"}
}