{
  "type": "Feature",
  "properties": {
    "iso:country":"US",
    "sg:address":"6787 Lee Hwy",
    "sg:city":"Chattanooga",
    "sg:classifiers":[
        {
            "category":"Real Estate",
            "subcategory":"Real Estate Agent",
            "type":"Services"
        }
    ],
    "sg:phone":"+1 423 899 4737",
    "sg:postcode":"37421",
    "sg:province":"TN",
    "sg:tags":[
        "commercial",
        "investment"
    ],
    "wof:name":"Anchor Trust Inc",
    "wof:placetype":"venue"
},
  "geometry": {"coordinates":[-85.16976,35.040385],"type":"Point"}
}