{
  "type": "Feature",
  "properties": {
    "iso:country":"US",
    "sg:address":"1424 Dickerson Bay Dr",
    "sg:city":"Gallatin",
    "sg:classifiers":[
        {
            "category":"Shopping",
            "type":"Retail Goods"
        }
    ],
    "sg:phone":"+1 615 451 4080",
    "sg:postcode":"37066",
    "sg:province":"TN",
    "sg:tags":[
        "merchandise"
    ],
    "wof:name":"Southern Awning & Sign Co",
    "wof:placetype":"venue"
},
  "geometry": {"coordinates":[-86.498446,36.332848],"type":"Point"}
}