{
  "type": "Feature",
  "properties": {
    "addr:full":"836 Walker Rd Oneida TN 37841",
    "addr:housenumber":"836",
    "addr:postcode":"37841",
    "addr:street":"Walker Rd",
    "iso:country":"US",
    "sg:address":"836 Walker Rd",
    "sg:city":"Oneida",
    "sg:classifiers":[
        {
            "category":"Farming",
            "subcategory":"Farm",
            "type":"Manufacturing & Wholesale Goods"
        }
    ],
    "sg:phone":"+1 423 663 3633",
    "sg:postcode":"37841",
    "sg:province":"TN",
    "sg:tags":[
        "crop",
        "general"
    ],
    "wof:name":"Walker Farms",
    "wof:placetype":"venue"
},
  "geometry": {"coordinates":[-84.423688,36.432071],"type":"Point"}
}