{
  "type": "Feature",
  "properties": {
    "addr:full":"1761 Powder Branch Rd Johnson City TN 37601",
    "addr:housenumber":"1761",
    "addr:postcode":"37601",
    "addr:street":"Powder Branch Rd",
    "iso:country":"US",
    "sg:address":"1761 Powder Branch Rd",
    "sg:city":"Johnson City",
    "sg:classifiers":[
        {
            "category":"Education",
            "subcategory":"Special Training",
            "type":"Public Place"
        }
    ],
    "sg:phone":"+1 423 547 9677",
    "sg:postcode":"37601",
    "sg:province":"TN",
    "wof:name":"Language Connection Inc",
    "wof:placetype":"venue"
},
  "geometry": {"coordinates":[-82.274072,36.269644],"type":"Point"}
}