{
  "type": "Feature",
  "properties": {
    "iso:country":"US",
    "sg:address":"17 S Seminole Dr",
    "sg:city":"Chattanooga",
    "sg:classifiers":[
        {
            "category":"Restaurant",
            "type":"Food & Drink"
        }
    ],
    "sg:phone":"+1 423 622 5362",
    "sg:postcode":"37411",
    "sg:province":"TN",
    "wof:name":"Ra Jae's",
    "wof:placetype":"venue"
},
  "geometry": {"coordinates":[-85.25518599999999,35.026955],"type":"Point"}
}