{
  "type": "Feature",
  "properties": {
    "addr:full":"3072 Chateau Valley Dr Nashville TN 37207",
    "addr:housenumber":"3072",
    "addr:postcode":"37207",
    "addr:street":"Chateau Valley Dr",
    "iso:country":"US",
    "sg:address":"3072 Chateau Valley Dr",
    "sg:city":"Nashville",
    "sg:classifiers":[
        {
            "category":"Retail",
            "subcategory":"Laundry & Dry Cleaning",
            "type":"Services"
        }
    ],
    "sg:phone":"+1 615 226 4904",
    "sg:postcode":"37207",
    "sg:province":"TN",
    "wof:name":"Peterkin & Sons",
    "wof:placetype":"venue"
},
  "geometry": {"coordinates":[-86.81154600000001,36.214247],"type":"Point"}
}