{
  "type": "Feature",
  "properties": {
    "iso:country":"US",
    "sg:address":"3170 State Hwy 25",
    "sg:city":"Cottontown",
    "sg:classifiers":[
        {
            "category":"Organizations",
            "subcategory":"Religious Organization",
            "type":"Services"
        }
    ],
    "sg:phone":"+1 615 325 4640",
    "sg:postcode":"37048",
    "sg:province":"TN",
    "sg:tags":[
        "church"
    ],
    "wof:name":"Birdwell's Chapel Church",
    "wof:placetype":"venue"
},
  "geometry": {"coordinates":[-86.59156400000001,36.493416],"type":"Point"}
}