{
  "type": "Feature",
  "properties": {
    "iso:country":"US",
    "sg:address":"214 Brisbane Rd",
    "sg:city":"Oak Ridge",
    "sg:classifiers":[
        {
            "category":"Professional",
            "subcategory":"Business Services",
            "type":"Services"
        }
    ],
    "sg:phone":"+1 865 481 8004",
    "sg:postcode":"37830",
    "sg:province":"TN",
    "wof:name":"Signs By Design",
    "wof:placetype":"venue"
},
  "geometry": {"coordinates":[-84.213807,36.041829],"type":"Point"}
}