{
  "type": "Feature",
  "properties": {
    "iso:country":"US",
    "sg:address":"320 Nancy Lynn Ln",
    "sg:city":"Knoxville",
    "sg:classifiers":[
        {
            "category":"Health Services",
            "subcategory":"Clinic",
            "type":"Services"
        }
    ],
    "sg:phone":"+1 865 588 2928",
    "sg:postcode":"37919",
    "sg:province":"TN",
    "wof:name":"Medical Mgt Professionals",
    "wof:placetype":"venue"
},
  "geometry": {"coordinates":[-84.00945900000001,35.926385],"type":"Point"}
}