{
  "type": "Feature",
  "properties": {
    "addr:full":"679 Cedar Brake Dr Cordova TN 38018",
    "addr:housenumber":"679",
    "addr:postcode":"38018",
    "addr:street":"Cedar Brake Dr",
    "iso:country":"US",
    "sg:address":"679 Cedar Brake Dr",
    "sg:city":"Cordova",
    "sg:classifiers":[
        {
            "category":"Professional",
            "subcategory":"Management & Consulting",
            "type":"Services"
        }
    ],
    "sg:phone":"+1 901 624 3355",
    "sg:postcode":"38018",
    "sg:province":"TN",
    "wof:name":"Benefits Company RR LLC",
    "wof:placetype":"venue"
},
  "geometry": {"coordinates":[-89.786928,35.143371],"type":"Point"}
}