{
  "type": "Feature",
  "properties": {
    "addr:full":"555 E Main St Hendersonville TN 37075",
    "addr:housenumber":"555",
    "addr:postcode":"37075",
    "addr:street":"E Main St",
    "iso:country":"US",
    "sg:address":"555 E Main St",
    "sg:city":"Hendersonville",
    "sg:classifiers":[
        {
            "category":"Insurance",
            "subcategory":"Insurance Agent",
            "type":"Services"
        }
    ],
    "sg:phone":"+1 615 824 9200",
    "sg:postcode":"37075",
    "sg:province":"TN",
    "wof:name":"Jantz Insurance & Financial",
    "wof:placetype":"venue"
},
  "geometry": {"coordinates":[-86.57799900000001,36.319888],"type":"Point"}
}