{
  "type": "Feature",
  "properties": {
    "iso:country":"US",
    "sg:address":"255 Co Rd 422",
    "sg:city":"Athens",
    "sg:classifiers":[
        {
            "category":"Banks & Credit Unions",
            "subcategory":"Investment Brokerage",
            "type":"Services"
        }
    ],
    "sg:phone":"+1 423 746 5000",
    "sg:postcode":"37303",
    "sg:province":"TN",
    "sg:tags":[
        "advisory"
    ],
    "wof:name":"Beneficial Financial Services",
    "wof:placetype":"venue"
},
  "geometry": {"coordinates":[-84.515888,35.472501],"type":"Point"}
}