{
  "type": "Feature",
  "properties": {
    "iso:country":"US",
    "sg:address":"4075 Middle Rd",
    "sg:city":"Milan",
    "sg:classifiers":[
        {
            "category":"Personal",
            "subcategory":"Barber",
            "type":"Services"
        }
    ],
    "sg:phone":"+1 731 686 7614",
    "sg:postcode":"38358",
    "sg:province":"TN",
    "sg:tags":[
        "shop"
    ],
    "wof:name":"Tripod Enterprise",
    "wof:placetype":"venue"
},
  "geometry": {"coordinates":[-88.760133,35.940327],"type":"Point"}
}