{
  "type": "Feature",
  "properties": {
    "iso:country":"US",
    "sg:address":"3900 Dortch Rd",
    "sg:city":"Adams",
    "sg:classifiers":[
        {
            "category":"Manufacturing",
            "subcategory":"Toys & Sporting Goods",
            "type":"Manufacturing & Wholesale Goods"
        }
    ],
    "sg:phone":"+1 615 696 2169",
    "sg:postcode":"37032",
    "sg:province":"TN",
    "sg:tags":[
        "mfg",
        "craft",
        "hand"
    ],
    "wof:name":"Windy Hill",
    "wof:placetype":"venue"
},
  "geometry": {"coordinates":[-87.06509200000001,36.519141],"type":"Point"}
}