{
  "type": "Feature",
  "properties": {
    "addr:full":"122 Charter Pl La Vergne TN 37086",
    "addr:housenumber":"122",
    "addr:postcode":"37086",
    "addr:street":"Charter Pl",
    "iso:country":"US",
    "sg:address":"122 Charter Pl",
    "sg:city":"La Vergne",
    "sg:classifiers":[
        {
            "category":"Building & Trades",
            "subcategory":"Construction",
            "type":"Services"
        }
    ],
    "sg:phone":"+1 615 793 2220",
    "sg:postcode":"37086",
    "sg:province":"TN",
    "sg:tags":[
        "contractor"
    ],
    "wof:name":"Factory Outlet",
    "wof:placetype":"venue"
},
  "geometry": {"coordinates":[-86.59162499999999,35.989952],"type":"Point"}
}