{
  "type": "Feature",
  "properties": {
    "addr:full":"494 Lakeview Trl Decherd TN 37324",
    "addr:housenumber":"494",
    "addr:postcode":"37324",
    "addr:street":"Lakeview Trl",
    "iso:country":"US",
    "sg:address":"494 Lakeview Trl",
    "sg:city":"Decherd",
    "sg:classifiers":[
        {
            "category":"Retail",
            "subcategory":"Repair Shop",
            "type":"Services"
        }
    ],
    "sg:phone":"+1 931 962 9992",
    "sg:postcode":"37324",
    "sg:province":"TN",
    "wof:name":"Land n Lake Taxidermy",
    "wof:placetype":"venue"
},
  "geometry": {"coordinates":[-86.04360699999999,35.298249],"type":"Point"}
}