{
  "type": "Feature",
  "properties": {
    "iso:country":"US",
    "sg:address":"1418 Antioch Pike",
    "sg:city":"Antioch",
    "sg:classifiers":[
        {
            "category":"Manufacturing",
            "subcategory":"Paper Products",
            "type":"Manufacturing & Wholesale Goods"
        }
    ],
    "sg:phone":"+1 615 834 0626",
    "sg:postcode":"37013",
    "sg:province":"TN",
    "sg:tags":[
        "converted",
        "mfg"
    ],
    "wof:name":"Sydcor",
    "wof:placetype":"venue"
},
  "geometry": {"coordinates":[-86.688124,36.082398],"type":"Point"}
}