{
  "type": "Feature",
  "properties": {
    "iso:country":"US",
    "sg:address":"1259 Trotters Stop Cove",
    "sg:city":"Cordova",
    "sg:classifiers":[
        {
            "category":"Professional",
            "subcategory":"Business Services",
            "type":"Services"
        }
    ],
    "sg:phone":"+1 901 385 1836",
    "sg:postcode":"38018",
    "sg:province":"TN",
    "wof:name":"B & C Enterprises",
    "wof:placetype":"venue"
},
  "geometry": {"coordinates":[-89.831929,35.159567],"type":"Point"}
}