{
  "type": "Feature",
  "properties": {
    "iso:country":"US",
    "sg:address":"231 3rd Ave",
    "sg:city":"Dayton",
    "sg:classifiers":[
        {
            "category":"Organizations",
            "subcategory":"Religious Organization",
            "type":"Services"
        }
    ],
    "sg:phone":"+1 423 775 0255",
    "sg:postcode":"37321",
    "sg:province":"TN",
    "sg:tags":[
        "church"
    ],
    "wof:name":"First Baptist Church",
    "wof:placetype":"venue"
},
  "geometry": {"coordinates":[-85.009804,35.493795],"type":"Point"}
}