{
  "type": "Feature",
  "properties": {
    "iso:country":"US",
    "sg:address":"531 SE Broad St",
    "sg:city":"Murfreesboro",
    "sg:classifiers":[
        {
            "category":"Home & Garden",
            "subcategory":"Furniture",
            "type":"Retail Goods"
        }
    ],
    "sg:phone":"+1 615 907 1199",
    "sg:postcode":"37130",
    "sg:province":"TN",
    "wof:name":"Furniture & Merchandise Outlet",
    "wof:placetype":"venue"
},
  "geometry": {"coordinates":[-86.385824,35.837985],"type":"Point"}
}