{
  "type": "Feature",
  "properties": {
    "iso:country":"US",
    "sg:address":"4845 Willow Rd",
    "sg:city":"Memphis",
    "sg:classifiers":[
        {
            "category":"Government",
            "subcategory":"Office",
            "type":"Public Place"
        }
    ],
    "sg:phone":"+1 901 767 4580",
    "sg:postcode":"38117",
    "sg:province":"TN",
    "sg:tags":[
        "recreation",
        "park"
    ],
    "wof:name":"Park Commission",
    "wof:placetype":"venue"
},
  "geometry": {"coordinates":[-89.90152399999999,35.085654],"type":"Point"}
}