{
  "type": "Feature",
  "properties": {
    "iso:country":"US",
    "sg:address":"952 Parkway",
    "sg:city":"Gatlinburg",
    "sg:classifiers":[
        {
            "category":"Food & Beverages",
            "subcategory":"Groceries & Convenience Stores",
            "type":"Retail Goods"
        }
    ],
    "sg:phone":"+1 865 436 8247",
    "sg:postcode":"37738",
    "sg:province":"TN",
    "wof:name":"Smokies Market & Tobacco",
    "wof:placetype":"venue"
},
  "geometry": {"coordinates":[-83.51947699999999,35.710116],"type":"Point"}
}