{
  "type": "Feature",
  "properties": {
    "iso:country":"US",
    "sg:address":"110 Midtown Ct",
    "sg:city":"Hendersonville",
    "sg:classifiers":[
        {
            "category":"Building & Trades",
            "subcategory":"Construction",
            "type":"Services"
        },
        {
            "category":"Retail",
            "subcategory":"Auto Repair",
            "type":"Services"
        }
    ],
    "sg:phone":"+1 615 822 2222",
    "sg:postcode":"37075",
    "sg:province":"TN",
    "sg:tags":[
        "marking",
        "mfg",
        "lithographic",
        "coating",
        "tinting",
        "contractor",
        "glass",
        "devices"
    ],
    "wof:name":"Sun Cool Glass & Trim",
    "wof:placetype":"venue"
},
  "geometry": {"coordinates":[-86.63436299999999,36.304359],"type":"Point"}
}