{
  "type": "Feature",
  "properties": {
    "iso:country":"US",
    "sg:address":"760 Disco Loop Rd",
    "sg:city":"Friendsville",
    "sg:classifiers":[
        {
            "category":"Building & Trades",
            "subcategory":"Construction",
            "type":"Services"
        }
    ],
    "sg:phone":"+1 865 995 2134",
    "sg:postcode":"37737",
    "sg:province":"TN",
    "sg:tags":[
        "builder",
        "operative"
    ],
    "wof:name":"Contech Development",
    "wof:placetype":"venue"
},
  "geometry": {"coordinates":[-84.155383,35.787619],"type":"Point"}
}