{
  "type": "Feature",
  "properties": {
    "addr:full":"2801 E Magnolia Ave Knoxville TN 37914",
    "addr:housenumber":"2801",
    "addr:postcode":"37914",
    "addr:street":"E Magnolia Ave",
    "iso:country":"US",
    "sg:address":"2801 E Magnolia Ave",
    "sg:city":"Knoxville",
    "sg:classifiers":[
        {
            "category":"Travel",
            "subcategory":"Hotels & Motels",
            "type":"Entertainment"
        }
    ],
    "sg:phone":"+1 865 524 7227",
    "sg:postcode":"37914",
    "sg:province":"TN",
    "sg:tags":[
        "operation"
    ],
    "wof:name":"Budget Motel",
    "wof:placetype":"venue"
},
  "geometry": {"coordinates":[-83.889186,35.992233],"type":"Point"}
}