{
  "type": "Feature",
  "properties": {
    "addr:full":"3028 Nolensville Pike Nashville TN 37211",
    "addr:housenumber":"3028",
    "addr:postcode":"37211",
    "addr:street":"Nolensville Pike",
    "iso:country":"US",
    "sg:address":"3028 Nolensville Pike",
    "sg:city":"Nashville",
    "sg:classifiers":[
        {
            "category":"Autos & Motor Vehicles",
            "subcategory":"Automobile Sales",
            "type":"Retail Goods"
        },
        {
            "category":"Autos & Motor Vehicles",
            "subcategory":"Auto Supplies",
            "type":"Retail Goods"
        }
    ],
    "sg:phone":"+1 615 833 0056",
    "sg:postcode":"37211",
    "sg:province":"TN",
    "sg:tags":[
        "used",
        "car",
        "dealers-used",
        "part",
        "new",
        "cars-wholesale"
    ],
    "sg:website":"http://www.nashvillecityinformation.com",
    "wof:name":"New Day Auto Sales, Inc.",
    "wof:placetype":"venue"
},
  "geometry": {"coordinates":[-86.742547,36.105717],"type":"Point"}
}