{
  "type": "Feature",
  "properties": {
    "iso:country":"US",
    "sg:address":"225 Morgan St",
    "sg:city":"Knoxville",
    "sg:classifiers":[
        {
            "category":"Professional",
            "subcategory":"Accounting & Tax Preparation",
            "type":"Services"
        }
    ],
    "sg:phone":"+1 865 974 7189",
    "sg:postcode":"37917",
    "sg:province":"TN",
    "sg:tags":[
        "work",
        "computer",
        "statistical"
    ],
    "wof:name":"Univ Ten Statistical Cmpt Svcs",
    "wof:placetype":"venue"
},
  "geometry": {"coordinates":[-83.91778100000001,35.972536],"type":"Point"}
}