{
  "type": "Feature",
  "properties": {
    "iso:country":"US",
    "sg:address":"340 Hester Dr",
    "sg:city":"White House",
    "sg:classifiers":[
        {
            "category":"Professional",
            "type":"Services"
        }
    ],
    "sg:phone":"+1 615 672 8850",
    "sg:postcode":"37188",
    "sg:province":"TN",
    "wof:name":"Shri Prannath Inc",
    "wof:placetype":"venue"
},
  "geometry": {"coordinates":[-86.677779,36.46892],"type":"Point"}
}