{
  "type": "Feature",
  "properties": {
    "iso:country":"US",
    "sg:address":"107 N Cannon St",
    "sg:city":"Woodbury",
    "sg:classifiers":[
        {
            "category":"Shopping",
            "subcategory":"Used Merchandise",
            "type":"Retail Goods"
        }
    ],
    "sg:phone":"+1 615 563 4171",
    "sg:postcode":"37190",
    "sg:province":"TN",
    "sg:tags":[
        "antique"
    ],
    "wof:name":"David Duggin Antiques",
    "wof:placetype":"venue"
},
  "geometry": {"coordinates":[-86.069858,35.828549],"type":"Point"}
}