{
  "type": "Feature",
  "properties": {
    "iso:country":"US",
    "sg:address":"427 S College St",
    "sg:city":"Lebanon",
    "sg:classifiers":[
        {
            "category":"Bars & Pubs",
            "type":"Food & Drink"
        }
    ],
    "sg:phone":"+1 615 449 5068",
    "sg:postcode":"37087",
    "sg:province":"TN",
    "sg:tags":[
        "drinking"
    ],
    "wof:name":"Thirsty Turtle The",
    "wof:placetype":"venue"
},
  "geometry": {"coordinates":[-86.290905,36.198032],"type":"Point"}
}