{
  "type": "Feature",
  "properties": {
    "iso:country":"US",
    "sg:address":"1715 Broadway",
    "sg:city":"Nashville",
    "sg:classifiers":[
        {
            "category":"Retail",
            "subcategory":"Funeral Services",
            "type":"Services"
        }
    ],
    "sg:phone":"+1 615 244 6480",
    "sg:postcode":"37203",
    "sg:province":"TN",
    "sg:tags":[
        "director"
    ],
    "wof:name":"Roesch Patton",
    "wof:placetype":"venue"
},
  "geometry": {"coordinates":[-86.79509899999999,36.152195],"type":"Point"}
}