{
  "type": "Feature",
  "properties": {
    "iso:country":"US",
    "sg:address":"1229 Gunbarrel Rd",
    "sg:city":"Chattanooga",
    "sg:classifiers":[
        {
            "category":"Building & Trades",
            "subcategory":"Electrical",
            "type":"Services"
        }
    ],
    "sg:phone":"+1 423 894 1879",
    "sg:postcode":"37421",
    "sg:province":"TN",
    "sg:tags":[
        "electric",
        "contractor"
    ],
    "wof:name":"George W Arp Electric Co",
    "wof:placetype":"venue"
},
  "geometry": {"coordinates":[-85.16620500000001,35.010603],"type":"Point"}
}