{
  "type": "Feature",
  "properties": {
    "iso:country":"US",
    "sg:address":"1118 E Broadway Ave",
    "sg:city":"Maryville",
    "sg:classifiers":[
        {
            "category":"Shopping",
            "type":"Retail Goods"
        }
    ],
    "sg:phone":"+1 865 982 7946",
    "sg:postcode":"37804",
    "sg:province":"TN",
    "sg:tags":[
        "pool",
        "swimming"
    ],
    "wof:name":"Backyard Splash",
    "wof:placetype":"venue"
},
  "geometry": {"coordinates":[-83.962857,35.763838],"type":"Point"}
}