{
  "type": "Feature",
  "properties": {
    "iso:country":"US",
    "sg:address":"102 Mc Kinney Cir",
    "sg:city":"Estill Springs",
    "sg:classifiers":[
        {
            "category":"Building & Trades",
            "subcategory":"Construction",
            "type":"Services"
        }
    ],
    "sg:phone":"+1 931 649 5499",
    "sg:postcode":"37330",
    "sg:province":"TN",
    "sg:tags":[
        "house"
    ],
    "wof:name":"Will Green Custom Remodel",
    "wof:placetype":"venue"
},
  "geometry": {"coordinates":[-86.13440799999999,35.25786],"type":"Point"}
}