{
  "type": "Feature",
  "properties": {
    "iso:country":"US",
    "sg:address":"162 Island Rd",
    "sg:city":"Jacksboro",
    "sg:classifiers":[
        {
            "category":"Organizations",
            "subcategory":"Religious Organization",
            "type":"Services"
        }
    ],
    "sg:phone":"+1 423 566 2047",
    "sg:postcode":"37757",
    "sg:province":"TN",
    "sg:tags":[
        "church"
    ],
    "wof:name":"East Jacksboro Baptist Church",
    "wof:placetype":"venue"
},
  "geometry": {"coordinates":[-84.17542,36.327336],"type":"Point"}
}