{
  "type": "Feature",
  "properties": {
    "iso:country":"US",
    "sg:address":"4398 State Hwy 70",
    "sg:city":"Eidson",
    "sg:classifiers":[
        {
            "category":"Travel",
            "subcategory":"Campground",
            "type":"Entertainment"
        }
    ],
    "sg:phone":"+1 423 272 3220",
    "sg:postcode":"37731",
    "sg:province":"TN",
    "sg:tags":[
        "trailer"
    ],
    "wof:name":"Frog Level Campground",
    "wof:placetype":"venue"
},
  "geometry": {"coordinates":[-83.023701,36.537307],"type":"Point"}
}