{
  "type": "Feature",
  "properties": {
    "addr:full":"2655 Teaster Ln Pigeon Forge TN 37863",
    "addr:housenumber":"2655",
    "addr:postcode":"37863",
    "addr:street":"Teaster Ln",
    "iso:country":"US",
    "sg:address":"2655 Teaster Ln",
    "sg:city":"Pigeon Forge",
    "sg:classifiers":[
        {
            "category":"Shopping",
            "subcategory":"Clothing, Apparel, & Fashions",
            "type":"Retail Goods"
        }
    ],
    "sg:phone":"+1 865 774 0042",
    "sg:postcode":"37863",
    "sg:province":"TN",
    "wof:name":"Totes-Isotoner Outlet Str 155",
    "wof:placetype":"venue"
},
  "geometry": {"coordinates":[-83.55472899999999,35.794374],"type":"Point"}
}