{
  "type": "Feature",
  "properties": {
    "iso:country":"US",
    "sg:address":"112 Main St",
    "sg:city":"Cumberland City",
    "sg:classifiers":[
        {
            "category":"Personal",
            "subcategory":"Beauty Salon",
            "type":"Services"
        }
    ],
    "sg:phone":"+1 931 827 2579",
    "sg:postcode":"37050",
    "sg:province":"TN",
    "sg:tags":[
        "shop"
    ],
    "wof:name":"Nancy's Beauty Shop",
    "wof:placetype":"venue"
},
  "geometry": {"coordinates":[-87.633245,36.393476],"type":"Point"}
}