{
  "type": "Feature",
  "properties": {
    "iso:country":"US",
    "sg:address":"7420 Chapman Hwy",
    "sg:city":"Knoxville",
    "sg:classifiers":[
        {
            "category":"Professional",
            "subcategory":"Accounting & Tax Preparation",
            "type":"Services"
        }
    ],
    "sg:phone":"+1 865 573 8870",
    "sg:postcode":"37920",
    "sg:province":"TN",
    "sg:tags":[
        "return",
        "filing"
    ],
    "wof:name":"Jackson Hewitt Tax Svc",
    "wof:placetype":"venue"
},
  "geometry": {"coordinates":[-83.84393799999999,35.90843],"type":"Point"}
}