{
  "type": "Feature",
  "properties": {
    "addr:full":"316 Knox Rd NE Knoxville TN 37918",
    "addr:housenumber":"316",
    "addr:postcode":"37918",
    "addr:street":"Knox Rd Ne",
    "iso:country":"US",
    "sg:address":"316 Knox Rd NE",
    "sg:city":"Knoxville",
    "sg:classifiers":[
        {
            "category":"Recreation",
            "type":"Entertainment"
        }
    ],
    "sg:phone":"+1 865 219 0303",
    "sg:postcode":"37918",
    "sg:province":"TN",
    "sg:tags":[
        "martial",
        "arts",
        "instruction"
    ],
    "wof:name":"Flying Dragon Chinese Martial",
    "wof:placetype":"venue"
},
  "geometry": {"coordinates":[-83.933189,36.032874],"type":"Point"}
}