{
  "type": "Feature",
  "properties": {
    "iso:country":"US",
    "sg:address":"1305 Pleasant Ave",
    "sg:city":"Chattanooga",
    "sg:classifiers":[
        {
            "category":"Building & Trades",
            "subcategory":"Construction",
            "type":"Services"
        }
    ],
    "sg:phone":"+1 423 296 8975",
    "sg:postcode":"37412",
    "sg:province":"TN",
    "sg:tags":[
        "house"
    ],
    "wof:name":"Bosnija Construction",
    "wof:placetype":"venue"
},
  "geometry": {"coordinates":[-85.226755,34.995512],"type":"Point"}
}