{
  "type": "Feature",
  "properties": {
    "iso:country":"US",
    "sg:address":"3670 N Watkins St",
    "sg:city":"Memphis",
    "sg:classifiers":[
        {
            "category":"Shopping",
            "subcategory":"Beauty & Cosmetics",
            "type":"Retail Goods"
        }
    ],
    "sg:phone":"+1 901 357 9780",
    "sg:postcode":"38127",
    "sg:province":"TN",
    "sg:tags":[
        "apparel",
        "salons-equipment",
        "supply"
    ],
    "wof:name":"Beauty Plus Beauty Supply",
    "wof:placetype":"venue"
},
  "geometry": {"coordinates":[-90.003122,35.225765],"type":"Point"}
}