{
  "type": "Feature",
  "properties": {
    "iso:country":"US",
    "sg:address":"424 E Castle St",
    "sg:city":"Murfreesboro",
    "sg:classifiers":[
        {
            "category":"Organizations",
            "subcategory":"Religious Organization",
            "type":"Services"
        }
    ],
    "sg:phone":"+1 615 890 4838",
    "sg:postcode":"37130",
    "sg:province":"TN",
    "sg:tags":[
        "church"
    ],
    "wof:name":"Original Church Of God",
    "wof:placetype":"venue"
},
  "geometry": {"coordinates":[-86.38595100000001,35.841007],"type":"Point"}
}