{
  "type": "Feature",
  "properties": {
    "iso:country":"US",
    "sg:address":"6700 White Tail Dr",
    "sg:city":"Ooltewah",
    "sg:classifiers":[
        {
            "category":"Shopping",
            "subcategory":"Jewelry",
            "type":"Retail Goods"
        }
    ],
    "sg:phone":"+1 423 479 1055",
    "sg:postcode":"37363",
    "sg:province":"TN",
    "sg:tags":[
        "jeweler"
    ],
    "wof:name":"Sparkles & Such",
    "wof:placetype":"venue"
},
  "geometry": {"coordinates":[-85.098849,35.114484],"type":"Point"}
}