{
  "type": "Feature",
  "properties": {
    "addr:full":"1328 Cheshire Dr Nashville TN 37207",
    "addr:housenumber":"1328",
    "addr:postcode":"37207",
    "addr:street":"Cheshire Dr",
    "iso:country":"US",
    "sg:address":"1328 Cheshire Dr",
    "sg:city":"Nashville",
    "sg:classifiers":[
        {
            "category":"Wholesale",
            "subcategory":"Machinery & Supplies",
            "type":"Manufacturing & Wholesale Goods"
        }
    ],
    "sg:phone":"+1 615 865 5589",
    "sg:postcode":"37207",
    "sg:province":"TN",
    "sg:tags":[
        "director",
        "equipment",
        "funeral"
    ],
    "wof:name":"Ramsey, Dave Associates",
    "wof:placetype":"venue"
},
  "geometry": {"coordinates":[-86.773144,36.267073],"type":"Point"}
}