{
  "type": "Feature",
  "properties": {
    "iso:country":"US",
    "sg:address":"444 Harmony Cir",
    "sg:city":"Johnson City",
    "sg:classifiers":[
        {
            "category":"Professional",
            "subcategory":"Business Services",
            "type":"Services"
        }
    ],
    "sg:phone":"+1 423 477 7882",
    "sg:postcode":"37615",
    "sg:province":"TN",
    "wof:name":"Service Group Associates",
    "wof:placetype":"venue"
},
  "geometry": {"coordinates":[-82.422134,36.415606],"type":"Point"}
}