{
  "type": "Feature",
  "properties": {
    "addr:full":"1465 Madison St Clarksville TN 37040",
    "addr:housenumber":"1465",
    "addr:postcode":"37040",
    "addr:street":"Madison St",
    "iso:country":"US",
    "sg:address":"1465 Madison St",
    "sg:city":"Clarksville",
    "sg:classifiers":[
        {
            "category":"Autos & Motor Vehicles",
            "subcategory":"Automobile Sales",
            "type":"Retail Goods"
        }
    ],
    "sg:phone":"+1 931 647 4557",
    "sg:postcode":"37040",
    "sg:province":"TN",
    "sg:tags":[
        "car",
        "dealer"
    ],
    "wof:name":"Boggs Auto Plus",
    "wof:placetype":"venue"
},
  "geometry": {"coordinates":[-87.33293399999999,36.520662],"type":"Point"}
}