{
  "type": "Feature",
  "properties": {
    "addr:full":"218 Gardendale Dr Columbia TN 38401",
    "addr:housenumber":"218",
    "addr:postcode":"38401",
    "addr:street":"Gardendale Dr",
    "iso:country":"US",
    "sg:address":"218 Gardendale Dr",
    "sg:city":"Columbia",
    "sg:classifiers":[
        {
            "category":"Building & Trades",
            "subcategory":"Construction",
            "type":"Services"
        }
    ],
    "sg:phone":"+1 931 285 2343",
    "sg:postcode":"38401",
    "sg:province":"TN",
    "sg:tags":[
        "contractor"
    ],
    "wof:name":"Davis Mike Stone Masonry",
    "wof:placetype":"venue"
},
  "geometry": {"coordinates":[-87.053788,35.588842],"type":"Point"}
}