{
  "type": "Feature",
  "properties": {
    "addr:full":"25 N Cove Eads TN 38028",
    "addr:housenumber":"25",
    "addr:postcode":"38028",
    "addr:street":"N Cove",
    "iso:country":"US",
    "sg:address":"25 N Cove",
    "sg:city":"Eads",
    "sg:classifiers":[
        {
            "category":"Building & Trades",
            "subcategory":"Construction",
            "type":"Services"
        }
    ],
    "sg:phone":"+1 901 861 5457",
    "sg:postcode":"38028",
    "sg:province":"TN",
    "sg:tags":[
        "house"
    ],
    "wof:name":"Barnett Genral Construction",
    "wof:placetype":"venue"
},
  "geometry": {"coordinates":[-89.564575,35.244729],"type":"Point"}
}