{
  "type": "Feature",
  "properties": {
    "addr:full":"624 4th Ave S Nashville TN 37210",
    "addr:housenumber":"624",
    "addr:postcode":"37210",
    "addr:street":"4Th Ave S",
    "iso:country":"US",
    "sg:address":"624 4th Ave S",
    "sg:city":"Nashville",
    "sg:classifiers":[
        {
            "category":"Wholesale",
            "subcategory":"Plants",
            "type":"Manufacturing & Wholesale Goods"
        },
        {
            "category":"Shopping",
            "subcategory":"Florist",
            "type":"Retail Goods"
        }
    ],
    "sg:phone":"+1 615 244 0561",
    "sg:postcode":"37210",
    "sg:province":"TN",
    "sg:tags":[
        "flower"
    ],
    "wof:name":"Nashville Cut Flower Inc",
    "wof:placetype":"venue"
},
  "geometry": {"coordinates":[-86.772341,36.153681],"type":"Point"}
}