{
  "type": "Feature",
  "properties": {
    "iso:country":"US",
    "sg:address":"1621 Tom Garrison Rd",
    "sg:city":"Evensville",
    "sg:classifiers":[
        {
            "category":"Personal",
            "subcategory":"Beauty Salon",
            "type":"Services"
        }
    ],
    "sg:phone":"+1 423 365 6073",
    "sg:postcode":"37332",
    "sg:province":"TN",
    "sg:tags":[
        "shop"
    ],
    "wof:name":"Johnnies Beauty Shop",
    "wof:placetype":"venue"
},
  "geometry": {"coordinates":[-84.85207,35.586764],"type":"Point"}
}