{
  "type": "Feature",
  "properties": {
    "addr:full":"3945 Nolensville Pike Nashville TN 37211",
    "addr:housenumber":"3945",
    "addr:postcode":"37211",
    "addr:street":"Nolensville Pike",
    "iso:country":"US",
    "sg:address":"3945 Nolensville Pike",
    "sg:city":"Nashville",
    "sg:classifiers":[
        {
            "category":"Shopping",
            "subcategory":"Discount & Variety Stores",
            "type":"Retail Goods"
        }
    ],
    "sg:phone":"+1 615 833 6340",
    "sg:postcode":"37211",
    "sg:province":"TN",
    "wof:name":"Dollar Tree",
    "wof:placetype":"venue"
},
  "geometry": {"coordinates":[-86.728645,36.085318],"type":"Point"}
}