{
  "type": "Feature",
  "properties": {
    "iso:country":"US",
    "sg:address":"2500 12th Ave S",
    "sg:city":"Nashville",
    "sg:classifiers":[
        {
            "category":"Retail",
            "subcategory":"Laundry & Dry Cleaning",
            "type":"Services"
        }
    ],
    "sg:phone":"+1 615 297 2438",
    "sg:postcode":"37204",
    "sg:province":"TN",
    "sg:tags":[
        "drycleaning",
        "hotel",
        "valet"
    ],
    "wof:name":"Royal Cleaners",
    "wof:placetype":"venue"
},
  "geometry": {"coordinates":[-86.789329,36.125785],"type":"Point"}
}