{
  "type": "Feature",
  "properties": {
    "addr:full":"1700 Mc Daniel St Nashville TN 37208",
    "addr:housenumber":"1700",
    "addr:postcode":"37208",
    "addr:street":"Mc Daniel St",
    "iso:country":"US",
    "sg:address":"1700 Mc Daniel St",
    "sg:city":"Nashville",
    "sg:classifiers":[
        {
            "category":"Retail",
            "subcategory":"Auto Repair",
            "type":"Services"
        }
    ],
    "sg:phone":"+1 615 726 3623",
    "sg:postcode":"37208",
    "sg:province":"TN",
    "sg:tags":[
        "repairing",
        "automobile",
        "general"
    ],
    "wof:name":"Richard's Automotive",
    "wof:placetype":"venue"
},
  "geometry": {"coordinates":[-86.813756,36.183695],"type":"Point"}
}