{
  "type": "Feature",
  "properties": {
    "iso:country":"US",
    "sg:address":"205 S 4th St",
    "sg:city":"Smithville",
    "sg:classifiers":[
        {
            "category":"Health Services",
            "subcategory":"Chiropractor",
            "type":"Services"
        }
    ],
    "sg:phone":"+1 615 597 5375",
    "sg:postcode":"37166",
    "sg:province":"TN",
    "wof:name":"Atnip Chiropractic Clinic",
    "wof:placetype":"venue"
},
  "geometry": {"coordinates":[-85.813857,35.960462],"type":"Point"}
}