{
  "type": "Feature",
  "properties": {
    "addr:full":"2539 G W Loy Rd New Market TN 37820",
    "addr:housenumber":"2539",
    "addr:postcode":"37820",
    "addr:street":"G W Loy Rd",
    "iso:country":"US",
    "sg:address":"2539 G W Loy Rd",
    "sg:city":"New Market",
    "sg:classifiers":[
        {
            "category":"Farming",
            "subcategory":"Livestock Farm",
            "type":"Manufacturing & Wholesale Goods"
        }
    ],
    "sg:phone":"+1 865 933 6044",
    "sg:postcode":"37820",
    "sg:province":"TN",
    "sg:tags":[
        "beef",
        "feedlot",
        "cattle"
    ],
    "wof:name":"Steve Mc Clane",
    "wof:placetype":"venue"
},
  "geometry": {"coordinates":[-83.593261,36.053542],"type":"Point"}
}