{
  "type": "Feature",
  "properties": {
    "iso:country":"US",
    "sg:address":"3924 Dickerson Pike",
    "sg:city":"Nashville",
    "sg:classifiers":[
        {
            "category":"Manufacturing",
            "subcategory":"Glass & Minerals",
            "type":"Manufacturing & Wholesale Goods"
        },
        {
            "category":"Retail",
            "subcategory":"Auto Repair",
            "type":"Services"
        }
    ],
    "sg:phone":"+1 615 712 6238",
    "sg:postcode":"37207",
    "sg:province":"TN",
    "sg:tags":[
        "plate",
        "window",
        "windshield",
        "glass-auto"
    ],
    "sg:website":"http://www.autoglasscompanyinc.com",
    "wof:name":"Cameratrux Inc",
    "wof:placetype":"venue"
},
  "geometry": {"coordinates":[-86.7552,36.27027],"type":"Point"}
}