{
  "type": "Feature",
  "properties": {
    "iso:country":"US",
    "sg:address":"400 Industrial Dr",
    "sg:city":"Smithville",
    "sg:classifiers":[
        {
            "category":"Wholesale",
            "subcategory":"Auto Parts",
            "type":"Manufacturing & Wholesale Goods"
        }
    ],
    "sg:phone":"+1 615 597 6664",
    "sg:postcode":"37122",
    "sg:province":"TN",
    "sg:tags":[
        "automobile",
        "supply"
    ],
    "wof:name":"Federal-Mogul Distribution Ctr",
    "wof:placetype":"venue"
},
  "geometry": {"coordinates":[-86.51341600000001,36.198914],"type":"Point"}
}