{
  "type": "Feature",
  "properties": {
    "iso:country":"US",
    "sg:address":"4646 Getwell Rd",
    "sg:city":"Memphis",
    "sg:classifiers":[
        {
            "category":"Home & Garden",
            "subcategory":"Furniture",
            "type":"Retail Goods"
        }
    ],
    "sg:phone":"+1 901 367 2100",
    "sg:postcode":"38118",
    "sg:province":"TN",
    "sg:tags":[
        "maker",
        "cabinet"
    ],
    "wof:name":"Dixie Cabinets Inc",
    "wof:placetype":"venue"
},
  "geometry": {"coordinates":[-89.936913,35.021537],"type":"Point"}
}