{
  "type": "Feature",
  "properties": {
    "addr:full":"11900 Mott St Arlington TN 38002",
    "addr:housenumber":"11900",
    "addr:postcode":"38002",
    "addr:street":"Mott St",
    "iso:country":"US",
    "sg:address":"11900 Mott St",
    "sg:city":"Arlington",
    "sg:classifiers":[
        {
            "category":"Insurance",
            "subcategory":"Insurance Agent",
            "type":"Services"
        }
    ],
    "sg:phone":"+1 901 867 3951",
    "sg:postcode":"38002",
    "sg:province":"TN",
    "wof:name":"MetLife",
    "wof:placetype":"venue"
},
  "geometry": {"coordinates":[-89.66551,35.295853],"type":"Point"}
}