{
  "type": "Feature",
  "properties": {
    "iso:country":"US",
    "sg:address":"117 Longview St",
    "sg:city":"La Vergne",
    "sg:classifiers":[
        {
            "category":"Professional",
            "type":"Services"
        },
        {
            "category":"Wholesale",
            "subcategory":"Groceries",
            "type":"Manufacturing & Wholesale Goods"
        }
    ],
    "sg:phone":"+1 615 287 9114",
    "sg:postcode":"37086",
    "sg:province":"TN",
    "sg:tags":[
        "food",
        "product",
        "establishment"
    ],
    "wof:name":"Slush Puppie Of Nashville",
    "wof:placetype":"venue"
},
  "geometry": {"coordinates":[-86.592181,36.002521],"type":"Point"}
}