{
  "type": "Feature",
  "properties": {
    "addr:full":"5635 Sycamore Grove Ln Memphis TN 38120",
    "addr:housenumber":"5635",
    "addr:postcode":"38120",
    "addr:street":"Sycamore Grove Ln",
    "iso:country":"US",
    "sg:address":"5635 Sycamore Grove Ln",
    "sg:city":"Memphis",
    "sg:classifiers":[
        {
            "category":"Professional",
            "subcategory":"Research",
            "type":"Services"
        }
    ],
    "sg:phone":"+1 901 767 2137",
    "sg:postcode":"38120",
    "sg:province":"TN",
    "sg:tags":[
        "development",
        "laboratory"
    ],
    "sg:website":"www.coolpak.com",
    "wof:name":"Coolpak Inc",
    "wof:placetype":"venue"
},
  "geometry": {"coordinates":[-89.875443,35.125209],"type":"Point"}
}