{
  "type": "Feature",
  "properties": {
    "addr:full":"3233 Lu Ann Dr Antioch TN 37013",
    "addr:postcode":"3233;37013",
    "addr:street":"Ann Dr",
    "iso:country":"US",
    "sg:address":"3233 Lu Ann Dr",
    "sg:city":"Antioch",
    "sg:classifiers":[
        {
            "category":"Building & Trades",
            "subcategory":"Construction",
            "type":"Services"
        }
    ],
    "sg:phone":"+1 615 414 1505",
    "sg:postcode":"37013",
    "sg:province":"TN",
    "sg:tags":[
        "hanging",
        "contractor"
    ],
    "wof:name":"Ramirez Painting",
    "wof:placetype":"venue"
},
  "geometry": {"coordinates":[-86.62083699999999,36.072105],"type":"Point"}
}