{
  "type": "Feature",
  "properties": {
    "iso:country":"US",
    "sg:address":"2650 Thousand Oaks Blvd",
    "sg:city":"Memphis",
    "sg:classifiers":[
        {
            "category":"Communications",
            "subcategory":"Radio Station",
            "type":"Services"
        }
    ],
    "sg:phone":"+1 901 259 1300",
    "sg:postcode":"38118",
    "sg:province":"TN",
    "sg:tags":[
        "broadcast"
    ],
    "wof:name":"American Urban Radio Netw",
    "wof:placetype":"venue"
},
  "geometry": {"coordinates":[-89.90212099999999,35.076532],"type":"Point"}
}