{
  "type": "Feature",
  "properties": {
    "iso:country":"US",
    "sg:address":"444 W Blount Ave",
    "sg:city":"Knoxville",
    "sg:classifiers":[
        {
            "category":"Manufacturing",
            "subcategory":"Leather Goods",
            "type":"Manufacturing & Wholesale Goods"
        }
    ],
    "sg:phone":"+1 865 573 4555",
    "sg:postcode":"37920",
    "sg:province":"TN",
    "sg:tags":[
        "mitten",
        "glove"
    ],
    "sg:website":"www.knoxvilleglove.com",
    "wof:name":"Knoxville Glove Co",
    "wof:placetype":"venue"
},
  "geometry": {"coordinates":[-83.919679,35.951794],"type":"Point"}
}