{
  "type": "Feature",
  "properties": {
    "iso:country":"US",
    "sg:address":"178 Nettleton Rd",
    "sg:city":"Harrogate",
    "sg:classifiers":[
        {
            "category":"Real Estate",
            "subcategory":"Surveying",
            "type":"Services"
        }
    ],
    "sg:phone":"+1 423 869 3024",
    "sg:postcode":"37752",
    "sg:province":"TN",
    "sg:tags":[
        "surveyor"
    ],
    "wof:name":"William L Parsons Engineering",
    "wof:placetype":"venue"
},
  "geometry": {"coordinates":[-83.656088,36.583849],"type":"Point"}
}