{
  "type": "Feature",
  "properties": {
    "iso:country":"US",
    "sg:address":"1209 Lakeview Dr",
    "sg:city":"Franklin",
    "sg:classifiers":[
        {
            "category":"Retail",
            "subcategory":"Laundry & Dry Cleaning",
            "type":"Services"
        }
    ],
    "sg:phone":"+1 615 370 4597",
    "sg:postcode":"37067",
    "sg:province":"TN",
    "sg:tags":[
        "cleaners"
    ],
    "wof:name":"Servepro",
    "wof:placetype":"venue"
},
  "geometry": {"coordinates":[-86.825993,35.919293],"type":"Point"}
}