{
  "type": "Feature",
  "properties": {
    "addr:full":"1310 Higgs St Lewisburg TN 37091",
    "addr:housenumber":"1310",
    "addr:postcode":"37091",
    "addr:street":"Higgs St",
    "iso:country":"US",
    "sg:address":"1310 Higgs St",
    "sg:city":"Lewisburg",
    "sg:classifiers":[
        {
            "category":"Building & Trades",
            "subcategory":"Electrical",
            "type":"Services"
        }
    ],
    "sg:phone":"+1 931 359 7742",
    "sg:postcode":"37091",
    "sg:province":"TN",
    "sg:tags":[
        "electric",
        "contractor"
    ],
    "wof:name":"Custom Industrial Svc Inc",
    "wof:placetype":"venue"
},
  "geometry": {"coordinates":[-86.767124,35.435798],"type":"Point"}
}