{
  "type": "Feature",
  "properties": {
    "iso:country":"US",
    "sg:address":"4986 Barfield Crescent Rd",
    "sg:city":"Murfreesboro",
    "sg:classifiers":[
        {
            "category":"Food & Beverages",
            "subcategory":"Groceries & Convenience Stores",
            "type":"Retail Goods"
        }
    ],
    "sg:phone":"+1 615 217 8575",
    "sg:postcode":"37128",
    "sg:province":"TN",
    "wof:name":"Cresent Corner Market",
    "wof:placetype":"venue"
},
  "geometry": {"coordinates":[-86.458333,35.73983],"type":"Point"}
}