{
  "type": "Feature",
  "properties": {
    "addr:full":"108 Knox Rd NE Knoxville TN 37918",
    "addr:housenumber":"108",
    "addr:postcode":"37918",
    "addr:street":"Knox Rd Ne",
    "iso:country":"US",
    "sg:address":"108 Knox Rd NE",
    "sg:city":"Knoxville",
    "sg:classifiers":[
        {
            "category":"Shopping",
            "subcategory":"Bicycles & Sporting Goods",
            "type":"Retail Goods"
        }
    ],
    "sg:phone":"+1 865 689 5585",
    "sg:postcode":"37918",
    "sg:province":"TN",
    "wof:name":"Rhea Springs Live Bait",
    "wof:placetype":"venue"
},
  "geometry": {"coordinates":[-83.931866,36.03207],"type":"Point"}
}