{
  "type": "Feature",
  "properties": {
    "iso:country":"US",
    "sg:address":"2702 W Broad St",
    "sg:city":"Cookeville",
    "sg:classifiers":[
        {
            "category":"Retail",
            "subcategory":"Auto Repair",
            "type":"Services"
        }
    ],
    "sg:phone":"+1 931 520 0086",
    "sg:postcode":"38501",
    "sg:province":"TN",
    "sg:tags":[
        "transmission"
    ],
    "wof:name":"All-Pro-Matic",
    "wof:placetype":"venue"
},
  "geometry": {"coordinates":[-85.582565,36.173537],"type":"Point"}
}