{
  "type": "Feature",
  "properties": {
    "iso:country":"US",
    "sg:address":"2330 S Germantown Rd",
    "sg:city":"Germantown",
    "sg:classifiers":[
        {
            "category":"Shopping",
            "subcategory":"Used Merchandise",
            "type":"Retail Goods"
        }
    ],
    "sg:phone":"+1 901 754 5975",
    "sg:postcode":"38138",
    "sg:province":"TN",
    "sg:tags":[
        "antique"
    ],
    "wof:name":"Cottage Antiques & Gifts",
    "wof:placetype":"venue"
},
  "geometry": {"coordinates":[-89.810316,35.08609],"type":"Point"}
}