{
  "type": "Feature",
  "properties": {
    "iso:country":"US",
    "sg:address":"68 Walnut St",
    "sg:city":"Friendship",
    "sg:classifiers":[
        {
            "category":"Organizations",
            "subcategory":"Religious Organization",
            "type":"Services"
        }
    ],
    "sg:phone":"+1 731 677 2425",
    "sg:postcode":"38034",
    "sg:province":"TN",
    "sg:tags":[
        "church"
    ],
    "wof:name":"Friendship Methodist Chr Prsng",
    "wof:placetype":"venue"
},
  "geometry": {"coordinates":[-89.243702,35.910995],"type":"Point"}
}