{
  "type": "Feature",
  "properties": {
    "iso:country":"US",
    "sg:address":"1053 W Rex Rd",
    "sg:city":"Memphis",
    "sg:classifiers":[
        {
            "category":"Banks & Credit Unions",
            "subcategory":"Investment Brokerage",
            "type":"Services"
        }
    ],
    "sg:phone":"+1 901 683 5858",
    "sg:postcode":"38119",
    "sg:province":"TN",
    "sg:tags":[
        "consultant",
        "planning",
        "financial"
    ],
    "wof:name":"American Express Advisory Brnc",
    "wof:placetype":"venue"
},
  "geometry": {"coordinates":[-89.87271,35.103014],"type":"Point"}
}