{
  "type": "Feature",
  "properties": {
    "addr:full":"202 E Cedar St Bristol TN 37620",
    "addr:housenumber":"202",
    "addr:postcode":"37620",
    "addr:street":"E Cedar St",
    "iso:country":"US",
    "sg:address":"202 E Cedar St",
    "sg:city":"Bristol",
    "sg:classifiers":[
        {
            "category":"Food & Beverages",
            "subcategory":"Groceries & Convenience Stores",
            "type":"Retail Goods"
        }
    ],
    "sg:phone":"+1 423 652 0700",
    "sg:postcode":"37620",
    "sg:province":"TN",
    "wof:name":"AJS Market",
    "wof:placetype":"venue"
},
  "geometry": {"coordinates":[-82.17054,36.582151],"type":"Point"}
}