{
  "type": "Feature",
  "properties": {
    "addr:full":"241 Hinshaw Ln Spring City TN 37306",
    "addr:housenumber":"241",
    "addr:postcode":"37306",
    "addr:street":"Hinshaw Ln",
    "iso:country":"US",
    "sg:address":"241 Hinshaw Ln",
    "sg:city":"Spring City",
    "sg:classifiers":[
        {
            "category":"Social Services",
            "subcategory":"Child Care",
            "type":"Services"
        }
    ],
    "sg:phone":"+1 423 365 7031",
    "sg:postcode":"37306",
    "sg:province":"TN",
    "sg:tags":[
        "kindergarten",
        "academic",
        "school"
    ],
    "wof:name":"Sequatchie Valley Head Start",
    "wof:placetype":"venue"
},
  "geometry": {"coordinates":[-86.19940699999999,35.148232],"type":"Point"}
}