{
  "type": "Feature",
  "properties": {
    "addr:full":"5390 Center Hill Rd Finger TN 38334",
    "addr:housenumber":"5390",
    "addr:postcode":"38334",
    "addr:street":"Center Hill Rd",
    "iso:country":"US",
    "sg:address":"5390 Center Hill Rd",
    "sg:city":"Finger",
    "sg:classifiers":[
        {
            "category":"Education",
            "subcategory":"School",
            "type":"Public Place"
        }
    ],
    "sg:phone":"+1 731 687 3088",
    "sg:postcode":"38334",
    "sg:province":"TN",
    "wof:name":"Pine Hill Christian School",
    "wof:placetype":"venue"
},
  "geometry": {"coordinates":[-88.49660799999999,35.359072],"type":"Point"}
}