{
  "type": "Feature",
  "properties": {
    "iso:country":"US",
    "sg:address":"4387 Cato Rd",
    "sg:city":"Nashville",
    "sg:classifiers":[
        {
            "category":"Building & Trades",
            "subcategory":"Cleaning & Sanitation",
            "type":"Services"
        }
    ],
    "sg:phone":"+1 615 256 2036",
    "sg:postcode":"37218",
    "sg:province":"TN",
    "sg:tags":[
        "maintenance"
    ],
    "wof:name":"Sparkling Touch Janitorial",
    "wof:placetype":"venue"
},
  "geometry": {"coordinates":[-86.868465,36.216574],"type":"Point"}
}