{
  "type": "Feature",
  "properties": {
    "iso:country":"US",
    "sg:address":"126 Lynn Cobb Rd",
    "sg:city":"Brownsville",
    "sg:classifiers":[
        {
            "category":"Shopping",
            "subcategory":"Bicycles & Sporting Goods",
            "type":"Retail Goods"
        }
    ],
    "sg:phone":"+1 731 772 4202",
    "sg:postcode":"38012",
    "sg:province":"TN",
    "sg:tags":[
        "gun",
        "gunsmith"
    ],
    "wof:name":"Hill's Holster Co",
    "wof:placetype":"venue"
},
  "geometry": {"coordinates":[-89.35495299999999,35.523116],"type":"Point"}
}