{
  "type": "Feature",
  "properties": {
    "addr:full":"10095 State Hwy 100 Scotts Hill TN 38374",
    "addr:housenumber":"10095",
    "addr:postcode":"38374",
    "addr:street":"State Hwy 100 Scotts Hill",
    "iso:country":"US",
    "sg:address":"10095 State Hwy 100",
    "sg:city":"Scotts Hill",
    "sg:classifiers":[
        {
            "category":"Wholesale",
            "subcategory":"Medical Equipment & Supplies",
            "type":"Manufacturing & Wholesale Goods"
        }
    ],
    "sg:phone":"+1 731 549 2858",
    "sg:postcode":"38374",
    "sg:province":"TN",
    "sg:tags":[
        "physician",
        "surgeon"
    ],
    "wof:name":"Lincare",
    "wof:placetype":"venue"
},
  "geometry": {"coordinates":[-88.250936,35.525321],"type":"Point"}
}