{
  "type": "Feature",
  "properties": {
    "addr:full":"126 Glancy St Goodlettsville TN 37072",
    "addr:housenumber":"126",
    "addr:postcode":"37072",
    "addr:street":"Glancy St",
    "iso:country":"US",
    "sg:address":"126 Glancy St",
    "sg:city":"Goodlettsville",
    "sg:classifiers":[
        {
            "category":"Professional",
            "subcategory":"Engineering",
            "type":"Services"
        },
        {
            "category":"Wholesale",
            "subcategory":"Computers",
            "type":"Manufacturing & Wholesale Goods"
        },
        {
            "category":"Professional",
            "subcategory":"Computer Services",
            "type":"Services"
        }
    ],
    "sg:phone":"+1 615 859 5710",
    "sg:postcode":"37072",
    "sg:province":"TN",
    "sg:tags":[
        "designer",
        "rooms-installation",
        "consultant",
        "integration",
        "system",
        "equipment",
        "engineer"
    ],
    "wof:name":"Kemp T G Sales Inc",
    "wof:placetype":"venue"
},
  "geometry": {"coordinates":[-86.70397,36.297335],"type":"Point"}
}