{
  "type": "Feature",
  "properties": {
    "iso:country":"US",
    "sg:address":"101 N Highland Ave",
    "sg:city":"Jackson",
    "sg:classifiers":[
        {
            "category":"Social Services",
            "type":"Services"
        }
    ],
    "sg:phone":"+1 731 423 6183",
    "sg:postcode":"38301",
    "sg:province":"TN",
    "wof:name":"Madison Cnty Cmnty Corrections",
    "wof:placetype":"venue"
},
  "geometry": {"coordinates":[-88.819328,35.615172],"type":"Point"}
}