{
  "type": "Feature",
  "properties": {
    "addr:full":"5025 Bobby Hicks Hwy Johnson City TN 37615",
    "addr:housenumber":"5025",
    "addr:postcode":"37615",
    "addr:street":"Bobby Hicks Hwy",
    "iso:country":"US",
    "sg:address":"5025 Bobby Hicks Hwy",
    "sg:city":"Johnson City",
    "sg:classifiers":[
        {
            "category":"Building & Trades",
            "subcategory":"Construction",
            "type":"Services"
        }
    ],
    "sg:phone":"+1 423 467 9955",
    "sg:postcode":"37615",
    "sg:province":"TN",
    "sg:tags":[
        "home",
        "improvement"
    ],
    "wof:name":"Andy Oncall Tri Cities",
    "wof:placetype":"venue"
},
  "geometry": {"coordinates":[-82.474071,36.410475],"type":"Point"}
}