{
  "type": "Feature",
  "properties": {
    "addr:full":"2828 Trousdale Ferry Pike Lebanon TN 37087",
    "addr:housenumber":"2828",
    "addr:postcode":"37087",
    "addr:street":"Trousdale Ferry Pike",
    "iso:country":"US",
    "sg:address":"2828 Trousdale Ferry Pike",
    "sg:city":"Lebanon",
    "sg:classifiers":[
        {
            "category":"Farming",
            "subcategory":"Livestock Farm",
            "type":"Manufacturing & Wholesale Goods"
        }
    ],
    "sg:phone":"+1 615 444 3685",
    "sg:postcode":"37087",
    "sg:province":"TN",
    "sg:tags":[
        "beef",
        "tobacco",
        "crop",
        "field",
        "cattle",
        "feedlot"
    ],
    "wof:name":"Billy McDaniel",
    "wof:placetype":"venue"
},
  "geometry": {"coordinates":[-86.22643600000001,36.207085],"type":"Point"}
}