{
  "type": "Feature",
  "properties": {
    "iso:country":"US",
    "sg:address":"3845 Shiloh Adamsville Rd",
    "sg:city":"Stantonville",
    "sg:classifiers":[
        {
            "category":"Wholesale",
            "subcategory":"Machinery & Supplies",
            "type":"Manufacturing & Wholesale Goods"
        }
    ],
    "sg:phone":"+1 731 632 3608",
    "sg:postcode":"38379",
    "sg:province":"TN",
    "sg:tags":[
        "equipment",
        "industrial"
    ],
    "wof:name":"D and C Equipment",
    "wof:placetype":"venue"
},
  "geometry": {"coordinates":[-88.391533,35.179698],"type":"Point"}
}