{
  "type": "Feature",
  "properties": {
    "addr:full":"6570 Stage Rd Memphis TN 38134",
    "addr:housenumber":"6570",
    "addr:postcode":"38134",
    "addr:street":"Stage Rd",
    "iso:country":"US",
    "sg:address":"6570 Stage Rd",
    "sg:city":"Memphis",
    "sg:classifiers":[
        {
            "category":"Health Services",
            "subcategory":"Doctor",
            "type":"Services"
        }
    ],
    "sg:phone":"+1 901 372 4418",
    "sg:postcode":"38134",
    "sg:province":"TN",
    "sg:tags":[
        "physician",
        "surgeon"
    ],
    "wof:name":"Ob/Gyn Physicians Of Memphis",
    "wof:placetype":"venue"
},
  "geometry": {"coordinates":[-89.84450699999999,35.204723],"type":"Point"}
}