{
  "type": "Feature",
  "properties": {
    "iso:country":"US",
    "sg:address":"1491 Riverside Dr",
    "sg:city":"Chattanooga",
    "sg:classifiers":[
        {
            "category":"Organizations",
            "subcategory":"Community Association",
            "type":"Services"
        }
    ],
    "sg:phone":"+1 423 624 6687",
    "sg:postcode":"37406",
    "sg:province":"TN",
    "sg:tags":[
        "military"
    ],
    "sg:website":"www.vfw.org",
    "wof:name":"Veterans Of Foreign Wars",
    "wof:placetype":"venue"
},
  "geometry": {"coordinates":[-85.28104,35.055802],"type":"Point"}
}