{
  "type": "Feature",
  "properties": {
    "iso:country":"US",
    "sg:address":"112 Hawkins Ct Cir",
    "sg:city":"Carthage",
    "sg:classifiers":[
        {
            "category":"Wholesale",
            "subcategory":"Metals & Minerals",
            "type":"Manufacturing & Wholesale Goods"
        }
    ],
    "sg:phone":"+1 615 735 1798",
    "sg:postcode":"37030",
    "sg:province":"TN",
    "sg:tags":[
        "aluminum"
    ],
    "wof:name":"Tri Star Aluminum",
    "wof:placetype":"venue"
},
  "geometry": {"coordinates":[-85.94835,36.24576],"type":"Point"}
}