{
  "type": "Feature",
  "properties": {
    "iso:country":"US",
    "sg:address":"313 Beatress Cir",
    "sg:city":"Rockford",
    "sg:classifiers":[
        {
            "category":"Professional",
            "type":"Services"
        }
    ],
    "sg:phone":"+1 865 681 3479",
    "sg:postcode":"37853",
    "sg:province":"TN",
    "wof:name":"David E Wells",
    "wof:placetype":"venue"
},
  "geometry": {"coordinates":[-83.94894499999999,35.826239],"type":"Point"}
}