{
  "type": "Feature",
  "properties": {
    "iso:country":"US",
    "sg:address":"546 W Shelby Dr",
    "sg:city":"Memphis",
    "sg:classifiers":[
        {
            "category":"Organizations",
            "subcategory":"Religious Organization",
            "type":"Services"
        }
    ],
    "sg:phone":"+1 901 785 4673",
    "sg:postcode":"38109",
    "sg:province":"TN",
    "wof:name":"Progressive Life",
    "wof:placetype":"venue"
},
  "geometry": {"coordinates":[-90.08144900000001,35.020977],"type":"Point"}
}