{
  "type": "Feature",
  "properties": {
    "addr:full":"131 Callis Rd Linden TN 37090",
    "addr:housenumber":"131",
    "addr:postcode":"37090",
    "addr:street":"Callis Rd",
    "iso:country":"US",
    "sg:address":"131 Callis Rd",
    "sg:city":"Linden",
    "sg:classifiers":[
        {
            "category":"Manufacturing",
            "subcategory":"Lumber",
            "type":"Manufacturing & Wholesale Goods"
        }
    ],
    "sg:phone":"+1 931 589 5127",
    "sg:postcode":"37090",
    "sg:province":"TN",
    "sg:tags":[
        "mill"
    ],
    "wof:name":"Hensley Brothers",
    "wof:placetype":"venue"
},
  "geometry": {"coordinates":[-86.423885,36.169707],"type":"Point"}
}