{
  "type": "Feature",
  "properties": {
    "iso:country":"US",
    "sg:address":"1015 N Main Ave",
    "sg:city":"Erwin",
    "sg:classifiers":[
        {
            "category":"Retail",
            "subcategory":"Funeral Services",
            "type":"Services"
        }
    ],
    "sg:phone":"+1 423 743 1390",
    "sg:postcode":"37650",
    "sg:province":"TN",
    "sg:tags":[
        "director"
    ],
    "wof:name":"Erwin Memorial Funeral Home",
    "wof:placetype":"venue"
},
  "geometry": {"coordinates":[-82.405982,36.156423],"type":"Point"}
}