{
  "type": "Feature",
  "properties": {
    "iso:country":"US",
    "sg:address":"912 Watts Cir",
    "sg:city":"Nashville",
    "sg:classifiers":[
        {
            "category":"Retail",
            "subcategory":"Repair Shop",
            "type":"Services"
        }
    ],
    "sg:phone":"+1 615 353 0518",
    "sg:postcode":"37209",
    "sg:province":"TN",
    "wof:name":"Chongs Cleaning Co",
    "wof:placetype":"venue"
},
  "geometry": {"coordinates":[-86.871396,36.143341],"type":"Point"}
}