{
  "type": "Feature",
  "properties": {
    "iso:country":"US",
    "sg:address":"9146 State Hwy 49 E",
    "sg:city":"Orlinda",
    "sg:classifiers":[
        {
            "category":"Government",
            "subcategory":"Fire Station",
            "type":"Public Place"
        }
    ],
    "sg:phone":"+1 615 654 2389",
    "sg:postcode":"37141",
    "sg:province":"TN",
    "sg:tags":[
        "department",
        "protection"
    ],
    "wof:name":"Orlinda Fire Department",
    "wof:placetype":"venue"
},
  "geometry": {"coordinates":[-86.71590999999999,36.601397],"type":"Point"}
}