{
  "type": "Feature",
  "properties": {
    "addr:full":"1309 Bruceville Slab Rd Dyersburg TN 38024",
    "addr:housenumber":"1309",
    "addr:postcode":"38024",
    "addr:street":"Bruceville Slab Rd",
    "iso:country":"US",
    "sg:address":"1309 Bruceville Slab Rd",
    "sg:city":"Dyersburg",
    "sg:classifiers":[
        {
            "category":"Building & Trades",
            "subcategory":"Construction",
            "type":"Services"
        }
    ],
    "sg:phone":"+1 731 286 6667",
    "sg:postcode":"38024",
    "sg:province":"TN",
    "sg:tags":[
        "hanging",
        "contractor"
    ],
    "wof:name":"Rushing Paving",
    "wof:placetype":"venue"
},
  "geometry": {"coordinates":[-89.36607600000001,35.933429],"type":"Point"}
}