{
  "type": "Feature",
  "properties": {
    "iso:country":"US",
    "sg:address":"3449 Bradyville Pike",
    "sg:city":"Murfreesboro",
    "sg:classifiers":[
        {
            "category":"Building & Trades",
            "subcategory":"Landscaping Services",
            "type":"Services"
        }
    ],
    "sg:phone":"+1 615 896 8750",
    "sg:postcode":"37127",
    "sg:province":"TN",
    "wof:name":"Malone Gardens & Landscapes",
    "wof:placetype":"venue"
},
  "geometry": {"coordinates":[-86.32369799999999,35.801049],"type":"Point"}
}