{
  "type": "Feature",
  "properties": {
    "addr:full":"5569 Hwy 31 W Portland TN 37148",
    "addr:housenumber":"5569",
    "addr:postcode":"37148",
    "addr:street":"Hwy 31 W",
    "iso:country":"US",
    "sg:address":"5569 Hwy 31 W",
    "sg:city":"Portland",
    "sg:classifiers":[
        {
            "category":"Freight",
            "type":"Transportation"
        }
    ],
    "sg:phone":"+1 615 323 0720",
    "sg:postcode":"37148",
    "sg:province":"TN",
    "sg:tags":[
        "operator",
        "trucking"
    ],
    "sg:website":"www.baylortrucking.com",
    "wof:name":"Baylor Trucking",
    "wof:placetype":"venue"
},
  "geometry": {"coordinates":[-86.579117,36.609597],"type":"Point"}
}