{
  "type": "Feature",
  "properties": {
    "iso:country":"US",
    "sg:address":"2413 E Lamar Alexander Pkwy",
    "sg:city":"Maryville",
    "sg:classifiers":[
        {
            "category":"Autos & Motor Vehicles",
            "subcategory":"Automobile Sales",
            "type":"Retail Goods"
        },
        {
            "category":"Retail",
            "subcategory":"Auto Repair",
            "type":"Services"
        }
    ],
    "sg:phone":"+1 865 681 0434",
    "sg:postcode":"37804",
    "sg:province":"TN",
    "sg:tags":[
        "automotive",
        "dealer",
        "car"
    ],
    "wof:name":"Parkway Automotive",
    "wof:placetype":"venue"
},
  "geometry": {"coordinates":[-83.936825,35.755839],"type":"Point"}
}