{
  "type": "Feature",
  "properties": {
    "addr:full":"725 Buckhorn Rd Gatlinburg TN 37738",
    "addr:housenumber":"725",
    "addr:postcode":"37738",
    "addr:street":"Buckhorn Rd",
    "iso:country":"US",
    "sg:address":"725 Buckhorn Rd",
    "sg:city":"Gatlinburg",
    "sg:classifiers":[
        {
            "category":"Shopping",
            "type":"Retail Goods"
        }
    ],
    "sg:phone":"+1 865 436 0789",
    "sg:postcode":"37738",
    "sg:province":"TN",
    "sg:tags":[
        "merchandise"
    ],
    "wof:name":"Art For God",
    "wof:placetype":"venue"
},
  "geometry": {"coordinates":[-83.43828999999999,35.756738],"type":"Point"}
}