{
  "type": "Feature",
  "properties": {
    "iso:country":"US",
    "sg:address":"1107 Lakeview Dr",
    "sg:city":"Franklin",
    "sg:classifiers":[
        {
            "category":"Insurance",
            "subcategory":"Insurance Agent",
            "type":"Services"
        }
    ],
    "sg:phone":"+1 615 599 9935",
    "sg:postcode":"37067",
    "sg:province":"TN",
    "wof:name":"The Robinson Agency",
    "wof:placetype":"venue"
},
  "geometry": {"coordinates":[-86.82490799999999,35.920446],"type":"Point"}
}