{
  "type": "Feature",
  "properties": {
    "iso:country":"US",
    "sg:address":"2993 Vanguard Dr",
    "sg:city":"Memphis",
    "sg:classifiers":[
        {
            "category":"Travel",
            "subcategory":"Hotels & Motels",
            "type":"Entertainment"
        }
    ],
    "sg:phone":"+1 901 348 0207",
    "sg:postcode":"38131",
    "sg:province":"TN",
    "sg:website":"http://www.studioplus.com",
    "wof:name":"StudioPlus",
    "wof:placetype":"venue"
},
  "geometry": {"coordinates":[-89.99468899999999,35.065978],"type":"Point"}
}