{
  "type": "Feature",
  "properties": {
    "iso:country":"US",
    "sg:address":"5800 Challenge Dr",
    "sg:city":"Memphis",
    "sg:classifiers":[
        {
            "category":"Professional",
            "subcategory":"Employment Agencies",
            "type":"Services"
        }
    ],
    "sg:phone":"+1 901 795 5126",
    "sg:postcode":"38115",
    "sg:province":"TN",
    "sg:tags":[
        "help",
        "contractor"
    ],
    "wof:name":"Randstad",
    "wof:placetype":"venue"
},
  "geometry": {"coordinates":[-89.870216,35.039737],"type":"Point"}
}