{
  "type": "Feature",
  "properties": {
    "addr:full":"4419 HIGHWAY 58 STE 1 CHATTANOOGA TN 37416",
    "addr:housenumber":"4419",
    "addr:postcode":"37416",
    "addr:street":"Highway 58 Ste 1",
    "iso:country":"US",
    "sg:address":"4419 HIGHWAY 58 STE 1",
    "sg:city":"CHATTANOOGA",
    "sg:classifiers":[
        {
            "category":"Home & Garden",
            "subcategory":"Household Appliances",
            "type":"Retail Goods"
        },
        {
            "category":"Communications",
            "subcategory":"Radio Station",
            "type":"Services"
        },
        {
            "category":"Shopping",
            "subcategory":"Computers & Home Electronics",
            "type":"Retail Goods"
        },
        {
            "category":"Home & Garden",
            "subcategory":"Furniture",
            "type":"Retail Goods"
        }
    ],
    "sg:phone":"+1 423 208 9167",
    "sg:postcode":"37416",
    "sg:province":"TN",
    "sg:tags":[
        "renting",
        "television",
        "leasing",
        "radio-renting",
        "equipment",
        "rental"
    ],
    "sg:website":"http://www.rentacenter.com/",
    "wof:name":"Rent-A-Center",
    "wof:placetype":"venue"
},
  "geometry": {"coordinates":[-85.201364,35.084351],"type":"Point"}
}