{
  "type": "Feature",
  "properties": {
    "iso:country":"US",
    "sg:address":"339 Main St",
    "sg:city":"Franklin",
    "sg:classifiers":[
        {
            "category":"Professional",
            "subcategory":"Lawyer & Legal Services",
            "type":"Services"
        }
    ],
    "sg:phone":"+1 615 794 0807",
    "sg:postcode":"37064",
    "sg:province":"TN",
    "sg:tags":[
        "attorney"
    ],
    "wof:name":"Fox Johnston & Taylor",
    "wof:placetype":"venue"
},
  "geometry": {"coordinates":[-86.8695,35.92483],"type":"Point"}
}