{
  "type": "Feature",
  "properties": {
    "iso:country":"US",
    "sg:address":"390 Main St",
    "sg:city":"Savannah",
    "sg:classifiers":[
        {
            "category":"Restaurant",
            "type":"Food & Drink"
        }
    ],
    "sg:phone":"+1 731 926 1911",
    "sg:postcode":"38372",
    "sg:province":"TN",
    "wof:name":"Uptown",
    "wof:placetype":"venue"
},
  "geometry": {"coordinates":[-88.25167999999999,35.22516],"type":"Point"}
}