{
  "type": "Feature",
  "properties": {
    "iso:country":"US",
    "sg:address":"104 Timber Creek Dr",
    "sg:city":"Cordova",
    "sg:classifiers":[
        {
            "category":"Organizations",
            "subcategory":"Professional Association",
            "type":"Services"
        }
    ],
    "sg:phone":"+1 901 682 0800",
    "sg:postcode":"38018",
    "sg:province":"TN",
    "sg:website":"www.cottonseed.com",
    "wof:name":"National Cottonseed Products",
    "wof:placetype":"venue"
},
  "geometry": {"coordinates":[-89.79323599999999,35.129248],"type":"Point"}
}