{
  "type": "Feature",
  "properties": {
    "iso:country":"US",
    "sg:address":"508 Roberts Mill Rd",
    "sg:city":"Hixson",
    "sg:classifiers":[
        {
            "category":"Shopping",
            "subcategory":"Florist",
            "type":"Retail Goods"
        }
    ],
    "sg:phone":"+1 423 842 4927",
    "sg:postcode":"37343",
    "sg:province":"TN",
    "wof:name":"Flowers By Smith",
    "wof:placetype":"venue"
},
  "geometry": {"coordinates":[-85.254544,35.200239],"type":"Point"}
}