{
  "type": "Feature",
  "properties": {
    "addr:full":"134 College St E Fayetteville TN 37334",
    "addr:housenumber":"134",
    "addr:postcode":"37334",
    "addr:street":"College St E",
    "iso:country":"US",
    "sg:address":"134 College St E",
    "sg:city":"Fayetteville",
    "sg:classifiers":[
        {
            "category":"Shopping",
            "subcategory":"Jewelry",
            "type":"Retail Goods"
        }
    ],
    "sg:phone":"+1 931 433 1058",
    "sg:postcode":"37334",
    "sg:province":"TN",
    "wof:name":"Wishing Well",
    "wof:placetype":"venue"
},
  "geometry": {"coordinates":[-86.570138,35.152275],"type":"Point"}
}