{
  "type": "Feature",
  "properties": {
    "iso:country":"US",
    "sg:address":"3110 Jenkinsville-Jamestown Rd",
    "sg:city":"Dyersburg",
    "sg:classifiers":[
        {
            "category":"Building & Trades",
            "subcategory":"Construction",
            "type":"Services"
        }
    ],
    "sg:phone":"+1 731 286 2013",
    "sg:postcode":"38024",
    "sg:province":"TN",
    "sg:tags":[
        "house"
    ],
    "wof:name":"Hart Construction John",
    "wof:placetype":"venue"
},
  "geometry": {"coordinates":[-89.416712,36.076725],"type":"Point"}
}