{
  "type": "Feature",
  "properties": {
    "addr:full":"359 US Hwy 70 Mason TN 38049",
    "addr:housenumber":"359",
    "addr:postcode":"38049",
    "addr:street":"Us Hwy 70",
    "iso:country":"US",
    "sg:address":"359 US Hwy 70",
    "sg:city":"Mason",
    "sg:classifiers":[
        {
            "category":"Organizations",
            "subcategory":"Religious Organization",
            "type":"Services"
        }
    ],
    "sg:phone":"+1 901 294 3597",
    "sg:postcode":"38049",
    "sg:province":"TN",
    "sg:tags":[
        "church"
    ],
    "wof:name":"First Baptist Church Of Mason",
    "wof:placetype":"venue"
},
  "geometry": {"coordinates":[-89.536833,35.411821],"type":"Point"}
}