{
  "type": "Feature",
  "properties": {
    "iso:country":"US",
    "sg:address":"1239 Huntsville Hwy",
    "sg:city":"Fayetteville",
    "sg:classifiers":[
        {
            "category":"Restaurant",
            "type":"Food & Drink"
        }
    ],
    "sg:menulink":"http://www.allmenus.com/tn/fayetteville/246229-krystal/menu/",
    "sg:phone":"+1 931 433 0742",
    "sg:postcode":"37334",
    "sg:province":"TN",
    "sg:tags":[
        "burger",
        "american"
    ],
    "wof:name":"Krystal",
    "wof:placetype":"venue"
},
  "geometry": {"coordinates":[-86.566596,35.132546],"type":"Point"}
}