{
  "type": "Feature",
  "properties": {
    "iso:country":"US",
    "sg:address":"408 W College St",
    "sg:city":"Dickson",
    "sg:classifiers":[
        {
            "category":"Insurance",
            "subcategory":"Insurance Agent",
            "type":"Services"
        }
    ],
    "sg:phone":"+1 615 446 3303",
    "sg:postcode":"37055",
    "sg:province":"TN",
    "wof:name":"Morrison Fuson Smith & White",
    "wof:placetype":"venue"
},
  "geometry": {"coordinates":[-87.391527,36.08002],"type":"Point"}
}