{
  "type": "Feature",
  "properties": {
    "iso:country":"US",
    "sg:address":"7305 Derris Dr SW",
    "sg:city":"Knoxville",
    "sg:classifiers":[
        {
            "category":"Building & Trades",
            "subcategory":"Landscaping Services",
            "type":"Services"
        }
    ],
    "sg:phone":"+1 865 691 0286",
    "sg:postcode":"37919",
    "sg:province":"TN",
    "wof:name":"Vanaman Landscaping",
    "wof:placetype":"venue"
},
  "geometry": {"coordinates":[-84.005996,35.895304],"type":"Point"}
}