{
  "type": "Feature",
  "properties": {
    "iso:country":"US",
    "sg:address":"159 Central Ave",
    "sg:city":"Crossville",
    "sg:classifiers":[
        {
            "category":"Retail",
            "subcategory":"Car Wash",
            "type":"Services"
        }
    ],
    "sg:phone":"+1 931 707 7481",
    "sg:postcode":"38555",
    "sg:province":"TN",
    "sg:tags":[
        "automobile",
        "detail",
        "clean"
    ],
    "wof:name":"Simmons Detail Crome Shop",
    "wof:placetype":"venue"
},
  "geometry": {"coordinates":[-85.035624,35.953453],"type":"Point"}
}