{
  "type": "Feature",
  "properties": {
    "iso:country":"US",
    "sg:address":"11007 Thornton Dr",
    "sg:city":"Knoxville",
    "sg:classifiers":[
        {
            "category":"Communications",
            "subcategory":"Film & Video Production",
            "type":"Services"
        }
    ],
    "sg:phone":"+1 865 966 5576",
    "sg:postcode":"37934",
    "sg:province":"TN",
    "sg:tags":[
        "motion"
    ],
    "wof:name":"2 Bad Productions",
    "wof:placetype":"venue"
},
  "geometry": {"coordinates":[-84.149084,35.879002],"type":"Point"}
}