{
  "type": "Feature",
  "properties": {
    "iso:country":"US",
    "sg:address":"973 McEvers Rd",
    "sg:city":"Memphis",
    "sg:classifiers":[
        {
            "category":"Professional",
            "subcategory":"Business Services",
            "type":"Services"
        }
    ],
    "sg:phone":"+1 901 323 7350",
    "sg:postcode":"38111",
    "sg:province":"TN",
    "wof:name":"Property Solutions LLC",
    "wof:placetype":"venue"
},
  "geometry": {"coordinates":[-89.933627,35.104644],"type":"Point"}
}