{
  "type": "Feature",
  "properties": {
    "addr:full":"6483 Farnell Ave Memphis TN 38134",
    "addr:housenumber":"6483",
    "addr:postcode":"38134",
    "addr:street":"Farnell Ave",
    "iso:country":"US",
    "sg:address":"6483 Farnell Ave",
    "sg:city":"Memphis",
    "sg:classifiers":[
        {
            "category":"Real Estate",
            "subcategory":"Real Estate Agent",
            "type":"Services"
        }
    ],
    "sg:phone":"+1 901 384 0123",
    "sg:postcode":"38134",
    "sg:province":"TN",
    "sg:tags":[
        "inspection"
    ],
    "wof:name":"All American Home Inspections",
    "wof:placetype":"venue"
},
  "geometry": {"coordinates":[-89.84662,35.210279],"type":"Point"}
}