{
  "type": "Feature",
  "properties": {
    "iso:country":"US",
    "sg:address":"2203 Nave Dr",
    "sg:city":"Johnson City",
    "sg:classifiers":[
        {
            "category":"Building & Trades",
            "subcategory":"Cleaning & Sanitation",
            "type":"Services"
        }
    ],
    "sg:phone":"+1 423 282 9750",
    "sg:postcode":"37601",
    "sg:province":"TN",
    "sg:tags":[
        "janitor"
    ],
    "wof:name":"Professional Touch Cleaning",
    "wof:placetype":"venue"
},
  "geometry": {"coordinates":[-82.36513100000001,36.349533],"type":"Point"}
}