{
  "type": "Feature",
  "properties": {
    "iso:country":"US",
    "sg:address":"1420 E Stone Dr",
    "sg:city":"Kingsport",
    "sg:classifiers":[
        {
            "category":"Banks & Credit Unions",
            "subcategory":"Bank",
            "type":"Services"
        }
    ],
    "sg:phone":"+1 423 245 0505",
    "sg:postcode":"37660",
    "sg:province":"TN",
    "sg:tags":[
        "loan",
        "real estate"
    ],
    "wof:name":"Tri Cities Mortgage LLC",
    "wof:placetype":"venue"
},
  "geometry": {"coordinates":[-82.520578,36.548734],"type":"Point"}
}