{
  "type": "Feature",
  "properties": {
    "iso:country":"US",
    "sg:address":"1947 Alder Branch Ln",
    "sg:city":"Germantown",
    "sg:classifiers":[
        {
            "category":"Building & Trades",
            "subcategory":"Construction",
            "type":"Services"
        }
    ],
    "sg:phone":"+1 901 737 0298",
    "sg:postcode":"38139",
    "sg:province":"TN",
    "sg:tags":[
        "house"
    ],
    "wof:name":"REO Services",
    "wof:placetype":"venue"
},
  "geometry": {"coordinates":[-89.77331599999999,35.094423],"type":"Point"}
}