{
  "type": "Feature",
  "properties": {
    "addr:full":"501 S Valley View Cir Kingsport TN 37664",
    "addr:housenumber":"501",
    "addr:postcode":"37664",
    "addr:street":"S Valley View Cir",
    "iso:country":"US",
    "sg:address":"501 S Valley View Cir",
    "sg:city":"Kingsport",
    "sg:classifiers":[
        {
            "category":"Retail",
            "subcategory":"Repair Shop",
            "type":"Services"
        }
    ],
    "sg:phone":"+1 423 323 8956",
    "sg:postcode":"37664",
    "sg:province":"TN",
    "wof:name":"Keith Jounston Lawn Mower",
    "wof:placetype":"venue"
},
  "geometry": {"coordinates":[-82.42744399999999,36.535713],"type":"Point"}
}