{
  "type": "Feature",
  "properties": {
    "iso:country":"US",
    "sg:address":"325 Gill St",
    "sg:city":"Alcoa",
    "sg:classifiers":[
        {
            "category":"Home & Garden",
            "subcategory":"Home Furnishings",
            "type":"Retail Goods"
        }
    ],
    "sg:phone":"+1 865 681 6870",
    "sg:postcode":"37701",
    "sg:province":"TN",
    "wof:name":"Added Ingredients",
    "wof:placetype":"venue"
},
  "geometry": {"coordinates":[-83.97377299999999,35.760732],"type":"Point"}
}