{
  "type": "Feature",
  "properties": {
    "iso:country":"US",
    "sg:address":"1657 Rising View Ln",
    "sg:city":"Knoxville",
    "sg:classifiers":[
        {
            "category":"Insurance",
            "subcategory":"Title Insurance",
            "type":"Services"
        }
    ],
    "sg:phone":"+1 865 777 5278",
    "sg:postcode":"37922",
    "sg:province":"TN",
    "sg:tags":[
        "agency"
    ],
    "wof:name":"American Mortgage Closers LLC",
    "wof:placetype":"venue"
},
  "geometry": {"coordinates":[-84.086454,35.861537],"type":"Point"}
}