{
  "type": "Feature",
  "properties": {
    "iso:country":"US",
    "sg:address":"288 Dandridge Dr",
    "sg:city":"Franklin",
    "sg:classifiers":[
        {
            "category":"Shopping",
            "subcategory":"Clothing, Apparel, & Fashions",
            "type":"Retail Goods"
        }
    ],
    "sg:phone":"+1 615 591 8605",
    "sg:postcode":"37067",
    "sg:province":"TN",
    "sg:tags":[
        "wear"
    ],
    "wof:name":"Hadley Eric & Leslie Inc",
    "wof:placetype":"venue"
},
  "geometry": {"coordinates":[-86.817355,35.9039],"type":"Point"}
}