{
  "type": "Feature",
  "properties": {
    "iso:country":"US",
    "sg:address":"12740 Kingston Pike",
    "sg:city":"Knoxville",
    "sg:classifiers":[
        {
            "category":"Real Estate",
            "subcategory":"Real Estate Agent",
            "type":"Services"
        }
    ],
    "sg:phone":"+1 865 966 9700",
    "sg:postcode":"37934",
    "sg:province":"TN",
    "wof:name":"Cornerstone Realty Assoc LLC",
    "wof:placetype":"venue"
},
  "geometry": {"coordinates":[-84.20871,35.867618],"type":"Point"}
}