{
  "type": "Feature",
  "properties": {
    "iso:country":"US",
    "sg:address":"4800 Nevada Ave",
    "sg:city":"Nashville",
    "sg:classifiers":[
        {
            "category":"Organizations",
            "subcategory":"Community Association",
            "type":"Services"
        }
    ],
    "sg:phone":"+1 615 298 1436",
    "sg:postcode":"37209",
    "sg:province":"TN",
    "sg:tags":[
        "book",
        "telephone"
    ],
    "wof:name":"Mostly Mystery",
    "wof:placetype":"venue"
},
  "geometry": {"coordinates":[-86.845799,36.14859],"type":"Point"}
}