{
  "type": "Feature",
  "properties": {
    "iso:country":"US",
    "sg:address":"116 Main St",
    "sg:city":"Lafayette",
    "sg:classifiers":[
        {
            "category":"Professional",
            "subcategory":"Lawyer & Legal Services",
            "type":"Services"
        }
    ],
    "sg:phone":"+1 615 666 6887",
    "sg:postcode":"37083",
    "sg:province":"TN",
    "wof:name":"Cothrnstnnett Lisa Atty At Law",
    "wof:placetype":"venue"
},
  "geometry": {"coordinates":[-86.024964,36.521621],"type":"Point"}
}