{
  "type": "Feature",
  "properties": {
    "iso:country":"US",
    "sg:address":"219 N 1st St",
    "sg:city":"La Follette",
    "sg:classifiers":[
        {
            "category":"Manufacturing",
            "subcategory":"Metals",
            "type":"Manufacturing & Wholesale Goods"
        }
    ],
    "sg:phone":"+1 423 562 5854",
    "sg:postcode":"37766",
    "sg:province":"TN",
    "sg:tags":[
        "fabricator",
        "sheet"
    ],
    "sg:website":"www.lafollettemachine.com",
    "wof:name":"LA Follette Machine & Tool Co",
    "wof:placetype":"venue"
},
  "geometry": {"coordinates":[-84.123305,36.383858],"type":"Point"}
}