{
  "type": "Feature",
  "properties": {
    "addr:full":"1445 Beddington Park Nashville TN 37215",
    "addr:housenumber":"1445",
    "addr:postcode":"37215",
    "addr:street":"Beddington Park",
    "iso:country":"US",
    "sg:address":"1445 Beddington Park",
    "sg:city":"Nashville",
    "sg:classifiers":[
        {
            "category":"Professional",
            "subcategory":"Business Services",
            "type":"Services"
        }
    ],
    "sg:phone":"+1 615 345 3462",
    "sg:postcode":"37215",
    "sg:province":"TN",
    "wof:name":"Norma Tillman Enterprises",
    "wof:placetype":"venue"
},
  "geometry": {"coordinates":[-86.829072,36.056917],"type":"Point"}
}