{
  "type": "Feature",
  "properties": {
    "iso:country":"US",
    "sg:address":"129 Confederate Dr",
    "sg:city":"Franklin",
    "sg:classifiers":[
        {
            "category":"Manufacturing",
            "subcategory":"Tools & Machinery",
            "type":"Manufacturing & Wholesale Goods"
        }
    ],
    "sg:phone":"+1 615 794 4556",
    "sg:postcode":"37064",
    "sg:province":"TN",
    "sg:tags":[
        "construction"
    ],
    "sg:website":"www.mantiscranes.com",
    "wof:name":"Spandeck Inc",
    "wof:placetype":"venue"
},
  "geometry": {"coordinates":[-86.870755,35.904473],"type":"Point"}
}