{
  "type": "Feature",
  "properties": {
    "addr:full":"1324 Getwell Rd Memphis TN 38111",
    "addr:housenumber":"1324",
    "addr:postcode":"38111",
    "addr:street":"Getwell Rd",
    "iso:country":"US",
    "sg:address":"1324 Getwell Rd",
    "sg:city":"Memphis",
    "sg:classifiers":[
        {
            "category":"Retail",
            "subcategory":"Self-service Laundry",
            "type":"Services"
        }
    ],
    "sg:phone":"+1 901 428 4991",
    "sg:postcode":"38111",
    "sg:province":"TN",
    "sg:tags":[
        "coin"
    ],
    "wof:name":"Laundry Company Inc",
    "wof:placetype":"venue"
},
  "geometry": {"coordinates":[-89.930898,35.095258],"type":"Point"}
}