{
  "type": "Feature",
  "properties": {
    "iso:country":"US",
    "sg:address":"26 Century Blvd",
    "sg:city":"Nashville",
    "sg:classifiers":[
        {
            "category":"Professional",
            "subcategory":"Detective & Security Services",
            "type":"Services"
        }
    ],
    "sg:phone":"+1 615 883 9874",
    "sg:postcode":"37214",
    "sg:province":"TN",
    "sg:tags":[
        "car"
    ],
    "wof:name":"Security Office",
    "wof:placetype":"venue"
},
  "geometry": {"coordinates":[-86.685861,36.147776],"type":"Point"}
}