{
  "type": "Feature",
  "properties": {
    "iso:country":"US",
    "sg:address":"2772 Florence Dr",
    "sg:city":"Pigeon Forge",
    "sg:classifiers":[
        {
            "category":"Restaurant",
            "type":"Food & Drink"
        }
    ],
    "sg:phone":"+1 865 428 1823",
    "sg:postcode":"37863",
    "sg:province":"TN",
    "wof:name":"Collier Development Restaurant",
    "wof:placetype":"venue"
},
  "geometry": {"coordinates":[-83.57267400000001,35.799942],"type":"Point"}
}