{
  "type": "Feature",
  "properties": {
    "iso:country":"US",
    "sg:address":"780 Rivergate Meadows Dr",
    "sg:city":"Goodlettsville",
    "sg:classifiers":[
        {
            "category":"Wholesale",
            "subcategory":"Stationery",
            "type":"Manufacturing & Wholesale Goods"
        }
    ],
    "sg:phone":"+1 615 859 3007",
    "sg:postcode":"37072",
    "sg:province":"TN",
    "sg:tags":[
        "school",
        "supply"
    ],
    "wof:name":"Parent-Teacher Store",
    "wof:placetype":"venue"
},
  "geometry": {"coordinates":[-86.708991,36.297368],"type":"Point"}
}