{
  "type": "Feature",
  "properties": {
    "iso:country":"US",
    "sg:address":"817 19th St",
    "sg:city":"Knoxville",
    "sg:classifiers":[
        {
            "category":"Real Estate",
            "subcategory":"Real Estate Agent",
            "type":"Services"
        }
    ],
    "sg:phone":"+1 865 546 6688",
    "sg:postcode":"37916",
    "sg:province":"TN",
    "wof:name":"First KNOX Realty",
    "wof:placetype":"venue"
},
  "geometry": {"coordinates":[-83.93561800000001,35.954406],"type":"Point"}
}