{
  "type": "Feature",
  "properties": {
    "iso:country":"US",
    "sg:address":"2443 Sawmill St",
    "sg:city":"Murfreesboro",
    "sg:classifiers":[
        {
            "category":"Professional",
            "subcategory":"Business Services",
            "type":"Services"
        }
    ],
    "sg:phone":"+1 615 867 7118",
    "sg:postcode":"37128",
    "sg:province":"TN",
    "sg:tags":[
        "pressure",
        "washing"
    ],
    "wof:name":"Drakes Pressure Washing",
    "wof:placetype":"venue"
},
  "geometry": {"coordinates":[-86.44080099999999,35.820873],"type":"Point"}
}