{
  "type": "Feature",
  "properties": {
    "iso:country":"US",
    "sg:address":"253 Ridgewood Dr",
    "sg:city":"Mc Minnville",
    "sg:classifiers":[
        {
            "category":"Home & Garden",
            "subcategory":"Garden Supply",
            "type":"Retail Goods"
        }
    ],
    "sg:phone":"+1 931 815 9455",
    "sg:postcode":"37110",
    "sg:province":"TN",
    "sg:tags":[
        "nurseryman"
    ],
    "wof:name":"Ridgewood Farms",
    "wof:placetype":"venue"
},
  "geometry": {"coordinates":[-85.73205299999999,35.580769],"type":"Point"}
}