{
  "type": "Feature",
  "properties": {
    "iso:country":"US",
    "sg:address":"229 Carriage Dr",
    "sg:city":"Nashville",
    "sg:classifiers":[
        {
            "category":"Building & Trades",
            "subcategory":"Construction",
            "type":"Services"
        }
    ],
    "sg:phone":"+1 615 456 7983",
    "sg:postcode":"37221",
    "sg:province":"TN",
    "sg:tags":[
        "contractor"
    ],
    "wof:name":"Donnelly Timmons & Assoc Inc",
    "wof:placetype":"venue"
},
  "geometry": {"coordinates":[-86.94150999999999,36.079357],"type":"Point"}
}