{
  "type": "Feature",
  "properties": {
    "iso:country":"US",
    "sg:address":"1801 West End Avenue   Suite 910",
    "sg:city":"Nashville",
    "sg:classifiers":[
        {
            "category":"Professional",
            "subcategory":"Computer Services",
            "type":"Services"
        }
    ],
    "sg:phone":"+1 615 234 4020",
    "sg:postcode":"37203",
    "sg:province":"TN",
    "sg:website":"http://mypmcinside.com/",
    "wof:name":"Premier Micronutrient Corporation",
    "wof:placetype":"venue"
},
  "geometry": {"coordinates":[-86.79745,36.1523],"type":"Point"}
}