{
  "type": "Feature",
  "properties": {
    "iso:country":"US",
    "sg:address":"303 S Tarver Ave",
    "sg:city":"Lebanon",
    "sg:classifiers":[
        {
            "category":"Building & Trades",
            "subcategory":"Construction",
            "type":"Services"
        }
    ],
    "sg:phone":"+1 615 449 1205",
    "sg:postcode":"37087",
    "sg:province":"TN",
    "sg:tags":[
        "hanging",
        "contractor"
    ],
    "wof:name":"Lee E Painter",
    "wof:placetype":"venue"
},
  "geometry": {"coordinates":[-86.30273800000001,36.202947],"type":"Point"}
}