{
  "type": "Feature",
  "properties": {
    "iso:country":"US",
    "sg:address":"119 Stonebrook Pl",
    "sg:city":"Jackson",
    "sg:classifiers":[
        {
            "category":"Shopping",
            "subcategory":"Shoes",
            "type":"Retail Goods"
        },
        {
            "category":"Shopping",
            "subcategory":"Clothing, Apparel, & Fashions",
            "type":"Retail Goods"
        }
    ],
    "sg:phone":"+1 731 654 5992",
    "sg:postcode":"38305",
    "sg:province":"TN",
    "wof:name":"Hibbett Sports",
    "wof:placetype":"venue"
},
  "geometry": {"coordinates":[-88.85621399999999,35.686149],"type":"Point"}
}