{
  "type": "Feature",
  "properties": {
    "addr:full":"710 W College St Pulaski TN 38478",
    "addr:housenumber":"710",
    "addr:postcode":"38478",
    "addr:street":"W College St",
    "iso:country":"US",
    "sg:address":"710 W College St",
    "sg:city":"Pulaski",
    "sg:classifiers":[
        {
            "category":"Retail",
            "subcategory":"Auto Repair",
            "type":"Services"
        }
    ],
    "sg:phone":"+1 931 363 5271",
    "sg:postcode":"38478",
    "sg:province":"TN",
    "sg:tags":[
        "automobile",
        "lubrication"
    ],
    "wof:name":"Texaco Xpress Lube",
    "wof:placetype":"venue"
},
  "geometry": {"coordinates":[-87.03983100000001,35.199389],"type":"Point"}
}