{
  "type": "Feature",
  "properties": {
    "iso:country":"US",
    "sg:address":"2116 Summitt Ave",
    "sg:city":"Nashville",
    "sg:classifiers":[
        {
            "category":"Shopping",
            "type":"Retail Goods"
        }
    ],
    "sg:phone":"+1 615 259 1189",
    "sg:postcode":"37218",
    "sg:province":"TN",
    "sg:tags":[
        "merchandise"
    ],
    "wof:name":"HI Tech Spy Shop",
    "wof:placetype":"venue"
},
  "geometry": {"coordinates":[-86.830454,36.198425],"type":"Point"}
}