{
  "type": "Feature",
  "properties": {
    "addr:full":"1919 Division St Nashville TN 37203",
    "addr:housenumber":"1919",
    "addr:postcode":"37203",
    "addr:street":"Division St",
    "iso:country":"US",
    "sg:address":"1919 Division St",
    "sg:city":"Nashville",
    "sg:classifiers":[
        {
            "category":"Health Services",
            "subcategory":"Health Practitioner",
            "type":"Services"
        }
    ],
    "sg:phone":"+1 615 329 0733",
    "sg:postcode":"37203",
    "sg:province":"TN",
    "wof:name":"Life Styles Ministries Inc",
    "wof:placetype":"venue"
},
  "geometry": {"coordinates":[-86.798174,36.148988],"type":"Point"}
}