{
  "type": "Feature",
  "properties": {
    "iso:country":"US",
    "sg:address":"124 College St E",
    "sg:city":"Fayetteville",
    "sg:classifiers":[
        {
            "category":"Home & Garden",
            "subcategory":"Hardware",
            "type":"Retail Goods"
        }
    ],
    "sg:phone":"+1 931 433 2205",
    "sg:postcode":"37334",
    "sg:province":"TN",
    "wof:name":"Ashby Hardware Co",
    "wof:placetype":"venue"
},
  "geometry": {"coordinates":[-86.57025,35.15229],"type":"Point"}
}