{
  "type": "Feature",
  "properties": {
    "iso:country":"US",
    "sg:address":"7663 US Hwy 70 S",
    "sg:city":"Nashville",
    "sg:classifiers":[
        {
            "category":"Shopping",
            "subcategory":"Hobbies, Toys, & Games",
            "type":"Retail Goods"
        }
    ],
    "sg:phone":"+1 615 662 2431",
    "sg:postcode":"37221",
    "sg:province":"TN",
    "wof:name":"Toys R Us",
    "wof:placetype":"venue"
},
  "geometry": {"coordinates":[-86.956227,36.081192],"type":"Point"}
}