{
  "type": "Feature",
  "properties": {
    "iso:country":"US",
    "sg:address":"2233 Elvis Presley Blvd",
    "sg:city":"Memphis",
    "sg:classifiers":[
        {
            "category":"Manufacturing",
            "subcategory":"Building Materials",
            "type":"Manufacturing & Wholesale Goods"
        }
    ],
    "sg:phone":"+1 901 309 8985",
    "sg:postcode":"38116",
    "sg:province":"TN",
    "sg:tags":[
        "mfg",
        "wood",
        "cabinet",
        "kitchen",
        "carpentry"
    ],
    "wof:name":"Blue Ribbon Cabinets",
    "wof:placetype":"venue"
},
  "geometry": {"coordinates":[-90.01856600000001,35.083304],"type":"Point"}
}