{
  "type": "Feature",
  "properties": {
    "addr:full":"2565 Winchester Rd Memphis TN 38116",
    "addr:housenumber":"2565",
    "addr:postcode":"38116",
    "addr:street":"Winchester Rd",
    "iso:country":"US",
    "sg:address":"2565 Winchester Rd",
    "sg:city":"Memphis",
    "sg:classifiers":[
        {
            "category":"Government",
            "subcategory":"Office",
            "type":"Public Place"
        }
    ],
    "sg:phone":"+1 901 332 4585",
    "sg:postcode":"38116",
    "sg:province":"TN",
    "sg:tags":[
        "township",
        "government-city",
        "village"
    ],
    "wof:name":"City Of Memphis",
    "wof:placetype":"venue"
},
  "geometry": {"coordinates":[-89.978465,35.052287],"type":"Point"}
}