{
  "type": "Feature",
  "properties": {
    "iso:country":"US",
    "sg:address":"4813 Nolensville Pike",
    "sg:city":"Nashville",
    "sg:classifiers":[
        {
            "category":"Real Estate",
            "subcategory":"Real Estate Agent",
            "type":"Services"
        }
    ],
    "sg:phone":"+1 615 331 6500",
    "sg:postcode":"37211",
    "sg:province":"TN",
    "wof:name":"Metro Realty & Insurance",
    "wof:placetype":"venue"
},
  "geometry": {"coordinates":[-86.717068,36.063347],"type":"Point"}
}