{
  "type": "Feature",
  "properties": {
    "iso:country":"US",
    "sg:address":"2807 Bransford Ave",
    "sg:city":"Nashville",
    "sg:classifiers":[
        {
            "category":"Manufacturing",
            "subcategory":"Apparel",
            "type":"Manufacturing & Wholesale Goods"
        }
    ],
    "sg:phone":"+1 615 298 3152",
    "sg:postcode":"37204",
    "sg:province":"TN",
    "sg:tags":[
        "flag",
        "banner"
    ],
    "wof:name":"A Banner Flag & Flag Pole Co",
    "wof:placetype":"venue"
},
  "geometry": {"coordinates":[-86.766924,36.113487],"type":"Point"}
}