{
  "type": "Feature",
  "properties": {
    "addr:full":"1229 Linden Hwy Hohenwald TN 38462",
    "addr:housenumber":"1229",
    "addr:postcode":"38462",
    "addr:street":"Linden Hwy",
    "iso:country":"US",
    "sg:address":"1229 Linden Hwy",
    "sg:city":"Hohenwald",
    "sg:classifiers":[
        {
            "category":"Real Estate",
            "subcategory":"Real Estate Agent",
            "type":"Services"
        }
    ],
    "sg:phone":"+1 931 796 1115",
    "sg:postcode":"38462",
    "sg:province":"TN",
    "wof:name":"Big Tree Realty",
    "wof:placetype":"venue"
},
  "geometry": {"coordinates":[-87.60292200000001,35.550733],"type":"Point"}
}