{
  "type": "Feature",
  "properties": {
    "addr:full":"2536 Una Antioch Pike Antioch TN 37013",
    "addr:housenumber":"2536",
    "addr:postcode":"37013",
    "addr:street":"Una Antioch Pike",
    "iso:country":"US",
    "sg:address":"2536 Una Antioch Pike",
    "sg:city":"Antioch",
    "sg:classifiers":[
        {
            "category":"Social Services",
            "subcategory":"Child Care",
            "type":"Services"
        }
    ],
    "sg:phone":"+1 615 833 3288",
    "sg:postcode":"37013",
    "sg:province":"TN",
    "sg:tags":[
        "day"
    ],
    "wof:name":"K9 Tender Care MBL Dog Groming",
    "wof:placetype":"venue"
},
  "geometry": {"coordinates":[-86.663945,36.062647],"type":"Point"}
}