{
  "type": "Feature",
  "properties": {
    "iso:country":"US",
    "sg:address":"5502 Hixson Pike",
    "sg:city":"Hixson",
    "sg:classifiers":[
        {
            "category":"Professional",
            "subcategory":"Management & Consulting",
            "type":"Services"
        },
        {
            "category":"Insurance",
            "subcategory":"Insurance Agent",
            "type":"Services"
        }
    ],
    "sg:phone":"+1 423 842 0321",
    "sg:postcode":"37343",
    "sg:province":"TN",
    "wof:name":"Insurance Network",
    "wof:placetype":"venue"
},
  "geometry": {"coordinates":[-85.223949,35.145154],"type":"Point"}
}