{
  "type": "Feature",
  "properties": {
    "iso:country":"US",
    "sg:address":"1949 Cordes Rd",
    "sg:city":"Germantown",
    "sg:classifiers":[
        {
            "category":"Retail",
            "subcategory":"Portrait Studio",
            "type":"Services"
        }
    ],
    "sg:phone":"+1 901 755 8174",
    "sg:postcode":"38139",
    "sg:province":"TN",
    "sg:tags":[
        "photographic"
    ],
    "wof:name":"Jim Bentley Photography",
    "wof:placetype":"venue"
},
  "geometry": {"coordinates":[-89.77669299999999,35.094245],"type":"Point"}
}