{
  "type": "Feature",
  "properties": {
    "iso:country":"US",
    "sg:address":"6800 Poplar Ave",
    "sg:city":"Germantown",
    "sg:classifiers":[
        {
            "category":"Banks & Credit Unions",
            "subcategory":"Bank",
            "type":"Services"
        }
    ],
    "sg:phone":"+1 901 759 4601",
    "sg:postcode":"38138",
    "sg:province":"TN",
    "sg:tags":[
        "loan",
        "real estate"
    ],
    "wof:name":"Trinity Mortgage Group Inc",
    "wof:placetype":"venue"
},
  "geometry": {"coordinates":[-89.836511,35.097995],"type":"Point"}
}