{
  "type": "Feature",
  "properties": {
    "iso:country":"US",
    "sg:address":"302 Maple St",
    "sg:city":"Bell Buckle",
    "sg:classifiers":[
        {
            "category":"Personal",
            "subcategory":"Beauty Salon",
            "type":"Services"
        }
    ],
    "sg:phone":"+1 931 389 6762",
    "sg:postcode":"37020",
    "sg:province":"TN",
    "wof:name":"Lynn's Clip N Style",
    "wof:placetype":"venue"
},
  "geometry": {"coordinates":[-86.35128,35.591193],"type":"Point"}
}