{
  "type": "Feature",
  "properties": {
    "addr:full":"2861 Dodge Dr Memphis TN 38128",
    "addr:housenumber":"2861",
    "addr:postcode":"38128",
    "addr:street":"Dodge Dr",
    "iso:country":"US",
    "sg:address":"2861 Dodge Dr",
    "sg:city":"Memphis",
    "sg:classifiers":[
        {
            "category":"Banks & Credit Unions",
            "subcategory":"Bank",
            "type":"Services"
        }
    ],
    "sg:phone":"+1 901 821 9030",
    "sg:postcode":"38128",
    "sg:province":"TN",
    "sg:tags":[
        "loan",
        "real estate"
    ],
    "wof:name":"A Mortgage Link",
    "wof:placetype":"venue"
},
  "geometry": {"coordinates":[-89.908469,35.20338],"type":"Point"}
}