{
  "type": "Feature",
  "properties": {
    "iso:country":"US",
    "sg:address":"715 Ohio Ave",
    "sg:city":"Etowah",
    "sg:classifiers":[
        {
            "category":"Personal",
            "subcategory":"Beauty Salon",
            "type":"Services"
        }
    ],
    "sg:phone":"+1 423 263 2644",
    "sg:postcode":"37331",
    "sg:province":"TN",
    "sg:tags":[
        "shop"
    ],
    "wof:name":"Gloria's Hair Affair",
    "wof:placetype":"venue"
},
  "geometry": {"coordinates":[-84.526425,35.323883],"type":"Point"}
}