{
  "type": "Feature",
  "properties": {
    "iso:country":"US",
    "sg:address":"441 Snyder Rd",
    "sg:city":"Morristown",
    "sg:classifiers":[
        {
            "category":"Retail",
            "subcategory":"Auto Repair",
            "type":"Services"
        }
    ],
    "sg:phone":"+1 423 581 5927",
    "sg:postcode":"37813",
    "sg:province":"TN",
    "sg:tags":[
        "repairing",
        "automobile"
    ],
    "wof:name":"Sapp's Auto Repair Svc",
    "wof:placetype":"venue"
},
  "geometry": {"coordinates":[-83.24882,36.225307],"type":"Point"}
}