{
  "type": "Feature",
  "properties": {
    "iso:country":"US",
    "sg:address":"3850 Viscount Ave",
    "sg:city":"Memphis",
    "sg:classifiers":[
        {
            "category":"Building & Trades",
            "subcategory":"Electrical",
            "type":"Services"
        }
    ],
    "sg:phone":"+1 901 366 1900",
    "sg:postcode":"38118",
    "sg:province":"TN",
    "sg:tags":[
        "telecommunication",
        "contractor"
    ],
    "wof:name":"Network Communications Systems",
    "wof:placetype":"venue"
},
  "geometry": {"coordinates":[-89.934619,35.048875],"type":"Point"}
}