{
  "type": "Feature",
  "properties": {
    "iso:country":"US",
    "sg:address":"966 E Raines Rd",
    "sg:city":"Memphis",
    "sg:classifiers":[
        {
            "category":"Health Services",
            "subcategory":"Nursing And Care Facility",
            "type":"Services"
        }
    ],
    "sg:phone":"+1 901 398 7742",
    "sg:postcode":"38116",
    "sg:province":"TN",
    "sg:tags":[
        "nurses-home",
        "institution",
        "home"
    ],
    "wof:name":"Robinson Care Home",
    "wof:placetype":"venue"
},
  "geometry": {"coordinates":[-90.03184400000001,35.035318],"type":"Point"}
}