{
  "type": "Feature",
  "properties": {
    "iso:country":"US",
    "sg:address":"3035 Parkway",
    "sg:city":"Pigeon Forge",
    "sg:classifiers":[
        {
            "category":"Travel",
            "subcategory":"Hotels & Motels",
            "type":"Entertainment"
        }
    ],
    "sg:phone":"+1 865 453 5334",
    "sg:postcode":"37863",
    "sg:province":"TN",
    "sg:tags":[
        "operation"
    ],
    "wof:name":"Willow Brook Lodge",
    "wof:placetype":"venue"
},
  "geometry": {"coordinates":[-83.562524,35.794798],"type":"Point"}
}