{
  "type": "Feature",
  "properties": {
    "iso:country":"US",
    "sg:address":"6514 Robertson Ave",
    "sg:city":"Nashville",
    "sg:classifiers":[
        {
            "category":"Mining & Drilling",
            "type":"Manufacturing & Wholesale Goods"
        }
    ],
    "sg:phone":"+1 615 356 2121",
    "sg:postcode":"37209",
    "sg:province":"TN",
    "sg:tags":[
        "stone"
    ],
    "sg:website":"www.rogersgroupinc.com",
    "wof:name":"Reostone LLC",
    "wof:placetype":"venue"
},
  "geometry": {"coordinates":[-86.884782,36.16163],"type":"Point"}
}