{
  "type": "Feature",
  "properties": {
    "iso:country":"US",
    "sg:address":"6737 Centennial Blvd",
    "sg:city":"Nashville",
    "sg:classifiers":[
        {
            "category":"Wholesale",
            "subcategory":"Photographic Equipment",
            "type":"Manufacturing & Wholesale Goods"
        }
    ],
    "sg:phone":"+1 615 298 5252",
    "sg:postcode":"37209",
    "sg:province":"TN",
    "sg:tags":[
        "motion",
        "picture",
        "supply"
    ],
    "sg:website":"www.citationsupport.com",
    "wof:name":"Citation Support Inc",
    "wof:placetype":"venue"
},
  "geometry": {"coordinates":[-86.87112500000001,36.171265],"type":"Point"}
}