{
  "type": "Feature",
  "properties": {
    "iso:country":"US",
    "sg:address":"11552 Kingston Pike",
    "sg:city":"Knoxville",
    "sg:classifiers":[
        {
            "category":"Food & Beverages",
            "subcategory":"Bakery",
            "type":"Retail Goods"
        }
    ],
    "sg:phone":"+1 865 671 8077",
    "sg:postcode":"37934",
    "sg:province":"TN",
    "sg:tags":[
        "baker"
    ],
    "wof:name":"V G's Bakery",
    "wof:placetype":"venue"
},
  "geometry": {"coordinates":[-84.167286,35.878057],"type":"Point"}
}