{
  "type": "Feature",
  "properties": {
    "iso:country":"US",
    "sg:address":"738 E Main St",
    "sg:city":"Jefferson City",
    "sg:classifiers":[
        {
            "category":"Restaurant",
            "type":"Food & Drink"
        }
    ],
    "sg:phone":"+1 865 475 4438",
    "sg:postcode":"37760",
    "sg:province":"TN",
    "sg:tags":[
        "eating"
    ],
    "wof:name":"Old City Cafe",
    "wof:placetype":"venue"
},
  "geometry": {"coordinates":[-83.490251,36.127393],"type":"Point"}
}