{
  "type": "Feature",
  "properties": {
    "addr:full":"9 White Plains Dr Jackson TN 38305",
    "addr:housenumber":"9",
    "addr:postcode":"38305",
    "addr:street":"White Plains Dr",
    "iso:country":"US",
    "sg:address":"9 White Plains Dr",
    "sg:city":"Jackson",
    "sg:classifiers":[
        {
            "category":"Building & Trades",
            "subcategory":"Construction",
            "type":"Services"
        }
    ],
    "sg:phone":"+1 731 668 7433",
    "sg:postcode":"38305",
    "sg:province":"TN",
    "sg:tags":[
        "concrete",
        "pumping"
    ],
    "wof:name":"Golden Circle Concrete Pumping",
    "wof:placetype":"venue"
},
  "geometry": {"coordinates":[-88.873203,35.701671],"type":"Point"}
}