{
  "type": "Feature",
  "properties": {
    "iso:country":"US",
    "sg:address":"2000 Mallory Ln",
    "sg:city":"Franklin",
    "sg:classifiers":[
        {
            "category":"Shopping",
            "type":"Retail Goods"
        }
    ],
    "sg:phone":"+1 615 771 8889",
    "sg:postcode":"37067",
    "sg:province":"TN",
    "sg:tags":[
        "material",
        "artist",
        "supply"
    ],
    "wof:name":"Art Store",
    "wof:placetype":"venue"
},
  "geometry": {"coordinates":[-86.81783,35.952121],"type":"Point"}
}