{
  "type": "Feature",
  "properties": {
    "addr:full":"202 E Moulton St Hickman TN 42050",
    "addr:housenumber":"202",
    "addr:postcode":"42050",
    "addr:street":"E Moulton St",
    "iso:country":"US",
    "sg:address":"202 E Moulton St",
    "sg:city":"Hickman",
    "sg:classifiers":[
        {
            "category":"Government",
            "subcategory":"Office",
            "type":"Public Place"
        }
    ],
    "sg:phone":"+1 270 236 9510",
    "sg:postcode":"42050",
    "sg:province":"TN",
    "wof:name":"Pretrial Services Agency",
    "wof:placetype":"venue"
},
  "geometry": {"coordinates":[-89.191836,36.571681],"type":"Point"}
}