{
  "type": "Feature",
  "properties": {
    "iso:country":"US",
    "sg:address":"217 W Main St",
    "sg:city":"Woodbury",
    "sg:classifiers":[
        {
            "category":"Shopping",
            "subcategory":"Used Merchandise",
            "type":"Retail Goods"
        }
    ],
    "sg:phone":"+1 615 563 8588",
    "sg:postcode":"37190",
    "sg:province":"TN",
    "sg:tags":[
        "shop",
        "consignment"
    ],
    "wof:name":"Madi's New & Consignment Apprl",
    "wof:placetype":"venue"
},
  "geometry": {"coordinates":[-86.07111500000001,35.82764],"type":"Point"}
}