{
  "type": "Feature",
  "properties": {
    "iso:country":"US",
    "sg:address":"818 Currey Rd",
    "sg:city":"Nashville",
    "sg:classifiers":[
        {
            "category":"Home & Garden",
            "subcategory":"Carpets & Floor Coverings",
            "type":"Retail Goods"
        }
    ],
    "sg:phone":"+1 615 293 6979",
    "sg:postcode":"37217",
    "sg:province":"TN",
    "sg:tags":[
        "material"
    ],
    "wof:name":"Floortech",
    "wof:placetype":"venue"
},
  "geometry": {"coordinates":[-86.709731,36.112482],"type":"Point"}
}