{
  "type": "Feature",
  "properties": {
    "addr:full":"905 Mallard Dr Gallatin TN 37066",
    "addr:housenumber":"905",
    "addr:postcode":"37066",
    "addr:street":"Mallard Dr",
    "iso:country":"US",
    "sg:address":"905 Mallard Dr",
    "sg:city":"Gallatin",
    "sg:classifiers":[
        {
            "category":"Building & Trades",
            "subcategory":"Construction",
            "type":"Services"
        }
    ],
    "sg:phone":"+1 615 451 2001",
    "sg:postcode":"37066",
    "sg:province":"TN",
    "sg:tags":[
        "steel",
        "erection",
        "contractor"
    ],
    "wof:name":"Cumberland Steel Inc",
    "wof:placetype":"venue"
},
  "geometry": {"coordinates":[-86.481657,36.382653],"type":"Point"}
}