{
  "type": "Feature",
  "properties": {
    "addr:full":"1501 Dodds Ave Chattanooga TN 37404",
    "addr:housenumber":"1501",
    "addr:postcode":"37404",
    "addr:street":"Dodds Ave",
    "iso:country":"US",
    "sg:address":"1501 Dodds Ave",
    "sg:city":"Chattanooga",
    "sg:classifiers":[
        {
            "category":"Professional",
            "subcategory":"Business Services",
            "type":"Services"
        }
    ],
    "sg:phone":"+1 423 624 6754",
    "sg:postcode":"37404",
    "sg:province":"TN",
    "sg:tags":[
        "translator",
        "interpreter"
    ],
    "wof:name":"Las Americas",
    "wof:placetype":"venue"
},
  "geometry": {"coordinates":[-85.27049100000001,35.020755],"type":"Point"}
}