{
  "type": "Feature",
  "properties": {
    "iso:country":"US",
    "sg:address":"833 Nashville Hwy",
    "sg:city":"Columbia",
    "sg:classifiers":[
        {
            "category":"Personal",
            "subcategory":"Beauty Salon",
            "type":"Services"
        }
    ],
    "sg:phone":"+1 931 380 1796",
    "sg:postcode":"38401",
    "sg:province":"TN",
    "wof:name":"Heads Up Hair Cutting Center",
    "wof:placetype":"venue"
},
  "geometry": {"coordinates":[-87.026701,35.628631],"type":"Point"}
}