{
  "type": "Feature",
  "properties": {
    "addr:full":"100 Stewarts Ferry Pike Nashville TN 37214",
    "addr:housenumber":"100",
    "addr:postcode":"37214",
    "addr:street":"Stewarts Ferry Pike",
    "iso:country":"US",
    "sg:address":"100 Stewarts Ferry Pike",
    "sg:city":"Nashville",
    "sg:classifiers":[
        {
            "category":"Real Estate",
            "subcategory":"Real Estate Operator",
            "type":"Services"
        }
    ],
    "sg:phone":"+1 615 883 9300",
    "sg:postcode":"37214",
    "sg:province":"TN",
    "sg:tags":[
        "apartment"
    ],
    "wof:name":"Stewarts Ferry Apartments",
    "wof:placetype":"venue"
},
  "geometry": {"coordinates":[-86.657607,36.167747],"type":"Point"}
}