{
  "type": "Feature",
  "properties": {
    "addr:full":"1726 Thorntree Dr Dyersburg TN 38024",
    "addr:housenumber":"1726",
    "addr:postcode":"38024",
    "addr:street":"Thorntree Dr",
    "iso:country":"US",
    "sg:address":"1726 Thorntree Dr",
    "sg:city":"Dyersburg",
    "sg:classifiers":[
        {
            "category":"Shopping",
            "subcategory":"Computers & Home Electronics",
            "type":"Retail Goods"
        }
    ],
    "sg:phone":"+1 731 285 8912",
    "sg:postcode":"38024",
    "sg:province":"TN",
    "wof:name":"Sunrise Digital LLC",
    "wof:placetype":"venue"
},
  "geometry": {"coordinates":[-89.400434,36.04953],"type":"Point"}
}