{
  "type": "Feature",
  "properties": {
    "iso:country":"US",
    "sg:address":"1244 Greenfield Dr",
    "sg:city":"Clarksville",
    "sg:classifiers":[
        {
            "category":"Professional",
            "subcategory":"Engineering",
            "type":"Services"
        }
    ],
    "sg:phone":"+1 931 645 5245",
    "sg:postcode":"37040",
    "sg:province":"TN",
    "sg:tags":[
        "engineer"
    ],
    "wof:name":"Achievement Assoc",
    "wof:placetype":"venue"
},
  "geometry": {"coordinates":[-87.33871499999999,36.513922],"type":"Point"}
}