{
  "type": "Feature",
  "properties": {
    "addr:full":"404 S Washington St Maryville TN 37804",
    "addr:housenumber":"404",
    "addr:postcode":"37804",
    "addr:street":"S Washington St",
    "iso:country":"US",
    "sg:address":"404 S Washington St",
    "sg:city":"Maryville",
    "sg:classifiers":[
        {
            "category":"Professional",
            "subcategory":"Business Services",
            "type":"Services"
        }
    ],
    "sg:phone":"+1 865 406 7818",
    "sg:postcode":"37804",
    "sg:province":"TN",
    "wof:name":"Kevin S Proffitt Cfp",
    "wof:placetype":"venue"
},
  "geometry": {"coordinates":[-83.965099,35.758187],"type":"Point"}
}