{
  "type": "Feature",
  "properties": {
    "iso:country":"US",
    "sg:address":"3035 Directors Row",
    "sg:city":"Memphis",
    "sg:classifiers":[
        {
            "category":"Organizations",
            "subcategory":"Labor Organization",
            "type":"Services"
        }
    ],
    "sg:phone":"+1 901 332 3570",
    "sg:postcode":"38131",
    "sg:province":"TN",
    "wof:name":"Midsouth Interfaith Network Fo",
    "wof:placetype":"venue"
},
  "geometry": {"coordinates":[-89.993358,35.06544],"type":"Point"}
}