{
  "type": "Feature",
  "properties": {
    "iso:country":"US",
    "sg:address":"5106 McMinnville Hwy",
    "sg:city":"Doyle",
    "sg:classifiers":[
        {
            "category":"Organizations",
            "subcategory":"Religious Organization",
            "type":"Services"
        }
    ],
    "sg:phone":"+1 931 657 4673",
    "sg:postcode":"38559",
    "sg:province":"TN",
    "wof:name":"Vision Of Hope Ministries",
    "wof:placetype":"venue"
},
  "geometry": {"coordinates":[-85.512178,35.854663],"type":"Point"}
}