{
  "type": "Feature",
  "properties": {
    "iso:country":"US",
    "sg:address":"1180 Mechanics Way",
    "sg:city":"Sevierville",
    "sg:classifiers":[
        {
            "category":"Retail",
            "subcategory":"Repair Shop",
            "type":"Services"
        }
    ],
    "sg:phone":"+1 865 428 4187",
    "sg:postcode":"37862",
    "sg:province":"TN",
    "sg:tags":[
        "electrical"
    ],
    "wof:name":"Wilsons TV & Vcr Service",
    "wof:placetype":"venue"
},
  "geometry": {"coordinates":[-83.55046400000001,35.843258],"type":"Point"}
}