{
  "type": "Feature",
  "properties": {
    "iso:country":"US",
    "sg:address":"336 Roosters Roost",
    "sg:city":"Goodspring",
    "sg:classifiers":[
        {
            "category":"Taxi",
            "type":"Transportation"
        }
    ],
    "sg:phone":"+1 931 363 6600",
    "sg:postcode":"38460",
    "sg:province":"TN",
    "sg:tags":[
        "taxicab"
    ],
    "wof:name":"City Cab Co",
    "wof:placetype":"venue"
},
  "geometry": {"coordinates":[-87.138114,35.125694],"type":"Point"}
}