{
  "type": "Feature",
  "properties": {
    "iso:country":"US",
    "sg:address":"1104 Wheatfield Dr",
    "sg:city":"Lascassas",
    "sg:classifiers":[
        {
            "category":"Wholesale",
            "subcategory":"Non-durable Goods",
            "type":"Manufacturing & Wholesale Goods"
        }
    ],
    "sg:phone":"+1 615 642 9709",
    "sg:postcode":"37085",
    "sg:province":"TN",
    "wof:name":"Dj Distributing",
    "wof:placetype":"venue"
},
  "geometry": {"coordinates":[-86.297273,35.93454],"type":"Point"}
}