{
  "type": "Feature",
  "properties": {
    "addr:full":"795 E McKellar Ave Memphis TN 38106",
    "addr:housenumber":"795",
    "addr:postcode":"38106",
    "addr:street":"E Mckellar Ave",
    "iso:country":"US",
    "sg:address":"795 E McKellar Ave",
    "sg:city":"Memphis",
    "sg:classifiers":[
        {
            "category":"Personal",
            "subcategory":"Beauty Salon",
            "type":"Services"
        }
    ],
    "sg:phone":"+1 901 948 6968",
    "sg:postcode":"38106",
    "sg:province":"TN",
    "sg:tags":[
        "shop"
    ],
    "wof:name":"Todays Highlight & Style",
    "wof:placetype":"venue"
},
  "geometry": {"coordinates":[-90.035929,35.089091],"type":"Point"}
}