{
  "type": "Feature",
  "properties": {
    "iso:country":"US",
    "sg:address":"215 Uffelman Dr",
    "sg:city":"Clarksville",
    "sg:classifiers":[
        {
            "category":"Personal",
            "subcategory":"Beauty Salon",
            "type":"Services"
        }
    ],
    "sg:phone":"+1 931 552 1505",
    "sg:postcode":"37043",
    "sg:province":"TN",
    "sg:tags":[
        "shop",
        "barber"
    ],
    "wof:name":"Hair Shack",
    "wof:placetype":"venue"
},
  "geometry": {"coordinates":[-87.30795999999999,36.517664],"type":"Point"}
}