{
  "type": "Feature",
  "properties": {
    "iso:country":"US",
    "sg:address":"865 Choctaw Dr",
    "sg:city":"Chuckey",
    "sg:classifiers":[
        {
            "category":"Building & Trades",
            "subcategory":"Cleaning & Sanitation",
            "type":"Services"
        }
    ],
    "sg:phone":"+1 423 257 8395",
    "sg:postcode":"37641",
    "sg:province":"TN",
    "sg:tags":[
        "maintenance"
    ],
    "wof:name":"Hensleys Cleaning Service",
    "wof:placetype":"venue"
},
  "geometry": {"coordinates":[-82.69566500000001,36.217664],"type":"Point"}
}