{
  "type": "Feature",
  "properties": {
    "iso:country":"US",
    "sg:address":"1750 Memorial Dr",
    "sg:city":"Clarksville",
    "sg:classifiers":[
        {
            "category":"Banks & Credit Unions",
            "subcategory":"Investment Brokerage",
            "type":"Services"
        }
    ],
    "sg:phone":"+1 931 905 1064",
    "sg:postcode":"37043",
    "sg:province":"TN",
    "sg:tags":[
        "security"
    ],
    "wof:name":"A G Edwards & Sons Inc",
    "wof:placetype":"venue"
},
  "geometry": {"coordinates":[-87.309757,36.517575],"type":"Point"}
}