{
  "type": "Feature",
  "properties": {
    "addr:full":"9161 Cedarpark Ln NW Knoxville TN 37923",
    "addr:housenumber":"9161",
    "addr:postcode":"37923",
    "addr:street":"Cedarpark Ln Nw",
    "iso:country":"US",
    "sg:address":"9161 Cedarpark Ln NW",
    "sg:city":"Knoxville",
    "sg:classifiers":[
        {
            "category":"Retail",
            "subcategory":"Repair Shop",
            "type":"Services"
        }
    ],
    "sg:phone":"+1 865 769 2563",
    "sg:postcode":"37923",
    "sg:province":"TN",
    "sg:tags":[
        "equipment",
        "electronic",
        "supply"
    ],
    "wof:name":"John's TV & Electronics",
    "wof:placetype":"venue"
},
  "geometry": {"coordinates":[-84.08763,35.928049],"type":"Point"}
}