{
  "type": "Feature",
  "properties": {
    "iso:country":"US",
    "sg:address":"3835 Knight Rd",
    "sg:city":"Memphis",
    "sg:classifiers":[
        {
            "category":"Manufacturing",
            "subcategory":"Tools & Machinery",
            "type":"Manufacturing & Wholesale Goods"
        }
    ],
    "sg:phone":"+1 901 366 5494",
    "sg:postcode":"38118",
    "sg:province":"TN",
    "sg:tags":[
        "water",
        "pump",
        "mfg"
    ],
    "wof:name":"Pentair Inc",
    "wof:placetype":"venue"
},
  "geometry": {"coordinates":[-89.91127400000001,35.044112],"type":"Point"}
}