{
  "type": "Feature",
  "properties": {
    "iso:country":"US",
    "sg:address":"3020 N John B Dennis Hwy",
    "sg:city":"Kingsport",
    "sg:classifiers":[
        {
            "category":"Restaurant",
            "type":"Food & Drink"
        }
    ],
    "sg:menulink":"http://www.allmenus.com/tn/kingsport/154879-hardees/menu/",
    "sg:phone":"+1 423 288 8901",
    "sg:postcode":"37660",
    "sg:province":"TN",
    "sg:tags":[
        "burger",
        "american"
    ],
    "wof:name":"Hardee's",
    "wof:placetype":"venue"
},
  "geometry": {"coordinates":[-82.50723600000001,36.573657],"type":"Point"}
}