{
  "type": "Feature",
  "properties": {
    "iso:country":"US",
    "sg:address":"2017 Gregory Rd",
    "sg:city":"Kingsport",
    "sg:classifiers":[
        {
            "category":"Professional",
            "type":"Services"
        }
    ],
    "sg:phone":"+1 423 245 8490",
    "sg:postcode":"37665",
    "sg:province":"TN",
    "wof:name":"Daves Mobile Service",
    "wof:placetype":"venue"
},
  "geometry": {"coordinates":[-82.582009,36.59315],"type":"Point"}
}