{
  "type": "Feature",
  "properties": {
    "addr:full":"2934 Ridgeway Rd Ste 103 Memphis TN 38115",
    "addr:housenumber":"2934",
    "addr:postcode":"38115",
    "addr:street":"Ridgeway Rd Ste 103",
    "iso:country":"US",
    "sg:address":"2934 Ridgeway Rd Ste 103",
    "sg:city":"Memphis",
    "sg:classifiers":[
        {
            "category":"Wholesale",
            "subcategory":"Machinery & Supplies",
            "type":"Manufacturing & Wholesale Goods"
        },
        {
            "category":"Professional",
            "subcategory":"Business Services",
            "type":"Services"
        }
    ],
    "sg:phone":"+1 901 757 8221",
    "sg:postcode":"38115",
    "sg:province":"TN",
    "sg:tags":[
        "equipment",
        "irrigation",
        "system",
        "consultant"
    ],
    "wof:name":"Carefree Irrigation Service Inc",
    "wof:placetype":"venue"
},
  "geometry": {"coordinates":[-89.856651,35.068439],"type":"Point"}
}