{
  "type": "Feature",
  "properties": {
    "iso:country":"US",
    "sg:address":"1001 17th Ave S",
    "sg:city":"Nashville",
    "sg:classifiers":[
        {
            "category":"Professional",
            "subcategory":"Business Services",
            "type":"Services"
        }
    ],
    "sg:phone":"+1 615 327 9040",
    "sg:postcode":"37212",
    "sg:province":"TN",
    "sg:tags":[
        "recording",
        "studio"
    ],
    "wof:name":"Seventeen Grand Recording",
    "wof:placetype":"venue"
},
  "geometry": {"coordinates":[-86.794415,36.143506],"type":"Point"}
}