{
  "type": "Feature",
  "properties": {
    "iso:country":"US",
    "sg:address":"524 Justice Dr",
    "sg:city":"Greeneville",
    "sg:classifiers":[
        {
            "category":"Professional",
            "subcategory":"Accounting & Tax Preparation",
            "type":"Services"
        }
    ],
    "sg:phone":"+1 423 798 9800",
    "sg:postcode":"37745",
    "sg:province":"TN",
    "sg:tags":[
        "return",
        "filing"
    ],
    "wof:name":"West Greene Tax Svc",
    "wof:placetype":"venue"
},
  "geometry": {"coordinates":[-82.79419300000001,36.176272],"type":"Point"}
}