{
  "type": "Feature",
  "properties": {
    "iso:country":"US",
    "sg:address":"298 Timberlane Dr",
    "sg:city":"Cordova",
    "sg:classifiers":[
        {
            "category":"Professional",
            "subcategory":"Management & Consulting",
            "type":"Services"
        }
    ],
    "sg:phone":"+1 901 737 5096",
    "sg:postcode":"38018",
    "sg:province":"TN",
    "sg:tags":[
        "consultant",
        "telecommunication"
    ],
    "wof:name":"Delta Consulting",
    "wof:placetype":"venue"
},
  "geometry": {"coordinates":[-89.765596,35.132956],"type":"Point"}
}