{
  "type": "Feature",
  "properties": {
    "addr:full":"555 Bolivar Hwy Jackson TN 38301",
    "addr:housenumber":"555",
    "addr:postcode":"38301",
    "addr:street":"Bolivar Hwy",
    "iso:country":"US",
    "sg:address":"555 Bolivar Hwy",
    "sg:city":"Jackson",
    "sg:classifiers":[
        {
            "category":"Shopping",
            "type":"Retail Goods"
        },
        {
            "category":"Wholesale",
            "subcategory":"Electrical",
            "type":"Manufacturing & Wholesale Goods"
        }
    ],
    "sg:phone":"+1 731 265 9480",
    "sg:postcode":"38301",
    "sg:province":"TN",
    "sg:tags":[
        "operated",
        "card",
        "merchandise",
        "telephone"
    ],
    "wof:name":"Telaleasing Enterprises Inc",
    "wof:placetype":"venue"
},
  "geometry": {"coordinates":[-88.826708,35.542117],"type":"Point"}
}