{
  "type": "Feature",
  "properties": {
    "addr:full":"629 N Highland St Memphis TN 38122",
    "addr:housenumber":"629",
    "addr:postcode":"38122",
    "addr:street":"N Highland St",
    "iso:country":"US",
    "sg:address":"629 N Highland St",
    "sg:city":"Memphis",
    "sg:classifiers":[
        {
            "category":"Food & Beverages",
            "subcategory":"Groceries & Convenience Stores",
            "type":"Retail Goods"
        }
    ],
    "sg:phone":"+1 901 458 4247",
    "sg:postcode":"38122",
    "sg:province":"TN",
    "sg:tags":[
        "station",
        "gasoline"
    ],
    "wof:name":"Circle K",
    "wof:placetype":"venue"
},
  "geometry": {"coordinates":[-89.944597,35.149162],"type":"Point"}
}