{
  "type": "Feature",
  "properties": {
    "addr:full":"3829 Trenton Rd Clarksville TN 37040",
    "addr:housenumber":"3829",
    "addr:postcode":"37040",
    "addr:street":"Trenton Rd",
    "iso:country":"US",
    "sg:address":"3829 Trenton Rd",
    "sg:city":"Clarksville",
    "sg:classifiers":[
        {
            "category":"Restaurant",
            "type":"Food & Drink"
        }
    ],
    "sg:menulink":"http://www.allmenus.com/tn/st-bethlehem/191778-sonic/menu/",
    "sg:phone":"+1 931 551 4470",
    "sg:postcode":"37040",
    "sg:province":"TN",
    "sg:tags":[
        "burger",
        "american"
    ],
    "wof:name":"Sonic",
    "wof:placetype":"venue"
},
  "geometry": {"coordinates":[-87.318382,36.6218],"type":"Point"}
}