{
  "type": "Feature",
  "properties": {
    "iso:country":"US",
    "sg:address":"1992 Cooks Valley Rd",
    "sg:city":"Kingsport",
    "sg:classifiers":[
        {
            "category":"Wholesale",
            "subcategory":"Construction Materials",
            "type":"Manufacturing & Wholesale Goods"
        }
    ],
    "sg:phone":"+1 423 288 7133",
    "sg:postcode":"37664",
    "sg:province":"TN",
    "sg:tags":[
        "brokerage",
        "lumber"
    ],
    "wof:name":"Bright Forest Products LLC",
    "wof:placetype":"venue"
},
  "geometry": {"coordinates":[-82.496731,36.509914],"type":"Point"}
}