{
  "type": "Feature",
  "properties": {
    "addr:full":"1106 Hadley Ave Old Hickory TN 37138",
    "addr:housenumber":"1106",
    "addr:postcode":"37138",
    "addr:street":"Hadley Ave",
    "iso:country":"US",
    "sg:address":"1106 Hadley Ave",
    "sg:city":"Old Hickory",
    "sg:classifiers":[
        {
            "category":"Organizations",
            "subcategory":"Religious Organization",
            "type":"Services"
        }
    ],
    "sg:phone":"+1 615 847 3447",
    "sg:postcode":"37138",
    "sg:province":"TN",
    "sg:tags":[
        "church"
    ],
    "sg:website":"www.fbcoh.org",
    "wof:name":"First Baptist Church Old Hckry",
    "wof:placetype":"venue"
},
  "geometry": {"coordinates":[-86.647899,36.259205],"type":"Point"}
}