{
  "type": "Feature",
  "properties": {
    "addr:full":"103 Slatestone Rd Briceville TN 37710",
    "addr:housenumber":"103",
    "addr:postcode":"37710",
    "addr:street":"Slatestone Rd",
    "iso:country":"US",
    "sg:address":"103 Slatestone Rd",
    "sg:city":"Briceville",
    "sg:classifiers":[
        {
            "category":"Education",
            "subcategory":"School",
            "type":"Public Place"
        }
    ],
    "sg:phone":"+1 865 426 2289",
    "sg:postcode":"37710",
    "sg:province":"TN",
    "sg:website":"www.bes.acs.ac",
    "wof:name":"Briceville Elementary School",
    "wof:placetype":"venue"
},
  "geometry": {"coordinates":[-84.18772800000001,36.180685],"type":"Point"}
}