{
  "type": "Feature",
  "properties": {
    "iso:country":"US",
    "sg:address":"1232 S Jackson St",
    "sg:city":"Tullahoma",
    "sg:classifiers":[
        {
            "category":"Home & Garden",
            "subcategory":"Mobile Homes",
            "type":"Retail Goods"
        }
    ],
    "sg:phone":"+1 931 461 9022",
    "sg:postcode":"37388",
    "sg:province":"TN",
    "wof:name":"Horton Homes Of Coffee County",
    "wof:placetype":"venue"
},
  "geometry": {"coordinates":[-86.19878,35.348181],"type":"Point"}
}