{
  "type": "Feature",
  "properties": {
    "addr:full":"200 Main St Nashville TN 37206",
    "addr:housenumber":"200",
    "addr:postcode":"37206",
    "addr:street":"Main St",
    "iso:country":"US",
    "sg:address":"200 Main St",
    "sg:city":"Nashville",
    "sg:classifiers":[
        {
            "category":"Retail",
            "subcategory":"Auto Repair",
            "type":"Services"
        }
    ],
    "sg:phone":"+1 615 726 3220",
    "sg:postcode":"37206",
    "sg:province":"TN",
    "sg:tags":[
        "body",
        "automobile",
        "painting"
    ],
    "wof:name":"Accurate Autobody Inc",
    "wof:placetype":"venue"
},
  "geometry": {"coordinates":[-86.772032,36.17032],"type":"Point"}
}