{
  "type": "Feature",
  "properties": {
    "iso:country":"US",
    "sg:address":"2400 Coker Ave",
    "sg:city":"Knoxville",
    "sg:classifiers":[
        {
            "category":"Personal",
            "subcategory":"Beauty Salon",
            "type":"Services"
        }
    ],
    "sg:phone":"+1 865 524 0895",
    "sg:postcode":"37917",
    "sg:province":"TN",
    "sg:tags":[
        "shop",
        "barber"
    ],
    "wof:name":"Cameo Family Hair Care Center",
    "wof:placetype":"venue"
},
  "geometry": {"coordinates":[-83.90976999999999,35.999899],"type":"Point"}
}