{
  "type": "Feature",
  "properties": {
    "iso:country":"US",
    "sg:address":"5441 Nolensville Pike",
    "sg:city":"Nashville",
    "sg:classifiers":[
        {
            "category":"Building & Trades",
            "subcategory":"Equipment Rental",
            "type":"Services"
        }
    ],
    "sg:phone":"+1 615 331 9911",
    "sg:postcode":"37211",
    "sg:province":"TN",
    "sg:tags":[
        "leasing",
        "furniture"
    ],
    "wof:name":"Aarons Sales & Lease Ownership",
    "wof:placetype":"venue"
},
  "geometry": {"coordinates":[-86.71409199999999,36.050341],"type":"Point"}
}