{
  "type": "Feature",
  "properties": {
    "iso:country":"US",
    "sg:address":"294 Shofner Ave",
    "sg:city":"Memphis",
    "sg:classifiers":[
        {
            "category":"Freight",
            "type":"Transportation"
        }
    ],
    "sg:phone":"+1 901 332 1030",
    "sg:postcode":"38109",
    "sg:province":"TN",
    "sg:tags":[
        "trucking"
    ],
    "wof:name":"Mac Trucking",
    "wof:placetype":"venue"
},
  "geometry": {"coordinates":[-90.052964,35.031866],"type":"Point"}
}