{
  "type": "Feature",
  "properties": {
    "addr:full":"2700 Stonewall St Knoxville TN 37921",
    "addr:housenumber":"2700",
    "addr:postcode":"37921",
    "addr:street":"Stonewall St",
    "iso:country":"US",
    "sg:address":"2700 Stonewall St",
    "sg:city":"Knoxville",
    "sg:classifiers":[
        {
            "category":"Recreation",
            "type":"Entertainment"
        }
    ],
    "sg:phone":"+1 865 546 0696",
    "sg:postcode":"37921",
    "sg:province":"TN",
    "sg:tags":[
        "center"
    ],
    "wof:name":"Lonsdale Recreation Ctr",
    "wof:placetype":"venue"
},
  "geometry": {"coordinates":[-83.957348,35.982116],"type":"Point"}
}