{
  "type": "Feature",
  "properties": {
    "iso:country":"US",
    "sg:address":"4015 Divine Ave",
    "sg:city":"Chattanooga",
    "sg:classifiers":[
        {
            "category":"Professional",
            "subcategory":"Engineering",
            "type":"Services"
        }
    ],
    "sg:phone":"+1 423 648 2345",
    "sg:postcode":"37407",
    "sg:province":"TN",
    "sg:tags":[
        "engineer"
    ],
    "wof:name":"Atlantic Engineering Group",
    "wof:placetype":"venue"
},
  "geometry": {"coordinates":[-85.295012,34.996085],"type":"Point"}
}