{
  "type": "Feature",
  "properties": {
    "iso:country":"US",
    "sg:address":"12841 US Hwy 70 E",
    "sg:city":"Lenoir City",
    "sg:classifiers":[
        {
            "category":"Real Estate",
            "subcategory":"Developer",
            "type":"Services"
        }
    ],
    "sg:phone":"+1 865 986 5091",
    "sg:postcode":"37771",
    "sg:province":"TN",
    "sg:tags":[
        "development",
        "consultant"
    ],
    "wof:name":"R S C M Corporation",
    "wof:placetype":"venue"
},
  "geometry": {"coordinates":[-84.23774400000001,35.855139],"type":"Point"}
}