{
  "type": "Feature",
  "properties": {
    "addr:full":"2437 E Clark Ave Maryville TN 37804",
    "addr:housenumber":"2437",
    "addr:postcode":"37804",
    "addr:street":"E Clark Ave",
    "iso:country":"US",
    "sg:address":"2437 E Clark Ave",
    "sg:city":"Maryville",
    "sg:classifiers":[
        {
            "category":"Building & Trades",
            "subcategory":"Construction",
            "type":"Services"
        }
    ],
    "sg:phone":"+1 865 982 4181",
    "sg:postcode":"37804",
    "sg:province":"TN",
    "sg:tags":[
        "wallcoverings-installation",
        "wallpaper",
        "painting",
        "contractor"
    ],
    "wof:name":"Real Deal Painting",
    "wof:placetype":"venue"
},
  "geometry": {"coordinates":[-83.944267,35.785831],"type":"Point"}
}