{
  "type": "Feature",
  "properties": {
    "addr:full":"205 Bowling Ave Nashville TN 37205",
    "addr:housenumber":"205",
    "addr:postcode":"37205",
    "addr:street":"Bowling Ave",
    "iso:country":"US",
    "sg:address":"205 Bowling Ave",
    "sg:city":"Nashville",
    "sg:classifiers":[
        {
            "category":"Professional",
            "subcategory":"Business Services",
            "type":"Services"
        }
    ],
    "sg:phone":"+1 615 269 3919",
    "sg:postcode":"37205",
    "sg:province":"TN",
    "sg:tags":[
        "interior",
        "consultant",
        "design",
        "decorator"
    ],
    "wof:name":"C & A Designs",
    "wof:placetype":"venue"
},
  "geometry": {"coordinates":[-86.826151,36.129025],"type":"Point"}
}