{
  "type": "Feature",
  "properties": {
    "iso:country":"US",
    "sg:address":"3617 Winchester Rd",
    "sg:city":"Memphis",
    "sg:classifiers":[
        {
            "category":"Banks & Credit Unions",
            "subcategory":"Bank",
            "type":"Services"
        }
    ],
    "sg:phone":"+1 901 547 0209",
    "sg:postcode":"38118",
    "sg:province":"TN",
    "sg:tags":[
        "state"
    ],
    "wof:name":"I Trust Federal Credit Union",
    "wof:placetype":"venue"
},
  "geometry": {"coordinates":[-89.94067200000001,35.051897],"type":"Point"}
}