{
  "type": "Feature",
  "properties": {
    "addr:full":"2444 Poplar Ave Memphis TN 38112",
    "addr:housenumber":"2444",
    "addr:postcode":"38112",
    "addr:street":"Poplar Ave",
    "iso:country":"US",
    "sg:address":"2444 Poplar Ave",
    "sg:city":"Memphis",
    "sg:classifiers":[
        {
            "category":"Autos & Motor Vehicles",
            "subcategory":"Fuel & Gas Station",
            "type":"Retail Goods"
        },
        {
            "category":"Food & Beverages",
            "subcategory":"Groceries & Convenience Stores",
            "type":"Retail Goods"
        }
    ],
    "sg:phone":"+1 901 454 6012",
    "sg:postcode":"38112",
    "sg:province":"TN",
    "sg:website":"http://www.texaco.com/",
    "wof:name":"Texaco",
    "wof:placetype":"venue"
},
  "geometry": {"coordinates":[-89.979507,35.139254],"type":"Point"}
}