{
  "type": "Feature",
  "properties": {
    "iso:country":"US",
    "sg:address":"2116 Wilder St",
    "sg:city":"Chattanooga",
    "sg:classifiers":[
        {
            "category":"Personal",
            "subcategory":"Beauty Salon",
            "type":"Services"
        }
    ],
    "sg:phone":"+1 423 698 3005",
    "sg:postcode":"37406",
    "sg:province":"TN",
    "sg:tags":[
        "shop"
    ],
    "wof:name":"Michael's Hair Styles",
    "wof:placetype":"venue"
},
  "geometry": {"coordinates":[-85.25064999999999,35.073265],"type":"Point"}
}