{
  "type": "Feature",
  "properties": {
    "iso:country":"US",
    "sg:address":"400 Barclay Dr",
    "sg:city":"Knoxville",
    "sg:classifiers":[
        {
            "category":"Building & Trades",
            "subcategory":"Landscaping Services",
            "type":"Services"
        }
    ],
    "sg:phone":"+1 865 573 3590",
    "sg:postcode":"37920",
    "sg:province":"TN",
    "wof:name":"Little River Ldscp Mangement",
    "wof:placetype":"venue"
},
  "geometry": {"coordinates":[-83.896303,35.934946],"type":"Point"}
}