{
  "type": "Feature",
  "properties": {
    "iso:country":"US",
    "sg:address":"4497 Macon Rd",
    "sg:city":"Memphis",
    "sg:classifiers":[
        {
            "category":"Professional",
            "subcategory":"Business Services",
            "type":"Services"
        }
    ],
    "sg:phone":"+1 901 763 0199",
    "sg:postcode":"38122",
    "sg:province":"TN",
    "sg:tags":[
        "notary",
        "public"
    ],
    "wof:name":"Tequilas",
    "wof:placetype":"venue"
},
  "geometry": {"coordinates":[-89.910759,35.161919],"type":"Point"}
}