{
  "type": "Feature",
  "properties": {
    "iso:country":"US",
    "sg:address":"6700 Baum Dr SW",
    "sg:city":"Knoxville",
    "sg:classifiers":[
        {
            "category":"Professional",
            "subcategory":"Research",
            "type":"Services"
        }
    ],
    "sg:phone":"+1 865 588 9180",
    "sg:postcode":"37919",
    "sg:province":"TN",
    "sg:tags":[
        "environmental",
        "ecological"
    ],
    "wof:name":"Integrated Environmental Mgmt",
    "wof:placetype":"venue"
},
  "geometry": {"coordinates":[-84.01166499999999,35.927383],"type":"Point"}
}