{
  "type": "Feature",
  "properties": {
    "iso:country":"US",
    "sg:address":"981 Lexington Hwy",
    "sg:city":"Loretto",
    "sg:classifiers":[
        {
            "category":"Farming",
            "subcategory":"Farm",
            "type":"Manufacturing & Wholesale Goods"
        }
    ],
    "sg:phone":"+1 931 853 6707",
    "sg:postcode":"38469",
    "sg:province":"TN",
    "sg:tags":[
        "crop",
        "general"
    ],
    "wof:name":"Shady Brook Angus Bull Barn",
    "wof:placetype":"venue"
},
  "geometry": {"coordinates":[-87.391504,35.057369],"type":"Point"}
}