{
  "type": "Feature",
  "properties": {
    "iso:country":"US",
    "sg:address":"1105 Murfreesboro Pike",
    "sg:city":"Nashville",
    "sg:classifiers":[
        {
            "category":"Banks & Credit Unions",
            "subcategory":"Bank",
            "type":"Services"
        }
    ],
    "sg:phone":"+1 615 860 8205",
    "sg:postcode":"37217",
    "sg:province":"TN",
    "sg:tags":[
        "institution",
        "business"
    ],
    "wof:name":"Cash Advance Services",
    "wof:placetype":"venue"
},
  "geometry": {"coordinates":[-86.710677,36.12631],"type":"Point"}
}