{
  "type": "Feature",
  "properties": {
    "iso:country":"US",
    "sg:address":"4900 Jonquil Dr",
    "sg:city":"Nashville",
    "sg:classifiers":[
        {
            "category":"Shopping",
            "subcategory":"Clothing, Apparel, & Fashions",
            "type":"Retail Goods"
        }
    ],
    "sg:phone":"+1 615 833 6289",
    "sg:postcode":"37211",
    "sg:province":"TN",
    "sg:tags":[
        "t"
    ],
    "wof:name":"M S Shirts",
    "wof:placetype":"venue"
},
  "geometry": {"coordinates":[-86.71817299999999,36.084294],"type":"Point"}
}