{
  "type": "Feature",
  "properties": {
    "addr:full":"2810 Summer Oaks Dr Memphis TN 38134",
    "addr:housenumber":"2810",
    "addr:postcode":"38134",
    "addr:street":"Summer Oaks Dr",
    "iso:country":"US",
    "sg:address":"2810 Summer Oaks Dr",
    "sg:city":"Memphis",
    "sg:classifiers":[
        {
            "category":"Professional",
            "subcategory":"Secretarial Services",
            "type":"Services"
        }
    ],
    "sg:phone":"+1 901 373 3377",
    "sg:postcode":"38134",
    "sg:province":"TN",
    "sg:tags":[
        "reporting",
        "business"
    ],
    "wof:name":"Davis Executive Svcs & Suites",
    "wof:placetype":"venue"
},
  "geometry": {"coordinates":[-89.843233,35.202147],"type":"Point"}
}