{
  "type": "Feature",
  "properties": {
    "iso:country":"US",
    "sg:address":"120 Pearce Dr",
    "sg:city":"Morristown",
    "sg:classifiers":[
        {
            "category":"Health Services",
            "subcategory":"Doctor",
            "type":"Services"
        }
    ],
    "sg:phone":"+1 423 587 3537",
    "sg:postcode":"37814",
    "sg:province":"TN",
    "sg:tags":[
        "medical",
        "clinic",
        "center",
        "kidney",
        "dialysis"
    ],
    "wof:name":"Morristown Dialysis Center",
    "wof:placetype":"venue"
},
  "geometry": {"coordinates":[-83.32393,36.205096],"type":"Point"}
}