{
  "type": "Feature",
  "properties": {
    "addr:full":"5531 Hopewell Rd Tazewell TN 37752",
    "addr:housenumber":"5531",
    "addr:postcode":"37752",
    "addr:street":"Hopewell Rd",
    "iso:country":"US",
    "sg:address":"5531 Hopewell Rd",
    "sg:city":"Tazewell",
    "sg:classifiers":[
        {
            "category":"Freight",
            "type":"Transportation"
        }
    ],
    "sg:phone":"+1 423 626 3485",
    "sg:postcode":"37752",
    "sg:province":"TN",
    "sg:tags":[
        "operator",
        "trucking"
    ],
    "wof:name":"Cosby Enterprises Inc",
    "wof:placetype":"venue"
},
  "geometry": {"coordinates":[-83.45018399999999,36.560445],"type":"Point"}
}