{
  "type": "Feature",
  "properties": {
    "addr:full":"7822 US Hwy 51 N Millington TN 38053",
    "addr:housenumber":"7822",
    "addr:postcode":"38053",
    "addr:street":"Us Hwy 51 N",
    "iso:country":"US",
    "sg:address":"7822 US Hwy 51 N",
    "sg:city":"Millington",
    "sg:classifiers":[
        {
            "category":"Restaurant",
            "type":"Food & Drink"
        }
    ],
    "sg:phone":"+1 901 872 4030",
    "sg:postcode":"38053",
    "sg:province":"TN",
    "wof:name":"Barb A Rosas Bar B Q",
    "wof:placetype":"venue"
},
  "geometry": {"coordinates":[-89.911473,35.339774],"type":"Point"}
}