{
  "type": "Feature",
  "properties": {
    "addr:full":"7135 Deadfall Rd Arlington TN 38002",
    "addr:housenumber":"7135",
    "addr:postcode":"38002",
    "addr:street":"Deadfall Rd",
    "iso:country":"US",
    "sg:address":"7135 Deadfall Rd",
    "sg:city":"Arlington",
    "sg:classifiers":[
        {
            "category":"Organizations",
            "subcategory":"Membership Organization",
            "type":"Services"
        }
    ],
    "sg:phone":"+1 901 829 3214",
    "sg:postcode":"38002",
    "sg:province":"TN",
    "wof:name":"Free & Accepted Masons of",
    "wof:placetype":"venue"
},
  "geometry": {"coordinates":[-89.733335,35.328959],"type":"Point"}
}