{
  "type": "Feature",
  "properties": {
    "addr:full":"235 E Sullivan St Kingsport TN 37660",
    "addr:housenumber":"235",
    "addr:postcode":"37660",
    "addr:street":"E Sullivan St",
    "iso:country":"US",
    "sg:address":"235 E Sullivan St",
    "sg:city":"Kingsport",
    "sg:classifiers":[
        {
            "category":"Insurance",
            "subcategory":"Insurance Agent",
            "type":"Services"
        }
    ],
    "sg:phone":"+1 423 390 2105",
    "sg:postcode":"37660",
    "sg:province":"TN",
    "wof:name":"Primerica Financial Svc",
    "wof:placetype":"venue"
},
  "geometry": {"coordinates":[-82.55734699999999,36.548226],"type":"Point"}
}