{
  "type": "Feature",
  "properties": {
    "addr:full":"6300 Asheville Hwy Knoxville TN 37924",
    "addr:postcode":"6300;37924",
    "addr:street":"Asheville Hwy",
    "iso:country":"US",
    "sg:address":"6300 Asheville Hwy",
    "sg:city":"Knoxville",
    "sg:classifiers":[
        {
            "category":"Travel",
            "subcategory":"Hotels & Motels",
            "type":"Entertainment"
        }
    ],
    "sg:phone":"+1 865 525 8001",
    "sg:postcode":"37924",
    "sg:province":"TN",
    "wof:name":"Gateway Inn",
    "wof:placetype":"venue"
},
  "geometry": {"coordinates":[-83.817111,36.017638],"type":"Point"}
}