{
  "type": "Feature",
  "properties": {
    "addr:full":"274 Mallory Station Rd Franklin TN 37067",
    "addr:housenumber":"274",
    "addr:postcode":"37067",
    "addr:street":"Mallory Station Rd",
    "iso:country":"US",
    "sg:address":"274 Mallory Station Rd",
    "sg:city":"Franklin",
    "sg:classifiers":[
        {
            "category":"Professional",
            "subcategory":"Computer Services",
            "type":"Services"
        }
    ],
    "sg:phone":"+1 615 504 4700",
    "sg:postcode":"37067",
    "sg:province":"TN",
    "sg:tags":[
        "repair"
    ],
    "wof:name":"Techopoly On-Site Computer Svc",
    "wof:placetype":"venue"
},
  "geometry": {"coordinates":[-86.831616,35.955883],"type":"Point"}
}