{
  "type": "Feature",
  "properties": {
    "addr:full":"6815 Stage Rd Memphis TN 38134",
    "addr:housenumber":"6815",
    "addr:postcode":"38134",
    "addr:street":"Stage Rd",
    "iso:country":"US",
    "sg:address":"6815 Stage Rd",
    "sg:city":"Memphis",
    "sg:classifiers":[
        {
            "category":"Restaurant",
            "type":"Food & Drink"
        }
    ],
    "sg:menulink":"http://www.allmenus.com/tn/memphis/29950-cks-coffee-shop/menu/",
    "sg:phone":"+1 901 388 6522",
    "sg:postcode":"38134",
    "sg:province":"TN",
    "sg:tags":[
        "american",
        "diner"
    ],
    "wof:name":"CK's Coffee Shop",
    "wof:placetype":"venue"
},
  "geometry": {"coordinates":[-89.836108,35.205082],"type":"Point"}
}