{
  "type": "Feature",
  "properties": {
    "iso:country":"US",
    "sg:address":"1010 Market St",
    "sg:city":"Chattanooga",
    "sg:classifiers":[
        {
            "category":"Professional",
            "subcategory":"Lawyer & Legal Services",
            "type":"Services"
        }
    ],
    "sg:phone":"+1 423 756 3452",
    "sg:postcode":"37402",
    "sg:province":"TN",
    "wof:name":"Arvin H Reingold",
    "wof:placetype":"venue"
},
  "geometry": {"coordinates":[-85.30943499999999,35.044158],"type":"Point"}
}