{
  "type": "Feature",
  "properties": {
    "iso:country":"US",
    "sg:address":"817 Pineville Rd",
    "sg:city":"Chattanooga",
    "sg:classifiers":[
        {
            "category":"Wholesale",
            "subcategory":"Petroleum",
            "type":"Manufacturing & Wholesale Goods"
        }
    ],
    "sg:phone":"+1 423 266 3287",
    "sg:postcode":"37405",
    "sg:province":"TN",
    "sg:tags":[
        "pipe",
        "line",
        "company"
    ],
    "sg:website":"www.colpipe.com",
    "wof:name":"Colonial Pipeline Co",
    "wof:placetype":"venue"
},
  "geometry": {"coordinates":[-85.33026099999999,35.067195],"type":"Point"}
}