{
  "type": "Feature",
  "properties": {
    "iso:country":"US",
    "sg:address":"2915 Tipton Station Rd",
    "sg:city":"Knoxville",
    "sg:classifiers":[
        {
            "category":"Personal",
            "subcategory":"Beauty Salon",
            "type":"Services"
        }
    ],
    "sg:phone":"+1 865 573 4037",
    "sg:postcode":"37920",
    "sg:province":"TN",
    "sg:tags":[
        "shop"
    ],
    "wof:name":"Sylvias Hair Fashions",
    "wof:placetype":"venue"
},
  "geometry": {"coordinates":[-83.917276,35.879998],"type":"Point"}
}