{
  "type": "Feature",
  "properties": {
    "addr:full":"2039 Hunterwood Dr Brentwood TN 37027",
    "addr:housenumber":"2039",
    "addr:postcode":"37027",
    "addr:street":"Hunterwood Dr",
    "iso:country":"US",
    "sg:address":"2039 Hunterwood Dr",
    "sg:city":"Brentwood",
    "sg:classifiers":[
        {
            "category":"Professional",
            "subcategory":"Management & Consulting",
            "type":"Services"
        }
    ],
    "sg:phone":"+1 615 370 3389",
    "sg:postcode":"37027",
    "sg:province":"TN",
    "wof:name":"Enc Project Management Inc",
    "wof:placetype":"venue"
},
  "geometry": {"coordinates":[-86.886017,36.013204],"type":"Point"}
}