{
  "type": "Feature",
  "properties": {
    "iso:country":"US",
    "sg:address":"2817 Emery Dr",
    "sg:city":"Nashville",
    "sg:classifiers":[
        {
            "category":"Retail",
            "subcategory":"Repair Shop",
            "type":"Services"
        }
    ],
    "sg:phone":"+1 615 871 0363",
    "sg:postcode":"37214",
    "sg:province":"TN",
    "sg:tags":[
        "appliance"
    ],
    "wof:name":"Ralph's Appliance Repair Svc",
    "wof:placetype":"venue"
},
  "geometry": {"coordinates":[-86.66499899999999,36.156559],"type":"Point"}
}