{
  "type": "Feature",
  "properties": {
    "iso:country":"US",
    "sg:address":"107 Shevel Dr",
    "sg:city":"Goodlettsville",
    "sg:classifiers":[
        {
            "category":"Home & Garden",
            "subcategory":"Building Materials",
            "type":"Retail Goods"
        }
    ],
    "sg:phone":"+1 615 859 0418",
    "sg:postcode":"37072",
    "sg:province":"TN",
    "sg:tags":[
        "paint",
        "wallpaper",
        "store",
        "glass"
    ],
    "wof:name":"Sloan Glass",
    "wof:placetype":"venue"
},
  "geometry": {"coordinates":[-86.712787,36.31294],"type":"Point"}
}