{
  "type": "Feature",
  "properties": {
    "iso:country":"US",
    "sg:address":"1217 Tuckaleechee Trl",
    "sg:city":"Maryville",
    "sg:classifiers":[
        {
            "category":"Communications",
            "subcategory":"Radio Station",
            "type":"Services"
        }
    ],
    "sg:phone":"+1 865 983 9111",
    "sg:postcode":"37803",
    "sg:province":"TN",
    "sg:tags":[
        "company",
        "broadcasting"
    ],
    "wof:name":"WBCR 1470 AM Radio Brdcstng",
    "wof:placetype":"venue"
},
  "geometry": {"coordinates":[-83.912347,35.752441],"type":"Point"}
}