{
  "type": "Feature",
  "properties": {
    "addr:full":"2000 Jonesborough Rd Erwin TN 37650",
    "addr:postcode":"37650",
    "addr:street":"Jonesborough Rd",
    "iso:country":"US",
    "sg:address":"2000 Jonesborough Rd",
    "sg:city":"Erwin",
    "sg:classifiers":[
        {
            "category":"Autos & Motor Vehicles",
            "subcategory":"Boat Sales",
            "type":"Retail Goods"
        },
        {
            "category":"Recreation",
            "type":"Entertainment"
        }
    ],
    "sg:phone":"+1 423 743 7733",
    "sg:postcode":"37650",
    "sg:province":"TN",
    "sg:tags":[
        "operator",
        "rafts",
        "tour"
    ],
    "sg:website":"www.cherokeeadventures.com",
    "wof:name":"Cherokee Adventures Inc",
    "wof:placetype":"venue"
},
  "geometry": {"coordinates":[-82.441492,36.146638],"type":"Point"}
}