{
  "type": "Feature",
  "properties": {
    "addr:full":"423 E M L King Blvd Chattanooga TN 37403",
    "addr:housenumber":"423",
    "addr:postcode":"37403",
    "addr:street":"E M L King Blvd",
    "iso:country":"US",
    "sg:address":"423 E M L King Blvd",
    "sg:city":"Chattanooga",
    "sg:classifiers":[
        {
            "category":"Personal",
            "subcategory":"Barber",
            "type":"Services"
        }
    ],
    "sg:phone":"+1 423 756 9785",
    "sg:postcode":"37403",
    "sg:province":"TN",
    "sg:tags":[
        "shop"
    ],
    "wof:name":"Renewal Barber Shop",
    "wof:placetype":"venue"
},
  "geometry": {"coordinates":[-85.303023,35.04389],"type":"Point"}
}