{
  "type": "Feature",
  "properties": {
    "iso:country":"US",
    "sg:address":"7707 Shallowford Rd",
    "sg:city":"Chattanooga",
    "sg:classifiers":[
        {
            "category":"Building & Trades",
            "subcategory":"Construction",
            "type":"Services"
        }
    ],
    "sg:phone":"+1 423 648 4220",
    "sg:postcode":"37421",
    "sg:province":"TN",
    "sg:tags":[
        "builder",
        "operative"
    ],
    "wof:name":"Harvest Active Adult Cmnty LLC",
    "wof:placetype":"venue"
},
  "geometry": {"coordinates":[-85.13708200000001,35.035608],"type":"Point"}
}