{
  "type": "Feature",
  "properties": {
    "iso:country":"US",
    "sg:address":"5069 Country View Ln",
    "sg:city":"Memphis",
    "sg:classifiers":[
        {
            "category":"Professional",
            "subcategory":"Business Services",
            "type":"Services"
        }
    ],
    "sg:phone":"+1 901 380 3343",
    "sg:postcode":"38134",
    "sg:province":"TN",
    "wof:name":"Tcd Contracting Enterprises",
    "wof:placetype":"venue"
},
  "geometry": {"coordinates":[-89.893207,35.194487],"type":"Point"}
}