{
  "type": "Feature",
  "properties": {
    "addr:full":"3014 Old Clarksville Springfield Rd Adams TN 37010",
    "addr:housenumber":"3014",
    "addr:postcode":"37010",
    "addr:street":"Old Clarksville Springfield Rd",
    "iso:country":"US",
    "sg:address":"3014 Old Clarksville Springfield Rd",
    "sg:city":"Adams",
    "sg:classifiers":[
        {
            "category":"Organizations",
            "subcategory":"Community Association",
            "type":"Services"
        }
    ],
    "sg:phone":"+1 931 368 0225",
    "sg:postcode":"37010",
    "sg:province":"TN",
    "sg:tags":[
        "fraternal"
    ],
    "wof:name":"Benevolent Lodge Order 210",
    "wof:placetype":"venue"
},
  "geometry": {"coordinates":[-87.14709000000001,36.553391],"type":"Point"}
}