{
  "type": "Feature",
  "properties": {
    "iso:country":"US",
    "sg:address":"2460 Old Hwy 25E",
    "sg:city":"Tazewell",
    "sg:classifiers":[
        {
            "category":"Autos & Motor Vehicles",
            "subcategory":"Fuel & Gas Station",
            "type":"Retail Goods"
        }
    ],
    "sg:phone":"+1 423 626 5041",
    "sg:postcode":"37879",
    "sg:province":"TN",
    "sg:tags":[
        "convenience",
        "store"
    ],
    "wof:name":"Marsh Petroleum Co",
    "wof:placetype":"venue"
},
  "geometry": {"coordinates":[-83.582461,36.477929],"type":"Point"}
}