{
  "type": "Feature",
  "properties": {
    "iso:country":"US",
    "sg:address":"925 E Baddour Pkwy",
    "sg:city":"Lebanon",
    "sg:classifiers":[
        {
            "category":"Government",
            "subcategory":"Office",
            "type":"Public Place"
        }
    ],
    "sg:phone":"+1 615 444 1890",
    "sg:postcode":"37087",
    "sg:province":"TN",
    "sg:tags":[
        "farm",
        "agency"
    ],
    "wof:name":"Farm Service Agency",
    "wof:placetype":"venue"
},
  "geometry": {"coordinates":[-86.27562,36.199916],"type":"Point"}
}