{
  "type": "Feature",
  "properties": {
    "iso:country":"US",
    "sg:address":"7760 Valley View Hwy",
    "sg:city":"Whitwell",
    "sg:classifiers":[
        {
            "category":"Building & Trades",
            "subcategory":"Landscaping Services",
            "type":"Services"
        }
    ],
    "sg:phone":"+1 423 658 2722",
    "sg:postcode":"37397",
    "sg:province":"TN",
    "sg:tags":[
        "landscape"
    ],
    "wof:name":"Layne Brothers Construction",
    "wof:placetype":"venue"
},
  "geometry": {"coordinates":[-85.55385699999999,35.1548],"type":"Point"}
}