{
  "type": "Feature",
  "properties": {
    "addr:full":"701 Blueberry Hills Rd NE Cleveland TN 37312",
    "addr:housenumber":"701",
    "addr:postcode":"37312",
    "addr:street":"Blueberry Hills Rd Ne",
    "iso:country":"US",
    "sg:address":"701 Blueberry Hills Rd NE",
    "sg:city":"Cleveland",
    "sg:classifiers":[
        {
            "category":"Building & Trades",
            "subcategory":"Construction",
            "type":"Services"
        }
    ],
    "sg:phone":"+1 423 478 5568",
    "sg:postcode":"37312",
    "sg:province":"TN",
    "sg:tags":[
        "house"
    ],
    "wof:name":"Davis Construction",
    "wof:placetype":"venue"
},
  "geometry": {"coordinates":[-84.841864,35.187753],"type":"Point"}
}