{
  "type": "Feature",
  "properties": {
    "iso:country":"US",
    "sg:address":"1269 Hardison Rd",
    "sg:city":"Columbia",
    "sg:classifiers":[
        {
            "category":"Shopping",
            "type":"Retail Goods"
        }
    ],
    "sg:phone":"+1 931 486 1067",
    "sg:postcode":"38401",
    "sg:province":"TN",
    "sg:tags":[
        "picture",
        "frame"
    ],
    "wof:name":"Southern Prints & Framing",
    "wof:placetype":"venue"
},
  "geometry": {"coordinates":[-87.016654,35.737331],"type":"Point"}
}