{
  "type": "Feature",
  "properties": {
    "addr:full":"8532 Snow Ridge Dr Ooltewah TN 37363",
    "addr:housenumber":"8532",
    "addr:postcode":"37363",
    "addr:street":"Snow Ridge Dr",
    "iso:country":"US",
    "sg:address":"8532 Snow Ridge Dr",
    "sg:city":"Ooltewah",
    "sg:classifiers":[
        {
            "category":"Professional",
            "type":"Services"
        }
    ],
    "sg:phone":"+1 423 238 6811",
    "sg:postcode":"37363",
    "sg:province":"TN",
    "wof:name":"Jet Source One LLC",
    "wof:placetype":"venue"
},
  "geometry": {"coordinates":[-85.067859,35.120702],"type":"Point"}
}