{
  "type": "Feature",
  "properties": {
    "addr:full":"2744 W Andrew Johnson Hwy Morristown TN 37814",
    "addr:housenumber":"2744",
    "addr:postcode":"37814",
    "addr:street":"W Andrew Johnson Hwy",
    "iso:country":"US",
    "sg:address":"2744 W Andrew Johnson Hwy",
    "sg:city":"Morristown",
    "sg:classifiers":[
        {
            "category":"Home & Garden",
            "subcategory":"Building Materials",
            "type":"Retail Goods"
        }
    ],
    "sg:phone":"+1 423 317 7727",
    "sg:postcode":"37814",
    "sg:province":"TN",
    "sg:tags":[
        "center"
    ],
    "wof:name":"Lowe's",
    "wof:placetype":"venue"
},
  "geometry": {"coordinates":[-83.331744,36.202208],"type":"Point"}
}