{
  "type": "Feature",
  "properties": {
    "iso:country":"US",
    "sg:address":"100 S Main St",
    "sg:city":"Goodlettsville",
    "sg:classifiers":[
        {
            "category":"Organizations",
            "subcategory":"Community Association",
            "type":"Services"
        }
    ],
    "sg:phone":"+1 615 859 1480",
    "sg:postcode":"37072",
    "sg:province":"TN",
    "sg:tags":[
        "chamber",
        "commerce"
    ],
    "wof:name":"Goodlettsville Area Chamber Of Commerce",
    "wof:placetype":"venue"
},
  "geometry": {"coordinates":[-86.713295,36.322254],"type":"Point"}
}