{
  "type": "Feature",
  "properties": {
    "iso:country":"US",
    "sg:address":"4437 Shepard Pl",
    "sg:city":"Nashville",
    "sg:classifiers":[
        {
            "category":"Banks & Credit Unions",
            "subcategory":"Financial Services",
            "type":"Services"
        }
    ],
    "sg:phone":"+1 615 385 0255",
    "sg:postcode":"37205",
    "sg:province":"TN",
    "sg:tags":[
        "company",
        "holding"
    ],
    "wof:name":"Ramsey Investments LP",
    "wof:placetype":"venue"
},
  "geometry": {"coordinates":[-86.85664199999999,36.097067],"type":"Point"}
}