{
  "type": "Feature",
  "properties": {
    "iso:country":"US",
    "sg:address":"4233 Lucy Rd",
    "sg:city":"Millington",
    "sg:classifiers":[
        {
            "category":"Building & Trades",
            "subcategory":"Construction",
            "type":"Services"
        }
    ],
    "sg:phone":"+1 901 872 4135",
    "sg:postcode":"38053",
    "sg:province":"TN",
    "sg:tags":[
        "wallcoverings-installation",
        "wallpaper",
        "painting",
        "contractor"
    ],
    "wof:name":"Sawyer Painting",
    "wof:placetype":"venue"
},
  "geometry": {"coordinates":[-89.925468,35.305882],"type":"Point"}
}