{
  "type": "Feature",
  "properties": {
    "addr:full":"601 Congress Pkwy NW Athens TN 37303",
    "addr:housenumber":"601",
    "addr:postcode":"37303",
    "addr:street":"Congress Pkwy Nw",
    "iso:country":"US",
    "sg:address":"601 Congress Pkwy NW",
    "sg:city":"Athens",
    "sg:classifiers":[
        {
            "category":"Wholesale",
            "subcategory":"Machinery & Supplies",
            "type":"Manufacturing & Wholesale Goods"
        }
    ],
    "sg:phone":"+1 423 746 0252",
    "sg:postcode":"37303",
    "sg:province":"TN",
    "sg:tags":[
        "equipment",
        "industrial"
    ],
    "sg:website":"www.fastenal.com",
    "wof:name":"Fastenal Co",
    "wof:placetype":"venue"
},
  "geometry": {"coordinates":[-84.613457,35.460495],"type":"Point"}
}