{
  "type": "Feature",
  "properties": {
    "iso:country":"US",
    "sg:address":"920 Pickwick St S",
    "sg:city":"Savannah",
    "sg:classifiers":[
        {
            "category":"Wholesale",
            "subcategory":"Medical Equipment & Supplies",
            "type":"Manufacturing & Wholesale Goods"
        }
    ],
    "sg:phone":"+1 731 926 3702",
    "sg:postcode":"38372",
    "sg:province":"TN",
    "sg:tags":[
        "physician",
        "surgeon"
    ],
    "wof:name":"Family Homecare Inc",
    "wof:placetype":"venue"
},
  "geometry": {"coordinates":[-88.244969,35.211092],"type":"Point"}
}