{
  "type": "Feature",
  "properties": {
    "addr:full":"114 N Market St Paris TN 38242",
    "addr:housenumber":"114",
    "addr:postcode":"38242",
    "addr:street":"N Market St",
    "iso:country":"US",
    "sg:address":"114 N Market St",
    "sg:city":"Paris",
    "sg:classifiers":[
        {
            "category":"Shopping",
            "subcategory":"Jewelry",
            "type":"Retail Goods"
        }
    ],
    "sg:phone":"+1 731 642 0881",
    "sg:postcode":"38242",
    "sg:province":"TN",
    "sg:tags":[
        "jeweler"
    ],
    "wof:name":"Moon's Jewelry & Repair",
    "wof:placetype":"venue"
},
  "geometry": {"coordinates":[-88.326431,36.302637],"type":"Point"}
}