{
  "type": "Feature",
  "properties": {
    "iso:country":"US",
    "sg:address":"165 Carnavon Pkwy",
    "sg:city":"Nashville",
    "sg:classifiers":[
        {
            "category":"Professional",
            "subcategory":"Business Services",
            "type":"Services"
        }
    ],
    "sg:phone":"+1 615 352 4509",
    "sg:postcode":"37205",
    "sg:province":"TN",
    "wof:name":"B Mc Music Inc",
    "wof:placetype":"venue"
},
  "geometry": {"coordinates":[-86.904522,36.090533],"type":"Point"}
}