{
  "type": "Feature",
  "properties": {
    "iso:country":"US",
    "sg:address":"316 Beersheba Hwy",
    "sg:city":"Mc Minnville",
    "sg:classifiers":[
        {
            "category":"Retail",
            "subcategory":"Auto Repair",
            "type":"Services"
        }
    ],
    "sg:phone":"+1 931 473 2673",
    "sg:postcode":"37110",
    "sg:province":"TN",
    "sg:tags":[
        "repairing",
        "automobile"
    ],
    "wof:name":"Mc Minnville Radiator Svc",
    "wof:placetype":"venue"
},
  "geometry": {"coordinates":[-85.762944,35.678209],"type":"Point"}
}