{
  "type": "Feature",
  "properties": {
    "addr:full":"1201 Villa Pl Nashville TN 37212",
    "addr:housenumber":"1201",
    "addr:postcode":"37212",
    "addr:street":"Villa Pl",
    "iso:country":"US",
    "sg:address":"1201 Villa Pl",
    "sg:city":"Nashville",
    "sg:classifiers":[
        {
            "category":"Personal",
            "subcategory":"Beauty Salon",
            "type":"Services"
        }
    ],
    "sg:phone":"+1 615 321 1363",
    "sg:postcode":"37212",
    "sg:province":"TN",
    "sg:website":"www.eyecandysalon.net",
    "wof:name":"Eye Candy",
    "wof:placetype":"venue"
},
  "geometry": {"coordinates":[-86.792395,36.140609],"type":"Point"}
}