{
  "type": "Feature",
  "properties": {
    "iso:country":"US",
    "sg:address":"106 Earline Ave",
    "sg:city":"Hendersonville",
    "sg:classifiers":[
        {
            "category":"Shopping",
            "subcategory":"Catalog Store",
            "type":"Retail Goods"
        }
    ],
    "sg:phone":"+1 615 824 3043",
    "sg:postcode":"37075",
    "sg:province":"TN",
    "sg:tags":[
        "mail",
        "house"
    ],
    "wof:name":"Avon Mgmt",
    "wof:placetype":"venue"
},
  "geometry": {"coordinates":[-86.617017,36.254457],"type":"Point"}
}