{
  "type": "Feature",
  "properties": {
    "iso:country":"US",
    "sg:address":"1700 Clinch Ave",
    "sg:city":"Knoxville",
    "sg:classifiers":[
        {
            "category":"Real Estate",
            "subcategory":"Real Estate Operator",
            "type":"Services"
        }
    ],
    "sg:phone":"+1 865 521 8355",
    "sg:postcode":"37916",
    "sg:province":"TN",
    "sg:tags":[
        "condominium"
    ],
    "wof:name":"University Towers Condominiums",
    "wof:placetype":"venue"
},
  "geometry": {"coordinates":[-83.934834,35.957688],"type":"Point"}
}