{
  "type": "Feature",
  "properties": {
    "addr:full":"4251 Mackham Cove Memphis TN 38118",
    "addr:housenumber":"4251",
    "addr:postcode":"38118",
    "addr:street":"Mackham Cove",
    "iso:country":"US",
    "sg:address":"4251 Mackham Cove",
    "sg:city":"Memphis",
    "sg:classifiers":[
        {
            "category":"Shopping",
            "subcategory":"Florist",
            "type":"Retail Goods"
        }
    ],
    "sg:phone":"+1 901 365 4466",
    "sg:postcode":"38118",
    "sg:province":"TN",
    "wof:name":"Dreamspun Creations",
    "wof:placetype":"venue"
},
  "geometry": {"coordinates":[-89.959524,35.032621],"type":"Point"}
}