{
  "type": "Feature",
  "properties": {
    "addr:full":"5411 Fountain Rd NE Knoxville TN 37918",
    "addr:housenumber":"5411",
    "addr:postcode":"37918",
    "addr:street":"Fountain Rd Ne",
    "iso:country":"US",
    "sg:address":"5411 Fountain Rd NE",
    "sg:city":"Knoxville",
    "sg:classifiers":[
        {
            "category":"Health Services",
            "subcategory":"Clinic",
            "type":"Services"
        }
    ],
    "sg:phone":"+1 865 545 3500",
    "sg:postcode":"37918",
    "sg:province":"TN",
    "sg:tags":[
        "home"
    ],
    "wof:name":"St Mary's Home Health Svc",
    "wof:placetype":"venue"
},
  "geometry": {"coordinates":[-83.933712,36.035662],"type":"Point"}
}