{
  "type": "Feature",
  "properties": {
    "iso:country":"US",
    "sg:address":"110 Hassell Dr",
    "sg:city":"Clifton",
    "sg:classifiers":[
        {
            "category":"Sports & Exercise",
            "subcategory":"Golf",
            "type":"Entertainment"
        }
    ],
    "sg:phone":"+1 931 676 3174",
    "sg:postcode":"38425",
    "sg:province":"TN",
    "sg:tags":[
        "resort"
    ],
    "wof:name":"Bear Trace & Ross Creek",
    "wof:placetype":"venue"
},
  "geometry": {"coordinates":[-88.05018,35.389886],"type":"Point"}
}