{
  "type": "Feature",
  "properties": {
    "iso:country":"US",
    "sg:address":"108 N Maple St",
    "sg:city":"Lebanon",
    "sg:classifiers":[
        {
            "category":"Sports & Exercise",
            "subcategory":"Race Track",
            "type":"Entertainment"
        }
    ],
    "sg:phone":"+1 615 847 4435",
    "sg:postcode":"37087",
    "sg:province":"TN",
    "wof:name":"Thurman Racing",
    "wof:placetype":"venue"
},
  "geometry": {"coordinates":[-86.292427,36.208855],"type":"Point"}
}