{
  "type": "Feature",
  "properties": {
    "addr:full":"237 Ardmore Hwy Fayetteville TN 37334",
    "addr:housenumber":"237",
    "addr:postcode":"37334",
    "addr:street":"Ardmore Hwy",
    "iso:country":"US",
    "sg:address":"237 Ardmore Hwy",
    "sg:city":"Fayetteville",
    "sg:classifiers":[
        {
            "category":"Shopping",
            "subcategory":"Musical Instruments",
            "type":"Retail Goods"
        }
    ],
    "sg:phone":"+1 931 433 0277",
    "sg:postcode":"37334",
    "sg:province":"TN",
    "sg:tags":[
        "music",
        "dealer"
    ],
    "wof:name":"Smartt's Music & Outlet",
    "wof:placetype":"venue"
},
  "geometry": {"coordinates":[-86.5857,35.100724],"type":"Point"}
}