{
  "type": "Feature",
  "properties": {
    "iso:country":"US",
    "sg:address":"2636 Vesta Rd",
    "sg:city":"Lebanon",
    "sg:classifiers":[
        {
            "category":"Arts & Performance",
            "subcategory":"Theater",
            "type":"Entertainment"
        }
    ],
    "sg:phone":"+1 615 547 0341",
    "sg:postcode":"37090",
    "sg:province":"TN",
    "sg:tags":[
        "talent",
        "agency",
        "casting"
    ],
    "wof:name":"Top Notch Talent",
    "wof:placetype":"venue"
},
  "geometry": {"coordinates":[-86.39010399999999,36.062474],"type":"Point"}
}