{
  "type": "Feature",
  "properties": {
    "iso:country":"US",
    "sg:address":"7519 Delbridge Rd",
    "sg:city":"Murfreesboro",
    "sg:classifiers":[
        {
            "category":"Recreation",
            "type":"Entertainment"
        }
    ],
    "sg:phone":"+1 615 459 5917",
    "sg:postcode":"37127",
    "sg:province":"TN",
    "wof:name":"Park Place Construction",
    "wof:placetype":"venue"
},
  "geometry": {"coordinates":[-86.307604,35.736653],"type":"Point"}
}