{
  "type": "Feature",
  "properties": {
    "iso:country":"US",
    "sg:address":"1880 Kimbrough Rd",
    "sg:city":"Germantown",
    "sg:classifiers":[
        {
            "category":"Real Estate",
            "subcategory":"Real Estate Operator",
            "type":"Services"
        }
    ],
    "sg:phone":"+1 901 754 2140",
    "sg:postcode":"38138",
    "sg:province":"TN",
    "sg:tags":[
        "building",
        "apartment"
    ],
    "wof:name":"Chardonnay Apartments",
    "wof:placetype":"venue"
},
  "geometry": {"coordinates":[-89.79077100000001,35.096515],"type":"Point"}
}