{
  "type": "Feature",
  "properties": {
    "iso:country":"US",
    "sg:address":"1118 State Hwy 163",
    "sg:city":"Calhoun",
    "sg:classifiers":[
        {
            "category":"Autos & Motor Vehicles",
            "subcategory":"Automobile Sales",
            "type":"Retail Goods"
        }
    ],
    "sg:phone":"+1 423 336 5084",
    "sg:postcode":"37309",
    "sg:province":"TN",
    "sg:tags":[
        "used"
    ],
    "wof:name":"Hiwassee Motors Inc",
    "wof:placetype":"venue"
},
  "geometry": {"coordinates":[-84.720296,35.30706],"type":"Point"}
}