{
  "type": "Feature",
  "properties": {
    "iso:country":"US",
    "sg:address":"6727 Heritage Business Ct",
    "sg:city":"Chattanooga",
    "sg:classifiers":[
        {
            "category":"Shopping",
            "subcategory":"Books",
            "type":"Retail Goods"
        }
    ],
    "sg:phone":"+1 423 894 6446",
    "sg:postcode":"37421",
    "sg:province":"TN",
    "wof:name":"Gideons Intl Northeast Camp",
    "wof:placetype":"venue"
},
  "geometry": {"coordinates":[-85.174482,35.035925],"type":"Point"}
}