{
  "type": "Feature",
  "properties": {
    "iso:country":"US",
    "sg:address":"475 N Germantown Pkwy",
    "sg:city":"Cordova",
    "sg:classifiers":[
        {
            "category":"Shopping",
            "subcategory":"Optical Goods",
            "type":"Retail Goods"
        }
    ],
    "sg:phone":"+1 901 248 0203",
    "sg:postcode":"38018",
    "sg:province":"TN",
    "wof:name":"Target Optical",
    "wof:placetype":"venue"
},
  "geometry": {"coordinates":[-89.79586999999999,35.137407],"type":"Point"}
}