{
  "type": "Feature",
  "properties": {
    "addr:full":"3942 Macon Rd Memphis TN 38122",
    "addr:housenumber":"3942",
    "addr:postcode":"38122",
    "addr:street":"Macon Rd",
    "iso:country":"US",
    "sg:address":"3942 Macon Rd",
    "sg:city":"Memphis",
    "sg:classifiers":[
        {
            "category":"Banks & Credit Unions",
            "subcategory":"Bank",
            "type":"Services"
        }
    ],
    "sg:phone":"+1 901 324 3759",
    "sg:postcode":"38122",
    "sg:province":"TN",
    "wof:name":"Western Union",
    "wof:placetype":"venue"
},
  "geometry": {"coordinates":[-89.929027,35.162317],"type":"Point"}
}