{
  "type": "Feature",
  "properties": {
    "addr:full":"117 Oak St Smyrna TN 37167",
    "addr:housenumber":"117",
    "addr:postcode":"37167",
    "addr:street":"Oak St",
    "iso:country":"US",
    "sg:address":"117 Oak St",
    "sg:city":"Smyrna",
    "sg:classifiers":[
        {
            "category":"Building & Trades",
            "subcategory":"Landscaping Services",
            "type":"Services"
        }
    ],
    "sg:phone":"+1 615 812 2326",
    "sg:postcode":"37167",
    "sg:province":"TN",
    "sg:tags":[
        "lawn",
        "maintenance",
        "grounds"
    ],
    "wof:name":"Garden Of Eden",
    "wof:placetype":"venue"
},
  "geometry": {"coordinates":[-86.515607,35.983716],"type":"Point"}
}