{
  "type": "Feature",
  "properties": {
    "addr:full":"151 Meek St Martin TN 38237",
    "addr:housenumber":"151",
    "addr:postcode":"38237",
    "addr:street":"Meek St",
    "iso:country":"US",
    "sg:address":"151 Meek St",
    "sg:city":"Martin",
    "sg:classifiers":[
        {
            "category":"Freight",
            "type":"Transportation"
        }
    ],
    "sg:phone":"+1 731 587 4858",
    "sg:postcode":"38237",
    "sg:province":"TN",
    "sg:tags":[
        "distance",
        "long",
        "trucking"
    ],
    "wof:name":"Ducak Trucking",
    "wof:placetype":"venue"
},
  "geometry": {"coordinates":[-88.840402,36.337674],"type":"Point"}
}