{
  "type": "Feature",
  "properties": {
    "addr:full":"329 E Jere Whitson Rd Cookeville TN 38501",
    "addr:housenumber":"329",
    "addr:postcode":"38501",
    "addr:street":"E Jere Whitson Rd",
    "iso:country":"US",
    "sg:address":"329 E Jere Whitson Rd",
    "sg:city":"Cookeville",
    "sg:classifiers":[
        {
            "category":"Organizations",
            "subcategory":"Religious Organization",
            "type":"Services"
        }
    ],
    "sg:phone":"+1 931 526 6303",
    "sg:postcode":"38501",
    "sg:province":"TN",
    "wof:name":"Church Of Christ",
    "wof:placetype":"venue"
},
  "geometry": {"coordinates":[-85.498994,36.185305],"type":"Point"}
}