{
  "type": "Feature",
  "properties": {
    "addr:full":"3512 Blue Springs Rd Strawberry Plains TN 37871",
    "addr:housenumber":"3512",
    "addr:postcode":"37871",
    "addr:street":"Blue Springs Rd",
    "iso:country":"US",
    "sg:address":"3512 Blue Springs Rd",
    "sg:city":"Strawberry Plains",
    "sg:classifiers":[
        {
            "category":"Building & Trades",
            "subcategory":"Electrical",
            "type":"Services"
        }
    ],
    "sg:phone":"+1 865 932 3113",
    "sg:postcode":"37871",
    "sg:province":"TN",
    "sg:tags":[
        "electrical",
        "contractor"
    ],
    "wof:name":"J&K Electric",
    "wof:placetype":"venue"
},
  "geometry": {"coordinates":[-83.630555,36.055379],"type":"Point"}
}