{
  "type": "Feature",
  "properties": {
    "iso:country":"US",
    "sg:address":"2402 Winford Ave",
    "sg:city":"Nashville",
    "sg:classifiers":[
        {
            "category":"Professional",
            "subcategory":"Engineering",
            "type":"Services"
        }
    ],
    "sg:phone":"+1 615 255 7766",
    "sg:postcode":"37211",
    "sg:province":"TN",
    "sg:tags":[
        "civil",
        "engineer"
    ],
    "wof:name":"Joel B Spaulding & Co Inc",
    "wof:placetype":"venue"
},
  "geometry": {"coordinates":[-86.753888,36.117685],"type":"Point"}
}