{
  "type": "Feature",
  "properties": {
    "iso:country":"US",
    "sg:address":"8021 Schroeder Rd",
    "sg:city":"Powell",
    "sg:classifiers":[
        {
            "category":"Building & Trades",
            "subcategory":"Construction",
            "type":"Services"
        }
    ],
    "sg:phone":"+1 865 938 9117",
    "sg:postcode":"37849",
    "sg:province":"TN",
    "sg:tags":[
        "hanging",
        "contractor"
    ],
    "wof:name":"Chitwood Painting Gen Rep",
    "wof:placetype":"venue"
},
  "geometry": {"coordinates":[-83.99746500000001,36.064562],"type":"Point"}
}