{
  "type": "Feature",
  "properties": {
    "addr:full":"2427 Woodale Ln Nashville TN 37207",
    "addr:postcode":"2427;37207",
    "addr:street":"Woodale Ln",
    "iso:country":"US",
    "sg:address":"2427 Woodale Ln",
    "sg:city":"Nashville",
    "sg:classifiers":[
        {
            "category":"Arts & Performance",
            "subcategory":"Theater",
            "type":"Entertainment"
        }
    ],
    "sg:phone":"+1 615 485 3457",
    "sg:postcode":"37207",
    "sg:province":"TN",
    "sg:tags":[
        "bureau"
    ],
    "wof:name":"Get Money 2getha Entertainment",
    "wof:placetype":"venue"
},
  "geometry": {"coordinates":[-86.801098,36.221733],"type":"Point"}
}