{
  "type": "Feature",
  "properties": {
    "addr:full":"1224 Trotwood Ave Columbia TN 38401",
    "addr:housenumber":"1224",
    "addr:postcode":"38401",
    "addr:street":"Trotwood Ave",
    "iso:country":"US",
    "sg:address":"1224 Trotwood Ave",
    "sg:city":"Columbia",
    "sg:classifiers":[
        {
            "category":"Health Services",
            "subcategory":"Doctor",
            "type":"Services"
        }
    ],
    "sg:phone":"+1 931 388 8520",
    "sg:postcode":"38401",
    "sg:province":"TN",
    "sg:tags":[
        "medical"
    ],
    "wof:name":"Southern Radiation Oncologists",
    "wof:placetype":"venue"
},
  "geometry": {"coordinates":[-87.065513,35.606125],"type":"Point"}
}