{
  "type": "Feature",
  "properties": {
    "iso:country":"US",
    "sg:address":"6895 Arno Allisona Rd",
    "sg:city":"College Grove",
    "sg:classifiers":[
        {
            "category":"Building & Trades",
            "subcategory":"Landscaping Services",
            "type":"Services"
        }
    ],
    "sg:phone":"+1 615 368 7060",
    "sg:postcode":"37046",
    "sg:province":"TN",
    "sg:tags":[
        "supp",
        "f"
    ],
    "wof:name":"Scott Powers Landscaping",
    "wof:placetype":"venue"
},
  "geometry": {"coordinates":[-86.729803,35.75914],"type":"Point"}
}