{
  "type": "Feature",
  "properties": {
    "addr:full":"115 Sugar Limb Rd Lenoir City TN 37771",
    "addr:housenumber":"115",
    "addr:postcode":"37771",
    "addr:street":"Sugar Limb Rd",
    "iso:country":"US",
    "sg:address":"115 Sugar Limb Rd",
    "sg:city":"Lenoir City",
    "sg:classifiers":[
        {
            "category":"Local Transit",
            "type":"Transportation"
        }
    ],
    "sg:phone":"+1 865 986 8766",
    "sg:postcode":"37771",
    "sg:province":"TN",
    "sg:tags":[
        "ambulance"
    ],
    "wof:name":"Rural Metro Ambulance",
    "wof:placetype":"venue"
},
  "geometry": {"coordinates":[-84.318533,35.770429],"type":"Point"}
}