{
  "type": "Feature",
  "properties": {
    "addr:full":"3317 Winchester Rd Memphis TN 38118",
    "addr:housenumber":"3317",
    "addr:postcode":"38118",
    "addr:street":"Winchester Rd",
    "iso:country":"US",
    "sg:address":"3317 Winchester Rd",
    "sg:city":"Memphis",
    "sg:classifiers":[
        {
            "category":"Banks & Credit Unions",
            "subcategory":"Bank",
            "type":"Services"
        }
    ],
    "sg:phone":"+1 901 795 5046",
    "sg:postcode":"38118",
    "sg:province":"TN",
    "sg:tags":[
        "cashing",
        "check"
    ],
    "wof:name":"Ace Cash Express",
    "wof:placetype":"venue"
},
  "geometry": {"coordinates":[-89.95262200000001,35.052188],"type":"Point"}
}