{
  "type": "Feature",
  "properties": {
    "iso:country":"US",
    "sg:address":"816 Old Hwy 92",
    "sg:city":"Dandridge",
    "sg:classifiers":[
        {
            "category":"Government",
            "subcategory":"Office",
            "type":"Public Place"
        }
    ],
    "sg:phone":"+1 865 397 0915",
    "sg:postcode":"37725",
    "sg:province":"TN",
    "wof:name":"Tennessee State Government",
    "wof:placetype":"venue"
},
  "geometry": {"coordinates":[-83.429815,36.02799],"type":"Point"}
}