{
  "type": "Feature",
  "properties": {
    "iso:country":"US",
    "sg:address":"56 Casey Jones Ln",
    "sg:city":"Jackson",
    "sg:classifiers":[
        {
            "category":"Communications",
            "subcategory":"Radio Station",
            "type":"Services"
        }
    ],
    "sg:phone":"+1 731 664 3882",
    "sg:postcode":"38305",
    "sg:province":"TN",
    "sg:tags":[
        "company",
        "broadcasting"
    ],
    "wof:name":"WAMP",
    "wof:placetype":"venue"
},
  "geometry": {"coordinates":[-88.85533100000001,35.660459],"type":"Point"}
}