{
  "type": "Feature",
  "properties": {
    "iso:country":"US",
    "sg:address":"6870 Hillshire Dr",
    "sg:city":"Memphis",
    "sg:classifiers":[
        {
            "category":"Building & Trades",
            "subcategory":"Electrical",
            "type":"Services"
        }
    ],
    "sg:phone":"+1 901 373 8181",
    "sg:postcode":"38133",
    "sg:province":"TN",
    "sg:tags":[
        "electric",
        "contractor"
    ],
    "wof:name":"Gray Electric Co",
    "wof:placetype":"venue"
},
  "geometry": {"coordinates":[-89.834699,35.186343],"type":"Point"}
}