{
  "type": "Feature",
  "properties": {
    "iso:country":"US",
    "sg:address":"108 Mimosa Dr",
    "sg:city":"Greeneville",
    "sg:classifiers":[
        {
            "category":"Manufacturing",
            "subcategory":"Tools & Machinery",
            "type":"Manufacturing & Wholesale Goods"
        }
    ],
    "sg:phone":"+1 423 639 9771",
    "sg:postcode":"37745",
    "sg:province":"TN",
    "sg:tags":[
        "mfg",
        "repair",
        "industrial",
        "welding"
    ],
    "wof:name":"Quality Machine Products Co",
    "wof:placetype":"venue"
},
  "geometry": {"coordinates":[-82.813163,36.171629],"type":"Point"}
}