{
  "type": "Feature",
  "properties": {
    "addr:full":"1416 Antioch Pike Antioch TN 37013",
    "addr:housenumber":"1416",
    "addr:postcode":"37013",
    "addr:street":"Antioch Pike",
    "iso:country":"US",
    "sg:address":"1416 Antioch Pike",
    "sg:city":"Antioch",
    "sg:classifiers":[
        {
            "category":"Home & Garden",
            "subcategory":"Building Materials",
            "type":"Retail Goods"
        }
    ],
    "sg:phone":"+1 615 254 5955",
    "sg:postcode":"37013",
    "sg:province":"TN",
    "sg:tags":[
        "glass",
        "window",
        "plate"
    ],
    "wof:name":"Terry's Auto Glass Co",
    "wof:placetype":"venue"
},
  "geometry": {"coordinates":[-86.68804,36.082298],"type":"Point"}
}