{
  "type": "Feature",
  "properties": {
    "iso:country":"US",
    "sg:address":"452 E Mark Twain Ave",
    "sg:city":"Jamestown",
    "sg:classifiers":[
        {
            "category":"Government",
            "subcategory":"Office",
            "type":"Public Place"
        }
    ],
    "sg:phone":"+1 931 879 8212",
    "sg:postcode":"38556",
    "sg:province":"TN",
    "wof:name":"Fentress County Soil Cnsrvtn",
    "wof:placetype":"venue"
},
  "geometry": {"coordinates":[-84.92725,36.427987],"type":"Point"}
}