{
  "type": "Feature",
  "properties": {
    "iso:country":"US",
    "sg:address":"1318 Milestone Dr",
    "sg:city":"Collierville",
    "sg:classifiers":[
        {
            "category":"Professional",
            "subcategory":"Employment Agencies",
            "type":"Services"
        }
    ],
    "sg:phone":"+1 901 861 5804",
    "sg:postcode":"38017",
    "sg:province":"TN",
    "wof:name":"Job Search Prep Store",
    "wof:placetype":"venue"
},
  "geometry": {"coordinates":[-89.669454,35.075221],"type":"Point"}
}