{
  "type": "Feature",
  "properties": {
    "iso:country":"US",
    "sg:address":"893 Delaney Cove",
    "sg:city":"Memphis",
    "sg:classifiers":[
        {
            "category":"Freight",
            "type":"Transportation"
        }
    ],
    "sg:phone":"+1 901 396 8051",
    "sg:postcode":"38116",
    "sg:province":"TN",
    "sg:tags":[
        "trucking"
    ],
    "wof:name":"A Woman's Touch Trucking",
    "wof:placetype":"venue"
},
  "geometry": {"coordinates":[-90.033423,35.005175],"type":"Point"}
}