{
  "type": "Feature",
  "properties": {
    "iso:country":"US",
    "sg:address":"2189 Spicer Cv",
    "sg:city":"Memphis",
    "sg:classifiers":[
        {
            "category":"Health Services",
            "subcategory":"Doctor",
            "type":"Services"
        }
    ],
    "sg:phone":"+1 901 373 6291",
    "sg:postcode":"38134",
    "sg:province":"TN",
    "sg:tags":[
        "physician",
        "cardiology",
        "thoracic",
        "surgeons",
        "surgery",
        "surgeon",
        "cardiovascular"
    ],
    "wof:name":"Thoracic And Cardiovascular Surgery Association",
    "wof:placetype":"venue"
},
  "geometry": {"coordinates":[-89.890372,35.185],"type":"Point"}
}