{
  "type": "Feature",
  "properties": {
    "iso:country":"US",
    "sg:address":"410 E Iris Dr",
    "sg:city":"Nashville",
    "sg:classifiers":[
        {
            "category":"Shopping",
            "subcategory":"Hobbies, Toys, & Games",
            "type":"Retail Goods"
        }
    ],
    "sg:phone":"+1 615 298 2872",
    "sg:postcode":"37204",
    "sg:province":"TN",
    "sg:tags":[
        "house",
        "mfg",
        "p",
        "accessory",
        "doll"
    ],
    "wof:name":"Miniature Cottage Inc",
    "wof:placetype":"venue"
},
  "geometry": {"coordinates":[-86.762598,36.113849],"type":"Point"}
}