{
  "type": "Feature",
  "properties": {
    "addr:full":"124 Old Quick Rd Fayetteville TN 37334",
    "addr:housenumber":"124",
    "addr:postcode":"37334",
    "addr:street":"Old Quick Rd",
    "iso:country":"US",
    "sg:address":"124 Old Quick Rd",
    "sg:city":"Fayetteville",
    "sg:classifiers":[
        {
            "category":"Professional",
            "subcategory":"Business Services",
            "type":"Services"
        }
    ],
    "sg:phone":"+1 931 433 5564",
    "sg:postcode":"37334",
    "sg:province":"TN",
    "sg:tags":[
        "graphics"
    ],
    "wof:name":"Isotec LLC",
    "wof:placetype":"venue"
},
  "geometry": {"coordinates":[-86.554153,34.995483],"type":"Point"}
}