{
  "type": "Feature",
  "properties": {
    "iso:country":"US",
    "sg:address":"3279 Homewood Dr",
    "sg:city":"Memphis",
    "sg:classifiers":[
        {
            "category":"Building & Trades",
            "subcategory":"Cleaning & Sanitation",
            "type":"Services"
        }
    ],
    "sg:phone":"+1 901 383 7296",
    "sg:postcode":"38128",
    "sg:province":"TN",
    "sg:tags":[
        "janitor",
        "maintenance"
    ],
    "wof:name":"Duncan & Associates",
    "wof:placetype":"venue"
},
  "geometry": {"coordinates":[-89.92927899999999,35.216437],"type":"Point"}
}