{
  "type": "Feature",
  "properties": {
    "iso:country":"US",
    "sg:address":"403 College Ave",
    "sg:city":"Lawrenceburg",
    "sg:classifiers":[
        {
            "category":"Health Services",
            "subcategory":"Doctor",
            "type":"Services"
        }
    ],
    "sg:phone":"+1 931 363 1531",
    "sg:postcode":"38464",
    "sg:province":"TN",
    "wof:name":"Dugger G G DDS Ms PC",
    "wof:placetype":"venue"
},
  "geometry": {"coordinates":[-87.331285,35.235288],"type":"Point"}
}