{
  "type": "Feature",
  "properties": {
    "addr:full":"2806 Suck Creek Rd Chattanooga TN 37405",
    "addr:housenumber":"2806",
    "addr:postcode":"37405",
    "addr:street":"Suck Creek Rd",
    "iso:country":"US",
    "sg:address":"2806 Suck Creek Rd",
    "sg:city":"Chattanooga",
    "sg:classifiers":[
        {
            "category":"Food & Beverages",
            "subcategory":"Groceries & Convenience Stores",
            "type":"Retail Goods"
        }
    ],
    "sg:phone":"+1 423 886 0016",
    "sg:postcode":"37405",
    "sg:province":"TN",
    "sg:tags":[
        "grocer"
    ],
    "wof:name":"Little Store",
    "wof:placetype":"venue"
},
  "geometry": {"coordinates":[-85.390225,35.123401],"type":"Point"}
}