{
  "type": "Feature",
  "properties": {
    "addr:full":"1398 Florence Rd Savannah TN 38372",
    "addr:housenumber":"1398",
    "addr:postcode":"38372",
    "addr:street":"Florence Rd",
    "iso:country":"US",
    "sg:address":"1398 Florence Rd",
    "sg:city":"Savannah",
    "sg:classifiers":[
        {
            "category":"Retail",
            "subcategory":"Auto Repair",
            "type":"Services"
        }
    ],
    "sg:phone":"+1 731 926 2478",
    "sg:postcode":"38372",
    "sg:province":"TN",
    "sg:tags":[
        "repairing",
        "automobile"
    ],
    "wof:name":"Quality Car Care",
    "wof:placetype":"venue"
},
  "geometry": {"coordinates":[-88.23927399999999,35.202802],"type":"Point"}
}