{
  "type": "Feature",
  "properties": {
    "addr:full":"144 Taft Church Rd Sparta TN 38583",
    "addr:housenumber":"144",
    "addr:postcode":"38583",
    "addr:street":"Taft Church Rd",
    "iso:country":"US",
    "sg:address":"144 Taft Church Rd",
    "sg:city":"Sparta",
    "sg:classifiers":[
        {
            "category":"Food & Beverages",
            "subcategory":"Groceries & Convenience Stores",
            "type":"Retail Goods"
        }
    ],
    "sg:phone":"+1 931 738 2284",
    "sg:postcode":"38583",
    "sg:province":"TN",
    "wof:name":"Shell",
    "wof:placetype":"venue"
},
  "geometry": {"coordinates":[-85.48669599999999,35.930872],"type":"Point"}
}