{
  "type": "Feature",
  "properties": {
    "iso:country":"US",
    "sg:address":"2341 Covington Dr",
    "sg:city":"Morristown",
    "sg:classifiers":[
        {
            "category":"Wholesale",
            "subcategory":"Groceries",
            "type":"Manufacturing & Wholesale Goods"
        }
    ],
    "sg:phone":"+1 423 586 1681",
    "sg:postcode":"37814",
    "sg:province":"TN",
    "sg:tags":[
        "distributor",
        "independent",
        "baking"
    ],
    "wof:name":"Donald H Covington Distributor",
    "wof:placetype":"venue"
},
  "geometry": {"coordinates":[-83.38678299999999,36.232694],"type":"Point"}
}