{
  "type": "Feature",
  "properties": {
    "addr:full":"2191 Filmore Ave Memphis TN 38114",
    "addr:housenumber":"2191",
    "addr:postcode":"38114",
    "addr:street":"Filmore Ave",
    "iso:country":"US",
    "sg:address":"2191 Filmore Ave",
    "sg:city":"Memphis",
    "sg:classifiers":[
        {
            "category":"Building & Trades",
            "subcategory":"Plumbing",
            "type":"Services"
        }
    ],
    "sg:phone":"+1 901 743 0342",
    "sg:postcode":"38114",
    "sg:province":"TN",
    "sg:tags":[
        "plumbing",
        "contractor"
    ],
    "wof:name":"Mid South Plumbing & Htg Co",
    "wof:placetype":"venue"
},
  "geometry": {"coordinates":[-89.990033,35.093519],"type":"Point"}
}