{
  "type": "Feature",
  "properties": {
    "iso:country":"US",
    "sg:address":"7509 Kingston Pike",
    "sg:city":"Knoxville",
    "sg:classifiers":[
        {
            "category":"Travel",
            "subcategory":"Travel Agent",
            "type":"Entertainment"
        }
    ],
    "sg:phone":"+1 865 679 2066",
    "sg:postcode":"37919",
    "sg:province":"TN",
    "sg:tags":[
        "agency",
        "bureau"
    ],
    "wof:name":"Passport Travel",
    "wof:placetype":"venue"
},
  "geometry": {"coordinates":[-84.031367,35.930186],"type":"Point"}
}