{
  "type": "Feature",
  "properties": {
    "iso:country":"US",
    "sg:address":"138 Madison Ave",
    "sg:city":"Memphis",
    "sg:classifiers":[
        {
            "category":"Banks & Credit Unions",
            "subcategory":"Bank",
            "type":"Services"
        }
    ],
    "sg:phone":"+1 901 525 5050",
    "sg:postcode":"38103",
    "sg:province":"TN",
    "sg:tags":[
        "personal",
        "institution"
    ],
    "wof:name":"Service Loan Co",
    "wof:placetype":"venue"
},
  "geometry": {"coordinates":[-90.05094699999999,35.144771],"type":"Point"}
}