{
  "type": "Feature",
  "properties": {
    "iso:country":"US",
    "sg:address":"3445 Poplar Ave",
    "sg:city":"Memphis",
    "sg:classifiers":[
        {
            "category":"Health Services",
            "subcategory":"Optometrist",
            "type":"Services"
        }
    ],
    "sg:phone":"+1 901 458 2020",
    "sg:postcode":"38111",
    "sg:province":"TN",
    "sg:tags":[
        "group"
    ],
    "wof:name":"Nance Gary Od",
    "wof:placetype":"venue"
},
  "geometry": {"coordinates":[-89.946443,35.128023],"type":"Point"}
}