{
  "type": "Feature",
  "properties": {
    "iso:country":"US",
    "sg:address":"2837 Boones Creek Rd",
    "sg:city":"Gray",
    "sg:classifiers":[
        {
            "category":"Organizations",
            "subcategory":"Religious Organization",
            "type":"Services"
        }
    ],
    "sg:phone":"+1 423 282 8897",
    "sg:postcode":"37615",
    "sg:province":"TN",
    "sg:tags":[
        "alliance",
        "christian",
        "missionary",
        "church"
    ],
    "sg:website":"www.cmachurch.org",
    "wof:name":"Johnson City Alliance Church",
    "wof:placetype":"venue"
},
  "geometry": {"coordinates":[-82.42401700000001,36.381222],"type":"Point"}
}