{
  "type": "Feature",
  "properties": {
    "addr:full":"560 R B Wilson Dr Huntingdon TN 38344",
    "addr:housenumber":"560",
    "addr:postcode":"38344",
    "addr:street":"R B Wilson Dr",
    "iso:country":"US",
    "sg:address":"560 R B Wilson Dr",
    "sg:city":"Huntingdon",
    "sg:classifiers":[
        {
            "category":"Health Services",
            "subcategory":"Doctor",
            "type":"Services"
        }
    ],
    "sg:phone":"+1 731 986 2180",
    "sg:postcode":"38344",
    "sg:province":"TN",
    "sg:tags":[
        "dentist"
    ],
    "wof:name":"Webbs Dental Clinic",
    "wof:placetype":"venue"
},
  "geometry": {"coordinates":[-88.413411,36.023264],"type":"Point"}
}