{
  "type": "Feature",
  "properties": {
    "iso:country":"US",
    "sg:address":"2115 Saint John Ave",
    "sg:city":"Dyersburg",
    "sg:classifiers":[
        {
            "category":"Organizations",
            "subcategory":"Religious Organization",
            "type":"Services"
        }
    ],
    "sg:phone":"+1 731 286 4255",
    "sg:postcode":"38024",
    "sg:province":"TN",
    "sg:tags":[
        "church"
    ],
    "sg:website":"www.edpc.org",
    "wof:name":"East Dyersburg Pentecostal Chr",
    "wof:placetype":"venue"
},
  "geometry": {"coordinates":[-89.35314700000001,36.059828],"type":"Point"}
}