{
  "type": "Feature",
  "properties": {
    "iso:country":"US",
    "sg:address":"4406 Malone Rd",
    "sg:city":"Memphis",
    "sg:classifiers":[
        {
            "category":"Wholesale",
            "subcategory":"Machinery & Supplies",
            "type":"Manufacturing & Wholesale Goods"
        }
    ],
    "sg:phone":"+1 901 542 3625",
    "sg:postcode":"38118",
    "sg:province":"TN",
    "sg:tags":[
        "industrial",
        "equipment",
        "used",
        "machinery-new",
        "supplies-wholesale"
    ],
    "wof:name":"Bluff City Dock Hoppers",
    "wof:placetype":"venue"
},
  "geometry": {"coordinates":[-89.91916999999999,35.026665],"type":"Point"}
}