{
  "type": "Feature",
  "properties": {
    "addr:full":"601 W Summit Hill Dr Knoxville TN 37902",
    "addr:housenumber":"601",
    "addr:postcode":"37902",
    "addr:street":"W Summit Hill Dr",
    "iso:country":"US",
    "sg:address":"601 W Summit Hill Dr",
    "sg:city":"Knoxville",
    "sg:classifiers":[
        {
            "category":"Government",
            "subcategory":"Office",
            "type":"Public Place"
        }
    ],
    "sg:phone":"+1 865 545 4637",
    "sg:postcode":"37902",
    "sg:province":"TN",
    "sg:tags":[
        "federal",
        "program",
        "adm"
    ],
    "wof:name":"US Commerce Dept",
    "wof:placetype":"venue"
},
  "geometry": {"coordinates":[-83.923587,35.964791],"type":"Point"}
}