{
  "type": "Feature",
  "properties": {
    "iso:country":"US",
    "sg:address":"1424 Tanner Dr",
    "sg:city":"Monterey",
    "sg:classifiers":[
        {
            "category":"Professional",
            "type":"Services"
        }
    ],
    "sg:phone":"+1 931 839 7600",
    "sg:postcode":"38574",
    "sg:province":"TN",
    "wof:name":"Fantasia Creations Inc",
    "wof:placetype":"venue"
},
  "geometry": {"coordinates":[-85.283541,36.053783],"type":"Point"}
}