{
  "type": "Feature",
  "properties": {
    "addr:full":"1421 W Lamar Alexander Pkwy Maryville TN 37801",
    "addr:housenumber":"1421",
    "addr:postcode":"37801",
    "addr:street":"W Lamar Alexander Pkwy",
    "iso:country":"US",
    "sg:address":"1421 W Lamar Alexander Pkwy",
    "sg:city":"Maryville",
    "sg:classifiers":[
        {
            "category":"Shopping",
            "subcategory":"Jewelry",
            "type":"Retail Goods"
        }
    ],
    "sg:phone":"+1 865 984 1390",
    "sg:postcode":"37801",
    "sg:province":"TN",
    "sg:tags":[
        "jeweler"
    ],
    "wof:name":"R & K Jewelers",
    "wof:placetype":"venue"
},
  "geometry": {"coordinates":[-84.00655399999999,35.752724],"type":"Point"}
}