{
  "type": "Feature",
  "properties": {
    "addr:full":"144 Hospital Rd Winchester TN 37398",
    "addr:housenumber":"144",
    "addr:postcode":"37398",
    "addr:street":"Hospital Rd",
    "iso:country":"US",
    "sg:address":"144 Hospital Rd",
    "sg:city":"Winchester",
    "sg:classifiers":[
        {
            "category":"Health Services",
            "subcategory":"Medical Lab",
            "type":"Services"
        }
    ],
    "sg:phone":"+1 931 962 4624",
    "sg:postcode":"37398",
    "sg:province":"TN",
    "sg:tags":[
        "resonance",
        "magnetic",
        "imaging"
    ],
    "sg:website":"www.summitopenmri.com",
    "wof:name":"Summit Open MRI",
    "wof:placetype":"venue"
},
  "geometry": {"coordinates":[-86.09080400000001,35.17662],"type":"Point"}
}