{
  "type": "Feature",
  "properties": {
    "iso:country":"US",
    "sg:address":"135 Western Plaza Dr",
    "sg:city":"Newport",
    "sg:classifiers":[
        {
            "category":"Shopping",
            "subcategory":"Discount & Variety Stores",
            "type":"Retail Goods"
        }
    ],
    "sg:phone":"+1 423 613 9800",
    "sg:postcode":"37821",
    "sg:province":"TN",
    "wof:name":"U Save Discount",
    "wof:placetype":"venue"
},
  "geometry": {"coordinates":[-83.20809199999999,35.971732],"type":"Point"}
}