{
  "type": "Feature",
  "properties": {
    "iso:country":"US",
    "sg:address":"213 Deer Pointe",
    "sg:city":"Nashville",
    "sg:classifiers":[
        {
            "category":"Professional",
            "type":"Services"
        }
    ],
    "sg:phone":"+1 615 356 6849",
    "sg:postcode":"37209",
    "sg:province":"TN",
    "wof:name":"John R Davis",
    "wof:placetype":"venue"
},
  "geometry": {"coordinates":[-86.934558,36.104252],"type":"Point"}
}