{
  "type": "Feature",
  "properties": {
    "iso:country":"US",
    "sg:address":"1056 Oaklawn Dr",
    "sg:city":"Cookeville",
    "sg:classifiers":[
        {
            "category":"Health Services",
            "subcategory":"Health Practitioner",
            "type":"Services"
        }
    ],
    "sg:phone":"+1 931 528 6001",
    "sg:postcode":"38501",
    "sg:province":"TN",
    "sg:tags":[
        "nurse",
        "registry"
    ],
    "wof:name":"Janice M Whiting Rn",
    "wof:placetype":"venue"
},
  "geometry": {"coordinates":[-85.480935,36.172055],"type":"Point"}
}