{
  "type": "Feature",
  "properties": {
    "addr:full":"3410 Lebanon Pike Hermitage TN 37076",
    "addr:housenumber":"3410",
    "addr:postcode":"37076",
    "addr:street":"Lebanon Pike",
    "iso:country":"US",
    "sg:address":"3410 Lebanon Pike",
    "sg:city":"Hermitage",
    "sg:classifiers":[
        {
            "category":"Restaurant",
            "type":"Food & Drink"
        }
    ],
    "sg:phone":"+1 615 889 1150",
    "sg:postcode":"37076",
    "sg:province":"TN",
    "sg:tags":[
        "eating"
    ],
    "wof:name":"Pizza Hut",
    "wof:placetype":"venue"
},
  "geometry": {"coordinates":[-86.625235,36.191357],"type":"Point"}
}