{
  "type": "Feature",
  "properties": {
    "addr:full":"1448 US Hwy 51 Bus Dyersburg TN 38024",
    "addr:housenumber":"1448",
    "addr:postcode":"38024",
    "addr:street":"Us Hwy 51 Bus",
    "iso:country":"US",
    "sg:address":"1448 US Hwy 51 Bus",
    "sg:city":"Dyersburg",
    "sg:classifiers":[
        {
            "category":"Health Services",
            "subcategory":"Doctor",
            "type":"Services"
        }
    ],
    "sg:phone":"+1 731 285 0208",
    "sg:postcode":"38024",
    "sg:province":"TN",
    "sg:tags":[
        "clinic"
    ],
    "wof:name":"Liberty Medical Clinic PC",
    "wof:placetype":"venue"
},
  "geometry": {"coordinates":[-89.372512,36.046408],"type":"Point"}
}