{
  "type": "Feature",
  "properties": {
    "iso:country":"US",
    "sg:address":"2116 N Roan St",
    "sg:city":"Johnson City",
    "sg:classifiers":[
        {
            "category":"Shopping",
            "subcategory":"Department Store",
            "type":"Retail Goods"
        }
    ],
    "sg:phone":"+1 423 854 8899",
    "sg:postcode":"37601",
    "sg:province":"TN",
    "sg:website":"www.target.com",
    "wof:name":"Target",
    "wof:placetype":"venue"
},
  "geometry": {"coordinates":[-82.376223,36.343174],"type":"Point"}
}