{
  "type": "Feature",
  "properties": {
    "iso:country":"US",
    "sg:address":"9405 S Northshore Dr",
    "sg:city":"Knoxville",
    "sg:classifiers":[
        {
            "category":"Food & Beverages",
            "subcategory":"Liquor & Beverages",
            "type":"Retail Goods"
        }
    ],
    "sg:phone":"+1 865 692 2004",
    "sg:postcode":"37922",
    "sg:province":"TN",
    "sg:tags":[
        "alcoholic"
    ],
    "wof:name":"Parkway Wines & Spirits",
    "wof:placetype":"venue"
},
  "geometry": {"coordinates":[-84.06344799999999,35.863914],"type":"Point"}
}