{
  "type": "Feature",
  "properties": {
    "iso:country":"US",
    "sg:address":"5837 Outer Dr",
    "sg:city":"Knoxville",
    "sg:classifiers":[
        {
            "category":"Home & Garden",
            "subcategory":"Home Furnishings",
            "type":"Retail Goods"
        }
    ],
    "sg:phone":"+1 865 691 7494",
    "sg:postcode":"37921",
    "sg:province":"TN",
    "wof:name":"Lamp Light",
    "wof:placetype":"venue"
},
  "geometry": {"coordinates":[-84.027356,35.975108],"type":"Point"}
}