{
  "type": "Feature",
  "properties": {
    "addr:full":"1201 Riverfront Pkwy Chattanooga TN 37408",
    "addr:housenumber":"1201",
    "addr:postcode":"37408",
    "addr:street":"Riverfront Pkwy",
    "iso:country":"US",
    "sg:address":"1201 Riverfront Pkwy",
    "sg:city":"Chattanooga",
    "sg:classifiers":[
        {
            "category":"Wholesale",
            "subcategory":"Electrical",
            "type":"Manufacturing & Wholesale Goods"
        }
    ],
    "sg:phone":"+1 423 265 6905",
    "sg:postcode":"37408",
    "sg:province":"TN",
    "sg:tags":[
        "equipment",
        "apparatus"
    ],
    "wof:name":"A B B Electric Systems",
    "wof:placetype":"venue"
},
  "geometry": {"coordinates":[-85.320744,35.043122],"type":"Point"}
}