{
  "type": "Feature",
  "properties": {
    "iso:country":"US",
    "sg:address":"411 Florence Rd",
    "sg:city":"Savannah",
    "sg:classifiers":[
        {
            "category":"Cinema",
            "subcategory":"Movie Theater",
            "type":"Entertainment"
        }
    ],
    "sg:phone":"+1 731 925 3954",
    "sg:postcode":"38372",
    "sg:province":"TN",
    "sg:tags":[
        "motion",
        "picture"
    ],
    "wof:name":"Southgate Cinema 6",
    "wof:placetype":"venue"
},
  "geometry": {"coordinates":[-88.23981499999999,35.21912],"type":"Point"}
}