{
  "type": "Feature",
  "properties": {
    "iso:country":"US",
    "sg:address":"1120 Dry Gap Pike",
    "sg:city":"Knoxville",
    "sg:classifiers":[
        {
            "category":"Organizations",
            "subcategory":"Religious Organization",
            "type":"Services"
        }
    ],
    "sg:phone":"+1 865 688 1000",
    "sg:postcode":"37918",
    "sg:province":"TN",
    "sg:tags":[
        "church"
    ],
    "sg:website":"www.faithseekers.org",
    "wof:name":"Faith United Methodist Church",
    "wof:placetype":"venue"
},
  "geometry": {"coordinates":[-83.965762,36.03931],"type":"Point"}
}