{
  "type": "Feature",
  "properties": {
    "iso:country":"US",
    "sg:address":"3668 Camelot Dr",
    "sg:city":"Maryville",
    "sg:classifiers":[
        {
            "category":"Retail",
            "subcategory":"Repair Shop",
            "type":"Services"
        }
    ],
    "sg:phone":"+1 865 983 3882",
    "sg:postcode":"37803",
    "sg:province":"TN",
    "sg:tags":[
        "welding"
    ],
    "wof:name":"C & H Welding Maintenance",
    "wof:placetype":"venue"
},
  "geometry": {"coordinates":[-83.884338,35.739842],"type":"Point"}
}