{
  "type": "Feature",
  "properties": {
    "iso:country":"US",
    "sg:address":"522 Colburn Dr",
    "sg:city":"Lewisburg",
    "sg:classifiers":[
        {
            "category":"Building & Trades",
            "subcategory":"Plumbing",
            "type":"Services"
        }
    ],
    "sg:phone":"+1 931 270 5893",
    "sg:postcode":"37091",
    "sg:province":"TN",
    "sg:tags":[
        "plumbing",
        "contractor"
    ],
    "wof:name":"Sims Plumbing & Electric",
    "wof:placetype":"venue"
},
  "geometry": {"coordinates":[-86.799347,35.445753],"type":"Point"}
}