{
  "type": "Feature",
  "properties": {
    "addr:full":"4145 Park Ave Memphis TN 38117",
    "addr:housenumber":"4145",
    "addr:postcode":"38117",
    "addr:street":"Park Ave",
    "iso:country":"US",
    "sg:address":"4145 Park Ave",
    "sg:city":"Memphis",
    "sg:classifiers":[
        {
            "category":"Professional",
            "subcategory":"Management & Consulting",
            "type":"Services"
        }
    ],
    "sg:phone":"+1 901 682 0240",
    "sg:postcode":"38117",
    "sg:province":"TN",
    "wof:name":"Healthcare Consultants of S",
    "wof:placetype":"venue"
},
  "geometry": {"coordinates":[-89.923602,35.107254],"type":"Point"}
}