{
  "type": "Feature",
  "properties": {
    "iso:country":"US",
    "sg:address":"620 Chestnut St",
    "sg:city":"Chattanooga",
    "sg:classifiers":[
        {
            "category":"Insurance",
            "subcategory":"Health Insurance",
            "type":"Services"
        }
    ],
    "sg:phone":"+1 423 763 7104",
    "sg:postcode":"37402",
    "sg:province":"TN",
    "sg:tags":[
        "plan"
    ],
    "wof:name":"Tennessee Health Care Network",
    "wof:placetype":"venue"
},
  "geometry": {"coordinates":[-85.31158600000001,35.048595],"type":"Point"}
}