{
  "type": "Feature",
  "properties": {
    "iso:country":"US",
    "sg:address":"1063 Joe Quick Rd",
    "sg:city":"Hazel Green",
    "sg:classifiers":[
        {
            "category":"Manufacturing",
            "subcategory":"Printing",
            "type":"Manufacturing & Wholesale Goods"
        }
    ],
    "sg:phone":"+1 256 829 0503",
    "sg:postcode":"35750",
    "sg:province":"TN",
    "sg:tags":[
        "publisher",
        "guide"
    ],
    "wof:name":"ASP Publishing Inc",
    "wof:placetype":"venue"
},
  "geometry": {"coordinates":[-86.532163,34.932265],"type":"Point"}
}