{
  "type": "Feature",
  "properties": {
    "addr:full":"605 Canyon Dr Columbia TN 38401",
    "addr:housenumber":"605",
    "addr:postcode":"38401",
    "addr:street":"Canyon Dr",
    "iso:country":"US",
    "sg:address":"605 Canyon Dr",
    "sg:city":"Columbia",
    "sg:classifiers":[
        {
            "category":"Building & Trades",
            "subcategory":"Electrical",
            "type":"Services"
        }
    ],
    "sg:phone":"+1 931 388 9191",
    "sg:postcode":"38401",
    "sg:province":"TN",
    "sg:tags":[
        "electric",
        "contractor"
    ],
    "wof:name":"Shackelford Electric Svc",
    "wof:placetype":"venue"
},
  "geometry": {"coordinates":[-86.988844,35.684623],"type":"Point"}
}