{
  "type": "Feature",
  "properties": {
    "iso:country":"US",
    "sg:address":"4377 Wildwood Rd",
    "sg:city":"Memphis",
    "sg:classifiers":[
        {
            "category":"Building & Trades",
            "subcategory":"Construction",
            "type":"Services"
        }
    ],
    "sg:phone":"+1 901 268 4167",
    "sg:postcode":"38135",
    "sg:province":"TN",
    "sg:tags":[
        "hanging",
        "contractor"
    ],
    "wof:name":"Roger Bateson Painting",
    "wof:placetype":"venue"
},
  "geometry": {"coordinates":[-89.871878,35.245451],"type":"Point"}
}