{
  "type": "Feature",
  "properties": {
    "addr:full":"291 Floyd Dr Lewisburg TN 37091",
    "addr:housenumber":"291",
    "addr:postcode":"37091",
    "addr:street":"Floyd Dr",
    "iso:country":"US",
    "sg:address":"291 Floyd Dr",
    "sg:city":"Lewisburg",
    "sg:classifiers":[
        {
            "category":"Building & Trades",
            "subcategory":"Construction",
            "type":"Services"
        }
    ],
    "sg:phone":"+1 615 286 2356",
    "sg:postcode":"37091",
    "sg:province":"TN",
    "sg:tags":[
        "general",
        "contractor"
    ],
    "wof:name":"J H Co",
    "wof:placetype":"venue"
},
  "geometry": {"coordinates":[-86.81176499999999,35.453618],"type":"Point"}
}