{
  "type": "Feature",
  "properties": {
    "iso:country":"US",
    "sg:address":"405 Scenic Dr",
    "sg:city":"Rogersville",
    "sg:classifiers":[
        {
            "category":"Health Services",
            "subcategory":"Doctor",
            "type":"Services"
        }
    ],
    "sg:phone":"+1 423 224 4920",
    "sg:postcode":"37857",
    "sg:province":"TN",
    "sg:tags":[
        "physician",
        "surgeon"
    ],
    "wof:name":"Blue Ridge Obstetrics & Gyn",
    "wof:placetype":"venue"
},
  "geometry": {"coordinates":[-83.01444100000001,36.400651],"type":"Point"}
}