{
  "type": "Feature",
  "properties": {
    "iso:country":"US",
    "sg:address":"1018 42nd Ave N",
    "sg:city":"Nashville",
    "sg:classifiers":[
        {
            "category":"Place Of Worship",
            "subcategory":"Church",
            "type":"Public Place"
        },
        {
            "category":"Place Of Worship",
            "type":"Public Place"
        }
    ],
    "sg:phone":"+1 615 321 3509",
    "sg:postcode":"37209",
    "sg:province":"TN",
    "sg:tags":[
        "churches-baptist-primitive",
        "churches-baptist"
    ],
    "wof:name":"Belle Meade United Primitive Baptist Church",
    "wof:placetype":"venue"
},
  "geometry": {"coordinates":[-86.837788,36.161431],"type":"Point"}
}