{
  "type": "Feature",
  "properties": {
    "addr:full":"6528 Birch Walk Dr Memphis TN 38115",
    "addr:housenumber":"6528",
    "addr:postcode":"38115",
    "addr:street":"Birch Walk Dr",
    "iso:country":"US",
    "sg:address":"6528 Birch Walk Dr",
    "sg:city":"Memphis",
    "sg:classifiers":[
        {
            "category":"Professional",
            "subcategory":"Management & Consulting",
            "type":"Services"
        }
    ],
    "sg:phone":"+1 901 949 2487",
    "sg:postcode":"38115",
    "sg:province":"TN",
    "wof:name":"Guffin Enterprises Inc",
    "wof:placetype":"venue"
},
  "geometry": {"coordinates":[-89.84352,35.039538],"type":"Point"}
}