{
  "type": "Feature",
  "properties": {
    "addr:full":"1515 Monticello Ave Madison TN 37115",
    "addr:housenumber":"1515",
    "addr:postcode":"37115",
    "addr:street":"Monticello Ave",
    "iso:country":"US",
    "sg:address":"1515 Monticello Ave",
    "sg:city":"Madison",
    "sg:classifiers":[
        {
            "category":"Building & Trades",
            "subcategory":"Construction",
            "type":"Services"
        }
    ],
    "sg:phone":"+1 615 865 2888",
    "sg:postcode":"37115",
    "sg:province":"TN",
    "sg:tags":[
        "concrete",
        "contractor"
    ],
    "wof:name":"Concrete Coating Systems Inc",
    "wof:placetype":"venue"
},
  "geometry": {"coordinates":[-86.710525,36.289877],"type":"Point"}
}