{
  "type": "Feature",
  "properties": {
    "iso:country":"US",
    "sg:address":"8216 State Hwy 100",
    "sg:city":"Nashville",
    "sg:classifiers":[
        {
            "category":"Home & Garden",
            "subcategory":"Garden Supply",
            "type":"Retail Goods"
        }
    ],
    "sg:phone":"+1 615 662 8849",
    "sg:postcode":"37221",
    "sg:province":"TN",
    "wof:name":"Moore & Moore W Grdn Ctr LLC",
    "wof:placetype":"venue"
},
  "geometry": {"coordinates":[-86.96096900000001,36.041719],"type":"Point"}
}