{
  "type": "Feature",
  "properties": {
    "addr:full":"618 Grassmere Park Nashville TN 37211",
    "addr:housenumber":"618",
    "addr:postcode":"37211",
    "addr:street":"Grassmere Park",
    "iso:country":"US",
    "sg:address":"618 Grassmere Park",
    "sg:city":"Nashville",
    "sg:classifiers":[
        {
            "category":"Professional",
            "subcategory":"Engineering",
            "type":"Services"
        }
    ],
    "sg:phone":"+1 615 331 0809",
    "sg:postcode":"37211",
    "sg:province":"TN",
    "sg:tags":[
        "engineer"
    ],
    "wof:name":"Anderson Delk Epps & Assoc",
    "wof:placetype":"venue"
},
  "geometry": {"coordinates":[-86.74915799999999,36.0889],"type":"Point"}
}