{
  "type": "Feature",
  "properties": {
    "addr:full":"3878 Voltaire Ave Memphis TN 38128",
    "addr:housenumber":"3878",
    "addr:postcode":"38128",
    "addr:street":"Voltaire Ave",
    "iso:country":"US",
    "sg:address":"3878 Voltaire Ave",
    "sg:city":"Memphis",
    "sg:classifiers":[
        {
            "category":"Building & Trades",
            "subcategory":"Cleaning & Sanitation",
            "type":"Services"
        }
    ],
    "sg:phone":"+1 901 315 1963",
    "sg:postcode":"38128",
    "sg:province":"TN",
    "sg:tags":[
        "house"
    ],
    "wof:name":"Parker, Melvin",
    "wof:placetype":"venue"
},
  "geometry": {"coordinates":[-89.934416,35.239702],"type":"Point"}
}