{
  "type": "Feature",
  "properties": {
    "iso:country":"US",
    "sg:address":"427 Greenwood Ave",
    "sg:city":"Jackson",
    "sg:classifiers":[
        {
            "category":"Retail",
            "subcategory":"Repair Shop",
            "type":"Services"
        }
    ],
    "sg:phone":"+1 731 427 1451",
    "sg:postcode":"38301",
    "sg:province":"TN",
    "sg:tags":[
        "refinishing",
        "furniture"
    ],
    "wof:name":"Snider Cabinet Works",
    "wof:placetype":"venue"
},
  "geometry": {"coordinates":[-88.809842,35.634182],"type":"Point"}
}