{
  "type": "Feature",
  "properties": {
    "addr:full":"435 Hwy 321 Hampton TN 37658",
    "addr:housenumber":"435",
    "addr:postcode":"37658",
    "addr:street":"Hwy 321",
    "iso:country":"US",
    "sg:address":"435 Hwy 321",
    "sg:city":"Hampton",
    "sg:classifiers":[
        {
            "category":"Social Services",
            "subcategory":"Child Care",
            "type":"Services"
        }
    ],
    "sg:phone":"+1 423 725 2009",
    "sg:postcode":"37658",
    "sg:province":"TN",
    "sg:tags":[
        "day"
    ],
    "wof:name":"Toddler Time Day Care Center",
    "wof:placetype":"venue"
},
  "geometry": {"coordinates":[-82.171513,36.28751],"type":"Point"}
}