{
  "type": "Feature",
  "properties": {
    "iso:country":"US",
    "sg:address":"628 Neill Ave",
    "sg:city":"Nashville",
    "sg:classifiers":[
        {
            "category":"Building & Trades",
            "subcategory":"Construction",
            "type":"Services"
        }
    ],
    "sg:phone":"+1 615 227 0263",
    "sg:postcode":"37206",
    "sg:province":"TN",
    "sg:tags":[
        "house"
    ],
    "wof:name":"R O E Construction Co",
    "wof:placetype":"venue"
},
  "geometry": {"coordinates":[-86.760004,36.181499],"type":"Point"}
}