{
  "type": "Feature",
  "properties": {
    "iso:country":"US",
    "sg:address":"390 Grandview Ct",
    "sg:city":"Kingsport",
    "sg:classifiers":[
        {
            "category":"Sports & Exercise",
            "subcategory":"Race Track",
            "type":"Entertainment"
        }
    ],
    "sg:phone":"+1 423 323 1282",
    "sg:postcode":"37664",
    "sg:province":"TN",
    "sg:tags":[
        "operation",
        "racing",
        "or"
    ],
    "wof:name":"J K M Racing Inc",
    "wof:placetype":"venue"
},
  "geometry": {"coordinates":[-82.461533,36.519945],"type":"Point"}
}