{
  "type": "Feature",
  "properties": {
    "iso:country":"US",
    "sg:address":"2717 Huntley Dr",
    "sg:city":"Memphis",
    "sg:classifiers":[
        {
            "category":"Wholesale",
            "subcategory":"Non-durable Goods",
            "type":"Manufacturing & Wholesale Goods"
        },
        {
            "category":"Building & Trades",
            "subcategory":"Cleaning & Sanitation",
            "type":"Services"
        },
        {
            "category":"Home & Garden",
            "subcategory":"Hardware",
            "type":"Retail Goods"
        }
    ],
    "sg:phone":"+1 901 521 1612",
    "sg:postcode":"38132",
    "sg:province":"TN",
    "sg:tags":[
        "supply",
        "supplies-wholesale",
        "equipment",
        "janitor",
        "janitorial",
        "manufacturer"
    ],
    "sg:website":"http://www.mempchemical.com",
    "wof:name":"Memphis Chemical & Janitorial Supply",
    "wof:placetype":"venue"
},
  "geometry": {"coordinates":[-90.012123,35.070996],"type":"Point"}
}