{
  "type": "Feature",
  "properties": {
    "iso:country":"US",
    "sg:address":"339 Woods View Cir",
    "sg:city":"Kodak",
    "sg:classifiers":[
        {
            "category":"Professional",
            "subcategory":"Business Services",
            "type":"Services"
        }
    ],
    "sg:phone":"+1 865 932 9570",
    "sg:postcode":"37764",
    "sg:province":"TN",
    "wof:name":"Janbill Enterprises LLC",
    "wof:placetype":"venue"
},
  "geometry": {"coordinates":[-83.59175999999999,35.943335],"type":"Point"}
}