{
  "type": "Feature",
  "properties": {
    "iso:country":"US",
    "sg:address":"929 W Poplar Ave",
    "sg:city":"Collierville",
    "sg:classifiers":[
        {
            "category":"Restaurant",
            "type":"Food & Drink"
        }
    ],
    "sg:phone":"+1 901 861 5171",
    "sg:postcode":"38017",
    "sg:province":"TN",
    "wof:name":"Grill 901",
    "wof:placetype":"venue"
},
  "geometry": {"coordinates":[-89.692522,35.046105],"type":"Point"}
}