{
  "type": "Feature",
  "properties": {
    "addr:full":"4300 Charlotte Ave Nashville TN 37209",
    "addr:housenumber":"4300",
    "addr:postcode":"37209",
    "addr:street":"Charlotte Ave",
    "iso:country":"US",
    "sg:address":"4300 Charlotte Ave",
    "sg:city":"Nashville",
    "sg:classifiers":[
        {
            "category":"Health Services",
            "subcategory":"Doctor",
            "type":"Services"
        }
    ],
    "sg:phone":"+1 615 298 2488",
    "sg:postcode":"37209",
    "sg:province":"TN",
    "sg:tags":[
        "dentist"
    ],
    "wof:name":"Roney Otis Guinn DDS",
    "wof:placetype":"venue"
},
  "geometry": {"coordinates":[-86.83957599999999,36.152279],"type":"Point"}
}