{
  "type": "Feature",
  "properties": {
    "iso:country":"US",
    "sg:address":"2307 Crestmoor Rd",
    "sg:city":"Nashville",
    "sg:classifiers":[
        {
            "category":"Banks & Credit Unions",
            "subcategory":"Bank",
            "type":"Services"
        }
    ],
    "sg:phone":"+1 615 743 3500",
    "sg:postcode":"37215",
    "sg:province":"TN",
    "sg:tags":[
        "national"
    ],
    "wof:name":"Pinnacle National Bank",
    "wof:placetype":"venue"
},
  "geometry": {"coordinates":[-86.8172,36.109777],"type":"Point"}
}