{
  "type": "Feature",
  "properties": {
    "addr:full":"680 N Germantown Pkwy Cordova TN 38018",
    "addr:housenumber":"680",
    "addr:postcode":"38018",
    "addr:street":"N Germantown Pkwy",
    "iso:country":"US",
    "sg:address":"680 N Germantown Pkwy",
    "sg:city":"Cordova",
    "sg:classifiers":[
        {
            "category":"Shopping",
            "subcategory":"Jewelry",
            "type":"Retail Goods"
        }
    ],
    "sg:phone":"+1 901 752 3974",
    "sg:postcode":"38018",
    "sg:province":"TN",
    "sg:tags":[
        "jewelery"
    ],
    "wof:name":"Oxford Gold & Diamond",
    "wof:placetype":"venue"
},
  "geometry": {"coordinates":[-89.79547599999999,35.142307],"type":"Point"}
}