{
  "type": "Feature",
  "properties": {
    "iso:country":"US",
    "sg:address":"111 W Liberty Ave",
    "sg:city":"Covington",
    "sg:classifiers":[
        {
            "category":"Shopping",
            "subcategory":"Clothing, Apparel, & Fashions",
            "type":"Retail Goods"
        }
    ],
    "sg:phone":"+1 901 476 3095",
    "sg:postcode":"38019",
    "sg:province":"TN",
    "sg:tags":[
        "alteration"
    ],
    "wof:name":"Sewing Basket",
    "wof:placetype":"venue"
},
  "geometry": {"coordinates":[-89.647811,35.564523],"type":"Point"}
}