{
  "type": "Feature",
  "properties": {
    "addr:full":"7570 Poplar Ave Germantown TN 38138",
    "addr:housenumber":"7570",
    "addr:postcode":"38138",
    "addr:street":"Poplar Ave",
    "iso:country":"US",
    "sg:address":"7570 Poplar Ave",
    "sg:city":"Germantown",
    "sg:classifiers":[
        {
            "category":"Professional",
            "subcategory":"Printing & Photocopies",
            "type":"Services"
        }
    ],
    "sg:phone":"+1 901 756 7603",
    "sg:postcode":"38138",
    "sg:province":"TN",
    "sg:tags":[
        "photocopying",
        "lithographic",
        "commercial"
    ],
    "wof:name":"Kinkos",
    "wof:placetype":"venue"
},
  "geometry": {"coordinates":[-89.809505,35.093214],"type":"Point"}
}