{
  "type": "Feature",
  "properties": {
    "addr:full":"1800 Union Ave Memphis TN 38104",
    "addr:housenumber":"1800",
    "addr:postcode":"38104",
    "addr:street":"Union Ave",
    "iso:country":"US",
    "sg:address":"1800 Union Ave",
    "sg:city":"Memphis",
    "sg:classifiers":[
        {
            "category":"Shopping",
            "subcategory":"Pharmacy",
            "type":"Retail Goods"
        }
    ],
    "sg:phone":"+1 901 726 4444",
    "sg:postcode":"38104",
    "sg:province":"TN",
    "wof:name":"Super D Express",
    "wof:placetype":"venue"
},
  "geometry": {"coordinates":[-90.00158500000001,35.135413],"type":"Point"}
}