{
  "type": "Feature",
  "properties": {
    "addr:full":"121 Walton Ferry Rd Hendersonville TN 37075",
    "addr:housenumber":"121",
    "addr:postcode":"37075",
    "addr:street":"Walton Ferry Rd",
    "iso:country":"US",
    "sg:address":"121 Walton Ferry Rd",
    "sg:city":"Hendersonville",
    "sg:classifiers":[
        {
            "category":"Government",
            "subcategory":"Fire Station",
            "type":"Public Place"
        },
        {
            "category":"Professional",
            "subcategory":"Detective & Security Services",
            "type":"Services"
        },
        {
            "category":"Shopping",
            "subcategory":"Computers & Home Electronics",
            "type":"Retail Goods"
        }
    ],
    "sg:phone":"+1 877 519 9692",
    "sg:postcode":"37075",
    "sg:province":"TN",
    "sg:tags":[
        "control",
        "monitoring",
        "supply",
        "consultant",
        "system",
        "surveillance",
        "equipment",
        "protection"
    ],
    "sg:website":"http://www.homesecurityteam.com/?tfid=y",
    "wof:name":"Advanced Direct Security - ADT Authorized Company",
    "wof:placetype":"venue"
},
  "geometry": {"coordinates":[-86.62016300000001,36.303051],"type":"Point"}
}