{
  "type": "Feature",
  "properties": {
    "iso:country":"US",
    "sg:address":"403 E Eaton St",
    "sg:city":"Trenton",
    "sg:classifiers":[
        {
            "category":"Autos & Motor Vehicles",
            "subcategory":"Automobile Sales",
            "type":"Retail Goods"
        }
    ],
    "sg:phone":"+1 731 855 9662",
    "sg:postcode":"38382",
    "sg:province":"TN",
    "sg:tags":[
        "car",
        "dealer"
    ],
    "sg:website":"www.lewismilliganford.com",
    "wof:name":"Lewis Milligan Ford",
    "wof:placetype":"venue"
},
  "geometry": {"coordinates":[-88.93744,35.980518],"type":"Point"}
}