{
  "type": "Feature",
  "properties": {
    "addr:full":"319 Depot St Ridgely TN 38080",
    "addr:housenumber":"319",
    "addr:postcode":"38080",
    "addr:street":"Depot St",
    "iso:country":"US",
    "sg:address":"319 Depot St",
    "sg:city":"Ridgely",
    "sg:classifiers":[
        {
            "category":"Freight",
            "type":"Transportation"
        },
        {
            "category":"Wholesale",
            "subcategory":"Chemicals & Plastics",
            "type":"Manufacturing & Wholesale Goods"
        }
    ],
    "sg:phone":"+1 731 264 5545",
    "sg:postcode":"38080",
    "sg:province":"TN",
    "sg:tags":[
        "farm",
        "general",
        "supply"
    ],
    "wof:name":"Helena Chemical Company",
    "wof:placetype":"venue"
},
  "geometry": {"coordinates":[-89.492068,36.263513],"type":"Point"}
}