{
  "type": "Feature",
  "properties": {
    "iso:country":"US",
    "sg:address":"1403 NW Broad St",
    "sg:city":"Murfreesboro",
    "sg:classifiers":[
        {
            "category":"Autos & Motor Vehicles",
            "subcategory":"Auto Supplies",
            "type":"Retail Goods"
        }
    ],
    "sg:phone":"+1 615 867 9610",
    "sg:postcode":"37129",
    "sg:province":"TN",
    "sg:tags":[
        "automobile",
        "parts"
    ],
    "sg:website":"www.oreillyauto.com",
    "wof:name":"O'REILLY Auto Parts",
    "wof:placetype":"venue"
},
  "geometry": {"coordinates":[-86.400922,35.852291],"type":"Point"}
}