{
  "type": "Feature",
  "properties": {
    "iso:country":"US",
    "sg:address":"2201 Murfreesboro Pike",
    "sg:city":"Nashville",
    "sg:classifiers":[
        {
            "category":"Home & Garden",
            "subcategory":"Carpets & Floor Coverings",
            "type":"Retail Goods"
        }
    ],
    "sg:phone":"+1 615 360 0079",
    "sg:postcode":"37217",
    "sg:province":"TN",
    "wof:name":"Licra",
    "wof:placetype":"venue"
},
  "geometry": {"coordinates":[-86.650881,36.090587],"type":"Point"}
}