{
  "type": "Feature",
  "properties": {
    "iso:country":"US",
    "sg:address":"232 Industrial Dr",
    "sg:city":"Decatur",
    "sg:classifiers":[
        {
            "category":"Manufacturing",
            "subcategory":"Furniture",
            "type":"Manufacturing & Wholesale Goods"
        },
        {
            "category":"Building & Trades",
            "subcategory":"Construction",
            "type":"Services"
        }
    ],
    "sg:phone":"+1 423 334 1972",
    "sg:postcode":"37326",
    "sg:province":"TN",
    "sg:tags":[
        "cabinet",
        "maker",
        "mfg"
    ],
    "wof:name":"American Manufacturing Co Inc",
    "wof:placetype":"venue"
},
  "geometry": {"coordinates":[-84.391064,35.030483],"type":"Point"}
}