{
  "type": "Feature",
  "properties": {
    "addr:full":"2101 Fort Henry Dr Kingsport TN 37664",
    "addr:housenumber":"2101",
    "addr:postcode":"37664",
    "addr:street":"Fort Henry Dr",
    "iso:country":"US",
    "sg:address":"2101 Fort Henry Dr",
    "sg:city":"Kingsport",
    "sg:classifiers":[
        {
            "category":"Food & Beverages",
            "subcategory":"Bakery",
            "type":"Retail Goods"
        }
    ],
    "sg:phone":"+1 423 378 3477",
    "sg:postcode":"37664",
    "sg:province":"TN",
    "sg:tags":[
        "pretzel"
    ],
    "sg:website":"www.auntieannes.com",
    "wof:name":"Auntie Anne's Hand Rolled Soft",
    "wof:placetype":"venue"
},
  "geometry": {"coordinates":[-82.522086,36.527122],"type":"Point"}
}