{
  "type": "Feature",
  "properties": {
    "iso:country":"US",
    "sg:address":"710 James Robertson Pkwy",
    "sg:city":"Nashville",
    "sg:classifiers":[
        {
            "category":"Government",
            "subcategory":"Office",
            "type":"Public Place"
        }
    ],
    "sg:phone":"+1 615 741 3151",
    "sg:postcode":"37243",
    "sg:province":"TN",
    "sg:tags":[
        "administrative",
        "program",
        "health"
    ],
    "wof:name":"TN Dept of Health Fiscal Srv",
    "wof:placetype":"venue"
},
  "geometry": {"coordinates":[-86.78713399999999,36.167144],"type":"Point"}
}