{
  "type": "Feature",
  "properties": {
    "iso:country":"US",
    "sg:address":"808 Pinecrest Rd",
    "sg:city":"Jacksboro",
    "sg:classifiers":[
        {
            "category":"Organizations",
            "subcategory":"Religious Organization",
            "type":"Services"
        }
    ],
    "sg:phone":"+1 423 562 0735",
    "sg:postcode":"37757",
    "sg:province":"TN",
    "sg:tags":[
        "church"
    ],
    "wof:name":"Cumberland View Baptist Church",
    "wof:placetype":"venue"
},
  "geometry": {"coordinates":[-84.141575,36.307365],"type":"Point"}
}