{
  "type": "Feature",
  "properties": {
    "iso:country":"US",
    "sg:address":"715 N Woodson Rd",
    "sg:city":"Clarksville",
    "sg:classifiers":[
        {
            "category":"Social Services",
            "subcategory":"Child Care",
            "type":"Services"
        }
    ],
    "sg:phone":"+1 931 358 0569",
    "sg:postcode":"37043",
    "sg:province":"TN",
    "sg:tags":[
        "day"
    ],
    "wof:name":"Miss Kathys Day Care",
    "wof:placetype":"venue"
},
  "geometry": {"coordinates":[-87.202372,36.524768],"type":"Point"}
}