{
  "type": "Feature",
  "properties": {
    "iso:country":"US",
    "sg:address":"312 Prince St",
    "sg:city":"Sevierville",
    "sg:classifiers":[
        {
            "category":"Health Services",
            "subcategory":"Doctor",
            "type":"Services"
        }
    ],
    "sg:phone":"+1 865 774 0066",
    "sg:postcode":"37862",
    "sg:province":"TN",
    "sg:tags":[
        "clinic",
        "medical"
    ],
    "wof:name":"Mountain Hope Good Shepherd",
    "wof:placetype":"venue"
},
  "geometry": {"coordinates":[-83.561245,35.864312],"type":"Point"}
}