{
  "type": "Feature",
  "properties": {
    "addr:full":"105 Industrial Dr Smyrna TN 37110",
    "addr:housenumber":"105",
    "addr:postcode":"37110",
    "addr:street":"Industrial Dr",
    "iso:country":"US",
    "sg:address":"105 Industrial Dr",
    "sg:city":"Smyrna",
    "sg:classifiers":[
        {
            "category":"Banks & Credit Unions",
            "subcategory":"Bank",
            "type":"Services"
        }
    ],
    "sg:phone":"+1 615 459 6262",
    "sg:postcode":"37110",
    "sg:province":"TN",
    "wof:name":"Beacon Federal",
    "wof:placetype":"venue"
},
  "geometry": {"coordinates":[-85.759221,35.698476],"type":"Point"}
}