{
  "type": "Feature",
  "properties": {
    "addr:full":"434 E Bell St Murfreesboro TN 37130",
    "addr:housenumber":"434",
    "addr:postcode":"37130",
    "addr:street":"E Bell St",
    "iso:country":"US",
    "sg:address":"434 E Bell St",
    "sg:city":"Murfreesboro",
    "sg:classifiers":[
        {
            "category":"Health Services",
            "subcategory":"Hospital",
            "type":"Services"
        }
    ],
    "sg:phone":"+1 615 890 4622",
    "sg:postcode":"37130",
    "sg:province":"TN",
    "sg:tags":[
        "mental"
    ],
    "wof:name":"Guidance Center",
    "wof:placetype":"venue"
},
  "geometry": {"coordinates":[-86.38565800000001,35.849364],"type":"Point"}
}