{
  "type": "Feature",
  "properties": {
    "iso:country":"US",
    "sg:address":"2017 Saint John Ave",
    "sg:city":"Dyersburg",
    "sg:classifiers":[
        {
            "category":"Health Services",
            "subcategory":"Health Practitioner",
            "type":"Services"
        }
    ],
    "sg:phone":"+1 731 285 7999",
    "sg:postcode":"38024",
    "sg:province":"TN",
    "wof:name":"McKee W Neil Ofc",
    "wof:placetype":"venue"
},
  "geometry": {"coordinates":[-89.355183,36.05838],"type":"Point"}
}