{
  "type": "Feature",
  "properties": {
    "iso:country":"US",
    "sg:address":"2727 Swanson Ln",
    "sg:city":"Knoxville",
    "sg:classifiers":[
        {
            "category":"Building & Trades",
            "subcategory":"Construction",
            "type":"Services"
        }
    ],
    "sg:phone":"+1 865 531 3781",
    "sg:postcode":"37932",
    "sg:province":"TN",
    "sg:tags":[
        "excavation",
        "contractor"
    ],
    "wof:name":"Muse Construction & Excav Co",
    "wof:placetype":"venue"
},
  "geometry": {"coordinates":[-84.193556,35.945092],"type":"Point"}
}