{
  "type": "Feature",
  "properties": {
    "iso:country":"US",
    "sg:address":"3244 Moorewood Dr",
    "sg:city":"Nashville",
    "sg:classifiers":[
        {
            "category":"Personal",
            "subcategory":"Beauty Salon",
            "type":"Services"
        }
    ],
    "sg:phone":"+1 615 226 8324",
    "sg:postcode":"37207",
    "sg:province":"TN",
    "sg:tags":[
        "shop"
    ],
    "wof:name":"Shear Essence",
    "wof:placetype":"venue"
},
  "geometry": {"coordinates":[-86.77341199999999,36.23693],"type":"Point"}
}