{
  "type": "Feature",
  "properties": {
    "iso:country":"US",
    "sg:address":"2258 Young Ave",
    "sg:city":"Memphis",
    "sg:classifiers":[
        {
            "category":"Communications",
            "subcategory":"Film & Video Production",
            "type":"Services"
        }
    ],
    "sg:phone":"+1 901 726 6633",
    "sg:postcode":"38104",
    "sg:province":"TN",
    "sg:tags":[
        "recording",
        "service-sound"
    ],
    "wof:name":"Young Avenue Sound",
    "wof:placetype":"venue"
},
  "geometry": {"coordinates":[-89.987027,35.119528],"type":"Point"}
}