{
  "type": "Feature",
  "properties": {
    "addr:full":"1210 Genelle Dr Goodlettsville TN 37072",
    "addr:housenumber":"1210",
    "addr:postcode":"37072",
    "addr:street":"Genelle Dr",
    "iso:country":"US",
    "sg:address":"1210 Genelle Dr",
    "sg:city":"Goodlettsville",
    "sg:classifiers":[
        {
            "category":"Banks & Credit Unions",
            "subcategory":"Bank",
            "type":"Services"
        }
    ],
    "sg:phone":"+1 615 859 4303",
    "sg:postcode":"37072",
    "sg:province":"TN",
    "sg:tags":[
        "personal",
        "institution"
    ],
    "wof:name":"Consolidated Financial Svcs",
    "wof:placetype":"venue"
},
  "geometry": {"coordinates":[-86.741941,36.298743],"type":"Point"}
}