{
  "type": "Feature",
  "properties": {
    "iso:country":"US",
    "sg:address":"7212 Kingston Pike",
    "sg:city":"Knoxville",
    "sg:classifiers":[
        {
            "category":"Personal",
            "subcategory":"Piercing",
            "type":"Services"
        }
    ],
    "sg:phone":"+1 865 330 0006",
    "sg:postcode":"37919",
    "sg:province":"TN",
    "sg:tags":[
        "body"
    ],
    "wof:name":"Alter Ego Tattoo & Body",
    "wof:placetype":"venue"
},
  "geometry": {"coordinates":[-84.029372,35.930378],"type":"Point"}
}