{
  "type": "Feature",
  "properties": {
    "addr:full":"149 Barber Rd Corryton TN 37721",
    "addr:housenumber":"149",
    "addr:postcode":"37721",
    "addr:street":"Barber Rd",
    "iso:country":"US",
    "sg:address":"149 Barber Rd",
    "sg:city":"Corryton",
    "sg:classifiers":[
        {
            "category":"Freight",
            "type":"Transportation"
        }
    ],
    "sg:phone":"+1 865 992 9078",
    "sg:postcode":"37721",
    "sg:province":"TN",
    "wof:name":"Jcs Transport Inc",
    "wof:placetype":"venue"
},
  "geometry": {"coordinates":[-83.78959500000001,36.179078],"type":"Point"}
}