{
  "type": "Feature",
  "properties": {
    "iso:country":"US",
    "sg:address":"840 Old US Hwy 127 S",
    "sg:city":"Jamestown",
    "sg:classifiers":[
        {
            "category":"Restaurant",
            "type":"Food & Drink"
        }
    ],
    "sg:phone":"+1 931 879 7013",
    "sg:postcode":"38556",
    "sg:province":"TN",
    "sg:tags":[
        "eating"
    ],
    "wof:name":"Jamestown Sub Station",
    "wof:placetype":"venue"
},
  "geometry": {"coordinates":[-84.937285,36.410111],"type":"Point"}
}