{
  "type": "Feature",
  "properties": {
    "iso:country":"US",
    "sg:address":"1405 Patriot Ave",
    "sg:city":"Paris",
    "sg:classifiers":[
        {
            "category":"Restaurant",
            "type":"Food & Drink"
        }
    ],
    "sg:phone":"+1 731 644 1810",
    "sg:postcode":"38242",
    "sg:province":"TN",
    "sg:tags":[
        "eating"
    ],
    "wof:name":"Hong Kong Restaurant",
    "wof:placetype":"venue"
},
  "geometry": {"coordinates":[-88.29907799999999,36.294102],"type":"Point"}
}