{
  "type": "Feature",
  "properties": {
    "iso:country":"US",
    "sg:address":"2500 Shadow Ln",
    "sg:city":"Nashville",
    "sg:classifiers":[
        {
            "category":"Building & Trades",
            "subcategory":"Construction",
            "type":"Services"
        }
    ],
    "sg:phone":"+1 615 419 7968",
    "sg:postcode":"37216",
    "sg:province":"TN",
    "sg:tags":[
        "painter"
    ],
    "wof:name":"A-Team Coatings & Restorations",
    "wof:placetype":"venue"
},
  "geometry": {"coordinates":[-86.701837,36.204876],"type":"Point"}
}