{
  "type": "Feature",
  "properties": {
    "addr:full":"1033 E Tickle St Dyersburg TN 38024",
    "addr:housenumber":"1033",
    "addr:postcode":"38024",
    "addr:street":"E Tickle St",
    "iso:country":"US",
    "sg:address":"1033 E Tickle St",
    "sg:city":"Dyersburg",
    "sg:classifiers":[
        {
            "category":"Professional",
            "subcategory":"Accounting & Tax Preparation",
            "type":"Services"
        }
    ],
    "sg:phone":"+1 731 285 6237",
    "sg:postcode":"38024",
    "sg:province":"TN",
    "sg:tags":[
        "return"
    ],
    "wof:name":"Charles Cowles Jr CPA",
    "wof:placetype":"venue"
},
  "geometry": {"coordinates":[-89.37329699999999,36.047249],"type":"Point"}
}