{
  "type": "Feature",
  "properties": {
    "iso:country":"US",
    "sg:address":"2460 State Hwy 82 Scn",
    "sg:city":"Shelbyville",
    "sg:classifiers":[
        {
            "category":"Building & Trades",
            "subcategory":"Construction",
            "type":"Services"
        }
    ],
    "sg:phone":"+1 931 695 5352",
    "sg:postcode":"37160",
    "sg:province":"TN",
    "sg:tags":[
        "residential"
    ],
    "wof:name":"Martin Lafferty Builders",
    "wof:placetype":"venue"
},
  "geometry": {"coordinates":[-86.45417500000001,35.525935],"type":"Point"}
}