{
  "type": "Feature",
  "properties": {
    "iso:country":"US",
    "sg:address":"810 NW Broad St",
    "sg:city":"Murfreesboro",
    "sg:classifiers":[
        {
            "category":"Wholesale",
            "subcategory":"Tobacco Products",
            "type":"Manufacturing & Wholesale Goods"
        }
    ],
    "sg:phone":"+1 615 494 9466",
    "sg:postcode":"37129",
    "sg:province":"TN",
    "sg:tags":[
        "cigarette",
        "cigar",
        "dealer"
    ],
    "wof:name":"Super Cheap Cigarettes",
    "wof:placetype":"venue"
},
  "geometry": {"coordinates":[-86.394976,35.844931],"type":"Point"}
}