{
  "type": "Feature",
  "properties": {
    "iso:country":"US",
    "sg:address":"100 Cherokee Blvd",
    "sg:city":"Chattanooga",
    "sg:classifiers":[
        {
            "category":"Professional",
            "subcategory":"Engineering",
            "type":"Services"
        }
    ],
    "sg:phone":"+1 423 266 6555",
    "sg:postcode":"37405",
    "sg:province":"TN",
    "sg:tags":[
        "engineer"
    ],
    "wof:name":"Adkins Consulting Svc",
    "wof:placetype":"venue"
},
  "geometry": {"coordinates":[-85.311026,35.063983],"type":"Point"}
}