{
  "type": "Feature",
  "properties": {
    "iso:country":"US",
    "sg:address":"2277 West St",
    "sg:city":"Germantown",
    "sg:classifiers":[
        {
            "category":"Professional",
            "type":"Services"
        }
    ],
    "sg:phone":"+1 901 755 5887",
    "sg:postcode":"38138",
    "sg:province":"TN",
    "wof:name":"Diversified Recovery Svc",
    "wof:placetype":"venue"
},
  "geometry": {"coordinates":[-89.811757,35.087226],"type":"Point"}
}