{
  "type": "Feature",
  "properties": {
    "iso:country":"US",
    "sg:address":"200 W Eaton St",
    "sg:city":"Trenton",
    "sg:classifiers":[
        {
            "category":"Restaurant",
            "type":"Food & Drink"
        }
    ],
    "sg:phone":"+1 731 855 1075",
    "sg:postcode":"38382",
    "sg:province":"TN",
    "sg:tags":[
        "eating"
    ],
    "wof:name":"Cottons Cafe Inc",
    "wof:placetype":"venue"
},
  "geometry": {"coordinates":[-88.942849,35.980737],"type":"Point"}
}