{
  "type": "Feature",
  "properties": {
    "iso:country":"US",
    "sg:address":"304 W Due West Ave",
    "sg:city":"Madison",
    "sg:classifiers":[
        {
            "category":"Arts & Performance",
            "subcategory":"Theater",
            "type":"Entertainment"
        }
    ],
    "sg:phone":"+1 615 868 3738",
    "sg:postcode":"37115",
    "sg:province":"TN",
    "sg:tags":[
        "theatrical"
    ],
    "wof:name":"Tennessee Players Inc",
    "wof:placetype":"venue"
},
  "geometry": {"coordinates":[-86.72850800000001,36.248658],"type":"Point"}
}