{
  "type": "Feature",
  "properties": {
    "iso:country":"US",
    "sg:address":"9218 Kingston Pike",
    "sg:city":"Knoxville",
    "sg:classifiers":[
        {
            "category":"Shopping",
            "subcategory":"Florist",
            "type":"Retail Goods"
        }
    ],
    "sg:phone":"+1 865 691 6372",
    "sg:postcode":"37922",
    "sg:province":"TN",
    "wof:name":"Flower Peddler",
    "wof:placetype":"venue"
},
  "geometry": {"coordinates":[-84.09029200000001,35.910961],"type":"Point"}
}