{
  "type": "Feature",
  "properties": {
    "addr:full":"5725 State Hwy 111 Scn Cookeville TN 38583",
    "addr:housenumber":"5725",
    "addr:postcode":"38583",
    "addr:street":"State Hwy 111",
    "iso:country":"US",
    "sg:address":"5725 State Hwy 111 Scn",
    "sg:city":"Cookeville",
    "sg:classifiers":[
        {
            "category":"Retail",
            "subcategory":"Repair Shop",
            "type":"Services"
        }
    ],
    "sg:phone":"+1 931 537 3559",
    "sg:postcode":"38583",
    "sg:province":"TN",
    "sg:tags":[
        "scooter",
        "motorcycle",
        "motor"
    ],
    "wof:name":"Moto Sports",
    "wof:placetype":"venue"
},
  "geometry": {"coordinates":[-85.50751200000001,36.044995],"type":"Point"}
}