{
  "type": "Feature",
  "properties": {
    "iso:country":"US",
    "sg:address":"1679 N Shelby Oaks Dr",
    "sg:city":"Memphis",
    "sg:classifiers":[
        {
            "category":"Building & Trades",
            "subcategory":"Construction",
            "type":"Services"
        }
    ],
    "sg:phone":"+1 901 507 7566",
    "sg:postcode":"38134",
    "sg:province":"TN",
    "sg:tags":[
        "repairing",
        "remodeling",
        "contractor"
    ],
    "wof:name":"American Remodelers",
    "wof:placetype":"venue"
},
  "geometry": {"coordinates":[-89.85512,35.170504],"type":"Point"}
}