{
  "type": "Feature",
  "properties": {
    "addr:full":"2190 Summerfield Rd Cookeville TN 38506",
    "addr:housenumber":"2190",
    "addr:postcode":"38506",
    "addr:street":"Summerfield Rd",
    "iso:country":"US",
    "sg:address":"2190 Summerfield Rd",
    "sg:city":"Cookeville",
    "sg:classifiers":[
        {
            "category":"Retail",
            "subcategory":"Repair Shop",
            "type":"Services"
        },
        {
            "category":"Retail",
            "subcategory":"Auto Repair",
            "type":"Services"
        }
    ],
    "sg:phone":"+1 931 526 5391",
    "sg:postcode":"38506",
    "sg:province":"TN",
    "sg:tags":[
        "farm",
        "hog",
        "parts",
        "trailer",
        "tractor"
    ],
    "wof:name":"Cookeville Trailer Repr & Svc",
    "wof:placetype":"venue"
},
  "geometry": {"coordinates":[-85.483439,36.189868],"type":"Point"}
}