{
  "type": "Feature",
  "properties": {
    "iso:country":"US",
    "sg:address":"3880 Lamar Ave",
    "sg:city":"Memphis",
    "sg:classifiers":[
        {
            "category":"Professional",
            "type":"Services"
        }
    ],
    "sg:phone":"+1 901 363 7748",
    "sg:postcode":"38118",
    "sg:province":"TN",
    "wof:name":"Culbreath Land Co Inc",
    "wof:placetype":"venue"
},
  "geometry": {"coordinates":[-89.937449,35.061608],"type":"Point"}
}