{
  "type": "Feature",
  "properties": {
    "iso:country":"US",
    "sg:address":"861 W Outer Dr",
    "sg:city":"Oak Ridge",
    "sg:classifiers":[
        {
            "category":"Education",
            "subcategory":"Special Training",
            "type":"Public Place"
        }
    ],
    "sg:phone":"+1 865 482 5614",
    "sg:postcode":"37830",
    "sg:province":"TN",
    "sg:tags":[
        "instruction",
        "music"
    ],
    "sg:website":"www.musicartsschool.org",
    "wof:name":"Music Arts",
    "wof:placetype":"venue"
},
  "geometry": {"coordinates":[-84.305087,36.011652],"type":"Point"}
}