{
  "type": "Feature",
  "properties": {
    "addr:full":"627 Smithview Dr Maryville TN 37803",
    "addr:housenumber":"627",
    "addr:postcode":"37803",
    "addr:street":"Smithview Dr",
    "iso:country":"US",
    "sg:address":"627 Smithview Dr",
    "sg:city":"Maryville",
    "sg:classifiers":[
        {
            "category":"Social Services",
            "type":"Services"
        }
    ],
    "sg:phone":"+1 865 380 4390",
    "sg:postcode":"37803",
    "sg:province":"TN",
    "sg:tags":[
        "specialty",
        "special",
        "outpatient"
    ],
    "sg:website":"www.cherokeehealth.com",
    "wof:name":"Cherokee Health Systems",
    "wof:placetype":"venue"
},
  "geometry": {"coordinates":[-83.95169199999999,35.753781],"type":"Point"}
}