{
  "type": "Feature",
  "properties": {
    "iso:country":"US",
    "sg:address":"2129 Gunbarrel Rd",
    "sg:city":"Chattanooga",
    "sg:classifiers":[
        {
            "category":"Retail",
            "subcategory":"Laundry & Dry Cleaning",
            "type":"Services"
        }
    ],
    "sg:phone":"+1 423 894 4035",
    "sg:postcode":"37421",
    "sg:province":"TN",
    "sg:tags":[
        "garment",
        "agent",
        "cleaners"
    ],
    "wof:name":"Kleen-A-Matic Inc",
    "wof:placetype":"venue"
},
  "geometry": {"coordinates":[-85.152618,35.035584],"type":"Point"}
}