{
  "type": "Feature",
  "properties": {
    "iso:country":"US",
    "sg:address":"2525 Pled Wade Rd",
    "sg:city":"Puryear",
    "sg:phone":"+1 731 782 3636",
    "sg:postcode":"38251",
    "sg:province":"TN",
    "sg:tags":[
        "farm",
        "soybean"
    ],
    "wof:name":"Rocking S Angus",
    "wof:placetype":"venue"
},
  "geometry": {"coordinates":[-88.438834,36.414742],"type":"Point"}
}