{
  "type": "Feature",
  "properties": {
    "iso:country":"US",
    "sg:address":"6807 Glover Rd",
    "sg:city":"Chattanooga",
    "sg:classifiers":[
        {
            "category":"Wholesale",
            "subcategory":"Office Equipment",
            "type":"Manufacturing & Wholesale Goods"
        }
    ],
    "sg:phone":"+1 423 344 5012",
    "sg:postcode":"37416",
    "sg:province":"TN",
    "sg:tags":[
        "machine",
        "duplicating",
        "copying"
    ],
    "wof:name":"Davis Business Systems",
    "wof:placetype":"venue"
},
  "geometry": {"coordinates":[-85.143958,35.140698],"type":"Point"}
}