{
  "type": "Feature",
  "properties": {
    "iso:country":"US",
    "sg:address":"270 W Church St",
    "sg:city":"Lexington",
    "sg:classifiers":[
        {
            "category":"Shopping",
            "subcategory":"Pharmacy",
            "type":"Retail Goods"
        }
    ],
    "sg:phone":"+1 731 968 5474",
    "sg:postcode":"38351",
    "sg:province":"TN",
    "wof:name":"Professional Arts Pharmacy",
    "wof:placetype":"venue"
},
  "geometry": {"coordinates":[-88.403161,35.655358],"type":"Point"}
}