{
  "type": "Feature",
  "properties": {
    "iso:country":"US",
    "sg:address":"112 Calderwood Hwy",
    "sg:city":"Maryville",
    "sg:classifiers":[
        {
            "category":"Retail",
            "subcategory":"Auto Repair",
            "type":"Services"
        }
    ],
    "sg:phone":"+1 865 984 7436",
    "sg:postcode":"37801",
    "sg:province":"TN",
    "sg:tags":[
        "repairing",
        "automobile",
        "general"
    ],
    "wof:name":"Foothills Auto Center",
    "wof:placetype":"venue"
},
  "geometry": {"coordinates":[-84.04370900000001,35.696211],"type":"Point"}
}