{
  "type": "Feature",
  "properties": {
    "addr:full":"3108 New Allen Rd Memphis TN 38128",
    "addr:housenumber":"3108",
    "addr:postcode":"38128",
    "addr:street":"New Allen Rd",
    "iso:country":"US",
    "sg:address":"3108 New Allen Rd",
    "sg:city":"Memphis",
    "sg:classifiers":[
        {
            "category":"Real Estate",
            "subcategory":"Real Estate Operator",
            "type":"Services"
        }
    ],
    "sg:phone":"+1 901 386 6861",
    "sg:postcode":"38128",
    "sg:province":"TN",
    "sg:tags":[
        "apartment"
    ],
    "wof:name":"Hunters Ridge Apartments",
    "wof:placetype":"venue"
},
  "geometry": {"coordinates":[-89.95282,35.210724],"type":"Point"}
}