{
  "type": "Feature",
  "properties": {
    "addr:full":"5397 Rawlings Rd Joelton TN 37080",
    "addr:housenumber":"5397",
    "addr:postcode":"37080",
    "addr:street":"Rawlings Rd",
    "iso:country":"US",
    "sg:address":"5397 Rawlings Rd",
    "sg:city":"Joelton",
    "sg:classifiers":[
        {
            "category":"Restaurant",
            "type":"Food & Drink"
        }
    ],
    "sg:phone":"+1 615 876 0700",
    "sg:postcode":"37080",
    "sg:province":"TN",
    "sg:tags":[
        "eating"
    ],
    "wof:name":"Shadowbrook",
    "wof:placetype":"venue"
},
  "geometry": {"coordinates":[-86.890479,36.311957],"type":"Point"}
}