{
  "type": "Feature",
  "properties": {
    "iso:country":"US",
    "sg:address":"3386 N Watkins St",
    "sg:city":"Memphis",
    "sg:classifiers":[
        {
            "category":"Utilities",
            "subcategory":"Mobile Phone",
            "type":"Services"
        }
    ],
    "sg:phone":"+1 901 353 9904",
    "sg:postcode":"38127",
    "sg:province":"TN",
    "sg:tags":[
        "telephone",
        "cellular"
    ],
    "wof:name":"Chit Chat Wireless",
    "wof:placetype":"venue"
},
  "geometry": {"coordinates":[-90.003286,35.219146],"type":"Point"}
}