{
  "type": "Feature",
  "properties": {
    "iso:country":"US",
    "sg:address":"325 Fawn Lake Dr",
    "sg:city":"Millington",
    "sg:classifiers":[
        {
            "category":"Real Estate",
            "subcategory":"Real Estate Operator",
            "type":"Services"
        }
    ],
    "sg:phone":"+1 901 876 5760",
    "sg:postcode":"38053",
    "sg:province":"TN",
    "sg:tags":[
        "property",
        "lessor"
    ],
    "wof:name":"Marilyn Presson",
    "wof:placetype":"venue"
},
  "geometry": {"coordinates":[-90.052055,35.316441],"type":"Point"}
}