{
  "type": "Feature",
  "properties": {
    "addr:full":"125 Public Sq Gallatin TN 37066",
    "addr:housenumber":"125",
    "addr:postcode":"37066",
    "addr:street":"Public Sq",
    "iso:country":"US",
    "sg:address":"125 Public Sq",
    "sg:city":"Gallatin",
    "sg:classifiers":[
        {
            "category":"Professional",
            "subcategory":"Lawyer & Legal Services",
            "type":"Services"
        }
    ],
    "sg:phone":"+1 615 452 2000",
    "sg:postcode":"37066",
    "sg:province":"TN",
    "wof:name":"Kelly Philip",
    "wof:placetype":"venue"
},
  "geometry": {"coordinates":[-86.445796,36.388697],"type":"Point"}
}