{
  "type": "Feature",
  "properties": {
    "iso:country":"US",
    "sg:address":"4636 Fennel Rd NE",
    "sg:city":"Knoxville",
    "sg:classifiers":[
        {
            "category":"Building & Trades",
            "subcategory":"Construction",
            "type":"Services"
        }
    ],
    "sg:phone":"+1 865 633 5051",
    "sg:postcode":"37912",
    "sg:province":"TN",
    "sg:tags":[
        "concrete",
        "contractor"
    ],
    "wof:name":"Total Polish Solutions",
    "wof:placetype":"venue"
},
  "geometry": {"coordinates":[-83.96232000000001,36.009108],"type":"Point"}
}