{
  "type": "Feature",
  "properties": {
    "iso:country":"US",
    "sg:address":"1172 Fort Campbell Blvd",
    "sg:city":"Clarksville",
    "sg:classifiers":[
        {
            "category":"Building & Trades",
            "subcategory":"Equipment Rental",
            "type":"Services"
        }
    ],
    "sg:phone":"+1 931 648 2400",
    "sg:postcode":"37042",
    "sg:province":"TN",
    "sg:tags":[
        "camping"
    ],
    "wof:name":"Cathedral Tent Rental & Mfg",
    "wof:placetype":"venue"
},
  "geometry": {"coordinates":[-87.39619399999999,36.555114],"type":"Point"}
}