{
  "type": "Feature",
  "properties": {
    "iso:country":"US",
    "sg:address":"1007 May Ave",
    "sg:city":"Knoxville",
    "sg:classifiers":[
        {
            "category":"Manufacturing",
            "subcategory":"Signs",
            "type":"Manufacturing & Wholesale Goods"
        },
        {
            "category":"Building & Trades",
            "subcategory":"Construction",
            "type":"Services"
        }
    ],
    "sg:phone":"+1 865 546 6251",
    "sg:postcode":"37921",
    "sg:province":"TN",
    "wof:name":"Neon Service Company Inc",
    "wof:placetype":"venue"
},
  "geometry": {"coordinates":[-83.93067000000001,35.973313],"type":"Point"}
}