{
  "type": "Feature",
  "properties": {
    "addr:full":"6 N Washington Ave Brownsville TN 38012",
    "addr:housenumber":"6",
    "addr:postcode":"38012",
    "addr:street":"N Washington Ave",
    "iso:country":"US",
    "sg:address":"6 N Washington Ave",
    "sg:city":"Brownsville",
    "sg:classifiers":[
        {
            "category":"Banks & Credit Unions",
            "subcategory":"Bank",
            "type":"Services"
        }
    ],
    "sg:phone":"+1 731 772 1642",
    "sg:postcode":"38012",
    "sg:province":"TN",
    "sg:website":"www.unionplanters.com",
    "wof:name":"Union Planters Bank",
    "wof:placetype":"venue"
},
  "geometry": {"coordinates":[-89.26208699999999,35.593839],"type":"Point"}
}