{
  "type": "Feature",
  "properties": {
    "iso:country":"US",
    "sg:address":"201 Rose St",
    "sg:city":"Franklin",
    "sg:classifiers":[
        {
            "category":"Professional",
            "subcategory":"Business Services",
            "type":"Services"
        }
    ],
    "sg:phone":"+1 615 599 6100",
    "sg:postcode":"37073",
    "sg:province":"TN",
    "sg:tags":[
        "interior",
        "consultant",
        "design",
        "decorator"
    ],
    "sg:website":"www.spectruminteriors.com",
    "wof:name":"Spectrum Interiors Tenn Inc",
    "wof:placetype":"venue"
},
  "geometry": {"coordinates":[-86.781747,36.410976],"type":"Point"}
}