{
  "type": "Feature",
  "properties": {
    "iso:country":"US",
    "sg:address":"500 Deaderick St",
    "sg:city":"Nashville",
    "sg:classifiers":[
        {
            "category":"Government",
            "subcategory":"Jail",
            "type":"Public Place"
        }
    ],
    "sg:phone":"+1 615 741 3816",
    "sg:postcode":"37219",
    "sg:province":"TN",
    "sg:tags":[
        "correctional",
        "for",
        "support",
        "state",
        "govt",
        "institution"
    ],
    "wof:name":"Tennesse Corrections Institute",
    "wof:placetype":"venue"
},
  "geometry": {"coordinates":[-86.780998,36.165527],"type":"Point"}
}