{
  "type": "Feature",
  "properties": {
    "addr:full":"8445 US Hwy 51 N Millington TN 38053",
    "addr:housenumber":"8445",
    "addr:postcode":"38053",
    "addr:street":"Us Hwy 51 N",
    "iso:country":"US",
    "sg:address":"8445 US Hwy 51 N",
    "sg:city":"Millington",
    "sg:classifiers":[
        {
            "category":"Food & Beverages",
            "subcategory":"Specialty",
            "type":"Retail Goods"
        }
    ],
    "sg:phone":"+1 901 872 8550",
    "sg:postcode":"38053",
    "sg:province":"TN",
    "wof:name":"GNC",
    "wof:placetype":"venue"
},
  "geometry": {"coordinates":[-89.89480500000001,35.356892],"type":"Point"}
}