{
  "type": "Feature",
  "properties": {
    "addr:full":"152 Mifflin Rd Jackson TN 38301",
    "addr:housenumber":"152",
    "addr:postcode":"38301",
    "addr:street":"Mifflin Rd",
    "iso:country":"US",
    "sg:address":"152 Mifflin Rd",
    "sg:city":"Jackson",
    "sg:classifiers":[
        {
            "category":"Sports & Exercise",
            "subcategory":"Gym",
            "type":"Entertainment"
        }
    ],
    "sg:phone":"+1 731 660 5850",
    "sg:postcode":"38301",
    "sg:province":"TN",
    "sg:tags":[
        "spa"
    ],
    "wof:name":"V I P Family Spa",
    "wof:placetype":"venue"
},
  "geometry": {"coordinates":[-88.76663000000001,35.602468],"type":"Point"}
}