{
  "type": "Feature",
  "properties": {
    "iso:country":"US",
    "sg:address":"232 Hatton Pl",
    "sg:city":"Ashland City",
    "sg:classifiers":[
        {
            "category":"Utilities",
            "subcategory":"Mobile Phone",
            "type":"Services"
        }
    ],
    "sg:phone":"+1 615 792 9595",
    "sg:postcode":"37067",
    "sg:province":"TN",
    "sg:tags":[
        "telephone",
        "cellular"
    ],
    "sg:website":"www.americancellular.com",
    "wof:name":"American Cellular",
    "wof:placetype":"venue"
},
  "geometry": {"coordinates":[-86.801806,35.955697],"type":"Point"}
}