{
  "type": "Feature",
  "properties": {
    "iso:country":"US",
    "sg:address":"11 Music Cir E",
    "sg:city":"Nashville",
    "sg:classifiers":[
        {
            "category":"Professional",
            "subcategory":"Management & Consulting",
            "type":"Services"
        }
    ],
    "sg:phone":"+1 615 782 0105",
    "sg:postcode":"37203",
    "sg:province":"TN",
    "sg:tags":[
        "public",
        "relations"
    ],
    "wof:name":"Logicom",
    "wof:placetype":"venue"
},
  "geometry": {"coordinates":[-86.789255,36.151989],"type":"Point"}
}