{
  "type": "Feature",
  "properties": {
    "addr:full":"170 John France Rd Jonesborough TN 37659",
    "addr:housenumber":"170",
    "addr:postcode":"37659",
    "addr:street":"John France Rd",
    "iso:country":"US",
    "sg:address":"170 John France Rd",
    "sg:city":"Jonesborough",
    "sg:classifiers":[
        {
            "category":"Real Estate",
            "subcategory":"Real Estate Agent",
            "type":"Services"
        }
    ],
    "sg:phone":"+1 423 753 0737",
    "sg:postcode":"37659",
    "sg:province":"TN",
    "wof:name":"Grace Commercial Properties",
    "wof:placetype":"venue"
},
  "geometry": {"coordinates":[-82.438282,36.325],"type":"Point"}
}