{
  "type": "Feature",
  "properties": {
    "addr:full":"1940 Hixson Marina Rd Hixson TN 37343",
    "addr:housenumber":"1940",
    "addr:postcode":"37343",
    "addr:street":"Hixson Marina Rd",
    "iso:country":"US",
    "sg:address":"1940 Hixson Marina Rd",
    "sg:city":"Hixson",
    "sg:classifiers":[
        {
            "category":"Retail",
            "subcategory":"Repair Shop",
            "type":"Services"
        },
        {
            "category":"Recreation",
            "subcategory":"Marina",
            "type":"Entertainment"
        }
    ],
    "sg:phone":"+1 423 847 0076",
    "sg:postcode":"37343",
    "sg:province":"TN",
    "sg:tags":[
        "repairing",
        "boat"
    ],
    "wof:name":"Larry Knight Marine Service",
    "wof:placetype":"venue"
},
  "geometry": {"coordinates":[-85.18418800000001,35.143892],"type":"Point"}
}