{
  "type": "Feature",
  "properties": {
    "addr:full":"112 E Main St Woodbury TN 37190",
    "addr:housenumber":"112",
    "addr:postcode":"37190",
    "addr:street":"E Main St",
    "iso:country":"US",
    "sg:address":"112 E Main St",
    "sg:city":"Woodbury",
    "sg:classifiers":[
        {
            "category":"Health Services",
            "subcategory":"Optometrist",
            "type":"Services"
        }
    ],
    "sg:phone":"+1 615 563 8494",
    "sg:postcode":"37190",
    "sg:province":"TN",
    "wof:name":"Woodbury Optometry Center",
    "wof:placetype":"venue"
},
  "geometry": {"coordinates":[-86.068701,35.827588],"type":"Point"}
}