{
  "type": "Feature",
  "properties": {
    "iso:country":"US",
    "sg:address":"321 W Mallory Ave",
    "sg:city":"Memphis",
    "sg:classifiers":[
        {
            "category":"Autos & Motor Vehicles",
            "subcategory":"Fuel & Gas Station",
            "type":"Retail Goods"
        },
        {
            "category":"Manufacturing",
            "subcategory":"Petroleum Products",
            "type":"Manufacturing & Wholesale Goods"
        },
        {
            "category":"Wholesale",
            "subcategory":"Petroleum",
            "type":"Manufacturing & Wholesale Goods"
        }
    ],
    "sg:phone":"+1 901 775 5767",
    "sg:postcode":"38109",
    "sg:province":"TN",
    "sg:tags":[
        "oil",
        "refiner",
        "products-wholesale",
        "manufacturer",
        "oils-petroleum"
    ],
    "sg:website":"http://www.premcor.com",
    "wof:name":"Lima Refinery Company",
    "wof:placetype":"venue"
},
  "geometry": {"coordinates":[-90.07437400000001,35.08683],"type":"Point"}
}