{
  "type": "Feature",
  "properties": {
    "iso:country":"US",
    "sg:address":"2061 Old Rock Island Rd",
    "sg:city":"Rock Island",
    "sg:classifiers":[
        {
            "category":"Organizations",
            "subcategory":"Community Association",
            "type":"Services"
        }
    ],
    "sg:phone":"+1 931 686 2996",
    "sg:postcode":"38581",
    "sg:province":"TN",
    "wof:name":"Boy Scout Troop 499",
    "wof:placetype":"venue"
},
  "geometry": {"coordinates":[-85.660663,35.739647],"type":"Point"}
}