{
  "type": "Feature",
  "properties": {
    "iso:country":"US",
    "sg:address":"374 State Hwy 100",
    "sg:city":"Centerville",
    "sg:classifiers":[
        {
            "category":"Retail",
            "subcategory":"Auto Repair",
            "type":"Services"
        }
    ],
    "sg:phone":"+1 931 729 5113",
    "sg:postcode":"37033",
    "sg:province":"TN",
    "sg:tags":[
        "body"
    ],
    "wof:name":"Bryant Automotive",
    "wof:placetype":"venue"
},
  "geometry": {"coordinates":[-87.449761,35.788402],"type":"Point"}
}