{
  "type": "Feature",
  "properties": {
    "addr:full":"2130 Old Nashville Dirt Rd Shelbyville TN 37160",
    "addr:housenumber":"2130",
    "addr:postcode":"37160",
    "addr:street":"Old Nashville Dirt Rd",
    "iso:country":"US",
    "sg:address":"2130 Old Nashville Dirt Rd",
    "sg:city":"Shelbyville",
    "sg:classifiers":[
        {
            "category":"Shopping",
            "type":"Retail Goods"
        }
    ],
    "sg:phone":"+1 931 294 3204",
    "sg:postcode":"37160",
    "sg:province":"TN",
    "sg:tags":[
        "merchandise"
    ],
    "wof:name":"Artistic Treasures",
    "wof:placetype":"venue"
},
  "geometry": {"coordinates":[-86.52817400000001,35.594402],"type":"Point"}
}