{
  "type": "Feature",
  "properties": {
    "iso:country":"US",
    "sg:address":"816 Marina St",
    "sg:city":"Nashville",
    "sg:classifiers":[
        {
            "category":"Arts & Performance",
            "subcategory":"Theater",
            "type":"Entertainment"
        }
    ],
    "sg:phone":"+1 615 668 7345",
    "sg:postcode":"37206",
    "sg:province":"TN",
    "sg:tags":[
        "bureau"
    ],
    "wof:name":"Professional Electronic Gaming",
    "wof:placetype":"venue"
},
  "geometry": {"coordinates":[-86.759643,36.180779],"type":"Point"}
}