{
  "type": "Feature",
  "properties": {
    "iso:country":"US",
    "sg:address":"9659 Woodland Run Ln",
    "sg:city":"Cordova",
    "sg:classifiers":[
        {
            "category":"Building & Trades",
            "subcategory":"Construction",
            "type":"Services"
        }
    ],
    "sg:phone":"+1 901 461 7484",
    "sg:postcode":"38018",
    "sg:province":"TN",
    "sg:tags":[
        "resurfacing",
        "laying",
        "refinishing",
        "floor"
    ],
    "wof:name":"B & B Premier Floors",
    "wof:placetype":"venue"
},
  "geometry": {"coordinates":[-89.740223,35.151187],"type":"Point"}
}