{
  "type": "Feature",
  "properties": {
    "iso:country":"US",
    "sg:address":"224 Martin Burgess Rd",
    "sg:city":"Crossville",
    "sg:classifiers":[
        {
            "category":"Recreation",
            "type":"Entertainment"
        }
    ],
    "sg:phone":"+1 931 788 5408",
    "sg:postcode":"38572",
    "sg:province":"TN",
    "sg:tags":[
        "guide"
    ],
    "wof:name":"Loshbough Hunting Range Office",
    "wof:placetype":"venue"
},
  "geometry": {"coordinates":[-85.17203000000001,35.836101],"type":"Point"}
}