{
  "type": "Feature",
  "properties": {
    "addr:full":"1668 Memorial Blvd Murfreesboro TN 37129",
    "addr:housenumber":"1668",
    "addr:postcode":"37129",
    "addr:street":"Memorial Blvd",
    "iso:country":"US",
    "sg:address":"1668 Memorial Blvd",
    "sg:city":"Murfreesboro",
    "sg:classifiers":[
        {
            "category":"Manufacturing",
            "subcategory":"Printing",
            "type":"Manufacturing & Wholesale Goods"
        }
    ],
    "sg:phone":"+1 615 890 2266",
    "sg:postcode":"37129",
    "sg:province":"TN",
    "sg:tags":[
        "printer",
        "offset"
    ],
    "wof:name":"Sierra Copies & Printing",
    "wof:placetype":"venue"
},
  "geometry": {"coordinates":[-86.397048,35.852282],"type":"Point"}
}