{
  "type": "Feature",
  "properties": {
    "addr:full":"90 Parks Plz Trimble TN 38259",
    "addr:housenumber":"90",
    "addr:postcode":"38259",
    "addr:street":"Parks Plz",
    "iso:country":"US",
    "sg:address":"90 Parks Plz",
    "sg:city":"Trimble",
    "sg:classifiers":[
        {
            "category":"Government",
            "subcategory":"Police Station",
            "type":"Public Place"
        }
    ],
    "sg:phone":"+1 731 297 3177",
    "sg:postcode":"38259",
    "sg:province":"TN",
    "sg:tags":[
        "department"
    ],
    "wof:name":"Trimble Police Dept",
    "wof:placetype":"venue"
},
  "geometry": {"coordinates":[-89.191492,36.204273],"type":"Point"}
}