{
  "type": "Feature",
  "properties": {
    "iso:country":"US",
    "sg:address":"1048 4th Ave S",
    "sg:city":"Nashville",
    "sg:classifiers":[
        {
            "category":"Manufacturing",
            "subcategory":"Building Materials",
            "type":"Manufacturing & Wholesale Goods"
        }
    ],
    "sg:phone":"+1 615 256 5615",
    "sg:postcode":"37210",
    "sg:province":"TN",
    "sg:tags":[
        "mfg",
        "wood",
        "kitchen",
        "cabinet"
    ],
    "wof:name":"Rich Brothers Mllwk & Lbr Co",
    "wof:placetype":"venue"
},
  "geometry": {"coordinates":[-86.767833,36.146848],"type":"Point"}
}