{
  "type": "Feature",
  "properties": {
    "iso:country":"US",
    "sg:address":"4409 Chapman Hwy",
    "sg:city":"Knoxville",
    "sg:classifiers":[
        {
            "category":"Banks & Credit Unions",
            "subcategory":"Bank",
            "type":"Services"
        }
    ],
    "sg:phone":"+1 865 577 3113",
    "sg:postcode":"37920",
    "sg:province":"TN",
    "sg:tags":[
        "cashing",
        "agency",
        "check"
    ],
    "wof:name":"Check Into Cash",
    "wof:placetype":"venue"
},
  "geometry": {"coordinates":[-83.904143,35.932887],"type":"Point"}
}