{
  "type": "Feature",
  "properties": {
    "iso:country":"US",
    "sg:address":"1229 Heil Quaker Blvd",
    "sg:city":"La Vergne",
    "sg:classifiers":[
        {
            "category":"Manufacturing",
            "subcategory":"Tools & Machinery",
            "type":"Manufacturing & Wholesale Goods"
        }
    ],
    "sg:phone":"+1 615 793 6653",
    "sg:postcode":"37086",
    "sg:province":"TN",
    "sg:tags":[
        "die",
        "mfg"
    ],
    "sg:website":"www.kennedyandbowden.com",
    "wof:name":"Kennedy & Bowden Machine Co",
    "wof:placetype":"venue"
},
  "geometry": {"coordinates":[-86.605388,36.004101],"type":"Point"}
}