{
  "type": "Feature",
  "properties": {
    "iso:country":"US",
    "sg:address":"410 W Main St",
    "sg:city":"Mc Minnville",
    "sg:classifiers":[
        {
            "category":"Organizations",
            "subcategory":"Professional Association",
            "type":"Services"
        }
    ],
    "sg:phone":"+1 931 473 3860",
    "sg:postcode":"37110",
    "sg:province":"TN",
    "sg:website":"www.americanheart.org",
    "wof:name":"American Heart Assn",
    "wof:placetype":"venue"
},
  "geometry": {"coordinates":[-85.779512,35.682956],"type":"Point"}
}