{
  "type": "Feature",
  "properties": {
    "iso:country":"US",
    "sg:address":"804 Montvale Station Rd",
    "sg:city":"Maryville",
    "sg:classifiers":[
        {
            "category":"Education",
            "subcategory":"School",
            "type":"Public Place"
        }
    ],
    "sg:phone":"+1 865 984 8917",
    "sg:postcode":"37803",
    "sg:province":"TN",
    "sg:tags":[
        "child",
        "day",
        "care"
    ],
    "wof:name":"Wesley Day School",
    "wof:placetype":"venue"
},
  "geometry": {"coordinates":[-83.969818,35.741962],"type":"Point"}
}