{
  "type": "Feature",
  "properties": {
    "addr:full":"812 W College St Pulaski TN 38478",
    "addr:housenumber":"812",
    "addr:postcode":"38478",
    "addr:street":"W College St",
    "iso:country":"US",
    "sg:address":"812 W College St",
    "sg:city":"Pulaski",
    "sg:classifiers":[
        {
            "category":"Restaurant",
            "type":"Food & Drink"
        }
    ],
    "sg:menulink":"http://www.allmenus.com/tn/pulaski/201833-mcdonalds/menu/",
    "sg:phone":"+1 931 363 8670",
    "sg:postcode":"38478",
    "sg:province":"TN",
    "sg:tags":[
        "burger",
        "american"
    ],
    "wof:name":"McDonald's",
    "wof:placetype":"venue"
},
  "geometry": {"coordinates":[-87.04208199999999,35.200004],"type":"Point"}
}