{
  "type": "Feature",
  "properties": {
    "iso:country":"US",
    "sg:address":"1318 Clairmonte Ln",
    "sg:city":"Franklin",
    "sg:classifiers":[
        {
            "category":"Wholesale",
            "subcategory":"Machinery & Supplies",
            "type":"Manufacturing & Wholesale Goods"
        }
    ],
    "sg:phone":"+1 615 591 7402",
    "sg:postcode":"37064",
    "sg:province":"TN",
    "sg:tags":[
        "industrial"
    ],
    "wof:name":"Honeywell",
    "wof:placetype":"venue"
},
  "geometry": {"coordinates":[-86.889269,35.925213],"type":"Point"}
}