{
  "type": "Feature",
  "properties": {
    "iso:country":"US",
    "sg:address":"4282 Pate Rd",
    "sg:city":"Franklin",
    "sg:classifiers":[
        {
            "category":"Shopping",
            "subcategory":"Computers & Home Electronics",
            "type":"Retail Goods"
        }
    ],
    "sg:phone":"+1 615 591 6870",
    "sg:postcode":"37064",
    "sg:province":"TN",
    "sg:tags":[
        "programming"
    ],
    "wof:name":"Bjk Computer Service",
    "wof:placetype":"venue"
},
  "geometry": {"coordinates":[-86.77727299999999,35.888313],"type":"Point"}
}