{
  "type": "Feature",
  "properties": {
    "iso:country":"US",
    "sg:address":"3810 Gallatin Pike",
    "sg:city":"Nashville",
    "sg:classifiers":[
        {
            "category":"Organizations",
            "subcategory":"Religious Organization",
            "type":"Services"
        }
    ],
    "sg:phone":"+1 615 227 3022",
    "sg:postcode":"37216",
    "sg:province":"TN",
    "sg:tags":[
        "church"
    ],
    "wof:name":"Bethel Primitive Baptst Church",
    "wof:placetype":"venue"
},
  "geometry": {"coordinates":[-86.729693,36.215483],"type":"Point"}
}