{
  "type": "Feature",
  "properties": {
    "addr:full":"230 Franklin Rd Franklin TN 37064",
    "addr:housenumber":"230",
    "addr:postcode":"37064",
    "addr:street":"Franklin Rd",
    "iso:country":"US",
    "sg:address":"230 Franklin Rd",
    "sg:city":"Franklin",
    "sg:classifiers":[
        {
            "category":"Home & Garden",
            "subcategory":"Home Furnishings",
            "type":"Retail Goods"
        }
    ],
    "sg:phone":"+1 615 599 2200",
    "sg:postcode":"37064",
    "sg:province":"TN",
    "sg:tags":[
        "pottery"
    ],
    "wof:name":"Third Coast Clay Ceramic",
    "wof:placetype":"venue"
},
  "geometry": {"coordinates":[-86.860957,35.934403],"type":"Point"}
}