{
  "type": "Feature",
  "properties": {
    "addr:full":"311 E Belz Blvd Memphis TN 38109",
    "addr:housenumber":"311",
    "addr:postcode":"38109",
    "addr:street":"E Belz Blvd",
    "iso:country":"US",
    "sg:address":"311 E Belz Blvd",
    "sg:city":"Memphis",
    "sg:classifiers":[
        {
            "category":"Wholesale",
            "subcategory":"Machinery & Supplies",
            "type":"Manufacturing & Wholesale Goods"
        }
    ],
    "sg:phone":"+1 901 774 5001",
    "sg:postcode":"38109",
    "sg:province":"TN",
    "sg:tags":[
        "equipment",
        "belting",
        "conveying",
        "conveyor"
    ],
    "sg:website":"http://www.luttrellbelting.com",
    "wof:name":"Luttrell Belting & Supply Co Inc",
    "wof:placetype":"venue"
},
  "geometry": {"coordinates":[-90.053203,35.095326],"type":"Point"}
}