{
  "type": "Feature",
  "properties": {
    "iso:country":"US",
    "sg:address":"240 Samsonite Blvd",
    "sg:city":"Murfreesboro",
    "sg:classifiers":[
        {
            "category":"Professional",
            "type":"Services"
        }
    ],
    "sg:phone":"+1 615 893 9308",
    "sg:postcode":"37129",
    "sg:province":"TN",
    "wof:name":"Total Controls Inc",
    "wof:placetype":"venue"
},
  "geometry": {"coordinates":[-86.395425,35.827788],"type":"Point"}
}