{
  "type": "Feature",
  "properties": {
    "iso:country":"US",
    "sg:address":"9311 Davis Dr",
    "sg:city":"Corryton",
    "sg:classifiers":[
        {
            "category":"Personal",
            "subcategory":"Beauty Salon",
            "type":"Services"
        }
    ],
    "sg:phone":"+1 865 687 0204",
    "sg:postcode":"37721",
    "sg:province":"TN",
    "wof:name":"Corryton Beauty Nook",
    "wof:placetype":"venue"
},
  "geometry": {"coordinates":[-83.780613,36.151286],"type":"Point"}
}