{
  "type": "Feature",
  "properties": {
    "iso:country":"US",
    "sg:address":"1102 N Fillmore St",
    "sg:city":"Corinth",
    "sg:classifiers":[
        {
            "category":"Professional",
            "subcategory":"Business Services",
            "type":"Services"
        }
    ],
    "sg:phone":"+1 662 287 2697",
    "sg:postcode":"38834",
    "sg:province":"TN",
    "sg:tags":[
        "interior",
        "home",
        "decorating"
    ],
    "wof:name":"Kate Williams Interiors",
    "wof:placetype":"venue"
},
  "geometry": {"coordinates":[-88.51826,34.94049],"type":"Point"}
}