{
  "type": "Feature",
  "properties": {
    "iso:country":"US",
    "sg:address":"8995 Glenalden Dr",
    "sg:city":"Germantown",
    "sg:classifiers":[
        {
            "category":"Banks & Credit Unions",
            "subcategory":"Bank",
            "type":"Services"
        }
    ],
    "sg:phone":"+1 901 753 4400",
    "sg:postcode":"38139",
    "sg:province":"TN",
    "wof:name":"First Mercantile Trust Co",
    "wof:placetype":"venue"
},
  "geometry": {"coordinates":[-89.76437300000001,35.086535],"type":"Point"}
}