{
  "type": "Feature",
  "properties": {
    "iso:country":"US",
    "sg:address":"22 Bond St",
    "sg:city":"Jackson",
    "sg:classifiers":[
        {
            "category":"Wholesale",
            "subcategory":"Chemicals & Plastics",
            "type":"Manufacturing & Wholesale Goods"
        }
    ],
    "sg:phone":"+1 731 424 1505",
    "sg:postcode":"38301",
    "sg:province":"TN",
    "sg:tags":[
        "equipment",
        "car",
        "ti",
        "wash",
        "supply"
    ],
    "wof:name":"Golden Circle Tire Co",
    "wof:placetype":"venue"
},
  "geometry": {"coordinates":[-88.8165,35.579583],"type":"Point"}
}