{
  "type": "Feature",
  "properties": {
    "addr:full":"4536 Nolensville Pike Nashville TN 37211",
    "addr:housenumber":"4536",
    "addr:postcode":"37211",
    "addr:street":"Nolensville Pike",
    "iso:country":"US",
    "sg:address":"4536 Nolensville Pike",
    "sg:city":"Nashville",
    "sg:classifiers":[
        {
            "category":"Shopping",
            "subcategory":"Bicycles & Sporting Goods",
            "type":"Retail Goods"
        }
    ],
    "sg:phone":"+1 615 831 9550",
    "sg:postcode":"37211",
    "sg:province":"TN",
    "wof:name":"Deportes Alvarez",
    "wof:placetype":"venue"
},
  "geometry": {"coordinates":[-86.722386,36.070563],"type":"Point"}
}