{
  "type": "Feature",
  "properties": {
    "iso:country":"US",
    "sg:address":"8728 Asheville Hwy",
    "sg:city":"Knoxville",
    "sg:classifiers":[
        {
            "category":"Retail",
            "subcategory":"Auto Repair",
            "type":"Services"
        }
    ],
    "sg:phone":"+1 865 933 0160",
    "sg:postcode":"37924",
    "sg:province":"TN",
    "sg:tags":[
        "repairing",
        "automobile",
        "general"
    ],
    "wof:name":"Rusty's Garage",
    "wof:placetype":"venue"
},
  "geometry": {"coordinates":[-83.733729,36.02566],"type":"Point"}
}