{
  "type": "Feature",
  "properties": {
    "iso:country":"US",
    "sg:address":"1103 Bumpus Mills Rd",
    "sg:city":"Dover",
    "sg:classifiers":[
        {
            "category":"Building & Trades",
            "subcategory":"Construction",
            "type":"Services"
        }
    ],
    "sg:phone":"+1 931 232 4618",
    "sg:postcode":"37058",
    "sg:province":"TN",
    "sg:tags":[
        "contracting",
        "general"
    ],
    "wof:name":"Drh Contractors",
    "wof:placetype":"venue"
},
  "geometry": {"coordinates":[-87.834225,36.552806],"type":"Point"}
}