{
  "type": "Feature",
  "properties": {
    "iso:country":"US",
    "sg:address":"384 Flowertown Rd",
    "sg:city":"Normandy",
    "sg:classifiers":[
        {
            "category":"Building & Trades",
            "subcategory":"Construction",
            "type":"Services"
        }
    ],
    "sg:phone":"+1 931 455 6635",
    "sg:postcode":"37360",
    "sg:province":"TN",
    "sg:tags":[
        "general",
        "contractor"
    ],
    "wof:name":"R C Riddle General Contractor",
    "wof:placetype":"venue"
},
  "geometry": {"coordinates":[-86.25678000000001,35.404545],"type":"Point"}
}