{
  "type": "Feature",
  "properties": {
    "iso:country":"US",
    "sg:address":"4325 Chestnut Oak Cove",
    "sg:city":"Millington",
    "sg:classifiers":[
        {
            "category":"Professional",
            "subcategory":"Accounting & Tax Preparation",
            "type":"Services"
        }
    ],
    "sg:phone":"+1 901 873 2640",
    "sg:postcode":"38053",
    "sg:province":"TN",
    "wof:name":"Unique Opportunities",
    "wof:placetype":"venue"
},
  "geometry": {"coordinates":[-89.919495,35.343314],"type":"Point"}
}