{
  "type": "Feature",
  "properties": {
    "iso:country":"US",
    "sg:address":"2260 Lebanon Pike",
    "sg:city":"Nashville",
    "sg:classifiers":[
        {
            "category":"Restaurant",
            "type":"Food & Drink"
        }
    ],
    "sg:phone":"+1 615 399 9400",
    "sg:postcode":"37214",
    "sg:province":"TN",
    "wof:name":"Steak-Out Charbroiled Delivery",
    "wof:placetype":"venue"
},
  "geometry": {"coordinates":[-86.68240299999999,36.16904],"type":"Point"}
}