{
  "type": "Feature",
  "properties": {
    "iso:country":"US",
    "sg:address":"141 Steel Bridge Rd",
    "sg:city":"Elizabethton",
    "sg:classifiers":[
        {
            "category":"Travel",
            "subcategory":"Hotels & Motels",
            "type":"Entertainment"
        }
    ],
    "sg:phone":"+1 423 542 6033",
    "sg:postcode":"37643",
    "sg:province":"TN",
    "sg:tags":[
        "accommodation"
    ],
    "wof:name":"Bee Cliff Cabins",
    "wof:placetype":"venue"
},
  "geometry": {"coordinates":[-82.155196,36.350598],"type":"Point"}
}