{
  "type": "Feature",
  "properties": {
    "addr:full":"710 Locust St SW Knoxville TN 37902",
    "addr:housenumber":"710",
    "addr:postcode":"37902",
    "addr:street":"Locust St Sw",
    "iso:country":"US",
    "sg:address":"710 Locust St SW",
    "sg:city":"Knoxville",
    "sg:classifiers":[
        {
            "category":"Government",
            "subcategory":"Police Station",
            "type":"Public Place"
        }
    ],
    "sg:phone":"+1 423 544 0751",
    "sg:postcode":"37902",
    "sg:province":"TN",
    "sg:tags":[
        "investigation"
    ],
    "wof:name":"FBI",
    "wof:placetype":"venue"
},
  "geometry": {"coordinates":[-83.919905,35.961479],"type":"Point"}
}