{
  "type": "Feature",
  "properties": {
    "iso:country":"US",
    "sg:address":"30 State Rte 186 N",
    "sg:city":"Humboldt",
    "sg:classifiers":[
        {
            "category":"Organizations",
            "subcategory":"Religious Organization",
            "type":"Services"
        }
    ],
    "sg:phone":"+1 731 787 6007",
    "sg:postcode":"38343",
    "sg:province":"TN",
    "sg:tags":[
        "church"
    ],
    "wof:name":"Parker's Chapel CME Church",
    "wof:placetype":"venue"
},
  "geometry": {"coordinates":[-88.843031,35.891765],"type":"Point"}
}