{
  "type": "Feature",
  "properties": {
    "iso:country":"US",
    "sg:address":"520 W College St",
    "sg:city":"Murfreesboro",
    "sg:classifiers":[
        {
            "category":"Retail",
            "subcategory":"Auto Repair",
            "type":"Services"
        }
    ],
    "sg:phone":"+1 615 895 8142",
    "sg:postcode":"37130",
    "sg:province":"TN",
    "sg:tags":[
        "body"
    ],
    "wof:name":"Uptown Collision Inc",
    "wof:placetype":"venue"
},
  "geometry": {"coordinates":[-86.396784,35.848519],"type":"Point"}
}