{
  "type": "Feature",
  "properties": {
    "addr:full":"4211 Charlotte Ave Nashville TN 37209",
    "addr:housenumber":"4211",
    "addr:postcode":"37209",
    "addr:street":"Charlotte Ave",
    "iso:country":"US",
    "sg:address":"4211 Charlotte Ave",
    "sg:city":"Nashville",
    "sg:classifiers":[
        {
            "category":"Food & Beverages",
            "subcategory":"Groceries & Convenience Stores",
            "type":"Retail Goods"
        }
    ],
    "sg:phone":"+1 615 298 5474",
    "sg:postcode":"37209",
    "sg:province":"TN",
    "wof:name":"Mapco Express",
    "wof:placetype":"venue"
},
  "geometry": {"coordinates":[-86.83750999999999,36.152285],"type":"Point"}
}