{
  "type": "Feature",
  "properties": {
    "addr:full":"3332 US Hwy 41 S Springfield TN 37172",
    "addr:housenumber":"3332",
    "addr:postcode":"37172",
    "addr:street":"Us Hwy 41 S",
    "iso:country":"US",
    "sg:address":"3332 US Hwy 41 S",
    "sg:city":"Springfield",
    "sg:classifiers":[
        {
            "category":"Retail",
            "subcategory":"Veterinary Services",
            "type":"Services"
        }
    ],
    "sg:phone":"+1 615 643 7931",
    "sg:postcode":"37172",
    "sg:province":"TN",
    "sg:tags":[
        "veterinarian"
    ],
    "wof:name":"Greenbrier-Springfield Animal",
    "wof:placetype":"venue"
},
  "geometry": {"coordinates":[-86.836392,36.46307],"type":"Point"}
}