{
  "type": "Feature",
  "properties": {
    "addr:full":"913 Davidson St Tullahoma TN 37388",
    "addr:housenumber":"913",
    "addr:postcode":"37388",
    "addr:street":"Davidson St",
    "iso:country":"US",
    "sg:address":"913 Davidson St",
    "sg:city":"Tullahoma",
    "sg:classifiers":[
        {
            "category":"Retail",
            "subcategory":"Auto Repair",
            "type":"Services"
        }
    ],
    "sg:phone":"+1 931 455 4747",
    "sg:postcode":"37388",
    "sg:province":"TN",
    "sg:tags":[
        "repairing",
        "automobile",
        "general"
    ],
    "wof:name":"Bruce's Auto Repair",
    "wof:placetype":"venue"
},
  "geometry": {"coordinates":[-86.216621,35.371757],"type":"Point"}
}