{
  "type": "Feature",
  "properties": {
    "addr:full":"412 Broadway Nashville TN 37203",
    "addr:housenumber":"412",
    "addr:postcode":"37203",
    "addr:street":"Broadway",
    "iso:country":"US",
    "sg:address":"412 Broadway",
    "sg:city":"Nashville",
    "sg:classifiers":[
        {
            "category":"Recreation",
            "type":"Entertainment"
        },
        {
            "category":"Organizations",
            "subcategory":"Community Association",
            "type":"Services"
        }
    ],
    "sg:phone":"+1 615 726 0504",
    "sg:postcode":"37203",
    "sg:province":"TN",
    "sg:tags":[
        "club",
        "membership"
    ],
    "wof:name":"Stage On Broadway Inc",
    "wof:placetype":"venue"
},
  "geometry": {"coordinates":[-86.77770200000001,36.160896],"type":"Point"}
}