{
  "type": "Feature",
  "properties": {
    "iso:country":"US",
    "sg:address":"1336 N Watkins St",
    "sg:city":"Memphis",
    "sg:classifiers":[
        {
            "category":"Retail",
            "subcategory":"Auto Repair",
            "type":"Services"
        }
    ],
    "sg:phone":"+1 901 728 4404",
    "sg:postcode":"38108",
    "sg:province":"TN",
    "sg:tags":[
        "body",
        "painting",
        "repairing",
        "automobile"
    ],
    "wof:name":"Mid-City Body Works",
    "wof:placetype":"venue"
},
  "geometry": {"coordinates":[-90.008422,35.17553],"type":"Point"}
}