{
  "type": "Feature",
  "properties": {
    "addr:full":"2645 W Andrew Johnson Hwy Morristown TN 37814",
    "addr:housenumber":"2645",
    "addr:postcode":"37814",
    "addr:street":"W Andrew Johnson Hwy",
    "iso:country":"US",
    "sg:address":"2645 W Andrew Johnson Hwy",
    "sg:city":"Morristown",
    "sg:classifiers":[
        {
            "category":"Building & Trades",
            "subcategory":"Equipment Rental",
            "type":"Services"
        }
    ],
    "sg:phone":"+1 423 581 6825",
    "sg:postcode":"37814",
    "sg:province":"TN",
    "sg:tags":[
        "appliance"
    ],
    "wof:name":"Aarons Sales & Lease Ownership",
    "wof:placetype":"venue"
},
  "geometry": {"coordinates":[-83.329026,36.203099],"type":"Point"}
}