{
  "type": "Feature",
  "properties": {
    "iso:country":"US",
    "sg:address":"6910 Shallowford Rd",
    "sg:city":"Chattanooga",
    "sg:classifiers":[
        {
            "category":"Personal",
            "subcategory":"Tattoo Parlor",
            "type":"Services"
        }
    ],
    "sg:phone":"+1 423 899 0056",
    "sg:postcode":"37421",
    "sg:province":"TN",
    "sg:tags":[
        "tattooing"
    ],
    "wof:name":"Evermore Galleries",
    "wof:placetype":"venue"
},
  "geometry": {"coordinates":[-85.162195,35.044747],"type":"Point"}
}