{
  "type": "Feature",
  "properties": {
    "iso:country":"US",
    "sg:address":"411 Big Horn Dr",
    "sg:city":"Old Hickory",
    "sg:classifiers":[
        {
            "category":"Freight",
            "type":"Transportation"
        }
    ],
    "sg:phone":"+1 615 541 0412",
    "sg:postcode":"37138",
    "sg:province":"TN",
    "sg:tags":[
        "trucking"
    ],
    "wof:name":"Golden Rule Transportation Inc",
    "wof:placetype":"venue"
},
  "geometry": {"coordinates":[-86.583668,36.223749],"type":"Point"}
}