{
  "type": "Feature",
  "properties": {
    "iso:country":"US",
    "sg:address":"829 Mount Moriah Rd",
    "sg:city":"Memphis",
    "sg:classifiers":[
        {
            "category":"Shopping",
            "subcategory":"Clothing, Apparel, & Fashions",
            "type":"Retail Goods"
        }
    ],
    "sg:phone":"+1 901 682 8989",
    "sg:postcode":"38117",
    "sg:province":"TN",
    "sg:tags":[
        "alteration"
    ],
    "wof:name":"Nandwani's Alterations",
    "wof:placetype":"venue"
},
  "geometry": {"coordinates":[-89.895458,35.106982],"type":"Point"}
}