{
  "type": "Feature",
  "properties": {
    "addr:full":"6936 McMinnville Hwy Manchester TN 37355",
    "addr:housenumber":"6936",
    "addr:postcode":"37355",
    "addr:street":"Mcminnville Hwy",
    "iso:country":"US",
    "sg:address":"6936 McMinnville Hwy",
    "sg:city":"Manchester",
    "sg:classifiers":[
        {
            "category":"Building & Trades",
            "subcategory":"Construction",
            "type":"Services"
        }
    ],
    "sg:phone":"+1 931 723 0922",
    "sg:postcode":"37355",
    "sg:province":"TN",
    "sg:tags":[
        "paving",
        "contractor"
    ],
    "wof:name":"Keele & Wooten",
    "wof:placetype":"venue"
},
  "geometry": {"coordinates":[-85.995058,35.545989],"type":"Point"}
}