{
  "type": "Feature",
  "properties": {
    "addr:full":"116 Longwood Pl Nashville TN 37215",
    "addr:housenumber":"116",
    "addr:postcode":"37215",
    "addr:street":"Longwood Pl",
    "iso:country":"US",
    "sg:address":"116 Longwood Pl",
    "sg:city":"Nashville",
    "sg:classifiers":[
        {
            "category":"Organizations",
            "subcategory":"Community Association",
            "type":"Services"
        }
    ],
    "sg:phone":"+1 615 385 4240",
    "sg:postcode":"37215",
    "sg:province":"TN",
    "wof:name":"Longwood Homeowners Assn",
    "wof:placetype":"venue"
},
  "geometry": {"coordinates":[-86.830009,36.109872],"type":"Point"}
}