{
  "type": "Feature",
  "properties": {
    "iso:country":"US",
    "sg:address":"711 Mountain View Rd",
    "sg:city":"Benton",
    "sg:classifiers":[
        {
            "category":"Autos & Motor Vehicles",
            "subcategory":"Automobile Sales",
            "type":"Retail Goods"
        }
    ],
    "sg:phone":"+1 423 338 2709",
    "sg:postcode":"37307",
    "sg:province":"TN",
    "sg:tags":[
        "used"
    ],
    "wof:name":"Millers Motor Company",
    "wof:placetype":"venue"
},
  "geometry": {"coordinates":[-84.58753,35.206078],"type":"Point"}
}