{
  "type": "Feature",
  "properties": {
    "iso:country":"US",
    "sg:address":"10312 Chapman Hwy",
    "sg:city":"Seymour",
    "sg:classifiers":[
        {
            "category":"Autos & Motor Vehicles",
            "subcategory":"Auto Supplies",
            "type":"Retail Goods"
        }
    ],
    "sg:phone":"+1 865 577 3917",
    "sg:postcode":"37865",
    "sg:province":"TN",
    "sg:tags":[
        "automobile",
        "parts"
    ],
    "wof:name":"Paul Ellis Ford Parts",
    "wof:placetype":"venue"
},
  "geometry": {"coordinates":[-83.784926,35.88206],"type":"Point"}
}