{
  "type": "Feature",
  "properties": {
    "iso:country":"US",
    "sg:address":"2515 Perimeter Place Dr",
    "sg:city":"Nashville",
    "sg:classifiers":[
        {
            "category":"Government",
            "subcategory":"Police Station",
            "type":"Public Place"
        }
    ],
    "sg:phone":"+1 615 889 6937",
    "sg:postcode":"37214",
    "sg:province":"TN",
    "sg:tags":[
        "department"
    ],
    "wof:name":"Chief Of Resource Management",
    "wof:placetype":"venue"
},
  "geometry": {"coordinates":[-86.67984,36.148716],"type":"Point"}
}