{
  "type": "Feature",
  "properties": {
    "iso:country":"US",
    "sg:address":"8739 Raspberry Ln",
    "sg:city":"Cordova",
    "sg:classifiers":[
        {
            "category":"Home & Garden",
            "subcategory":"Building Materials",
            "type":"Retail Goods"
        },
        {
            "category":"Building & Trades",
            "subcategory":"Construction",
            "type":"Services"
        }
    ],
    "sg:phone":"+1 901 751 1147",
    "sg:postcode":"38016",
    "sg:province":"TN",
    "sg:tags":[
        "repair",
        "altering",
        "handyman",
        "improvement",
        "maintenance",
        "contractor",
        "remodeling"
    ],
    "wof:name":"Tad's Mr Fix It Handyman Service",
    "wof:placetype":"venue"
},
  "geometry": {"coordinates":[-89.771185,35.173377],"type":"Point"}
}