{
  "type": "Feature",
  "properties": {
    "iso:country":"US",
    "sg:address":"3621 Roy Messer Hwy",
    "sg:city":"White Pine",
    "sg:classifiers":[
        {
            "category":"Wholesale",
            "subcategory":"Electrical",
            "type":"Manufacturing & Wholesale Goods"
        }
    ],
    "sg:phone":"+1 865 674 2001",
    "sg:postcode":"37890",
    "sg:province":"TN",
    "sg:tags":[
        "electronic"
    ],
    "wof:name":"Atlantic Coast Communications",
    "wof:placetype":"venue"
},
  "geometry": {"coordinates":[-83.33285600000001,36.107532],"type":"Point"}
}