{
  "type": "Feature",
  "properties": {
    "addr:full":"325 S Calderwood St Alcoa TN 37701",
    "addr:housenumber":"325",
    "addr:postcode":"37701",
    "addr:street":"S Calderwood St",
    "iso:country":"US",
    "sg:address":"325 S Calderwood St",
    "sg:city":"Alcoa",
    "sg:classifiers":[
        {
            "category":"Restaurant",
            "type":"Food & Drink"
        }
    ],
    "sg:menulink":"http://www.allmenus.com/tn/maryville-alcoa/200257-long-john-silvers/menu/",
    "sg:phone":"+1 615 984 5630",
    "sg:postcode":"37701",
    "sg:province":"TN",
    "sg:tags":[
        "seafood",
        "american"
    ],
    "wof:name":"Long John Silver's",
    "wof:placetype":"venue"
},
  "geometry": {"coordinates":[-83.97509700000001,35.758998],"type":"Point"}
}