{
  "type": "Feature",
  "properties": {
    "iso:country":"US",
    "sg:address":"6013 Moss Rose Ct",
    "sg:city":"Brentwood",
    "sg:classifiers":[
        {
            "category":"Professional",
            "subcategory":"Business Services",
            "type":"Services"
        }
    ],
    "sg:phone":"+1 615 371 2900",
    "sg:postcode":"37027",
    "sg:province":"TN",
    "sg:tags":[
        "lecture",
        "bureau",
        "seminar"
    ],
    "sg:website":"www.fosterseminars.com",
    "wof:name":"Foster Seminars & Comm LLC",
    "wof:placetype":"venue"
},
  "geometry": {"coordinates":[-86.824326,36.024261],"type":"Point"}
}