{
  "type": "Feature",
  "properties": {
    "iso:country":"US",
    "sg:address":"712 Front St",
    "sg:city":"Humboldt",
    "sg:classifiers":[
        {
            "category":"Restaurant",
            "type":"Food & Drink"
        }
    ],
    "sg:phone":"+1 731 824 3474",
    "sg:postcode":"38343",
    "sg:province":"TN",
    "sg:tags":[
        "delivery",
        "eating"
    ],
    "wof:name":"Perry's Fish House",
    "wof:placetype":"venue"
},
  "geometry": {"coordinates":[-88.92280700000001,35.824338],"type":"Point"}
}