{
  "type": "Feature",
  "properties": {
    "addr:full":"120 S High St Trenton TN 38382",
    "addr:housenumber":"120",
    "addr:postcode":"38382",
    "addr:street":"S High St",
    "iso:country":"US",
    "sg:address":"120 S High St",
    "sg:city":"Trenton",
    "sg:classifiers":[
        {
            "category":"Home & Garden",
            "subcategory":"Hardware",
            "type":"Retail Goods"
        }
    ],
    "sg:phone":"+1 731 855 1921",
    "sg:postcode":"38382",
    "sg:province":"TN",
    "sg:tags":[
        "household"
    ],
    "wof:name":"D C Taylor & Co Inc",
    "wof:placetype":"venue"
},
  "geometry": {"coordinates":[-88.942924,35.98055],"type":"Point"}
}