{
  "type": "Feature",
  "properties": {
    "iso:country":"US",
    "sg:address":"1003 1st Ave",
    "sg:city":"Lawrenceburg",
    "sg:classifiers":[
        {
            "category":"Retail",
            "subcategory":"Repair Shop",
            "type":"Services"
        }
    ],
    "sg:phone":"+1 931 766 6266",
    "sg:postcode":"38464",
    "sg:province":"TN",
    "wof:name":"G & G Auto Repair",
    "wof:placetype":"venue"
},
  "geometry": {"coordinates":[-87.325275,35.250613],"type":"Point"}
}