{
  "type": "Feature",
  "properties": {
    "addr:full":"50 W Broad St Cookeville TN 38501",
    "addr:housenumber":"50",
    "addr:postcode":"38501",
    "addr:street":"W Broad St",
    "iso:country":"US",
    "sg:address":"50 W Broad St",
    "sg:city":"Cookeville",
    "sg:classifiers":[
        {
            "category":"Retail",
            "subcategory":"Laundry & Dry Cleaning",
            "type":"Services"
        }
    ],
    "sg:phone":"+1 931 528 1329",
    "sg:postcode":"38501",
    "sg:province":"TN",
    "wof:name":"Lisas Alterations",
    "wof:placetype":"venue"
},
  "geometry": {"coordinates":[-85.50739900000001,36.163891],"type":"Point"}
}