{
  "type": "Feature",
  "properties": {
    "addr:full":"128 E Jefferson St Brownsville TN 38012",
    "addr:housenumber":"128",
    "addr:postcode":"38012",
    "addr:street":"E Jefferson St",
    "iso:country":"US",
    "sg:address":"128 E Jefferson St",
    "sg:city":"Brownsville",
    "sg:classifiers":[
        {
            "category":"Shopping",
            "subcategory":"Florist",
            "type":"Retail Goods"
        }
    ],
    "sg:phone":"+1 731 772 0234",
    "sg:postcode":"38012",
    "sg:province":"TN",
    "wof:name":"Family Flower Shop",
    "wof:placetype":"venue"
},
  "geometry": {"coordinates":[-89.26087099999999,35.592654],"type":"Point"}
}