{
  "type": "Feature",
  "properties": {
    "iso:country":"US",
    "sg:address":"1090 Ridgecrest Dr",
    "sg:city":"Kingston Springs",
    "sg:classifiers":[
        {
            "category":"Recreation",
            "type":"Entertainment"
        }
    ],
    "sg:phone":"+1 615 952 9675",
    "sg:postcode":"37082",
    "sg:province":"TN",
    "wof:name":"Showcase Stables",
    "wof:placetype":"venue"
},
  "geometry": {"coordinates":[-87.135408,36.088787],"type":"Point"}
}