{
  "type": "Feature",
  "properties": {
    "iso:country":"US",
    "sg:address":"228 Dunavant Dr",
    "sg:city":"Rockford",
    "sg:classifiers":[
        {
            "category":"Real Estate",
            "subcategory":"Real Estate Agent",
            "type":"Services"
        }
    ],
    "sg:phone":"+1 865 573 6431",
    "sg:postcode":"37853",
    "sg:province":"TN",
    "wof:name":"Invesco Properties",
    "wof:placetype":"venue"
},
  "geometry": {"coordinates":[-83.940017,35.860692],"type":"Point"}
}