{
  "type": "Feature",
  "properties": {
    "iso:country":"US",
    "sg:address":"222 E Court St",
    "sg:city":"Dyersburg",
    "sg:classifiers":[
        {
            "category":"Personal",
            "subcategory":"Beauty Salon",
            "type":"Services"
        }
    ],
    "sg:phone":"+1 731 286 2118",
    "sg:postcode":"38024",
    "sg:province":"TN",
    "sg:tags":[
        "shop"
    ],
    "wof:name":"Tangles & Tan",
    "wof:placetype":"venue"
},
  "geometry": {"coordinates":[-89.384484,36.032676],"type":"Point"}
}