{
  "type": "Feature",
  "properties": {
    "addr:full":"1426 Martha Dandridge Cir Dandridge TN 37725",
    "addr:housenumber":"1426",
    "addr:postcode":"37725",
    "addr:street":"Martha Dandridge Cir",
    "iso:country":"US",
    "sg:address":"1426 Martha Dandridge Cir",
    "sg:city":"Dandridge",
    "sg:classifiers":[
        {
            "category":"Freight",
            "type":"Transportation"
        }
    ],
    "sg:phone":"+1 865 397 7723",
    "sg:postcode":"37725",
    "sg:province":"TN",
    "sg:tags":[
        "trucking"
    ],
    "wof:name":"LNC Trucking Svc",
    "wof:placetype":"venue"
},
  "geometry": {"coordinates":[-83.43387,36.002399],"type":"Point"}
}