{
  "type": "Feature",
  "properties": {
    "iso:country":"US",
    "sg:address":"60 E Main St",
    "sg:city":"Auburntown",
    "sg:classifiers":[
        {
            "category":"Manufacturing",
            "subcategory":"Retail Goods",
            "type":"Manufacturing & Wholesale Goods"
        }
    ],
    "sg:phone":"+1 615 464 4130",
    "sg:postcode":"37016",
    "sg:province":"TN",
    "sg:tags":[
        "product",
        "mfg"
    ],
    "wof:name":"Spur Mfg",
    "wof:placetype":"venue"
},
  "geometry": {"coordinates":[-86.09508599999999,35.948305],"type":"Point"}
}