{
  "type": "Feature",
  "properties": {
    "iso:country":"US",
    "sg:address":"83 Lewis St",
    "sg:city":"Nashville",
    "sg:classifiers":[
        {
            "category":"Personal",
            "type":"Services"
        }
    ],
    "sg:phone":"+1 615 254 3283",
    "sg:postcode":"37210",
    "sg:province":"TN",
    "sg:tags":[
        "wedding",
        "chapel"
    ],
    "wof:name":"Harvest Outreach-Jesus Christ",
    "wof:placetype":"venue"
},
  "geometry": {"coordinates":[-86.757987,36.151727],"type":"Point"}
}