{
  "type": "Feature",
  "properties": {
    "addr:full":"791 W Elk Ave Elizabethton TN 37643",
    "addr:housenumber":"791",
    "addr:postcode":"37643",
    "addr:street":"W Elk Ave",
    "iso:country":"US",
    "sg:address":"791 W Elk Ave",
    "sg:city":"Elizabethton",
    "sg:classifiers":[
        {
            "category":"Shopping",
            "subcategory":"Department Store",
            "type":"Retail Goods"
        }
    ],
    "sg:phone":"+1 423 543 8133",
    "sg:postcode":"37643",
    "sg:province":"TN",
    "wof:name":"Wal-Mart",
    "wof:placetype":"venue"
},
  "geometry": {"coordinates":[-82.232912,36.351485],"type":"Point"}
}