{
  "type": "Feature",
  "properties": {
    "addr:full":"4452 Olive Hill Rd Olivehill TN 38475",
    "addr:housenumber":"4452",
    "addr:postcode":"38475",
    "addr:street":"Olive Hill Rd",
    "iso:country":"US",
    "sg:address":"4452 Olive Hill Rd",
    "sg:city":"Olivehill",
    "sg:classifiers":[
        {
            "category":"Manufacturing",
            "subcategory":"Apparel",
            "type":"Manufacturing & Wholesale Goods"
        }
    ],
    "sg:phone":"+1 731 925 3208",
    "sg:postcode":"38475",
    "sg:province":"TN",
    "sg:tags":[
        "textile",
        "product",
        "fabricated",
        "mfg"
    ],
    "wof:name":"Country Maid Products",
    "wof:placetype":"venue"
},
  "geometry": {"coordinates":[-87.992295,35.218132],"type":"Point"}
}