{
  "type": "Feature",
  "properties": {
    "iso:country":"US",
    "sg:address":"3115 Clarksville Pike",
    "sg:city":"Nashville",
    "sg:classifiers":[
        {
            "category":"Restaurant",
            "type":"Food & Drink"
        }
    ],
    "sg:menulink":"http://www.allmenus.com/tn/nashville/191768-sonic/menu/",
    "sg:phone":"+1 615 742 4811",
    "sg:postcode":"37218",
    "sg:province":"TN",
    "sg:tags":[
        "burger",
        "american"
    ],
    "wof:name":"Sonic",
    "wof:placetype":"venue"
},
  "geometry": {"coordinates":[-86.830669,36.192731],"type":"Point"}
}