{
  "type": "Feature",
  "properties": {
    "iso:country":"US",
    "sg:address":"683 Ethridge Red Hill Rd",
    "sg:city":"Ethridge",
    "sg:classifiers":[
        {
            "category":"Farming",
            "subcategory":"Farm",
            "type":"Manufacturing & Wholesale Goods"
        }
    ],
    "sg:phone":"+1 931 829 2839",
    "sg:postcode":"38456",
    "sg:province":"TN",
    "wof:name":"Rose Duaine Shop",
    "wof:placetype":"venue"
},
  "geometry": {"coordinates":[-87.360783,35.314581],"type":"Point"}
}