{
  "type": "Feature",
  "properties": {
    "iso:country":"US",
    "sg:address":"206 College St",
    "sg:city":"Hartsville",
    "sg:classifiers":[
        {
            "category":"Professional",
            "subcategory":"Business Services",
            "type":"Services"
        }
    ],
    "sg:phone":"+1 615 374 9451",
    "sg:postcode":"37074",
    "sg:province":"TN",
    "wof:name":"Southern Home Solutions Inc",
    "wof:placetype":"venue"
},
  "geometry": {"coordinates":[-86.16114,36.392397],"type":"Point"}
}