{
  "type": "Feature",
  "properties": {
    "iso:country":"US",
    "sg:address":"7539 Chowning Rd",
    "sg:city":"Springfield",
    "sg:classifiers":[
        {
            "category":"Building & Trades",
            "subcategory":"Construction",
            "type":"Services"
        }
    ],
    "sg:phone":"+1 615 654 4389",
    "sg:postcode":"37172",
    "sg:province":"TN",
    "sg:tags":[
        "contractor"
    ],
    "wof:name":"Little Guys",
    "wof:placetype":"venue"
},
  "geometry": {"coordinates":[-86.72852399999999,36.500049],"type":"Point"}
}