{
  "type": "Feature",
  "properties": {
    "iso:country":"US",
    "sg:address":"608 Enon Springs Rd W",
    "sg:city":"Smyrna",
    "sg:classifiers":[
        {
            "category":"Shopping",
            "subcategory":"Pharmacy",
            "type":"Retail Goods"
        }
    ],
    "sg:phone":"+1 615 220 5432",
    "sg:postcode":"37167",
    "sg:province":"TN",
    "sg:website":"www.nissanrx.com",
    "wof:name":"Nissan Family Pharmacy",
    "wof:placetype":"venue"
},
  "geometry": {"coordinates":[-86.524736,35.977626],"type":"Point"}
}