{
  "type": "Feature",
  "properties": {
    "iso:country":"US",
    "sg:address":"4839 Lynbar Ave",
    "sg:city":"Memphis",
    "sg:classifiers":[
        {
            "category":"Wholesale",
            "subcategory":"Groceries",
            "type":"Manufacturing & Wholesale Goods"
        }
    ],
    "sg:phone":"+1 901 761 3220",
    "sg:postcode":"38117",
    "sg:province":"TN",
    "sg:tags":[
        "food",
        "broker"
    ],
    "wof:name":"Advantage Sales & Marketing",
    "wof:placetype":"venue"
},
  "geometry": {"coordinates":[-89.900057,35.141274],"type":"Point"}
}