{
  "type": "Feature",
  "properties": {
    "iso:country":"US",
    "sg:address":"4721 Trousdale Dr",
    "sg:city":"Nashville",
    "sg:classifiers":[
        {
            "category":"Professional",
            "subcategory":"Credit Reporting & Collection",
            "type":"Services"
        }
    ],
    "sg:phone":"+1 615 831 7068",
    "sg:postcode":"37220",
    "sg:province":"TN",
    "sg:tags":[
        "se"
    ],
    "wof:name":"Account Mgt Svcs of Tenn",
    "wof:placetype":"venue"
},
  "geometry": {"coordinates":[-86.75884000000001,36.078137],"type":"Point"}
}