{
  "type": "Feature",
  "properties": {
    "iso:country":"US",
    "sg:address":"925 40th Ave N",
    "sg:city":"Nashville",
    "sg:classifiers":[
        {
            "category":"Food & Beverages",
            "subcategory":"Groceries & Convenience Stores",
            "type":"Retail Goods"
        }
    ],
    "sg:phone":"+1 615 327 0384",
    "sg:postcode":"37209",
    "sg:province":"TN",
    "sg:tags":[
        "grocer"
    ],
    "wof:name":"40th Avenue Market Inc",
    "wof:placetype":"venue"
},
  "geometry": {"coordinates":[-86.836365,36.161402],"type":"Point"}
}