{
  "type": "Feature",
  "properties": {
    "iso:country":"US",
    "sg:address":"538 Myatt Dr",
    "sg:city":"Madison",
    "sg:classifiers":[
        {
            "category":"Manufacturing",
            "subcategory":"Textiles",
            "type":"Manufacturing & Wholesale Goods"
        }
    ],
    "sg:phone":"+1 615 847 7663",
    "sg:postcode":"37115",
    "sg:province":"TN",
    "sg:tags":[
        "fabric",
        "mfg"
    ],
    "sg:website":"www.precisionfabrics.com",
    "wof:name":"Precision Fabrics Group",
    "wof:placetype":"venue"
},
  "geometry": {"coordinates":[-86.692801,36.285559],"type":"Point"}
}