{
  "type": "Feature",
  "properties": {
    "addr:full":"50 Humphreys Center Memphis TN 38120",
    "addr:housenumber":"50",
    "addr:postcode":"38120",
    "addr:street":"Humphreys Center",
    "iso:country":"US",
    "sg:address":"50 Humphreys Center",
    "sg:city":"Memphis",
    "sg:classifiers":[
        {
            "category":"Shopping",
            "subcategory":"Clothing, Apparel, & Fashions",
            "type":"Retail Goods"
        }
    ],
    "sg:phone":"+1 901 747 0110",
    "sg:postcode":"38120",
    "sg:province":"TN",
    "sg:tags":[
        "uniform"
    ],
    "wof:name":"Landau Uniforms",
    "wof:placetype":"venue"
},
  "geometry": {"coordinates":[-89.857249,35.129372],"type":"Point"}
}