{
  "type": "Feature",
  "properties": {
    "iso:country":"US",
    "sg:address":"931 Ashland Ter",
    "sg:city":"Chattanooga",
    "sg:classifiers":[
        {
            "category":"Freight",
            "type":"Transportation"
        }
    ],
    "sg:phone":"+1 423 870 0551",
    "sg:postcode":"37415",
    "sg:province":"TN",
    "sg:tags":[
        "trucking"
    ],
    "wof:name":"Keon Transport LLC",
    "wof:placetype":"venue"
},
  "geometry": {"coordinates":[-85.268045,35.11724],"type":"Point"}
}