{
  "type": "Feature",
  "properties": {
    "addr:full":"1401 Market St Chattanooga TN 37402",
    "addr:housenumber":"1401",
    "addr:postcode":"37402",
    "addr:street":"Market St",
    "iso:country":"US",
    "sg:address":"1401 Market St",
    "sg:city":"Chattanooga",
    "sg:classifiers":[
        {
            "category":"Real Estate",
            "subcategory":"Developer",
            "type":"Services"
        }
    ],
    "sg:phone":"+1 423 266 3300",
    "sg:postcode":"37402",
    "sg:province":"TN",
    "wof:name":"Pennrose Properties",
    "wof:placetype":"venue"
},
  "geometry": {"coordinates":[-85.307423,35.037834],"type":"Point"}
}