{
  "type": "Feature",
  "properties": {
    "addr:full":"2515 Cornell Pl Murfreesboro TN 37129",
    "addr:housenumber":"2515",
    "addr:postcode":"37129",
    "addr:street":"Cornell Pl",
    "iso:country":"US",
    "sg:address":"2515 Cornell Pl",
    "sg:city":"Murfreesboro",
    "sg:classifiers":[
        {
            "category":"Professional",
            "subcategory":"Business Services",
            "type":"Services"
        }
    ],
    "sg:phone":"+1 615 896 8650",
    "sg:postcode":"37129",
    "sg:province":"TN",
    "wof:name":"Rick Lalance Enterprises",
    "wof:placetype":"venue"
},
  "geometry": {"coordinates":[-86.411773,35.89466],"type":"Point"}
}