{
  "type": "Feature",
  "properties": {
    "iso:country":"US",
    "sg:address":"1360 Barren Valley Rd",
    "sg:city":"Chuckey",
    "sg:phone":"+1 423 257 3977",
    "sg:postcode":"37641",
    "sg:province":"TN",
    "sg:tags":[
        "farm",
        "field",
        "crop"
    ],
    "wof:name":"Gary Brumit Farm",
    "wof:placetype":"venue"
},
  "geometry": {"coordinates":[-82.674381,36.173507],"type":"Point"}
}