{
  "type": "Feature",
  "properties": {
    "addr:full":"1751 US Hwy 25E Tazewell TN 37879",
    "addr:housenumber":"1751",
    "addr:postcode":"37879",
    "addr:street":"Us Hwy 25E",
    "iso:country":"US",
    "sg:address":"1751 US Hwy 25E",
    "sg:city":"Tazewell",
    "sg:classifiers":[
        {
            "category":"Wholesale",
            "subcategory":"Non-durable Goods",
            "type":"Manufacturing & Wholesale Goods"
        }
    ],
    "sg:phone":"+1 423 626 1422",
    "sg:postcode":"37879",
    "sg:province":"TN",
    "wof:name":"Noah's Wholesale",
    "wof:placetype":"venue"
},
  "geometry": {"coordinates":[-83.5686,36.453348],"type":"Point"}
}