{
  "type": "Feature",
  "properties": {
    "addr:full":"4510 Millbranch Rd Memphis TN 38116",
    "addr:housenumber":"4510",
    "addr:postcode":"38116",
    "addr:street":"Millbranch Rd",
    "iso:country":"US",
    "sg:address":"4510 Millbranch Rd",
    "sg:city":"Memphis",
    "sg:classifiers":[
        {
            "category":"Restaurant",
            "type":"Food & Drink"
        }
    ],
    "sg:phone":"+1 901 346 1234",
    "sg:postcode":"38116",
    "sg:province":"TN",
    "sg:tags":[
        "pizza"
    ],
    "wof:name":"Havens Pizza & Wings",
    "wof:placetype":"venue"
},
  "geometry": {"coordinates":[-90.00753,35.025811],"type":"Point"}
}