{
  "type": "Feature",
  "properties": {
    "iso:country":"US",
    "sg:address":"2529 Lafayette Cir",
    "sg:city":"Kingsport",
    "sg:classifiers":[
        {
            "category":"Building & Trades",
            "subcategory":"Equipment Rental",
            "type":"Services"
        }
    ],
    "sg:phone":"+1 423 247 2599",
    "sg:postcode":"37664",
    "sg:province":"TN",
    "sg:tags":[
        "crane"
    ],
    "wof:name":"Lift A Lot",
    "wof:placetype":"venue"
},
  "geometry": {"coordinates":[-82.520633,36.522501],"type":"Point"}
}