{
  "type": "Feature",
  "properties": {
    "iso:country":"US",
    "sg:address":"725 W Shiloh Rd",
    "sg:city":"Corinth",
    "sg:classifiers":[
        {
            "category":"Professional",
            "subcategory":"Accounting & Tax Preparation",
            "type":"Services"
        }
    ],
    "sg:phone":"+1 662 287 5265",
    "sg:postcode":"38834",
    "sg:province":"TN",
    "sg:tags":[
        "accountant"
    ],
    "wof:name":"Dobbins & Mitchell",
    "wof:placetype":"venue"
},
  "geometry": {"coordinates":[-88.53016700000001,34.945619],"type":"Point"}
}