{
  "type": "Feature",
  "properties": {
    "iso:country":"US",
    "sg:address":"3311 Kimball Ave",
    "sg:city":"Memphis",
    "sg:classifiers":[
        {
            "category":"Social Services",
            "subcategory":"Child Care",
            "type":"Services"
        }
    ],
    "sg:phone":"+1 901 743 7335",
    "sg:postcode":"38111",
    "sg:province":"TN",
    "sg:tags":[
        "kindergarten",
        "academic",
        "school"
    ],
    "wof:name":"Southern Ave Charter School",
    "wof:placetype":"venue"
},
  "geometry": {"coordinates":[-89.952384,35.094623],"type":"Point"}
}