{
  "type": "Feature",
  "properties": {
    "addr:full":"409 Graham St Newport TN 37821",
    "addr:housenumber":"409",
    "addr:postcode":"37821",
    "addr:street":"Graham St",
    "iso:country":"US",
    "sg:address":"409 Graham St",
    "sg:city":"Newport",
    "sg:classifiers":[
        {
            "category":"Building & Trades",
            "subcategory":"Construction",
            "type":"Services"
        }
    ],
    "sg:phone":"+1 423 623 5458",
    "sg:postcode":"37821",
    "sg:province":"TN",
    "sg:tags":[
        "contractor",
        "sheet",
        "metalwork",
        "mfg"
    ],
    "wof:name":"Weatherguard",
    "wof:placetype":"venue"
},
  "geometry": {"coordinates":[-83.204846,35.967559],"type":"Point"}
}