{
  "type": "Feature",
  "properties": {
    "addr:full":"3440 Macon Rd Memphis TN 38122",
    "addr:housenumber":"3440",
    "addr:postcode":"38122",
    "addr:street":"Macon Rd",
    "iso:country":"US",
    "sg:address":"3440 Macon Rd",
    "sg:city":"Memphis",
    "sg:classifiers":[
        {
            "category":"Professional",
            "subcategory":"Engineering",
            "type":"Services"
        }
    ],
    "sg:phone":"+1 901 458 8754",
    "sg:postcode":"38122",
    "sg:province":"TN",
    "sg:tags":[
        "consultant"
    ],
    "wof:name":"J P Thomas and Associates Inc",
    "wof:placetype":"venue"
},
  "geometry": {"coordinates":[-89.94628400000001,35.162327],"type":"Point"}
}