{
  "type": "Feature",
  "properties": {
    "iso:country":"US",
    "sg:address":"56 Thomas Rd",
    "sg:city":"Fayetteville",
    "sg:classifiers":[
        {
            "category":"Farming",
            "subcategory":"Livestock Farm",
            "type":"Manufacturing & Wholesale Goods"
        }
    ],
    "sg:phone":"+1 931 433 2644",
    "sg:postcode":"37334",
    "sg:province":"TN",
    "sg:tags":[
        "feedlot",
        "hog",
        "or",
        "beef",
        "cattle"
    ],
    "wof:name":"Clayton Thomas",
    "wof:placetype":"venue"
},
  "geometry": {"coordinates":[-86.527764,35.297106],"type":"Point"}
}