{
  "type": "Feature",
  "properties": {
    "iso:country":"US",
    "sg:address":"423 Brown St",
    "sg:city":"Celina",
    "sg:classifiers":[
        {
            "category":"Retail",
            "subcategory":"Funeral Services",
            "type":"Services"
        }
    ],
    "sg:phone":"+1 931 243 5050",
    "sg:postcode":"38551",
    "sg:province":"TN",
    "sg:tags":[
        "director"
    ],
    "wof:name":"Hall Funeral Home LLC",
    "wof:placetype":"venue"
},
  "geometry": {"coordinates":[-85.505295,36.548786],"type":"Point"}
}