{
  "type": "Feature",
  "properties": {
    "iso:country":"US",
    "sg:address":"4627 Corinth Rd",
    "sg:city":"Blaine",
    "sg:classifiers":[
        {
            "category":"Retail",
            "subcategory":"Veterinary Services",
            "type":"Services"
        }
    ],
    "sg:phone":"+1 865 828 5275",
    "sg:postcode":"37774",
    "sg:province":"TN",
    "wof:name":"Southern Dairy Consulting",
    "wof:placetype":"venue"
},
  "geometry": {"coordinates":[-84.331079,35.688902],"type":"Point"}
}