{
  "type": "Feature",
  "properties": {
    "iso:country":"US",
    "sg:address":"30 Lennon Cove",
    "sg:city":"Jackson",
    "sg:classifiers":[
        {
            "category":"Organizations",
            "subcategory":"Religious Organization",
            "type":"Services"
        }
    ],
    "sg:phone":"+1 731 660 4913",
    "sg:postcode":"38305",
    "sg:province":"TN",
    "wof:name":"Community Temple of Deliv",
    "wof:placetype":"venue"
},
  "geometry": {"coordinates":[-88.837476,35.666397],"type":"Point"}
}