{
  "type": "Feature",
  "properties": {
    "addr:full":"6572 Fairview Rd Hixson TN 37343",
    "addr:housenumber":"6572",
    "addr:postcode":"37343",
    "addr:street":"Fairview Rd",
    "iso:country":"US",
    "sg:address":"6572 Fairview Rd",
    "sg:city":"Hixson",
    "sg:classifiers":[
        {
            "category":"Building & Trades",
            "subcategory":"Construction",
            "type":"Services"
        }
    ],
    "sg:phone":"+1 423 847 9456",
    "sg:postcode":"37343",
    "sg:province":"TN",
    "sg:tags":[
        "contractor"
    ],
    "wof:name":"Ivey League Drywall",
    "wof:placetype":"venue"
},
  "geometry": {"coordinates":[-85.182107,35.163918],"type":"Point"}
}