{
  "type": "Feature",
  "properties": {
    "addr:full":"708 Smithville Hwy Mc Minnville TN 37110",
    "addr:housenumber":"708",
    "addr:postcode":"37110",
    "addr:street":"Smithville Hwy Mc Minnville",
    "iso:country":"US",
    "sg:address":"708 Smithville Hwy",
    "sg:city":"Mc Minnville",
    "sg:classifiers":[
        {
            "category":"Restaurant",
            "type":"Food & Drink"
        },
        {
            "category":"Ice Cream",
            "type":"Food & Drink"
        }
    ],
    "sg:menulink":"http://www.allmenus.com/tn/mcminnville/192819-dairy-queen/menu/",
    "sg:phone":"+1 931 473 5154",
    "sg:postcode":"37110",
    "sg:province":"TN",
    "sg:tags":[
        "burger",
        "american",
        "ice",
        "cream"
    ],
    "wof:name":"Dairy Queen",
    "wof:placetype":"venue"
},
  "geometry": {"coordinates":[-85.77875299999999,35.694223],"type":"Point"}
}