{
  "type": "Feature",
  "properties": {
    "iso:country":"US",
    "sg:address":"2900 Kingsport Hwy",
    "sg:city":"Greeneville",
    "sg:classifiers":[
        {
            "category":"Shopping",
            "type":"Retail Goods"
        }
    ],
    "sg:phone":"+1 423 638 1020",
    "sg:postcode":"37745",
    "sg:province":"TN",
    "sg:tags":[
        "dry",
        "ice"
    ],
    "wof:name":"East Tennessee Dry Ice Inc",
    "wof:placetype":"venue"
},
  "geometry": {"coordinates":[-82.800832,36.197041],"type":"Point"}
}