{
  "type": "Feature",
  "properties": {
    "iso:country":"US",
    "sg:address":"520 Northgate Mall",
    "sg:city":"Chattanooga",
    "sg:classifiers":[
        {
            "category":"Education",
            "subcategory":"Library",
            "type":"Public Place"
        }
    ],
    "sg:phone":"+1 423 870 0636",
    "sg:postcode":"37415",
    "sg:province":"TN",
    "wof:name":"North Gate Branch Library",
    "wof:placetype":"venue"
},
  "geometry": {"coordinates":[-85.239754,35.127004],"type":"Point"}
}