{
  "type": "Feature",
  "properties": {
    "iso:country":"US",
    "sg:address":"1320 Brick Church Pike",
    "sg:city":"Nashville",
    "sg:classifiers":[
        {
            "category":"Government",
            "subcategory":"Fire Station",
            "type":"Public Place"
        }
    ],
    "sg:phone":"+1 615 226 0683",
    "sg:postcode":"37207",
    "sg:province":"TN",
    "sg:tags":[
        "department"
    ],
    "sg:website":"www.wvol1470.com",
    "wof:name":"WVOL",
    "wof:placetype":"venue"
},
  "geometry": {"coordinates":[-86.77719999999999,36.199661],"type":"Point"}
}