{
  "type": "Feature",
  "properties": {
    "iso:country":"US",
    "sg:address":"202 Chilton St",
    "sg:city":"Nashville",
    "sg:classifiers":[
        {
            "category":"Organizations",
            "subcategory":"Religious Organization",
            "type":"Services"
        }
    ],
    "sg:phone":"+1 615 833 7757",
    "sg:postcode":"37211",
    "sg:province":"TN",
    "sg:tags":[
        "church"
    ],
    "wof:name":"True House Of Praise Church",
    "wof:placetype":"venue"
},
  "geometry": {"coordinates":[-86.739165,36.10063],"type":"Point"}
}