{
  "type": "Feature",
  "properties": {
    "iso:country":"US",
    "sg:address":"5621 Franklin Pike Cir",
    "sg:city":"Brentwood",
    "sg:classifiers":[
        {
            "category":"Autos & Motor Vehicles",
            "subcategory":"Fuel & Gas Station",
            "type":"Retail Goods"
        }
    ],
    "sg:phone":"+1 615 661 4102",
    "sg:postcode":"37027",
    "sg:province":"TN",
    "sg:tags":[
        "station",
        "gasoline"
    ],
    "wof:name":"Shell",
    "wof:placetype":"venue"
},
  "geometry": {"coordinates":[-86.784918,36.039398],"type":"Point"}
}