{
  "type": "Feature",
  "properties": {
    "iso:country":"US",
    "sg:address":"511 N 2nd St",
    "sg:city":"Clarksville",
    "sg:classifiers":[
        {
            "category":"Building & Trades",
            "subcategory":"Pest Control",
            "type":"Services"
        }
    ],
    "sg:phone":"+1 931 645 4235",
    "sg:postcode":"37040",
    "sg:province":"TN",
    "sg:website":"http://www.realpagessites.com/catosexterminating",
    "wof:name":"Cato's Exterminating Company",
    "wof:placetype":"venue"
},
  "geometry": {"coordinates":[-87.360849,36.534035],"type":"Point"}
}