{
  "type": "Feature",
  "properties": {
    "iso:country":"US",
    "sg:address":"4851 Nolensville Pike",
    "sg:city":"Nashville",
    "sg:classifiers":[
        {
            "category":"Autos & Motor Vehicles",
            "subcategory":"Auto Supplies",
            "type":"Retail Goods"
        }
    ],
    "sg:phone":"+1 615 315 0010",
    "sg:postcode":"37211",
    "sg:province":"TN",
    "sg:tags":[
        "automobile",
        "part",
        "batteries-storage"
    ],
    "sg:website":"http://www.advanceautoparts.com",
    "wof:name":"Advance Auto Parts",
    "wof:placetype":"venue"
},
  "geometry": {"coordinates":[-86.71728,36.064829],"type":"Point"}
}