{
  "type": "Feature",
  "properties": {
    "addr:full":"407 S Lowry St Smyrna TN 37167",
    "addr:housenumber":"407",
    "addr:postcode":"37167",
    "addr:street":"S Lowry St",
    "iso:country":"US",
    "sg:address":"407 S Lowry St",
    "sg:city":"Smyrna",
    "sg:classifiers":[
        {
            "category":"Food & Beverages",
            "subcategory":"Groceries & Convenience Stores",
            "type":"Retail Goods"
        }
    ],
    "sg:phone":"+1 615 223 9336",
    "sg:postcode":"37167",
    "sg:province":"TN",
    "wof:name":"Aldi 25 Inc",
    "wof:placetype":"venue"
},
  "geometry": {"coordinates":[-86.495014,35.955958],"type":"Point"}
}