{
  "type": "Feature",
  "properties": {
    "iso:country":"US",
    "sg:address":"275 Stewarts Ferry Pike",
    "sg:city":"Nashville",
    "sg:classifiers":[
        {
            "category":"Government",
            "subcategory":"Police Station",
            "type":"Public Place"
        }
    ],
    "sg:phone":"+1 615 232 2901",
    "sg:postcode":"37214",
    "sg:province":"TN",
    "sg:tags":[
        "state"
    ],
    "sg:website":"www.state.tn.us",
    "wof:name":"Highway Patrol",
    "wof:placetype":"venue"
},
  "geometry": {"coordinates":[-86.64507399999999,36.160997],"type":"Point"}
}