{
  "type": "Feature",
  "properties": {
    "iso:country":"US",
    "sg:address":"900 Old Jonesboro Rd",
    "sg:city":"Chuckey",
    "sg:classifiers":[
        {
            "category":"Organizations",
            "subcategory":"Religious Organization",
            "type":"Services"
        }
    ],
    "sg:phone":"+1 423 638 5240",
    "sg:postcode":"37641",
    "sg:province":"TN",
    "sg:tags":[
        "church"
    ],
    "wof:name":"Horse Creek Church Of God",
    "wof:placetype":"venue"
},
  "geometry": {"coordinates":[-82.706587,36.160241],"type":"Point"}
}