{
  "type": "Feature",
  "properties": {
    "iso:country":"US",
    "sg:address":"700 Atlantic Ave NE",
    "sg:city":"Knoxville",
    "sg:classifiers":[
        {
            "category":"Personal",
            "subcategory":"Tanning Parlor",
            "type":"Services"
        }
    ],
    "sg:phone":"+1 865 688 9176",
    "sg:postcode":"37917",
    "sg:province":"TN",
    "sg:tags":[
        "salon"
    ],
    "wof:name":"Rachel's Hair Styling/Tanning",
    "wof:placetype":"venue"
},
  "geometry": {"coordinates":[-83.93465500000001,35.998124],"type":"Point"}
}