{
  "type": "Feature",
  "properties": {
    "addr:full":"202 Walton Ferry Rd Hendersonville TN 37075",
    "addr:housenumber":"202",
    "addr:postcode":"37075",
    "addr:street":"Walton Ferry Rd",
    "iso:country":"US",
    "sg:address":"202 Walton Ferry Rd",
    "sg:city":"Hendersonville",
    "sg:classifiers":[
        {
            "category":"Health Services",
            "subcategory":"Nursing And Care Facility",
            "type":"Services"
        }
    ],
    "sg:phone":"+1 615 822 7520",
    "sg:postcode":"37075",
    "sg:province":"TN",
    "sg:tags":[
        "skilled"
    ],
    "wof:name":"Sunpointe Senior Living",
    "wof:placetype":"venue"
},
  "geometry": {"coordinates":[-86.62066,36.299593],"type":"Point"}
}