{
  "type": "Feature",
  "properties": {
    "iso:country":"US",
    "sg:address":"6321 Charlotte Pike",
    "sg:city":"Nashville",
    "sg:classifiers":[
        {
            "category":"Restaurant",
            "type":"Food & Drink"
        }
    ],
    "sg:phone":"+1 615 354 5600",
    "sg:postcode":"37209",
    "sg:province":"TN",
    "wof:name":"El Jalisiense Taqueria",
    "wof:placetype":"venue"
},
  "geometry": {"coordinates":[-86.872721,36.144437],"type":"Point"}
}