{
  "type": "Feature",
  "properties": {
    "iso:country":"US",
    "sg:address":"869 Stirrup Dr",
    "sg:city":"Nashville",
    "sg:classifiers":[
        {
            "category":"Professional",
            "subcategory":"Management & Consulting",
            "type":"Services"
        }
    ],
    "sg:phone":"+1 615 646 5035",
    "sg:postcode":"37221",
    "sg:province":"TN",
    "wof:name":"Linda Slobey Consultants",
    "wof:placetype":"venue"
},
  "geometry": {"coordinates":[-86.93163300000001,36.077632],"type":"Point"}
}