{
  "type": "Feature",
  "properties": {
    "addr:full":"159 Omni Dr Mc Minnville TN 37110",
    "addr:housenumber":"159",
    "addr:postcode":"37110",
    "addr:street":"Omni Dr",
    "iso:country":"US",
    "sg:address":"159 Omni Dr",
    "sg:city":"Mc Minnville",
    "sg:classifiers":[
        {
            "category":"Health Services",
            "subcategory":"Doctor",
            "type":"Services"
        }
    ],
    "sg:phone":"+1 931 815 3420",
    "sg:postcode":"37110",
    "sg:province":"TN",
    "sg:tags":[
        "physician",
        "surgeon"
    ],
    "wof:name":"Heart Group",
    "wof:placetype":"venue"
},
  "geometry": {"coordinates":[-85.74548900000001,35.69773],"type":"Point"}
}