{
  "type": "Feature",
  "properties": {
    "iso:country":"US",
    "sg:address":"208 W Main St",
    "sg:city":"Union City",
    "sg:classifiers":[
        {
            "category":"Health Services",
            "subcategory":"Chiropractor",
            "type":"Services"
        }
    ],
    "sg:phone":"+1 731 885 1144",
    "sg:postcode":"38261",
    "sg:province":"TN",
    "wof:name":"House Chiropractic Ctr",
    "wof:placetype":"venue"
},
  "geometry": {"coordinates":[-89.05895,36.425764],"type":"Point"}
}