{
  "type": "Feature",
  "properties": {
    "iso:country":"US",
    "sg:address":"347 E Main St",
    "sg:city":"Adamsville",
    "sg:classifiers":[
        {
            "category":"Shopping",
            "subcategory":"Pharmacy",
            "type":"Retail Goods"
        }
    ],
    "sg:phone":"+1 731 632 0995",
    "sg:postcode":"38310",
    "sg:province":"TN",
    "wof:name":"Todd's Discount Drugs",
    "wof:placetype":"venue"
},
  "geometry": {"coordinates":[-88.385428,35.235416],"type":"Point"}
}