{
  "type": "Feature",
  "properties": {
    "iso:country":"US",
    "sg:address":"6 Cadillac Dr",
    "sg:city":"Brentwood",
    "sg:classifiers":[
        {
            "category":"Personal",
            "type":"Services"
        }
    ],
    "sg:phone":"+1 615 370 5687",
    "sg:postcode":"37027",
    "sg:province":"TN",
    "sg:tags":[
        "program",
        "physical",
        "exercise",
        "fitness"
    ],
    "wof:name":"Absolute Pilates",
    "wof:placetype":"venue"
},
  "geometry": {"coordinates":[-86.79506499999999,36.036059],"type":"Point"}
}