{
  "type": "Feature",
  "properties": {
    "iso:country":"US",
    "sg:address":"2588 Music Valley Dr",
    "sg:city":"Nashville",
    "sg:classifiers":[
        {
            "category":"Autos & Motor Vehicles",
            "subcategory":"Recreational Vehicle Sales",
            "type":"Retail Goods"
        }
    ],
    "sg:phone":"+1 615 871 4278",
    "sg:postcode":"37214",
    "sg:province":"TN",
    "sg:website":"www.musiccityrv.com",
    "wof:name":"Music City Rv LLC",
    "wof:placetype":"venue"
},
  "geometry": {"coordinates":[-86.701891,36.232035],"type":"Point"}
}