{
  "type": "Feature",
  "properties": {
    "iso:country":"US",
    "sg:address":"287 Faith Cir",
    "sg:city":"Johnson City",
    "sg:classifiers":[
        {
            "category":"Autos & Motor Vehicles",
            "subcategory":"Automobile Sales",
            "type":"Retail Goods"
        }
    ],
    "sg:phone":"+1 423 928 6335",
    "sg:postcode":"37604",
    "sg:province":"TN",
    "sg:tags":[
        "car",
        "dealer"
    ],
    "wof:name":"Cars Wholesale",
    "wof:placetype":"venue"
},
  "geometry": {"coordinates":[-82.409098,36.311573],"type":"Point"}
}