{
  "type": "Feature",
  "properties": {
    "iso:country":"US",
    "sg:address":"229 S Danny Thomas Blvd",
    "sg:city":"Memphis",
    "sg:classifiers":[
        {
            "category":"Place Of Worship",
            "type":"Public Place"
        }
    ],
    "sg:phone":"+1 901 527 9202",
    "sg:postcode":"38126",
    "sg:province":"TN",
    "sg:tags":[
        "church"
    ],
    "wof:name":"Patterson, J O Bishop",
    "wof:placetype":"venue"
},
  "geometry": {"coordinates":[-90.04620799999999,35.137379],"type":"Point"}
}