{
  "type": "Feature",
  "properties": {
    "iso:country":"US",
    "sg:address":"2301 Andersonville Hwy",
    "sg:city":"Clinton",
    "sg:classifiers":[
        {
            "category":"Restaurant",
            "type":"Food & Drink"
        }
    ],
    "sg:menulink":"http://www.allmenus.com/tn/norris/203578-mcdonalds/menu/",
    "sg:postcode":"37716",
    "sg:province":"TN",
    "sg:tags":[
        "burger",
        "american"
    ],
    "wof:name":"McDonald's",
    "wof:placetype":"venue"
},
  "geometry": {"coordinates":[-84.08049699999999,36.168142],"type":"Point"}
}