{
  "type": "Feature",
  "properties": {
    "iso:country":"US",
    "sg:address":"3035 Darrow St",
    "sg:city":"Memphis",
    "sg:classifiers":[
        {
            "category":"Banks & Credit Unions",
            "subcategory":"Bank",
            "type":"Services"
        }
    ],
    "sg:phone":"+1 901 346 5660",
    "sg:postcode":"38118",
    "sg:province":"TN",
    "sg:tags":[
        "banker",
        "mortgage"
    ],
    "wof:name":"Allied Mortgage Capital",
    "wof:placetype":"venue"
},
  "geometry": {"coordinates":[-89.887833,35.066119],"type":"Point"}
}