{
  "type": "Feature",
  "properties": {
    "iso:country":"US",
    "sg:address":"726 Lafayette Rd",
    "sg:city":"Red Boiling Spgs",
    "sg:classifiers":[
        {
            "category":"Personal",
            "subcategory":"Beauty Salon",
            "type":"Services"
        }
    ],
    "sg:phone":"+1 615 699 2117",
    "sg:postcode":"37150",
    "sg:province":"TN",
    "wof:name":"Faye's Fashion & Faces",
    "wof:placetype":"venue"
},
  "geometry": {"coordinates":[-85.863084,36.520406],"type":"Point"}
}