{
  "type": "Feature",
  "properties": {
    "iso:country":"US",
    "sg:address":"300 W Powell Rd",
    "sg:city":"Collierville",
    "sg:classifiers":[
        {
            "category":"Organizations",
            "subcategory":"Religious Organization",
            "type":"Services"
        }
    ],
    "sg:phone":"+1 901 853 9337",
    "sg:postcode":"38017",
    "sg:province":"TN",
    "wof:name":"Greenhills Baptist Church",
    "wof:placetype":"venue"
},
  "geometry": {"coordinates":[-89.67345,35.061102],"type":"Point"}
}