{
  "type": "Feature",
  "properties": {
    "iso:country":"US",
    "sg:address":"118 N Locust Ave",
    "sg:city":"Lawrenceburg",
    "sg:classifiers":[
        {
            "category":"Organizations",
            "subcategory":"Community Association",
            "type":"Services"
        }
    ],
    "sg:phone":"+1 931 762 2501",
    "sg:postcode":"38464",
    "sg:province":"TN",
    "sg:tags":[
        "fraternal"
    ],
    "wof:name":"Mimosa Lodge",
    "wof:placetype":"venue"
},
  "geometry": {"coordinates":[-87.330144,35.241286],"type":"Point"}
}