{
  "type": "Feature",
  "properties": {
    "addr:full":"1007 Maxwell Ave Nashville TN 37206",
    "addr:housenumber":"1007",
    "addr:postcode":"37206",
    "addr:street":"Maxwell Ave",
    "iso:country":"US",
    "sg:address":"1007 Maxwell Ave",
    "sg:city":"Nashville",
    "sg:classifiers":[
        {
            "category":"Organizations",
            "subcategory":"Community Association",
            "type":"Services"
        }
    ],
    "sg:phone":"+1 615 226 9516",
    "sg:postcode":"37206",
    "sg:province":"TN",
    "wof:name":"Maxwell Area Neighborhood Assn",
    "wof:placetype":"venue"
},
  "geometry": {"coordinates":[-86.751918,36.182766],"type":"Point"}
}