{
  "type": "Feature",
  "properties": {
    "iso:country":"US",
    "sg:address":"315 S Cannon Blvd",
    "sg:city":"Shelbyville",
    "sg:classifiers":[
        {
            "category":"Home & Garden",
            "subcategory":"Furniture",
            "type":"Retail Goods"
        }
    ],
    "sg:phone":"+1 931 684 2453",
    "sg:postcode":"37160",
    "sg:province":"TN",
    "sg:tags":[
        "household",
        "appliance"
    ],
    "wof:name":"Bedford Home Furnishings",
    "wof:placetype":"venue"
},
  "geometry": {"coordinates":[-86.464378,35.480047],"type":"Point"}
}