{
  "type": "Feature",
  "properties": {
    "iso:country":"US",
    "sg:address":"213 1st Ave NW",
    "sg:city":"Winchester",
    "sg:classifiers":[
        {
            "category":"Organizations",
            "subcategory":"Religious Organization",
            "type":"Services"
        }
    ],
    "sg:phone":"+1 931 967 0898",
    "sg:postcode":"37398",
    "sg:province":"TN",
    "sg:tags":[
        "church"
    ],
    "wof:name":"Trinity Episcopal Church",
    "wof:placetype":"venue"
},
  "geometry": {"coordinates":[-86.113309,35.185611],"type":"Point"}
}