{
  "type": "Feature",
  "properties": {
    "addr:full":"525 Two Mile Pkwy Goodlettsville TN 37072",
    "addr:housenumber":"525",
    "addr:postcode":"37072",
    "addr:street":"Two Mile Pkwy",
    "iso:country":"US",
    "sg:address":"525 Two Mile Pkwy",
    "sg:city":"Goodlettsville",
    "sg:classifiers":[
        {
            "category":"Health Services",
            "subcategory":"Optometrist",
            "type":"Services"
        }
    ],
    "sg:phone":"+1 615 859 1928",
    "sg:postcode":"37072",
    "sg:province":"TN",
    "sg:tags":[
        "optical",
        "good"
    ],
    "wof:name":"Ezell T H Od",
    "wof:placetype":"venue"
},
  "geometry": {"coordinates":[-86.70420300000001,36.308189],"type":"Point"}
}