{
  "type": "Feature",
  "properties": {
    "iso:country":"US",
    "sg:address":"509 S Highland Park Ave",
    "sg:city":"Chattanooga",
    "sg:classifiers":[
        {
            "category":"Health Services",
            "subcategory":"Hospital",
            "type":"Services"
        }
    ],
    "sg:phone":"+1 423 756 1295",
    "sg:postcode":"37404",
    "sg:province":"TN",
    "sg:tags":[
        "mental"
    ],
    "wof:name":"Fortwood Center",
    "wof:placetype":"venue"
},
  "geometry": {"coordinates":[-85.28116300000001,35.036235],"type":"Point"}
}