{
  "type": "Feature",
  "properties": {
    "iso:country":"US",
    "sg:address":"229 S Mendenhall Rd",
    "sg:city":"Memphis",
    "sg:classifiers":[
        {
            "category":"Building & Trades",
            "subcategory":"Plumbing",
            "type":"Services"
        }
    ],
    "sg:phone":"+1 901 680 7741",
    "sg:postcode":"38117",
    "sg:province":"TN",
    "sg:tags":[
        "contractor"
    ],
    "wof:name":"Thorntons Air Condition Htg",
    "wof:placetype":"venue"
},
  "geometry": {"coordinates":[-89.894915,35.123128],"type":"Point"}
}