{
  "type": "Feature",
  "properties": {
    "addr:full":"405 Tyson Ave Paris TN 38242",
    "addr:housenumber":"405",
    "addr:postcode":"38242",
    "addr:street":"Tyson Ave",
    "iso:country":"US",
    "sg:address":"405 Tyson Ave",
    "sg:city":"Paris",
    "sg:classifiers":[
        {
            "category":"Health Services",
            "subcategory":"Doctor",
            "type":"Services"
        }
    ],
    "sg:phone":"+1 731 644 3339",
    "sg:postcode":"38242",
    "sg:province":"TN",
    "sg:tags":[
        "clinic"
    ],
    "wof:name":"Wound Care Clinic",
    "wof:placetype":"venue"
},
  "geometry": {"coordinates":[-88.314369,36.293641],"type":"Point"}
}