{
  "type": "Feature",
  "properties": {
    "addr:full":"911 W Baxter Ave Knoxville TN 37921",
    "addr:housenumber":"911",
    "addr:postcode":"37921",
    "addr:street":"W Baxter Ave",
    "iso:country":"US",
    "sg:address":"911 W Baxter Ave",
    "sg:city":"Knoxville",
    "sg:classifiers":[
        {
            "category":"Retail",
            "subcategory":"Auto Repair",
            "type":"Services"
        }
    ],
    "sg:phone":"+1 865 673 6625",
    "sg:postcode":"37921",
    "sg:province":"TN",
    "sg:tags":[
        "repairing",
        "automobile",
        "general"
    ],
    "wof:name":"A Plus Auto Center",
    "wof:placetype":"venue"
},
  "geometry": {"coordinates":[-83.938062,35.975196],"type":"Point"}
}