{
  "type": "Feature",
  "properties": {
    "iso:country":"US",
    "sg:address":"1501 Havana St",
    "sg:city":"Memphis",
    "sg:classifiers":[
        {
            "category":"Organizations",
            "subcategory":"Religious Organization",
            "type":"Services"
        }
    ],
    "sg:phone":"+1 901 774 8672",
    "sg:postcode":"38106",
    "sg:province":"TN",
    "wof:name":"Prince Peace Baptist Church",
    "wof:placetype":"venue"
},
  "geometry": {"coordinates":[-90.033886,35.106929],"type":"Point"}
}