{
  "type": "Feature",
  "properties": {
    "iso:country":"US",
    "sg:address":"260 Droke Farm Private Dr",
    "sg:city":"Kingsport",
    "sg:classifiers":[
        {
            "category":"Real Estate",
            "subcategory":"Developer",
            "type":"Services"
        }
    ],
    "sg:phone":"+1 423 239 6109",
    "sg:postcode":"37663",
    "sg:province":"TN",
    "sg:tags":[
        "cemetery"
    ],
    "wof:name":"Mount Lebanon Cemetery Trust C",
    "wof:placetype":"venue"
},
  "geometry": {"coordinates":[-82.50013,36.471274],"type":"Point"}
}