{
  "type": "Feature",
  "properties": {
    "iso:country":"US",
    "sg:address":"2276 Cooks Rd",
    "sg:city":"Mount Juliet",
    "sg:classifiers":[
        {
            "category":"Wholesale",
            "subcategory":"Machinery & Supplies",
            "type":"Manufacturing & Wholesale Goods"
        }
    ],
    "sg:phone":"+1 615 443 2259",
    "sg:postcode":"37122",
    "sg:province":"TN",
    "sg:tags":[
        "equipment",
        "industrial"
    ],
    "wof:name":"World Indus Spares & Engrg",
    "wof:placetype":"venue"
},
  "geometry": {"coordinates":[-86.455749,36.263575],"type":"Point"}
}