{
  "type": "Feature",
  "properties": {
    "addr:full":"5414 Main St Spring Hill TN 37174",
    "addr:housenumber":"5414",
    "addr:postcode":"37174",
    "addr:street":"Main St",
    "iso:country":"US",
    "sg:address":"5414 Main St",
    "sg:city":"Spring Hill",
    "sg:classifiers":[
        {
            "category":"Autos & Motor Vehicles",
            "subcategory":"Fuel & Gas Station",
            "type":"Retail Goods"
        }
    ],
    "sg:phone":"+1 931 486 3656",
    "sg:postcode":"37174",
    "sg:province":"TN",
    "sg:tags":[
        "station",
        "gasoline",
        "store"
    ],
    "wof:name":"Quik Mart 36",
    "wof:placetype":"venue"
},
  "geometry": {"coordinates":[-86.936322,35.745855],"type":"Point"}
}