{
  "type": "Feature",
  "properties": {
    "addr:full":"5745 Old State Hwy 63 Speedwell TN 37870",
    "addr:housenumber":"5745",
    "addr:postcode":"37870",
    "addr:street":"Old State Hwy 63",
    "iso:country":"US",
    "sg:address":"5745 Old State Hwy 63",
    "sg:city":"Speedwell",
    "sg:classifiers":[
        {
            "category":"Food & Beverages",
            "subcategory":"Groceries & Convenience Stores",
            "type":"Retail Goods"
        }
    ],
    "sg:phone":"+1 423 562 2956",
    "sg:postcode":"37870",
    "sg:province":"TN",
    "wof:name":"D & P Grocery Store",
    "wof:placetype":"venue"
},
  "geometry": {"coordinates":[-83.92334700000001,36.447048],"type":"Point"}
}