{
  "type": "Feature",
  "properties": {
    "iso:country":"US",
    "sg:address":"356 W Dumplin Valley Rd",
    "sg:city":"Kodak",
    "sg:classifiers":[
        {
            "category":"Personal",
            "subcategory":"Beauty Salon",
            "type":"Services"
        }
    ],
    "sg:phone":"+1 865 933 2219",
    "sg:postcode":"37764",
    "sg:province":"TN",
    "wof:name":"Kodak Beauty Salon",
    "wof:placetype":"venue"
},
  "geometry": {"coordinates":[-83.62530099999999,35.975683],"type":"Point"}
}