{
  "type": "Feature",
  "properties": {
    "iso:country":"US",
    "sg:address":"620 Commodore Ln",
    "sg:city":"Knoxville",
    "sg:classifiers":[
        {
            "category":"Building & Trades",
            "subcategory":"Construction",
            "type":"Services"
        }
    ],
    "sg:phone":"+1 865 777 1748",
    "sg:postcode":"37934",
    "sg:province":"TN",
    "sg:tags":[
        "contractor"
    ],
    "wof:name":"National Contractors",
    "wof:placetype":"venue"
},
  "geometry": {"coordinates":[-84.132453,35.884548],"type":"Point"}
}