{
  "type": "Feature",
  "properties": {
    "iso:country":"US",
    "sg:address":"650 Murfreesboro Pike",
    "sg:city":"Nashville",
    "sg:classifiers":[
        {
            "category":"Retail",
            "subcategory":"Auto Repair",
            "type":"Services"
        }
    ],
    "sg:phone":"+1 615 254 4641",
    "sg:postcode":"37217",
    "sg:province":"TN",
    "sg:tags":[
        "truck"
    ],
    "wof:name":"A-Plus Truck Repair",
    "wof:placetype":"venue"
},
  "geometry": {"coordinates":[-86.738196,36.140795],"type":"Point"}
}