{
  "type": "Feature",
  "properties": {
    "addr:full":"1299 Madison St Shelbyville TN 37160",
    "addr:housenumber":"1299",
    "addr:postcode":"37160",
    "addr:street":"Madison St",
    "iso:country":"US",
    "sg:address":"1299 Madison St",
    "sg:city":"Shelbyville",
    "sg:classifiers":[
        {
            "category":"Shopping",
            "subcategory":"Florist",
            "type":"Retail Goods"
        }
    ],
    "sg:phone":"+1 931 685 8050",
    "sg:postcode":"37160",
    "sg:province":"TN",
    "wof:name":"Precious Petals Flowers",
    "wof:placetype":"venue"
},
  "geometry": {"coordinates":[-86.429346,35.485293],"type":"Point"}
}