{
  "type": "Feature",
  "properties": {
    "iso:country":"US",
    "sg:address":"7227 Butterfly Dr",
    "sg:city":"Memphis",
    "sg:classifiers":[
        {
            "category":"Retail",
            "subcategory":"Repair Shop",
            "type":"Services"
        }
    ],
    "sg:phone":"+1 901 372 8083",
    "sg:postcode":"38133",
    "sg:province":"TN",
    "sg:tags":[
        "lock",
        "locksmith"
    ],
    "wof:name":"Roadrunner Mobile Lock & Key",
    "wof:placetype":"venue"
},
  "geometry": {"coordinates":[-89.826391,35.188079],"type":"Point"}
}