{
  "type": "Feature",
  "properties": {
    "addr:full":"2406 Chillicothe St NW Knoxville TN 37921",
    "addr:housenumber":"2406",
    "addr:postcode":"37921",
    "addr:street":"Chillicothe St Nw",
    "iso:country":"US",
    "sg:address":"2406 Chillicothe St NW",
    "sg:city":"Knoxville",
    "sg:classifiers":[
        {
            "category":"Manufacturing",
            "subcategory":"Printing",
            "type":"Manufacturing & Wholesale Goods"
        }
    ],
    "sg:phone":"+1 865 524 5278",
    "sg:postcode":"37921",
    "sg:province":"TN",
    "sg:tags":[
        "lithographic",
        "commercial"
    ],
    "wof:name":"United Printing Services",
    "wof:placetype":"venue"
},
  "geometry": {"coordinates":[-83.97187,35.96867],"type":"Point"}
}