{
  "type": "Feature",
  "properties": {
    "iso:country":"US",
    "sg:address":"815 Crossland Ave",
    "sg:city":"Clarksville",
    "sg:classifiers":[
        {
            "category":"Organizations",
            "subcategory":"Religious Organization",
            "type":"Services"
        }
    ],
    "sg:phone":"+1 931 552 2766",
    "sg:postcode":"37040",
    "sg:province":"TN",
    "sg:tags":[
        "church"
    ],
    "wof:name":"Refuge of Hope Ministries Inc",
    "wof:placetype":"venue"
},
  "geometry": {"coordinates":[-87.347667,36.519927],"type":"Point"}
}