{
  "type": "Feature",
  "properties": {
    "addr:full":"2125 Miller Ave Crossville TN 38555",
    "addr:housenumber":"2125",
    "addr:postcode":"38555",
    "addr:street":"Miller Ave",
    "iso:country":"US",
    "sg:address":"2125 Miller Ave",
    "sg:city":"Crossville",
    "sg:classifiers":[
        {
            "category":"Organizations",
            "subcategory":"Religious Organization",
            "type":"Services"
        }
    ],
    "sg:phone":"+1 931 456 9953",
    "sg:postcode":"38555",
    "sg:province":"TN",
    "sg:website":"www.ddcm.org",
    "wof:name":"Grace Community Ctr",
    "wof:placetype":"venue"
},
  "geometry": {"coordinates":[-85.025041,35.934566],"type":"Point"}
}