{
  "type": "Feature",
  "properties": {
    "iso:country":"US",
    "sg:address":"7623 Clinton Hwy",
    "sg:city":"Powell",
    "sg:classifiers":[
        {
            "category":"Building & Trades",
            "subcategory":"Equipment Rental",
            "type":"Services"
        }
    ],
    "sg:phone":"+1 865 938 9494",
    "sg:postcode":"37849",
    "sg:province":"TN",
    "sg:tags":[
        "tape",
        "video"
    ],
    "wof:name":"New Released Videos & Tan",
    "wof:placetype":"venue"
},
  "geometry": {"coordinates":[-84.05516299999999,36.020649],"type":"Point"}
}