{
  "type": "Feature",
  "properties": {
    "iso:country":"US",
    "sg:address":"326 Asbury Rd",
    "sg:city":"Ripley",
    "sg:classifiers":[
        {
            "category":"Health Services",
            "subcategory":"Doctor",
            "type":"Services"
        }
    ],
    "sg:phone":"+1 731 221 1637",
    "sg:postcode":"38063",
    "sg:province":"TN",
    "sg:tags":[
        "physician",
        "surgeon"
    ],
    "wof:name":"Syed A Zaidi MD",
    "wof:placetype":"venue"
},
  "geometry": {"coordinates":[-89.567297,35.723846],"type":"Point"}
}