{
  "type": "Feature",
  "properties": {
    "iso:country":"US",
    "sg:address":"162 Rising Ln",
    "sg:city":"La Follette",
    "sg:classifiers":[
        {
            "category":"Building & Trades",
            "subcategory":"Construction",
            "type":"Services"
        }
    ],
    "sg:phone":"+1 423 566 4499",
    "sg:postcode":"37766",
    "sg:province":"TN",
    "sg:tags":[
        "steel",
        "fabrication",
        "welding"
    ],
    "wof:name":"Steel Solutions",
    "wof:placetype":"venue"
},
  "geometry": {"coordinates":[-84.066211,36.381168],"type":"Point"}
}