{
  "type": "Feature",
  "properties": {
    "iso:country":"US",
    "sg:address":"1331 Dolan Dr",
    "sg:city":"Memphis",
    "sg:classifiers":[
        {
            "category":"Organizations",
            "subcategory":"Religious Organization",
            "type":"Services"
        }
    ],
    "sg:phone":"+1 901 396 1903",
    "sg:postcode":"38116",
    "sg:province":"TN",
    "wof:name":"Now Faith Ministries Inc",
    "wof:placetype":"venue"
},
  "geometry": {"coordinates":[-90.02019799999999,35.044487],"type":"Point"}
}