{
  "type": "Feature",
  "properties": {
    "iso:country":"US",
    "sg:address":"4828 Montgomery Rd",
    "sg:city":"Millington",
    "sg:classifiers":[
        {
            "category":"Organizations",
            "subcategory":"Religious Organization",
            "type":"Services"
        }
    ],
    "sg:phone":"+1 901 872 6454",
    "sg:postcode":"38053",
    "sg:province":"TN",
    "wof:name":"Spirit Unity & Love Christian",
    "wof:placetype":"venue"
},
  "geometry": {"coordinates":[-89.905795,35.340088],"type":"Point"}
}