{
  "type": "Feature",
  "properties": {
    "iso:country":"US",
    "sg:address":"1331 Union Ave",
    "sg:city":"Memphis",
    "sg:classifiers":[
        {
            "category":"Organizations",
            "subcategory":"Non-profit Organization",
            "type":"Services"
        }
    ],
    "sg:phone":"+1 901 323 0321",
    "sg:postcode":"38104",
    "sg:province":"TN",
    "sg:tags":[
        "information",
        "alcoholism",
        "treatment"
    ],
    "wof:name":"Al-Ateen",
    "wof:placetype":"venue"
},
  "geometry": {"coordinates":[-90.017356,35.136843],"type":"Point"}
}