{
  "type": "Feature",
  "properties": {
    "iso:country":"US",
    "sg:address":"668 Colonial Rd",
    "sg:city":"Memphis",
    "sg:classifiers":[
        {
            "category":"Banks & Credit Unions",
            "subcategory":"Bank",
            "type":"Services"
        }
    ],
    "sg:phone":"+1 901 507 6166",
    "sg:postcode":"38117",
    "sg:province":"TN",
    "sg:tags":[
        "loan",
        "real estate"
    ],
    "wof:name":"Big River Mortgage LLC",
    "wof:placetype":"venue"
},
  "geometry": {"coordinates":[-89.90190699999999,35.113154],"type":"Point"}
}