{
  "type": "Feature",
  "properties": {
    "iso:country":"US",
    "sg:address":"5916 Spruce Hollow Cove",
    "sg:city":"Memphis",
    "sg:classifiers":[
        {
            "category":"Building & Trades",
            "subcategory":"Construction",
            "type":"Services"
        }
    ],
    "sg:phone":"+1 901 483 9546",
    "sg:postcode":"38134",
    "sg:province":"TN",
    "wof:name":"James Nabakowski",
    "wof:placetype":"venue"
},
  "geometry": {"coordinates":[-89.865207,35.19849],"type":"Point"}
}