{
  "type": "Feature",
  "properties": {
    "addr:full":"4032 Brighton-Clopton Rd Brighton TN 38011",
    "addr:housenumber":"4032",
    "addr:postcode":"38011",
    "addr:street":"Brighton-Clopton Rd",
    "iso:country":"US",
    "sg:address":"4032 Brighton-Clopton Rd",
    "sg:city":"Brighton",
    "sg:classifiers":[
        {
            "category":"Building & Trades",
            "subcategory":"Construction",
            "type":"Services"
        }
    ],
    "sg:phone":"+1 901 475 2764",
    "sg:postcode":"38011",
    "sg:province":"TN",
    "sg:tags":[
        "carpentry",
        "contractor"
    ],
    "wof:name":"Wood N Dimensions",
    "wof:placetype":"venue"
},
  "geometry": {"coordinates":[-89.676018,35.463841],"type":"Point"}
}