{
  "type": "Feature",
  "properties": {
    "iso:country":"US",
    "sg:address":"9950 Kingston Pike",
    "sg:city":"Knoxville",
    "sg:classifiers":[
        {
            "category":"Professional",
            "subcategory":"Lawyer & Legal Services",
            "type":"Services"
        }
    ],
    "sg:phone":"+1 865 693 9600",
    "sg:postcode":"37922",
    "sg:province":"TN",
    "wof:name":"Shumate W F Jr Atty",
    "wof:placetype":"venue"
},
  "geometry": {"coordinates":[-84.114722,35.904036],"type":"Point"}
}