{
  "type": "Feature",
  "properties": {
    "addr:full":"960 Brownfield Rd Dover TN 37058",
    "addr:housenumber":"960",
    "addr:postcode":"37058",
    "addr:street":"Brownfield Rd",
    "iso:country":"US",
    "sg:address":"960 Brownfield Rd",
    "sg:city":"Dover",
    "sg:classifiers":[
        {
            "category":"Restaurant",
            "type":"Food & Drink"
        }
    ],
    "sg:phone":"+1 931 232 8954",
    "sg:postcode":"37058",
    "sg:province":"TN",
    "sg:tags":[
        "eating"
    ],
    "wof:name":"P J's Restaurant & Resort",
    "wof:placetype":"venue"
},
  "geometry": {"coordinates":[-88.000058,36.388138],"type":"Point"}
}