{
  "type": "Feature",
  "properties": {
    "addr:full":"6083 Old Millington Rd Millington TN 38053",
    "addr:housenumber":"6083",
    "addr:postcode":"38053",
    "addr:street":"Old Millington Rd",
    "iso:country":"US",
    "sg:address":"6083 Old Millington Rd",
    "sg:city":"Millington",
    "sg:classifiers":[
        {
            "category":"Education",
            "subcategory":"School",
            "type":"Public Place"
        }
    ],
    "sg:phone":"+1 901 358 5150",
    "sg:postcode":"38053",
    "sg:province":"TN",
    "sg:tags":[
        "organization",
        "religious"
    ],
    "wof:name":"Woodlawn Ter Baptst Academy",
    "wof:placetype":"venue"
},
  "geometry": {"coordinates":[-89.96436300000001,35.293828],"type":"Point"}
}