{
  "type": "Feature",
  "properties": {
    "addr:full":"421 N Trenton St Rutherford TN 38369",
    "addr:housenumber":"421",
    "addr:postcode":"38369",
    "addr:street":"N Trenton St",
    "iso:country":"US",
    "sg:address":"421 N Trenton St",
    "sg:city":"Rutherford",
    "sg:classifiers":[
        {
            "category":"Building & Trades",
            "subcategory":"Construction",
            "type":"Services"
        }
    ],
    "sg:phone":"+1 731 665 6866",
    "sg:postcode":"38369",
    "sg:province":"TN",
    "sg:tags":[
        "contractor"
    ],
    "wof:name":"Sunrise Vinyl Products",
    "wof:placetype":"venue"
},
  "geometry": {"coordinates":[-88.988445,36.135699],"type":"Point"}
}