{
  "type": "Feature",
  "properties": {
    "iso:country":"US",
    "sg:address":"1100 Ridgeway Cir",
    "sg:city":"Signal Mountain",
    "sg:classifiers":[
        {
            "category":"Wholesale",
            "subcategory":"Scrap",
            "type":"Manufacturing & Wholesale Goods"
        }
    ],
    "sg:phone":"+1 423 886 4341",
    "sg:postcode":"37303",
    "sg:province":"TN",
    "sg:tags":[
        "recycling",
        "center"
    ],
    "wof:name":"Recycle Signal",
    "wof:placetype":"venue"
},
  "geometry": {"coordinates":[-84.616125,35.427209],"type":"Point"}
}