{
  "type": "Feature",
  "properties": {
    "iso:country":"US",
    "sg:address":"414 Wilson Ave",
    "sg:city":"Tullahoma",
    "sg:classifiers":[
        {
            "category":"Government",
            "subcategory":"Police Station",
            "type":"Public Place"
        }
    ],
    "sg:phone":"+1 931 393 0335",
    "sg:postcode":"37388",
    "sg:province":"TN",
    "sg:tags":[
        "federal"
    ],
    "wof:name":"Federal Bureau-Investigation",
    "wof:placetype":"venue"
},
  "geometry": {"coordinates":[-86.22178,35.36645],"type":"Point"}
}