{
  "type": "Feature",
  "properties": {
    "iso:country":"US",
    "sg:address":"6227 Ladd Rd",
    "sg:city":"Franklin",
    "sg:classifiers":[
        {
            "category":"Freight",
            "type":"Transportation"
        }
    ],
    "sg:phone":"+1 615 395 0148",
    "sg:postcode":"37067",
    "sg:province":"TN",
    "sg:tags":[
        "operator",
        "local",
        "trucking"
    ],
    "wof:name":"Pritchard John",
    "wof:placetype":"venue"
},
  "geometry": {"coordinates":[-86.74088399999999,35.871632],"type":"Point"}
}