{
  "type": "Feature",
  "properties": {
    "addr:full":"500 S Cumberland St Lebanon TN 37087",
    "addr:housenumber":"500",
    "addr:postcode":"37087",
    "addr:street":"S Cumberland St",
    "iso:country":"US",
    "sg:address":"500 S Cumberland St",
    "sg:city":"Lebanon",
    "sg:classifiers":[
        {
            "category":"Building & Trades",
            "subcategory":"Construction",
            "type":"Services"
        }
    ],
    "sg:phone":"+1 615 453 5600",
    "sg:postcode":"37087",
    "sg:province":"TN",
    "sg:tags":[
        "general",
        "contractor"
    ],
    "wof:name":"B & T Stafford Construction",
    "wof:placetype":"venue"
},
  "geometry": {"coordinates":[-86.29265599999999,36.196964],"type":"Point"}
}