{
  "type": "Feature",
  "properties": {
    "iso:country":"US",
    "sg:address":"1535 State Hwy 431",
    "sg:city":"Martin",
    "sg:classifiers":[
        {
            "category":"Wholesale",
            "subcategory":"Farm Supplies",
            "type":"Manufacturing & Wholesale Goods"
        }
    ],
    "sg:phone":"+1 731 587 5361",
    "sg:postcode":"38237",
    "sg:province":"TN",
    "sg:tags":[
        "livestock"
    ],
    "wof:name":"West Tenn Auction Co",
    "wof:placetype":"venue"
},
  "geometry": {"coordinates":[-88.928427,36.37184],"type":"Point"}
}