{
  "type": "Feature",
  "properties": {
    "addr:full":"1350 Westover Rd Jackson TN 38301",
    "addr:housenumber":"1350",
    "addr:postcode":"38301",
    "addr:street":"Westover Rd",
    "iso:country":"US",
    "sg:address":"1350 Westover Rd",
    "sg:city":"Jackson",
    "sg:classifiers":[
        {
            "category":"Building & Trades",
            "subcategory":"Construction",
            "type":"Services"
        }
    ],
    "sg:phone":"+1 731 427 5760",
    "sg:postcode":"38301",
    "sg:province":"TN",
    "sg:tags":[
        "siding",
        "contractor"
    ],
    "wof:name":"J & B Remodeling",
    "wof:placetype":"venue"
},
  "geometry": {"coordinates":[-88.87460799999999,35.610927],"type":"Point"}
}