{
  "type": "Feature",
  "properties": {
    "iso:country":"US",
    "sg:address":"1745 Leach Rd",
    "sg:city":"Cedar Grove",
    "sg:classifiers":[
        {
            "category":"Government",
            "subcategory":"Office",
            "type":"Public Place"
        }
    ],
    "sg:phone":"+1 731 986 5550",
    "sg:postcode":"38321",
    "sg:province":"TN",
    "sg:tags":[
        "forestry"
    ],
    "wof:name":"Tennessee Forestry Division",
    "wof:placetype":"venue"
},
  "geometry": {"coordinates":[-88.481919,35.915652],"type":"Point"}
}