{
  "type": "Feature",
  "properties": {
    "addr:full":"2740 Old Elm Hill Pike Nashville TN 37214",
    "addr:housenumber":"2740",
    "addr:postcode":"37214",
    "addr:street":"Old Elm Hill Pike",
    "iso:country":"US",
    "sg:address":"2740 Old Elm Hill Pike",
    "sg:city":"Nashville",
    "sg:classifiers":[
        {
            "category":"Banks & Credit Unions",
            "subcategory":"Bank",
            "type":"Services"
        }
    ],
    "sg:phone":"+1 615 889 5252",
    "sg:postcode":"37214",
    "sg:province":"TN",
    "sg:tags":[
        "broker",
        "mortgage"
    ],
    "wof:name":"Five Star Mortgage",
    "wof:placetype":"venue"
},
  "geometry": {"coordinates":[-86.668966,36.151135],"type":"Point"}
}