{
  "type": "Feature",
  "properties": {
    "addr:full":"2812 N Broadway St Knoxville TN 37917",
    "addr:housenumber":"2812",
    "addr:postcode":"37917",
    "addr:street":"N Broadway St",
    "iso:country":"US",
    "sg:address":"2812 N Broadway St",
    "sg:city":"Knoxville",
    "sg:classifiers":[
        {
            "category":"Restaurant",
            "type":"Food & Drink"
        }
    ],
    "sg:phone":"+1 865 524 2160",
    "sg:postcode":"37917",
    "sg:province":"TN",
    "wof:name":"Sonny's Real Pit Bar-B-Q",
    "wof:placetype":"venue"
},
  "geometry": {"coordinates":[-83.92458000000001,35.998369],"type":"Point"}
}