{
  "type": "Feature",
  "properties": {
    "iso:country":"US",
    "sg:address":"10227 Shrewsbury Run W",
    "sg:city":"Collierville",
    "sg:classifiers":[
        {
            "category":"Professional",
            "subcategory":"Business Services",
            "type":"Services"
        }
    ],
    "sg:phone":"+1 901 854 5869",
    "sg:postcode":"38017",
    "sg:province":"TN",
    "wof:name":"Lucas Enterprises",
    "wof:placetype":"venue"
},
  "geometry": {"coordinates":[-89.72205,35.085917],"type":"Point"}
}