{
  "type": "Feature",
  "properties": {
    "iso:country":"US",
    "sg:address":"1930 Wilson Pkwy",
    "sg:city":"Fayetteville",
    "sg:classifiers":[
        {
            "category":"Autos & Motor Vehicles",
            "subcategory":"Motorcycle Sales",
            "type":"Retail Goods"
        }
    ],
    "sg:phone":"+1 931 433 0006",
    "sg:postcode":"37334",
    "sg:province":"TN",
    "sg:tags":[
        "hardware",
        "repair"
    ],
    "wof:name":"Fayetteville Cycle Inc",
    "wof:placetype":"venue"
},
  "geometry": {"coordinates":[-86.576402,35.140752],"type":"Point"}
}