{
  "type": "Feature",
  "properties": {
    "addr:full":"5180 Park Ave Memphis TN 38119",
    "addr:housenumber":"5180",
    "addr:postcode":"38119",
    "addr:street":"Park Ave",
    "iso:country":"US",
    "sg:address":"5180 Park Ave",
    "sg:city":"Memphis",
    "sg:classifiers":[
        {
            "category":"Health Services",
            "subcategory":"Doctor",
            "type":"Services"
        },
        {
            "category":"Health Services",
            "subcategory":"Podiatrist",
            "type":"Services"
        }
    ],
    "sg:phone":"+1 901 682 4668",
    "sg:postcode":"38119",
    "sg:province":"TN",
    "sg:tags":[
        "physician",
        "surgeons"
    ],
    "wof:name":"East Memphis Podiatry Group",
    "wof:placetype":"venue"
},
  "geometry": {"coordinates":[-89.888896,35.105562],"type":"Point"}
}