{
  "type": "Feature",
  "properties": {
    "iso:country":"US",
    "sg:address":"2209 W Blount Ave",
    "sg:city":"Knoxville",
    "sg:classifiers":[
        {
            "category":"Home & Garden",
            "subcategory":"Building Materials",
            "type":"Retail Goods"
        }
    ],
    "sg:phone":"+1 865 573 4501",
    "sg:postcode":"37920",
    "sg:province":"TN",
    "sg:tags":[
        "mixed",
        "concrete"
    ],
    "sg:website":"www.rinker.com",
    "wof:name":"Rinker Materials Corp",
    "wof:placetype":"venue"
},
  "geometry": {"coordinates":[-83.920051,35.949326],"type":"Point"}
}