{
  "type": "Feature",
  "properties": {
    "iso:country":"US",
    "sg:address":"397 N Main St",
    "sg:city":"Lake City",
    "sg:classifiers":[
        {
            "category":"Shopping",
            "subcategory":"Florist",
            "type":"Retail Goods"
        }
    ],
    "sg:phone":"+1 865 426 2871",
    "sg:postcode":"37769",
    "sg:province":"TN",
    "wof:name":"Knight's Flowers",
    "wof:placetype":"venue"
},
  "geometry": {"coordinates":[-84.156584,36.225629],"type":"Point"}
}