{
  "type": "Feature",
  "properties": {
    "addr:full":"207 Lombardy St Trenton TN 38382",
    "addr:housenumber":"207",
    "addr:postcode":"38382",
    "addr:street":"Lombardy St",
    "iso:country":"US",
    "sg:address":"207 Lombardy St",
    "sg:city":"Trenton",
    "sg:classifiers":[
        {
            "category":"Building & Trades",
            "subcategory":"Construction",
            "type":"Services"
        }
    ],
    "sg:phone":"+1 731 855 2599",
    "sg:postcode":"38382",
    "sg:province":"TN",
    "sg:tags":[
        "concrete",
        "contractor"
    ],
    "wof:name":"Star Concrete Pumping Co Inc",
    "wof:placetype":"venue"
},
  "geometry": {"coordinates":[-88.93943400000001,35.967728],"type":"Point"}
}