{
  "type": "Feature",
  "properties": {
    "iso:country":"US",
    "sg:address":"4900 Hixson Pike",
    "sg:city":"Hixson",
    "sg:classifiers":[
        {
            "category":"Building & Trades",
            "subcategory":"Construction",
            "type":"Services"
        }
    ],
    "sg:phone":"+1 423 870 1321",
    "sg:postcode":"37343",
    "sg:province":"TN",
    "sg:tags":[
        "home",
        "builder"
    ],
    "wof:name":"Home Collection",
    "wof:placetype":"venue"
},
  "geometry": {"coordinates":[-85.246241,35.129001],"type":"Point"}
}