{
  "type": "Feature",
  "properties": {
    "iso:country":"US",
    "sg:address":"6302 S York Hwy",
    "sg:city":"Clarkrange",
    "sg:classifiers":[
        {
            "category":"Autos & Motor Vehicles",
            "subcategory":"Fuel & Gas Station",
            "type":"Retail Goods"
        }
    ],
    "sg:phone":"+1 931 863 4150",
    "sg:postcode":"38553",
    "sg:province":"TN",
    "sg:tags":[
        "oil"
    ],
    "wof:name":"Mike's Gas & Deli",
    "wof:placetype":"venue"
},
  "geometry": {"coordinates":[-85.013869,36.216053],"type":"Point"}
}