{
  "type": "Feature",
  "properties": {
    "iso:country":"US",
    "sg:address":"3131 Democrat Rd Bldg D",
    "sg:city":"Memphis",
    "sg:classifiers":[
        {
            "category":"Transit Center",
            "subcategory":"Freight",
            "type":"Transportation"
        }
    ],
    "sg:phone":"+1 901 224 6582",
    "sg:postcode":"38118",
    "sg:province":"TN",
    "sg:tags":[
        "air",
        "cargo",
        "express",
        "package"
    ],
    "wof:name":"Federal Express Charter Program Team Arrangement",
    "wof:placetype":"venue"
},
  "geometry": {"coordinates":[-89.962059,35.068981],"type":"Point"}
}