{
  "type": "Feature",
  "properties": {
    "addr:full":"6259 E Stage Plz Bartlett TN 38134",
    "addr:housenumber":"6259",
    "addr:postcode":"38134",
    "addr:street":"E Stage Plz",
    "iso:country":"US",
    "sg:address":"6259 E Stage Plz",
    "sg:city":"Bartlett",
    "sg:classifiers":[
        {
            "category":"Organizations",
            "subcategory":"Professional Association",
            "type":"Services"
        }
    ],
    "sg:phone":"+1 901 386 8771",
    "sg:postcode":"38134",
    "sg:province":"TN",
    "sg:website":"www.shelbycea.org",
    "wof:name":"Shelby County Education Assn",
    "wof:placetype":"venue"
},
  "geometry": {"coordinates":[-89.854676,35.205683],"type":"Point"}
}