{
  "type": "Feature",
  "properties": {
    "addr:full":"4923 E Shelby Dr Memphis TN 38118",
    "addr:housenumber":"4923",
    "addr:postcode":"38118",
    "addr:street":"E Shelby Dr",
    "iso:country":"US",
    "sg:address":"4923 E Shelby Dr",
    "sg:city":"Memphis",
    "sg:classifiers":[
        {
            "category":"Retail",
            "subcategory":"Auto Rental",
            "type":"Services"
        }
    ],
    "sg:phone":"+1 901 368 0095",
    "sg:postcode":"38118",
    "sg:province":"TN",
    "sg:tags":[
        "renting",
        "truck",
        "leasing"
    ],
    "wof:name":"U-Haul Co",
    "wof:placetype":"venue"
},
  "geometry": {"coordinates":[-89.90068100000001,35.02039],"type":"Point"}
}