{
  "type": "Feature",
  "properties": {
    "iso:country":"US",
    "sg:address":"336 Robbins St",
    "sg:city":"Lawrenceburg",
    "sg:classifiers":[
        {
            "category":"Professional",
            "subcategory":"Lawyer & Legal Services",
            "type":"Services"
        }
    ],
    "sg:phone":"+1 931 762 1912",
    "sg:postcode":"38464",
    "sg:province":"TN",
    "wof:name":"Shackleford & Tomerlin",
    "wof:placetype":"venue"
},
  "geometry": {"coordinates":[-87.321779,35.25811],"type":"Point"}
}