{
  "type": "Feature",
  "properties": {
    "iso:country":"US",
    "sg:address":"8330 Carriage Hills Dr",
    "sg:city":"Brentwood",
    "sg:classifiers":[
        {
            "category":"Personal",
            "subcategory":"Beauty Salon",
            "type":"Services"
        }
    ],
    "sg:phone":"+1 615 661 5880",
    "sg:postcode":"37027",
    "sg:province":"TN",
    "wof:name":"S C Of Middle Tn Inc",
    "wof:placetype":"venue"
},
  "geometry": {"coordinates":[-86.778018,35.958012],"type":"Point"}
}