{
  "type": "Feature",
  "properties": {
    "iso:country":"US",
    "sg:address":"130 Spurgeon Ln",
    "sg:city":"Blountville",
    "sg:classifiers":[
        {
            "category":"Professional",
            "subcategory":"Management & Consulting",
            "type":"Services"
        }
    ],
    "sg:phone":"+1 423 279 0660",
    "sg:postcode":"37617",
    "sg:province":"TN",
    "sg:website":"www.transformationnetwork.com",
    "wof:name":"Transformation Network",
    "wof:placetype":"venue"
},
  "geometry": {"coordinates":[-82.398703,36.503099],"type":"Point"}
}