{
  "type": "Feature",
  "properties": {
    "iso:country":"US",
    "sg:address":"820 Ridgefields Rd",
    "sg:city":"Kingsport",
    "sg:classifiers":[
        {
            "category":"Professional",
            "subcategory":"Management & Consulting",
            "type":"Services"
        }
    ],
    "sg:phone":"+1 423 245 3642",
    "sg:postcode":"37660",
    "sg:province":"TN",
    "wof:name":"Vandevate & Vandevate Inc",
    "wof:placetype":"venue"
},
  "geometry": {"coordinates":[-82.59494599999999,36.538355],"type":"Point"}
}