{
  "type": "Feature",
  "properties": {
    "addr:full":"115 Moore Ave Smyrna TN 37167",
    "addr:housenumber":"115",
    "addr:postcode":"37167",
    "addr:street":"Moore Ave",
    "iso:country":"US",
    "sg:address":"115 Moore Ave",
    "sg:city":"Smyrna",
    "sg:classifiers":[
        {
            "category":"Retail",
            "subcategory":"Auto Repair",
            "type":"Services"
        }
    ],
    "sg:phone":"+1 615 459 4903",
    "sg:postcode":"37167",
    "sg:province":"TN",
    "sg:tags":[
        "automotive"
    ],
    "wof:name":"Thurman Automotive",
    "wof:placetype":"venue"
},
  "geometry": {"coordinates":[-86.522522,35.989659],"type":"Point"}
}