{
  "type": "Feature",
  "properties": {
    "iso:country":"US",
    "sg:address":"119 N Maple St",
    "sg:city":"Murfreesboro",
    "sg:classifiers":[
        {
            "category":"Professional",
            "subcategory":"Lawyer & Legal Services",
            "type":"Services"
        }
    ],
    "sg:phone":"+1 615 904 1600",
    "sg:postcode":"37130",
    "sg:province":"TN",
    "sg:tags":[
        "attorney"
    ],
    "wof:name":"Scott & Assoc",
    "wof:placetype":"venue"
},
  "geometry": {"coordinates":[-86.392678,35.846319],"type":"Point"}
}