{
  "type": "Feature",
  "properties": {
    "iso:country":"US",
    "sg:address":"3828 Bloomingdale Rd",
    "sg:city":"Kingsport",
    "sg:classifiers":[
        {
            "category":"Wholesale",
            "subcategory":"Sporting Goods",
            "type":"Manufacturing & Wholesale Goods"
        },
        {
            "category":"Shopping",
            "subcategory":"Bicycles & Sporting Goods",
            "type":"Retail Goods"
        }
    ],
    "sg:phone":"+1 423 288 6288",
    "sg:postcode":"37660",
    "sg:province":"TN",
    "sg:tags":[
        "equipment",
        "playground"
    ],
    "wof:name":"Outdoor Recreation Inc",
    "wof:placetype":"venue"
},
  "geometry": {"coordinates":[-82.46543,36.587007],"type":"Point"}
}