{
  "type": "Feature",
  "properties": {
    "addr:full":"4711 Old Kingston Pike Knoxville TN 37919",
    "addr:housenumber":"4711",
    "addr:postcode":"37919",
    "addr:street":"Old Kingston Pike",
    "iso:country":"US",
    "sg:address":"4711 Old Kingston Pike",
    "sg:city":"Knoxville",
    "sg:classifiers":[
        {
            "category":"Professional",
            "type":"Services"
        }
    ],
    "sg:phone":"+1 865 558 6511",
    "sg:postcode":"37919",
    "sg:province":"TN",
    "sg:tags":[
        "establishment"
    ],
    "wof:name":"WNOX",
    "wof:placetype":"venue"
},
  "geometry": {"coordinates":[-83.982615,35.939483],"type":"Point"}
}