{
  "type": "Feature",
  "properties": {
    "addr:full":"138 Connie Ct Cleveland TN 37312",
    "addr:housenumber":"138",
    "addr:postcode":"37312",
    "addr:street":"Connie Ct",
    "iso:country":"US",
    "sg:address":"138 Connie Ct",
    "sg:city":"Cleveland",
    "sg:classifiers":[
        {
            "category":"Communications",
            "subcategory":"Radio Station",
            "type":"Services"
        }
    ],
    "sg:phone":"+1 423 336 1515",
    "sg:postcode":"37312",
    "sg:province":"TN",
    "sg:tags":[
        "broadcast"
    ],
    "wof:name":"Wllj Radio/103 1fm",
    "wof:placetype":"venue"
},
  "geometry": {"coordinates":[-84.811235,35.221422],"type":"Point"}
}