{
  "type": "Feature",
  "properties": {
    "addr:full":"3746 Haynes Rd Memphis TN 38133",
    "addr:housenumber":"3746",
    "addr:postcode":"38133",
    "addr:street":"Haynes Rd",
    "iso:country":"US",
    "sg:address":"3746 Haynes Rd",
    "sg:city":"Memphis",
    "sg:classifiers":[
        {
            "category":"Building & Trades",
            "subcategory":"Construction",
            "type":"Services"
        }
    ],
    "sg:phone":"+1 901 382 8183",
    "sg:postcode":"38133",
    "sg:province":"TN",
    "sg:tags":[
        "house",
        "carpentry",
        "contractor"
    ],
    "wof:name":"B and B Builders",
    "wof:placetype":"venue"
},
  "geometry": {"coordinates":[-89.801897,35.227928],"type":"Point"}
}