{
  "type": "Feature",
  "properties": {
    "iso:country":"US",
    "sg:address":"149 Longview Dr",
    "sg:city":"Harriman",
    "sg:classifiers":[
        {
            "category":"Retail",
            "subcategory":"Repair Shop",
            "type":"Services"
        }
    ],
    "sg:phone":"+1 865 882 5146",
    "sg:postcode":"37748",
    "sg:province":"TN",
    "sg:tags":[
        "plumbing",
        "drain",
        "cleaning",
        "sewer"
    ],
    "wof:name":"Service Sewer & Drain",
    "wof:placetype":"venue"
},
  "geometry": {"coordinates":[-84.554627,35.909673],"type":"Point"}
}