{
  "type": "Feature",
  "properties": {
    "iso:country":"US",
    "sg:address":"104 N Kentucky Ave",
    "sg:city":"Parsons",
    "sg:classifiers":[
        {
            "category":"Personal",
            "subcategory":"Beauty Salon",
            "type":"Services"
        }
    ],
    "sg:phone":"+1 731 847 2734",
    "sg:postcode":"38363",
    "sg:province":"TN",
    "sg:tags":[
        "shop"
    ],
    "wof:name":"Northside Beauty Shop",
    "wof:placetype":"venue"
},
  "geometry": {"coordinates":[-88.125877,35.654234],"type":"Point"}
}