{
  "type": "Feature",
  "properties": {
    "iso:country":"US",
    "sg:address":"296 State St",
    "sg:city":"Greeneville",
    "sg:classifiers":[
        {
            "category":"Farming",
            "subcategory":"Farm",
            "type":"Manufacturing & Wholesale Goods"
        }
    ],
    "sg:phone":"+1 423 638 1922",
    "sg:postcode":"37743",
    "sg:province":"TN",
    "sg:tags":[
        "crop",
        "general"
    ],
    "wof:name":"A&W Farms LLC",
    "wof:placetype":"venue"
},
  "geometry": {"coordinates":[-82.85574200000001,36.172814],"type":"Point"}
}