{
  "type": "Feature",
  "properties": {
    "iso:country":"US",
    "sg:address":"3337 Page St",
    "sg:city":"Kingsport",
    "sg:classifiers":[
        {
            "category":"Professional",
            "subcategory":"Engineering",
            "type":"Services"
        },
        {
            "category":"Retail",
            "subcategory":"Repair Shop",
            "type":"Services"
        },
        {
            "category":"Building & Trades",
            "subcategory":"Construction",
            "type":"Services"
        }
    ],
    "sg:phone":"+1 423 245 8602",
    "sg:postcode":"37660",
    "sg:province":"TN",
    "sg:tags":[
        "major",
        "refinishing",
        "specialty",
        "appliance",
        "system",
        "heating",
        "equipment",
        "small",
        "contractor",
        "air conditioning"
    ],
    "wof:name":"Caldwell HVAC & Appliance Repair",
    "wof:placetype":"venue"
},
  "geometry": {"coordinates":[-82.485741,36.587892],"type":"Point"}
}