{
  "type": "Feature",
  "properties": {
    "addr:full":"429 W Main St Hendersonville TN 37075",
    "addr:housenumber":"429",
    "addr:postcode":"37075",
    "addr:street":"W Main St",
    "iso:country":"US",
    "sg:address":"429 W Main St",
    "sg:city":"Hendersonville",
    "sg:classifiers":[
        {
            "category":"Banks & Credit Unions",
            "subcategory":"Bank",
            "type":"Services"
        }
    ],
    "sg:phone":"+1 615 822 4900",
    "sg:postcode":"37075",
    "sg:province":"TN",
    "sg:tags":[
        "state",
        "commercial"
    ],
    "wof:name":"First Tennessee Bank Nat Assn",
    "wof:placetype":"venue"
},
  "geometry": {"coordinates":[-86.632631,36.302271],"type":"Point"}
}