{
  "type": "Feature",
  "properties": {
    "iso:country":"US",
    "sg:address":"4409 Chapman Hwy",
    "sg:city":"Knoxville",
    "sg:classifiers":[
        {
            "category":"Banks & Credit Unions",
            "subcategory":"Bank",
            "type":"Services"
        },
        {
            "category":"Banks & Credit Unions",
            "subcategory":"Financial Services",
            "type":"Services"
        }
    ],
    "sg:phone":"+1 865 450 4201",
    "sg:postcode":"37920",
    "sg:province":"TN",
    "sg:tags":[
        "financing",
        "loan"
    ],
    "sg:website":"http://www.SunTrust.com",
    "wof:name":"SunTrust Bank - Chapman Square Kroger",
    "wof:placetype":"venue"
},
  "geometry": {"coordinates":[-83.905452,35.934137],"type":"Point"}
}