{
  "type": "Feature",
  "properties": {
    "iso:country":"US",
    "sg:address":"3716 Hughes Dr",
    "sg:city":"Kingsport",
    "sg:classifiers":[
        {
            "category":"Professional",
            "subcategory":"Computer Services",
            "type":"Services"
        }
    ],
    "sg:phone":"+1 423 349 5089",
    "sg:postcode":"37660",
    "sg:province":"TN",
    "sg:tags":[
        "related"
    ],
    "wof:name":"Eagle Developers Ibd",
    "wof:placetype":"venue"
},
  "geometry": {"coordinates":[-82.60373300000001,36.484279],"type":"Point"}
}