{
  "type": "Feature",
  "properties": {
    "iso:country":"US",
    "sg:address":"1036 Mineral Wells Ave",
    "sg:city":"Paris",
    "sg:classifiers":[
        {
            "category":"Autos & Motor Vehicles",
            "subcategory":"Auto Supplies",
            "type":"Retail Goods"
        }
    ],
    "sg:phone":"+1 731 642 0143",
    "sg:postcode":"38242",
    "sg:province":"TN",
    "sg:tags":[
        "automotive",
        "gasoline",
        "tire",
        "repair"
    ],
    "wof:name":"Joe & Jerry's Car Care Ctr Inc",
    "wof:placetype":"venue"
},
  "geometry": {"coordinates":[-88.31329100000001,36.288839],"type":"Point"}
}