{
  "type": "Feature",
  "properties": {
    "iso:country":"US",
    "sg:address":"4104 Hillsboro Pike",
    "sg:city":"Nashville",
    "sg:classifiers":[
        {
            "category":"Shopping",
            "type":"Retail Goods"
        }
    ],
    "sg:phone":"+1 615 385 9949",
    "sg:postcode":"37215",
    "sg:province":"TN",
    "sg:tags":[
        "engine",
        "honda",
        "parts"
    ],
    "wof:name":"Southern Discount Parts",
    "wof:placetype":"venue"
},
  "geometry": {"coordinates":[-86.81864299999999,36.100934],"type":"Point"}
}