{
  "type": "Feature",
  "properties": {
    "iso:country":"US",
    "sg:address":"574 Airways Blvd",
    "sg:city":"Jackson",
    "sg:classifiers":[
        {
            "category":"Restaurant",
            "type":"Food & Drink"
        }
    ],
    "sg:phone":"+1 731 427 2818",
    "sg:postcode":"38301",
    "sg:province":"TN",
    "sg:tags":[
        "eating"
    ],
    "wof:name":"Airways Restaurant",
    "wof:placetype":"venue"
},
  "geometry": {"coordinates":[-88.84567699999999,35.617711],"type":"Point"}
}