{
  "type": "Feature",
  "properties": {
    "addr:full":"5514 Ringgold Rd Chattanooga TN 37412",
    "addr:housenumber":"5514",
    "addr:postcode":"37412",
    "addr:street":"Ringgold Rd",
    "iso:country":"US",
    "sg:address":"5514 Ringgold Rd",
    "sg:city":"Chattanooga",
    "sg:classifiers":[
        {
            "category":"Shopping",
            "subcategory":"Used Merchandise",
            "type":"Retail Goods"
        }
    ],
    "sg:phone":"+1 423 499 5611",
    "sg:postcode":"37412",
    "sg:province":"TN",
    "sg:tags":[
        "record",
        "tape"
    ],
    "wof:name":"Music 101",
    "wof:placetype":"venue"
},
  "geometry": {"coordinates":[-85.227305,34.992386],"type":"Point"}
}