{
  "type": "Feature",
  "properties": {
    "iso:country":"US",
    "sg:address":"873 Asheville Hwy",
    "sg:city":"Strawberry Plns",
    "sg:classifiers":[
        {
            "category":"Building & Trades",
            "subcategory":"Construction",
            "type":"Services"
        }
    ],
    "sg:phone":"+1 865 933 3967",
    "sg:postcode":"37871",
    "sg:province":"TN",
    "sg:tags":[
        "excavating",
        "contractor"
    ],
    "wof:name":"Southern Land Svc",
    "wof:placetype":"venue"
},
  "geometry": {"coordinates":[-83.659048,36.01987],"type":"Point"}
}