{
  "type": "Feature",
  "properties": {
    "iso:country":"US",
    "sg:address":"1400 18th Ave S",
    "sg:city":"Nashville",
    "sg:classifiers":[
        {
            "category":"Professional",
            "subcategory":"Business Services",
            "type":"Services"
        }
    ],
    "sg:phone":"+1 615 858 1230",
    "sg:postcode":"37212",
    "sg:province":"TN",
    "sg:tags":[
        "recording",
        "travel",
        "agency",
        "studio"
    ],
    "wof:name":"BMG Music Travel Group",
    "wof:placetype":"venue"
},
  "geometry": {"coordinates":[-86.796316,36.140387],"type":"Point"}
}