{
  "type": "Feature",
  "properties": {
    "iso:country":"US",
    "sg:address":"411 Doublehead Ln",
    "sg:city":"Knoxville",
    "sg:classifiers":[
        {
            "category":"Professional",
            "subcategory":"Secretarial Services",
            "type":"Services"
        }
    ],
    "sg:phone":"+1 865 691 7826",
    "sg:postcode":"37909",
    "sg:province":"TN",
    "sg:tags":[
        "reporting"
    ],
    "wof:name":"Mary Jendrek",
    "wof:placetype":"venue"
},
  "geometry": {"coordinates":[-84.057125,35.933254],"type":"Point"}
}