{
  "type": "Feature",
  "properties": {
    "addr:full":"3477 Henry Branch Way Sevierville TN 37876",
    "addr:housenumber":"3477",
    "addr:postcode":"37876",
    "addr:street":"Henry Branch Way",
    "iso:country":"US",
    "sg:address":"3477 Henry Branch Way",
    "sg:city":"Sevierville",
    "sg:classifiers":[
        {
            "category":"Building & Trades",
            "subcategory":"Construction",
            "type":"Services"
        }
    ],
    "sg:phone":"+1 865 453 6394",
    "sg:postcode":"37876",
    "sg:province":"TN",
    "sg:tags":[
        "residential"
    ],
    "wof:name":"Bobby Parton Construction",
    "wof:placetype":"venue"
},
  "geometry": {"coordinates":[-83.39421299999999,35.79853],"type":"Point"}
}