{
  "type": "Feature",
  "properties": {
    "addr:full":"882 Urbane Rd NE Cleveland TN 37312",
    "addr:housenumber":"882",
    "addr:postcode":"37312",
    "addr:street":"Urbane Rd Ne",
    "iso:country":"US",
    "sg:address":"882 Urbane Rd NE",
    "sg:city":"Cleveland",
    "sg:classifiers":[
        {
            "category":"Wholesale",
            "subcategory":"Construction Materials",
            "type":"Manufacturing & Wholesale Goods"
        }
    ],
    "sg:phone":"+1 423 472 7186",
    "sg:postcode":"37312",
    "sg:province":"TN",
    "sg:tags":[
        "insulation"
    ],
    "wof:name":"Soltech Inc",
    "wof:placetype":"venue"
},
  "geometry": {"coordinates":[-84.81094400000001,35.201954],"type":"Point"}
}