{
  "type": "Feature",
  "properties": {
    "addr:full":"4420 Lebanon Pike Hermitage TN 37076",
    "addr:housenumber":"4420",
    "addr:postcode":"37076",
    "addr:street":"Lebanon Pike",
    "iso:country":"US",
    "sg:address":"4420 Lebanon Pike",
    "sg:city":"Hermitage",
    "sg:classifiers":[
        {
            "category":"Autos & Motor Vehicles",
            "subcategory":"Auto Supplies",
            "type":"Retail Goods"
        },
        {
            "category":"Retail",
            "subcategory":"Auto Repair",
            "type":"Services"
        }
    ],
    "sg:phone":"+1 615 871 9025",
    "sg:postcode":"37076",
    "sg:province":"TN",
    "sg:tags":[
        "lube",
        "oil",
        "tire"
    ],
    "sg:website":"http://www.firestonecompleteautocare.com/?s_kwcid=IYP_NTL",
    "wof:name":"Firestone Complete Auto Care Store",
    "wof:placetype":"venue"
},
  "geometry": {"coordinates":[-86.60399099999999,36.214909],"type":"Point"}
}