{
  "type": "Feature",
  "properties": {
    "addr:full":"96 W University Pkwy Jackson TN 38305",
    "addr:housenumber":"96",
    "addr:postcode":"38305",
    "addr:street":"W University Pkwy",
    "iso:country":"US",
    "sg:address":"96 W University Pkwy",
    "sg:city":"Jackson",
    "sg:classifiers":[
        {
            "category":"Professional",
            "subcategory":"Management & Consulting",
            "type":"Services"
        },
        {
            "category":"Insurance",
            "subcategory":"Insurance Agent",
            "type":"Services"
        }
    ],
    "sg:phone":"+1 731 668 1614",
    "sg:postcode":"38305",
    "sg:province":"TN",
    "sg:tags":[
        "employee",
        "consultant",
        "benefit"
    ],
    "wof:name":"Benefit Consulting Services",
    "wof:placetype":"venue"
},
  "geometry": {"coordinates":[-88.832387,35.696047],"type":"Point"}
}