{
  "type": "Feature",
  "properties": {
    "addr:full":"916 William Blount Dr Maryville TN 37801",
    "addr:housenumber":"916",
    "addr:postcode":"37801",
    "addr:street":"William Blount Dr",
    "iso:country":"US",
    "sg:address":"916 William Blount Dr",
    "sg:city":"Maryville",
    "sg:classifiers":[
        {
            "category":"Home & Garden",
            "subcategory":"Furniture",
            "type":"Retail Goods"
        }
    ],
    "sg:phone":"+1 865 983 0008",
    "sg:postcode":"37801",
    "sg:province":"TN",
    "wof:name":"Anything Oak",
    "wof:placetype":"venue"
},
  "geometry": {"coordinates":[-84.032437,35.730362],"type":"Point"}
}