{
  "type": "Feature",
  "properties": {
    "iso:country":"US",
    "sg:address":"2657 Appling Rd",
    "sg:city":"Memphis",
    "sg:classifiers":[
        {
            "category":"Banks & Credit Unions",
            "subcategory":"Bank",
            "type":"Services"
        }
    ],
    "sg:phone":"+1 901 388 0850",
    "sg:postcode":"38133",
    "sg:province":"TN",
    "sg:tags":[
        "loan",
        "real estate"
    ],
    "wof:name":"Home Mortgage Store",
    "wof:placetype":"venue"
},
  "geometry": {"coordinates":[-89.815016,35.198019],"type":"Point"}
}