{
  "type": "Feature",
  "properties": {
    "addr:full":"2905 Wilkinson Pike Maryville TN 37803",
    "addr:housenumber":"2905",
    "addr:postcode":"37803",
    "addr:street":"Wilkinson Pike",
    "iso:country":"US",
    "sg:address":"2905 Wilkinson Pike",
    "sg:city":"Maryville",
    "sg:classifiers":[
        {
            "category":"Food & Beverages",
            "subcategory":"Groceries & Convenience Stores",
            "type":"Retail Goods"
        }
    ],
    "sg:phone":"+1 865 984 9430",
    "sg:postcode":"37803",
    "sg:province":"TN",
    "sg:tags":[
        "market"
    ],
    "wof:name":"Minna Market",
    "wof:placetype":"venue"
},
  "geometry": {"coordinates":[-83.927314,35.723448],"type":"Point"}
}