{
  "type": "Feature",
  "properties": {
    "iso:country":"US",
    "sg:address":"5315 N Watkins St",
    "sg:city":"Memphis",
    "sg:classifiers":[
        {
            "category":"Retail",
            "subcategory":"Auto Repair",
            "type":"Services"
        }
    ],
    "sg:phone":"+1 901 354 2096",
    "sg:postcode":"38127",
    "sg:province":"TN",
    "sg:tags":[
        "automotive"
    ],
    "wof:name":"Discount Tow Service",
    "wof:placetype":"venue"
},
  "geometry": {"coordinates":[-90.026642,35.270315],"type":"Point"}
}