{
  "type": "Feature",
  "properties": {
    "addr:full":"1001 Riverside Dr Nashville TN 37206",
    "addr:housenumber":"1001",
    "addr:postcode":"37206",
    "addr:street":"Riverside Dr",
    "iso:country":"US",
    "sg:address":"1001 Riverside Dr",
    "sg:city":"Nashville",
    "sg:classifiers":[
        {
            "category":"Food & Beverages",
            "subcategory":"Groceries & Convenience Stores",
            "type":"Retail Goods"
        }
    ],
    "sg:phone":"+1 615 227 5729",
    "sg:postcode":"37206",
    "sg:province":"TN",
    "wof:name":"Piggly Wiggly",
    "wof:placetype":"venue"
},
  "geometry": {"coordinates":[-86.72647499999999,36.187553],"type":"Point"}
}