{
  "type": "Feature",
  "properties": {
    "addr:full":"320 Premier Ct Franklin TN 37067",
    "addr:housenumber":"320",
    "addr:postcode":"37067",
    "addr:street":"Premier Ct",
    "iso:country":"US",
    "sg:address":"320 Premier Ct",
    "sg:city":"Franklin",
    "sg:classifiers":[
        {
            "category":"Utilities",
            "subcategory":"Telephone",
            "type":"Services"
        },
        {
            "category":"Shopping",
            "type":"Retail Goods"
        }
    ],
    "sg:phone":"+1 615 661 7303",
    "sg:postcode":"37067",
    "sg:province":"TN",
    "sg:tags":[
        "company",
        "electrical",
        "merchandise",
        "contractor"
    ],
    "wof:name":"Bell South",
    "wof:placetype":"venue"
},
  "geometry": {"coordinates":[-86.82869100000001,35.953773],"type":"Point"}
}