{
  "type": "Feature",
  "properties": {
    "iso:country":"US",
    "sg:address":"5941 Stage Rd",
    "sg:city":"Memphis",
    "sg:classifiers":[
        {
            "category":"Retail",
            "subcategory":"Auto Repair",
            "type":"Services"
        }
    ],
    "sg:phone":"+1 901 382 2530",
    "sg:postcode":"38134",
    "sg:province":"TN",
    "sg:tags":[
        "brake"
    ],
    "wof:name":"Mr Quick Tune",
    "wof:placetype":"venue"
},
  "geometry": {"coordinates":[-89.86455100000001,35.204703],"type":"Point"}
}