{
  "type": "Feature",
  "properties": {
    "iso:country":"US",
    "sg:address":"126 Eldridge Dr",
    "sg:city":"Elizabethton",
    "sg:classifiers":[
        {
            "category":"Professional",
            "type":"Services"
        }
    ],
    "sg:phone":"+1 423 474 6642",
    "sg:postcode":"37643",
    "sg:province":"TN",
    "wof:name":"Ray Colbaugh Rev",
    "wof:placetype":"venue"
},
  "geometry": {"coordinates":[-82.135363,36.382454],"type":"Point"}
}