{
  "type": "Feature",
  "properties": {
    "addr:full":"2102 Scenic Ridge Cove Knoxville TN 37923",
    "addr:housenumber":"2102",
    "addr:postcode":"37923",
    "addr:street":"Scenic Ridge Cove",
    "iso:country":"US",
    "sg:address":"2102 Scenic Ridge Cove",
    "sg:city":"Knoxville",
    "sg:classifiers":[
        {
            "category":"Professional",
            "subcategory":"Research",
            "type":"Services"
        }
    ],
    "sg:phone":"+1 865 539 6122",
    "sg:postcode":"37923",
    "sg:province":"TN",
    "sg:tags":[
        "nonphysical",
        "commercial"
    ],
    "wof:name":"Financial Wizards",
    "wof:placetype":"venue"
},
  "geometry": {"coordinates":[-84.065377,35.953102],"type":"Point"}
}