{
  "type": "Feature",
  "properties": {
    "iso:country":"US",
    "sg:address":"3446 Old Brownsville Rd",
    "sg:city":"Memphis",
    "sg:classifiers":[
        {
            "category":"Manufacturing",
            "subcategory":"Furniture",
            "type":"Manufacturing & Wholesale Goods"
        }
    ],
    "sg:phone":"+1 901 525 5556",
    "sg:postcode":"38134",
    "sg:province":"TN",
    "sg:tags":[
        "mfg",
        "wood",
        "contractor",
        "trade"
    ],
    "wof:name":"Countertop Design Specialist",
    "wof:placetype":"venue"
},
  "geometry": {"coordinates":[-89.882918,35.220589],"type":"Point"}
}