{
  "type": "Feature",
  "properties": {
    "iso:country":"US",
    "sg:address":"618 S Gay St",
    "sg:city":"Knoxville",
    "sg:classifiers":[
        {
            "category":"Professional",
            "subcategory":"Management & Consulting",
            "type":"Services"
        }
    ],
    "sg:phone":"+1 865 523 9011",
    "sg:postcode":"37902",
    "sg:province":"TN",
    "wof:name":"BDT Dev & Management LLC",
    "wof:placetype":"venue"
},
  "geometry": {"coordinates":[-83.91748699999999,35.964038],"type":"Point"}
}