{
  "type": "Feature",
  "properties": {
    "iso:country":"US",
    "sg:address":"123 Charles Latham Dr",
    "sg:city":"Jackson",
    "sg:classifiers":[
        {
            "category":"Wholesale",
            "subcategory":"Machinery & Supplies",
            "type":"Manufacturing & Wholesale Goods"
        }
    ],
    "sg:phone":"+1 731 424 0579",
    "sg:postcode":"38301",
    "sg:province":"TN",
    "sg:tags":[
        "equipment",
        "establishment"
    ],
    "wof:name":"Eagle Machine Works",
    "wof:placetype":"venue"
},
  "geometry": {"coordinates":[-88.759259,35.595632],"type":"Point"}
}