{
  "type": "Feature",
  "properties": {
    "iso:country":"US",
    "sg:address":"9789 US Hwy 64",
    "sg:city":"Arlington",
    "sg:classifiers":[
        {
            "category":"Social Services",
            "subcategory":"Child Care",
            "type":"Services"
        }
    ],
    "sg:phone":"+1 901 385 0985",
    "sg:postcode":"38002",
    "sg:province":"TN",
    "wof:name":"Tender Hearts Learning Ctr",
    "wof:placetype":"venue"
},
  "geometry": {"coordinates":[-89.734911,35.205298],"type":"Point"}
}