{
  "type": "Feature",
  "properties": {
    "addr:full":"9220 Dutchtown Rd Knoxville TN 37923",
    "addr:postcode":"9220;37923",
    "addr:street":"Dutchtown Rd",
    "iso:country":"US",
    "sg:address":"9220 Dutchtown Rd",
    "sg:city":"Knoxville",
    "sg:classifiers":[
        {
            "category":"Home & Garden",
            "subcategory":"Building Materials",
            "type":"Retail Goods"
        }
    ],
    "sg:phone":"+1 865 693 4113",
    "sg:postcode":"37923",
    "sg:province":"TN",
    "sg:tags":[
        "insulation",
        "product",
        "conservation",
        "energy"
    ],
    "wof:name":"Planet Energy",
    "wof:placetype":"venue"
},
  "geometry": {"coordinates":[-84.09538000000001,35.926756],"type":"Point"}
}