{
  "type": "Feature",
  "properties": {
    "iso:country":"US",
    "sg:address":"63 Main St",
    "sg:city":"Gordonsville",
    "sg:classifiers":[
        {
            "category":"Government",
            "subcategory":"Police Station",
            "type":"Public Place"
        }
    ],
    "sg:phone":"+1 615 683 6088",
    "sg:postcode":"38563",
    "sg:province":"TN",
    "sg:tags":[
        "department"
    ],
    "wof:name":"Gordonsville Police Dept",
    "wof:placetype":"venue"
},
  "geometry": {"coordinates":[-85.93239199999999,36.172905],"type":"Point"}
}