{
  "type": "Feature",
  "properties": {
    "iso:country":"US",
    "sg:address":"410 N Fork Rd",
    "sg:city":"Manchester",
    "sg:classifiers":[
        {
            "category":"Building & Trades",
            "subcategory":"Construction",
            "type":"Services"
        }
    ],
    "sg:phone":"+1 931 728 7031",
    "sg:postcode":"37355",
    "sg:province":"TN",
    "wof:name":"Watts Paving & Sealing",
    "wof:placetype":"venue"
},
  "geometry": {"coordinates":[-86.148076,35.562674],"type":"Point"}
}