{
  "type": "Feature",
  "properties": {
    "iso:country":"US",
    "sg:address":"321 Walnut St",
    "sg:city":"Paris",
    "sg:classifiers":[
        {
            "category":"Professional",
            "subcategory":"Research",
            "type":"Services"
        }
    ],
    "sg:phone":"+1 731 642 9281",
    "sg:postcode":"38242",
    "sg:province":"TN",
    "sg:tags":[
        "nonphysical",
        "commercial"
    ],
    "wof:name":"Stan Kowalsky",
    "wof:placetype":"venue"
},
  "geometry": {"coordinates":[-88.320808,36.299117],"type":"Point"}
}