{
  "type": "Feature",
  "properties": {
    "iso:country":"US",
    "sg:address":"200 Butler Dr",
    "sg:city":"Murfreesboro",
    "sg:classifiers":[
        {
            "category":"Building & Trades",
            "subcategory":"Electrical",
            "type":"Services"
        }
    ],
    "sg:phone":"+1 615 904 6673",
    "sg:postcode":"37127",
    "sg:province":"TN",
    "sg:tags":[
        "electric",
        "contractor"
    ],
    "wof:name":"Fast Electrical Contrs Inc",
    "wof:placetype":"venue"
},
  "geometry": {"coordinates":[-86.397398,35.805825],"type":"Point"}
}