{
  "type": "Feature",
  "properties": {
    "iso:country":"US",
    "sg:address":"370 Shawanee Rd",
    "sg:city":"Harrogate",
    "sg:classifiers":[
        {
            "category":"Wholesale",
            "subcategory":"Machinery & Supplies",
            "type":"Manufacturing & Wholesale Goods"
        }
    ],
    "sg:phone":"+1 423 869 0089",
    "sg:postcode":"37752",
    "sg:province":"TN",
    "sg:tags":[
        "equipment",
        "mining"
    ],
    "wof:name":"T & A Mining & Industrial",
    "wof:placetype":"venue"
},
  "geometry": {"coordinates":[-83.63978299999999,36.580639],"type":"Point"}
}