{
  "type": "Feature",
  "properties": {
    "iso:country":"US",
    "sg:address":"3140 Battle Creek Rd",
    "sg:city":"Springfield",
    "sg:classifiers":[
        {
            "category":"Professional",
            "subcategory":"Business Services",
            "type":"Services"
        }
    ],
    "sg:phone":"+1 615 382 9106",
    "sg:postcode":"37172",
    "sg:province":"TN",
    "wof:name":"S & A Family",
    "wof:placetype":"venue"
},
  "geometry": {"coordinates":[-86.960539,36.431415],"type":"Point"}
}