{
  "type": "Feature",
  "properties": {
    "iso:country":"US",
    "sg:address":"131 Foothills Mall Dr",
    "sg:city":"Maryville",
    "sg:classifiers":[
        {
            "category":"Shopping",
            "subcategory":"Clothing, Apparel, & Fashions",
            "type":"Retail Goods"
        }
    ],
    "sg:phone":"+1 865 982 5651",
    "sg:postcode":"37801",
    "sg:province":"TN",
    "sg:tags":[
        "tuxedo"
    ],
    "wof:name":"Mitchell's Tuxedo Rentals Inc",
    "wof:placetype":"venue"
},
  "geometry": {"coordinates":[-83.992667,35.737491],"type":"Point"}
}