{
  "type": "Feature",
  "properties": {
    "iso:country":"US",
    "sg:address":"1101 Nashboro Blvd",
    "sg:city":"Nashville",
    "sg:classifiers":[
        {
            "category":"Recreation",
            "type":"Entertainment"
        }
    ],
    "sg:phone":"+1 615 367 2311",
    "sg:postcode":"37217",
    "sg:province":"TN",
    "sg:tags":[
        "club",
        "golf"
    ],
    "sg:website":"www.nashborogolf.com",
    "wof:name":"Nashboro Golf Club",
    "wof:placetype":"venue"
},
  "geometry": {"coordinates":[-86.636392,36.089081],"type":"Point"}
}