{
  "type": "Feature",
  "properties": {
    "iso:country":"US",
    "sg:address":"4106 Bristol Hwy",
    "sg:city":"Johnson City",
    "sg:classifiers":[
        {
            "category":"Building & Trades",
            "subcategory":"Plumbing",
            "type":"Services"
        }
    ],
    "sg:phone":"+1 423 282 8259",
    "sg:postcode":"37601",
    "sg:province":"TN",
    "sg:tags":[
        "conditioning",
        "air",
        "system",
        "contractor"
    ],
    "wof:name":"Eads Sheet Metal",
    "wof:placetype":"venue"
},
  "geometry": {"coordinates":[-82.361486,36.386678],"type":"Point"}
}