{
  "type": "Feature",
  "properties": {
    "iso:country":"US",
    "sg:address":"123 Lake St",
    "sg:city":"Ridgely",
    "sg:classifiers":[
        {
            "category":"Shopping",
            "subcategory":"Florist",
            "type":"Retail Goods"
        }
    ],
    "sg:phone":"+1 731 264 5117",
    "sg:postcode":"38080",
    "sg:province":"TN",
    "wof:name":"Tam Anns Hearts & Flowers",
    "wof:placetype":"venue"
},
  "geometry": {"coordinates":[-89.487244,36.263984],"type":"Point"}
}