{
  "type": "Feature",
  "properties": {
    "iso:country":"US",
    "sg:address":"1734 Somerset Dr",
    "sg:city":"Murfreesboro",
    "sg:classifiers":[
        {
            "category":"Professional",
            "subcategory":"Employment Agencies",
            "type":"Services"
        }
    ],
    "sg:phone":"+1 615 867 0581",
    "sg:postcode":"37129",
    "sg:province":"TN",
    "wof:name":"Read To Succeed Inc",
    "wof:placetype":"venue"
},
  "geometry": {"coordinates":[-86.41548299999999,35.895335],"type":"Point"}
}