{
  "type": "Feature",
  "properties": {
    "iso:country":"US",
    "sg:address":"3708 US Hwy 41A N",
    "sg:city":"Unionville",
    "sg:classifiers":[
        {
            "category":"Retail",
            "subcategory":"Repair Shop",
            "type":"Services"
        },
        {
            "category":"Building & Trades",
            "subcategory":"Construction",
            "type":"Services"
        }
    ],
    "sg:phone":"+1 931 294 5968",
    "sg:postcode":"37180",
    "sg:province":"TN",
    "sg:tags":[
        "welding",
        "contractor"
    ],
    "wof:name":"White's Welding",
    "wof:placetype":"venue"
},
  "geometry": {"coordinates":[-86.59282399999999,35.626006],"type":"Point"}
}