{
  "type": "Feature",
  "properties": {
    "iso:country":"US",
    "sg:address":"7011 Shallowford Rd",
    "sg:city":"Chattanooga",
    "sg:classifiers":[
        {
            "category":"Professional",
            "subcategory":"Business Services",
            "type":"Services"
        }
    ],
    "sg:phone":"+1 423 855 0304",
    "sg:postcode":"37421",
    "sg:province":"TN",
    "sg:tags":[
        "broker"
    ],
    "wof:name":"Impire Business Brokers",
    "wof:placetype":"venue"
},
  "geometry": {"coordinates":[-85.159817,35.044024],"type":"Point"}
}