{
  "type": "Feature",
  "properties": {
    "iso:country":"US",
    "sg:address":"142 Tipton Rd",
    "sg:city":"Townsend",
    "sg:classifiers":[
        {
            "category":"Restaurant",
            "type":"Food & Drink"
        }
    ],
    "sg:phone":"+1 865 448 2290",
    "sg:postcode":"37882",
    "sg:province":"TN",
    "wof:name":"Tuckaleechee Trout Farm",
    "wof:placetype":"venue"
},
  "geometry": {"coordinates":[-83.779419,35.669788],"type":"Point"}
}