{
  "type": "Feature",
  "properties": {
    "iso:country":"US",
    "sg:address":"1912 Columbia Ave",
    "sg:city":"Franklin",
    "sg:classifiers":[
        {
            "category":"Shopping",
            "subcategory":"Used Merchandise",
            "type":"Retail Goods"
        }
    ],
    "sg:phone":"+1 615 591 7233",
    "sg:postcode":"37064",
    "sg:province":"TN",
    "sg:tags":[
        "pawnbroker"
    ],
    "wof:name":"Standon Inc",
    "wof:placetype":"venue"
},
  "geometry": {"coordinates":[-86.876358,35.897549],"type":"Point"}
}