{
  "type": "Feature",
  "properties": {
    "addr:full":"1485 Blythe Ferry Rd NE Cleveland TN 37312",
    "addr:housenumber":"1485",
    "addr:postcode":"37312",
    "addr:street":"Blythe Ferry Rd Ne",
    "iso:country":"US",
    "sg:address":"1485 Blythe Ferry Rd NE",
    "sg:city":"Cleveland",
    "sg:classifiers":[
        {
            "category":"Wholesale",
            "subcategory":"Machinery & Supplies",
            "type":"Manufacturing & Wholesale Goods"
        },
        {
            "category":"Wholesale",
            "subcategory":"Electrical",
            "type":"Manufacturing & Wholesale Goods"
        }
    ],
    "sg:phone":"+1 423 476 7834",
    "sg:postcode":"37312",
    "sg:province":"TN",
    "sg:tags":[
        "transmission",
        "bearing",
        "industrial",
        "power",
        "equipment"
    ],
    "wof:name":"Applied Industrial Tech Inc",
    "wof:placetype":"venue"
},
  "geometry": {"coordinates":[-84.836395,35.178614],"type":"Point"}
}