{
  "type": "Feature",
  "properties": {
    "addr:full":"605 Glenwood Dr Chattanooga TN 37404",
    "addr:housenumber":"605",
    "addr:postcode":"37404",
    "addr:street":"Glenwood Dr",
    "iso:country":"US",
    "sg:address":"605 Glenwood Dr",
    "sg:city":"Chattanooga",
    "sg:classifiers":[
        {
            "category":"Health Services",
            "subcategory":"Doctor",
            "type":"Services"
        }
    ],
    "sg:phone":"+1 423 624 5200",
    "sg:postcode":"37404",
    "sg:province":"TN",
    "sg:tags":[
        "medical"
    ],
    "wof:name":"Morrison Richard C MD",
    "wof:placetype":"venue"
},
  "geometry": {"coordinates":[-85.259503,35.041165],"type":"Point"}
}