{
  "type": "Feature",
  "properties": {
    "iso:country":"US",
    "sg:address":"707 42nd Ave N",
    "sg:city":"Nashville",
    "sg:classifiers":[
        {
            "category":"Home & Garden",
            "subcategory":"Home Furnishings",
            "type":"Retail Goods"
        }
    ],
    "sg:phone":"+1 615 329 3667",
    "sg:postcode":"37209",
    "sg:province":"TN",
    "sg:tags":[
        "window",
        "door"
    ],
    "wof:name":"Oakley Window & Door",
    "wof:placetype":"venue"
},
  "geometry": {"coordinates":[-86.83738,36.157787],"type":"Point"}
}