{
  "type": "Feature",
  "properties": {
    "addr:full":"3615 Summer Ave Memphis TN 38122",
    "addr:housenumber":"3615",
    "addr:postcode":"38122",
    "addr:street":"Summer Ave",
    "iso:country":"US",
    "sg:address":"3615 Summer Ave",
    "sg:city":"Memphis",
    "sg:classifiers":[
        {
            "category":"Shopping",
            "subcategory":"Bicycles & Sporting Goods",
            "type":"Retail Goods"
        }
    ],
    "sg:phone":"+1 901 324 8346",
    "sg:postcode":"38122",
    "sg:province":"TN",
    "sg:tags":[
        "marksmanship",
        "instruction",
        "safety",
        "gun",
        "repair"
    ],
    "wof:name":"Guns & Ammo",
    "wof:placetype":"venue"
},
  "geometry": {"coordinates":[-89.940423,35.149394],"type":"Point"}
}