{
  "type": "Feature",
  "properties": {
    "iso:country":"US",
    "sg:address":"3343 Old Greenbrier Pike",
    "sg:city":"Springfield",
    "sg:classifiers":[
        {
            "category":"Retail",
            "subcategory":"Repair Shop",
            "type":"Services"
        }
    ],
    "sg:phone":"+1 615 384 1999",
    "sg:postcode":"37172",
    "sg:province":"TN",
    "sg:tags":[
        "automobile",
        "cleaning",
        "hydraulic"
    ],
    "wof:name":"Shoemakers Equipment Service",
    "wof:placetype":"venue"
},
  "geometry": {"coordinates":[-86.83357599999999,36.468218],"type":"Point"}
}