{
  "type": "Feature",
  "properties": {
    "iso:country":"US",
    "sg:address":"8825 Quail Run Dr",
    "sg:city":"Chattanooga",
    "sg:classifiers":[
        {
            "category":"Building & Trades",
            "subcategory":"Electrical",
            "type":"Services"
        }
    ],
    "sg:phone":"+1 423 510 8682",
    "sg:postcode":"37421",
    "sg:province":"TN",
    "sg:tags":[
        "electrical",
        "contractor"
    ],
    "wof:name":"Swope Construction",
    "wof:placetype":"venue"
},
  "geometry": {"coordinates":[-85.097289,35.028367],"type":"Point"}
}