{
  "type": "Feature",
  "properties": {
    "addr:full":"310 E Pkwy Gatlinburg TN 37738",
    "addr:housenumber":"310",
    "addr:postcode":"37738",
    "addr:street":"E Pkwy",
    "iso:country":"US",
    "sg:address":"310 E Pkwy",
    "sg:city":"Gatlinburg",
    "sg:classifiers":[
        {
            "category":"Travel",
            "subcategory":"Hotels & Motels",
            "type":"Entertainment"
        }
    ],
    "sg:phone":"+1 865 436 5856",
    "sg:postcode":"37738",
    "sg:province":"TN",
    "wof:name":"Ogle's Vacation Motel",
    "wof:placetype":"venue"
},
  "geometry": {"coordinates":[-83.50734,35.715729],"type":"Point"}
}