{
  "type": "Feature",
  "properties": {
    "iso:country":"US",
    "sg:address":"250 Nimrod Hill Ln",
    "sg:city":"Cookeville",
    "sg:classifiers":[
        {
            "category":"Building & Trades",
            "subcategory":"Pest Control",
            "type":"Services"
        }
    ],
    "sg:phone":"+1 931 858 7007",
    "sg:postcode":"38501",
    "sg:province":"TN",
    "wof:name":"Will Roberts Pest Control",
    "wof:placetype":"venue"
},
  "geometry": {"coordinates":[-85.536964,36.305601],"type":"Point"}
}