{
  "type": "Feature",
  "properties": {
    "iso:country":"US",
    "sg:address":"2608 Sutherland Ave NW",
    "sg:city":"Knoxville",
    "sg:classifiers":[
        {
            "category":"Food & Beverages",
            "subcategory":"Groceries & Convenience Stores",
            "type":"Retail Goods"
        },
        {
            "category":"Restaurant",
            "type":"Food & Drink"
        }
    ],
    "sg:phone":"+1 865 524 6272",
    "sg:postcode":"37919",
    "sg:province":"TN",
    "sg:tags":[
        "deli",
        "delicatessen"
    ],
    "wof:name":"Sutherland Deli",
    "wof:placetype":"venue"
},
  "geometry": {"coordinates":[-83.960218,35.954122],"type":"Point"}
}