{
  "type": "Feature",
  "properties": {
    "iso:country":"US",
    "sg:address":"805 Cook Dr",
    "sg:city":"Athens",
    "sg:classifiers":[
        {
            "category":"Health Services",
            "subcategory":"Doctor",
            "type":"Services"
        }
    ],
    "sg:phone":"+1 423 745 7552",
    "sg:postcode":"37303",
    "sg:province":"TN",
    "sg:tags":[
        "medical"
    ],
    "wof:name":"Michael F Lett MD",
    "wof:placetype":"venue"
},
  "geometry": {"coordinates":[-84.60439100000001,35.442399],"type":"Point"}
}