{
  "type": "Feature",
  "properties": {
    "iso:country":"US",
    "sg:address":"530 Joe B Jackson Pkwy",
    "sg:city":"Murfreesboro",
    "sg:classifiers":[
        {
            "category":"Wholesale",
            "subcategory":"Computers",
            "type":"Manufacturing & Wholesale Goods"
        }
    ],
    "sg:phone":"+1 615 494 5678",
    "sg:postcode":"37127",
    "sg:province":"TN",
    "sg:tags":[
        "electronics"
    ],
    "wof:name":"Aberrant Systems Inc",
    "wof:placetype":"venue"
},
  "geometry": {"coordinates":[-86.388398,35.77599],"type":"Point"}
}