{
  "type": "Feature",
  "properties": {
    "iso:country":"US",
    "sg:address":"611 Lower Sharon Rd",
    "sg:city":"Sharon",
    "sg:classifiers":[
        {
            "category":"Manufacturing",
            "subcategory":"Printing",
            "type":"Manufacturing & Wholesale Goods"
        }
    ],
    "sg:phone":"+1 731 456 2567",
    "sg:postcode":"38255",
    "sg:province":"TN",
    "sg:tags":[
        "screen"
    ],
    "wof:name":"Kap's",
    "wof:placetype":"venue"
},
  "geometry": {"coordinates":[-88.79056300000001,36.241031],"type":"Point"}
}