{
  "type": "Feature",
  "properties": {
    "addr:full":"2121 Hoitt Ave Knoxville TN 37917",
    "addr:housenumber":"2121",
    "addr:postcode":"37917",
    "addr:street":"Hoitt Ave",
    "iso:country":"US",
    "sg:address":"2121 Hoitt Ave",
    "sg:city":"Knoxville",
    "sg:classifiers":[
        {
            "category":"Organizations",
            "subcategory":"Religious Organization",
            "type":"Services"
        }
    ],
    "sg:phone":"+1 865 673 9110",
    "sg:postcode":"37917",
    "sg:province":"TN",
    "wof:name":"Hoitt Avenue Missionary Church",
    "wof:placetype":"venue"
},
  "geometry": {"coordinates":[-83.909971,35.993077],"type":"Point"}
}