{
  "type": "Feature",
  "properties": {
    "iso:country":"US",
    "sg:address":"1535 Appling Care Ln",
    "sg:city":"Cordova",
    "sg:classifiers":[
        {
            "category":"Social Services",
            "subcategory":"Adult Care",
            "type":"Services"
        }
    ],
    "sg:phone":"+1 901 377 7500",
    "sg:postcode":"38016",
    "sg:province":"TN",
    "sg:tags":[
        "home",
        "residential"
    ],
    "wof:name":"Atria Cordova",
    "wof:placetype":"venue"
},
  "geometry": {"coordinates":[-89.81661,35.168648],"type":"Point"}
}