{
  "type": "Feature",
  "properties": {
    "iso:country":"US",
    "sg:address":"2601 N John B Dennis Hwy",
    "sg:city":"Kingsport",
    "sg:classifiers":[
        {
            "category":"Real Estate",
            "subcategory":"Real Estate Operator",
            "type":"Services"
        }
    ],
    "sg:phone":"+1 423 288 6911",
    "sg:postcode":"37660",
    "sg:province":"TN",
    "sg:tags":[
        "building",
        "apartment"
    ],
    "wof:name":"Cross Creek Apartments",
    "wof:placetype":"venue"
},
  "geometry": {"coordinates":[-82.50401,36.562936],"type":"Point"}
}