{
  "type": "Feature",
  "properties": {
    "addr:full":"1166 Englewood St Memphis TN 38106",
    "addr:housenumber":"1166",
    "addr:postcode":"38106",
    "addr:street":"Englewood St",
    "iso:country":"US",
    "sg:address":"1166 Englewood St",
    "sg:city":"Memphis",
    "sg:classifiers":[
        {
            "category":"Organizations",
            "subcategory":"Religious Organization",
            "type":"Services"
        }
    ],
    "sg:phone":"+1 901 948 4442",
    "sg:postcode":"38106",
    "sg:province":"TN",
    "wof:name":"Charity Loving Mission",
    "wof:placetype":"venue"
},
  "geometry": {"coordinates":[-90.02519700000001,35.114709],"type":"Point"}
}