{
  "type": "Feature",
  "properties": {
    "iso:country":"US",
    "sg:address":"2531 Lamar Ave",
    "sg:city":"Memphis",
    "sg:classifiers":[
        {
            "category":"Autos & Motor Vehicles",
            "subcategory":"Automobile Sales",
            "type":"Retail Goods"
        }
    ],
    "sg:phone":"+1 901 743 5622",
    "sg:postcode":"38114",
    "sg:province":"TN",
    "sg:tags":[
        "used"
    ],
    "wof:name":"Gus Wells Motor Co",
    "wof:placetype":"venue"
},
  "geometry": {"coordinates":[-89.98033,35.10188],"type":"Point"}
}