{
  "type": "Feature",
  "properties": {
    "iso:country":"US",
    "sg:address":"8433 Woolrich Dr",
    "sg:city":"Cordova",
    "sg:classifiers":[
        {
            "category":"Autos & Motor Vehicles",
            "subcategory":"Auto Supplies",
            "type":"Retail Goods"
        }
    ],
    "sg:phone":"+1 901 755 1891",
    "sg:postcode":"38016",
    "sg:province":"TN",
    "sg:tags":[
        "automobile",
        "parts"
    ],
    "wof:name":"Vito's Parts",
    "wof:placetype":"venue"
},
  "geometry": {"coordinates":[-89.78317300000001,35.182749],"type":"Point"}
}