{
  "type": "Feature",
  "properties": {
    "iso:country":"US",
    "sg:address":"2882 Alcoa Hwy",
    "sg:city":"Knoxville",
    "sg:classifiers":[
        {
            "category":"Personal",
            "subcategory":"Beauty Salon",
            "type":"Services"
        }
    ],
    "sg:phone":"+1 865 573 5041",
    "sg:postcode":"37920",
    "sg:province":"TN",
    "sg:tags":[
        "shop"
    ],
    "wof:name":"Southgate Buty & Styling Salon",
    "wof:placetype":"venue"
},
  "geometry": {"coordinates":[-83.956062,35.916648],"type":"Point"}
}