{
  "type": "Feature",
  "properties": {
    "iso:country":"US",
    "sg:address":"210 Kraft St",
    "sg:city":"Clarksville",
    "sg:classifiers":[
        {
            "category":"Organizations",
            "subcategory":"Religious Organization",
            "type":"Services"
        }
    ],
    "sg:phone":"+1 931 552 0490",
    "sg:postcode":"37040",
    "sg:province":"TN",
    "sg:tags":[
        "church"
    ],
    "wof:name":"Faith Christian Center",
    "wof:placetype":"venue"
},
  "geometry": {"coordinates":[-87.34816499999999,36.541767],"type":"Point"}
}