{
  "type": "Feature",
  "properties": {
    "iso:country":"US",
    "sg:address":"6000 Wellesley Way",
    "sg:city":"Brentwood",
    "sg:classifiers":[
        {
            "category":"Organizations",
            "subcategory":"Religious Organization",
            "type":"Services"
        },
        {
            "category":"Professional",
            "subcategory":"Management & Consulting",
            "type":"Services"
        }
    ],
    "sg:phone":"+1 615 373 1048",
    "sg:postcode":"37027",
    "sg:province":"TN",
    "sg:tags":[
        "consultant"
    ],
    "wof:name":"Church Consultants LLC",
    "wof:placetype":"venue"
},
  "geometry": {"coordinates":[-86.817932,36.037365],"type":"Point"}
}