{
  "type": "Feature",
  "properties": {
    "iso:country":"US",
    "sg:address":"4260 Boogertown Rd",
    "sg:city":"Sevierville",
    "sg:classifiers":[
        {
            "category":"Professional",
            "type":"Services"
        }
    ],
    "sg:phone":"+1 865 430 4408",
    "sg:postcode":"37876",
    "sg:province":"TN",
    "wof:name":"Keith Lamon",
    "wof:placetype":"venue"
},
  "geometry": {"coordinates":[-83.469515,35.763569],"type":"Point"}
}