{
  "type": "Feature",
  "properties": {
    "iso:country":"US",
    "sg:address":"855 Hillwood Blvd",
    "sg:city":"Nashville",
    "sg:classifiers":[
        {
            "category":"Restaurant",
            "type":"Food & Drink"
        }
    ],
    "sg:menulink":"http://www.allmenus.com/tn/nashville/166337-arbys/menu/",
    "sg:phone":"+1 615 353 0443",
    "sg:postcode":"37209",
    "sg:province":"TN",
    "sg:tags":[
        "burger",
        "american"
    ],
    "wof:name":"Arby's",
    "wof:placetype":"venue"
},
  "geometry": {"coordinates":[-86.880278,36.138182],"type":"Point"}
}