{
  "type": "Feature",
  "properties": {
    "iso:country":"US",
    "sg:address":"20 Music Sq E",
    "sg:city":"Nashville",
    "sg:classifiers":[
        {
            "category":"Wholesale",
            "subcategory":"Durable Goods & Equipment",
            "type":"Manufacturing & Wholesale Goods"
        }
    ],
    "sg:phone":"+1 615 327 9394",
    "sg:postcode":"37203",
    "sg:province":"TN",
    "sg:tags":[
        "compact",
        "record",
        "disc",
        "tape"
    ],
    "sg:website":"www.warnerchappell.com",
    "wof:name":"Warner/Chappell Music Inc",
    "wof:placetype":"venue"
},
  "geometry": {"coordinates":[-86.791799,36.150448],"type":"Point"}
}