{
  "type": "Feature",
  "properties": {
    "addr:full":"619 Lischey Ave Nashville TN 37207",
    "addr:housenumber":"619",
    "addr:postcode":"37207",
    "addr:street":"Lischey Ave",
    "iso:country":"US",
    "sg:address":"619 Lischey Ave",
    "sg:city":"Nashville",
    "sg:classifiers":[
        {
            "category":"Professional",
            "subcategory":"Computer Services",
            "type":"Services"
        }
    ],
    "sg:phone":"+1 615 578 7961",
    "sg:postcode":"37207",
    "sg:province":"TN",
    "sg:tags":[
        "equipment",
        "processing",
        "datum"
    ],
    "wof:name":"Computer Centre",
    "wof:placetype":"venue"
},
  "geometry": {"coordinates":[-86.76517800000001,36.181932],"type":"Point"}
}