{
  "type": "Feature",
  "properties": {
    "addr:full":"407 New Englewood Rd Athens TN 37303",
    "addr:housenumber":"407",
    "addr:postcode":"37303",
    "addr:street":"New Englewood Rd",
    "iso:country":"US",
    "sg:address":"407 New Englewood Rd",
    "sg:city":"Athens",
    "sg:classifiers":[
        {
            "category":"Organizations",
            "subcategory":"Religious Organization",
            "type":"Services"
        }
    ],
    "sg:phone":"+1 423 744 7325",
    "sg:postcode":"37303",
    "sg:province":"TN",
    "sg:tags":[
        "church"
    ],
    "wof:name":"Better Living Ctr",
    "wof:placetype":"venue"
},
  "geometry": {"coordinates":[-84.57172,35.428305],"type":"Point"}
}