{
  "type": "Feature",
  "properties": {
    "iso:country":"US",
    "sg:address":"3521 Lamar Ave",
    "sg:city":"Memphis",
    "sg:classifiers":[
        {
            "category":"Food & Beverages",
            "subcategory":"Groceries & Convenience Stores",
            "type":"Retail Goods"
        }
    ],
    "sg:phone":"+1 901 362 9286",
    "sg:postcode":"38118",
    "sg:province":"TN",
    "sg:tags":[
        "station"
    ],
    "wof:name":"Delta Market",
    "wof:placetype":"venue"
},
  "geometry": {"coordinates":[-89.94540000000001,35.070031],"type":"Point"}
}