{
  "type": "Feature",
  "properties": {
    "addr:full":"70 State Hwy 114 S Scotts Hill TN 38374",
    "addr:housenumber":"70",
    "addr:postcode":"38374",
    "addr:street":"State Hwy 114 S",
    "iso:country":"US",
    "sg:address":"70 State Hwy 114 S",
    "sg:city":"Scotts Hill",
    "sg:classifiers":[
        {
            "category":"Shopping",
            "subcategory":"Discount & Variety Stores",
            "type":"Retail Goods"
        }
    ],
    "sg:phone":"+1 731 549 3225",
    "sg:postcode":"38374",
    "sg:province":"TN",
    "sg:tags":[
        "merchandise",
        "general"
    ],
    "wof:name":"Stanfill Dollar Saver",
    "wof:placetype":"venue"
},
  "geometry": {"coordinates":[-88.24447600000001,35.51482],"type":"Point"}
}