{
  "type": "Feature",
  "properties": {
    "iso:country":"US",
    "sg:address":"6242 Ringgold Rd",
    "sg:city":"Chattanooga",
    "sg:classifiers":[
        {
            "category":"Real Estate",
            "subcategory":"Real Estate Agent",
            "type":"Services"
        }
    ],
    "sg:phone":"+1 423 855 0778",
    "sg:postcode":"37412",
    "sg:province":"TN",
    "wof:name":"Manhattan Properties",
    "wof:placetype":"venue"
},
  "geometry": {"coordinates":[-85.21246600000001,34.989686],"type":"Point"}
}