{
  "type": "Feature",
  "properties": {
    "iso:country":"US",
    "sg:address":"520 College St",
    "sg:city":"Knoxville",
    "sg:classifiers":[
        {
            "category":"Organizations",
            "subcategory":"Religious Organization",
            "type":"Services"
        }
    ],
    "sg:phone":"+1 865 523 2334",
    "sg:postcode":"37921",
    "sg:province":"TN",
    "wof:name":"Rogers Memorial Baptist Church",
    "wof:placetype":"venue"
},
  "geometry": {"coordinates":[-83.936071,35.966637],"type":"Point"}
}