{
  "type": "Feature",
  "properties": {
    "iso:country":"US",
    "sg:address":"1212 Nichol Ln",
    "sg:city":"Nashville",
    "sg:classifiers":[
        {
            "category":"Professional",
            "subcategory":"Computer Services",
            "type":"Services"
        }
    ],
    "sg:phone":"+1 615 269 9321",
    "sg:postcode":"37205",
    "sg:province":"TN",
    "sg:tags":[
        "development",
        "software"
    ],
    "wof:name":"Ssmca Ventures LLC",
    "wof:placetype":"venue"
},
  "geometry": {"coordinates":[-86.86713,36.087824],"type":"Point"}
}