{
  "type": "Feature",
  "properties": {
    "addr:full":"100 Creme St Copperhill TN 37317",
    "addr:housenumber":"100",
    "addr:postcode":"37317",
    "addr:street":"Creme St",
    "iso:country":"US",
    "sg:address":"100 Creme St",
    "sg:city":"Copperhill",
    "sg:classifiers":[
        {
            "category":"Professional",
            "subcategory":"Lawyer & Legal Services",
            "type":"Services"
        }
    ],
    "sg:phone":"+1 423 496 7000",
    "sg:postcode":"37317",
    "sg:province":"TN",
    "sg:tags":[
        "attorney",
        "practice",
        "plan"
    ],
    "wof:name":"Blue Ridge Law Llp",
    "wof:placetype":"venue"
},
  "geometry": {"coordinates":[-84.368866,34.990303],"type":"Point"}
}