{
  "type": "Feature",
  "properties": {
    "iso:country":"US",
    "sg:address":"712 Rundle Ave",
    "sg:city":"Nashville",
    "sg:classifiers":[
        {
            "category":"Autos & Motor Vehicles",
            "subcategory":"Auto Supplies",
            "type":"Retail Goods"
        },
        {
            "category":"Wholesale",
            "subcategory":"Auto Parts",
            "type":"Manufacturing & Wholesale Goods"
        }
    ],
    "sg:phone":"+1 615 259 0450",
    "sg:postcode":"37210",
    "sg:province":"TN",
    "sg:tags":[
        "equipment",
        "truck",
        "rec"
    ],
    "wof:name":"Rhino Linings of Middle Tenn",
    "wof:placetype":"venue"
},
  "geometry": {"coordinates":[-86.746728,36.147352],"type":"Point"}
}