{
  "type": "Feature",
  "properties": {
    "iso:country":"US",
    "sg:address":"1875 Madison St",
    "sg:city":"Clarksville",
    "sg:classifiers":[
        {
            "category":"Retail",
            "subcategory":"Car Wash",
            "type":"Services"
        }
    ],
    "sg:phone":"+1 931 542 0573",
    "sg:postcode":"37043",
    "sg:province":"TN",
    "sg:tags":[
        "polishing",
        "washing"
    ],
    "wof:name":"Lite Touch Auto Wash",
    "wof:placetype":"venue"
},
  "geometry": {"coordinates":[-87.30971700000001,36.514],"type":"Point"}
}