{
  "type": "Feature",
  "properties": {
    "iso:country":"US",
    "sg:address":"8300 Terry Ln",
    "sg:city":"Hermitage",
    "sg:classifiers":[
        {
            "category":"Real Estate",
            "subcategory":"Real Estate Operator",
            "type":"Services"
        }
    ],
    "sg:phone":"+1 615 889 5140",
    "sg:postcode":"37076",
    "sg:province":"TN",
    "sg:tags":[
        "building",
        "apartment"
    ],
    "wof:name":"Alan Estates",
    "wof:placetype":"venue"
},
  "geometry": {"coordinates":[-86.61284499999999,36.201055],"type":"Point"}
}