{
  "type": "Feature",
  "properties": {
    "addr:full":"203 S Holly St Monterey TN 38574",
    "addr:housenumber":"203",
    "addr:postcode":"38574",
    "addr:street":"S Holly St",
    "iso:country":"US",
    "sg:address":"203 S Holly St",
    "sg:city":"Monterey",
    "sg:classifiers":[
        {
            "category":"Retail",
            "subcategory":"Funeral Services",
            "type":"Services"
        }
    ],
    "sg:phone":"+1 931 839 2266",
    "sg:postcode":"38574",
    "sg:province":"TN",
    "sg:tags":[
        "director"
    ],
    "wof:name":"Horner Funeral Home",
    "wof:placetype":"venue"
},
  "geometry": {"coordinates":[-85.269659,36.146738],"type":"Point"}
}