{
  "type": "Feature",
  "properties": {
    "iso:country":"US",
    "sg:address":"4706 Buckingham Dr",
    "sg:city":"Chattanooga",
    "sg:classifiers":[
        {
            "category":"Wholesale",
            "subcategory":"Non-durable Goods",
            "type":"Manufacturing & Wholesale Goods"
        }
    ],
    "sg:phone":"+1 423 892 6438",
    "sg:postcode":"37421",
    "sg:province":"TN",
    "wof:name":"American Advertising",
    "wof:placetype":"venue"
},
  "geometry": {"coordinates":[-85.12093400000001,35.060788],"type":"Point"}
}