{
  "type": "Feature",
  "properties": {
    "addr:full":"10 Ridgeside Rd Chattanooga TN 37411",
    "addr:housenumber":"10",
    "addr:postcode":"37411",
    "addr:street":"Ridgeside Rd",
    "iso:country":"US",
    "sg:address":"10 Ridgeside Rd",
    "sg:city":"Chattanooga",
    "sg:classifiers":[
        {
            "category":"Professional",
            "subcategory":"Advertising",
            "type":"Services"
        }
    ],
    "sg:phone":"+1 423 622 0406",
    "sg:postcode":"37411",
    "sg:province":"TN",
    "sg:tags":[
        "agency"
    ],
    "sg:website":"www.connellagency.com",
    "wof:name":"Connell Communications",
    "wof:placetype":"venue"
},
  "geometry": {"coordinates":[-85.25095399999999,35.035139],"type":"Point"}
}