{
  "type": "Feature",
  "properties": {
    "addr:full":"252 E Broadway Blvd Jefferson City TN 37760",
    "addr:housenumber":"252",
    "addr:postcode":"37760",
    "addr:street":"E Broadway Blvd",
    "iso:country":"US",
    "sg:address":"252 E Broadway Blvd",
    "sg:city":"Jefferson City",
    "sg:classifiers":[
        {
            "category":"Utilities",
            "subcategory":"Mobile Phone",
            "type":"Services"
        }
    ],
    "sg:phone":"+1 865 475 2211",
    "sg:postcode":"37760",
    "sg:province":"TN",
    "sg:tags":[
        "wireless",
        "communications",
        "electronics",
        "telephone",
        "cellular"
    ],
    "wof:name":"Freedom Electronics & Wireless",
    "wof:placetype":"venue"
},
  "geometry": {"coordinates":[-83.482936,36.118079],"type":"Point"}
}