{
  "type": "Feature",
  "properties": {
    "iso:country":"US",
    "sg:address":"6313 Clinton Hwy",
    "sg:city":"Knoxville",
    "sg:classifiers":[
        {
            "category":"Manufacturing",
            "subcategory":"Buildings",
            "type":"Manufacturing & Wholesale Goods"
        }
    ],
    "sg:phone":"+1 865 938 2041",
    "sg:postcode":"37912",
    "sg:province":"TN",
    "sg:tags":[
        "mobile",
        "home",
        "mfg"
    ],
    "wof:name":"International Homes",
    "wof:placetype":"venue"
},
  "geometry": {"coordinates":[-84.004662,36.008948],"type":"Point"}
}