{
  "type": "Feature",
  "properties": {
    "iso:country":"US",
    "sg:address":"388 Harding Pl",
    "sg:city":"Nashville",
    "sg:classifiers":[
        {
            "category":"Personal",
            "type":"Services"
        }
    ],
    "sg:phone":"+1 615 833 5402",
    "sg:postcode":"37211",
    "sg:province":"TN",
    "sg:tags":[
        "control",
        "weight"
    ],
    "wof:name":"Overeaters Anonymous",
    "wof:placetype":"venue"
},
  "geometry": {"coordinates":[-86.721642,36.080479],"type":"Point"}
}