{
  "type": "Feature",
  "properties": {
    "iso:country":"US",
    "sg:address":"430 Boillin Ln",
    "sg:city":"Clarksville",
    "sg:classifiers":[
        {
            "category":"Bus Station",
            "type":"Transportation"
        }
    ],
    "sg:phone":"+1 931 553 2430",
    "sg:postcode":"37040",
    "sg:province":"TN",
    "sg:tags":[
        "facility"
    ],
    "sg:website":"www.cityofclarksville.com",
    "wof:name":"Transit System",
    "wof:placetype":"venue"
},
  "geometry": {"coordinates":[-87.334951,36.514703],"type":"Point"}
}