{
  "type": "Feature",
  "properties": {
    "iso:country":"US",
    "sg:address":"4510 Murfreesboro Hwy",
    "sg:city":"Manchester",
    "sg:classifiers":[
        {
            "category":"Shopping",
            "subcategory":"Bicycles & Sporting Goods",
            "type":"Retail Goods"
        }
    ],
    "sg:phone":"+1 931 728 0909",
    "sg:postcode":"37355",
    "sg:province":"TN",
    "wof:name":"Moonlite Grocery and Bait Shop",
    "wof:placetype":"venue"
},
  "geometry": {"coordinates":[-86.134925,35.51655],"type":"Point"}
}