{
  "type": "Feature",
  "properties": {
    "addr:full":"1861 US Hwy 51 S Covington TN 38019",
    "addr:housenumber":"1861",
    "addr:postcode":"38019",
    "addr:street":"Us Hwy 51 S",
    "iso:country":"US",
    "sg:address":"1861 US Hwy 51 S",
    "sg:city":"Covington",
    "sg:classifiers":[
        {
            "category":"Organizations",
            "subcategory":"Religious Organization",
            "type":"Services"
        }
    ],
    "sg:phone":"+1 901 476 9592",
    "sg:postcode":"38019",
    "sg:province":"TN",
    "sg:tags":[
        "church"
    ],
    "wof:name":"First Assembly Of God Church",
    "wof:placetype":"venue"
},
  "geometry": {"coordinates":[-89.671485,35.538407],"type":"Point"}
}