{
  "type": "Feature",
  "properties": {
    "iso:country":"US",
    "sg:address":"134 Annadel Cemetery Rd",
    "sg:city":"Lancing",
    "sg:classifiers":[
        {
            "category":"Organizations",
            "subcategory":"Religious Organization",
            "type":"Services"
        }
    ],
    "sg:phone":"+1 423 628 2914",
    "sg:postcode":"37770",
    "sg:province":"TN",
    "wof:name":"Annadell Baptist Church",
    "wof:placetype":"venue"
},
  "geometry": {"coordinates":[-84.656695,36.175227],"type":"Point"}
}