{
  "type": "Feature",
  "properties": {
    "iso:country":"US",
    "sg:address":"203 Glenview Cove",
    "sg:city":"Franklin",
    "sg:classifiers":[
        {
            "category":"Building & Trades",
            "subcategory":"Construction",
            "type":"Services"
        }
    ],
    "sg:phone":"+1 615 495 0268",
    "sg:postcode":"37064",
    "sg:province":"TN",
    "sg:tags":[
        "handyman"
    ],
    "wof:name":"THEHANDYMANSOURCE.COM",
    "wof:placetype":"venue"
},
  "geometry": {"coordinates":[-86.852717,35.920722],"type":"Point"}
}