{
  "type": "Feature",
  "properties": {
    "addr:full":"505 Ellington Dr Lafayette TN 37083",
    "addr:housenumber":"505",
    "addr:postcode":"37083",
    "addr:street":"Ellington Dr",
    "iso:country":"US",
    "sg:address":"505 Ellington Dr",
    "sg:city":"Lafayette",
    "sg:classifiers":[
        {
            "category":"Shopping",
            "subcategory":"Discount & Variety Stores",
            "type":"Retail Goods"
        }
    ],
    "sg:phone":"+1 615 666 8822",
    "sg:postcode":"37083",
    "sg:province":"TN",
    "wof:name":"Dollar General",
    "wof:placetype":"venue"
},
  "geometry": {"coordinates":[-86.037975,36.525785],"type":"Point"}
}