{
  "type": "Feature",
  "properties": {
    "iso:country":"US",
    "sg:address":"215 Raindrop Ln",
    "sg:city":"Hendersonville",
    "sg:classifiers":[
        {
            "category":"Shopping",
            "subcategory":"Catalog Store",
            "type":"Retail Goods"
        }
    ],
    "sg:phone":"+1 615 822 0315",
    "sg:postcode":"37075",
    "sg:province":"TN",
    "sg:tags":[
        "house",
        "mail"
    ],
    "wof:name":"Donco",
    "wof:placetype":"venue"
},
  "geometry": {"coordinates":[-86.60632099999999,36.329806],"type":"Point"}
}