{
  "type": "Feature",
  "properties": {
    "iso:country":"US",
    "sg:address":"600 W 5th Ave",
    "sg:city":"Springfield",
    "sg:classifiers":[
        {
            "category":"Real Estate",
            "subcategory":"Real Estate Operator",
            "type":"Services"
        }
    ],
    "sg:phone":"+1 615 382 5901",
    "sg:postcode":"37172",
    "sg:province":"TN",
    "sg:tags":[
        "apartment"
    ],
    "wof:name":"Charlestown Square Apartments",
    "wof:placetype":"venue"
},
  "geometry": {"coordinates":[-86.89079099999999,36.509942],"type":"Point"}
}