{
  "type": "Feature",
  "properties": {
    "iso:country":"US",
    "sg:address":"4413 Section Line Rd",
    "sg:city":"Union City",
    "sg:phone":"+1 731 885 5955",
    "sg:postcode":"38261",
    "sg:province":"TN",
    "sg:tags":[
        "farm",
        "corn",
        "soybean"
    ],
    "wof:name":"Circle K Farms Inc",
    "wof:placetype":"venue"
},
  "geometry": {"coordinates":[-89.010915,36.464905],"type":"Point"}
}