{
  "type": "Feature",
  "properties": {
    "iso:country":"US",
    "sg:address":"108 Harding Pl",
    "sg:city":"Nashville",
    "sg:classifiers":[
        {
            "category":"Real Estate",
            "subcategory":"Real Estate Agent",
            "type":"Services"
        }
    ],
    "sg:phone":"+1 615 352 3357",
    "sg:postcode":"37205",
    "sg:province":"TN",
    "sg:website":"www.hotels-motels-forsale.com",
    "wof:name":"Maxwell G Horkins Co",
    "wof:placetype":"venue"
},
  "geometry": {"coordinates":[-86.868031,36.101604],"type":"Point"}
}