{
  "type": "Feature",
  "properties": {
    "iso:country":"US",
    "sg:address":"1225 Park Dr",
    "sg:city":"Cookeville",
    "sg:classifiers":[
        {
            "category":"Building & Trades",
            "subcategory":"Plumbing",
            "type":"Services"
        }
    ],
    "sg:phone":"+1 931 528 1157",
    "sg:postcode":"38501",
    "sg:province":"TN",
    "sg:tags":[
        "plumbing",
        "contractor"
    ],
    "wof:name":"Buck's Plumbing & Sewer Svc",
    "wof:placetype":"venue"
},
  "geometry": {"coordinates":[-85.486921,36.178674],"type":"Point"}
}