{
  "type": "Feature",
  "properties": {
    "iso:country":"US",
    "sg:address":"131 N Houston St",
    "sg:city":"Maryville",
    "sg:classifiers":[
        {
            "category":"Social Services",
            "subcategory":"Child Care",
            "type":"Services"
        }
    ],
    "sg:phone":"+1 865 379 1299",
    "sg:postcode":"37801",
    "sg:province":"TN",
    "sg:tags":[
        "day"
    ],
    "wof:name":"A Mother's Touch Preschool",
    "wof:placetype":"venue"
},
  "geometry": {"coordinates":[-83.979653,35.749981],"type":"Point"}
}