{
  "type": "Feature",
  "properties": {
    "iso:country":"US",
    "sg:address":"1204 Lay St SE",
    "sg:city":"Cleveland",
    "sg:classifiers":[
        {
            "category":"Organizations",
            "subcategory":"Non-profit Organization",
            "type":"Services"
        }
    ],
    "sg:phone":"+1 423 559 8074",
    "sg:postcode":"37311",
    "sg:province":"TN",
    "sg:tags":[
        "social"
    ],
    "wof:name":"Lay Street Boys/Girls Club of",
    "wof:placetype":"venue"
},
  "geometry": {"coordinates":[-84.865894,35.144934],"type":"Point"}
}