{
  "type": "Feature",
  "properties": {
    "iso:country":"US",
    "sg:address":"3706 Vulcan Dr",
    "sg:city":"Nashville",
    "sg:classifiers":[
        {
            "category":"Freight",
            "type":"Transportation"
        },
        {
            "category":"Shopping",
            "type":"Retail Goods"
        }
    ],
    "sg:phone":"+1 615 331 0048",
    "sg:postcode":"37211",
    "sg:province":"TN",
    "sg:tags":[
        "warehouse",
        "self",
        "storage",
        "merchandise"
    ],
    "sg:website":"www.arrow-speed.com",
    "wof:name":"Arrow Speed Warehouse",
    "wof:placetype":"venue"
},
  "geometry": {"coordinates":[-86.74624300000001,36.096192],"type":"Point"}
}