{
  "type": "Feature",
  "properties": {
    "iso:country":"US",
    "sg:address":"104 Briarcrest Ct W",
    "sg:city":"Hendersonville",
    "sg:classifiers":[
        {
            "category":"Retail",
            "subcategory":"Repair Shop",
            "type":"Services"
        }
    ],
    "sg:phone":"+1 615 822 0024",
    "sg:postcode":"37075",
    "sg:province":"TN",
    "wof:name":"Dry Cleaning To Your Door",
    "wof:placetype":"venue"
},
  "geometry": {"coordinates":[-86.565793,36.333323],"type":"Point"}
}