{
  "type": "Feature",
  "properties": {
    "iso:country":"US",
    "sg:address":"2913 Village Ln",
    "sg:city":"Sevierville",
    "sg:classifiers":[
        {
            "category":"Travel",
            "subcategory":"Hotels & Motels",
            "type":"Entertainment"
        }
    ],
    "sg:phone":"+1 865 908 2700",
    "sg:postcode":"37862",
    "sg:province":"TN",
    "sg:tags":[
        "operation"
    ],
    "wof:name":"Terry Kay Cabin Rentals",
    "wof:placetype":"venue"
},
  "geometry": {"coordinates":[-83.59634800000001,35.799407],"type":"Point"}
}