{
  "type": "Feature",
  "properties": {
    "iso:country":"US",
    "sg:address":"140 Wiseman Ln",
    "sg:city":"Johnson City",
    "sg:classifiers":[
        {
            "category":"Retail",
            "subcategory":"Animal Services",
            "type":"Services"
        }
    ],
    "sg:phone":"+1 423 926 6043",
    "sg:postcode":"37601",
    "sg:province":"TN",
    "wof:name":"Wiseman Farms",
    "wof:placetype":"venue"
},
  "geometry": {"coordinates":[-82.32073200000001,36.259647],"type":"Point"}
}