{
  "type": "Feature",
  "properties": {
    "iso:country":"US",
    "sg:address":"6 Creekwood Rd",
    "sg:city":"Humboldt",
    "sg:classifiers":[
        {
            "category":"Building & Trades",
            "subcategory":"Construction",
            "type":"Services"
        }
    ],
    "sg:phone":"+1 731 784 2003",
    "sg:postcode":"38343",
    "sg:province":"TN",
    "sg:tags":[
        "house"
    ],
    "wof:name":"Dickson Construction",
    "wof:placetype":"venue"
},
  "geometry": {"coordinates":[-88.85986200000001,35.819285],"type":"Point"}
}