{
  "type": "Feature",
  "properties": {
    "addr:full":"406 Caldwell Dr Goodlettsville TN 37072",
    "addr:housenumber":"406",
    "addr:postcode":"37072",
    "addr:street":"Caldwell Dr",
    "iso:country":"US",
    "sg:address":"406 Caldwell Dr",
    "sg:city":"Goodlettsville",
    "sg:classifiers":[
        {
            "category":"Insurance",
            "subcategory":"Insurance Agent",
            "type":"Services"
        }
    ],
    "sg:phone":"+1 615 851 9834",
    "sg:postcode":"37072",
    "sg:province":"TN",
    "wof:name":"Claims Asssting Bookeeping Svc",
    "wof:placetype":"venue"
},
  "geometry": {"coordinates":[-86.691757,36.326181],"type":"Point"}
}