{
  "type": "Feature",
  "properties": {
    "addr:full":"3750 Hacks Cross Rd Memphis TN 38125",
    "addr:housenumber":"3750",
    "addr:postcode":"38125",
    "addr:street":"Hacks Cross Rd",
    "iso:country":"US",
    "sg:address":"3750 Hacks Cross Rd",
    "sg:city":"Memphis",
    "sg:classifiers":[
        {
            "category":"Restaurant",
            "type":"Food & Drink"
        }
    ],
    "sg:menulink":"http://www.allmenus.com/tn/memphis/33303-outback-steakhouse/menu/",
    "sg:phone":"+1 901 754 4911",
    "sg:postcode":"38125",
    "sg:province":"TN",
    "sg:tags":[
        "american",
        "steakhouse"
    ],
    "wof:name":"Outback Steakhouse",
    "wof:placetype":"venue"
},
  "geometry": {"coordinates":[-89.79593,35.046416],"type":"Point"}
}