{
  "type": "Feature",
  "properties": {
    "iso:country":"US",
    "sg:address":"1318 W Main St",
    "sg:city":"Lebanon",
    "sg:classifiers":[
        {
            "category":"Autos & Motor Vehicles",
            "subcategory":"Auto Supplies",
            "type":"Retail Goods"
        },
        {
            "category":"Shopping",
            "subcategory":"Computers & Home Electronics",
            "type":"Retail Goods"
        }
    ],
    "sg:phone":"+1 615 443 1989",
    "sg:postcode":"37087",
    "sg:province":"TN",
    "sg:tags":[
        "automobile",
        "alarm"
    ],
    "wof:name":"J & R Electronics",
    "wof:placetype":"venue"
},
  "geometry": {"coordinates":[-86.32405199999999,36.213969],"type":"Point"}
}