{
  "type": "Feature",
  "properties": {
    "iso:country":"US",
    "sg:address":"713 Holder Dr",
    "sg:city":"Nashville",
    "sg:classifiers":[
        {
            "category":"Retail",
            "subcategory":"Repair Shop",
            "type":"Services"
        }
    ],
    "sg:phone":"+1 615 361 3208",
    "sg:postcode":"37217",
    "sg:province":"TN",
    "sg:tags":[
        "sharpening"
    ],
    "wof:name":"Bladerunner Of Nashville",
    "wof:placetype":"venue"
},
  "geometry": {"coordinates":[-86.613761,36.08168],"type":"Point"}
}