{
  "type": "Feature",
  "properties": {
    "iso:country":"US",
    "sg:address":"3735 Vulcan Dr",
    "sg:city":"Nashville",
    "sg:classifiers":[
        {
            "category":"Wholesale",
            "subcategory":"Machinery & Supplies",
            "type":"Manufacturing & Wholesale Goods"
        }
    ],
    "sg:phone":"+1 615 832 3365",
    "sg:postcode":"37211",
    "sg:province":"TN",
    "sg:tags":[
        "contractor"
    ],
    "wof:name":"Southern Machinery Co",
    "wof:placetype":"venue"
},
  "geometry": {"coordinates":[-86.746499,36.095567],"type":"Point"}
}