{
  "type": "Feature",
  "properties": {
    "addr:full":"14654 Hwy 51 S Atoka TN 38004",
    "addr:housenumber":"14654",
    "addr:postcode":"38004",
    "addr:street":"Hwy 51 S",
    "iso:country":"US",
    "sg:address":"14654 Hwy 51 S",
    "sg:city":"Atoka",
    "sg:classifiers":[
        {
            "category":"Social Services",
            "subcategory":"Child Care",
            "type":"Services"
        }
    ],
    "sg:phone":"+1 901 837 7086",
    "sg:postcode":"38004",
    "sg:province":"TN",
    "sg:tags":[
        "day"
    ],
    "wof:name":"Angels Little Learning Center",
    "wof:placetype":"venue"
},
  "geometry": {"coordinates":[-89.829605,35.412836],"type":"Point"}
}