{
  "type": "Feature",
  "properties": {
    "iso:country":"US",
    "sg:address":"204 Ledgeview Dr",
    "sg:city":"Shelbyville",
    "sg:classifiers":[
        {
            "category":"Building & Trades",
            "subcategory":"Plumbing",
            "type":"Services"
        }
    ],
    "sg:phone":"+1 931 684 5393",
    "sg:postcode":"37160",
    "sg:province":"TN",
    "sg:tags":[
        "mechanical",
        "contractor"
    ],
    "wof:name":"R N Wilson Contractor",
    "wof:placetype":"venue"
},
  "geometry": {"coordinates":[-86.424791,35.510532],"type":"Point"}
}