{
  "type": "Feature",
  "properties": {
    "iso:country":"US",
    "sg:address":"705 N Whispering Oak Cir",
    "sg:city":"Powell",
    "sg:classifiers":[
        {
            "category":"Freight",
            "type":"Transportation"
        }
    ],
    "sg:phone":"+1 865 938 5184",
    "sg:postcode":"37849",
    "sg:province":"TN",
    "sg:tags":[
        "arrangement"
    ],
    "wof:name":"Anthony Novarro",
    "wof:placetype":"venue"
},
  "geometry": {"coordinates":[-83.997496,36.058504],"type":"Point"}
}