{
  "type": "Feature",
  "properties": {
    "addr:full":"340 Edgemont Ave Bristol TN 37620",
    "addr:housenumber":"340",
    "addr:postcode":"37620",
    "addr:street":"Edgemont Ave",
    "iso:country":"US",
    "sg:address":"340 Edgemont Ave",
    "sg:city":"Bristol",
    "sg:classifiers":[
        {
            "category":"Banks & Credit Unions",
            "subcategory":"Financial Services",
            "type":"Services"
        }
    ],
    "sg:phone":"+1 423 968 7072",
    "sg:postcode":"37620",
    "sg:province":"TN",
    "sg:tags":[
        "investor"
    ],
    "wof:name":"S J Strategic Investments LLC",
    "wof:placetype":"venue"
},
  "geometry": {"coordinates":[-82.18203800000001,36.59141],"type":"Point"}
}