{
  "type": "Feature",
  "properties": {
    "iso:country":"US",
    "sg:address":"908 Crockett St",
    "sg:city":"Nashville",
    "sg:classifiers":[
        {
            "category":"Retail",
            "subcategory":"Repair Shop",
            "type":"Services"
        }
    ],
    "sg:phone":"+1 615 227 8426",
    "sg:postcode":"37207",
    "sg:province":"TN",
    "sg:tags":[
        "marine",
        "mechanic"
    ],
    "wof:name":"Inglewood Marine",
    "wof:placetype":"venue"
},
  "geometry": {"coordinates":[-86.75341299999999,36.195547],"type":"Point"}
}