{
  "type": "Feature",
  "properties": {
    "addr:full":"2987 Lamar Ave Memphis TN 38114",
    "addr:housenumber":"2987",
    "addr:postcode":"38114",
    "addr:street":"Lamar Ave",
    "iso:country":"US",
    "sg:address":"2987 Lamar Ave",
    "sg:city":"Memphis",
    "sg:classifiers":[
        {
            "category":"Shopping",
            "type":"Retail Goods"
        }
    ],
    "sg:phone":"+1 901 743 3355",
    "sg:postcode":"38114",
    "sg:province":"TN",
    "sg:tags":[
        "cosmetic",
        "perfume"
    ],
    "wof:name":"Beauty & Beyond",
    "wof:placetype":"venue"
},
  "geometry": {"coordinates":[-89.963342,35.086994],"type":"Point"}
}