{
  "type": "Feature",
  "properties": {
    "iso:country":"US",
    "sg:address":"2413 Crestmoor Rd",
    "sg:city":"Nashville",
    "sg:classifiers":[
        {
            "category":"Professional",
            "subcategory":"Business Services",
            "type":"Services"
        }
    ],
    "sg:phone":"+1 615 383 6295",
    "sg:postcode":"37215",
    "sg:province":"TN",
    "wof:name":"Brooding Stud Music",
    "wof:placetype":"venue"
},
  "geometry": {"coordinates":[-86.81773200000001,36.109787],"type":"Point"}
}