{
  "type": "Feature",
  "properties": {
    "addr:full":"512 Walden Ave NW Harriman TN 37748",
    "addr:housenumber":"512",
    "addr:postcode":"harriman;37748",
    "addr:street":"Walden Ave Nw",
    "iso:country":"US",
    "sg:address":"512 Walden Ave NW",
    "sg:city":"Harriman",
    "sg:classifiers":[
        {
            "category":"Autos & Motor Vehicles",
            "subcategory":"Auto Supplies",
            "type":"Retail Goods"
        }
    ],
    "sg:phone":"+1 865 882 6336",
    "sg:postcode":"37748",
    "sg:province":"TN",
    "wof:name":"B & W Muffler & Brake Shop",
    "wof:placetype":"venue"
},
  "geometry": {"coordinates":[-84.55033,35.933364],"type":"Point"}
}