{
  "type": "Feature",
  "properties": {
    "iso:country":"US",
    "sg:address":"105 Cedar Point Pl",
    "sg:city":"Johnson City",
    "sg:classifiers":[
        {
            "category":"Building & Trades",
            "subcategory":"Plumbing",
            "type":"Services"
        }
    ],
    "sg:phone":"+1 423 416 6015",
    "sg:postcode":"37601",
    "sg:province":"TN",
    "sg:tags":[
        "plumbing",
        "contractor"
    ],
    "wof:name":"Salts Plumbing",
    "wof:placetype":"venue"
},
  "geometry": {"coordinates":[-82.39518099999999,36.386323],"type":"Point"}
}