{
  "type": "Feature",
  "properties": {
    "iso:country":"US",
    "sg:address":"1022 Mineral Wells Ave",
    "sg:city":"Paris",
    "sg:classifiers":[
        {
            "category":"Organizations",
            "subcategory":"Religious Organization",
            "type":"Services"
        }
    ],
    "sg:phone":"+1 731 642 4670",
    "sg:postcode":"38242",
    "sg:province":"TN",
    "sg:tags":[
        "church"
    ],
    "wof:name":"First United Pentecostal Chr",
    "wof:placetype":"venue"
},
  "geometry": {"coordinates":[-88.31437,36.289712],"type":"Point"}
}