{
  "type": "Feature",
  "properties": {
    "iso:country":"US",
    "sg:address":"2038 E Shelby Dr",
    "sg:city":"Memphis",
    "sg:classifiers":[
        {
            "category":"Autos & Motor Vehicles",
            "subcategory":"Fuel & Gas Station",
            "type":"Retail Goods"
        },
        {
            "category":"Food & Beverages",
            "subcategory":"Groceries & Convenience Stores",
            "type":"Retail Goods"
        }
    ],
    "sg:phone":"+1 901 395 0599",
    "sg:postcode":"38116",
    "sg:province":"TN",
    "sg:website":"http://www.flashmarketinc.com",
    "wof:name":"Flash Market, Inc.",
    "wof:placetype":"venue"
},
  "geometry": {"coordinates":[-89.996106,35.021043],"type":"Point"}
}