{
  "type": "Feature",
  "properties": {
    "iso:country":"US",
    "sg:address":"1031 John Ross Rd",
    "sg:city":"Chattanooga",
    "sg:classifiers":[
        {
            "category":"Personal",
            "subcategory":"Beauty Salon",
            "type":"Services"
        }
    ],
    "sg:phone":"+1 423 867 5934",
    "sg:postcode":"37412",
    "sg:province":"TN",
    "sg:tags":[
        "shop"
    ],
    "wof:name":"Carolyns Hair Creations",
    "wof:placetype":"venue"
},
  "geometry": {"coordinates":[-85.253163,34.996159],"type":"Point"}
}