{
  "type": "Feature",
  "properties": {
    "iso:country":"US",
    "sg:address":"8218 Luree Ln",
    "sg:city":"Hermitage",
    "sg:classifiers":[
        {
            "category":"Retail",
            "subcategory":"Repair Shop",
            "type":"Services"
        }
    ],
    "sg:phone":"+1 615 391 9191",
    "sg:postcode":"37076",
    "sg:province":"TN",
    "sg:tags":[
        "scooter",
        "motorcycle",
        "motor"
    ],
    "wof:name":"Jose's Cycle Shop",
    "wof:placetype":"venue"
},
  "geometry": {"coordinates":[-86.61696600000001,36.199842],"type":"Point"}
}