{
  "type": "Feature",
  "properties": {
    "iso:country":"US",
    "sg:address":"2176 Hillsboro Rd",
    "sg:city":"Franklin",
    "sg:classifiers":[
        {
            "category":"Health Services",
            "subcategory":"Doctor",
            "type":"Services"
        }
    ],
    "sg:phone":"+1 615 591 0294",
    "sg:postcode":"37069",
    "sg:province":"TN",
    "sg:tags":[
        "dentist"
    ],
    "wof:name":"Nina H Foley DDS",
    "wof:placetype":"venue"
},
  "geometry": {"coordinates":[-86.890762,35.987925],"type":"Point"}
}