{
  "type": "Feature",
  "properties": {
    "iso:country":"US",
    "sg:address":"129 S Oak St",
    "sg:city":"Mc Kenzie",
    "sg:classifiers":[
        {
            "category":"Retail",
            "subcategory":"Auto Repair",
            "type":"Services"
        }
    ],
    "sg:phone":"+1 731 352 3208",
    "sg:postcode":"38201",
    "sg:province":"TN",
    "sg:tags":[
        "muffler",
        "exhaust",
        "system"
    ],
    "wof:name":"Jerry's Muffler Shop & Garage",
    "wof:placetype":"venue"
},
  "geometry": {"coordinates":[-88.516655,36.127618],"type":"Point"}
}