{
  "type": "Feature",
  "properties": {
    "iso:country":"US",
    "sg:address":"1535 Tatumville Rd",
    "sg:city":"Newbern",
    "sg:classifiers":[
        {
            "category":"Farming",
            "subcategory":"Farm",
            "type":"Manufacturing & Wholesale Goods"
        }
    ],
    "sg:phone":"+1 731 627 2492",
    "sg:postcode":"38059",
    "sg:province":"TN",
    "sg:tags":[
        "crop",
        "general"
    ],
    "wof:name":"Alan Burchfiel",
    "wof:placetype":"venue"
},
  "geometry": {"coordinates":[-89.19325499999999,36.04486],"type":"Point"}
}