{
  "type": "Feature",
  "properties": {
    "iso:country":"US",
    "sg:address":"8644 Old Midway Rd",
    "sg:city":"Lenoir City",
    "sg:classifiers":[
        {
            "category":"Freight",
            "type":"Transportation"
        }
    ],
    "sg:phone":"+1 865 986 9426",
    "sg:postcode":"37772",
    "sg:province":"TN",
    "sg:tags":[
        "operator",
        "local",
        "trucking"
    ],
    "wof:name":"Circle H Trucking",
    "wof:placetype":"venue"
},
  "geometry": {"coordinates":[-84.23618999999999,35.820887],"type":"Point"}
}