{
  "type": "Feature",
  "properties": {
    "iso:country":"US",
    "sg:address":"146 Greenmeadow Ln",
    "sg:city":"Jonesborough",
    "sg:classifiers":[
        {
            "category":"Health Services",
            "subcategory":"Nursing And Care Facility",
            "type":"Services"
        }
    ],
    "sg:phone":"+1 423 753 8607",
    "sg:postcode":"37659",
    "sg:province":"TN",
    "sg:tags":[
        "home",
        "retirement",
        "community"
    ],
    "wof:name":"Whiteheads Home For Elderly",
    "wof:placetype":"venue"
},
  "geometry": {"coordinates":[-82.52786999999999,36.367219],"type":"Point"}
}