{
  "type": "Feature",
  "properties": {
    "iso:country":"US",
    "sg:address":"410 Sandburg Dr",
    "sg:city":"Clarksville",
    "sg:classifiers":[
        {
            "category":"Retail",
            "subcategory":"Portrait Studio",
            "type":"Services"
        }
    ],
    "sg:phone":"+1 931 920 5796",
    "sg:postcode":"37042",
    "sg:province":"TN",
    "sg:tags":[
        "photo"
    ],
    "wof:name":"Clarksville Photographer",
    "wof:placetype":"venue"
},
  "geometry": {"coordinates":[-87.417782,36.605083],"type":"Point"}
}