{
  "type": "Feature",
  "properties": {
    "addr:full":"40 Dover Crossing Rd Clarksville TN 37042",
    "addr:housenumber":"40",
    "addr:postcode":"37042",
    "addr:street":"Dover Crossing Rd",
    "iso:country":"US",
    "sg:address":"40 Dover Crossing Rd",
    "sg:city":"Clarksville",
    "sg:classifiers":[
        {
            "category":"Restaurant",
            "type":"Food & Drink"
        }
    ],
    "sg:menulink":"http://www.allmenus.com/tn/clarksville/177825-jack-in-the-box/menu/",
    "sg:phone":"+1 931 648 4401",
    "sg:postcode":"37042",
    "sg:province":"TN",
    "sg:tags":[
        "burger",
        "american"
    ],
    "wof:name":"Jack in the Box",
    "wof:placetype":"venue"
},
  "geometry": {"coordinates":[-87.39651499999999,36.553942],"type":"Point"}
}