{
  "type": "Feature",
  "properties": {
    "iso:country":"US",
    "sg:address":"181 Wild Creek Rd",
    "sg:city":"Shelbyville",
    "sg:classifiers":[
        {
            "category":"Building & Trades",
            "subcategory":"Construction",
            "type":"Services"
        }
    ],
    "sg:phone":"+1 931 684 0445",
    "sg:postcode":"37160",
    "sg:province":"TN",
    "sg:tags":[
        "builder",
        "operative"
    ],
    "wof:name":"Norman Construction",
    "wof:placetype":"venue"
},
  "geometry": {"coordinates":[-86.430341,35.545961],"type":"Point"}
}