{
  "type": "Feature",
  "properties": {
    "iso:country":"US",
    "sg:address":"310 N Poplar St",
    "sg:city":"Kenton",
    "sg:classifiers":[
        {
            "category":"Food & Beverages",
            "subcategory":"Groceries & Convenience Stores",
            "type":"Retail Goods"
        }
    ],
    "sg:phone":"+1 731 749 7333",
    "sg:postcode":"38233",
    "sg:province":"TN",
    "wof:name":"Reed's Market",
    "wof:placetype":"venue"
},
  "geometry": {"coordinates":[-89.013406,36.204498],"type":"Point"}
}