{
  "type": "Feature",
  "properties": {
    "addr:full":"7227 Winchester Rd Memphis TN 38125",
    "addr:housenumber":"7227",
    "addr:postcode":"38125",
    "addr:street":"Winchester Rd",
    "iso:country":"US",
    "sg:address":"7227 Winchester Rd",
    "sg:city":"Memphis",
    "sg:classifiers":[
        {
            "category":"Building & Trades",
            "subcategory":"Plumbing",
            "type":"Services"
        }
    ],
    "sg:phone":"+1 901 850 5454",
    "sg:postcode":"38125",
    "sg:province":"TN",
    "sg:tags":[
        "conditioning",
        "air",
        "system",
        "contractor"
    ],
    "wof:name":"Mbj Inc",
    "wof:placetype":"venue"
},
  "geometry": {"coordinates":[-89.819788,35.049347],"type":"Point"}
}