{
  "type": "Feature",
  "properties": {
    "iso:country":"US",
    "sg:address":"3300 Browns Mill Rd",
    "sg:city":"Johnson City",
    "sg:classifiers":[
        {
            "category":"Building & Trades",
            "subcategory":"Construction",
            "type":"Services"
        }
    ],
    "sg:phone":"+1 423 282 9100",
    "sg:postcode":"37604",
    "sg:province":"TN",
    "sg:tags":[
        "warehouse",
        "general",
        "for",
        "contractor"
    ],
    "wof:name":"Charles E Allen Company",
    "wof:placetype":"venue"
},
  "geometry": {"coordinates":[-82.402844,36.362204],"type":"Point"}
}