{
  "type": "Feature",
  "properties": {
    "iso:country":"US",
    "sg:address":"710 N Main St",
    "sg:city":"Columbia",
    "sg:classifiers":[
        {
            "category":"Personal",
            "subcategory":"Beauty Salon",
            "type":"Services"
        }
    ],
    "sg:phone":"+1 931 380 1504",
    "sg:postcode":"38401",
    "sg:province":"TN",
    "wof:name":"Hair Your Way",
    "wof:placetype":"venue"
},
  "geometry": {"coordinates":[-87.033585,35.6161],"type":"Point"}
}