{
  "type": "Feature",
  "properties": {
    "iso:country":"US",
    "sg:address":"44 S Front St",
    "sg:city":"Memphis",
    "sg:classifiers":[
        {
            "category":"Freight",
            "type":"Transportation"
        }
    ],
    "sg:phone":"+1 901 544 9115",
    "sg:postcode":"38103",
    "sg:province":"TN",
    "sg:tags":[
        "operator",
        "trucking"
    ],
    "wof:name":"Delta Logistics & Consulting",
    "wof:placetype":"venue"
},
  "geometry": {"coordinates":[-90.05457,35.144224],"type":"Point"}
}