{
  "type": "Feature",
  "properties": {
    "addr:full":"151 Heritage Park Dr Murfreesboro TN 37129",
    "addr:housenumber":"151",
    "addr:postcode":"37129",
    "addr:street":"Heritage Park Dr",
    "iso:country":"US",
    "sg:address":"151 Heritage Park Dr",
    "sg:city":"Murfreesboro",
    "sg:classifiers":[
        {
            "category":"Real Estate",
            "subcategory":"Real Estate Services",
            "type":"Services"
        }
    ],
    "sg:phone":"+1 615 890 1161",
    "sg:postcode":"37129",
    "sg:province":"TN",
    "sg:tags":[
        "company",
        "title"
    ],
    "wof:name":"Watauga Title Co",
    "wof:placetype":"venue"
},
  "geometry": {"coordinates":[-86.38712200000001,35.873794],"type":"Point"}
}