{
  "type": "Feature",
  "properties": {
    "iso:country":"US",
    "sg:address":"151 Heritage Park Dr",
    "sg:city":"Murfreesboro",
    "sg:classifiers":[
        {
            "category":"Real Estate",
            "subcategory":"Real Estate Services",
            "type":"Services"
        }
    ],
    "sg:phone":"+1 615 890 1161",
    "sg:postcode":"37129",
    "sg:province":"TN",
    "sg:tags":[
        "company",
        "title"
    ],
    "wof:name":"Watauga Title Co",
    "wof:placetype":"venue"
},
  "geometry": {"coordinates":[-86.38712200000001,35.873794],"type":"Point"}
}