{
  "type": "Feature",
  "properties": {
    "iso:country":"US",
    "sg:address":"4112 Bennett Rd",
    "sg:city":"Chattanooga",
    "sg:classifiers":[
        {
            "category":"Organizations",
            "subcategory":"Religious Organization",
            "type":"Services"
        }
    ],
    "sg:phone":"+1 423 867 7018",
    "sg:postcode":"37412",
    "sg:province":"TN",
    "sg:tags":[
        "church"
    ],
    "wof:name":"Bennett Road Bible Baptist Chr",
    "wof:placetype":"venue"
},
  "geometry": {"coordinates":[-85.249089,34.990104],"type":"Point"}
}