{
  "type": "Feature",
  "properties": {
    "iso:country":"US",
    "sg:address":"10402 Lexington Dr",
    "sg:city":"Knoxville",
    "sg:classifiers":[
        {
            "category":"Wholesale",
            "subcategory":"Auto Parts",
            "type":"Manufacturing & Wholesale Goods"
        }
    ],
    "sg:phone":"+1 865 777 3966",
    "sg:postcode":"37932",
    "sg:province":"TN",
    "sg:tags":[
        "automobile"
    ],
    "wof:name":"Auto Dyno",
    "wof:placetype":"venue"
},
  "geometry": {"coordinates":[-84.135701,35.910772],"type":"Point"}
}