{
  "type": "Feature",
  "properties": {
    "iso:country":"US",
    "sg:address":"1020 Sandra St",
    "sg:city":"Dyersburg",
    "sg:classifiers":[
        {
            "category":"Manufacturing",
            "subcategory":"Chemicals & Compounds",
            "type":"Manufacturing & Wholesale Goods"
        }
    ],
    "sg:phone":"+1 731 285 3032",
    "sg:postcode":"38024",
    "sg:province":"TN",
    "sg:tags":[
        "control",
        "device",
        "bug",
        "mfg"
    ],
    "wof:name":"Outdoor Assets LLC",
    "wof:placetype":"venue"
},
  "geometry": {"coordinates":[-89.421521,36.048161],"type":"Point"}
}