{
  "type": "Feature",
  "properties": {
    "iso:country":"US",
    "sg:address":"2230 Cowan Hwy",
    "sg:city":"Winchester",
    "sg:classifiers":[
        {
            "category":"Health Services",
            "subcategory":"Health Practitioner",
            "type":"Services"
        }
    ],
    "sg:phone":"+1 931 962 3433",
    "sg:postcode":"37398",
    "sg:province":"TN",
    "sg:tags":[
        "psychologist"
    ],
    "wof:name":"Winchester Sleep Ctr",
    "wof:placetype":"venue"
},
  "geometry": {"coordinates":[-86.077076,35.17321],"type":"Point"}
}