{
  "type": "Feature",
  "properties": {
    "iso:country":"US",
    "sg:address":"412 Georgia Ave",
    "sg:city":"Chattanooga",
    "sg:classifiers":[
        {
            "category":"Banks & Credit Unions",
            "subcategory":"Investment Brokerage",
            "type":"Services"
        }
    ],
    "sg:phone":"+1 423 305 7471",
    "sg:postcode":"37403",
    "sg:province":"TN",
    "sg:tags":[
        "security"
    ],
    "wof:name":"Sterne Agee And Leach",
    "wof:placetype":"venue"
},
  "geometry": {"coordinates":[-85.304675,35.052102],"type":"Point"}
}