{
  "type": "Feature",
  "properties": {
    "iso:country":"US",
    "sg:address":"103 N Shady St",
    "sg:city":"Mountain City",
    "sg:classifiers":[
        {
            "category":"Shopping",
            "subcategory":"Pharmacy",
            "type":"Retail Goods"
        }
    ],
    "sg:phone":"+1 423 727 5651",
    "sg:postcode":"37683",
    "sg:province":"TN",
    "wof:name":"Rite Aid Pharmacy",
    "wof:placetype":"venue"
},
  "geometry": {"coordinates":[-81.808705,36.476939],"type":"Point"}
}