{
  "type": "Feature",
  "properties": {
    "addr:full":"181 W Dunbar Cave Rd Clarksville TN 37040",
    "addr:housenumber":"181",
    "addr:postcode":"37040",
    "addr:street":"W Dunbar Cave Rd",
    "iso:country":"US",
    "sg:address":"181 W Dunbar Cave Rd",
    "sg:city":"Clarksville",
    "sg:classifiers":[
        {
            "category":"Wholesale",
            "subcategory":"Medical Equipment & Supplies",
            "type":"Manufacturing & Wholesale Goods"
        }
    ],
    "sg:phone":"+1 931 552 7107",
    "sg:postcode":"37040",
    "sg:province":"TN",
    "wof:name":"Enamelite LLC",
    "wof:placetype":"venue"
},
  "geometry": {"coordinates":[-87.32851700000001,36.556714],"type":"Point"}
}