{
  "type": "Feature",
  "properties": {
    "addr:full":"210 Ash St Jackson TN 38301",
    "addr:housenumber":"210",
    "addr:postcode":"38301",
    "addr:street":"Ash St",
    "iso:country":"US",
    "sg:address":"210 Ash St",
    "sg:city":"Jackson",
    "sg:classifiers":[
        {
            "category":"Organizations",
            "subcategory":"Religious Organization",
            "type":"Services"
        }
    ],
    "sg:phone":"+1 731 256 1212",
    "sg:postcode":"38301",
    "sg:province":"TN",
    "sg:tags":[
        "church"
    ],
    "wof:name":"Mt Zion Missionary Bapt Church",
    "wof:placetype":"venue"
},
  "geometry": {"coordinates":[-88.781892,35.615739],"type":"Point"}
}