{
  "type": "Feature",
  "properties": {
    "iso:country":"US",
    "sg:address":"186 McClellan Rd",
    "sg:city":"Madisonville",
    "sg:classifiers":[
        {
            "category":"Retail",
            "subcategory":"Veterinary Services",
            "type":"Services"
        },
        {
            "category":"Professional",
            "type":"Services"
        }
    ],
    "sg:phone":"+1 423 442 8599",
    "sg:postcode":"37354",
    "sg:province":"TN",
    "sg:tags":[
        "veterinarian"
    ],
    "wof:name":"Prevent A Ltter Pal Connection",
    "wof:placetype":"venue"
},
  "geometry": {"coordinates":[-84.36277800000001,35.490147],"type":"Point"}
}