{
  "type": "Feature",
  "properties": {
    "addr:full":"3830 Whites Creek Pike Nashville TN 37207",
    "addr:housenumber":"3830",
    "addr:postcode":"37207",
    "addr:street":"Whites Creek Pike",
    "iso:country":"US",
    "sg:address":"3830 Whites Creek Pike",
    "sg:city":"Nashville",
    "sg:classifiers":[
        {
            "category":"Building & Trades",
            "subcategory":"Landscaping Services",
            "type":"Services"
        }
    ],
    "sg:phone":"+1 615 256 8873",
    "sg:postcode":"37207",
    "sg:province":"TN",
    "sg:tags":[
        "landscape",
        "contractor"
    ],
    "wof:name":"Turf Scapes",
    "wof:placetype":"venue"
},
  "geometry": {"coordinates":[-86.82698000000001,36.249386],"type":"Point"}
}