{
  "type": "Feature",
  "properties": {
    "addr:full":"3537 Paragon Dr Nashville TN 37211",
    "addr:housenumber":"3537",
    "addr:postcode":"37211",
    "addr:street":"Paragon Dr",
    "iso:country":"US",
    "sg:address":"3537 Paragon Dr",
    "sg:city":"Nashville",
    "sg:classifiers":[
        {
            "category":"Shopping",
            "subcategory":"Computers & Home Electronics",
            "type":"Retail Goods"
        }
    ],
    "sg:phone":"+1 615 300 7172",
    "sg:postcode":"37211",
    "sg:province":"TN",
    "wof:name":"Little Gaming",
    "wof:placetype":"venue"
},
  "geometry": {"coordinates":[-86.707178,36.09103],"type":"Point"}
}