{
  "type": "Feature",
  "properties": {
    "addr:full":"622 Mcgavock Pike Nashville TN 37214",
    "addr:housenumber":"622",
    "addr:postcode":"37214",
    "addr:street":"Mcgavock Pike",
    "iso:country":"US",
    "sg:address":"622 Mcgavock Pike",
    "sg:city":"Nashville",
    "sg:classifiers":[
        {
            "category":"Restaurant",
            "type":"Food & Drink"
        }
    ],
    "sg:menulink":"http://www.allmenus.com/tn/nashville/177843-jack-in-the-box/menu/",
    "sg:phone":"+1 615 232 9411",
    "sg:postcode":"37214",
    "sg:province":"TN",
    "sg:tags":[
        "burger",
        "american"
    ],
    "wof:name":"Jack in the Box",
    "wof:placetype":"venue"
},
  "geometry": {"coordinates":[-86.682974,36.153252],"type":"Point"}
}