{
  "type": "Feature",
  "properties": {
    "iso:country":"US",
    "sg:address":"112 Jefferson Ct",
    "sg:city":"Oak Ridge",
    "sg:classifiers":[
        {
            "category":"Education",
            "subcategory":"Dance Studio",
            "type":"Public Place"
        }
    ],
    "sg:phone":"+1 865 482 4900",
    "sg:postcode":"37830",
    "sg:province":"TN",
    "sg:tags":[
        "instruction",
        "dancing"
    ],
    "wof:name":"Oak Ridge Academy of Dance",
    "wof:placetype":"venue"
},
  "geometry": {"coordinates":[-84.283796,36.008962],"type":"Point"}
}