{
  "type": "Feature",
  "properties": {
    "addr:full":"2422 Crestpark Rd Knoxville TN 37912",
    "addr:housenumber":"2422",
    "addr:postcode":"37912",
    "addr:street":"Crestpark Rd",
    "iso:country":"US",
    "sg:address":"2422 Crestpark Rd",
    "sg:city":"Knoxville",
    "sg:classifiers":[
        {
            "category":"Shopping",
            "type":"Retail Goods"
        }
    ],
    "sg:phone":"+1 865 329 3061",
    "sg:postcode":"37912",
    "sg:province":"TN",
    "sg:tags":[
        "merchandise"
    ],
    "wof:name":"Predator Custom Shop",
    "wof:placetype":"venue"
},
  "geometry": {"coordinates":[-84.010943,35.998957],"type":"Point"}
}