{
  "type": "Feature",
  "properties": {
    "iso:country":"US",
    "sg:address":"1700 6th St NE",
    "sg:city":"Cleveland",
    "sg:classifiers":[
        {
            "category":"Government",
            "subcategory":"Office",
            "type":"Public Place"
        }
    ],
    "sg:phone":"+1 423 478 0340",
    "sg:postcode":"37311",
    "sg:province":"TN",
    "sg:tags":[
        "transportation"
    ],
    "wof:name":"Transportation Tennessee Dept",
    "wof:placetype":"venue"
},
  "geometry": {"coordinates":[-84.851044,35.153221],"type":"Point"}
}