{
  "type": "Feature",
  "properties": {
    "iso:country":"US",
    "sg:address":"10 Market St",
    "sg:city":"Chattanooga",
    "sg:classifiers":[
        {
            "category":"Restaurant",
            "type":"Food & Drink"
        }
    ],
    "sg:phone":"+1 423 267 5259",
    "sg:postcode":"37402",
    "sg:province":"TN",
    "sg:tags":[
        "eating"
    ],
    "wof:name":"Mystic Java To Go",
    "wof:placetype":"venue"
},
  "geometry": {"coordinates":[-85.308515,35.062643],"type":"Point"}
}