{
  "type": "Feature",
  "properties": {
    "addr:full":"33 Ridgerock Dr Signal Mountain TN 37377",
    "addr:housenumber":"33",
    "addr:postcode":"37377",
    "addr:street":"Ridgerock Dr",
    "iso:country":"US",
    "sg:address":"33 Ridgerock Dr",
    "sg:city":"Signal Mountain",
    "sg:classifiers":[
        {
            "category":"Building & Trades",
            "subcategory":"Construction",
            "type":"Services"
        }
    ],
    "sg:phone":"+1 423 886 3009",
    "sg:postcode":"37377",
    "sg:province":"TN",
    "sg:tags":[
        "insulation",
        "heat",
        "contractor"
    ],
    "wof:name":"Certainteed Fiberglass",
    "wof:placetype":"venue"
},
  "geometry": {"coordinates":[-85.33068799999999,35.15226],"type":"Point"}
}