{
  "type": "Feature",
  "properties": {
    "addr:full":"4 Thomas Cir Gordonsville TN 38567",
    "addr:housenumber":"4",
    "addr:postcode":"38567",
    "addr:street":"Thomas Cir",
    "iso:country":"US",
    "sg:address":"4 Thomas Cir",
    "sg:city":"Gordonsville",
    "sg:classifiers":[
        {
            "category":"Shopping",
            "subcategory":"Used Merchandise",
            "type":"Retail Goods"
        }
    ],
    "sg:phone":"+1 615 683 6066",
    "sg:postcode":"38567",
    "sg:province":"TN",
    "sg:tags":[
        "antique"
    ],
    "wof:name":"Antique Mall Of Tn",
    "wof:placetype":"venue"
},
  "geometry": {"coordinates":[-85.94505700000001,36.140825],"type":"Point"}
}