{
  "type": "Feature",
  "properties": {
    "iso:country":"US",
    "sg:address":"176 Henry Copeland Ln",
    "sg:city":"Crawford",
    "sg:classifiers":[
        {
            "category":"Building & Trades",
            "subcategory":"Construction",
            "type":"Services"
        }
    ],
    "sg:phone":"+1 931 445 7102",
    "sg:postcode":"38554",
    "sg:province":"TN",
    "sg:tags":[
        "contractor"
    ],
    "wof:name":"Cantrell Painting",
    "wof:placetype":"venue"
},
  "geometry": {"coordinates":[-85.13913700000001,36.233935],"type":"Point"}
}