{
  "type": "Feature",
  "properties": {
    "iso:country":"US",
    "sg:address":"2325 Old Callahan Dr",
    "sg:city":"Knoxville",
    "sg:classifiers":[
        {
            "category":"Freight",
            "type":"Transportation"
        }
    ],
    "sg:phone":"+1 865 588 2606",
    "sg:postcode":"37912",
    "sg:province":"TN",
    "sg:tags":[
        "commercial",
        "storage"
    ],
    "wof:name":"A+ Ice Chalet Storage",
    "wof:placetype":"venue"
},
  "geometry": {"coordinates":[-84.02324900000001,36.00986],"type":"Point"}
}