{
  "type": "Feature",
  "properties": {
    "iso:country":"US",
    "sg:address":"1475 Parker Loop",
    "sg:city":"Henderson",
    "sg:classifiers":[
        {
            "category":"Farming",
            "subcategory":"Farm",
            "type":"Manufacturing & Wholesale Goods"
        }
    ],
    "sg:phone":"+1 731 989 9368",
    "sg:postcode":"38340",
    "sg:province":"TN",
    "sg:tags":[
        "crop",
        "general"
    ],
    "wof:name":"Allen Roark",
    "wof:placetype":"venue"
},
  "geometry": {"coordinates":[-88.729271,35.422864],"type":"Point"}
}