{
  "type": "Feature",
  "properties": {
    "iso:country":"US",
    "sg:address":"285 E G E Patterson Ave",
    "sg:city":"Memphis",
    "sg:classifiers":[
        {
            "category":"Wholesale",
            "subcategory":"Electrical",
            "type":"Manufacturing & Wholesale Goods"
        }
    ],
    "sg:phone":"+1 901 525 2348",
    "sg:postcode":"38126",
    "sg:province":"TN",
    "sg:tags":[
        "equipment",
        "electric",
        "supply"
    ],
    "sg:website":"www.twobillsupply.com",
    "wof:name":"Two Bill Supply",
    "wof:placetype":"venue"
},
  "geometry": {"coordinates":[-90.052606,35.132607],"type":"Point"}
}