{
  "type": "Feature",
  "properties": {
    "iso:country":"US",
    "sg:address":"2807 Bakertown Rd",
    "sg:city":"Knoxville",
    "sg:classifiers":[
        {
            "category":"Building & Trades",
            "subcategory":"Construction",
            "type":"Services"
        }
    ],
    "sg:phone":"+1 865 693 6349",
    "sg:postcode":"37931",
    "sg:province":"TN",
    "sg:tags":[
        "special",
        "contractor"
    ],
    "wof:name":"Quality Tile Service",
    "wof:placetype":"venue"
},
  "geometry": {"coordinates":[-84.073463,35.959631],"type":"Point"}
}