{
  "type": "Feature",
  "properties": {
    "iso:country":"US",
    "sg:address":"3736 Old Hickory Blvd",
    "sg:city":"Nashville",
    "sg:classifiers":[
        {
            "category":"Bars & Pubs",
            "type":"Food & Drink"
        }
    ],
    "sg:phone":"+1 615 356 6750",
    "sg:postcode":"37209",
    "sg:province":"TN",
    "sg:tags":[
        "drinking"
    ],
    "wof:name":"Scullys Inc",
    "wof:placetype":"venue"
},
  "geometry": {"coordinates":[-86.881111,36.139639],"type":"Point"}
}