{
  "type": "Feature",
  "properties": {
    "addr:full":"610 Bluff Rd Liberty TN 37095",
    "addr:housenumber":"610",
    "addr:postcode":"37095",
    "addr:street":"Bluff Rd",
    "iso:country":"US",
    "sg:address":"610 Bluff Rd",
    "sg:city":"Liberty",
    "sg:classifiers":[
        {
            "category":"Organizations",
            "subcategory":"Religious Organization",
            "type":"Services"
        }
    ],
    "sg:phone":"+1 615 536 5177",
    "sg:postcode":"37095",
    "sg:province":"TN",
    "sg:tags":[
        "church"
    ],
    "wof:name":"Carmelite Center-Spirituality",
    "wof:placetype":"venue"
},
  "geometry": {"coordinates":[-85.957189,36.003448],"type":"Point"}
}