{
  "type": "Feature",
  "properties": {
    "iso:country":"US",
    "sg:address":"8800 Mossy Hollow Way",
    "sg:city":"Knoxville",
    "sg:classifiers":[
        {
            "category":"Retail",
            "subcategory":"Portrait Studio",
            "type":"Services"
        }
    ],
    "sg:phone":"+1 865 692 1488",
    "sg:postcode":"37922",
    "sg:province":"TN",
    "sg:tags":[
        "photo"
    ],
    "wof:name":"American Portraits Inc",
    "wof:placetype":"venue"
},
  "geometry": {"coordinates":[-84.04276,35.858964],"type":"Point"}
}