{
  "type": "Feature",
  "properties": {
    "addr:full":"7801 Old Woodbury Pike Readyville TN 37149",
    "addr:housenumber":"7801",
    "addr:postcode":"37149",
    "addr:street":"Old Woodbury Pike",
    "iso:country":"US",
    "sg:address":"7801 Old Woodbury Pike",
    "sg:city":"Readyville",
    "sg:classifiers":[
        {
            "category":"Education",
            "subcategory":"School",
            "type":"Public Place"
        }
    ],
    "sg:phone":"+1 615 893 7604",
    "sg:postcode":"37149",
    "sg:province":"TN",
    "wof:name":"Kittrell Elementary School",
    "wof:placetype":"venue"
},
  "geometry": {"coordinates":[-86.249067,35.825181],"type":"Point"}
}