{
  "type": "Feature",
  "properties": {
    "iso:country":"US",
    "sg:address":"100 James Robertson Pkwy",
    "sg:city":"Nashville",
    "sg:classifiers":[
        {
            "category":"Government",
            "subcategory":"Office",
            "type":"Public Place"
        }
    ],
    "sg:phone":"+1 615 862 6195",
    "sg:postcode":"37201",
    "sg:province":"TN",
    "wof:name":"Davidson County JIS",
    "wof:placetype":"venue"
},
  "geometry": {"coordinates":[-86.778228,36.167747],"type":"Point"}
}