{
  "type": "Feature",
  "properties": {
    "iso:country":"US",
    "sg:address":"1330 E Main St",
    "sg:city":"Johnson City",
    "sg:classifiers":[
        {
            "category":"Building & Trades",
            "subcategory":"Construction",
            "type":"Services"
        }
    ],
    "sg:phone":"+1 423 232 0170",
    "sg:postcode":"37601",
    "sg:province":"TN",
    "sg:tags":[
        "contractor",
        "hanging"
    ],
    "wof:name":"Rodgers Enterprisers",
    "wof:placetype":"venue"
},
  "geometry": {"coordinates":[-82.331748,36.325539],"type":"Point"}
}