{
  "type": "Feature",
  "properties": {
    "addr:full":"4213 Lebanon Pike Hermitage TN 37076",
    "addr:housenumber":"4213",
    "addr:postcode":"37076",
    "addr:street":"Lebanon Pike",
    "iso:country":"US",
    "sg:address":"4213 Lebanon Pike",
    "sg:city":"Hermitage",
    "sg:classifiers":[
        {
            "category":"Home & Garden",
            "subcategory":"Building Materials",
            "type":"Retail Goods"
        },
        {
            "category":"Manufacturing",
            "subcategory":"Metals",
            "type":"Manufacturing & Wholesale Goods"
        }
    ],
    "sg:phone":"+1 615 889 8012",
    "sg:postcode":"37076",
    "sg:province":"TN",
    "sg:tags":[
        "paint",
        "coating"
    ],
    "wof:name":"PPG Porter Paints",
    "wof:placetype":"venue"
},
  "geometry": {"coordinates":[-86.614622,36.204654],"type":"Point"}
}