{
  "type": "Feature",
  "properties": {
    "iso:country":"US",
    "sg:address":"4889 Roane Rd",
    "sg:city":"Memphis",
    "sg:classifiers":[
        {
            "category":"Building & Trades",
            "subcategory":"Construction",
            "type":"Services"
        }
    ],
    "sg:phone":"+1 901 680 8200",
    "sg:postcode":"38117",
    "sg:province":"TN",
    "sg:tags":[
        "general",
        "contractor"
    ],
    "wof:name":"Catmur Development",
    "wof:placetype":"venue"
},
  "geometry": {"coordinates":[-89.897361,35.123879],"type":"Point"}
}