{
  "type": "Feature",
  "properties": {
    "addr:full":"126 Main St Ducktown TN 37326",
    "addr:housenumber":"126",
    "addr:postcode":"37326",
    "addr:street":"Main St",
    "iso:country":"US",
    "sg:address":"126 Main St",
    "sg:city":"Ducktown",
    "sg:classifiers":[
        {
            "category":"Personal",
            "subcategory":"Beauty Salon",
            "type":"Services"
        }
    ],
    "sg:phone":"+1 423 496 4002",
    "sg:postcode":"37326",
    "sg:province":"TN",
    "wof:name":"Cutting Corners",
    "wof:placetype":"venue"
},
  "geometry": {"coordinates":[-84.385595,35.030527],"type":"Point"}
}