{
  "type": "Feature",
  "properties": {
    "iso:country":"US",
    "sg:address":"266 Adams St",
    "sg:city":"Blountville",
    "sg:classifiers":[
        {
            "category":"Health Services",
            "subcategory":"Clinic",
            "type":"Services"
        }
    ],
    "sg:phone":"+1 423 323 3360",
    "sg:postcode":"37617",
    "sg:province":"TN",
    "sg:tags":[
        "other"
    ],
    "wof:name":"Tri-Cities Eldercare Assoc",
    "wof:placetype":"venue"
},
  "geometry": {"coordinates":[-82.392381,36.543294],"type":"Point"}
}