{
  "type": "Feature",
  "properties": {
    "addr:full":"108 Center Pointe Dr Clarksville TN 37040",
    "addr:housenumber":"108",
    "addr:postcode":"37040",
    "addr:street":"Pointe Dr",
    "iso:country":"US",
    "sg:address":"108 Center Pointe Dr",
    "sg:city":"Clarksville",
    "sg:classifiers":[
        {
            "category":"Government",
            "subcategory":"Office",
            "type":"Public Place"
        }
    ],
    "sg:phone":"+1 931 647 5381",
    "sg:postcode":"37040",
    "sg:province":"TN",
    "sg:tags":[
        "program",
        "administrative"
    ],
    "wof:name":"Social Security Administration",
    "wof:placetype":"venue"
},
  "geometry": {"coordinates":[-87.308893,36.569666],"type":"Point"}
}