{
  "type": "Feature",
  "properties": {
    "iso:country":"US",
    "sg:address":"292 Elders Row Dr",
    "sg:city":"Memphis",
    "sg:phone":"+1 901 528 9090",
    "sg:postcode":"38126",
    "sg:province":"TN",
    "wof:name":"Owens Place Apartments",
    "wof:placetype":"venue"
},
  "geometry": {"coordinates":[-90.05271999999999,35.136305],"type":"Point"}
}