{
  "type": "Feature",
  "properties": {
    "iso:country":"US",
    "sg:address":"2105 W Van Hook St",
    "sg:city":"Milan",
    "sg:classifiers":[
        {
            "category":"Building & Trades",
            "subcategory":"Construction",
            "type":"Services"
        }
    ],
    "sg:phone":"+1 731 686 3966",
    "sg:postcode":"38358",
    "sg:province":"TN",
    "sg:tags":[
        "contractor"
    ],
    "wof:name":"Ornamental Iron & Siding",
    "wof:placetype":"venue"
},
  "geometry": {"coordinates":[-88.759152,35.912565],"type":"Point"}
}