{
  "type": "Feature",
  "properties": {
    "iso:country":"US",
    "sg:address":"250 W Spring St",
    "sg:city":"Cookeville",
    "sg:classifiers":[
        {
            "category":"Restaurant",
            "type":"Food & Drink"
        }
    ],
    "sg:menulink":"http://www.allmenus.com/tn/cookeville/215013-burger-king/menu/",
    "sg:phone":"+1 931 526 9677",
    "sg:postcode":"38501",
    "sg:province":"TN",
    "sg:tags":[
        "burger",
        "american"
    ],
    "wof:name":"Burger King",
    "wof:placetype":"venue"
},
  "geometry": {"coordinates":[-85.512123,36.161674],"type":"Point"}
}