{
  "type": "Feature",
  "properties": {
    "addr:full":"453 McDermitt Rd Memphis TN 38120",
    "addr:housenumber":"453",
    "addr:postcode":"38120",
    "addr:street":"Mcdermitt Rd",
    "iso:country":"US",
    "sg:address":"453 McDermitt Rd",
    "sg:city":"Memphis",
    "sg:classifiers":[
        {
            "category":"Professional",
            "type":"Services"
        }
    ],
    "sg:phone":"+1 901 682 1571",
    "sg:postcode":"38120",
    "sg:province":"TN",
    "wof:name":"Billy C Burt",
    "wof:placetype":"venue"
},
  "geometry": {"coordinates":[-89.88042900000001,35.141637],"type":"Point"}
}