{
  "type": "Feature",
  "properties": {
    "iso:country":"US",
    "sg:address":"301 Germantown Bend Cove",
    "sg:city":"Cordova",
    "sg:classifiers":[
        {
            "category":"Health Services",
            "subcategory":"Clinic",
            "type":"Services"
        }
    ],
    "sg:phone":"+1 901 752 0095",
    "sg:postcode":"38018",
    "sg:province":"TN",
    "sg:tags":[
        "home",
        "care"
    ],
    "wof:name":"Cumberland Medical Supply",
    "wof:placetype":"venue"
},
  "geometry": {"coordinates":[-89.798536,35.123091],"type":"Point"}
}