{
  "type": "Feature",
  "properties": {
    "iso:country":"US",
    "sg:address":"2753 E Center St",
    "sg:city":"Kingsport",
    "sg:classifiers":[
        {
            "category":"Personal",
            "subcategory":"Beauty Salon",
            "type":"Services"
        }
    ],
    "sg:phone":"+1 423 246 4071",
    "sg:postcode":"37664",
    "sg:province":"TN",
    "sg:tags":[
        "shop"
    ],
    "wof:name":"Kingsport Beauty School",
    "wof:placetype":"venue"
},
  "geometry": {"coordinates":[-82.515843,36.533809],"type":"Point"}
}