{
  "type": "Feature",
  "properties": {
    "addr:full":"2010 25th Ave N Nashville TN 37208",
    "addr:housenumber":"2010",
    "addr:postcode":"37208",
    "addr:street":"25Th Ave N",
    "iso:country":"US",
    "sg:address":"2010 25th Ave N",
    "sg:city":"Nashville",
    "sg:classifiers":[
        {
            "category":"Organizations",
            "subcategory":"Religious Organization",
            "type":"Services"
        }
    ],
    "sg:phone":"+1 615 256 5442",
    "sg:postcode":"37208",
    "sg:province":"TN",
    "sg:tags":[
        "place",
        "worship",
        "church"
    ],
    "sg:website":"http://www.adventist.org",
    "wof:name":"Hillcrest Seventh Day Adventist Church",
    "wof:placetype":"venue"
},
  "geometry": {"coordinates":[-86.817483,36.183229],"type":"Point"}
}