{
  "type": "Feature",
  "properties": {
    "iso:country":"US",
    "sg:address":"1124 Cook Dr SW",
    "sg:city":"Knoxville",
    "sg:classifiers":[
        {
            "category":"Organizations",
            "subcategory":"Religious Organization",
            "type":"Services"
        }
    ],
    "sg:phone":"+1 865 577 5555",
    "sg:postcode":"37920",
    "sg:province":"TN",
    "wof:name":"Montgomery Villages Ministries",
    "wof:placetype":"venue"
},
  "geometry": {"coordinates":[-83.922112,35.922543],"type":"Point"}
}