{
  "type": "Feature",
  "properties": {
    "iso:country":"US",
    "sg:address":"330 Circle Dr",
    "sg:city":"Baxter",
    "sg:classifiers":[
        {
            "category":"Personal",
            "subcategory":"Beauty Salon",
            "type":"Services"
        }
    ],
    "sg:phone":"+1 931 858 5504",
    "sg:postcode":"38544",
    "sg:province":"TN",
    "sg:tags":[
        "shop"
    ],
    "wof:name":"Grandeur Hair Designs",
    "wof:placetype":"venue"
},
  "geometry": {"coordinates":[-85.637422,36.149592],"type":"Point"}
}