{
  "type": "Feature",
  "properties": {
    "iso:country":"US",
    "sg:address":"3818 Cleghorn Ave",
    "sg:city":"Nashville",
    "sg:classifiers":[
        {
            "category":"Banks & Credit Unions",
            "subcategory":"Bank",
            "type":"Services"
        }
    ],
    "sg:phone":"+1 615 383 5876",
    "sg:postcode":"37215",
    "sg:province":"TN",
    "sg:tags":[
        "loan"
    ],
    "wof:name":"Twin Equity Partners LLC",
    "wof:placetype":"venue"
},
  "geometry": {"coordinates":[-86.819367,36.107094],"type":"Point"}
}