{
  "type": "Feature",
  "properties": {
    "iso:country":"US",
    "sg:address":"3213 Maryville Pike",
    "sg:city":"Knoxville",
    "sg:classifiers":[
        {
            "category":"Wholesale",
            "subcategory":"Auto Parts",
            "type":"Manufacturing & Wholesale Goods"
        }
    ],
    "sg:phone":"+1 865 573 5823",
    "sg:postcode":"37920",
    "sg:province":"TN",
    "sg:tags":[
        "automotive"
    ],
    "wof:name":"Patricks Service Center",
    "wof:placetype":"venue"
},
  "geometry": {"coordinates":[-83.937744,35.884362],"type":"Point"}
}