{
  "type": "Feature",
  "properties": {
    "addr:full":"2257 Kirby Rd Memphis TN 38119",
    "addr:housenumber":"2257",
    "addr:postcode":"38119",
    "addr:street":"Kirby Rd",
    "iso:country":"US",
    "sg:address":"2257 Kirby Rd",
    "sg:city":"Memphis",
    "sg:classifiers":[
        {
            "category":"Building & Trades",
            "subcategory":"Construction",
            "type":"Services"
        }
    ],
    "sg:phone":"+1 901 683 0353",
    "sg:postcode":"38119",
    "sg:province":"TN",
    "wof:name":"Jonathon William Company",
    "wof:placetype":"venue"
},
  "geometry": {"coordinates":[-89.845761,35.088078],"type":"Point"}
}