{
  "type": "Feature",
  "properties": {
    "iso:country":"US",
    "sg:address":"5015 US Hwy 411",
    "sg:city":"Benton",
    "sg:classifiers":[
        {
            "category":"Banks & Credit Unions",
            "subcategory":"Bank",
            "type":"Services"
        }
    ],
    "sg:phone":"+1 423 338 1065",
    "sg:postcode":"37307",
    "sg:province":"TN",
    "sg:tags":[
        "cashing",
        "check"
    ],
    "wof:name":"Global Cash Advance",
    "wof:placetype":"venue"
},
  "geometry": {"coordinates":[-84.701238,35.16093],"type":"Point"}
}