{
  "type": "Feature",
  "properties": {
    "addr:full":"108 David Collins Dr Smyrna TN 37167",
    "addr:housenumber":"108",
    "addr:postcode":"37167",
    "addr:street":"David Collins Dr",
    "iso:country":"US",
    "sg:address":"108 David Collins Dr",
    "sg:city":"Smyrna",
    "sg:classifiers":[
        {
            "category":"Government",
            "subcategory":"Office",
            "type":"Public Place"
        }
    ],
    "sg:phone":"+1 615 355 6175",
    "sg:postcode":"37167",
    "sg:province":"TN",
    "wof:name":"Rutherford County North Health",
    "wof:placetype":"venue"
},
  "geometry": {"coordinates":[-86.523515,35.982739],"type":"Point"}
}