{
  "type": "Feature",
  "properties": {
    "iso:country":"US",
    "sg:address":"184 Old Shackle Island Rd",
    "sg:city":"Hendersonville",
    "sg:classifiers":[
        {
            "category":"Retail",
            "subcategory":"Auto Repair",
            "type":"Services"
        }
    ],
    "sg:phone":"+1 615 338 0335",
    "sg:postcode":"37075",
    "sg:province":"TN",
    "sg:tags":[
        "repairing",
        "automobile"
    ],
    "wof:name":"Larry's Automotive Paint & Rpr",
    "wof:placetype":"venue"
},
  "geometry": {"coordinates":[-86.619438,36.311035],"type":"Point"}
}