{
  "type": "Feature",
  "properties": {
    "iso:country":"US",
    "sg:address":"2026 Jordan Dr",
    "sg:city":"Nashville",
    "sg:classifiers":[
        {
            "category":"Professional",
            "subcategory":"Business Services",
            "type":"Services"
        }
    ],
    "sg:phone":"+1 615 593 6623",
    "sg:postcode":"37218",
    "sg:province":"TN",
    "sg:tags":[
        "interior",
        "consultant",
        "design",
        "decorator"
    ],
    "wof:name":"FTH Design",
    "wof:placetype":"venue"
},
  "geometry": {"coordinates":[-86.846175,36.204096],"type":"Point"}
}