{
  "type": "Feature",
  "properties": {
    "addr:full":"1603 Carmack Blvd Columbia TN 38401",
    "addr:housenumber":"1603",
    "addr:postcode":"38401",
    "addr:street":"Carmack Blvd",
    "iso:country":"US",
    "sg:address":"1603 Carmack Blvd",
    "sg:city":"Columbia",
    "sg:classifiers":[
        {
            "category":"Insurance",
            "subcategory":"Insurance Agent",
            "type":"Services"
        }
    ],
    "sg:phone":"+1 931 388 2009",
    "sg:postcode":"38401",
    "sg:province":"TN",
    "wof:name":"Shelter Insurance",
    "wof:placetype":"venue"
},
  "geometry": {"coordinates":[-87.03598100000001,35.601743],"type":"Point"}
}