{
  "type": "Feature",
  "properties": {
    "iso:country":"US",
    "sg:address":"516 Patriot Dr",
    "sg:city":"Dandridge",
    "sg:classifiers":[
        {
            "category":"Food & Beverages",
            "subcategory":"Groceries & Convenience Stores",
            "type":"Retail Goods"
        }
    ],
    "sg:phone":"+1 865 397 9386",
    "sg:postcode":"37725",
    "sg:province":"TN",
    "sg:tags":[
        "station",
        "gasoline"
    ],
    "wof:name":"40 Top Flite",
    "wof:placetype":"venue"
},
  "geometry": {"coordinates":[-83.44426799999999,36.039194],"type":"Point"}
}