{
  "type": "Feature",
  "properties": {
    "iso:country":"US",
    "sg:address":"415 Rosedale Ave",
    "sg:city":"Jamestown",
    "sg:classifiers":[
        {
            "category":"Professional",
            "subcategory":"Business Services",
            "type":"Services"
        }
    ],
    "sg:phone":"+1 931 879 7629",
    "sg:postcode":"38556",
    "sg:province":"TN",
    "wof:name":"Pine Haven Community Center",
    "wof:placetype":"venue"
},
  "geometry": {"coordinates":[-84.923907,36.428656],"type":"Point"}
}