{
  "type": "Feature",
  "properties": {
    "iso:country":"US",
    "sg:address":"1605 W Reelfoot Ave",
    "sg:city":"Union City",
    "sg:classifiers":[
        {
            "category":"Local Transit",
            "type":"Transportation"
        }
    ],
    "sg:phone":"+1 731 884 0196",
    "sg:postcode":"38261",
    "sg:province":"TN",
    "sg:tags":[
        "bus",
        "line"
    ],
    "wof:name":"Greyhound",
    "wof:placetype":"venue"
},
  "geometry": {"coordinates":[-89.07772199999999,36.412589],"type":"Point"}
}