{
  "type": "Feature",
  "properties": {
    "iso:country":"US",
    "sg:address":"10 Netherwood Dr",
    "sg:city":"Jackson",
    "sg:classifiers":[
        {
            "category":"Professional",
            "type":"Services"
        }
    ],
    "sg:phone":"+1 731 668 7220",
    "sg:postcode":"38305",
    "sg:province":"TN",
    "wof:name":"William M Grissom",
    "wof:placetype":"venue"
},
  "geometry": {"coordinates":[-88.832506,35.720746],"type":"Point"}
}