{
  "type": "Feature",
  "properties": {
    "iso:country":"US",
    "sg:address":"2200 Hamilton Place Blvd",
    "sg:city":"Chattanooga",
    "sg:classifiers":[
        {
            "category":"Home & Garden",
            "subcategory":"Home Furnishings",
            "type":"Retail Goods"
        }
    ],
    "sg:phone":"+1 423 485 8901",
    "sg:postcode":"37421",
    "sg:province":"TN",
    "sg:tags":[
        "miscellaneous",
        "store"
    ],
    "wof:name":"Castle Susan M",
    "wof:placetype":"venue"
},
  "geometry": {"coordinates":[-85.15577999999999,35.039408],"type":"Point"}
}