{
  "type": "Feature",
  "properties": {
    "iso:country":"US",
    "sg:address":"140 Cord Dr",
    "sg:city":"Columbia",
    "sg:classifiers":[
        {
            "category":"Social Services",
            "type":"Services"
        }
    ],
    "sg:phone":"+1 931 381 9959",
    "sg:postcode":"38401",
    "sg:province":"TN",
    "sg:tags":[
        "youth",
        "organization",
        "center"
    ],
    "wof:name":"Columbia National Little Lg",
    "wof:placetype":"venue"
},
  "geometry": {"coordinates":[-87.049598,35.586434],"type":"Point"}
}