{
  "type": "Feature",
  "properties": {
    "iso:country":"US",
    "sg:address":"433 E Elk Ave",
    "sg:city":"Elizabethton",
    "sg:classifiers":[
        {
            "category":"Personal",
            "type":"Services"
        }
    ],
    "sg:phone":"+1 423 542 6227",
    "sg:postcode":"37643",
    "sg:province":"TN",
    "sg:tags":[
        "wear",
        "formal"
    ],
    "wof:name":"Dynasty Rent A Gown & Tux",
    "wof:placetype":"venue"
},
  "geometry": {"coordinates":[-82.217679,36.347592],"type":"Point"}
}