{
  "type": "Feature",
  "properties": {
    "addr:full":"5536 Hillview Dr Brentwood TN 37027",
    "addr:housenumber":"5536",
    "addr:postcode":"37027",
    "addr:street":"Hillview Dr",
    "iso:country":"US",
    "sg:address":"5536 Hillview Dr",
    "sg:city":"Brentwood",
    "sg:classifiers":[
        {
            "category":"Professional",
            "subcategory":"Business Services",
            "type":"Services"
        },
        {
            "category":"Banks & Credit Unions",
            "subcategory":"Financial Services",
            "type":"Services"
        }
    ],
    "sg:phone":"+1 615 661 8515",
    "sg:postcode":"37027",
    "sg:province":"TN",
    "sg:tags":[
        "motion",
        "production",
        "copywriter"
    ],
    "wof:name":"Schreibman Creative Service",
    "wof:placetype":"venue"
},
  "geometry": {"coordinates":[-86.791693,36.043217],"type":"Point"}
}