{
  "type": "Feature",
  "properties": {
    "addr:full":"5004 Merlin Ct Columbia TN 38401",
    "addr:housenumber":"5004",
    "addr:postcode":"38401",
    "addr:street":"Merlin Ct",
    "iso:country":"US",
    "sg:address":"5004 Merlin Ct",
    "sg:city":"Columbia",
    "sg:classifiers":[
        {
            "category":"Home & Garden",
            "subcategory":"Building Materials",
            "type":"Retail Goods"
        }
    ],
    "sg:phone":"+1 931 388 2362",
    "sg:postcode":"38401",
    "sg:province":"TN",
    "sg:tags":[
        "supply"
    ],
    "wof:name":"Marshall County Bldg Ctr Inc",
    "wof:placetype":"venue"
},
  "geometry": {"coordinates":[-87.09658,35.586228],"type":"Point"}
}