{
  "type": "Feature",
  "properties": {
    "addr:full":"718 6th Ave S Nashville TN 37203",
    "addr:housenumber":"718",
    "addr:postcode":"37203",
    "addr:street":"6Th Ave S",
    "iso:country":"US",
    "sg:address":"718 6th Ave S",
    "sg:city":"Nashville",
    "sg:classifiers":[
        {
            "category":"Shopping",
            "subcategory":"Gifts & Souvenirs",
            "type":"Retail Goods"
        }
    ],
    "sg:phone":"+1 615 891 7913",
    "sg:postcode":"37203",
    "sg:province":"TN",
    "sg:tags":[
        "shop"
    ],
    "wof:name":"Legends Gifts",
    "wof:placetype":"venue"
},
  "geometry": {"coordinates":[-86.774743,36.151964],"type":"Point"}
}