{
  "type": "Feature",
  "properties": {
    "addr:full":"292 Mysen Dr Cordova TN 38018",
    "addr:housenumber":"292",
    "addr:postcode":"38018",
    "addr:street":"Mysen Dr",
    "iso:country":"US",
    "sg:address":"292 Mysen Dr",
    "sg:city":"Cordova",
    "sg:classifiers":[
        {
            "category":"Wholesale",
            "subcategory":"Machinery & Supplies",
            "type":"Manufacturing & Wholesale Goods"
        }
    ],
    "sg:phone":"+1 901 581 1189",
    "sg:postcode":"38018",
    "sg:province":"TN",
    "sg:tags":[
        "consultant",
        "industrial"
    ],
    "wof:name":"Agu International Inc",
    "wof:placetype":"venue"
},
  "geometry": {"coordinates":[-89.776687,35.121344],"type":"Point"}
}