{
  "type": "Feature",
  "properties": {
    "addr:full":"507 Stonewall St Memphis TN 38112",
    "addr:housenumber":"507",
    "addr:postcode":"38112",
    "addr:street":"Stonewall St",
    "iso:country":"US",
    "sg:address":"507 Stonewall St",
    "sg:city":"Memphis",
    "sg:classifiers":[
        {
            "category":"Communications",
            "subcategory":"Film & Video Production",
            "type":"Services"
        }
    ],
    "sg:phone":"+1 901 725 1928",
    "sg:postcode":"38112",
    "sg:province":"TN",
    "sg:tags":[
        "motion",
        "picture"
    ],
    "wof:name":"Donna Giles",
    "wof:placetype":"venue"
},
  "geometry": {"coordinates":[-90.009237,35.151936],"type":"Point"}
}