{
  "type": "Feature",
  "properties": {
    "iso:country":"US",
    "sg:address":"3540 Hickory Hill Rd",
    "sg:city":"Memphis",
    "sg:classifiers":[
        {
            "category":"Shopping",
            "subcategory":"Used Merchandise",
            "type":"Retail Goods"
        }
    ],
    "sg:phone":"+1 901 565 7755",
    "sg:postcode":"38115",
    "sg:province":"TN",
    "sg:tags":[
        "clothing"
    ],
    "wof:name":"Encore",
    "wof:placetype":"venue"
},
  "geometry": {"coordinates":[-89.866153,35.05222],"type":"Point"}
}