{
  "type": "Feature",
  "properties": {
    "addr:full":"5306 Pittman Center Rd Sevierville TN 37876",
    "addr:postcode":"5306;37876",
    "addr:street":"Center Rd",
    "iso:country":"US",
    "sg:address":"5306 Pittman Center Rd",
    "sg:city":"Sevierville",
    "sg:classifiers":[
        {
            "category":"Travel",
            "subcategory":"Hotels & Motels",
            "type":"Entertainment"
        }
    ],
    "sg:phone":"+1 865 436 9496",
    "sg:postcode":"37876",
    "sg:province":"TN",
    "sg:tags":[
        "operation"
    ],
    "wof:name":"Riverside Rentals",
    "wof:placetype":"venue"
},
  "geometry": {"coordinates":[-83.414244,35.748238],"type":"Point"}
}