{
  "type": "Feature",
  "properties": {
    "addr:full":"3105 Miser Station Rd Louisville TN 37777",
    "addr:housenumber":"3105",
    "addr:postcode":"37777",
    "addr:street":"Miser Station Rd",
    "iso:country":"US",
    "sg:address":"3105 Miser Station Rd",
    "sg:city":"Louisville",
    "sg:classifiers":[
        {
            "category":"Education",
            "subcategory":"School",
            "type":"Public Place"
        }
    ],
    "sg:phone":"+1 865 983 6644",
    "sg:postcode":"37777",
    "sg:province":"TN",
    "sg:website":"www.blountk12.org",
    "wof:name":"Middle Settlements Elementary",
    "wof:placetype":"venue"
},
  "geometry": {"coordinates":[-84.036574,35.801647],"type":"Point"}
}