{
  "type": "Feature",
  "properties": {
    "iso:country":"US",
    "sg:address":"707 Youngs Ln",
    "sg:city":"Nashville",
    "sg:classifiers":[
        {
            "category":"Health Services",
            "subcategory":"Doctor",
            "type":"Services"
        }
    ],
    "sg:phone":"+1 615 228 3452",
    "sg:postcode":"37207",
    "sg:province":"TN",
    "sg:tags":[
        "medical"
    ],
    "wof:name":"Dixon Gardner L MD",
    "wof:placetype":"venue"
},
  "geometry": {"coordinates":[-86.797577,36.204689],"type":"Point"}
}