{
  "type": "Feature",
  "properties": {
    "iso:country":"US",
    "sg:address":"116 Patricia Pl",
    "sg:city":"Cleveland",
    "sg:classifiers":[
        {
            "category":"Professional",
            "type":"Services"
        }
    ],
    "sg:phone":"+1 423 728 5759",
    "sg:postcode":"37312",
    "sg:province":"TN",
    "wof:name":"Emilian Inc",
    "wof:placetype":"venue"
},
  "geometry": {"coordinates":[-84.815113,35.220737],"type":"Point"}
}