{
  "type": "Feature",
  "properties": {
    "iso:country":"US",
    "sg:address":"205 Summit St",
    "sg:city":"Sweetwater",
    "sg:classifiers":[
        {
            "category":"Health Services",
            "subcategory":"Doctor",
            "type":"Services"
        }
    ],
    "sg:phone":"+1 423 351 7000",
    "sg:postcode":"37874",
    "sg:province":"TN",
    "sg:tags":[
        "physician",
        "medical",
        "surgeon"
    ],
    "wof:name":"Sweetwater Family Medicine",
    "wof:placetype":"venue"
},
  "geometry": {"coordinates":[-84.465147,35.601427],"type":"Point"}
}