{
  "type": "Feature",
  "properties": {
    "addr:full":"605 Congress Pkwy NW Athens TN 37303",
    "addr:housenumber":"605",
    "addr:postcode":"37303",
    "addr:street":"Congress Pkwy Nw",
    "iso:country":"US",
    "sg:address":"605 Congress Pkwy NW",
    "sg:city":"Athens",
    "sg:classifiers":[
        {
            "category":"Health Services",
            "subcategory":"Doctor",
            "type":"Services"
        }
    ],
    "sg:phone":"+1 423 745 2727",
    "sg:postcode":"37303",
    "sg:province":"TN",
    "sg:tags":[
        "dentist"
    ],
    "wof:name":"Parkway Dentistry",
    "wof:placetype":"venue"
},
  "geometry": {"coordinates":[-84.61342999999999,35.460411],"type":"Point"}
}