{
  "type": "Feature",
  "properties": {
    "addr:full":"401 Irvine St Paris TN 38242",
    "addr:housenumber":"401",
    "addr:postcode":"38242",
    "addr:street":"Irvine St",
    "iso:country":"US",
    "sg:address":"401 Irvine St",
    "sg:city":"Paris",
    "sg:classifiers":[
        {
            "category":"Organizations",
            "subcategory":"Religious Organization",
            "type":"Services"
        }
    ],
    "sg:phone":"+1 731 642 5917",
    "sg:postcode":"38242",
    "sg:province":"TN",
    "sg:tags":[
        "church"
    ],
    "wof:name":"Paris West Baptist Church",
    "wof:placetype":"venue"
},
  "geometry": {"coordinates":[-88.336839,36.300663],"type":"Point"}
}