{
  "type": "Feature",
  "properties": {
    "addr:full":"511 Union St Nashville TN 37201",
    "addr:housenumber":"511",
    "addr:postcode":"37201",
    "addr:street":"Union St",
    "iso:country":"US",
    "sg:address":"511 Union St",
    "sg:city":"Nashville",
    "sg:classifiers":[
        {
            "category":"Banks & Credit Unions",
            "subcategory":"Investment Brokerage",
            "type":"Services"
        }
    ],
    "sg:phone":"+1 615 251 0600",
    "sg:postcode":"37201",
    "sg:province":"TN",
    "sg:tags":[
        "security"
    ],
    "wof:name":"UBS Financial Services Inc",
    "wof:placetype":"venue"
},
  "geometry": {"coordinates":[-86.78154000000001,36.164239],"type":"Point"}
}