{
  "type": "Feature",
  "properties": {
    "iso:country":"US",
    "sg:address":"1008 Columbia Ave",
    "sg:city":"Franklin",
    "sg:classifiers":[
        {
            "category":"Restaurant",
            "type":"Food & Drink"
        }
    ],
    "sg:phone":"+1 615 591 6769",
    "sg:postcode":"37064",
    "sg:province":"TN",
    "sg:tags":[
        "eating"
    ],
    "wof:name":"La Superior",
    "wof:placetype":"venue"
},
  "geometry": {"coordinates":[-86.87287499999999,35.91896],"type":"Point"}
}