{
  "type": "Feature",
  "properties": {
    "iso:country":"US",
    "sg:address":"2116 Main St",
    "sg:city":"Surgoinsville",
    "sg:classifiers":[
        {
            "category":"Cinema",
            "subcategory":"Movie Rental",
            "type":"Entertainment"
        }
    ],
    "sg:phone":"+1 423 345 5081",
    "sg:postcode":"37873",
    "sg:province":"TN",
    "sg:tags":[
        "video",
        "tape"
    ],
    "wof:name":"Cliffhanger Video",
    "wof:placetype":"venue"
},
  "geometry": {"coordinates":[-82.847617,36.473523],"type":"Point"}
}