{
  "type": "Feature",
  "properties": {
    "iso:country":"US",
    "sg:address":"161 Jim Range Rd",
    "sg:city":"Jonesborough",
    "sg:classifiers":[
        {
            "category":"Health Services",
            "subcategory":"Doctor",
            "type":"Services"
        }
    ],
    "sg:phone":"+1 423 753 4080",
    "sg:postcode":"37659",
    "sg:province":"TN",
    "sg:tags":[
        "medical"
    ],
    "wof:name":"Thomas R Borthwick MD",
    "wof:placetype":"venue"
},
  "geometry": {"coordinates":[-82.437059,36.272008],"type":"Point"}
}