{
  "type": "Feature",
  "properties": {
    "iso:country":"US",
    "sg:address":"6701 Baum Dr SW",
    "sg:city":"Knoxville",
    "sg:classifiers":[
        {
            "category":"Professional",
            "subcategory":"Accounting & Tax Preparation",
            "type":"Services"
        }
    ],
    "sg:phone":"+1 865 330 7474",
    "sg:postcode":"37919",
    "sg:province":"TN",
    "sg:tags":[
        "accountant"
    ],
    "wof:name":"Addability",
    "wof:placetype":"venue"
},
  "geometry": {"coordinates":[-84.011665,35.927383],"type":"Point"}
}