{
  "type": "Feature",
  "properties": {
    "iso:country":"US",
    "sg:address":"832 Georgia Ave",
    "sg:city":"Chattanooga",
    "sg:classifiers":[
        {
            "category":"Professional",
            "subcategory":"Lawyer & Legal Services",
            "type":"Services"
        }
    ],
    "sg:phone":"+1 423 756 3456",
    "sg:postcode":"37402",
    "sg:province":"TN",
    "wof:name":"Kyle Hedrick Atty",
    "wof:placetype":"venue"
},
  "geometry": {"coordinates":[-85.30816799999999,35.045822],"type":"Point"}
}