{
  "type": "Feature",
  "properties": {
    "iso:country":"US",
    "sg:address":"102 Hammond Ave",
    "sg:city":"Lebanon",
    "sg:classifiers":[
        {
            "category":"Professional",
            "subcategory":"Advertising",
            "type":"Services"
        }
    ],
    "sg:phone":"+1 615 449 4863",
    "sg:postcode":"37087",
    "sg:province":"TN",
    "sg:tags":[
        "agency"
    ],
    "wof:name":"Lg Advertising",
    "wof:placetype":"venue"
},
  "geometry": {"coordinates":[-86.301293,36.209723],"type":"Point"}
}