{
  "type": "Feature",
  "properties": {
    "iso:country":"US",
    "sg:address":"140 W Tennessee Ave",
    "sg:city":"Oak Ridge",
    "sg:classifiers":[
        {
            "category":"Health Services",
            "subcategory":"Doctor",
            "type":"Services"
        }
    ],
    "sg:phone":"+1 865 482 1097",
    "sg:postcode":"37830",
    "sg:province":"TN",
    "wof:name":"Greer J Glenn DDS",
    "wof:placetype":"venue"
},
  "geometry": {"coordinates":[-84.24487999999999,36.025566],"type":"Point"}
}