{
  "type": "Feature",
  "properties": {
    "iso:country":"US",
    "sg:address":"1120 Litton Ave",
    "sg:city":"Nashville",
    "sg:classifiers":[
        {
            "category":"Real Estate",
            "subcategory":"Real Estate Operator",
            "type":"Services"
        }
    ],
    "sg:phone":"+1 615 228 5588",
    "sg:postcode":"37216",
    "sg:province":"TN",
    "sg:tags":[
        "building",
        "apartment"
    ],
    "wof:name":"Litton Park Apartments",
    "wof:placetype":"venue"
},
  "geometry": {"coordinates":[-86.73840300000001,36.202274],"type":"Point"}
}