{
  "type": "Feature",
  "properties": {
    "iso:country":"US",
    "sg:address":"1215 Vales Mill Rd",
    "sg:city":"Pulaski",
    "sg:classifiers":[
        {
            "category":"Building & Trades",
            "subcategory":"Plumbing",
            "type":"Services"
        }
    ],
    "sg:phone":"+1 931 363 4150",
    "sg:postcode":"38478",
    "sg:province":"TN",
    "sg:tags":[
        "conditioning",
        "air",
        "system",
        "contractor"
    ],
    "wof:name":"A-1 Heating & Cooling",
    "wof:placetype":"venue"
},
  "geometry": {"coordinates":[-87.060283,35.193059],"type":"Point"}
}