{
  "type": "Feature",
  "properties": {
    "iso:country":"US",
    "sg:address":"103 S Main St",
    "sg:city":"Dickson",
    "sg:classifiers":[
        {
            "category":"Shopping",
            "subcategory":"Used Merchandise",
            "type":"Retail Goods"
        }
    ],
    "sg:phone":"+1 615 441 3424",
    "sg:postcode":"37055",
    "sg:province":"TN",
    "wof:name":"Dots Antiques & Flea Market",
    "wof:placetype":"venue"
},
  "geometry": {"coordinates":[-87.389195,36.075619],"type":"Point"}
}