{
  "type": "Feature",
  "properties": {
    "iso:country":"US",
    "sg:address":"2107 32nd Ave S",
    "sg:city":"Nashville",
    "sg:classifiers":[
        {
            "category":"Farming",
            "subcategory":"Farm & Veterinary Services",
            "type":"Manufacturing & Wholesale Goods"
        }
    ],
    "sg:phone":"+1 615 269 5502",
    "sg:postcode":"37212",
    "sg:province":"TN",
    "sg:tags":[
        "livestock"
    ],
    "wof:name":"Wilson Pike Partners LLC",
    "wof:placetype":"venue"
},
  "geometry": {"coordinates":[-86.81475399999999,36.133545],"type":"Point"}
}