{
  "type": "Feature",
  "properties": {
    "addr:full":"116 Mavella Ct Goodlettsville TN 37072",
    "addr:housenumber":"116",
    "addr:postcode":"37072",
    "addr:street":"Mavella Ct",
    "iso:country":"US",
    "sg:address":"116 Mavella Ct",
    "sg:city":"Goodlettsville",
    "sg:classifiers":[
        {
            "category":"Professional",
            "subcategory":"Secretarial Services",
            "type":"Services"
        }
    ],
    "sg:phone":"+1 615 855 2391",
    "sg:postcode":"37072",
    "sg:province":"TN",
    "sg:tags":[
        "reporting"
    ],
    "wof:name":"Choice Business Services",
    "wof:placetype":"venue"
},
  "geometry": {"coordinates":[-86.717929,36.329035],"type":"Point"}
}