{
  "type": "Feature",
  "properties": {
    "iso:country":"US",
    "sg:address":"2816 Azalea Pl",
    "sg:city":"Nashville",
    "sg:classifiers":[
        {
            "category":"Professional",
            "subcategory":"Business Services",
            "type":"Services"
        }
    ],
    "sg:phone":"+1 615 292 3606",
    "sg:postcode":"37204",
    "sg:province":"TN",
    "sg:tags":[
        "appraiser"
    ],
    "wof:name":"Neiman-Ross Associates Inc",
    "wof:placetype":"venue"
},
  "geometry": {"coordinates":[-86.767859,36.116631],"type":"Point"}
}