{
  "type": "Feature",
  "properties": {
    "iso:country":"US",
    "sg:address":"211 Public Sq",
    "sg:city":"Lafayette",
    "sg:classifiers":[
        {
            "category":"Health Services",
            "subcategory":"Clinic",
            "type":"Services"
        }
    ],
    "sg:phone":"+1 615 666 2555",
    "sg:postcode":"37083",
    "sg:province":"TN",
    "sg:tags":[
        "agency",
        "welfare"
    ],
    "wof:name":"Home Care Solutions Inc",
    "wof:placetype":"venue"
},
  "geometry": {"coordinates":[-86.025431,36.520678],"type":"Point"}
}