{
  "type": "Feature",
  "properties": {
    "iso:country":"US",
    "sg:address":"217 Cromwell Sq N",
    "sg:city":"Brownsville",
    "sg:classifiers":[
        {
            "category":"Shopping",
            "subcategory":"Computers & Home Electronics",
            "type":"Retail Goods"
        }
    ],
    "sg:phone":"+1 731 772 3897",
    "sg:postcode":"38012",
    "sg:province":"TN",
    "sg:tags":[
        "equipment",
        "electronic",
        "supply"
    ],
    "wof:name":"Mike Electronics",
    "wof:placetype":"venue"
},
  "geometry": {"coordinates":[-89.266986,35.597298],"type":"Point"}
}