{
  "type": "Feature",
  "properties": {
    "iso:country":"US",
    "sg:address":"600 Old Hickory Blvd",
    "sg:city":"Nashville",
    "sg:classifiers":[
        {
            "category":"Professional",
            "subcategory":"Accounting & Tax Preparation",
            "type":"Services"
        }
    ],
    "sg:phone":"+1 615 353 5550",
    "sg:postcode":"37209",
    "sg:province":"TN",
    "sg:tags":[
        "return",
        "filing"
    ],
    "sg:website":"www.libertytax.com",
    "wof:name":"Liberty Tax Svc",
    "wof:placetype":"venue"
},
  "geometry": {"coordinates":[-86.922309,36.107032],"type":"Point"}
}