{
  "type": "Feature",
  "properties": {
    "iso:country":"US",
    "sg:address":"110 N Campbell Station Rd",
    "sg:city":"Knoxville",
    "sg:classifiers":[
        {
            "category":"Personal",
            "subcategory":"Hair Removal",
            "type":"Services"
        }
    ],
    "sg:phone":"+1 865 777 4774",
    "sg:postcode":"37934",
    "sg:province":"TN",
    "sg:tags":[
        "removing"
    ],
    "sg:website":"www.americanlaser.com",
    "wof:name":"American Laser Ctr",
    "wof:placetype":"venue"
},
  "geometry": {"coordinates":[-84.16051299999999,35.881508],"type":"Point"}
}