{
  "type": "Feature",
  "properties": {
    "iso:country":"US",
    "sg:address":"3383 W Lamar Alexander Pkwy",
    "sg:city":"Friendsville",
    "sg:classifiers":[
        {
            "category":"Building & Trades",
            "subcategory":"Construction",
            "type":"Services"
        }
    ],
    "sg:phone":"+1 865 380 8900",
    "sg:postcode":"37737",
    "sg:province":"TN",
    "sg:tags":[
        "sun",
        "solarium",
        "rooms"
    ],
    "wof:name":"Show Case Homes",
    "wof:placetype":"venue"
},
  "geometry": {"coordinates":[-84.1314,35.75503],"type":"Point"}
}