{
  "type": "Feature",
  "properties": {
    "addr:full":"1333 Brow Estates Dr Signal Mountain TN 37377",
    "addr:housenumber":"1333",
    "addr:postcode":"37377",
    "addr:street":"Brow Estates Dr",
    "iso:country":"US",
    "sg:address":"1333 Brow Estates Dr",
    "sg:city":"Signal Mountain",
    "sg:classifiers":[
        {
            "category":"Professional",
            "type":"Services"
        }
    ],
    "sg:phone":"+1 423 886 9933",
    "sg:postcode":"37377",
    "sg:province":"TN",
    "wof:name":"Paul H Tyner",
    "wof:placetype":"venue"
},
  "geometry": {"coordinates":[-85.32360799999999,35.138283],"type":"Point"}
}