{
  "type": "Feature",
  "properties": {
    "iso:country":"US",
    "sg:address":"5821 Ringgold Rd",
    "sg:city":"Chattanooga",
    "sg:classifiers":[
        {
            "category":"Organizations",
            "subcategory":"Religious Organization",
            "type":"Services"
        }
    ],
    "sg:phone":"+1 423 894 8656",
    "sg:postcode":"37412",
    "sg:province":"TN",
    "sg:tags":[
        "clergy"
    ],
    "wof:name":"Knight, Charles D",
    "wof:placetype":"venue"
},
  "geometry": {"coordinates":[-85.21901699999999,34.990379],"type":"Point"}
}