{
  "type": "Feature",
  "properties": {
    "iso:country":"US",
    "sg:address":"515 Orchard Ln",
    "sg:city":"Savannah",
    "sg:classifiers":[
        {
            "category":"Building & Trades",
            "subcategory":"Landscaping Services",
            "type":"Services"
        }
    ],
    "sg:phone":"+1 731 925 8215",
    "sg:postcode":"38372",
    "sg:province":"TN",
    "wof:name":"Blount Landscaping & Turf Care",
    "wof:placetype":"venue"
},
  "geometry": {"coordinates":[-88.25158399999999,35.258033],"type":"Point"}
}