{
  "type": "Feature",
  "properties": {
    "addr:full":"425 Dixon Rd Bolivar TN 38008",
    "addr:housenumber":"425",
    "addr:postcode":"38008",
    "addr:street":"Dixon Rd",
    "iso:country":"US",
    "sg:address":"425 Dixon Rd",
    "sg:city":"Bolivar",
    "sg:classifiers":[
        {
            "category":"Retail",
            "subcategory":"Auto Repair",
            "type":"Services"
        }
    ],
    "sg:phone":"+1 731 658 1960",
    "sg:postcode":"38008",
    "sg:province":"TN",
    "sg:tags":[
        "exhaust"
    ],
    "wof:name":"Jeters Mufflers & More",
    "wof:placetype":"venue"
},
  "geometry": {"coordinates":[-88.96708,35.221574],"type":"Point"}
}