{
  "type": "Feature",
  "properties": {
    "addr:full":"2315 Silverdale Dr Johnson City TN 37601",
    "addr:housenumber":"2315",
    "addr:postcode":"37601",
    "addr:street":"Silverdale Dr",
    "iso:country":"US",
    "sg:address":"2315 Silverdale Dr",
    "sg:city":"Johnson City",
    "sg:classifiers":[
        {
            "category":"Professional",
            "subcategory":"Advertising",
            "type":"Services"
        }
    ],
    "sg:phone":"+1 423 283 9400",
    "sg:postcode":"37601",
    "sg:province":"TN",
    "sg:tags":[
        "directory",
        "telephone"
    ],
    "wof:name":"L M Berry and Company",
    "wof:placetype":"venue"
},
  "geometry": {"coordinates":[-82.366873,36.352577],"type":"Point"}
}