{
  "type": "Feature",
  "properties": {
    "addr:full":"505 Page Dr Goodlettsville TN 37072",
    "addr:housenumber":"505",
    "addr:postcode":"37072",
    "addr:street":"Page Dr",
    "iso:country":"US",
    "sg:address":"505 Page Dr",
    "sg:city":"Goodlettsville",
    "sg:classifiers":[
        {
            "category":"Retail",
            "subcategory":"Auto Repair",
            "type":"Services"
        }
    ],
    "sg:phone":"+1 615 859 1198",
    "sg:postcode":"37072",
    "sg:province":"TN",
    "sg:tags":[
        "body"
    ],
    "wof:name":"J&J Services",
    "wof:placetype":"venue"
},
  "geometry": {"coordinates":[-86.690866,36.325661],"type":"Point"}
}