{
  "type": "Feature",
  "properties": {
    "addr:full":"405 Clear Branch Rd Lake City TN 37769",
    "addr:housenumber":"405",
    "addr:postcode":"37769",
    "addr:street":"Clear Branch Rd",
    "iso:country":"US",
    "sg:address":"405 Clear Branch Rd",
    "sg:city":"Lake City",
    "sg:classifiers":[
        {
            "category":"Building & Trades",
            "subcategory":"Cleaning & Sanitation",
            "type":"Services"
        }
    ],
    "sg:phone":"+1 865 426 4785",
    "sg:postcode":"37769",
    "sg:province":"TN",
    "sg:tags":[
        "maintenance"
    ],
    "wof:name":"Williams Cleaning Service",
    "wof:placetype":"venue"
},
  "geometry": {"coordinates":[-84.132437,36.18904],"type":"Point"}
}