{
  "type": "Feature",
  "properties": {
    "iso:country":"US",
    "sg:address":"6504 Orchard Rd",
    "sg:city":"Knoxville",
    "sg:classifiers":[
        {
            "category":"Wholesale",
            "subcategory":"Furniture",
            "type":"Manufacturing & Wholesale Goods"
        }
    ],
    "sg:phone":"+1 865 690 8163",
    "sg:postcode":"37919",
    "sg:province":"TN",
    "sg:tags":[
        "trade",
        "business",
        "contractor"
    ],
    "wof:name":"Commercial Interiors",
    "wof:placetype":"venue"
},
  "geometry": {"coordinates":[-84.003259,35.923733],"type":"Point"}
}