{
  "type": "Feature",
  "properties": {
    "addr:full":"2713 Mount Moriah Pkwy Memphis TN 38115",
    "addr:housenumber":"2713",
    "addr:postcode":"38115",
    "addr:street":"Mount Moriah Pkwy",
    "iso:country":"US",
    "sg:address":"2713 Mount Moriah Pkwy",
    "sg:city":"Memphis",
    "sg:classifiers":[
        {
            "category":"Shopping",
            "subcategory":"Clothing, Apparel, & Fashions",
            "type":"Retail Goods"
        }
    ],
    "sg:phone":"+1 901 363 3318",
    "sg:postcode":"38115",
    "sg:province":"TN",
    "wof:name":"Casey Charles Custom Clothiers",
    "wof:placetype":"venue"
},
  "geometry": {"coordinates":[-89.87085500000001,35.073907],"type":"Point"}
}