{
  "type": "Feature",
  "properties": {
    "iso:country":"US",
    "sg:address":"7529 Chapman Hwy",
    "sg:city":"Knoxville",
    "sg:classifiers":[
        {
            "category":"Shopping",
            "subcategory":"Bicycles & Sporting Goods",
            "type":"Retail Goods"
        }
    ],
    "sg:phone":"+1 865 579 5273",
    "sg:postcode":"37920",
    "sg:province":"TN",
    "sg:tags":[
        "repair"
    ],
    "wof:name":"Clubs & Components Golf Shop",
    "wof:placetype":"venue"
},
  "geometry": {"coordinates":[-83.839743,35.907484],"type":"Point"}
}