{
  "type": "Feature",
  "properties": {
    "addr:full":"3468 US Hwy 41 S Springfield TN 37172",
    "addr:housenumber":"3468",
    "addr:postcode":"37172",
    "addr:street":"Us Hwy 41 S",
    "iso:country":"US",
    "sg:address":"3468 US Hwy 41 S",
    "sg:city":"Springfield",
    "sg:classifiers":[
        {
            "category":"Home & Garden",
            "subcategory":"Building Materials",
            "type":"Retail Goods"
        }
    ],
    "sg:phone":"+1 615 384 4284",
    "sg:postcode":"37172",
    "sg:province":"TN",
    "sg:tags":[
        "lumber"
    ],
    "sg:website":"www.84lumber.com",
    "wof:name":"84 Lumber",
    "wof:placetype":"venue"
},
  "geometry": {"coordinates":[-86.842224,36.467922],"type":"Point"}
}