{
  "type": "Feature",
  "properties": {
    "iso:country":"US",
    "sg:address":"1735 W State of Franklin Rd",
    "sg:city":"Johnson City",
    "sg:classifiers":[
        {
            "category":"Restaurant",
            "type":"Food & Drink"
        }
    ],
    "sg:menulink":"http://www.allmenus.com/tn/johnson-city/85669-dominos-pizza/menu/",
    "sg:phone":"+1 423 929 1131",
    "sg:postcode":"37604",
    "sg:province":"TN",
    "sg:tags":[
        "american",
        "wing",
        "pizza"
    ],
    "wof:name":"Domino's Pizza",
    "wof:placetype":"venue"
},
  "geometry": {"coordinates":[-82.376616,36.301902],"type":"Point"}
}