{
  "type": "Feature",
  "properties": {
    "iso:country":"US",
    "sg:address":"4850 State Hwy 58",
    "sg:city":"Chattanooga",
    "sg:classifiers":[
        {
            "category":"Social Services",
            "type":"Services"
        }
    ],
    "sg:phone":"+1 423 894 1740",
    "sg:postcode":"37416",
    "sg:province":"TN",
    "sg:tags":[
        "organization",
        "welfare"
    ],
    "wof:name":"Chattanooga Goodwill",
    "wof:placetype":"venue"
},
  "geometry": {"coordinates":[-85.183861,35.091415],"type":"Point"}
}