{
  "type": "Feature",
  "properties": {
    "addr:full":"3389 US Hwy 41A S Clarksville TN 37043",
    "addr:housenumber":"3389",
    "addr:postcode":"37043",
    "addr:street":"Us Hwy 41A S",
    "iso:country":"US",
    "sg:address":"3389 US Hwy 41A S",
    "sg:city":"Clarksville",
    "sg:classifiers":[
        {
            "category":"Banks & Credit Unions",
            "subcategory":"Bank",
            "type":"Services"
        }
    ],
    "sg:phone":"+1 931 358 0477",
    "sg:postcode":"37043",
    "sg:province":"TN",
    "wof:name":"First Federal Savings Bank",
    "wof:placetype":"venue"
},
  "geometry": {"coordinates":[-87.22208500000001,36.496641],"type":"Point"}
}