{
  "type": "Feature",
  "properties": {
    "iso:country":"US",
    "sg:address":"3601 Lyon Springs Rd",
    "sg:city":"Sevierville",
    "sg:classifiers":[
        {
            "category":"Real Estate",
            "subcategory":"Real Estate Operator",
            "type":"Services"
        }
    ],
    "sg:phone":"+1 865 774 7511",
    "sg:postcode":"37862",
    "sg:province":"TN",
    "sg:tags":[
        "apartment"
    ],
    "wof:name":"Oak-Rise Apartment",
    "wof:placetype":"venue"
},
  "geometry": {"coordinates":[-83.64721400000001,35.698514],"type":"Point"}
}