{
  "type": "Feature",
  "properties": {
    "addr:full":"2200 Lake Ln Knoxville TN 37919",
    "addr:housenumber":"2200",
    "addr:postcode":"37919",
    "addr:street":"Lake Ln",
    "iso:country":"US",
    "sg:address":"2200 Lake Ln",
    "sg:city":"Knoxville",
    "sg:classifiers":[
        {
            "category":"Organizations",
            "subcategory":"Professional Association",
            "type":"Services"
        }
    ],
    "sg:phone":"+1 865 588 9656",
    "sg:postcode":"37919",
    "sg:province":"TN",
    "wof:name":"Duncan's Landing Homeowner's",
    "wof:placetype":"venue"
},
  "geometry": {"coordinates":[-83.989639,35.890228],"type":"Point"}
}