{
  "type": "Feature",
  "properties": {
    "iso:country":"US",
    "sg:address":"117 Old Hen Valley Rd",
    "sg:city":"Oliver Springs",
    "sg:classifiers":[
        {
            "category":"Organizations",
            "subcategory":"Religious Organization",
            "type":"Services"
        }
    ],
    "sg:phone":"+1 865 435 4820",
    "sg:postcode":"37840",
    "sg:province":"TN",
    "sg:tags":[
        "church"
    ],
    "wof:name":"Mt Pisgah Christian Acad High",
    "wof:placetype":"venue"
},
  "geometry": {"coordinates":[-84.394921,36.00614],"type":"Point"}
}