{
  "type": "Feature",
  "properties": {
    "addr:full":"112 Glenrose Ave Nashville TN 37210",
    "addr:housenumber":"112",
    "addr:postcode":"37210",
    "addr:street":"Glenrose Ave",
    "iso:country":"US",
    "sg:address":"112 Glenrose Ave",
    "sg:city":"Nashville",
    "sg:classifiers":[
        {
            "category":"Retail",
            "subcategory":"Auto Repair",
            "type":"Services"
        }
    ],
    "sg:phone":"+1 615 242 7171",
    "sg:postcode":"37210",
    "sg:province":"TN",
    "sg:tags":[
        "repairing",
        "automobile"
    ],
    "wof:name":"Complete Auto Repair & Tire",
    "wof:placetype":"venue"
},
  "geometry": {"coordinates":[-86.742013,36.125363],"type":"Point"}
}