{
  "type": "Feature",
  "properties": {
    "iso:country":"US",
    "sg:address":"4340 Elvis Presley Blvd",
    "sg:city":"Memphis",
    "sg:classifiers":[
        {
            "category":"Professional",
            "type":"Services"
        },
        {
            "category":"Personal",
            "type":"Services"
        }
    ],
    "sg:phone":"+1 901 353 2900",
    "sg:postcode":"38116",
    "sg:province":"TN",
    "sg:tags":[
        "mover",
        "material",
        "moving",
        "services-labor"
    ],
    "sg:website":"https://www.allamericanmoving.com",
    "wof:name":"All American Mayflower",
    "wof:placetype":"venue"
},
  "geometry": {"coordinates":[-90.025177,35.030025],"type":"Point"}
}