{
  "type": "Feature",
  "properties": {
    "addr:full":"206 Linda Ln Madison TN 37115",
    "addr:housenumber":"206",
    "addr:postcode":"37115",
    "addr:street":"Linda Ln",
    "iso:country":"US",
    "sg:address":"206 Linda Ln",
    "sg:city":"Madison",
    "sg:classifiers":[
        {
            "category":"Shopping",
            "subcategory":"Beauty & Cosmetics",
            "type":"Retail Goods"
        }
    ],
    "sg:phone":"+1 615 865 2250",
    "sg:postcode":"37115",
    "sg:province":"TN",
    "sg:tags":[
        "merchandise"
    ],
    "wof:name":"Williams Sandra",
    "wof:placetype":"venue"
},
  "geometry": {"coordinates":[-86.72574299999999,36.257522],"type":"Point"}
}