{
  "type": "Feature",
  "properties": {
    "iso:country":"US",
    "sg:address":"825 McCallie Ave",
    "sg:city":"Chattanooga",
    "sg:classifiers":[
        {
            "category":"Shopping",
            "type":"Retail Goods"
        }
    ],
    "sg:phone":"+1 423 267 0072",
    "sg:postcode":"37403",
    "sg:province":"TN",
    "sg:tags":[
        "art",
        "supply"
    ],
    "wof:name":"Art Accent Inc",
    "wof:placetype":"venue"
},
  "geometry": {"coordinates":[-85.293351,35.042915],"type":"Point"}
}