{
  "type": "Feature",
  "properties": {
    "addr:full":"2219 S Germantown Rd Germantown TN 38138",
    "addr:housenumber":"2219",
    "addr:postcode":"38138",
    "addr:street":"S Germantown Rd",
    "iso:country":"US",
    "sg:address":"2219 S Germantown Rd",
    "sg:city":"Germantown",
    "sg:classifiers":[
        {
            "category":"Shopping",
            "subcategory":"Clothing, Apparel, & Fashions",
            "type":"Retail Goods"
        }
    ],
    "sg:phone":"+1 901 755 4685",
    "sg:postcode":"38138",
    "sg:province":"TN",
    "sg:tags":[
        "tailor"
    ],
    "wof:name":"Perfect Fit",
    "wof:placetype":"venue"
},
  "geometry": {"coordinates":[-89.808998,35.092491],"type":"Point"}
}