{
  "type": "Feature",
  "properties": {
    "iso:country":"US",
    "sg:address":"4000 Game Reserve Rd",
    "sg:city":"Chattanooga",
    "sg:classifiers":[
        {
            "category":"Government",
            "subcategory":"Office",
            "type":"Public Place"
        }
    ],
    "sg:phone":"+1 423 658 5551",
    "sg:postcode":"37405",
    "sg:province":"TN",
    "sg:tags":[
        "government-state"
    ],
    "wof:name":"Tennessee State Government",
    "wof:placetype":"venue"
},
  "geometry": {"coordinates":[-85.451874,35.036201],"type":"Point"}
}