{
  "type": "Feature",
  "properties": {
    "addr:full":"475 Taurus Farm Rd Lafayette TN 37083",
    "addr:housenumber":"475",
    "addr:postcode":"37083",
    "addr:street":"Taurus Farm Rd",
    "iso:country":"US",
    "sg:address":"475 Taurus Farm Rd",
    "sg:city":"Lafayette",
    "sg:phone":"+1 615 666 8958",
    "sg:postcode":"37083",
    "sg:province":"TN",
    "sg:tags":[
        "hog",
        "fee",
        "tobacco",
        "beef",
        "farm",
        "cattle",
        "or",
        "feedlot"
    ],
    "wof:name":"Taurus Farms",
    "wof:placetype":"venue"
},
  "geometry": {"coordinates":[-85.929941,36.531656],"type":"Point"}
}