{
  "type": "Feature",
  "properties": {
    "addr:full":"1803 21st Ave S Nashville TN 37212",
    "addr:housenumber":"1803",
    "addr:postcode":"37212",
    "addr:street":"21St Ave S",
    "iso:country":"US",
    "sg:address":"1803 21st Ave S",
    "sg:city":"Nashville",
    "sg:classifiers":[
        {
            "category":"Bars & Pubs",
            "subcategory":"Sports Bar",
            "type":"Food & Drink"
        }
    ],
    "sg:phone":"+1 615 383 3601",
    "sg:postcode":"37212",
    "sg:province":"TN",
    "wof:name":"Sam's Sports Bar & Grill",
    "wof:placetype":"venue"
},
  "geometry": {"coordinates":[-86.800875,36.136621],"type":"Point"}
}