{
  "type": "Feature",
  "properties": {
    "iso:country":"US",
    "sg:address":"204 Twelve Oaks Rd",
    "sg:city":"Tullahoma",
    "sg:classifiers":[
        {
            "category":"Professional",
            "type":"Services"
        }
    ],
    "sg:phone":"+1 931 455 5845",
    "sg:postcode":"37388",
    "sg:province":"TN",
    "wof:name":"Wj Rymer Jr",
    "wof:placetype":"venue"
},
  "geometry": {"coordinates":[-86.201014,35.385218],"type":"Point"}
}