{
  "type": "Feature",
  "properties": {
    "iso:country":"US",
    "sg:address":"119 Nicole Ct",
    "sg:city":"Maryville",
    "sg:classifiers":[
        {
            "category":"Building & Trades",
            "subcategory":"Electrical",
            "type":"Services"
        }
    ],
    "sg:phone":"+1 865 982 9757",
    "sg:postcode":"37801",
    "sg:province":"TN",
    "wof:name":"K & S Communications",
    "wof:placetype":"venue"
},
  "geometry": {"coordinates":[-84.021541,35.71182],"type":"Point"}
}