{
  "type": "Feature",
  "properties": {
    "iso:country":"US",
    "sg:address":"1021 Foster Ave",
    "sg:city":"Nashville",
    "sg:classifiers":[
        {
            "category":"Retail",
            "subcategory":"Auto Repair",
            "type":"Services"
        }
    ],
    "sg:phone":"+1 615 251 3005",
    "sg:postcode":"37210",
    "sg:province":"TN",
    "sg:tags":[
        "repairing",
        "automobile"
    ],
    "wof:name":"T & M Steering Column Repair",
    "wof:placetype":"venue"
},
  "geometry": {"coordinates":[-86.740859,36.139988],"type":"Point"}
}