{
  "type": "Feature",
  "properties": {
    "iso:country":"US",
    "sg:address":"1226 Armstrong Ave NE",
    "sg:city":"Knoxville",
    "sg:classifiers":[
        {
            "category":"Social Services",
            "subcategory":"Child Care",
            "type":"Services"
        }
    ],
    "sg:phone":"+1 865 524 0371",
    "sg:postcode":"37917",
    "sg:province":"TN",
    "sg:tags":[
        "kindergarten",
        "academic",
        "school"
    ],
    "wof:name":"First Lutheran School",
    "wof:placetype":"venue"
},
  "geometry": {"coordinates":[-83.923376,35.984989],"type":"Point"}
}