{
  "type": "Feature",
  "properties": {
    "addr:full":"1849 Azrock Dr Knoxville TN 37914",
    "addr:housenumber":"1849",
    "addr:postcode":"37914",
    "addr:street":"Azrock Dr",
    "iso:country":"US",
    "sg:address":"1849 Azrock Dr",
    "sg:city":"Knoxville",
    "sg:classifiers":[
        {
            "category":"Freight",
            "type":"Transportation"
        },
        {
            "category":"Taxi",
            "type":"Transportation"
        }
    ],
    "sg:phone":"+1 865 673 6736",
    "sg:postcode":"37914",
    "sg:province":"TN",
    "sg:tags":[
        "taxicab"
    ],
    "wof:name":"Selig Transport Systems LLC",
    "wof:placetype":"venue"
},
  "geometry": {"coordinates":[-83.853244,35.986758],"type":"Point"}
}