{
  "type": "Feature",
  "properties": {
    "addr:full":"721 Kleeman Dr Clarksville TN 37040",
    "addr:housenumber":"721",
    "addr:postcode":"37040",
    "addr:street":"Kleeman Dr",
    "iso:country":"US",
    "sg:address":"721 Kleeman Dr",
    "sg:city":"Clarksville",
    "sg:classifiers":[
        {
            "category":"Professional",
            "subcategory":"Business Services",
            "type":"Services"
        }
    ],
    "sg:phone":"+1 931 431 7064",
    "sg:postcode":"37040",
    "sg:province":"TN",
    "sg:tags":[
        "worship",
        "leader"
    ],
    "wof:name":"Christina Palmer",
    "wof:placetype":"venue"
},
  "geometry": {"coordinates":[-87.348647,36.512275],"type":"Point"}
}