{
  "type": "Feature",
  "properties": {
    "iso:country":"US",
    "sg:address":"1559 Dibrell-Lucky Rd",
    "sg:city":"Mc Minnville",
    "sg:classifiers":[
        {
            "category":"Building & Trades",
            "subcategory":"Construction",
            "type":"Services"
        }
    ],
    "sg:phone":"+1 931 934 2541",
    "sg:postcode":"37110",
    "sg:province":"TN",
    "sg:tags":[
        "hanging",
        "contractor"
    ],
    "wof:name":"Welcome Painting Company",
    "wof:placetype":"venue"
},
  "geometry": {"coordinates":[-85.816895,35.798182],"type":"Point"}
}