{
  "type": "Feature",
  "properties": {
    "addr:full":"235 Deer Park Ln Lafayette TN 37083",
    "addr:housenumber":"235",
    "addr:postcode":"37083",
    "addr:street":"Deer Park Ln",
    "iso:country":"US",
    "sg:address":"235 Deer Park Ln",
    "sg:city":"Lafayette",
    "sg:classifiers":[
        {
            "category":"Building & Trades",
            "subcategory":"Construction",
            "type":"Services"
        }
    ],
    "sg:phone":"+1 615 666 5597",
    "sg:postcode":"37083",
    "sg:province":"TN",
    "sg:tags":[
        "house"
    ],
    "wof:name":"T & E Construction",
    "wof:placetype":"venue"
},
  "geometry": {"coordinates":[-86.094202,36.533942],"type":"Point"}
}