{
  "type": "Feature",
  "properties": {
    "iso:country":"US",
    "sg:address":"217 Main Ave S",
    "sg:city":"Fayetteville",
    "sg:classifiers":[
        {
            "category":"Home & Garden",
            "subcategory":"Building Materials",
            "type":"Retail Goods"
        }
    ],
    "sg:phone":"+1 931 438 7020",
    "sg:postcode":"37334",
    "sg:province":"TN",
    "wof:name":"Touch Of Glass",
    "wof:placetype":"venue"
},
  "geometry": {"coordinates":[-86.570823,35.151173],"type":"Point"}
}