{
  "type": "Feature",
  "properties": {
    "iso:country":"US",
    "sg:address":"400 Airways Blvd",
    "sg:city":"Jackson",
    "sg:classifiers":[
        {
            "category":"Wholesale",
            "subcategory":"Auto Parts",
            "type":"Manufacturing & Wholesale Goods"
        }
    ],
    "sg:phone":"+1 731 265 4041",
    "sg:postcode":"38301",
    "sg:province":"TN",
    "sg:tags":[
        "paint",
        "glass"
    ],
    "wof:name":"Reliable Glass & Paint Co",
    "wof:placetype":"venue"
},
  "geometry": {"coordinates":[-88.83695,35.616935],"type":"Point"}
}