{
  "type": "Feature",
  "properties": {
    "iso:country":"US",
    "sg:address":"3828 Memorial Blvd",
    "sg:city":"Kingsport",
    "sg:classifiers":[
        {
            "category":"Government",
            "subcategory":"Office",
            "type":"Public Place"
        }
    ],
    "sg:phone":"+1 423 229 9443",
    "sg:postcode":"37664",
    "sg:province":"TN",
    "sg:tags":[
        "fire",
        "protection"
    ],
    "wof:name":"Fire Station 3",
    "wof:placetype":"venue"
},
  "geometry": {"coordinates":[-82.50202899999999,36.529542],"type":"Point"}
}