{
  "type": "Feature",
  "properties": {
    "addr:full":"6930 State Hwy 88 Friendship TN 38034",
    "addr:housenumber":"6930",
    "addr:postcode":"38034",
    "addr:street":"State Hwy 88",
    "iso:country":"US",
    "sg:address":"6930 State Hwy 88",
    "sg:city":"Friendship",
    "sg:classifiers":[
        {
            "category":"Organizations",
            "subcategory":"Religious Organization",
            "type":"Services"
        }
    ],
    "sg:phone":"+1 731 656 2949",
    "sg:postcode":"38034",
    "sg:province":"TN",
    "sg:tags":[
        "church"
    ],
    "wof:name":"Maury City Church Of God",
    "wof:placetype":"venue"
},
  "geometry": {"coordinates":[-89.23179399999999,35.809791],"type":"Point"}
}