{
  "type": "Feature",
  "properties": {
    "iso:country":"US",
    "sg:address":"10047 McCormick Pl",
    "sg:city":"Knoxville",
    "sg:classifiers":[
        {
            "category":"Health Services",
            "subcategory":"Doctor",
            "type":"Services"
        }
    ],
    "sg:phone":"+1 865 539 4956",
    "sg:postcode":"37923",
    "sg:province":"TN",
    "sg:tags":[
        "physician",
        "surgeon"
    ],
    "wof:name":"L Warren Chesney MD",
    "wof:placetype":"venue"
},
  "geometry": {"coordinates":[-84.119001,35.931206],"type":"Point"}
}