{
  "type": "Feature",
  "properties": {
    "iso:country":"US",
    "sg:address":"5258 Tusculum Ct",
    "sg:city":"Nashville",
    "sg:classifiers":[
        {
            "category":"Building & Trades",
            "subcategory":"Cleaning & Sanitation",
            "type":"Services"
        }
    ],
    "sg:phone":"+1 615 837 0480",
    "sg:postcode":"37211",
    "sg:province":"TN",
    "sg:tags":[
        "janitor"
    ],
    "wof:name":"R & S Cleaning Svc",
    "wof:placetype":"venue"
},
  "geometry": {"coordinates":[-86.69904200000001,36.050413],"type":"Point"}
}