{
  "type": "Feature",
  "properties": {
    "iso:country":"US",
    "sg:address":"1494 Getwell Rd",
    "sg:city":"Memphis",
    "sg:classifiers":[
        {
            "category":"Personal",
            "subcategory":"Beauty Salon",
            "type":"Services"
        }
    ],
    "sg:phone":"+1 901 744 6006",
    "sg:postcode":"38111",
    "sg:province":"TN",
    "sg:tags":[
        "shop"
    ],
    "wof:name":"Unique Hair Designs By Faye",
    "wof:placetype":"venue"
},
  "geometry": {"coordinates":[-89.93100699999999,35.090759],"type":"Point"}
}