{
  "type": "Feature",
  "properties": {
    "iso:country":"US",
    "sg:address":"5860 Summer Ave",
    "sg:city":"Memphis",
    "sg:classifiers":[
        {
            "category":"Restaurant",
            "type":"Food & Drink"
        }
    ],
    "sg:menulink":"http://www.allmenus.com/tn/memphis/191651-sonic/menu/",
    "sg:phone":"+1 901 379 0307",
    "sg:postcode":"38134",
    "sg:province":"TN",
    "sg:tags":[
        "burger",
        "american"
    ],
    "wof:name":"Sonic",
    "wof:placetype":"venue"
},
  "geometry": {"coordinates":[-89.867403,35.173204],"type":"Point"}
}