{
  "type": "Feature",
  "properties": {
    "iso:country":"US",
    "sg:address":"2400 Choto Rd",
    "sg:city":"Concord Farragut",
    "sg:classifiers":[
        {
            "category":"Health Services",
            "subcategory":"Doctor",
            "type":"Services"
        }
    ],
    "sg:phone":"+1 865 966 3630",
    "sg:postcode":"37922",
    "sg:province":"TN",
    "sg:tags":[
        "dentist"
    ],
    "wof:name":"Richard M Bowles DDS",
    "wof:placetype":"venue"
},
  "geometry": {"coordinates":[-84.149719,35.812259],"type":"Point"}
}