{
  "type": "Feature",
  "properties": {
    "addr:full":"106 N 7th St La Follette TN 37766",
    "addr:housenumber":"106",
    "addr:postcode":"37766",
    "addr:street":"N 7Th St",
    "iso:country":"US",
    "sg:address":"106 N 7th St",
    "sg:city":"La Follette",
    "sg:classifiers":[
        {
            "category":"Shopping",
            "subcategory":"Musical Instruments",
            "type":"Retail Goods"
        }
    ],
    "sg:phone":"+1 423 562 6721",
    "sg:postcode":"37766",
    "sg:province":"TN",
    "sg:tags":[
        "music",
        "dealer"
    ],
    "wof:name":"David's Music Store",
    "wof:placetype":"venue"
},
  "geometry": {"coordinates":[-84.125485,36.378476],"type":"Point"}
}