{
  "type": "Feature",
  "properties": {
    "iso:country":"US",
    "sg:address":"403 Old Stone Bridge Rd",
    "sg:city":"Goodlettsville",
    "sg:classifiers":[
        {
            "category":"Manufacturing",
            "subcategory":"Motor Vehicles & Parts",
            "type":"Manufacturing & Wholesale Goods"
        }
    ],
    "sg:phone":"+1 615 859 2992",
    "sg:postcode":"37072",
    "sg:province":"TN",
    "sg:tags":[
        "mfg"
    ],
    "wof:name":"Command Automotive Inc",
    "wof:placetype":"venue"
},
  "geometry": {"coordinates":[-86.716003,36.336751],"type":"Point"}
}