{
  "type": "Feature",
  "properties": {
    "iso:country":"US",
    "sg:address":"301 N Spring St",
    "sg:city":"Murfreesboro",
    "sg:classifiers":[
        {
            "category":"Professional",
            "subcategory":"Lawyer & Legal Services",
            "type":"Services"
        }
    ],
    "sg:phone":"+1 615 217 3560",
    "sg:postcode":"37130",
    "sg:province":"TN",
    "sg:tags":[
        "attorney"
    ],
    "wof:name":"Derek R Howard Attorney",
    "wof:placetype":"venue"
},
  "geometry": {"coordinates":[-86.38970999999999,35.848931],"type":"Point"}
}