{
  "type": "Feature",
  "properties": {
    "iso:country":"US",
    "sg:address":"145 S Main St",
    "sg:city":"Memphis",
    "sg:classifiers":[
        {
            "category":"Restaurant",
            "type":"Food & Drink"
        }
    ],
    "sg:phone":"+1 901 543 3330",
    "sg:postcode":"38103",
    "sg:province":"TN",
    "sg:tags":[
        "eating"
    ],
    "wof:name":"Big River Grill",
    "wof:placetype":"venue"
},
  "geometry": {"coordinates":[-90.05432500000001,35.141709],"type":"Point"}
}