{
  "type": "Feature",
  "properties": {
    "iso:country":"US",
    "sg:address":"1425 W Main St",
    "sg:city":"Greeneville",
    "sg:classifiers":[
        {
            "category":"Banks & Credit Unions",
            "subcategory":"Financial Services",
            "type":"Services"
        }
    ],
    "sg:phone":"+1 423 639 9202",
    "sg:postcode":"37743",
    "sg:province":"TN",
    "sg:tags":[
        "management",
        "open",
        "investment"
    ],
    "wof:name":"Ross & Warner Inc",
    "wof:placetype":"venue"
},
  "geometry": {"coordinates":[-82.856488,36.148926],"type":"Point"}
}