{
  "type": "Feature",
  "properties": {
    "iso:country":"US",
    "sg:address":"103 W 4th Ave",
    "sg:city":"Watauga",
    "sg:classifiers":[
        {
            "category":"Government",
            "subcategory":"Police Station",
            "type":"Public Place"
        }
    ],
    "sg:phone":"+1 423 928 2631",
    "sg:postcode":"37694",
    "sg:province":"TN",
    "sg:tags":[
        "department"
    ],
    "wof:name":"Watauga Police Dept",
    "wof:placetype":"venue"
},
  "geometry": {"coordinates":[-82.29271300000001,36.368061],"type":"Point"}
}