{
  "type": "Feature",
  "properties": {
    "iso:country":"US",
    "sg:address":"5997 N 2nd St",
    "sg:city":"Russellville",
    "sg:classifiers":[
        {
            "category":"Place Of Worship",
            "subcategory":"Church",
            "type":"Public Place"
        }
    ],
    "sg:phone":"+1 423 586 0225",
    "sg:postcode":"37860",
    "sg:province":"TN",
    "sg:tags":[
        "churches-methodist"
    ],
    "wof:name":"Russellville United Methodist Church",
    "wof:placetype":"venue"
},
  "geometry": {"coordinates":[-83.19496599999999,36.260272],"type":"Point"}
}