{
  "type": "Feature",
  "properties": {
    "iso:country":"US",
    "sg:address":"8530 Hixson Pike",
    "sg:city":"Hixson",
    "sg:classifiers":[
        {
            "category":"Restaurant",
            "type":"Food & Drink"
        }
    ],
    "sg:menulink":"http://www.allmenus.com/tn/middle-valley/85662-dominos-pizza/menu/",
    "sg:phone":"+1 423 843 3030",
    "sg:postcode":"37343",
    "sg:province":"TN",
    "sg:tags":[
        "american",
        "wing",
        "pizza"
    ],
    "wof:name":"Domino's Pizza",
    "wof:placetype":"venue"
},
  "geometry": {"coordinates":[-85.158975,35.198844],"type":"Point"}
}