{
  "type": "Feature",
  "properties": {
    "iso:country":"US",
    "sg:address":"617 William D Jones Blvd",
    "sg:city":"Fayetteville",
    "sg:classifiers":[
        {
            "category":"Professional",
            "type":"Services"
        }
    ],
    "sg:phone":"+1 931 438 8265",
    "sg:postcode":"37334",
    "sg:province":"TN",
    "wof:name":"Micro Med",
    "wof:placetype":"venue"
},
  "geometry": {"coordinates":[-86.58836700000001,35.149003],"type":"Point"}
}