{
  "type": "Feature",
  "properties": {
    "iso:country":"US",
    "sg:address":"304 S Perimeter Park Dr",
    "sg:city":"Nashville",
    "sg:classifiers":[
        {
            "category":"Insurance",
            "subcategory":"Insurance Agent",
            "type":"Services"
        }
    ],
    "sg:phone":"+1 615 781 5100",
    "sg:postcode":"37211",
    "sg:province":"TN",
    "wof:name":"State Farm Insurance",
    "wof:placetype":"venue"
},
  "geometry": {"coordinates":[-86.69589000000001,36.086778],"type":"Point"}
}