{
  "type": "Feature",
  "properties": {
    "iso:country":"US",
    "sg:address":"8109 Carriage Xing",
    "sg:city":"Chattanooga",
    "sg:classifiers":[
        {
            "category":"Shopping",
            "subcategory":"Clothing, Apparel, & Fashions",
            "type":"Retail Goods"
        }
    ],
    "sg:phone":"+1 423 624 4666",
    "sg:postcode":"37421",
    "sg:province":"TN",
    "wof:name":"S W & Associates",
    "wof:placetype":"venue"
},
  "geometry": {"coordinates":[-85.14108,35.010704],"type":"Point"}
}