{
  "type": "Feature",
  "properties": {
    "iso:country":"US",
    "sg:address":"2002 Ravenwood Dr",
    "sg:city":"Murfreesboro",
    "sg:classifiers":[
        {
            "category":"Wholesale",
            "subcategory":"Machinery & Supplies",
            "type":"Manufacturing & Wholesale Goods"
        }
    ],
    "sg:phone":"+1 615 907 8084",
    "sg:postcode":"37129",
    "sg:province":"TN",
    "sg:tags":[
        "equipment",
        "establishment"
    ],
    "wof:name":"Castle Guardians LLC",
    "wof:placetype":"venue"
},
  "geometry": {"coordinates":[-86.400025,35.884607],"type":"Point"}
}