{
  "type": "Feature",
  "properties": {
    "addr:full":"201 N Laurel Cir Columbia TN 38401",
    "addr:housenumber":"201",
    "addr:postcode":"38401",
    "addr:street":"N Laurel Cir",
    "iso:country":"US",
    "sg:address":"201 N Laurel Cir",
    "sg:city":"Columbia",
    "sg:classifiers":[
        {
            "category":"Shopping",
            "type":"Retail Goods"
        }
    ],
    "sg:phone":"+1 931 388 6230",
    "sg:postcode":"38401",
    "sg:province":"TN",
    "sg:tags":[
        "electrical",
        "merchandise",
        "contractor"
    ],
    "wof:name":"Hardison Electronics Inc",
    "wof:placetype":"venue"
},
  "geometry": {"coordinates":[-87.01877399999999,35.644968],"type":"Point"}
}