{
  "type": "Feature",
  "properties": {
    "iso:country":"US",
    "sg:address":"7507 Falling Leaves Cir NW",
    "sg:city":"Knoxville",
    "sg:classifiers":[
        {
            "category":"Shopping",
            "type":"Retail Goods"
        }
    ],
    "sg:phone":"+1 865 769 4189",
    "sg:postcode":"37909",
    "sg:province":"TN",
    "sg:tags":[
        "merchandise"
    ],
    "wof:name":"Energy 4 Freedom Retail Store",
    "wof:placetype":"venue"
},
  "geometry": {"coordinates":[-84.04301599999999,35.943933],"type":"Point"}
}