{
  "type": "Feature",
  "properties": {
    "iso:country":"US",
    "sg:address":"3200 Beasleys Bend Rd",
    "sg:city":"Lebanon",
    "sg:classifiers":[
        {
            "category":"Building & Trades",
            "subcategory":"Construction",
            "type":"Services"
        }
    ],
    "sg:phone":"+1 615 443 1383",
    "sg:postcode":"37087",
    "sg:province":"TN",
    "sg:tags":[
        "house"
    ],
    "wof:name":"Old El Paso Construction",
    "wof:placetype":"venue"
},
  "geometry": {"coordinates":[-86.213268,36.317949],"type":"Point"}
}