{
  "type": "Feature",
  "properties": {
    "iso:country":"US",
    "sg:address":"60 S Broad St",
    "sg:city":"Lexington",
    "sg:classifiers":[
        {
            "category":"Personal",
            "subcategory":"Beauty Salon",
            "type":"Services"
        }
    ],
    "sg:phone":"+1 731 968 1215",
    "sg:postcode":"38351",
    "sg:province":"TN",
    "sg:tags":[
        "shop"
    ],
    "wof:name":"Tangels Hair Salon",
    "wof:placetype":"venue"
},
  "geometry": {"coordinates":[-88.39510300000001,35.649598],"type":"Point"}
}