{
  "type": "Feature",
  "properties": {
    "addr:full":"5317 State Hwy 153 Hixson TN 37343",
    "addr:housenumber":"5317",
    "addr:postcode":"37343",
    "addr:street":"State Hwy 153",
    "iso:country":"US",
    "sg:address":"5317 State Hwy 153",
    "sg:city":"Hixson",
    "sg:classifiers":[
        {
            "category":"Restaurant",
            "type":"Food & Drink"
        }
    ],
    "sg:phone":"+1 423 877 7671",
    "sg:postcode":"37343",
    "sg:province":"TN",
    "sg:tags":[
        "eating"
    ],
    "wof:name":"Long John Silvers",
    "wof:placetype":"venue"
},
  "geometry": {"coordinates":[-85.246644,35.135008],"type":"Point"}
}