{
  "type": "Feature",
  "properties": {
    "addr:full":"1211 Riverside Dr Nashville TN 37206",
    "addr:housenumber":"1211",
    "addr:postcode":"37206",
    "addr:street":"Riverside Dr",
    "iso:country":"US",
    "sg:address":"1211 Riverside Dr",
    "sg:city":"Nashville",
    "sg:classifiers":[
        {
            "category":"Organizations",
            "subcategory":"Religious Organization",
            "type":"Services"
        }
    ],
    "sg:phone":"+1 615 262 0224",
    "sg:postcode":"37206",
    "sg:province":"TN",
    "sg:tags":[
        "churches-lutheran",
        "church"
    ],
    "wof:name":"Memorial Lutheran Church",
    "wof:placetype":"venue"
},
  "geometry": {"coordinates":[-86.726468,36.188266],"type":"Point"}
}