{
  "type": "Feature",
  "properties": {
    "iso:country":"US",
    "sg:address":"5000 Old Hickory Blvd",
    "sg:city":"Hermitage",
    "sg:classifiers":[
        {
            "category":"Restaurant",
            "type":"Food & Drink"
        }
    ],
    "sg:phone":"+1 615 882 0999",
    "sg:postcode":"37076",
    "sg:province":"TN",
    "sg:website":"www.famousdaves.com",
    "wof:name":"Famous Dave's",
    "wof:placetype":"venue"
},
  "geometry": {"coordinates":[-86.618926,36.195163],"type":"Point"}
}