{
  "type": "Feature",
  "properties": {
    "iso:country":"US",
    "sg:address":"220 Water St",
    "sg:city":"Lewisburg",
    "sg:classifiers":[
        {
            "category":"Wholesale",
            "subcategory":"Vending Machines",
            "type":"Manufacturing & Wholesale Goods"
        }
    ],
    "sg:phone":"+1 931 359 1902",
    "sg:postcode":"37091",
    "sg:province":"TN",
    "wof:name":"Russell Vending Svc",
    "wof:placetype":"venue"
},
  "geometry": {"coordinates":[-86.78978600000001,35.451128],"type":"Point"}
}