{
  "type": "Feature",
  "properties": {
    "iso:country":"US",
    "sg:address":"907 Douglas Ave",
    "sg:city":"Nashville",
    "sg:classifiers":[
        {
            "category":"Personal",
            "type":"Services"
        }
    ],
    "sg:phone":"+1 615 383 9535",
    "sg:postcode":"37204",
    "sg:province":"TN",
    "wof:name":"Branches",
    "wof:placetype":"venue"
},
  "geometry": {"coordinates":[-86.78212499999999,36.130241],"type":"Point"}
}