{
  "type": "Feature",
  "properties": {
    "addr:full":"425 E Vann Rd Greeneville TN 37743",
    "addr:housenumber":"425",
    "addr:postcode":"37743",
    "addr:street":"E Vann Rd",
    "iso:country":"US",
    "sg:address":"425 E Vann Rd",
    "sg:city":"Greeneville",
    "sg:classifiers":[
        {
            "category":"Communications",
            "subcategory":"Radio Station",
            "type":"Services"
        }
    ],
    "sg:phone":"+1 423 638 6269",
    "sg:postcode":"37743",
    "sg:province":"TN",
    "sg:tags":[
        "company",
        "broadcasting"
    ],
    "wof:name":"Radio Greenville Inc",
    "wof:placetype":"venue"
},
  "geometry": {"coordinates":[-82.840576,36.152478],"type":"Point"}
}