{
  "type": "Feature",
  "properties": {
    "addr:full":"207 Monroe St Smyrna TN 37167",
    "addr:housenumber":"207",
    "addr:postcode":"37167",
    "addr:street":"Monroe St",
    "iso:country":"US",
    "sg:address":"207 Monroe St",
    "sg:city":"Smyrna",
    "sg:classifiers":[
        {
            "category":"Retail",
            "subcategory":"Auto Repair",
            "type":"Services"
        }
    ],
    "sg:phone":"+1 615 355 1886",
    "sg:postcode":"37167",
    "sg:province":"TN",
    "sg:tags":[
        "repairing",
        "automobile"
    ],
    "wof:name":"Discount Transmission & Auto",
    "wof:placetype":"venue"
},
  "geometry": {"coordinates":[-86.519503,35.984082],"type":"Point"}
}